Workbook

Sheet Combined P&L
A1: Keystone Bookkeepers
A2: Combined Monthly Income Statement ($000s) — Jan 2024 through Jul 2026
A3: Source: Target-provided QuickBooks Online P&L exports — Keystone P&L 2024.xlsx, Keystone P&L 2025.xlsx, Keystone P&L 2026.xlsx (accrual basis). All figures on this tab are live formulas linking to the "Raw - 20XX PL" tabs (each detail cell = raw cell / 1,000; every subtotal and FY total is a SUM/difference formula, never a hardcoded number), so this tab recalculates automatically if the raw tabs are updated. Values are in $000s. FY2026 reflects Jan–Jul only (YTD, 7 months) as that is the period the target has reported to date. Blank monthly cells indicate the account did not yet exist in the chart of accounts for that period (treated as $0 in subtotals). See the Tie-Out / Check section at the bottom of this tab, which foots every FY total back to each Raw tab's own reported Total column.
A6: Line Item | B6: FY2024 ($000s) | C6: FY2025 ($000s) | D6: FY2026 YTD (7 mo., $000s) | F6: 45292 | G6: 45323 | H6: 45352 | I6: 45383 | J6: 45413 | K6: 45444 | L6: 45474 | M6: 45505 | N6: 45536 | O6: 45566 | P6: 45597 | Q6: 45627 | R6: 45658 | S6: 45689 | T6: 45717 | U6: 45748 | V6: 45778 | W6: 45809 | X6: 45839 | Y6: 45870 | Z6: 45901 | AA6: 45931 | AB6: 45962 | AC6: 45992 | AD6: 46023 | AE6: 46054 | AF6: 46082 | AG6: 46113 | AH6: 46143 | AI6: 46174 | AJ6: 46204
A7: Income
A8: Income Tax Revenue | B8: =SUM(F8:Q8) -> 0 | C8: =SUM(R8:AC8) -> 0 | D8: =SUM(AD8:AJ8) -> 0 | R8: ='Raw - 2025 PL'!B7/1000 -> 0 | S8: ='Raw - 2025 PL'!C7/1000 -> 0 | T8: ='Raw - 2025 PL'!D7/1000 -> 0 | U8: ='Raw - 2025 PL'!E7/1000 -> 0 | V8: ='Raw - 2025 PL'!F7/1000 -> 0 | W8: ='Raw - 2025 PL'!G7/1000 -> 0 | X8: ='Raw - 2025 PL'!H7/1000 -> 0 | Y8: ='Raw - 2025 PL'!I7/1000 -> 0 | ... AC8: ='Raw - 2025 PL'!M7/1000 -> 0 | AD8: ='Raw - 2026 PL'!B7/1000 -> 0 | AE8: ='Raw - 2026 PL'!C7/1000 -> 0 | AF8: ='Raw - 2026 PL'!D7/1000 -> 0 | AG8: ='Raw - 2026 PL'!E7/1000 -> 0 | AH8: ='Raw - 2026 PL'!F7/1000 -> 0 | AI8: ='Raw - 2026 PL'!G7/1000 -> 0 | AJ8: ='Raw - 2026 PL'!H7/1000 -> 0
A9: Business Income Tax | B9: =SUM(F9:Q9) -> 0 | C9: =SUM(R9:AC9) -> 1.75 | D9: =SUM(AD9:AJ9) -> 21.59 | R9: ='Raw - 2025 PL'!B8/1000 -> 0 | S9: ='Raw - 2025 PL'!C8/1000 -> 0 | T9: ='Raw - 2025 PL'!D8/1000 -> 0 | U9: ='Raw - 2025 PL'!E8/1000 -> 0 | V9: ='Raw - 2025 PL'!F8/1000 -> 0 | W9: ='Raw - 2025 PL'!G8/1000 -> 0 | X9: ='Raw - 2025 PL'!H8/1000 -> 0 | Y9: ='Raw - 2025 PL'!I8/1000 -> 0 | ... AC9: ='Raw - 2025 PL'!M8/1000 -> 0.875 | AD9: ='Raw - 2026 PL'!B8/1000 -> 0 | AE9: ='Raw - 2026 PL'!C8/1000 -> 0 | AF9: ='Raw - 2026 PL'!D8/1000 -> 14.19 | AG9: ='Raw - 2026 PL'!E8/1000 -> 4.3 | AH9: ='Raw - 2026 PL'!F8/1000 -> 0 | AI9: ='Raw - 2026 PL'!G8/1000 -> 3.1 | AJ9: ='Raw - 2026 PL'!H8/1000 -> 0
A10: Individual Income Tax | B10: =SUM(F10:Q10) -> 0 | C10: =SUM(R10:AC10) -> 1.65 | D10: =SUM(AD10:AJ10) -> 2.325 | R10: ='Raw - 2025 PL'!B9/1000 -> 0 | S10: ='Raw - 2025 PL'!C9/1000 -> 0 | T10: ='Raw - 2025 PL'!D9/1000 -> 0 | U10: ='Raw - 2025 PL'!E9/1000 -> 0 | V10: ='Raw - 2025 PL'!F9/1000 -> 0 | W10: ='Raw - 2025 PL'!G9/1000 -> 0 | X10: ='Raw - 2025 PL'!H9/1000 -> 0 | Y10: ='Raw - 2025 PL'!I9/1000 -> 0 | ... AC10: ='Raw - 2025 PL'!M9/1000 -> 0 | AD10: ='Raw - 2026 PL'!B9/1000 -> 0 | AE10: ='Raw - 2026 PL'!C9/1000 -> 0 | AF10: ='Raw - 2026 PL'!D9/1000 -> 0 | AG10: ='Raw - 2026 PL'!E9/1000 -> 2.325 | AH10: ='Raw - 2026 PL'!F9/1000 -> 0 | AI10: ='Raw - 2026 PL'!G9/1000 -> 0 | AJ10: ='Raw - 2026 PL'!H9/1000 -> 0
A11: Total Income Tax Revenue | B11: =SUM(F11:Q11) -> 0 | C11: =SUM(R11:AC11) -> 3.4 | D11: =SUM(AD11:AJ11) -> 23.915 | F11: =SUM(F8,F9,F10) -> 0 | G11: =SUM(G8,G9,G10) -> 0 | H11: =SUM(H8,H9,H10) -> 0 | I11: =SUM(I8,I9,I10) -> 0 | J11: =SUM(J8,J9,J10) -> 0 | K11: =SUM(K8,K9,K10) -> 0 | L11: =SUM(L8,L9,L10) -> 0 | M11: =SUM(M8,M9,M10) -> 0 | ... AJ11: =SUM(AJ8,AJ9,AJ10) -> 0
A12: Non-Recurring Revenue | B12: =SUM(F12:Q12) -> 0 | C12: =SUM(R12:AC12) -> 0 | D12: =SUM(AD12:AJ12) -> 0 | F12: ='Raw - 2024 PL'!B7/1000 -> 0 | G12: ='Raw - 2024 PL'!C7/1000 -> 0 | H12: ='Raw - 2024 PL'!D7/1000 -> 0 | I12: ='Raw - 2024 PL'!E7/1000 -> 0 | J12: ='Raw - 2024 PL'!F7/1000 -> 0 | K12: ='Raw - 2024 PL'!G7/1000 -> 0 | L12: ='Raw - 2024 PL'!H7/1000 -> 0 | M12: ='Raw - 2024 PL'!I7/1000 -> 0 | ... Q12: ='Raw - 2024 PL'!M7/1000 -> 0 | R12: ='Raw - 2025 PL'!B11/1000 -> 0 | S12: ='Raw - 2025 PL'!C11/1000 -> 0 | T12: ='Raw - 2025 PL'!D11/1000 -> 0 | U12: ='Raw - 2025 PL'!E11/1000 -> 0 | V12: ='Raw - 2025 PL'!F11/1000 -> 0 | W12: ='Raw - 2025 PL'!G11/1000 -> 0 | X12: ='Raw - 2025 PL'!H11/1000 -> 0 | Y12: ='Raw - 2025 PL'!I11/1000 -> 0 | ... AC12: ='Raw - 2025 PL'!M11/1000 -> 0 | AD12: ='Raw - 2026 PL'!B11/1000 -> 0 | AE12: ='Raw - 2026 PL'!C11/1000 -> 0 | AF12: ='Raw - 2026 PL'!D11/1000 -> 0 | AG12: ='Raw - 2026 PL'!E11/1000 -> 0 | AH12: ='Raw - 2026 PL'!F11/1000 -> 0 | AI12: ='Raw - 2026 PL'!G11/1000 -> 0 | AJ12: ='Raw - 2026 PL'!H11/1000 -> 0
A13: 1099 Filing | B13: =SUM(F13:Q13) -> 10.475 | C13: =SUM(R13:AC13) -> 23.55 | D13: =SUM(AD13:AJ13) -> 38.7015 | F13: ='Raw - 2024 PL'!B8/1000 -> 6.945 | G13: ='Raw - 2024 PL'!C8/1000 -> 3.38 | H13: ='Raw - 2024 PL'!D8/1000 -> 0.045 | I13: ='Raw - 2024 PL'!E8/1000 -> 0.06 | J13: ='Raw - 2024 PL'!F8/1000 -> 0.015 | K13: ='Raw - 2024 PL'!G8/1000 -> 0 | L13: ='Raw - 2024 PL'!H8/1000 -> 0 | M13: ='Raw - 2024 PL'!I8/1000 -> 0.015 | ... Q13: ='Raw - 2024 PL'!M8/1000 -> 0 | R13: ='Raw - 2025 PL'!B12/1000 -> 13.485 | S13: ='Raw - 2025 PL'!C12/1000 -> 9.915 | T13: ='Raw - 2025 PL'!D12/1000 -> 0.06 | U13: ='Raw - 2025 PL'!E12/1000 -> 0.03 | V13: ='Raw - 2025 PL'!F12/1000 -> 0 | W13: ='Raw - 2025 PL'!G12/1000 -> 0 | X13: ='Raw - 2025 PL'!H12/1000 -> 0 | Y13: ='Raw - 2025 PL'!I12/1000 -> 0.03 | ... AC13: ='Raw - 2025 PL'!M12/1000 -> 0 | AD13: ='Raw - 2026 PL'!B12/1000 -> 6.105 | AE13: ='Raw - 2026 PL'!C12/1000 -> 31.1565 | AF13: ='Raw - 2026 PL'!D12/1000 -> 1.26 | AG13: ='Raw - 2026 PL'!E12/1000 -> 0.18 | AH13: ='Raw - 2026 PL'!F12/1000 -> 0 | AI13: ='Raw - 2026 PL'!G12/1000 -> 0 | AJ13: ='Raw - 2026 PL'!H12/1000 -> 0
A14: Billable Expense Income | B14: =SUM(F14:Q14) -> 0.3747 | C14: =SUM(R14:AC14) -> 1.12194 | D14: =SUM(AD14:AJ14) -> 0.25783 | F14: ='Raw - 2024 PL'!B9/1000 -> 0.05 | G14: ='Raw - 2024 PL'!C9/1000 -> 0 | H14: ='Raw - 2024 PL'!D9/1000 -> 0 | I14: ='Raw - 2024 PL'!E9/1000 -> 0.025 | J14: ='Raw - 2024 PL'!F9/1000 -> 0 | K14: ='Raw - 2024 PL'!G9/1000 -> 0 | L14: ='Raw - 2024 PL'!H9/1000 -> 0.2997 | M14: ='Raw - 2024 PL'!I9/1000 -> 0 | ... Q14: ='Raw - 2024 PL'!M9/1000 -> 0 | R14: ='Raw - 2025 PL'!B13/1000 -> 0.025 | S14: ='Raw - 2025 PL'!C13/1000 -> 0.3996 | T14: ='Raw - 2025 PL'!D13/1000 -> 0 | U14: ='Raw - 2025 PL'!E13/1000 -> 0 | V14: ='Raw - 2025 PL'!F13/1000 -> 0.07294 | W14: ='Raw - 2025 PL'!G13/1000 -> 0 | X14: ='Raw - 2025 PL'!H13/1000 -> 0.28971 | Y14: ='Raw - 2025 PL'!I13/1000 -> 0.30969 | ... AC14: ='Raw - 2025 PL'!M13/1000 -> 0.025 | AD14: ='Raw - 2026 PL'!B13/1000 -> 0.15984 | AE14: ='Raw - 2026 PL'!C13/1000 -> 0 | AF14: ='Raw - 2026 PL'!D13/1000 -> 0.075 | AG14: ='Raw - 2026 PL'!E13/1000 -> 0 | AH14: ='Raw - 2026 PL'!F13/1000 -> 0 | AI14: ='Raw - 2026 PL'!G13/1000 -> 0.02299 | AJ14: ='Raw - 2026 PL'!H13/1000 -> 0
A15: Offshore Recruiting | B15: =SUM(F15:Q15) -> 23.6 | C15: =SUM(R15:AC15) -> 0.2 | D15: =SUM(AD15:AJ15) -> 0 | F15: ='Raw - 2024 PL'!B10/1000 -> 0.5 | G15: ='Raw - 2024 PL'!C10/1000 -> 3 | H15: ='Raw - 2024 PL'!D10/1000 -> 0 | I15: ='Raw - 2024 PL'!E10/1000 -> 0 | J15: ='Raw - 2024 PL'!F10/1000 -> 3 | K15: ='Raw - 2024 PL'!G10/1000 -> 0.565 | L15: ='Raw - 2024 PL'!H10/1000 -> 10.5 | M15: ='Raw - 2024 PL'!I10/1000 -> 6.5 | ... Q15: ='Raw - 2024 PL'!M10/1000 -> 0 | R15: ='Raw - 2025 PL'!B14/1000 -> 0.1 | S15: ='Raw - 2025 PL'!C14/1000 -> 0 | T15: ='Raw - 2025 PL'!D14/1000 -> 0.1 | U15: ='Raw - 2025 PL'!E14/1000 -> 0 | V15: ='Raw - 2025 PL'!F14/1000 -> 0 | W15: ='Raw - 2025 PL'!G14/1000 -> 0 | X15: ='Raw - 2025 PL'!H14/1000 -> 0 | Y15: ='Raw - 2025 PL'!I14/1000 -> 0 | ... AC15: ='Raw - 2025 PL'!M14/1000 -> 0
A16: Profit Share | B16: =SUM(F16:Q16) -> 6.2004 | C16: =SUM(R16:AC16) -> 23.26179 | D16: =SUM(AD16:AJ16) -> 8.07938 | F16: ='Raw - 2024 PL'!B11/1000 -> 0.0686 | G16: ='Raw - 2024 PL'!C11/1000 -> 0.1312 | H16: ='Raw - 2024 PL'!D11/1000 -> 0.0712 | I16: ='Raw - 2024 PL'!E11/1000 -> 0.0556 | J16: ='Raw - 2024 PL'!F11/1000 -> 0.577 | K16: ='Raw - 2024 PL'!G11/1000 -> 0.8068 | L16: ='Raw - 2024 PL'!H11/1000 -> 0.6656 | M16: ='Raw - 2024 PL'!I11/1000 -> 0.8264 | ... Q16: ='Raw - 2024 PL'!M11/1000 -> 0.2468 | R16: ='Raw - 2025 PL'!B15/1000 -> 7.3584 | S16: ='Raw - 2025 PL'!C15/1000 -> 1.29335 | T16: ='Raw - 2025 PL'!D15/1000 -> 0.96833 | U16: ='Raw - 2025 PL'!E15/1000 -> 1.1656 | V16: ='Raw - 2025 PL'!F15/1000 -> 0.96093 | W16: ='Raw - 2025 PL'!G15/1000 -> 1.71127 | X16: ='Raw - 2025 PL'!H15/1000 -> 1.04707 | Y16: ='Raw - 2025 PL'!I15/1000 -> 2.04088 | ... AC16: ='Raw - 2025 PL'!M15/1000 -> 2.26793 | AD16: ='Raw - 2026 PL'!B14/1000 -> 2.67784 | AE16: ='Raw - 2026 PL'!C14/1000 -> 2.35401 | AF16: ='Raw - 2026 PL'!D14/1000 -> 0.2276 | AG16: ='Raw - 2026 PL'!E14/1000 -> 1.47836 | AH16: ='Raw - 2026 PL'!F14/1000 -> 0.66824 | AI16: ='Raw - 2026 PL'!G14/1000 -> 0.58613 | AJ16: ='Raw - 2026 PL'!H14/1000 -> 0.0872
A17: Total Non-Recurring Revenue | B17: =SUM(F17:Q17) -> 40.6501 | C17: =SUM(R17:AC17) -> 48.13373 | D17: =SUM(AD17:AJ17) -> 47.03871 | F17: =SUM(F12,F13,F14,F15,F16) -> 7.5636 | G17: =SUM(G12,G13,G14,G15,G16) -> 6.5112 | H17: =SUM(H12,H13,H14,H15,H16) -> 0.1162 | I17: =SUM(I12,I13,I14,I15,I16) -> 0.1406 | J17: =SUM(J12,J13,J14,J15,J16) -> 3.592 | K17: =SUM(K12,K13,K14,K15,K16) -> 1.3718 | L17: =SUM(L12,L13,L14,L15,L16) -> 11.4653 | M17: =SUM(M12,M13,M14,M15,M16) -> 7.3414 | ... AJ17: =SUM(AJ12,AJ13,AJ14,AJ15,AJ16) -> 0.0872
A18: Onboarding Revenue | B18: =SUM(F18:Q18) -> 0 | C18: =SUM(R18:AC18) -> 0 | D18: =SUM(AD18:AJ18) -> 0 | F18: ='Raw - 2024 PL'!B13/1000 -> 0 | G18: ='Raw - 2024 PL'!C13/1000 -> 0 | H18: ='Raw - 2024 PL'!D13/1000 -> 0 | I18: ='Raw - 2024 PL'!E13/1000 -> 0 | J18: ='Raw - 2024 PL'!F13/1000 -> 0 | K18: ='Raw - 2024 PL'!G13/1000 -> 0 | L18: ='Raw - 2024 PL'!H13/1000 -> 0 | M18: ='Raw - 2024 PL'!I13/1000 -> 0 | ... Q18: ='Raw - 2024 PL'!M13/1000 -> 0 | R18: ='Raw - 2025 PL'!B17/1000 -> 0 | S18: ='Raw - 2025 PL'!C17/1000 -> 0 | T18: ='Raw - 2025 PL'!D17/1000 -> 0 | U18: ='Raw - 2025 PL'!E17/1000 -> 0 | V18: ='Raw - 2025 PL'!F17/1000 -> 0 | W18: ='Raw - 2025 PL'!G17/1000 -> 0 | X18: ='Raw - 2025 PL'!H17/1000 -> 0 | Y18: ='Raw - 2025 PL'!I17/1000 -> 0 | ... AC18: ='Raw - 2025 PL'!M17/1000 -> 0 | AD18: ='Raw - 2026 PL'!B16/1000 -> 0 | AE18: ='Raw - 2026 PL'!C16/1000 -> 0 | AF18: ='Raw - 2026 PL'!D16/1000 -> 0 | AG18: ='Raw - 2026 PL'!E16/1000 -> 0 | AH18: ='Raw - 2026 PL'!F16/1000 -> 0 | AI18: ='Raw - 2026 PL'!G16/1000 -> 0 | AJ18: ='Raw - 2026 PL'!H16/1000 -> 0
A19: Historical Cleanup | B19: =SUM(F19:Q19) -> 17.624 | C19: =SUM(R19:AC19) -> 5.03375 | D19: =SUM(AD19:AJ19) -> 0 | F19: ='Raw - 2024 PL'!B14/1000 -> 1.2 | G19: ='Raw - 2024 PL'!C14/1000 -> 1.7625 | H19: ='Raw - 2024 PL'!D14/1000 -> 0.66 | I19: ='Raw - 2024 PL'!E14/1000 -> 0.395 | J19: ='Raw - 2024 PL'!F14/1000 -> 2.465 | K19: ='Raw - 2024 PL'!G14/1000 -> 1.275 | L19: ='Raw - 2024 PL'!H14/1000 -> 1.4625 | M19: ='Raw - 2024 PL'!I14/1000 -> 0 | ... Q19: ='Raw - 2024 PL'!M14/1000 -> 4 | R19: ='Raw - 2025 PL'!B18/1000 -> 1.08375 | S19: ='Raw - 2025 PL'!C18/1000 -> 2 | T19: ='Raw - 2025 PL'!D18/1000 -> 1.355 | U19: ='Raw - 2025 PL'!E18/1000 -> 0 | V19: ='Raw - 2025 PL'!F18/1000 -> 0 | W19: ='Raw - 2025 PL'!G18/1000 -> 0 | X19: ='Raw - 2025 PL'!H18/1000 -> 0 | Y19: ='Raw - 2025 PL'!I18/1000 -> 0 | ... AC19: ='Raw - 2025 PL'!M18/1000 -> 0
A20: Onboarding | B20: =SUM(F20:Q20) -> 44.0585 | C20: =SUM(R20:AC20) -> 74.5193 | D20: =SUM(AD20:AJ20) -> 59.055 | F20: ='Raw - 2024 PL'!B15/1000 -> 5.465 | G20: ='Raw - 2024 PL'!C15/1000 -> 3.9 | H20: ='Raw - 2024 PL'!D15/1000 -> 2.755 | I20: ='Raw - 2024 PL'!E15/1000 -> 3.502 | J20: ='Raw - 2024 PL'!F15/1000 -> 4.659 | K20: ='Raw - 2024 PL'!G15/1000 -> 3.937 | L20: ='Raw - 2024 PL'!H15/1000 -> 4.602 | M20: ='Raw - 2024 PL'!I15/1000 -> 4.738 | ... Q20: ='Raw - 2024 PL'!M15/1000 -> 3.305 | R20: ='Raw - 2025 PL'!B19/1000 -> 3.079 | S20: ='Raw - 2025 PL'!C19/1000 -> 0.7 | T20: ='Raw - 2025 PL'!D19/1000 -> 10.43855 | U20: ='Raw - 2025 PL'!E19/1000 -> 4.3 | V20: ='Raw - 2025 PL'!F19/1000 -> 11.14 | W20: ='Raw - 2025 PL'!G19/1000 -> 6.1625 | X20: ='Raw - 2025 PL'!H19/1000 -> 6.434 | Y20: ='Raw - 2025 PL'!I19/1000 -> 3.965 | ... AC20: ='Raw - 2025 PL'!M19/1000 -> 9.99 | AD20: ='Raw - 2026 PL'!B17/1000 -> 10.2105 | AE20: ='Raw - 2026 PL'!C17/1000 -> 6.675 | AF20: ='Raw - 2026 PL'!D17/1000 -> 9.099 | AG20: ='Raw - 2026 PL'!E17/1000 -> 8.9545 | AH20: ='Raw - 2026 PL'!F17/1000 -> 12.606 | AI20: ='Raw - 2026 PL'!G17/1000 -> 5.4115 | AJ20: ='Raw - 2026 PL'!H17/1000 -> 6.0985
A21: Total Onboarding Revenue | B21: =SUM(F21:Q21) -> 61.6825 | C21: =SUM(R21:AC21) -> 79.55305 | D21: =SUM(AD21:AJ21) -> 59.055 | F21: =SUM(F18,F19,F20) -> 6.665 | G21: =SUM(G18,G19,G20) -> 5.6625 | H21: =SUM(H18,H19,H20) -> 3.415 | I21: =SUM(I18,I19,I20) -> 3.897 | J21: =SUM(J18,J19,J20) -> 7.124 | K21: =SUM(K18,K19,K20) -> 5.212 | L21: =SUM(L18,L19,L20) -> 6.0645 | M21: =SUM(M18,M19,M20) -> 4.738 | ... AJ21: =SUM(AJ18,AJ19,AJ20) -> 6.0985
A22: SMB Bookkeeping Subscription | B22: =SUM(F22:Q22) -> 224.791 | C22: =SUM(R22:AC22) -> 149.77 | D22: =SUM(AD22:AJ22) -> 73.4185 | F22: ='Raw - 2024 PL'!B17/1000 -> 22.001 | G22: ='Raw - 2024 PL'!C17/1000 -> 22.036 | H22: ='Raw - 2024 PL'!D17/1000 -> 22.111 | I22: ='Raw - 2024 PL'!E17/1000 -> 22.146 | J22: ='Raw - 2024 PL'!F17/1000 -> 21.966 | K22: ='Raw - 2024 PL'!G17/1000 -> 17.816 | L22: ='Raw - 2024 PL'!H17/1000 -> 17.621 | M22: ='Raw - 2024 PL'!I17/1000 -> 17.536 | ... Q22: ='Raw - 2024 PL'!M17/1000 -> 15.0755 | R22: ='Raw - 2025 PL'!B21/1000 -> 14.5625 | S22: ='Raw - 2025 PL'!C21/1000 -> 12.8025 | T22: ='Raw - 2025 PL'!D21/1000 -> 12.4025 | U22: ='Raw - 2025 PL'!E21/1000 -> 12.6025 | V22: ='Raw - 2025 PL'!F21/1000 -> 12.7525 | W22: ='Raw - 2025 PL'!G21/1000 -> 12.7925 | X22: ='Raw - 2025 PL'!H21/1000 -> 12.5375 | Y22: ='Raw - 2025 PL'!I21/1000 -> 11.8575 | ... AC22: ='Raw - 2025 PL'!M21/1000 -> 11.7475 | AD22: ='Raw - 2026 PL'!B19/1000 -> 11.2805 | AE22: ='Raw - 2026 PL'!C19/1000 -> 10.9305 | AF22: ='Raw - 2026 PL'!D19/1000 -> 10.6255 | AG22: ='Raw - 2026 PL'!E19/1000 -> 10.3155 | AH22: ='Raw - 2026 PL'!F19/1000 -> 10.3155 | AI22: ='Raw - 2026 PL'!G19/1000 -> 9.9755 | AJ22: ='Raw - 2026 PL'!H19/1000 -> 9.9755
A23: STR Recurring Revenue | B23: =SUM(F23:Q23) -> 0 | C23: =SUM(R23:AC23) -> 0 | D23: =SUM(AD23:AJ23) -> 0 | F23: ='Raw - 2024 PL'!B18/1000 -> 0 | G23: ='Raw - 2024 PL'!C18/1000 -> 0 | H23: ='Raw - 2024 PL'!D18/1000 -> 0 | I23: ='Raw - 2024 PL'!E18/1000 -> 0 | J23: ='Raw - 2024 PL'!F18/1000 -> 0 | K23: ='Raw - 2024 PL'!G18/1000 -> 0 | L23: ='Raw - 2024 PL'!H18/1000 -> 0 | M23: ='Raw - 2024 PL'!I18/1000 -> 0 | ... Q23: ='Raw - 2024 PL'!M18/1000 -> 0 | R23: ='Raw - 2025 PL'!B22/1000 -> 0 | S23: ='Raw - 2025 PL'!C22/1000 -> 0 | T23: ='Raw - 2025 PL'!D22/1000 -> 0 | U23: ='Raw - 2025 PL'!E22/1000 -> 0 | V23: ='Raw - 2025 PL'!F22/1000 -> 0 | W23: ='Raw - 2025 PL'!G22/1000 -> 0 | X23: ='Raw - 2025 PL'!H22/1000 -> 0 | Y23: ='Raw - 2025 PL'!I22/1000 -> 0 | ... AC23: ='Raw - 2025 PL'!M22/1000 -> 0 | AD23: ='Raw - 2026 PL'!B20/1000 -> 0 | AE23: ='Raw - 2026 PL'!C20/1000 -> 0 | AF23: ='Raw - 2026 PL'!D20/1000 -> 0 | AG23: ='Raw - 2026 PL'!E20/1000 -> 0 | AH23: ='Raw - 2026 PL'!F20/1000 -> 0 | AI23: ='Raw - 2026 PL'!G20/1000 -> 0 | AJ23: ='Raw - 2026 PL'!H20/1000 -> 0
A24: Controller Services | B24: =SUM(F24:Q24) -> 13.75 | C24: =SUM(R24:AC24) -> 46.4 | D24: =SUM(AD24:AJ24) -> 24.25 | F24: ='Raw - 2024 PL'!B19/1000 -> 0 | G24: ='Raw - 2024 PL'!C19/1000 -> 0 | H24: ='Raw - 2024 PL'!D19/1000 -> 0 | I24: ='Raw - 2024 PL'!E19/1000 -> 0 | J24: ='Raw - 2024 PL'!F19/1000 -> 0 | K24: ='Raw - 2024 PL'!G19/1000 -> 0 | L24: ='Raw - 2024 PL'!H19/1000 -> 1.25 | M24: ='Raw - 2024 PL'!I19/1000 -> 1.25 | ... Q24: ='Raw - 2024 PL'!M19/1000 -> 3 | R24: ='Raw - 2025 PL'!B23/1000 -> 4.45 | S24: ='Raw - 2025 PL'!C23/1000 -> 3.45 | T24: ='Raw - 2025 PL'!D23/1000 -> 3.45 | U24: ='Raw - 2025 PL'!E23/1000 -> 5.95 | V24: ='Raw - 2025 PL'!F23/1000 -> 5.2 | W24: ='Raw - 2025 PL'!G23/1000 -> 5 | X24: ='Raw - 2025 PL'!H23/1000 -> 4 | Y24: ='Raw - 2025 PL'!I23/1000 -> 2.95 | ... AC24: ='Raw - 2025 PL'!M23/1000 -> 2.95 | AD24: ='Raw - 2026 PL'!B21/1000 -> 2.75 | AE24: ='Raw - 2026 PL'!C21/1000 -> 3.5 | AF24: ='Raw - 2026 PL'!D21/1000 -> 2.75 | AG24: ='Raw - 2026 PL'!E21/1000 -> 4.75 | AH24: ='Raw - 2026 PL'!F21/1000 -> 3.5 | AI24: ='Raw - 2026 PL'!G21/1000 -> 3.5 | AJ24: ='Raw - 2026 PL'!H21/1000 -> 3.5
A25: Occupancy Taxes | B25: =SUM(F25:Q25) -> 0.56 | C25: =SUM(R25:AC25) -> 55.0805 | D25: =SUM(AD25:AJ25) -> 91.65114 | F25: ='Raw - 2024 PL'!B20/1000 -> 0 | G25: ='Raw - 2024 PL'!C20/1000 -> 0 | H25: ='Raw - 2024 PL'!D20/1000 -> 0 | I25: ='Raw - 2024 PL'!E20/1000 -> 0 | J25: ='Raw - 2024 PL'!F20/1000 -> 0 | K25: ='Raw - 2024 PL'!G20/1000 -> 0 | L25: ='Raw - 2024 PL'!H20/1000 -> 0 | M25: ='Raw - 2024 PL'!I20/1000 -> 0 | ... Q25: ='Raw - 2024 PL'!M20/1000 -> 0.48 | R25: ='Raw - 2025 PL'!B24/1000 -> 1.13 | S25: ='Raw - 2025 PL'!C24/1000 -> 2.14 | T25: ='Raw - 2025 PL'!D24/1000 -> 2.66 | U25: ='Raw - 2025 PL'!E24/1000 -> 3.65 | V25: ='Raw - 2025 PL'!F24/1000 -> 3.623 | W25: ='Raw - 2025 PL'!G24/1000 -> 4.964 | X25: ='Raw - 2025 PL'!H24/1000 -> 5.0585 | Y25: ='Raw - 2025 PL'!I24/1000 -> 4.73 | ... AC25: ='Raw - 2025 PL'!M24/1000 -> 8.885 | AD25: ='Raw - 2026 PL'!B22/1000 -> 10.90952 | AE25: ='Raw - 2026 PL'!C22/1000 -> 10.33497 | AF25: ='Raw - 2026 PL'!D22/1000 -> 11.175 | AG25: ='Raw - 2026 PL'!E22/1000 -> 11.95311 | AH25: ='Raw - 2026 PL'!F22/1000 -> 15.04071 | AI25: ='Raw - 2026 PL'!G22/1000 -> 16.16868 | AJ25: ='Raw - 2026 PL'!H22/1000 -> 16.06915
A26: STR Bill Pay | B26: =SUM(F26:Q26) -> 0.06 | C26: =SUM(R26:AC26) -> 36.6065 | D26: =SUM(AD26:AJ26) -> 45.13 | F26: ='Raw - 2024 PL'!B21/1000 -> 0 | G26: ='Raw - 2024 PL'!C21/1000 -> 0 | H26: ='Raw - 2024 PL'!D21/1000 -> 0 | I26: ='Raw - 2024 PL'!E21/1000 -> 0 | J26: ='Raw - 2024 PL'!F21/1000 -> 0 | K26: ='Raw - 2024 PL'!G21/1000 -> 0 | L26: ='Raw - 2024 PL'!H21/1000 -> 0 | M26: ='Raw - 2024 PL'!I21/1000 -> 0 | ... Q26: ='Raw - 2024 PL'!M21/1000 -> 0.06 | R26: ='Raw - 2025 PL'!B25/1000 -> 0.97 | S26: ='Raw - 2025 PL'!C25/1000 -> 1.1 | T26: ='Raw - 2025 PL'!D25/1000 -> 1.735 | U26: ='Raw - 2025 PL'!E25/1000 -> 2.14 | V26: ='Raw - 2025 PL'!F25/1000 -> 2.363 | W26: ='Raw - 2025 PL'!G25/1000 -> 3.2635 | X26: ='Raw - 2025 PL'!H25/1000 -> 3.92 | Y26: ='Raw - 2025 PL'!I25/1000 -> 3.905 | ... AC26: ='Raw - 2025 PL'!M25/1000 -> 5.305 | AD26: ='Raw - 2026 PL'!B23/1000 -> 6.3 | AE26: ='Raw - 2026 PL'!C23/1000 -> 6.39 | AF26: ='Raw - 2026 PL'!D23/1000 -> 6.425 | AG26: ='Raw - 2026 PL'!E23/1000 -> 6.08 | AH26: ='Raw - 2026 PL'!F23/1000 -> 6.325 | AI26: ='Raw - 2026 PL'!G23/1000 -> 6.655 | AJ26: ='Raw - 2026 PL'!H23/1000 -> 6.955
A27: STR Bookkeeping Subscription | B27: =SUM(F27:Q27) -> 793.47225 | C27: =SUM(R27:AC27) -> 1450.4923 | D27: =SUM(AD27:AJ27) -> 1261.4769 | F27: ='Raw - 2024 PL'!B22/1000 -> 44.6835 | G27: ='Raw - 2024 PL'!C22/1000 -> 47.046 | H27: ='Raw - 2024 PL'!D22/1000 -> 52.47 | I27: ='Raw - 2024 PL'!E22/1000 -> 57.1697 | J27: ='Raw - 2024 PL'!F22/1000 -> 57.51415 | K27: ='Raw - 2024 PL'!G22/1000 -> 65.516 | L27: ='Raw - 2024 PL'!H22/1000 -> 68.28125 | M27: ='Raw - 2024 PL'!I22/1000 -> 73.25135 | ... Q27: ='Raw - 2024 PL'!M22/1000 -> 89.58455 | R27: ='Raw - 2025 PL'!B26/1000 -> 92.4189 | S27: ='Raw - 2025 PL'!C26/1000 -> 94.00215 | T27: ='Raw - 2025 PL'!D26/1000 -> 101.50605 | U27: ='Raw - 2025 PL'!E26/1000 -> 106.1375 | V27: ='Raw - 2025 PL'!F26/1000 -> 115.93875 | W27: ='Raw - 2025 PL'!G26/1000 -> 119.43125 | X27: ='Raw - 2025 PL'!H26/1000 -> 122.094 | Y27: ='Raw - 2025 PL'!I26/1000 -> 130.08525 | ... AC27: ='Raw - 2025 PL'!M26/1000 -> 150.39825 | AD27: ='Raw - 2026 PL'!B24/1000 -> 156.5388 | AE27: ='Raw - 2026 PL'!C24/1000 -> 164.9034 | AF27: ='Raw - 2026 PL'!D24/1000 -> 170.34425 | AG27: ='Raw - 2026 PL'!E24/1000 -> 183.662 | AH27: ='Raw - 2026 PL'!F24/1000 -> 190.7844 | AI27: ='Raw - 2026 PL'!G24/1000 -> 194.4065 | AJ27: ='Raw - 2026 PL'!H24/1000 -> 200.8375
A28: Topkey Subscription | B28: =SUM(F28:Q28) -> 0 | C28: =SUM(R28:AC28) -> 9.947 | D28: =SUM(AD28:AJ28) -> 45.086 | R28: ='Raw - 2025 PL'!B27/1000 -> 0 | S28: ='Raw - 2025 PL'!C27/1000 -> 0 | T28: ='Raw - 2025 PL'!D27/1000 -> 0 | U28: ='Raw - 2025 PL'!E27/1000 -> 0 | V28: ='Raw - 2025 PL'!F27/1000 -> 0 | W28: ='Raw - 2025 PL'!G27/1000 -> 0 | X28: ='Raw - 2025 PL'!H27/1000 -> 0 | Y28: ='Raw - 2025 PL'!I27/1000 -> 0 | ... AC28: ='Raw - 2025 PL'!M27/1000 -> 4.259 | AD28: ='Raw - 2026 PL'!B25/1000 -> 5.254 | AE28: ='Raw - 2026 PL'!C25/1000 -> 5.652 | AF28: ='Raw - 2026 PL'!D25/1000 -> 5.324 | AG28: ='Raw - 2026 PL'!E25/1000 -> 6.321 | AH28: ='Raw - 2026 PL'!F25/1000 -> 6.959 | AI28: ='Raw - 2026 PL'!G25/1000 -> 7.673 | AJ28: ='Raw - 2026 PL'!H25/1000 -> 7.903
A29: Total STR Recurring Revenue | B29: =SUM(F29:Q29) -> 807.84225 | C29: =SUM(R29:AC29) -> 1598.5264 | D29: =SUM(AD29:AJ29) -> 1467.594 | F29: =SUM(F23,F24,F25,F26,F27,F28) -> 44.6835 | G29: =SUM(G23,G24,G25,G26,G27,G28) -> 47.046 | H29: =SUM(H23,H24,H25,H26,H27,H28) -> 52.47 | I29: =SUM(I23,I24,I25,I26,I27,I28) -> 57.1697 | J29: =SUM(J23,J24,J25,J26,J27,J28) -> 57.51415 | K29: =SUM(K23,K24,K25,K26,K27,K28) -> 65.516 | L29: =SUM(L23,L24,L25,L26,L27,L28) -> 69.53125 | M29: =SUM(M23,M24,M25,M26,M27,M28) -> 74.50135 | ... AJ29: =SUM(AJ23,AJ24,AJ25,AJ26,AJ27,AJ28) -> 235.26465
A30: Total Income | B30: =SUM(F30:Q30) -> 1134.9659 | C30: =SUM(R30:AC30) -> 1879.3831 | D30: =SUM(AD30:AJ30) -> 1671.0212 | F30: =SUM(F11,F17,F21,F22,F29) -> 80.9131 | G30: =SUM(G11,G17,G21,G22,G29) -> 81.2557 | H30: =SUM(H11,H17,H21,H22,H29) -> 78.1122 | I30: =SUM(I11,I17,I21,I22,I29) -> 83.3533 | J30: =SUM(J11,J17,J21,J22,J29) -> 90.19615 | K30: =SUM(K11,K17,K21,K22,K29) -> 89.9158 | L30: =SUM(L11,L17,L21,L22,L29) -> 104.68205 | M30: =SUM(M11,M17,M21,M22,M29) -> 104.11675 | ... AJ30: =SUM(AJ11,AJ17,AJ21,AJ22,AJ29) -> 251.42585
A31: Cost of Goods Sold
A32: 1099 Filing Fees | B32: =SUM(F32:Q32) -> 1.34593 | C32: =SUM(R32:AC32) -> 2.49433 | D32: =SUM(AD32:AJ32) -> 3.20461 | F32: ='Raw - 2024 PL'!B26/1000 -> 1.29934 | G32: ='Raw - 2024 PL'!C26/1000 -> 0.03012 | H32: ='Raw - 2024 PL'!D26/1000 -> 0.01063 | I32: ='Raw - 2024 PL'!E26/1000 -> 0.00325 | J32: ='Raw - 2024 PL'!F26/1000 -> 0.00065 | K32: ='Raw - 2024 PL'!G26/1000 -> 0 | L32: ='Raw - 2024 PL'!H26/1000 -> 0 | M32: ='Raw - 2024 PL'!I26/1000 -> 0.00194 | ... Q32: ='Raw - 2024 PL'!M26/1000 -> 0 | R32: ='Raw - 2025 PL'!B31/1000 -> 1.22655 | S32: ='Raw - 2025 PL'!C31/1000 -> 0 | T32: ='Raw - 2025 PL'!D31/1000 -> 1.15433 | U32: ='Raw - 2025 PL'!E31/1000 -> 0 | V32: ='Raw - 2025 PL'!F31/1000 -> 0 | W32: ='Raw - 2025 PL'!G31/1000 -> 0 | X32: ='Raw - 2025 PL'!H31/1000 -> 0 | Y32: ='Raw - 2025 PL'!I31/1000 -> 0 | ... AC32: ='Raw - 2025 PL'!M31/1000 -> 0 | AD32: ='Raw - 2026 PL'!B29/1000 -> 2.4948 | AE32: ='Raw - 2026 PL'!C29/1000 -> 0 | AF32: ='Raw - 2026 PL'!D29/1000 -> 0 | AG32: ='Raw - 2026 PL'!E29/1000 -> 0.70981 | AH32: ='Raw - 2026 PL'!F29/1000 -> 0 | AI32: ='Raw - 2026 PL'!G29/1000 -> 0 | AJ32: ='Raw - 2026 PL'!H29/1000 -> 0
A33: Contract Labor - Tax | B33: =SUM(F33:Q33) -> 0 | C33: =SUM(R33:AC33) -> 1.5875 | D33: =SUM(AD33:AJ33) -> 30.5155 | R33: ='Raw - 2025 PL'!B32/1000 -> 0 | S33: ='Raw - 2025 PL'!C32/1000 -> 0 | T33: ='Raw - 2025 PL'!D32/1000 -> 0 | U33: ='Raw - 2025 PL'!E32/1000 -> 0 | V33: ='Raw - 2025 PL'!F32/1000 -> 0 | W33: ='Raw - 2025 PL'!G32/1000 -> 0 | X33: ='Raw - 2025 PL'!H32/1000 -> 0 | Y33: ='Raw - 2025 PL'!I32/1000 -> 0 | ... AC33: ='Raw - 2025 PL'!M32/1000 -> 0 | AD33: ='Raw - 2026 PL'!B30/1000 -> 0 | AE33: ='Raw - 2026 PL'!C30/1000 -> 3 | AF33: ='Raw - 2026 PL'!D30/1000 -> 16.2655 | AG33: ='Raw - 2026 PL'!E30/1000 -> 2.8 | AH33: ='Raw - 2026 PL'!F30/1000 -> 0 | AI33: ='Raw - 2026 PL'!G30/1000 -> 8.45 | AJ33: ='Raw - 2026 PL'!H30/1000 -> 0
A34: Direct Labor | B34: =SUM(F34:Q34) -> 0 | C34: =SUM(R34:AC34) -> 0 | D34: =SUM(AD34:AJ34) -> 0 | F34: ='Raw - 2024 PL'!B27/1000 -> 0 | G34: ='Raw - 2024 PL'!C27/1000 -> 0 | H34: ='Raw - 2024 PL'!D27/1000 -> 0 | I34: ='Raw - 2024 PL'!E27/1000 -> 0 | J34: ='Raw - 2024 PL'!F27/1000 -> 0 | K34: ='Raw - 2024 PL'!G27/1000 -> 0 | L34: ='Raw - 2024 PL'!H27/1000 -> 0 | M34: ='Raw - 2024 PL'!I27/1000 -> 0 | ... Q34: ='Raw - 2024 PL'!M27/1000 -> 0 | R34: ='Raw - 2025 PL'!B33/1000 -> 0 | S34: ='Raw - 2025 PL'!C33/1000 -> 0 | T34: ='Raw - 2025 PL'!D33/1000 -> 0 | U34: ='Raw - 2025 PL'!E33/1000 -> 0 | V34: ='Raw - 2025 PL'!F33/1000 -> 0 | W34: ='Raw - 2025 PL'!G33/1000 -> 0 | X34: ='Raw - 2025 PL'!H33/1000 -> 0 | Y34: ='Raw - 2025 PL'!I33/1000 -> 0 | ... AC34: ='Raw - 2025 PL'!M33/1000 -> 0 | AD34: ='Raw - 2026 PL'!B31/1000 -> 0 | AE34: ='Raw - 2026 PL'!C31/1000 -> 0 | AF34: ='Raw - 2026 PL'!D31/1000 -> 0 | AG34: ='Raw - 2026 PL'!E31/1000 -> 0 | AH34: ='Raw - 2026 PL'!F31/1000 -> 0 | AI34: ='Raw - 2026 PL'!G31/1000 -> 0 | AJ34: ='Raw - 2026 PL'!H31/1000 -> 0
A35: Bookkeeper Wages | B35: =SUM(F35:Q35) -> 183.36903 | C35: =SUM(R35:AC35) -> 316.18462 | D35: =SUM(AD35:AJ35) -> 267.7574 | F35: ='Raw - 2024 PL'!B28/1000 -> 9.555 | G35: ='Raw - 2024 PL'!C28/1000 -> 9.555 | H35: ='Raw - 2024 PL'!D28/1000 -> 10.3972 | I35: ='Raw - 2024 PL'!E28/1000 -> 14.99967 | J35: ='Raw - 2024 PL'!F28/1000 -> 18.0098 | K35: ='Raw - 2024 PL'!G28/1000 -> 13.89127 | L35: ='Raw - 2024 PL'!H28/1000 -> 14.04824 | M35: ='Raw - 2024 PL'!I28/1000 -> 13.39091 | ... Q35: ='Raw - 2024 PL'!M28/1000 -> 21.78143 | R35: ='Raw - 2025 PL'!B34/1000 -> 19.40233 | S35: ='Raw - 2025 PL'!C34/1000 -> 16.40053 | T35: ='Raw - 2025 PL'!D34/1000 -> 19.56983 | U35: ='Raw - 2025 PL'!E34/1000 -> 22.1542 | V35: ='Raw - 2025 PL'!F34/1000 -> 20.79154 | W35: ='Raw - 2025 PL'!G34/1000 -> 21.04079 | X35: ='Raw - 2025 PL'!H34/1000 -> 27.90891 | Y35: ='Raw - 2025 PL'!I34/1000 -> 29.547 | ... AC35: ='Raw - 2025 PL'!M34/1000 -> 34.06458 | AD35: ='Raw - 2026 PL'!B32/1000 -> 38.37888 | AE35: ='Raw - 2026 PL'!C32/1000 -> 29.70152 | AF35: ='Raw - 2026 PL'!D32/1000 -> 37.4225 | AG35: ='Raw - 2026 PL'!E32/1000 -> 38.7723 | AH35: ='Raw - 2026 PL'!F32/1000 -> 38.29477 | AI35: ='Raw - 2026 PL'!G32/1000 -> 40.69983 | AJ35: ='Raw - 2026 PL'!H32/1000 -> 44.4876
A36: Client Lead Wages | B36: =SUM(F36:Q36) -> 286.16129 | C36: =SUM(R36:AC36) -> 352.95844 | D36: =SUM(AD36:AJ36) -> 202.05309 | F36: ='Raw - 2024 PL'!B29/1000 -> 9.96108 | G36: ='Raw - 2024 PL'!C29/1000 -> 13.85026 | H36: ='Raw - 2024 PL'!D29/1000 -> 12.79054 | I36: ='Raw - 2024 PL'!E29/1000 -> 14.57145 | J36: ='Raw - 2024 PL'!F29/1000 -> 28.28563 | K36: ='Raw - 2024 PL'!G29/1000 -> 26.54254 | L36: ='Raw - 2024 PL'!H29/1000 -> 28.31119 | M36: ='Raw - 2024 PL'!I29/1000 -> 28.18746 | ... Q36: ='Raw - 2024 PL'!M29/1000 -> 32.72211 | R36: ='Raw - 2025 PL'!B35/1000 -> 32.78076 | S36: ='Raw - 2025 PL'!C35/1000 -> 23.36184 | T36: ='Raw - 2025 PL'!D35/1000 -> 26.91427 | U36: ='Raw - 2025 PL'!E35/1000 -> 28.81298 | V36: ='Raw - 2025 PL'!F35/1000 -> 30.65875 | W36: ='Raw - 2025 PL'!G35/1000 -> 29.2716 | X36: ='Raw - 2025 PL'!H35/1000 -> 29.47963 | Y36: ='Raw - 2025 PL'!I35/1000 -> 26.83064 | ... AC36: ='Raw - 2025 PL'!M35/1000 -> 32.66971 | AD36: ='Raw - 2026 PL'!B33/1000 -> 26.1149 | AE36: ='Raw - 2026 PL'!C33/1000 -> 21.9055 | AF36: ='Raw - 2026 PL'!D33/1000 -> 30.75844 | AG36: ='Raw - 2026 PL'!E33/1000 -> 31.59038 | AH36: ='Raw - 2026 PL'!F33/1000 -> 27.69992 | AI36: ='Raw - 2026 PL'!G33/1000 -> 31.24024 | AJ36: ='Raw - 2026 PL'!H33/1000 -> 32.74371
A37: Occupancy Tax Specialist | B37: =SUM(F37:Q37) -> 1.11335 | C37: =SUM(R37:AC37) -> 29.56415 | D37: =SUM(AD37:AJ37) -> 42.08505 | F37: ='Raw - 2024 PL'!B30/1000 -> 0 | G37: ='Raw - 2024 PL'!C30/1000 -> 0 | H37: ='Raw - 2024 PL'!D30/1000 -> 0 | I37: ='Raw - 2024 PL'!E30/1000 -> 0 | J37: ='Raw - 2024 PL'!F30/1000 -> 0 | K37: ='Raw - 2024 PL'!G30/1000 -> 0 | L37: ='Raw - 2024 PL'!H30/1000 -> 0 | M37: ='Raw - 2024 PL'!I30/1000 -> 0 | ... Q37: ='Raw - 2024 PL'!M30/1000 -> 1.11335 | R37: ='Raw - 2025 PL'!B36/1000 -> 2.17917 | S37: ='Raw - 2025 PL'!C36/1000 -> 1.82504 | T37: ='Raw - 2025 PL'!D36/1000 -> 1.97853 | U37: ='Raw - 2025 PL'!E36/1000 -> 2.06213 | V37: ='Raw - 2025 PL'!F36/1000 -> 2.06213 | W37: ='Raw - 2025 PL'!G36/1000 -> 1.98968 | X37: ='Raw - 2025 PL'!H36/1000 -> 2.17917 | Y37: ='Raw - 2025 PL'!I36/1000 -> 2.12293 | ... AC37: ='Raw - 2025 PL'!M36/1000 -> 3.15033 | AD37: ='Raw - 2026 PL'!B34/1000 -> 1.69116 | AE37: ='Raw - 2026 PL'!C34/1000 -> 5.54919 | AF37: ='Raw - 2026 PL'!D34/1000 -> 7.1999 | AG37: ='Raw - 2026 PL'!E34/1000 -> 8.1927 | AH37: ='Raw - 2026 PL'!F34/1000 -> 8.28335 | AI37: ='Raw - 2026 PL'!G34/1000 -> 5.49265 | AJ37: ='Raw - 2026 PL'!H34/1000 -> 5.6761
A38: Onboarding Team Wages | B38: =SUM(F38:Q38) -> 122.81255 | C38: =SUM(R38:AC38) -> 152.16972 | D38: =SUM(AD38:AJ38) -> 111.27999 | F38: ='Raw - 2024 PL'!B31/1000 -> 9.13728 | G38: ='Raw - 2024 PL'!C31/1000 -> 8.96296 | H38: ='Raw - 2024 PL'!D31/1000 -> 10.19584 | I38: ='Raw - 2024 PL'!E31/1000 -> 15.04429 | J38: ='Raw - 2024 PL'!F31/1000 -> 16.63744 | K38: ='Raw - 2024 PL'!G31/1000 -> 7.49499 | L38: ='Raw - 2024 PL'!H31/1000 -> 7.98202 | M38: ='Raw - 2024 PL'!I31/1000 -> 5.90274 | ... Q38: ='Raw - 2024 PL'!M31/1000 -> 12.85047 | R38: ='Raw - 2025 PL'!B37/1000 -> 10.34556 | S38: ='Raw - 2025 PL'!C37/1000 -> 8.08798 | T38: ='Raw - 2025 PL'!D37/1000 -> 9.75287 | U38: ='Raw - 2025 PL'!E37/1000 -> 10.28 | V38: ='Raw - 2025 PL'!F37/1000 -> 11.13632 | W38: ='Raw - 2025 PL'!G37/1000 -> 10.87432 | X38: ='Raw - 2025 PL'!H37/1000 -> 13.47257 | Y38: ='Raw - 2025 PL'!I37/1000 -> 12.70407 | ... AC38: ='Raw - 2025 PL'!M37/1000 -> 20.93052 | AD38: ='Raw - 2026 PL'!B35/1000 -> 16.55394 | AE38: ='Raw - 2026 PL'!C35/1000 -> 11.52661 | AF38: ='Raw - 2026 PL'!D35/1000 -> 14.93883 | AG38: ='Raw - 2026 PL'!E35/1000 -> 15.58352 | AH38: ='Raw - 2026 PL'!F35/1000 -> 19.6034 | AI38: ='Raw - 2026 PL'!G35/1000 -> 16.64457 | AJ38: ='Raw - 2026 PL'!H35/1000 -> 16.42912
A39: Sr. Client Lead Wages | B39: =SUM(F39:Q39) -> 0 | C39: =SUM(R39:AC39) -> 0 | D39: =SUM(AD39:AJ39) -> 7.995 | AD39: ='Raw - 2026 PL'!B36/1000 -> 0 | AE39: ='Raw - 2026 PL'!C36/1000 -> 0 | AF39: ='Raw - 2026 PL'!D36/1000 -> 0 | AG39: ='Raw - 2026 PL'!E36/1000 -> 0 | AH39: ='Raw - 2026 PL'!F36/1000 -> 2.51706 | AI39: ='Raw - 2026 PL'!G36/1000 -> 2.72117 | AJ39: ='Raw - 2026 PL'!H36/1000 -> 2.75677
A40: Total Direct Labor | B40: =SUM(F40:Q40) -> 593.45622 | C40: =SUM(R40:AC40) -> 850.87693 | D40: =SUM(AD40:AJ40) -> 631.17053 | F40: =SUM(F34,F35,F36,F37,F38,F39) -> 28.65336 | G40: =SUM(G34,G35,G36,G37,G38,G39) -> 32.36822 | H40: =SUM(H34,H35,H36,H37,H38,H39) -> 33.38358 | I40: =SUM(I34,I35,I36,I37,I38,I39) -> 44.61541 | J40: =SUM(J34,J35,J36,J37,J38,J39) -> 62.93287 | K40: =SUM(K34,K35,K36,K37,K38,K39) -> 47.9288 | L40: =SUM(L34,L35,L36,L37,L38,L39) -> 50.34145 | M40: =SUM(M34,M35,M36,M37,M38,M39) -> 47.48111 | ... AJ40: =SUM(AJ34,AJ35,AJ36,AJ37,AJ38,AJ39) -> 102.0933
A41: Occupancy Tax Filing Fees | B41: =SUM(F41:Q41) -> 0 | C41: =SUM(R41:AC41) -> 1.75591 | D41: =SUM(AD41:AJ41) -> 1.53949 | R41: ='Raw - 2025 PL'!B39/1000 -> 0.1 | S41: ='Raw - 2025 PL'!C39/1000 -> 0 | T41: ='Raw - 2025 PL'!D39/1000 -> 0 | U41: ='Raw - 2025 PL'!E39/1000 -> 0.1498 | V41: ='Raw - 2025 PL'!F39/1000 -> 0.05975 | W41: ='Raw - 2025 PL'!G39/1000 -> 0.0697 | X41: ='Raw - 2025 PL'!H39/1000 -> 0.1597 | Y41: ='Raw - 2025 PL'!I39/1000 -> 0.31085 | ... AC41: ='Raw - 2025 PL'!M39/1000 -> 0.1095 | AD41: ='Raw - 2026 PL'!B38/1000 -> 0.2294 | AE41: ='Raw - 2026 PL'!C38/1000 -> 0.1194 | AF41: ='Raw - 2026 PL'!D38/1000 -> 0.17935 | AG41: ='Raw - 2026 PL'!E38/1000 -> 0.0699 | AH41: ='Raw - 2026 PL'!F38/1000 -> 0.0699 | AI41: ='Raw - 2026 PL'!G38/1000 -> 0.16398 | AJ41: ='Raw - 2026 PL'!H38/1000 -> 0.70756
A42: Payment Collection Fees | B42: =SUM(F42:Q42) -> 8.67099 | C42: =SUM(R42:AC42) -> 13.35153 | D42: =SUM(AD42:AJ42) -> 9.02684 | F42: ='Raw - 2024 PL'!B33/1000 -> 0.6179 | G42: ='Raw - 2024 PL'!C33/1000 -> 0.8374 | H42: ='Raw - 2024 PL'!D33/1000 -> 0.62936 | I42: ='Raw - 2024 PL'!E33/1000 -> 0.68245 | J42: ='Raw - 2024 PL'!F33/1000 -> 0.72151 | K42: ='Raw - 2024 PL'!G33/1000 -> 0.78747 | L42: ='Raw - 2024 PL'!H33/1000 -> 0.65562 | M42: ='Raw - 2024 PL'!I33/1000 -> 0.79491 | ... Q42: ='Raw - 2024 PL'!M33/1000 -> 0.79818 | R42: ='Raw - 2025 PL'!B40/1000 -> 0.83546 | S42: ='Raw - 2025 PL'!C40/1000 -> 1.05394 | T42: ='Raw - 2025 PL'!D40/1000 -> 0.87069 | U42: ='Raw - 2025 PL'!E40/1000 -> 0.90555 | V42: ='Raw - 2025 PL'!F40/1000 -> 0.91157 | W42: ='Raw - 2025 PL'!G40/1000 -> 1.00249 | X42: ='Raw - 2025 PL'!H40/1000 -> 1.22475 | Y42: ='Raw - 2025 PL'!I40/1000 -> 1.10438 | ... AC42: ='Raw - 2025 PL'!M40/1000 -> 1.30514 | AD42: ='Raw - 2026 PL'!B39/1000 -> 1.22974 | AE42: ='Raw - 2026 PL'!C39/1000 -> 1.73847 | AF42: ='Raw - 2026 PL'!D39/1000 -> 1.35348 | AG42: ='Raw - 2026 PL'!E39/1000 -> 1.23399 | AH42: ='Raw - 2026 PL'!F39/1000 -> 1.17137 | AI42: ='Raw - 2026 PL'!G39/1000 -> 1.15392 | AJ42: ='Raw - 2026 PL'!H39/1000 -> 1.14587
A43: Referral Fees | B43: =SUM(F43:Q43) -> 24.82 | C43: =SUM(R43:AC43) -> 27.15374 | D43: =SUM(AD43:AJ43) -> 20.62969 | F43: ='Raw - 2024 PL'!B34/1000 -> 2.21 | G43: ='Raw - 2024 PL'!C34/1000 -> 2.735 | H43: ='Raw - 2024 PL'!D34/1000 -> 2.715 | I43: ='Raw - 2024 PL'!E34/1000 -> 2.735 | J43: ='Raw - 2024 PL'!F34/1000 -> 0.78 | K43: ='Raw - 2024 PL'!G34/1000 -> 3.245 | L43: ='Raw - 2024 PL'!H34/1000 -> 1.28 | M43: ='Raw - 2024 PL'!I34/1000 -> 1.3 | ... Q43: ='Raw - 2024 PL'!M34/1000 -> 2.355 | R43: ='Raw - 2025 PL'!B41/1000 -> 1.47025 | S43: ='Raw - 2025 PL'!C41/1000 -> 1.665 | T43: ='Raw - 2025 PL'!D41/1000 -> 2.62775 | U43: ='Raw - 2025 PL'!E41/1000 -> 1.24875 | V43: ='Raw - 2025 PL'!F41/1000 -> 2.154 | W43: ='Raw - 2025 PL'!G41/1000 -> 4.154 | X43: ='Raw - 2025 PL'!H41/1000 -> 3.76975 | Y43: ='Raw - 2025 PL'!I41/1000 -> 1.696 | ... AC43: ='Raw - 2025 PL'!M41/1000 -> 2.75745 | AD43: ='Raw - 2026 PL'!B40/1000 -> 1.8688 | AE43: ='Raw - 2026 PL'!C40/1000 -> 4.43991 | AF43: ='Raw - 2026 PL'!D40/1000 -> 2.39361 | AG43: ='Raw - 2026 PL'!E40/1000 -> 3.65786 | AH43: ='Raw - 2026 PL'!F40/1000 -> 2.93379 | AI43: ='Raw - 2026 PL'!G40/1000 -> 1.5662 | AJ43: ='Raw - 2026 PL'!H40/1000 -> 3.76952
A44: Service Discount | B44: =SUM(F44:Q44) -> 0 | C44: =SUM(R44:AC44) -> 4.64 | D44: =SUM(AD44:AJ44) -> 0 | R44: ='Raw - 2025 PL'!B42/1000 -> 0 | S44: ='Raw - 2025 PL'!C42/1000 -> 0 | T44: ='Raw - 2025 PL'!D42/1000 -> 4.64 | U44: ='Raw - 2025 PL'!E42/1000 -> 0 | V44: ='Raw - 2025 PL'!F42/1000 -> 0 | W44: ='Raw - 2025 PL'!G42/1000 -> 0 | X44: ='Raw - 2025 PL'!H42/1000 -> 0 | Y44: ='Raw - 2025 PL'!I42/1000 -> 0 | ... AC44: ='Raw - 2025 PL'!M42/1000 -> 0
A45: Software & Apps - COGS | B45: =SUM(F45:Q45) -> 114.42269 | C45: =SUM(R45:AC45) -> 157.49471 | D45: =SUM(AD45:AJ45) -> 152.28157 | F45: ='Raw - 2024 PL'!B35/1000 -> 7.073 | G45: ='Raw - 2024 PL'!C35/1000 -> 7.01818 | H45: ='Raw - 2024 PL'!D35/1000 -> 7.77788 | I45: ='Raw - 2024 PL'!E35/1000 -> 7.76124 | J45: ='Raw - 2024 PL'!F35/1000 -> 7.71821 | K45: ='Raw - 2024 PL'!G35/1000 -> 8.91264 | L45: ='Raw - 2024 PL'!H35/1000 -> 10.84668 | M45: ='Raw - 2024 PL'!I35/1000 -> 11.13514 | ... Q45: ='Raw - 2024 PL'!M35/1000 -> 11.96958 | R45: ='Raw - 2025 PL'!B43/1000 -> 10.84853 | S45: ='Raw - 2025 PL'!C43/1000 -> 12.21311 | T45: ='Raw - 2025 PL'!D43/1000 -> 11.57167 | U45: ='Raw - 2025 PL'!E43/1000 -> 11.81087 | V45: ='Raw - 2025 PL'!F43/1000 -> 12.52563 | W45: ='Raw - 2025 PL'!G43/1000 -> 12.86333 | X45: ='Raw - 2025 PL'!H43/1000 -> 13.13545 | Y45: ='Raw - 2025 PL'!I43/1000 -> 14.25715 | ... AC45: ='Raw - 2025 PL'!M43/1000 -> 17.10842 | AD45: ='Raw - 2026 PL'!B41/1000 -> 18.4683 | AE45: ='Raw - 2026 PL'!C41/1000 -> 17.92027 | AF45: ='Raw - 2026 PL'!D41/1000 -> 18.40906 | AG45: ='Raw - 2026 PL'!E41/1000 -> 21.38775 | AH45: ='Raw - 2026 PL'!F41/1000 -> 23.44584 | AI45: ='Raw - 2026 PL'!G41/1000 -> 24.67467 | AJ45: ='Raw - 2026 PL'!H41/1000 -> 27.97568
A46: Software & Apps - Tax | B46: =SUM(F46:Q46) -> 0 | C46: =SUM(R46:AC46) -> 0.39695 | D46: =SUM(AD46:AJ46) -> 3.78835 | R46: ='Raw - 2025 PL'!B44/1000 -> 0 | S46: ='Raw - 2025 PL'!C44/1000 -> 0 | T46: ='Raw - 2025 PL'!D44/1000 -> 0 | U46: ='Raw - 2025 PL'!E44/1000 -> 0 | V46: ='Raw - 2025 PL'!F44/1000 -> 0 | W46: ='Raw - 2025 PL'!G44/1000 -> 0 | X46: ='Raw - 2025 PL'!H44/1000 -> 0 | Y46: ='Raw - 2025 PL'!I44/1000 -> 0 | ... AC46: ='Raw - 2025 PL'!M44/1000 -> 0 | AD46: ='Raw - 2026 PL'!B42/1000 -> 0 | AE46: ='Raw - 2026 PL'!C42/1000 -> 2.18405 | AF46: ='Raw - 2026 PL'!D42/1000 -> 1.6043 | AG46: ='Raw - 2026 PL'!E42/1000 -> 0 | AH46: ='Raw - 2026 PL'!F42/1000 -> 0 | AI46: ='Raw - 2026 PL'!G42/1000 -> 0 | AJ46: ='Raw - 2026 PL'!H42/1000 -> 0
A47: Software & Apps - Topkey | B47: =SUM(F47:Q47) -> 0 | C47: =SUM(R47:AC47) -> 7.14125 | D47: =SUM(AD47:AJ47) -> 28.82775 | R47: ='Raw - 2025 PL'!B45/1000 -> 0 | S47: ='Raw - 2025 PL'!C45/1000 -> 0 | T47: ='Raw - 2025 PL'!D45/1000 -> 0 | U47: ='Raw - 2025 PL'!E45/1000 -> 0 | V47: ='Raw - 2025 PL'!F45/1000 -> 0 | W47: ='Raw - 2025 PL'!G45/1000 -> 0 | X47: ='Raw - 2025 PL'!H45/1000 -> 0 | Y47: ='Raw - 2025 PL'!I45/1000 -> 0 | ... AC47: ='Raw - 2025 PL'!M45/1000 -> 2.4505 | AD47: ='Raw - 2026 PL'!B43/1000 -> 2.94975 | AE47: ='Raw - 2026 PL'!C43/1000 -> 3.42 | AF47: ='Raw - 2026 PL'!D43/1000 -> 3.678 | AG47: ='Raw - 2026 PL'!E43/1000 -> 4.218 | AH47: ='Raw - 2026 PL'!F43/1000 -> 4.284 | AI47: ='Raw - 2026 PL'!G43/1000 -> 5.208 | AJ47: ='Raw - 2026 PL'!H43/1000 -> 5.07
A48: Total Cost of Goods Sold | B48: =SUM(F48:Q48) -> 742.71583 | C48: =SUM(R48:AC48) -> 1066.8928 | D48: =SUM(AD48:AJ48) -> 880.98433 | F48: =SUM(F32,F33,F40,F41,F42,F43,F44,F45,F46,F47) -> 39.8536 | G48: =SUM(G32,G33,G40,G41,G42,G43,G44,G45,G46,G47) -> 42.98892 | H48: =SUM(H32,H33,H40,H41,H42,H43,H44,H45,H46,H47) -> 44.51645 | I48: =SUM(I32,I33,I40,I41,I42,I43,I44,I45,I46,I47) -> 55.79735 | J48: =SUM(J32,J33,J40,J41,J42,J43,J44,J45,J46,J47) -> 72.15324 | K48: =SUM(K32,K33,K40,K41,K42,K43,K44,K45,K46,K47) -> 60.87391 | L48: =SUM(L32,L33,L40,L41,L42,L43,L44,L45,L46,L47) -> 63.12375 | M48: =SUM(M32,M33,M40,M41,M42,M43,M44,M45,M46,M47) -> 60.7131 | ... AJ48: =SUM(AJ32,AJ33,AJ40,AJ41,AJ42,AJ43,AJ44,AJ45,AJ46,AJ47) -> 140.76193
A49: Gross Profit | B49: =SUM(F49:Q49) -> 392.25002 | C49: =SUM(R49:AC49) -> 812.49028 | D49: =SUM(AD49:AJ49) -> 790.03687 | F49: =F30-F48 -> 41.0595 | G49: =G30-G48 -> 38.26678 | H49: =H30-H48 -> 33.59575 | I49: =I30-I48 -> 27.55595 | J49: =J30-J48 -> 18.04291 | K49: =K30-K48 -> 29.04189 | L49: =L30-L48 -> 41.5583 | M49: =M30-M48 -> 43.40365 | ... AJ49: =AJ30-AJ48 -> 110.66392
A50: Expenses
A51: General & Admin Expenses | B51: =SUM(F51:Q51) -> 0 | C51: =SUM(R51:AC51) -> 0 | D51: =SUM(AD51:AJ51) -> 0 | F51: ='Raw - 2024 PL'!B39/1000 -> 0 | G51: ='Raw - 2024 PL'!C39/1000 -> 0 | H51: ='Raw - 2024 PL'!D39/1000 -> 0 | I51: ='Raw - 2024 PL'!E39/1000 -> 0 | J51: ='Raw - 2024 PL'!F39/1000 -> 0 | K51: ='Raw - 2024 PL'!G39/1000 -> 0 | L51: ='Raw - 2024 PL'!H39/1000 -> 0 | M51: ='Raw - 2024 PL'!I39/1000 -> 0 | ... Q51: ='Raw - 2024 PL'!M39/1000 -> 0 | R51: ='Raw - 2025 PL'!B49/1000 -> 0 | S51: ='Raw - 2025 PL'!C49/1000 -> 0 | T51: ='Raw - 2025 PL'!D49/1000 -> 0 | U51: ='Raw - 2025 PL'!E49/1000 -> 0 | V51: ='Raw - 2025 PL'!F49/1000 -> 0 | W51: ='Raw - 2025 PL'!G49/1000 -> 0 | X51: ='Raw - 2025 PL'!H49/1000 -> 0 | Y51: ='Raw - 2025 PL'!I49/1000 -> 0 | ... AC51: ='Raw - 2025 PL'!M49/1000 -> 0 | AD51: ='Raw - 2026 PL'!B47/1000 -> 0 | AE51: ='Raw - 2026 PL'!C47/1000 -> 0 | AF51: ='Raw - 2026 PL'!D47/1000 -> 0 | AG51: ='Raw - 2026 PL'!E47/1000 -> 0 | AH51: ='Raw - 2026 PL'!F47/1000 -> 0 | AI51: ='Raw - 2026 PL'!G47/1000 -> 0 | AJ51: ='Raw - 2026 PL'!H47/1000 -> 0
A52: Bank Fees | B52: =SUM(F52:Q52) -> 0.14789 | C52: =SUM(R52:AC52) -> 1.83498 | D52: =SUM(AD52:AJ52) -> 1.44025 | F52: ='Raw - 2024 PL'!B40/1000 -> 0.001 | G52: ='Raw - 2024 PL'!C40/1000 -> 0.001 | H52: ='Raw - 2024 PL'!D40/1000 -> 0.001 | I52: ='Raw - 2024 PL'!E40/1000 -> 0.096 | J52: ='Raw - 2024 PL'!F40/1000 -> 0.002 | K52: ='Raw - 2024 PL'!G40/1000 -> 0.001 | L52: ='Raw - 2024 PL'!H40/1000 -> 0.00563 | M52: ='Raw - 2024 PL'!I40/1000 -> 0.001 | ... Q52: ='Raw - 2024 PL'!M40/1000 -> 0.02467 | R52: ='Raw - 2025 PL'!B50/1000 -> 0.13744 | S52: ='Raw - 2025 PL'!C50/1000 -> 0.12214 | T52: ='Raw - 2025 PL'!D50/1000 -> 0.0435 | U52: ='Raw - 2025 PL'!E50/1000 -> 0.399 | V52: ='Raw - 2025 PL'!F50/1000 -> 0.1013 | W52: ='Raw - 2025 PL'!G50/1000 -> 0.0696 | X52: ='Raw - 2025 PL'!H50/1000 -> 0.1472 | Y52: ='Raw - 2025 PL'!I50/1000 -> 0.1098 | ... AC52: ='Raw - 2025 PL'!M50/1000 -> 0.3137 | AD52: ='Raw - 2026 PL'!B48/1000 -> 0.1471 | AE52: ='Raw - 2026 PL'!C48/1000 -> 0.1556 | AF52: ='Raw - 2026 PL'!D48/1000 -> 0.17065 | AG52: ='Raw - 2026 PL'!E48/1000 -> 0.3032 | AH52: ='Raw - 2026 PL'!F48/1000 -> 0.18285 | AI52: ='Raw - 2026 PL'!G48/1000 -> 0.1777 | AJ52: ='Raw - 2026 PL'!H48/1000 -> 0.30315
A53: Company Meals | B53: =SUM(F53:Q53) -> 0 | C53: =SUM(R53:AC53) -> 0 | D53: =SUM(AD53:AJ53) -> 0.01984 | AD53: ='Raw - 2026 PL'!B49/1000 -> 0 | AE53: ='Raw - 2026 PL'!C49/1000 -> 0 | AF53: ='Raw - 2026 PL'!D49/1000 -> 0 | AG53: ='Raw - 2026 PL'!E49/1000 -> 0.01984 | AH53: ='Raw - 2026 PL'!F49/1000 -> 0 | AI53: ='Raw - 2026 PL'!G49/1000 -> 0 | AJ53: ='Raw - 2026 PL'!H49/1000 -> 0
A54: Computer Equipment | B54: =SUM(F54:Q54) -> 0 | C54: =SUM(R54:AC54) -> 2.63107 | D54: =SUM(AD54:AJ54) -> 1.66852 | R54: ='Raw - 2025 PL'!B51/1000 -> 0 | S54: ='Raw - 2025 PL'!C51/1000 -> 0 | T54: ='Raw - 2025 PL'!D51/1000 -> 0 | U54: ='Raw - 2025 PL'!E51/1000 -> 1.84999 | V54: ='Raw - 2025 PL'!F51/1000 -> 0 | W54: ='Raw - 2025 PL'!G51/1000 -> 0 | X54: ='Raw - 2025 PL'!H51/1000 -> 0 | Y54: ='Raw - 2025 PL'!I51/1000 -> 0 | ... AC54: ='Raw - 2025 PL'!M51/1000 -> 0 | AD54: ='Raw - 2026 PL'!B50/1000 -> 0.79968 | AE54: ='Raw - 2026 PL'!C50/1000 -> 0.86884 | AF54: ='Raw - 2026 PL'!D50/1000 -> 0 | AG54: ='Raw - 2026 PL'!E50/1000 -> 0 | AH54: ='Raw - 2026 PL'!F50/1000 -> 0 | AI54: ='Raw - 2026 PL'!G50/1000 -> 0 | AJ54: ='Raw - 2026 PL'!H50/1000 -> 0
A55: Employee Benefits | B55: =SUM(F55:Q55) -> 0 | C55: =SUM(R55:AC55) -> 0 | D55: =SUM(AD55:AJ55) -> 0 | F55: ='Raw - 2024 PL'!B41/1000 -> 0 | G55: ='Raw - 2024 PL'!C41/1000 -> 0 | H55: ='Raw - 2024 PL'!D41/1000 -> 0 | I55: ='Raw - 2024 PL'!E41/1000 -> 0 | J55: ='Raw - 2024 PL'!F41/1000 -> 0 | K55: ='Raw - 2024 PL'!G41/1000 -> 0 | L55: ='Raw - 2024 PL'!H41/1000 -> 0 | M55: ='Raw - 2024 PL'!I41/1000 -> 0 | ... Q55: ='Raw - 2024 PL'!M41/1000 -> 0 | R55: ='Raw - 2025 PL'!B52/1000 -> 0 | S55: ='Raw - 2025 PL'!C52/1000 -> 0 | T55: ='Raw - 2025 PL'!D52/1000 -> 0 | U55: ='Raw - 2025 PL'!E52/1000 -> 0 | V55: ='Raw - 2025 PL'!F52/1000 -> 0 | W55: ='Raw - 2025 PL'!G52/1000 -> 0 | X55: ='Raw - 2025 PL'!H52/1000 -> 0 | Y55: ='Raw - 2025 PL'!I52/1000 -> 0 | ... AC55: ='Raw - 2025 PL'!M52/1000 -> 0 | AD55: ='Raw - 2026 PL'!B51/1000 -> 0 | AE55: ='Raw - 2026 PL'!C51/1000 -> 0 | AF55: ='Raw - 2026 PL'!D51/1000 -> 0 | AG55: ='Raw - 2026 PL'!E51/1000 -> 0 | AH55: ='Raw - 2026 PL'!F51/1000 -> 0 | AI55: ='Raw - 2026 PL'!G51/1000 -> 0 | AJ55: ='Raw - 2026 PL'!H51/1000 -> 0
A56: Education and Training | B56: =SUM(F56:Q56) -> 0 | C56: =SUM(R56:AC56) -> 0.336 | D56: =SUM(AD56:AJ56) -> 0.0162 | R56: ='Raw - 2025 PL'!B53/1000 -> 0 | S56: ='Raw - 2025 PL'!C53/1000 -> 0 | T56: ='Raw - 2025 PL'!D53/1000 -> 0 | U56: ='Raw - 2025 PL'!E53/1000 -> 0 | V56: ='Raw - 2025 PL'!F53/1000 -> 0.3 | W56: ='Raw - 2025 PL'!G53/1000 -> 0.036 | X56: ='Raw - 2025 PL'!H53/1000 -> 0 | Y56: ='Raw - 2025 PL'!I53/1000 -> 0 | ... AC56: ='Raw - 2025 PL'!M53/1000 -> 0 | AD56: ='Raw - 2026 PL'!B52/1000 -> 0.0162 | AE56: ='Raw - 2026 PL'!C52/1000 -> 0 | AF56: ='Raw - 2026 PL'!D52/1000 -> 0 | AG56: ='Raw - 2026 PL'!E52/1000 -> 0 | AH56: ='Raw - 2026 PL'!F52/1000 -> 0 | AI56: ='Raw - 2026 PL'!G52/1000 -> 0 | AJ56: ='Raw - 2026 PL'!H52/1000 -> 0
A57: Employee Equipment Allowance | B57: =SUM(F57:Q57) -> 1.60626 | C57: =SUM(R57:AC57) -> 6.12 | D57: =SUM(AD57:AJ57) -> 4.106 | F57: ='Raw - 2024 PL'!B42/1000 -> 0 | G57: ='Raw - 2024 PL'!C42/1000 -> 0 | H57: ='Raw - 2024 PL'!D42/1000 -> 0 | I57: ='Raw - 2024 PL'!E42/1000 -> 0 | J57: ='Raw - 2024 PL'!F42/1000 -> 0 | K57: ='Raw - 2024 PL'!G42/1000 -> 0 | L57: ='Raw - 2024 PL'!H42/1000 -> 0.381 | M57: ='Raw - 2024 PL'!I42/1000 -> 0.31926 | ... Q57: ='Raw - 2024 PL'!M42/1000 -> 0.093 | R57: ='Raw - 2025 PL'!B54/1000 -> 0 | S57: ='Raw - 2025 PL'!C54/1000 -> 0.173 | T57: ='Raw - 2025 PL'!D54/1000 -> 0.145 | U57: ='Raw - 2025 PL'!E54/1000 -> 0.29 | V57: ='Raw - 2025 PL'!F54/1000 -> 1.004 | W57: ='Raw - 2025 PL'!G54/1000 -> 1.224 | X57: ='Raw - 2025 PL'!H54/1000 -> 0.783 | Y57: ='Raw - 2025 PL'!I54/1000 -> 0.328 | ... AC57: ='Raw - 2025 PL'!M54/1000 -> 0.628 | AD57: ='Raw - 2026 PL'!B53/1000 -> 0.648 | AE57: ='Raw - 2026 PL'!C53/1000 -> 0.071 | AF57: ='Raw - 2026 PL'!D53/1000 -> 1.059 | AG57: ='Raw - 2026 PL'!E53/1000 -> 0.749 | AH57: ='Raw - 2026 PL'!F53/1000 -> 0.477 | AI57: ='Raw - 2026 PL'!G53/1000 -> 0.582 | AJ57: ='Raw - 2026 PL'!H53/1000 -> 0.52
A58: Employee Internet Allowance | B58: =SUM(F58:Q58) -> 0.4103 | C58: =SUM(R58:AC58) -> 2.3864 | D58: =SUM(AD58:AJ58) -> 2.397 | F58: ='Raw - 2024 PL'!B43/1000 -> 0 | G58: ='Raw - 2024 PL'!C43/1000 -> 0 | H58: ='Raw - 2024 PL'!D43/1000 -> 0 | I58: ='Raw - 2024 PL'!E43/1000 -> 0 | J58: ='Raw - 2024 PL'!F43/1000 -> 0 | K58: ='Raw - 2024 PL'!G43/1000 -> 0 | L58: ='Raw - 2024 PL'!H43/1000 -> 0.042 | M58: ='Raw - 2024 PL'!I43/1000 -> 0.0403 | ... Q58: ='Raw - 2024 PL'!M43/1000 -> 0.146 | R58: ='Raw - 2025 PL'!B55/1000 -> 0.15 | S58: ='Raw - 2025 PL'!C55/1000 -> 0.243 | T58: ='Raw - 2025 PL'!D55/1000 -> 0.136 | U58: ='Raw - 2025 PL'!E55/1000 -> 0.144 | V58: ='Raw - 2025 PL'!F55/1000 -> 0.1704 | W58: ='Raw - 2025 PL'!G55/1000 -> 0.185 | X58: ='Raw - 2025 PL'!H55/1000 -> 0.161 | Y58: ='Raw - 2025 PL'!I55/1000 -> 0.168 | ... AC58: ='Raw - 2025 PL'!M55/1000 -> 0.197 | AD58: ='Raw - 2026 PL'!B54/1000 -> 0.254 | AE58: ='Raw - 2026 PL'!C54/1000 -> 0.314 | AF58: ='Raw - 2026 PL'!D54/1000 -> 0.338 | AG58: ='Raw - 2026 PL'!E54/1000 -> 0.29 | AH58: ='Raw - 2026 PL'!F54/1000 -> 0.443 | AI58: ='Raw - 2026 PL'!G54/1000 -> 0.388 | AJ58: ='Raw - 2026 PL'!H54/1000 -> 0.37
A59: Employee Medical Allowance | B59: =SUM(F59:Q59) -> 0 | C59: =SUM(R59:AC59) -> 2.519 | D59: =SUM(AD59:AJ59) -> 4.1 | R59: ='Raw - 2025 PL'!B56/1000 -> 0 | S59: ='Raw - 2025 PL'!C56/1000 -> 0 | T59: ='Raw - 2025 PL'!D56/1000 -> 0 | U59: ='Raw - 2025 PL'!E56/1000 -> 0 | V59: ='Raw - 2025 PL'!F56/1000 -> 0 | W59: ='Raw - 2025 PL'!G56/1000 -> 0 | X59: ='Raw - 2025 PL'!H56/1000 -> 0 | Y59: ='Raw - 2025 PL'!I56/1000 -> 0 | ... AC59: ='Raw - 2025 PL'!M56/1000 -> 2.519 | AD59: ='Raw - 2026 PL'!B55/1000 -> 0 | AE59: ='Raw - 2026 PL'!C55/1000 -> 0 | AF59: ='Raw - 2026 PL'!D55/1000 -> 1.55 | AG59: ='Raw - 2026 PL'!E55/1000 -> 0.524 | AH59: ='Raw - 2026 PL'!F55/1000 -> 0.223 | AI59: ='Raw - 2026 PL'!G55/1000 -> 1.282 | AJ59: ='Raw - 2026 PL'!H55/1000 -> 0.521
A60: Employee Referral Fees | B60: =SUM(F60:Q60) -> 0.6 | C60: =SUM(R60:AC60) -> 3.2 | D60: =SUM(AD60:AJ60) -> 2.806 | F60: ='Raw - 2024 PL'!B44/1000 -> 0 | G60: ='Raw - 2024 PL'!C44/1000 -> 0 | H60: ='Raw - 2024 PL'!D44/1000 -> 0 | I60: ='Raw - 2024 PL'!E44/1000 -> 0 | J60: ='Raw - 2024 PL'!F44/1000 -> 0 | K60: ='Raw - 2024 PL'!G44/1000 -> 0 | L60: ='Raw - 2024 PL'!H44/1000 -> 0 | M60: ='Raw - 2024 PL'!I44/1000 -> 0 | ... Q60: ='Raw - 2024 PL'!M44/1000 -> 0.2 | R60: ='Raw - 2025 PL'!B57/1000 -> 0 | S60: ='Raw - 2025 PL'!C57/1000 -> 0.4 | T60: ='Raw - 2025 PL'!D57/1000 -> 0.2 | U60: ='Raw - 2025 PL'!E57/1000 -> 0 | V60: ='Raw - 2025 PL'!F57/1000 -> 0.6 | W60: ='Raw - 2025 PL'!G57/1000 -> 0.2 | X60: ='Raw - 2025 PL'!H57/1000 -> 0.2 | Y60: ='Raw - 2025 PL'!I57/1000 -> 0 | ... AC60: ='Raw - 2025 PL'!M57/1000 -> 0.4 | AD60: ='Raw - 2026 PL'!B56/1000 -> 0.4 | AE60: ='Raw - 2026 PL'!C56/1000 -> 0.4 | AF60: ='Raw - 2026 PL'!D56/1000 -> 1.006 | AG60: ='Raw - 2026 PL'!E56/1000 -> 0 | AH60: ='Raw - 2026 PL'!F56/1000 -> 0 | AI60: ='Raw - 2026 PL'!G56/1000 -> 0.8 | AJ60: ='Raw - 2026 PL'!H56/1000 -> 0.2
A61: Other Employee Benefits | B61: =SUM(F61:Q61) -> 0.26145 | C61: =SUM(R61:AC61) -> 1.89798 | D61: =SUM(AD61:AJ61) -> 2.6736 | F61: ='Raw - 2024 PL'!B45/1000 -> 0 | G61: ='Raw - 2024 PL'!C45/1000 -> 0 | H61: ='Raw - 2024 PL'!D45/1000 -> 0 | I61: ='Raw - 2024 PL'!E45/1000 -> 0 | J61: ='Raw - 2024 PL'!F45/1000 -> 0 | K61: ='Raw - 2024 PL'!G45/1000 -> 0.06145 | L61: ='Raw - 2024 PL'!H45/1000 -> 0.1 | M61: ='Raw - 2024 PL'!I45/1000 -> 0 | ... Q61: ='Raw - 2024 PL'!M45/1000 -> 0 | R61: ='Raw - 2025 PL'!B58/1000 -> 0 | S61: ='Raw - 2025 PL'!C58/1000 -> 0.03454 | T61: ='Raw - 2025 PL'!D58/1000 -> 0 | U61: ='Raw - 2025 PL'!E58/1000 -> 0.1 | V61: ='Raw - 2025 PL'!F58/1000 -> 0 | W61: ='Raw - 2025 PL'!G58/1000 -> 0.036 | X61: ='Raw - 2025 PL'!H58/1000 -> 0.2363 | Y61: ='Raw - 2025 PL'!I58/1000 -> 1.07114 | ... AC61: ='Raw - 2025 PL'!M58/1000 -> 0.08 | AD61: ='Raw - 2026 PL'!B57/1000 -> 0.08 | AE61: ='Raw - 2026 PL'!C57/1000 -> 0.18 | AF61: ='Raw - 2026 PL'!D57/1000 -> 1.005 | AG61: ='Raw - 2026 PL'!E57/1000 -> 0.18 | AH61: ='Raw - 2026 PL'!F57/1000 -> 0.14 | AI61: ='Raw - 2026 PL'!G57/1000 -> 0.1986 | AJ61: ='Raw - 2026 PL'!H57/1000 -> 0.89
A62: ST/LT Disability | B62: =SUM(F62:Q62) -> 2.49604 | C62: =SUM(R62:AC62) -> 2.77307 | D62: =SUM(AD62:AJ62) -> 1.26371 | F62: ='Raw - 2024 PL'!B46/1000 -> 0 | G62: ='Raw - 2024 PL'!C46/1000 -> 0.6277 | H62: ='Raw - 2024 PL'!D46/1000 -> 0 | I62: ='Raw - 2024 PL'!E46/1000 -> 0.3389 | J62: ='Raw - 2024 PL'!F46/1000 -> 0.3389 | K62: ='Raw - 2024 PL'!G46/1000 -> 0 | L62: ='Raw - 2024 PL'!H46/1000 -> 0.3389 | M62: ='Raw - 2024 PL'!I46/1000 -> 0 | ... Q62: ='Raw - 2024 PL'!M46/1000 -> 0.34329 | R62: ='Raw - 2025 PL'!B59/1000 -> 0.78724 | S62: ='Raw - 2025 PL'!C59/1000 -> 0.18053 | T62: ='Raw - 2025 PL'!D59/1000 -> 0.18053 | U62: ='Raw - 2025 PL'!E59/1000 -> 0.18053 | V62: ='Raw - 2025 PL'!F59/1000 -> 0.18053 | W62: ='Raw - 2025 PL'!G59/1000 -> 0.18053 | X62: ='Raw - 2025 PL'!H59/1000 -> 0.18053 | Y62: ='Raw - 2025 PL'!I59/1000 -> 0.18053 | ... AC62: ='Raw - 2025 PL'!M59/1000 -> 0.18053 | AD62: ='Raw - 2026 PL'!B58/1000 -> 0.18053 | AE62: ='Raw - 2026 PL'!C58/1000 -> 0.18053 | AF62: ='Raw - 2026 PL'!D58/1000 -> 0.18053 | AG62: ='Raw - 2026 PL'!E58/1000 -> 0.18053 | AH62: ='Raw - 2026 PL'!F58/1000 -> 0.18053 | AI62: ='Raw - 2026 PL'!G58/1000 -> 0.18053 | AJ62: ='Raw - 2026 PL'!H58/1000 -> 0.18053
A63: Total Employee Benefits | B63: =SUM(F63:Q63) -> 5.37405 | C63: =SUM(R63:AC63) -> 19.23245 | D63: =SUM(AD63:AJ63) -> 17.36251 | F63: =SUM(F55,F56,F57,F58,F59,F60,F61,F62) -> 0 | G63: =SUM(G55,G56,G57,G58,G59,G60,G61,G62) -> 0.6277 | H63: =SUM(H55,H56,H57,H58,H59,H60,H61,H62) -> 0 | I63: =SUM(I55,I56,I57,I58,I59,I60,I61,I62) -> 0.3389 | J63: =SUM(J55,J56,J57,J58,J59,J60,J61,J62) -> 0.3389 | K63: =SUM(K55,K56,K57,K58,K59,K60,K61,K62) -> 0.06145 | L63: =SUM(L55,L56,L57,L58,L59,L60,L61,L62) -> 0.8619 | M63: =SUM(M55,M56,M57,M58,M59,M60,M61,M62) -> 0.35956 | ... AJ63: =SUM(AJ55,AJ56,AJ57,AJ58,AJ59,AJ60,AJ61,AJ62) -> 2.68153
A64: Indirect Labor | B64: =SUM(F64:Q64) -> 101.3752 | C64: =SUM(R64:AC64) -> 281.24054 | D64: =SUM(AD64:AJ64) -> 357.27472 | F64: ='Raw - 2024 PL'!B48/1000 -> 3.09346 | G64: ='Raw - 2024 PL'!C48/1000 -> 4.63017 | H64: ='Raw - 2024 PL'!D48/1000 -> 4.39507 | I64: ='Raw - 2024 PL'!E48/1000 -> 5.86387 | J64: ='Raw - 2024 PL'!F48/1000 -> 7.37233 | K64: ='Raw - 2024 PL'!G48/1000 -> 4.9504 | L64: ='Raw - 2024 PL'!H48/1000 -> 4.9504 | M64: ='Raw - 2024 PL'!I48/1000 -> 4.70035 | ... Q64: ='Raw - 2024 PL'!M48/1000 -> 24.44012 | R64: ='Raw - 2025 PL'!B61/1000 -> 21.05234 | S64: ='Raw - 2025 PL'!C61/1000 -> 19.91603 | T64: ='Raw - 2025 PL'!D61/1000 -> 11.74387 | U64: ='Raw - 2025 PL'!E61/1000 -> 19.61792 | V64: ='Raw - 2025 PL'!F61/1000 -> 20.66978 | W64: ='Raw - 2025 PL'!G61/1000 -> 20.6939 | X64: ='Raw - 2025 PL'!H61/1000 -> 22.60264 | Y64: ='Raw - 2025 PL'!I61/1000 -> 19.96128 | ... AC64: ='Raw - 2025 PL'!M61/1000 -> 33.45969 | AD64: ='Raw - 2026 PL'!B60/1000 -> 36.2536 | AE64: ='Raw - 2026 PL'!C60/1000 -> 33.60751 | AF64: ='Raw - 2026 PL'!D60/1000 -> 57.19924 | AG64: ='Raw - 2026 PL'!E60/1000 -> 58.24595 | AH64: ='Raw - 2026 PL'!F60/1000 -> 54.06923 | AI64: ='Raw - 2026 PL'!G60/1000 -> 60.00381 | AJ64: ='Raw - 2026 PL'!H60/1000 -> 57.89538
A65: Insurance | B65: =SUM(F65:Q65) -> 2.08994 | C65: =SUM(R65:AC65) -> 2.61982 | D65: =SUM(AD65:AJ65) -> 3.70971 | F65: ='Raw - 2024 PL'!B49/1000 -> 0.14747 | G65: ='Raw - 2024 PL'!C49/1000 -> 0.14747 | H65: ='Raw - 2024 PL'!D49/1000 -> 0.17755 | I65: ='Raw - 2024 PL'!E49/1000 -> 0.19167 | J65: ='Raw - 2024 PL'!F49/1000 -> 0.18014 | K65: ='Raw - 2024 PL'!G49/1000 -> 0.17622 | L65: ='Raw - 2024 PL'!H49/1000 -> 0.1762 | M65: ='Raw - 2024 PL'!I49/1000 -> 0.17622 | ... Q65: ='Raw - 2024 PL'!M49/1000 -> 0.17622 | R65: ='Raw - 2025 PL'!B62/1000 -> 0.17678 | S65: ='Raw - 2025 PL'!C62/1000 -> 0.20899 | T65: ='Raw - 2025 PL'!D62/1000 -> 0.1896 | U65: ='Raw - 2025 PL'!E62/1000 -> 0.1759 | V65: ='Raw - 2025 PL'!F62/1000 -> 0.2357 | W65: ='Raw - 2025 PL'!G62/1000 -> 0.22676 | X65: ='Raw - 2025 PL'!H62/1000 -> 0.22676 | Y65: ='Raw - 2025 PL'!I62/1000 -> 0.22676 | ... AC65: ='Raw - 2025 PL'!M62/1000 -> 0.23352 | AD65: ='Raw - 2026 PL'!B61/1000 -> 0.22943 | AE65: ='Raw - 2026 PL'!C61/1000 -> 2.22858 | AF65: ='Raw - 2026 PL'!D61/1000 -> 0.25448 | AG65: ='Raw - 2026 PL'!E61/1000 -> 0.25564 | AH65: ='Raw - 2026 PL'!F61/1000 -> 0.26164 | AI65: ='Raw - 2026 PL'!G61/1000 -> 0.26183 | AJ65: ='Raw - 2026 PL'!H61/1000 -> 0.21811
A66: Legal & Professional Fees | B66: =SUM(F66:Q66) -> 0 | C66: =SUM(R66:AC66) -> 0 | D66: =SUM(AD66:AJ66) -> 0 | F66: ='Raw - 2024 PL'!B50/1000 -> 0 | G66: ='Raw - 2024 PL'!C50/1000 -> 0 | H66: ='Raw - 2024 PL'!D50/1000 -> 0 | I66: ='Raw - 2024 PL'!E50/1000 -> 0 | J66: ='Raw - 2024 PL'!F50/1000 -> 0 | K66: ='Raw - 2024 PL'!G50/1000 -> 0 | L66: ='Raw - 2024 PL'!H50/1000 -> 0 | M66: ='Raw - 2024 PL'!I50/1000 -> 0 | ... Q66: ='Raw - 2024 PL'!M50/1000 -> 0 | R66: ='Raw - 2025 PL'!B63/1000 -> 0 | S66: ='Raw - 2025 PL'!C63/1000 -> 0 | T66: ='Raw - 2025 PL'!D63/1000 -> 0 | U66: ='Raw - 2025 PL'!E63/1000 -> 0 | V66: ='Raw - 2025 PL'!F63/1000 -> 0 | W66: ='Raw - 2025 PL'!G63/1000 -> 0 | X66: ='Raw - 2025 PL'!H63/1000 -> 0 | Y66: ='Raw - 2025 PL'!I63/1000 -> 0 | ... AC66: ='Raw - 2025 PL'!M63/1000 -> 0 | AD66: ='Raw - 2026 PL'!B62/1000 -> 0 | AE66: ='Raw - 2026 PL'!C62/1000 -> 0 | AF66: ='Raw - 2026 PL'!D62/1000 -> 0 | AG66: ='Raw - 2026 PL'!E62/1000 -> 0 | AH66: ='Raw - 2026 PL'!F62/1000 -> 0 | AI66: ='Raw - 2026 PL'!G62/1000 -> 0 | AJ66: ='Raw - 2026 PL'!H62/1000 -> 0
A67: Accounting Fees | B67: =SUM(F67:Q67) -> 3.4925 | C67: =SUM(R67:AC67) -> 1.4 | D67: =SUM(AD67:AJ67) -> 0.95 | F67: ='Raw - 2024 PL'!B51/1000 -> 0 | G67: ='Raw - 2024 PL'!C51/1000 -> 0 | H67: ='Raw - 2024 PL'!D51/1000 -> 2.6 | I67: ='Raw - 2024 PL'!E51/1000 -> 0 | J67: ='Raw - 2024 PL'!F51/1000 -> 0 | K67: ='Raw - 2024 PL'!G51/1000 -> 0 | L67: ='Raw - 2024 PL'!H51/1000 -> 0 | M67: ='Raw - 2024 PL'!I51/1000 -> 0 | ... Q67: ='Raw - 2024 PL'!M51/1000 -> 0 | R67: ='Raw - 2025 PL'!B64/1000 -> 0 | S67: ='Raw - 2025 PL'!C64/1000 -> 0 | T67: ='Raw - 2025 PL'!D64/1000 -> 0 | U67: ='Raw - 2025 PL'!E64/1000 -> 1.4 | V67: ='Raw - 2025 PL'!F64/1000 -> 0 | W67: ='Raw - 2025 PL'!G64/1000 -> 0 | X67: ='Raw - 2025 PL'!H64/1000 -> 0 | Y67: ='Raw - 2025 PL'!I64/1000 -> 0 | ... AC67: ='Raw - 2025 PL'!M64/1000 -> 0 | AD67: ='Raw - 2026 PL'!B63/1000 -> 0 | AE67: ='Raw - 2026 PL'!C63/1000 -> 0 | AF67: ='Raw - 2026 PL'!D63/1000 -> 0.95 | AG67: ='Raw - 2026 PL'!E63/1000 -> 0 | AH67: ='Raw - 2026 PL'!F63/1000 -> 0 | AI67: ='Raw - 2026 PL'!G63/1000 -> 0 | AJ67: ='Raw - 2026 PL'!H63/1000 -> 0
A68: Other Professional Fees | B68: =SUM(F68:Q68) -> 18.23425 | C68: =SUM(R68:AC68) -> 27.04095 | D68: =SUM(AD68:AJ68) -> 57.55 | F68: ='Raw - 2024 PL'!B52/1000 -> 0 | G68: ='Raw - 2024 PL'!C52/1000 -> 1.1665 | H68: ='Raw - 2024 PL'!D52/1000 -> 1.1665 | I68: ='Raw - 2024 PL'!E52/1000 -> 1.16667 | J68: ='Raw - 2024 PL'!F52/1000 -> 1.16667 | K68: ='Raw - 2024 PL'!G52/1000 -> 2.66666 | L68: ='Raw - 2024 PL'!H52/1000 -> 1.16667 | M68: ='Raw - 2024 PL'!I52/1000 -> 1.16667 | ... Q68: ='Raw - 2024 PL'!M52/1000 -> 2.16666 | R68: ='Raw - 2025 PL'!B65/1000 -> 2.16667 | S68: ='Raw - 2025 PL'!C65/1000 -> 2.16667 | T68: ='Raw - 2025 PL'!D65/1000 -> 2.16666 | U68: ='Raw - 2025 PL'!E65/1000 -> 2.76067 | V68: ='Raw - 2025 PL'!F65/1000 -> 1.58667 | W68: ='Raw - 2025 PL'!G65/1000 -> 1.16666 | X68: ='Raw - 2025 PL'!H65/1000 -> 0 | Y68: ='Raw - 2025 PL'!I65/1000 -> 0.2 | ... AC68: ='Raw - 2025 PL'!M65/1000 -> 7.5 | AD68: ='Raw - 2026 PL'!B64/1000 -> 0 | AE68: ='Raw - 2026 PL'!C64/1000 -> 0 | AF68: ='Raw - 2026 PL'!D64/1000 -> 6.6 | AG68: ='Raw - 2026 PL'!E64/1000 -> 14 | AH68: ='Raw - 2026 PL'!F64/1000 -> 18 | AI68: ='Raw - 2026 PL'!G64/1000 -> 0 | AJ68: ='Raw - 2026 PL'!H64/1000 -> 18.95
A69: Recruiting Fees | B69: =SUM(F69:Q69) -> 14.90205 | C69: =SUM(R69:AC69) -> 31.6041 | D69: =SUM(AD69:AJ69) -> 5.5646 | F69: ='Raw - 2024 PL'!B53/1000 -> 0.02492 | G69: ='Raw - 2024 PL'!C53/1000 -> 1.02492 | H69: ='Raw - 2024 PL'!D53/1000 -> 1.02492 | I69: ='Raw - 2024 PL'!E53/1000 -> 1.22492 | J69: ='Raw - 2024 PL'!F53/1000 -> 1.02492 | K69: ='Raw - 2024 PL'!G53/1000 -> 1.51802 | L69: ='Raw - 2024 PL'!H53/1000 -> 2.01331 | M69: ='Raw - 2024 PL'!I53/1000 -> 1.6009 | ... Q69: ='Raw - 2024 PL'!M53/1000 -> 1.28772 | R69: ='Raw - 2025 PL'!B66/1000 -> 2.41295 | S69: ='Raw - 2025 PL'!C66/1000 -> 22.3793 | T69: ='Raw - 2025 PL'!D66/1000 -> 0.72983 | U69: ='Raw - 2025 PL'!E66/1000 -> 0.59597 | V69: ='Raw - 2025 PL'!F66/1000 -> 0.87534 | W69: ='Raw - 2025 PL'!G66/1000 -> 0.52967 | X69: ='Raw - 2025 PL'!H66/1000 -> 0.77688 | Y69: ='Raw - 2025 PL'!I66/1000 -> 0.21671 | ... AC69: ='Raw - 2025 PL'!M66/1000 -> 0.75176 | AD69: ='Raw - 2026 PL'!B65/1000 -> 0.8203 | AE69: ='Raw - 2026 PL'!C65/1000 -> 0.68046 | AF69: ='Raw - 2026 PL'!D65/1000 -> 0.77239 | AG69: ='Raw - 2026 PL'!E65/1000 -> 0.71608 | AH69: ='Raw - 2026 PL'!F65/1000 -> 0.6402 | AI69: ='Raw - 2026 PL'!G65/1000 -> 1.13538 | AJ69: ='Raw - 2026 PL'!H65/1000 -> 0.79979
A70: Total Legal & Professional Fees | B70: =SUM(F70:Q70) -> 36.6288 | C70: =SUM(R70:AC70) -> 60.04505 | D70: =SUM(AD70:AJ70) -> 64.0646 | F70: =SUM(F66,F67,F68,F69) -> 0.02492 | G70: =SUM(G66,G67,G68,G69) -> 2.19142 | H70: =SUM(H66,H67,H68,H69) -> 4.79142 | I70: =SUM(I66,I67,I68,I69) -> 2.39159 | J70: =SUM(J66,J67,J68,J69) -> 2.19159 | K70: =SUM(K66,K67,K68,K69) -> 4.18468 | L70: =SUM(L66,L67,L68,L69) -> 3.17998 | M70: =SUM(M66,M67,M68,M69) -> 2.76757 | ... AJ70: =SUM(AJ66,AJ67,AJ68,AJ69) -> 19.74979
A71: Office Supplies | B71: =SUM(F71:Q71) -> 3.10898 | C71: =SUM(R71:AC71) -> 1.3865 | D71: =SUM(AD71:AJ71) -> 0.71668 | F71: ='Raw - 2024 PL'!B55/1000 -> 0 | G71: ='Raw - 2024 PL'!C55/1000 -> 0 | H71: ='Raw - 2024 PL'!D55/1000 -> 0 | I71: ='Raw - 2024 PL'!E55/1000 -> 2.15898 | J71: ='Raw - 2024 PL'!F55/1000 -> 0 | K71: ='Raw - 2024 PL'!G55/1000 -> 0 | L71: ='Raw - 2024 PL'!H55/1000 -> 0 | M71: ='Raw - 2024 PL'!I55/1000 -> 0 | ... Q71: ='Raw - 2024 PL'!M55/1000 -> 0.95 | R71: ='Raw - 2025 PL'!B68/1000 -> 0.02997 | S71: ='Raw - 2025 PL'!C68/1000 -> 0 | T71: ='Raw - 2025 PL'!D68/1000 -> 0.38209 | U71: ='Raw - 2025 PL'!E68/1000 -> 0 | V71: ='Raw - 2025 PL'!F68/1000 -> 0.56156 | W71: ='Raw - 2025 PL'!G68/1000 -> 0 | X71: ='Raw - 2025 PL'!H68/1000 -> 0 | Y71: ='Raw - 2025 PL'!I68/1000 -> 0.34999 | ... AC71: ='Raw - 2025 PL'!M68/1000 -> 0.06289 | AD71: ='Raw - 2026 PL'!B67/1000 -> 0.04003 | AE71: ='Raw - 2026 PL'!C67/1000 -> 0.0214 | AF71: ='Raw - 2026 PL'!D67/1000 -> 0 | AG71: ='Raw - 2026 PL'!E67/1000 -> 0.05735 | AH71: ='Raw - 2026 PL'!F67/1000 -> 0.47175 | AI71: ='Raw - 2026 PL'!G67/1000 -> -0.015 | AJ71: ='Raw - 2026 PL'!H67/1000 -> 0.14115
A72: Other Business Expenses | B72: =SUM(F72:Q72) -> 0.06499 | C72: =SUM(R72:AC72) -> 0 | D72: =SUM(AD72:AJ72) -> 0 | F72: ='Raw - 2024 PL'!B56/1000 -> 0 | G72: ='Raw - 2024 PL'!C56/1000 -> 0 | H72: ='Raw - 2024 PL'!D56/1000 -> 0 | I72: ='Raw - 2024 PL'!E56/1000 -> 0 | J72: ='Raw - 2024 PL'!F56/1000 -> 0.06499 | K72: ='Raw - 2024 PL'!G56/1000 -> 0 | L72: ='Raw - 2024 PL'!H56/1000 -> 0 | M72: ='Raw - 2024 PL'!I56/1000 -> 0 | ... Q72: ='Raw - 2024 PL'!M56/1000 -> 0
A73: Penalties | B73: =SUM(F73:Q73) -> 1.75 | C73: =SUM(R73:AC73) -> 0 | D73: =SUM(AD73:AJ73) -> 0 | F73: ='Raw - 2024 PL'!B57/1000 -> 0 | G73: ='Raw - 2024 PL'!C57/1000 -> 0 | H73: ='Raw - 2024 PL'!D57/1000 -> 0 | I73: ='Raw - 2024 PL'!E57/1000 -> 1.75 | J73: ='Raw - 2024 PL'!F57/1000 -> 0 | K73: ='Raw - 2024 PL'!G57/1000 -> 0 | L73: ='Raw - 2024 PL'!H57/1000 -> 0 | M73: ='Raw - 2024 PL'!I57/1000 -> 0 | ... Q73: ='Raw - 2024 PL'!M57/1000 -> 0
A74: Postage | B74: =SUM(F74:Q74) -> 0.48076 | C74: =SUM(R74:AC74) -> 0.40107 | D74: =SUM(AD74:AJ74) -> 0.39127 | F74: ='Raw - 2024 PL'!B58/1000 -> 0.05283 | G74: ='Raw - 2024 PL'!C58/1000 -> 0.34499 | H74: ='Raw - 2024 PL'!D58/1000 -> 0.03075 | I74: ='Raw - 2024 PL'!E58/1000 -> 0 | J74: ='Raw - 2024 PL'!F58/1000 -> 0 | K74: ='Raw - 2024 PL'!G58/1000 -> 0.0112 | L74: ='Raw - 2024 PL'!H58/1000 -> 0 | M74: ='Raw - 2024 PL'!I58/1000 -> 0 | ... Q74: ='Raw - 2024 PL'!M58/1000 -> 0.00991 | R74: ='Raw - 2025 PL'!B69/1000 -> 0.0299 | S74: ='Raw - 2025 PL'!C69/1000 -> 0.33999 | T74: ='Raw - 2025 PL'!D69/1000 -> 0 | U74: ='Raw - 2025 PL'!E69/1000 -> 0.01083 | V74: ='Raw - 2025 PL'!F69/1000 -> 0.005 | W74: ='Raw - 2025 PL'!G69/1000 -> -0.00955 | X74: ='Raw - 2025 PL'!H69/1000 -> 0 | Y74: ='Raw - 2025 PL'!I69/1000 -> 0 | ... AC74: ='Raw - 2025 PL'!M69/1000 -> 0 | AD74: ='Raw - 2026 PL'!B68/1000 -> 0.0075 | AE74: ='Raw - 2026 PL'!C68/1000 -> 0.12741 | AF74: ='Raw - 2026 PL'!D68/1000 -> 0.01225 | AG74: ='Raw - 2026 PL'!E68/1000 -> 0.02225 | AH74: ='Raw - 2026 PL'!F68/1000 -> 0 | AI74: ='Raw - 2026 PL'!G68/1000 -> 0.21045 | AJ74: ='Raw - 2026 PL'!H68/1000 -> 0.01141
A75: Professional Organizations | B75: =SUM(F75:Q75) -> 5.44332 | C75: =SUM(R75:AC75) -> 11.22296 | D75: =SUM(AD75:AJ75) -> 6.57881 | F75: ='Raw - 2024 PL'!B59/1000 -> 0.33417 | G75: ='Raw - 2024 PL'!C59/1000 -> 0.33417 | H75: ='Raw - 2024 PL'!D59/1000 -> 0.33417 | I75: ='Raw - 2024 PL'!E59/1000 -> 0.33417 | J75: ='Raw - 2024 PL'!F59/1000 -> 0.255 | K75: ='Raw - 2024 PL'!G59/1000 -> 0.255 | L75: ='Raw - 2024 PL'!H59/1000 -> 0.25496 | M75: ='Raw - 2024 PL'!I59/1000 -> 0.205 | ... Q75: ='Raw - 2024 PL'!M59/1000 -> 0.78417 | R75: ='Raw - 2025 PL'!B70/1000 -> 0.78417 | S75: ='Raw - 2025 PL'!C70/1000 -> 0.78417 | T75: ='Raw - 2025 PL'!D70/1000 -> 0.78417 | U75: ='Raw - 2025 PL'!E70/1000 -> 0.78417 | V75: ='Raw - 2025 PL'!F70/1000 -> 0.78417 | W75: ='Raw - 2025 PL'!G70/1000 -> 0.78417 | X75: ='Raw - 2025 PL'!H70/1000 -> 1.48598 | Y75: ='Raw - 2025 PL'!I70/1000 -> 0.9633 | ... AC75: ='Raw - 2025 PL'!M70/1000 -> 1.0294 | AD75: ='Raw - 2026 PL'!B69/1000 -> 0.93983 | AE75: ='Raw - 2026 PL'!C69/1000 -> 0.93983 | AF75: ='Raw - 2026 PL'!D69/1000 -> 0.93983 | AG75: ='Raw - 2026 PL'!E69/1000 -> 0.93983 | AH75: ='Raw - 2026 PL'!F69/1000 -> 0.93983 | AI75: ='Raw - 2026 PL'!G69/1000 -> 0.93983 | AJ75: ='Raw - 2026 PL'!H69/1000 -> 0.93983
A76: Software & Apps - AI tools | B76: =SUM(F76:Q76) -> 0 | C76: =SUM(R76:AC76) -> 0 | D76: =SUM(AD76:AJ76) -> 6.52752 | AD76: ='Raw - 2026 PL'!B70/1000 -> 0.12 | AE76: ='Raw - 2026 PL'!C70/1000 -> 0.12 | AF76: ='Raw - 2026 PL'!D70/1000 -> 0.70166 | AG76: ='Raw - 2026 PL'!E70/1000 -> 2.20736 | AH76: ='Raw - 2026 PL'!F70/1000 -> 0.91487 | AI76: ='Raw - 2026 PL'!G70/1000 -> 1.15165 | AJ76: ='Raw - 2026 PL'!H70/1000 -> 1.31198
A77: Software & Apps - G&A | B77: =SUM(F77:Q77) -> 60.91594 | C77: =SUM(R77:AC77) -> 117.05866 | D77: =SUM(AD77:AJ77) -> 97.04798 | F77: ='Raw - 2024 PL'!B60/1000 -> 3.45285 | G77: ='Raw - 2024 PL'!C60/1000 -> 3.61753 | H77: ='Raw - 2024 PL'!D60/1000 -> 3.97407 | I77: ='Raw - 2024 PL'!E60/1000 -> 4.22365 | J77: ='Raw - 2024 PL'!F60/1000 -> 5.09725 | K77: ='Raw - 2024 PL'!G60/1000 -> 5.33351 | L77: ='Raw - 2024 PL'!H60/1000 -> 5.51369 | M77: ='Raw - 2024 PL'!I60/1000 -> 5.23169 | ... Q77: ='Raw - 2024 PL'!M60/1000 -> 6.67654 | R77: ='Raw - 2025 PL'!B71/1000 -> 7.74646 | S77: ='Raw - 2025 PL'!C71/1000 -> 7.89181 | T77: ='Raw - 2025 PL'!D71/1000 -> 7.89085 | U77: ='Raw - 2025 PL'!E71/1000 -> 7.83463 | V77: ='Raw - 2025 PL'!F71/1000 -> 8.11723 | W77: ='Raw - 2025 PL'!G71/1000 -> 8.34584 | X77: ='Raw - 2025 PL'!H71/1000 -> 8.98468 | Y77: ='Raw - 2025 PL'!I71/1000 -> 9.8566 | ... AC77: ='Raw - 2025 PL'!M71/1000 -> 14.42143 | AD77: ='Raw - 2026 PL'!B71/1000 -> 13.26316 | AE77: ='Raw - 2026 PL'!C71/1000 -> 14.7201 | AF77: ='Raw - 2026 PL'!D71/1000 -> 14.99072 | AG77: ='Raw - 2026 PL'!E71/1000 -> 14.74459 | AH77: ='Raw - 2026 PL'!F71/1000 -> 13.2292 | AI77: ='Raw - 2026 PL'!G71/1000 -> 13.11499 | AJ77: ='Raw - 2026 PL'!H71/1000 -> 12.98522
A78: State Filing Fees | B78: =SUM(F78:Q78) -> 0.102 | C78: =SUM(R78:AC78) -> 0.5 | D78: =SUM(AD78:AJ78) -> 0.523 | F78: ='Raw - 2024 PL'!B61/1000 -> 0 | G78: ='Raw - 2024 PL'!C61/1000 -> 0 | H78: ='Raw - 2024 PL'!D61/1000 -> 0.102 | I78: ='Raw - 2024 PL'!E61/1000 -> 0 | J78: ='Raw - 2024 PL'!F61/1000 -> 0 | K78: ='Raw - 2024 PL'!G61/1000 -> 0 | L78: ='Raw - 2024 PL'!H61/1000 -> 0 | M78: ='Raw - 2024 PL'!I61/1000 -> 0 | ... Q78: ='Raw - 2024 PL'!M61/1000 -> 0 | R78: ='Raw - 2025 PL'!B72/1000 -> 0.102 | S78: ='Raw - 2025 PL'!C72/1000 -> 0 | T78: ='Raw - 2025 PL'!D72/1000 -> 0 | U78: ='Raw - 2025 PL'!E72/1000 -> 0.398 | V78: ='Raw - 2025 PL'!F72/1000 -> 0 | W78: ='Raw - 2025 PL'!G72/1000 -> 0 | X78: ='Raw - 2025 PL'!H72/1000 -> 0 | Y78: ='Raw - 2025 PL'!I72/1000 -> 0 | ... AC78: ='Raw - 2025 PL'!M72/1000 -> 0 | AD78: ='Raw - 2026 PL'!B72/1000 -> 0 | AE78: ='Raw - 2026 PL'!C72/1000 -> 0.102 | AF78: ='Raw - 2026 PL'!D72/1000 -> 0.401 | AG78: ='Raw - 2026 PL'!E72/1000 -> 0.005 | AH78: ='Raw - 2026 PL'!F72/1000 -> 0.005 | AI78: ='Raw - 2026 PL'!G72/1000 -> 0.005 | AJ78: ='Raw - 2026 PL'!H72/1000 -> 0.005
A79: Utilities | B79: =SUM(F79:Q79) -> 1.05983 | C79: =SUM(R79:AC79) -> 3.29133 | D79: =SUM(AD79:AJ79) -> 1.943 | F79: ='Raw - 2024 PL'!B62/1000 -> 0.085 | G79: ='Raw - 2024 PL'!C62/1000 -> 0.085 | H79: ='Raw - 2024 PL'!D62/1000 -> 0.097 | I79: ='Raw - 2024 PL'!E62/1000 -> 0.11283 | J79: ='Raw - 2024 PL'!F62/1000 -> 0.085 | K79: ='Raw - 2024 PL'!G62/1000 -> 0.085 | L79: ='Raw - 2024 PL'!H62/1000 -> 0.085 | M79: ='Raw - 2024 PL'!I62/1000 -> 0.085 | ... Q79: ='Raw - 2024 PL'!M62/1000 -> 0.085 | R79: ='Raw - 2025 PL'!B73/1000 -> 0.085 | S79: ='Raw - 2025 PL'!C73/1000 -> 0.09449 | T79: ='Raw - 2025 PL'!D73/1000 -> 0.82489 | U79: ='Raw - 2025 PL'!E73/1000 -> 0.253 | V79: ='Raw - 2025 PL'!F73/1000 -> 0.26295 | W79: ='Raw - 2025 PL'!G73/1000 -> 0.253 | X79: ='Raw - 2025 PL'!H73/1000 -> 0.253 | Y79: ='Raw - 2025 PL'!I73/1000 -> 0.253 | ... AC79: ='Raw - 2025 PL'!M73/1000 -> 0.253 | AD79: ='Raw - 2026 PL'!B73/1000 -> 0.253 | AE79: ='Raw - 2026 PL'!C73/1000 -> 0.255 | AF79: ='Raw - 2026 PL'!D73/1000 -> 0.283 | AG79: ='Raw - 2026 PL'!E73/1000 -> 0.283 | AH79: ='Raw - 2026 PL'!F73/1000 -> 0.283 | AI79: ='Raw - 2026 PL'!G73/1000 -> 0.293 | AJ79: ='Raw - 2026 PL'!H73/1000 -> 0.293
A80: Total General & Admin Expenses | B80: =SUM(F80:Q80) -> 218.5417 | C80: =SUM(R80:AC80) -> 501.46443 | D80: =SUM(AD80:AJ80) -> 559.26841 | F80: =SUM(F51,F52,F53,F54,F63,F64,F65,F70,F71,F72,F73,F74,F75,F76,F77,F78,F79) -> 7.1917 | G80: =SUM(G51,G52,G53,G54,G63,G64,G65,G70,G71,G72,G73,G74,G75,G76,G77,G78,G79) -> 11.97945 | H80: =SUM(H51,H52,H53,H54,H63,H64,H65,H70,H71,H72,H73,H74,H75,H76,H77,H78,H79) -> 13.90303 | I80: =SUM(I51,I52,I53,I54,I63,I64,I65,I70,I71,I72,I73,I74,I75,I76,I77,I78,I79) -> 17.46166 | J80: =SUM(J51,J52,J53,J54,J63,J64,J65,J70,J71,J72,J73,J74,J75,J76,J77,J78,J79) -> 15.5872 | K80: =SUM(K51,K52,K53,K54,K63,K64,K65,K70,K71,K72,K73,K74,K75,K76,K77,K78,K79) -> 15.05846 | L80: =SUM(L51,L52,L53,L54,L63,L64,L65,L70,L71,L72,L73,L74,L75,L76,L77,L78,L79) -> 15.02776 | M80: =SUM(M51,M52,M53,M54,M63,M64,M65,M70,M71,M72,M73,M74,M75,M76,M77,M78,M79) -> 13.52639 | ... AJ80: =SUM(AJ51,AJ52,AJ53,AJ54,AJ63,AJ64,AJ65,AJ70,AJ71,AJ72,AJ73,AJ74,AJ75,AJ76,AJ77,AJ78,AJ79) -> 96.53555
A81: Payroll Wages - Owner | B81: =SUM(F81:Q81) -> 0 | C81: =SUM(R81:AC81) -> 90.66704 | D81: =SUM(AD81:AJ81) -> 63.14302 | R81: ='Raw - 2025 PL'!B75/1000 -> 0 | S81: ='Raw - 2025 PL'!C75/1000 -> 0 | T81: ='Raw - 2025 PL'!D75/1000 -> 8.90639 | U81: ='Raw - 2025 PL'!E75/1000 -> 9.23323 | V81: ='Raw - 2025 PL'!F75/1000 -> 9.10884 | W81: ='Raw - 2025 PL'!G75/1000 -> 8.69479 | X81: ='Raw - 2025 PL'!H75/1000 -> 9.52287 | Y81: ='Raw - 2025 PL'!I75/1000 -> 8.69481 | ... AC81: ='Raw - 2025 PL'!M75/1000 -> 9.59364 | AD81: ='Raw - 2026 PL'!B75/1000 -> 9.27621 | AE81: ='Raw - 2026 PL'!C75/1000 -> 8.32263 | AF81: ='Raw - 2026 PL'!D75/1000 -> 9.10883 | AG81: ='Raw - 2026 PL'!E75/1000 -> 9.10883 | AH81: ='Raw - 2026 PL'!F75/1000 -> 8.69481 | AI81: ='Raw - 2026 PL'!G75/1000 -> 9.10884 | AJ81: ='Raw - 2026 PL'!H75/1000 -> 9.52287
A82: Sales & Marketing | B82: =SUM(F82:Q82) -> 0 | C82: =SUM(R82:AC82) -> 0 | D82: =SUM(AD82:AJ82) -> 0 | F82: ='Raw - 2024 PL'!B64/1000 -> 0 | G82: ='Raw - 2024 PL'!C64/1000 -> 0 | H82: ='Raw - 2024 PL'!D64/1000 -> 0 | I82: ='Raw - 2024 PL'!E64/1000 -> 0 | J82: ='Raw - 2024 PL'!F64/1000 -> 0 | K82: ='Raw - 2024 PL'!G64/1000 -> 0 | L82: ='Raw - 2024 PL'!H64/1000 -> 0 | M82: ='Raw - 2024 PL'!I64/1000 -> 0 | ... Q82: ='Raw - 2024 PL'!M64/1000 -> 0 | R82: ='Raw - 2025 PL'!B76/1000 -> 0 | S82: ='Raw - 2025 PL'!C76/1000 -> 0 | T82: ='Raw - 2025 PL'!D76/1000 -> 0 | U82: ='Raw - 2025 PL'!E76/1000 -> 0 | V82: ='Raw - 2025 PL'!F76/1000 -> 0 | W82: ='Raw - 2025 PL'!G76/1000 -> 0 | X82: ='Raw - 2025 PL'!H76/1000 -> 0 | Y82: ='Raw - 2025 PL'!I76/1000 -> 0 | ... AC82: ='Raw - 2025 PL'!M76/1000 -> 0 | AD82: ='Raw - 2026 PL'!B76/1000 -> 0 | AE82: ='Raw - 2026 PL'!C76/1000 -> 0 | AF82: ='Raw - 2026 PL'!D76/1000 -> 0 | AG82: ='Raw - 2026 PL'!E76/1000 -> 0 | AH82: ='Raw - 2026 PL'!F76/1000 -> 0 | AI82: ='Raw - 2026 PL'!G76/1000 -> 0 | AJ82: ='Raw - 2026 PL'!H76/1000 -> 0
A83: Conferences & Meetups | B83: =SUM(F83:Q83) -> 0.31046 | C83: =SUM(R83:AC83) -> 0 | D83: =SUM(AD83:AJ83) -> 0 | F83: ='Raw - 2024 PL'!B65/1000 -> 0 | G83: ='Raw - 2024 PL'!C65/1000 -> 0 | H83: ='Raw - 2024 PL'!D65/1000 -> 0.25 | I83: ='Raw - 2024 PL'!E65/1000 -> 0.06046 | J83: ='Raw - 2024 PL'!F65/1000 -> 0 | K83: ='Raw - 2024 PL'!G65/1000 -> 0 | L83: ='Raw - 2024 PL'!H65/1000 -> 0 | M83: ='Raw - 2024 PL'!I65/1000 -> 0 | ... Q83: ='Raw - 2024 PL'!M65/1000 -> 0 | R83: ='Raw - 2025 PL'!B77/1000 -> 0 | S83: ='Raw - 2025 PL'!C77/1000 -> 0 | T83: ='Raw - 2025 PL'!D77/1000 -> 0 | U83: ='Raw - 2025 PL'!E77/1000 -> 0 | V83: ='Raw - 2025 PL'!F77/1000 -> 0 | W83: ='Raw - 2025 PL'!G77/1000 -> 0 | X83: ='Raw - 2025 PL'!H77/1000 -> 0 | Y83: ='Raw - 2025 PL'!I77/1000 -> 0 | ... AC83: ='Raw - 2025 PL'!M77/1000 -> 0 | AD83: ='Raw - 2026 PL'!B77/1000 -> 0 | AE83: ='Raw - 2026 PL'!C77/1000 -> 0 | AF83: ='Raw - 2026 PL'!D77/1000 -> 0 | AG83: ='Raw - 2026 PL'!E77/1000 -> 0 | AH83: ='Raw - 2026 PL'!F77/1000 -> 0 | AI83: ='Raw - 2026 PL'!G77/1000 -> 0 | AJ83: ='Raw - 2026 PL'!H77/1000 -> 0
A84: C&M - Ticket/Sponsorship | B84: =SUM(F84:Q84) -> 0 | C84: =SUM(R84:AC84) -> 8.8288 | D84: =SUM(AD84:AJ84) -> 11.695 | R84: ='Raw - 2025 PL'!B78/1000 -> 0 | S84: ='Raw - 2025 PL'!C78/1000 -> 0 | T84: ='Raw - 2025 PL'!D78/1000 -> 0 | U84: ='Raw - 2025 PL'!E78/1000 -> 0 | V84: ='Raw - 2025 PL'!F78/1000 -> 0 | W84: ='Raw - 2025 PL'!G78/1000 -> 0 | X84: ='Raw - 2025 PL'!H78/1000 -> 0 | Y84: ='Raw - 2025 PL'!I78/1000 -> 6.4 | ... AC84: ='Raw - 2025 PL'!M78/1000 -> 0 | AD84: ='Raw - 2026 PL'!B78/1000 -> 0 | AE84: ='Raw - 2026 PL'!C78/1000 -> 0 | AF84: ='Raw - 2026 PL'!D78/1000 -> 0 | AG84: ='Raw - 2026 PL'!E78/1000 -> 0 | AH84: ='Raw - 2026 PL'!F78/1000 -> 0 | AI84: ='Raw - 2026 PL'!G78/1000 -> 0 | AJ84: ='Raw - 2026 PL'!H78/1000 -> 11.695
A85: C&M - Event Cost/Supplies | B85: =SUM(F85:Q85) -> 0 | C85: =SUM(R85:AC85) -> 2.6695 | D85: =SUM(AD85:AJ85) -> 0.15048 | R85: ='Raw - 2025 PL'!B79/1000 -> 0 | S85: ='Raw - 2025 PL'!C79/1000 -> 0 | T85: ='Raw - 2025 PL'!D79/1000 -> 0 | U85: ='Raw - 2025 PL'!E79/1000 -> 0 | V85: ='Raw - 2025 PL'!F79/1000 -> 0 | W85: ='Raw - 2025 PL'!G79/1000 -> 0 | X85: ='Raw - 2025 PL'!H79/1000 -> 0 | Y85: ='Raw - 2025 PL'!I79/1000 -> 0.77 | ... AC85: ='Raw - 2025 PL'!M79/1000 -> 0 | AD85: ='Raw - 2026 PL'!B79/1000 -> 0.05 | AE85: ='Raw - 2026 PL'!C79/1000 -> 0 | AF85: ='Raw - 2026 PL'!D79/1000 -> 0 | AG85: ='Raw - 2026 PL'!E79/1000 -> 0 | AH85: ='Raw - 2026 PL'!F79/1000 -> 0.09805 | AI85: ='Raw - 2026 PL'!G79/1000 -> 0.00243 | AJ85: ='Raw - 2026 PL'!H79/1000 -> 0
A86: Total Conferences & Meetups | B86: =SUM(F86:Q86) -> 0.31046 | C86: =SUM(R86:AC86) -> 11.4983 | D86: =SUM(AD86:AJ86) -> 11.84548 | F86: =SUM(F83,F84,F85) -> 0 | G86: =SUM(G83,G84,G85) -> 0 | H86: =SUM(H83,H84,H85) -> 0.25 | I86: =SUM(I83,I84,I85) -> 0.06046 | J86: =SUM(J83,J84,J85) -> 0 | K86: =SUM(K83,K84,K85) -> 0 | L86: =SUM(L83,L84,L85) -> 0 | M86: =SUM(M83,M84,M85) -> 0 | ... AJ86: =SUM(AJ83,AJ84,AJ85) -> 11.695
A87: Other Advertising | B87: =SUM(F87:Q87) -> 0.1 | C87: =SUM(R87:AC87) -> 0.1 | D87: =SUM(AD87:AJ87) -> 0 | F87: ='Raw - 2024 PL'!B66/1000 -> 0 | G87: ='Raw - 2024 PL'!C66/1000 -> 0 | H87: ='Raw - 2024 PL'!D66/1000 -> 0 | I87: ='Raw - 2024 PL'!E66/1000 -> 0 | J87: ='Raw - 2024 PL'!F66/1000 -> 0 | K87: ='Raw - 2024 PL'!G66/1000 -> 0 | L87: ='Raw - 2024 PL'!H66/1000 -> 0 | M87: ='Raw - 2024 PL'!I66/1000 -> 0 | ... Q87: ='Raw - 2024 PL'!M66/1000 -> 0 | R87: ='Raw - 2025 PL'!B81/1000 -> 0 | S87: ='Raw - 2025 PL'!C81/1000 -> 0 | T87: ='Raw - 2025 PL'!D81/1000 -> 0 | U87: ='Raw - 2025 PL'!E81/1000 -> 0 | V87: ='Raw - 2025 PL'!F81/1000 -> 0 | W87: ='Raw - 2025 PL'!G81/1000 -> 0 | X87: ='Raw - 2025 PL'!H81/1000 -> 0.1 | Y87: ='Raw - 2025 PL'!I81/1000 -> 0 | ... AC87: ='Raw - 2025 PL'!M81/1000 -> 0
A88: Sales and Marketing Wages | B88: =SUM(F88:Q88) -> 0 | C88: =SUM(R88:AC88) -> 19.14963 | D88: =SUM(AD88:AJ88) -> 51.94131 | R88: ='Raw - 2025 PL'!B82/1000 -> 0 | S88: ='Raw - 2025 PL'!C82/1000 -> 0 | T88: ='Raw - 2025 PL'!D82/1000 -> 0 | U88: ='Raw - 2025 PL'!E82/1000 -> 0 | V88: ='Raw - 2025 PL'!F82/1000 -> 0 | W88: ='Raw - 2025 PL'!G82/1000 -> 1.4668 | X88: ='Raw - 2025 PL'!H82/1000 -> 1.63265 | Y88: ='Raw - 2025 PL'!I82/1000 -> 1.71805 | ... AC88: ='Raw - 2025 PL'!M82/1000 -> 7.81939 | AD88: ='Raw - 2026 PL'!B81/1000 -> 5.6534 | AE88: ='Raw - 2026 PL'!C81/1000 -> 5.95689 | AF88: ='Raw - 2026 PL'!D81/1000 -> 7.7828 | AG88: ='Raw - 2026 PL'!E81/1000 -> 8.13701 | AH88: ='Raw - 2026 PL'!F81/1000 -> 7.80825 | AI88: ='Raw - 2026 PL'!G81/1000 -> 8.4072 | AJ88: ='Raw - 2026 PL'!H81/1000 -> 8.19576
A89: Social Media | B89: =SUM(F89:Q89) -> 5.144 | C89: =SUM(R89:AC89) -> 0.144 | D89: =SUM(AD89:AJ89) -> 0.144 | F89: ='Raw - 2024 PL'!B67/1000 -> 1.144 | G89: ='Raw - 2024 PL'!C67/1000 -> 1 | H89: ='Raw - 2024 PL'!D67/1000 -> 1 | I89: ='Raw - 2024 PL'!E67/1000 -> 0 | J89: ='Raw - 2024 PL'!F67/1000 -> 1 | K89: ='Raw - 2024 PL'!G67/1000 -> 1 | L89: ='Raw - 2024 PL'!H67/1000 -> 0 | M89: ='Raw - 2024 PL'!I67/1000 -> 0 | ... Q89: ='Raw - 2024 PL'!M67/1000 -> 0 | R89: ='Raw - 2025 PL'!B83/1000 -> 0.144 | S89: ='Raw - 2025 PL'!C83/1000 -> 0 | T89: ='Raw - 2025 PL'!D83/1000 -> 0 | U89: ='Raw - 2025 PL'!E83/1000 -> 0 | V89: ='Raw - 2025 PL'!F83/1000 -> 0 | W89: ='Raw - 2025 PL'!G83/1000 -> 0 | X89: ='Raw - 2025 PL'!H83/1000 -> 0 | Y89: ='Raw - 2025 PL'!I83/1000 -> 0 | ... AC89: ='Raw - 2025 PL'!M83/1000 -> 0 | AD89: ='Raw - 2026 PL'!B82/1000 -> 0.144 | AE89: ='Raw - 2026 PL'!C82/1000 -> 0 | AF89: ='Raw - 2026 PL'!D82/1000 -> 0 | AG89: ='Raw - 2026 PL'!E82/1000 -> 0 | AH89: ='Raw - 2026 PL'!F82/1000 -> 0 | AI89: ='Raw - 2026 PL'!G82/1000 -> 0 | AJ89: ='Raw - 2026 PL'!H82/1000 -> 0
A90: Software & Apps | B90: =SUM(F90:Q90) -> 1.198 | C90: =SUM(R90:AC90) -> 3.23943 | D90: =SUM(AD90:AJ90) -> 2.13 | F90: ='Raw - 2024 PL'!B68/1000 -> 0 | G90: ='Raw - 2024 PL'!C68/1000 -> 0 | H90: ='Raw - 2024 PL'!D68/1000 -> 0 | I90: ='Raw - 2024 PL'!E68/1000 -> 0 | J90: ='Raw - 2024 PL'!F68/1000 -> 0 | K90: ='Raw - 2024 PL'!G68/1000 -> 0 | L90: ='Raw - 2024 PL'!H68/1000 -> 0 | M90: ='Raw - 2024 PL'!I68/1000 -> 0.17 | ... Q90: ='Raw - 2024 PL'!M68/1000 -> 0.17 | R90: ='Raw - 2025 PL'!B84/1000 -> 0.17 | S90: ='Raw - 2025 PL'!C84/1000 -> 0.17 | T90: ='Raw - 2025 PL'!D84/1000 -> 0.31643 | U90: ='Raw - 2025 PL'!E84/1000 -> 0.27 | V90: ='Raw - 2025 PL'!F84/1000 -> 0.27 | W90: ='Raw - 2025 PL'!G84/1000 -> 0.27 | X90: ='Raw - 2025 PL'!H84/1000 -> 0.27 | Y90: ='Raw - 2025 PL'!I84/1000 -> 0.22 | ... AC90: ='Raw - 2025 PL'!M84/1000 -> 0.275 | AD90: ='Raw - 2026 PL'!B83/1000 -> 0.27 | AE90: ='Raw - 2026 PL'!C83/1000 -> 0.27 | AF90: ='Raw - 2026 PL'!D83/1000 -> 0.27 | AG90: ='Raw - 2026 PL'!E83/1000 -> 0.27 | AH90: ='Raw - 2026 PL'!F83/1000 -> 0.27 | AI90: ='Raw - 2026 PL'!G83/1000 -> 0.27 | AJ90: ='Raw - 2026 PL'!H83/1000 -> 0.51
A91: Travel, Meals & Entertainment | B91: =SUM(F91:Q91) -> 0 | C91: =SUM(R91:AC91) -> 0 | D91: =SUM(AD91:AJ91) -> 0 | R91: ='Raw - 2025 PL'!B85/1000 -> 0 | S91: ='Raw - 2025 PL'!C85/1000 -> 0 | T91: ='Raw - 2025 PL'!D85/1000 -> 0 | U91: ='Raw - 2025 PL'!E85/1000 -> 0 | V91: ='Raw - 2025 PL'!F85/1000 -> 0 | W91: ='Raw - 2025 PL'!G85/1000 -> 0 | X91: ='Raw - 2025 PL'!H85/1000 -> 0 | Y91: ='Raw - 2025 PL'!I85/1000 -> 0 | ... AC91: ='Raw - 2025 PL'!M85/1000 -> 0 | AD91: ='Raw - 2026 PL'!B84/1000 -> 0 | AE91: ='Raw - 2026 PL'!C84/1000 -> 0 | AF91: ='Raw - 2026 PL'!D84/1000 -> 0 | AG91: ='Raw - 2026 PL'!E84/1000 -> 0 | AH91: ='Raw - 2026 PL'!F84/1000 -> 0 | AI91: ='Raw - 2026 PL'!G84/1000 -> 0 | AJ91: ='Raw - 2026 PL'!H84/1000 -> 0
A92: Accommodation | B92: =SUM(F92:Q92) -> 0 | C92: =SUM(R92:AC92) -> 10.46727 | D92: =SUM(AD92:AJ92) -> 7.37219 | R92: ='Raw - 2025 PL'!B86/1000 -> 0 | S92: ='Raw - 2025 PL'!C86/1000 -> 0 | T92: ='Raw - 2025 PL'!D86/1000 -> 0 | U92: ='Raw - 2025 PL'!E86/1000 -> 3.76065 | V92: ='Raw - 2025 PL'!F86/1000 -> 3.37618 | W92: ='Raw - 2025 PL'!G86/1000 -> 0 | X92: ='Raw - 2025 PL'!H86/1000 -> 0 | Y92: ='Raw - 2025 PL'!I86/1000 -> 0.53011 | ... AC92: ='Raw - 2025 PL'!M86/1000 -> 0.42286 | AD92: ='Raw - 2026 PL'!B85/1000 -> 0 | AE92: ='Raw - 2026 PL'!C85/1000 -> 0 | AF92: ='Raw - 2026 PL'!D85/1000 -> 0 | AG92: ='Raw - 2026 PL'!E85/1000 -> 6.0151 | AH92: ='Raw - 2026 PL'!F85/1000 -> 1.35709 | AI92: ='Raw - 2026 PL'!G85/1000 -> 0 | AJ92: ='Raw - 2026 PL'!H85/1000 -> 0
A93: Airfare | B93: =SUM(F93:Q93) -> 0 | C93: =SUM(R93:AC93) -> 11.9719 | D93: =SUM(AD93:AJ93) -> 6.46323 | R93: ='Raw - 2025 PL'!B87/1000 -> 0 | S93: ='Raw - 2025 PL'!C87/1000 -> 0 | T93: ='Raw - 2025 PL'!D87/1000 -> 0 | U93: ='Raw - 2025 PL'!E87/1000 -> 6.54148 | V93: ='Raw - 2025 PL'!F87/1000 -> 3.35522 | W93: ='Raw - 2025 PL'!G87/1000 -> 0 | X93: ='Raw - 2025 PL'!H87/1000 -> 0 | Y93: ='Raw - 2025 PL'!I87/1000 -> 0.35841 | ... AC93: ='Raw - 2025 PL'!M87/1000 -> 0 | AD93: ='Raw - 2026 PL'!B86/1000 -> 0 | AE93: ='Raw - 2026 PL'!C86/1000 -> 0 | AF93: ='Raw - 2026 PL'!D86/1000 -> 0 | AG93: ='Raw - 2026 PL'!E86/1000 -> 3.75 | AH93: ='Raw - 2026 PL'!F86/1000 -> 2.71323 | AI93: ='Raw - 2026 PL'!G86/1000 -> 0 | AJ93: ='Raw - 2026 PL'!H86/1000 -> 0
A94: Entertainment | B94: =SUM(F94:Q94) -> 0 | C94: =SUM(R94:AC94) -> 0 | D94: =SUM(AD94:AJ94) -> 1.59703 | AD94: ='Raw - 2026 PL'!B87/1000 -> 0 | AE94: ='Raw - 2026 PL'!C87/1000 -> 0 | AF94: ='Raw - 2026 PL'!D87/1000 -> 0 | AG94: ='Raw - 2026 PL'!E87/1000 -> 0 | AH94: ='Raw - 2026 PL'!F87/1000 -> 1.59703 | AI94: ='Raw - 2026 PL'!G87/1000 -> 0 | AJ94: ='Raw - 2026 PL'!H87/1000 -> 0
A95: Meals | B95: =SUM(F95:Q95) -> 0 | C95: =SUM(R95:AC95) -> 4.66018 | D95: =SUM(AD95:AJ95) -> 4.22444 | R95: ='Raw - 2025 PL'!B88/1000 -> 0.00691 | S95: ='Raw - 2025 PL'!C88/1000 -> 0 | T95: ='Raw - 2025 PL'!D88/1000 -> 0 | U95: ='Raw - 2025 PL'!E88/1000 -> 0.99225 | V95: ='Raw - 2025 PL'!F88/1000 -> 2.42593 | W95: ='Raw - 2025 PL'!G88/1000 -> 0 | X95: ='Raw - 2025 PL'!H88/1000 -> 0.09766 | Y95: ='Raw - 2025 PL'!I88/1000 -> 0.033 | ... AC95: ='Raw - 2025 PL'!M88/1000 -> 0.00988 | AD95: ='Raw - 2026 PL'!B88/1000 -> 0 | AE95: ='Raw - 2026 PL'!C88/1000 -> 0 | AF95: ='Raw - 2026 PL'!D88/1000 -> 0 | AG95: ='Raw - 2026 PL'!E88/1000 -> 0 | AH95: ='Raw - 2026 PL'!F88/1000 -> 4.07126 | AI95: ='Raw - 2026 PL'!G88/1000 -> 0.15318 | AJ95: ='Raw - 2026 PL'!H88/1000 -> 0
A96: Other Travel Expenses | B96: =SUM(F96:Q96) -> 0 | C96: =SUM(R96:AC96) -> 0.71549 | D96: =SUM(AD96:AJ96) -> 0 | R96: ='Raw - 2025 PL'!B89/1000 -> 0 | S96: ='Raw - 2025 PL'!C89/1000 -> 0 | T96: ='Raw - 2025 PL'!D89/1000 -> 0 | U96: ='Raw - 2025 PL'!E89/1000 -> 0 | V96: ='Raw - 2025 PL'!F89/1000 -> 0.71549 | W96: ='Raw - 2025 PL'!G89/1000 -> 0 | X96: ='Raw - 2025 PL'!H89/1000 -> 0 | Y96: ='Raw - 2025 PL'!I89/1000 -> 0 | ... AC96: ='Raw - 2025 PL'!M89/1000 -> 0
A97: Parking | B97: =SUM(F97:Q97) -> 0 | C97: =SUM(R97:AC97) -> 0.235 | D97: =SUM(AD97:AJ97) -> 0 | R97: ='Raw - 2025 PL'!B90/1000 -> 0 | S97: ='Raw - 2025 PL'!C90/1000 -> 0 | T97: ='Raw - 2025 PL'!D90/1000 -> 0 | U97: ='Raw - 2025 PL'!E90/1000 -> 0 | V97: ='Raw - 2025 PL'!F90/1000 -> 0 | W97: ='Raw - 2025 PL'!G90/1000 -> 0 | X97: ='Raw - 2025 PL'!H90/1000 -> 0 | Y97: ='Raw - 2025 PL'!I90/1000 -> 0 | ... AC97: ='Raw - 2025 PL'!M90/1000 -> 0
A98: Transportation | B98: =SUM(F98:Q98) -> 0 | C98: =SUM(R98:AC98) -> 1.71138 | D98: =SUM(AD98:AJ98) -> 1.02853 | R98: ='Raw - 2025 PL'!B91/1000 -> 0 | S98: ='Raw - 2025 PL'!C91/1000 -> 0 | T98: ='Raw - 2025 PL'!D91/1000 -> 0 | U98: ='Raw - 2025 PL'!E91/1000 -> 0.11191 | V98: ='Raw - 2025 PL'!F91/1000 -> 0.9119 | W98: ='Raw - 2025 PL'!G91/1000 -> 0 | X98: ='Raw - 2025 PL'!H91/1000 -> 0 | Y98: ='Raw - 2025 PL'!I91/1000 -> 0 | ... AC98: ='Raw - 2025 PL'!M91/1000 -> 0 | AD98: ='Raw - 2026 PL'!B89/1000 -> 0 | AE98: ='Raw - 2026 PL'!C89/1000 -> 0 | AF98: ='Raw - 2026 PL'!D89/1000 -> 0 | AG98: ='Raw - 2026 PL'!E89/1000 -> 0 | AH98: ='Raw - 2026 PL'!F89/1000 -> 0.51582 | AI98: ='Raw - 2026 PL'!G89/1000 -> 0.50272 | AJ98: ='Raw - 2026 PL'!H89/1000 -> 0.00999
A99: Total Travel, Meals & Entertainment | B99: =SUM(F99:Q99) -> 0 | C99: =SUM(R99:AC99) -> 29.76122 | D99: =SUM(AD99:AJ99) -> 20.68542 | F99: =SUM(F91,F92,F93,F94,F95,F96,F97,F98) -> 0 | G99: =SUM(G91,G92,G93,G94,G95,G96,G97,G98) -> 0 | H99: =SUM(H91,H92,H93,H94,H95,H96,H97,H98) -> 0 | I99: =SUM(I91,I92,I93,I94,I95,I96,I97,I98) -> 0 | J99: =SUM(J91,J92,J93,J94,J95,J96,J97,J98) -> 0 | K99: =SUM(K91,K92,K93,K94,K95,K96,K97,K98) -> 0 | L99: =SUM(L91,L92,L93,L94,L95,L96,L97,L98) -> 0 | M99: =SUM(M91,M92,M93,M94,M95,M96,M97,M98) -> 0 | ... AJ99: =SUM(AJ91,AJ92,AJ93,AJ94,AJ95,AJ96,AJ97,AJ98) -> 0.00999
A100: Website | B100: =SUM(F100:Q100) -> 7.26173 | C100: =SUM(R100:AC100) -> 4.91967 | D100: =SUM(AD100:AJ100) -> 2.90857 | F100: ='Raw - 2024 PL'!B69/1000 -> 0.43326 | G100: ='Raw - 2024 PL'!C69/1000 -> 1.63176 | H100: ='Raw - 2024 PL'!D69/1000 -> 0.43368 | I100: ='Raw - 2024 PL'!E69/1000 -> 0.48413 | J100: ='Raw - 2024 PL'!F69/1000 -> 0.48413 | K100: ='Raw - 2024 PL'!G69/1000 -> 0.48413 | L100: ='Raw - 2024 PL'!H69/1000 -> 0.49344 | M100: ='Raw - 2024 PL'!I69/1000 -> 0.84344 | ... Q100: ='Raw - 2024 PL'!M69/1000 -> 0.49344 | R100: ='Raw - 2025 PL'!B93/1000 -> 0.53067 | S100: ='Raw - 2025 PL'!C93/1000 -> 0.399 | T100: ='Raw - 2025 PL'!D93/1000 -> 0.399 | U100: ='Raw - 2025 PL'!E93/1000 -> 0.399 | V100: ='Raw - 2025 PL'!F93/1000 -> 0.399 | W100: ='Raw - 2025 PL'!G93/1000 -> 0.399 | X100: ='Raw - 2025 PL'!H93/1000 -> 0.399 | Y100: ='Raw - 2025 PL'!I93/1000 -> 0.399 | ... AC100: ='Raw - 2025 PL'!M93/1000 -> 0.399 | AD100: ='Raw - 2026 PL'!B91/1000 -> 0.43619 | AE100: ='Raw - 2026 PL'!C91/1000 -> 0.399 | AF100: ='Raw - 2026 PL'!D91/1000 -> 0.47738 | AG100: ='Raw - 2026 PL'!E91/1000 -> 0.399 | AH100: ='Raw - 2026 PL'!F91/1000 -> 0.399 | AI100: ='Raw - 2026 PL'!G91/1000 -> 0.399 | AJ100: ='Raw - 2026 PL'!H91/1000 -> 0.399
A101: Total Sales & Marketing | B101: =SUM(F101:Q101) -> 14.01419 | C101: =SUM(R101:AC101) -> 68.81225 | D101: =SUM(AD101:AJ101) -> 89.65478 | F101: =SUM(F82,F86,F87,F88,F89,F90,F99,F100) -> 1.57726 | G101: =SUM(G82,G86,G87,G88,G89,G90,G99,G100) -> 2.63176 | H101: =SUM(H82,H86,H87,H88,H89,H90,H99,H100) -> 1.68368 | I101: =SUM(I82,I86,I87,I88,I89,I90,I99,I100) -> 0.54459 | J101: =SUM(J82,J86,J87,J88,J89,J90,J99,J100) -> 1.48413 | K101: =SUM(K82,K86,K87,K88,K89,K90,K99,K100) -> 1.48413 | L101: =SUM(L82,L86,L87,L88,L89,L90,L99,L100) -> 0.49344 | M101: =SUM(M82,M86,M87,M88,M89,M90,M99,M100) -> 1.01344 | ... AJ101: =SUM(AJ82,AJ86,AJ87,AJ88,AJ89,AJ90,AJ99,AJ100) -> 20.80975
A102: Total Expenses | B102: =SUM(F102:Q102) -> 232.55589 | C102: =SUM(R102:AC102) -> 660.94372 | D102: =SUM(AD102:AJ102) -> 712.06621 | F102: =SUM(F80,F81,F101) -> 8.76896 | G102: =SUM(G80,G81,G101) -> 14.61121 | H102: =SUM(H80,H81,H101) -> 15.58671 | I102: =SUM(I80,I81,I101) -> 18.00625 | J102: =SUM(J80,J81,J101) -> 17.07133 | K102: =SUM(K80,K81,K101) -> 16.54259 | L102: =SUM(L80,L81,L101) -> 15.5212 | M102: =SUM(M80,M81,M101) -> 14.53983 | ... AJ102: =SUM(AJ80,AJ81,AJ101) -> 126.86817
...

Sheet Raw - 2024 PL
A1: Keystone Bookkeepers
A2: Profit and Loss
A3: January - December 2024
B5: Jan 2024 | C5: Feb 2024 | D5: Mar 2024 | E5: Apr 2024 | F5: May 2024 | G5: Jun 2024 | H5: Jul 2024 | I5: Aug 2024 | J5: Sep 2024 | K5: Oct 2024 | L5: Nov 2024 | M5: Dec 2024 | N5: Total
A6: Income
A7: Non-Recurring Revenue | N7: 0
A8: 1099 Filing | B8: 6945 | C8: 3380 | D8: 45 | E8: 60 | F8: 15 | I8: 15 | L8: 15 | N8: 10475
A9: Billable Expense Income | B9: 50 | E9: 25 | H9: 299.7 | N9: 374.7
A10: Offshore Recruiting | B10: 500 | C10: 3000 | F10: 3000 | G10: 565 | H10: 10500 | I10: 6500 | J10: 500 | K10: -965 | L10: 0 | N10: 23600
A11: Profit Share | B11: 68.6 | C11: 131.2 | D11: 71.2 | E11: 55.6 | F11: 577 | G11: 806.8 | H11: 665.6 | I11: 826.4 | J11: 1380.8 | K11: 860.4 | L11: 510 | M11: 246.8 | N11: 6200.4
A12: Total Non-Recurring Revenue | B12: 7563.6 | C12: 6511.2 | D12: 116.2 | E12: 140.6 | F12: 3592 | G12: 1371.8 | H12: 11465.3 | I12: 7341.4 | J12: 1880.8 | K12: -104.6 | L12: 525 | M12: 246.8 | N12: 40650.1
A13: Onboarding Revenue | N13: 0
A14: Historical Cleanup | B14: 1200 | C14: 1762.5 | D14: 660 | E14: 395 | F14: 2465 | G14: 1275 | H14: 1462.5 | J14: 1145.25 | K14: 1355.25 | L14: 1903.5 | M14: 4000 | N14: 17624
A15: Onboarding | B15: 5465 | C15: 3900 | D15: 2755 | E15: 3502 | F15: 4659 | G15: 3937 | H15: 4602 | I15: 4738 | J15: 2119 | K15: 2064 | L15: 3012.5 | M15: 3305 | N15: 44058.5
A16: Total Onboarding Revenue | B16: 6665 | C16: 5662.5 | D16: 3415 | E16: 3897 | F16: 7124 | G16: 5212 | H16: 6064.5 | I16: 4738 | J16: 3264.25 | K16: 3419.25 | L16: 4916 | M16: 7305 | N16: 61682.5
A17: SMB Bookkeeping Subscription | B17: 22001 | C17: 22036 | D17: 22111 | E17: 22146 | F17: 21966 | G17: 17816 | H17: 17621 | I17: 17536 | J17: 16426 | K17: 15381 | L17: 14675.5 | M17: 15075.5 | N17: 224791
A18: STR Recurring Revenue | N18: 0
A19: Controller Services | H19: 1250 | I19: 1250 | J19: 1250 | K19: 1250 | L19: 5750 | M19: 3000 | N19: 13750
A20: Occupancy Taxes | L20: 80 | M20: 480 | N20: 560
A21: STR Bill Pay | M21: 60 | N21: 60
A22: STR Bookkeeping Subscription | B22: 44683.5 | C22: 47046 | D22: 52470 | E22: 57169.7 | F22: 57514.15 | G22: 65516 | H22: 68281.25 | I22: 73251.35 | J22: 75551.7 | K22: 79113.25 | L22: 83290.8 | M22: 89584.55 | N22: 793472.25
A23: Total STR Recurring Revenue | B23: 44683.5 | C23: 47046 | D23: 52470 | E23: 57169.7 | F23: 57514.15 | G23: 65516 | H23: 69531.25 | I23: 74501.35 | J23: 76801.7 | K23: 80363.25 | L23: 89120.8 | M23: 93124.55 | N23: 807842.25
A24: Total Income | B24: 80913.1 | C24: 81255.7 | D24: 78112.2 | E24: 83353.3 | F24: 90196.15 | G24: 89915.8 | H24: 104682.05 | I24: 104116.75 | J24: 98372.75 | K24: 99058.9 | L24: 109237.3 | M24: 115751.85 | N24: 1134965.9
A25: Cost of Goods Sold
A26: 1099 Filing Fees | B26: 1299.34 | C26: 30.12 | D26: 10.63 | E26: 3.25 | F26: 0.65 | I26: 1.94 | N26: 1345.93
A27: Direct Labor | N27: 0
A28: Bookkeeper Wages | B28: 9555 | C28: 9555 | D28: 10397.2 | E28: 14999.67 | F28: 18009.8 | G28: 13891.27 | H28: 14048.24 | I28: 13390.91 | J28: 14669.31 | K28: 15882.53 | L28: 27188.67 | M28: 21781.43 | N28: 183369.03
A29: Client Lead Wages | B29: 9961.08 | C29: 13850.26 | D29: 12790.54 | E29: 14571.45 | F29: 28285.63 | G29: 26542.54 | H29: 28311.19 | I29: 28187.46 | J29: 30868.01 | K29: 31621.28 | L29: 28449.74 | M29: 32722.11 | N29: 286161.29
A30: Occupancy Tax Specialist | M30: 1113.35 | N30: 1113.35
A31: Onboarding Team Wages | B31: 9137.28 | C31: 8962.96 | D31: 10195.84 | E31: 15044.29 | F31: 16637.44 | G31: 7494.99 | H31: 7982.02 | I31: 5902.74 | J31: 7767.63 | K31: 8214.17 | L31: 12622.72 | M31: 12850.47 | N31: 122812.55
A32: Total Direct Labor | B32: 28653.36 | C32: 32368.22 | D32: 33383.58 | E32: 44615.41 | F32: 62932.87 | G32: 47928.8 | H32: 50341.45 | I32: 47481.11 | J32: 53304.95 | K32: 55717.98 | L32: 68261.13 | M32: 68467.36 | N32: 593456.22
A33: Payment Collection Fees | B33: 617.9 | C33: 837.4 | D33: 629.36 | E33: 682.45 | F33: 721.51 | G33: 787.47 | H33: 655.62 | I33: 794.91 | J33: 690.63 | K33: 717.61 | L33: 737.95 | M33: 798.18 | N33: 8670.99
A34: Referral Fees | B34: 2210 | C34: 2735 | D34: 2715 | E34: 2735 | F34: 780 | G34: 3245 | H34: 1280 | I34: 1300 | J34: 1810 | K34: 1820 | L34: 1835 | M34: 2355 | N34: 24820
A35: Software & Apps - COGS | B35: 7073 | C35: 7018.18 | D35: 7777.88 | E35: 7761.24 | F35: 7718.21 | G35: 8912.64 | H35: 10846.68 | I35: 11135.14 | J35: 11034.5 | K35: 11728.73 | L35: 11446.91 | M35: 11969.58 | N35: 114422.69
A36: Total Cost of Goods Sold | B36: 39853.6 | C36: 42988.92 | D36: 44516.45 | E36: 55797.35 | F36: 72153.24 | G36: 60873.91 | H36: 63123.75 | I36: 60713.1 | J36: 66840.08 | K36: 69984.32 | L36: 82280.99 | M36: 83590.12 | N36: 742715.83
A37: Gross Profit | B37: 41059.5 | C37: 38266.78 | D37: 33595.75 | E37: 27555.95 | F37: 18042.91 | G37: 29041.89 | H37: 41558.3 | I37: 43403.65 | J37: 31532.67 | K37: 29074.58 | L37: 26956.31 | M37: 32161.73 | N37: 392250.02
A38: Expenses
A39: General & Admin Expenses | N39: 0
A40: Bank Fees | B40: 1 | C40: 1 | D40: 1 | E40: 96 | F40: 2 | G40: 1 | H40: 5.63 | I40: 1 | J40: 1 | K40: 4.17 | L40: 9.42 | M40: 24.67 | N40: 147.89
A41: Employee Benefits | N41: 0
A42: Employee Equipment Allowance | H42: 381 | I42: 319.26 | L42: 813 | M42: 93 | N42: 1606.26
A43: Employee Internet Allowance | H43: 42 | I43: 40.3 | J43: 18 | K43: 60 | L43: 104 | M43: 146 | N43: 410.3
A44: Employee Referral Fees | J44: 200 | K44: 200 | M44: 200 | N44: 600
A45: Other Employee Benefits | G45: 61.45 | H45: 100 | K45: 100 | N45: 261.45
A46: ST/LT Disability | C46: 627.7 | E46: 338.9 | F46: 338.9 | H46: 338.9 | J46: 169.45 | K46: 338.9 | M46: 343.29 | N46: 2496.04
A47: Total Employee Benefits | B47: 0 | C47: 627.7 | D47: 0 | E47: 338.9 | F47: 338.9 | G47: 61.45 | H47: 861.9 | I47: 359.56 | J47: 387.45 | K47: 698.9 | L47: 917 | M47: 782.29 | N47: 5374.05
A48: Indirect Labor | B48: 3093.46 | C48: 4630.17 | D48: 4395.07 | E48: 5863.87 | F48: 7372.33 | G48: 4950.4 | H48: 4950.4 | I48: 4700.35 | J48: 4950.4 | K48: 5999.87 | L48: 26028.76 | M48: 24440.12 | N48: 101375.2
A49: Insurance | B49: 147.47 | C49: 147.47 | D49: 177.55 | E49: 191.67 | F49: 180.14 | G49: 176.22 | H49: 176.2 | I49: 176.22 | J49: 187.12 | K49: 177.44 | L49: 176.22 | M49: 176.22 | N49: 2089.94
A50: Legal & Professional Fees | N50: 0
A51: Accounting Fees | D51: 2600 | J51: 892.5 | N51: 3492.5
A52: Other Professional Fees | C52: 1166.5 | D52: 1166.5 | E52: 1166.67 | F52: 1166.67 | G52: 2666.66 | H52: 1166.67 | I52: 1166.67 | J52: 3067.91 | K52: 1166.67 | L52: 2166.67 | M52: 2166.66 | N52: 18234.25
A53: Recruiting Fees | B53: 24.92 | C53: 1024.92 | D53: 1024.92 | E53: 1224.92 | F53: 1024.92 | G53: 1518.02 | H53: 2013.31 | I53: 1600.9 | J53: 1589.69 | K53: 1125.82 | L53: 1441.99 | M53: 1287.72 | N53: 14902.05
A54: Total Legal & Professional Fees | B54: 24.92 | C54: 2191.42 | D54: 4791.42 | E54: 2391.59 | F54: 2191.59 | G54: 4184.68 | H54: 3179.98 | I54: 2767.57 | J54: 5550.1 | K54: 2292.49 | L54: 3608.66 | M54: 3454.38 | N54: 36628.8
A55: Office Supplies | E55: 2158.98 | M55: 950 | N55: 3108.98
A56: Other Business Expenses | F56: 64.99 | N56: 64.99
A57: Penalties | E57: 1750 | N57: 1750
A58: Postage | B58: 52.83 | C58: 344.99 | D58: 30.75 | G58: 11.2 | K58: 6.08 | L58: 25 | M58: 9.91 | N58: 480.76
A59: Professional Organizations | B59: 334.17 | C59: 334.17 | D59: 334.17 | E59: 334.17 | F59: 255 | G59: 255 | H59: 254.96 | I59: 205 | J59: 784.17 | K59: 784.17 | L59: 784.17 | M59: 784.17 | N59: 5443.32
A60: Software & Apps - G&A | B60: 3452.85 | C60: 3617.53 | D60: 3974.07 | E60: 4223.65 | F60: 5097.25 | G60: 5333.51 | H60: 5513.69 | I60: 5231.69 | J60: 5516.22 | K60: 6127.97 | L60: 6150.97 | M60: 6676.54 | N60: 60915.94
A61: State Filing Fees | D61: 102 | N61: 102
A62: Utilities | B62: 85 | C62: 85 | D62: 97 | E62: 112.83 | F62: 85 | G62: 85 | H62: 85 | I62: 85 | J62: 85 | K62: 85 | L62: 85 | M62: 85 | N62: 1059.83
A63: Total General & Admin Expenses | B63: 7191.7 | C63: 11979.45 | D63: 13903.03 | E63: 17461.66 | F63: 15587.2 | G63: 15058.46 | H63: 15027.76 | I63: 13526.39 | J63: 17461.46 | K63: 16176.09 | L63: 37785.2 | M63: 37383.3 | N63: 218541.7
A64: Sales & Marketing | N64: 0
A65: Conferences & Meetups | D65: 250 | E65: 60.46 | N65: 310.46
A66: Other Advertising | J66: 100 | N66: 100
A67: Social Media | B67: 1144 | C67: 1000 | D67: 1000 | F67: 1000 | G67: 1000 | N67: 5144
A68: Software & Apps | I68: 170 | J68: 170 | K68: 518 | L68: 170 | M68: 170 | N68: 1198
A69: Website | B69: 433.26 | C69: 1631.76 | D69: 433.68 | E69: 484.13 | F69: 484.13 | G69: 484.13 | H69: 493.44 | I69: 843.44 | J69: 493.44 | K69: 493.44 | L69: 493.44 | M69: 493.44 | N69: 7261.73
A70: Total Sales & Marketing | B70: 1577.26 | C70: 2631.76 | D70: 1683.68 | E70: 544.59 | F70: 1484.13 | G70: 1484.13 | H70: 493.44 | I70: 1013.44 | J70: 763.44 | K70: 1011.44 | L70: 663.44 | M70: 663.44 | N70: 14014.19
A71: Total Expenses | B71: 8768.96 | C71: 14611.21 | D71: 15586.71 | E71: 18006.25 | F71: 17071.33 | G71: 16542.59 | H71: 15521.2 | I71: 14539.83 | J71: 18224.9 | K71: 17187.53 | L71: 38448.64 | M71: 38046.74 | N71: 232555.89
A72: Net Operating Income | B72: 32290.54 | C72: 23655.57 | D72: 18009.04 | E72: 9549.7 | F72: 971.58 | G72: 12499.3 | H72: 26037.1 | I72: 28863.82 | J72: 13307.77 | K72: 11887.05 | L72: -11492.33 | M72: -5885.01 | N72: 159694.13
A73: Other Income
A74: Credit Card Rewards | M74: 27.36 | N74: 27.36
A75: Total Other Income | B75: 0 | C75: 0 | D75: 0 | E75: 0 | F75: 0 | G75: 0 | H75: 0 | I75: 0 | J75: 0 | K75: 0 | L75: 0 | M75: 27.36 | N75: 27.36
A76: Other Expenses
A77: Amortization Expense | M77: 6673 | N77: 6673
A78: Interest Expense | L78: 71.5 | M78: 8.14 | N78: 79.64
A79: State Taxes | E79: 6246 | G79: 2472 | J79: 2472 | M79: -3693 | N79: 7497
A80: Total Other Expenses | B80: 0 | C80: 0 | D80: 0 | E80: 6246 | F80: 0 | G80: 2472 | H80: 0 | I80: 0 | J80: 2472 | K80: 0 | L80: 71.5 | M80: 2988.14 | N80: 14249.64
A81: Net Other Income | B81: 0 | C81: 0 | D81: 0 | E81: -6246 | F81: 0 | G81: -2472 | H81: 0 | I81: 0 | J81: -2472 | K81: 0 | L81: -71.5 | M81: -2960.78 | N81: -14222.28
A82: Net Income | B82: 32290.54 | C82: 23655.57 | D82: 18009.04 | E82: 3303.7 | F82: 971.58 | G82: 10027.3 | H82: 26037.1 | I82: 28863.82 | J82: 10835.77 | K82: 11887.05 | L82: -11563.83 | M82: -8845.79 | N82: 145471.85
A86: Friday, Aug 28, 2026 02:05:07 PM GMT-7 - Accrual Basis

Sheet Raw - 2025 PL
A1: Keystone Bookkeepers
A2: Profit and Loss
A3: January - December 2025
B5: Jan 2025 | C5: Feb 2025 | D5: Mar 2025 | E5: Apr 2025 | F5: May 2025 | G5: Jun 2025 | H5: Jul 2025 | I5: Aug 2025 | J5: Sep 2025 | K5: Oct 2025 | L5: Nov 2025 | M5: Dec 2025 | N5: Total
A6: Income
A7: Income Tax Revenue | N7: 0
A8: Business Income Tax | J8: 875 | K8: 0 | L8: 0 | M8: 875 | N8: 1750
A9: Individual Income Tax | J9: 0 | K9: 1650 | N9: 1650
A10: Total Income Tax Revenue | B10: 0 | C10: 0 | D10: 0 | E10: 0 | F10: 0 | G10: 0 | H10: 0 | I10: 0 | J10: 875 | K10: 1650 | L10: 0 | M10: 875 | N10: 3400
A11: Non-Recurring Revenue | N11: 0
A12: 1099 Filing | B12: 13485 | C12: 9915 | D12: 60 | E12: 30 | I12: 30 | J12: 30 | N12: 23550
A13: Billable Expense Income | B13: 25 | C13: 399.6 | F13: 72.94 | H13: 289.71 | I13: 309.69 | M13: 25 | N13: 1121.94
A14: Offshore Recruiting | B14: 100 | D14: 100 | N14: 200
A15: Profit Share | B15: 7358.4 | C15: 1293.35 | D15: 968.33 | E15: 1165.6 | F15: 960.93 | G15: 1711.27 | H15: 1047.07 | I15: 2040.88 | J15: 1136.21 | K15: 2014.24 | L15: 1297.58 | M15: 2267.93 | N15: 23261.79
A16: Total Non-Recurring Revenue | B16: 20968.4 | C16: 11607.95 | D16: 1128.33 | E16: 1195.6 | F16: 1033.87 | G16: 1711.27 | H16: 1336.78 | I16: 2380.57 | J16: 1166.21 | K16: 2014.24 | L16: 1297.58 | M16: 2292.93 | N16: 48133.73
A17: Onboarding Revenue | N17: 0
A18: Historical Cleanup | B18: 1083.75 | C18: 2000 | D18: 1355 | K18: 595 | N18: 5033.75
A19: Onboarding | B19: 3079 | C19: 700 | D19: 10438.55 | E19: 4300 | F19: 11140 | G19: 6162.5 | H19: 6434 | I19: 3965 | J19: 3920 | K19: 9136.5 | L19: 5253.75 | M19: 9990 | N19: 74519.3
A20: Total Onboarding Revenue | B20: 4162.75 | C20: 2700 | D20: 11793.55 | E20: 4300 | F20: 11140 | G20: 6162.5 | H20: 6434 | I20: 3965 | J20: 3920 | K20: 9731.5 | L20: 5253.75 | M20: 9990 | N20: 79553.05
A21: SMB Bookkeeping Subscription | B21: 14562.5 | C21: 12802.5 | D21: 12402.5 | E21: 12602.5 | F21: 12752.5 | G21: 12792.5 | H21: 12537.5 | I21: 11857.5 | J21: 12302.5 | K21: 11692.5 | L21: 11717.5 | M21: 11747.5 | N21: 149770
A22: STR Recurring Revenue | N22: 0
A23: Controller Services | B23: 4450 | C23: 3450 | D23: 3450 | E23: 5950 | F23: 5200 | G23: 5000 | H23: 4000 | I23: 2950 | J23: 3025 | K23: 3025 | L23: 2950 | M23: 2950 | N23: 46400
A24: Occupancy Taxes | B24: 1130 | C24: 2140 | D24: 2660 | E24: 3650 | F24: 3623 | G24: 4964 | H24: 5058.5 | I24: 4730 | J24: 4820 | K24: 5370 | L24: 8050 | M24: 8885 | N24: 55080.5
A25: STR Bill Pay | B25: 970 | C25: 1100 | D25: 1735 | E25: 2140 | F25: 2363 | G25: 3263.5 | H25: 3920 | I25: 3905 | J25: 3780 | K25: 3795 | L25: 4330 | M25: 5305 | N25: 36606.5
A26: STR Bookkeeping Subscription | B26: 92418.9 | C26: 94002.15 | D26: 101506.05 | E26: 106137.5 | F26: 115938.75 | G26: 119431.25 | H26: 122094 | I26: 130085.25 | J26: 133590.5 | K26: 139609 | L26: 145280.75 | M26: 150398.25 | N26: 1450492.4
A27: Topkey Subscription | J27: 520 | K27: 2357 | L27: 2811 | M27: 4259 | N27: 9947
A28: Total STR Recurring Revenue | B28: 98968.9 | C28: 100692.15 | D28: 109351.05 | E28: 117877.5 | F28: 127124.75 | G28: 132658.75 | H28: 135072.5 | I28: 141670.25 | J28: 145735.5 | K28: 154156 | L28: 163421.75 | M28: 171797.25 | N28: 1598526.4
A29: Total Income | B29: 138662.55 | C29: 127802.6 | D29: 134675.43 | E29: 135975.6 | F29: 152051.12 | G29: 153325.02 | H29: 155380.78 | I29: 159873.32 | J29: 163999.21 | K29: 179244.24 | L29: 181690.58 | M29: 196702.68 | N29: 1879383.1
A30: Cost of Goods Sold
A31: 1099 Filing Fees | B31: 1226.55 | C31: 0 | D31: 1154.33 | E31: 0 | F31: 0 | G31: 0 | H31: 0 | I31: 0 | J31: 0 | K31: 113.45 | L31: 0 | M31: 0 | N31: 2494.33
A32: Contract Labor - Tax | K32: 1150 | L32: 437.5 | N32: 1587.5
A33: Direct Labor | N33: 0
A34: Bookkeeper Wages | B34: 19402.33 | C34: 16400.53 | D34: 19569.83 | E34: 22154.2 | F34: 20791.54 | G34: 21040.79 | H34: 27908.91 | I34: 29547 | J34: 33447.27 | K34: 37794.32 | L34: 34063.32 | M34: 34064.58 | N34: 316184.62
A35: Client Lead Wages | B35: 32780.76 | C35: 23361.84 | D35: 26914.27 | E35: 28812.98 | F35: 30658.75 | G35: 29271.6 | H35: 29479.63 | I35: 26830.64 | J35: 29785.55 | K35: 32899.37 | L35: 29493.34 | M35: 32669.71 | N35: 352958.44
A36: Occupancy Tax Specialist | B36: 2179.17 | C36: 1825.04 | D36: 1978.53 | E36: 2062.13 | F36: 2062.13 | G36: 1989.68 | H36: 2179.17 | I36: 2122.93 | J36: 3104.2 | K36: 3271.37 | L36: 3639.47 | M36: 3150.33 | N36: 29564.15
A37: Onboarding Team Wages | B37: 10345.56 | C37: 8087.98 | D37: 9752.87 | E37: 10280 | F37: 11136.32 | G37: 10874.32 | H37: 13472.57 | I37: 12704.07 | J37: 14698.84 | K37: 15543.06 | L37: 14343.61 | M37: 20930.52 | N37: 152169.72
A38: Total Direct Labor | B38: 64707.82 | C38: 49675.39 | D38: 58215.5 | E38: 63309.31 | F38: 64648.74 | G38: 63176.39 | H38: 73040.28 | I38: 71204.64 | J38: 81035.86 | K38: 89508.12 | L38: 81539.74 | M38: 90815.14 | N38: 850876.93
A39: Occupancy Tax Filing Fees | B39: 100 | E39: 149.8 | F39: 59.75 | G39: 69.7 | H39: 159.7 | I39: 310.85 | J39: 467.51 | K39: 517.51 | L39: -188.41 | M39: 109.5 | N39: 1755.91
A40: Payment Collection Fees | B40: 835.46 | C40: 1053.94 | D40: 870.69 | E40: 905.55 | F40: 911.57 | G40: 1002.49 | H40: 1224.75 | I40: 1104.38 | J40: 1297.23 | K40: 1217.39 | L40: 1622.94 | M40: 1305.14 | N40: 13351.53
A41: Referral Fees | B41: 1470.25 | C41: 1665 | D41: 2627.75 | E41: 1248.75 | F41: 2154 | G41: 4154 | H41: 3769.75 | I41: 1696 | J41: 2227.5 | K41: 1664.5 | L41: 1718.79 | M41: 2757.45 | N41: 27153.74
A42: Service Discount | D42: 4640 | N42: 4640
A43: Software & Apps - COGS | B43: 10848.53 | C43: 12213.11 | D43: 11571.67 | E43: 11810.87 | F43: 12525.63 | G43: 12863.33 | H43: 13135.45 | I43: 14257.15 | J43: 13595.12 | K43: 12347.62 | L43: 15217.81 | M43: 17108.42 | N43: 157494.71
A44: Software & Apps - Tax | J44: 396.95 | N44: 396.95
A45: Software & Apps - Topkey | J45: 937.25 | K45: 1392.25 | L45: 2361.25 | M45: 2450.5 | N45: 7141.25
A46: Total Cost of Goods Sold | B46: 79188.61 | C46: 64607.44 | D46: 79079.94 | E46: 77424.28 | F46: 80299.69 | G46: 81265.91 | H46: 91329.93 | I46: 88573.02 | J46: 99957.42 | K46: 107910.84 | L46: 102709.62 | M46: 114546.15 | N46: 1066892.9
A47: Gross Profit | B47: 59473.94 | C47: 63195.16 | D47: 55595.49 | E47: 58551.32 | F47: 71751.43 | G47: 72059.11 | H47: 64050.85 | I47: 71300.3 | J47: 64041.79 | K47: 71333.4 | L47: 78980.96 | M47: 82156.53 | N47: 812490.28
A48: Expenses
A49: General & Admin Expenses | N49: 0
A50: Bank Fees | B50: 137.44 | C50: 122.14 | D50: 43.5 | E50: 399 | F50: 101.3 | G50: 69.6 | H50: 147.2 | I50: 109.8 | J50: 116.6 | K50: 148.9 | L50: 125.8 | M50: 313.7 | N50: 1834.98
A51: Computer Equipment | E51: 1849.99 | K51: 781.08 | N51: 2631.07
A52: Employee Benefits | N52: 0
A53: Education and Training | F53: 300 | G53: 36 | N53: 336
A54: Employee Equipment Allowance | C54: 173 | D54: 145 | E54: 290 | F54: 1004 | G54: 1224 | H54: 783 | I54: 328 | J54: 236 | K54: 772 | L54: 537 | M54: 628 | N54: 6120
A55: Employee Internet Allowance | B55: 150 | C55: 243 | D55: 136 | E55: 144 | F55: 170.4 | G55: 185 | H55: 161 | I55: 168 | J55: 211 | K55: 381 | L55: 240 | M55: 197 | N55: 2386.4
A56: Employee Medical Allowance | M56: 2519 | N56: 2519
A57: Employee Referral Fees | C57: 400 | D57: 200 | F57: 600 | G57: 200 | H57: 200 | J57: 200 | K57: 1000 | M57: 400 | N57: 3200
A58: Other Employee Benefits | C58: 34.54 | E58: 100 | G58: 36 | H58: 236.3 | I58: 1071.14 | J58: 80 | K58: 180 | L58: 80 | M58: 80 | N58: 1897.98
A59: ST/LT Disability | B59: 787.24 | C59: 180.53 | D59: 180.53 | E59: 180.53 | F59: 180.53 | G59: 180.53 | H59: 180.53 | I59: 180.53 | J59: 180.53 | K59: 180.53 | L59: 180.53 | M59: 180.53 | N59: 2773.07
A60: Total Employee Benefits | B60: 937.24 | C60: 1031.07 | D60: 661.53 | E60: 714.53 | F60: 2254.93 | G60: 1861.53 | H60: 1560.83 | I60: 1747.67 | J60: 907.53 | K60: 2513.53 | L60: 1037.53 | M60: 4004.53 | N60: 19232.45
A61: Indirect Labor | B61: 21052.34 | C61: 19916.03 | D61: 11743.87 | E61: 19617.92 | F61: 20669.78 | G61: 20693.9 | H61: 22602.64 | I61: 19961.28 | J61: 27605.63 | K61: 34185.89 | L61: 29731.57 | M61: 33459.69 | N61: 281240.54
A62: Insurance | B62: 176.78 | C62: 208.99 | D62: 189.6 | E62: 175.9 | F62: 235.7 | G62: 226.76 | H62: 226.76 | I62: 226.76 | J62: 243.25 | K62: 242.28 | L62: 233.52 | M62: 233.52 | N62: 2619.82
A63: Legal & Professional Fees | N63: 0
A64: Accounting Fees | E64: 1400 | N64: 1400
A65: Other Professional Fees | B65: 2166.67 | C65: 2166.67 | D65: 2166.66 | E65: 2760.67 | F65: 1586.67 | G65: 1166.66 | H65: 0 | I65: 200 | J65: 1326.95 | K65: 0 | L65: 6000 | M65: 7500 | N65: 27040.95
A66: Recruiting Fees | B66: 2412.95 | C66: 22379.3 | D66: 729.83 | E66: 595.97 | F66: 875.34 | G66: 529.67 | H66: 776.88 | I66: 216.71 | J66: 749.52 | K66: 925.73 | L66: 660.44 | M66: 751.76 | N66: 31604.1
A67: Total Legal & Professional Fees | B67: 4579.62 | C67: 24545.97 | D67: 2896.49 | E67: 4756.64 | F67: 2462.01 | G67: 1696.33 | H67: 776.88 | I67: 416.71 | J67: 2076.47 | K67: 925.73 | L67: 6660.44 | M67: 8251.76 | N67: 60045.05
A68: Office Supplies | B68: 29.97 | D68: 382.09 | F68: 561.56 | I68: 349.99 | M68: 62.89 | N68: 1386.5
A69: Postage | B69: 29.9 | C69: 339.99 | E69: 10.83 | F69: 5 | G69: -9.55 | K69: 21.15 | L69: 3.75 | N69: 401.07
A70: Professional Organizations | B70: 784.17 | C70: 784.17 | D70: 784.17 | E70: 784.17 | F70: 784.17 | G70: 784.17 | H70: 1485.98 | I70: 963.3 | J70: 980.42 | K70: 1029.42 | L70: 1029.42 | M70: 1029.4 | N70: 11222.96
A71: Software & Apps - G&A | B71: 7746.46 | C71: 7891.81 | D71: 7890.85 | E71: 7834.63 | F71: 8117.23 | G71: 8345.84 | H71: 8984.68 | I71: 9856.6 | J71: 10733.91 | K71: 12089.39 | L71: 13145.83 | M71: 14421.43 | N71: 117058.66
A72: State Filing Fees | B72: 102 | E72: 398 | N72: 500
A73: Utilities | B73: 85 | C73: 94.49 | D73: 824.89 | E73: 253 | F73: 262.95 | G73: 253 | H73: 253 | I73: 253 | J73: 253 | K73: 253 | L73: 253 | M73: 253 | N73: 3291.33
A74: Total General & Admin Expenses | B74: 35660.92 | C74: 54934.66 | D74: 25416.99 | E74: 36794.61 | F74: 35454.63 | G74: 33921.58 | H74: 36037.97 | I74: 33885.11 | J74: 42916.81 | K74: 52190.37 | L74: 52220.86 | M74: 62029.92 | N74: 501464.43
A75: Payroll Wages - Owner | D75: 8906.39 | E75: 9233.23 | F75: 9108.84 | G75: 8694.79 | H75: 9522.87 | I75: 8694.81 | J75: 9108.84 | K75: 9522.87 | L75: 8280.76 | M75: 9593.64 | N75: 90667.04
A76: Sales & Marketing | N76: 0
A77: Conferences & Meetups | N77: 0
A78: C&M - Ticket/Sponsorship | I78: 6400 | J78: 0 | K78: 2428.8 | N78: 8828.8
A79: C&M - Event Cost/Supplies | I79: 770 | J79: 1649.5 | K79: 250 | N79: 2669.5
A80: Total Conferences & Meetups | B80: 0 | C80: 0 | D80: 0 | E80: 0 | F80: 0 | G80: 0 | H80: 0 | I80: 7170 | J80: 1649.5 | K80: 2678.8 | L80: 0 | M80: 0 | N80: 11498.3
A81: Other Advertising | H81: 100 | N81: 100
A82: Sales and Marketing Wages | G82: 1466.8 | H82: 1632.65 | I82: 1718.05 | J82: 1914.6 | K82: 2352.9 | L82: 2245.24 | M82: 7819.39 | N82: 19149.63
A83: Social Media | B83: 144 | N83: 144
A84: Software & Apps | B84: 170 | C84: 170 | D84: 316.43 | E84: 270 | F84: 270 | G84: 270 | H84: 270 | I84: 220 | J84: 220 | K84: 568 | L84: 220 | M84: 275 | N84: 3239.43
A85: Travel, Meals & Entertainment | N85: 0
A86: Accommodation | E86: 3760.65 | F86: 3376.18 | I86: 530.11 | J86: 1005.79 | K86: 299.32 | L86: 1072.36 | M86: 422.86 | N86: 10467.27
A87: Airfare | E87: 6541.48 | F87: 3355.22 | I87: 358.41 | J87: 880.96 | K87: 376.97 | L87: 458.86 | N87: 11971.9
A88: Meals | B88: 6.91 | E88: 992.25 | F88: 2425.93 | H88: 97.66 | I88: 33 | J88: 687.61 | K88: 250.05 | L88: 156.89 | M88: 9.88 | N88: 4660.18
A89: Other Travel Expenses | F89: 715.49 | N89: 715.49
A90: Parking | J90: 148 | L90: 87 | N90: 235
A91: Transportation | E91: 111.91 | F91: 911.9 | J91: 241.87 | K91: 110.45 | L91: 335.25 | N91: 1711.38
A92: Total Travel, Meals & Entertainment | B92: 6.91 | C92: 0 | D92: 0 | E92: 11406.29 | F92: 10784.72 | G92: 0 | H92: 97.66 | I92: 921.52 | J92: 2964.23 | K92: 1036.79 | L92: 2110.36 | M92: 432.74 | N92: 29761.22
A93: Website | B93: 530.67 | C93: 399 | D93: 399 | E93: 399 | F93: 399 | G93: 399 | H93: 399 | I93: 399 | J93: 399 | K93: 399 | L93: 399 | M93: 399 | N93: 4919.67
A94: Total Sales & Marketing | B94: 851.58 | C94: 569 | D94: 715.43 | E94: 12075.29 | F94: 11453.72 | G94: 2135.8 | H94: 2499.31 | I94: 10428.57 | J94: 7147.33 | K94: 7035.49 | L94: 4974.6 | M94: 8926.13 | N94: 68812.25
A95: Total Expenses | B95: 36512.5 | C95: 55503.66 | D95: 35038.81 | E95: 58103.13 | F95: 56017.19 | G95: 44752.17 | H95: 48060.15 | I95: 53008.49 | J95: 59172.98 | K95: 68748.73 | L95: 65476.22 | M95: 80549.69 | N95: 660943.72
A96: Net Operating Income | B96: 22961.44 | C96: 7691.5 | D96: 20556.68 | E96: 448.19 | F96: 15734.24 | G96: 27306.94 | H96: 15990.7 | I96: 18291.81 | J96: 4868.81 | K96: 2584.67 | L96: 13504.74 | M96: 1606.84 | N96: 151546.56
A97: Other Income
A98: Other Miscellaneous Income | C98: 19.93 | D98: 12.93 | E98: 19.63 | F98: 23.15 | G98: 9.62 | H98: 32.07 | I98: 16.34 | J98: 15.84 | K98: 23.96 | L98: 25.13 | M98: 18.62 | N98: 217.22
A99: Total Other Income | B99: 0 | C99: 19.93 | D99: 12.93 | E99: 19.63 | F99: 23.15 | G99: 9.62 | H99: 32.07 | I99: 16.34 | J99: 15.84 | K99: 23.96 | L99: 25.13 | M99: 18.62 | N99: 217.22
A100: Other Expenses
A101: Amortization Expense | M101: 6673 | N101: 6673
...

Sheet Raw - 2026 PL
A1: Keystone Bookkeepers
A2: Profit and Loss
A3: January - July, 2026
B5: Jan 2026 | C5: Feb 2026 | D5: Mar 2026 | E5: Apr 2026 | F5: May 2026 | G5: Jun 2026 | H5: Jul 2026 | I5: Total
A6: Income
A7: Income Tax Revenue | I7: 0
A8: Business Income Tax | B8: 0 | C8: 0 | D8: 14190 | E8: 4300 | G8: 3100 | I8: 21590
A9: Individual Income Tax | B9: 0 | C9: 0 | D9: 0 | E9: 2325 | I9: 2325
A10: Total Income Tax Revenue | B10: 0 | C10: 0 | D10: 14190 | E10: 6625 | F10: 0 | G10: 3100 | H10: 0 | I10: 23915
A11: Non-Recurring Revenue | I11: 0
A12: 1099 Filing | B12: 6105 | C12: 31156.5 | D12: 1260 | E12: 180 | I12: 38701.5
A13: Billable Expense Income | B13: 159.84 | D13: 75 | G13: 22.99 | I13: 257.83
A14: Profit Share | B14: 2677.84 | C14: 2354.01 | D14: 227.6 | E14: 1478.36 | F14: 668.24 | G14: 586.13 | H14: 87.2 | I14: 8079.38
A15: Total Non-Recurring Revenue | B15: 8942.68 | C15: 33510.51 | D15: 1562.6 | E15: 1658.36 | F15: 668.24 | G15: 609.12 | H15: 87.2 | I15: 47038.71
A16: Onboarding Revenue | I16: 0
A17: Onboarding | B17: 10210.5 | C17: 6675 | D17: 9099 | E17: 8954.5 | F17: 12606 | G17: 5411.5 | H17: 6098.5 | I17: 59055
A18: Total Onboarding Revenue | B18: 10210.5 | C18: 6675 | D18: 9099 | E18: 8954.5 | F18: 12606 | G18: 5411.5 | H18: 6098.5 | I18: 59055
A19: SMB Bookkeeping Subscription | B19: 11280.5 | C19: 10930.5 | D19: 10625.5 | E19: 10315.5 | F19: 10315.5 | G19: 9975.5 | H19: 9975.5 | I19: 73418.5
A20: STR Recurring Revenue | I20: 0
A21: Controller Services | B21: 2750 | C21: 3500 | D21: 2750 | E21: 4750 | F21: 3500 | G21: 3500 | H21: 3500 | I21: 24250
A22: Occupancy Taxes | B22: 10909.52 | C22: 10334.97 | D22: 11175 | E22: 11953.11 | F22: 15040.71 | G22: 16168.68 | H22: 16069.15 | I22: 91651.14
A23: STR Bill Pay | B23: 6300 | C23: 6390 | D23: 6425 | E23: 6080 | F23: 6325 | G23: 6655 | H23: 6955 | I23: 45130
A24: STR Bookkeeping Subscription | B24: 156538.8 | C24: 164903.4 | D24: 170344.25 | E24: 183662 | F24: 190784.4 | G24: 194406.5 | H24: 200837.5 | I24: 1261476.9
A25: Topkey Subscription | B25: 5254 | C25: 5652 | D25: 5324 | E25: 6321 | F25: 6959 | G25: 7673 | H25: 7903 | I25: 45086
A26: Total STR Recurring Revenue | B26: 181752.32 | C26: 190780.37 | D26: 196018.25 | E26: 212766.11 | F26: 222609.11 | G26: 228403.18 | H26: 235264.65 | I26: 1467594
A27: Total Income | B27: 212186 | C27: 241896.38 | D27: 231495.35 | E27: 240319.47 | F27: 246198.85 | G27: 247499.3 | H27: 251425.85 | I27: 1671021.2
A28: Cost of Goods Sold
A29: 1099 Filing Fees | B29: 2494.8 | C29: 0 | D29: 0 | E29: 709.81 | F29: 0 | G29: 0 | H29: 0 | I29: 3204.61
A30: Contract Labor - Tax | C30: 3000 | D30: 16265.5 | E30: 2800 | G30: 8450 | I30: 30515.5
A31: Direct Labor | I31: 0
A32: Bookkeeper Wages | B32: 38378.88 | C32: 29701.52 | D32: 37422.5 | E32: 38772.3 | F32: 38294.77 | G32: 40699.83 | H32: 44487.6 | I32: 267757.4
A33: Client Lead Wages | B33: 26114.9 | C33: 21905.5 | D33: 30758.44 | E33: 31590.38 | F33: 27699.92 | G33: 31240.24 | H33: 32743.71 | I33: 202053.09
A34: Occupancy Tax Specialist | B34: 1691.16 | C34: 5549.19 | D34: 7199.9 | E34: 8192.7 | F34: 8283.35 | G34: 5492.65 | H34: 5676.1 | I34: 42085.05
A35: Onboarding Team Wages | B35: 16553.94 | C35: 11526.61 | D35: 14938.83 | E35: 15583.52 | F35: 19603.4 | G35: 16644.57 | H35: 16429.12 | I35: 111279.99
A36: Sr. Client Lead Wages | F36: 2517.06 | G36: 2721.17 | H36: 2756.77 | I36: 7995
A37: Total Direct Labor | B37: 82738.88 | C37: 68682.82 | D37: 90319.67 | E37: 94138.9 | F37: 96398.5 | G37: 96798.46 | H37: 102093.3 | I37: 631170.53
A38: Occupancy Tax Filing Fees | B38: 229.4 | C38: 119.4 | D38: 179.35 | E38: 69.9 | F38: 69.9 | G38: 163.98 | H38: 707.56 | I38: 1539.49
A39: Payment Collection Fees | B39: 1229.74 | C39: 1738.47 | D39: 1353.48 | E39: 1233.99 | F39: 1171.37 | G39: 1153.92 | H39: 1145.87 | I39: 9026.84
A40: Referral Fees | B40: 1868.8 | C40: 4439.91 | D40: 2393.61 | E40: 3657.86 | F40: 2933.79 | G40: 1566.2 | H40: 3769.52 | I40: 20629.69
A41: Software & Apps - COGS | B41: 18468.3 | C41: 17920.27 | D41: 18409.06 | E41: 21387.75 | F41: 23445.84 | G41: 24674.67 | H41: 27975.68 | I41: 152281.57
A42: Software & Apps - Tax | C42: 2184.05 | D42: 1604.3 | I42: 3788.35
A43: Software & Apps - Topkey | B43: 2949.75 | C43: 3420 | D43: 3678 | E43: 4218 | F43: 4284 | G43: 5208 | H43: 5070 | I43: 28827.75
A44: Total Cost of Goods Sold | B44: 109979.67 | C44: 101504.92 | D44: 134202.97 | E44: 128216.21 | F44: 128303.4 | G44: 138015.23 | H44: 140761.93 | I44: 880984.33
A45: Gross Profit | B45: 102206.33 | C45: 140391.46 | D45: 97292.38 | E45: 112103.26 | F45: 117895.45 | G45: 109484.07 | H45: 110663.92 | I45: 790036.87
A46: Expenses
A47: General & Admin Expenses | I47: 0
A48: Bank Fees | B48: 147.1 | C48: 155.6 | D48: 170.65 | E48: 303.2 | F48: 182.85 | G48: 177.7 | H48: 303.15 | I48: 1440.25
A49: Company Meals | E49: 19.84 | I49: 19.84
A50: Computer Equipment | B50: 799.68 | C50: 868.84 | I50: 1668.52
A51: Employee Benefits | I51: 0
A52: Education and Training | B52: 16.2 | I52: 16.2
A53: Employee Equipment Allowance | B53: 648 | C53: 71 | D53: 1059 | E53: 749 | F53: 477 | G53: 582 | H53: 520 | I53: 4106
A54: Employee Internet Allowance | B54: 254 | C54: 314 | D54: 338 | E54: 290 | F54: 443 | G54: 388 | H54: 370 | I54: 2397
A55: Employee Medical Allowance | D55: 1550 | E55: 524 | F55: 223 | G55: 1282 | H55: 521 | I55: 4100
A56: Employee Referral Fees | B56: 400 | C56: 400 | D56: 1006 | G56: 800 | H56: 200 | I56: 2806
A57: Other Employee Benefits | B57: 80 | C57: 180 | D57: 1005 | E57: 180 | F57: 140 | G57: 198.6 | H57: 890 | I57: 2673.6
A58: ST/LT Disability | B58: 180.53 | C58: 180.53 | D58: 180.53 | E58: 180.53 | F58: 180.53 | G58: 180.53 | H58: 180.53 | I58: 1263.71
A59: Total Employee Benefits | B59: 1578.73 | C59: 1145.53 | D59: 5138.53 | E59: 1923.53 | F59: 1463.53 | G59: 3431.13 | H59: 2681.53 | I59: 17362.51
A60: Indirect Labor | B60: 36253.6 | C60: 33607.51 | D60: 57199.24 | E60: 58245.95 | F60: 54069.23 | G60: 60003.81 | H60: 57895.38 | I60: 357274.72
A61: Insurance | B61: 229.43 | C61: 2228.58 | D61: 254.48 | E61: 255.64 | F61: 261.64 | G61: 261.83 | H61: 218.11 | I61: 3709.71
A62: Legal & Professional Fees | I62: 0
A63: Accounting Fees | D63: 950 | I63: 950
A64: Other Professional Fees | B64: 0 | C64: 0 | D64: 6600 | E64: 14000 | F64: 18000 | G64: 0 | H64: 18950 | I64: 57550
A65: Recruiting Fees | B65: 820.3 | C65: 680.46 | D65: 772.39 | E65: 716.08 | F65: 640.2 | G65: 1135.38 | H65: 799.79 | I65: 5564.6
A66: Total Legal & Professional Fees | B66: 820.3 | C66: 680.46 | D66: 8322.39 | E66: 14716.08 | F66: 18640.2 | G66: 1135.38 | H66: 19749.79 | I66: 64064.6
A67: Office Supplies | B67: 40.03 | C67: 21.4 | E67: 57.35 | F67: 471.75 | G67: -15 | H67: 141.15 | I67: 716.68
A68: Postage | B68: 7.5 | C68: 127.41 | D68: 12.25 | E68: 22.25 | G68: 210.45 | H68: 11.41 | I68: 391.27
A69: Professional Organizations | B69: 939.83 | C69: 939.83 | D69: 939.83 | E69: 939.83 | F69: 939.83 | G69: 939.83 | H69: 939.83 | I69: 6578.81
A70: Software & Apps - AI tools | B70: 120 | C70: 120 | D70: 701.66 | E70: 2207.36 | F70: 914.87 | G70: 1151.65 | H70: 1311.98 | I70: 6527.52
A71: Software & Apps - G&A | B71: 13263.16 | C71: 14720.1 | D71: 14990.72 | E71: 14744.59 | F71: 13229.2 | G71: 13114.99 | H71: 12985.22 | I71: 97047.98
A72: State Filing Fees | C72: 102 | D72: 401 | E72: 5 | F72: 5 | G72: 5 | H72: 5 | I72: 523
A73: Utilities | B73: 253 | C73: 255 | D73: 283 | E73: 283 | F73: 283 | G73: 293 | H73: 293 | I73: 1943
A74: Total General & Admin Expenses | B74: 54452.36 | C74: 54972.26 | D74: 88413.75 | E74: 93723.62 | F74: 90461.1 | G74: 80709.77 | H74: 96535.55 | I74: 559268.41
A75: Payroll Wages - Owner | B75: 9276.21 | C75: 8322.63 | D75: 9108.83 | E75: 9108.83 | F75: 8694.81 | G75: 9108.84 | H75: 9522.87 | I75: 63143.02
A76: Sales & Marketing | I76: 0
A77: Conferences & Meetups | I77: 0
A78: C&M - Ticket/Sponsorship | H78: 11695 | I78: 11695
A79: C&M - Event Cost/Supplies | B79: 50 | F79: 98.05 | G79: 2.43 | I79: 150.48
A80: Total Conferences & Meetups | B80: 50 | C80: 0 | D80: 0 | E80: 0 | F80: 98.05 | G80: 2.43 | H80: 11695 | I80: 11845.48
A81: Sales and Marketing Wages | B81: 5653.4 | C81: 5956.89 | D81: 7782.8 | E81: 8137.01 | F81: 7808.25 | G81: 8407.2 | H81: 8195.76 | I81: 51941.31
A82: Social Media | B82: 144 | I82: 144
A83: Software & Apps | B83: 270 | C83: 270 | D83: 270 | E83: 270 | F83: 270 | G83: 270 | H83: 510 | I83: 2130
A84: Travel, Meals & Entertainment | I84: 0
A85: Accommodation | E85: 6015.1 | F85: 1357.09 | I85: 7372.19
A86: Airfare | E86: 3750 | F86: 2713.23 | I86: 6463.23
A87: Entertainment | F87: 1597.03 | I87: 1597.03
A88: Meals | F88: 4071.26 | G88: 153.18 | I88: 4224.44
A89: Transportation | F89: 515.82 | G89: 502.72 | H89: 9.99 | I89: 1028.53
A90: Total Travel, Meals & Entertainment | B90: 0 | C90: 0 | D90: 0 | E90: 9765.1 | F90: 10254.43 | G90: 655.9 | H90: 9.99 | I90: 20685.42
A91: Website | B91: 436.19 | C91: 399 | D91: 477.38 | E91: 399 | F91: 399 | G91: 399 | H91: 399 | I91: 2908.57
A92: Total Sales & Marketing | B92: 6553.59 | C92: 6625.89 | D92: 8530.18 | E92: 18571.11 | F92: 18829.73 | G92: 9734.53 | H92: 20809.75 | I92: 89654.78
A93: Total Expenses | B93: 70282.16 | C93: 69920.78 | D93: 106052.76 | E93: 121403.56 | F93: 117985.64 | G93: 99553.14 | H93: 126868.17 | I93: 712066.21
A94: Net Operating Income | B94: 31924.17 | C94: 70470.68 | D94: -8760.38 | E94: -9300.3 | F94: -90.19 | G94: 9930.93 | H94: -16204.25 | I94: 77970.66
A95: Other Income
A96: Other Miscellaneous Income | B96: 10.3 | C96: 13.8 | D96: 9.25 | E96: 61.81 | F96: 33.16 | G96: 16.14 | H96: 11.41 | I96: 155.87
A97: Total Other Income | B97: 10.3 | C97: 13.8 | D97: 9.25 | E97: 61.81 | F97: 33.16 | G97: 16.14 | H97: 11.41 | I97: 155.87
A98: Other Expenses
A99: Interest Expense | B99: 288.7 | C99: 144.53 | E99: 150 | F99: 117.69 | G99: 110.11 | I99: 811.03
A100: State Taxes | D100: 5036 | E100: -4864 | G100: 1000 | I100: 1172
A101: Total Other Expenses | B101: 288.7 | C101: 144.53 | D101: 5036 | E101: -4714 | F101: 117.69 | G101: 1110.11 | H101: 0 | I101: 1983.03
...
