Workbook
Name __CF96: #REF!
Name __CF96: #REF!
Name _apr1: #REF!
Name _apr1: #REF!
Name _apr2: #REF!
Name _apr2: #REF!
Name _aug1: #REF!
Name _AUG3: #REF!
Name _CF96: #REF!
Name _feb021: #REF!
Name _feb023: #REF!
Name _IS96: #REF!
Name _jan021: #REF!
Name _JAN023: #REF!
Name _JF1: #REF!
Name _jul1: #REF!
Name _JUL3: #REF!
Name _may1: #REF!
Name _MAY3: #REF!
Name _NOV2: #REF!
Name _OCT1: #REF!
Name _OCT3: #REF!
Name _QTR32: #REF!
Name _QTR32: #REF!
Name _yr011: #REF!
Name _yr011: #REF!
Name _YR012: #REF!
Name _YR012: #REF!
Name a: #REF!
Name amparo: #REF!
Name amparo1: #REF!
Name amparo2: #REF!
Name area1: #REF!
Name area2: #REF!
Name area3: #REF!
Name area3: #REF!
Name awqwqw: #REF!
Name CF: #REF!
Name CompName: #REF!
Name FEB01YTD1: #REF!
Name FEB01YTD1: #REF!
Name JULY2: #REF!
Name LAST: #REF!
Name mr: #REF!
Name mr: #REF!
Name new: #REF!
Name new: #REF!
Name NINE1: #REF!
Name NINE2: #REF!
Name nov1st: #REF!
Name nov2nd: #REF!
Name OK: #REF!
Name old: #REF!
Name PeriodEnd: #REF!
Name Q3ONE: #REF!
Name Q3ONE: #REF!
Name Q3TWO: #REF!
Name Q3TWO: #REF!
Name q4one: #REF!
Name q4one: #REF!

Sheet Cover
B24: Keystone Bookkeepers
B25: Pre-LOI Business Analysis
B26: ="As of "&TEXT(TODAY(),"mm/dd/yy") -> As of 09/27/26

Sheet Offer Overview
B2: Keystone Bookkeepers
B3: Offer & Equity Upside Scenarios ($000s) | G3: Print | H3: 0
B5: Offer Price | C5: Today
B6: Run-Rate Revenue (PF Jul'26) | C6: 2998.541
B7: (x) Revenue Multiple — Implied | C7: 1.0004
B8: Total Valuation | C8: =C6*C7 -> 2999.7404
B10: Offer Components | C10: Amount | D10: % Total
B11: Topkey Equity | C11: 1450 | D11: =C11/$C$14 -> 0.48333333
B12: Rolled Keystone Equity | C12: =+C14-C13-C11 -> 900 | D12: =C12/$C$14 -> 0.3
B13: Cash at Close | C13: 650 | D13: =C13/$C$14 -> 0.21666667
B14: Total Valuation | C14: 3000 | D14: =C14/$C$14 -> 1
B15: Note: Total Valuation is calculated as 1.0x run-rate July'26 recurring revenue
B17: Future Value - Partnership
B18: Topkey Equity | D18: =C18/$C$21 -> 0
B19: Rolled Keystone Equity | D19: =C19/$C$21 -> 0
B20: Cash at Close | C20: =+C13 -> 650 | D20: =C20/$C$21 -> 1
B21: Total Valuation | C21: =SUM(C18:C20) -> 650 | D21: =C21/$C$21 -> 1
B23: Future Value - Standalone
B24: Topkey Equity | C24: 0 | D24: =C24/$C$21 -> 0
B25: Keystone Equity | D25: =C25/$C$21 -> 0
B26: Cash at Close | C26: 0 | D26: =C26/$C$21 -> 0
B27: Total Valuation | C27: =SUM(C24:C26) -> 0 | D27: =C27/$C$21 -> 0
B29: Partnership vs. Standalone | C29: Variance | D29: % Change
B30: Increase in Revenue | C30: =+'Ben''s Partnership Model'!C42 -> 2993.6651
B31: Increase in Valuation | C31: =+C21-C27 -> 650
B32: Increase in Annual Net Client Wins
B33: Increase in Annual Net CFO Client Wins
B49: (-) Cash at Close | C49: 650
B50: Topkey Equity Consideration | C50: =C8-C49 -> 2349.7404
B52: Topkey Pre-Deal Valuation | C52: 50000
B53: (+) Keystone Value Acquired | C53: =$C$8 -> 2999.7404
B54: (-) Cash Paid at Close | C54: =$C$49 -> 650
B55: Topkey Post-Money Valuation | C55: =C52+C53-C54 -> 52349.74
B56: Ben's Implied Topkey Ownership % | C56: =IFERROR($C$50/$C$55,0) -> 0.044885427
B57: Keystone Enterprise Value Today | C57: =$C$8 -> 2999.7404
B58: Existing Shareholders' Value Post-Close | C58: =(1-$C$56)*$C$55 -> 50000
B60: Topkey Pre-Deal Valuation | C60: =$C$52 -> 50000
B61: (-) Cash Paid at Close | C61: =$C$54 -> 650
B62: Topkey ex-Keystone Growth Base | C62: =C60-C61 -> 49350
B64: Scenario 1 — Ben Retains 100% of Keystone | C64: Today | D64: 2.0x Valuation | E64: 3.0x Valuation
B65: Keystone Growth Multiple | C65: 1 | D65: 2 | E65: 3
B66: Keystone Enterprise Value | C66: =$C$57*C$65 -> 2999.7404 | D66: =$C$57*D$65 -> 5999.4809 | E66: =$C$57*E$65 -> 8999.2213
B67: Ben's Ownership % — Keystone | C67: 1 | D67: =$C$67 -> 1 | E67: =$C$67 -> 1
B68: Ben's Keystone Equity Value | C68: =C66*$C$67 -> 2999.7404 | D68: =D66*$C$67 -> 5999.4809 | E68: =E66*$C$67 -> 8999.2213
B69: (-) Value at Offer Today | C69: =$C$68 -> 2999.7404 | D69: =$C$68 -> 2999.7404 | E69: =$C$68 -> 2999.7404
B70: Ben's Net Gain vs. Today | C70: =C68-C69 -> 0 | D70: =D68-D69 -> 2999.7404 | E70: =E68-E69 -> 5999.4809
B72: Combined Topkey + Keystone TEV | C72: Growth (ex-Keystone) | D72: =D$64 -> 2.0x Valuation | E72: =E$64 -> 3.0x Valuation
B73: Topkey Grows Half as Fast as Keystone | C73: 0.5 | D73: =$C$62*(1+(D$65-1)*$C73)+$C$57*D$65 -> 80024.481 | E73: =$C$62*(1+(E$65-1)*$C73)+$C$57*E$65 -> 107699.22
B74: Topkey Keeps Pace with Keystone | C74: 1 | D74: =$C$62*(1+(D$65-1)*$C74)+$C$57*D$65 -> 104699.48 | E74: =$C$62*(1+(E$65-1)*$C74)+$C$57*E$65 -> 157049.22
B75: Topkey Outgrows Keystone | C75: 1.5 | D75: =$C$62*(1+(D$65-1)*$C75)+$C$57*D$65 -> 129374.48 | E75: =$C$62*(1+(E$65-1)*$C75)+$C$57*E$65 -> 206399.22
B77: Ben's Total Value — Cash + Topkey Equity | D77: =+D$72 -> 2.0x Valuation | E77: =+E$72 -> 3.0x Valuation
B78: =$B73 -> Topkey Grows Half as Fast as Keystone | D78: =$C$49+$C$56*D73 -> 4241.933 | E78: =$C$49+$C$56*E73 -> 5484.1255
B79: =$B74 -> Topkey Keeps Pace with Keystone | D79: =$C$49+$C$56*D74 -> 5349.4809 | E79: =$C$49+$C$56*E74 -> 7699.2213
B80: =$B75 -> Topkey Outgrows Keystone | D80: =$C$49+$C$56*D75 -> 6457.0288 | E80: =$C$49+$C$56*E75 -> 9914.3171
B82: Delta vs. Scenario 1 | D82: =+D$72 -> 2.0x Valuation | E82: =+E$72 -> 3.0x Valuation
B83: =$B73 -> Topkey Grows Half as Fast as Keystone | D83: =D78-D$68 -> -1757.5479 | E83: =E78-E$68 -> -3515.0958
B84: =$B74 -> Topkey Keeps Pace with Keystone | D84: =D79-D$68 -> -650 | E84: =E79-E$68 -> -1300
B85: =$B75 -> Topkey Outgrows Keystone | D85: =D80-D$68 -> 457.5479 | E85: =E80-E$68 -> 915.09581
B87: Topkey Growth Required for Parity | D87: =+D$72 -> 2.0x Valuation | E87: =+E$72 -> 3.0x Valuation
B88: Ben's Value — Scenario 1 (Retain 100%) | D88: =D$68 -> 5999.4809 | E88: =E$68 -> 8999.2213
B89: (-) Ben's Cash at Close | D89: =$C$49 -> 650 | E89: =$C$49 -> 650
B90: Required Topkey Equity Value | D90: =D88-D89 -> 5349.4809 | E90: =E88-E89 -> 8349.2213
B91: Required Combined Enterprise Value | D91: =IFERROR(D90/$C$56,0) -> 119180.8 | E91: =IFERROR(E90/$C$56,0) -> 186011.85
B92: (-) Keystone Value at Growth | D92: =$C$57*D$65 -> 5999.4809 | E92: =$C$57*E$65 -> 8999.2213
B93: Required Topkey ex-Keystone Value | D93: =D91-D92 -> 113181.31 | E93: =E91-E92 -> 177012.63
B94: Required Growth Share for Ben to Break Even | D94: =IFERROR((D93/$C$62-1)/(D$65-1),0) -> 1.293441 | E94: =IFERROR((E93/$C$62-1)/(E$65-1),0) -> 1.293441
B96: Offer & Scenario Assumptions
B97: Assumption | C97: Value | D97: Rationale
B98: Run-Rate Revenue (PF Jul'26) ($000s) | C98: =$C$6 -> 2998.541 | D98: Unrounded PF Jul'26 run-rate revenue (P&L Overview K16); same basis as the Buyout and Partnership tabs
B99: Revenue Multiple | C99: =$C$7 -> 1.0004 | D99: Implied by rounded offer ÷ PF Jul'26 run-rate revenue
B100: Total Valuation — Offer Price ($000s) | C100: =$C$8 -> 2999.7404 | D100: Rounded $3.0M offer price; Keystone value today
B101: Cash at Close ($000s) | C101: =$C$49 -> 650 | D101: Per Topkey offer; balance paid in Topkey equity
B102: Topkey Pre-Deal Valuation ($000s) | C102: =$C$52 -> 50000 | D102: Topkey stated valuation before Keystone; pending confirmation
B103: Ben's Keystone Ownership % | C103: =$C$67 -> 1 | D103: Sole owner; retains full upside in Scenario 1
B104: Topkey ex-Keystone Growth Share — Half Pace | C104: =$C$73 -> 0.5 | D104: Topkey ex-Keystone grows at half Keystone's rate
B105: Topkey ex-Keystone Growth Share — Keeps Pace | C105: =$C$74 -> 1 | D105: Topkey ex-Keystone grows at Keystone's rate
B106: Topkey ex-Keystone Growth Share — Outgrows | C106: =$C$75 -> 1.5 | D106: Default 1.5x Keystone's growth rate
B107: Valuation Growth Multiples | C107: =D$65&"x / "&E$65&"x" -> 2x / 3x | D107: Business doubles / triples in value
B108: Topkey ex-Keystone Growth Base ($000s) | C108: =$C$62 -> 49350 | D108: Pre-deal Topkey less the $650K cash paid to Ben at close
B109: Topkey Post-Money Valuation ($000s) | C109: =$C$55 -> 52349.74 | D109: Pre-deal + Keystone acquired − cash paid at close

Sheet Ben's Partnership Model
B2: Keystone Bookkeepers
B3: Partnership Rollover Scenarios ($000s) | G3: Print | H3: 0
B5: General Assumptions | C5: Value | F5: Rationale / Notes
B6: Ben's Rollover % — Keystone | C6: 0.3 | F6: Input — share of Keystone Ben keeps; Topkey buys the rest for cash + Topkey equity
B7: Horizon (Years) | C7: 5 | F7: Input — projection horizon for the Year 5 columns
B8: Est. Topkey Dilution — Ben's Stake (Year 5) | C8: 0.1 | F8: Input — future Topkey equity issuance (capital raise, option pool, acquisitions) reduces Ben's Topkey % by this share by Year 5
B9: Current Topkey Valuation | C9: 50000
B10: Topkey - Current Monthly Revenue | C10: 261.5 | F10: Based on Aug'26 financials
B11: Topkey - Current Run-Rate Revenue | C11: =C10*12 -> 3138
B12: Topkey - Current ARR Revenue Multiple | C12: =C9/C11 -> 15.933716
B13: Topkey - Future ARR Revenue Multiple | C13: =C12 -> 15.933716 | F13: Held flat at the current implied multiple
B14: Topkey - Current Client Count | C14: 325 | F14: Input — Topkey-provided client count; pending confirmation
B15: Topkey - Avg. Revenue Per Client | C15: =C11/C14 -> 9.6553846
B16: Topkey - Annual Net Client Wins | C16: ='Offer Comparison'!$C$20 -> 65 | F16: Input on Offer Comparison (C20). AMB placeholder; pending confirmation
B17: Total Net Client Wins | C17: =C16*$C$7 -> 325
B18: Total Additional Revenue | C18: =C17*C15 -> 3138
B19: ="Check - "&$C$7&" Year Topkey Valuation Growth" -> Check - 5 Year Topkey Valuation Growth | C19: =IFERROR(D80/C80-1,0) -> 1.0131712 | F19: % growth in Topkey ex-Keystone value (row 84), today → Year 5; value net of cash paid, not revenue
B21: Keystone Standalone Assumptions
B22: Revenue Multiple | C22: 1 | F22: Input — Keystone valued at 1.0x revenue today
B23: Scaled Revenue Multiple | C23: 1.25 | F23: Input — Keystone standalone revenue multiple at Year 5
B24: Avg. Revenue Per Client | C24: 16.631473 | F24: Input — Sep'26 annualized fee per non-tax client
B25: Target Monthly Net Client Wins | C25: 3 | F25: Input — Core bookkeeping net client growth: FY24 not tracked at core level; FY25 +44 (~3.7/month); LTM Sep'26 +26 (~2.2/month). See build at rows 167-172
B26: Annual Net Client Wins | C26: =C25*12 -> 36
B27: Total Net Client Wins | C27: =C26*$C$7 -> 180
B28: Total Additional Revenue | C28: =C27*C24 -> 2993.6651
B30: Keystone Partnership Assumptions
B31: Software-Integration Revenue Multiple | C31: 2 | F31: Input — revenue multiple with Topkey software integration
B32: VR Platform Run-Rate Tech Cost | C32: 240 | F32: Input — run-rate tech cost provided by Keystone; see platform-fee memo (rows 174-185)
B33: VR Platform Cost / Client
B35: =+B24 -> Avg. Revenue Per Client | C35: =+C24 -> 16.631473
B37: =+B26 -> Annual Net Client Wins | C37: =+C26 -> 36
B38: (+) Additional Annual Net Client Wins From Topkey | C38: 36
B39: Total Annual Net Client Wins | C39: =SUM(C37:C38) -> 72
B40: Total Net Client Wins | C40: =C39*$C$7 -> 360
B41: Total Additional Revenue | C41: =C40*C35 -> 5987.3303
B42: Increase in Keystone Revenue vs. Standalone | C42: =C41-C28 -> 2993.6651
B44: Cash Earnout — Year 3 Keystone Revenue (Sliding Scale)
B45: Earnout Measurement Year | C45: 3 | F45: Earnout measured on Year 3 run-rate: average of months 34–36 × 12 (window in C60)
B46: Keystone Revenue at Close | C46: =C148 -> 2998.541 | F46: PF Jul'26 run-rate revenue at close (C152)
B47: Year 3 Run-Rate Revenue Target | C47: =C46+C41*(C45-(C56-1)/2/12)/C7 -> 6491.1503 | F47: Run-rate at close + partnership added revenue ramped to the midpoint of the averaging window (month 35 ÷ 60); same basis as the earnout measurement
B48: (x) Achievement vs. Target | C48: 1 | F48: Base case assumes the model's Year 3 revenue is achieved; flex to test payout
B49: Year 3 Run-Rate Revenue — Achieved | C49: =C47*C48 -> 6491.1503
B50: Threshold — % of Target | C50: 0.8 | F50: No earnout below this share of target; payout starts at the threshold % below
B51: Target Earnout — at 100% of Target | C51: 0 | F51: Initial position does not include earnout
B52: Payout at Threshold — % of Target Earnout | C52: 0.5 | F52: Share of target earnout paid at the 80% threshold
B53: Cap — % of Target Earnout | C53: 1.5 | F53: Payout capped at 150% of target earnout, reached at 120% of target revenue (mirrors the 80% threshold)
B54: Payout % Earned | C54: =IF(C48<C50,0,MIN(C53,C52+(1-C52)*(C48-C50)/(1-C50))) -> 1 | F54: Straight line from threshold payout at 80% to 100% at target, continuing above target until the cap
B55: Maximum Earnout (Cap) | C55: =C51*C53 -> 0 | F55: Topkey's maximum earnout exposure
B56: Run-Rate Window — Months Averaged | C56: 3 | F56: Earnout measured on average monthly recurring revenue for the last 3 months of Year 3 (months 34–36) × 12; averaging prevents one strong month from triggering the payout
B57: Cash Earnout Payable — Year 3 | C57: =C51*C54 -> 0 | F57: Paid in cash by Topkey; flows into Scenario 2 (row 94) and Ben's MOIC/IRR (rows 100-101)
B58: Probability of Achievement | C58: 0.7 | F58: AMB estimate for the memo line below
B59: Discount Rate | C59: 0.15 | F59: AMB estimate for the memo line below
B60: Risk-Weighted Earnout — PV at Close (Memo) | C60: =C57*C58/(1+C59)^C45 -> 0 | F60: Memo only; not used in Scenario 2
B62: Offer Structure | C62: =C$147 -> Today | D62: % of Total
B63: Cash at Close | C63: =$C$153 -> 650 | D63: =IFERROR(C63/C$66,0) -> 0.21666667 | F63: Cash paid at close for Topkey's stake (C157)
B64: (+) Topkey Equity Issued to Ben | C64: =$C$154 -> 1450 | D64: =IFERROR(C64/C$66,0) -> 0.48333333 | F64: Topkey stock issued at the pre-deal valuation (C159); equity issued in C158
B65: (+) Ben's Rolled Keystone Equity | C65: =$C$149*$C$150 -> 900 | D65: =IFERROR(C65/C$66,0) -> 0.3 | F65: Keystone value today × Ben's rollover % (C153 × C154)
B66: Total Offer Value — at Close | C66: =SUM(C63:C65) -> 3000 | D66: =IFERROR(C66/C$66,0) -> 1 | F66: Ties to Keystone Value Today (C153)
B67: (+) Cash Earnout — Year 3 (Contingent) | C67: =$C$57 -> 0 | D67: =IFERROR(C67/C$66,0) -> 0 | F67: Paid only if Year 3 revenue target is met (C61); % shown vs. offer value at close
B68: Total Consideration incl. Earnout | C68: =C66+C67 -> 3000 | D68: =IFERROR(C68/C$66,0) -> 1
B70: Scenario 1 — Ben Retains 100% of Keystone | C70: =C$147 -> Today | D70: ="Year "&$C$7 -> Year 5
B71: Keystone Enterprise Value | C71: =ROUND(C148*C22,-1) -> 3000 | D71: =(C148+C28)*$C$23 -> 7490.2577 | F71: Today at offer value; Year 5 = (PF run-rate revenue + standalone added revenue) × standalone multiple
B72: Ben's Ownership % — Keystone | C72: 1 | D72: =$C$72 -> 1
B73: Ben's Value — Scenario 1 | C73: =C71*C72 -> 3000 | D73: =D71*D72 -> 7490.2577
B75: ="Scenario 2 — Ben Rolls "&TEXT($C$150,"0%")&" of Keystone Equity" -> Scenario 2 — Ben Rolls 30% of Keystone Equity | C75: =C$147 -> Today | D75: =D$70 -> Year 5
B76: Keystone Enterprise Value — Partnership | C76: =C149 -> 3000 | D76: =(C41+C148)*C31 -> 17971.743 | F76: Today at offer value; Year 5 = partnership revenue × software-integration multiple (C35)
B77: (x) Ben's Retained Keystone % | C77: =$C$150 -> 0.3 | D77: =$C$150 -> 0.3
B78: Ben's Keystone Equity Value | C78: =C76*C77 -> 900 | D78: =D76*D77 -> 5391.5228 | F78: Ben's retained Keystone stake (rollover % × Keystone value)
B80: Topkey ex-Keystone Value | C80: =C158 -> 49350 | D80: =($C$11+$C$18)*$C$13-$C$153-$C$57 -> 99350
B81: (+) Topkey's Share of Keystone Value | C81: =C76*$C$151 -> 2100 | D81: =D76*$C$151 -> 12580.22 | F81: Topkey's stake in Keystone is part of Topkey's value
B82: Topkey Combined Enterprise Value | C82: =C80+C81 -> 51450 | D82: =D80+D81 -> 111930.22
B83: (x) Ben's Topkey Ownership % | C83: =$C$157 -> 0.028182702 | D83: =$D$157 -> 0.025364431
B84: Ben's Topkey Equity Value | C84: =C82*C83 -> 1450 | D84: =D82*D83 -> 2839.0464 | F84: Ties to Topkey equity issued (tie-out row 164)
B85: Ben's Value by Source
B86: Keystone — Ben's Direct Retained Stake | C86: =C78 -> 900 | D86: =D78 -> 5391.5228 | F86: Keystone value Ben owns directly
B87: (+) Keystone — Ben's Indirect Share via Topkey | C87: =C81*C83 -> 59.183673 | D87: =D81*D83 -> 319.09012 | F87: Ben's Topkey % × Topkey's Keystone stake
B88: (+) Topkey ex-Keystone — Ben's Share | C88: =C80*C83 -> 1390.8163 | D88: =D80*D83 -> 2519.9563 | F88: Ben's Topkey % × Topkey's own business
B89: (+) Cash at Close | C89: =$C$153 -> 650 | D89: =$C$153 -> 650
B90: (+) Cash Earnout — Year 3 | D90: =$C$57 -> 0
B91: Ben's Value — Scenario 2 | C91: =SUM(C86:C90) -> 3000 | D91: =SUM(D86:D90) -> 8880.5692 | F91: Direct Keystone + indirect Keystone + Topkey + cash
B93: Scenario 2 vs. Scenario 1 | C93: =C$147 -> Today | D93: =D$70 -> Year 5
B94: Increase in Proceeds | C94: =C91-C73 -> 0 | D94: =D91-D73 -> 1390.3115
B95: Delta (%) | C95: 0 | D95: =IFERROR(D91/D73-1,0) -> 0.18561597
B96: Partnership MOIC — Keystone (Ben) | D96: =IFERROR(D91/C149,0) -> 2.9601897 | F96: Ben's Year 5 value (D95: cash + earnout + retained stake + Topkey stock) ÷ Keystone value given up at close (C153)
B97: Partnership IRR — Keystone (Ben) | D97: =IFERROR(IRR(D184:D189),0) -> 0.28490909 | F97: IRR on Ben's cash flows (rows 188-193); Year 5 = stake values, not a cash exit
B98: Break-Even Topkey Value CAGR (ex-Keystone, Net of Cash) | C98: 0 | D98: =MAX(0,IFERROR(((C111+$C$57)/$C$158)^(1/$C$7)-1,0)) -> 0 | F98: Topkey value CAGR needed for Scenario 2 to equal Scenario 1 (from required value in C115, before earnout paid); floored at zero
B99: Estimated Topkey Value CAGR (ex-Keystone, Net of Cash) | C99: 0 | D99: =IFERROR(((D80+$C$57)/$C$158)^(1/$C$7)-1,0) -> 0.15020736
B101: Where Ben's Year 5 Value Comes From | C101: ="Year "&$C$7 -> Year 5 | D101: % of Total | F101: Split of Ben's Scenario 2 value
B102: Ben's Retained Keystone Value | C102: =D78 -> 5391.5228 | D102: =IFERROR(C102/C$106,0) -> 0.60711455 | F102: Ben's retained Keystone stake at the partnership multiple (D79)
B103: (+) Ben's Share of Topkey ex-Keystone Value | C103: =D80*$D$157 -> 2519.9563 | D103: =IFERROR(C103/C$106,0) -> 0.28376067 | F103: Ben's Topkey % × Topkey's own Year 5 value
B104: (+) Ben's Share of Topkey's Keystone Stake | C104: =D81*$D$157 -> 319.09012 | D104: =IFERROR(C104/C$106,0) -> 0.035931269 | F104: Ben's Topkey % × Topkey's Keystone stake
B105: (+) Cash at Close + Earnout | C105: =D89+D90 -> 650 | D105: =IFERROR(C105/C$106,0) -> 0.073193507 | F105: Cash at close (D90) + Year 3 earnout (D91)
B106: Ben's Value — Scenario 2 | C106: =SUM(C102:C105) -> 8880.5692 | D106: =SUM(D102:D105) -> 1 | F106: Ties to D92
B107: Ben's Value per 1.0x of Partnership Multiple | C107: =(C41+C148)*($C$150+$C$151*$D$157) -> 2855.3065 | F107: Year 5 partnership revenue × (retained % + Topkey stake % × Ben's Topkey %)
B109: Break-Even Stress Tests | C109: Break-Even | D109: Base Case
B110: Partnership Revenue Multiple | C110: =IFERROR((D73-D89-D90-D80*$D$157)/(($C$150+$C$151*$D$157)*(C41+C148)),0) -> 1.513078 | D110: =C31 -> 2 | F110: Keystone partnership multiple at which Scenario 2 equals Scenario 1
B111: Required Topkey ex-Keystone Value — Year 5 | C111: =MAX(0,(D73-D89-D90-D78)/$D$157-D81) -> 44536.571 | D111: =D80 -> 99350 | F111: Topkey Year 5 value needed to break even; zero means not needed
B112: Topkey Future Revenue Multiple | C112: =IFERROR((C111+$C$153+$C$57)/($C$11+$C$18),0) -> 7.1998997 | D112: =$C$13 -> 15.933716 | F112: Multiple at which the offer breaks even (flat multiple assumed in base)
B113: Topkey Annual Net Client Wins | C113: =IFERROR(((C111+$C$153+$C$57)/$C$13-$C$11)/$C$15/C7,0) -> -6.2574581 | D113: =$C$16 -> 65 | F113: Net wins per year at which the offer breaks even. Base is an AMB placeholder
B114: Topkey Value CAGR (ex-Keystone, Net of Cash) | C114: =D98 -> 0 | D114: =D99 -> 0.15020736 | F114: Break-even vs. estimated (rows 102-103); growth in Topkey's value vs. today's valuation, not revenue growth
...

Sheet Condensed P&L
A1: Topkey, Inc.
A2: Profit and Loss
A3: For the month ended August, 2026
B5: Jan 2023 | C5: Feb 2023 | D5: Mar 2023 | E5: Apr 2023 | F5: May 2023 | G5: Jun 2023 | H5: Jul 2023 | I5: Aug 2023 | J5: Sep 2023 | K5: Oct 2023 | L5: Nov 2023 | M5: Dec 2023 | N5: Jan 2024 | O5: Feb 2024 | P5: Mar 2024 | Q5: Apr 2024 | R5: May 2024 | S5: Jun 2024 | T5: Jul 2024 | U5: Aug 2024 | V5: Sep 2024 | W5: Oct 2024 | X5: Nov 2024 | Y5: Dec 2024 | Z5: Jan 2025 | AA5: Feb 2025 | AB5: Mar 2025 | AC5: Apr 2025 | AD5: May 2025 | AE5: Jun 2025 | AF5: Jul 2025 | AG5: Aug 2025 | AH5: Sep 2025 | AI5: Oct 2025 | AJ5: Nov 2025 | AK5: Dec 2025 | AL5: Jan 2026 | AM5: Feb 2026 | AN5: Mar 2026 | AO5: Apr 2026 | AP5: May 2026 | AQ5: Jun 2026 | AR5: Jul 2026 | AS5: Aug 2026 | AT5: YTD 2026 | AU5: 2025
A6: Income
A7: Customer Platform Fee - Revenue | B7: 0 | C7: 0 | D7: 0 | E7: 0 | F7: 0 | G7: 0 | H7: 0 | I7: 2964.93 | J7: 3441.94 | K7: 4592.17 | L7: 8712.13 | M7: 13095.5 | N7: 18089.37 | O7: 21184.19 | P7: 25553.9 | Q7: 24988.4 | R7: 24939.4 | S7: 29681.83 | T7: 30558.73 | U7: 31772.21 | V7: 34937.13 | W7: 34861.03 | X7: 36603.28 | Y7: 40226.09 | Z7: 47634.09 | AA7: 50486.44 | AB7: 63798.6 | AC7: 69443.49 | AD7: 71040.58 | AE7: 79098.82 | AF7: 85201.02 | AG7: 85244.04 | AH7: 100429.94 | AI7: 107351.74 | AJ7: 110416.22 | AK7: 125776.14 | AL7: 133115.98 | AM7: 137271.13 | AN7: 149658.79 | AO7: 154471.08 | AP7: 159780.56 | AQ7: 179120.57 | AR7: 203261.24 | AS7: 212201.09 | AT7: 1328880.4 | AU7: 995921.12
A8: Implementation Fees | B8: 0 | C8: 0 | D8: 0 | E8: 0 | F8: 0 | G8: 0 | H8: 0 | I8: 0 | J8: 0 | K8: 0 | L8: 0 | M8: 0 | N8: 0 | O8: 0 | P8: 0 | Q8: 0 | R8: 0 | S8: 0 | T8: 0 | U8: 0 | V8: 0 | W8: 0 | X8: 0 | Y8: 0 | Z8: 126.92 | AA8: 265.38 | AB8: 384.62 | AC8: 604.31 | AD8: 654.31 | AE8: 801.23 | AF8: 876.23 | AG8: 1053.15 | AH8: 1186.79 | AI8: 1475.48 | AJ8: 1713.94 | AK8: 1779.33 | AL8: 1867.79 | AM8: 1871.63 | AN8: 2294.71 | AO8: 2508.33 | AP8: 3149.94 | AQ8: 2511.71 | AR8: 2497.48 | AS8: 2568.63 | AT8: 19270.22 | AU8: 10921.69
A9: Interchange Revenue - AMEX | B9: 0 | C9: 0 | D9: 0 | E9: 0 | F9: 0 | G9: 0 | H9: 0 | I9: 0 | J9: 0 | K9: 0 | L9: 0 | M9: 0 | N9: 0 | O9: 0 | P9: 0 | Q9: 0 | R9: 0 | S9: 0 | T9: 0 | U9: 0 | V9: 0 | W9: 0 | X9: 0 | Y9: 0 | Z9: 0 | AA9: 0 | AB9: 0 | AC9: 0 | AD9: 0 | AE9: 0 | AF9: 0 | AG9: 0 | AH9: 0 | AI9: 0 | AJ9: 0 | AK9: 0 | AL9: 0 | AM9: 0 | AN9: 0 | AO9: 0 | AP9: 0 | AQ9: 0 | AR9: 8134.58 | AS9: 0 | AT9: 8134.58 | AU9: 0
A10: Interchange Share - Topkey | B10: 135.2 | C10: 261.48 | D10: 1317.57 | E10: 2070.4 | F10: 2114.53 | G10: 3267.79 | H10: 4339.31 | I10: 6467.25 | J10: 6648.08 | K10: 8248.23 | L10: 8771.72 | M10: -38811.91 | N10: 12769.28 | O10: 16478.9 | P10: 18637.52 | Q10: 20532.37 | R10: 22739.95 | S10: 23382.47 | T10: 26033.3 | U10: 29459.13 | V10: 25779.82 | W10: 26287.6 | X10: 25803.15 | Y10: 27760.46 | Z10: 33608.01 | AA10: 29675.68 | AB10: 35213.78 | AC10: 36939.21 | AD10: 39085.7 | AE10: 36427.74 | AF10: 44250.65 | AG10: 45918.22 | AH10: 42126.21 | AI10: 42006.24 | AJ10: 36722.11 | AK10: 51189.95 | AL10: 51748.98 | AM10: 52865.02 | AN10: 61141.18 | AO10: 63756.3 | AP10: 64086.66 | AQ10: 67902.07 | AR10: 68489.46 | AS10: 63912.68 | AT10: 493902.35 | AU10: 473163.5
A11: Contra Interchange Share | B11: 0 | C11: 0 | D11: 0 | E11: 0 | F11: 0 | G11: 0 | H11: 0 | I11: 0 | J11: 0 | K11: 0 | L11: 0 | M11: -50255.02 | N11: -12769 | O11: -14581 | P11: -17079 | Q11: -19313 | R11: -20735 | S11: -21576 | T11: -24561 | U11: -27348 | V11: -23678 | W11: -24265 | X11: -23674.94 | Y11: -42095.37 | Z11: -28649.48 | AA11: -21384.94 | AB11: -31827.62 | AC11: -33976.97 | AD11: -29041.63 | AE11: -34882.34 | AF11: -42616.89 | AG11: -41763.49 | AH11: -33072.73 | AI11: -38846.08 | AJ11: -35394.95 | AK11: -44157.49 | AL11: -44244.5 | AM11: -40994.38 | AN11: -47407.6 | AO11: -49195.06 | AP11: -50991.46 | AQ11: -51624.59 | AR11: -54391.74 | AS11: -49152.17 | AT11: -388001.5 | AU11: -415614.61
A12: Total Interchange Share - Topkey | B12: 135.2 | C12: 261.48 | D12: 1317.57 | E12: 2070.4 | F12: 2114.53 | G12: 3267.79 | H12: 4339.31 | I12: 6467.25 | J12: 6648.08 | K12: 8248.23 | L12: 8771.72 | M12: -38811.91 | N12: 0.28 | O12: 1897.9 | P12: 1558.52 | Q12: 1219.37 | R12: 2004.95 | S12: 1806.47 | T12: 1472.3 | U12: 2111.13 | V12: 2101.82 | W12: 2022.6 | X12: 2128.21 | Y12: -14334.91 | Z12: 4958.53 | AA12: 8290.74 | AB12: 3386.16 | AC12: 2962.24 | AD12: 10044.07 | AE12: 1545.4 | AF12: 1633.76 | AG12: 4154.73 | AH12: 9053.48 | AI12: 3160.16 | AJ12: 1327.16 | AK12: 7032.46 | AL12: 7504.48 | AM12: 11870.64 | AN12: 13733.58 | AO12: 14561.24 | AP12: 13095.2 | AQ12: 16277.48 | AR12: 14097.72 | AS12: 14760.51 | AT12: 105900.85 | AU12: 57548.89
A13: Operating Interest Income | B13: 0 | C13: 0 | D13: 0 | E13: 0 | F13: 0 | G13: 0 | H13: 0 | I13: 0 | J13: 0 | K13: 0 | L13: 0 | M13: 0 | N13: 0 | O13: 0 | P13: 0 | Q13: 0 | R13: 0 | S13: 0 | T13: 0 | U13: 0 | V13: 0 | W13: 0 | X13: 0 | Y13: 0 | Z13: 9045.22 | AA13: 8878.46 | AB13: 8678.27 | AC13: 10880.59 | AD13: 12861.95 | AE13: 15553.39 | AF13: 17422.54 | AG13: 22961.15 | AH13: 24701.44 | AI13: 18056.34 | AJ13: 17173.84 | AK13: 15651.18 | AL13: 13741.14 | AM13: 16372.14 | AN13: 15465.63 | AO13: 19055.24 | AP13: 19664.68 | AQ13: 21848.02 | AR13: 24995.1 | AS13: 31986.15 | AT13: 163128.1 | AU13: 181864.37
A14: Total Revenue | B14: 135.2 | C14: 261.48 | D14: 1317.57 | E14: 2070.4 | F14: 2114.53 | G14: 3267.79 | H14: 4339.31 | I14: 9432.18 | J14: 10090.02 | K14: 12840.4 | L14: 17483.85 | M14: -25716.41 | N14: 18089.65 | O14: 23082.09 | P14: 27112.42 | Q14: 26207.77 | R14: 26944.35 | S14: 31488.3 | T14: 32031.03 | U14: 33883.34 | V14: 37038.95 | W14: 36883.63 | X14: 38731.49 | Y14: 25891.18 | Z14: 61764.76 | AA14: 67921.02 | AB14: 76247.65 | AC14: 83890.63 | AD14: 94600.91 | AE14: 96998.84 | AF14: 105133.55 | AG14: 113413.07 | AH14: 135371.65 | AI14: 130043.72 | AJ14: 130631.16 | AK14: 150239.11 | AL14: 156229.39 | AM14: 167385.54 | AN14: 181152.71 | AO14: 190595.89 | AP14: 195690.38 | AQ14: 219757.78 | AR14: 252986.12 | AS14: 261516.38 | AT14: 1625314.2 | AU14: 1246256.1
A15: Cost of Goods Sold | M15: 0 | N15: 1762.03 | O15: 8164.9 | P15: 6045.75 | Q15: 5884.61 | R15: 6032.76 | S15: 6565.42 | T15: 5865.95 | U15: 5222.5 | V15: 5576.1 | W15: 5731.87 | X15: 6082.66 | Y15: 6283.77 | Z15: 12555.58 | AA15: 10728.93 | AB15: 13506.71 | AC15: 13785.76 | AD15: 15133.23 | AE15: 14820.05 | AF15: 19832.55 | AG15: 19724.73 | AH15: 22963.42 | AI15: 21069.45 | AJ15: 20882.85 | AK15: 20993.31 | AL15: 22418.19 | AM15: 21117.04 | AN15: 22635.94 | AO15: 23078.3 | AP15: 23901.23 | AQ15: 24059.21 | AR15: 25625.39 | AS15: 26236.49 | AT15: 189071.79 | AU15: 205996.57
A16: Gross Profit | B16: 135.2 | C16: 261.48 | D16: 1317.57 | E16: 2070.4 | F16: 2114.53 | G16: 3267.79 | H16: 4339.31 | I16: 9432.18 | J16: 10090.02 | K16: 12840.4 | L16: 17483.85 | M16: -25716.41 | N16: 16327.62 | O16: 14917.19 | P16: 21066.67 | Q16: 20323.16 | R16: 20911.59 | S16: 24922.88 | T16: 26165.08 | U16: 28660.84 | V16: 31462.85 | W16: 31151.76 | X16: 32648.83 | Y16: 19607.41 | Z16: 49209.18 | AA16: 57192.09 | AB16: 62740.94 | AC16: 70104.87 | AD16: 79467.68 | AE16: 82178.79 | AF16: 85301 | AG16: 93688.34 | AH16: 112408.23 | AI16: 108974.27 | AJ16: 109748.31 | AK16: 129245.8 | AL16: 133811.2 | AM16: 146268.5 | AN16: 158516.77 | AO16: 167517.59 | AP16: 171789.15 | AQ16: 195698.57 | AR16: 227360.73 | AS16: 235279.89 | AT16: 1436242.4 | AU16: 1040259.5
A18: Operating Expenses
A19: Personnel | B19: 26996.64 | C19: 25199.36 | D19: 16690.42 | E19: 32072.55 | F19: 58139.65 | G19: 56525.89 | H19: 52094.4 | I19: 41179.64 | J19: 44182.22 | K19: 46570.86 | L19: 32655.49 | M19: 63594.62 | N19: 56935.52 | O19: 58842.55 | P19: 59021.71 | Q19: 58903.41 | R19: 95941.7 | S19: 64429.87 | T19: 79591.57 | U19: 83469.76 | V19: 78799.31 | W19: 72583.64 | X19: 94251.31 | Y19: 79983.68 | Z19: 88098.15 | AA19: 111545.07 | AB19: 94617.1 | AC19: 116343.01 | AD19: 120406.67 | AE19: 116916.48 | AF19: 113732.56 | AG19: 156380.56 | AH19: 143198.3 | AI19: 117971.66 | AJ19: 147759 | AK19: 170966.44 | AL19: 145774.2 | AM19: 128955.32 | AN19: 155547.48 | AO19: 160134.68 | AP19: 153570.33 | AQ19: 151976.51 | AR19: 149483.09 | AS19: 159372.43 | AT19: 1204814 | AU19: 1497935
A20: Professional & Other Services | B20: 28231.56 | C20: 28110.76 | D20: 53083.12 | E20: 29433.31 | F20: 41370.43 | G20: 42673.81 | H20: 60062.77 | I20: 56208.52 | J20: 57859.86 | K20: 55752.11 | L20: 54126.76 | M20: 63425.01 | N20: 60043.59 | O20: 51244.87 | P20: 44939.41 | Q20: 51595.66 | R20: 51556.73 | S20: 50645.2 | T20: 59702.05 | U20: 51472.05 | V20: 59848.05 | W20: 59065.05 | X20: 58230.3 | Y20: 83261.52 | Z20: 51021.73 | AA20: 55469.82 | AB20: 73605.8 | AC20: 65540.3 | AD20: 58845.3 | AE20: 69511.45 | AF20: 103903.8 | AG20: 74193.3 | AH20: 66966.3 | AI20: 71369.3 | AJ20: 88436.8 | AK20: 113061.76 | AL20: 78788.06 | AM20: 71422.2 | AN20: 77643.63 | AO20: 78073.65 | AP20: 80965.59 | AQ20: 84513.34 | AR20: 70857.17 | AS20: 65389.36 | AT20: 607653 | AU20: 891925.66
A21: General & Administrative Expenses | B21: 4209.26 | C21: 5976.39 | D21: 20985.52 | E21: 17292.07 | F21: 16789.84 | G21: 20837.73 | H21: 12846.41 | I21: 13789.59 | J21: 11901.22 | K21: 17980.22 | L21: 14356.61 | M21: 21523.38 | N21: 20665.24 | O21: 8095.46 | P21: 14564.28 | Q21: 18472 | R21: 25789.83 | S21: 17751.24 | T21: 29244.41 | U21: 13760.17 | V21: 29976.1 | W21: 25652.27 | X21: 20577.7 | Y21: 33015.78 | Z21: 25330.08 | AA21: 25538.53 | AB21: 36041.05 | AC21: 24107.14 | AD21: 44449.41 | AE21: 36695.62 | AF21: 40107.18 | AG21: 27254.81 | AH21: 50799.13 | AI21: 45464.07 | AJ21: 33007.12 | AK21: 53186.26 | AL21: 61269.04 | AM21: 55468.76 | AN21: 50052.16 | AO21: 40308.41 | AP21: 23001.25 | AQ21: 49673.43 | AR21: 40106.72 | AS21: 41056.15 | AT21: 360935.92 | AU21: 441980.4
A22: Other Operating Expenses | B22: 1911.16 | C22: 4898.83 | D22: 1364.74 | E22: 17802.68 | F22: 1334.92 | G22: 9881.05 | H22: 1389.74 | I22: 2960.06 | J22: 5012.51 | K22: 5314.06 | L22: 7043.13 | M22: 12267.81 | N22: 20309.48 | O22: 9665.45 | P22: 12444.16 | Q22: 4498.2 | R22: 11675.39 | S22: 11832.65 | T22: 3700.92 | U22: 7423.43 | V22: 3082.82 | W22: 7344.55 | X22: 6990.99 | Y22: 1514.39 | Z22: 12902.26 | AA22: 1794.87 | AB22: 4687.89 | AC22: 3587.56 | AD22: 3441.46 | AE22: 4529.3 | AF22: 9737.83 | AG22: 5672.93 | AH22: 3576.23 | AI22: 2633.15 | AJ22: 3447.48 | AK22: 1726.02 | AL22: 3885.85 | AM22: 2358.98 | AN22: 1801.28 | AO22: 801.72 | AP22: 2044.55 | AQ22: 3227.73 | AR22: 1847.95 | AS22: 1750.38 | AT22: 17718.44 | AU22: 57736.98
A24: Total Operating Expenses | B24: 61348.62 | C24: 64185.34 | D24: 92123.8 | E24: 96600.61 | F24: 117634.84 | G24: 129918.48 | H24: 126393.32 | I24: 114137.81 | J24: 118955.81 | K24: 125617.25 | L24: 108181.99 | M24: 160810.82 | N24: 157953.83 | O24: 127848.33 | P24: 130969.56 | Q24: 133469.27 | R24: 184963.65 | S24: 144658.96 | T24: 172238.95 | U24: 156125.41 | V24: 171706.28 | W24: 164645.51 | X24: 180050.3 | Y24: 197775.37 | Z24: 177352.22 | AA24: 194348.29 | AB24: 208951.84 | AC24: 209578.01 | AD24: 227142.84 | AE24: 227652.85 | AF24: 267481.37 | AG24: 263501.6 | AH24: 264539.96 | AI24: 237438.18 | AJ24: 272650.4 | AK24: 338940.48 | AL24: 289717.15 | AM24: 258205.26 | AN24: 285044.55 | AO24: 279318.46 | AP24: 259581.72 | AQ24: 289391.01 | AR24: 262294.93 | AS24: 267568.32 | AT24: 2191121.4 | AU24: 2889578
A25: EBITDA | B25: -61213.42 | C25: -63923.86 | D25: -90806.23 | E25: -94530.21 | F25: -115520.31 | G25: -126650.69 | H25: -122054.01 | I25: -104705.63 | J25: -108865.79 | K25: -112776.85 | L25: -90698.14 | M25: -186527.23 | N25: -141626.21 | O25: -112931.14 | P25: -109902.89 | Q25: -113146.11 | R25: -164052.06 | S25: -119736.08 | T25: -146073.87 | U25: -127464.57 | V25: -140243.43 | W25: -133493.75 | X25: -147401.47 | Y25: -178167.96 | Z25: -128143.04 | AA25: -137156.2 | AB25: -146210.9 | AC25: -139473.14 | AD25: -147675.16 | AE25: -145474.06 | AF25: -182180.37 | AG25: -169813.26 | AH25: -152131.73 | AI25: -128463.91 | AJ25: -162902.09 | AK25: -209694.68 | AL25: -155905.95 | AM25: -111936.76 | AN25: -126527.78 | AO25: -111800.87 | AP25: -87792.57 | AQ25: -93692.44 | AR25: -34934.2 | AS25: -32288.43 | AT25: -754879 | AU25: -1849318.5
A27: Interest, Taxes, Depreciation & Amortization | B27: 0 | C27: 0 | D27: 1328805 | E27: 825 | F27: 0 | G27: 0 | H27: 0 | I27: 0 | J27: 0 | K27: 0 | L27: 0 | M27: 9073.51 | N27: 1987.3 | O27: 4622.56 | P27: 2095.65 | Q27: 3220.64 | R27: 2070.63 | S27: 2070.62 | T27: 2445.61 | U27: 2117.18 | V27: 2217.19 | W27: 3394.68 | X27: 3120.7 | Y27: 2234.68 | Z27: 2234.68 | AA27: 4026 | AB27: 1257.89 | AC27: 1650.42 | AD27: 500.41 | AE27: 500.41 | AF27: 500.41 | AG27: 4419.3 | AH27: 4528.68 | AI27: 4644.67 | AJ27: 4572.24 | AK27: 4850.73 | AL27: 7750.42 | AM27: 5345.29 | AN27: 4900.42 | AO27: 6473.71 | AP27: 4900.42 | AQ27: 4773.71 | AR27: 4900.42 | AS27: 5000.42 | AT27: 44044.81 | AU27: 33685.84
A28: Operating Income (Loss) | B28: -61213.42 | C28: -63923.86 | D28: -1419611.2 | E28: -95355.21 | F28: -115520.31 | G28: -126650.69 | H28: -122054.01 | I28: -104705.63 | J28: -108865.79 | K28: -112776.85 | L28: -90698.14 | M28: -195600.74 | N28: -143613.51 | O28: -117553.7 | P28: -111998.54 | Q28: -116366.75 | R28: -166122.69 | S28: -121806.7 | T28: -148519.48 | U28: -129581.75 | V28: -142460.62 | W28: -136888.43 | X28: -150522.17 | Y28: -180402.64 | Z28: -130377.72 | AA28: -141182.2 | AB28: -147468.79 | AC28: -141123.56 | AD28: -148175.57 | AE28: -145974.47 | AF28: -182680.78 | AG28: -174232.56 | AH28: -156660.41 | AI28: -133108.58 | AJ28: -167474.33 | AK28: -214545.41 | AL28: -163656.37 | AM28: -117282.05 | AN28: -131428.2 | AO28: -118274.58 | AP28: -92692.99 | AQ28: -98466.15 | AR28: -39834.62 | AS28: -37288.85 | AT28: -798923.81 | AU28: -1883004.4
A30: Other Income | B30: 2365.48 | C30: 2140.12 | D30: 5771.04 | E30: 12188.38 | F30: 14108.62 | G30: 16084.31 | H30: 19328.48 | I30: 16211.08 | J30: 15571.01 | K30: 15509.79 | L30: 19737.4 | M30: 20697.51 | N30: 15584.31 | O30: 13807.27 | P30: 14226.52 | Q30: 16360.45 | R30: 14867.77 | S30: 15766.29 | T30: 18103.7 | U30: 16947.05 | V30: 16719.07 | W30: 14915.06 | X30: 13378.36 | Y30: 12654.88 | Z30: 3081.79 | AA30: 3207.46 | AB30: 2974.96 | AC30: 3453.99 | AD30: 6922.21 | AE30: 1679.2 | AF30: 474.32 | AG30: 2553.27 | AH30: 3044.56 | AI30: 4350.84 | AJ30: 4519.59 | AK30: 2068.21 | AL30: 3681.49 | AM30: 3137.78 | AN30: 4206.68 | AO30: 3375.3 | AP30: 2978.98 | AQ30: 3873.66 | AR30: 2623.04 | AS30: 3725.1 | AT30: 27602.03 | AU30: 38330.4
A31: Other Expenses | M31: 0 | N31: 0 | O31: 0 | P31: 0 | Q31: 0 | R31: 0 | S31: 34.58 | T31: 0 | U31: 41.32 | V31: 0 | W31: 0 | X31: 0 | Y31: 0 | Z31: 0 | AA31: 0 | AB31: 0 | AC31: 0 | AD31: 0 | AE31: 0 | AF31: 0 | AG31: 0 | AH31: 0 | AI31: 0 | AJ31: 0 | AK31: 0 | AL31: 0 | AM31: 0 | AN31: 0 | AO31: 0 | AP31: 0 | AQ31: 0 | AR31: 0 | AS31: 0 | AT31: 0 | AU31: 0
A32: Net Income (Loss) | B32: -58847.94 | C32: -61783.74 | D32: -1413840.2 | E32: -83166.83 | F32: -101411.69 | G32: -110566.38 | H32: -102725.53 | I32: -88494.55 | J32: -93294.78 | K32: -97267.06 | L32: -70960.74 | M32: -174903.23 | N32: -128029.2 | O32: -103746.43 | P32: -97772.02 | Q32: -100006.3 | R32: -151254.92 | S32: -106074.99 | T32: -130415.78 | U32: -112676.02 | V32: -125741.55 | W32: -121973.37 | X32: -137143.81 | Y32: -167747.76 | Z32: -127295.93 | AA32: -137974.74 | AB32: -144493.83 | AC32: -137669.57 | AD32: -141253.36 | AE32: -144295.27 | AF32: -182206.46 | AG32: -171679.29 | AH32: -153615.85 | AI32: -128757.74 | AJ32: -162954.74 | AK32: -212477.2 | AL32: -159974.88 | AM32: -114144.27 | AN32: -127221.52 | AO32: -114899.28 | AP32: -89714.01 | AQ32: -94592.49 | AR32: -37211.58 | AS32: -33563.75 | AT32: -771321.78 | AU32: -1844674
A35: Check Balance | B35: 0 | C35: 0 | D35: 0 | E35: 0 | F35: 0 | G35: 0 | H35: 0 | I35: 0 | J35: 0 | K35: 0 | L35: 0 | M35: 0 | N35: 0 | O35: 0 | P35: 0 | Q35: -670.66 | R35: -5 | S35: 0 | T35: 0 | U35: 0 | V35: 0 | W35: 0 | X35: 0 | Y35: 0 | Z35: 0 | AA35: 0 | AB35: 0 | AC35: 0 | AD35: 0 | AE35: 0 | AF35: 0 | AG35: 0 | AH35: 0 | AI35: 0 | AJ35: 0 | AK35: 0 | AL35: 0 | AM35: 0 | AN35: 0 | AO35: 0 | AP35: 0 | AQ35: 0 | AR35: 5.8207661e-11 | AS35: -5.8207661e-11
A37: Total Cash at End of Period | N37: 4394800.4 | O37: 4349809.8 | P37: 4168717 | Q37: 4061391.4 | R37: 3855622.6 | S37: 3723791 | T37: 3666813.7 | U37: 3504737.6 | V37: 3434417 | W37: 3356034.6 | X37: 3207939.8 | Y37: 3058500.5 | Z37: 2939136.8 | AA37: 2857256 | AB37: 2609063.5 | AC37: 2630200.5 | AD37: 2985816 | AE37: 2843294.9 | AF37: 3305383.5 | AG37: 3417314 | AH37: 3548725.8 | AI37: 3273845.2 | AJ37: 3233279.3 | AK37: 3061884.5 | AL37: 2801240.4 | AM37: 2691873.6 | AN37: 2639816.1 | AO37: 2534741.6 | AP37: 2264014.6 | AQ37: 2707565.8 | AR37: 2687899.9 | AS37: 2521756.4
A38: Unrestricted cash at end of Period * | N38: 4354800.4 | O38: 4309809.8 | P38: 4128717 | Q38: 4021391.4 | R38: 3815622.6 | S38: 3683791 | T38: 3626813.7 | U38: 3464737.6 | V38: 3394417 | W38: 3316034.6 | X38: 3167939.8 | Y38: 3018500.5 | Z38: 2899136.8 | AA38: 2817256 | AB38: 2569063.5 | AC38: 2590200.5 | AD38: 2945816 | AE38: 2803294.9 | AF38: 3265383.5 | AG38: 2877314 | AH38: 3008725.8 | AI38: 2733845.2 | AJ38: 2693279.3 | AK38: 2521884.5 | AL38: 2261240.4 | AM38: 2151873.6 | AN38: 2099816.1 | AO38: 1994741.6 | AP38: 1724014.6 | AQ38: 2167565.8 | AR38: 2147899.9 | AS38: 1981756.4
A39: Cash burn *** | N39: 142600.6 | O39: 44990.95 | P39: 181092.49 | Q39: 107325.02 | R39: 205768.42 | S39: 131832.02 | T39: 56977.29 | U39: 162075.79 | V39: 70320.64 | W39: 78382.35 | X39: 148094.84 | Y39: 149439.31 | Z39: 119363.66 | AA39: 81880.81 | AB39: 248192.5 | AC39: 78862.98 | AD39: 394384.48 | AE39: 142521.13 | AF39: 77911.43 | AG39: 388069.51 | AH39: -131411.79 | AI39: 274880.52 | AJ39: 40565.97 | AK39: 171394.82 | AL39: 260644.05 | AM39: 110519.45 | AN39: 52057.49 | AO39: 105074.45 | AP39: 270727.05 | AQ39: 3399.93 | AR39: 19665.88 | AS39: 166143.51
A40: Normalized Cash Burn (3 month average) | N40: 142600.6 | O40: 93795.775 | P40: 122894.68 | Q40: 111136.15 | R40: 164728.64 | S40: 148308.49 | T40: 131525.91 | U40: 116961.7 | V40: 96457.907 | W40: 103592.93 | X40: 98932.61 | Y40: 125305.5 | Z40: 138965.94 | AA40: 116894.59 | AB40: 149812.32 | AC40: 136312.1 | AD40: 240479.99 | AE40: 205256.2 | AF40: 204939.01 | AG40: 202834.02 | AH40: 111523.05 | AI40: 177179.41 | AJ40: 61344.9 | AK40: 162280.44 | AL40: 157534.95 | AM40: 180852.77 | AN40: 141073.66 | AO40: 89217.13 | AP40: 142619.66 | AQ40: 126400.48 | AR40: 97930.953 | AS40: 63069.773
A41: Cash runway **** | N41: 30.538444 | O41: 45.948869 | P41: 33.595572 | Q41: 36.184367 | R41: 23.163079 | S41: 24.838706 | T41: 27.574899 | U41: 29.622839 | V41: 35.190655 | W41: 32.010241 | X41: 32.021189 | Y41: 24.08913 | Z41: 20.862212 | AA41: 24.100824 | AB41: 17.148546 | AC41: 19.001986 | AD41: 12.249735 | AE41: 13.657541 | AF41: 15.93344 | AG41: 14.185559 | AH41: 26.97851 | AI41: 15.429813 | AJ41: 43.903882 | AK41: 15.540286 | AL41: 14.353897 | AM41: 11.898483 | AN41: 14.884536 | AO41: 22.358281 | AP41: 12.088197 | AQ41: 17.148399 | AR41: 21.932799 | AS41: 31.421651
A43: Net Quick Assets ** | N43: 4847670.5 | O43: 4744076.3 | P43: 4646456.6 | Q43: 4546603 | R43: 4395501.4 | S43: 4289579.4 | T43: 4157640 | U43: 4045163.1 | V43: 3912791.3 | W43: 3791134.8 | X43: 3654307.6 | Y43: 3486876.4 | Z43: 3354809.6 | AA43: 3217292.7 | AB43: 3071726.2 | AC43: 3034557.1 | AD43: 3643804.1 | AE43: 3504545.2 | AF43: 3857927.2 | AG43: 3683493.9 | AH43: 3530500.1 | AI43: 3399057.8 | AJ43: 3233147.3 | AK43: 3016112.4 | AL43: 2857583 | AM43: 2745563.7 | AN43: 2619314.6 | AO43: 2505387.6 | AP43: 2416645.9 | AQ43: 2323025.8 | AR43: 2286786.6 | AS43: 2254195.1
A44: Increase (Decrease) in Quick Assets | Y44: -167431.18 | Z44: -132066.84 | AA44: -137516.84 | AB44: -145566.51 | AC44: -37169.15 | AD44: 609247.05 | AE44: -139258.86 | AF44: 353381.99 | AG44: -174433.36 | AH44: -152993.74 | AI44: -131442.3 | AJ44: -165910.58 | AK44: -217034.85 | AL44: -158529.37 | AM44: -112019.3 | AN44: -126249.18 | AO44: -113926.94 | AP44: -88741.67 | AQ44: -93620.15 | AR44: -36239.24 | AS44: -32591.41
A45: Normalized Increase (Decrease) in Quick Assets (3 month average) | Y45: -167431.18 | Z45: -149749.01 | AA45: -145671.62 | AB45: -138383.4 | AC45: -106750.83 | AD45: 142170.46 | AE45: 144273.01 | AF45: 274456.73 | AG45: 13229.923 | AH45: 8651.63 | AI45: -152956.47 | AJ45: -150115.54 | AK45: -171462.58 | AL45: -180491.6 | AM45: -162527.84 | AN45: -132265.95 | AO45: -117398.47 | AP45: -109639.26 | AQ45: -98762.92 | AR45: -72867.02 | AS45: -54150.267
A46: Quick Assets Runway | Y46: 20.825729 | Z46: 22.402883 | AA46: 22.085927 | AB46: 22.197216 | AC46: 28.426542 | AD46: -25.629825 | AE46: -24.291066 | AF46: -14.056596 | AG46: -278.42141 | AH46: -408.07341 | AI46: 22.222387 | AJ46: 21.537725 | AK46: 17.5905 | AL46: 15.832222 | AM46: 16.892883 | AN46: 19.803393 | AO46: 21.340888 | AP46: 22.041793 | AQ46: 23.521234 | AR46: 31.383012 | AS46: 41.628514
A48: Number of FTEs | N48: 4 | O48: 4 | P48: 4 | Q48: 4 | R48: 4 | S48: 5 | T48: 4 | U48: 5 | V48: 5 | W48: 5 | X48: 5 | Y48: 12 | Z48: 14 | AA48: 14 | AB48: 14 | AC48: 15 | AD48: 15 | AE48: 15 | AF48: 17 | AG48: 17 | AH48: 15 | AI48: 16 | AJ48: 17 | AK48: 17 | AL48: 16 | AM48: 16 | AN48: 17 | AO48: 17 | AP48: 17 | AQ48: 16 | AR48: 16 | AS48: 17
A50: * Unrestricted Cash balance includes Total Cash (per the Balance Sheet) - $40k (Minimum balance to be maintained in 0792 account) -$500K (Warehouse Line Payable)
A51: ** Net Quick Assets = Unrestricted Cash (as defined above) + Accounts Receivable + Dispute Receivable + Felicis Pledge Receivable - Accounts Payable - Accrued Expenses - Payable to Bank - Credit Cards - Deferred Implementation Fees - Payroll liability - Earnings Credit Liability - Rewards Points Liability]
A53: *** Cash Burn is sum of cash flow from operating activities, and cash flow from investing activities (Note - Excludes planned decrease in A/R during June as this will not be recurring)
A54: **** Net Quick Assets / Cash burn
A55: Files used:
A56: Financial Statements - Topkey - from QBO
A59: ARR (Subscription Revenue) | N59: 217072.44 | O59: 254210.28 | P59: 306646.8 | Q59: 299860.8 | R59: 299272.8 | S59: 356181.96 | T59: 366704.76 | U59: 381266.52 | V59: 419245.56 | W59: 418332.36 | X59: 439239.36 | Y59: 482713.08 | Z59: 571609.08 | AA59: 605837.28 | AB59: 765583.2 | AC59: 840573.6 | AD59: 860338.68 | AE59: 958800.6 | AF59: 1032927 | AG59: 1035566.3 | AH59: 1219400.8 | AI59: 1305926.6 | AJ59: 1345561.9 | AK59: 1530665.6 | AL59: 1619805.2 | AM59: 1669713.1 | AN59: 1823442 | AO59: 1883752.9 | AP59: 1955166 | AQ59: 2179587.4 | AR59: 2469104.6 | AS59: 2577236.6
A60: ARR (Interchange Revenue) | N60: 3.36 | O60: 22774.8 | P60: 18702.24 | Q60: 14632.44 | R60: 24059.4 | S60: 21677.64 | T60: 17667.6 | U60: 25333.56 | V60: 25221.84 | W60: 24271.2 | X60: 25538.52 | Y60: -172018.92 | Z60: 59502.36 | AA60: 99488.88 | AB60: 40633.92 | AC60: 35546.88 | AD60: 120528.84 | AE60: 18544.8 | AF60: 19605.12 | AG60: 49856.76 | AH60: 108641.76 | AI60: 37921.92 | AJ60: 15925.92 | AK60: 84389.52 | AL60: 90053.76 | AM60: 142447.68 | AN60: 164802.96 | AO60: 174734.88 | AP60: 157142.4 | AQ60: 195329.76 | AR60: 169172.64 | AS60: 177126.12
A61: ARR (Deposit Revenue) | N61: 0 | O61: 0 | P61: 0 | Q61: 0 | R61: 0 | S61: 0 | T61: 0 | U61: 0 | V61: 0 | W61: 0 | X61: 0 | Y61: 0 | Z61: 108542.64 | AA61: 106541.52 | AB61: 104139.24 | AC61: 130567.08 | AD61: 154343.4 | AE61: 186640.68 | AF61: 209070.48 | AG61: 275533.8 | AH61: 296417.28 | AI61: 216676.08 | AJ61: 206086.08 | AK61: 187814.16 | AL61: 164893.68 | AM61: 196465.68 | AN61: 185587.56 | AO61: 228662.88 | AP61: 235976.16 | AQ61: 262176.24 | AR61: 299941.2 | AS61: 383833.8
A62: ARR (Total Revenues) | N62: 217075.8 | O62: 276985.08 | P62: 325349.04 | Q62: 314493.24 | R62: 323332.2 | S62: 377859.6 | T62: 384372.36 | U62: 406600.08 | V62: 444467.4 | W62: 442603.56 | X62: 464777.88 | Y62: 310694.16 | Z62: 741177.12 | AA62: 815052.24 | AB62: 914971.8 | AC62: 1006687.6 | AD62: 1135210.9 | AE62: 1163986.1 | AF62: 1261602.6 | AG62: 1360956.8 | AH62: 1624459.8 | AI62: 1560524.6 | AJ62: 1567573.9 | AK62: 1802869.3 | AL62: 1874752.7 | AM62: 2008626.5 | AN62: 2173832.5 | AO62: 2287150.7 | AP62: 2348284.6 | AQ62: 2637093.4 | AR62: 3035833.4 | AS62: 3138196.6
AS63: =AS62/12 -> 261516.38
AS64: 325
AS65: =AS63/AS64 -> 804.66578

Sheet Offer Comparison
B2: =Cover!$B$24 -> Keystone Bookkeepers
B3: Offer Comparison — Partnership vs. 100% Buyout ($000s) | H3: Print | I3: 0
B5: Deal Assumptions | C5: Partnership | D5: 100% Buyout | E5: Variance | G5: Notes
B7: Horizon (Years) | C7: 5 | D7: =C7 -> 5 | E7: =C7-D7 -> 0 | G7: Input — drives Partnership and Buyout tabs (D = C)
B8: Est. Topkey Dilution — Ben's Stake (Year 5) | C8: 0.05 | D8: =C8 -> 0.05 | E8: =C8-D8 -> 0 | G8: Input — drives Partnership and Buyout tabs (D = C)
B9: Topkey Valuation Today — Pre-Deal | C9: 50000 | D9: =C9 -> 50000 | E9: =C9-D9 -> 0 | G9: Input — single Topkey valuation; drives Offer Overview, Partnership and Buyout tabs
B10: Topkey 5-Year Valuation Growth (ex-Keystone) | C10: ='Partnership Analysis'!$C$19 -> 1.0131712 | D10: ='100% Buyout Analysis'!$C$18 -> 1 | E10: =C10-D10 -> 0.013171226 | G10: Differs because each offer's cash at close is netted from Topkey's ex-Keystone base; measures value growth, not revenue
B11: Keystone 5-Yr Revenue Increase — Standalone (% of Start) | C11: =IFERROR('Partnership Analysis'!$C$28/'Partnership Analysis'!$C$47,0) -> 0.99837392 | D11: =IFERROR('100% Buyout Analysis'!$C$27/'100% Buyout Analysis'!$C$46,0) -> 0.99837392 | E11: =C11-D11 -> 0 | G11: Total additional standalone revenue ÷ Keystone run-rate revenue at close
B12: Keystone 5-Yr Revenue Increase — Partnership (% of Start) | C12: =IFERROR('Partnership Analysis'!$C$42/'Partnership Analysis'!$C$47,0) -> 1.6639565 | D12: =IFERROR('100% Buyout Analysis'!$C$41/'100% Buyout Analysis'!$C$46,0) -> 1.6639565 | E12: =C12-D12 -> 0 | G12: Total additional partnership revenue ÷ Keystone run-rate revenue at close
B13: Keystone Initial Revenue Multiple | C13: 1 | D13: =C13 -> 1 | E13: =C13-D13 -> 0 | G13: Input — drives Partnership and Buyout tabs (D = C)
B14: Keystone Scaled Revenue Multiple | C14: 1.25 | D14: =C14 -> 1.25 | E14: =C14-D14 -> 0 | G14: Input — drives Partnership and Buyout tabs (D = C)
B15: Keystone Software-Integration Revenue Multiple | C15: 2 | D15: =C15 -> 2 | E15: =C15-D15 -> 0 | G15: Input — drives Partnership and Buyout tabs (D = C)
B16: General Assumptions
B17: Ben's Rollover % — Keystone | C17: 0.3 | D17: 0 | E17: =C17-D17 -> 0.3 | G17: Input — share of Keystone Ben keeps (Partnership 30%; Buyout 0% = Topkey acquires 100%)
B18: Topkey - Current Monthly Revenue | C18: 261 | D18: =C18 -> 261 | E18: =C18-D18 -> 0 | G18: Input — drives Partnership and Buyout tabs (D = C). Topkey-provided monthly revenue ($000s); red = pending seller confirmation
B19: Topkey - Current Client Count | C19: 325 | D19: =C19 -> 325 | E19: =C19-D19 -> 0 | G19: Input — drives Partnership and Buyout tabs (D = C). Topkey-provided client count; red = pending seller confirmation
B20: Topkey - Annual Net Client Wins | C20: 65 | D20: =C20 -> 65 | E20: =C20-D20 -> 0 | G20: Input — drives Partnership and Buyout tabs (D = C). AMB placeholder; red = pending confirmation
B21: Cash at Close | C21: 650 | D21: ='100% Buyout Analysis'!$C$174 -> 500 | E21: =C21-D21 -> 150 | G21: Partnership cash at close set to cover Ben's tax situation
B22: Keystone Standalone Assumptions
B23: Avg. Revenue Per Client | C23: ='Steady-State Staffing'!$AB$8 -> 16.631473 | D23: =C23 -> 16.631473 | E23: =C23-D23 -> 0 | G23: Linked to Steady-State Staffing AB8 (Sep'26 annualized fee per non-tax client); drives both tabs (D = C)
B24: Improved Client Retention
B25: Target Monthly Net Client Wins | C25: 3 | D25: =C25 -> 3 | E25: =C25-D25 -> 0 | G25: Input — drives Partnership and Buyout tabs (D = C). AMB target pace; LTM actual is 26/yr (~2.2/month)
B26: Keystone Partnership Assumptions
B27: VR Platform Run-Rate Tech Cost | C27: 240 | D27: =C27 -> 240 | E27: =C27-D27 -> 0 | G27: Input — drives Partnership and Buyout tabs (D = C). Run-rate tech cost provided by the target; memo only
B28: Software-Enabled Price Increase / Client | C28: 0 | D28: =C28 -> 0 | E28: =C28-D28 -> 0 | G28: Input — drives Partnership and Buyout tabs (D = C). Only if Topkey software supports higher client fees
B29: Additional Annual Net Client Wins From Topkey | C29: 24 | D29: =C29 -> 24 | E29: =C29-D29 -> 0 | G29: Input — drives Partnership and Buyout tabs (D = C). Topkey-provided; red = pending seller confirmation
B31: Offer Structure | C31: Partnership | D31: 100% Buyout | E31: Variance
B32: Keystone Value Today (100%) | C32: ='Partnership Analysis'!$C$185 -> 3000 | D32: ='100% Buyout Analysis'!$C$173 -> 3000 | E32: =C32-D32 -> 0
B33: Ben's Rollover % — Keystone | C33: =C17 -> 0.3 | D33: =D17 -> 0 | E33: =C33-D33 -> 0.3 | G33: Linked to Ben's Rollover % input (row 17)
B34: Keystone Stake Acquired by Topkey | C34: ='Partnership Analysis'!$C$187 -> 0.7 | D34: ='100% Buyout Analysis'!$C$96 -> 1 | E34: =C34-D34 -> -0.3
B35: Price for Topkey's Stake (at Close) | C35: ='Partnership Analysis'!$C$188 -> 2100 | D35: ='100% Buyout Analysis'!$C$173 -> 3000 | E35: =C35-D35 -> -900
B36: Cash at Close | C36: ='Partnership Analysis'!$C$189 -> 650 | D36: ='100% Buyout Analysis'!$C$174 -> 500 | E36: =C36-D36 -> 150 | G36: Partnership cash of $650K is set to cover Ben's tax situation
B37: (+) Topkey Equity Issued to Ben | C37: ='Partnership Analysis'!$C$190 -> 1450 | D37: ='100% Buyout Analysis'!$C$175 -> 2500 | E37: =C37-D37 -> -1050
B38: (+) Target Cash Earnout (at 100% Achievement) — Year 3 | C38: ='Partnership Analysis'!$C$58 -> 0 | D38: ='100% Buyout Analysis'!$C$57 -> 500 | E38: =C38-D38 -> -500 | G38: Buyout: $500K target, capped at $750K (150% of target). Partnership: no earnout
B39: Total Consideration Paid by Topkey | C39: =SUM(C36:C38) -> 2100 | D39: =SUM(D36:D38) -> 3500 | E39: =C39-D39 -> -1400 | G39: Cash + equity issued + target earnout; tie-out to analysis tabs in row 38
B40: Tie Out — Consideration vs. Analysis Tab | C40: =C39-'Partnership Analysis'!$C$106 -> 0 | D40: =D39-'100% Buyout Analysis'!$C$95 -> 0 | G40: Must equal zero
B41: % of Consideration in Cash (incl. Earnout) | C41: =IFERROR((C36+C38)/C39,0) -> 0.30952381 | D41: =IFERROR((D36+D38)/D39,0) -> 0.28571429 | E41: =C41-D41 -> 0.023809524
B43: Where Ben's Year 5 Value Comes From | C43: Partnership | D43: 100% Buyout | E43: Variance
B45: Retained Keystone Stake (Direct) | C45: =IFERROR(C108/C$113,0) -> 0.57042373 | D45: =IFERROR(D108/D$113,0) -> 0 | E45: =C45-D45 -> 0.57042373
B46: Keystone via Topkey | C46: =IFERROR(C109/C$113,0) -> 0.035635314 | D46: =IFERROR(D109/D$113,0) -> 0.11654379 | E46: =C46-D46 -> -0.080908475
B47: Topkey ex-Keystone | C47: =IFERROR(C110/C$113,0) -> 0.31657987 | D47: =IFERROR(D110/D$113,0) -> 0.72219954 | E47: =C47-D47 -> -0.40561966
B48: Cash at Close | C48: =IFERROR(C111/C$113,0) -> 0.077361086 | D48: =IFERROR(D111/D$113,0) -> 0.080628337 | E48: =C48-D48 -> -0.0032672511
B49: Cash Earnout — Year 3 | C49: =IFERROR(C112/C$113,0) -> 0 | D49: =IFERROR(D112/D$113,0) -> 0.080628337 | E49: =C49-D49 -> -0.080628337
B51: Return Profile — Jon (Topkey) | C51: Partnership | D51: 100% Buyout | E51: Variance | K51: Helper: Year | L51: 0 | M51: 1 | N51: 2 | O51: 3 | P51: 4 | Q51: 5
B52: Cash at Close (Year 0) | C52: =C36 -> 650 | D52: =D36 -> 500 | E52: =C52-D52 -> 150 | K52: Helper: Partnership CF | L52: =-(L$51=0)*($C$36+$C$37)-(L$51=$L$54)*$C$38+(L$51=$C$7)*$C$56 -> -2100 | M52: =-(M$51=0)*($C$36+$C$37)-(M$51=$L$54)*$C$38+(M$51=$C$7)*$C$56 -> 0 | N52: =-(N$51=0)*($C$36+$C$37)-(N$51=$L$54)*$C$38+(N$51=$C$7)*$C$56 -> 0 | O52: =-(O$51=0)*($C$36+$C$37)-(O$51=$L$54)*$C$38+(O$51=$C$7)*$C$56 -> 0 | P52: =-(P$51=0)*($C$36+$C$37)-(P$51=$L$54)*$C$38+(P$51=$C$7)*$C$56 -> 0 | Q52: =-(Q$51=0)*($C$36+$C$37)-(Q$51=$L$54)*$C$38+(Q$51=$C$7)*$C$56 -> 11183.176
B53: (+) Equity Issued to Ben (Year 0) | C53: =C37 -> 1450 | D53: =D37 -> 2500 | E53: =C53-D53 -> -1050 | K53: Helper: Buyout CF | L53: =-(L$51=0)*($D$36+$D$37)-(L$51=$L$54)*$D$38+(L$51=$D$7)*$D$56 -> -3000 | M53: =-(M$51=0)*($D$36+$D$37)-(M$51=$L$54)*$D$38+(M$51=$D$7)*$D$56 -> 0 | N53: =-(N$51=0)*($D$36+$D$37)-(N$51=$L$54)*$D$38+(N$51=$D$7)*$D$56 -> 0 | O53: =-(O$51=0)*($D$36+$D$37)-(O$51=$L$54)*$D$38+(O$51=$D$7)*$D$56 -> -500 | P53: =-(P$51=0)*($D$36+$D$37)-(P$51=$L$54)*$D$38+(P$51=$D$7)*$D$56 -> 0 | Q53: =-(Q$51=0)*($D$36+$D$37)-(Q$51=$L$54)*$D$38+(Q$51=$D$7)*$D$56 -> 15975.966
B54: (+) Target Cash Earnout (at 100% Achievement) (Year 3) | C54: =C38 -> 0 | D54: =D38 -> 500 | E54: =C54-D54 -> -500 | K54: Helper: Earnout Year | L54: ='100% Buyout Analysis'!$C$45 -> 3 | M54: Year the target earnout is paid — linked to 100% Buyout Analysis (Earnout Measurement Year)
B55: Total Invested by Jon (Topkey) | C55: =SUM(C52:C54) -> 2100 | D55: =SUM(D52:D54) -> 3500 | E55: =C55-D55 -> -1400 | G55: Ties to Total Consideration (row 37) | K55: Helper: Partnership Hurdle CF | L55: =-(L$51=0)*($C$36+$C$37)+(L$51=$C$7)*$C$133 -> -2100 | M55: =-(M$51=0)*($C$36+$C$37)+(M$51=$C$7)*$C$133 -> 0 | N55: =-(N$51=0)*($C$36+$C$37)+(N$51=$C$7)*$C$133 -> 0 | O55: =-(O$51=0)*($C$36+$C$37)+(O$51=$C$7)*$C$133 -> 0 | P55: =-(P$51=0)*($C$36+$C$37)+(P$51=$C$7)*$C$133 -> 0 | Q55: =-(Q$51=0)*($C$36+$C$37)+(Q$51=$C$7)*$C$133 -> 3550
B56: Topkey's Keystone Stake — Year 5 Value | C56: ='Partnership Analysis'!$D$82 -> 11183.176 | D56: ='100% Buyout Analysis'!$D$76 -> 15975.966 | E56: =C56-D56 -> -4792.7898 | G56: Topkey's stake acquired (row 32) × Keystone Year 5 value | K56: Helper: Buyout Hurdle CF | L56: =-(L$51=0)*($D$36+$D$37)+(L$51=$D$7)*$D$133 -> -3000 | M56: =-(M$51=0)*($D$36+$D$37)+(M$51=$D$7)*$D$133 -> 0 | N56: =-(N$51=0)*($D$36+$D$37)+(N$51=$D$7)*$D$133 -> 0 | O56: =-(O$51=0)*($D$36+$D$37)+(O$51=$D$7)*$D$133 -> 0 | P56: =-(P$51=0)*($D$36+$D$37)+(P$51=$D$7)*$D$133 -> 0 | Q56: =-(Q$51=0)*($D$36+$D$37)+(Q$51=$D$7)*$D$133 -> 5500
B57: Deal MOIC | C57: =IFERROR(C56/C55,0) -> 5.3253219 | D57: =IFERROR(D56/D55,0) -> 4.5645617 | E57: =C57-D57 -> 0.76076028 | G57: Standard acquirer view: stake value ÷ consideration at issue price
B58: Deal IRR | C58: =IFERROR(IRR($L52:$Q52),0) -> 0.39723409 | D58: =IFERROR(IRR($L53:$Q53),0) -> 0.38016247 | E58: =C58-D58 -> 0.017071621 | G58: Cash-flow IRR; see helper cash flows in L50:Q51
B59: (-) Hurdle MOIC — Break-Even | C59: =IFERROR(C133/(C52+C53),0) -> 1.6904762 | D59: =IFERROR(D133/(D52+D53),0) -> 1.8333333 | E59: =C59-D59 -> -0.14285714 | G59: Break-even stake value (row 131) ÷ cash + stock; no earnout paid at break-even
B60: (-) Hurdle IRR — Break-Even | C60: =IFERROR(IRR($L55:$Q55),0) -> 0.11071289 | D60: =IFERROR(IRR($L56:$Q56),0) -> 0.12888132 | E60: =C60-D60 -> -0.018168431 | G60: Cash-flow IRR on break-even flows (L53:Q54): cash + stock at Yr 0, break-even stake value (row 131) at Yr 5; no earnout
B61: Excess MOIC over Hurdle | C61: =C57-C59 -> 3.6348458 | D61: =D57-D59 -> 2.7312283 | E61: =C61-D61 -> 0.90361742 | G61: Deal return after backing out the cost of paying in Topkey stock
B62: Excess IRR over Hurdle (% pts) | C62: =C58-C60 -> 0.2865212 | D62: =D58-D60 -> 0.25128115 | E62: =C62-D62 -> 0.035240053 | G62: Deal IRR less hurdle IRR
B63: Jon's Year 5 Value — With Deal | C63: =C$152*('Partnership Analysis'!$D$81+'Partnership Analysis'!$D$82) -> 102047.15 | D63: =D$152*('100% Buyout Analysis'!$D$75+'100% Buyout Analysis'!$D$76) -> 104025.87 | E63: =C63-D63 -> -1978.7239 | G63: Jon's diluted % × (Topkey ex-Keystone + Keystone stake)
B64: (-) Jon's Year 5 Value — Without Deal | C64: =(1-C$8)*('Partnership Analysis'!$D$81+C36+C38) -> 95000 | D64: =(1-D$8)*('100% Buyout Analysis'!$D$75+D36+D38) -> 95000 | E64: =C64-D64 -> 0 | G64: Topkey keeps its cash and pays no earnout; Jon diluted by the same est. %
B65: Net Value Created for Jon | C65: =C63-C64 -> 7047.1499 | D65: =D63-D64 -> 9025.8739 | E65: =C65-D65 -> -1978.7239 | G65: Includes the cost of stock sharing Topkey's growth with Ben
B66: All-In MOIC | C66: =IFERROR((C55+C65)/C55,0) -> 4.3557857 | D66: =IFERROR((D55+D65)/D55,0) -> 3.5788211 | E66: =C66-D66 -> 0.77696458 | G66: (Invested + net value created) ÷ invested
B67: All-In IRR | C67: =IFERROR(C66^(1/C$7)-1,0) -> 0.34218784 | D67: =IFERROR(D66^(1/D$7)-1,0) -> 0.29047025 | E67: =C67-D67 -> 0.05171759 | G67: MOIC^(1 / horizon) − 1
B69: Partnership Upside Analysis
C70: First 70% (Partnership) | D70: 100% (Buyout) | E70: Extra 30% | G70: Column E = incremental cost and return of buying the last 30% (Buyout less Partnership)
B71: Keystone Stake Acquired by Topkey | C71: =C34 -> 0.7 | D71: =D34 -> 1 | E71: =D71-C71 -> 0.3
B72: Total Invested by Jon (Topkey) | C72: =C55 -> 2100 | D72: =D55 -> 3500 | E72: =D72-C72 -> 1400 | G72: Incremental cost of the last 30%
B73: Cost per 1% of Keystone | C73: =IFERROR(C72/(C71*100),0) -> 30 | D73: =IFERROR(D72/(D71*100),0) -> 35 | E73: =IFERROR(E72/(E71*100),0) -> 46.666667 | G73: Price per point rises on the extra 30% (earnout added)
B74: Paid in Topkey Stock (% of Invested) | C74: =IFERROR(C53/C72,0) -> 0.69047619 | D74: =IFERROR(D53/D72,0) -> 0.71428571 | E74: =IFERROR((D53-C53)/E72,0) -> 0.75 | G74: Stock is Jon's most expensive currency (shares Topkey's growth)
B75: Keystone Stake Value — Year 5 | C75: =C56 -> 11183.176 | D75: =D56 -> 15975.966 | E75: =D75-C75 -> 4792.7898
B76: Deal MOIC | C76: =IFERROR(C75/C72,0) -> 5.3253219 | D76: =IFERROR(D75/D72,0) -> 4.5645617 | E76: =IFERROR(E75/E72,0) -> 3.4234213 | G76: Stake value ÷ consideration at issue price
B77: Hurdle MOIC — Break-Even | C77: =C59 -> 1.6904762 | D77: =D59 -> 1.8333333 | E77: n/m | G77: From Jon's return profile (row 57); n/m for the extra 30% (break-even excludes earnout, so hurdles aren't additive)
B78: Net Value Created for Jon | C78: =C65 -> 7047.1499 | D78: =D65 -> 9025.8739 | E78: =D78-C78 -> 1978.7239 | G78: Incremental value to Jon from the last 30%
B79: All-In MOIC | C79: =IFERROR((C72+C78)/C72,0) -> 4.3557857 | D79: =IFERROR((D72+D78)/D72,0) -> 3.5788211 | E79: =IFERROR((E72+E78)/E72,0) -> 2.4133742 | G79: (Invested + net value created) ÷ invested
B80: All-In IRR | C80: =IFERROR(C79^(1/C$7)-1,0) -> 0.34218784 | D80: =IFERROR(D79^(1/D$7)-1,0) -> 0.29047025 | E80: =IFERROR(E79^(1/D$7)-1,0) -> 0.19268274 | G80: MOIC^(1 / horizon) − 1
B82: Return Profile — Ben | C82: Partnership | D82: 100% Buyout | E82: Variance | K82: Helper: Year | L82: 0 | M82: 1 | N82: 2 | O82: 3 | P82: 4 | Q82: 5
B83: Keystone Value Contributed by Ben (Year 0) | C83: =C32 -> 3000 | D83: =D32 -> 3000 | E83: =C83-D83 -> 0 | G83: Ben gives up 100% of Keystone at today's value in both offers | K83: Helper: Partnership CF | L83: =-(L$82=0)*($C$83-$C$84)+(L$82=$L$54)*$C$85+(L$82=$C$7)*($C$86+$C$87) -> -2350 | M83: =-(M$82=0)*($C$83-$C$84)+(M$82=$L$54)*$C$85+(M$82=$C$7)*($C$86+$C$87) -> 0 | N83: =-(N$82=0)*($C$83-$C$84)+(N$82=$L$54)*$C$85+(N$82=$C$7)*($C$86+$C$87) -> 0 | O83: =-(O$82=0)*($C$83-$C$84)+(O$82=$L$54)*$C$85+(O$82=$C$7)*($C$86+$C$87) -> 0 | P83: =-(P$82=0)*($C$83-$C$84)+(P$82=$L$54)*$C$85+(P$82=$C$7)*($C$86+$C$87) -> 0 | Q83: =-(Q$82=0)*($C$83-$C$84)+(Q$82=$L$54)*$C$85+(Q$82=$C$7)*($C$86+$C$87) -> 7752.1571
B84: Cash at Close (Year 0) | C84: =C111 -> 650 | D84: =D111 -> 500 | E84: =C84-D84 -> 150 | K84: Helper: Buyout CF | L84: =-(L$82=0)*($D$83-$D$84)+(L$82=$L$54)*$D$85+(L$82=$D$7)*($D$86+$D$87) -> -2500 | M84: =-(M$82=0)*($D$83-$D$84)+(M$82=$L$54)*$D$85+(M$82=$D$7)*($D$86+$D$87) -> 0 | N84: =-(N$82=0)*($D$83-$D$84)+(N$82=$L$54)*$D$85+(N$82=$D$7)*($D$86+$D$87) -> 0 | O84: =-(O$82=0)*($D$83-$D$84)+(O$82=$L$54)*$D$85+(O$82=$D$7)*($D$86+$D$87) -> 500 | P84: =-(P$82=0)*($D$83-$D$84)+(P$82=$L$54)*$D$85+(P$82=$D$7)*($D$86+$D$87) -> 0 | Q84: =-(Q$82=0)*($D$83-$D$84)+(Q$82=$L$54)*$D$85+(Q$82=$D$7)*($D$86+$D$87) -> 5201.2937
B85: (+) Target Cash Earnout (at 100% Achievement) (Year 3) | C85: =C112 -> 0 | D85: =D112 -> 500 | E85: =C85-D85 -> -500
B86: (+) Retained Keystone Stake — Year 5 | C86: =C108 -> 4792.7898 | D86: =D108 -> 0 | E86: =C86-D86 -> 4792.7898 | G86: Partnership: Ben's retained stake (row 31); Buyout: none
B87: (+) Topkey Equity — Year 5 | C87: =C109+C110 -> 2959.3673 | D87: =D109+D110 -> 5201.2937 | E87: =C87-D87 -> -2241.9263 | G87: Diluted Topkey stake, incl. Ben's indirect share of Keystone
B88: Total Value Received by Ben | C88: =SUM(C84:C87) -> 8402.1571 | D88: =SUM(D84:D87) -> 6201.2937 | E88: =C88-D88 -> 2200.8634 | G88: Ties to Ben's Value — Offer (row 93); tie-out in row 103
B89: Total MOIC | C89: =IFERROR(C88/C83,0) -> 2.800719 | D89: =IFERROR(D88/D83,0) -> 2.0670979 | E89: =C89-D89 -> 0.73362114 | G89: Total value received ÷ Keystone value contributed
B90: Total IRR | C90: =IFERROR(IRR($L83:$Q83),0) -> 0.26961177 | D90: =IFERROR(IRR($L84:$Q84),0) -> 0.18762215 | E90: =C90-D90 -> 0.081989624 | G90: Cash-flow IRR; see helper cash flows in L81:Q82
B91: (-) Ben's Year 5 Value — Standalone | C91: =C96 -> 7490.2577 | D91: =D96 -> 7490.2577 | E91: =C91-D91 -> 0 | G91: Ben keeps 100% of Keystone
B92: Net Value Created for Ben | C92: =C88-C91 -> 911.8994 | D92: =D88-D91 -> -1288.964 | E92: =C92-D92 -> 2200.8634 | G92: Offer vs. keeping 100% of Keystone
B94: Ben — Offer vs. Standalone (Year 5) | C94: Partnership | D94: 100% Buyout | E94: Variance
B95: Ben's Value — Offer | C95: ='Partnership Analysis'!$D$92 -> 8402.1571 | D95: ='100% Buyout Analysis'!$D$81 -> 6201.2937 | E95: =C95-D95 -> 2200.8634
B96: (-) Ben's Value — Standalone | C96: ='Partnership Analysis'!$D$74 -> 7490.2577 | D96: ='100% Buyout Analysis'!$D$72 -> 7490.2577 | E96: =C96-D96 -> 0
B97: Offer Less Standalone ($) | C97: =C95-C96 -> 911.8994 | D97: =D95-D96 -> -1288.964 | E97: =C97-D97 -> 2200.8634
B98: Offer Less Standalone (%) | C98: =IFERROR(C95/C96-1,0) -> 0.12174473 | D98: =IFERROR(D95/D96-1,0) -> -0.1720854
B99: MOIC — Offer | C99: ='Partnership Analysis'!$D$97 -> 2.800719 | D99: ='100% Buyout Analysis'!$D$86 -> 2.0670979 | E99: =C99-D99 -> 0.73362114
B100: (-) MOIC — Standalone | C100: =IFERROR('Partnership Analysis'!$D$74/'Partnership Analysis'!$C$74,0) -> 2.4967526 | D100: =IFERROR('100% Buyout Analysis'!$D$72/'100% Buyout Analysis'!$C$72,0) -> 2.4967526 | E100: =C100-D100 -> 0 | G100: Keystone Year 5 value ÷ value today
B101: MOIC Delta — Offer vs. Standalone | C101: =C99-C100 -> 0.30396647 | D101: =D99-D100 -> -0.42965467 | E101: =C101-D101 -> 0.73362114
B102: IRR — Offer | C102: ='Partnership Analysis'!$D$98 -> 0.26961177 | D102: ='100% Buyout Analysis'!$D$87 -> 0.18762215 | E102: =C102-D102 -> 0.081989624 | G102: From each tab's cash-flow IRR (includes cash timing)
B103: (-) IRR — Standalone | C103: =IFERROR(C100^(1/C$7)-1,0) -> 0.20081223 | D103: =IFERROR(D100^(1/D$7)-1,0) -> 0.20081223 | E103: =C103-D103 -> 0
B104: IRR Delta — Offer vs. Standalone | C104: =C102-C103 -> 0.068799546 | D104: =D102-D103 -> -0.013190078 | E104: =C104-D104 -> 0.081989624
B105: Tie Out — Ben's Value by Source vs. Offer | C105: =C88-C95 -> 0 | D105: =D88-D95 -> 0 | G105: Must equal zero
B107: Ben's Year 5 Value | C107: Partnership | D107: 100% Buyout | E107: Variance
B108: Retained Keystone Stake (Direct) | C108: ='Partnership Analysis'!$D$87 -> 4792.7898 | D108: 0 | E108: =C108-D108 -> 4792.7898 | G108: Buyout: no retained stake
B109: (+) Keystone via Topkey | C109: ='Partnership Analysis'!$D$88 -> 299.41351 | D109: ='100% Buyout Analysis'!$C$118 -> 722.72226 | E109: =C109-D109 -> -423.30875
B110: (+) Topkey ex-Keystone | C110: ='Partnership Analysis'!$D$89 -> 2659.9538 | D110: ='100% Buyout Analysis'!$C$117 -> 4478.5714 | E110: =C110-D110 -> -1818.6176
B111: (+) Cash at Close | C111: ='Partnership Analysis'!$D$90 -> 650 | D111: ='100% Buyout Analysis'!$C$119 -> 500 | E111: =C111-D111 -> 150
...

Sheet Partnership Analysis
B2: =Cover!$B$24 -> Keystone Bookkeepers
B3: Partnership Rollover Scenarios ($000s) | G3: Print | H3: 0
B5: Revenue Growth Assumptions | C5: Value | F5: Rationale / Notes
B6: General Assumptions
B7: Ben's Rollover % — Keystone | C7: ='Offer Comparison'!$C$17 -> 0.3 | F7: Input on Offer Comparison (C17). Share of Keystone Ben keeps; Topkey buys the rest for cash + Topkey equity
B8: Est. Topkey Dilution — Ben's Stake (Year 5) | C8: ='Offer Comparison'!$C$8 -> 0.05 | F8: Linked to Offer Comparison (C8). AMB estimate: future Topkey equity issuance (capital raise, option pool, acquisitions) reduces Ben's Topkey % by this share by Year 5
B9: Horizon (Years) | C9: ='Offer Comparison'!$C$7 -> 5 | F9: Linked to Offer Comparison (C7). Projection horizon for the Year 5 columns
B10: Topkey - Current Monthly Revenue | C10: ='Offer Comparison'!$C$18 -> 261 | F10: Input on Offer Comparison (C18). Topkey-provided monthly revenue ($000s); pending confirmation
B11: Topkey - Current Run-Rate Revenue | C11: =C10*12 -> 3132
B12: Topkey - Current Revenue Multiple | C12: =IFERROR(C191/C11,0) -> 15.96424 | F12: Implied: Topkey pre-deal valuation (C191) ÷ run-rate revenue (C11)
B13: Topkey - Future Revenue Multiple | C13: =C12 -> 15.96424 | F13: Held flat at the current implied multiple
B14: Topkey - Current Client Count | C14: ='Offer Comparison'!$C$19 -> 325 | F14: Input on Offer Comparison (C19). Topkey-provided client count; pending confirmation
B15: Topkey - Avg. Revenue Per Client | C15: =C11/C14 -> 9.6369231
B16: Topkey - Annual Net Client Wins | C16: ='Offer Comparison'!$C$20 -> 65 | F16: Input on Offer Comparison (C20). AMB placeholder; pending confirmation
B17: Total Net Client Wins | C17: =C16*$C$9 -> 325
B18: Total Additional Revenue | C18: =C17*C15 -> 3132
B19: ="Check - "&$C$9&" Year Topkey Valuation Growth" -> Check - 5 Year Topkey Valuation Growth | C19: =IFERROR(D81/C81-1,0) -> 1.0131712 | F19: % growth in Topkey ex-Keystone value (row 81), today → Year 5; value net of cash paid, not revenue
B21: Keystone Standalone Assumptions
B22: Revenue Multiple | C22: ='Offer Comparison'!$C$13 -> 1 | F22: Linked to Offer Comparison (C13). Keystone valued at 1.0x revenue today (offer implies ~1.0x)
B23: Scaled Revenue Multiple | C23: ='Offer Comparison'!$C$14 -> 1.25 | F23: Linked to Offer Comparison (C14). Keystone standalone revenue multiple at Year 5
B24: Avg. Revenue Per Client | C24: ='Offer Comparison'!$C$23 -> 16.631473 | F24: Input on Offer Comparison (C22). Sep'26 annualized fee per non-tax client (Steady-State Staffing AB8)
B25: Target Monthly Net Client Wins | C25: ='Offer Comparison'!$C$25 -> 3 | F25: Input on Offer Comparison (C23). AMB target pace; LTM actual is 26/yr (~2.2/month), see build at rows 200-204
B26: Annual Net Client Wins | C26: =C25*12 -> 36 | F26: Target monthly pace × 12
B27: Total Net Client Wins | C27: =C26*$C$9 -> 180
B28: Total Additional Revenue | C28: =C27*C24 -> 2993.6651
B30: Keystone Partnership Assumptions
B31: Software-Integration Revenue Multiple | C31: ='Offer Comparison'!$C$15 -> 2 | F31: Linked to Offer Comparison (C15). Revenue multiple with Topkey software integration
B32: VR Platform Run-Rate Tech Cost | C32: ='Offer Comparison'!$C$27 -> 240 | F32: Input on Offer Comparison (C25). Run-rate tech cost provided by the target; see platform-fee memo (rows 207-216)
B34: =+B24 -> Avg. Revenue Per Client | C34: =+C24 -> 16.631473
B35: (+) Software-Enabled Price Increase / Client | C35: ='Offer Comparison'!$C$28 -> 0 | F35: Input on Offer Comparison (C26). Only if Topkey software supports higher client fees; VR cost handled in the memo block (rows 207-216)
B36: Total Avg. Revenue Per Client | C36: =+C34+C35 -> 16.631473
B38: =+B26 -> Annual Net Client Wins | C38: =+C26 -> 36
B39: (+) Additional Annual Net Client Wins From Topkey | C39: ='Offer Comparison'!$C$29 -> 24 | F39: Input on Offer Comparison (C27). Topkey-provided; pending confirmation
B40: Total Annual Net Client Wins | C40: =SUM(C38:C39) -> 60
B41: Total Net Client Wins | C41: =C40*$C$9 -> 300
B42: Total Additional Revenue | C42: =C41*C36 -> 4989.4419
B43: Increase in Keystone Revenue vs. Standalone | C43: =C42-C28 -> 1995.7768
B45: Cash Earnout — Year 3 Keystone Revenue (Sliding Scale)
B46: Earnout Measurement Year | C46: 3 | F46: Earnout measured on Year 3 run-rate: average of months 34–36 × 12 (window in C57)
B47: Keystone Revenue at Close | C47: =C184 -> 2998.541 | F47: PF Jul'26 run-rate revenue at close (C184)
B48: Year 3 Run-Rate Revenue Target | C48: =C47+C42*(C46-(C57-1)/2/12)/C9 -> 5909.0488 | F48: Run-rate at close + partnership added revenue ramped to the midpoint of the averaging window (month 35 ÷ 60); same basis as the earnout measurement
B49: (x) Achievement vs. Target | C49: 1 | F49: Base case assumes the model's Year 3 revenue is achieved; flex to test payout
B50: Year 3 Run-Rate Revenue — Achieved | C50: =C48*C49 -> 5909.0488
B51: Threshold — % of Target | C51: 0.8 | F51: No earnout below this share of target; payout starts at the threshold % below
B52: Target Earnout — at 100% of Target | C52: 0 | F52: Initial position does not include earnout
B53: Payout at Threshold — % of Target Earnout | C53: 0.5 | F53: Share of target earnout paid at the 80% threshold
B54: Cap — % of Target Earnout | C54: 1.5 | F54: Payout capped at 150% of target earnout, reached at 120% of target revenue (mirrors the 80% threshold)
B55: Payout % Earned | C55: =IF(C49<C51,0,MIN(C54,C53+(1-C53)*(C49-C51)/(1-C51))) -> 1 | F55: Straight line from threshold payout at 80% to 100% at target, continuing above target until the cap
B56: Maximum Earnout (Cap) | C56: =C52*C54 -> 0 | F56: Topkey's maximum earnout exposure
B57: Run-Rate Window — Months Averaged | C57: 3 | F57: Earnout measured on average monthly recurring revenue for the last 3 months of Year 3 (months 34–36) × 12; averaging prevents one strong month from triggering the payout
B58: Cash Earnout Payable — Year 3 | C58: =C52*C55 -> 0 | F58: Paid in cash by Topkey; flows into Scenario 2 (row 91), Ben's MOIC/IRR (rows 97-98) and Topkey's return (row 105)
B59: Probability of Achievement | C59: 0.7 | F59: AMB estimate for the memo line below
B60: Discount Rate | C60: 0.15 | F60: AMB estimate for the memo line below
B61: Risk-Weighted Earnout — PV at Close (Memo) | C61: =C58*C59/(1+C60)^C46 -> 0 | F61: Memo only; not used in Scenario 2
B63: Offer Structure | C63: =C$183 -> Today | D63: % of Total
B64: Cash at Close | C64: =$C$189 -> 650 | D64: =IFERROR(C64/C$67,0) -> 0.21666667 | F64: Cash paid at close for Topkey's stake (C189)
B65: (+) Topkey Equity Issued to Ben | C65: =$C$190 -> 1450 | D65: =IFERROR(C65/C$67,0) -> 0.48333333 | F65: Topkey stock issued at the $60M pre-deal valuation (C190)
B66: (+) Ben's Rolled Keystone Equity | C66: =$C$185*$C$186 -> 900 | D66: =IFERROR(C66/C$67,0) -> 0.3 | F66: Keystone value today × Ben's rollover % (C185 × C186)
B67: Total Offer Value — at Close | C67: =SUM(C64:C66) -> 3000 | D67: =IFERROR(C67/C$67,0) -> 1 | F67: Ties to Keystone Value Today (C185)
B68: (+) Cash Earnout — Year 3 (Contingent) | C68: =$C$58 -> 0 | D68: =IFERROR(C68/C$67,0) -> 0 | F68: Paid only if Year 3 revenue target is met (C58); % shown vs. offer value at close
B69: Total Consideration incl. Earnout | C69: =C67+C68 -> 3000 | D69: =IFERROR(C69/C$67,0) -> 1
B71: Scenario 1 — Ben Retains 100% of Keystone | C71: =C$183 -> Today | D71: ="Year "&$C$9 -> Year 5
B72: Keystone Enterprise Value | C72: =ROUND(C184*C22,-1) -> 3000 | D72: =(C184+C28)*$C$23 -> 7490.2577 | F72: Today at offer value; Year 5 = (PF run-rate revenue + standalone added revenue) × standalone multiple
B73: Ben's Ownership % — Keystone | C73: 1 | D73: =$C$73 -> 1
B74: Ben's Value — Scenario 1 | C74: =C72*C73 -> 3000 | D74: =D72*D73 -> 7490.2577
B76: ="Scenario 2 — Ben Rolls "&TEXT($C$186,"0%")&" of Keystone Equity" -> Scenario 2 — Ben Rolls 30% of Keystone Equity | C76: =C$183 -> Today | D76: =D$71 -> Year 5
B77: Keystone Enterprise Value — Partnership | C77: =C185 -> 3000 | D77: =(C42+C184)*C31 -> 15975.966 | F77: Today at offer value; Year 5 = partnership revenue × software-integration multiple (C31)
B78: (x) Ben's Retained Keystone % | C78: =$C$186 -> 0.3 | D78: =$C$186 -> 0.3
B79: Ben's Keystone Equity Value | C79: =C77*C78 -> 900 | D79: =D77*D78 -> 4792.7898 | F79: Ben's retained Keystone stake (rollover % × Keystone value)
B81: Topkey ex-Keystone Value | C81: =C194 -> 49350 | D81: =(C11+C18)*C13-$C$189-$C$58 -> 99350
B82: (+) Topkey's Share of Keystone Value | C82: =C77*$C$187 -> 2100 | D82: =D77*$C$187 -> 11183.176 | F82: Topkey's stake in Keystone is part of Topkey's value
B83: Topkey Combined Enterprise Value | C83: =C81+C82 -> 51450 | D83: =D81+D82 -> 110533.18
B84: (x) Ben's Topkey Ownership % | C84: =$C$193 -> 0.028182702 | D84: =$D$193 -> 0.026773567
B85: Ben's Topkey Equity Value | C85: =C83*C84 -> 1450 | D85: =D83*D84 -> 2959.3673 | F85: Ties to Topkey equity issued (tie-out row 196)
B86: Ben's Value by Source
B87: Keystone — Ben's Direct Retained Stake | C87: =C79 -> 900 | D87: =D79 -> 4792.7898 | F87: Keystone value Ben owns directly
B88: (+) Keystone — Ben's Indirect Share via Topkey | C88: =C82*C84 -> 59.183673 | D88: =D82*D84 -> 299.41351 | F88: Ben's Topkey % × Topkey's Keystone stake
B89: (+) Topkey ex-Keystone — Ben's Share | C89: =C81*C84 -> 1390.8163 | D89: =D81*D84 -> 2659.9538 | F89: Ben's Topkey % × Topkey's own business
B90: (+) Cash at Close | C90: =$C$189 -> 650 | D90: =$C$189 -> 650
B91: (+) Cash Earnout — Year 3 | D91: =$C$58 -> 0
B92: Ben's Value — Scenario 2 | C92: =SUM(C87:C91) -> 3000 | D92: =SUM(D87:D91) -> 8402.1571 | F92: Direct Keystone + indirect Keystone + Topkey + cash
B94: Scenario 2 vs. Scenario 1 | C94: =C$183 -> Today | D94: =D$71 -> Year 5
B95: Increase in Proceeds | C95: =C92-C74 -> 0 | D95: =D92-D74 -> 911.8994
B96: Delta (%) | C96: 0 | D96: =IFERROR(D92/D74-1,0) -> 0.12174473
B97: Partnership MOIC — Keystone (Ben) | D97: =IFERROR(D92/C185,0) -> 2.800719 | F97: Ben's Year 5 value (D92: cash + earnout + retained stake + Topkey stock) ÷ Keystone value given up at close (C185)
B98: Partnership IRR — Keystone (Ben) | D98: =IFERROR(IRR(D227:D232),0) -> 0.26961177 | F98: IRR on Ben's cash flows (rows 227-232); Year 5 = stake values, not a cash exit
B99: Break-Even Topkey Value CAGR (ex-Keystone, Net of Cash) | C99: 0 | D99: =MAX(0,IFERROR(((C137+$C$58)/$C$194)^(1/$C$9)-1,0)) -> 0.05757777 | F99: Topkey value CAGR needed for Scenario 2 to equal Scenario 1 (from required value in C137, before earnout paid); floored at zero
B100: Estimated Topkey Value CAGR (ex-Keystone, Net of Cash) | C100: 0 | D100: =IFERROR(((D81+$C$58)/$C$194)^(1/$C$9)-1,0) -> 0.15020736
B102: Topkey's Return on the Keystone Stake | C102: Value
B103: Cash Paid at Close | C103: =C189 -> 650 | F103: Cash portion of stake price (C189)
B104: (+) Topkey Equity Issued to Ben | C104: =C190 -> 1450 | F104: Topkey stock issued, at issue value (C190)
B105: (+) Cash Earnout — Year 3 | C105: =C58 -> 0 | F105: Cash earnout at base-case achievement (C58)
B106: Total Consideration Paid by Topkey | C106: =SUM(C103:C105) -> 2100 | F106: Everything Topkey gives up for its Keystone stake
B107: (x) Topkey's Keystone Stake % | C107: =C187 -> 0.7 | F107: Topkey's share of Keystone (C187)
B108: Keystone Enterprise Value — Year 5 | C108: =D77 -> 15975.966 | F108: Year 5 partnership value of 100% of Keystone (D77)
B109: Value of Topkey's Keystone Stake — Year 5 | C109: =C107*C108 -> 11183.176 | F109: Topkey's stake % × Keystone Year 5 value; ties to Scenario 2 (D82)
B110: MOIC — Topkey | C110: =IFERROR(C109/C106,0) -> 5.3253219 | F110: Year 5 stake value ÷ total consideration
B111: IRR — Topkey | C111: =IFERROR(IRR(D219:D224),0) -> 0.39723409 | F111: IRR on Topkey's cash flows (rows 219-224); excludes software fee income and Keystone distributions, so understated
B113: Internal - Implied Keystone Standalone Multiple | C113: =D$71 -> Year 5
B114: Year 5 Keystone Standalone Revenue | C114: =+C28+C184 -> 5992.2062
...

Sheet Partnership Sensitivity Tables
B2: =Cover!$B$24 -> Keystone Bookkeepers
B3: Partnership Sensitivity Tables ($000s) | N3: Print | O3: 1
B5: Ben's Return Profile Based on Partnering
B6: Ben's Net Returns Based on Topkey Growth & Rollover %
D8: Topkey ex-Keystone Value Growth (%) | S8: Helper: IRR Year Index | Z8: Helper: Unrounded Net Return
D9: =E9-$G$441 -> 0.013171226 | E9: =F9-$G$441 -> 0.26317123 | F9: =G9-$G$441 -> 0.51317123 | G9: =H9-$G$441 -> 0.76317123 | H9: =$G$440 -> 1.0131712 | I9: =H9+$G$441 -> 1.2631712 | J9: =I9+$G$441 -> 1.5131712 | K9: =J9+$G$441 -> 1.7631712 | L9: =K9+$G$441 -> 2.0131712 | N9: Helper: Rollover % | O9: Helper: Cash at Close | P9: Helper: Topkey Equity Issued | Q9: Helper: Topkey ex-Keystone Today | R9: Helper: Ben's Yr 5 Topkey % | S9: 0 | T9: =S9+1 -> 1 | U9: =T9+1 -> 2 | V9: =U9+1 -> 3 | W9: =V9+1 -> 4 | X9: =W9+1 -> 5 | Z9: =D$9 -> 0.013171226 | AA9: =E$9 -> 0.26317123 | AB9: =F$9 -> 0.51317123 | AC9: =G$9 -> 0.76317123 | AD9: =H$9 -> 1.0131712 | AE9: =I$9 -> 1.2631712 | AF9: =J$9 -> 1.5131712 | AG9: =K$9 -> 1.7631712 | AH9: =L$9 -> 2.0131712 | AT9: Helper: Gradient Band (0 = below $1M hurdle)
B10: Ben's Rollover % | C10: =C11-$G$439 -> 0.15 | D10: =ROUND(Z10,$G$452) -> 2300 | E10: =ROUND(AA10,$G$452) -> 2700 | F10: =ROUND(AB10,$G$452) -> 3100 | G10: =ROUND(AC10,$G$452) -> 3500 | H10: =ROUND(AD10,$G$452) -> 4000 | I10: =ROUND(AE10,$G$452) -> 4400 | J10: =ROUND(AF10,$G$452) -> 4800 | K10: =ROUND(AG10,$G$452) -> 5300 | L10: =ROUND(AH10,$G$452) -> 5700 | N10: =$C10 -> 0.15 | O10: =$G$433 -> 650 | P10: =$G$430*(1-N10)-O10 -> 1900 | Q10: =$G$432-O10 -> 49350 | R10: =IFERROR(P10/(Q10+$G$430*(1-N10)),0)*(1-$G$434) -> 0.03477842 | Z10: =$O10+$G$435+$N10*$G$431+$R10*($Q10*(1+D$9)+$G$431*(1-$N10))-$G$430 -> 2257.5919 | AA10: =$O10+$G$435+$N10*$G$431+$R10*($Q10*(1+E$9)+$G$431*(1-$N10))-$G$430 -> 2686.6707 | AB10: =$O10+$G$435+$N10*$G$431+$R10*($Q10*(1+F$9)+$G$431*(1-$N10))-$G$430 -> 3115.7494 | AC10: =$O10+$G$435+$N10*$G$431+$R10*($Q10*(1+G$9)+$G$431*(1-$N10))-$G$430 -> 3544.8282 | AD10: =$O10+$G$435+$N10*$G$431+$R10*($Q10*(1+H$9)+$G$431*(1-$N10))-$G$430 -> 3973.9069 | AE10: =$O10+$G$435+$N10*$G$431+$R10*($Q10*(1+I$9)+$G$431*(1-$N10))-$G$430 -> 4402.9857 | AF10: =$O10+$G$435+$N10*$G$431+$R10*($Q10*(1+J$9)+$G$431*(1-$N10))-$G$430 -> 4832.0644 | AG10: =$O10+$G$435+$N10*$G$431+$R10*($Q10*(1+K$9)+$G$431*(1-$N10))-$G$430 -> 5261.1432 | AH10: =$O10+$G$435+$N10*$G$431+$R10*($Q10*(1+L$9)+$G$431*(1-$N10))-$G$430 -> 5690.222 | AT10: =IF(Z50<$G$449,0,MIN($G$446,1+IFERROR(INT((Z50-$G$449)/$G$451),0))) -> 0 | AU10: =IF(AA50<$G$449,0,MIN($G$446,1+IFERROR(INT((AA50-$G$449)/$G$451),0))) -> 0 | AV10: =IF(AB50<$G$449,0,MIN($G$446,1+IFERROR(INT((AB50-$G$449)/$G$451),0))) -> 0 | AW10: =IF(AC50<$G$449,0,MIN($G$446,1+IFERROR(INT((AC50-$G$449)/$G$451),0))) -> 0 | AX10: =IF(AD50<$G$449,0,MIN($G$446,1+IFERROR(INT((AD50-$G$449)/$G$451),0))) -> 0 | AY10: =IF(AE50<$G$449,0,MIN($G$446,1+IFERROR(INT((AE50-$G$449)/$G$451),0))) -> 0 | AZ10: =IF(AF50<$G$449,0,MIN($G$446,1+IFERROR(INT((AF50-$G$449)/$G$451),0))) -> 0 | BA10: =IF(AG50<$G$449,0,MIN($G$446,1+IFERROR(INT((AG50-$G$449)/$G$451),0))) -> 0 | BB10: =IF(AH50<$G$449,0,MIN($G$446,1+IFERROR(INT((AH50-$G$449)/$G$451),0))) -> 1
C11: =C12-$G$439 -> 0.2 | D11: =ROUND(Z11,$G$452) -> 2900 | E11: =ROUND(AA11,$G$452) -> 3300 | F11: =ROUND(AB11,$G$452) -> 3700 | G11: =ROUND(AC11,$G$452) -> 4100 | H11: =ROUND(AD11,$G$452) -> 4400 | I11: =ROUND(AE11,$G$452) -> 4800 | J11: =ROUND(AF11,$G$452) -> 5200 | K11: =ROUND(AG11,$G$452) -> 5600 | L11: =ROUND(AH11,$G$452) -> 6000 | N11: =$C11 -> 0.2 | O11: =$G$433 -> 650 | P11: =$G$430*(1-N11)-O11 -> 1750 | Q11: =$G$432-O11 -> 49350 | R11: =IFERROR(P11/(Q11+$G$430*(1-N11)),0)*(1-$G$434) -> 0.032125604 | Z11: =$O11+$G$435+$N11*$G$431+$R11*($Q11*(1+D$9)+$G$431*(1-$N11))-$G$430 -> 2862.0634 | AA11: =$O11+$G$435+$N11*$G$431+$R11*($Q11*(1+E$9)+$G$431*(1-$N11))-$G$430 -> 3258.413 | AB11: =$O11+$G$435+$N11*$G$431+$R11*($Q11*(1+F$9)+$G$431*(1-$N11))-$G$430 -> 3654.7627 | AC11: =$O11+$G$435+$N11*$G$431+$R11*($Q11*(1+G$9)+$G$431*(1-$N11))-$G$430 -> 4051.1123 | AD11: =$O11+$G$435+$N11*$G$431+$R11*($Q11*(1+H$9)+$G$431*(1-$N11))-$G$430 -> 4447.462 | AE11: =$O11+$G$435+$N11*$G$431+$R11*($Q11*(1+I$9)+$G$431*(1-$N11))-$G$430 -> 4843.8116 | AF11: =$O11+$G$435+$N11*$G$431+$R11*($Q11*(1+J$9)+$G$431*(1-$N11))-$G$430 -> 5240.1612 | AG11: =$O11+$G$435+$N11*$G$431+$R11*($Q11*(1+K$9)+$G$431*(1-$N11))-$G$430 -> 5636.5109 | AH11: =$O11+$G$435+$N11*$G$431+$R11*($Q11*(1+L$9)+$G$431*(1-$N11))-$G$430 -> 6032.8605 | AT11: =IF(Z51<$G$449,0,MIN($G$446,1+IFERROR(INT((Z51-$G$449)/$G$451),0))) -> 0 | AU11: =IF(AA51<$G$449,0,MIN($G$446,1+IFERROR(INT((AA51-$G$449)/$G$451),0))) -> 0 | AV11: =IF(AB51<$G$449,0,MIN($G$446,1+IFERROR(INT((AB51-$G$449)/$G$451),0))) -> 0 | AW11: =IF(AC51<$G$449,0,MIN($G$446,1+IFERROR(INT((AC51-$G$449)/$G$451),0))) -> 0 | AX11: =IF(AD51<$G$449,0,MIN($G$446,1+IFERROR(INT((AD51-$G$449)/$G$451),0))) -> 0 | AY11: =IF(AE51<$G$449,0,MIN($G$446,1+IFERROR(INT((AE51-$G$449)/$G$451),0))) -> 0 | AZ11: =IF(AF51<$G$449,0,MIN($G$446,1+IFERROR(INT((AF51-$G$449)/$G$451),0))) -> 0 | BA11: =IF(AG51<$G$449,0,MIN($G$446,1+IFERROR(INT((AG51-$G$449)/$G$451),0))) -> 1 | BB11: =IF(AH51<$G$449,0,MIN($G$446,1+IFERROR(INT((AH51-$G$449)/$G$451),0))) -> 3
C12: =C13-$G$439 -> 0.25 | D12: =ROUND(Z12,$G$452) -> 3500 | E12: =ROUND(AA12,$G$452) -> 3800 | F12: =ROUND(AB12,$G$452) -> 4200 | G12: =ROUND(AC12,$G$452) -> 4600 | H12: =ROUND(AD12,$G$452) -> 4900 | I12: =ROUND(AE12,$G$452) -> 5300 | J12: =ROUND(AF12,$G$452) -> 5700 | K12: =ROUND(AG12,$G$452) -> 6000 | L12: =ROUND(AH12,$G$452) -> 6400 | N12: =$C12 -> 0.25 | O12: =$G$433 -> 650 | P12: =$G$430*(1-N12)-O12 -> 1600 | Q12: =$G$432-O12 -> 49350 | R12: =IFERROR(P12/(Q12+$G$430*(1-N12)),0)*(1-$G$434) -> 0.029457364 | Z12: =$O12+$G$435+$N12*$G$431+$R12*($Q12*(1+D$9)+$G$431*(1-$N12))-$G$430 -> 3469.8171 | AA12: =$O12+$G$435+$N12*$G$431+$R12*($Q12*(1+E$9)+$G$431*(1-$N12))-$G$430 -> 3833.2473 | AB12: =$O12+$G$435+$N12*$G$431+$R12*($Q12*(1+F$9)+$G$431*(1-$N12))-$G$430 -> 4196.6775 | AC12: =$O12+$G$435+$N12*$G$431+$R12*($Q12*(1+G$9)+$G$431*(1-$N12))-$G$430 -> 4560.1078 | AD12: =$O12+$G$435+$N12*$G$431+$R12*($Q12*(1+H$9)+$G$431*(1-$N12))-$G$430 -> 4923.538 | AE12: =$O12+$G$435+$N12*$G$431+$R12*($Q12*(1+I$9)+$G$431*(1-$N12))-$G$430 -> 5286.9682 | AF12: =$O12+$G$435+$N12*$G$431+$R12*($Q12*(1+J$9)+$G$431*(1-$N12))-$G$430 -> 5650.3985 | AG12: =$O12+$G$435+$N12*$G$431+$R12*($Q12*(1+K$9)+$G$431*(1-$N12))-$G$430 -> 6013.8287 | AH12: =$O12+$G$435+$N12*$G$431+$R12*($Q12*(1+L$9)+$G$431*(1-$N12))-$G$430 -> 6377.2589 | AT12: =IF(Z52<$G$449,0,MIN($G$446,1+IFERROR(INT((Z52-$G$449)/$G$451),0))) -> 0 | AU12: =IF(AA52<$G$449,0,MIN($G$446,1+IFERROR(INT((AA52-$G$449)/$G$451),0))) -> 0 | AV12: =IF(AB52<$G$449,0,MIN($G$446,1+IFERROR(INT((AB52-$G$449)/$G$451),0))) -> 0 | AW12: =IF(AC52<$G$449,0,MIN($G$446,1+IFERROR(INT((AC52-$G$449)/$G$451),0))) -> 0 | AX12: =IF(AD52<$G$449,0,MIN($G$446,1+IFERROR(INT((AD52-$G$449)/$G$451),0))) -> 0 | AY12: =IF(AE52<$G$449,0,MIN($G$446,1+IFERROR(INT((AE52-$G$449)/$G$451),0))) -> 0 | AZ12: =IF(AF52<$G$449,0,MIN($G$446,1+IFERROR(INT((AF52-$G$449)/$G$451),0))) -> 1 | BA12: =IF(AG52<$G$449,0,MIN($G$446,1+IFERROR(INT((AG52-$G$449)/$G$451),0))) -> 3 | BB12: =IF(AH52<$G$449,0,MIN($G$446,1+IFERROR(INT((AH52-$G$449)/$G$451),0))) -> 4
C13: =$G$438 -> 0.3 | D13: =ROUND(Z13,$G$452) -> 4100 | E13: =ROUND(AA13,$G$452) -> 4400 | F13: =ROUND(AB13,$G$452) -> 4700 | G13: =ROUND(AC13,$G$452) -> 5100 | H13: =ROUND(AD13,$G$452) -> 5400 | I13: =ROUND(AE13,$G$452) -> 5700 | J13: =ROUND(AF13,$G$452) -> 6100 | K13: =ROUND(AG13,$G$452) -> 6400 | L13: =ROUND(AH13,$G$452) -> 6700 | N13: =$C13 -> 0.3 | O13: =$G$433 -> 650 | P13: =$G$430*(1-N13)-O13 -> 1450 | Q13: =$G$432-O13 -> 49350 | R13: =IFERROR(P13/(Q13+$G$430*(1-N13)),0)*(1-$G$434) -> 0.026773567 | Z13: =$O13+$G$435+$N13*$G$431+$R13*($Q13*(1+D$9)+$G$431*(1-$N13))-$G$430 -> 4080.8816 | AA13: =$O13+$G$435+$N13*$G$431+$R13*($Q13*(1+E$9)+$G$431*(1-$N13))-$G$430 -> 4411.2005 | AB13: =$O13+$G$435+$N13*$G$431+$R13*($Q13*(1+F$9)+$G$431*(1-$N13))-$G$430 -> 4741.5193 | AC13: =$O13+$G$435+$N13*$G$431+$R13*($Q13*(1+G$9)+$G$431*(1-$N13))-$G$430 -> 5071.8382 | AD13: =$O13+$G$435+$N13*$G$431+$R13*($Q13*(1+H$9)+$G$431*(1-$N13))-$G$430 -> 5402.1571 | AE13: =$O13+$G$435+$N13*$G$431+$R13*($Q13*(1+I$9)+$G$431*(1-$N13))-$G$430 -> 5732.476 | AF13: =$O13+$G$435+$N13*$G$431+$R13*($Q13*(1+J$9)+$G$431*(1-$N13))-$G$430 -> 6062.7949 | AG13: =$O13+$G$435+$N13*$G$431+$R13*($Q13*(1+K$9)+$G$431*(1-$N13))-$G$430 -> 6393.1137 | AH13: =$O13+$G$435+$N13*$G$431+$R13*($Q13*(1+L$9)+$G$431*(1-$N13))-$G$430 -> 6723.4326 | AT13: =IF(Z53<$G$449,0,MIN($G$446,1+IFERROR(INT((Z53-$G$449)/$G$451),0))) -> 0 | AU13: =IF(AA53<$G$449,0,MIN($G$446,1+IFERROR(INT((AA53-$G$449)/$G$451),0))) -> 0 | AV13: =IF(AB53<$G$449,0,MIN($G$446,1+IFERROR(INT((AB53-$G$449)/$G$451),0))) -> 0 | AW13: =IF(AC53<$G$449,0,MIN($G$446,1+IFERROR(INT((AC53-$G$449)/$G$451),0))) -> 0 | AX13: =IF(AD53<$G$449,0,MIN($G$446,1+IFERROR(INT((AD53-$G$449)/$G$451),0))) -> 0 | AY13: =IF(AE53<$G$449,0,MIN($G$446,1+IFERROR(INT((AE53-$G$449)/$G$451),0))) -> 2 | AZ13: =IF(AF53<$G$449,0,MIN($G$446,1+IFERROR(INT((AF53-$G$449)/$G$451),0))) -> 3 | BA13: =IF(AG53<$G$449,0,MIN($G$446,1+IFERROR(INT((AG53-$G$449)/$G$451),0))) -> 4 | BB13: =IF(AH53<$G$449,0,MIN($G$446,1+IFERROR(INT((AH53-$G$449)/$G$451),0))) -> 6
C14: =C13+$G$439 -> 0.35 | D14: =ROUND(Z14,$G$452) -> 4700 | E14: =ROUND(AA14,$G$452) -> 5000 | F14: =ROUND(AB14,$G$452) -> 5300 | G14: =ROUND(AC14,$G$452) -> 5600 | H14: =ROUND(AD14,$G$452) -> 5900 | I14: =ROUND(AE14,$G$452) -> 6200 | J14: =ROUND(AF14,$G$452) -> 6500 | K14: =ROUND(AG14,$G$452) -> 6800 | L14: =ROUND(AH14,$G$452) -> 7100 | N14: =$C14 -> 0.35 | O14: =$G$433 -> 650 | P14: =$G$430*(1-N14)-O14 -> 1300 | Q14: =$G$432-O14 -> 49350 | R14: =IFERROR(P14/(Q14+$G$430*(1-N14)),0)*(1-$G$434) -> 0.024074074 | Z14: =$O14+$G$435+$N14*$G$431+$R14*($Q14*(1+D$9)+$G$431*(1-$N14))-$G$430 -> 4695.286 | AA14: =$O14+$G$435+$N14*$G$431+$R14*($Q14*(1+E$9)+$G$431*(1-$N14))-$G$430 -> 4992.2999 | AB14: =$O14+$G$435+$N14*$G$431+$R14*($Q14*(1+F$9)+$G$431*(1-$N14))-$G$430 -> 5289.3138 | AC14: =$O14+$G$435+$N14*$G$431+$R14*($Q14*(1+G$9)+$G$431*(1-$N14))-$G$430 -> 5586.3277 | AD14: =$O14+$G$435+$N14*$G$431+$R14*($Q14*(1+H$9)+$G$431*(1-$N14))-$G$430 -> 5883.3416 | AE14: =$O14+$G$435+$N14*$G$431+$R14*($Q14*(1+I$9)+$G$431*(1-$N14))-$G$430 -> 6180.3555 | AF14: =$O14+$G$435+$N14*$G$431+$R14*($Q14*(1+J$9)+$G$431*(1-$N14))-$G$430 -> 6477.3694 | AG14: =$O14+$G$435+$N14*$G$431+$R14*($Q14*(1+K$9)+$G$431*(1-$N14))-$G$430 -> 6774.3832 | AH14: =$O14+$G$435+$N14*$G$431+$R14*($Q14*(1+L$9)+$G$431*(1-$N14))-$G$430 -> 7071.3971 | AT14: =IF(Z54<$G$449,0,MIN($G$446,1+IFERROR(INT((Z54-$G$449)/$G$451),0))) -> 0 | AU14: =IF(AA54<$G$449,0,MIN($G$446,1+IFERROR(INT((AA54-$G$449)/$G$451),0))) -> 0 | AV14: =IF(AB54<$G$449,0,MIN($G$446,1+IFERROR(INT((AB54-$G$449)/$G$451),0))) -> 0 | AW14: =IF(AC54<$G$449,0,MIN($G$446,1+IFERROR(INT((AC54-$G$449)/$G$451),0))) -> 1 | AX14: =IF(AD54<$G$449,0,MIN($G$446,1+IFERROR(INT((AD54-$G$449)/$G$451),0))) -> 2 | AY14: =IF(AE54<$G$449,0,MIN($G$446,1+IFERROR(INT((AE54-$G$449)/$G$451),0))) -> 4 | AZ14: =IF(AF54<$G$449,0,MIN($G$446,1+IFERROR(INT((AF54-$G$449)/$G$451),0))) -> 5 | BA14: =IF(AG54<$G$449,0,MIN($G$446,1+IFERROR(INT((AG54-$G$449)/$G$451),0))) -> 6 | BB14: =IF(AH54<$G$449,0,MIN($G$446,1+IFERROR(INT((AH54-$G$449)/$G$451),0))) -> 7
C15: =C14+$G$439 -> 0.4 | D15: =ROUND(Z15,$G$452) -> 5300 | E15: =ROUND(AA15,$G$452) -> 5600 | F15: =ROUND(AB15,$G$452) -> 5800 | G15: =ROUND(AC15,$G$452) -> 6100 | H15: =ROUND(AD15,$G$452) -> 6400 | I15: =ROUND(AE15,$G$452) -> 6600 | J15: =ROUND(AF15,$G$452) -> 6900 | K15: =ROUND(AG15,$G$452) -> 7200 | L15: =ROUND(AH15,$G$452) -> 7400 | N15: =$C15 -> 0.4 | O15: =$G$433 -> 650 | P15: =$G$430*(1-N15)-O15 -> 1150 | Q15: =$G$432-O15 -> 49350 | R15: =IFERROR(P15/(Q15+$G$430*(1-N15)),0)*(1-$G$434) -> 0.021358749 | Z15: =$O15+$G$435+$N15*$G$431+$R15*($Q15*(1+D$9)+$G$431*(1-$N15))-$G$430 -> 5313.0598 | AA15: =$O15+$G$435+$N15*$G$431+$R15*($Q15*(1+E$9)+$G$431*(1-$N15))-$G$430 -> 5576.5733 | AB15: =$O15+$G$435+$N15*$G$431+$R15*($Q15*(1+F$9)+$G$431*(1-$N15))-$G$430 -> 5840.0869 | AC15: =$O15+$G$435+$N15*$G$431+$R15*($Q15*(1+G$9)+$G$431*(1-$N15))-$G$430 -> 6103.6004 | AD15: =$O15+$G$435+$N15*$G$431+$R15*($Q15*(1+H$9)+$G$431*(1-$N15))-$G$430 -> 6367.114 | AE15: =$O15+$G$435+$N15*$G$431+$R15*($Q15*(1+I$9)+$G$431*(1-$N15))-$G$430 -> 6630.6276 | AF15: =$O15+$G$435+$N15*$G$431+$R15*($Q15*(1+J$9)+$G$431*(1-$N15))-$G$430 -> 6894.1411 | AG15: =$O15+$G$435+$N15*$G$431+$R15*($Q15*(1+K$9)+$G$431*(1-$N15))-$G$430 -> 7157.6547 | AH15: =$O15+$G$435+$N15*$G$431+$R15*($Q15*(1+L$9)+$G$431*(1-$N15))-$G$430 -> 7421.1683 | AT15: =IF(Z55<$G$449,0,MIN($G$446,1+IFERROR(INT((Z55-$G$449)/$G$451),0))) -> 0 | AU15: =IF(AA55<$G$449,0,MIN($G$446,1+IFERROR(INT((AA55-$G$449)/$G$451),0))) -> 1 | AV15: =IF(AB55<$G$449,0,MIN($G$446,1+IFERROR(INT((AB55-$G$449)/$G$451),0))) -> 2 | AW15: =IF(AC55<$G$449,0,MIN($G$446,1+IFERROR(INT((AC55-$G$449)/$G$451),0))) -> 3 | AX15: =IF(AD55<$G$449,0,MIN($G$446,1+IFERROR(INT((AD55-$G$449)/$G$451),0))) -> 4 | AY15: =IF(AE55<$G$449,0,MIN($G$446,1+IFERROR(INT((AE55-$G$449)/$G$451),0))) -> 5 | AZ15: =IF(AF55<$G$449,0,MIN($G$446,1+IFERROR(INT((AF55-$G$449)/$G$451),0))) -> 7 | BA15: =IF(AG55<$G$449,0,MIN($G$446,1+IFERROR(INT((AG55-$G$449)/$G$451),0))) -> 8 | BB15: =IF(AH55<$G$449,0,MIN($G$446,1+IFERROR(INT((AH55-$G$449)/$G$451),0))) -> 9
C16: =C15+$G$439 -> 0.45 | D16: =ROUND(Z16,$G$452) -> 5900 | E16: =ROUND(AA16,$G$452) -> 6200 | F16: =ROUND(AB16,$G$452) -> 6400 | G16: =ROUND(AC16,$G$452) -> 6600 | H16: =ROUND(AD16,$G$452) -> 6900 | I16: =ROUND(AE16,$G$452) -> 7100 | J16: =ROUND(AF16,$G$452) -> 7300 | K16: =ROUND(AG16,$G$452) -> 7500 | L16: =ROUND(AH16,$G$452) -> 7800 | N16: =$C16 -> 0.45 | O16: =$G$433 -> 650 | P16: =$G$430*(1-N16)-O16 -> 1000 | Q16: =$G$432-O16 -> 49350 | R16: =IFERROR(P16/(Q16+$G$430*(1-N16)),0)*(1-$G$434) -> 0.018627451 | Z16: =$O16+$G$435+$N16*$G$431+$R16*($Q16*(1+D$9)+$G$431*(1-$N16))-$G$430 -> 5934.2325 | AA16: =$O16+$G$435+$N16*$G$431+$R16*($Q16*(1+E$9)+$G$431*(1-$N16))-$G$430 -> 6164.0487 | AB16: =$O16+$G$435+$N16*$G$431+$R16*($Q16*(1+F$9)+$G$431*(1-$N16))-$G$430 -> 6393.8649 | AC16: =$O16+$G$435+$N16*$G$431+$R16*($Q16*(1+G$9)+$G$431*(1-$N16))-$G$430 -> 6623.681 | AD16: =$O16+$G$435+$N16*$G$431+$R16*($Q16*(1+H$9)+$G$431*(1-$N16))-$G$430 -> 6853.4972 | AE16: =$O16+$G$435+$N16*$G$431+$R16*($Q16*(1+I$9)+$G$431*(1-$N16))-$G$430 -> 7083.3134 | AF16: =$O16+$G$435+$N16*$G$431+$R16*($Q16*(1+J$9)+$G$431*(1-$N16))-$G$430 -> 7313.1296 | AG16: =$O16+$G$435+$N16*$G$431+$R16*($Q16*(1+K$9)+$G$431*(1-$N16))-$G$430 -> 7542.9457 | AH16: =$O16+$G$435+$N16*$G$431+$R16*($Q16*(1+L$9)+$G$431*(1-$N16))-$G$430 -> 7772.7619 | AT16: =IF(Z56<$G$449,0,MIN($G$446,1+IFERROR(INT((Z56-$G$449)/$G$451),0))) -> 2 | AU16: =IF(AA56<$G$449,0,MIN($G$446,1+IFERROR(INT((AA56-$G$449)/$G$451),0))) -> 3 | AV16: =IF(AB56<$G$449,0,MIN($G$446,1+IFERROR(INT((AB56-$G$449)/$G$451),0))) -> 4 | AW16: =IF(AC56<$G$449,0,MIN($G$446,1+IFERROR(INT((AC56-$G$449)/$G$451),0))) -> 5 | AX16: =IF(AD56<$G$449,0,MIN($G$446,1+IFERROR(INT((AD56-$G$449)/$G$451),0))) -> 6 | AY16: =IF(AE56<$G$449,0,MIN($G$446,1+IFERROR(INT((AE56-$G$449)/$G$451),0))) -> 7 | AZ16: =IF(AF56<$G$449,0,MIN($G$446,1+IFERROR(INT((AF56-$G$449)/$G$451),0))) -> 8 | BA16: =IF(AG56<$G$449,0,MIN($G$446,1+IFERROR(INT((AG56-$G$449)/$G$451),0))) -> 9 | BB16: =IF(AH56<$G$449,0,MIN($G$446,1+IFERROR(INT((AH56-$G$449)/$G$451),0))) -> 10
B17: Ben's Year 5 value (cash at close + earnout + retained Keystone stake + Topkey stock, after dilution) less Keystone value today (G430)
N18: =$G$436 -> 0.3 | O18: =$G$433 -> 650 | P18: =$G$430*(1-N18)-O18 -> 1450 | Q18: =$G$432-O18 -> 49350 | R18: =IFERROR(P18/(Q18+$G$430*(1-N18)),0)*(1-$G$434) -> 0.026773567
B19: Ben's % Return on Keystone Value Based on Topkey Growth & Rollover %
D21: Topkey ex-Keystone Value Growth (%)
D22: =E22-$G$441 -> 0.013171226 | E22: =F22-$G$441 -> 0.26317123 | F22: =G22-$G$441 -> 0.51317123 | G22: =H22-$G$441 -> 0.76317123 | H22: =$G$440 -> 1.0131712 | I22: =H22+$G$441 -> 1.2631712 | J22: =I22+$G$441 -> 1.5131712 | K22: =J22+$G$441 -> 1.7631712 | L22: =K22+$G$441 -> 2.0131712 | AT22: Helper: Gradient Band (0 = below $1M hurdle)
B23: Ben's Rollover % | C23: =C24-$G$439 -> 0.15 | D23: =IFERROR(Z10/$G$430,0) -> 0.75253063 | E23: =IFERROR(AA10/$G$430,0) -> 0.89555689 | F23: =IFERROR(AB10/$G$430,0) -> 1.0385831 | G23: =IFERROR(AC10/$G$430,0) -> 1.1816094 | H23: =IFERROR(AD10/$G$430,0) -> 1.3246356 | I23: =IFERROR(AE10/$G$430,0) -> 1.4676619 | J23: =IFERROR(AF10/$G$430,0) -> 1.6106881 | K23: =IFERROR(AG10/$G$430,0) -> 1.7537144 | L23: =IFERROR(AH10/$G$430,0) -> 1.8967407 | AT23: =IF(Z50<$G$449,0,MIN($G$446,1+IFERROR(INT((Z50-$G$449)/$G$451),0))) -> 0 | AU23: =IF(AA50<$G$449,0,MIN($G$446,1+IFERROR(INT((AA50-$G$449)/$G$451),0))) -> 0 | AV23: =IF(AB50<$G$449,0,MIN($G$446,1+IFERROR(INT((AB50-$G$449)/$G$451),0))) -> 0 | AW23: =IF(AC50<$G$449,0,MIN($G$446,1+IFERROR(INT((AC50-$G$449)/$G$451),0))) -> 0 | AX23: =IF(AD50<$G$449,0,MIN($G$446,1+IFERROR(INT((AD50-$G$449)/$G$451),0))) -> 0 | AY23: =IF(AE50<$G$449,0,MIN($G$446,1+IFERROR(INT((AE50-$G$449)/$G$451),0))) -> 0 | AZ23: =IF(AF50<$G$449,0,MIN($G$446,1+IFERROR(INT((AF50-$G$449)/$G$451),0))) -> 0 | BA23: =IF(AG50<$G$449,0,MIN($G$446,1+IFERROR(INT((AG50-$G$449)/$G$451),0))) -> 0 | BB23: =IF(AH50<$G$449,0,MIN($G$446,1+IFERROR(INT((AH50-$G$449)/$G$451),0))) -> 1
C24: =C25-$G$439 -> 0.2 | D24: =IFERROR(Z11/$G$430,0) -> 0.95402113 | E24: =IFERROR(AA11/$G$430,0) -> 1.0861377 | F24: =IFERROR(AB11/$G$430,0) -> 1.2182542 | G24: =IFERROR(AC11/$G$430,0) -> 1.3503708 | H24: =IFERROR(AD11/$G$430,0) -> 1.4824873 | I24: =IFERROR(AE11/$G$430,0) -> 1.6146039 | J24: =IFERROR(AF11/$G$430,0) -> 1.7467204 | K24: =IFERROR(AG11/$G$430,0) -> 1.878837 | L24: =IFERROR(AH11/$G$430,0) -> 2.0109535 | AT24: =IF(Z51<$G$449,0,MIN($G$446,1+IFERROR(INT((Z51-$G$449)/$G$451),0))) -> 0 | AU24: =IF(AA51<$G$449,0,MIN($G$446,1+IFERROR(INT((AA51-$G$449)/$G$451),0))) -> 0 | AV24: =IF(AB51<$G$449,0,MIN($G$446,1+IFERROR(INT((AB51-$G$449)/$G$451),0))) -> 0 | AW24: =IF(AC51<$G$449,0,MIN($G$446,1+IFERROR(INT((AC51-$G$449)/$G$451),0))) -> 0 | AX24: =IF(AD51<$G$449,0,MIN($G$446,1+IFERROR(INT((AD51-$G$449)/$G$451),0))) -> 0 | AY24: =IF(AE51<$G$449,0,MIN($G$446,1+IFERROR(INT((AE51-$G$449)/$G$451),0))) -> 0 | AZ24: =IF(AF51<$G$449,0,MIN($G$446,1+IFERROR(INT((AF51-$G$449)/$G$451),0))) -> 0 | BA24: =IF(AG51<$G$449,0,MIN($G$446,1+IFERROR(INT((AG51-$G$449)/$G$451),0))) -> 1 | BB24: =IF(AH51<$G$449,0,MIN($G$446,1+IFERROR(INT((AH51-$G$449)/$G$451),0))) -> 3
C25: =C26-$G$439 -> 0.25 | D25: =IFERROR(Z12/$G$430,0) -> 1.1566057 | E25: =IFERROR(AA12/$G$430,0) -> 1.2777491 | F25: =IFERROR(AB12/$G$430,0) -> 1.3988925 | G25: =IFERROR(AC12/$G$430,0) -> 1.5200359 | H25: =IFERROR(AD12/$G$430,0) -> 1.6411793 | I25: =IFERROR(AE12/$G$430,0) -> 1.7623227 | J25: =IFERROR(AF12/$G$430,0) -> 1.8834662 | K25: =IFERROR(AG12/$G$430,0) -> 2.0046096 | L25: =IFERROR(AH12/$G$430,0) -> 2.125753 | AT25: =IF(Z52<$G$449,0,MIN($G$446,1+IFERROR(INT((Z52-$G$449)/$G$451),0))) -> 0 | AU25: =IF(AA52<$G$449,0,MIN($G$446,1+IFERROR(INT((AA52-$G$449)/$G$451),0))) -> 0 | AV25: =IF(AB52<$G$449,0,MIN($G$446,1+IFERROR(INT((AB52-$G$449)/$G$451),0))) -> 0 | AW25: =IF(AC52<$G$449,0,MIN($G$446,1+IFERROR(INT((AC52-$G$449)/$G$451),0))) -> 0 | AX25: =IF(AD52<$G$449,0,MIN($G$446,1+IFERROR(INT((AD52-$G$449)/$G$451),0))) -> 0 | AY25: =IF(AE52<$G$449,0,MIN($G$446,1+IFERROR(INT((AE52-$G$449)/$G$451),0))) -> 0 | AZ25: =IF(AF52<$G$449,0,MIN($G$446,1+IFERROR(INT((AF52-$G$449)/$G$451),0))) -> 1 | BA25: =IF(AG52<$G$449,0,MIN($G$446,1+IFERROR(INT((AG52-$G$449)/$G$451),0))) -> 3 | BB25: =IF(AH52<$G$449,0,MIN($G$446,1+IFERROR(INT((AH52-$G$449)/$G$451),0))) -> 4
C26: =$G$438 -> 0.3 | D26: =IFERROR(Z13/$G$430,0) -> 1.3602939 | E26: =IFERROR(AA13/$G$430,0) -> 1.4704002 | F26: =IFERROR(AB13/$G$430,0) -> 1.5805064 | G26: =IFERROR(AC13/$G$430,0) -> 1.6906127 | H26: =IFERROR(AD13/$G$430,0) -> 1.800719 | I26: =IFERROR(AE13/$G$430,0) -> 1.9108253 | J26: =IFERROR(AF13/$G$430,0) -> 2.0209316 | K26: =IFERROR(AG13/$G$430,0) -> 2.1310379 | L26: =IFERROR(AH13/$G$430,0) -> 2.2411442 | AT26: =IF(Z53<$G$449,0,MIN($G$446,1+IFERROR(INT((Z53-$G$449)/$G$451),0))) -> 0 | AU26: =IF(AA53<$G$449,0,MIN($G$446,1+IFERROR(INT((AA53-$G$449)/$G$451),0))) -> 0 | AV26: =IF(AB53<$G$449,0,MIN($G$446,1+IFERROR(INT((AB53-$G$449)/$G$451),0))) -> 0 | AW26: =IF(AC53<$G$449,0,MIN($G$446,1+IFERROR(INT((AC53-$G$449)/$G$451),0))) -> 0 | AX26: =IF(AD53<$G$449,0,MIN($G$446,1+IFERROR(INT((AD53-$G$449)/$G$451),0))) -> 0 | AY26: =IF(AE53<$G$449,0,MIN($G$446,1+IFERROR(INT((AE53-$G$449)/$G$451),0))) -> 2 | AZ26: =IF(AF53<$G$449,0,MIN($G$446,1+IFERROR(INT((AF53-$G$449)/$G$451),0))) -> 3 | BA26: =IF(AG53<$G$449,0,MIN($G$446,1+IFERROR(INT((AG53-$G$449)/$G$451),0))) -> 4 | BB26: =IF(AH53<$G$449,0,MIN($G$446,1+IFERROR(INT((AH53-$G$449)/$G$451),0))) -> 6
C27: =C26+$G$439 -> 0.35 | D27: =IFERROR(Z14/$G$430,0) -> 1.5650953 | E27: =IFERROR(AA14/$G$430,0) -> 1.6641 | F27: =IFERROR(AB14/$G$430,0) -> 1.7631046 | G27: =IFERROR(AC14/$G$430,0) -> 1.8621092 | H27: =IFERROR(AD14/$G$430,0) -> 1.9611139 | I27: =IFERROR(AE14/$G$430,0) -> 2.0601185 | J27: =IFERROR(AF14/$G$430,0) -> 2.1591231 | K27: =IFERROR(AG14/$G$430,0) -> 2.2581277 | L27: =IFERROR(AH14/$G$430,0) -> 2.3571324 | AT27: =IF(Z54<$G$449,0,MIN($G$446,1+IFERROR(INT((Z54-$G$449)/$G$451),0))) -> 0 | AU27: =IF(AA54<$G$449,0,MIN($G$446,1+IFERROR(INT((AA54-$G$449)/$G$451),0))) -> 0 | AV27: =IF(AB54<$G$449,0,MIN($G$446,1+IFERROR(INT((AB54-$G$449)/$G$451),0))) -> 0 | AW27: =IF(AC54<$G$449,0,MIN($G$446,1+IFERROR(INT((AC54-$G$449)/$G$451),0))) -> 1 | AX27: =IF(AD54<$G$449,0,MIN($G$446,1+IFERROR(INT((AD54-$G$449)/$G$451),0))) -> 2 | AY27: =IF(AE54<$G$449,0,MIN($G$446,1+IFERROR(INT((AE54-$G$449)/$G$451),0))) -> 4 | AZ27: =IF(AF54<$G$449,0,MIN($G$446,1+IFERROR(INT((AF54-$G$449)/$G$451),0))) -> 5 | BA27: =IF(AG54<$G$449,0,MIN($G$446,1+IFERROR(INT((AG54-$G$449)/$G$451),0))) -> 6 | BB27: =IF(AH54<$G$449,0,MIN($G$446,1+IFERROR(INT((AH54-$G$449)/$G$451),0))) -> 7
C28: =C27+$G$439 -> 0.4 | D28: =IFERROR(Z15/$G$430,0) -> 1.7710199 | E28: =IFERROR(AA15/$G$430,0) -> 1.8588578 | F28: =IFERROR(AB15/$G$430,0) -> 1.9466956 | G28: =IFERROR(AC15/$G$430,0) -> 2.0345335 | H28: =IFERROR(AD15/$G$430,0) -> 2.1223713 | I28: =IFERROR(AE15/$G$430,0) -> 2.2102092 | J28: =IFERROR(AF15/$G$430,0) -> 2.298047 | K28: =IFERROR(AG15/$G$430,0) -> 2.3858849 | L28: =IFERROR(AH15/$G$430,0) -> 2.4737228 | AT28: =IF(Z55<$G$449,0,MIN($G$446,1+IFERROR(INT((Z55-$G$449)/$G$451),0))) -> 0 | AU28: =IF(AA55<$G$449,0,MIN($G$446,1+IFERROR(INT((AA55-$G$449)/$G$451),0))) -> 1 | AV28: =IF(AB55<$G$449,0,MIN($G$446,1+IFERROR(INT((AB55-$G$449)/$G$451),0))) -> 2 | AW28: =IF(AC55<$G$449,0,MIN($G$446,1+IFERROR(INT((AC55-$G$449)/$G$451),0))) -> 3 | AX28: =IF(AD55<$G$449,0,MIN($G$446,1+IFERROR(INT((AD55-$G$449)/$G$451),0))) -> 4 | AY28: =IF(AE55<$G$449,0,MIN($G$446,1+IFERROR(INT((AE55-$G$449)/$G$451),0))) -> 5 | AZ28: =IF(AF55<$G$449,0,MIN($G$446,1+IFERROR(INT((AF55-$G$449)/$G$451),0))) -> 7 | BA28: =IF(AG55<$G$449,0,MIN($G$446,1+IFERROR(INT((AG55-$G$449)/$G$451),0))) -> 8 | BB28: =IF(AH55<$G$449,0,MIN($G$446,1+IFERROR(INT((AH55-$G$449)/$G$451),0))) -> 9
C29: =C28+$G$439 -> 0.45 | D29: =IFERROR(Z16/$G$430,0) -> 1.9780775 | E29: =IFERROR(AA16/$G$430,0) -> 2.0546829 | F29: =IFERROR(AB16/$G$430,0) -> 2.1312883 | G29: =IFERROR(AC16/$G$430,0) -> 2.2078937 | H29: =IFERROR(AD16/$G$430,0) -> 2.2844991 | I29: =IFERROR(AE16/$G$430,0) -> 2.3611045 | J29: =IFERROR(AF16/$G$430,0) -> 2.4377099 | K29: =IFERROR(AG16/$G$430,0) -> 2.5143152 | L29: =IFERROR(AH16/$G$430,0) -> 2.5909206 | AT29: =IF(Z56<$G$449,0,MIN($G$446,1+IFERROR(INT((Z56-$G$449)/$G$451),0))) -> 2 | AU29: =IF(AA56<$G$449,0,MIN($G$446,1+IFERROR(INT((AA56-$G$449)/$G$451),0))) -> 3 | AV29: =IF(AB56<$G$449,0,MIN($G$446,1+IFERROR(INT((AB56-$G$449)/$G$451),0))) -> 4 | AW29: =IF(AC56<$G$449,0,MIN($G$446,1+IFERROR(INT((AC56-$G$449)/$G$451),0))) -> 5 | AX29: =IF(AD56<$G$449,0,MIN($G$446,1+IFERROR(INT((AD56-$G$449)/$G$451),0))) -> 6 | AY29: =IF(AE56<$G$449,0,MIN($G$446,1+IFERROR(INT((AE56-$G$449)/$G$451),0))) -> 7 | AZ29: =IF(AF56<$G$449,0,MIN($G$446,1+IFERROR(INT((AF56-$G$449)/$G$451),0))) -> 8 | BA29: =IF(AG56<$G$449,0,MIN($G$446,1+IFERROR(INT((AG56-$G$449)/$G$451),0))) -> 9 | BB29: =IF(AH56<$G$449,0,MIN($G$446,1+IFERROR(INT((AH56-$G$449)/$G$451),0))) -> 10
B30: Ben's Year 5 total value ÷ Keystone value today (G430), less 1
B32: Ben's IRR Based on Topkey Growth & Rollover %
D34: Topkey ex-Keystone Value Growth (%) | BD34: Helper: IRR CF — Col D | BJ34: Helper: IRR CF — Col E | BP34: Helper: IRR CF — Col F | BV34: Helper: IRR CF — Col G | CB34: Helper: IRR CF — Col H | CH34: Helper: IRR CF — Col I | CN34: Helper: IRR CF — Col J | CT34: Helper: IRR CF — Col K | CZ34: Helper: IRR CF — Col L
D35: =E35-$G$441 -> 0.013171226 | E35: =F35-$G$441 -> 0.26317123 | F35: =G35-$G$441 -> 0.51317123 | G35: =H35-$G$441 -> 0.76317123 | H35: =$G$440 -> 1.0131712 | I35: =H35+$G$441 -> 1.2631712 | J35: =I35+$G$441 -> 1.5131712 | K35: =J35+$G$441 -> 1.7631712 | L35: =K35+$G$441 -> 2.0131712 | AT35: Helper: Gradient Band (0 = below $1M hurdle) | BD35: =$S$9 -> 0 | BE35: =$T$9 -> 1 | BF35: =$U$9 -> 2 | BG35: =$V$9 -> 3 | BH35: =$W$9 -> 4 | BI35: =$X$9 -> 5 | BJ35: =$S$9 -> 0 | BK35: =$T$9 -> 1 | BL35: =$U$9 -> 2 | BM35: =$V$9 -> 3 | BN35: =$W$9 -> 4 | BO35: =$X$9 -> 5 | BP35: =$S$9 -> 0 | BQ35: =$T$9 -> 1 | BR35: =$U$9 -> 2 | BS35: =$V$9 -> 3 | BT35: =$W$9 -> 4 | BU35: =$X$9 -> 5 | BV35: =$S$9 -> 0 | BW35: =$T$9 -> 1 | BX35: =$U$9 -> 2 | BY35: =$V$9 -> 3 | BZ35: =$W$9 -> 4 | CA35: =$X$9 -> 5 | CB35: =$S$9 -> 0 | CC35: =$T$9 -> 1 | CD35: =$U$9 -> 2 | CE35: =$V$9 -> 3 | CF35: =$W$9 -> 4 | CG35: =$X$9 -> 5 | CH35: =$S$9 -> 0 | CI35: =$T$9 -> 1 | CJ35: =$U$9 -> 2 | CK35: =$V$9 -> 3 | CL35: =$W$9 -> 4 | CM35: =$X$9 -> 5 | CN35: =$S$9 -> 0 | CO35: =$T$9 -> 1 | CP35: =$U$9 -> 2 | CQ35: =$V$9 -> 3 | CR35: =$W$9 -> 4 | CS35: =$X$9 -> 5 | CT35: =$S$9 -> 0 | CU35: =$T$9 -> 1 | CV35: =$U$9 -> 2 | CW35: =$V$9 -> 3 | CX35: =$W$9 -> 4 | CY35: =$X$9 -> 5 | CZ35: =$S$9 -> 0 | DA35: =$T$9 -> 1 | DB35: =$U$9 -> 2 | DC35: =$V$9 -> 3 | DD35: =$W$9 -> 4 | DE35: =$X$9 -> 5
B36: Ben's Rollover % | C36: =C37-$G$439 -> 0.15 | D36: =IFERROR(IRR(BD36:BI36),0) -> 0.14414543 | E36: =IFERROR(IRR(BJ36:BO36),0) -> 0.16470285 | F36: =IFERROR(IRR(BP36:BU36),0) -> 0.18390368 | G36: =IFERROR(IRR(BV36:CA36),0) -> 0.2019341 | H36: =IFERROR(IRR(CB36:CG36),0) -> 0.21894335 | I36: =IFERROR(IRR(CH36:CM36),0) -> 0.235053 | J36: =IFERROR(IRR(CN36:CS36),0) -> 0.2503635 | K36: =IFERROR(IRR(CT36:CY36),0) -> 0.26495887 | L36: =IFERROR(IRR(CZ36:DE36),0) -> 0.27891015 | AT36: =IF(Z50<$G$449,0,MIN($G$446,1+IFERROR(INT((Z50-$G$449)/$G$451),0))) -> 0 | AU36: =IF(AA50<$G$449,0,MIN($G$446,1+IFERROR(INT((AA50-$G$449)/$G$451),0))) -> 0 | AV36: =IF(AB50<$G$449,0,MIN($G$446,1+IFERROR(INT((AB50-$G$449)/$G$451),0))) -> 0 | AW36: =IF(AC50<$G$449,0,MIN($G$446,1+IFERROR(INT((AC50-$G$449)/$G$451),0))) -> 0 | AX36: =IF(AD50<$G$449,0,MIN($G$446,1+IFERROR(INT((AD50-$G$449)/$G$451),0))) -> 0 | AY36: =IF(AE50<$G$449,0,MIN($G$446,1+IFERROR(INT((AE50-$G$449)/$G$451),0))) -> 0 | AZ36: =IF(AF50<$G$449,0,MIN($G$446,1+IFERROR(INT((AF50-$G$449)/$G$451),0))) -> 0 | BA36: =IF(AG50<$G$449,0,MIN($G$446,1+IFERROR(INT((AG50-$G$449)/$G$451),0))) -> 0 | BB36: =IF(AH50<$G$449,0,MIN($G$446,1+IFERROR(INT((AH50-$G$449)/$G$451),0))) -> 1 | BD36: =(BD$35=0)*($O10-$G$430)+(BD$35=$G$444)*$G$435+(BD$35=$G$445)*(Z10+$G$430-$O10-$G$435) -> -2350 | BE36: =(BE$35=0)*($O10-$G$430)+(BE$35=$G$444)*$G$435+(BE$35=$G$445)*(Z10+$G$430-$O10-$G$435) -> 0 | BF36: =(BF$35=0)*($O10-$G$430)+(BF$35=$G$444)*$G$435+(BF$35=$G$445)*(Z10+$G$430-$O10-$G$435) -> 0 | BG36: =(BG$35=0)*($O10-$G$430)+(BG$35=$G$444)*$G$435+(BG$35=$G$445)*(Z10+$G$430-$O10-$G$435) -> 0 | BH36: =(BH$35=0)*($O10-$G$430)+(BH$35=$G$444)*$G$435+(BH$35=$G$445)*(Z10+$G$430-$O10-$G$435) -> 0 | BI36: =(BI$35=0)*($O10-$G$430)+(BI$35=$G$444)*$G$435+(BI$35=$G$445)*(Z10+$G$430-$O10-$G$435) -> 4607.5919 | BJ36: =(BJ$35=0)*($O10-$G$430)+(BJ$35=$G$444)*$G$435+(BJ$35=$G$445)*(AA10+$G$430-$O10-$G$435) -> -2350 | BK36: =(BK$35=0)*($O10-$G$430)+(BK$35=$G$444)*$G$435+(BK$35=$G$445)*(AA10+$G$430-$O10-$G$435) -> 0 | BL36: =(BL$35=0)*($O10-$G$430)+(BL$35=$G$444)*$G$435+(BL$35=$G$445)*(AA10+$G$430-$O10-$G$435) -> 0 | BM36: =(BM$35=0)*($O10-$G$430)+(BM$35=$G$444)*$G$435+(BM$35=$G$445)*(AA10+$G$430-$O10-$G$435) -> 0 | BN36: =(BN$35=0)*($O10-$G$430)+(BN$35=$G$444)*$G$435+(BN$35=$G$445)*(AA10+$G$430-$O10-$G$435) -> 0 | BO36: =(BO$35=0)*($O10-$G$430)+(BO$35=$G$444)*$G$435+(BO$35=$G$445)*(AA10+$G$430-$O10-$G$435) -> 5036.6707 | BP36: =(BP$35=0)*($O10-$G$430)+(BP$35=$G$444)*$G$435+(BP$35=$G$445)*(AB10+$G$430-$O10-$G$435) -> -2350 | BQ36: =(BQ$35=0)*($O10-$G$430)+(BQ$35=$G$444)*$G$435+(BQ$35=$G$445)*(AB10+$G$430-$O10-$G$435) -> 0 | BR36: =(BR$35=0)*($O10-$G$430)+(BR$35=$G$444)*$G$435+(BR$35=$G$445)*(AB10+$G$430-$O10-$G$435) -> 0 | BS36: =(BS$35=0)*($O10-$G$430)+(BS$35=$G$444)*$G$435+(BS$35=$G$445)*(AB10+$G$430-$O10-$G$435) -> 0 | BT36: =(BT$35=0)*($O10-$G$430)+(BT$35=$G$444)*$G$435+(BT$35=$G$445)*(AB10+$G$430-$O10-$G$435) -> 0 | BU36: =(BU$35=0)*($O10-$G$430)+(BU$35=$G$444)*$G$435+(BU$35=$G$445)*(AB10+$G$430-$O10-$G$435) -> 5465.7494 | BV36: =(BV$35=0)*($O10-$G$430)+(BV$35=$G$444)*$G$435+(BV$35=$G$445)*(AC10+$G$430-$O10-$G$435) -> -2350 | BW36: =(BW$35=0)*($O10-$G$430)+(BW$35=$G$444)*$G$435+(BW$35=$G$445)*(AC10+$G$430-$O10-$G$435) -> 0 | BX36: =(BX$35=0)*($O10-$G$430)+(BX$35=$G$444)*$G$435+(BX$35=$G$445)*(AC10+$G$430-$O10-$G$435) -> 0 | BY36: =(BY$35=0)*($O10-$G$430)+(BY$35=$G$444)*$G$435+(BY$35=$G$445)*(AC10+$G$430-$O10-$G$435) -> 0 | BZ36: =(BZ$35=0)*($O10-$G$430)+(BZ$35=$G$444)*$G$435+(BZ$35=$G$445)*(AC10+$G$430-$O10-$G$435) -> 0 | CA36: =(CA$35=0)*($O10-$G$430)+(CA$35=$G$444)*$G$435+(CA$35=$G$445)*(AC10+$G$430-$O10-$G$435) -> 5894.8282 | CB36: =(CB$35=0)*($O10-$G$430)+(CB$35=$G$444)*$G$435+(CB$35=$G$445)*(AD10+$G$430-$O10-$G$435) -> -2350 | CC36: =(CC$35=0)*($O10-$G$430)+(CC$35=$G$444)*$G$435+(CC$35=$G$445)*(AD10+$G$430-$O10-$G$435) -> 0 | CD36: =(CD$35=0)*($O10-$G$430)+(CD$35=$G$444)*$G$435+(CD$35=$G$445)*(AD10+$G$430-$O10-$G$435) -> 0 | CE36: =(CE$35=0)*($O10-$G$430)+(CE$35=$G$444)*$G$435+(CE$35=$G$445)*(AD10+$G$430-$O10-$G$435) -> 0 | CF36: =(CF$35=0)*($O10-$G$430)+(CF$35=$G$444)*$G$435+(CF$35=$G$445)*(AD10+$G$430-$O10-$G$435) -> 0 | CG36: =(CG$35=0)*($O10-$G$430)+(CG$35=$G$444)*$G$435+(CG$35=$G$445)*(AD10+$G$430-$O10-$G$435) -> 6323.9069 | CH36: =(CH$35=0)*($O10-$G$430)+(CH$35=$G$444)*$G$435+(CH$35=$G$445)*(AE10+$G$430-$O10-$G$435) -> -2350 | CI36: =(CI$35=0)*($O10-$G$430)+(CI$35=$G$444)*$G$435+(CI$35=$G$445)*(AE10+$G$430-$O10-$G$435) -> 0 | CJ36: =(CJ$35=0)*($O10-$G$430)+(CJ$35=$G$444)*$G$435+(CJ$35=$G$445)*(AE10+$G$430-$O10-$G$435) -> 0 | CK36: =(CK$35=0)*($O10-$G$430)+(CK$35=$G$444)*$G$435+(CK$35=$G$445)*(AE10+$G$430-$O10-$G$435) -> 0 | CL36: =(CL$35=0)*($O10-$G$430)+(CL$35=$G$444)*$G$435+(CL$35=$G$445)*(AE10+$G$430-$O10-$G$435) -> 0 | CM36: =(CM$35=0)*($O10-$G$430)+(CM$35=$G$444)*$G$435+(CM$35=$G$445)*(AE10+$G$430-$O10-$G$435) -> 6752.9857 | CN36: =(CN$35=0)*($O10-$G$430)+(CN$35=$G$444)*$G$435+(CN$35=$G$445)*(AF10+$G$430-$O10-$G$435) -> -2350 | CO36: =(CO$35=0)*($O10-$G$430)+(CO$35=$G$444)*$G$435+(CO$35=$G$445)*(AF10+$G$430-$O10-$G$435) -> 0 | CP36: =(CP$35=0)*($O10-$G$430)+(CP$35=$G$444)*$G$435+(CP$35=$G$445)*(AF10+$G$430-$O10-$G$435) -> 0 | CQ36: =(CQ$35=0)*($O10-$G$430)+(CQ$35=$G$444)*$G$435+(CQ$35=$G$445)*(AF10+$G$430-$O10-$G$435) -> 0 | CR36: =(CR$35=0)*($O10-$G$430)+(CR$35=$G$444)*$G$435+(CR$35=$G$445)*(AF10+$G$430-$O10-$G$435) -> 0 | CS36: =(CS$35=0)*($O10-$G$430)+(CS$35=$G$444)*$G$435+(CS$35=$G$445)*(AF10+$G$430-$O10-$G$435) -> 7182.0644 | CT36: =(CT$35=0)*($O10-$G$430)+(CT$35=$G$444)*$G$435+(CT$35=$G$445)*(AG10+$G$430-$O10-$G$435) -> -2350 | CU36: =(CU$35=0)*($O10-$G$430)+(CU$35=$G$444)*$G$435+(CU$35=$G$445)*(AG10+$G$430-$O10-$G$435) -> 0 | CV36: =(CV$35=0)*($O10-$G$430)+(CV$35=$G$444)*$G$435+(CV$35=$G$445)*(AG10+$G$430-$O10-$G$435) -> 0 | CW36: =(CW$35=0)*($O10-$G$430)+(CW$35=$G$444)*$G$435+(CW$35=$G$445)*(AG10+$G$430-$O10-$G$435) -> 0 | CX36: =(CX$35=0)*($O10-$G$430)+(CX$35=$G$444)*$G$435+(CX$35=$G$445)*(AG10+$G$430-$O10-$G$435) -> 0 | CY36: =(CY$35=0)*($O10-$G$430)+(CY$35=$G$444)*$G$435+(CY$35=$G$445)*(AG10+$G$430-$O10-$G$435) -> 7611.1432 | CZ36: =(CZ$35=0)*($O10-$G$430)+(CZ$35=$G$444)*$G$435+(CZ$35=$G$445)*(AH10+$G$430-$O10-$G$435) -> -2350 | DA36: =(DA$35=0)*($O10-$G$430)+(DA$35=$G$444)*$G$435+(DA$35=$G$445)*(AH10+$G$430-$O10-$G$435) -> 0 | DB36: =(DB$35=0)*($O10-$G$430)+(DB$35=$G$444)*$G$435+(DB$35=$G$445)*(AH10+$G$430-$O10-$G$435) -> 0 | DC36: =(DC$35=0)*($O10-$G$430)+(DC$35=$G$444)*$G$435+(DC$35=$G$445)*(AH10+$G$430-$O10-$G$435) -> 0 | DD36: =(DD$35=0)*($O10-$G$430)+(DD$35=$G$444)*$G$435+(DD$35=$G$445)*(AH10+$G$430-$O10-$G$435) -> 0 | DE36: =(DE$35=0)*($O10-$G$430)+(DE$35=$G$444)*$G$435+(DE$35=$G$445)*(AH10+$G$430-$O10-$G$435) -> 8040.222
C37: =C38-$G$439 -> 0.2 | D37: =IFERROR(IRR(BD37:BI37),0) -> 0.17270389 | E37: =IFERROR(IRR(BJ37:BO37),0) -> 0.19002045 | F37: =IFERROR(IRR(BP37:BU37),0) -> 0.20638408 | G37: =IFERROR(IRR(BV37:CA37),0) -> 0.22190521 | H37: =IFERROR(IRR(CB37:CG37),0) -> 0.23667558 | I37: =IFERROR(IRR(CH37:CM37),0) -> 0.25077226 | J37: =IFERROR(IRR(CN37:CS37),0) -> 0.26426067 | K37: =IFERROR(IRR(CT37:CY37),0) -> 0.27719687 | L37: =IFERROR(IRR(CZ37:DE37),0) -> 0.28962925 | AT37: =IF(Z51<$G$449,0,MIN($G$446,1+IFERROR(INT((Z51-$G$449)/$G$451),0))) -> 0 | AU37: =IF(AA51<$G$449,0,MIN($G$446,1+IFERROR(INT((AA51-$G$449)/$G$451),0))) -> 0 | AV37: =IF(AB51<$G$449,0,MIN($G$446,1+IFERROR(INT((AB51-$G$449)/$G$451),0))) -> 0 | AW37: =IF(AC51<$G$449,0,MIN($G$446,1+IFERROR(INT((AC51-$G$449)/$G$451),0))) -> 0 | AX37: =IF(AD51<$G$449,0,MIN($G$446,1+IFERROR(INT((AD51-$G$449)/$G$451),0))) -> 0 | AY37: =IF(AE51<$G$449,0,MIN($G$446,1+IFERROR(INT((AE51-$G$449)/$G$451),0))) -> 0 | AZ37: =IF(AF51<$G$449,0,MIN($G$446,1+IFERROR(INT((AF51-$G$449)/$G$451),0))) -> 0 | BA37: =IF(AG51<$G$449,0,MIN($G$446,1+IFERROR(INT((AG51-$G$449)/$G$451),0))) -> 1 | BB37: =IF(AH51<$G$449,0,MIN($G$446,1+IFERROR(INT((AH51-$G$449)/$G$451),0))) -> 3 | BD37: =(BD$35=0)*($O11-$G$430)+(BD$35=$G$444)*$G$435+(BD$35=$G$445)*(Z11+$G$430-$O11-$G$435) -> -2350 | BE37: =(BE$35=0)*($O11-$G$430)+(BE$35=$G$444)*$G$435+(BE$35=$G$445)*(Z11+$G$430-$O11-$G$435) -> 0 | BF37: =(BF$35=0)*($O11-$G$430)+(BF$35=$G$444)*$G$435+(BF$35=$G$445)*(Z11+$G$430-$O11-$G$435) -> 0 | BG37: =(BG$35=0)*($O11-$G$430)+(BG$35=$G$444)*$G$435+(BG$35=$G$445)*(Z11+$G$430-$O11-$G$435) -> 0 | BH37: =(BH$35=0)*($O11-$G$430)+(BH$35=$G$444)*$G$435+(BH$35=$G$445)*(Z11+$G$430-$O11-$G$435) -> 0 | BI37: =(BI$35=0)*($O11-$G$430)+(BI$35=$G$444)*$G$435+(BI$35=$G$445)*(Z11+$G$430-$O11-$G$435) -> 5212.0634 | BJ37: =(BJ$35=0)*($O11-$G$430)+(BJ$35=$G$444)*$G$435+(BJ$35=$G$445)*(AA11+$G$430-$O11-$G$435) -> -2350 | BK37: =(BK$35=0)*($O11-$G$430)+(BK$35=$G$444)*$G$435+(BK$35=$G$445)*(AA11+$G$430-$O11-$G$435) -> 0 | BL37: =(BL$35=0)*($O11-$G$430)+(BL$35=$G$444)*$G$435+(BL$35=$G$445)*(AA11+$G$430-$O11-$G$435) -> 0 | BM37: =(BM$35=0)*($O11-$G$430)+(BM$35=$G$444)*$G$435+(BM$35=$G$445)*(AA11+$G$430-$O11-$G$435) -> 0 | BN37: =(BN$35=0)*($O11-$G$430)+(BN$35=$G$444)*$G$435+(BN$35=$G$445)*(AA11+$G$430-$O11-$G$435) -> 0 | BO37: =(BO$35=0)*($O11-$G$430)+(BO$35=$G$444)*$G$435+(BO$35=$G$445)*(AA11+$G$430-$O11-$G$435) -> 5608.413 | BP37: =(BP$35=0)*($O11-$G$430)+(BP$35=$G$444)*$G$435+(BP$35=$G$445)*(AB11+$G$430-$O11-$G$435) -> -2350 | BQ37: =(BQ$35=0)*($O11-$G$430)+(BQ$35=$G$444)*$G$435+(BQ$35=$G$445)*(AB11+$G$430-$O11-$G$435) -> 0 | BR37: =(BR$35=0)*($O11-$G$430)+(BR$35=$G$444)*$G$435+(BR$35=$G$445)*(AB11+$G$430-$O11-$G$435) -> 0 | BS37: =(BS$35=0)*($O11-$G$430)+(BS$35=$G$444)*$G$435+(BS$35=$G$445)*(AB11+$G$430-$O11-$G$435) -> 0 | BT37: =(BT$35=0)*($O11-$G$430)+(BT$35=$G$444)*$G$435+(BT$35=$G$445)*(AB11+$G$430-$O11-$G$435) -> 0 | BU37: =(BU$35=0)*($O11-$G$430)+(BU$35=$G$444)*$G$435+(BU$35=$G$445)*(AB11+$G$430-$O11-$G$435) -> 6004.7627 | BV37: =(BV$35=0)*($O11-$G$430)+(BV$35=$G$444)*$G$435+(BV$35=$G$445)*(AC11+$G$430-$O11-$G$435) -> -2350 | BW37: =(BW$35=0)*($O11-$G$430)+(BW$35=$G$444)*$G$435+(BW$35=$G$445)*(AC11+$G$430-$O11-$G$435) -> 0 | BX37: =(BX$35=0)*($O11-$G$430)+(BX$35=$G$444)*$G$435+(BX$35=$G$445)*(AC11+$G$430-$O11-$G$435) -> 0 | BY37: =(BY$35=0)*($O11-$G$430)+(BY$35=$G$444)*$G$435+(BY$35=$G$445)*(AC11+$G$430-$O11-$G$435) -> 0 | BZ37: =(BZ$35=0)*($O11-$G$430)+(BZ$35=$G$444)*$G$435+(BZ$35=$G$445)*(AC11+$G$430-$O11-$G$435) -> 0 | CA37: =(CA$35=0)*($O11-$G$430)+(CA$35=$G$444)*$G$435+(CA$35=$G$445)*(AC11+$G$430-$O11-$G$435) -> 6401.1123 | CB37: =(CB$35=0)*($O11-$G$430)+(CB$35=$G$444)*$G$435+(CB$35=$G$445)*(AD11+$G$430-$O11-$G$435) -> -2350 | CC37: =(CC$35=0)*($O11-$G$430)+(CC$35=$G$444)*$G$435+(CC$35=$G$445)*(AD11+$G$430-$O11-$G$435) -> 0 | CD37: =(CD$35=0)*($O11-$G$430)+(CD$35=$G$444)*$G$435+(CD$35=$G$445)*(AD11+$G$430-$O11-$G$435) -> 0 | CE37: =(CE$35=0)*($O11-$G$430)+(CE$35=$G$444)*$G$435+(CE$35=$G$445)*(AD11+$G$430-$O11-$G$435) -> 0 | CF37: =(CF$35=0)*($O11-$G$430)+(CF$35=$G$444)*$G$435+(CF$35=$G$445)*(AD11+$G$430-$O11-$G$435) -> 0 | CG37: =(CG$35=0)*($O11-$G$430)+(CG$35=$G$444)*$G$435+(CG$35=$G$445)*(AD11+$G$430-$O11-$G$435) -> 6797.462 | CH37: =(CH$35=0)*($O11-$G$430)+(CH$35=$G$444)*$G$435+(CH$35=$G$445)*(AE11+$G$430-$O11-$G$435) -> -2350 | CI37: =(CI$35=0)*($O11-$G$430)+(CI$35=$G$444)*$G$435+(CI$35=$G$445)*(AE11+$G$430-$O11-$G$435) -> 0 | CJ37: =(CJ$35=0)*($O11-$G$430)+(CJ$35=$G$444)*$G$435+(CJ$35=$G$445)*(AE11+$G$430-$O11-$G$435) -> 0 | CK37: =(CK$35=0)*($O11-$G$430)+(CK$35=$G$444)*$G$435+(CK$35=$G$445)*(AE11+$G$430-$O11-$G$435) -> 0 | CL37: =(CL$35=0)*($O11-$G$430)+(CL$35=$G$444)*$G$435+(CL$35=$G$445)*(AE11+$G$430-$O11-$G$435) -> 0 | CM37: =(CM$35=0)*($O11-$G$430)+(CM$35=$G$444)*$G$435+(CM$35=$G$445)*(AE11+$G$430-$O11-$G$435) -> 7193.8116 | CN37: =(CN$35=0)*($O11-$G$430)+(CN$35=$G$444)*$G$435+(CN$35=$G$445)*(AF11+$G$430-$O11-$G$435) -> -2350 | CO37: =(CO$35=0)*($O11-$G$430)+(CO$35=$G$444)*$G$435+(CO$35=$G$445)*(AF11+$G$430-$O11-$G$435) -> 0 | CP37: =(CP$35=0)*($O11-$G$430)+(CP$35=$G$444)*$G$435+(CP$35=$G$445)*(AF11+$G$430-$O11-$G$435) -> 0 | CQ37: =(CQ$35=0)*($O11-$G$430)+(CQ$35=$G$444)*$G$435+(CQ$35=$G$445)*(AF11+$G$430-$O11-$G$435) -> 0 | CR37: =(CR$35=0)*($O11-$G$430)+(CR$35=$G$444)*$G$435+(CR$35=$G$445)*(AF11+$G$430-$O11-$G$435) -> 0 | CS37: =(CS$35=0)*($O11-$G$430)+(CS$35=$G$444)*$G$435+(CS$35=$G$445)*(AF11+$G$430-$O11-$G$435) -> 7590.1612 | CT37: =(CT$35=0)*($O11-$G$430)+(CT$35=$G$444)*$G$435+(CT$35=$G$445)*(AG11+$G$430-$O11-$G$435) -> -2350 | CU37: =(CU$35=0)*($O11-$G$430)+(CU$35=$G$444)*$G$435+(CU$35=$G$445)*(AG11+$G$430-$O11-$G$435) -> 0 | CV37: =(CV$35=0)*($O11-$G$430)+(CV$35=$G$444)*$G$435+(CV$35=$G$445)*(AG11+$G$430-$O11-$G$435) -> 0 | CW37: =(CW$35=0)*($O11-$G$430)+(CW$35=$G$444)*$G$435+(CW$35=$G$445)*(AG11+$G$430-$O11-$G$435) -> 0 | CX37: =(CX$35=0)*($O11-$G$430)+(CX$35=$G$444)*$G$435+(CX$35=$G$445)*(AG11+$G$430-$O11-$G$435) -> 0 | CY37: =(CY$35=0)*($O11-$G$430)+(CY$35=$G$444)*$G$435+(CY$35=$G$445)*(AG11+$G$430-$O11-$G$435) -> 7986.5109 | CZ37: =(CZ$35=0)*($O11-$G$430)+(CZ$35=$G$444)*$G$435+(CZ$35=$G$445)*(AH11+$G$430-$O11-$G$435) -> -2350 | DA37: =(DA$35=0)*($O11-$G$430)+(DA$35=$G$444)*$G$435+(DA$35=$G$445)*(AH11+$G$430-$O11-$G$435) -> 0 | DB37: =(DB$35=0)*($O11-$G$430)+(DB$35=$G$444)*$G$435+(DB$35=$G$445)*(AH11+$G$430-$O11-$G$435) -> 0 | DC37: =(DC$35=0)*($O11-$G$430)+(DC$35=$G$444)*$G$435+(DC$35=$G$445)*(AH11+$G$430-$O11-$G$435) -> 0 | DD37: =(DD$35=0)*($O11-$G$430)+(DD$35=$G$444)*$G$435+(DD$35=$G$445)*(AH11+$G$430-$O11-$G$435) -> 0 | DE37: =(DE$35=0)*($O11-$G$430)+(DE$35=$G$444)*$G$435+(DE$35=$G$445)*(AH11+$G$430-$O11-$G$435) -> 8382.8605
C38: =C39-$G$439 -> 0.25 | D38: =IFERROR(IRR(BD38:BI38),0) -> 0.19885951 | E38: =IFERROR(IRR(BJ38:BO38),0) -> 0.21347197 | F38: =IFERROR(IRR(BP38:BU38),0) -> 0.22741271 | G38: =IFERROR(IRR(BV38:CA38),0) -> 0.24074745 | H38: =IFERROR(IRR(CB38:CG38),0) -> 0.25353242 | I38: =IFERROR(IRR(CH38:CM38),0) -> 0.26581613 | J38: =IFERROR(IRR(CN38:CS38),0) -> 0.27764074 | K38: =IFERROR(IRR(CT38:CY38),0) -> 0.28904314 | L38: =IFERROR(IRR(CZ38:DE38),0) -> 0.30005582 | AT38: =IF(Z52<$G$449,0,MIN($G$446,1+IFERROR(INT((Z52-$G$449)/$G$451),0))) -> 0 | AU38: =IF(AA52<$G$449,0,MIN($G$446,1+IFERROR(INT((AA52-$G$449)/$G$451),0))) -> 0 | AV38: =IF(AB52<$G$449,0,MIN($G$446,1+IFERROR(INT((AB52-$G$449)/$G$451),0))) -> 0 | AW38: =IF(AC52<$G$449,0,MIN($G$446,1+IFERROR(INT((AC52-$G$449)/$G$451),0))) -> 0 | AX38: =IF(AD52<$G$449,0,MIN($G$446,1+IFERROR(INT((AD52-$G$449)/$G$451),0))) -> 0 | AY38: =IF(AE52<$G$449,0,MIN($G$446,1+IFERROR(INT((AE52-$G$449)/$G$451),0))) -> 0 | AZ38: =IF(AF52<$G$449,0,MIN($G$446,1+IFERROR(INT((AF52-$G$449)/$G$451),0))) -> 1 | BA38: =IF(AG52<$G$449,0,MIN($G$446,1+IFERROR(INT((AG52-$G$449)/$G$451),0))) -> 3 | BB38: =IF(AH52<$G$449,0,MIN($G$446,1+IFERROR(INT((AH52-$G$449)/$G$451),0))) -> 4 | BD38: =(BD$35=0)*($O12-$G$430)+(BD$35=$G$444)*$G$435+(BD$35=$G$445)*(Z12+$G$430-$O12-$G$435) -> -2350 | BE38: =(BE$35=0)*($O12-$G$430)+(BE$35=$G$444)*$G$435+(BE$35=$G$445)*(Z12+$G$430-$O12-$G$435) -> 0 | BF38: =(BF$35=0)*($O12-$G$430)+(BF$35=$G$444)*$G$435+(BF$35=$G$445)*(Z12+$G$430-$O12-$G$435) -> 0 | BG38: =(BG$35=0)*($O12-$G$430)+(BG$35=$G$444)*$G$435+(BG$35=$G$445)*(Z12+$G$430-$O12-$G$435) -> 0 | BH38: =(BH$35=0)*($O12-$G$430)+(BH$35=$G$444)*$G$435+(BH$35=$G$445)*(Z12+$G$430-$O12-$G$435) -> 0 | BI38: =(BI$35=0)*($O12-$G$430)+(BI$35=$G$444)*$G$435+(BI$35=$G$445)*(Z12+$G$430-$O12-$G$435) -> 5819.8171 | BJ38: =(BJ$35=0)*($O12-$G$430)+(BJ$35=$G$444)*$G$435+(BJ$35=$G$445)*(AA12+$G$430-$O12-$G$435) -> -2350 | BK38: =(BK$35=0)*($O12-$G$430)+(BK$35=$G$444)*$G$435+(BK$35=$G$445)*(AA12+$G$430-$O12-$G$435) -> 0 | BL38: =(BL$35=0)*($O12-$G$430)+(BL$35=$G$444)*$G$435+(BL$35=$G$445)*(AA12+$G$430-$O12-$G$435) -> 0 | BM38: =(BM$35=0)*($O12-$G$430)+(BM$35=$G$444)*$G$435+(BM$35=$G$445)*(AA12+$G$430-$O12-$G$435) -> 0 | BN38: =(BN$35=0)*($O12-$G$430)+(BN$35=$G$444)*$G$435+(BN$35=$G$445)*(AA12+$G$430-$O12-$G$435) -> 0 | BO38: =(BO$35=0)*($O12-$G$430)+(BO$35=$G$444)*$G$435+(BO$35=$G$445)*(AA12+$G$430-$O12-$G$435) -> 6183.2473 | BP38: =(BP$35=0)*($O12-$G$430)+(BP$35=$G$444)*$G$435+(BP$35=$G$445)*(AB12+$G$430-$O12-$G$435) -> -2350 | BQ38: =(BQ$35=0)*($O12-$G$430)+(BQ$35=$G$444)*$G$435+(BQ$35=$G$445)*(AB12+$G$430-$O12-$G$435) -> 0 | BR38: =(BR$35=0)*($O12-$G$430)+(BR$35=$G$444)*$G$435+(BR$35=$G$445)*(AB12+$G$430-$O12-$G$435) -> 0 | BS38: =(BS$35=0)*($O12-$G$430)+(BS$35=$G$444)*$G$435+(BS$35=$G$445)*(AB12+$G$430-$O12-$G$435) -> 0 | BT38: =(BT$35=0)*($O12-$G$430)+(BT$35=$G$444)*$G$435+(BT$35=$G$445)*(AB12+$G$430-$O12-$G$435) -> 0 | BU38: =(BU$35=0)*($O12-$G$430)+(BU$35=$G$444)*$G$435+(BU$35=$G$445)*(AB12+$G$430-$O12-$G$435) -> 6546.6775 | BV38: =(BV$35=0)*($O12-$G$430)+(BV$35=$G$444)*$G$435+(BV$35=$G$445)*(AC12+$G$430-$O12-$G$435) -> -2350 | BW38: =(BW$35=0)*($O12-$G$430)+(BW$35=$G$444)*$G$435+(BW$35=$G$445)*(AC12+$G$430-$O12-$G$435) -> 0 | BX38: =(BX$35=0)*($O12-$G$430)+(BX$35=$G$444)*$G$435+(BX$35=$G$445)*(AC12+$G$430-$O12-$G$435) -> 0 | BY38: =(BY$35=0)*($O12-$G$430)+(BY$35=$G$444)*$G$435+(BY$35=$G$445)*(AC12+$G$430-$O12-$G$435) -> 0 | BZ38: =(BZ$35=0)*($O12-$G$430)+(BZ$35=$G$444)*$G$435+(BZ$35=$G$445)*(AC12+$G$430-$O12-$G$435) -> 0 | CA38: =(CA$35=0)*($O12-$G$430)+(CA$35=$G$444)*$G$435+(CA$35=$G$445)*(AC12+$G$430-$O12-$G$435) -> 6910.1078 | CB38: =(CB$35=0)*($O12-$G$430)+(CB$35=$G$444)*$G$435+(CB$35=$G$445)*(AD12+$G$430-$O12-$G$435) -> -2350 | CC38: =(CC$35=0)*($O12-$G$430)+(CC$35=$G$444)*$G$435+(CC$35=$G$445)*(AD12+$G$430-$O12-$G$435) -> 0 | CD38: =(CD$35=0)*($O12-$G$430)+(CD$35=$G$444)*$G$435+(CD$35=$G$445)*(AD12+$G$430-$O12-$G$435) -> 0 | CE38: =(CE$35=0)*($O12-$G$430)+(CE$35=$G$444)*$G$435+(CE$35=$G$445)*(AD12+$G$430-$O12-$G$435) -> 0 | CF38: =(CF$35=0)*($O12-$G$430)+(CF$35=$G$444)*$G$435+(CF$35=$G$445)*(AD12+$G$430-$O12-$G$435) -> 0 | CG38: =(CG$35=0)*($O12-$G$430)+(CG$35=$G$444)*$G$435+(CG$35=$G$445)*(AD12+$G$430-$O12-$G$435) -> 7273.538 | CH38: =(CH$35=0)*($O12-$G$430)+(CH$35=$G$444)*$G$435+(CH$35=$G$445)*(AE12+$G$430-$O12-$G$435) -> -2350 | CI38: =(CI$35=0)*($O12-$G$430)+(CI$35=$G$444)*$G$435+(CI$35=$G$445)*(AE12+$G$430-$O12-$G$435) -> 0 | CJ38: =(CJ$35=0)*($O12-$G$430)+(CJ$35=$G$444)*$G$435+(CJ$35=$G$445)*(AE12+$G$430-$O12-$G$435) -> 0 | CK38: =(CK$35=0)*($O12-$G$430)+(CK$35=$G$444)*$G$435+(CK$35=$G$445)*(AE12+$G$430-$O12-$G$435) -> 0 | CL38: =(CL$35=0)*($O12-$G$430)+(CL$35=$G$444)*$G$435+(CL$35=$G$445)*(AE12+$G$430-$O12-$G$435) -> 0 | CM38: =(CM$35=0)*($O12-$G$430)+(CM$35=$G$444)*$G$435+(CM$35=$G$445)*(AE12+$G$430-$O12-$G$435) -> 7636.9682 | CN38: =(CN$35=0)*($O12-$G$430)+(CN$35=$G$444)*$G$435+(CN$35=$G$445)*(AF12+$G$430-$O12-$G$435) -> -2350 | CO38: =(CO$35=0)*($O12-$G$430)+(CO$35=$G$444)*$G$435+(CO$35=$G$445)*(AF12+$G$430-$O12-$G$435) -> 0 | CP38: =(CP$35=0)*($O12-$G$430)+(CP$35=$G$444)*$G$435+(CP$35=$G$445)*(AF12+$G$430-$O12-$G$435) -> 0 | CQ38: =(CQ$35=0)*($O12-$G$430)+(CQ$35=$G$444)*$G$435+(CQ$35=$G$445)*(AF12+$G$430-$O12-$G$435) -> 0 | CR38: =(CR$35=0)*($O12-$G$430)+(CR$35=$G$444)*$G$435+(CR$35=$G$445)*(AF12+$G$430-$O12-$G$435) -> 0 | CS38: =(CS$35=0)*($O12-$G$430)+(CS$35=$G$444)*$G$435+(CS$35=$G$445)*(AF12+$G$430-$O12-$G$435) -> 8000.3985 | CT38: =(CT$35=0)*($O12-$G$430)+(CT$35=$G$444)*$G$435+(CT$35=$G$445)*(AG12+$G$430-$O12-$G$435) -> -2350 | CU38: =(CU$35=0)*($O12-$G$430)+(CU$35=$G$444)*$G$435+(CU$35=$G$445)*(AG12+$G$430-$O12-$G$435) -> 0 | CV38: =(CV$35=0)*($O12-$G$430)+(CV$35=$G$444)*$G$435+(CV$35=$G$445)*(AG12+$G$430-$O12-$G$435) -> 0 | CW38: =(CW$35=0)*($O12-$G$430)+(CW$35=$G$444)*$G$435+(CW$35=$G$445)*(AG12+$G$430-$O12-$G$435) -> 0 | CX38: =(CX$35=0)*($O12-$G$430)+(CX$35=$G$444)*$G$435+(CX$35=$G$445)*(AG12+$G$430-$O12-$G$435) -> 0 | CY38: =(CY$35=0)*($O12-$G$430)+(CY$35=$G$444)*$G$435+(CY$35=$G$445)*(AG12+$G$430-$O12-$G$435) -> 8363.8287 | CZ38: =(CZ$35=0)*($O12-$G$430)+(CZ$35=$G$444)*$G$435+(CZ$35=$G$445)*(AH12+$G$430-$O12-$G$435) -> -2350 | DA38: =(DA$35=0)*($O12-$G$430)+(DA$35=$G$444)*$G$435+(DA$35=$G$445)*(AH12+$G$430-$O12-$G$435) -> 0 | DB38: =(DB$35=0)*($O12-$G$430)+(DB$35=$G$444)*$G$435+(DB$35=$G$445)*(AH12+$G$430-$O12-$G$435) -> 0 | DC38: =(DC$35=0)*($O12-$G$430)+(DC$35=$G$444)*$G$435+(DC$35=$G$445)*(AH12+$G$430-$O12-$G$435) -> 0 | DD38: =(DD$35=0)*($O12-$G$430)+(DD$35=$G$444)*$G$435+(DD$35=$G$445)*(AH12+$G$430-$O12-$G$435) -> 0 | DE38: =(DE$35=0)*($O12-$G$430)+(DE$35=$G$444)*$G$435+(DE$35=$G$445)*(AH12+$G$430-$O12-$G$435) -> 8727.2589
C39: =$G$438 -> 0.3 | D39: =IFERROR(IRR(BD39:BI39),0) -> 0.22303963 | E39: =IFERROR(IRR(BJ39:BO39),0) -> 0.23535333 | F39: =IFERROR(IRR(BP39:BU39),0) -> 0.24719478 | G39: =IFERROR(IRR(BV39:CA39),0) -> 0.25860289 | H39: =IFERROR(IRR(CB39:CG39),0) -> 0.26961177 | I39: =IFERROR(IRR(CH39:CM39),0) -> 0.28025156 | J39: =IFERROR(IRR(CN39:CS39),0) -> 0.29054897 | K39: =IFERROR(IRR(CT39:CY39),0) -> 0.30052784 | L39: =IFERROR(IRR(CZ39:DE39),0) -> 0.31020952 | AT39: =IF(Z53<$G$449,0,MIN($G$446,1+IFERROR(INT((Z53-$G$449)/$G$451),0))) -> 0 | AU39: =IF(AA53<$G$449,0,MIN($G$446,1+IFERROR(INT((AA53-$G$449)/$G$451),0))) -> 0 | AV39: =IF(AB53<$G$449,0,MIN($G$446,1+IFERROR(INT((AB53-$G$449)/$G$451),0))) -> 0 | AW39: =IF(AC53<$G$449,0,MIN($G$446,1+IFERROR(INT((AC53-$G$449)/$G$451),0))) -> 0 | AX39: =IF(AD53<$G$449,0,MIN($G$446,1+IFERROR(INT((AD53-$G$449)/$G$451),0))) -> 0 | AY39: =IF(AE53<$G$449,0,MIN($G$446,1+IFERROR(INT((AE53-$G$449)/$G$451),0))) -> 2 | AZ39: =IF(AF53<$G$449,0,MIN($G$446,1+IFERROR(INT((AF53-$G$449)/$G$451),0))) -> 3 | BA39: =IF(AG53<$G$449,0,MIN($G$446,1+IFERROR(INT((AG53-$G$449)/$G$451),0))) -> 4 | BB39: =IF(AH53<$G$449,0,MIN($G$446,1+IFERROR(INT((AH53-$G$449)/$G$451),0))) -> 6 | BD39: =(BD$35=0)*($O13-$G$430)+(BD$35=$G$444)*$G$435+(BD$35=$G$445)*(Z13+$G$430-$O13-$G$435) -> -2350 | BE39: =(BE$35=0)*($O13-$G$430)+(BE$35=$G$444)*$G$435+(BE$35=$G$445)*(Z13+$G$430-$O13-$G$435) -> 0 | BF39: =(BF$35=0)*($O13-$G$430)+(BF$35=$G$444)*$G$435+(BF$35=$G$445)*(Z13+$G$430-$O13-$G$435) -> 0 | BG39: =(BG$35=0)*($O13-$G$430)+(BG$35=$G$444)*$G$435+(BG$35=$G$445)*(Z13+$G$430-$O13-$G$435) -> 0 | BH39: =(BH$35=0)*($O13-$G$430)+(BH$35=$G$444)*$G$435+(BH$35=$G$445)*(Z13+$G$430-$O13-$G$435) -> 0 | BI39: =(BI$35=0)*($O13-$G$430)+(BI$35=$G$444)*$G$435+(BI$35=$G$445)*(Z13+$G$430-$O13-$G$435) -> 6430.8816 | BJ39: =(BJ$35=0)*($O13-$G$430)+(BJ$35=$G$444)*$G$435+(BJ$35=$G$445)*(AA13+$G$430-$O13-$G$435) -> -2350 | BK39: =(BK$35=0)*($O13-$G$430)+(BK$35=$G$444)*$G$435+(BK$35=$G$445)*(AA13+$G$430-$O13-$G$435) -> 0 | BL39: =(BL$35=0)*($O13-$G$430)+(BL$35=$G$444)*$G$435+(BL$35=$G$445)*(AA13+$G$430-$O13-$G$435) -> 0 | BM39: =(BM$35=0)*($O13-$G$430)+(BM$35=$G$444)*$G$435+(BM$35=$G$445)*(AA13+$G$430-$O13-$G$435) -> 0 | BN39: =(BN$35=0)*($O13-$G$430)+(BN$35=$G$444)*$G$435+(BN$35=$G$445)*(AA13+$G$430-$O13-$G$435) -> 0 | BO39: =(BO$35=0)*($O13-$G$430)+(BO$35=$G$444)*$G$435+(BO$35=$G$445)*(AA13+$G$430-$O13-$G$435) -> 6761.2005 | BP39: =(BP$35=0)*($O13-$G$430)+(BP$35=$G$444)*$G$435+(BP$35=$G$445)*(AB13+$G$430-$O13-$G$435) -> -2350 | BQ39: =(BQ$35=0)*($O13-$G$430)+(BQ$35=$G$444)*$G$435+(BQ$35=$G$445)*(AB13+$G$430-$O13-$G$435) -> 0 | BR39: =(BR$35=0)*($O13-$G$430)+(BR$35=$G$444)*$G$435+(BR$35=$G$445)*(AB13+$G$430-$O13-$G$435) -> 0 | BS39: =(BS$35=0)*($O13-$G$430)+(BS$35=$G$444)*$G$435+(BS$35=$G$445)*(AB13+$G$430-$O13-$G$435) -> 0 | BT39: =(BT$35=0)*($O13-$G$430)+(BT$35=$G$444)*$G$435+(BT$35=$G$445)*(AB13+$G$430-$O13-$G$435) -> 0 | BU39: =(BU$35=0)*($O13-$G$430)+(BU$35=$G$444)*$G$435+(BU$35=$G$445)*(AB13+$G$430-$O13-$G$435) -> 7091.5193 | BV39: =(BV$35=0)*($O13-$G$430)+(BV$35=$G$444)*$G$435+(BV$35=$G$445)*(AC13+$G$430-$O13-$G$435) -> -2350 | BW39: =(BW$35=0)*($O13-$G$430)+(BW$35=$G$444)*$G$435+(BW$35=$G$445)*(AC13+$G$430-$O13-$G$435) -> 0 | BX39: =(BX$35=0)*($O13-$G$430)+(BX$35=$G$444)*$G$435+(BX$35=$G$445)*(AC13+$G$430-$O13-$G$435) -> 0 | BY39: =(BY$35=0)*($O13-$G$430)+(BY$35=$G$444)*$G$435+(BY$35=$G$445)*(AC13+$G$430-$O13-$G$435) -> 0 | BZ39: =(BZ$35=0)*($O13-$G$430)+(BZ$35=$G$444)*$G$435+(BZ$35=$G$445)*(AC13+$G$430-$O13-$G$435) -> 0 | CA39: =(CA$35=0)*($O13-$G$430)+(CA$35=$G$444)*$G$435+(CA$35=$G$445)*(AC13+$G$430-$O13-$G$435) -> 7421.8382 | CB39: =(CB$35=0)*($O13-$G$430)+(CB$35=$G$444)*$G$435+(CB$35=$G$445)*(AD13+$G$430-$O13-$G$435) -> -2350 | CC39: =(CC$35=0)*($O13-$G$430)+(CC$35=$G$444)*$G$435+(CC$35=$G$445)*(AD13+$G$430-$O13-$G$435) -> 0 | CD39: =(CD$35=0)*($O13-$G$430)+(CD$35=$G$444)*$G$435+(CD$35=$G$445)*(AD13+$G$430-$O13-$G$435) -> 0 | CE39: =(CE$35=0)*($O13-$G$430)+(CE$35=$G$444)*$G$435+(CE$35=$G$445)*(AD13+$G$430-$O13-$G$435) -> 0 | CF39: =(CF$35=0)*($O13-$G$430)+(CF$35=$G$444)*$G$435+(CF$35=$G$445)*(AD13+$G$430-$O13-$G$435) -> 0 | CG39: =(CG$35=0)*($O13-$G$430)+(CG$35=$G$444)*$G$435+(CG$35=$G$445)*(AD13+$G$430-$O13-$G$435) -> 7752.1571 | CH39: =(CH$35=0)*($O13-$G$430)+(CH$35=$G$444)*$G$435+(CH$35=$G$445)*(AE13+$G$430-$O13-$G$435) -> -2350 | CI39: =(CI$35=0)*($O13-$G$430)+(CI$35=$G$444)*$G$435+(CI$35=$G$445)*(AE13+$G$430-$O13-$G$435) -> 0 | CJ39: =(CJ$35=0)*($O13-$G$430)+(CJ$35=$G$444)*$G$435+(CJ$35=$G$445)*(AE13+$G$430-$O13-$G$435) -> 0 | CK39: =(CK$35=0)*($O13-$G$430)+(CK$35=$G$444)*$G$435+(CK$35=$G$445)*(AE13+$G$430-$O13-$G$435) -> 0 | CL39: =(CL$35=0)*($O13-$G$430)+(CL$35=$G$444)*$G$435+(CL$35=$G$445)*(AE13+$G$430-$O13-$G$435) -> 0 | CM39: =(CM$35=0)*($O13-$G$430)+(CM$35=$G$444)*$G$435+(CM$35=$G$445)*(AE13+$G$430-$O13-$G$435) -> 8082.476 | CN39: =(CN$35=0)*($O13-$G$430)+(CN$35=$G$444)*$G$435+(CN$35=$G$445)*(AF13+$G$430-$O13-$G$435) -> -2350 | CO39: =(CO$35=0)*($O13-$G$430)+(CO$35=$G$444)*$G$435+(CO$35=$G$445)*(AF13+$G$430-$O13-$G$435) -> 0 | CP39: =(CP$35=0)*($O13-$G$430)+(CP$35=$G$444)*$G$435+(CP$35=$G$445)*(AF13+$G$430-$O13-$G$435) -> 0 | CQ39: =(CQ$35=0)*($O13-$G$430)+(CQ$35=$G$444)*$G$435+(CQ$35=$G$445)*(AF13+$G$430-$O13-$G$435) -> 0 | CR39: =(CR$35=0)*($O13-$G$430)+(CR$35=$G$444)*$G$435+(CR$35=$G$445)*(AF13+$G$430-$O13-$G$435) -> 0 | CS39: =(CS$35=0)*($O13-$G$430)+(CS$35=$G$444)*$G$435+(CS$35=$G$445)*(AF13+$G$430-$O13-$G$435) -> 8412.7949 | CT39: =(CT$35=0)*($O13-$G$430)+(CT$35=$G$444)*$G$435+(CT$35=$G$445)*(AG13+$G$430-$O13-$G$435) -> -2350 | CU39: =(CU$35=0)*($O13-$G$430)+(CU$35=$G$444)*$G$435+(CU$35=$G$445)*(AG13+$G$430-$O13-$G$435) -> 0 | CV39: =(CV$35=0)*($O13-$G$430)+(CV$35=$G$444)*$G$435+(CV$35=$G$445)*(AG13+$G$430-$O13-$G$435) -> 0 | CW39: =(CW$35=0)*($O13-$G$430)+(CW$35=$G$444)*$G$435+(CW$35=$G$445)*(AG13+$G$430-$O13-$G$435) -> 0 | CX39: =(CX$35=0)*($O13-$G$430)+(CX$35=$G$444)*$G$435+(CX$35=$G$445)*(AG13+$G$430-$O13-$G$435) -> 0 | CY39: =(CY$35=0)*($O13-$G$430)+(CY$35=$G$444)*$G$435+(CY$35=$G$445)*(AG13+$G$430-$O13-$G$435) -> 8743.1137 | CZ39: =(CZ$35=0)*($O13-$G$430)+(CZ$35=$G$444)*$G$435+(CZ$35=$G$445)*(AH13+$G$430-$O13-$G$435) -> -2350 | DA39: =(DA$35=0)*($O13-$G$430)+(DA$35=$G$444)*$G$435+(DA$35=$G$445)*(AH13+$G$430-$O13-$G$435) -> 0 | DB39: =(DB$35=0)*($O13-$G$430)+(DB$35=$G$444)*$G$435+(DB$35=$G$445)*(AH13+$G$430-$O13-$G$435) -> 0 | DC39: =(DC$35=0)*($O13-$G$430)+(DC$35=$G$444)*$G$435+(DC$35=$G$445)*(AH13+$G$430-$O13-$G$435) -> 0 | DD39: =(DD$35=0)*($O13-$G$430)+(DD$35=$G$444)*$G$435+(DD$35=$G$445)*(AH13+$G$430-$O13-$G$435) -> 0 | DE39: =(DE$35=0)*($O13-$G$430)+(DE$35=$G$444)*$G$435+(DE$35=$G$445)*(AH13+$G$430-$O13-$G$435) -> 9073.4326
C40: =C39+$G$439 -> 0.35 | D40: =IFERROR(IRR(BD40:BI40),0) -> 0.2455643 | E40: =IFERROR(IRR(BJ40:BO40),0) -> 0.25589361 | F40: =IFERROR(IRR(BP40:BU40),0) -> 0.26589387 | G40: =IFERROR(IRR(BV40:CA40),0) -> 0.27558777 | H40: =IFERROR(IRR(CB40:CG40),0) -> 0.28499564 | I40: =IFERROR(IRR(CH40:CM40),0) -> 0.29413581 | J40: =IFERROR(IRR(CN40:CS40),0) -> 0.30302482 | K40: =IFERROR(IRR(CT40:CY40),0) -> 0.31167769 | L40: =IFERROR(IRR(CZ40:DE40),0) -> 0.32010808 | AT40: =IF(Z54<$G$449,0,MIN($G$446,1+IFERROR(INT((Z54-$G$449)/$G$451),0))) -> 0 | AU40: =IF(AA54<$G$449,0,MIN($G$446,1+IFERROR(INT((AA54-$G$449)/$G$451),0))) -> 0 | AV40: =IF(AB54<$G$449,0,MIN($G$446,1+IFERROR(INT((AB54-$G$449)/$G$451),0))) -> 0 | AW40: =IF(AC54<$G$449,0,MIN($G$446,1+IFERROR(INT((AC54-$G$449)/$G$451),0))) -> 1 | AX40: =IF(AD54<$G$449,0,MIN($G$446,1+IFERROR(INT((AD54-$G$449)/$G$451),0))) -> 2 | AY40: =IF(AE54<$G$449,0,MIN($G$446,1+IFERROR(INT((AE54-$G$449)/$G$451),0))) -> 4 | AZ40: =IF(AF54<$G$449,0,MIN($G$446,1+IFERROR(INT((AF54-$G$449)/$G$451),0))) -> 5 | BA40: =IF(AG54<$G$449,0,MIN($G$446,1+IFERROR(INT((AG54-$G$449)/$G$451),0))) -> 6 | BB40: =IF(AH54<$G$449,0,MIN($G$446,1+IFERROR(INT((AH54-$G$449)/$G$451),0))) -> 7 | BD40: =(BD$35=0)*($O14-$G$430)+(BD$35=$G$444)*$G$435+(BD$35=$G$445)*(Z14+$G$430-$O14-$G$435) -> -2350 | BE40: =(BE$35=0)*($O14-$G$430)+(BE$35=$G$444)*$G$435+(BE$35=$G$445)*(Z14+$G$430-$O14-$G$435) -> 0 | BF40: =(BF$35=0)*($O14-$G$430)+(BF$35=$G$444)*$G$435+(BF$35=$G$445)*(Z14+$G$430-$O14-$G$435) -> 0 | BG40: =(BG$35=0)*($O14-$G$430)+(BG$35=$G$444)*$G$435+(BG$35=$G$445)*(Z14+$G$430-$O14-$G$435) -> 0 | BH40: =(BH$35=0)*($O14-$G$430)+(BH$35=$G$444)*$G$435+(BH$35=$G$445)*(Z14+$G$430-$O14-$G$435) -> 0 | BI40: =(BI$35=0)*($O14-$G$430)+(BI$35=$G$444)*$G$435+(BI$35=$G$445)*(Z14+$G$430-$O14-$G$435) -> 7045.286 | BJ40: =(BJ$35=0)*($O14-$G$430)+(BJ$35=$G$444)*$G$435+(BJ$35=$G$445)*(AA14+$G$430-$O14-$G$435) -> -2350 | BK40: =(BK$35=0)*($O14-$G$430)+(BK$35=$G$444)*$G$435+(BK$35=$G$445)*(AA14+$G$430-$O14-$G$435) -> 0 | BL40: =(BL$35=0)*($O14-$G$430)+(BL$35=$G$444)*$G$435+(BL$35=$G$445)*(AA14+$G$430-$O14-$G$435) -> 0 | BM40: =(BM$35=0)*($O14-$G$430)+(BM$35=$G$444)*$G$435+(BM$35=$G$445)*(AA14+$G$430-$O14-$G$435) -> 0 | BN40: =(BN$35=0)*($O14-$G$430)+(BN$35=$G$444)*$G$435+(BN$35=$G$445)*(AA14+$G$430-$O14-$G$435) -> 0 | BO40: =(BO$35=0)*($O14-$G$430)+(BO$35=$G$444)*$G$435+(BO$35=$G$445)*(AA14+$G$430-$O14-$G$435) -> 7342.2999 | BP40: =(BP$35=0)*($O14-$G$430)+(BP$35=$G$444)*$G$435+(BP$35=$G$445)*(AB14+$G$430-$O14-$G$435) -> -2350 | BQ40: =(BQ$35=0)*($O14-$G$430)+(BQ$35=$G$444)*$G$435+(BQ$35=$G$445)*(AB14+$G$430-$O14-$G$435) -> 0 | BR40: =(BR$35=0)*($O14-$G$430)+(BR$35=$G$444)*$G$435+(BR$35=$G$445)*(AB14+$G$430-$O14-$G$435) -> 0 | BS40: =(BS$35=0)*($O14-$G$430)+(BS$35=$G$444)*$G$435+(BS$35=$G$445)*(AB14+$G$430-$O14-$G$435) -> 0 | BT40: =(BT$35=0)*($O14-$G$430)+(BT$35=$G$444)*$G$435+(BT$35=$G$445)*(AB14+$G$430-$O14-$G$435) -> 0 | BU40: =(BU$35=0)*($O14-$G$430)+(BU$35=$G$444)*$G$435+(BU$35=$G$445)*(AB14+$G$430-$O14-$G$435) -> 7639.3138 | BV40: =(BV$35=0)*($O14-$G$430)+(BV$35=$G$444)*$G$435+(BV$35=$G$445)*(AC14+$G$430-$O14-$G$435) -> -2350 | BW40: =(BW$35=0)*($O14-$G$430)+(BW$35=$G$444)*$G$435+(BW$35=$G$445)*(AC14+$G$430-$O14-$G$435) -> 0 | BX40: =(BX$35=0)*($O14-$G$430)+(BX$35=$G$444)*$G$435+(BX$35=$G$445)*(AC14+$G$430-$O14-$G$435) -> 0 | BY40: =(BY$35=0)*($O14-$G$430)+(BY$35=$G$444)*$G$435+(BY$35=$G$445)*(AC14+$G$430-$O14-$G$435) -> 0 | BZ40: =(BZ$35=0)*($O14-$G$430)+(BZ$35=$G$444)*$G$435+(BZ$35=$G$445)*(AC14+$G$430-$O14-$G$435) -> 0 | CA40: =(CA$35=0)*($O14-$G$430)+(CA$35=$G$444)*$G$435+(CA$35=$G$445)*(AC14+$G$430-$O14-$G$435) -> 7936.3277 | CB40: =(CB$35=0)*($O14-$G$430)+(CB$35=$G$444)*$G$435+(CB$35=$G$445)*(AD14+$G$430-$O14-$G$435) -> -2350 | CC40: =(CC$35=0)*($O14-$G$430)+(CC$35=$G$444)*$G$435+(CC$35=$G$445)*(AD14+$G$430-$O14-$G$435) -> 0 | CD40: =(CD$35=0)*($O14-$G$430)+(CD$35=$G$444)*$G$435+(CD$35=$G$445)*(AD14+$G$430-$O14-$G$435) -> 0 | CE40: =(CE$35=0)*($O14-$G$430)+(CE$35=$G$444)*$G$435+(CE$35=$G$445)*(AD14+$G$430-$O14-$G$435) -> 0 | CF40: =(CF$35=0)*($O14-$G$430)+(CF$35=$G$444)*$G$435+(CF$35=$G$445)*(AD14+$G$430-$O14-$G$435) -> 0 | CG40: =(CG$35=0)*($O14-$G$430)+(CG$35=$G$444)*$G$435+(CG$35=$G$445)*(AD14+$G$430-$O14-$G$435) -> 8233.3416 | CH40: =(CH$35=0)*($O14-$G$430)+(CH$35=$G$444)*$G$435+(CH$35=$G$445)*(AE14+$G$430-$O14-$G$435) -> -2350 | CI40: =(CI$35=0)*($O14-$G$430)+(CI$35=$G$444)*$G$435+(CI$35=$G$445)*(AE14+$G$430-$O14-$G$435) -> 0 | CJ40: =(CJ$35=0)*($O14-$G$430)+(CJ$35=$G$444)*$G$435+(CJ$35=$G$445)*(AE14+$G$430-$O14-$G$435) -> 0 | CK40: =(CK$35=0)*($O14-$G$430)+(CK$35=$G$444)*$G$435+(CK$35=$G$445)*(AE14+$G$430-$O14-$G$435) -> 0 | CL40: =(CL$35=0)*($O14-$G$430)+(CL$35=$G$444)*$G$435+(CL$35=$G$445)*(AE14+$G$430-$O14-$G$435) -> 0 | CM40: =(CM$35=0)*($O14-$G$430)+(CM$35=$G$444)*$G$435+(CM$35=$G$445)*(AE14+$G$430-$O14-$G$435) -> 8530.3555 | CN40: =(CN$35=0)*($O14-$G$430)+(CN$35=$G$444)*$G$435+(CN$35=$G$445)*(AF14+$G$430-$O14-$G$435) -> -2350 | CO40: =(CO$35=0)*($O14-$G$430)+(CO$35=$G$444)*$G$435+(CO$35=$G$445)*(AF14+$G$430-$O14-$G$435) -> 0 | CP40: =(CP$35=0)*($O14-$G$430)+(CP$35=$G$444)*$G$435+(CP$35=$G$445)*(AF14+$G$430-$O14-$G$435) -> 0 | CQ40: =(CQ$35=0)*($O14-$G$430)+(CQ$35=$G$444)*$G$435+(CQ$35=$G$445)*(AF14+$G$430-$O14-$G$435) -> 0 | CR40: =(CR$35=0)*($O14-$G$430)+(CR$35=$G$444)*$G$435+(CR$35=$G$445)*(AF14+$G$430-$O14-$G$435) -> 0 | CS40: =(CS$35=0)*($O14-$G$430)+(CS$35=$G$444)*$G$435+(CS$35=$G$445)*(AF14+$G$430-$O14-$G$435) -> 8827.3694 | CT40: =(CT$35=0)*($O14-$G$430)+(CT$35=$G$444)*$G$435+(CT$35=$G$445)*(AG14+$G$430-$O14-$G$435) -> -2350 | CU40: =(CU$35=0)*($O14-$G$430)+(CU$35=$G$444)*$G$435+(CU$35=$G$445)*(AG14+$G$430-$O14-$G$435) -> 0 | CV40: =(CV$35=0)*($O14-$G$430)+(CV$35=$G$444)*$G$435+(CV$35=$G$445)*(AG14+$G$430-$O14-$G$435) -> 0 | CW40: =(CW$35=0)*($O14-$G$430)+(CW$35=$G$444)*$G$435+(CW$35=$G$445)*(AG14+$G$430-$O14-$G$435) -> 0 | CX40: =(CX$35=0)*($O14-$G$430)+(CX$35=$G$444)*$G$435+(CX$35=$G$445)*(AG14+$G$430-$O14-$G$435) -> 0 | CY40: =(CY$35=0)*($O14-$G$430)+(CY$35=$G$444)*$G$435+(CY$35=$G$445)*(AG14+$G$430-$O14-$G$435) -> 9124.3832 | CZ40: =(CZ$35=0)*($O14-$G$430)+(CZ$35=$G$444)*$G$435+(CZ$35=$G$445)*(AH14+$G$430-$O14-$G$435) -> -2350 | DA40: =(DA$35=0)*($O14-$G$430)+(DA$35=$G$444)*$G$435+(DA$35=$G$445)*(AH14+$G$430-$O14-$G$435) -> 0 | DB40: =(DB$35=0)*($O14-$G$430)+(DB$35=$G$444)*$G$435+(DB$35=$G$445)*(AH14+$G$430-$O14-$G$435) -> 0 | DC40: =(DC$35=0)*($O14-$G$430)+(DC$35=$G$444)*$G$435+(DC$35=$G$445)*(AH14+$G$430-$O14-$G$435) -> 0 | DD40: =(DD$35=0)*($O14-$G$430)+(DD$35=$G$444)*$G$435+(DD$35=$G$445)*(AH14+$G$430-$O14-$G$435) -> 0 | DE40: =(DE$35=0)*($O14-$G$430)+(DE$35=$G$444)*$G$435+(DE$35=$G$445)*(AH14+$G$430-$O14-$G$435) -> 9421.3971
C41: =C40+$G$439 -> 0.4 | D41: =IFERROR(IRR(BD41:BI41),0) -> 0.26667987 | E41: =IFERROR(IRR(BJ41:BO41),0) -> 0.27527405 | F41: =IFERROR(IRR(BP41:BU41),0) -> 0.28364262 | G41: =IFERROR(IRR(BV41:CA41),0) -> 0.29179849 | H41: =IFERROR(IRR(CB41:CG41),0) -> 0.29975343 | I41: =IFERROR(IRR(CH41:CM41),0) -> 0.30751827 | J41: =IFERROR(IRR(CN41:CS41),0) -> 0.31510292 | K41: =IFERROR(IRR(CT41:CY41),0) -> 0.32251653 | L41: =IFERROR(IRR(CZ41:DE41),0) -> 0.32976754 | AT41: =IF(Z55<$G$449,0,MIN($G$446,1+IFERROR(INT((Z55-$G$449)/$G$451),0))) -> 0 | AU41: =IF(AA55<$G$449,0,MIN($G$446,1+IFERROR(INT((AA55-$G$449)/$G$451),0))) -> 1 | AV41: =IF(AB55<$G$449,0,MIN($G$446,1+IFERROR(INT((AB55-$G$449)/$G$451),0))) -> 2 | AW41: =IF(AC55<$G$449,0,MIN($G$446,1+IFERROR(INT((AC55-$G$449)/$G$451),0))) -> 3 | AX41: =IF(AD55<$G$449,0,MIN($G$446,1+IFERROR(INT((AD55-$G$449)/$G$451),0))) -> 4 | AY41: =IF(AE55<$G$449,0,MIN($G$446,1+IFERROR(INT((AE55-$G$449)/$G$451),0))) -> 5 | AZ41: =IF(AF55<$G$449,0,MIN($G$446,1+IFERROR(INT((AF55-$G$449)/$G$451),0))) -> 7 | BA41: =IF(AG55<$G$449,0,MIN($G$446,1+IFERROR(INT((AG55-$G$449)/$G$451),0))) -> 8 | BB41: =IF(AH55<$G$449,0,MIN($G$446,1+IFERROR(INT((AH55-$G$449)/$G$451),0))) -> 9 | BD41: =(BD$35=0)*($O15-$G$430)+(BD$35=$G$444)*$G$435+(BD$35=$G$445)*(Z15+$G$430-$O15-$G$435) -> -2350 | BE41: =(BE$35=0)*($O15-$G$430)+(BE$35=$G$444)*$G$435+(BE$35=$G$445)*(Z15+$G$430-$O15-$G$435) -> 0 | BF41: =(BF$35=0)*($O15-$G$430)+(BF$35=$G$444)*$G$435+(BF$35=$G$445)*(Z15+$G$430-$O15-$G$435) -> 0 | BG41: =(BG$35=0)*($O15-$G$430)+(BG$35=$G$444)*$G$435+(BG$35=$G$445)*(Z15+$G$430-$O15-$G$435) -> 0 | BH41: =(BH$35=0)*($O15-$G$430)+(BH$35=$G$444)*$G$435+(BH$35=$G$445)*(Z15+$G$430-$O15-$G$435) -> 0 | BI41: =(BI$35=0)*($O15-$G$430)+(BI$35=$G$444)*$G$435+(BI$35=$G$445)*(Z15+$G$430-$O15-$G$435) -> 7663.0598 | BJ41: =(BJ$35=0)*($O15-$G$430)+(BJ$35=$G$444)*$G$435+(BJ$35=$G$445)*(AA15+$G$430-$O15-$G$435) -> -2350 | BK41: =(BK$35=0)*($O15-$G$430)+(BK$35=$G$444)*$G$435+(BK$35=$G$445)*(AA15+$G$430-$O15-$G$435) -> 0 | BL41: =(BL$35=0)*($O15-$G$430)+(BL$35=$G$444)*$G$435+(BL$35=$G$445)*(AA15+$G$430-$O15-$G$435) -> 0 | BM41: =(BM$35=0)*($O15-$G$430)+(BM$35=$G$444)*$G$435+(BM$35=$G$445)*(AA15+$G$430-$O15-$G$435) -> 0 | BN41: =(BN$35=0)*($O15-$G$430)+(BN$35=$G$444)*$G$435+(BN$35=$G$445)*(AA15+$G$430-$O15-$G$435) -> 0 | BO41: =(BO$35=0)*($O15-$G$430)+(BO$35=$G$444)*$G$435+(BO$35=$G$445)*(AA15+$G$430-$O15-$G$435) -> 7926.5733 | BP41: =(BP$35=0)*($O15-$G$430)+(BP$35=$G$444)*$G$435+(BP$35=$G$445)*(AB15+$G$430-$O15-$G$435) -> -2350 | BQ41: =(BQ$35=0)*($O15-$G$430)+(BQ$35=$G$444)*$G$435+(BQ$35=$G$445)*(AB15+$G$430-$O15-$G$435) -> 0 | BR41: =(BR$35=0)*($O15-$G$430)+(BR$35=$G$444)*$G$435+(BR$35=$G$445)*(AB15+$G$430-$O15-$G$435) -> 0 | BS41: =(BS$35=0)*($O15-$G$430)+(BS$35=$G$444)*$G$435+(BS$35=$G$445)*(AB15+$G$430-$O15-$G$435) -> 0 | BT41: =(BT$35=0)*($O15-$G$430)+(BT$35=$G$444)*$G$435+(BT$35=$G$445)*(AB15+$G$430-$O15-$G$435) -> 0 | BU41: =(BU$35=0)*($O15-$G$430)+(BU$35=$G$444)*$G$435+(BU$35=$G$445)*(AB15+$G$430-$O15-$G$435) -> 8190.0869 | BV41: =(BV$35=0)*($O15-$G$430)+(BV$35=$G$444)*$G$435+(BV$35=$G$445)*(AC15+$G$430-$O15-$G$435) -> -2350 | BW41: =(BW$35=0)*($O15-$G$430)+(BW$35=$G$444)*$G$435+(BW$35=$G$445)*(AC15+$G$430-$O15-$G$435) -> 0 | BX41: =(BX$35=0)*($O15-$G$430)+(BX$35=$G$444)*$G$435+(BX$35=$G$445)*(AC15+$G$430-$O15-$G$435) -> 0 | BY41: =(BY$35=0)*($O15-$G$430)+(BY$35=$G$444)*$G$435+(BY$35=$G$445)*(AC15+$G$430-$O15-$G$435) -> 0 | BZ41: =(BZ$35=0)*($O15-$G$430)+(BZ$35=$G$444)*$G$435+(BZ$35=$G$445)*(AC15+$G$430-$O15-$G$435) -> 0 | CA41: =(CA$35=0)*($O15-$G$430)+(CA$35=$G$444)*$G$435+(CA$35=$G$445)*(AC15+$G$430-$O15-$G$435) -> 8453.6004 | CB41: =(CB$35=0)*($O15-$G$430)+(CB$35=$G$444)*$G$435+(CB$35=$G$445)*(AD15+$G$430-$O15-$G$435) -> -2350 | CC41: =(CC$35=0)*($O15-$G$430)+(CC$35=$G$444)*$G$435+(CC$35=$G$445)*(AD15+$G$430-$O15-$G$435) -> 0 | CD41: =(CD$35=0)*($O15-$G$430)+(CD$35=$G$444)*$G$435+(CD$35=$G$445)*(AD15+$G$430-$O15-$G$435) -> 0 | CE41: =(CE$35=0)*($O15-$G$430)+(CE$35=$G$444)*$G$435+(CE$35=$G$445)*(AD15+$G$430-$O15-$G$435) -> 0 | CF41: =(CF$35=0)*($O15-$G$430)+(CF$35=$G$444)*$G$435+(CF$35=$G$445)*(AD15+$G$430-$O15-$G$435) -> 0 | CG41: =(CG$35=0)*($O15-$G$430)+(CG$35=$G$444)*$G$435+(CG$35=$G$445)*(AD15+$G$430-$O15-$G$435) -> 8717.114 | CH41: =(CH$35=0)*($O15-$G$430)+(CH$35=$G$444)*$G$435+(CH$35=$G$445)*(AE15+$G$430-$O15-$G$435) -> -2350 | CI41: =(CI$35=0)*($O15-$G$430)+(CI$35=$G$444)*$G$435+(CI$35=$G$445)*(AE15+$G$430-$O15-$G$435) -> 0 | CJ41: =(CJ$35=0)*($O15-$G$430)+(CJ$35=$G$444)*$G$435+(CJ$35=$G$445)*(AE15+$G$430-$O15-$G$435) -> 0 | CK41: =(CK$35=0)*($O15-$G$430)+(CK$35=$G$444)*$G$435+(CK$35=$G$445)*(AE15+$G$430-$O15-$G$435) -> 0 | CL41: =(CL$35=0)*($O15-$G$430)+(CL$35=$G$444)*$G$435+(CL$35=$G$445)*(AE15+$G$430-$O15-$G$435) -> 0 | CM41: =(CM$35=0)*($O15-$G$430)+(CM$35=$G$444)*$G$435+(CM$35=$G$445)*(AE15+$G$430-$O15-$G$435) -> 8980.6276 | CN41: =(CN$35=0)*($O15-$G$430)+(CN$35=$G$444)*$G$435+(CN$35=$G$445)*(AF15+$G$430-$O15-$G$435) -> -2350 | CO41: =(CO$35=0)*($O15-$G$430)+(CO$35=$G$444)*$G$435+(CO$35=$G$445)*(AF15+$G$430-$O15-$G$435) -> 0 | CP41: =(CP$35=0)*($O15-$G$430)+(CP$35=$G$444)*$G$435+(CP$35=$G$445)*(AF15+$G$430-$O15-$G$435) -> 0 | CQ41: =(CQ$35=0)*($O15-$G$430)+(CQ$35=$G$444)*$G$435+(CQ$35=$G$445)*(AF15+$G$430-$O15-$G$435) -> 0 | CR41: =(CR$35=0)*($O15-$G$430)+(CR$35=$G$444)*$G$435+(CR$35=$G$445)*(AF15+$G$430-$O15-$G$435) -> 0 | CS41: =(CS$35=0)*($O15-$G$430)+(CS$35=$G$444)*$G$435+(CS$35=$G$445)*(AF15+$G$430-$O15-$G$435) -> 9244.1411 | CT41: =(CT$35=0)*($O15-$G$430)+(CT$35=$G$444)*$G$435+(CT$35=$G$445)*(AG15+$G$430-$O15-$G$435) -> -2350 | CU41: =(CU$35=0)*($O15-$G$430)+(CU$35=$G$444)*$G$435+(CU$35=$G$445)*(AG15+$G$430-$O15-$G$435) -> 0 | CV41: =(CV$35=0)*($O15-$G$430)+(CV$35=$G$444)*$G$435+(CV$35=$G$445)*(AG15+$G$430-$O15-$G$435) -> 0 | CW41: =(CW$35=0)*($O15-$G$430)+(CW$35=$G$444)*$G$435+(CW$35=$G$445)*(AG15+$G$430-$O15-$G$435) -> 0 | CX41: =(CX$35=0)*($O15-$G$430)+(CX$35=$G$444)*$G$435+(CX$35=$G$445)*(AG15+$G$430-$O15-$G$435) -> 0 | CY41: =(CY$35=0)*($O15-$G$430)+(CY$35=$G$444)*$G$435+(CY$35=$G$445)*(AG15+$G$430-$O15-$G$435) -> 9507.6547 | CZ41: =(CZ$35=0)*($O15-$G$430)+(CZ$35=$G$444)*$G$435+(CZ$35=$G$445)*(AH15+$G$430-$O15-$G$435) -> -2350 | DA41: =(DA$35=0)*($O15-$G$430)+(DA$35=$G$444)*$G$435+(DA$35=$G$445)*(AH15+$G$430-$O15-$G$435) -> 0 | DB41: =(DB$35=0)*($O15-$G$430)+(DB$35=$G$444)*$G$435+(DB$35=$G$445)*(AH15+$G$430-$O15-$G$435) -> 0 | DC41: =(DC$35=0)*($O15-$G$430)+(DC$35=$G$444)*$G$435+(DC$35=$G$445)*(AH15+$G$430-$O15-$G$435) -> 0 | DD41: =(DD$35=0)*($O15-$G$430)+(DD$35=$G$444)*$G$435+(DD$35=$G$445)*(AH15+$G$430-$O15-$G$435) -> 0 | DE41: =(DE$35=0)*($O15-$G$430)+(DE$35=$G$444)*$G$435+(DE$35=$G$445)*(AH15+$G$430-$O15-$G$435) -> 9771.1683
C42: =C41+$G$439 -> 0.45 | D42: =IFERROR(IRR(BD42:BI42),0) -> 0.28658026 | E42: =IFERROR(IRR(BJ42:BO42),0) -> 0.29364065 | F42: =IFERROR(IRR(BP42:BU42),0) -> 0.30055018 | G42: =IFERROR(IRR(BV42:CA42),0) -> 0.30731593 | H42: =IFERROR(IRR(CB42:CG42),0) -> 0.31394445 | I42: =IFERROR(IRR(CH42:CM42),0) -> 0.32044185 | J42: =IFERROR(IRR(CN42:CS42),0) -> 0.32681383 | K42: =IFERROR(IRR(CT42:CY42),0) -> 0.3330657 | L42: =IFERROR(IRR(CZ42:DE42),0) -> 0.33920244 | AT42: =IF(Z56<$G$449,0,MIN($G$446,1+IFERROR(INT((Z56-$G$449)/$G$451),0))) -> 2 | AU42: =IF(AA56<$G$449,0,MIN($G$446,1+IFERROR(INT((AA56-$G$449)/$G$451),0))) -> 3 | AV42: =IF(AB56<$G$449,0,MIN($G$446,1+IFERROR(INT((AB56-$G$449)/$G$451),0))) -> 4 | AW42: =IF(AC56<$G$449,0,MIN($G$446,1+IFERROR(INT((AC56-$G$449)/$G$451),0))) -> 5 | AX42: =IF(AD56<$G$449,0,MIN($G$446,1+IFERROR(INT((AD56-$G$449)/$G$451),0))) -> 6 | AY42: =IF(AE56<$G$449,0,MIN($G$446,1+IFERROR(INT((AE56-$G$449)/$G$451),0))) -> 7 | AZ42: =IF(AF56<$G$449,0,MIN($G$446,1+IFERROR(INT((AF56-$G$449)/$G$451),0))) -> 8 | BA42: =IF(AG56<$G$449,0,MIN($G$446,1+IFERROR(INT((AG56-$G$449)/$G$451),0))) -> 9 | BB42: =IF(AH56<$G$449,0,MIN($G$446,1+IFERROR(INT((AH56-$G$449)/$G$451),0))) -> 10 | BD42: =(BD$35=0)*($O16-$G$430)+(BD$35=$G$444)*$G$435+(BD$35=$G$445)*(Z16+$G$430-$O16-$G$435) -> -2350 | BE42: =(BE$35=0)*($O16-$G$430)+(BE$35=$G$444)*$G$435+(BE$35=$G$445)*(Z16+$G$430-$O16-$G$435) -> 0 | BF42: =(BF$35=0)*($O16-$G$430)+(BF$35=$G$444)*$G$435+(BF$35=$G$445)*(Z16+$G$430-$O16-$G$435) -> 0 | BG42: =(BG$35=0)*($O16-$G$430)+(BG$35=$G$444)*$G$435+(BG$35=$G$445)*(Z16+$G$430-$O16-$G$435) -> 0 | BH42: =(BH$35=0)*($O16-$G$430)+(BH$35=$G$444)*$G$435+(BH$35=$G$445)*(Z16+$G$430-$O16-$G$435) -> 0 | BI42: =(BI$35=0)*($O16-$G$430)+(BI$35=$G$444)*$G$435+(BI$35=$G$445)*(Z16+$G$430-$O16-$G$435) -> 8284.2325 | BJ42: =(BJ$35=0)*($O16-$G$430)+(BJ$35=$G$444)*$G$435+(BJ$35=$G$445)*(AA16+$G$430-$O16-$G$435) -> -2350 | BK42: =(BK$35=0)*($O16-$G$430)+(BK$35=$G$444)*$G$435+(BK$35=$G$445)*(AA16+$G$430-$O16-$G$435) -> 0 | BL42: =(BL$35=0)*($O16-$G$430)+(BL$35=$G$444)*$G$435+(BL$35=$G$445)*(AA16+$G$430-$O16-$G$435) -> 0 | BM42: =(BM$35=0)*($O16-$G$430)+(BM$35=$G$444)*$G$435+(BM$35=$G$445)*(AA16+$G$430-$O16-$G$435) -> 0 | BN42: =(BN$35=0)*($O16-$G$430)+(BN$35=$G$444)*$G$435+(BN$35=$G$445)*(AA16+$G$430-$O16-$G$435) -> 0 | BO42: =(BO$35=0)*($O16-$G$430)+(BO$35=$G$444)*$G$435+(BO$35=$G$445)*(AA16+$G$430-$O16-$G$435) -> 8514.0487 | BP42: =(BP$35=0)*($O16-$G$430)+(BP$35=$G$444)*$G$435+(BP$35=$G$445)*(AB16+$G$430-$O16-$G$435) -> -2350 | BQ42: =(BQ$35=0)*($O16-$G$430)+(BQ$35=$G$444)*$G$435+(BQ$35=$G$445)*(AB16+$G$430-$O16-$G$435) -> 0 | BR42: =(BR$35=0)*($O16-$G$430)+(BR$35=$G$444)*$G$435+(BR$35=$G$445)*(AB16+$G$430-$O16-$G$435) -> 0 | BS42: =(BS$35=0)*($O16-$G$430)+(BS$35=$G$444)*$G$435+(BS$35=$G$445)*(AB16+$G$430-$O16-$G$435) -> 0 | BT42: =(BT$35=0)*($O16-$G$430)+(BT$35=$G$444)*$G$435+(BT$35=$G$445)*(AB16+$G$430-$O16-$G$435) -> 0 | BU42: =(BU$35=0)*($O16-$G$430)+(BU$35=$G$444)*$G$435+(BU$35=$G$445)*(AB16+$G$430-$O16-$G$435) -> 8743.8649 | BV42: =(BV$35=0)*($O16-$G$430)+(BV$35=$G$444)*$G$435+(BV$35=$G$445)*(AC16+$G$430-$O16-$G$435) -> -2350 | BW42: =(BW$35=0)*($O16-$G$430)+(BW$35=$G$444)*$G$435+(BW$35=$G$445)*(AC16+$G$430-$O16-$G$435) -> 0 | BX42: =(BX$35=0)*($O16-$G$430)+(BX$35=$G$444)*$G$435+(BX$35=$G$445)*(AC16+$G$430-$O16-$G$435) -> 0 | BY42: =(BY$35=0)*($O16-$G$430)+(BY$35=$G$444)*$G$435+(BY$35=$G$445)*(AC16+$G$430-$O16-$G$435) -> 0 | BZ42: =(BZ$35=0)*($O16-$G$430)+(BZ$35=$G$444)*$G$435+(BZ$35=$G$445)*(AC16+$G$430-$O16-$G$435) -> 0 | CA42: =(CA$35=0)*($O16-$G$430)+(CA$35=$G$444)*$G$435+(CA$35=$G$445)*(AC16+$G$430-$O16-$G$435) -> 8973.681 | CB42: =(CB$35=0)*($O16-$G$430)+(CB$35=$G$444)*$G$435+(CB$35=$G$445)*(AD16+$G$430-$O16-$G$435) -> -2350 | CC42: =(CC$35=0)*($O16-$G$430)+(CC$35=$G$444)*$G$435+(CC$35=$G$445)*(AD16+$G$430-$O16-$G$435) -> 0 | CD42: =(CD$35=0)*($O16-$G$430)+(CD$35=$G$444)*$G$435+(CD$35=$G$445)*(AD16+$G$430-$O16-$G$435) -> 0 | CE42: =(CE$35=0)*($O16-$G$430)+(CE$35=$G$444)*$G$435+(CE$35=$G$445)*(AD16+$G$430-$O16-$G$435) -> 0 | CF42: =(CF$35=0)*($O16-$G$430)+(CF$35=$G$444)*$G$435+(CF$35=$G$445)*(AD16+$G$430-$O16-$G$435) -> 0 | CG42: =(CG$35=0)*($O16-$G$430)+(CG$35=$G$444)*$G$435+(CG$35=$G$445)*(AD16+$G$430-$O16-$G$435) -> 9203.4972 | CH42: =(CH$35=0)*($O16-$G$430)+(CH$35=$G$444)*$G$435+(CH$35=$G$445)*(AE16+$G$430-$O16-$G$435) -> -2350 | CI42: =(CI$35=0)*($O16-$G$430)+(CI$35=$G$444)*$G$435+(CI$35=$G$445)*(AE16+$G$430-$O16-$G$435) -> 0 | CJ42: =(CJ$35=0)*($O16-$G$430)+(CJ$35=$G$444)*$G$435+(CJ$35=$G$445)*(AE16+$G$430-$O16-$G$435) -> 0 | CK42: =(CK$35=0)*($O16-$G$430)+(CK$35=$G$444)*$G$435+(CK$35=$G$445)*(AE16+$G$430-$O16-$G$435) -> 0 | CL42: =(CL$35=0)*($O16-$G$430)+(CL$35=$G$444)*$G$435+(CL$35=$G$445)*(AE16+$G$430-$O16-$G$435) -> 0 | CM42: =(CM$35=0)*($O16-$G$430)+(CM$35=$G$444)*$G$435+(CM$35=$G$445)*(AE16+$G$430-$O16-$G$435) -> 9433.3134 | CN42: =(CN$35=0)*($O16-$G$430)+(CN$35=$G$444)*$G$435+(CN$35=$G$445)*(AF16+$G$430-$O16-$G$435) -> -2350 | CO42: =(CO$35=0)*($O16-$G$430)+(CO$35=$G$444)*$G$435+(CO$35=$G$445)*(AF16+$G$430-$O16-$G$435) -> 0 | CP42: =(CP$35=0)*($O16-$G$430)+(CP$35=$G$444)*$G$435+(CP$35=$G$445)*(AF16+$G$430-$O16-$G$435) -> 0 | CQ42: =(CQ$35=0)*($O16-$G$430)+(CQ$35=$G$444)*$G$435+(CQ$35=$G$445)*(AF16+$G$430-$O16-$G$435) -> 0 | CR42: =(CR$35=0)*($O16-$G$430)+(CR$35=$G$444)*$G$435+(CR$35=$G$445)*(AF16+$G$430-$O16-$G$435) -> 0 | CS42: =(CS$35=0)*($O16-$G$430)+(CS$35=$G$444)*$G$435+(CS$35=$G$445)*(AF16+$G$430-$O16-$G$435) -> 9663.1296 | CT42: =(CT$35=0)*($O16-$G$430)+(CT$35=$G$444)*$G$435+(CT$35=$G$445)*(AG16+$G$430-$O16-$G$435) -> -2350 | CU42: =(CU$35=0)*($O16-$G$430)+(CU$35=$G$444)*$G$435+(CU$35=$G$445)*(AG16+$G$430-$O16-$G$435) -> 0 | CV42: =(CV$35=0)*($O16-$G$430)+(CV$35=$G$444)*$G$435+(CV$35=$G$445)*(AG16+$G$430-$O16-$G$435) -> 0 | CW42: =(CW$35=0)*($O16-$G$430)+(CW$35=$G$444)*$G$435+(CW$35=$G$445)*(AG16+$G$430-$O16-$G$435) -> 0 | CX42: =(CX$35=0)*($O16-$G$430)+(CX$35=$G$444)*$G$435+(CX$35=$G$445)*(AG16+$G$430-$O16-$G$435) -> 0 | CY42: =(CY$35=0)*($O16-$G$430)+(CY$35=$G$444)*$G$435+(CY$35=$G$445)*(AG16+$G$430-$O16-$G$435) -> 9892.9457 | CZ42: =(CZ$35=0)*($O16-$G$430)+(CZ$35=$G$444)*$G$435+(CZ$35=$G$445)*(AH16+$G$430-$O16-$G$435) -> -2350 | DA42: =(DA$35=0)*($O16-$G$430)+(DA$35=$G$444)*$G$435+(DA$35=$G$445)*(AH16+$G$430-$O16-$G$435) -> 0 | DB42: =(DB$35=0)*($O16-$G$430)+(DB$35=$G$444)*$G$435+(DB$35=$G$445)*(AH16+$G$430-$O16-$G$435) -> 0 | DC42: =(DC$35=0)*($O16-$G$430)+(DC$35=$G$444)*$G$435+(DC$35=$G$445)*(AH16+$G$430-$O16-$G$435) -> 0 | DD42: =(DD$35=0)*($O16-$G$430)+(DD$35=$G$444)*$G$435+(DD$35=$G$445)*(AH16+$G$430-$O16-$G$435) -> 0 | DE42: =(DE$35=0)*($O16-$G$430)+(DE$35=$G$444)*$G$435+(DE$35=$G$445)*(AH16+$G$430-$O16-$G$435) -> 10122.762
B43: IRR on Ben's cash flows: Yr 0 = cash at close less Keystone value today; earnout in Yr 3; Yr 5 = stake value
B45: Ben's Return Profile Based on Partnering — Less Standalone
B46: Ben's Net Returns vs. Standalone Based on Topkey Growth & Rollover %
D48: Topkey ex-Keystone Value Growth (%) | Z48: Helper: Unrounded Net Return vs. Standalone
D49: =E49-$G$441 -> 0.013171226 | E49: =F49-$G$441 -> 0.26317123 | F49: =G49-$G$441 -> 0.51317123 | G49: =H49-$G$441 -> 0.76317123 | H49: =$G$440 -> 1.0131712 | I49: =H49+$G$441 -> 1.2631712 | J49: =I49+$G$441 -> 1.5131712 | K49: =J49+$G$441 -> 1.7631712 | L49: =K49+$G$441 -> 2.0131712 | Z49: =D$9 -> 0.013171226 | AA49: =E$9 -> 0.26317123 | AB49: =F$9 -> 0.51317123 | AC49: =G$9 -> 0.76317123 | AD49: =H$9 -> 1.0131712 | AE49: =I$9 -> 1.2631712 | AF49: =J$9 -> 1.5131712 | AG49: =K$9 -> 1.7631712 | AH49: =L$9 -> 2.0131712 | AT49: Helper: Gradient Band (0 = below $1M hurdle)
B50: Ben's Rollover % | C50: =C51-$G$439 -> 0.15 | D50: =ROUND(Z50,$G$452) -> -2200 | E50: =ROUND(AA50,$G$452) -> -1800 | F50: =ROUND(AB50,$G$452) -> -1400 | G50: =ROUND(AC50,$G$452) -> -900 | H50: =ROUND(AD50,$G$452) -> -500 | I50: =ROUND(AE50,$G$452) -> -100 | J50: =ROUND(AF50,$G$452) -> 300 | K50: =ROUND(AG50,$G$452) -> 800 | L50: =ROUND(AH50,$G$452) -> 1200 | Z50: =Z10+$G$430-$G$447 -> -2232.6658 | AA50: =AA10+$G$430-$G$447 -> -1803.587 | AB50: =AB10+$G$430-$G$447 -> -1374.5083 | AC50: =AC10+$G$430-$G$447 -> -945.42953 | AD50: =AD10+$G$430-$G$447 -> -516.35077 | AE50: =AE10+$G$430-$G$447 -> -87.272012 | AF50: =AF10+$G$430-$G$447 -> 341.80674 | AG50: =AG10+$G$430-$G$447 -> 770.8855 | AH50: =AH10+$G$430-$G$447 -> 1199.9643 | AT50: =IF(Z50<$G$449,0,MIN($G$446,1+IFERROR(INT((Z50-$G$449)/$G$451),0))) -> 0 | AU50: =IF(AA50<$G$449,0,MIN($G$446,1+IFERROR(INT((AA50-$G$449)/$G$451),0))) -> 0 | AV50: =IF(AB50<$G$449,0,MIN($G$446,1+IFERROR(INT((AB50-$G$449)/$G$451),0))) -> 0 | AW50: =IF(AC50<$G$449,0,MIN($G$446,1+IFERROR(INT((AC50-$G$449)/$G$451),0))) -> 0 | AX50: =IF(AD50<$G$449,0,MIN($G$446,1+IFERROR(INT((AD50-$G$449)/$G$451),0))) -> 0 | AY50: =IF(AE50<$G$449,0,MIN($G$446,1+IFERROR(INT((AE50-$G$449)/$G$451),0))) -> 0 | AZ50: =IF(AF50<$G$449,0,MIN($G$446,1+IFERROR(INT((AF50-$G$449)/$G$451),0))) -> 0 | BA50: =IF(AG50<$G$449,0,MIN($G$446,1+IFERROR(INT((AG50-$G$449)/$G$451),0))) -> 0 | BB50: =IF(AH50<$G$449,0,MIN($G$446,1+IFERROR(INT((AH50-$G$449)/$G$451),0))) -> 1
C51: =C52-$G$439 -> 0.2 | D51: =ROUND(Z51,$G$452) -> -1600 | E51: =ROUND(AA51,$G$452) -> -1200 | F51: =ROUND(AB51,$G$452) -> -800 | G51: =ROUND(AC51,$G$452) -> -400 | H51: =ROUND(AD51,$G$452) -> 0 | I51: =ROUND(AE51,$G$452) -> 400 | J51: =ROUND(AF51,$G$452) -> 700 | K51: =ROUND(AG51,$G$452) -> 1100 | L51: =ROUND(AH51,$G$452) -> 1500 | Z51: =Z11+$G$430-$G$447 -> -1628.1943 | AA51: =AA11+$G$430-$G$447 -> -1231.8447 | AB51: =AB11+$G$430-$G$447 -> -835.49502 | AC51: =AC11+$G$430-$G$447 -> -439.14539 | AD51: =AD11+$G$430-$G$447 -> -42.795748 | AE51: =AE11+$G$430-$G$447 -> 353.55389 | AF51: =AF11+$G$430-$G$447 -> 749.90353 | AG51: =AG11+$G$430-$G$447 -> 1146.2532 | AH51: =AH11+$G$430-$G$447 -> 1542.6028 | AT51: =IF(Z51<$G$449,0,MIN($G$446,1+IFERROR(INT((Z51-$G$449)/$G$451),0))) -> 0 | AU51: =IF(AA51<$G$449,0,MIN($G$446,1+IFERROR(INT((AA51-$G$449)/$G$451),0))) -> 0 | AV51: =IF(AB51<$G$449,0,MIN($G$446,1+IFERROR(INT((AB51-$G$449)/$G$451),0))) -> 0 | AW51: =IF(AC51<$G$449,0,MIN($G$446,1+IFERROR(INT((AC51-$G$449)/$G$451),0))) -> 0 | AX51: =IF(AD51<$G$449,0,MIN($G$446,1+IFERROR(INT((AD51-$G$449)/$G$451),0))) -> 0 | AY51: =IF(AE51<$G$449,0,MIN($G$446,1+IFERROR(INT((AE51-$G$449)/$G$451),0))) -> 0 | AZ51: =IF(AF51<$G$449,0,MIN($G$446,1+IFERROR(INT((AF51-$G$449)/$G$451),0))) -> 0 | BA51: =IF(AG51<$G$449,0,MIN($G$446,1+IFERROR(INT((AG51-$G$449)/$G$451),0))) -> 1 | BB51: =IF(AH51<$G$449,0,MIN($G$446,1+IFERROR(INT((AH51-$G$449)/$G$451),0))) -> 3
C52: =C53-$G$439 -> 0.25 | D52: =ROUND(Z52,$G$452) -> -1000 | E52: =ROUND(AA52,$G$452) -> -700 | F52: =ROUND(AB52,$G$452) -> -300 | G52: =ROUND(AC52,$G$452) -> 100 | H52: =ROUND(AD52,$G$452) -> 400 | I52: =ROUND(AE52,$G$452) -> 800 | J52: =ROUND(AF52,$G$452) -> 1200 | K52: =ROUND(AG52,$G$452) -> 1500 | L52: =ROUND(AH52,$G$452) -> 1900 | Z52: =Z12+$G$430-$G$447 -> -1020.4406 | AA52: =AA12+$G$430-$G$447 -> -657.01041 | AB52: =AB12+$G$430-$G$447 -> -293.58017 | AC52: =AC12+$G$430-$G$447 -> 69.85006 | AD52: =AD12+$G$430-$G$447 -> 433.28029 | AE52: =AE12+$G$430-$G$447 -> 796.71053 | AF52: =AF12+$G$430-$G$447 -> 1160.1408 | AG52: =AG12+$G$430-$G$447 -> 1523.571 | AH52: =AH12+$G$430-$G$447 -> 1887.0012 | AT52: =IF(Z52<$G$449,0,MIN($G$446,1+IFERROR(INT((Z52-$G$449)/$G$451),0))) -> 0 | AU52: =IF(AA52<$G$449,0,MIN($G$446,1+IFERROR(INT((AA52-$G$449)/$G$451),0))) -> 0 | AV52: =IF(AB52<$G$449,0,MIN($G$446,1+IFERROR(INT((AB52-$G$449)/$G$451),0))) -> 0 | AW52: =IF(AC52<$G$449,0,MIN($G$446,1+IFERROR(INT((AC52-$G$449)/$G$451),0))) -> 0 | AX52: =IF(AD52<$G$449,0,MIN($G$446,1+IFERROR(INT((AD52-$G$449)/$G$451),0))) -> 0 | AY52: =IF(AE52<$G$449,0,MIN($G$446,1+IFERROR(INT((AE52-$G$449)/$G$451),0))) -> 0 | AZ52: =IF(AF52<$G$449,0,MIN($G$446,1+IFERROR(INT((AF52-$G$449)/$G$451),0))) -> 1 | BA52: =IF(AG52<$G$449,0,MIN($G$446,1+IFERROR(INT((AG52-$G$449)/$G$451),0))) -> 3 | BB52: =IF(AH52<$G$449,0,MIN($G$446,1+IFERROR(INT((AH52-$G$449)/$G$451),0))) -> 4
C53: =$G$438 -> 0.3 | D53: =ROUND(Z53,$G$452) -> -400 | E53: =ROUND(AA53,$G$452) -> -100 | F53: =ROUND(AB53,$G$452) -> 300 | G53: =ROUND(AC53,$G$452) -> 600 | H53: =ROUND(AD53,$G$452) -> 900 | I53: =ROUND(AE53,$G$452) -> 1200 | J53: =ROUND(AF53,$G$452) -> 1600 | K53: =ROUND(AG53,$G$452) -> 1900 | L53: =ROUND(AH53,$G$452) -> 2200 | Z53: =Z13+$G$430-$G$447 -> -409.37611 | AA53: =AA13+$G$430-$G$447 -> -79.057232 | AB53: =AB13+$G$430-$G$447 -> 251.26165 | AC53: =AC13+$G$430-$G$447 -> 581.58052 | AD53: =AD13+$G$430-$G$447 -> 911.8994 | AE53: =AE13+$G$430-$G$447 -> 1242.2183 | AF53: =AF13+$G$430-$G$447 -> 1572.5372 | AG53: =AG13+$G$430-$G$447 -> 1902.856 | AH53: =AH13+$G$430-$G$447 -> 2233.1749 | AT53: =IF(Z53<$G$449,0,MIN($G$446,1+IFERROR(INT((Z53-$G$449)/$G$451),0))) -> 0 | AU53: =IF(AA53<$G$449,0,MIN($G$446,1+IFERROR(INT((AA53-$G$449)/$G$451),0))) -> 0 | AV53: =IF(AB53<$G$449,0,MIN($G$446,1+IFERROR(INT((AB53-$G$449)/$G$451),0))) -> 0 | AW53: =IF(AC53<$G$449,0,MIN($G$446,1+IFERROR(INT((AC53-$G$449)/$G$451),0))) -> 0 | AX53: =IF(AD53<$G$449,0,MIN($G$446,1+IFERROR(INT((AD53-$G$449)/$G$451),0))) -> 0 | AY53: =IF(AE53<$G$449,0,MIN($G$446,1+IFERROR(INT((AE53-$G$449)/$G$451),0))) -> 2 | AZ53: =IF(AF53<$G$449,0,MIN($G$446,1+IFERROR(INT((AF53-$G$449)/$G$451),0))) -> 3 | BA53: =IF(AG53<$G$449,0,MIN($G$446,1+IFERROR(INT((AG53-$G$449)/$G$451),0))) -> 4 | BB53: =IF(AH53<$G$449,0,MIN($G$446,1+IFERROR(INT((AH53-$G$449)/$G$451),0))) -> 6
C54: =C53+$G$439 -> 0.35 | D54: =ROUND(Z54,$G$452) -> 200 | E54: =ROUND(AA54,$G$452) -> 500 | F54: =ROUND(AB54,$G$452) -> 800 | G54: =ROUND(AC54,$G$452) -> 1100 | H54: =ROUND(AD54,$G$452) -> 1400 | I54: =ROUND(AE54,$G$452) -> 1700 | J54: =ROUND(AF54,$G$452) -> 2000 | K54: =ROUND(AG54,$G$452) -> 2300 | L54: =ROUND(AH54,$G$452) -> 2600 | Z54: =Z14+$G$430-$G$447 -> 205.02833 | AA54: =AA14+$G$430-$G$447 -> 502.04222 | AB54: =AB14+$G$430-$G$447 -> 799.05611 | AC54: =AC14+$G$430-$G$447 -> 1096.07 | AD54: =AD14+$G$430-$G$447 -> 1393.0839 | AE54: =AE14+$G$430-$G$447 -> 1690.0978 | AF54: =AF14+$G$430-$G$447 -> 1987.1117 | AG54: =AG14+$G$430-$G$447 -> 2284.1256 | AH54: =AH14+$G$430-$G$447 -> 2581.1394 | AT54: =IF(Z54<$G$449,0,MIN($G$446,1+IFERROR(INT((Z54-$G$449)/$G$451),0))) -> 0 | AU54: =IF(AA54<$G$449,0,MIN($G$446,1+IFERROR(INT((AA54-$G$449)/$G$451),0))) -> 0 | AV54: =IF(AB54<$G$449,0,MIN($G$446,1+IFERROR(INT((AB54-$G$449)/$G$451),0))) -> 0 | AW54: =IF(AC54<$G$449,0,MIN($G$446,1+IFERROR(INT((AC54-$G$449)/$G$451),0))) -> 1 | AX54: =IF(AD54<$G$449,0,MIN($G$446,1+IFERROR(INT((AD54-$G$449)/$G$451),0))) -> 2 | AY54: =IF(AE54<$G$449,0,MIN($G$446,1+IFERROR(INT((AE54-$G$449)/$G$451),0))) -> 4 | AZ54: =IF(AF54<$G$449,0,MIN($G$446,1+IFERROR(INT((AF54-$G$449)/$G$451),0))) -> 5 | BA54: =IF(AG54<$G$449,0,MIN($G$446,1+IFERROR(INT((AG54-$G$449)/$G$451),0))) -> 6 | BB54: =IF(AH54<$G$449,0,MIN($G$446,1+IFERROR(INT((AH54-$G$449)/$G$451),0))) -> 7
C55: =C54+$G$439 -> 0.4 | D55: =ROUND(Z55,$G$452) -> 800 | E55: =ROUND(AA55,$G$452) -> 1100 | F55: =ROUND(AB55,$G$452) -> 1300 | G55: =ROUND(AC55,$G$452) -> 1600 | H55: =ROUND(AD55,$G$452) -> 1900 | I55: =ROUND(AE55,$G$452) -> 2100 | J55: =ROUND(AF55,$G$452) -> 2400 | K55: =ROUND(AG55,$G$452) -> 2700 | L55: =ROUND(AH55,$G$452) -> 2900 | Z55: =Z15+$G$430-$G$447 -> 822.80206 | AA55: =AA15+$G$430-$G$447 -> 1086.3156 | AB55: =AB15+$G$430-$G$447 -> 1349.8292 | AC55: =AC15+$G$430-$G$447 -> 1613.3427 | AD55: =AD15+$G$430-$G$447 -> 1876.8563 | AE55: =AE15+$G$430-$G$447 -> 2140.3699 | AF55: =AF15+$G$430-$G$447 -> 2403.8834 | AG55: =AG15+$G$430-$G$447 -> 2667.397 | AH55: =AH15+$G$430-$G$447 -> 2930.9106 | AT55: =IF(Z55<$G$449,0,MIN($G$446,1+IFERROR(INT((Z55-$G$449)/$G$451),0))) -> 0 | AU55: =IF(AA55<$G$449,0,MIN($G$446,1+IFERROR(INT((AA55-$G$449)/$G$451),0))) -> 1 | AV55: =IF(AB55<$G$449,0,MIN($G$446,1+IFERROR(INT((AB55-$G$449)/$G$451),0))) -> 2 | AW55: =IF(AC55<$G$449,0,MIN($G$446,1+IFERROR(INT((AC55-$G$449)/$G$451),0))) -> 3 | AX55: =IF(AD55<$G$449,0,MIN($G$446,1+IFERROR(INT((AD55-$G$449)/$G$451),0))) -> 4 | AY55: =IF(AE55<$G$449,0,MIN($G$446,1+IFERROR(INT((AE55-$G$449)/$G$451),0))) -> 5 | AZ55: =IF(AF55<$G$449,0,MIN($G$446,1+IFERROR(INT((AF55-$G$449)/$G$451),0))) -> 7 | BA55: =IF(AG55<$G$449,0,MIN($G$446,1+IFERROR(INT((AG55-$G$449)/$G$451),0))) -> 8 | BB55: =IF(AH55<$G$449,0,MIN($G$446,1+IFERROR(INT((AH55-$G$449)/$G$451),0))) -> 9
C56: =C55+$G$439 -> 0.45 | D56: =ROUND(Z56,$G$452) -> 1400 | E56: =ROUND(AA56,$G$452) -> 1700 | F56: =ROUND(AB56,$G$452) -> 1900 | G56: =ROUND(AC56,$G$452) -> 2100 | H56: =ROUND(AD56,$G$452) -> 2400 | I56: =ROUND(AE56,$G$452) -> 2600 | J56: =ROUND(AF56,$G$452) -> 2800 | K56: =ROUND(AG56,$G$452) -> 3100 | L56: =ROUND(AH56,$G$452) -> 3300 | Z56: =Z16+$G$430-$G$447 -> 1443.9748 | AA56: =AA16+$G$430-$G$447 -> 1673.791 | AB56: =AB16+$G$430-$G$447 -> 1903.6072 | AC56: =AC16+$G$430-$G$447 -> 2133.4233 | AD56: =AD16+$G$430-$G$447 -> 2363.2395 | AE56: =AE16+$G$430-$G$447 -> 2593.0557 | AF56: =AF16+$G$430-$G$447 -> 2822.8719 | AG56: =AG16+$G$430-$G$447 -> 3052.688 | AH56: =AH16+$G$430-$G$447 -> 3282.5042 | AT56: =IF(Z56<$G$449,0,MIN($G$446,1+IFERROR(INT((Z56-$G$449)/$G$451),0))) -> 2 | AU56: =IF(AA56<$G$449,0,MIN($G$446,1+IFERROR(INT((AA56-$G$449)/$G$451),0))) -> 3 | AV56: =IF(AB56<$G$449,0,MIN($G$446,1+IFERROR(INT((AB56-$G$449)/$G$451),0))) -> 4 | AW56: =IF(AC56<$G$449,0,MIN($G$446,1+IFERROR(INT((AC56-$G$449)/$G$451),0))) -> 5 | AX56: =IF(AD56<$G$449,0,MIN($G$446,1+IFERROR(INT((AD56-$G$449)/$G$451),0))) -> 6 | AY56: =IF(AE56<$G$449,0,MIN($G$446,1+IFERROR(INT((AE56-$G$449)/$G$451),0))) -> 7 | AZ56: =IF(AF56<$G$449,0,MIN($G$446,1+IFERROR(INT((AF56-$G$449)/$G$451),0))) -> 8 | BA56: =IF(AG56<$G$449,0,MIN($G$446,1+IFERROR(INT((AG56-$G$449)/$G$451),0))) -> 9 | BB56: =IF(AH56<$G$449,0,MIN($G$446,1+IFERROR(INT((AH56-$G$449)/$G$451),0))) -> 10
B57: Ben's Year 5 partnership value less standalone Year 5 value (G447)
B59: Ben's % Return vs. Standalone Based on Topkey Growth & Rollover %
D61: Topkey ex-Keystone Value Growth (%)
D62: =E62-$G$441 -> 0.013171226 | E62: =F62-$G$441 -> 0.26317123 | F62: =G62-$G$441 -> 0.51317123 | G62: =H62-$G$441 -> 0.76317123 | H62: =$G$440 -> 1.0131712 | I62: =H62+$G$441 -> 1.2631712 | J62: =I62+$G$441 -> 1.5131712 | K62: =J62+$G$441 -> 1.7631712 | L62: =K62+$G$441 -> 2.0131712 | AT62: Helper: Gradient Band (0 = below $1M hurdle)
B63: Ben's Rollover % | C63: =C64-$G$439 -> 0.15 | D63: =IFERROR(Z50/$G$447,0) -> -0.29807597 | E63: =IFERROR(AA50/$G$447,0) -> -0.24079105 | F63: =IFERROR(AB50/$G$447,0) -> -0.18350614 | G63: =IFERROR(AC50/$G$447,0) -> -0.12622123 | H63: =IFERROR(AD50/$G$447,0) -> -0.068936316 | I63: =IFERROR(AE50/$G$447,0) -> -0.011651403 | J63: =IFERROR(AF50/$G$447,0) -> 0.045633509 | K63: =IFERROR(AG50/$G$447,0) -> 0.10291842 | L63: =IFERROR(AH50/$G$447,0) -> 0.16020333 | AT63: =IF(Z50<$G$449,0,MIN($G$446,1+IFERROR(INT((Z50-$G$449)/$G$451),0))) -> 0 | AU63: =IF(AA50<$G$449,0,MIN($G$446,1+IFERROR(INT((AA50-$G$449)/$G$451),0))) -> 0 | AV63: =IF(AB50<$G$449,0,MIN($G$446,1+IFERROR(INT((AB50-$G$449)/$G$451),0))) -> 0 | AW63: =IF(AC50<$G$449,0,MIN($G$446,1+IFERROR(INT((AC50-$G$449)/$G$451),0))) -> 0 | AX63: =IF(AD50<$G$449,0,MIN($G$446,1+IFERROR(INT((AD50-$G$449)/$G$451),0))) -> 0 | AY63: =IF(AE50<$G$449,0,MIN($G$446,1+IFERROR(INT((AE50-$G$449)/$G$451),0))) -> 0 | AZ63: =IF(AF50<$G$449,0,MIN($G$446,1+IFERROR(INT((AF50-$G$449)/$G$451),0))) -> 0 | BA63: =IF(AG50<$G$449,0,MIN($G$446,1+IFERROR(INT((AG50-$G$449)/$G$451),0))) -> 0 | BB63: =IF(AH50<$G$449,0,MIN($G$446,1+IFERROR(INT((AH50-$G$449)/$G$451),0))) -> 1
C64: =C65-$G$439 -> 0.2 | D64: =IFERROR(Z51/$G$447,0) -> -0.21737494 | E64: =IFERROR(AA51/$G$447,0) -> -0.16445958 | F64: =IFERROR(AB51/$G$447,0) -> -0.11154423 | G64: =IFERROR(AC51/$G$447,0) -> -0.058628875 | H64: =IFERROR(AD51/$G$447,0) -> -0.0057135214 | I64: =IFERROR(AE51/$G$447,0) -> 0.047201833 | J64: =IFERROR(AF51/$G$447,0) -> 0.10011719 | K64: =IFERROR(AG51/$G$447,0) -> 0.15303254 | L64: =IFERROR(AH51/$G$447,0) -> 0.20594789 | AT64: =IF(Z51<$G$449,0,MIN($G$446,1+IFERROR(INT((Z51-$G$449)/$G$451),0))) -> 0 | AU64: =IF(AA51<$G$449,0,MIN($G$446,1+IFERROR(INT((AA51-$G$449)/$G$451),0))) -> 0 | AV64: =IF(AB51<$G$449,0,MIN($G$446,1+IFERROR(INT((AB51-$G$449)/$G$451),0))) -> 0 | AW64: =IF(AC51<$G$449,0,MIN($G$446,1+IFERROR(INT((AC51-$G$449)/$G$451),0))) -> 0 | AX64: =IF(AD51<$G$449,0,MIN($G$446,1+IFERROR(INT((AD51-$G$449)/$G$451),0))) -> 0 | AY64: =IF(AE51<$G$449,0,MIN($G$446,1+IFERROR(INT((AE51-$G$449)/$G$451),0))) -> 0 | AZ64: =IF(AF51<$G$449,0,MIN($G$446,1+IFERROR(INT((AF51-$G$449)/$G$451),0))) -> 0 | BA64: =IF(AG51<$G$449,0,MIN($G$446,1+IFERROR(INT((AG51-$G$449)/$G$451),0))) -> 1 | BB64: =IF(AH51<$G$449,0,MIN($G$446,1+IFERROR(INT((AH51-$G$449)/$G$451),0))) -> 3
C65: =C66-$G$439 -> 0.25 | D65: =IFERROR(Z52/$G$447,0) -> -0.13623572 | E65: =IFERROR(AA52/$G$447,0) -> -0.087715327 | F65: =IFERROR(AB52/$G$447,0) -> -0.039194936 | G65: =IFERROR(AC52/$G$447,0) -> 0.0093254548 | H65: =IFERROR(AD52/$G$447,0) -> 0.057845846 | I65: =IFERROR(AE52/$G$447,0) -> 0.10636624 | J65: =IFERROR(AF52/$G$447,0) -> 0.15488663 | K65: =IFERROR(AG52/$G$447,0) -> 0.20340702 | L65: =IFERROR(AH52/$G$447,0) -> 0.25192741 | AT65: =IF(Z52<$G$449,0,MIN($G$446,1+IFERROR(INT((Z52-$G$449)/$G$451),0))) -> 0 | AU65: =IF(AA52<$G$449,0,MIN($G$446,1+IFERROR(INT((AA52-$G$449)/$G$451),0))) -> 0 | AV65: =IF(AB52<$G$449,0,MIN($G$446,1+IFERROR(INT((AB52-$G$449)/$G$451),0))) -> 0 | AW65: =IF(AC52<$G$449,0,MIN($G$446,1+IFERROR(INT((AC52-$G$449)/$G$451),0))) -> 0 | AX65: =IF(AD52<$G$449,0,MIN($G$446,1+IFERROR(INT((AD52-$G$449)/$G$451),0))) -> 0 | AY65: =IF(AE52<$G$449,0,MIN($G$446,1+IFERROR(INT((AE52-$G$449)/$G$451),0))) -> 0 | AZ65: =IF(AF52<$G$449,0,MIN($G$446,1+IFERROR(INT((AF52-$G$449)/$G$451),0))) -> 1 | BA65: =IF(AG52<$G$449,0,MIN($G$446,1+IFERROR(INT((AG52-$G$449)/$G$451),0))) -> 3 | BB65: =IF(AH52<$G$449,0,MIN($G$446,1+IFERROR(INT((AH52-$G$449)/$G$451),0))) -> 4
C66: =$G$438 -> 0.3 | D66: =IFERROR(Z53/$G$447,0) -> -0.054654476 | E66: =IFERROR(AA53/$G$447,0) -> -0.010554675 | F66: =IFERROR(AB53/$G$447,0) -> 0.033545127 | G66: =IFERROR(AC53/$G$447,0) -> 0.077644928 | H66: =IFERROR(AD53/$G$447,0) -> 0.12174473 | I66: =IFERROR(AE53/$G$447,0) -> 0.16584453 | J66: =IFERROR(AF53/$G$447,0) -> 0.20994433 | K66: =IFERROR(AG53/$G$447,0) -> 0.25404413 | L66: =IFERROR(AH53/$G$447,0) -> 0.29814394 | AT66: =IF(Z53<$G$449,0,MIN($G$446,1+IFERROR(INT((Z53-$G$449)/$G$451),0))) -> 0 | AU66: =IF(AA53<$G$449,0,MIN($G$446,1+IFERROR(INT((AA53-$G$449)/$G$451),0))) -> 0 | AV66: =IF(AB53<$G$449,0,MIN($G$446,1+IFERROR(INT((AB53-$G$449)/$G$451),0))) -> 0 | AW66: =IF(AC53<$G$449,0,MIN($G$446,1+IFERROR(INT((AC53-$G$449)/$G$451),0))) -> 0 | AX66: =IF(AD53<$G$449,0,MIN($G$446,1+IFERROR(INT((AD53-$G$449)/$G$451),0))) -> 0 | AY66: =IF(AE53<$G$449,0,MIN($G$446,1+IFERROR(INT((AE53-$G$449)/$G$451),0))) -> 2 | AZ66: =IF(AF53<$G$449,0,MIN($G$446,1+IFERROR(INT((AF53-$G$449)/$G$451),0))) -> 3 | BA66: =IF(AG53<$G$449,0,MIN($G$446,1+IFERROR(INT((AG53-$G$449)/$G$451),0))) -> 4 | BB66: =IF(AH53<$G$449,0,MIN($G$446,1+IFERROR(INT((AH53-$G$449)/$G$451),0))) -> 6
C67: =C66+$G$439 -> 0.35 | D67: =IFERROR(Z54/$G$447,0) -> 0.027372667 | E67: =IFERROR(AA54/$G$447,0) -> 0.067026027 | F67: =IFERROR(AB54/$G$447,0) -> 0.10667939 | G67: =IFERROR(AC54/$G$447,0) -> 0.14633275 | H67: =IFERROR(AD54/$G$447,0) -> 0.18598611 | I67: =IFERROR(AE54/$G$447,0) -> 0.22563947 | J67: =IFERROR(AF54/$G$447,0) -> 0.26529283 | K67: =IFERROR(AG54/$G$447,0) -> 0.30494619 | L67: =IFERROR(AH54/$G$447,0) -> 0.34459955 | AT67: =IF(Z54<$G$449,0,MIN($G$446,1+IFERROR(INT((Z54-$G$449)/$G$451),0))) -> 0 | AU67: =IF(AA54<$G$449,0,MIN($G$446,1+IFERROR(INT((AA54-$G$449)/$G$451),0))) -> 0 | AV67: =IF(AB54<$G$449,0,MIN($G$446,1+IFERROR(INT((AB54-$G$449)/$G$451),0))) -> 0 | AW67: =IF(AC54<$G$449,0,MIN($G$446,1+IFERROR(INT((AC54-$G$449)/$G$451),0))) -> 1 | AX67: =IF(AD54<$G$449,0,MIN($G$446,1+IFERROR(INT((AD54-$G$449)/$G$451),0))) -> 2 | AY67: =IF(AE54<$G$449,0,MIN($G$446,1+IFERROR(INT((AE54-$G$449)/$G$451),0))) -> 4 | AZ67: =IF(AF54<$G$449,0,MIN($G$446,1+IFERROR(INT((AF54-$G$449)/$G$451),0))) -> 5 | BA67: =IF(AG54<$G$449,0,MIN($G$446,1+IFERROR(INT((AG54-$G$449)/$G$451),0))) -> 6 | BB67: =IF(AH54<$G$449,0,MIN($G$446,1+IFERROR(INT((AH54-$G$449)/$G$451),0))) -> 7
C68: =C67+$G$439 -> 0.4 | D68: =IFERROR(Z55/$G$447,0) -> 0.10984963 | E68: =IFERROR(AA55/$G$447,0) -> 0.14503047 | F68: =IFERROR(AB55/$G$447,0) -> 0.18021131 | G68: =IFERROR(AC55/$G$447,0) -> 0.21539216 | H68: =IFERROR(AD55/$G$447,0) -> 0.250573 | I68: =IFERROR(AE55/$G$447,0) -> 0.28575384 | J68: =IFERROR(AF55/$G$447,0) -> 0.32093468 | K68: =IFERROR(AG55/$G$447,0) -> 0.35611552 | L68: =IFERROR(AH55/$G$447,0) -> 0.39129636 | AT68: =IF(Z55<$G$449,0,MIN($G$446,1+IFERROR(INT((Z55-$G$449)/$G$451),0))) -> 0 | AU68: =IF(AA55<$G$449,0,MIN($G$446,1+IFERROR(INT((AA55-$G$449)/$G$451),0))) -> 1 | AV68: =IF(AB55<$G$449,0,MIN($G$446,1+IFERROR(INT((AB55-$G$449)/$G$451),0))) -> 2 | AW68: =IF(AC55<$G$449,0,MIN($G$446,1+IFERROR(INT((AC55-$G$449)/$G$451),0))) -> 3 | AX68: =IF(AD55<$G$449,0,MIN($G$446,1+IFERROR(INT((AD55-$G$449)/$G$451),0))) -> 4 | AY68: =IF(AE55<$G$449,0,MIN($G$446,1+IFERROR(INT((AE55-$G$449)/$G$451),0))) -> 5 | AZ68: =IF(AF55<$G$449,0,MIN($G$446,1+IFERROR(INT((AF55-$G$449)/$G$451),0))) -> 7 | BA68: =IF(AG55<$G$449,0,MIN($G$446,1+IFERROR(INT((AG55-$G$449)/$G$451),0))) -> 8 | BB68: =IF(AH55<$G$449,0,MIN($G$446,1+IFERROR(INT((AH55-$G$449)/$G$451),0))) -> 9
C69: =C68+$G$439 -> 0.45 | D69: =IFERROR(Z56/$G$447,0) -> 0.19278039 | E69: =IFERROR(AA56/$G$447,0) -> 0.2234624 | F69: =IFERROR(AB56/$G$447,0) -> 0.25414442 | G69: =IFERROR(AC56/$G$447,0) -> 0.28482643 | H69: =IFERROR(AD56/$G$447,0) -> 0.31550844 | I69: =IFERROR(AE56/$G$447,0) -> 0.34619045 | J69: =IFERROR(AF56/$G$447,0) -> 0.37687246 | K69: =IFERROR(AG56/$G$447,0) -> 0.40755448 | L69: =IFERROR(AH56/$G$447,0) -> 0.43823649 | AT69: =IF(Z56<$G$449,0,MIN($G$446,1+IFERROR(INT((Z56-$G$449)/$G$451),0))) -> 2 | AU69: =IF(AA56<$G$449,0,MIN($G$446,1+IFERROR(INT((AA56-$G$449)/$G$451),0))) -> 3 | AV69: =IF(AB56<$G$449,0,MIN($G$446,1+IFERROR(INT((AB56-$G$449)/$G$451),0))) -> 4 | AW69: =IF(AC56<$G$449,0,MIN($G$446,1+IFERROR(INT((AC56-$G$449)/$G$451),0))) -> 5 | AX69: =IF(AD56<$G$449,0,MIN($G$446,1+IFERROR(INT((AD56-$G$449)/$G$451),0))) -> 6 | AY69: =IF(AE56<$G$449,0,MIN($G$446,1+IFERROR(INT((AE56-$G$449)/$G$451),0))) -> 7 | AZ69: =IF(AF56<$G$449,0,MIN($G$446,1+IFERROR(INT((AF56-$G$449)/$G$451),0))) -> 8 | BA69: =IF(AG56<$G$449,0,MIN($G$446,1+IFERROR(INT((AG56-$G$449)/$G$451),0))) -> 9 | BB69: =IF(AH56<$G$449,0,MIN($G$446,1+IFERROR(INT((AH56-$G$449)/$G$451),0))) -> 10
B70: Ben's Year 5 partnership value ÷ standalone Year 5 value (G447), less 1
B72: Ben's IRR Premium vs. Standalone Based on Topkey Growth & Rollover %
D74: Topkey ex-Keystone Value Growth (%)
D75: =E75-$G$441 -> 0.013171226 | E75: =F75-$G$441 -> 0.26317123 | F75: =G75-$G$441 -> 0.51317123 | G75: =H75-$G$441 -> 0.76317123 | H75: =$G$440 -> 1.0131712 | I75: =H75+$G$441 -> 1.2631712 | J75: =I75+$G$441 -> 1.5131712 | K75: =J75+$G$441 -> 1.7631712 | L75: =K75+$G$441 -> 2.0131712 | AT75: Helper: Gradient Band (0 = below $1M hurdle)
B76: Ben's Rollover % | C76: =C77-$G$439 -> 0.15 | D76: =D36-$G$448 -> -0.0566668 | E76: =E36-$G$448 -> -0.036109376 | F76: =F36-$G$448 -> -0.016908545 | G76: =G36-$G$448 -> 0.0011218766 | H76: =H36-$G$448 -> 0.018131121 | I76: =I36-$G$448 -> 0.03424077 | J76: =J36-$G$448 -> 0.049551273 | K76: =K36-$G$448 -> 0.064146648 | L76: =L36-$G$448 -> 0.078097927 | AT76: =IF(Z50<$G$449,0,MIN($G$446,1+IFERROR(INT((Z50-$G$449)/$G$451),0))) -> 0 | AU76: =IF(AA50<$G$449,0,MIN($G$446,1+IFERROR(INT((AA50-$G$449)/$G$451),0))) -> 0 | AV76: =IF(AB50<$G$449,0,MIN($G$446,1+IFERROR(INT((AB50-$G$449)/$G$451),0))) -> 0 | AW76: =IF(AC50<$G$449,0,MIN($G$446,1+IFERROR(INT((AC50-$G$449)/$G$451),0))) -> 0 | AX76: =IF(AD50<$G$449,0,MIN($G$446,1+IFERROR(INT((AD50-$G$449)/$G$451),0))) -> 0 | AY76: =IF(AE50<$G$449,0,MIN($G$446,1+IFERROR(INT((AE50-$G$449)/$G$451),0))) -> 0 | AZ76: =IF(AF50<$G$449,0,MIN($G$446,1+IFERROR(INT((AF50-$G$449)/$G$451),0))) -> 0 | BA76: =IF(AG50<$G$449,0,MIN($G$446,1+IFERROR(INT((AG50-$G$449)/$G$451),0))) -> 0 | BB76: =IF(AH50<$G$449,0,MIN($G$446,1+IFERROR(INT((AH50-$G$449)/$G$451),0))) -> 1
C77: =C78-$G$439 -> 0.2 | D77: =D37-$G$448 -> -0.028108337 | E77: =E37-$G$448 -> -0.010791773 | F77: =F37-$G$448 -> 0.0055718531 | G77: =G37-$G$448 -> 0.021092985 | H77: =H37-$G$448 -> 0.035863353 | I77: =I37-$G$448 -> 0.04996003 | J77: =J37-$G$448 -> 0.063448444 | K77: =K37-$G$448 -> 0.076384642 | L77: =L37-$G$448 -> 0.088817026 | AT77: =IF(Z51<$G$449,0,MIN($G$446,1+IFERROR(INT((Z51-$G$449)/$G$451),0))) -> 0 | AU77: =IF(AA51<$G$449,0,MIN($G$446,1+IFERROR(INT((AA51-$G$449)/$G$451),0))) -> 0 | AV77: =IF(AB51<$G$449,0,MIN($G$446,1+IFERROR(INT((AB51-$G$449)/$G$451),0))) -> 0 | AW77: =IF(AC51<$G$449,0,MIN($G$446,1+IFERROR(INT((AC51-$G$449)/$G$451),0))) -> 0 | AX77: =IF(AD51<$G$449,0,MIN($G$446,1+IFERROR(INT((AD51-$G$449)/$G$451),0))) -> 0 | AY77: =IF(AE51<$G$449,0,MIN($G$446,1+IFERROR(INT((AE51-$G$449)/$G$451),0))) -> 0 | AZ77: =IF(AF51<$G$449,0,MIN($G$446,1+IFERROR(INT((AF51-$G$449)/$G$451),0))) -> 0 | BA77: =IF(AG51<$G$449,0,MIN($G$446,1+IFERROR(INT((AG51-$G$449)/$G$451),0))) -> 1 | BB77: =IF(AH51<$G$449,0,MIN($G$446,1+IFERROR(INT((AH51-$G$449)/$G$451),0))) -> 3
C78: =C79-$G$439 -> 0.25 | D78: =D38-$G$448 -> -0.0019527117 | E78: =E38-$G$448 -> 0.012659749 | F78: =F38-$G$448 -> 0.026600488 | G78: =G38-$G$448 -> 0.039935225 | H78: =H38-$G$448 -> 0.052720192 | I78: =I38-$G$448 -> 0.0650039 | J78: =J38-$G$448 -> 0.076828512 | K78: =K38-$G$448 -> 0.088230918 | L78: =L38-$G$448 -> 0.099243594 | AT78: =IF(Z52<$G$449,0,MIN($G$446,1+IFERROR(INT((Z52-$G$449)/$G$451),0))) -> 0 | AU78: =IF(AA52<$G$449,0,MIN($G$446,1+IFERROR(INT((AA52-$G$449)/$G$451),0))) -> 0 | AV78: =IF(AB52<$G$449,0,MIN($G$446,1+IFERROR(INT((AB52-$G$449)/$G$451),0))) -> 0 | AW78: =IF(AC52<$G$449,0,MIN($G$446,1+IFERROR(INT((AC52-$G$449)/$G$451),0))) -> 0 | AX78: =IF(AD52<$G$449,0,MIN($G$446,1+IFERROR(INT((AD52-$G$449)/$G$451),0))) -> 0 | AY78: =IF(AE52<$G$449,0,MIN($G$446,1+IFERROR(INT((AE52-$G$449)/$G$451),0))) -> 0 | AZ78: =IF(AF52<$G$449,0,MIN($G$446,1+IFERROR(INT((AF52-$G$449)/$G$451),0))) -> 1 | BA78: =IF(AG52<$G$449,0,MIN($G$446,1+IFERROR(INT((AG52-$G$449)/$G$451),0))) -> 3 | BB78: =IF(AH52<$G$449,0,MIN($G$446,1+IFERROR(INT((AH52-$G$449)/$G$451),0))) -> 4
C79: =$G$438 -> 0.3 | D79: =D39-$G$448 -> 0.022227405 | E79: =E39-$G$448 -> 0.034541104 | F79: =F39-$G$448 -> 0.046382558 | G79: =G39-$G$448 -> 0.057790663 | H79: =H39-$G$448 -> 0.068799546 | I79: =I39-$G$448 -> 0.079439329 | J79: =J39-$G$448 -> 0.08973674 | K79: =K39-$G$448 -> 0.099715613 | L79: =L39-$G$448 -> 0.1093973 | AT79: =IF(Z53<$G$449,0,MIN($G$446,1+IFERROR(INT((Z53-$G$449)/$G$451),0))) -> 0 | AU79: =IF(AA53<$G$449,0,MIN($G$446,1+IFERROR(INT((AA53-$G$449)/$G$451),0))) -> 0 | AV79: =IF(AB53<$G$449,0,MIN($G$446,1+IFERROR(INT((AB53-$G$449)/$G$451),0))) -> 0 | AW79: =IF(AC53<$G$449,0,MIN($G$446,1+IFERROR(INT((AC53-$G$449)/$G$451),0))) -> 0 | AX79: =IF(AD53<$G$449,0,MIN($G$446,1+IFERROR(INT((AD53-$G$449)/$G$451),0))) -> 0 | AY79: =IF(AE53<$G$449,0,MIN($G$446,1+IFERROR(INT((AE53-$G$449)/$G$451),0))) -> 2 | AZ79: =IF(AF53<$G$449,0,MIN($G$446,1+IFERROR(INT((AF53-$G$449)/$G$451),0))) -> 3 | BA79: =IF(AG53<$G$449,0,MIN($G$446,1+IFERROR(INT((AG53-$G$449)/$G$451),0))) -> 4 | BB79: =IF(AH53<$G$449,0,MIN($G$446,1+IFERROR(INT((AH53-$G$449)/$G$451),0))) -> 6
C80: =C79+$G$439 -> 0.35 | D80: =D40-$G$448 -> 0.044752078 | E80: =E40-$G$448 -> 0.055081387 | F80: =F40-$G$448 -> 0.065081646 | G80: =G40-$G$448 -> 0.074775542 | H80: =H40-$G$448 -> 0.084183415 | I80: =I40-$G$448 -> 0.09332358 | J80: =J40-$G$448 -> 0.10221259 | K80: =K40-$G$448 -> 0.11086546 | L80: =L40-$G$448 -> 0.11929586 | AT80: =IF(Z54<$G$449,0,MIN($G$446,1+IFERROR(INT((Z54-$G$449)/$G$451),0))) -> 0 | AU80: =IF(AA54<$G$449,0,MIN($G$446,1+IFERROR(INT((AA54-$G$449)/$G$451),0))) -> 0 | AV80: =IF(AB54<$G$449,0,MIN($G$446,1+IFERROR(INT((AB54-$G$449)/$G$451),0))) -> 0 | AW80: =IF(AC54<$G$449,0,MIN($G$446,1+IFERROR(INT((AC54-$G$449)/$G$451),0))) -> 1 | AX80: =IF(AD54<$G$449,0,MIN($G$446,1+IFERROR(INT((AD54-$G$449)/$G$451),0))) -> 2 | AY80: =IF(AE54<$G$449,0,MIN($G$446,1+IFERROR(INT((AE54-$G$449)/$G$451),0))) -> 4 | AZ80: =IF(AF54<$G$449,0,MIN($G$446,1+IFERROR(INT((AF54-$G$449)/$G$451),0))) -> 5 | BA80: =IF(AG54<$G$449,0,MIN($G$446,1+IFERROR(INT((AG54-$G$449)/$G$451),0))) -> 6 | BB80: =IF(AH54<$G$449,0,MIN($G$446,1+IFERROR(INT((AH54-$G$449)/$G$451),0))) -> 7
C81: =C80+$G$439 -> 0.4 | D81: =D41-$G$448 -> 0.065867647 | E81: =E41-$G$448 -> 0.074461828 | F81: =F41-$G$448 -> 0.082830397 | G81: =G41-$G$448 -> 0.090986259 | H81: =H41-$G$448 -> 0.098941206 | I81: =I41-$G$448 -> 0.10670604 | J81: =J41-$G$448 -> 0.11429069 | K81: =K41-$G$448 -> 0.1217043 | L81: =L41-$G$448 -> 0.12895531 | AT81: =IF(Z55<$G$449,0,MIN($G$446,1+IFERROR(INT((Z55-$G$449)/$G$451),0))) -> 0 | AU81: =IF(AA55<$G$449,0,MIN($G$446,1+IFERROR(INT((AA55-$G$449)/$G$451),0))) -> 1 | AV81: =IF(AB55<$G$449,0,MIN($G$446,1+IFERROR(INT((AB55-$G$449)/$G$451),0))) -> 2 | AW81: =IF(AC55<$G$449,0,MIN($G$446,1+IFERROR(INT((AC55-$G$449)/$G$451),0))) -> 3 | AX81: =IF(AD55<$G$449,0,MIN($G$446,1+IFERROR(INT((AD55-$G$449)/$G$451),0))) -> 4 | AY81: =IF(AE55<$G$449,0,MIN($G$446,1+IFERROR(INT((AE55-$G$449)/$G$451),0))) -> 5 | AZ81: =IF(AF55<$G$449,0,MIN($G$446,1+IFERROR(INT((AF55-$G$449)/$G$451),0))) -> 7 | BA81: =IF(AG55<$G$449,0,MIN($G$446,1+IFERROR(INT((AG55-$G$449)/$G$451),0))) -> 8 | BB81: =IF(AH55<$G$449,0,MIN($G$446,1+IFERROR(INT((AH55-$G$449)/$G$451),0))) -> 9
C82: =C81+$G$439 -> 0.45 | D82: =D42-$G$448 -> 0.085768033 | E82: =E42-$G$448 -> 0.092828423 | F82: =F42-$G$448 -> 0.099737958 | G82: =G42-$G$448 -> 0.1065037 | H82: =H42-$G$448 -> 0.11313222 | I82: =I42-$G$448 -> 0.11962962 | J82: =J42-$G$448 -> 0.1260016 | K82: =K42-$G$448 -> 0.13225347 | L82: =L42-$G$448 -> 0.13839021 | AT82: =IF(Z56<$G$449,0,MIN($G$446,1+IFERROR(INT((Z56-$G$449)/$G$451),0))) -> 2 | AU82: =IF(AA56<$G$449,0,MIN($G$446,1+IFERROR(INT((AA56-$G$449)/$G$451),0))) -> 3 | AV82: =IF(AB56<$G$449,0,MIN($G$446,1+IFERROR(INT((AB56-$G$449)/$G$451),0))) -> 4 | AW82: =IF(AC56<$G$449,0,MIN($G$446,1+IFERROR(INT((AC56-$G$449)/$G$451),0))) -> 5 | AX82: =IF(AD56<$G$449,0,MIN($G$446,1+IFERROR(INT((AD56-$G$449)/$G$451),0))) -> 6 | AY82: =IF(AE56<$G$449,0,MIN($G$446,1+IFERROR(INT((AE56-$G$449)/$G$451),0))) -> 7 | AZ82: =IF(AF56<$G$449,0,MIN($G$446,1+IFERROR(INT((AF56-$G$449)/$G$451),0))) -> 8 | BA82: =IF(AG56<$G$449,0,MIN($G$446,1+IFERROR(INT((AG56-$G$449)/$G$451),0))) -> 9 | BB82: =IF(AH56<$G$449,0,MIN($G$446,1+IFERROR(INT((AH56-$G$449)/$G$451),0))) -> 10
B83: Partnership IRR (table above) less standalone IRR (G448), in percentage points
B85: Ben's Return Profile Based on Partnering — Net Client Wins
B86: Ben's Net Returns Based on Net Client Wins & Rollover %
D88: Keystone Total Annual Net Client Wins — Partnership (#) | Z88: Helper: Unrounded Net Return — Net Client Wins | AJ88: Helper: Keystone EV Yr 5 by Net Client Wins
D89: =E89+$G$458 -> 76 | E89: =F89+$G$458 -> 72 | F89: =G89+$G$458 -> 68 | G89: =H89+$G$458 -> 64 | H89: =$G$457 -> 60 | I89: =H89-$G$458 -> 56 | J89: =I89-$G$458 -> 52 | K89: =J89-$G$458 -> 48 | L89: =K89-$G$458 -> 44 | N89: Helper: Rollover % | O89: Helper: Cash at Close | P89: Helper: Topkey Equity Issued | Q89: Helper: Topkey ex-Keystone Today | R89: Helper: Ben's Yr 5 Topkey % | Z89: =D$89 -> 76 | AA89: =E$89 -> 72 | AB89: =F$89 -> 68 | AC89: =G$89 -> 64 | AD89: =H$89 -> 60 | AE89: =I$89 -> 56 | AF89: =J$89 -> 52 | AG89: =K$89 -> 48 | AH89: =L$89 -> 44 | AJ89: =D$89 -> 76 | AK89: =E$89 -> 72 | AL89: =F$89 -> 68 | AM89: =G$89 -> 64 | AN89: =H$89 -> 60 | AO89: =I$89 -> 56 | AP89: =J$89 -> 52 | AQ89: =K$89 -> 48 | AR89: =L$89 -> 44 | AT89: Helper: Gradient Band (0 = below $1M hurdle)
B90: Ben's Rollover % | C90: =C91-$G$439 -> 0.15 | D90: =ROUND(Z90,$G$452) -> 4500 | E90: =ROUND(AA90,$G$452) -> 4300 | F90: =ROUND(AB90,$G$452) -> 4200 | G90: =ROUND(AC90,$G$452) -> 4100 | H90: =ROUND(AD90,$G$452) -> 4000 | I90: =ROUND(AE90,$G$452) -> 3900 | J90: =ROUND(AF90,$G$452) -> 3700 | K90: =ROUND(AG90,$G$452) -> 3600 | L90: =ROUND(AH90,$G$452) -> 3500 | N90: =$C90 -> 0.15 | O90: =$G$433 -> 650 | P90: =$G$430*(1-N90)-O90 -> 1900 | Q90: =$G$432-O90 -> 49350 | R90: =IFERROR(P90/(Q90+$G$430*(1-N90)),0)*(1-$G$434) -> 0.03477842 | Z90: =$O90+$G$435+$N90*AJ$90+$R90*($Q90*(1+$G$437)+AJ$90*(1-$N90))-$G$430 -> 4451.7269 | AA90: =$O90+$G$435+$N90*AK$90+$R90*($Q90*(1+$G$437)+AK$90*(1-$N90))-$G$430 -> 4332.2719 | AB90: =$O90+$G$435+$N90*AL$90+$R90*($Q90*(1+$G$437)+AL$90*(1-$N90))-$G$430 -> 4212.8169 | AC90: =$O90+$G$435+$N90*AM$90+$R90*($Q90*(1+$G$437)+AM$90*(1-$N90))-$G$430 -> 4093.3619 | AD90: =$O90+$G$435+$N90*AN$90+$R90*($Q90*(1+$G$437)+AN$90*(1-$N90))-$G$430 -> 3973.9069 | AE90: =$O90+$G$435+$N90*AO$90+$R90*($Q90*(1+$G$437)+AO$90*(1-$N90))-$G$430 -> 3854.4519 | AF90: =$O90+$G$435+$N90*AP$90+$R90*($Q90*(1+$G$437)+AP$90*(1-$N90))-$G$430 -> 3734.9969 | AG90: =$O90+$G$435+$N90*AQ$90+$R90*($Q90*(1+$G$437)+AQ$90*(1-$N90))-$G$430 -> 3615.5419 | AH90: =$O90+$G$435+$N90*AR$90+$R90*($Q90*(1+$G$437)+AR$90*(1-$N90))-$G$430 -> 3496.087 | AJ90: =($G$453+AJ$89*$G$445*$G$454)*$G$455 -> 18637.002 | AK90: =($G$453+AK$89*$G$445*$G$454)*$G$455 -> 17971.743 | AL90: =($G$453+AL$89*$G$445*$G$454)*$G$455 -> 17306.484 | AM90: =($G$453+AM$89*$G$445*$G$454)*$G$455 -> 16641.225 | AN90: =($G$453+AN$89*$G$445*$G$454)*$G$455 -> 15975.966 | AO90: =($G$453+AO$89*$G$445*$G$454)*$G$455 -> 15310.707 | AP90: =($G$453+AP$89*$G$445*$G$454)*$G$455 -> 14645.448 | AQ90: =($G$453+AQ$89*$G$445*$G$454)*$G$455 -> 13980.189 | AR90: =($G$453+AR$89*$G$445*$G$454)*$G$455 -> 13314.93 | AT90: =IF(Z130<$G$449,0,MIN($G$446,1+IFERROR(INT((Z130-$G$449)/$G$463),0))) -> 0 | AU90: =IF(AA130<$G$449,0,MIN($G$446,1+IFERROR(INT((AA130-$G$449)/$G$463),0))) -> 0 | AV90: =IF(AB130<$G$449,0,MIN($G$446,1+IFERROR(INT((AB130-$G$449)/$G$463),0))) -> 0 | AW90: =IF(AC130<$G$449,0,MIN($G$446,1+IFERROR(INT((AC130-$G$449)/$G$463),0))) -> 0 | AX90: =IF(AD130<$G$449,0,MIN($G$446,1+IFERROR(INT((AD130-$G$449)/$G$463),0))) -> 0 | AY90: =IF(AE130<$G$449,0,MIN($G$446,1+IFERROR(INT((AE130-$G$449)/$G$463),0))) -> 0 | AZ90: =IF(AF130<$G$449,0,MIN($G$446,1+IFERROR(INT((AF130-$G$449)/$G$463),0))) -> 0 | BA90: =IF(AG130<$G$449,0,MIN($G$446,1+IFERROR(INT((AG130-$G$449)/$G$463),0))) -> 0 | BB90: =IF(AH130<$G$449,0,MIN($G$446,1+IFERROR(INT((AH130-$G$449)/$G$463),0))) -> 0
C91: =C92-$G$439 -> 0.2 | D91: =ROUND(Z91,$G$452) -> 5000 | E91: =ROUND(AA91,$G$452) -> 4900 | F91: =ROUND(AB91,$G$452) -> 4700 | G91: =ROUND(AC91,$G$452) -> 4600 | H91: =ROUND(AD91,$G$452) -> 4400 | I91: =ROUND(AE91,$G$452) -> 4300 | J91: =ROUND(AF91,$G$452) -> 4100 | K91: =ROUND(AG91,$G$452) -> 4000 | L91: =ROUND(AH91,$G$452) -> 3800 | N91: =$C91 -> 0.2 | O91: =$G$433 -> 650 | P91: =$G$430*(1-N91)-O91 -> 1750 | Q91: =$G$432-O91 -> 49350 | R91: =IFERROR(P91/(Q91+$G$430*(1-N91)),0)*(1-$G$434) -> 0.032125604 | Z91: =$O91+$G$435+$N91*AJ$90+$R91*($Q91*(1+$G$437)+AJ$90*(1-$N91))-$G$430 -> 5048.059 | AA91: =$O91+$G$435+$N91*AK$90+$R91*($Q91*(1+$G$437)+AK$90*(1-$N91))-$G$430 -> 4897.9097 | AB91: =$O91+$G$435+$N91*AL$90+$R91*($Q91*(1+$G$437)+AL$90*(1-$N91))-$G$430 -> 4747.7605 | AC91: =$O91+$G$435+$N91*AM$90+$R91*($Q91*(1+$G$437)+AM$90*(1-$N91))-$G$430 -> 4597.6112 | AD91: =$O91+$G$435+$N91*AN$90+$R91*($Q91*(1+$G$437)+AN$90*(1-$N91))-$G$430 -> 4447.462 | AE91: =$O91+$G$435+$N91*AO$90+$R91*($Q91*(1+$G$437)+AO$90*(1-$N91))-$G$430 -> 4297.3127 | AF91: =$O91+$G$435+$N91*AP$90+$R91*($Q91*(1+$G$437)+AP$90*(1-$N91))-$G$430 -> 4147.1634 | AG91: =$O91+$G$435+$N91*AQ$90+$R91*($Q91*(1+$G$437)+AQ$90*(1-$N91))-$G$430 -> 3997.0142 | AH91: =$O91+$G$435+$N91*AR$90+$R91*($Q91*(1+$G$437)+AR$90*(1-$N91))-$G$430 -> 3846.8649 | AT91: =IF(Z131<$G$449,0,MIN($G$446,1+IFERROR(INT((Z131-$G$449)/$G$463),0))) -> 0 | AU91: =IF(AA131<$G$449,0,MIN($G$446,1+IFERROR(INT((AA131-$G$449)/$G$463),0))) -> 0 | AV91: =IF(AB131<$G$449,0,MIN($G$446,1+IFERROR(INT((AB131-$G$449)/$G$463),0))) -> 0 | AW91: =IF(AC131<$G$449,0,MIN($G$446,1+IFERROR(INT((AC131-$G$449)/$G$463),0))) -> 0 | AX91: =IF(AD131<$G$449,0,MIN($G$446,1+IFERROR(INT((AD131-$G$449)/$G$463),0))) -> 0 | AY91: =IF(AE131<$G$449,0,MIN($G$446,1+IFERROR(INT((AE131-$G$449)/$G$463),0))) -> 0 | AZ91: =IF(AF131<$G$449,0,MIN($G$446,1+IFERROR(INT((AF131-$G$449)/$G$463),0))) -> 0 | BA91: =IF(AG131<$G$449,0,MIN($G$446,1+IFERROR(INT((AG131-$G$449)/$G$463),0))) -> 0 | BB91: =IF(AH131<$G$449,0,MIN($G$446,1+IFERROR(INT((AH131-$G$449)/$G$463),0))) -> 1
C92: =C93-$G$439 -> 0.25 | D92: =ROUND(Z92,$G$452) -> 5600 | E92: =ROUND(AA92,$G$452) -> 5500 | F92: =ROUND(AB92,$G$452) -> 5300 | G92: =ROUND(AC92,$G$452) -> 5100 | H92: =ROUND(AD92,$G$452) -> 4900 | I92: =ROUND(AE92,$G$452) -> 4700 | J92: =ROUND(AF92,$G$452) -> 4600 | K92: =ROUND(AG92,$G$452) -> 4400 | L92: =ROUND(AH92,$G$452) -> 4200 | N92: =$C92 -> 0.25 | O92: =$G$433 -> 650 | P92: =$G$430*(1-N92)-O92 -> 1600 | Q92: =$G$432-O92 -> 49350 | R92: =IFERROR(P92/(Q92+$G$430*(1-N92)),0)*(1-$G$434) -> 0.029457364 | Z92: =$O92+$G$435+$N92*AJ$90+$R92*($Q92*(1+$G$437)+AJ$90*(1-$N92))-$G$430 -> 5647.5872 | AA92: =$O92+$G$435+$N92*AK$90+$R92*($Q92*(1+$G$437)+AK$90*(1-$N92))-$G$430 -> 5466.5749 | AB92: =$O92+$G$435+$N92*AL$90+$R92*($Q92*(1+$G$437)+AL$90*(1-$N92))-$G$430 -> 5285.5626 | AC92: =$O92+$G$435+$N92*AM$90+$R92*($Q92*(1+$G$437)+AM$90*(1-$N92))-$G$430 -> 5104.5503 | AD92: =$O92+$G$435+$N92*AN$90+$R92*($Q92*(1+$G$437)+AN$90*(1-$N92))-$G$430 -> 4923.538 | AE92: =$O92+$G$435+$N92*AO$90+$R92*($Q92*(1+$G$437)+AO$90*(1-$N92))-$G$430 -> 4742.5257 | AF92: =$O92+$G$435+$N92*AP$90+$R92*($Q92*(1+$G$437)+AP$90*(1-$N92))-$G$430 -> 4561.5134 | AG92: =$O92+$G$435+$N92*AQ$90+$R92*($Q92*(1+$G$437)+AQ$90*(1-$N92))-$G$430 -> 4380.5011 | AH92: =$O92+$G$435+$N92*AR$90+$R92*($Q92*(1+$G$437)+AR$90*(1-$N92))-$G$430 -> 4199.4887 | AJ92: Helper: Standalone Yr 5 Value by Net Client Wins | AT92: =IF(Z132<$G$449,0,MIN($G$446,1+IFERROR(INT((Z132-$G$449)/$G$463),0))) -> 0 | AU92: =IF(AA132<$G$449,0,MIN($G$446,1+IFERROR(INT((AA132-$G$449)/$G$463),0))) -> 0 | AV92: =IF(AB132<$G$449,0,MIN($G$446,1+IFERROR(INT((AB132-$G$449)/$G$463),0))) -> 0 | AW92: =IF(AC132<$G$449,0,MIN($G$446,1+IFERROR(INT((AC132-$G$449)/$G$463),0))) -> 0 | AX92: =IF(AD132<$G$449,0,MIN($G$446,1+IFERROR(INT((AD132-$G$449)/$G$463),0))) -> 0 | AY92: =IF(AE132<$G$449,0,MIN($G$446,1+IFERROR(INT((AE132-$G$449)/$G$463),0))) -> 0 | AZ92: =IF(AF132<$G$449,0,MIN($G$446,1+IFERROR(INT((AF132-$G$449)/$G$463),0))) -> 0 | BA92: =IF(AG132<$G$449,0,MIN($G$446,1+IFERROR(INT((AG132-$G$449)/$G$463),0))) -> 1 | BB92: =IF(AH132<$G$449,0,MIN($G$446,1+IFERROR(INT((AH132-$G$449)/$G$463),0))) -> 3
C93: =$G$438 -> 0.3 | D93: =ROUND(Z93,$G$452) -> 6300 | E93: =ROUND(AA93,$G$452) -> 6000 | F93: =ROUND(AB93,$G$452) -> 5800 | G93: =ROUND(AC93,$G$452) -> 5600 | H93: =ROUND(AD93,$G$452) -> 5400 | I93: =ROUND(AE93,$G$452) -> 5200 | J93: =ROUND(AF93,$G$452) -> 5000 | K93: =ROUND(AG93,$G$452) -> 4800 | L93: =ROUND(AH93,$G$452) -> 4600 | N93: =$C93 -> 0.3 | O93: =$G$433 -> 650 | P93: =$G$430*(1-N93)-O93 -> 1450 | Q93: =$G$432-O93 -> 49350 | R93: =IFERROR(P93/(Q93+$G$430*(1-N93)),0)*(1-$G$434) -> 0.026773567 | Z93: =$O93+$G$435+$N93*AJ$90+$R93*($Q93*(1+$G$437)+AJ$90*(1-$N93))-$G$430 -> 6250.3396 | AA93: =$O93+$G$435+$N93*AK$90+$R93*($Q93*(1+$G$437)+AK$90*(1-$N93))-$G$430 -> 6038.294 | AB93: =$O93+$G$435+$N93*AL$90+$R93*($Q93*(1+$G$437)+AL$90*(1-$N93))-$G$430 -> 5826.2483 | AC93: =$O93+$G$435+$N93*AM$90+$R93*($Q93*(1+$G$437)+AM$90*(1-$N93))-$G$430 -> 5614.2027 | AD93: =$O93+$G$435+$N93*AN$90+$R93*($Q93*(1+$G$437)+AN$90*(1-$N93))-$G$430 -> 5402.1571 | AE93: =$O93+$G$435+$N93*AO$90+$R93*($Q93*(1+$G$437)+AO$90*(1-$N93))-$G$430 -> 5190.1115 | AF93: =$O93+$G$435+$N93*AP$90+$R93*($Q93*(1+$G$437)+AP$90*(1-$N93))-$G$430 -> 4978.0659 | AG93: =$O93+$G$435+$N93*AQ$90+$R93*($Q93*(1+$G$437)+AQ$90*(1-$N93))-$G$430 -> 4766.0202 | AH93: =$O93+$G$435+$N93*AR$90+$R93*($Q93*(1+$G$437)+AR$90*(1-$N93))-$G$430 -> 4553.9746 | AJ93: =($G$453+(AJ$89-$G$459)*$G$445*$G$460)*$G$461*$G$462 -> 9153.405 | AK93: =($G$453+(AK$89-$G$459)*$G$445*$G$460)*$G$461*$G$462 -> 8737.6182 | AL93: =($G$453+(AL$89-$G$459)*$G$445*$G$460)*$G$461*$G$462 -> 8321.8313 | AM93: =($G$453+(AM$89-$G$459)*$G$445*$G$460)*$G$461*$G$462 -> 7906.0445 | AN93: =($G$453+(AN$89-$G$459)*$G$445*$G$460)*$G$461*$G$462 -> 7490.2577 | AO93: =($G$453+(AO$89-$G$459)*$G$445*$G$460)*$G$461*$G$462 -> 7074.4709 | AP93: =($G$453+(AP$89-$G$459)*$G$445*$G$460)*$G$461*$G$462 -> 6658.684 | AQ93: =($G$453+(AQ$89-$G$459)*$G$445*$G$460)*$G$461*$G$462 -> 6242.8972 | AR93: =($G$453+(AR$89-$G$459)*$G$445*$G$460)*$G$461*$G$462 -> 5827.1104 | AT93: =IF(Z133<$G$449,0,MIN($G$446,1+IFERROR(INT((Z133-$G$449)/$G$463),0))) -> 0 | AU93: =IF(AA133<$G$449,0,MIN($G$446,1+IFERROR(INT((AA133-$G$449)/$G$463),0))) -> 0 | AV93: =IF(AB133<$G$449,0,MIN($G$446,1+IFERROR(INT((AB133-$G$449)/$G$463),0))) -> 0 | AW93: =IF(AC133<$G$449,0,MIN($G$446,1+IFERROR(INT((AC133-$G$449)/$G$463),0))) -> 0 | AX93: =IF(AD133<$G$449,0,MIN($G$446,1+IFERROR(INT((AD133-$G$449)/$G$463),0))) -> 0 | AY93: =IF(AE133<$G$449,0,MIN($G$446,1+IFERROR(INT((AE133-$G$449)/$G$463),0))) -> 1 | AZ93: =IF(AF133<$G$449,0,MIN($G$446,1+IFERROR(INT((AF133-$G$449)/$G$463),0))) -> 2 | BA93: =IF(AG133<$G$449,0,MIN($G$446,1+IFERROR(INT((AG133-$G$449)/$G$463),0))) -> 3 | BB93: =IF(AH133<$G$449,0,MIN($G$446,1+IFERROR(INT((AH133-$G$449)/$G$463),0))) -> 5
C94: =C93+$G$439 -> 0.35 | D94: =ROUND(Z94,$G$452) -> 6900 | E94: =ROUND(AA94,$G$452) -> 6600 | F94: =ROUND(AB94,$G$452) -> 6400 | G94: =ROUND(AC94,$G$452) -> 6100 | H94: =ROUND(AD94,$G$452) -> 5900 | I94: =ROUND(AE94,$G$452) -> 5600 | J94: =ROUND(AF94,$G$452) -> 5400 | K94: =ROUND(AG94,$G$452) -> 5200 | L94: =ROUND(AH94,$G$452) -> 4900 | N94: =$C94 -> 0.35 | O94: =$G$433 -> 650 | P94: =$G$430*(1-N94)-O94 -> 1300 | Q94: =$G$432-O94 -> 49350 | R94: =IFERROR(P94/(Q94+$G$430*(1-N94)),0)*(1-$G$434) -> 0.024074074 | Z94: =$O94+$G$435+$N94*AJ$90+$R94*($Q94*(1+$G$437)+AJ$90*(1-$N94))-$G$430 -> 6856.3444 | AA94: =$O94+$G$435+$N94*AK$90+$R94*($Q94*(1+$G$437)+AK$90*(1-$N94))-$G$430 -> 6613.0937 | AB94: =$O94+$G$435+$N94*AL$90+$R94*($Q94*(1+$G$437)+AL$90*(1-$N94))-$G$430 -> 6369.843 | AC94: =$O94+$G$435+$N94*AM$90+$R94*($Q94*(1+$G$437)+AM$90*(1-$N94))-$G$430 -> 6126.5923 | AD94: =$O94+$G$435+$N94*AN$90+$R94*($Q94*(1+$G$437)+AN$90*(1-$N94))-$G$430 -> 5883.3416 | AE94: =$O94+$G$435+$N94*AO$90+$R94*($Q94*(1+$G$437)+AO$90*(1-$N94))-$G$430 -> 5640.0909 | AF94: =$O94+$G$435+$N94*AP$90+$R94*($Q94*(1+$G$437)+AP$90*(1-$N94))-$G$430 -> 5396.8402 | AG94: =$O94+$G$435+$N94*AQ$90+$R94*($Q94*(1+$G$437)+AQ$90*(1-$N94))-$G$430 -> 5153.5895 | AH94: =$O94+$G$435+$N94*AR$90+$R94*($Q94*(1+$G$437)+AR$90*(1-$N94))-$G$430 -> 4910.3388 | AJ94: Helper: Standalone IRR by Net Client Wins | AT94: =IF(Z134<$G$449,0,MIN($G$446,1+IFERROR(INT((Z134-$G$449)/$G$463),0))) -> 0 | AU94: =IF(AA134<$G$449,0,MIN($G$446,1+IFERROR(INT((AA134-$G$449)/$G$463),0))) -> 0 | AV94: =IF(AB134<$G$449,0,MIN($G$446,1+IFERROR(INT((AB134-$G$449)/$G$463),0))) -> 1 | AW94: =IF(AC134<$G$449,0,MIN($G$446,1+IFERROR(INT((AC134-$G$449)/$G$463),0))) -> 2 | AX94: =IF(AD134<$G$449,0,MIN($G$446,1+IFERROR(INT((AD134-$G$449)/$G$463),0))) -> 3 | AY94: =IF(AE134<$G$449,0,MIN($G$446,1+IFERROR(INT((AE134-$G$449)/$G$463),0))) -> 4 | AZ94: =IF(AF134<$G$449,0,MIN($G$446,1+IFERROR(INT((AF134-$G$449)/$G$463),0))) -> 5 | BA94: =IF(AG134<$G$449,0,MIN($G$446,1+IFERROR(INT((AG134-$G$449)/$G$463),0))) -> 6 | BB94: =IF(AH134<$G$449,0,MIN($G$446,1+IFERROR(INT((AH134-$G$449)/$G$463),0))) -> 7
C95: =C94+$G$439 -> 0.4 | D95: =ROUND(Z95,$G$452) -> 7500 | E95: =ROUND(AA95,$G$452) -> 7200 | F95: =ROUND(AB95,$G$452) -> 6900 | G95: =ROUND(AC95,$G$452) -> 6600 | H95: =ROUND(AD95,$G$452) -> 6400 | I95: =ROUND(AE95,$G$452) -> 6100 | J95: =ROUND(AF95,$G$452) -> 5800 | K95: =ROUND(AG95,$G$452) -> 5500 | L95: =ROUND(AH95,$G$452) -> 5300 | N95: =$C95 -> 0.4 | O95: =$G$433 -> 650 | P95: =$G$430*(1-N95)-O95 -> 1150 | Q95: =$G$432-O95 -> 49350 | R95: =IFERROR(P95/(Q95+$G$430*(1-N95)),0)*(1-$G$434) -> 0.021358749 | Z95: =$O95+$G$435+$N95*AJ$90+$R95*($Q95*(1+$G$437)+AJ$90*(1-$N95))-$G$430 -> 7465.6301 | AA95: =$O95+$G$435+$N95*AK$90+$R95*($Q95*(1+$G$437)+AK$90*(1-$N95))-$G$430 -> 7191.0011 | AB95: =$O95+$G$435+$N95*AL$90+$R95*($Q95*(1+$G$437)+AL$90*(1-$N95))-$G$430 -> 6916.3721 | AC95: =$O95+$G$435+$N95*AM$90+$R95*($Q95*(1+$G$437)+AM$90*(1-$N95))-$G$430 -> 6641.743 | AD95: =$O95+$G$435+$N95*AN$90+$R95*($Q95*(1+$G$437)+AN$90*(1-$N95))-$G$430 -> 6367.114 | AE95: =$O95+$G$435+$N95*AO$90+$R95*($Q95*(1+$G$437)+AO$90*(1-$N95))-$G$430 -> 6092.485 | AF95: =$O95+$G$435+$N95*AP$90+$R95*($Q95*(1+$G$437)+AP$90*(1-$N95))-$G$430 -> 5817.856 | AG95: =$O95+$G$435+$N95*AQ$90+$R95*($Q95*(1+$G$437)+AQ$90*(1-$N95))-$G$430 -> 5543.2269 | AH95: =$O95+$G$435+$N95*AR$90+$R95*($Q95*(1+$G$437)+AR$90*(1-$N95))-$G$430 -> 5268.5979 | AJ95: =IFERROR((AJ$93/$G$430)^(1/$G$445)-1,0) -> 0.24994897 | AK95: =IFERROR((AK$93/$G$430)^(1/$G$445)-1,0) -> 0.23838123 | AL95: =IFERROR((AL$93/$G$430)^(1/$G$445)-1,0) -> 0.22636439 | AM95: =IFERROR((AM$93/$G$430)^(1/$G$445)-1,0) -> 0.2138572 | AN95: =IFERROR((AN$93/$G$430)^(1/$G$445)-1,0) -> 0.20081223 | AO95: =IFERROR((AO$93/$G$430)^(1/$G$445)-1,0) -> 0.18717445 | AP95: =IFERROR((AP$93/$G$430)^(1/$G$445)-1,0) -> 0.17287959 | AQ95: =IFERROR((AQ$93/$G$430)^(1/$G$445)-1,0) -> 0.15785183 | AR95: =IFERROR((AR$93/$G$430)^(1/$G$445)-1,0) -> 0.14200077 | AT95: =IF(Z135<$G$449,0,MIN($G$446,1+IFERROR(INT((Z135-$G$449)/$G$463),0))) -> 2 | AU95: =IF(AA135<$G$449,0,MIN($G$446,1+IFERROR(INT((AA135-$G$449)/$G$463),0))) -> 3 | AV95: =IF(AB135<$G$449,0,MIN($G$446,1+IFERROR(INT((AB135-$G$449)/$G$463),0))) -> 4 | AW95: =IF(AC135<$G$449,0,MIN($G$446,1+IFERROR(INT((AC135-$G$449)/$G$463),0))) -> 5 | AX95: =IF(AD135<$G$449,0,MIN($G$446,1+IFERROR(INT((AD135-$G$449)/$G$463),0))) -> 5 | AY95: =IF(AE135<$G$449,0,MIN($G$446,1+IFERROR(INT((AE135-$G$449)/$G$463),0))) -> 6 | AZ95: =IF(AF135<$G$449,0,MIN($G$446,1+IFERROR(INT((AF135-$G$449)/$G$463),0))) -> 7 | BA95: =IF(AG135<$G$449,0,MIN($G$446,1+IFERROR(INT((AG135-$G$449)/$G$463),0))) -> 8 | BB95: =IF(AH135<$G$449,0,MIN($G$446,1+IFERROR(INT((AH135-$G$449)/$G$463),0))) -> 9
C96: =C95+$G$439 -> 0.45 | D96: =ROUND(Z96,$G$452) -> 8100 | E96: =ROUND(AA96,$G$452) -> 7800 | F96: =ROUND(AB96,$G$452) -> 7500 | G96: =ROUND(AC96,$G$452) -> 7200 | H96: =ROUND(AD96,$G$452) -> 6900 | I96: =ROUND(AE96,$G$452) -> 6500 | J96: =ROUND(AF96,$G$452) -> 6200 | K96: =ROUND(AG96,$G$452) -> 5900 | L96: =ROUND(AH96,$G$452) -> 5600 | N96: =$C96 -> 0.45 | O96: =$G$433 -> 650 | P96: =$G$430*(1-N96)-O96 -> 1000 | Q96: =$G$432-O96 -> 49350 | R96: =IFERROR(P96/(Q96+$G$430*(1-N96)),0)*(1-$G$434) -> 0.018627451 | Z96: =$O96+$G$435+$N96*AJ$90+$R96*($Q96*(1+$G$437)+AJ$90*(1-$N96))-$G$430 -> 8078.2258 | AA96: =$O96+$G$435+$N96*AK$90+$R96*($Q96*(1+$G$437)+AK$90*(1-$N96))-$G$430 -> 7772.0437 | AB96: =$O96+$G$435+$N96*AL$90+$R96*($Q96*(1+$G$437)+AL$90*(1-$N96))-$G$430 -> 7465.8615 | AC96: =$O96+$G$435+$N96*AM$90+$R96*($Q96*(1+$G$437)+AM$90*(1-$N96))-$G$430 -> 7159.6794 | AD96: =$O96+$G$435+$N96*AN$90+$R96*($Q96*(1+$G$437)+AN$90*(1-$N96))-$G$430 -> 6853.4972 | AE96: =$O96+$G$435+$N96*AO$90+$R96*($Q96*(1+$G$437)+AO$90*(1-$N96))-$G$430 -> 6547.3151 | AF96: =$O96+$G$435+$N96*AP$90+$R96*($Q96*(1+$G$437)+AP$90*(1-$N96))-$G$430 -> 6241.1329 | AG96: =$O96+$G$435+$N96*AQ$90+$R96*($Q96*(1+$G$437)+AQ$90*(1-$N96))-$G$430 -> 5934.9507 | AH96: =$O96+$G$435+$N96*AR$90+$R96*($Q96*(1+$G$437)+AR$90*(1-$N96))-$G$430 -> 5628.7686 | AT96: =IF(Z136<$G$449,0,MIN($G$446,1+IFERROR(INT((Z136-$G$449)/$G$463),0))) -> 6 | AU96: =IF(AA136<$G$449,0,MIN($G$446,1+IFERROR(INT((AA136-$G$449)/$G$463),0))) -> 6 | AV96: =IF(AB136<$G$449,0,MIN($G$446,1+IFERROR(INT((AB136-$G$449)/$G$463),0))) -> 7 | AW96: =IF(AC136<$G$449,0,MIN($G$446,1+IFERROR(INT((AC136-$G$449)/$G$463),0))) -> 7 | AX96: =IF(AD136<$G$449,0,MIN($G$446,1+IFERROR(INT((AD136-$G$449)/$G$463),0))) -> 8 | AY96: =IF(AE136<$G$449,0,MIN($G$446,1+IFERROR(INT((AE136-$G$449)/$G$463),0))) -> 9 | AZ96: =IF(AF136<$G$449,0,MIN($G$446,1+IFERROR(INT((AF136-$G$449)/$G$463),0))) -> 9 | BA96: =IF(AG136<$G$449,0,MIN($G$446,1+IFERROR(INT((AG136-$G$449)/$G$463),0))) -> 10 | BB96: =IF(AH136<$G$449,0,MIN($G$446,1+IFERROR(INT((AH136-$G$449)/$G$463),0))) -> 10
B97: Ben's Year 5 value (cash at close + earnout + retained Keystone stake + Topkey stock, after dilution) less Keystone value today (G430); Topkey growth held at model (G437)
B99: Ben's % Return on Keystone Value Based on Net Client Wins & Rollover %
D101: Keystone Total Annual Net Client Wins — Partnership (#)
D102: =E102+$G$458 -> 76 | E102: =F102+$G$458 -> 72 | F102: =G102+$G$458 -> 68 | G102: =H102+$G$458 -> 64 | H102: =$G$457 -> 60 | I102: =H102-$G$458 -> 56 | J102: =I102-$G$458 -> 52 | K102: =J102-$G$458 -> 48 | L102: =K102-$G$458 -> 44 | AT102: Helper: Gradient Band (0 = below $1M hurdle)
B103: Ben's Rollover % | C103: =C104-$G$439 -> 0.15 | D103: =IFERROR(Z90/$G$430,0) -> 1.483909 | E103: =IFERROR(AA90/$G$430,0) -> 1.4440906 | F103: =IFERROR(AB90/$G$430,0) -> 1.4042723 | G103: =IFERROR(AC90/$G$430,0) -> 1.364454 | H103: =IFERROR(AD90/$G$430,0) -> 1.3246356 | I103: =IFERROR(AE90/$G$430,0) -> 1.2848173 | J103: =IFERROR(AF90/$G$430,0) -> 1.244999 | K103: =IFERROR(AG90/$G$430,0) -> 1.2051806 | L103: =IFERROR(AH90/$G$430,0) -> 1.1653623 | AT103: =IF(Z130<$G$449,0,MIN($G$446,1+IFERROR(INT((Z130-$G$449)/$G$463),0))) -> 0 | AU103: =IF(AA130<$G$449,0,MIN($G$446,1+IFERROR(INT((AA130-$G$449)/$G$463),0))) -> 0 | AV103: =IF(AB130<$G$449,0,MIN($G$446,1+IFERROR(INT((AB130-$G$449)/$G$463),0))) -> 0 | AW103: =IF(AC130<$G$449,0,MIN($G$446,1+IFERROR(INT((AC130-$G$449)/$G$463),0))) -> 0 | AX103: =IF(AD130<$G$449,0,MIN($G$446,1+IFERROR(INT((AD130-$G$449)/$G$463),0))) -> 0 | AY103: =IF(AE130<$G$449,0,MIN($G$446,1+IFERROR(INT((AE130-$G$449)/$G$463),0))) -> 0 | AZ103: =IF(AF130<$G$449,0,MIN($G$446,1+IFERROR(INT((AF130-$G$449)/$G$463),0))) -> 0 | BA103: =IF(AG130<$G$449,0,MIN($G$446,1+IFERROR(INT((AG130-$G$449)/$G$463),0))) -> 0 | BB103: =IF(AH130<$G$449,0,MIN($G$446,1+IFERROR(INT((AH130-$G$449)/$G$463),0))) -> 0
C104: =C105-$G$439 -> 0.2 | D104: =IFERROR(Z91/$G$430,0) -> 1.6826863 | E104: =IFERROR(AA91/$G$430,0) -> 1.6326366 | F104: =IFERROR(AB91/$G$430,0) -> 1.5825868 | G104: =IFERROR(AC91/$G$430,0) -> 1.5325371 | H104: =IFERROR(AD91/$G$430,0) -> 1.4824873 | I104: =IFERROR(AE91/$G$430,0) -> 1.4324376 | J104: =IFERROR(AF91/$G$430,0) -> 1.3823878 | K104: =IFERROR(AG91/$G$430,0) -> 1.3323381 | L104: =IFERROR(AH91/$G$430,0) -> 1.2822883 | AT104: =IF(Z131<$G$449,0,MIN($G$446,1+IFERROR(INT((Z131-$G$449)/$G$463),0))) -> 0 | AU104: =IF(AA131<$G$449,0,MIN($G$446,1+IFERROR(INT((AA131-$G$449)/$G$463),0))) -> 0 | AV104: =IF(AB131<$G$449,0,MIN($G$446,1+IFERROR(INT((AB131-$G$449)/$G$463),0))) -> 0 | AW104: =IF(AC131<$G$449,0,MIN($G$446,1+IFERROR(INT((AC131-$G$449)/$G$463),0))) -> 0 | AX104: =IF(AD131<$G$449,0,MIN($G$446,1+IFERROR(INT((AD131-$G$449)/$G$463),0))) -> 0 | AY104: =IF(AE131<$G$449,0,MIN($G$446,1+IFERROR(INT((AE131-$G$449)/$G$463),0))) -> 0 | AZ104: =IF(AF131<$G$449,0,MIN($G$446,1+IFERROR(INT((AF131-$G$449)/$G$463),0))) -> 0 | BA104: =IF(AG131<$G$449,0,MIN($G$446,1+IFERROR(INT((AG131-$G$449)/$G$463),0))) -> 0 | BB104: =IF(AH131<$G$449,0,MIN($G$446,1+IFERROR(INT((AH131-$G$449)/$G$463),0))) -> 1
C105: =C106-$G$439 -> 0.25 | D105: =IFERROR(Z92/$G$430,0) -> 1.8825291 | E105: =IFERROR(AA92/$G$430,0) -> 1.8221916 | F105: =IFERROR(AB92/$G$430,0) -> 1.7618542 | G105: =IFERROR(AC92/$G$430,0) -> 1.7015168 | H105: =IFERROR(AD92/$G$430,0) -> 1.6411793 | I105: =IFERROR(AE92/$G$430,0) -> 1.5808419 | J105: =IFERROR(AF92/$G$430,0) -> 1.5205045 | K105: =IFERROR(AG92/$G$430,0) -> 1.460167 | L105: =IFERROR(AH92/$G$430,0) -> 1.3998296 | AT105: =IF(Z132<$G$449,0,MIN($G$446,1+IFERROR(INT((Z132-$G$449)/$G$463),0))) -> 0 | AU105: =IF(AA132<$G$449,0,MIN($G$446,1+IFERROR(INT((AA132-$G$449)/$G$463),0))) -> 0 | AV105: =IF(AB132<$G$449,0,MIN($G$446,1+IFERROR(INT((AB132-$G$449)/$G$463),0))) -> 0 | AW105: =IF(AC132<$G$449,0,MIN($G$446,1+IFERROR(INT((AC132-$G$449)/$G$463),0))) -> 0 | AX105: =IF(AD132<$G$449,0,MIN($G$446,1+IFERROR(INT((AD132-$G$449)/$G$463),0))) -> 0 | AY105: =IF(AE132<$G$449,0,MIN($G$446,1+IFERROR(INT((AE132-$G$449)/$G$463),0))) -> 0 | AZ105: =IF(AF132<$G$449,0,MIN($G$446,1+IFERROR(INT((AF132-$G$449)/$G$463),0))) -> 0 | BA105: =IF(AG132<$G$449,0,MIN($G$446,1+IFERROR(INT((AG132-$G$449)/$G$463),0))) -> 1 | BB105: =IF(AH132<$G$449,0,MIN($G$446,1+IFERROR(INT((AH132-$G$449)/$G$463),0))) -> 3
