Workbook

Sheet Cover
B24: Keystone Bookkeepers
B25: Offer Structure Overview
B26: ="As of "&TEXT(TODAY(),"mm/dd/yy") -> As of 09/24/26

Sheet Offer Comparison
B2: =Cover!$B$24 -> Keystone Bookkeepers
B3: Offer Comparison — Partnership vs. 100% Buyout ($000s) | H3: Print | I3: 0
B5: Deal Assumptions | C5: Partnership | D5: 100% Buyout | E5: Variance | G5: Notes
B7: Horizon (Years) | C7: 5 | D7: =C7 -> 5 | E7: =C7-D7 -> 0 | G7: Input — drives Partnership and Buyout tabs (D = C)
B8: Est. Topkey Dilution — Ben's Stake (Year 5) | C8: 0.05 | D8: =C8 -> 0.05 | E8: =C8-D8 -> 0 | G8: Input — drives Partnership and Buyout tabs (D = C)
B9: Topkey Valuation Today — Pre-Deal | C9: 60000 | D9: =C9 -> 60000 | E9: =C9-D9 -> 0 | G9: Input — single Topkey valuation; drives Offer Overview, Partnership and Buyout tabs
B10: ="Topkey "&$C$7&"-Year Valuation Growth (ex-Keystone)" -> Topkey 5-Year Valuation Growth (ex-Keystone) | C10: ='Partnership Analysis'!$C$19 -> 2.021904 | D10: ='100% Buyout Analysis'!$C$18 -> 2.0084034 | E10: =C10-D10 -> 0.013500598 | G10: Differs because each offer's cash at close is netted from Topkey's ex-Keystone base; measures value growth, not revenue
B11: Keystone 5-Yr Revenue Increase — Standalone (% of Start) | C11: =IFERROR('Partnership Analysis'!$C$28/'Partnership Analysis'!$C$45,0) -> 0.99837392 | D11: =IFERROR('100% Buyout Analysis'!$C$27/'100% Buyout Analysis'!$C$44,0) -> 0.99837392 | E11: =C11-D11 -> 0 | G11: Total additional standalone revenue ÷ Keystone run-rate revenue at close
B12: Keystone 5-Yr Revenue Increase — Partnership (% of Start) | C12: =IFERROR('Partnership Analysis'!$C$40/'Partnership Analysis'!$C$45,0) -> 1.3311652 | D12: =IFERROR('100% Buyout Analysis'!$C$39/'100% Buyout Analysis'!$C$44,0) -> 1.3311652 | E12: =C12-D12 -> 0 | G12: Total additional partnership revenue ÷ Keystone run-rate revenue at close
B13: Keystone Initial Revenue Multiple | C13: 1 | D13: =C13 -> 1 | E13: =C13-D13 -> 0 | G13: Input — drives Partnership and Buyout tabs (D = C)
B14: Keystone Scaled Revenue Multiple | C14: 1.25 | D14: =C14 -> 1.25 | E14: =C14-D14 -> 0 | G14: Input — drives Partnership and Buyout tabs (D = C)
B15: Keystone Software-Integration Revenue Multiple | C15: 2 | D15: =C15 -> 2 | E15: =C15-D15 -> 0 | G15: Input — drives Partnership and Buyout tabs (D = C)
B16: General Assumptions
B17: Ben's Rollover % — Keystone | C17: 0.3 | D17: 0 | E17: =C17-D17 -> 0.3 | G17: ="Input — share of Keystone Ben keeps ("&"Partnership "&TEXT(C17,"0%")&"; "&"Buyout "&TEXT(D17,"0%")&" = Topkey "&"acquires "&TEXT(1-D17,"0%")&")" -> Input — share of Keystone Ben keeps (Partnership 30%; Buyout 0% = Topkey acquires 100%)
B18: Topkey - Current Monthly Revenue | C18: 261 | D18: =C18 -> 261 | E18: =C18-D18 -> 0 | G18: Input — drives Partnership and Buyout tabs (D = C). Topkey-provided monthly revenue ($000s); red = pending seller confirmation
B19: Topkey - Current Client Count | C19: 325 | D19: =C19 -> 325 | E19: =C19-D19 -> 0 | G19: Input — drives Partnership and Buyout tabs (D = C). Topkey-provided client count; red = pending seller confirmation
B20: Topkey - Annual Net Client Wins | C20: 130 | D20: =C20 -> 130 | E20: =C20-D20 -> 0 | G20: Input — drives Partnership and Buyout tabs (D = C). AMB placeholder; red = pending confirmation
B21: Keystone Standalone Assumptions
B22: Avg. Revenue Per Client | C22: =$C$156 -> 16.631473 | D22: =C22 -> 16.631473 | E22: =C22-D22 -> 0 | G22: ="Linked to Avg. Revenue Per Client — Sep'26 input ("&ADDRESS(ROW(C156),COLUMN(C156),4)&"; from Steady-State Staffing AB8, v49); drives both tabs (D = C)" -> Linked to Avg. Revenue Per Client — Sep'26 input (C156; from Steady-State Staffing AB8, v49); drives both tabs (D = C)
B23: Target Monthly Net Client Wins | C23: 3 | D23: =C23 -> 3 | E23: =C23-D23 -> 0 | G23: ="Input — drives Partnership and Buyout tabs (D = C). AMB target pace; LTM actual is "&TEXT(C160+C161,"0")&"/yr (~"&TEXT((C160+C161)/12,"0.0")&"/month)" -> Input — drives Partnership and Buyout tabs (D = C). AMB target pace; LTM actual is 26/yr (~2.2/month)
B24: Keystone Partnership Assumptions
B25: VR Platform Run-Rate Tech Cost | C25: 240 | D25: =C25 -> 240 | E25: =C25-D25 -> 0 | G25: Input — drives Partnership and Buyout tabs (D = C). Run-rate tech cost provided by the target; memo only
B26: Additional Annual Net Client Wins From Topkey | C26: 12 | D26: =C26 -> 12 | E26: =C26-D26 -> 0 | G26: Input — drives Partnership and Buyout tabs (D = C). Topkey-provided; red = pending seller confirmation
B28: Offer Structure | C28: Partnership | D28: 100% Buyout | E28: Variance
B29: Keystone Value Today (100%) | C29: ='Partnership Analysis'!$C$173 -> 3000 | D29: ='100% Buyout Analysis'!$C$164 -> 3000 | E29: =C29-D29 -> 0
B30: Ben's Rollover % — Keystone | C30: =C17 -> 0.3 | D30: =D17 -> 0 | E30: =C30-D30 -> 0.3 | G30: ="Linked to Ben's Rollover % input (row "&ROW($B$17)&")" -> Linked to Ben's Rollover % input (row 17)
B31: Keystone Stake Acquired by Topkey | C31: ='Partnership Analysis'!$C$175 -> 0.7 | D31: ='100% Buyout Analysis'!$C$94 -> 1 | E31: =C31-D31 -> -0.3
B32: Price for Topkey's Stake (at Close) | C32: ='Partnership Analysis'!$C$176 -> 2100 | D32: ='100% Buyout Analysis'!$C$164 -> 3000 | E32: =C32-D32 -> -900
B33: Cash at Close | C33: ='Partnership Analysis'!$C$177 -> 650 | D33: ='100% Buyout Analysis'!$C$165 -> 500 | E33: =C33-D33 -> 150 | G33: ="Partnership cash of "&TEXT(C33,"$#,##0")&"K"&" is set to cover Ben's tax situation" -> Partnership cash of $650K is set to cover Ben's tax situation
B34: (+) Topkey Equity Issued to Ben | C34: ='Partnership Analysis'!$C$178 -> 1450 | D34: ='100% Buyout Analysis'!$C$166 -> 2500 | E34: =C34-D34 -> -1050
B35: (+) Target Cash Earnout (at 100% Achievement) — Year 3 | C35: ='Partnership Analysis'!$C$56 -> 0 | D35: ='100% Buyout Analysis'!$C$55 -> 500 | E35: =C35-D35 -> -500 | G35: ="Buyout: "&TEXT('100% Buyout Analysis'!C49,"$#,##0")&"K target"&", capped at "&TEXT('100% Buyout Analysis'!C53,"$#,##0")&"K"&" ("&TEXT('100% Buyout Analysis'!C51,"0%")&" of target"&"). Partnership: no earnout" -> Buyout: $500K target, capped at $750K (150% of target). Partnership: no earnout
B36: Total Consideration Paid by Topkey | C36: =SUM(C33:C35) -> 2100 | D36: =SUM(D33:D35) -> 3500 | E36: =C36-D36 -> -1400 | G36: ="Cash + equity issued + target earnout; tie-out to analysis tabs in row "&ROW($B$37) -> Cash + equity issued + target earnout; tie-out to analysis tabs in row 37
B37: Tie Out — Consideration vs. Analysis Tab | C37: =C36-'Partnership Analysis'!$C$104 -> 0 | D37: =D36-'100% Buyout Analysis'!$C$93 -> 0 | G37: Must equal zero
B38: % of Consideration in Cash (incl. Earnout) | C38: =IFERROR((C33+C35)/C36,0) -> 0.30952381 | D38: =IFERROR((D33+D35)/D36,0) -> 0.28571429 | E38: =C38-D38 -> 0.023809524
B40: Where Ben's Year 5 Value Comes From | C40: Partnership | D40: 100% Buyout | E40: Variance
B42: Retained Keystone Stake (Direct) | C42: =IFERROR(C105/C$110,0) -> 0.46170498 | D42: =IFERROR(D105/D$110,0) -> 0 | E42: =C42-D42 -> 0.46170498
B43: Keystone via Topkey | C43: =IFERROR(C106/C$110,0) -> 0.024149662 | D43: =IFERROR(D106/D$110,0) -> 0.063750321 | E43: =C43-D43 -> -0.039600659
B44: Topkey ex-Keystone | C44: =IFERROR(C107/C$110,0) -> 0.44258976 | D44: =IFERROR(D107/D$110,0) -> 0.81624844 | E44: =C44-D44 -> -0.37365868
B45: Cash at Close | C45: =IFERROR(C108/C$110,0) -> 0.071555598 | D45: =IFERROR(D108/D$110,0) -> 0.06000062 | E45: =C45-D45 -> 0.011554978
B46: Cash Earnout — Year 3 | C46: =IFERROR(C109/C$110,0) -> 0 | D46: =IFERROR(D109/D$110,0) -> 0.06000062 | E46: =C46-D46 -> -0.06000062
B48: Return Profile — Jon (Topkey) | C48: Partnership | D48: 100% Buyout | E48: Variance | K48: Helper: Year | L48: 0 | M48: 1 | N48: 2 | O48: 3 | P48: 4 | Q48: 5
B49: Cash at Close (Year 0) | C49: =C33 -> 650 | D49: =D33 -> 500 | E49: =C49-D49 -> 150 | K49: Helper: Partnership CF | L49: =-(L$48=0)*($C$33+$C$34)-(L$48=$L$51)*$C$35+(L$48=$C$7)*$C$53 -> -2100 | M49: =-(M$48=0)*($C$33+$C$34)-(M$48=$L$51)*$C$35+(M$48=$C$7)*$C$53 -> 0 | N49: =-(N$48=0)*($C$33+$C$34)-(N$48=$L$51)*$C$35+(N$48=$C$7)*$C$53 -> 0 | O49: =-(O$48=0)*($C$33+$C$34)-(O$48=$L$51)*$C$35+(O$48=$C$7)*$C$53 -> 0 | P49: =-(P$48=0)*($C$33+$C$34)-(P$48=$L$51)*$C$35+(P$48=$C$7)*$C$53 -> 0 | Q49: =-(Q$48=0)*($C$33+$C$34)-(Q$48=$L$51)*$C$35+(Q$48=$C$7)*$C$53 -> 9786.1324
B50: (+) Equity Issued to Ben (Year 0) | C50: =C34 -> 1450 | D50: =D34 -> 2500 | E50: =C50-D50 -> -1050 | K50: Helper: Buyout CF | L50: =-(L$48=0)*($D$33+$D$34)-(L$48=$L$51)*$D$35+(L$48=$D$7)*$D$53 -> -3000 | M50: =-(M$48=0)*($D$33+$D$34)-(M$48=$L$51)*$D$35+(M$48=$D$7)*$D$53 -> 0 | N50: =-(N$48=0)*($D$33+$D$34)-(N$48=$L$51)*$D$35+(N$48=$D$7)*$D$53 -> 0 | O50: =-(O$48=0)*($D$33+$D$34)-(O$48=$L$51)*$D$35+(O$48=$D$7)*$D$53 -> -500 | P50: =-(P$48=0)*($D$33+$D$34)-(P$48=$L$51)*$D$35+(P$48=$D$7)*$D$53 -> 0 | Q50: =-(Q$48=0)*($D$33+$D$34)-(Q$48=$L$51)*$D$35+(Q$48=$D$7)*$D$53 -> 13980.189
B51: (+) Target Cash Earnout (at 100% Achievement) (Year 3) | C51: =C35 -> 0 | D51: =D35 -> 500 | E51: =C51-D51 -> -500 | K51: Helper: Earnout Year | L51: ='100% Buyout Analysis'!$C$43 -> 3 | M51: Year the target earnout is paid — linked to 100% Buyout Analysis (Earnout Measurement Year)
B52: Total Invested by Jon (Topkey) | C52: =SUM(C49:C51) -> 2100 | D52: =SUM(D49:D51) -> 3500 | E52: =C52-D52 -> -1400 | G52: ="Ties to Total Consideration (row "&ROW($B$36)&")" -> Ties to Total Consideration (row 36) | K52: Helper: Partnership Hurdle CF | L52: =-(L$48=0)*($C$33+$C$34)+(L$48=$C$7)*$C$130 -> -2100 | M52: =-(M$48=0)*($C$33+$C$34)+(M$48=$C$7)*$C$130 -> 0 | N52: =-(N$48=0)*($C$33+$C$34)+(N$48=$C$7)*$C$130 -> 0 | O52: =-(O$48=0)*($C$33+$C$34)+(O$48=$C$7)*$C$130 -> 0 | P52: =-(P$48=0)*($C$33+$C$34)+(P$48=$C$7)*$C$130 -> 0 | Q52: =-(Q$48=0)*($C$33+$C$34)+(Q$48=$C$7)*$C$130 -> 5000
B53: Topkey's Keystone Stake — Year 5 Value | C53: ='Partnership Analysis'!$D$80 -> 9786.1324 | D53: ='100% Buyout Analysis'!$D$74 -> 13980.189 | E53: =C53-D53 -> -4194.0567 | G53: ="Topkey's stake acquired (row "&ROW($B$31)&") × Keystone Year "&$C$7&" value" -> Topkey's stake acquired (row 31) × Keystone Year 5 value | K53: Helper: Buyout Hurdle CF | L53: =-(L$48=0)*($D$33+$D$34)+(L$48=$D$7)*$D$130 -> -3000 | M53: =-(M$48=0)*($D$33+$D$34)+(M$48=$D$7)*$D$130 -> 0 | N53: =-(N$48=0)*($D$33+$D$34)+(N$48=$D$7)*$D$130 -> 0 | O53: =-(O$48=0)*($D$33+$D$34)+(O$48=$D$7)*$D$130 -> 0 | P53: =-(P$48=0)*($D$33+$D$34)+(P$48=$D$7)*$D$130 -> 0 | Q53: =-(Q$48=0)*($D$33+$D$34)+(Q$48=$D$7)*$D$130 -> 8000
B54: Deal MOIC | C54: =IFERROR(C53/C52,0) -> 4.660063 | D54: =IFERROR(D53/D52,0) -> 3.9943397 | E54: =C54-D54 -> 0.66572329 | G54: Standard acquirer view: stake value ÷ consideration at issue price
B55: Deal IRR | C55: =IFERROR(IRR($L49:$Q49),0) -> 0.36043676 | D55: =IFERROR(IRR($L50:$Q50),0) -> 0.34242961 | E55: =C55-D55 -> 0.018007148 | G55: ="Cash-flow IRR; see helper cash flows in "&ADDRESS(ROW(L49),COLUMN(L49),4)&":"&ADDRESS(ROW(Q50),COLUMN(Q50),4) -> Cash-flow IRR; see helper cash flows in L49:Q50
B56: (-) Hurdle MOIC — Break-Even | C56: =IFERROR(C130/(C49+C50),0) -> 2.3809524 | D56: =IFERROR(D130/(D49+D50),0) -> 2.6666667 | E56: =C56-D56 -> -0.28571429 | G56: ="Break-even stake value (row "&ROW($B$130)&") ÷ cash + stock; no earnout paid at break-even" -> Break-even stake value (row 130) ÷ cash + stock; no earnout paid at break-even
B57: (-) Hurdle IRR — Break-Even | C57: =IFERROR(IRR($L52:$Q52),0) -> 0.18946082 | D57: =IFERROR(IRR($L53:$Q53),0) -> 0.21672868 | E57: =C57-D57 -> -0.027267862 | G57: ="Cash-flow IRR on break-even flows ("&ADDRESS(ROW(L52),COLUMN(L52),4)&":"&ADDRESS(ROW(Q53),COLUMN(Q53),4)&"): cash + stock at Yr 0, break-even stake value (row "&ROW($B$130)&") at Yr "&$C$7&"; no earnout" -> Cash-flow IRR on break-even flows (L52:Q53): cash + stock at Yr 0, break-even stake value (row 130) at Yr 5; no earnout
B58: Excess MOIC over Hurdle | C58: =C54-C56 -> 2.2791106 | D58: =D54-D56 -> 1.3276731 | E58: =C58-D58 -> 0.95143758 | G58: Deal return after backing out the cost of paying in Topkey stock
B59: Excess IRR over Hurdle (% pts) | C59: =C55-C57 -> 0.17097594 | D59: =D55-D57 -> 0.12570093 | E59: =C59-D59 -> 0.04527501 | G59: Deal IRR less hurdle IRR
B60: Jon's Year 5 Value — With Deal | C60: =C$149*('Partnership Analysis'!$D$79+'Partnership Analysis'!$D$80) -> 175439.54 | D60: =D$149*('100% Buyout Analysis'!$D$73+'100% Buyout Analysis'!$D$74) -> 175997.93 | E60: =C60-D60 -> -558.39551 | G60: Jon's diluted % × (Topkey ex-Keystone + Keystone stake)
B61: (-) Jon's Year 5 Value — Without Deal | C61: =(1-C$8)*('Partnership Analysis'!$D$79+C33+C35) -> 171000 | D61: =(1-D$8)*('100% Buyout Analysis'!$D$73+D33+D35) -> 171000 | E61: =C61-D61 -> 0 | G61: Topkey keeps its cash and pays no earnout; Jon diluted by the same est. %
B62: Net Value Created for Jon | C62: =C60-C61 -> 4439.5369 | D62: =D60-D61 -> 4997.9324 | E62: =C62-D62 -> -558.39551 | G62: Includes the cost of stock sharing Topkey's growth with Ben
B63: All-In MOIC | C63: =IFERROR((C52+C62)/C52,0) -> 3.1140652 | D63: =IFERROR((D52+D62)/D52,0) -> 2.4279807 | E63: =C63-D63 -> 0.68608451 | G63: (Invested + net value created) ÷ invested
B64: All-In IRR | C64: =IFERROR(C63^(1/C$7)-1,0) -> 0.25506304 | D64: =IFERROR(D63^(1/D$7)-1,0) -> 0.19412295 | E64: =C64-D64 -> 0.060940088 | G64: MOIC^(1 / horizon) − 1
B66: Partnership Upside Analysis
C67: ="First "&TEXT(C31,"0%")&" (Partnership)" -> First 70% (Partnership) | D67: =TEXT(D31,"0%")&" (Buyout)" -> 100% (Buyout) | E67: ="Extra "&TEXT(D31-C31,"0%") -> Extra 30% | G67: ="Column E = incremental cost and return of buying the "&"last "&TEXT(C17,"0%")&" (Buyout less Partnership)" -> Column E = incremental cost and return of buying the last 30% (Buyout less Partnership)
B68: Keystone Stake Acquired by Topkey | C68: =C31 -> 0.7 | D68: =D31 -> 1 | E68: =D68-C68 -> 0.3
B69: Total Invested by Jon (Topkey) | C69: =C52 -> 2100 | D69: =D52 -> 3500 | E69: =D69-C69 -> 1400 | G69: ="Incremental cost of the "&"last "&TEXT(C17,"0%") -> Incremental cost of the last 30%
B70: Cost per 1% of Keystone | C70: =IFERROR(C69/(C68*100),0) -> 30 | D70: =IFERROR(D69/(D68*100),0) -> 35 | E70: =IFERROR(E69/(E68*100),0) -> 46.666667 | G70: ="Price per point rises on the "&"extra "&TEXT(C17,"0%")&" (earnout added)" -> Price per point rises on the extra 30% (earnout added)
B71: Paid in Topkey Stock (% of Invested) | C71: =IFERROR(C50/C69,0) -> 0.69047619 | D71: =IFERROR(D50/D69,0) -> 0.71428571 | E71: =IFERROR((D50-C50)/E69,0) -> 0.75 | G71: Stock is Jon's most expensive currency (shares Topkey's growth)
B72: Keystone Stake Value — Year 5 | C72: =C53 -> 9786.1324 | D72: =D53 -> 13980.189 | E72: =D72-C72 -> 4194.0567
B73: Deal MOIC | C73: =IFERROR(C72/C69,0) -> 4.660063 | D73: =IFERROR(D72/D69,0) -> 3.9943397 | E73: =IFERROR(E72/E69,0) -> 2.9957548 | G73: Stake value ÷ consideration at issue price
B74: Hurdle MOIC — Break-Even | C74: =C56 -> 2.3809524 | D74: =D56 -> 2.6666667 | E74: n/m | G74: ="From Jon's return profile (row "&ROW($B$56)&"); n/m for the "&"extra "&TEXT(C17,"0%")&" (break-even excludes earnout, so hurdles aren't additive)" -> From Jon's return profile (row 56); n/m for the extra 30% (break-even excludes earnout, so hurdles aren't additive)
B75: Net Value Created for Jon | C75: =C62 -> 4439.5369 | D75: =D62 -> 4997.9324 | E75: =D75-C75 -> 558.39551 | G75: ="Incremental value to Jon from the "&"last "&TEXT(C17,"0%") -> Incremental value to Jon from the last 30%
B76: All-In MOIC | C76: =IFERROR((C69+C75)/C69,0) -> 3.1140652 | D76: =IFERROR((D69+D75)/D69,0) -> 2.4279807 | E76: =IFERROR((E69+E75)/E69,0) -> 1.3988539 | G76: (Invested + net value created) ÷ invested
B77: All-In IRR | C77: =IFERROR(C76^(1/C$7)-1,0) -> 0.25506304 | D77: =IFERROR(D76^(1/D$7)-1,0) -> 0.19412295 | E77: =IFERROR(E76^(1/D$7)-1,0) -> 0.069435198 | G77: MOIC^(1 / horizon) − 1
B79: Return Profile — Ben | C79: Partnership | D79: 100% Buyout | E79: Variance | K79: Helper: Year | L79: 0 | M79: 1 | N79: 2 | O79: 3 | P79: 4 | Q79: 5
B80: Keystone Value Contributed by Ben (Year 0) | C80: =C29 -> 3000 | D80: =D29 -> 3000 | E80: =C80-D80 -> 0 | G80: Ben gives up 100% of Keystone at today's value in both offers | K80: Helper: Partnership CF | L80: =-(L$79=0)*($C$80-$C$81)+(L$79=$L$51)*$C$82+(L$79=$C$7)*($C$83+$C$84) -> -2350 | M80: =-(M$79=0)*($C$80-$C$81)+(M$79=$L$51)*$C$82+(M$79=$C$7)*($C$83+$C$84) -> 0 | N80: =-(N$79=0)*($C$80-$C$81)+(N$79=$L$51)*$C$82+(N$79=$C$7)*($C$83+$C$84) -> 0 | O80: =-(O$79=0)*($C$80-$C$81)+(O$79=$L$51)*$C$82+(O$79=$C$7)*($C$83+$C$84) -> 0 | P80: =-(P$79=0)*($C$80-$C$81)+(P$79=$L$51)*$C$82+(P$79=$C$7)*($C$83+$C$84) -> 0 | Q80: =-(Q$79=0)*($C$80-$C$81)+(Q$79=$L$51)*$C$82+(Q$79=$C$7)*($C$83+$C$84) -> 8433.8455
B81: Cash at Close (Year 0) | C81: =C108 -> 650 | D81: =D108 -> 500 | E81: =C81-D81 -> 150 | K81: Helper: Buyout CF | L81: =-(L$79=0)*($D$80-$D$81)+(L$79=$L$51)*$D$82+(L$79=$D$7)*($D$83+$D$84) -> -2500 | M81: =-(M$79=0)*($D$80-$D$81)+(M$79=$L$51)*$D$82+(M$79=$D$7)*($D$83+$D$84) -> 0 | N81: =-(N$79=0)*($D$80-$D$81)+(N$79=$L$51)*$D$82+(N$79=$D$7)*($D$83+$D$84) -> 0 | O81: =-(O$79=0)*($D$80-$D$81)+(O$79=$L$51)*$D$82+(O$79=$D$7)*($D$83+$D$84) -> 500 | P81: =-(P$79=0)*($D$80-$D$81)+(P$79=$L$51)*$D$82+(P$79=$D$7)*($D$83+$D$84) -> 0 | Q81: =-(Q$79=0)*($D$80-$D$81)+(Q$79=$L$51)*$D$82+(Q$79=$D$7)*($D$83+$D$84) -> 7333.2472
B82: (+) Target Cash Earnout (at 100% Achievement) (Year 3) | C82: =C109 -> 0 | D82: =D109 -> 500 | E82: =C82-D82 -> -500
B83: (+) Retained Keystone Stake — Year 5 | C83: =C105 -> 4194.0567 | D83: =D105 -> 0 | E83: =C83-D83 -> 4194.0567 | G83: ="Partnership: Ben's retained stake (row "&ROW($B$30)&"); Buyout: none" -> Partnership: Ben's retained stake (row 30); Buyout: none
B84: (+) Topkey Equity — Year 5 | C84: =C106+C107 -> 4239.7888 | D84: =D106+D107 -> 7333.2472 | E84: =C84-D84 -> -3093.4584 | G84: Diluted Topkey stake, incl. Ben's indirect share of Keystone
B85: Total Value Received by Ben | C85: =SUM(C81:C84) -> 9083.8455 | D85: =SUM(D81:D84) -> 8333.2472 | E85: =C85-D85 -> 750.59835 | G85: ="Ties to Ben's Value — Offer (row "&ROW($B$92)&"); tie-out in row "&ROW($B$102) -> Ties to Ben's Value — Offer (row 92); tie-out in row 102
B86: Total MOIC | C86: =IFERROR(C85/C80,0) -> 3.0279485 | D86: =IFERROR(D85/D80,0) -> 2.7777491 | E86: =C86-D86 -> 0.25019945 | G86: Total value received ÷ Keystone value contributed
B87: Total IRR | C87: =IFERROR(IRR($L80:$Q80),0) -> 0.29119417 | D87: =IFERROR(IRR($L81:$Q81),0) -> 0.266139 | E87: =C87-D87 -> 0.025055167 | G87: ="Cash-flow IRR; see helper cash flows in "&ADDRESS(ROW(L80),COLUMN(L80),4)&":"&ADDRESS(ROW(Q81),COLUMN(Q81),4) -> Cash-flow IRR; see helper cash flows in L80:Q81
B88: (-) Ben's Year 5 Value — Standalone | C88: =C93 -> 7490.2577 | D88: =D93 -> 7490.2577 | E88: =C88-D88 -> 0 | G88: Ben keeps 100% of Keystone
B89: Net Value Created for Ben | C89: =C85-C88 -> 1593.5878 | D89: =D85-D88 -> 842.98949 | E89: =C89-D89 -> 750.59835 | G89: Offer vs. keeping 100% of Keystone
B91: Ben — Offer vs. Standalone (Year 5) | C91: Partnership | D91: 100% Buyout | E91: Variance
B92: Ben's Value — Offer | C92: ='Partnership Analysis'!$D$90 -> 9083.8455 | D92: ='100% Buyout Analysis'!$D$79 -> 8333.2472 | E92: =C92-D92 -> 750.59835
B93: (-) Ben's Value — Standalone | C93: ='Partnership Analysis'!$D$72 -> 7490.2577 | D93: ='100% Buyout Analysis'!$D$70 -> 7490.2577 | E93: =C93-D93 -> 0
B94: Offer Less Standalone ($) | C94: =C92-C93 -> 1593.5878 | D94: =D92-D93 -> 842.98949 | E94: =C94-D94 -> 750.59835
B95: Offer Less Standalone (%) | C95: =IFERROR(C92/C93-1,0) -> 0.21275474 | D95: =IFERROR(D92/D93-1,0) -> 0.11254479
B96: MOIC — Offer | C96: ='Partnership Analysis'!$D$95 -> 3.0279485 | D96: ='100% Buyout Analysis'!$D$84 -> 2.7777491 | E96: =C96-D96 -> 0.25019945
B97: (-) MOIC — Standalone | C97: =IFERROR('Partnership Analysis'!$D$72/'Partnership Analysis'!$C$72,0) -> 2.4967526 | D97: =IFERROR('100% Buyout Analysis'!$D$70/'100% Buyout Analysis'!$C$70,0) -> 2.4967526 | E97: =C97-D97 -> 0 | G97: ="Keystone Year "&$C$7&" value ÷ value today" -> Keystone Year 5 value ÷ value today
B98: MOIC Delta — Offer vs. Standalone | C98: =C96-C97 -> 0.53119594 | D98: =D96-D97 -> 0.2809965 | E98: =C98-D98 -> 0.25019945
B99: IRR — Offer | C99: ='Partnership Analysis'!$D$96 -> 0.29119417 | D99: ='100% Buyout Analysis'!$D$85 -> 0.266139 | E99: =C99-D99 -> 0.025055167 | G99: From each tab's cash-flow IRR (includes cash timing)
B100: (-) IRR — Standalone | C100: =IFERROR(C97^(1/C$7)-1,0) -> 0.20081223 | D100: =IFERROR(D97^(1/D$7)-1,0) -> 0.20081223 | E100: =C100-D100 -> 0
B101: IRR Delta — Offer vs. Standalone | C101: =C99-C100 -> 0.090381943 | D101: =D99-D100 -> 0.065326775 | E101: =C101-D101 -> 0.025055167
B102: Tie Out — Ben's Value by Source vs. Offer | C102: =C85-C92 -> 0 | D102: =D85-D92 -> 0 | G102: Must equal zero
B104: Ben's Year 5 Value | C104: Partnership | D104: 100% Buyout | E104: Variance
B105: Retained Keystone Stake (Direct) | C105: ='Partnership Analysis'!$D$85 -> 4194.0567 | D105: 0 | E105: =C105-D105 -> 4194.0567 | G105: Buyout: no retained stake
B106: (+) Keystone via Topkey | C106: ='Partnership Analysis'!$D$86 -> 219.3718 | D106: ='100% Buyout Analysis'!$C$116 -> 531.24718 | E106: =C106-D106 -> -311.87538
B107: (+) Topkey ex-Keystone | C107: ='Partnership Analysis'!$D$87 -> 4020.417 | D107: ='100% Buyout Analysis'!$C$115 -> 6802 | E107: =C107-D107 -> -2781.583
B108: (+) Cash at Close | C108: ='Partnership Analysis'!$D$88 -> 650 | D108: ='100% Buyout Analysis'!$C$117 -> 500 | E108: =C108-D108 -> 150
B109: (+) Cash Earnout — Year 3 | C109: ='Partnership Analysis'!$D$89 -> 0 | D109: ='100% Buyout Analysis'!$C$118 -> 500 | E109: =C109-D109 -> -500
B110: Ben's Value — Offer (Year 5) | C110: =SUM(C105:C109) -> 9083.8455 | D110: =SUM(D105:D109) -> 8333.2472 | E110: =C110-D110 -> 750.59835
B111: Tie Out — Value by Source vs. Offer | C111: =C110-C92 -> 0 | D111: =D110-D92 -> 0 | G111: Must equal zero
...

Sheet Partnership Analysis
B2: =Cover!$B$24 -> Keystone Bookkeepers
B3: Partnership Rollover Scenarios ($000s) | G3: Print | H3: 1
B5: Revenue Growth Assumptions | C5: Value | F5: Rationale / Notes
B6: General Assumptions
B7: Ben's Rollover % — Keystone | C7: ='Offer Comparison'!$C$17 -> 0.3 | F7: ="Input on Offer Comparison ("&ADDRESS(ROW('Offer Comparison'!C17),COLUMN('Offer Comparison'!C17),4)&"). Share of Keystone Ben keeps; Topkey buys the rest for cash + Topkey equity" -> Input on Offer Comparison (C17). Share of Keystone Ben keeps; Topkey buys the rest for cash + Topkey equity
B8: Est. Topkey Dilution — Ben's Stake (Year 5) | C8: ='Offer Comparison'!$C$8 -> 0.05 | F8: ="Linked to Offer Comparison ("&ADDRESS(ROW('Offer Comparison'!C8),COLUMN('Offer Comparison'!C8),4)&"). AMB estimate: future Topkey equity issuance (capital raise, option pool, acquisitions) reduces Ben's Topkey % by this share by Year "&$C$9 -> Linked to Offer Comparison (C8). AMB estimate: future Topkey equity issuance (capital raise, option pool, acquisitions) reduces Ben's Topkey % by this share by Year 5
B9: Horizon (Years) | C9: ='Offer Comparison'!$C$7 -> 5 | F9: ="Linked to Offer Comparison ("&ADDRESS(ROW('Offer Comparison'!C7),COLUMN('Offer Comparison'!C7),4)&"). Projection horizon for the Year "&$C$9&" columns" -> Linked to Offer Comparison (C7). Projection horizon for the Year 5 columns
B10: Topkey - Current Monthly Revenue | C10: ='Offer Comparison'!$C$18 -> 261 | F10: ="Input on Offer Comparison ("&ADDRESS(ROW('Offer Comparison'!C18),COLUMN('Offer Comparison'!C18),4)&"). Topkey-provided monthly revenue ($000s); pending confirmation" -> Input on Offer Comparison (C18). Topkey-provided monthly revenue ($000s); pending confirmation
B11: Topkey - Current Run-Rate Revenue | C11: =C10*12 -> 3132
B12: Topkey - Current Revenue Multiple | C12: =IFERROR(C179/C11,0) -> 19.157088 | F12: ="Implied: Topkey pre-deal valuation ("&ADDRESS(ROW(C179),COLUMN(C179),4)&") ÷ run-rate revenue ("&ADDRESS(ROW(C11),COLUMN(C11),4)&")" -> Implied: Topkey pre-deal valuation (C179) ÷ run-rate revenue (C11)
B13: Topkey - Future Revenue Multiple | C13: =C12 -> 19.157088 | F13: Held flat at the current implied multiple
B14: Topkey - Current Client Count | C14: ='Offer Comparison'!$C$19 -> 325 | F14: ="Input on Offer Comparison ("&ADDRESS(ROW('Offer Comparison'!C19),COLUMN('Offer Comparison'!C19),4)&"). Topkey-provided client count; pending confirmation" -> Input on Offer Comparison (C19). Topkey-provided client count; pending confirmation
B15: Topkey - Avg. Revenue Per Client | C15: =C11/C14 -> 9.6369231
B16: Topkey - Annual Net Client Wins | C16: ='Offer Comparison'!$C$20 -> 130 | F16: ="Input on Offer Comparison ("&ADDRESS(ROW('Offer Comparison'!C20),COLUMN('Offer Comparison'!C20),4)&"). AMB placeholder; pending confirmation" -> Input on Offer Comparison (C20). AMB placeholder; pending confirmation
B17: Total Net Client Wins | C17: =C16*$C$9 -> 650
B18: Total Additional Revenue | C18: =C17*C15 -> 6264
B19: ="Check - "&$C$9&" Year Topkey Valuation Growth" -> Check - 5 Year Topkey Valuation Growth | C19: =IFERROR(D79/C79-1,0) -> 2.021904 | F19: ="% growth in Topkey ex-Keystone value (row "&ROW($B$79)&"), today → Year "&$C$9&"; value net of cash paid, not revenue" -> % growth in Topkey ex-Keystone value (row 79), today → Year 5; value net of cash paid, not revenue
B21: Keystone Standalone Assumptions
B22: Revenue Multiple | C22: ='Offer Comparison'!$C$13 -> 1 | F22: ="Linked to Offer Comparison ("&ADDRESS(ROW('Offer Comparison'!C13),COLUMN('Offer Comparison'!C13),4)&"). Keystone valued at "&TEXT(C22,"0.0")&"x revenue"&" today (offer implies "&"~"&TEXT(C173/C172,"0.0")&"x"&")" -> Linked to Offer Comparison (C13). Keystone valued at 1.0x revenue today (offer implies ~1.0x)
B23: Scaled Revenue Multiple | C23: ='Offer Comparison'!$C$14 -> 1.25 | F23: ="Linked to Offer Comparison ("&ADDRESS(ROW('Offer Comparison'!C14),COLUMN('Offer Comparison'!C14),4)&"). Keystone standalone revenue multiple at Year "&$C$9 -> Linked to Offer Comparison (C14). Keystone standalone revenue multiple at Year 5
B24: Avg. Revenue Per Client | C24: ='Offer Comparison'!$C$22 -> 16.631473 | F24: ="Input on Offer Comparison ("&ADDRESS(ROW('Offer Comparison'!C22),COLUMN('Offer Comparison'!C22),4)&"). Sep'26 annualized fee per non-tax client (Steady-State Staffing AB8)" -> Input on Offer Comparison (C22). Sep'26 annualized fee per non-tax client (Steady-State Staffing AB8)
B25: Target Monthly Net Client Wins | C25: ='Offer Comparison'!$C$23 -> 3 | F25: ="Input on Offer Comparison ("&ADDRESS(ROW('Offer Comparison'!C23),COLUMN('Offer Comparison'!C23),4)&"). AMB target pace; LTM actual is "&TEXT(C192,"0")&"/yr (~"&TEXT(C192/12,"0.0")&"/month)"&", see build at rows "&ROW($B$188)&"-"&ROW($B$192) -> Input on Offer Comparison (C23). AMB target pace; LTM actual is 26/yr (~2.2/month), see build at rows 188-192
B26: Annual Net Client Wins | C26: =C25*12 -> 36 | F26: Target monthly pace × 12
B27: Total Net Client Wins | C27: =C26*$C$9 -> 180
B28: Total Additional Revenue | C28: =C27*C24 -> 2993.6651
B30: Keystone Partnership Assumptions
B31: Software-Integration Revenue Multiple | C31: ='Offer Comparison'!$C$15 -> 2 | F31: ="Linked to Offer Comparison ("&ADDRESS(ROW('Offer Comparison'!C15),COLUMN('Offer Comparison'!C15),4)&"). Revenue multiple with Topkey software integration" -> Linked to Offer Comparison (C15). Revenue multiple with Topkey software integration
B32: VR Platform Run-Rate Tech Cost | C32: ='Offer Comparison'!$C$25 -> 240 | F32: ="Input on Offer Comparison ("&ADDRESS(ROW('Offer Comparison'!C25),COLUMN('Offer Comparison'!C25),4)&"). Run-rate tech cost provided by the target; see platform-fee memo (rows "&ROW($B$195)&"-"&ROW($B$204)&")" -> Input on Offer Comparison (C25). Run-rate tech cost provided by the target; see platform-fee memo (rows 195-204)
B34: =B24 -> Avg. Revenue Per Client | C34: =C24 -> 16.631473
B36: =+B26 -> Annual Net Client Wins | C36: =+C26 -> 36
B37: (+) Additional Annual Net Client Wins From Topkey | C37: ='Offer Comparison'!$C$26 -> 12 | F37: ="Input on Offer Comparison ("&ADDRESS(ROW('Offer Comparison'!C26),COLUMN('Offer Comparison'!C26),4)&"). Topkey-provided; pending confirmation" -> Input on Offer Comparison (C26). Topkey-provided; pending confirmation
B38: Total Annual Net Client Wins | C38: =SUM(C36:C37) -> 48
B39: Total Net Client Wins | C39: =C38*$C$9 -> 240
B40: Total Additional Revenue | C40: =C39*C34 -> 3991.5535
B41: Increase in Keystone Revenue vs. Standalone | C41: =C40-C28 -> 997.88838
B43: Cash Earnout — Year 3 Keystone Revenue (Sliding Scale)
B44: Earnout Measurement Year | C44: 3 | F44: ="Earnout measured on Year "&$C$44&" run-rate: average of "&"months "&TEXT($C$44*12-$C$55+1,"0")&"–"&TEXT($C$44*12,"0")&" × 12 (window in "&ADDRESS(ROW(C55),COLUMN(C55),4)&")" -> Earnout measured on Year 3 run-rate: average of months 34–36 × 12 (window in C55)
B45: Keystone Revenue at Close | C45: =C172 -> 2998.541 | F45: ="PF Jul'26 run-rate revenue at close ("&ADDRESS(ROW(C172),COLUMN(C172),4)&")" -> PF Jul'26 run-rate revenue at close (C172)
B46: Year 3 Run-Rate Revenue Target | C46: =C45+C40*(C44-(C55-1)/2/12)/C9 -> 5326.9472 | F46: ="Run-rate at close + partnership added revenue ramped to the midpoint of the averaging window "&"(month "&ROUND($C$44*12-($C$55-1)/2,1)&" ÷ "&$C$9*12&")"&"; same basis as the earnout measurement" -> Run-rate at close + partnership added revenue ramped to the midpoint of the averaging window (month 35 ÷ 60); same basis as the earnout measurement
B47: (x) Achievement vs. Target | C47: 1 | F47: ="Base case assumes the model's Year "&$C$44&" revenue is achieved; flex to test payout" -> Base case assumes the model's Year 3 revenue is achieved; flex to test payout
B48: Year 3 Run-Rate Revenue — Achieved | C48: =C46*C47 -> 5326.9472
B49: Threshold — % of Target | C49: 0.8 | F49: No earnout below this share of target; payout starts at the threshold % below
B50: Target Earnout — at 100% of Target | C50: 0 | F50: Initial position does not include earnout
B51: Payout at Threshold — % of Target Earnout | C51: 0.5 | F51: ="Share of target earnout paid at the "&TEXT(C49,"0%")&" threshold" -> Share of target earnout paid at the 80% threshold
B52: Cap — % of Target Earnout | C52: 1.5 | F52: ="Payout capped at "&TEXT(C52,"0%")&" of target earnout, reached at "&TEXT(C49+(C52-C51)*(1-C49)/(1-C51),"0%")&" of target revenue (mirrors the "&TEXT(C49,"0%")&" threshold)" -> Payout capped at 150% of target earnout, reached at 120% of target revenue (mirrors the 80% threshold)
B53: Payout % Earned | C53: =IF(C47<C49,0,MIN(C52,C51+(1-C51)*(C47-C49)/(1-C49))) -> 1 | F53: ="Straight line from threshold payout at "&TEXT(C49,"0%")&" to 100% at target, continuing above target until the cap" -> Straight line from threshold payout at 80% to 100% at target, continuing above target until the cap
B54: Maximum Earnout (Cap) | C54: =C50*C52 -> 0 | F54: Topkey's maximum earnout exposure
B55: Run-Rate Window — Months Averaged | C55: 3 | F55: ="Earnout measured on average monthly recurring revenue for the "&"last "&C55&" months"&" of Year "&$C$44&" "&"(months "&TEXT($C$44*12-$C$55+1,"0")&"–"&TEXT($C$44*12,"0")&")"&" × 12; averaging prevents one strong month from triggering the payout" -> Earnout measured on average monthly recurring revenue for the last 3 months of Year 3 (months 34–36) × 12; averaging prevents one strong month from triggering the payout
B56: Cash Earnout Payable — Year 3 | C56: =C50*C53 -> 0 | F56: ="Paid in cash by Topkey; flows into Scenario 2 (row "&ROW($B$89)&"), Ben's MOIC/IRR (rows "&ROW($B$95)&"-"&ROW($B$96)&") and Topkey's return (row "&ROW($B$103)&")" -> Paid in cash by Topkey; flows into Scenario 2 (row 89), Ben's MOIC/IRR (rows 95-96) and Topkey's return (row 103)
B57: Probability of Achievement | C57: 0.7 | F57: AMB estimate for the memo line below
B58: Discount Rate | C58: 0.15 | F58: AMB estimate for the memo line below
B59: Risk-Weighted Earnout — PV at Close (Memo) | C59: =C56*C57/(1+C58)^C44 -> 0 | F59: Memo only; not used in Scenario 2
B61: Offer Structure | C61: =C$171 -> Today | D61: % of Total
B62: Cash at Close | C62: =$C$177 -> 650 | D62: =IFERROR(C62/C$65,0) -> 0.21666667 | F62: ="Cash paid at close for Topkey's stake ("&ADDRESS(ROW(C177),COLUMN(C177),4)&")" -> Cash paid at close for Topkey's stake (C177)
B63: (+) Topkey Equity Issued to Ben | C63: =$C$178 -> 1450 | D63: =IFERROR(C63/C$65,0) -> 0.48333333 | F63: ="Topkey stock issued at the "&TEXT(C179/1000,"$#,##0")&"M"&" pre-deal valuation ("&ADDRESS(ROW(C178),COLUMN(C178),4)&")" -> Topkey stock issued at the $60M pre-deal valuation (C178)
B64: (+) Ben's Rolled Keystone Equity | C64: =$C$173*$C$174 -> 900 | D64: =IFERROR(C64/C$65,0) -> 0.3 | F64: ="Keystone value today × Ben's rollover % ("&ADDRESS(ROW(C173),COLUMN(C173),4)&" × "&ADDRESS(ROW(C174),COLUMN(C174),4)&")" -> Keystone value today × Ben's rollover % (C173 × C174)
B65: Total Offer Value — at Close | C65: =SUM(C62:C64) -> 3000 | D65: =IFERROR(C65/C$65,0) -> 1 | F65: ="Ties to Keystone Value Today ("&ADDRESS(ROW(C173),COLUMN(C173),4)&")" -> Ties to Keystone Value Today (C173)
B66: (+) Cash Earnout — Year 3 (Contingent) | C66: =$C$56 -> 0 | D66: =IFERROR(C66/C$65,0) -> 0 | F66: ="Paid only if Year "&$C$44&" revenue target is met ("&ADDRESS(ROW(C56),COLUMN(C56),4)&"); % shown vs. offer value at close" -> Paid only if Year 3 revenue target is met (C56); % shown vs. offer value at close
B67: Total Consideration incl. Earnout | C67: =C65+C66 -> 3000 | D67: =IFERROR(C67/C$65,0) -> 1
B69: Scenario 1 — Ben Retains 100% of Keystone | C69: =C$171 -> Today | D69: ="Year "&$C$9 -> Year 5
B70: Keystone Enterprise Value | C70: =ROUND(C172*C22,-1) -> 3000 | D70: =(C172+C28)*$C$23 -> 7490.2577 | F70: ="Today at offer value; Year "&$C$9&" = (PF run-rate revenue + standalone added revenue) × standalone multiple" -> Today at offer value; Year 5 = (PF run-rate revenue + standalone added revenue) × standalone multiple
B71: Ben's Ownership % — Keystone | C71: ='Offer Comparison'!$C$153 -> 1 | D71: =$C$71 -> 1
B72: Ben's Value — Scenario 1 | C72: =C70*C71 -> 3000 | D72: =D70*D71 -> 7490.2577
B74: ="Scenario 2 — Ben Rolls "&TEXT($C$174,"0%")&" of Keystone Equity" -> Scenario 2 — Ben Rolls 30% of Keystone Equity | C74: =C$171 -> Today | D74: =D$69 -> Year 5
B75: Keystone Enterprise Value — Partnership | C75: =C173 -> 3000 | D75: =(C40+C172)*C31 -> 13980.189 | F75: ="Today at offer value; Year "&$C$9&" = partnership revenue × software-integration multiple ("&ADDRESS(ROW(C31),COLUMN(C31),4)&")" -> Today at offer value; Year 5 = partnership revenue × software-integration multiple (C31)
B76: (x) Ben's Retained Keystone % | C76: =$C$174 -> 0.3 | D76: =$C$174 -> 0.3
B77: Ben's Keystone Equity Value | C77: =C75*C76 -> 900 | D77: =D75*D76 -> 4194.0567 | F77: Ben's retained Keystone stake (rollover % × Keystone value)
B79: Topkey ex-Keystone Value | C79: =C182 -> 59350 | D79: =(C11+C18)*C13-$C$177-$C$56 -> 179350
B80: (+) Topkey's Share of Keystone Value | C80: =C75*$C$175 -> 2100 | D80: =D75*$C$175 -> 9786.1324 | F80: Topkey's stake in Keystone is part of Topkey's value
B81: Topkey Combined Enterprise Value | C81: =C79+C80 -> 61450 | D81: =D79+D80 -> 189136.13
B82: (x) Ben's Topkey Ownership % | C82: =$C$181 -> 0.02359642 | D82: =$D$181 -> 0.022416599
B83: Ben's Topkey Equity Value | C83: =C81*C82 -> 1450 | D83: =D81*D82 -> 4239.7888 | F83: ="Ties to Topkey equity issued (tie-out row "&ROW($B$184)&")" -> Ties to Topkey equity issued (tie-out row 184)
B84: Ben's Value by Source
B85: Keystone — Ben's Direct Retained Stake | C85: =C77 -> 900 | D85: =D77 -> 4194.0567 | F85: Keystone value Ben owns directly
B86: (+) Keystone — Ben's Indirect Share via Topkey | C86: =C80*C82 -> 49.552482 | D86: =D80*D82 -> 219.3718 | F86: Ben's Topkey % × Topkey's Keystone stake
B87: (+) Topkey ex-Keystone — Ben's Share | C87: =C79*C82 -> 1400.4475 | D87: =D79*D82 -> 4020.417 | F87: Ben's Topkey % × Topkey's own business
B88: (+) Cash at Close | C88: =$C$177 -> 650 | D88: =$C$177 -> 650
B89: (+) Cash Earnout — Year 3 | D89: =$C$56 -> 0
B90: Ben's Value — Scenario 2 | C90: =SUM(C85:C89) -> 3000 | D90: =SUM(D85:D89) -> 9083.8455 | F90: Direct Keystone + indirect Keystone + Topkey + cash
B92: Scenario 2 vs. Scenario 1 | C92: =C$171 -> Today | D92: =D$69 -> Year 5
B93: Increase in Proceeds | C93: =C90-C72 -> 0 | D93: =D90-D72 -> 1593.5878
B94: Delta (%) | C94: 0 | D94: =IFERROR(D90/D72-1,0) -> 0.21275474
B95: Partnership MOIC — Keystone (Ben) | D95: =IFERROR(D90/C173,0) -> 3.0279485 | F95: ="Ben's Year "&$C$9&" value ("&ADDRESS(ROW(D90),COLUMN(D90),4)&": cash + earnout + retained stake + Topkey stock) ÷ Keystone value given up at close ("&ADDRESS(ROW(C173),COLUMN(C173),4)&")" -> Ben's Year 5 value (D90: cash + earnout + retained stake + Topkey stock) ÷ Keystone value given up at close (C173)
B96: Partnership IRR — Keystone (Ben) | D96: =IFERROR(IRR(D215:D220),0) -> 0.29119417 | F96: ="IRR on Ben's cash flows (rows "&ROW($B$215)&"-"&ROW($B$220)&"); Year "&$C$9&" = stake values, not a cash exit" -> IRR on Ben's cash flows (rows 215-220); Year 5 = stake values, not a cash exit
B97: Break-Even Topkey Value CAGR (ex-Keystone, Net of Cash) | C97: 0 | D97: =MAX(0,IFERROR(((C135+$C$56)/$C$182)^(1/$C$9)-1,0)) -> 0.12774199 | F97: ="Topkey value CAGR needed for Scenario 2 to equal Scenario 1 (from required value in "&ADDRESS(ROW(C135),COLUMN(C135),4)&", before earnout paid); floored at zero" -> Topkey value CAGR needed for Scenario 2 to equal Scenario 1 (from required value in C135, before earnout paid); floored at zero
B98: Estimated Topkey Value CAGR (ex-Keystone, Net of Cash) | C98: 0 | D98: =IFERROR(((D79+$C$56)/$C$182)^(1/$C$9)-1,0) -> 0.24754475
B100: Topkey's Return on the Keystone Stake | C100: Value
B101: Cash Paid at Close | C101: =C177 -> 650 | F101: ="Cash portion of stake price ("&ADDRESS(ROW(C177),COLUMN(C177),4)&")" -> Cash portion of stake price (C177)
B102: (+) Topkey Equity Issued to Ben | C102: =C178 -> 1450 | F102: ="Topkey stock issued, at issue value ("&ADDRESS(ROW(C178),COLUMN(C178),4)&")" -> Topkey stock issued, at issue value (C178)
B103: (+) Cash Earnout — Year 3 | C103: =C56 -> 0 | F103: ="Cash earnout at base-case achievement ("&ADDRESS(ROW(C56),COLUMN(C56),4)&")" -> Cash earnout at base-case achievement (C56)
B104: Total Consideration Paid by Topkey | C104: =SUM(C101:C103) -> 2100 | F104: Everything Topkey gives up for its Keystone stake
B105: (x) Topkey's Keystone Stake % | C105: =C175 -> 0.7 | F105: ="Topkey's share of Keystone ("&ADDRESS(ROW(C175),COLUMN(C175),4)&")" -> Topkey's share of Keystone (C175)
B106: Keystone Enterprise Value — Year 5 | C106: =D75 -> 13980.189 | F106: ="Year "&$C$9&" partnership value of 100% of Keystone ("&ADDRESS(ROW(D75),COLUMN(D75),4)&")" -> Year 5 partnership value of 100% of Keystone (D75)
B107: Value of Topkey's Keystone Stake — Year 5 | C107: =C105*C106 -> 9786.1324 | F107: ="Topkey's stake % × Keystone Year "&$C$9&" value; ties to Scenario 2 ("&ADDRESS(ROW(D80),COLUMN(D80),4)&")" -> Topkey's stake % × Keystone Year 5 value; ties to Scenario 2 (D80)
B108: MOIC — Topkey | C108: =IFERROR(C107/C104,0) -> 4.660063 | F108: ="Year "&$C$9&" stake value ÷ total consideration" -> Year 5 stake value ÷ total consideration
B109: IRR — Topkey | C109: =IFERROR(IRR(D207:D212),0) -> 0.36043676 | F109: ="IRR on Topkey's cash flows (rows "&ROW($B$207)&"-"&ROW($B$212)&"); excludes software fee income and Keystone distributions, so understated" -> IRR on Topkey's cash flows (rows 207-212); excludes software fee income and Keystone distributions, so understated
B111: Internal - Implied Keystone Standalone Multiple | C111: =D$69 -> Year 5
B112: Year 5 Keystone Standalone Revenue | C112: =+C28+C172 -> 5992.2062
B113: (x) Steady-State Margins | C113: 0.15 | F113: Assumed steady-state EBITDA margin
B114: Year 5 EBITDA | C114: =C113*C112 -> 898.83092
...

Sheet Partnership Tables
B2: =Cover!$B$24 -> Keystone Bookkeepers
B3: Partnership Sensitivity Tables ($000s) | N3: Print | O3: 1
B5: Ben's Return Profile Based on Partnering
B6: Ben's Net Returns Based on Topkey Growth & Rollover %
D8: Topkey ex-Keystone Value Growth (%) | S8: Helper: IRR Year Index | Z8: Helper: Unrounded Net Return
D9: =E9-$G$441 -> 1.021904 | E9: =F9-$G$441 -> 1.271904 | F9: =G9-$G$441 -> 1.521904 | G9: =H9-$G$441 -> 1.771904 | H9: =$G$440 -> 2.021904 | I9: =H9+$G$441 -> 2.271904 | J9: =I9+$G$441 -> 2.521904 | K9: =J9+$G$441 -> 2.771904 | L9: =K9+$G$441 -> 3.021904 | N9: Helper: Rollover % | O9: Helper: Cash at Close | P9: Helper: Topkey Equity Issued | Q9: Helper: Topkey ex-Keystone Today | R9: Helper: Ben's Yr 5 Topkey % | S9: 0 | T9: =S9+1 -> 1 | U9: =T9+1 -> 2 | V9: =U9+1 -> 3 | W9: =V9+1 -> 4 | X9: =W9+1 -> 5 | Z9: =D$9 -> 1.021904 | AA9: =E$9 -> 1.271904 | AB9: =F$9 -> 1.521904 | AC9: =G$9 -> 1.771904 | AD9: =H$9 -> 2.021904 | AE9: =I$9 -> 2.271904 | AF9: =J$9 -> 2.521904 | AG9: =K$9 -> 2.771904 | AH9: =L$9 -> 3.021904 | AT9: Helper: Gradient Band (0 = below $1M hurdle)
B10: Ben's Rollover % | C10: =C11-$G$439 -> 0.15 | D10: =ROUND(Z10,$G$452) -> 3600 | E10: =ROUND(AA10,$G$452) -> 4000 | F10: =ROUND(AB10,$G$452) -> 4500 | G10: =ROUND(AC10,$G$452) -> 4900 | H10: =ROUND(AD10,$G$452) -> 5300 | I10: =ROUND(AE10,$G$452) -> 5800 | J10: =ROUND(AF10,$G$452) -> 6200 | K10: =ROUND(AG10,$G$452) -> 6600 | L10: =ROUND(AH10,$G$452) -> 7100 | N10: =$C10 -> 0.15 | O10: =$G$433 -> 650 | P10: =$G$430*(1-N10)-O10 -> 1900 | Q10: =$G$432-O10 -> 59350 | R10: =IFERROR(P10/(Q10+$G$430*(1-N10)),0)*(1-$G$434) -> 0.029159935 | Z10: =$O10+$G$435+$N10*$G$431+$R10*($Q10*(1+D$9)+$G$431*(1-$N10))-$G$430 -> 3592.7328 | AA10: =$O10+$G$435+$N10*$G$431+$R10*($Q10*(1+E$9)+$G$431*(1-$N10))-$G$430 -> 4025.3933 | AB10: =$O10+$G$435+$N10*$G$431+$R10*($Q10*(1+F$9)+$G$431*(1-$N10))-$G$430 -> 4458.0539 | AC10: =$O10+$G$435+$N10*$G$431+$R10*($Q10*(1+G$9)+$G$431*(1-$N10))-$G$430 -> 4890.7144 | AD10: =$O10+$G$435+$N10*$G$431+$R10*($Q10*(1+H$9)+$G$431*(1-$N10))-$G$430 -> 5323.375 | AE10: =$O10+$G$435+$N10*$G$431+$R10*($Q10*(1+I$9)+$G$431*(1-$N10))-$G$430 -> 5756.0355 | AF10: =$O10+$G$435+$N10*$G$431+$R10*($Q10*(1+J$9)+$G$431*(1-$N10))-$G$430 -> 6188.6961 | AG10: =$O10+$G$435+$N10*$G$431+$R10*($Q10*(1+K$9)+$G$431*(1-$N10))-$G$430 -> 6621.3566 | AH10: =$O10+$G$435+$N10*$G$431+$R10*($Q10*(1+L$9)+$G$431*(1-$N10))-$G$430 -> 7054.0171 | AT10: =IF(Z50<$G$449,0,MIN($G$446,1+IFERROR(INT((Z50-$G$449)/$G$451),0))) -> 0 | AU10: =IF(AA50<$G$449,0,MIN($G$446,1+IFERROR(INT((AA50-$G$449)/$G$451),0))) -> 0 | AV10: =IF(AB50<$G$449,0,MIN($G$446,1+IFERROR(INT((AB50-$G$449)/$G$451),0))) -> 0 | AW10: =IF(AC50<$G$449,0,MIN($G$446,1+IFERROR(INT((AC50-$G$449)/$G$451),0))) -> 0 | AX10: =IF(AD50<$G$449,0,MIN($G$446,1+IFERROR(INT((AD50-$G$449)/$G$451),0))) -> 0 | AY10: =IF(AE50<$G$449,0,MIN($G$446,1+IFERROR(INT((AE50-$G$449)/$G$451),0))) -> 2 | AZ10: =IF(AF50<$G$449,0,MIN($G$446,1+IFERROR(INT((AF50-$G$449)/$G$451),0))) -> 4 | BA10: =IF(AG50<$G$449,0,MIN($G$446,1+IFERROR(INT((AG50-$G$449)/$G$451),0))) -> 5 | BB10: =IF(AH50<$G$449,0,MIN($G$446,1+IFERROR(INT((AH50-$G$449)/$G$451),0))) -> 7
C11: =C12-$G$439 -> 0.2 | D11: =ROUND(Z11,$G$452) -> 4000 | E11: =ROUND(AA11,$G$452) -> 4400 | F11: =ROUND(AB11,$G$452) -> 4800 | G11: =ROUND(AC11,$G$452) -> 5200 | H11: =ROUND(AD11,$G$452) -> 5600 | I11: =ROUND(AE11,$G$452) -> 6000 | J11: =ROUND(AF11,$G$452) -> 6400 | K11: =ROUND(AG11,$G$452) -> 6800 | L11: =ROUND(AH11,$G$452) -> 7200 | N11: =$C11 -> 0.2 | O11: =$G$433 -> 650 | P11: =$G$430*(1-N11)-O11 -> 1750 | Q11: =$G$432-O11 -> 59350 | R11: =IFERROR(P11/(Q11+$G$430*(1-N11)),0)*(1-$G$434) -> 0.026923077 | Z11: =$O11+$G$435+$N11*$G$431+$R11*($Q11*(1+D$9)+$G$431*(1-$N11))-$G$430 -> 3977.9188 | AA11: =$O11+$G$435+$N11*$G$431+$R11*($Q11*(1+E$9)+$G$431*(1-$N11))-$G$430 -> 4377.39 | AB11: =$O11+$G$435+$N11*$G$431+$R11*($Q11*(1+F$9)+$G$431*(1-$N11))-$G$430 -> 4776.8611 | AC11: =$O11+$G$435+$N11*$G$431+$R11*($Q11*(1+G$9)+$G$431*(1-$N11))-$G$430 -> 5176.3323 | AD11: =$O11+$G$435+$N11*$G$431+$R11*($Q11*(1+H$9)+$G$431*(1-$N11))-$G$430 -> 5575.8034 | AE11: =$O11+$G$435+$N11*$G$431+$R11*($Q11*(1+I$9)+$G$431*(1-$N11))-$G$430 -> 5975.2746 | AF11: =$O11+$G$435+$N11*$G$431+$R11*($Q11*(1+J$9)+$G$431*(1-$N11))-$G$430 -> 6374.7457 | AG11: =$O11+$G$435+$N11*$G$431+$R11*($Q11*(1+K$9)+$G$431*(1-$N11))-$G$430 -> 6774.2169 | AH11: =$O11+$G$435+$N11*$G$431+$R11*($Q11*(1+L$9)+$G$431*(1-$N11))-$G$430 -> 7173.688 | AT11: =IF(Z51<$G$449,0,MIN($G$446,1+IFERROR(INT((Z51-$G$449)/$G$451),0))) -> 0 | AU11: =IF(AA51<$G$449,0,MIN($G$446,1+IFERROR(INT((AA51-$G$449)/$G$451),0))) -> 0 | AV11: =IF(AB51<$G$449,0,MIN($G$446,1+IFERROR(INT((AB51-$G$449)/$G$451),0))) -> 0 | AW11: =IF(AC51<$G$449,0,MIN($G$446,1+IFERROR(INT((AC51-$G$449)/$G$451),0))) -> 0 | AX11: =IF(AD51<$G$449,0,MIN($G$446,1+IFERROR(INT((AD51-$G$449)/$G$451),0))) -> 1 | AY11: =IF(AE51<$G$449,0,MIN($G$446,1+IFERROR(INT((AE51-$G$449)/$G$451),0))) -> 3 | AZ11: =IF(AF51<$G$449,0,MIN($G$446,1+IFERROR(INT((AF51-$G$449)/$G$451),0))) -> 4 | BA11: =IF(AG51<$G$449,0,MIN($G$446,1+IFERROR(INT((AG51-$G$449)/$G$451),0))) -> 6 | BB11: =IF(AH51<$G$449,0,MIN($G$446,1+IFERROR(INT((AH51-$G$449)/$G$451),0))) -> 8
C12: =C13-$G$439 -> 0.25 | D12: =ROUND(Z12,$G$452) -> 4400 | E12: =ROUND(AA12,$G$452) -> 4700 | F12: =ROUND(AB12,$G$452) -> 5100 | G12: =ROUND(AC12,$G$452) -> 5500 | H12: =ROUND(AD12,$G$452) -> 5800 | I12: =ROUND(AE12,$G$452) -> 6200 | J12: =ROUND(AF12,$G$452) -> 6600 | K12: =ROUND(AG12,$G$452) -> 6900 | L12: =ROUND(AH12,$G$452) -> 7300 | N12: =$C12 -> 0.25 | O12: =$G$433 -> 650 | P12: =$G$430*(1-N12)-O12 -> 1600 | Q12: =$G$432-O12 -> 59350 | R12: =IFERROR(P12/(Q12+$G$430*(1-N12)),0)*(1-$G$434) -> 0.024675325 | Z12: =$O12+$G$435+$N12*$G$431+$R12*($Q12*(1+D$9)+$G$431*(1-$N12))-$G$430 -> 4364.8105 | AA12: =$O12+$G$435+$N12*$G$431+$R12*($Q12*(1+E$9)+$G$431*(1-$N12))-$G$430 -> 4730.9306 | AB12: =$O12+$G$435+$N12*$G$431+$R12*($Q12*(1+F$9)+$G$431*(1-$N12))-$G$430 -> 5097.0508 | AC12: =$O12+$G$435+$N12*$G$431+$R12*($Q12*(1+G$9)+$G$431*(1-$N12))-$G$430 -> 5463.1709 | AD12: =$O12+$G$435+$N12*$G$431+$R12*($Q12*(1+H$9)+$G$431*(1-$N12))-$G$430 -> 5829.291 | AE12: =$O12+$G$435+$N12*$G$431+$R12*($Q12*(1+I$9)+$G$431*(1-$N12))-$G$430 -> 6195.4112 | AF12: =$O12+$G$435+$N12*$G$431+$R12*($Q12*(1+J$9)+$G$431*(1-$N12))-$G$430 -> 6561.5313 | AG12: =$O12+$G$435+$N12*$G$431+$R12*($Q12*(1+K$9)+$G$431*(1-$N12))-$G$430 -> 6927.6514 | AH12: =$O12+$G$435+$N12*$G$431+$R12*($Q12*(1+L$9)+$G$431*(1-$N12))-$G$430 -> 7293.7715 | AT12: =IF(Z52<$G$449,0,MIN($G$446,1+IFERROR(INT((Z52-$G$449)/$G$451),0))) -> 0 | AU12: =IF(AA52<$G$449,0,MIN($G$446,1+IFERROR(INT((AA52-$G$449)/$G$451),0))) -> 0 | AV12: =IF(AB52<$G$449,0,MIN($G$446,1+IFERROR(INT((AB52-$G$449)/$G$451),0))) -> 0 | AW12: =IF(AC52<$G$449,0,MIN($G$446,1+IFERROR(INT((AC52-$G$449)/$G$451),0))) -> 0 | AX12: =IF(AD52<$G$449,0,MIN($G$446,1+IFERROR(INT((AD52-$G$449)/$G$451),0))) -> 2 | AY12: =IF(AE52<$G$449,0,MIN($G$446,1+IFERROR(INT((AE52-$G$449)/$G$451),0))) -> 4 | AZ12: =IF(AF52<$G$449,0,MIN($G$446,1+IFERROR(INT((AF52-$G$449)/$G$451),0))) -> 5 | BA12: =IF(AG52<$G$449,0,MIN($G$446,1+IFERROR(INT((AG52-$G$449)/$G$451),0))) -> 7 | BB12: =IF(AH52<$G$449,0,MIN($G$446,1+IFERROR(INT((AH52-$G$449)/$G$451),0))) -> 8
C13: =$G$438 -> 0.3 | D13: =ROUND(Z13,$G$452) -> 4800 | E13: =ROUND(AA13,$G$452) -> 5100 | F13: =ROUND(AB13,$G$452) -> 5400 | G13: =ROUND(AC13,$G$452) -> 5800 | H13: =ROUND(AD13,$G$452) -> 6100 | I13: =ROUND(AE13,$G$452) -> 6400 | J13: =ROUND(AF13,$G$452) -> 6700 | K13: =ROUND(AG13,$G$452) -> 7100 | L13: =ROUND(AH13,$G$452) -> 7400 | N13: =$C13 -> 0.3 | O13: =$G$433 -> 650 | P13: =$G$430*(1-N13)-O13 -> 1450 | Q13: =$G$432-O13 -> 59350 | R13: =IFERROR(P13/(Q13+$G$430*(1-N13)),0)*(1-$G$434) -> 0.022416599 | Z13: =$O13+$G$435+$N13*$G$431+$R13*($Q13*(1+D$9)+$G$431*(1-$N13))-$G$430 -> 4753.4204 | AA13: =$O13+$G$435+$N13*$G$431+$R13*($Q13*(1+E$9)+$G$431*(1-$N13))-$G$430 -> 5086.0267 | AB13: =$O13+$G$435+$N13*$G$431+$R13*($Q13*(1+F$9)+$G$431*(1-$N13))-$G$430 -> 5418.633 | AC13: =$O13+$G$435+$N13*$G$431+$R13*($Q13*(1+G$9)+$G$431*(1-$N13))-$G$430 -> 5751.2392 | AD13: =$O13+$G$435+$N13*$G$431+$R13*($Q13*(1+H$9)+$G$431*(1-$N13))-$G$430 -> 6083.8455 | AE13: =$O13+$G$435+$N13*$G$431+$R13*($Q13*(1+I$9)+$G$431*(1-$N13))-$G$430 -> 6416.4518 | AF13: =$O13+$G$435+$N13*$G$431+$R13*($Q13*(1+J$9)+$G$431*(1-$N13))-$G$430 -> 6749.0581 | AG13: =$O13+$G$435+$N13*$G$431+$R13*($Q13*(1+K$9)+$G$431*(1-$N13))-$G$430 -> 7081.6644 | AH13: =$O13+$G$435+$N13*$G$431+$R13*($Q13*(1+L$9)+$G$431*(1-$N13))-$G$430 -> 7414.2707 | AT13: =IF(Z53<$G$449,0,MIN($G$446,1+IFERROR(INT((Z53-$G$449)/$G$451),0))) -> 0 | AU13: =IF(AA53<$G$449,0,MIN($G$446,1+IFERROR(INT((AA53-$G$449)/$G$451),0))) -> 0 | AV13: =IF(AB53<$G$449,0,MIN($G$446,1+IFERROR(INT((AB53-$G$449)/$G$451),0))) -> 0 | AW13: =IF(AC53<$G$449,0,MIN($G$446,1+IFERROR(INT((AC53-$G$449)/$G$451),0))) -> 2 | AX13: =IF(AD53<$G$449,0,MIN($G$446,1+IFERROR(INT((AD53-$G$449)/$G$451),0))) -> 3 | AY13: =IF(AE53<$G$449,0,MIN($G$446,1+IFERROR(INT((AE53-$G$449)/$G$451),0))) -> 5 | AZ13: =IF(AF53<$G$449,0,MIN($G$446,1+IFERROR(INT((AF53-$G$449)/$G$451),0))) -> 6 | BA13: =IF(AG53<$G$449,0,MIN($G$446,1+IFERROR(INT((AG53-$G$449)/$G$451),0))) -> 7 | BB13: =IF(AH53<$G$449,0,MIN($G$446,1+IFERROR(INT((AH53-$G$449)/$G$451),0))) -> 9
C14: =C13+$G$439 -> 0.35 | D14: =ROUND(Z14,$G$452) -> 5100 | E14: =ROUND(AA14,$G$452) -> 5400 | F14: =ROUND(AB14,$G$452) -> 5700 | G14: =ROUND(AC14,$G$452) -> 6000 | H14: =ROUND(AD14,$G$452) -> 6300 | I14: =ROUND(AE14,$G$452) -> 6600 | J14: =ROUND(AF14,$G$452) -> 6900 | K14: =ROUND(AG14,$G$452) -> 7200 | L14: =ROUND(AH14,$G$452) -> 7500 | N14: =$C14 -> 0.35 | O14: =$G$433 -> 650 | P14: =$G$430*(1-N14)-O14 -> 1300 | Q14: =$G$432-O14 -> 59350 | R14: =IFERROR(P14/(Q14+$G$430*(1-N14)),0)*(1-$G$434) -> 0.020146819 | Z14: =$O14+$G$435+$N14*$G$431+$R14*($Q14*(1+D$9)+$G$431*(1-$N14))-$G$430 -> 5143.7611 | AA14: =$O14+$G$435+$N14*$G$431+$R14*($Q14*(1+E$9)+$G$431*(1-$N14))-$G$430 -> 5442.6895 | AB14: =$O14+$G$435+$N14*$G$431+$R14*($Q14*(1+F$9)+$G$431*(1-$N14))-$G$430 -> 5741.6179 | AC14: =$O14+$G$435+$N14*$G$431+$R14*($Q14*(1+G$9)+$G$431*(1-$N14))-$G$430 -> 6040.5463 | AD14: =$O14+$G$435+$N14*$G$431+$R14*($Q14*(1+H$9)+$G$431*(1-$N14))-$G$430 -> 6339.4748 | AE14: =$O14+$G$435+$N14*$G$431+$R14*($Q14*(1+I$9)+$G$431*(1-$N14))-$G$430 -> 6638.4032 | AF14: =$O14+$G$435+$N14*$G$431+$R14*($Q14*(1+J$9)+$G$431*(1-$N14))-$G$430 -> 6937.3316 | AG14: =$O14+$G$435+$N14*$G$431+$R14*($Q14*(1+K$9)+$G$431*(1-$N14))-$G$430 -> 7236.26 | AH14: =$O14+$G$435+$N14*$G$431+$R14*($Q14*(1+L$9)+$G$431*(1-$N14))-$G$430 -> 7535.1885 | AT14: =IF(Z54<$G$449,0,MIN($G$446,1+IFERROR(INT((Z54-$G$449)/$G$451),0))) -> 0 | AU14: =IF(AA54<$G$449,0,MIN($G$446,1+IFERROR(INT((AA54-$G$449)/$G$451),0))) -> 0 | AV14: =IF(AB54<$G$449,0,MIN($G$446,1+IFERROR(INT((AB54-$G$449)/$G$451),0))) -> 2 | AW14: =IF(AC54<$G$449,0,MIN($G$446,1+IFERROR(INT((AC54-$G$449)/$G$451),0))) -> 3 | AX14: =IF(AD54<$G$449,0,MIN($G$446,1+IFERROR(INT((AD54-$G$449)/$G$451),0))) -> 4 | AY14: =IF(AE54<$G$449,0,MIN($G$446,1+IFERROR(INT((AE54-$G$449)/$G$451),0))) -> 6 | AZ14: =IF(AF54<$G$449,0,MIN($G$446,1+IFERROR(INT((AF54-$G$449)/$G$451),0))) -> 7 | BA14: =IF(AG54<$G$449,0,MIN($G$446,1+IFERROR(INT((AG54-$G$449)/$G$451),0))) -> 8 | BB14: =IF(AH54<$G$449,0,MIN($G$446,1+IFERROR(INT((AH54-$G$449)/$G$451),0))) -> 9
C15: =C14+$G$439 -> 0.4 | D15: =ROUND(Z15,$G$452) -> 5500 | E15: =ROUND(AA15,$G$452) -> 5800 | F15: =ROUND(AB15,$G$452) -> 6100 | G15: =ROUND(AC15,$G$452) -> 6300 | H15: =ROUND(AD15,$G$452) -> 6600 | I15: =ROUND(AE15,$G$452) -> 6900 | J15: =ROUND(AF15,$G$452) -> 7100 | K15: =ROUND(AG15,$G$452) -> 7400 | L15: =ROUND(AH15,$G$452) -> 7700 | N15: =$C15 -> 0.4 | O15: =$G$433 -> 650 | P15: =$G$430*(1-N15)-O15 -> 1150 | Q15: =$G$432-O15 -> 59350 | R15: =IFERROR(P15/(Q15+$G$430*(1-N15)),0)*(1-$G$434) -> 0.017865904 | Z15: =$O15+$G$435+$N15*$G$431+$R15*($Q15*(1+D$9)+$G$431*(1-$N15))-$G$430 -> 5535.8453 | AA15: =$O15+$G$435+$N15*$G$431+$R15*($Q15*(1+E$9)+$G$431*(1-$N15))-$G$430 -> 5800.9306 | AB15: =$O15+$G$435+$N15*$G$431+$R15*($Q15*(1+F$9)+$G$431*(1-$N15))-$G$430 -> 6066.016 | AC15: =$O15+$G$435+$N15*$G$431+$R15*($Q15*(1+G$9)+$G$431*(1-$N15))-$G$430 -> 6331.1013 | AD15: =$O15+$G$435+$N15*$G$431+$R15*($Q15*(1+H$9)+$G$431*(1-$N15))-$G$430 -> 6596.1867 | AE15: =$O15+$G$435+$N15*$G$431+$R15*($Q15*(1+I$9)+$G$431*(1-$N15))-$G$430 -> 6861.272 | AF15: =$O15+$G$435+$N15*$G$431+$R15*($Q15*(1+J$9)+$G$431*(1-$N15))-$G$430 -> 7126.3573 | AG15: =$O15+$G$435+$N15*$G$431+$R15*($Q15*(1+K$9)+$G$431*(1-$N15))-$G$430 -> 7391.4427 | AH15: =$O15+$G$435+$N15*$G$431+$R15*($Q15*(1+L$9)+$G$431*(1-$N15))-$G$430 -> 7656.528 | AT15: =IF(Z55<$G$449,0,MIN($G$446,1+IFERROR(INT((Z55-$G$449)/$G$451),0))) -> 1 | AU15: =IF(AA55<$G$449,0,MIN($G$446,1+IFERROR(INT((AA55-$G$449)/$G$451),0))) -> 2 | AV15: =IF(AB55<$G$449,0,MIN($G$446,1+IFERROR(INT((AB55-$G$449)/$G$451),0))) -> 3 | AW15: =IF(AC55<$G$449,0,MIN($G$446,1+IFERROR(INT((AC55-$G$449)/$G$451),0))) -> 4 | AX15: =IF(AD55<$G$449,0,MIN($G$446,1+IFERROR(INT((AD55-$G$449)/$G$451),0))) -> 5 | AY15: =IF(AE55<$G$449,0,MIN($G$446,1+IFERROR(INT((AE55-$G$449)/$G$451),0))) -> 6 | AZ15: =IF(AF55<$G$449,0,MIN($G$446,1+IFERROR(INT((AF55-$G$449)/$G$451),0))) -> 8 | BA15: =IF(AG55<$G$449,0,MIN($G$446,1+IFERROR(INT((AG55-$G$449)/$G$451),0))) -> 9 | BB15: =IF(AH55<$G$449,0,MIN($G$446,1+IFERROR(INT((AH55-$G$449)/$G$451),0))) -> 10
C16: =C15+$G$439 -> 0.45 | D16: =ROUND(Z16,$G$452) -> 5900 | E16: =ROUND(AA16,$G$452) -> 6200 | F16: =ROUND(AB16,$G$452) -> 6400 | G16: =ROUND(AC16,$G$452) -> 6600 | H16: =ROUND(AD16,$G$452) -> 6900 | I16: =ROUND(AE16,$G$452) -> 7100 | J16: =ROUND(AF16,$G$452) -> 7300 | K16: =ROUND(AG16,$G$452) -> 7500 | L16: =ROUND(AH16,$G$452) -> 7800 | N16: =$C16 -> 0.45 | O16: =$G$433 -> 650 | P16: =$G$430*(1-N16)-O16 -> 1000 | Q16: =$G$432-O16 -> 59350 | R16: =IFERROR(P16/(Q16+$G$430*(1-N16)),0)*(1-$G$434) -> 0.01557377 | Z16: =$O16+$G$435+$N16*$G$431+$R16*($Q16*(1+D$9)+$G$431*(1-$N16))-$G$430 -> 5929.6859 | AA16: =$O16+$G$435+$N16*$G$431+$R16*($Q16*(1+E$9)+$G$431*(1-$N16))-$G$430 -> 6160.7617 | AB16: =$O16+$G$435+$N16*$G$431+$R16*($Q16*(1+F$9)+$G$431*(1-$N16))-$G$430 -> 6391.8375 | AC16: =$O16+$G$435+$N16*$G$431+$R16*($Q16*(1+G$9)+$G$431*(1-$N16))-$G$430 -> 6622.9133 | AD16: =$O16+$G$435+$N16*$G$431+$R16*($Q16*(1+H$9)+$G$431*(1-$N16))-$G$430 -> 6853.9892 | AE16: =$O16+$G$435+$N16*$G$431+$R16*($Q16*(1+I$9)+$G$431*(1-$N16))-$G$430 -> 7085.065 | AF16: =$O16+$G$435+$N16*$G$431+$R16*($Q16*(1+J$9)+$G$431*(1-$N16))-$G$430 -> 7316.1408 | AG16: =$O16+$G$435+$N16*$G$431+$R16*($Q16*(1+K$9)+$G$431*(1-$N16))-$G$430 -> 7547.2166 | AH16: =$O16+$G$435+$N16*$G$431+$R16*($Q16*(1+L$9)+$G$431*(1-$N16))-$G$430 -> 7778.2924 | AT16: =IF(Z56<$G$449,0,MIN($G$446,1+IFERROR(INT((Z56-$G$449)/$G$451),0))) -> 2 | AU16: =IF(AA56<$G$449,0,MIN($G$446,1+IFERROR(INT((AA56-$G$449)/$G$451),0))) -> 3 | AV16: =IF(AB56<$G$449,0,MIN($G$446,1+IFERROR(INT((AB56-$G$449)/$G$451),0))) -> 4 | AW16: =IF(AC56<$G$449,0,MIN($G$446,1+IFERROR(INT((AC56-$G$449)/$G$451),0))) -> 5 | AX16: =IF(AD56<$G$449,0,MIN($G$446,1+IFERROR(INT((AD56-$G$449)/$G$451),0))) -> 6 | AY16: =IF(AE56<$G$449,0,MIN($G$446,1+IFERROR(INT((AE56-$G$449)/$G$451),0))) -> 7 | AZ16: =IF(AF56<$G$449,0,MIN($G$446,1+IFERROR(INT((AF56-$G$449)/$G$451),0))) -> 8 | BA16: =IF(AG56<$G$449,0,MIN($G$446,1+IFERROR(INT((AG56-$G$449)/$G$451),0))) -> 9 | BB16: =IF(AH56<$G$449,0,MIN($G$446,1+IFERROR(INT((AH56-$G$449)/$G$451),0))) -> 10
B17: Ben's Year 5 value (cash at close + earnout + retained Keystone stake + Topkey stock, after dilution) less Keystone value today (G430)
N18: =$G$436 -> 0.3 | O18: =$G$433 -> 650 | P18: =$G$430*(1-N18)-O18 -> 1450 | Q18: =$G$432-O18 -> 59350 | R18: =IFERROR(P18/(Q18+$G$430*(1-N18)),0)*(1-$G$434) -> 0.022416599
B19: Ben's % Return on Keystone Value Based on Topkey Growth & Rollover %
D21: Topkey ex-Keystone Value Growth (%)
D22: =E22-$G$441 -> 1.021904 | E22: =F22-$G$441 -> 1.271904 | F22: =G22-$G$441 -> 1.521904 | G22: =H22-$G$441 -> 1.771904 | H22: =$G$440 -> 2.021904 | I22: =H22+$G$441 -> 2.271904 | J22: =I22+$G$441 -> 2.521904 | K22: =J22+$G$441 -> 2.771904 | L22: =K22+$G$441 -> 3.021904 | AT22: Helper: Gradient Band (0 = below $1M hurdle)
B23: Ben's Rollover % | C23: =C24-$G$439 -> 0.15 | D23: =IFERROR(Z10/$G$430,0) -> 1.1975776 | E23: =IFERROR(AA10/$G$430,0) -> 1.3417978 | F23: =IFERROR(AB10/$G$430,0) -> 1.486018 | G23: =IFERROR(AC10/$G$430,0) -> 1.6302381 | H23: =IFERROR(AD10/$G$430,0) -> 1.7744583 | I23: =IFERROR(AE10/$G$430,0) -> 1.9186785 | J23: =IFERROR(AF10/$G$430,0) -> 2.0628987 | K23: =IFERROR(AG10/$G$430,0) -> 2.2071189 | L23: =IFERROR(AH10/$G$430,0) -> 2.351339 | AT23: =IF(Z50<$G$449,0,MIN($G$446,1+IFERROR(INT((Z50-$G$449)/$G$451),0))) -> 0 | AU23: =IF(AA50<$G$449,0,MIN($G$446,1+IFERROR(INT((AA50-$G$449)/$G$451),0))) -> 0 | AV23: =IF(AB50<$G$449,0,MIN($G$446,1+IFERROR(INT((AB50-$G$449)/$G$451),0))) -> 0 | AW23: =IF(AC50<$G$449,0,MIN($G$446,1+IFERROR(INT((AC50-$G$449)/$G$451),0))) -> 0 | AX23: =IF(AD50<$G$449,0,MIN($G$446,1+IFERROR(INT((AD50-$G$449)/$G$451),0))) -> 0 | AY23: =IF(AE50<$G$449,0,MIN($G$446,1+IFERROR(INT((AE50-$G$449)/$G$451),0))) -> 2 | AZ23: =IF(AF50<$G$449,0,MIN($G$446,1+IFERROR(INT((AF50-$G$449)/$G$451),0))) -> 4 | BA23: =IF(AG50<$G$449,0,MIN($G$446,1+IFERROR(INT((AG50-$G$449)/$G$451),0))) -> 5 | BB23: =IF(AH50<$G$449,0,MIN($G$446,1+IFERROR(INT((AH50-$G$449)/$G$451),0))) -> 7
C24: =C25-$G$439 -> 0.2 | D24: =IFERROR(Z11/$G$430,0) -> 1.3259729 | E24: =IFERROR(AA11/$G$430,0) -> 1.45913 | F24: =IFERROR(AB11/$G$430,0) -> 1.592287 | G24: =IFERROR(AC11/$G$430,0) -> 1.7254441 | H24: =IFERROR(AD11/$G$430,0) -> 1.8586011 | I24: =IFERROR(AE11/$G$430,0) -> 1.9917582 | J24: =IFERROR(AF11/$G$430,0) -> 2.1249152 | K24: =IFERROR(AG11/$G$430,0) -> 2.2580723 | L24: =IFERROR(AH11/$G$430,0) -> 2.3912293 | AT24: =IF(Z51<$G$449,0,MIN($G$446,1+IFERROR(INT((Z51-$G$449)/$G$451),0))) -> 0 | AU24: =IF(AA51<$G$449,0,MIN($G$446,1+IFERROR(INT((AA51-$G$449)/$G$451),0))) -> 0 | AV24: =IF(AB51<$G$449,0,MIN($G$446,1+IFERROR(INT((AB51-$G$449)/$G$451),0))) -> 0 | AW24: =IF(AC51<$G$449,0,MIN($G$446,1+IFERROR(INT((AC51-$G$449)/$G$451),0))) -> 0 | AX24: =IF(AD51<$G$449,0,MIN($G$446,1+IFERROR(INT((AD51-$G$449)/$G$451),0))) -> 1 | AY24: =IF(AE51<$G$449,0,MIN($G$446,1+IFERROR(INT((AE51-$G$449)/$G$451),0))) -> 3 | AZ24: =IF(AF51<$G$449,0,MIN($G$446,1+IFERROR(INT((AF51-$G$449)/$G$451),0))) -> 4 | BA24: =IF(AG51<$G$449,0,MIN($G$446,1+IFERROR(INT((AG51-$G$449)/$G$451),0))) -> 6 | BB24: =IF(AH51<$G$449,0,MIN($G$446,1+IFERROR(INT((AH51-$G$449)/$G$451),0))) -> 8
C25: =C26-$G$439 -> 0.25 | D25: =IFERROR(Z12/$G$430,0) -> 1.4549368 | E25: =IFERROR(AA12/$G$430,0) -> 1.5769769 | F25: =IFERROR(AB12/$G$430,0) -> 1.6990169 | G25: =IFERROR(AC12/$G$430,0) -> 1.821057 | H25: =IFERROR(AD12/$G$430,0) -> 1.943097 | I25: =IFERROR(AE12/$G$430,0) -> 2.0651371 | J25: =IFERROR(AF12/$G$430,0) -> 2.1871771 | K25: =IFERROR(AG12/$G$430,0) -> 2.3092171 | L25: =IFERROR(AH12/$G$430,0) -> 2.4312572 | AT25: =IF(Z52<$G$449,0,MIN($G$446,1+IFERROR(INT((Z52-$G$449)/$G$451),0))) -> 0 | AU25: =IF(AA52<$G$449,0,MIN($G$446,1+IFERROR(INT((AA52-$G$449)/$G$451),0))) -> 0 | AV25: =IF(AB52<$G$449,0,MIN($G$446,1+IFERROR(INT((AB52-$G$449)/$G$451),0))) -> 0 | AW25: =IF(AC52<$G$449,0,MIN($G$446,1+IFERROR(INT((AC52-$G$449)/$G$451),0))) -> 0 | AX25: =IF(AD52<$G$449,0,MIN($G$446,1+IFERROR(INT((AD52-$G$449)/$G$451),0))) -> 2 | AY25: =IF(AE52<$G$449,0,MIN($G$446,1+IFERROR(INT((AE52-$G$449)/$G$451),0))) -> 4 | AZ25: =IF(AF52<$G$449,0,MIN($G$446,1+IFERROR(INT((AF52-$G$449)/$G$451),0))) -> 5 | BA25: =IF(AG52<$G$449,0,MIN($G$446,1+IFERROR(INT((AG52-$G$449)/$G$451),0))) -> 7 | BB25: =IF(AH52<$G$449,0,MIN($G$446,1+IFERROR(INT((AH52-$G$449)/$G$451),0))) -> 8
C26: =$G$438 -> 0.3 | D26: =IFERROR(Z13/$G$430,0) -> 1.5844735 | E26: =IFERROR(AA13/$G$430,0) -> 1.6953422 | F26: =IFERROR(AB13/$G$430,0) -> 1.806211 | G26: =IFERROR(AC13/$G$430,0) -> 1.9170797 | H26: =IFERROR(AD13/$G$430,0) -> 2.0279485 | I26: =IFERROR(AE13/$G$430,0) -> 2.1388173 | J26: =IFERROR(AF13/$G$430,0) -> 2.249686 | K26: =IFERROR(AG13/$G$430,0) -> 2.3605548 | L26: =IFERROR(AH13/$G$430,0) -> 2.4714236 | AT26: =IF(Z53<$G$449,0,MIN($G$446,1+IFERROR(INT((Z53-$G$449)/$G$451),0))) -> 0 | AU26: =IF(AA53<$G$449,0,MIN($G$446,1+IFERROR(INT((AA53-$G$449)/$G$451),0))) -> 0 | AV26: =IF(AB53<$G$449,0,MIN($G$446,1+IFERROR(INT((AB53-$G$449)/$G$451),0))) -> 0 | AW26: =IF(AC53<$G$449,0,MIN($G$446,1+IFERROR(INT((AC53-$G$449)/$G$451),0))) -> 2 | AX26: =IF(AD53<$G$449,0,MIN($G$446,1+IFERROR(INT((AD53-$G$449)/$G$451),0))) -> 3 | AY26: =IF(AE53<$G$449,0,MIN($G$446,1+IFERROR(INT((AE53-$G$449)/$G$451),0))) -> 5 | AZ26: =IF(AF53<$G$449,0,MIN($G$446,1+IFERROR(INT((AF53-$G$449)/$G$451),0))) -> 6 | BA26: =IF(AG53<$G$449,0,MIN($G$446,1+IFERROR(INT((AG53-$G$449)/$G$451),0))) -> 7 | BB26: =IF(AH53<$G$449,0,MIN($G$446,1+IFERROR(INT((AH53-$G$449)/$G$451),0))) -> 9
C27: =C26+$G$439 -> 0.35 | D27: =IFERROR(Z14/$G$430,0) -> 1.714587 | E27: =IFERROR(AA14/$G$430,0) -> 1.8142298 | F27: =IFERROR(AB14/$G$430,0) -> 1.9138726 | G27: =IFERROR(AC14/$G$430,0) -> 2.0135154 | H27: =IFERROR(AD14/$G$430,0) -> 2.1131583 | I27: =IFERROR(AE14/$G$430,0) -> 2.2128011 | J27: =IFERROR(AF14/$G$430,0) -> 2.3124439 | K27: =IFERROR(AG14/$G$430,0) -> 2.4120867 | L27: =IFERROR(AH14/$G$430,0) -> 2.5117295 | AT27: =IF(Z54<$G$449,0,MIN($G$446,1+IFERROR(INT((Z54-$G$449)/$G$451),0))) -> 0 | AU27: =IF(AA54<$G$449,0,MIN($G$446,1+IFERROR(INT((AA54-$G$449)/$G$451),0))) -> 0 | AV27: =IF(AB54<$G$449,0,MIN($G$446,1+IFERROR(INT((AB54-$G$449)/$G$451),0))) -> 2 | AW27: =IF(AC54<$G$449,0,MIN($G$446,1+IFERROR(INT((AC54-$G$449)/$G$451),0))) -> 3 | AX27: =IF(AD54<$G$449,0,MIN($G$446,1+IFERROR(INT((AD54-$G$449)/$G$451),0))) -> 4 | AY27: =IF(AE54<$G$449,0,MIN($G$446,1+IFERROR(INT((AE54-$G$449)/$G$451),0))) -> 6 | AZ27: =IF(AF54<$G$449,0,MIN($G$446,1+IFERROR(INT((AF54-$G$449)/$G$451),0))) -> 7 | BA27: =IF(AG54<$G$449,0,MIN($G$446,1+IFERROR(INT((AG54-$G$449)/$G$451),0))) -> 8 | BB27: =IF(AH54<$G$449,0,MIN($G$446,1+IFERROR(INT((AH54-$G$449)/$G$451),0))) -> 9
C28: =C27+$G$439 -> 0.4 | D28: =IFERROR(Z15/$G$430,0) -> 1.8452818 | E28: =IFERROR(AA15/$G$430,0) -> 1.9336435 | F28: =IFERROR(AB15/$G$430,0) -> 2.0220053 | G28: =IFERROR(AC15/$G$430,0) -> 2.1103671 | H28: =IFERROR(AD15/$G$430,0) -> 2.1987289 | I28: =IFERROR(AE15/$G$430,0) -> 2.2870907 | J28: =IFERROR(AF15/$G$430,0) -> 2.3754524 | K28: =IFERROR(AG15/$G$430,0) -> 2.4638142 | L28: =IFERROR(AH15/$G$430,0) -> 2.552176 | AT28: =IF(Z55<$G$449,0,MIN($G$446,1+IFERROR(INT((Z55-$G$449)/$G$451),0))) -> 1 | AU28: =IF(AA55<$G$449,0,MIN($G$446,1+IFERROR(INT((AA55-$G$449)/$G$451),0))) -> 2 | AV28: =IF(AB55<$G$449,0,MIN($G$446,1+IFERROR(INT((AB55-$G$449)/$G$451),0))) -> 3 | AW28: =IF(AC55<$G$449,0,MIN($G$446,1+IFERROR(INT((AC55-$G$449)/$G$451),0))) -> 4 | AX28: =IF(AD55<$G$449,0,MIN($G$446,1+IFERROR(INT((AD55-$G$449)/$G$451),0))) -> 5 | AY28: =IF(AE55<$G$449,0,MIN($G$446,1+IFERROR(INT((AE55-$G$449)/$G$451),0))) -> 6 | AZ28: =IF(AF55<$G$449,0,MIN($G$446,1+IFERROR(INT((AF55-$G$449)/$G$451),0))) -> 8 | BA28: =IF(AG55<$G$449,0,MIN($G$446,1+IFERROR(INT((AG55-$G$449)/$G$451),0))) -> 9 | BB28: =IF(AH55<$G$449,0,MIN($G$446,1+IFERROR(INT((AH55-$G$449)/$G$451),0))) -> 10
C29: =C28+$G$439 -> 0.45 | D29: =IFERROR(Z16/$G$430,0) -> 1.976562 | E29: =IFERROR(AA16/$G$430,0) -> 2.0535872 | F29: =IFERROR(AB16/$G$430,0) -> 2.1306125 | G29: =IFERROR(AC16/$G$430,0) -> 2.2076378 | H29: =IFERROR(AD16/$G$430,0) -> 2.2846631 | I29: =IFERROR(AE16/$G$430,0) -> 2.3616883 | J29: =IFERROR(AF16/$G$430,0) -> 2.4387136 | K29: =IFERROR(AG16/$G$430,0) -> 2.5157389 | L29: =IFERROR(AH16/$G$430,0) -> 2.5927641 | AT29: =IF(Z56<$G$449,0,MIN($G$446,1+IFERROR(INT((Z56-$G$449)/$G$451),0))) -> 2 | AU29: =IF(AA56<$G$449,0,MIN($G$446,1+IFERROR(INT((AA56-$G$449)/$G$451),0))) -> 3 | AV29: =IF(AB56<$G$449,0,MIN($G$446,1+IFERROR(INT((AB56-$G$449)/$G$451),0))) -> 4 | AW29: =IF(AC56<$G$449,0,MIN($G$446,1+IFERROR(INT((AC56-$G$449)/$G$451),0))) -> 5 | AX29: =IF(AD56<$G$449,0,MIN($G$446,1+IFERROR(INT((AD56-$G$449)/$G$451),0))) -> 6 | AY29: =IF(AE56<$G$449,0,MIN($G$446,1+IFERROR(INT((AE56-$G$449)/$G$451),0))) -> 7 | AZ29: =IF(AF56<$G$449,0,MIN($G$446,1+IFERROR(INT((AF56-$G$449)/$G$451),0))) -> 8 | BA29: =IF(AG56<$G$449,0,MIN($G$446,1+IFERROR(INT((AG56-$G$449)/$G$451),0))) -> 9 | BB29: =IF(AH56<$G$449,0,MIN($G$446,1+IFERROR(INT((AH56-$G$449)/$G$451),0))) -> 10
B30: Ben's Year 5 total value ÷ Keystone value today (G430), less 1
B32: Ben's IRR Based on Topkey Growth & Rollover %
D34: Topkey ex-Keystone Value Growth (%) | BD34: Helper: IRR CF — Col D | BJ34: Helper: IRR CF — Col E | BP34: Helper: IRR CF — Col F | BV34: Helper: IRR CF — Col G | CB34: Helper: IRR CF — Col H | CH34: Helper: IRR CF — Col I | CN34: Helper: IRR CF — Col J | CT34: Helper: IRR CF — Col K | CZ34: Helper: IRR CF — Col L
D35: =E35-$G$441 -> 1.021904 | E35: =F35-$G$441 -> 1.271904 | F35: =G35-$G$441 -> 1.521904 | G35: =H35-$G$441 -> 1.771904 | H35: =$G$440 -> 2.021904 | I35: =H35+$G$441 -> 2.271904 | J35: =I35+$G$441 -> 2.521904 | K35: =J35+$G$441 -> 2.771904 | L35: =K35+$G$441 -> 3.021904 | AT35: Helper: Gradient Band (0 = below $1M hurdle) | BD35: =$S$9 -> 0 | BE35: =$T$9 -> 1 | BF35: =$U$9 -> 2 | BG35: =$V$9 -> 3 | BH35: =$W$9 -> 4 | BI35: =$X$9 -> 5 | BJ35: =$S$9 -> 0 | BK35: =$T$9 -> 1 | BL35: =$U$9 -> 2 | BM35: =$V$9 -> 3 | BN35: =$W$9 -> 4 | BO35: =$X$9 -> 5 | BP35: =$S$9 -> 0 | BQ35: =$T$9 -> 1 | BR35: =$U$9 -> 2 | BS35: =$V$9 -> 3 | BT35: =$W$9 -> 4 | BU35: =$X$9 -> 5 | BV35: =$S$9 -> 0 | BW35: =$T$9 -> 1 | BX35: =$U$9 -> 2 | BY35: =$V$9 -> 3 | BZ35: =$W$9 -> 4 | CA35: =$X$9 -> 5 | CB35: =$S$9 -> 0 | CC35: =$T$9 -> 1 | CD35: =$U$9 -> 2 | CE35: =$V$9 -> 3 | CF35: =$W$9 -> 4 | CG35: =$X$9 -> 5 | CH35: =$S$9 -> 0 | CI35: =$T$9 -> 1 | CJ35: =$U$9 -> 2 | CK35: =$V$9 -> 3 | CL35: =$W$9 -> 4 | CM35: =$X$9 -> 5 | CN35: =$S$9 -> 0 | CO35: =$T$9 -> 1 | CP35: =$U$9 -> 2 | CQ35: =$V$9 -> 3 | CR35: =$W$9 -> 4 | CS35: =$X$9 -> 5 | CT35: =$S$9 -> 0 | CU35: =$T$9 -> 1 | CV35: =$U$9 -> 2 | CW35: =$V$9 -> 3 | CX35: =$W$9 -> 4 | CY35: =$X$9 -> 5 | CZ35: =$S$9 -> 0 | DA35: =$T$9 -> 1 | DB35: =$U$9 -> 2 | DC35: =$V$9 -> 3 | DD35: =$W$9 -> 4 | DE35: =$X$9 -> 5
B36: Ben's Rollover % | C36: =C37-$G$439 -> 0.15 | D36: =IFERROR(IRR(BD36:BI36),0) -> 0.2038813 | E36: =IFERROR(IRR(BJ36:BO36),0) -> 0.22092173 | F36: =IFERROR(IRR(BP36:BU36),0) -> 0.23706074 | G36: =IFERROR(IRR(BV36:CA36),0) -> 0.252399 | H36: =IFERROR(IRR(CB36:CG36),0) -> 0.2670207 | I36: =IFERROR(IRR(CH36:CM36),0) -> 0.28099705 | J36: =IFERROR(IRR(CN36:CS36),0) -> 0.29438878 | K36: =IFERROR(IRR(CT36:CY36),0) -> 0.3072482 | L36: =IFERROR(IRR(CZ36:DE36),0) -> 0.31962067 | AT36: =IF(Z50<$G$449,0,MIN($G$446,1+IFERROR(INT((Z50-$G$449)/$G$451),0))) -> 0 | AU36: =IF(AA50<$G$449,0,MIN($G$446,1+IFERROR(INT((AA50-$G$449)/$G$451),0))) -> 0 | AV36: =IF(AB50<$G$449,0,MIN($G$446,1+IFERROR(INT((AB50-$G$449)/$G$451),0))) -> 0 | AW36: =IF(AC50<$G$449,0,MIN($G$446,1+IFERROR(INT((AC50-$G$449)/$G$451),0))) -> 0 | AX36: =IF(AD50<$G$449,0,MIN($G$446,1+IFERROR(INT((AD50-$G$449)/$G$451),0))) -> 0 | AY36: =IF(AE50<$G$449,0,MIN($G$446,1+IFERROR(INT((AE50-$G$449)/$G$451),0))) -> 2 | AZ36: =IF(AF50<$G$449,0,MIN($G$446,1+IFERROR(INT((AF50-$G$449)/$G$451),0))) -> 4 | BA36: =IF(AG50<$G$449,0,MIN($G$446,1+IFERROR(INT((AG50-$G$449)/$G$451),0))) -> 5 | BB36: =IF(AH50<$G$449,0,MIN($G$446,1+IFERROR(INT((AH50-$G$449)/$G$451),0))) -> 7 | BD36: =(BD$35=0)*($O10-$G$430)+(BD$35=$G$444)*$G$435+(BD$35=$G$445)*(Z10+$G$430-$O10-$G$435) -> -2350 | BE36: =(BE$35=0)*($O10-$G$430)+(BE$35=$G$444)*$G$435+(BE$35=$G$445)*(Z10+$G$430-$O10-$G$435) -> 0 | BF36: =(BF$35=0)*($O10-$G$430)+(BF$35=$G$444)*$G$435+(BF$35=$G$445)*(Z10+$G$430-$O10-$G$435) -> 0 | BG36: =(BG$35=0)*($O10-$G$430)+(BG$35=$G$444)*$G$435+(BG$35=$G$445)*(Z10+$G$430-$O10-$G$435) -> 0 | BH36: =(BH$35=0)*($O10-$G$430)+(BH$35=$G$444)*$G$435+(BH$35=$G$445)*(Z10+$G$430-$O10-$G$435) -> 0 | BI36: =(BI$35=0)*($O10-$G$430)+(BI$35=$G$444)*$G$435+(BI$35=$G$445)*(Z10+$G$430-$O10-$G$435) -> 5942.7328 | BJ36: =(BJ$35=0)*($O10-$G$430)+(BJ$35=$G$444)*$G$435+(BJ$35=$G$445)*(AA10+$G$430-$O10-$G$435) -> -2350 | BK36: =(BK$35=0)*($O10-$G$430)+(BK$35=$G$444)*$G$435+(BK$35=$G$445)*(AA10+$G$430-$O10-$G$435) -> 0 | BL36: =(BL$35=0)*($O10-$G$430)+(BL$35=$G$444)*$G$435+(BL$35=$G$445)*(AA10+$G$430-$O10-$G$435) -> 0 | BM36: =(BM$35=0)*($O10-$G$430)+(BM$35=$G$444)*$G$435+(BM$35=$G$445)*(AA10+$G$430-$O10-$G$435) -> 0 | BN36: =(BN$35=0)*($O10-$G$430)+(BN$35=$G$444)*$G$435+(BN$35=$G$445)*(AA10+$G$430-$O10-$G$435) -> 0 | BO36: =(BO$35=0)*($O10-$G$430)+(BO$35=$G$444)*$G$435+(BO$35=$G$445)*(AA10+$G$430-$O10-$G$435) -> 6375.3933 | BP36: =(BP$35=0)*($O10-$G$430)+(BP$35=$G$444)*$G$435+(BP$35=$G$445)*(AB10+$G$430-$O10-$G$435) -> -2350 | BQ36: =(BQ$35=0)*($O10-$G$430)+(BQ$35=$G$444)*$G$435+(BQ$35=$G$445)*(AB10+$G$430-$O10-$G$435) -> 0 | BR36: =(BR$35=0)*($O10-$G$430)+(BR$35=$G$444)*$G$435+(BR$35=$G$445)*(AB10+$G$430-$O10-$G$435) -> 0 | BS36: =(BS$35=0)*($O10-$G$430)+(BS$35=$G$444)*$G$435+(BS$35=$G$445)*(AB10+$G$430-$O10-$G$435) -> 0 | BT36: =(BT$35=0)*($O10-$G$430)+(BT$35=$G$444)*$G$435+(BT$35=$G$445)*(AB10+$G$430-$O10-$G$435) -> 0 | BU36: =(BU$35=0)*($O10-$G$430)+(BU$35=$G$444)*$G$435+(BU$35=$G$445)*(AB10+$G$430-$O10-$G$435) -> 6808.0539 | BV36: =(BV$35=0)*($O10-$G$430)+(BV$35=$G$444)*$G$435+(BV$35=$G$445)*(AC10+$G$430-$O10-$G$435) -> -2350 | BW36: =(BW$35=0)*($O10-$G$430)+(BW$35=$G$444)*$G$435+(BW$35=$G$445)*(AC10+$G$430-$O10-$G$435) -> 0 | BX36: =(BX$35=0)*($O10-$G$430)+(BX$35=$G$444)*$G$435+(BX$35=$G$445)*(AC10+$G$430-$O10-$G$435) -> 0 | BY36: =(BY$35=0)*($O10-$G$430)+(BY$35=$G$444)*$G$435+(BY$35=$G$445)*(AC10+$G$430-$O10-$G$435) -> 0 | BZ36: =(BZ$35=0)*($O10-$G$430)+(BZ$35=$G$444)*$G$435+(BZ$35=$G$445)*(AC10+$G$430-$O10-$G$435) -> 0 | CA36: =(CA$35=0)*($O10-$G$430)+(CA$35=$G$444)*$G$435+(CA$35=$G$445)*(AC10+$G$430-$O10-$G$435) -> 7240.7144 | CB36: =(CB$35=0)*($O10-$G$430)+(CB$35=$G$444)*$G$435+(CB$35=$G$445)*(AD10+$G$430-$O10-$G$435) -> -2350 | CC36: =(CC$35=0)*($O10-$G$430)+(CC$35=$G$444)*$G$435+(CC$35=$G$445)*(AD10+$G$430-$O10-$G$435) -> 0 | CD36: =(CD$35=0)*($O10-$G$430)+(CD$35=$G$444)*$G$435+(CD$35=$G$445)*(AD10+$G$430-$O10-$G$435) -> 0 | CE36: =(CE$35=0)*($O10-$G$430)+(CE$35=$G$444)*$G$435+(CE$35=$G$445)*(AD10+$G$430-$O10-$G$435) -> 0 | CF36: =(CF$35=0)*($O10-$G$430)+(CF$35=$G$444)*$G$435+(CF$35=$G$445)*(AD10+$G$430-$O10-$G$435) -> 0 | CG36: =(CG$35=0)*($O10-$G$430)+(CG$35=$G$444)*$G$435+(CG$35=$G$445)*(AD10+$G$430-$O10-$G$435) -> 7673.375 | CH36: =(CH$35=0)*($O10-$G$430)+(CH$35=$G$444)*$G$435+(CH$35=$G$445)*(AE10+$G$430-$O10-$G$435) -> -2350 | CI36: =(CI$35=0)*($O10-$G$430)+(CI$35=$G$444)*$G$435+(CI$35=$G$445)*(AE10+$G$430-$O10-$G$435) -> 0 | CJ36: =(CJ$35=0)*($O10-$G$430)+(CJ$35=$G$444)*$G$435+(CJ$35=$G$445)*(AE10+$G$430-$O10-$G$435) -> 0 | CK36: =(CK$35=0)*($O10-$G$430)+(CK$35=$G$444)*$G$435+(CK$35=$G$445)*(AE10+$G$430-$O10-$G$435) -> 0 | CL36: =(CL$35=0)*($O10-$G$430)+(CL$35=$G$444)*$G$435+(CL$35=$G$445)*(AE10+$G$430-$O10-$G$435) -> 0 | CM36: =(CM$35=0)*($O10-$G$430)+(CM$35=$G$444)*$G$435+(CM$35=$G$445)*(AE10+$G$430-$O10-$G$435) -> 8106.0355 | CN36: =(CN$35=0)*($O10-$G$430)+(CN$35=$G$444)*$G$435+(CN$35=$G$445)*(AF10+$G$430-$O10-$G$435) -> -2350 | CO36: =(CO$35=0)*($O10-$G$430)+(CO$35=$G$444)*$G$435+(CO$35=$G$445)*(AF10+$G$430-$O10-$G$435) -> 0 | CP36: =(CP$35=0)*($O10-$G$430)+(CP$35=$G$444)*$G$435+(CP$35=$G$445)*(AF10+$G$430-$O10-$G$435) -> 0 | CQ36: =(CQ$35=0)*($O10-$G$430)+(CQ$35=$G$444)*$G$435+(CQ$35=$G$445)*(AF10+$G$430-$O10-$G$435) -> 0 | CR36: =(CR$35=0)*($O10-$G$430)+(CR$35=$G$444)*$G$435+(CR$35=$G$445)*(AF10+$G$430-$O10-$G$435) -> 0 | CS36: =(CS$35=0)*($O10-$G$430)+(CS$35=$G$444)*$G$435+(CS$35=$G$445)*(AF10+$G$430-$O10-$G$435) -> 8538.6961 | CT36: =(CT$35=0)*($O10-$G$430)+(CT$35=$G$444)*$G$435+(CT$35=$G$445)*(AG10+$G$430-$O10-$G$435) -> -2350 | CU36: =(CU$35=0)*($O10-$G$430)+(CU$35=$G$444)*$G$435+(CU$35=$G$445)*(AG10+$G$430-$O10-$G$435) -> 0 | CV36: =(CV$35=0)*($O10-$G$430)+(CV$35=$G$444)*$G$435+(CV$35=$G$445)*(AG10+$G$430-$O10-$G$435) -> 0 | CW36: =(CW$35=0)*($O10-$G$430)+(CW$35=$G$444)*$G$435+(CW$35=$G$445)*(AG10+$G$430-$O10-$G$435) -> 0 | CX36: =(CX$35=0)*($O10-$G$430)+(CX$35=$G$444)*$G$435+(CX$35=$G$445)*(AG10+$G$430-$O10-$G$435) -> 0 | CY36: =(CY$35=0)*($O10-$G$430)+(CY$35=$G$444)*$G$435+(CY$35=$G$445)*(AG10+$G$430-$O10-$G$435) -> 8971.3566 | CZ36: =(CZ$35=0)*($O10-$G$430)+(CZ$35=$G$444)*$G$435+(CZ$35=$G$445)*(AH10+$G$430-$O10-$G$435) -> -2350 | DA36: =(DA$35=0)*($O10-$G$430)+(DA$35=$G$444)*$G$435+(DA$35=$G$445)*(AH10+$G$430-$O10-$G$435) -> 0 | DB36: =(DB$35=0)*($O10-$G$430)+(DB$35=$G$444)*$G$435+(DB$35=$G$445)*(AH10+$G$430-$O10-$G$435) -> 0 | DC36: =(DC$35=0)*($O10-$G$430)+(DC$35=$G$444)*$G$435+(DC$35=$G$445)*(AH10+$G$430-$O10-$G$435) -> 0 | DD36: =(DD$35=0)*($O10-$G$430)+(DD$35=$G$444)*$G$435+(DD$35=$G$445)*(AH10+$G$430-$O10-$G$435) -> 0 | DE36: =(DE$35=0)*($O10-$G$430)+(DE$35=$G$444)*$G$435+(DE$35=$G$445)*(AH10+$G$430-$O10-$G$435) -> 9404.0171
C37: =C38-$G$439 -> 0.2 | D37: =IFERROR(IRR(BD37:BI37),0) -> 0.21909797 | E37: =IFERROR(IRR(BJ37:BO37),0) -> 0.23411533 | F37: =IFERROR(IRR(BP37:BU37),0) -> 0.24843543 | G37: =IFERROR(IRR(BV37:CA37),0) -> 0.26212714 | H37: =IFERROR(IRR(CB37:CG37),0) -> 0.27524928 | I37: =IFERROR(IRR(CH37:CM37),0) -> 0.28785255 | J37: =IFERROR(IRR(CN37:CS37),0) -> 0.29998094 | K37: =IFERROR(IRR(CT37:CY37),0) -> 0.31167291 | L37: =IFERROR(IRR(CZ37:DE37),0) -> 0.32296227 | AT37: =IF(Z51<$G$449,0,MIN($G$446,1+IFERROR(INT((Z51-$G$449)/$G$451),0))) -> 0 | AU37: =IF(AA51<$G$449,0,MIN($G$446,1+IFERROR(INT((AA51-$G$449)/$G$451),0))) -> 0 | AV37: =IF(AB51<$G$449,0,MIN($G$446,1+IFERROR(INT((AB51-$G$449)/$G$451),0))) -> 0 | AW37: =IF(AC51<$G$449,0,MIN($G$446,1+IFERROR(INT((AC51-$G$449)/$G$451),0))) -> 0 | AX37: =IF(AD51<$G$449,0,MIN($G$446,1+IFERROR(INT((AD51-$G$449)/$G$451),0))) -> 1 | AY37: =IF(AE51<$G$449,0,MIN($G$446,1+IFERROR(INT((AE51-$G$449)/$G$451),0))) -> 3 | AZ37: =IF(AF51<$G$449,0,MIN($G$446,1+IFERROR(INT((AF51-$G$449)/$G$451),0))) -> 4 | BA37: =IF(AG51<$G$449,0,MIN($G$446,1+IFERROR(INT((AG51-$G$449)/$G$451),0))) -> 6 | BB37: =IF(AH51<$G$449,0,MIN($G$446,1+IFERROR(INT((AH51-$G$449)/$G$451),0))) -> 8 | BD37: =(BD$35=0)*($O11-$G$430)+(BD$35=$G$444)*$G$435+(BD$35=$G$445)*(Z11+$G$430-$O11-$G$435) -> -2350 | BE37: =(BE$35=0)*($O11-$G$430)+(BE$35=$G$444)*$G$435+(BE$35=$G$445)*(Z11+$G$430-$O11-$G$435) -> 0 | BF37: =(BF$35=0)*($O11-$G$430)+(BF$35=$G$444)*$G$435+(BF$35=$G$445)*(Z11+$G$430-$O11-$G$435) -> 0 | BG37: =(BG$35=0)*($O11-$G$430)+(BG$35=$G$444)*$G$435+(BG$35=$G$445)*(Z11+$G$430-$O11-$G$435) -> 0 | BH37: =(BH$35=0)*($O11-$G$430)+(BH$35=$G$444)*$G$435+(BH$35=$G$445)*(Z11+$G$430-$O11-$G$435) -> 0 | BI37: =(BI$35=0)*($O11-$G$430)+(BI$35=$G$444)*$G$435+(BI$35=$G$445)*(Z11+$G$430-$O11-$G$435) -> 6327.9188 | BJ37: =(BJ$35=0)*($O11-$G$430)+(BJ$35=$G$444)*$G$435+(BJ$35=$G$445)*(AA11+$G$430-$O11-$G$435) -> -2350 | BK37: =(BK$35=0)*($O11-$G$430)+(BK$35=$G$444)*$G$435+(BK$35=$G$445)*(AA11+$G$430-$O11-$G$435) -> 0 | BL37: =(BL$35=0)*($O11-$G$430)+(BL$35=$G$444)*$G$435+(BL$35=$G$445)*(AA11+$G$430-$O11-$G$435) -> 0 | BM37: =(BM$35=0)*($O11-$G$430)+(BM$35=$G$444)*$G$435+(BM$35=$G$445)*(AA11+$G$430-$O11-$G$435) -> 0 | BN37: =(BN$35=0)*($O11-$G$430)+(BN$35=$G$444)*$G$435+(BN$35=$G$445)*(AA11+$G$430-$O11-$G$435) -> 0 | BO37: =(BO$35=0)*($O11-$G$430)+(BO$35=$G$444)*$G$435+(BO$35=$G$445)*(AA11+$G$430-$O11-$G$435) -> 6727.39 | BP37: =(BP$35=0)*($O11-$G$430)+(BP$35=$G$444)*$G$435+(BP$35=$G$445)*(AB11+$G$430-$O11-$G$435) -> -2350 | BQ37: =(BQ$35=0)*($O11-$G$430)+(BQ$35=$G$444)*$G$435+(BQ$35=$G$445)*(AB11+$G$430-$O11-$G$435) -> 0 | BR37: =(BR$35=0)*($O11-$G$430)+(BR$35=$G$444)*$G$435+(BR$35=$G$445)*(AB11+$G$430-$O11-$G$435) -> 0 | BS37: =(BS$35=0)*($O11-$G$430)+(BS$35=$G$444)*$G$435+(BS$35=$G$445)*(AB11+$G$430-$O11-$G$435) -> 0 | BT37: =(BT$35=0)*($O11-$G$430)+(BT$35=$G$444)*$G$435+(BT$35=$G$445)*(AB11+$G$430-$O11-$G$435) -> 0 | BU37: =(BU$35=0)*($O11-$G$430)+(BU$35=$G$444)*$G$435+(BU$35=$G$445)*(AB11+$G$430-$O11-$G$435) -> 7126.8611 | BV37: =(BV$35=0)*($O11-$G$430)+(BV$35=$G$444)*$G$435+(BV$35=$G$445)*(AC11+$G$430-$O11-$G$435) -> -2350 | BW37: =(BW$35=0)*($O11-$G$430)+(BW$35=$G$444)*$G$435+(BW$35=$G$445)*(AC11+$G$430-$O11-$G$435) -> 0 | BX37: =(BX$35=0)*($O11-$G$430)+(BX$35=$G$444)*$G$435+(BX$35=$G$445)*(AC11+$G$430-$O11-$G$435) -> 0 | BY37: =(BY$35=0)*($O11-$G$430)+(BY$35=$G$444)*$G$435+(BY$35=$G$445)*(AC11+$G$430-$O11-$G$435) -> 0 | BZ37: =(BZ$35=0)*($O11-$G$430)+(BZ$35=$G$444)*$G$435+(BZ$35=$G$445)*(AC11+$G$430-$O11-$G$435) -> 0 | CA37: =(CA$35=0)*($O11-$G$430)+(CA$35=$G$444)*$G$435+(CA$35=$G$445)*(AC11+$G$430-$O11-$G$435) -> 7526.3323 | CB37: =(CB$35=0)*($O11-$G$430)+(CB$35=$G$444)*$G$435+(CB$35=$G$445)*(AD11+$G$430-$O11-$G$435) -> -2350 | CC37: =(CC$35=0)*($O11-$G$430)+(CC$35=$G$444)*$G$435+(CC$35=$G$445)*(AD11+$G$430-$O11-$G$435) -> 0 | CD37: =(CD$35=0)*($O11-$G$430)+(CD$35=$G$444)*$G$435+(CD$35=$G$445)*(AD11+$G$430-$O11-$G$435) -> 0 | CE37: =(CE$35=0)*($O11-$G$430)+(CE$35=$G$444)*$G$435+(CE$35=$G$445)*(AD11+$G$430-$O11-$G$435) -> 0 | CF37: =(CF$35=0)*($O11-$G$430)+(CF$35=$G$444)*$G$435+(CF$35=$G$445)*(AD11+$G$430-$O11-$G$435) -> 0 | CG37: =(CG$35=0)*($O11-$G$430)+(CG$35=$G$444)*$G$435+(CG$35=$G$445)*(AD11+$G$430-$O11-$G$435) -> 7925.8034 | CH37: =(CH$35=0)*($O11-$G$430)+(CH$35=$G$444)*$G$435+(CH$35=$G$445)*(AE11+$G$430-$O11-$G$435) -> -2350 | CI37: =(CI$35=0)*($O11-$G$430)+(CI$35=$G$444)*$G$435+(CI$35=$G$445)*(AE11+$G$430-$O11-$G$435) -> 0 | CJ37: =(CJ$35=0)*($O11-$G$430)+(CJ$35=$G$444)*$G$435+(CJ$35=$G$445)*(AE11+$G$430-$O11-$G$435) -> 0 | CK37: =(CK$35=0)*($O11-$G$430)+(CK$35=$G$444)*$G$435+(CK$35=$G$445)*(AE11+$G$430-$O11-$G$435) -> 0 | CL37: =(CL$35=0)*($O11-$G$430)+(CL$35=$G$444)*$G$435+(CL$35=$G$445)*(AE11+$G$430-$O11-$G$435) -> 0 | CM37: =(CM$35=0)*($O11-$G$430)+(CM$35=$G$444)*$G$435+(CM$35=$G$445)*(AE11+$G$430-$O11-$G$435) -> 8325.2746 | CN37: =(CN$35=0)*($O11-$G$430)+(CN$35=$G$444)*$G$435+(CN$35=$G$445)*(AF11+$G$430-$O11-$G$435) -> -2350 | CO37: =(CO$35=0)*($O11-$G$430)+(CO$35=$G$444)*$G$435+(CO$35=$G$445)*(AF11+$G$430-$O11-$G$435) -> 0 | CP37: =(CP$35=0)*($O11-$G$430)+(CP$35=$G$444)*$G$435+(CP$35=$G$445)*(AF11+$G$430-$O11-$G$435) -> 0 | CQ37: =(CQ$35=0)*($O11-$G$430)+(CQ$35=$G$444)*$G$435+(CQ$35=$G$445)*(AF11+$G$430-$O11-$G$435) -> 0 | CR37: =(CR$35=0)*($O11-$G$430)+(CR$35=$G$444)*$G$435+(CR$35=$G$445)*(AF11+$G$430-$O11-$G$435) -> 0 | CS37: =(CS$35=0)*($O11-$G$430)+(CS$35=$G$444)*$G$435+(CS$35=$G$445)*(AF11+$G$430-$O11-$G$435) -> 8724.7457 | CT37: =(CT$35=0)*($O11-$G$430)+(CT$35=$G$444)*$G$435+(CT$35=$G$445)*(AG11+$G$430-$O11-$G$435) -> -2350 | CU37: =(CU$35=0)*($O11-$G$430)+(CU$35=$G$444)*$G$435+(CU$35=$G$445)*(AG11+$G$430-$O11-$G$435) -> 0 | CV37: =(CV$35=0)*($O11-$G$430)+(CV$35=$G$444)*$G$435+(CV$35=$G$445)*(AG11+$G$430-$O11-$G$435) -> 0 | CW37: =(CW$35=0)*($O11-$G$430)+(CW$35=$G$444)*$G$435+(CW$35=$G$445)*(AG11+$G$430-$O11-$G$435) -> 0 | CX37: =(CX$35=0)*($O11-$G$430)+(CX$35=$G$444)*$G$435+(CX$35=$G$445)*(AG11+$G$430-$O11-$G$435) -> 0 | CY37: =(CY$35=0)*($O11-$G$430)+(CY$35=$G$444)*$G$435+(CY$35=$G$445)*(AG11+$G$430-$O11-$G$435) -> 9124.2169 | CZ37: =(CZ$35=0)*($O11-$G$430)+(CZ$35=$G$444)*$G$435+(CZ$35=$G$445)*(AH11+$G$430-$O11-$G$435) -> -2350 | DA37: =(DA$35=0)*($O11-$G$430)+(DA$35=$G$444)*$G$435+(DA$35=$G$445)*(AH11+$G$430-$O11-$G$435) -> 0 | DB37: =(DB$35=0)*($O11-$G$430)+(DB$35=$G$444)*$G$435+(DB$35=$G$445)*(AH11+$G$430-$O11-$G$435) -> 0 | DC37: =(DC$35=0)*($O11-$G$430)+(DC$35=$G$444)*$G$435+(DC$35=$G$445)*(AH11+$G$430-$O11-$G$435) -> 0 | DD37: =(DD$35=0)*($O11-$G$430)+(DD$35=$G$444)*$G$435+(DD$35=$G$445)*(AH11+$G$430-$O11-$G$435) -> 0 | DE37: =(DE$35=0)*($O11-$G$430)+(DE$35=$G$444)*$G$435+(DE$35=$G$445)*(AH11+$G$430-$O11-$G$435) -> 9523.688
C38: =C39-$G$439 -> 0.25 | D38: =IFERROR(IRR(BD38:BI38),0) -> 0.23365346 | E38: =IFERROR(IRR(BJ38:BO38),0) -> 0.24682211 | F38: =IFERROR(IRR(BP38:BU38),0) -> 0.25945684 | G38: =IFERROR(IRR(BV38:CA38),0) -> 0.27160402 | H38: =IFERROR(IRR(CB38:CG38),0) -> 0.28330403 | I38: =IFERROR(IRR(CH38:CM38),0) -> 0.2945923 | J38: =IFERROR(IRR(CN38:CS38),0) -> 0.30550006 | K38: =IFERROR(IRR(CT38:CY38),0) -> 0.31605499 | L38: =IFERROR(IRR(CZ38:DE38),0) -> 0.3262818 | AT38: =IF(Z52<$G$449,0,MIN($G$446,1+IFERROR(INT((Z52-$G$449)/$G$451),0))) -> 0 | AU38: =IF(AA52<$G$449,0,MIN($G$446,1+IFERROR(INT((AA52-$G$449)/$G$451),0))) -> 0 | AV38: =IF(AB52<$G$449,0,MIN($G$446,1+IFERROR(INT((AB52-$G$449)/$G$451),0))) -> 0 | AW38: =IF(AC52<$G$449,0,MIN($G$446,1+IFERROR(INT((AC52-$G$449)/$G$451),0))) -> 0 | AX38: =IF(AD52<$G$449,0,MIN($G$446,1+IFERROR(INT((AD52-$G$449)/$G$451),0))) -> 2 | AY38: =IF(AE52<$G$449,0,MIN($G$446,1+IFERROR(INT((AE52-$G$449)/$G$451),0))) -> 4 | AZ38: =IF(AF52<$G$449,0,MIN($G$446,1+IFERROR(INT((AF52-$G$449)/$G$451),0))) -> 5 | BA38: =IF(AG52<$G$449,0,MIN($G$446,1+IFERROR(INT((AG52-$G$449)/$G$451),0))) -> 7 | BB38: =IF(AH52<$G$449,0,MIN($G$446,1+IFERROR(INT((AH52-$G$449)/$G$451),0))) -> 8 | BD38: =(BD$35=0)*($O12-$G$430)+(BD$35=$G$444)*$G$435+(BD$35=$G$445)*(Z12+$G$430-$O12-$G$435) -> -2350 | BE38: =(BE$35=0)*($O12-$G$430)+(BE$35=$G$444)*$G$435+(BE$35=$G$445)*(Z12+$G$430-$O12-$G$435) -> 0 | BF38: =(BF$35=0)*($O12-$G$430)+(BF$35=$G$444)*$G$435+(BF$35=$G$445)*(Z12+$G$430-$O12-$G$435) -> 0 | BG38: =(BG$35=0)*($O12-$G$430)+(BG$35=$G$444)*$G$435+(BG$35=$G$445)*(Z12+$G$430-$O12-$G$435) -> 0 | BH38: =(BH$35=0)*($O12-$G$430)+(BH$35=$G$444)*$G$435+(BH$35=$G$445)*(Z12+$G$430-$O12-$G$435) -> 0 | BI38: =(BI$35=0)*($O12-$G$430)+(BI$35=$G$444)*$G$435+(BI$35=$G$445)*(Z12+$G$430-$O12-$G$435) -> 6714.8105 | BJ38: =(BJ$35=0)*($O12-$G$430)+(BJ$35=$G$444)*$G$435+(BJ$35=$G$445)*(AA12+$G$430-$O12-$G$435) -> -2350 | BK38: =(BK$35=0)*($O12-$G$430)+(BK$35=$G$444)*$G$435+(BK$35=$G$445)*(AA12+$G$430-$O12-$G$435) -> 0 | BL38: =(BL$35=0)*($O12-$G$430)+(BL$35=$G$444)*$G$435+(BL$35=$G$445)*(AA12+$G$430-$O12-$G$435) -> 0 | BM38: =(BM$35=0)*($O12-$G$430)+(BM$35=$G$444)*$G$435+(BM$35=$G$445)*(AA12+$G$430-$O12-$G$435) -> 0 | BN38: =(BN$35=0)*($O12-$G$430)+(BN$35=$G$444)*$G$435+(BN$35=$G$445)*(AA12+$G$430-$O12-$G$435) -> 0 | BO38: =(BO$35=0)*($O12-$G$430)+(BO$35=$G$444)*$G$435+(BO$35=$G$445)*(AA12+$G$430-$O12-$G$435) -> 7080.9306 | BP38: =(BP$35=0)*($O12-$G$430)+(BP$35=$G$444)*$G$435+(BP$35=$G$445)*(AB12+$G$430-$O12-$G$435) -> -2350 | BQ38: =(BQ$35=0)*($O12-$G$430)+(BQ$35=$G$444)*$G$435+(BQ$35=$G$445)*(AB12+$G$430-$O12-$G$435) -> 0 | BR38: =(BR$35=0)*($O12-$G$430)+(BR$35=$G$444)*$G$435+(BR$35=$G$445)*(AB12+$G$430-$O12-$G$435) -> 0 | BS38: =(BS$35=0)*($O12-$G$430)+(BS$35=$G$444)*$G$435+(BS$35=$G$445)*(AB12+$G$430-$O12-$G$435) -> 0 | BT38: =(BT$35=0)*($O12-$G$430)+(BT$35=$G$444)*$G$435+(BT$35=$G$445)*(AB12+$G$430-$O12-$G$435) -> 0 | BU38: =(BU$35=0)*($O12-$G$430)+(BU$35=$G$444)*$G$435+(BU$35=$G$445)*(AB12+$G$430-$O12-$G$435) -> 7447.0508 | BV38: =(BV$35=0)*($O12-$G$430)+(BV$35=$G$444)*$G$435+(BV$35=$G$445)*(AC12+$G$430-$O12-$G$435) -> -2350 | BW38: =(BW$35=0)*($O12-$G$430)+(BW$35=$G$444)*$G$435+(BW$35=$G$445)*(AC12+$G$430-$O12-$G$435) -> 0 | BX38: =(BX$35=0)*($O12-$G$430)+(BX$35=$G$444)*$G$435+(BX$35=$G$445)*(AC12+$G$430-$O12-$G$435) -> 0 | BY38: =(BY$35=0)*($O12-$G$430)+(BY$35=$G$444)*$G$435+(BY$35=$G$445)*(AC12+$G$430-$O12-$G$435) -> 0 | BZ38: =(BZ$35=0)*($O12-$G$430)+(BZ$35=$G$444)*$G$435+(BZ$35=$G$445)*(AC12+$G$430-$O12-$G$435) -> 0 | CA38: =(CA$35=0)*($O12-$G$430)+(CA$35=$G$444)*$G$435+(CA$35=$G$445)*(AC12+$G$430-$O12-$G$435) -> 7813.1709 | CB38: =(CB$35=0)*($O12-$G$430)+(CB$35=$G$444)*$G$435+(CB$35=$G$445)*(AD12+$G$430-$O12-$G$435) -> -2350 | CC38: =(CC$35=0)*($O12-$G$430)+(CC$35=$G$444)*$G$435+(CC$35=$G$445)*(AD12+$G$430-$O12-$G$435) -> 0 | CD38: =(CD$35=0)*($O12-$G$430)+(CD$35=$G$444)*$G$435+(CD$35=$G$445)*(AD12+$G$430-$O12-$G$435) -> 0 | CE38: =(CE$35=0)*($O12-$G$430)+(CE$35=$G$444)*$G$435+(CE$35=$G$445)*(AD12+$G$430-$O12-$G$435) -> 0 | CF38: =(CF$35=0)*($O12-$G$430)+(CF$35=$G$444)*$G$435+(CF$35=$G$445)*(AD12+$G$430-$O12-$G$435) -> 0 | CG38: =(CG$35=0)*($O12-$G$430)+(CG$35=$G$444)*$G$435+(CG$35=$G$445)*(AD12+$G$430-$O12-$G$435) -> 8179.291 | CH38: =(CH$35=0)*($O12-$G$430)+(CH$35=$G$444)*$G$435+(CH$35=$G$445)*(AE12+$G$430-$O12-$G$435) -> -2350 | CI38: =(CI$35=0)*($O12-$G$430)+(CI$35=$G$444)*$G$435+(CI$35=$G$445)*(AE12+$G$430-$O12-$G$435) -> 0 | CJ38: =(CJ$35=0)*($O12-$G$430)+(CJ$35=$G$444)*$G$435+(CJ$35=$G$445)*(AE12+$G$430-$O12-$G$435) -> 0 | CK38: =(CK$35=0)*($O12-$G$430)+(CK$35=$G$444)*$G$435+(CK$35=$G$445)*(AE12+$G$430-$O12-$G$435) -> 0 | CL38: =(CL$35=0)*($O12-$G$430)+(CL$35=$G$444)*$G$435+(CL$35=$G$445)*(AE12+$G$430-$O12-$G$435) -> 0 | CM38: =(CM$35=0)*($O12-$G$430)+(CM$35=$G$444)*$G$435+(CM$35=$G$445)*(AE12+$G$430-$O12-$G$435) -> 8545.4112 | CN38: =(CN$35=0)*($O12-$G$430)+(CN$35=$G$444)*$G$435+(CN$35=$G$445)*(AF12+$G$430-$O12-$G$435) -> -2350 | CO38: =(CO$35=0)*($O12-$G$430)+(CO$35=$G$444)*$G$435+(CO$35=$G$445)*(AF12+$G$430-$O12-$G$435) -> 0 | CP38: =(CP$35=0)*($O12-$G$430)+(CP$35=$G$444)*$G$435+(CP$35=$G$445)*(AF12+$G$430-$O12-$G$435) -> 0 | CQ38: =(CQ$35=0)*($O12-$G$430)+(CQ$35=$G$444)*$G$435+(CQ$35=$G$445)*(AF12+$G$430-$O12-$G$435) -> 0 | CR38: =(CR$35=0)*($O12-$G$430)+(CR$35=$G$444)*$G$435+(CR$35=$G$445)*(AF12+$G$430-$O12-$G$435) -> 0 | CS38: =(CS$35=0)*($O12-$G$430)+(CS$35=$G$444)*$G$435+(CS$35=$G$445)*(AF12+$G$430-$O12-$G$435) -> 8911.5313 | CT38: =(CT$35=0)*($O12-$G$430)+(CT$35=$G$444)*$G$435+(CT$35=$G$445)*(AG12+$G$430-$O12-$G$435) -> -2350 | CU38: =(CU$35=0)*($O12-$G$430)+(CU$35=$G$444)*$G$435+(CU$35=$G$445)*(AG12+$G$430-$O12-$G$435) -> 0 | CV38: =(CV$35=0)*($O12-$G$430)+(CV$35=$G$444)*$G$435+(CV$35=$G$445)*(AG12+$G$430-$O12-$G$435) -> 0 | CW38: =(CW$35=0)*($O12-$G$430)+(CW$35=$G$444)*$G$435+(CW$35=$G$445)*(AG12+$G$430-$O12-$G$435) -> 0 | CX38: =(CX$35=0)*($O12-$G$430)+(CX$35=$G$444)*$G$435+(CX$35=$G$445)*(AG12+$G$430-$O12-$G$435) -> 0 | CY38: =(CY$35=0)*($O12-$G$430)+(CY$35=$G$444)*$G$435+(CY$35=$G$445)*(AG12+$G$430-$O12-$G$435) -> 9277.6514 | CZ38: =(CZ$35=0)*($O12-$G$430)+(CZ$35=$G$444)*$G$435+(CZ$35=$G$445)*(AH12+$G$430-$O12-$G$435) -> -2350 | DA38: =(DA$35=0)*($O12-$G$430)+(DA$35=$G$444)*$G$435+(DA$35=$G$445)*(AH12+$G$430-$O12-$G$435) -> 0 | DB38: =(DB$35=0)*($O12-$G$430)+(DB$35=$G$444)*$G$435+(DB$35=$G$445)*(AH12+$G$430-$O12-$G$435) -> 0 | DC38: =(DC$35=0)*($O12-$G$430)+(DC$35=$G$444)*$G$435+(DC$35=$G$445)*(AH12+$G$430-$O12-$G$435) -> 0 | DD38: =(DD$35=0)*($O12-$G$430)+(DD$35=$G$444)*$G$435+(DD$35=$G$445)*(AH12+$G$430-$O12-$G$435) -> 0 | DE38: =(DE$35=0)*($O12-$G$430)+(DE$35=$G$444)*$G$435+(DE$35=$G$445)*(AH12+$G$430-$O12-$G$435) -> 9643.7715
C39: =$G$438 -> 0.3 | D39: =IFERROR(IRR(BD39:BI39),0) -> 0.24761311 | E39: =IFERROR(IRR(BJ39:BO39),0) -> 0.25908374 | F39: =IFERROR(IRR(BP39:BU39),0) -> 0.27015098 | G39: =IFERROR(IRR(BV39:CA39),0) -> 0.28084542 | H39: =IFERROR(IRR(CB39:CG39),0) -> 0.29119417 | I39: =IFERROR(IRR(CH39:CM39),0) -> 0.3012214 | J39: =IFERROR(IRR(CN39:CS39),0) -> 0.31094875 | K39: =IFERROR(IRR(CT39:CY39),0) -> 0.32039568 | L39: =IFERROR(IRR(CZ39:DE39),0) -> 0.32957974 | AT39: =IF(Z53<$G$449,0,MIN($G$446,1+IFERROR(INT((Z53-$G$449)/$G$451),0))) -> 0 | AU39: =IF(AA53<$G$449,0,MIN($G$446,1+IFERROR(INT((AA53-$G$449)/$G$451),0))) -> 0 | AV39: =IF(AB53<$G$449,0,MIN($G$446,1+IFERROR(INT((AB53-$G$449)/$G$451),0))) -> 0 | AW39: =IF(AC53<$G$449,0,MIN($G$446,1+IFERROR(INT((AC53-$G$449)/$G$451),0))) -> 2 | AX39: =IF(AD53<$G$449,0,MIN($G$446,1+IFERROR(INT((AD53-$G$449)/$G$451),0))) -> 3 | AY39: =IF(AE53<$G$449,0,MIN($G$446,1+IFERROR(INT((AE53-$G$449)/$G$451),0))) -> 5 | AZ39: =IF(AF53<$G$449,0,MIN($G$446,1+IFERROR(INT((AF53-$G$449)/$G$451),0))) -> 6 | BA39: =IF(AG53<$G$449,0,MIN($G$446,1+IFERROR(INT((AG53-$G$449)/$G$451),0))) -> 7 | BB39: =IF(AH53<$G$449,0,MIN($G$446,1+IFERROR(INT((AH53-$G$449)/$G$451),0))) -> 9 | BD39: =(BD$35=0)*($O13-$G$430)+(BD$35=$G$444)*$G$435+(BD$35=$G$445)*(Z13+$G$430-$O13-$G$435) -> -2350 | BE39: =(BE$35=0)*($O13-$G$430)+(BE$35=$G$444)*$G$435+(BE$35=$G$445)*(Z13+$G$430-$O13-$G$435) -> 0 | BF39: =(BF$35=0)*($O13-$G$430)+(BF$35=$G$444)*$G$435+(BF$35=$G$445)*(Z13+$G$430-$O13-$G$435) -> 0 | BG39: =(BG$35=0)*($O13-$G$430)+(BG$35=$G$444)*$G$435+(BG$35=$G$445)*(Z13+$G$430-$O13-$G$435) -> 0 | BH39: =(BH$35=0)*($O13-$G$430)+(BH$35=$G$444)*$G$435+(BH$35=$G$445)*(Z13+$G$430-$O13-$G$435) -> 0 | BI39: =(BI$35=0)*($O13-$G$430)+(BI$35=$G$444)*$G$435+(BI$35=$G$445)*(Z13+$G$430-$O13-$G$435) -> 7103.4204 | BJ39: =(BJ$35=0)*($O13-$G$430)+(BJ$35=$G$444)*$G$435+(BJ$35=$G$445)*(AA13+$G$430-$O13-$G$435) -> -2350 | BK39: =(BK$35=0)*($O13-$G$430)+(BK$35=$G$444)*$G$435+(BK$35=$G$445)*(AA13+$G$430-$O13-$G$435) -> 0 | BL39: =(BL$35=0)*($O13-$G$430)+(BL$35=$G$444)*$G$435+(BL$35=$G$445)*(AA13+$G$430-$O13-$G$435) -> 0 | BM39: =(BM$35=0)*($O13-$G$430)+(BM$35=$G$444)*$G$435+(BM$35=$G$445)*(AA13+$G$430-$O13-$G$435) -> 0 | BN39: =(BN$35=0)*($O13-$G$430)+(BN$35=$G$444)*$G$435+(BN$35=$G$445)*(AA13+$G$430-$O13-$G$435) -> 0 | BO39: =(BO$35=0)*($O13-$G$430)+(BO$35=$G$444)*$G$435+(BO$35=$G$445)*(AA13+$G$430-$O13-$G$435) -> 7436.0267 | BP39: =(BP$35=0)*($O13-$G$430)+(BP$35=$G$444)*$G$435+(BP$35=$G$445)*(AB13+$G$430-$O13-$G$435) -> -2350 | BQ39: =(BQ$35=0)*($O13-$G$430)+(BQ$35=$G$444)*$G$435+(BQ$35=$G$445)*(AB13+$G$430-$O13-$G$435) -> 0 | BR39: =(BR$35=0)*($O13-$G$430)+(BR$35=$G$444)*$G$435+(BR$35=$G$445)*(AB13+$G$430-$O13-$G$435) -> 0 | BS39: =(BS$35=0)*($O13-$G$430)+(BS$35=$G$444)*$G$435+(BS$35=$G$445)*(AB13+$G$430-$O13-$G$435) -> 0 | BT39: =(BT$35=0)*($O13-$G$430)+(BT$35=$G$444)*$G$435+(BT$35=$G$445)*(AB13+$G$430-$O13-$G$435) -> 0 | BU39: =(BU$35=0)*($O13-$G$430)+(BU$35=$G$444)*$G$435+(BU$35=$G$445)*(AB13+$G$430-$O13-$G$435) -> 7768.633 | BV39: =(BV$35=0)*($O13-$G$430)+(BV$35=$G$444)*$G$435+(BV$35=$G$445)*(AC13+$G$430-$O13-$G$435) -> -2350 | BW39: =(BW$35=0)*($O13-$G$430)+(BW$35=$G$444)*$G$435+(BW$35=$G$445)*(AC13+$G$430-$O13-$G$435) -> 0 | BX39: =(BX$35=0)*($O13-$G$430)+(BX$35=$G$444)*$G$435+(BX$35=$G$445)*(AC13+$G$430-$O13-$G$435) -> 0 | BY39: =(BY$35=0)*($O13-$G$430)+(BY$35=$G$444)*$G$435+(BY$35=$G$445)*(AC13+$G$430-$O13-$G$435) -> 0 | BZ39: =(BZ$35=0)*($O13-$G$430)+(BZ$35=$G$444)*$G$435+(BZ$35=$G$445)*(AC13+$G$430-$O13-$G$435) -> 0 | CA39: =(CA$35=0)*($O13-$G$430)+(CA$35=$G$444)*$G$435+(CA$35=$G$445)*(AC13+$G$430-$O13-$G$435) -> 8101.2392 | CB39: =(CB$35=0)*($O13-$G$430)+(CB$35=$G$444)*$G$435+(CB$35=$G$445)*(AD13+$G$430-$O13-$G$435) -> -2350 | CC39: =(CC$35=0)*($O13-$G$430)+(CC$35=$G$444)*$G$435+(CC$35=$G$445)*(AD13+$G$430-$O13-$G$435) -> 0 | CD39: =(CD$35=0)*($O13-$G$430)+(CD$35=$G$444)*$G$435+(CD$35=$G$445)*(AD13+$G$430-$O13-$G$435) -> 0 | CE39: =(CE$35=0)*($O13-$G$430)+(CE$35=$G$444)*$G$435+(CE$35=$G$445)*(AD13+$G$430-$O13-$G$435) -> 0 | CF39: =(CF$35=0)*($O13-$G$430)+(CF$35=$G$444)*$G$435+(CF$35=$G$445)*(AD13+$G$430-$O13-$G$435) -> 0 | CG39: =(CG$35=0)*($O13-$G$430)+(CG$35=$G$444)*$G$435+(CG$35=$G$445)*(AD13+$G$430-$O13-$G$435) -> 8433.8455 | CH39: =(CH$35=0)*($O13-$G$430)+(CH$35=$G$444)*$G$435+(CH$35=$G$445)*(AE13+$G$430-$O13-$G$435) -> -2350 | CI39: =(CI$35=0)*($O13-$G$430)+(CI$35=$G$444)*$G$435+(CI$35=$G$445)*(AE13+$G$430-$O13-$G$435) -> 0 | CJ39: =(CJ$35=0)*($O13-$G$430)+(CJ$35=$G$444)*$G$435+(CJ$35=$G$445)*(AE13+$G$430-$O13-$G$435) -> 0 | CK39: =(CK$35=0)*($O13-$G$430)+(CK$35=$G$444)*$G$435+(CK$35=$G$445)*(AE13+$G$430-$O13-$G$435) -> 0 | CL39: =(CL$35=0)*($O13-$G$430)+(CL$35=$G$444)*$G$435+(CL$35=$G$445)*(AE13+$G$430-$O13-$G$435) -> 0 | CM39: =(CM$35=0)*($O13-$G$430)+(CM$35=$G$444)*$G$435+(CM$35=$G$445)*(AE13+$G$430-$O13-$G$435) -> 8766.4518 | CN39: =(CN$35=0)*($O13-$G$430)+(CN$35=$G$444)*$G$435+(CN$35=$G$445)*(AF13+$G$430-$O13-$G$435) -> -2350 | CO39: =(CO$35=0)*($O13-$G$430)+(CO$35=$G$444)*$G$435+(CO$35=$G$445)*(AF13+$G$430-$O13-$G$435) -> 0 | CP39: =(CP$35=0)*($O13-$G$430)+(CP$35=$G$444)*$G$435+(CP$35=$G$445)*(AF13+$G$430-$O13-$G$435) -> 0 | CQ39: =(CQ$35=0)*($O13-$G$430)+(CQ$35=$G$444)*$G$435+(CQ$35=$G$445)*(AF13+$G$430-$O13-$G$435) -> 0 | CR39: =(CR$35=0)*($O13-$G$430)+(CR$35=$G$444)*$G$435+(CR$35=$G$445)*(AF13+$G$430-$O13-$G$435) -> 0 | CS39: =(CS$35=0)*($O13-$G$430)+(CS$35=$G$444)*$G$435+(CS$35=$G$445)*(AF13+$G$430-$O13-$G$435) -> 9099.0581 | CT39: =(CT$35=0)*($O13-$G$430)+(CT$35=$G$444)*$G$435+(CT$35=$G$445)*(AG13+$G$430-$O13-$G$435) -> -2350 | CU39: =(CU$35=0)*($O13-$G$430)+(CU$35=$G$444)*$G$435+(CU$35=$G$445)*(AG13+$G$430-$O13-$G$435) -> 0 | CV39: =(CV$35=0)*($O13-$G$430)+(CV$35=$G$444)*$G$435+(CV$35=$G$445)*(AG13+$G$430-$O13-$G$435) -> 0 | CW39: =(CW$35=0)*($O13-$G$430)+(CW$35=$G$444)*$G$435+(CW$35=$G$445)*(AG13+$G$430-$O13-$G$435) -> 0 | CX39: =(CX$35=0)*($O13-$G$430)+(CX$35=$G$444)*$G$435+(CX$35=$G$445)*(AG13+$G$430-$O13-$G$435) -> 0 | CY39: =(CY$35=0)*($O13-$G$430)+(CY$35=$G$444)*$G$435+(CY$35=$G$445)*(AG13+$G$430-$O13-$G$435) -> 9431.6644 | CZ39: =(CZ$35=0)*($O13-$G$430)+(CZ$35=$G$444)*$G$435+(CZ$35=$G$445)*(AH13+$G$430-$O13-$G$435) -> -2350 | DA39: =(DA$35=0)*($O13-$G$430)+(DA$35=$G$444)*$G$435+(DA$35=$G$445)*(AH13+$G$430-$O13-$G$435) -> 0 | DB39: =(DB$35=0)*($O13-$G$430)+(DB$35=$G$444)*$G$435+(DB$35=$G$445)*(AH13+$G$430-$O13-$G$435) -> 0 | DC39: =(DC$35=0)*($O13-$G$430)+(DC$35=$G$444)*$G$435+(DC$35=$G$445)*(AH13+$G$430-$O13-$G$435) -> 0 | DD39: =(DD$35=0)*($O13-$G$430)+(DD$35=$G$444)*$G$435+(DD$35=$G$445)*(AH13+$G$430-$O13-$G$435) -> 0 | DE39: =(DE$35=0)*($O13-$G$430)+(DE$35=$G$444)*$G$435+(DE$35=$G$445)*(AH13+$G$430-$O13-$G$435) -> 9764.2707
C40: =C39+$G$439 -> 0.35 | D40: =IFERROR(IRR(BD40:BI40),0) -> 0.26103284 | E40: =IFERROR(IRR(BJ40:BO40),0) -> 0.27093664 | F40: =IFERROR(IRR(BP40:BU40),0) -> 0.28054104 | G40: =IFERROR(IRR(BV40:CA40),0) -> 0.28986564 | H40: =IFERROR(IRR(CB40:CG40),0) -> 0.29892816 | I40: =IFERROR(IRR(CH40:CM40),0) -> 0.3077446 | J40: =IFERROR(IRR(CN40:CS40),0) -> 0.31632951 | K40: =IFERROR(IRR(CT40:CY40),0) -> 0.32469613 | L40: =IFERROR(IRR(CZ40:DE40),0) -> 0.33285657 | AT40: =IF(Z54<$G$449,0,MIN($G$446,1+IFERROR(INT((Z54-$G$449)/$G$451),0))) -> 0 | AU40: =IF(AA54<$G$449,0,MIN($G$446,1+IFERROR(INT((AA54-$G$449)/$G$451),0))) -> 0 | AV40: =IF(AB54<$G$449,0,MIN($G$446,1+IFERROR(INT((AB54-$G$449)/$G$451),0))) -> 2 | AW40: =IF(AC54<$G$449,0,MIN($G$446,1+IFERROR(INT((AC54-$G$449)/$G$451),0))) -> 3 | AX40: =IF(AD54<$G$449,0,MIN($G$446,1+IFERROR(INT((AD54-$G$449)/$G$451),0))) -> 4 | AY40: =IF(AE54<$G$449,0,MIN($G$446,1+IFERROR(INT((AE54-$G$449)/$G$451),0))) -> 6 | AZ40: =IF(AF54<$G$449,0,MIN($G$446,1+IFERROR(INT((AF54-$G$449)/$G$451),0))) -> 7 | BA40: =IF(AG54<$G$449,0,MIN($G$446,1+IFERROR(INT((AG54-$G$449)/$G$451),0))) -> 8 | BB40: =IF(AH54<$G$449,0,MIN($G$446,1+IFERROR(INT((AH54-$G$449)/$G$451),0))) -> 9 | BD40: =(BD$35=0)*($O14-$G$430)+(BD$35=$G$444)*$G$435+(BD$35=$G$445)*(Z14+$G$430-$O14-$G$435) -> -2350 | BE40: =(BE$35=0)*($O14-$G$430)+(BE$35=$G$444)*$G$435+(BE$35=$G$445)*(Z14+$G$430-$O14-$G$435) -> 0 | BF40: =(BF$35=0)*($O14-$G$430)+(BF$35=$G$444)*$G$435+(BF$35=$G$445)*(Z14+$G$430-$O14-$G$435) -> 0 | BG40: =(BG$35=0)*($O14-$G$430)+(BG$35=$G$444)*$G$435+(BG$35=$G$445)*(Z14+$G$430-$O14-$G$435) -> 0 | BH40: =(BH$35=0)*($O14-$G$430)+(BH$35=$G$444)*$G$435+(BH$35=$G$445)*(Z14+$G$430-$O14-$G$435) -> 0 | BI40: =(BI$35=0)*($O14-$G$430)+(BI$35=$G$444)*$G$435+(BI$35=$G$445)*(Z14+$G$430-$O14-$G$435) -> 7493.7611 | BJ40: =(BJ$35=0)*($O14-$G$430)+(BJ$35=$G$444)*$G$435+(BJ$35=$G$445)*(AA14+$G$430-$O14-$G$435) -> -2350 | BK40: =(BK$35=0)*($O14-$G$430)+(BK$35=$G$444)*$G$435+(BK$35=$G$445)*(AA14+$G$430-$O14-$G$435) -> 0 | BL40: =(BL$35=0)*($O14-$G$430)+(BL$35=$G$444)*$G$435+(BL$35=$G$445)*(AA14+$G$430-$O14-$G$435) -> 0 | BM40: =(BM$35=0)*($O14-$G$430)+(BM$35=$G$444)*$G$435+(BM$35=$G$445)*(AA14+$G$430-$O14-$G$435) -> 0 | BN40: =(BN$35=0)*($O14-$G$430)+(BN$35=$G$444)*$G$435+(BN$35=$G$445)*(AA14+$G$430-$O14-$G$435) -> 0 | BO40: =(BO$35=0)*($O14-$G$430)+(BO$35=$G$444)*$G$435+(BO$35=$G$445)*(AA14+$G$430-$O14-$G$435) -> 7792.6895 | BP40: =(BP$35=0)*($O14-$G$430)+(BP$35=$G$444)*$G$435+(BP$35=$G$445)*(AB14+$G$430-$O14-$G$435) -> -2350 | BQ40: =(BQ$35=0)*($O14-$G$430)+(BQ$35=$G$444)*$G$435+(BQ$35=$G$445)*(AB14+$G$430-$O14-$G$435) -> 0 | BR40: =(BR$35=0)*($O14-$G$430)+(BR$35=$G$444)*$G$435+(BR$35=$G$445)*(AB14+$G$430-$O14-$G$435) -> 0 | BS40: =(BS$35=0)*($O14-$G$430)+(BS$35=$G$444)*$G$435+(BS$35=$G$445)*(AB14+$G$430-$O14-$G$435) -> 0 | BT40: =(BT$35=0)*($O14-$G$430)+(BT$35=$G$444)*$G$435+(BT$35=$G$445)*(AB14+$G$430-$O14-$G$435) -> 0 | BU40: =(BU$35=0)*($O14-$G$430)+(BU$35=$G$444)*$G$435+(BU$35=$G$445)*(AB14+$G$430-$O14-$G$435) -> 8091.6179 | BV40: =(BV$35=0)*($O14-$G$430)+(BV$35=$G$444)*$G$435+(BV$35=$G$445)*(AC14+$G$430-$O14-$G$435) -> -2350 | BW40: =(BW$35=0)*($O14-$G$430)+(BW$35=$G$444)*$G$435+(BW$35=$G$445)*(AC14+$G$430-$O14-$G$435) -> 0 | BX40: =(BX$35=0)*($O14-$G$430)+(BX$35=$G$444)*$G$435+(BX$35=$G$445)*(AC14+$G$430-$O14-$G$435) -> 0 | BY40: =(BY$35=0)*($O14-$G$430)+(BY$35=$G$444)*$G$435+(BY$35=$G$445)*(AC14+$G$430-$O14-$G$435) -> 0 | BZ40: =(BZ$35=0)*($O14-$G$430)+(BZ$35=$G$444)*$G$435+(BZ$35=$G$445)*(AC14+$G$430-$O14-$G$435) -> 0 | CA40: =(CA$35=0)*($O14-$G$430)+(CA$35=$G$444)*$G$435+(CA$35=$G$445)*(AC14+$G$430-$O14-$G$435) -> 8390.5463 | CB40: =(CB$35=0)*($O14-$G$430)+(CB$35=$G$444)*$G$435+(CB$35=$G$445)*(AD14+$G$430-$O14-$G$435) -> -2350 | CC40: =(CC$35=0)*($O14-$G$430)+(CC$35=$G$444)*$G$435+(CC$35=$G$445)*(AD14+$G$430-$O14-$G$435) -> 0 | CD40: =(CD$35=0)*($O14-$G$430)+(CD$35=$G$444)*$G$435+(CD$35=$G$445)*(AD14+$G$430-$O14-$G$435) -> 0 | CE40: =(CE$35=0)*($O14-$G$430)+(CE$35=$G$444)*$G$435+(CE$35=$G$445)*(AD14+$G$430-$O14-$G$435) -> 0 | CF40: =(CF$35=0)*($O14-$G$430)+(CF$35=$G$444)*$G$435+(CF$35=$G$445)*(AD14+$G$430-$O14-$G$435) -> 0 | CG40: =(CG$35=0)*($O14-$G$430)+(CG$35=$G$444)*$G$435+(CG$35=$G$445)*(AD14+$G$430-$O14-$G$435) -> 8689.4748 | CH40: =(CH$35=0)*($O14-$G$430)+(CH$35=$G$444)*$G$435+(CH$35=$G$445)*(AE14+$G$430-$O14-$G$435) -> -2350 | CI40: =(CI$35=0)*($O14-$G$430)+(CI$35=$G$444)*$G$435+(CI$35=$G$445)*(AE14+$G$430-$O14-$G$435) -> 0 | CJ40: =(CJ$35=0)*($O14-$G$430)+(CJ$35=$G$444)*$G$435+(CJ$35=$G$445)*(AE14+$G$430-$O14-$G$435) -> 0 | CK40: =(CK$35=0)*($O14-$G$430)+(CK$35=$G$444)*$G$435+(CK$35=$G$445)*(AE14+$G$430-$O14-$G$435) -> 0 | CL40: =(CL$35=0)*($O14-$G$430)+(CL$35=$G$444)*$G$435+(CL$35=$G$445)*(AE14+$G$430-$O14-$G$435) -> 0 | CM40: =(CM$35=0)*($O14-$G$430)+(CM$35=$G$444)*$G$435+(CM$35=$G$445)*(AE14+$G$430-$O14-$G$435) -> 8988.4032 | CN40: =(CN$35=0)*($O14-$G$430)+(CN$35=$G$444)*$G$435+(CN$35=$G$445)*(AF14+$G$430-$O14-$G$435) -> -2350 | CO40: =(CO$35=0)*($O14-$G$430)+(CO$35=$G$444)*$G$435+(CO$35=$G$445)*(AF14+$G$430-$O14-$G$435) -> 0 | CP40: =(CP$35=0)*($O14-$G$430)+(CP$35=$G$444)*$G$435+(CP$35=$G$445)*(AF14+$G$430-$O14-$G$435) -> 0 | CQ40: =(CQ$35=0)*($O14-$G$430)+(CQ$35=$G$444)*$G$435+(CQ$35=$G$445)*(AF14+$G$430-$O14-$G$435) -> 0 | CR40: =(CR$35=0)*($O14-$G$430)+(CR$35=$G$444)*$G$435+(CR$35=$G$445)*(AF14+$G$430-$O14-$G$435) -> 0 | CS40: =(CS$35=0)*($O14-$G$430)+(CS$35=$G$444)*$G$435+(CS$35=$G$445)*(AF14+$G$430-$O14-$G$435) -> 9287.3316 | CT40: =(CT$35=0)*($O14-$G$430)+(CT$35=$G$444)*$G$435+(CT$35=$G$445)*(AG14+$G$430-$O14-$G$435) -> -2350 | CU40: =(CU$35=0)*($O14-$G$430)+(CU$35=$G$444)*$G$435+(CU$35=$G$445)*(AG14+$G$430-$O14-$G$435) -> 0 | CV40: =(CV$35=0)*($O14-$G$430)+(CV$35=$G$444)*$G$435+(CV$35=$G$445)*(AG14+$G$430-$O14-$G$435) -> 0 | CW40: =(CW$35=0)*($O14-$G$430)+(CW$35=$G$444)*$G$435+(CW$35=$G$445)*(AG14+$G$430-$O14-$G$435) -> 0 | CX40: =(CX$35=0)*($O14-$G$430)+(CX$35=$G$444)*$G$435+(CX$35=$G$445)*(AG14+$G$430-$O14-$G$435) -> 0 | CY40: =(CY$35=0)*($O14-$G$430)+(CY$35=$G$444)*$G$435+(CY$35=$G$445)*(AG14+$G$430-$O14-$G$435) -> 9586.26 | CZ40: =(CZ$35=0)*($O14-$G$430)+(CZ$35=$G$444)*$G$435+(CZ$35=$G$445)*(AH14+$G$430-$O14-$G$435) -> -2350 | DA40: =(DA$35=0)*($O14-$G$430)+(DA$35=$G$444)*$G$435+(DA$35=$G$445)*(AH14+$G$430-$O14-$G$435) -> 0 | DB40: =(DB$35=0)*($O14-$G$430)+(DB$35=$G$444)*$G$435+(DB$35=$G$445)*(AH14+$G$430-$O14-$G$435) -> 0 | DC40: =(DC$35=0)*($O14-$G$430)+(DC$35=$G$444)*$G$435+(DC$35=$G$445)*(AH14+$G$430-$O14-$G$435) -> 0 | DD40: =(DD$35=0)*($O14-$G$430)+(DD$35=$G$444)*$G$435+(DD$35=$G$445)*(AH14+$G$430-$O14-$G$435) -> 0 | DE40: =(DE$35=0)*($O14-$G$430)+(DE$35=$G$444)*$G$435+(DE$35=$G$445)*(AH14+$G$430-$O14-$G$435) -> 9885.1885
C41: =C40+$G$439 -> 0.4 | D41: =IFERROR(IRR(BD41:BI41),0) -> 0.27396084 | E41: =IFERROR(IRR(BJ41:BO41),0) -> 0.28241287 | F41: =IFERROR(IRR(BP41:BU41),0) -> 0.29064778 | G41: =IFERROR(IRR(BV41:CA41),0) -> 0.29867773 | H41: =IFERROR(IRR(CB41:CG41),0) -> 0.30651385 | I41: =IFERROR(IRR(CH41:CM41),0) -> 0.31416637 | J41: =IFERROR(IRR(CN41:CS41),0) -> 0.32164468 | K41: =IFERROR(IRR(CT41:CY41),0) -> 0.32895747 | L41: =IFERROR(IRR(CZ41:DE41),0) -> 0.33611276 | AT41: =IF(Z55<$G$449,0,MIN($G$446,1+IFERROR(INT((Z55-$G$449)/$G$451),0))) -> 1 | AU41: =IF(AA55<$G$449,0,MIN($G$446,1+IFERROR(INT((AA55-$G$449)/$G$451),0))) -> 2 | AV41: =IF(AB55<$G$449,0,MIN($G$446,1+IFERROR(INT((AB55-$G$449)/$G$451),0))) -> 3 | AW41: =IF(AC55<$G$449,0,MIN($G$446,1+IFERROR(INT((AC55-$G$449)/$G$451),0))) -> 4 | AX41: =IF(AD55<$G$449,0,MIN($G$446,1+IFERROR(INT((AD55-$G$449)/$G$451),0))) -> 5 | AY41: =IF(AE55<$G$449,0,MIN($G$446,1+IFERROR(INT((AE55-$G$449)/$G$451),0))) -> 6 | AZ41: =IF(AF55<$G$449,0,MIN($G$446,1+IFERROR(INT((AF55-$G$449)/$G$451),0))) -> 8 | BA41: =IF(AG55<$G$449,0,MIN($G$446,1+IFERROR(INT((AG55-$G$449)/$G$451),0))) -> 9 | BB41: =IF(AH55<$G$449,0,MIN($G$446,1+IFERROR(INT((AH55-$G$449)/$G$451),0))) -> 10 | BD41: =(BD$35=0)*($O15-$G$430)+(BD$35=$G$444)*$G$435+(BD$35=$G$445)*(Z15+$G$430-$O15-$G$435) -> -2350 | BE41: =(BE$35=0)*($O15-$G$430)+(BE$35=$G$444)*$G$435+(BE$35=$G$445)*(Z15+$G$430-$O15-$G$435) -> 0 | BF41: =(BF$35=0)*($O15-$G$430)+(BF$35=$G$444)*$G$435+(BF$35=$G$445)*(Z15+$G$430-$O15-$G$435) -> 0 | BG41: =(BG$35=0)*($O15-$G$430)+(BG$35=$G$444)*$G$435+(BG$35=$G$445)*(Z15+$G$430-$O15-$G$435) -> 0 | BH41: =(BH$35=0)*($O15-$G$430)+(BH$35=$G$444)*$G$435+(BH$35=$G$445)*(Z15+$G$430-$O15-$G$435) -> 0 | BI41: =(BI$35=0)*($O15-$G$430)+(BI$35=$G$444)*$G$435+(BI$35=$G$445)*(Z15+$G$430-$O15-$G$435) -> 7885.8453 | BJ41: =(BJ$35=0)*($O15-$G$430)+(BJ$35=$G$444)*$G$435+(BJ$35=$G$445)*(AA15+$G$430-$O15-$G$435) -> -2350 | BK41: =(BK$35=0)*($O15-$G$430)+(BK$35=$G$444)*$G$435+(BK$35=$G$445)*(AA15+$G$430-$O15-$G$435) -> 0 | BL41: =(BL$35=0)*($O15-$G$430)+(BL$35=$G$444)*$G$435+(BL$35=$G$445)*(AA15+$G$430-$O15-$G$435) -> 0 | BM41: =(BM$35=0)*($O15-$G$430)+(BM$35=$G$444)*$G$435+(BM$35=$G$445)*(AA15+$G$430-$O15-$G$435) -> 0 | BN41: =(BN$35=0)*($O15-$G$430)+(BN$35=$G$444)*$G$435+(BN$35=$G$445)*(AA15+$G$430-$O15-$G$435) -> 0 | BO41: =(BO$35=0)*($O15-$G$430)+(BO$35=$G$444)*$G$435+(BO$35=$G$445)*(AA15+$G$430-$O15-$G$435) -> 8150.9306 | BP41: =(BP$35=0)*($O15-$G$430)+(BP$35=$G$444)*$G$435+(BP$35=$G$445)*(AB15+$G$430-$O15-$G$435) -> -2350 | BQ41: =(BQ$35=0)*($O15-$G$430)+(BQ$35=$G$444)*$G$435+(BQ$35=$G$445)*(AB15+$G$430-$O15-$G$435) -> 0 | BR41: =(BR$35=0)*($O15-$G$430)+(BR$35=$G$444)*$G$435+(BR$35=$G$445)*(AB15+$G$430-$O15-$G$435) -> 0 | BS41: =(BS$35=0)*($O15-$G$430)+(BS$35=$G$444)*$G$435+(BS$35=$G$445)*(AB15+$G$430-$O15-$G$435) -> 0 | BT41: =(BT$35=0)*($O15-$G$430)+(BT$35=$G$444)*$G$435+(BT$35=$G$445)*(AB15+$G$430-$O15-$G$435) -> 0 | BU41: =(BU$35=0)*($O15-$G$430)+(BU$35=$G$444)*$G$435+(BU$35=$G$445)*(AB15+$G$430-$O15-$G$435) -> 8416.016 | BV41: =(BV$35=0)*($O15-$G$430)+(BV$35=$G$444)*$G$435+(BV$35=$G$445)*(AC15+$G$430-$O15-$G$435) -> -2350 | BW41: =(BW$35=0)*($O15-$G$430)+(BW$35=$G$444)*$G$435+(BW$35=$G$445)*(AC15+$G$430-$O15-$G$435) -> 0 | BX41: =(BX$35=0)*($O15-$G$430)+(BX$35=$G$444)*$G$435+(BX$35=$G$445)*(AC15+$G$430-$O15-$G$435) -> 0 | BY41: =(BY$35=0)*($O15-$G$430)+(BY$35=$G$444)*$G$435+(BY$35=$G$445)*(AC15+$G$430-$O15-$G$435) -> 0 | BZ41: =(BZ$35=0)*($O15-$G$430)+(BZ$35=$G$444)*$G$435+(BZ$35=$G$445)*(AC15+$G$430-$O15-$G$435) -> 0 | CA41: =(CA$35=0)*($O15-$G$430)+(CA$35=$G$444)*$G$435+(CA$35=$G$445)*(AC15+$G$430-$O15-$G$435) -> 8681.1013 | CB41: =(CB$35=0)*($O15-$G$430)+(CB$35=$G$444)*$G$435+(CB$35=$G$445)*(AD15+$G$430-$O15-$G$435) -> -2350 | CC41: =(CC$35=0)*($O15-$G$430)+(CC$35=$G$444)*$G$435+(CC$35=$G$445)*(AD15+$G$430-$O15-$G$435) -> 0 | CD41: =(CD$35=0)*($O15-$G$430)+(CD$35=$G$444)*$G$435+(CD$35=$G$445)*(AD15+$G$430-$O15-$G$435) -> 0 | CE41: =(CE$35=0)*($O15-$G$430)+(CE$35=$G$444)*$G$435+(CE$35=$G$445)*(AD15+$G$430-$O15-$G$435) -> 0 | CF41: =(CF$35=0)*($O15-$G$430)+(CF$35=$G$444)*$G$435+(CF$35=$G$445)*(AD15+$G$430-$O15-$G$435) -> 0 | CG41: =(CG$35=0)*($O15-$G$430)+(CG$35=$G$444)*$G$435+(CG$35=$G$445)*(AD15+$G$430-$O15-$G$435) -> 8946.1867 | CH41: =(CH$35=0)*($O15-$G$430)+(CH$35=$G$444)*$G$435+(CH$35=$G$445)*(AE15+$G$430-$O15-$G$435) -> -2350 | CI41: =(CI$35=0)*($O15-$G$430)+(CI$35=$G$444)*$G$435+(CI$35=$G$445)*(AE15+$G$430-$O15-$G$435) -> 0 | CJ41: =(CJ$35=0)*($O15-$G$430)+(CJ$35=$G$444)*$G$435+(CJ$35=$G$445)*(AE15+$G$430-$O15-$G$435) -> 0 | CK41: =(CK$35=0)*($O15-$G$430)+(CK$35=$G$444)*$G$435+(CK$35=$G$445)*(AE15+$G$430-$O15-$G$435) -> 0 | CL41: =(CL$35=0)*($O15-$G$430)+(CL$35=$G$444)*$G$435+(CL$35=$G$445)*(AE15+$G$430-$O15-$G$435) -> 0 | CM41: =(CM$35=0)*($O15-$G$430)+(CM$35=$G$444)*$G$435+(CM$35=$G$445)*(AE15+$G$430-$O15-$G$435) -> 9211.272 | CN41: =(CN$35=0)*($O15-$G$430)+(CN$35=$G$444)*$G$435+(CN$35=$G$445)*(AF15+$G$430-$O15-$G$435) -> -2350 | CO41: =(CO$35=0)*($O15-$G$430)+(CO$35=$G$444)*$G$435+(CO$35=$G$445)*(AF15+$G$430-$O15-$G$435) -> 0 | CP41: =(CP$35=0)*($O15-$G$430)+(CP$35=$G$444)*$G$435+(CP$35=$G$445)*(AF15+$G$430-$O15-$G$435) -> 0 | CQ41: =(CQ$35=0)*($O15-$G$430)+(CQ$35=$G$444)*$G$435+(CQ$35=$G$445)*(AF15+$G$430-$O15-$G$435) -> 0 | CR41: =(CR$35=0)*($O15-$G$430)+(CR$35=$G$444)*$G$435+(CR$35=$G$445)*(AF15+$G$430-$O15-$G$435) -> 0 | CS41: =(CS$35=0)*($O15-$G$430)+(CS$35=$G$444)*$G$435+(CS$35=$G$445)*(AF15+$G$430-$O15-$G$435) -> 9476.3573 | CT41: =(CT$35=0)*($O15-$G$430)+(CT$35=$G$444)*$G$435+(CT$35=$G$445)*(AG15+$G$430-$O15-$G$435) -> -2350 | CU41: =(CU$35=0)*($O15-$G$430)+(CU$35=$G$444)*$G$435+(CU$35=$G$445)*(AG15+$G$430-$O15-$G$435) -> 0 | CV41: =(CV$35=0)*($O15-$G$430)+(CV$35=$G$444)*$G$435+(CV$35=$G$445)*(AG15+$G$430-$O15-$G$435) -> 0 | CW41: =(CW$35=0)*($O15-$G$430)+(CW$35=$G$444)*$G$435+(CW$35=$G$445)*(AG15+$G$430-$O15-$G$435) -> 0 | CX41: =(CX$35=0)*($O15-$G$430)+(CX$35=$G$444)*$G$435+(CX$35=$G$445)*(AG15+$G$430-$O15-$G$435) -> 0 | CY41: =(CY$35=0)*($O15-$G$430)+(CY$35=$G$444)*$G$435+(CY$35=$G$445)*(AG15+$G$430-$O15-$G$435) -> 9741.4427 | CZ41: =(CZ$35=0)*($O15-$G$430)+(CZ$35=$G$444)*$G$435+(CZ$35=$G$445)*(AH15+$G$430-$O15-$G$435) -> -2350 | DA41: =(DA$35=0)*($O15-$G$430)+(DA$35=$G$444)*$G$435+(DA$35=$G$445)*(AH15+$G$430-$O15-$G$435) -> 0 | DB41: =(DB$35=0)*($O15-$G$430)+(DB$35=$G$444)*$G$435+(DB$35=$G$445)*(AH15+$G$430-$O15-$G$435) -> 0 | DC41: =(DC$35=0)*($O15-$G$430)+(DC$35=$G$444)*$G$435+(DC$35=$G$445)*(AH15+$G$430-$O15-$G$435) -> 0 | DD41: =(DD$35=0)*($O15-$G$430)+(DD$35=$G$444)*$G$435+(DD$35=$G$445)*(AH15+$G$430-$O15-$G$435) -> 0 | DE41: =(DE$35=0)*($O15-$G$430)+(DE$35=$G$444)*$G$435+(DE$35=$G$445)*(AH15+$G$430-$O15-$G$435) -> 10006.528
C42: =C41+$G$439 -> 0.45 | D42: =IFERROR(IRR(BD42:BI42),0) -> 0.28643901 | E42: =IFERROR(IRR(BJ42:BO42),0) -> 0.29354075 | F42: =IFERROR(IRR(BP42:BU42),0) -> 0.30048987 | G42: =IFERROR(IRR(BV42:CA42),0) -> 0.30729356 | H42: =IFERROR(IRR(CB42:CG42),0) -> 0.3139585 | I42: =IFERROR(IRR(CH42:CM42),0) -> 0.32049088 | J42: =IFERROR(IRR(CN42:CS42),0) -> 0.32689651 | K42: =IFERROR(IRR(CT42:CY42),0) -> 0.33318078 | L42: =IFERROR(IRR(CZ42:DE42),0) -> 0.33934874 | AT42: =IF(Z56<$G$449,0,MIN($G$446,1+IFERROR(INT((Z56-$G$449)/$G$451),0))) -> 2 | AU42: =IF(AA56<$G$449,0,MIN($G$446,1+IFERROR(INT((AA56-$G$449)/$G$451),0))) -> 3 | AV42: =IF(AB56<$G$449,0,MIN($G$446,1+IFERROR(INT((AB56-$G$449)/$G$451),0))) -> 4 | AW42: =IF(AC56<$G$449,0,MIN($G$446,1+IFERROR(INT((AC56-$G$449)/$G$451),0))) -> 5 | AX42: =IF(AD56<$G$449,0,MIN($G$446,1+IFERROR(INT((AD56-$G$449)/$G$451),0))) -> 6 | AY42: =IF(AE56<$G$449,0,MIN($G$446,1+IFERROR(INT((AE56-$G$449)/$G$451),0))) -> 7 | AZ42: =IF(AF56<$G$449,0,MIN($G$446,1+IFERROR(INT((AF56-$G$449)/$G$451),0))) -> 8 | BA42: =IF(AG56<$G$449,0,MIN($G$446,1+IFERROR(INT((AG56-$G$449)/$G$451),0))) -> 9 | BB42: =IF(AH56<$G$449,0,MIN($G$446,1+IFERROR(INT((AH56-$G$449)/$G$451),0))) -> 10 | BD42: =(BD$35=0)*($O16-$G$430)+(BD$35=$G$444)*$G$435+(BD$35=$G$445)*(Z16+$G$430-$O16-$G$435) -> -2350 | BE42: =(BE$35=0)*($O16-$G$430)+(BE$35=$G$444)*$G$435+(BE$35=$G$445)*(Z16+$G$430-$O16-$G$435) -> 0 | BF42: =(BF$35=0)*($O16-$G$430)+(BF$35=$G$444)*$G$435+(BF$35=$G$445)*(Z16+$G$430-$O16-$G$435) -> 0 | BG42: =(BG$35=0)*($O16-$G$430)+(BG$35=$G$444)*$G$435+(BG$35=$G$445)*(Z16+$G$430-$O16-$G$435) -> 0 | BH42: =(BH$35=0)*($O16-$G$430)+(BH$35=$G$444)*$G$435+(BH$35=$G$445)*(Z16+$G$430-$O16-$G$435) -> 0 | BI42: =(BI$35=0)*($O16-$G$430)+(BI$35=$G$444)*$G$435+(BI$35=$G$445)*(Z16+$G$430-$O16-$G$435) -> 8279.6859 | BJ42: =(BJ$35=0)*($O16-$G$430)+(BJ$35=$G$444)*$G$435+(BJ$35=$G$445)*(AA16+$G$430-$O16-$G$435) -> -2350 | BK42: =(BK$35=0)*($O16-$G$430)+(BK$35=$G$444)*$G$435+(BK$35=$G$445)*(AA16+$G$430-$O16-$G$435) -> 0 | BL42: =(BL$35=0)*($O16-$G$430)+(BL$35=$G$444)*$G$435+(BL$35=$G$445)*(AA16+$G$430-$O16-$G$435) -> 0 | BM42: =(BM$35=0)*($O16-$G$430)+(BM$35=$G$444)*$G$435+(BM$35=$G$445)*(AA16+$G$430-$O16-$G$435) -> 0 | BN42: =(BN$35=0)*($O16-$G$430)+(BN$35=$G$444)*$G$435+(BN$35=$G$445)*(AA16+$G$430-$O16-$G$435) -> 0 | BO42: =(BO$35=0)*($O16-$G$430)+(BO$35=$G$444)*$G$435+(BO$35=$G$445)*(AA16+$G$430-$O16-$G$435) -> 8510.7617 | BP42: =(BP$35=0)*($O16-$G$430)+(BP$35=$G$444)*$G$435+(BP$35=$G$445)*(AB16+$G$430-$O16-$G$435) -> -2350 | BQ42: =(BQ$35=0)*($O16-$G$430)+(BQ$35=$G$444)*$G$435+(BQ$35=$G$445)*(AB16+$G$430-$O16-$G$435) -> 0 | BR42: =(BR$35=0)*($O16-$G$430)+(BR$35=$G$444)*$G$435+(BR$35=$G$445)*(AB16+$G$430-$O16-$G$435) -> 0 | BS42: =(BS$35=0)*($O16-$G$430)+(BS$35=$G$444)*$G$435+(BS$35=$G$445)*(AB16+$G$430-$O16-$G$435) -> 0 | BT42: =(BT$35=0)*($O16-$G$430)+(BT$35=$G$444)*$G$435+(BT$35=$G$445)*(AB16+$G$430-$O16-$G$435) -> 0 | BU42: =(BU$35=0)*($O16-$G$430)+(BU$35=$G$444)*$G$435+(BU$35=$G$445)*(AB16+$G$430-$O16-$G$435) -> 8741.8375 | BV42: =(BV$35=0)*($O16-$G$430)+(BV$35=$G$444)*$G$435+(BV$35=$G$445)*(AC16+$G$430-$O16-$G$435) -> -2350 | BW42: =(BW$35=0)*($O16-$G$430)+(BW$35=$G$444)*$G$435+(BW$35=$G$445)*(AC16+$G$430-$O16-$G$435) -> 0 | BX42: =(BX$35=0)*($O16-$G$430)+(BX$35=$G$444)*$G$435+(BX$35=$G$445)*(AC16+$G$430-$O16-$G$435) -> 0 | BY42: =(BY$35=0)*($O16-$G$430)+(BY$35=$G$444)*$G$435+(BY$35=$G$445)*(AC16+$G$430-$O16-$G$435) -> 0 | BZ42: =(BZ$35=0)*($O16-$G$430)+(BZ$35=$G$444)*$G$435+(BZ$35=$G$445)*(AC16+$G$430-$O16-$G$435) -> 0 | CA42: =(CA$35=0)*($O16-$G$430)+(CA$35=$G$444)*$G$435+(CA$35=$G$445)*(AC16+$G$430-$O16-$G$435) -> 8972.9133 | CB42: =(CB$35=0)*($O16-$G$430)+(CB$35=$G$444)*$G$435+(CB$35=$G$445)*(AD16+$G$430-$O16-$G$435) -> -2350 | CC42: =(CC$35=0)*($O16-$G$430)+(CC$35=$G$444)*$G$435+(CC$35=$G$445)*(AD16+$G$430-$O16-$G$435) -> 0 | CD42: =(CD$35=0)*($O16-$G$430)+(CD$35=$G$444)*$G$435+(CD$35=$G$445)*(AD16+$G$430-$O16-$G$435) -> 0 | CE42: =(CE$35=0)*($O16-$G$430)+(CE$35=$G$444)*$G$435+(CE$35=$G$445)*(AD16+$G$430-$O16-$G$435) -> 0 | CF42: =(CF$35=0)*($O16-$G$430)+(CF$35=$G$444)*$G$435+(CF$35=$G$445)*(AD16+$G$430-$O16-$G$435) -> 0 | CG42: =(CG$35=0)*($O16-$G$430)+(CG$35=$G$444)*$G$435+(CG$35=$G$445)*(AD16+$G$430-$O16-$G$435) -> 9203.9892 | CH42: =(CH$35=0)*($O16-$G$430)+(CH$35=$G$444)*$G$435+(CH$35=$G$445)*(AE16+$G$430-$O16-$G$435) -> -2350 | CI42: =(CI$35=0)*($O16-$G$430)+(CI$35=$G$444)*$G$435+(CI$35=$G$445)*(AE16+$G$430-$O16-$G$435) -> 0 | CJ42: =(CJ$35=0)*($O16-$G$430)+(CJ$35=$G$444)*$G$435+(CJ$35=$G$445)*(AE16+$G$430-$O16-$G$435) -> 0 | CK42: =(CK$35=0)*($O16-$G$430)+(CK$35=$G$444)*$G$435+(CK$35=$G$445)*(AE16+$G$430-$O16-$G$435) -> 0 | CL42: =(CL$35=0)*($O16-$G$430)+(CL$35=$G$444)*$G$435+(CL$35=$G$445)*(AE16+$G$430-$O16-$G$435) -> 0 | CM42: =(CM$35=0)*($O16-$G$430)+(CM$35=$G$444)*$G$435+(CM$35=$G$445)*(AE16+$G$430-$O16-$G$435) -> 9435.065 | CN42: =(CN$35=0)*($O16-$G$430)+(CN$35=$G$444)*$G$435+(CN$35=$G$445)*(AF16+$G$430-$O16-$G$435) -> -2350 | CO42: =(CO$35=0)*($O16-$G$430)+(CO$35=$G$444)*$G$435+(CO$35=$G$445)*(AF16+$G$430-$O16-$G$435) -> 0 | CP42: =(CP$35=0)*($O16-$G$430)+(CP$35=$G$444)*$G$435+(CP$35=$G$445)*(AF16+$G$430-$O16-$G$435) -> 0 | CQ42: =(CQ$35=0)*($O16-$G$430)+(CQ$35=$G$444)*$G$435+(CQ$35=$G$445)*(AF16+$G$430-$O16-$G$435) -> 0 | CR42: =(CR$35=0)*($O16-$G$430)+(CR$35=$G$444)*$G$435+(CR$35=$G$445)*(AF16+$G$430-$O16-$G$435) -> 0 | CS42: =(CS$35=0)*($O16-$G$430)+(CS$35=$G$444)*$G$435+(CS$35=$G$445)*(AF16+$G$430-$O16-$G$435) -> 9666.1408 | CT42: =(CT$35=0)*($O16-$G$430)+(CT$35=$G$444)*$G$435+(CT$35=$G$445)*(AG16+$G$430-$O16-$G$435) -> -2350 | CU42: =(CU$35=0)*($O16-$G$430)+(CU$35=$G$444)*$G$435+(CU$35=$G$445)*(AG16+$G$430-$O16-$G$435) -> 0 | CV42: =(CV$35=0)*($O16-$G$430)+(CV$35=$G$444)*$G$435+(CV$35=$G$445)*(AG16+$G$430-$O16-$G$435) -> 0 | CW42: =(CW$35=0)*($O16-$G$430)+(CW$35=$G$444)*$G$435+(CW$35=$G$445)*(AG16+$G$430-$O16-$G$435) -> 0 | CX42: =(CX$35=0)*($O16-$G$430)+(CX$35=$G$444)*$G$435+(CX$35=$G$445)*(AG16+$G$430-$O16-$G$435) -> 0 | CY42: =(CY$35=0)*($O16-$G$430)+(CY$35=$G$444)*$G$435+(CY$35=$G$445)*(AG16+$G$430-$O16-$G$435) -> 9897.2166 | CZ42: =(CZ$35=0)*($O16-$G$430)+(CZ$35=$G$444)*$G$435+(CZ$35=$G$445)*(AH16+$G$430-$O16-$G$435) -> -2350 | DA42: =(DA$35=0)*($O16-$G$430)+(DA$35=$G$444)*$G$435+(DA$35=$G$445)*(AH16+$G$430-$O16-$G$435) -> 0 | DB42: =(DB$35=0)*($O16-$G$430)+(DB$35=$G$444)*$G$435+(DB$35=$G$445)*(AH16+$G$430-$O16-$G$435) -> 0 | DC42: =(DC$35=0)*($O16-$G$430)+(DC$35=$G$444)*$G$435+(DC$35=$G$445)*(AH16+$G$430-$O16-$G$435) -> 0 | DD42: =(DD$35=0)*($O16-$G$430)+(DD$35=$G$444)*$G$435+(DD$35=$G$445)*(AH16+$G$430-$O16-$G$435) -> 0 | DE42: =(DE$35=0)*($O16-$G$430)+(DE$35=$G$444)*$G$435+(DE$35=$G$445)*(AH16+$G$430-$O16-$G$435) -> 10128.292
B43: IRR on Ben's cash flows: Yr 0 = cash at close less Keystone value today; earnout in Yr 3; Yr 5 = stake value
B45: Ben's Return Profile Based on Partnering — Less Standalone
B46: Ben's Net Returns vs. Standalone Based on Topkey Growth & Rollover %
D48: Topkey ex-Keystone Value Growth (%) | Z48: Helper: Unrounded Net Return vs. Standalone
D49: =E49-$G$441 -> 1.021904 | E49: =F49-$G$441 -> 1.271904 | F49: =G49-$G$441 -> 1.521904 | G49: =H49-$G$441 -> 1.771904 | H49: =$G$440 -> 2.021904 | I49: =H49+$G$441 -> 2.271904 | J49: =I49+$G$441 -> 2.521904 | K49: =J49+$G$441 -> 2.771904 | L49: =K49+$G$441 -> 3.021904 | Z49: =D$9 -> 1.021904 | AA49: =E$9 -> 1.271904 | AB49: =F$9 -> 1.521904 | AC49: =G$9 -> 1.771904 | AD49: =H$9 -> 2.021904 | AE49: =I$9 -> 2.271904 | AF49: =J$9 -> 2.521904 | AG49: =K$9 -> 2.771904 | AH49: =L$9 -> 3.021904 | AT49: Helper: Gradient Band (0 = below $1M hurdle)
B50: Ben's Rollover % | C50: =C51-$G$439 -> 0.15 | D50: =ROUND(Z50,$G$452) -> -900 | E50: =ROUND(AA50,$G$452) -> -500 | F50: =ROUND(AB50,$G$452) -> 0 | G50: =ROUND(AC50,$G$452) -> 400 | H50: =ROUND(AD50,$G$452) -> 800 | I50: =ROUND(AE50,$G$452) -> 1300 | J50: =ROUND(AF50,$G$452) -> 1700 | K50: =ROUND(AG50,$G$452) -> 2100 | L50: =ROUND(AH50,$G$452) -> 2600 | Z50: =Z10+$G$430-$G$447 -> -897.52489 | AA50: =AA10+$G$430-$G$447 -> -464.86435 | AB50: =AB10+$G$430-$G$447 -> -32.203811 | AC50: =AC10+$G$430-$G$447 -> 400.45673 | AD50: =AD10+$G$430-$G$447 -> 833.11727 | AE50: =AE10+$G$430-$G$447 -> 1265.7778 | AF50: =AF10+$G$430-$G$447 -> 1698.4384 | AG50: =AG10+$G$430-$G$447 -> 2131.0989 | AH50: =AH10+$G$430-$G$447 -> 2563.7594 | AT50: =IF(Z50<$G$449,0,MIN($G$446,1+IFERROR(INT((Z50-$G$449)/$G$451),0))) -> 0 | AU50: =IF(AA50<$G$449,0,MIN($G$446,1+IFERROR(INT((AA50-$G$449)/$G$451),0))) -> 0 | AV50: =IF(AB50<$G$449,0,MIN($G$446,1+IFERROR(INT((AB50-$G$449)/$G$451),0))) -> 0 | AW50: =IF(AC50<$G$449,0,MIN($G$446,1+IFERROR(INT((AC50-$G$449)/$G$451),0))) -> 0 | AX50: =IF(AD50<$G$449,0,MIN($G$446,1+IFERROR(INT((AD50-$G$449)/$G$451),0))) -> 0 | AY50: =IF(AE50<$G$449,0,MIN($G$446,1+IFERROR(INT((AE50-$G$449)/$G$451),0))) -> 2 | AZ50: =IF(AF50<$G$449,0,MIN($G$446,1+IFERROR(INT((AF50-$G$449)/$G$451),0))) -> 4 | BA50: =IF(AG50<$G$449,0,MIN($G$446,1+IFERROR(INT((AG50-$G$449)/$G$451),0))) -> 5 | BB50: =IF(AH50<$G$449,0,MIN($G$446,1+IFERROR(INT((AH50-$G$449)/$G$451),0))) -> 7
C51: =C52-$G$439 -> 0.2 | D51: =ROUND(Z51,$G$452) -> -500 | E51: =ROUND(AA51,$G$452) -> -100 | F51: =ROUND(AB51,$G$452) -> 300 | G51: =ROUND(AC51,$G$452) -> 700 | H51: =ROUND(AD51,$G$452) -> 1100 | I51: =ROUND(AE51,$G$452) -> 1500 | J51: =ROUND(AF51,$G$452) -> 1900 | K51: =ROUND(AG51,$G$452) -> 2300 | L51: =ROUND(AH51,$G$452) -> 2700 | Z51: =Z11+$G$430-$G$447 -> -512.33889 | AA51: =AA11+$G$430-$G$447 -> -112.86773 | AB51: =AB11+$G$430-$G$447 -> 286.60342 | AC51: =AC11+$G$430-$G$447 -> 686.07457 | AD51: =AD11+$G$430-$G$447 -> 1085.5457 | AE51: =AE11+$G$430-$G$447 -> 1485.0169 | AF51: =AF11+$G$430-$G$447 -> 1884.488 | AG51: =AG11+$G$430-$G$447 -> 2283.9592 | AH51: =AH11+$G$430-$G$447 -> 2683.4303 | AT51: =IF(Z51<$G$449,0,MIN($G$446,1+IFERROR(INT((Z51-$G$449)/$G$451),0))) -> 0 | AU51: =IF(AA51<$G$449,0,MIN($G$446,1+IFERROR(INT((AA51-$G$449)/$G$451),0))) -> 0 | AV51: =IF(AB51<$G$449,0,MIN($G$446,1+IFERROR(INT((AB51-$G$449)/$G$451),0))) -> 0 | AW51: =IF(AC51<$G$449,0,MIN($G$446,1+IFERROR(INT((AC51-$G$449)/$G$451),0))) -> 0 | AX51: =IF(AD51<$G$449,0,MIN($G$446,1+IFERROR(INT((AD51-$G$449)/$G$451),0))) -> 1 | AY51: =IF(AE51<$G$449,0,MIN($G$446,1+IFERROR(INT((AE51-$G$449)/$G$451),0))) -> 3 | AZ51: =IF(AF51<$G$449,0,MIN($G$446,1+IFERROR(INT((AF51-$G$449)/$G$451),0))) -> 4 | BA51: =IF(AG51<$G$449,0,MIN($G$446,1+IFERROR(INT((AG51-$G$449)/$G$451),0))) -> 6 | BB51: =IF(AH51<$G$449,0,MIN($G$446,1+IFERROR(INT((AH51-$G$449)/$G$451),0))) -> 8
C52: =C53-$G$439 -> 0.25 | D52: =ROUND(Z52,$G$452) -> -100 | E52: =ROUND(AA52,$G$452) -> 200 | F52: =ROUND(AB52,$G$452) -> 600 | G52: =ROUND(AC52,$G$452) -> 1000 | H52: =ROUND(AD52,$G$452) -> 1300 | I52: =ROUND(AE52,$G$452) -> 1700 | J52: =ROUND(AF52,$G$452) -> 2100 | K52: =ROUND(AG52,$G$452) -> 2400 | L52: =ROUND(AH52,$G$452) -> 2800 | Z52: =Z12+$G$430-$G$447 -> -125.44719 | AA52: =AA12+$G$430-$G$447 -> 240.67294 | AB52: =AB12+$G$430-$G$447 -> 606.79307 | AC52: =AC12+$G$430-$G$447 -> 972.9132 | AD52: =AD12+$G$430-$G$447 -> 1339.0333 | AE52: =AE12+$G$430-$G$447 -> 1705.1535 | AF52: =AF12+$G$430-$G$447 -> 2071.2736 | AG52: =AG12+$G$430-$G$447 -> 2437.3937 | AH52: =AH12+$G$430-$G$447 -> 2803.5138 | AT52: =IF(Z52<$G$449,0,MIN($G$446,1+IFERROR(INT((Z52-$G$449)/$G$451),0))) -> 0 | AU52: =IF(AA52<$G$449,0,MIN($G$446,1+IFERROR(INT((AA52-$G$449)/$G$451),0))) -> 0 | AV52: =IF(AB52<$G$449,0,MIN($G$446,1+IFERROR(INT((AB52-$G$449)/$G$451),0))) -> 0 | AW52: =IF(AC52<$G$449,0,MIN($G$446,1+IFERROR(INT((AC52-$G$449)/$G$451),0))) -> 0 | AX52: =IF(AD52<$G$449,0,MIN($G$446,1+IFERROR(INT((AD52-$G$449)/$G$451),0))) -> 2 | AY52: =IF(AE52<$G$449,0,MIN($G$446,1+IFERROR(INT((AE52-$G$449)/$G$451),0))) -> 4 | AZ52: =IF(AF52<$G$449,0,MIN($G$446,1+IFERROR(INT((AF52-$G$449)/$G$451),0))) -> 5 | BA52: =IF(AG52<$G$449,0,MIN($G$446,1+IFERROR(INT((AG52-$G$449)/$G$451),0))) -> 7 | BB52: =IF(AH52<$G$449,0,MIN($G$446,1+IFERROR(INT((AH52-$G$449)/$G$451),0))) -> 8
C53: =$G$438 -> 0.3 | D53: =ROUND(Z53,$G$452) -> 300 | E53: =ROUND(AA53,$G$452) -> 600 | F53: =ROUND(AB53,$G$452) -> 900 | G53: =ROUND(AC53,$G$452) -> 1300 | H53: =ROUND(AD53,$G$452) -> 1600 | I53: =ROUND(AE53,$G$452) -> 1900 | J53: =ROUND(AF53,$G$452) -> 2300 | K53: =ROUND(AG53,$G$452) -> 2600 | L53: =ROUND(AH53,$G$452) -> 2900 | Z53: =Z13+$G$430-$G$447 -> 263.16269 | AA53: =AA13+$G$430-$G$447 -> 595.76898 | AB53: =AB13+$G$430-$G$447 -> 928.37526 | AC53: =AC13+$G$430-$G$447 -> 1260.9815 | AD53: =AD13+$G$430-$G$447 -> 1593.5878 | AE53: =AE13+$G$430-$G$447 -> 1926.1941 | AF53: =AF13+$G$430-$G$447 -> 2258.8004 | AG53: =AG13+$G$430-$G$447 -> 2591.4067 | AH53: =AH13+$G$430-$G$447 -> 2924.013 | AT53: =IF(Z53<$G$449,0,MIN($G$446,1+IFERROR(INT((Z53-$G$449)/$G$451),0))) -> 0 | AU53: =IF(AA53<$G$449,0,MIN($G$446,1+IFERROR(INT((AA53-$G$449)/$G$451),0))) -> 0 | AV53: =IF(AB53<$G$449,0,MIN($G$446,1+IFERROR(INT((AB53-$G$449)/$G$451),0))) -> 0 | AW53: =IF(AC53<$G$449,0,MIN($G$446,1+IFERROR(INT((AC53-$G$449)/$G$451),0))) -> 2 | AX53: =IF(AD53<$G$449,0,MIN($G$446,1+IFERROR(INT((AD53-$G$449)/$G$451),0))) -> 3 | AY53: =IF(AE53<$G$449,0,MIN($G$446,1+IFERROR(INT((AE53-$G$449)/$G$451),0))) -> 5 | AZ53: =IF(AF53<$G$449,0,MIN($G$446,1+IFERROR(INT((AF53-$G$449)/$G$451),0))) -> 6 | BA53: =IF(AG53<$G$449,0,MIN($G$446,1+IFERROR(INT((AG53-$G$449)/$G$451),0))) -> 7 | BB53: =IF(AH53<$G$449,0,MIN($G$446,1+IFERROR(INT((AH53-$G$449)/$G$451),0))) -> 9
C54: =C53+$G$439 -> 0.35 | D54: =ROUND(Z54,$G$452) -> 700 | E54: =ROUND(AA54,$G$452) -> 1000 | F54: =ROUND(AB54,$G$452) -> 1300 | G54: =ROUND(AC54,$G$452) -> 1600 | H54: =ROUND(AD54,$G$452) -> 1800 | I54: =ROUND(AE54,$G$452) -> 2100 | J54: =ROUND(AF54,$G$452) -> 2400 | K54: =ROUND(AG54,$G$452) -> 2700 | L54: =ROUND(AH54,$G$452) -> 3000 | Z54: =Z14+$G$430-$G$447 -> 653.50337 | AA54: =AA14+$G$430-$G$447 -> 952.43179 | AB54: =AB14+$G$430-$G$447 -> 1251.3602 | AC54: =AC14+$G$430-$G$447 -> 1550.2886 | AD54: =AD14+$G$430-$G$447 -> 1849.2171 | AE54: =AE14+$G$430-$G$447 -> 2148.1455 | AF54: =AF14+$G$430-$G$447 -> 2447.0739 | AG54: =AG14+$G$430-$G$447 -> 2746.0023 | AH54: =AH14+$G$430-$G$447 -> 3044.9308 | AT54: =IF(Z54<$G$449,0,MIN($G$446,1+IFERROR(INT((Z54-$G$449)/$G$451),0))) -> 0 | AU54: =IF(AA54<$G$449,0,MIN($G$446,1+IFERROR(INT((AA54-$G$449)/$G$451),0))) -> 0 | AV54: =IF(AB54<$G$449,0,MIN($G$446,1+IFERROR(INT((AB54-$G$449)/$G$451),0))) -> 2 | AW54: =IF(AC54<$G$449,0,MIN($G$446,1+IFERROR(INT((AC54-$G$449)/$G$451),0))) -> 3 | AX54: =IF(AD54<$G$449,0,MIN($G$446,1+IFERROR(INT((AD54-$G$449)/$G$451),0))) -> 4 | AY54: =IF(AE54<$G$449,0,MIN($G$446,1+IFERROR(INT((AE54-$G$449)/$G$451),0))) -> 6 | AZ54: =IF(AF54<$G$449,0,MIN($G$446,1+IFERROR(INT((AF54-$G$449)/$G$451),0))) -> 7 | BA54: =IF(AG54<$G$449,0,MIN($G$446,1+IFERROR(INT((AG54-$G$449)/$G$451),0))) -> 8 | BB54: =IF(AH54<$G$449,0,MIN($G$446,1+IFERROR(INT((AH54-$G$449)/$G$451),0))) -> 9
C55: =C54+$G$439 -> 0.4 | D55: =ROUND(Z55,$G$452) -> 1000 | E55: =ROUND(AA55,$G$452) -> 1300 | F55: =ROUND(AB55,$G$452) -> 1600 | G55: =ROUND(AC55,$G$452) -> 1800 | H55: =ROUND(AD55,$G$452) -> 2100 | I55: =ROUND(AE55,$G$452) -> 2400 | J55: =ROUND(AF55,$G$452) -> 2600 | K55: =ROUND(AG55,$G$452) -> 2900 | L55: =ROUND(AH55,$G$452) -> 3200 | Z55: =Z15+$G$430-$G$447 -> 1045.5876 | AA55: =AA15+$G$430-$G$447 -> 1310.6729 | AB55: =AB15+$G$430-$G$447 -> 1575.7583 | AC55: =AC15+$G$430-$G$447 -> 1840.8436 | AD55: =AD15+$G$430-$G$447 -> 2105.929 | AE55: =AE15+$G$430-$G$447 -> 2371.0143 | AF55: =AF15+$G$430-$G$447 -> 2636.0996 | AG55: =AG15+$G$430-$G$447 -> 2901.185 | AH55: =AH15+$G$430-$G$447 -> 3166.2703 | AT55: =IF(Z55<$G$449,0,MIN($G$446,1+IFERROR(INT((Z55-$G$449)/$G$451),0))) -> 1 | AU55: =IF(AA55<$G$449,0,MIN($G$446,1+IFERROR(INT((AA55-$G$449)/$G$451),0))) -> 2 | AV55: =IF(AB55<$G$449,0,MIN($G$446,1+IFERROR(INT((AB55-$G$449)/$G$451),0))) -> 3 | AW55: =IF(AC55<$G$449,0,MIN($G$446,1+IFERROR(INT((AC55-$G$449)/$G$451),0))) -> 4 | AX55: =IF(AD55<$G$449,0,MIN($G$446,1+IFERROR(INT((AD55-$G$449)/$G$451),0))) -> 5 | AY55: =IF(AE55<$G$449,0,MIN($G$446,1+IFERROR(INT((AE55-$G$449)/$G$451),0))) -> 6 | AZ55: =IF(AF55<$G$449,0,MIN($G$446,1+IFERROR(INT((AF55-$G$449)/$G$451),0))) -> 8 | BA55: =IF(AG55<$G$449,0,MIN($G$446,1+IFERROR(INT((AG55-$G$449)/$G$451),0))) -> 9 | BB55: =IF(AH55<$G$449,0,MIN($G$446,1+IFERROR(INT((AH55-$G$449)/$G$451),0))) -> 10
C56: =C55+$G$439 -> 0.45 | D56: =ROUND(Z56,$G$452) -> 1400 | E56: =ROUND(AA56,$G$452) -> 1700 | F56: =ROUND(AB56,$G$452) -> 1900 | G56: =ROUND(AC56,$G$452) -> 2100 | H56: =ROUND(AD56,$G$452) -> 2400 | I56: =ROUND(AE56,$G$452) -> 2600 | J56: =ROUND(AF56,$G$452) -> 2800 | K56: =ROUND(AG56,$G$452) -> 3100 | L56: =ROUND(AH56,$G$452) -> 3300 | Z56: =Z16+$G$430-$G$447 -> 1439.4282 | AA56: =AA16+$G$430-$G$447 -> 1670.504 | AB56: =AB16+$G$430-$G$447 -> 1901.5798 | AC56: =AC16+$G$430-$G$447 -> 2132.6556 | AD56: =AD16+$G$430-$G$447 -> 2363.7315 | AE56: =AE16+$G$430-$G$447 -> 2594.8073 | AF56: =AF16+$G$430-$G$447 -> 2825.8831 | AG56: =AG16+$G$430-$G$447 -> 3056.9589 | AH56: =AH16+$G$430-$G$447 -> 3288.0347 | AT56: =IF(Z56<$G$449,0,MIN($G$446,1+IFERROR(INT((Z56-$G$449)/$G$451),0))) -> 2 | AU56: =IF(AA56<$G$449,0,MIN($G$446,1+IFERROR(INT((AA56-$G$449)/$G$451),0))) -> 3 | AV56: =IF(AB56<$G$449,0,MIN($G$446,1+IFERROR(INT((AB56-$G$449)/$G$451),0))) -> 4 | AW56: =IF(AC56<$G$449,0,MIN($G$446,1+IFERROR(INT((AC56-$G$449)/$G$451),0))) -> 5 | AX56: =IF(AD56<$G$449,0,MIN($G$446,1+IFERROR(INT((AD56-$G$449)/$G$451),0))) -> 6 | AY56: =IF(AE56<$G$449,0,MIN($G$446,1+IFERROR(INT((AE56-$G$449)/$G$451),0))) -> 7 | AZ56: =IF(AF56<$G$449,0,MIN($G$446,1+IFERROR(INT((AF56-$G$449)/$G$451),0))) -> 8 | BA56: =IF(AG56<$G$449,0,MIN($G$446,1+IFERROR(INT((AG56-$G$449)/$G$451),0))) -> 9 | BB56: =IF(AH56<$G$449,0,MIN($G$446,1+IFERROR(INT((AH56-$G$449)/$G$451),0))) -> 10
B57: Ben's Year 5 partnership value less standalone Year 5 value (G447)
B59: Ben's % Return vs. Standalone Based on Topkey Growth & Rollover %
D61: Topkey ex-Keystone Value Growth (%)
D62: =E62-$G$441 -> 1.021904 | E62: =F62-$G$441 -> 1.271904 | F62: =G62-$G$441 -> 1.521904 | G62: =H62-$G$441 -> 1.771904 | H62: =$G$440 -> 2.021904 | I62: =H62+$G$441 -> 2.271904 | J62: =I62+$G$441 -> 2.521904 | K62: =J62+$G$441 -> 2.771904 | L62: =K62+$G$441 -> 3.021904 | AT62: Helper: Gradient Band (0 = below $1M hurdle)
B63: Ben's Rollover % | C63: =C64-$G$439 -> 0.15 | D63: =IFERROR(Z50/$G$447,0) -> -0.11982564 | E63: =IFERROR(AA50/$G$447,0) -> -0.062062531 | F63: =IFERROR(AB50/$G$447,0) -> -0.0042994263 | G63: =IFERROR(AC50/$G$447,0) -> 0.053463679 | H63: =IFERROR(AD50/$G$447,0) -> 0.11122678 | I63: =IFERROR(AE50/$G$447,0) -> 0.16898989 | J63: =IFERROR(AF50/$G$447,0) -> 0.22675299 | K63: =IFERROR(AG50/$G$447,0) -> 0.2845161 | L63: =IFERROR(AH50/$G$447,0) -> 0.3422792 | AT63: =IF(Z50<$G$449,0,MIN($G$446,1+IFERROR(INT((Z50-$G$449)/$G$451),0))) -> 0 | AU63: =IF(AA50<$G$449,0,MIN($G$446,1+IFERROR(INT((AA50-$G$449)/$G$451),0))) -> 0 | AV63: =IF(AB50<$G$449,0,MIN($G$446,1+IFERROR(INT((AB50-$G$449)/$G$451),0))) -> 0 | AW63: =IF(AC50<$G$449,0,MIN($G$446,1+IFERROR(INT((AC50-$G$449)/$G$451),0))) -> 0 | AX63: =IF(AD50<$G$449,0,MIN($G$446,1+IFERROR(INT((AD50-$G$449)/$G$451),0))) -> 0 | AY63: =IF(AE50<$G$449,0,MIN($G$446,1+IFERROR(INT((AE50-$G$449)/$G$451),0))) -> 2 | AZ63: =IF(AF50<$G$449,0,MIN($G$446,1+IFERROR(INT((AF50-$G$449)/$G$451),0))) -> 4 | BA63: =IF(AG50<$G$449,0,MIN($G$446,1+IFERROR(INT((AG50-$G$449)/$G$451),0))) -> 5 | BB63: =IF(AH50<$G$449,0,MIN($G$446,1+IFERROR(INT((AH50-$G$449)/$G$451),0))) -> 7
C64: =C65-$G$439 -> 0.2 | D64: =IFERROR(Z51/$G$447,0) -> -0.068400702 | E64: =IFERROR(AA51/$G$447,0) -> -0.015068605 | F64: =IFERROR(AB51/$G$447,0) -> 0.038263493 | G64: =IFERROR(AC51/$G$447,0) -> 0.09159559 | H64: =IFERROR(AD51/$G$447,0) -> 0.14492769 | I64: =IFERROR(AE51/$G$447,0) -> 0.19825979 | J64: =IFERROR(AF51/$G$447,0) -> 0.25159188 | K64: =IFERROR(AG51/$G$447,0) -> 0.30492398 | L64: =IFERROR(AH51/$G$447,0) -> 0.35825608 | AT64: =IF(Z51<$G$449,0,MIN($G$446,1+IFERROR(INT((Z51-$G$449)/$G$451),0))) -> 0 | AU64: =IF(AA51<$G$449,0,MIN($G$446,1+IFERROR(INT((AA51-$G$449)/$G$451),0))) -> 0 | AV64: =IF(AB51<$G$449,0,MIN($G$446,1+IFERROR(INT((AB51-$G$449)/$G$451),0))) -> 0 | AW64: =IF(AC51<$G$449,0,MIN($G$446,1+IFERROR(INT((AC51-$G$449)/$G$451),0))) -> 0 | AX64: =IF(AD51<$G$449,0,MIN($G$446,1+IFERROR(INT((AD51-$G$449)/$G$451),0))) -> 1 | AY64: =IF(AE51<$G$449,0,MIN($G$446,1+IFERROR(INT((AE51-$G$449)/$G$451),0))) -> 3 | AZ64: =IF(AF51<$G$449,0,MIN($G$446,1+IFERROR(INT((AF51-$G$449)/$G$451),0))) -> 4 | BA64: =IF(AG51<$G$449,0,MIN($G$446,1+IFERROR(INT((AG51-$G$449)/$G$451),0))) -> 6 | BB64: =IF(AH51<$G$449,0,MIN($G$446,1+IFERROR(INT((AH51-$G$449)/$G$451),0))) -> 8
C65: =C66-$G$439 -> 0.25 | D65: =IFERROR(Z52/$G$447,0) -> -0.016748047 | E65: =IFERROR(AA52/$G$447,0) -> 0.032131463 | F65: =IFERROR(AB52/$G$447,0) -> 0.081010974 | G65: =IFERROR(AC52/$G$447,0) -> 0.12989048 | H65: =IFERROR(AD52/$G$447,0) -> 0.17876999 | I65: =IFERROR(AE52/$G$447,0) -> 0.22764951 | J65: =IFERROR(AF52/$G$447,0) -> 0.27652902 | K65: =IFERROR(AG52/$G$447,0) -> 0.32540853 | L65: =IFERROR(AH52/$G$447,0) -> 0.37428804 | AT65: =IF(Z52<$G$449,0,MIN($G$446,1+IFERROR(INT((Z52-$G$449)/$G$451),0))) -> 0 | AU65: =IF(AA52<$G$449,0,MIN($G$446,1+IFERROR(INT((AA52-$G$449)/$G$451),0))) -> 0 | AV65: =IF(AB52<$G$449,0,MIN($G$446,1+IFERROR(INT((AB52-$G$449)/$G$451),0))) -> 0 | AW65: =IF(AC52<$G$449,0,MIN($G$446,1+IFERROR(INT((AC52-$G$449)/$G$451),0))) -> 0 | AX65: =IF(AD52<$G$449,0,MIN($G$446,1+IFERROR(INT((AD52-$G$449)/$G$451),0))) -> 2 | AY65: =IF(AE52<$G$449,0,MIN($G$446,1+IFERROR(INT((AE52-$G$449)/$G$451),0))) -> 4 | AZ65: =IF(AF52<$G$449,0,MIN($G$446,1+IFERROR(INT((AF52-$G$449)/$G$451),0))) -> 5 | BA65: =IF(AG52<$G$449,0,MIN($G$446,1+IFERROR(INT((AG52-$G$449)/$G$451),0))) -> 7 | BB65: =IF(AH52<$G$449,0,MIN($G$446,1+IFERROR(INT((AH52-$G$449)/$G$451),0))) -> 8
C66: =$G$438 -> 0.3 | D66: =IFERROR(Z53/$G$447,0) -> 0.035133997 | E66: =IFERROR(AA53/$G$447,0) -> 0.079539183 | F66: =IFERROR(AB53/$G$447,0) -> 0.12394437 | G66: =IFERROR(AC53/$G$447,0) -> 0.16834955 | H66: =IFERROR(AD53/$G$447,0) -> 0.21275474 | I66: =IFERROR(AE53/$G$447,0) -> 0.25715993 | J66: =IFERROR(AF53/$G$447,0) -> 0.30156511 | K66: =IFERROR(AG53/$G$447,0) -> 0.3459703 | L66: =IFERROR(AH53/$G$447,0) -> 0.39037548 | AT66: =IF(Z53<$G$449,0,MIN($G$446,1+IFERROR(INT((Z53-$G$449)/$G$451),0))) -> 0 | AU66: =IF(AA53<$G$449,0,MIN($G$446,1+IFERROR(INT((AA53-$G$449)/$G$451),0))) -> 0 | AV66: =IF(AB53<$G$449,0,MIN($G$446,1+IFERROR(INT((AB53-$G$449)/$G$451),0))) -> 0 | AW66: =IF(AC53<$G$449,0,MIN($G$446,1+IFERROR(INT((AC53-$G$449)/$G$451),0))) -> 2 | AX66: =IF(AD53<$G$449,0,MIN($G$446,1+IFERROR(INT((AD53-$G$449)/$G$451),0))) -> 3 | AY66: =IF(AE53<$G$449,0,MIN($G$446,1+IFERROR(INT((AE53-$G$449)/$G$451),0))) -> 5 | AZ66: =IF(AF53<$G$449,0,MIN($G$446,1+IFERROR(INT((AF53-$G$449)/$G$451),0))) -> 6 | BA66: =IF(AG53<$G$449,0,MIN($G$446,1+IFERROR(INT((AG53-$G$449)/$G$451),0))) -> 7 | BB66: =IF(AH53<$G$449,0,MIN($G$446,1+IFERROR(INT((AH53-$G$449)/$G$451),0))) -> 9
C67: =C66+$G$439 -> 0.35 | D67: =IFERROR(Z54/$G$447,0) -> 0.087247114 | E67: =IFERROR(AA54/$G$447,0) -> 0.12715608 | F67: =IFERROR(AB54/$G$447,0) -> 0.16706504 | G67: =IFERROR(AC54/$G$447,0) -> 0.20697401 | H67: =IFERROR(AD54/$G$447,0) -> 0.24688297 | I67: =IFERROR(AE54/$G$447,0) -> 0.28679193 | J67: =IFERROR(AF54/$G$447,0) -> 0.3267009 | K67: =IFERROR(AG54/$G$447,0) -> 0.36660986 | L67: =IFERROR(AH54/$G$447,0) -> 0.40651883 | AT67: =IF(Z54<$G$449,0,MIN($G$446,1+IFERROR(INT((Z54-$G$449)/$G$451),0))) -> 0 | AU67: =IF(AA54<$G$449,0,MIN($G$446,1+IFERROR(INT((AA54-$G$449)/$G$451),0))) -> 0 | AV67: =IF(AB54<$G$449,0,MIN($G$446,1+IFERROR(INT((AB54-$G$449)/$G$451),0))) -> 2 | AW67: =IF(AC54<$G$449,0,MIN($G$446,1+IFERROR(INT((AC54-$G$449)/$G$451),0))) -> 3 | AX67: =IF(AD54<$G$449,0,MIN($G$446,1+IFERROR(INT((AD54-$G$449)/$G$451),0))) -> 4 | AY67: =IF(AE54<$G$449,0,MIN($G$446,1+IFERROR(INT((AE54-$G$449)/$G$451),0))) -> 6 | AZ67: =IF(AF54<$G$449,0,MIN($G$446,1+IFERROR(INT((AF54-$G$449)/$G$451),0))) -> 7 | BA67: =IF(AG54<$G$449,0,MIN($G$446,1+IFERROR(INT((AG54-$G$449)/$G$451),0))) -> 8 | BB67: =IF(AH54<$G$449,0,MIN($G$446,1+IFERROR(INT((AH54-$G$449)/$G$451),0))) -> 9
C68: =C67+$G$439 -> 0.4 | D68: =IFERROR(Z55/$G$447,0) -> 0.139593 | E68: =IFERROR(AA55/$G$447,0) -> 0.17498369 | F68: =IFERROR(AB55/$G$447,0) -> 0.21037437 | G68: =IFERROR(AC55/$G$447,0) -> 0.24576506 | H68: =IFERROR(AD55/$G$447,0) -> 0.28115574 | I68: =IFERROR(AE55/$G$447,0) -> 0.31654642 | J68: =IFERROR(AF55/$G$447,0) -> 0.35193711 | K68: =IFERROR(AG55/$G$447,0) -> 0.38732779 | L68: =IFERROR(AH55/$G$447,0) -> 0.42271848 | AT68: =IF(Z55<$G$449,0,MIN($G$446,1+IFERROR(INT((Z55-$G$449)/$G$451),0))) -> 1 | AU68: =IF(AA55<$G$449,0,MIN($G$446,1+IFERROR(INT((AA55-$G$449)/$G$451),0))) -> 2 | AV68: =IF(AB55<$G$449,0,MIN($G$446,1+IFERROR(INT((AB55-$G$449)/$G$451),0))) -> 3 | AW68: =IF(AC55<$G$449,0,MIN($G$446,1+IFERROR(INT((AC55-$G$449)/$G$451),0))) -> 4 | AX68: =IF(AD55<$G$449,0,MIN($G$446,1+IFERROR(INT((AD55-$G$449)/$G$451),0))) -> 5 | AY68: =IF(AE55<$G$449,0,MIN($G$446,1+IFERROR(INT((AE55-$G$449)/$G$451),0))) -> 6 | AZ68: =IF(AF55<$G$449,0,MIN($G$446,1+IFERROR(INT((AF55-$G$449)/$G$451),0))) -> 8 | BA68: =IF(AG55<$G$449,0,MIN($G$446,1+IFERROR(INT((AG55-$G$449)/$G$451),0))) -> 9 | BB68: =IF(AH55<$G$449,0,MIN($G$446,1+IFERROR(INT((AH55-$G$449)/$G$451),0))) -> 10
C69: =C68+$G$439 -> 0.45 | D69: =IFERROR(Z56/$G$447,0) -> 0.19217339 | E69: =IFERROR(AA56/$G$447,0) -> 0.22302357 | F69: =IFERROR(AB56/$G$447,0) -> 0.25387375 | G69: =IFERROR(AC56/$G$447,0) -> 0.28472393 | H69: =IFERROR(AD56/$G$447,0) -> 0.31557412 | I69: =IFERROR(AE56/$G$447,0) -> 0.3464243 | J69: =IFERROR(AF56/$G$447,0) -> 0.37727448 | K69: =IFERROR(AG56/$G$447,0) -> 0.40812467 | L69: =IFERROR(AH56/$G$447,0) -> 0.43897485 | AT69: =IF(Z56<$G$449,0,MIN($G$446,1+IFERROR(INT((Z56-$G$449)/$G$451),0))) -> 2 | AU69: =IF(AA56<$G$449,0,MIN($G$446,1+IFERROR(INT((AA56-$G$449)/$G$451),0))) -> 3 | AV69: =IF(AB56<$G$449,0,MIN($G$446,1+IFERROR(INT((AB56-$G$449)/$G$451),0))) -> 4 | AW69: =IF(AC56<$G$449,0,MIN($G$446,1+IFERROR(INT((AC56-$G$449)/$G$451),0))) -> 5 | AX69: =IF(AD56<$G$449,0,MIN($G$446,1+IFERROR(INT((AD56-$G$449)/$G$451),0))) -> 6 | AY69: =IF(AE56<$G$449,0,MIN($G$446,1+IFERROR(INT((AE56-$G$449)/$G$451),0))) -> 7 | AZ69: =IF(AF56<$G$449,0,MIN($G$446,1+IFERROR(INT((AF56-$G$449)/$G$451),0))) -> 8 | BA69: =IF(AG56<$G$449,0,MIN($G$446,1+IFERROR(INT((AG56-$G$449)/$G$451),0))) -> 9 | BB69: =IF(AH56<$G$449,0,MIN($G$446,1+IFERROR(INT((AH56-$G$449)/$G$451),0))) -> 10
B70: Ben's Year 5 partnership value ÷ standalone Year 5 value (G447), less 1
B72: Ben's IRR Premium vs. Standalone Based on Topkey Growth & Rollover %
D74: Topkey ex-Keystone Value Growth (%)
D75: =E75-$G$441 -> 1.021904 | E75: =F75-$G$441 -> 1.271904 | F75: =G75-$G$441 -> 1.521904 | G75: =H75-$G$441 -> 1.771904 | H75: =$G$440 -> 2.021904 | I75: =H75+$G$441 -> 2.271904 | J75: =I75+$G$441 -> 2.521904 | K75: =J75+$G$441 -> 2.771904 | L75: =K75+$G$441 -> 3.021904 | AT75: Helper: Gradient Band (0 = below $1M hurdle)
B76: Ben's Rollover % | C76: =C77-$G$439 -> 0.15 | D76: =D36-$G$448 -> 0.0030690735 | E76: =E36-$G$448 -> 0.020109507 | F76: =F36-$G$448 -> 0.036248515 | G76: =G36-$G$448 -> 0.051586772 | H76: =H36-$G$448 -> 0.066208479 | I76: =I36-$G$448 -> 0.080184819 | J76: =J36-$G$448 -> 0.09357655 | K76: =K36-$G$448 -> 0.10643597 | L76: =L36-$G$448 -> 0.11880845 | AT76: =IF(Z50<$G$449,0,MIN($G$446,1+IFERROR(INT((Z50-$G$449)/$G$451),0))) -> 0 | AU76: =IF(AA50<$G$449,0,MIN($G$446,1+IFERROR(INT((AA50-$G$449)/$G$451),0))) -> 0 | AV76: =IF(AB50<$G$449,0,MIN($G$446,1+IFERROR(INT((AB50-$G$449)/$G$451),0))) -> 0 | AW76: =IF(AC50<$G$449,0,MIN($G$446,1+IFERROR(INT((AC50-$G$449)/$G$451),0))) -> 0 | AX76: =IF(AD50<$G$449,0,MIN($G$446,1+IFERROR(INT((AD50-$G$449)/$G$451),0))) -> 0 | AY76: =IF(AE50<$G$449,0,MIN($G$446,1+IFERROR(INT((AE50-$G$449)/$G$451),0))) -> 2 | AZ76: =IF(AF50<$G$449,0,MIN($G$446,1+IFERROR(INT((AF50-$G$449)/$G$451),0))) -> 4 | BA76: =IF(AG50<$G$449,0,MIN($G$446,1+IFERROR(INT((AG50-$G$449)/$G$451),0))) -> 5 | BB76: =IF(AH50<$G$449,0,MIN($G$446,1+IFERROR(INT((AH50-$G$449)/$G$451),0))) -> 7
C77: =C78-$G$439 -> 0.2 | D77: =D37-$G$448 -> 0.018285742 | E77: =E37-$G$448 -> 0.033303107 | F77: =F37-$G$448 -> 0.047623208 | G77: =G37-$G$448 -> 0.061314912 | H77: =H37-$G$448 -> 0.074437054 | I77: =I37-$G$448 -> 0.08704032 | J77: =J37-$G$448 -> 0.09916871 | K77: =K37-$G$448 -> 0.11086068 | L77: =L37-$G$448 -> 0.12215005 | AT77: =IF(Z51<$G$449,0,MIN($G$446,1+IFERROR(INT((Z51-$G$449)/$G$451),0))) -> 0 | AU77: =IF(AA51<$G$449,0,MIN($G$446,1+IFERROR(INT((AA51-$G$449)/$G$451),0))) -> 0 | AV77: =IF(AB51<$G$449,0,MIN($G$446,1+IFERROR(INT((AB51-$G$449)/$G$451),0))) -> 0 | AW77: =IF(AC51<$G$449,0,MIN($G$446,1+IFERROR(INT((AC51-$G$449)/$G$451),0))) -> 0 | AX77: =IF(AD51<$G$449,0,MIN($G$446,1+IFERROR(INT((AD51-$G$449)/$G$451),0))) -> 1 | AY77: =IF(AE51<$G$449,0,MIN($G$446,1+IFERROR(INT((AE51-$G$449)/$G$451),0))) -> 3 | AZ77: =IF(AF51<$G$449,0,MIN($G$446,1+IFERROR(INT((AF51-$G$449)/$G$451),0))) -> 4 | BA77: =IF(AG51<$G$449,0,MIN($G$446,1+IFERROR(INT((AG51-$G$449)/$G$451),0))) -> 6 | BB77: =IF(AH51<$G$449,0,MIN($G$446,1+IFERROR(INT((AH51-$G$449)/$G$451),0))) -> 8
C78: =C79-$G$439 -> 0.25 | D78: =D38-$G$448 -> 0.03284123 | E78: =E38-$G$448 -> 0.046009886 | F78: =F38-$G$448 -> 0.058644617 | G78: =G38-$G$448 -> 0.070791794 | H78: =H38-$G$448 -> 0.082491809 | I78: =I38-$G$448 -> 0.093780076 | J78: =J38-$G$448 -> 0.10468783 | K78: =K38-$G$448 -> 0.11524277 | L78: =L38-$G$448 -> 0.12546957 | AT78: =IF(Z52<$G$449,0,MIN($G$446,1+IFERROR(INT((Z52-$G$449)/$G$451),0))) -> 0 | AU78: =IF(AA52<$G$449,0,MIN($G$446,1+IFERROR(INT((AA52-$G$449)/$G$451),0))) -> 0 | AV78: =IF(AB52<$G$449,0,MIN($G$446,1+IFERROR(INT((AB52-$G$449)/$G$451),0))) -> 0 | AW78: =IF(AC52<$G$449,0,MIN($G$446,1+IFERROR(INT((AC52-$G$449)/$G$451),0))) -> 0 | AX78: =IF(AD52<$G$449,0,MIN($G$446,1+IFERROR(INT((AD52-$G$449)/$G$451),0))) -> 2 | AY78: =IF(AE52<$G$449,0,MIN($G$446,1+IFERROR(INT((AE52-$G$449)/$G$451),0))) -> 4 | AZ78: =IF(AF52<$G$449,0,MIN($G$446,1+IFERROR(INT((AF52-$G$449)/$G$451),0))) -> 5 | BA78: =IF(AG52<$G$449,0,MIN($G$446,1+IFERROR(INT((AG52-$G$449)/$G$451),0))) -> 7 | BB78: =IF(AH52<$G$449,0,MIN($G$446,1+IFERROR(INT((AH52-$G$449)/$G$451),0))) -> 8
C79: =$G$438 -> 0.3 | D79: =D39-$G$448 -> 0.046800888 | E79: =E39-$G$448 -> 0.058271514 | F79: =F39-$G$448 -> 0.069338756 | G79: =G39-$G$448 -> 0.080033192 | H79: =H39-$G$448 -> 0.090381943 | I79: =I39-$G$448 -> 0.10040918 | J79: =J39-$G$448 -> 0.11013653 | K79: =K39-$G$448 -> 0.11958346 | L79: =L39-$G$448 -> 0.12876752 | AT79: =IF(Z53<$G$449,0,MIN($G$446,1+IFERROR(INT((Z53-$G$449)/$G$451),0))) -> 0 | AU79: =IF(AA53<$G$449,0,MIN($G$446,1+IFERROR(INT((AA53-$G$449)/$G$451),0))) -> 0 | AV79: =IF(AB53<$G$449,0,MIN($G$446,1+IFERROR(INT((AB53-$G$449)/$G$451),0))) -> 0 | AW79: =IF(AC53<$G$449,0,MIN($G$446,1+IFERROR(INT((AC53-$G$449)/$G$451),0))) -> 2 | AX79: =IF(AD53<$G$449,0,MIN($G$446,1+IFERROR(INT((AD53-$G$449)/$G$451),0))) -> 3 | AY79: =IF(AE53<$G$449,0,MIN($G$446,1+IFERROR(INT((AE53-$G$449)/$G$451),0))) -> 5 | AZ79: =IF(AF53<$G$449,0,MIN($G$446,1+IFERROR(INT((AF53-$G$449)/$G$451),0))) -> 6 | BA79: =IF(AG53<$G$449,0,MIN($G$446,1+IFERROR(INT((AG53-$G$449)/$G$451),0))) -> 7 | BB79: =IF(AH53<$G$449,0,MIN($G$446,1+IFERROR(INT((AH53-$G$449)/$G$451),0))) -> 9
C80: =C79+$G$439 -> 0.35 | D80: =D40-$G$448 -> 0.060220612 | E80: =E40-$G$448 -> 0.070124419 | F80: =F40-$G$448 -> 0.079728812 | G80: =G40-$G$448 -> 0.089053419 | H80: =H40-$G$448 -> 0.098115936 | I80: =I40-$G$448 -> 0.10693238 | J80: =J40-$G$448 -> 0.11551729 | K80: =K40-$G$448 -> 0.12388391 | L80: =L40-$G$448 -> 0.13204435 | AT80: =IF(Z54<$G$449,0,MIN($G$446,1+IFERROR(INT((Z54-$G$449)/$G$451),0))) -> 0 | AU80: =IF(AA54<$G$449,0,MIN($G$446,1+IFERROR(INT((AA54-$G$449)/$G$451),0))) -> 0 | AV80: =IF(AB54<$G$449,0,MIN($G$446,1+IFERROR(INT((AB54-$G$449)/$G$451),0))) -> 2 | AW80: =IF(AC54<$G$449,0,MIN($G$446,1+IFERROR(INT((AC54-$G$449)/$G$451),0))) -> 3 | AX80: =IF(AD54<$G$449,0,MIN($G$446,1+IFERROR(INT((AD54-$G$449)/$G$451),0))) -> 4 | AY80: =IF(AE54<$G$449,0,MIN($G$446,1+IFERROR(INT((AE54-$G$449)/$G$451),0))) -> 6 | AZ80: =IF(AF54<$G$449,0,MIN($G$446,1+IFERROR(INT((AF54-$G$449)/$G$451),0))) -> 7 | BA80: =IF(AG54<$G$449,0,MIN($G$446,1+IFERROR(INT((AG54-$G$449)/$G$451),0))) -> 8 | BB80: =IF(AH54<$G$449,0,MIN($G$446,1+IFERROR(INT((AH54-$G$449)/$G$451),0))) -> 9
C81: =C80+$G$439 -> 0.4 | D81: =D41-$G$448 -> 0.073148612 | E81: =E41-$G$448 -> 0.081600641 | F81: =F41-$G$448 -> 0.089835551 | G81: =G41-$G$448 -> 0.097865502 | H81: =H41-$G$448 -> 0.10570163 | I81: =I41-$G$448 -> 0.11335414 | J81: =J41-$G$448 -> 0.12083246 | K81: =K41-$G$448 -> 0.12814525 | L81: =L41-$G$448 -> 0.13530053 | AT81: =IF(Z55<$G$449,0,MIN($G$446,1+IFERROR(INT((Z55-$G$449)/$G$451),0))) -> 1 | AU81: =IF(AA55<$G$449,0,MIN($G$446,1+IFERROR(INT((AA55-$G$449)/$G$451),0))) -> 2 | AV81: =IF(AB55<$G$449,0,MIN($G$446,1+IFERROR(INT((AB55-$G$449)/$G$451),0))) -> 3 | AW81: =IF(AC55<$G$449,0,MIN($G$446,1+IFERROR(INT((AC55-$G$449)/$G$451),0))) -> 4 | AX81: =IF(AD55<$G$449,0,MIN($G$446,1+IFERROR(INT((AD55-$G$449)/$G$451),0))) -> 5 | AY81: =IF(AE55<$G$449,0,MIN($G$446,1+IFERROR(INT((AE55-$G$449)/$G$451),0))) -> 6 | AZ81: =IF(AF55<$G$449,0,MIN($G$446,1+IFERROR(INT((AF55-$G$449)/$G$451),0))) -> 8 | BA81: =IF(AG55<$G$449,0,MIN($G$446,1+IFERROR(INT((AG55-$G$449)/$G$451),0))) -> 9 | BB81: =IF(AH55<$G$449,0,MIN($G$446,1+IFERROR(INT((AH55-$G$449)/$G$451),0))) -> 10
C82: =C81+$G$439 -> 0.45 | D82: =D42-$G$448 -> 0.08562678 | E82: =E42-$G$448 -> 0.092728521 | F82: =F42-$G$448 -> 0.099677644 | G82: =G42-$G$448 -> 0.10648134 | H82: =H42-$G$448 -> 0.11314627 | I82: =I42-$G$448 -> 0.11967866 | J82: =J42-$G$448 -> 0.12608428 | K82: =K42-$G$448 -> 0.13236855 | L82: =L42-$G$448 -> 0.13853652 | AT82: =IF(Z56<$G$449,0,MIN($G$446,1+IFERROR(INT((Z56-$G$449)/$G$451),0))) -> 2 | AU82: =IF(AA56<$G$449,0,MIN($G$446,1+IFERROR(INT((AA56-$G$449)/$G$451),0))) -> 3 | AV82: =IF(AB56<$G$449,0,MIN($G$446,1+IFERROR(INT((AB56-$G$449)/$G$451),0))) -> 4 | AW82: =IF(AC56<$G$449,0,MIN($G$446,1+IFERROR(INT((AC56-$G$449)/$G$451),0))) -> 5 | AX82: =IF(AD56<$G$449,0,MIN($G$446,1+IFERROR(INT((AD56-$G$449)/$G$451),0))) -> 6 | AY82: =IF(AE56<$G$449,0,MIN($G$446,1+IFERROR(INT((AE56-$G$449)/$G$451),0))) -> 7 | AZ82: =IF(AF56<$G$449,0,MIN($G$446,1+IFERROR(INT((AF56-$G$449)/$G$451),0))) -> 8 | BA82: =IF(AG56<$G$449,0,MIN($G$446,1+IFERROR(INT((AG56-$G$449)/$G$451),0))) -> 9 | BB82: =IF(AH56<$G$449,0,MIN($G$446,1+IFERROR(INT((AH56-$G$449)/$G$451),0))) -> 10
B83: Partnership IRR (table above) less standalone IRR (G448), in percentage points
B85: Ben's Return Profile Based on Partnering — Net Client Wins
B86: Ben's Net Returns Based on Net Client Wins & Rollover %
D88: Keystone Total Annual Net Client Wins — Partnership (#) | Z88: Helper: Unrounded Net Return — Net Client Wins | AJ88: Helper: Keystone EV Yr 5 by Net Client Wins
D89: =E89+$G$458 -> 64 | E89: =F89+$G$458 -> 60 | F89: =G89+$G$458 -> 56 | G89: =H89+$G$458 -> 52 | H89: =$G$457 -> 48 | I89: =H89-$G$458 -> 44 | J89: =I89-$G$458 -> 40 | K89: =J89-$G$458 -> 36 | L89: =K89-$G$458 -> 32 | N89: Helper: Rollover % | O89: Helper: Cash at Close | P89: Helper: Topkey Equity Issued | Q89: Helper: Topkey ex-Keystone Today | R89: Helper: Ben's Yr 5 Topkey % | Z89: =D$89 -> 64 | AA89: =E$89 -> 60 | AB89: =F$89 -> 56 | AC89: =G$89 -> 52 | AD89: =H$89 -> 48 | AE89: =I$89 -> 44 | AF89: =J$89 -> 40 | AG89: =K$89 -> 36 | AH89: =L$89 -> 32 | AJ89: =D$89 -> 64 | AK89: =E$89 -> 60 | AL89: =F$89 -> 56 | AM89: =G$89 -> 52 | AN89: =H$89 -> 48 | AO89: =I$89 -> 44 | AP89: =J$89 -> 40 | AQ89: =K$89 -> 36 | AR89: =L$89 -> 32 | AT89: Helper: Gradient Band (0 = below $1M hurdle)
B90: Ben's Rollover % | C90: =C91-$G$439 -> 0.15 | D90: =ROUND(Z90,$G$452) -> 5800 | E90: =ROUND(AA90,$G$452) -> 5700 | F90: =ROUND(AB90,$G$452) -> 5600 | G90: =ROUND(AC90,$G$452) -> 5400 | H90: =ROUND(AD90,$G$452) -> 5300 | I90: =ROUND(AE90,$G$452) -> 5200 | J90: =ROUND(AF90,$G$452) -> 5100 | K90: =ROUND(AG90,$G$452) -> 5000 | L90: =ROUND(AH90,$G$452) -> 4900 | N90: =$C90 -> 0.15 | O90: =$G$433 -> 650 | P90: =$G$430*(1-N90)-O90 -> 1900 | Q90: =$G$432-O90 -> 59350 | R90: =IFERROR(P90/(Q90+$G$430*(1-N90)),0)*(1-$G$434) -> 0.029159935 | Z90: =$O90+$G$435+$N90*AJ$90+$R90*($Q90*(1+$G$437)+AJ$90*(1-$N90))-$G$430 -> 5788.4866 | AA90: =$O90+$G$435+$N90*AK$90+$R90*($Q90*(1+$G$437)+AK$90*(1-$N90))-$G$430 -> 5672.2087 | AB90: =$O90+$G$435+$N90*AL$90+$R90*($Q90*(1+$G$437)+AL$90*(1-$N90))-$G$430 -> 5555.9308 | AC90: =$O90+$G$435+$N90*AM$90+$R90*($Q90*(1+$G$437)+AM$90*(1-$N90))-$G$430 -> 5439.6529 | AD90: =$O90+$G$435+$N90*AN$90+$R90*($Q90*(1+$G$437)+AN$90*(1-$N90))-$G$430 -> 5323.375 | AE90: =$O90+$G$435+$N90*AO$90+$R90*($Q90*(1+$G$437)+AO$90*(1-$N90))-$G$430 -> 5207.0971 | AF90: =$O90+$G$435+$N90*AP$90+$R90*($Q90*(1+$G$437)+AP$90*(1-$N90))-$G$430 -> 5090.8192 | AG90: =$O90+$G$435+$N90*AQ$90+$R90*($Q90*(1+$G$437)+AQ$90*(1-$N90))-$G$430 -> 4974.5412 | AH90: =$O90+$G$435+$N90*AR$90+$R90*($Q90*(1+$G$437)+AR$90*(1-$N90))-$G$430 -> 4858.2633 | AJ90: =($G$453+AJ$89*$G$445*$G$454)*$G$455 -> 16641.225 | AK90: =($G$453+AK$89*$G$445*$G$454)*$G$455 -> 15975.966 | AL90: =($G$453+AL$89*$G$445*$G$454)*$G$455 -> 15310.707 | AM90: =($G$453+AM$89*$G$445*$G$454)*$G$455 -> 14645.448 | AN90: =($G$453+AN$89*$G$445*$G$454)*$G$455 -> 13980.189 | AO90: =($G$453+AO$89*$G$445*$G$454)*$G$455 -> 13314.93 | AP90: =($G$453+AP$89*$G$445*$G$454)*$G$455 -> 12649.671 | AQ90: =($G$453+AQ$89*$G$445*$G$454)*$G$455 -> 11984.412 | AR90: =($G$453+AR$89*$G$445*$G$454)*$G$455 -> 11319.153 | AT90: =IF(Z130<$G$449,0,MIN($G$446,1+IFERROR(INT((Z130-$G$449)/$G$463),0))) -> 0 | AU90: =IF(AA130<$G$449,0,MIN($G$446,1+IFERROR(INT((AA130-$G$449)/$G$463),0))) -> 0 | AV90: =IF(AB130<$G$449,0,MIN($G$446,1+IFERROR(INT((AB130-$G$449)/$G$463),0))) -> 0 | AW90: =IF(AC130<$G$449,0,MIN($G$446,1+IFERROR(INT((AC130-$G$449)/$G$463),0))) -> 0 | AX90: =IF(AD130<$G$449,0,MIN($G$446,1+IFERROR(INT((AD130-$G$449)/$G$463),0))) -> 0 | AY90: =IF(AE130<$G$449,0,MIN($G$446,1+IFERROR(INT((AE130-$G$449)/$G$463),0))) -> 1 | AZ90: =IF(AF130<$G$449,0,MIN($G$446,1+IFERROR(INT((AF130-$G$449)/$G$463),0))) -> 3 | BA90: =IF(AG130<$G$449,0,MIN($G$446,1+IFERROR(INT((AG130-$G$449)/$G$463),0))) -> 5 | BB90: =IF(AH130<$G$449,0,MIN($G$446,1+IFERROR(INT((AH130-$G$449)/$G$463),0))) -> 6
C91: =C92-$G$439 -> 0.2 | D91: =ROUND(Z91,$G$452) -> 6200 | E91: =ROUND(AA91,$G$452) -> 6000 | F91: =ROUND(AB91,$G$452) -> 5900 | G91: =ROUND(AC91,$G$452) -> 5700 | H91: =ROUND(AD91,$G$452) -> 5600 | I91: =ROUND(AE91,$G$452) -> 5400 | J91: =ROUND(AF91,$G$452) -> 5300 | K91: =ROUND(AG91,$G$452) -> 5100 | L91: =ROUND(AH91,$G$452) -> 5000 | N91: =$C91 -> 0.2 | O91: =$G$433 -> 650 | P91: =$G$430*(1-N91)-O91 -> 1750 | Q91: =$G$432-O91 -> 59350 | R91: =IFERROR(P91/(Q91+$G$430*(1-N91)),0)*(1-$G$434) -> 0.026923077 | Z91: =$O91+$G$435+$N91*AJ$90+$R91*($Q91*(1+$G$437)+AJ$90*(1-$N91))-$G$430 -> 6165.3252 | AA91: =$O91+$G$435+$N91*AK$90+$R91*($Q91*(1+$G$437)+AK$90*(1-$N91))-$G$430 -> 6017.9447 | AB91: =$O91+$G$435+$N91*AL$90+$R91*($Q91*(1+$G$437)+AL$90*(1-$N91))-$G$430 -> 5870.5643 | AC91: =$O91+$G$435+$N91*AM$90+$R91*($Q91*(1+$G$437)+AM$90*(1-$N91))-$G$430 -> 5723.1839 | AD91: =$O91+$G$435+$N91*AN$90+$R91*($Q91*(1+$G$437)+AN$90*(1-$N91))-$G$430 -> 5575.8034 | AE91: =$O91+$G$435+$N91*AO$90+$R91*($Q91*(1+$G$437)+AO$90*(1-$N91))-$G$430 -> 5428.423 | AF91: =$O91+$G$435+$N91*AP$90+$R91*($Q91*(1+$G$437)+AP$90*(1-$N91))-$G$430 -> 5281.0426 | AG91: =$O91+$G$435+$N91*AQ$90+$R91*($Q91*(1+$G$437)+AQ$90*(1-$N91))-$G$430 -> 5133.6621 | AH91: =$O91+$G$435+$N91*AR$90+$R91*($Q91*(1+$G$437)+AR$90*(1-$N91))-$G$430 -> 4986.2817 | AT91: =IF(Z131<$G$449,0,MIN($G$446,1+IFERROR(INT((Z131-$G$449)/$G$463),0))) -> 0 | AU91: =IF(AA131<$G$449,0,MIN($G$446,1+IFERROR(INT((AA131-$G$449)/$G$463),0))) -> 0 | AV91: =IF(AB131<$G$449,0,MIN($G$446,1+IFERROR(INT((AB131-$G$449)/$G$463),0))) -> 0 | AW91: =IF(AC131<$G$449,0,MIN($G$446,1+IFERROR(INT((AC131-$G$449)/$G$463),0))) -> 0 | AX91: =IF(AD131<$G$449,0,MIN($G$446,1+IFERROR(INT((AD131-$G$449)/$G$463),0))) -> 1 | AY91: =IF(AE131<$G$449,0,MIN($G$446,1+IFERROR(INT((AE131-$G$449)/$G$463),0))) -> 2 | AZ91: =IF(AF131<$G$449,0,MIN($G$446,1+IFERROR(INT((AF131-$G$449)/$G$463),0))) -> 4 | BA91: =IF(AG131<$G$449,0,MIN($G$446,1+IFERROR(INT((AG131-$G$449)/$G$463),0))) -> 5 | BB91: =IF(AH131<$G$449,0,MIN($G$446,1+IFERROR(INT((AH131-$G$449)/$G$463),0))) -> 7
C92: =C93-$G$439 -> 0.25 | D92: =ROUND(Z92,$G$452) -> 6500 | E92: =ROUND(AA92,$G$452) -> 6400 | F92: =ROUND(AB92,$G$452) -> 6200 | G92: =ROUND(AC92,$G$452) -> 6000 | H92: =ROUND(AD92,$G$452) -> 5800 | I92: =ROUND(AE92,$G$452) -> 5700 | J92: =ROUND(AF92,$G$452) -> 5500 | K92: =ROUND(AG92,$G$452) -> 5300 | L92: =ROUND(AH92,$G$452) -> 5100 | N92: =$C92 -> 0.25 | O92: =$G$433 -> 650 | P92: =$G$430*(1-N92)-O92 -> 1600 | Q92: =$G$432-O92 -> 59350 | R92: =IFERROR(P92/(Q92+$G$430*(1-N92)),0)*(1-$G$434) -> 0.024675325 | Z92: =$O92+$G$435+$N92*AJ$90+$R92*($Q92*(1+$G$437)+AJ$90*(1-$N92))-$G$430 -> 6543.7964 | AA92: =$O92+$G$435+$N92*AK$90+$R92*($Q92*(1+$G$437)+AK$90*(1-$N92))-$G$430 -> 6365.17 | AB92: =$O92+$G$435+$N92*AL$90+$R92*($Q92*(1+$G$437)+AL$90*(1-$N92))-$G$430 -> 6186.5437 | AC92: =$O92+$G$435+$N92*AM$90+$R92*($Q92*(1+$G$437)+AM$90*(1-$N92))-$G$430 -> 6007.9174 | AD92: =$O92+$G$435+$N92*AN$90+$R92*($Q92*(1+$G$437)+AN$90*(1-$N92))-$G$430 -> 5829.291 | AE92: =$O92+$G$435+$N92*AO$90+$R92*($Q92*(1+$G$437)+AO$90*(1-$N92))-$G$430 -> 5650.6647 | AF92: =$O92+$G$435+$N92*AP$90+$R92*($Q92*(1+$G$437)+AP$90*(1-$N92))-$G$430 -> 5472.0383 | AG92: =$O92+$G$435+$N92*AQ$90+$R92*($Q92*(1+$G$437)+AQ$90*(1-$N92))-$G$430 -> 5293.412 | AH92: =$O92+$G$435+$N92*AR$90+$R92*($Q92*(1+$G$437)+AR$90*(1-$N92))-$G$430 -> 5114.7857 | AJ92: Helper: Standalone Yr 5 Value by Net Client Wins | AT92: =IF(Z132<$G$449,0,MIN($G$446,1+IFERROR(INT((Z132-$G$449)/$G$463),0))) -> 0 | AU92: =IF(AA132<$G$449,0,MIN($G$446,1+IFERROR(INT((AA132-$G$449)/$G$463),0))) -> 0 | AV92: =IF(AB132<$G$449,0,MIN($G$446,1+IFERROR(INT((AB132-$G$449)/$G$463),0))) -> 0 | AW92: =IF(AC132<$G$449,0,MIN($G$446,1+IFERROR(INT((AC132-$G$449)/$G$463),0))) -> 1 | AX92: =IF(AD132<$G$449,0,MIN($G$446,1+IFERROR(INT((AD132-$G$449)/$G$463),0))) -> 2 | AY92: =IF(AE132<$G$449,0,MIN($G$446,1+IFERROR(INT((AE132-$G$449)/$G$463),0))) -> 4 | AZ92: =IF(AF132<$G$449,0,MIN($G$446,1+IFERROR(INT((AF132-$G$449)/$G$463),0))) -> 5 | BA92: =IF(AG132<$G$449,0,MIN($G$446,1+IFERROR(INT((AG132-$G$449)/$G$463),0))) -> 6 | BB92: =IF(AH132<$G$449,0,MIN($G$446,1+IFERROR(INT((AH132-$G$449)/$G$463),0))) -> 8
C93: =$G$438 -> 0.3 | D93: =ROUND(Z93,$G$452) -> 6900 | E93: =ROUND(AA93,$G$452) -> 6700 | F93: =ROUND(AB93,$G$452) -> 6500 | G93: =ROUND(AC93,$G$452) -> 6300 | H93: =ROUND(AD93,$G$452) -> 6100 | I93: =ROUND(AE93,$G$452) -> 5900 | J93: =ROUND(AF93,$G$452) -> 5700 | K93: =ROUND(AG93,$G$452) -> 5500 | L93: =ROUND(AH93,$G$452) -> 5200 | N93: =$C93 -> 0.3 | O93: =$G$433 -> 650 | P93: =$G$430*(1-N93)-O93 -> 1450 | Q93: =$G$432-O93 -> 59350 | R93: =IFERROR(P93/(Q93+$G$430*(1-N93)),0)*(1-$G$434) -> 0.022416599 | Z93: =$O93+$G$435+$N93*AJ$90+$R93*($Q93*(1+$G$437)+AJ$90*(1-$N93))-$G$430 -> 6923.9122 | AA93: =$O93+$G$435+$N93*AK$90+$R93*($Q93*(1+$G$437)+AK$90*(1-$N93))-$G$430 -> 6713.8955 | AB93: =$O93+$G$435+$N93*AL$90+$R93*($Q93*(1+$G$437)+AL$90*(1-$N93))-$G$430 -> 6503.8789 | AC93: =$O93+$G$435+$N93*AM$90+$R93*($Q93*(1+$G$437)+AM$90*(1-$N93))-$G$430 -> 6293.8622 | AD93: =$O93+$G$435+$N93*AN$90+$R93*($Q93*(1+$G$437)+AN$90*(1-$N93))-$G$430 -> 6083.8455 | AE93: =$O93+$G$435+$N93*AO$90+$R93*($Q93*(1+$G$437)+AO$90*(1-$N93))-$G$430 -> 5873.8289 | AF93: =$O93+$G$435+$N93*AP$90+$R93*($Q93*(1+$G$437)+AP$90*(1-$N93))-$G$430 -> 5663.8122 | AG93: =$O93+$G$435+$N93*AQ$90+$R93*($Q93*(1+$G$437)+AQ$90*(1-$N93))-$G$430 -> 5453.7955 | AH93: =$O93+$G$435+$N93*AR$90+$R93*($Q93*(1+$G$437)+AR$90*(1-$N93))-$G$430 -> 5243.7789 | AJ93: =($G$453+(AJ$89-$G$459)*$G$445*$G$460)*$G$461*$G$462 -> 9153.405 | AK93: =($G$453+(AK$89-$G$459)*$G$445*$G$460)*$G$461*$G$462 -> 8737.6182 | AL93: =($G$453+(AL$89-$G$459)*$G$445*$G$460)*$G$461*$G$462 -> 8321.8313 | AM93: =($G$453+(AM$89-$G$459)*$G$445*$G$460)*$G$461*$G$462 -> 7906.0445 | AN93: =($G$453+(AN$89-$G$459)*$G$445*$G$460)*$G$461*$G$462 -> 7490.2577 | AO93: =($G$453+(AO$89-$G$459)*$G$445*$G$460)*$G$461*$G$462 -> 7074.4709 | AP93: =($G$453+(AP$89-$G$459)*$G$445*$G$460)*$G$461*$G$462 -> 6658.684 | AQ93: =($G$453+(AQ$89-$G$459)*$G$445*$G$460)*$G$461*$G$462 -> 6242.8972 | AR93: =($G$453+(AR$89-$G$459)*$G$445*$G$460)*$G$461*$G$462 -> 5827.1104 | AT93: =IF(Z133<$G$449,0,MIN($G$446,1+IFERROR(INT((Z133-$G$449)/$G$463),0))) -> 0 | AU93: =IF(AA133<$G$449,0,MIN($G$446,1+IFERROR(INT((AA133-$G$449)/$G$463),0))) -> 0 | AV93: =IF(AB133<$G$449,0,MIN($G$446,1+IFERROR(INT((AB133-$G$449)/$G$463),0))) -> 2 | AW93: =IF(AC133<$G$449,0,MIN($G$446,1+IFERROR(INT((AC133-$G$449)/$G$463),0))) -> 3 | AX93: =IF(AD133<$G$449,0,MIN($G$446,1+IFERROR(INT((AD133-$G$449)/$G$463),0))) -> 4 | AY93: =IF(AE133<$G$449,0,MIN($G$446,1+IFERROR(INT((AE133-$G$449)/$G$463),0))) -> 5 | AZ93: =IF(AF133<$G$449,0,MIN($G$446,1+IFERROR(INT((AF133-$G$449)/$G$463),0))) -> 6 | BA93: =IF(AG133<$G$449,0,MIN($G$446,1+IFERROR(INT((AG133-$G$449)/$G$463),0))) -> 7 | BB93: =IF(AH133<$G$449,0,MIN($G$446,1+IFERROR(INT((AH133-$G$449)/$G$463),0))) -> 8
C94: =C93+$G$439 -> 0.35 | D94: =ROUND(Z94,$G$452) -> 7300 | E94: =ROUND(AA94,$G$452) -> 7100 | F94: =ROUND(AB94,$G$452) -> 6800 | G94: =ROUND(AC94,$G$452) -> 6600 | H94: =ROUND(AD94,$G$452) -> 6300 | I94: =ROUND(AE94,$G$452) -> 6100 | J94: =ROUND(AF94,$G$452) -> 5900 | K94: =ROUND(AG94,$G$452) -> 5600 | L94: =ROUND(AH94,$G$452) -> 5400 | N94: =$C94 -> 0.35 | O94: =$G$433 -> 650 | P94: =$G$430*(1-N94)-O94 -> 1300 | Q94: =$G$432-O94 -> 59350 | R94: =IFERROR(P94/(Q94+$G$430*(1-N94)),0)*(1-$G$434) -> 0.020146819 | Z94: =$O94+$G$435+$N94*AJ$90+$R94*($Q94*(1+$G$437)+AJ$90*(1-$N94))-$G$430 -> 7305.6847 | AA94: =$O94+$G$435+$N94*AK$90+$R94*($Q94*(1+$G$437)+AK$90*(1-$N94))-$G$430 -> 7064.1322 | AB94: =$O94+$G$435+$N94*AL$90+$R94*($Q94*(1+$G$437)+AL$90*(1-$N94))-$G$430 -> 6822.5797 | AC94: =$O94+$G$435+$N94*AM$90+$R94*($Q94*(1+$G$437)+AM$90*(1-$N94))-$G$430 -> 6581.0272 | AD94: =$O94+$G$435+$N94*AN$90+$R94*($Q94*(1+$G$437)+AN$90*(1-$N94))-$G$430 -> 6339.4748 | AE94: =$O94+$G$435+$N94*AO$90+$R94*($Q94*(1+$G$437)+AO$90*(1-$N94))-$G$430 -> 6097.9223 | AF94: =$O94+$G$435+$N94*AP$90+$R94*($Q94*(1+$G$437)+AP$90*(1-$N94))-$G$430 -> 5856.3698 | AG94: =$O94+$G$435+$N94*AQ$90+$R94*($Q94*(1+$G$437)+AQ$90*(1-$N94))-$G$430 -> 5614.8173 | AH94: =$O94+$G$435+$N94*AR$90+$R94*($Q94*(1+$G$437)+AR$90*(1-$N94))-$G$430 -> 5373.2649 | AJ94: Helper: Standalone IRR by Net Client Wins | AT94: =IF(Z134<$G$449,0,MIN($G$446,1+IFERROR(INT((Z134-$G$449)/$G$463),0))) -> 1 | AU94: =IF(AA134<$G$449,0,MIN($G$446,1+IFERROR(INT((AA134-$G$449)/$G$463),0))) -> 2 | AV94: =IF(AB134<$G$449,0,MIN($G$446,1+IFERROR(INT((AB134-$G$449)/$G$463),0))) -> 3 | AW94: =IF(AC134<$G$449,0,MIN($G$446,1+IFERROR(INT((AC134-$G$449)/$G$463),0))) -> 4 | AX94: =IF(AD134<$G$449,0,MIN($G$446,1+IFERROR(INT((AD134-$G$449)/$G$463),0))) -> 5 | AY94: =IF(AE134<$G$449,0,MIN($G$446,1+IFERROR(INT((AE134-$G$449)/$G$463),0))) -> 6 | AZ94: =IF(AF134<$G$449,0,MIN($G$446,1+IFERROR(INT((AF134-$G$449)/$G$463),0))) -> 7 | BA94: =IF(AG134<$G$449,0,MIN($G$446,1+IFERROR(INT((AG134-$G$449)/$G$463),0))) -> 8 | BB94: =IF(AH134<$G$449,0,MIN($G$446,1+IFERROR(INT((AH134-$G$449)/$G$463),0))) -> 9
C95: =C94+$G$439 -> 0.4 | D95: =ROUND(Z95,$G$452) -> 7700 | E95: =ROUND(AA95,$G$452) -> 7400 | F95: =ROUND(AB95,$G$452) -> 7100 | G95: =ROUND(AC95,$G$452) -> 6900 | H95: =ROUND(AD95,$G$452) -> 6600 | I95: =ROUND(AE95,$G$452) -> 6300 | J95: =ROUND(AF95,$G$452) -> 6000 | K95: =ROUND(AG95,$G$452) -> 5800 | L95: =ROUND(AH95,$G$452) -> 5500 | N95: =$C95 -> 0.4 | O95: =$G$433 -> 650 | P95: =$G$430*(1-N95)-O95 -> 1150 | Q95: =$G$432-O95 -> 59350 | R95: =IFERROR(P95/(Q95+$G$430*(1-N95)),0)*(1-$G$434) -> 0.017865904 | Z95: =$O95+$G$435+$N95*AJ$90+$R95*($Q95*(1+$G$437)+AJ$90*(1-$N95))-$G$430 -> 7689.126 | AA95: =$O95+$G$435+$N95*AK$90+$R95*($Q95*(1+$G$437)+AK$90*(1-$N95))-$G$430 -> 7415.8912 | AB95: =$O95+$G$435+$N95*AL$90+$R95*($Q95*(1+$G$437)+AL$90*(1-$N95))-$G$430 -> 7142.6563 | AC95: =$O95+$G$435+$N95*AM$90+$R95*($Q95*(1+$G$437)+AM$90*(1-$N95))-$G$430 -> 6869.4215 | AD95: =$O95+$G$435+$N95*AN$90+$R95*($Q95*(1+$G$437)+AN$90*(1-$N95))-$G$430 -> 6596.1867 | AE95: =$O95+$G$435+$N95*AO$90+$R95*($Q95*(1+$G$437)+AO$90*(1-$N95))-$G$430 -> 6322.9518 | AF95: =$O95+$G$435+$N95*AP$90+$R95*($Q95*(1+$G$437)+AP$90*(1-$N95))-$G$430 -> 6049.717 | AG95: =$O95+$G$435+$N95*AQ$90+$R95*($Q95*(1+$G$437)+AQ$90*(1-$N95))-$G$430 -> 5776.4821 | AH95: =$O95+$G$435+$N95*AR$90+$R95*($Q95*(1+$G$437)+AR$90*(1-$N95))-$G$430 -> 5503.2473 | AJ95: =IFERROR((AJ$93/$G$430)^(1/$G$445)-1,0) -> 0.24994897 | AK95: =IFERROR((AK$93/$G$430)^(1/$G$445)-1,0) -> 0.23838123 | AL95: =IFERROR((AL$93/$G$430)^(1/$G$445)-1,0) -> 0.22636439 | AM95: =IFERROR((AM$93/$G$430)^(1/$G$445)-1,0) -> 0.2138572 | AN95: =IFERROR((AN$93/$G$430)^(1/$G$445)-1,0) -> 0.20081223 | AO95: =IFERROR((AO$93/$G$430)^(1/$G$445)-1,0) -> 0.18717445 | AP95: =IFERROR((AP$93/$G$430)^(1/$G$445)-1,0) -> 0.17287959 | AQ95: =IFERROR((AQ$93/$G$430)^(1/$G$445)-1,0) -> 0.15785183 | AR95: =IFERROR((AR$93/$G$430)^(1/$G$445)-1,0) -> 0.14200077 | AT95: =IF(Z135<$G$449,0,MIN($G$446,1+IFERROR(INT((Z135-$G$449)/$G$463),0))) -> 3 | AU95: =IF(AA135<$G$449,0,MIN($G$446,1+IFERROR(INT((AA135-$G$449)/$G$463),0))) -> 4 | AV95: =IF(AB135<$G$449,0,MIN($G$446,1+IFERROR(INT((AB135-$G$449)/$G$463),0))) -> 5 | AW95: =IF(AC135<$G$449,0,MIN($G$446,1+IFERROR(INT((AC135-$G$449)/$G$463),0))) -> 6 | AX95: =IF(AD135<$G$449,0,MIN($G$446,1+IFERROR(INT((AD135-$G$449)/$G$463),0))) -> 7 | AY95: =IF(AE135<$G$449,0,MIN($G$446,1+IFERROR(INT((AE135-$G$449)/$G$463),0))) -> 7 | AZ95: =IF(AF135<$G$449,0,MIN($G$446,1+IFERROR(INT((AF135-$G$449)/$G$463),0))) -> 8 | BA95: =IF(AG135<$G$449,0,MIN($G$446,1+IFERROR(INT((AG135-$G$449)/$G$463),0))) -> 9 | BB95: =IF(AH135<$G$449,0,MIN($G$446,1+IFERROR(INT((AH135-$G$449)/$G$463),0))) -> 10
C96: =C95+$G$439 -> 0.45 | D96: =ROUND(Z96,$G$452) -> 8100 | E96: =ROUND(AA96,$G$452) -> 7800 | F96: =ROUND(AB96,$G$452) -> 7500 | G96: =ROUND(AC96,$G$452) -> 7200 | H96: =ROUND(AD96,$G$452) -> 6900 | I96: =ROUND(AE96,$G$452) -> 6500 | J96: =ROUND(AF96,$G$452) -> 6200 | K96: =ROUND(AG96,$G$452) -> 5900 | L96: =ROUND(AH96,$G$452) -> 5600 | N96: =$C96 -> 0.45 | O96: =$G$433 -> 650 | P96: =$G$430*(1-N96)-O96 -> 1000 | Q96: =$G$432-O96 -> 59350 | R96: =IFERROR(P96/(Q96+$G$430*(1-N96)),0)*(1-$G$434) -> 0.01557377 | Z96: =$O96+$G$435+$N96*AJ$90+$R96*($Q96*(1+$G$437)+AJ$90*(1-$N96))-$G$430 -> 8074.2485 | AA96: =$O96+$G$435+$N96*AK$90+$R96*($Q96*(1+$G$437)+AK$90*(1-$N96))-$G$430 -> 7769.1837 | AB96: =$O96+$G$435+$N96*AL$90+$R96*($Q96*(1+$G$437)+AL$90*(1-$N96))-$G$430 -> 7464.1188 | AC96: =$O96+$G$435+$N96*AM$90+$R96*($Q96*(1+$G$437)+AM$90*(1-$N96))-$G$430 -> 7159.054 | AD96: =$O96+$G$435+$N96*AN$90+$R96*($Q96*(1+$G$437)+AN$90*(1-$N96))-$G$430 -> 6853.9892 | AE96: =$O96+$G$435+$N96*AO$90+$R96*($Q96*(1+$G$437)+AO$90*(1-$N96))-$G$430 -> 6548.9243 | AF96: =$O96+$G$435+$N96*AP$90+$R96*($Q96*(1+$G$437)+AP$90*(1-$N96))-$G$430 -> 6243.8595 | AG96: =$O96+$G$435+$N96*AQ$90+$R96*($Q96*(1+$G$437)+AQ$90*(1-$N96))-$G$430 -> 5938.7946 | AH96: =$O96+$G$435+$N96*AR$90+$R96*($Q96*(1+$G$437)+AR$90*(1-$N96))-$G$430 -> 5633.7298 | AT96: =IF(Z136<$G$449,0,MIN($G$446,1+IFERROR(INT((Z136-$G$449)/$G$463),0))) -> 6 | AU96: =IF(AA136<$G$449,0,MIN($G$446,1+IFERROR(INT((AA136-$G$449)/$G$463),0))) -> 6 | AV96: =IF(AB136<$G$449,0,MIN($G$446,1+IFERROR(INT((AB136-$G$449)/$G$463),0))) -> 7 | AW96: =IF(AC136<$G$449,0,MIN($G$446,1+IFERROR(INT((AC136-$G$449)/$G$463),0))) -> 7 | AX96: =IF(AD136<$G$449,0,MIN($G$446,1+IFERROR(INT((AD136-$G$449)/$G$463),0))) -> 8 | AY96: =IF(AE136<$G$449,0,MIN($G$446,1+IFERROR(INT((AE136-$G$449)/$G$463),0))) -> 9 | AZ96: =IF(AF136<$G$449,0,MIN($G$446,1+IFERROR(INT((AF136-$G$449)/$G$463),0))) -> 9 | BA96: =IF(AG136<$G$449,0,MIN($G$446,1+IFERROR(INT((AG136-$G$449)/$G$463),0))) -> 10 | BB96: =IF(AH136<$G$449,0,MIN($G$446,1+IFERROR(INT((AH136-$G$449)/$G$463),0))) -> 10
B97: Ben's Year 5 value (cash at close + earnout + retained Keystone stake + Topkey stock, after dilution) less Keystone value today (G430); Topkey growth held at model (G437)
B99: Ben's % Return on Keystone Value Based on Net Client Wins & Rollover %
D101: Keystone Total Annual Net Client Wins — Partnership (#)
D102: =E102+$G$458 -> 64 | E102: =F102+$G$458 -> 60 | F102: =G102+$G$458 -> 56 | G102: =H102+$G$458 -> 52 | H102: =$G$457 -> 48 | I102: =H102-$G$458 -> 44 | J102: =I102-$G$458 -> 40 | K102: =J102-$G$458 -> 36 | L102: =K102-$G$458 -> 32 | AT102: Helper: Gradient Band (0 = below $1M hurdle)
B103: Ben's Rollover % | C103: =C104-$G$439 -> 0.15 | D103: =IFERROR(Z90/$G$430,0) -> 1.9294955 | E103: =IFERROR(AA90/$G$430,0) -> 1.8907362 | F103: =IFERROR(AB90/$G$430,0) -> 1.8519769 | G103: =IFERROR(AC90/$G$430,0) -> 1.8132176 | H103: =IFERROR(AD90/$G$430,0) -> 1.7744583 | I103: =IFERROR(AE90/$G$430,0) -> 1.735699 | J103: =IFERROR(AF90/$G$430,0) -> 1.6969397 | K103: =IFERROR(AG90/$G$430,0) -> 1.6581804 | L103: =IFERROR(AH90/$G$430,0) -> 1.6194211 | AT103: =IF(Z130<$G$449,0,MIN($G$446,1+IFERROR(INT((Z130-$G$449)/$G$463),0))) -> 0 | AU103: =IF(AA130<$G$449,0,MIN($G$446,1+IFERROR(INT((AA130-$G$449)/$G$463),0))) -> 0 | AV103: =IF(AB130<$G$449,0,MIN($G$446,1+IFERROR(INT((AB130-$G$449)/$G$463),0))) -> 0 | AW103: =IF(AC130<$G$449,0,MIN($G$446,1+IFERROR(INT((AC130-$G$449)/$G$463),0))) -> 0 | AX103: =IF(AD130<$G$449,0,MIN($G$446,1+IFERROR(INT((AD130-$G$449)/$G$463),0))) -> 0 | AY103: =IF(AE130<$G$449,0,MIN($G$446,1+IFERROR(INT((AE130-$G$449)/$G$463),0))) -> 1 | AZ103: =IF(AF130<$G$449,0,MIN($G$446,1+IFERROR(INT((AF130-$G$449)/$G$463),0))) -> 3 | BA103: =IF(AG130<$G$449,0,MIN($G$446,1+IFERROR(INT((AG130-$G$449)/$G$463),0))) -> 5 | BB103: =IF(AH130<$G$449,0,MIN($G$446,1+IFERROR(INT((AH130-$G$449)/$G$463),0))) -> 6
C104: =C105-$G$439 -> 0.2 | D104: =IFERROR(Z91/$G$430,0) -> 2.0551084 | E104: =IFERROR(AA91/$G$430,0) -> 2.0059816 | F104: =IFERROR(AB91/$G$430,0) -> 1.9568548 | G104: =IFERROR(AC91/$G$430,0) -> 1.907728 | H104: =IFERROR(AD91/$G$430,0) -> 1.8586011 | I104: =IFERROR(AE91/$G$430,0) -> 1.8094743 | J104: =IFERROR(AF91/$G$430,0) -> 1.7603475 | K104: =IFERROR(AG91/$G$430,0) -> 1.7112207 | L104: =IFERROR(AH91/$G$430,0) -> 1.6620939 | AT104: =IF(Z131<$G$449,0,MIN($G$446,1+IFERROR(INT((Z131-$G$449)/$G$463),0))) -> 0 | AU104: =IF(AA131<$G$449,0,MIN($G$446,1+IFERROR(INT((AA131-$G$449)/$G$463),0))) -> 0 | AV104: =IF(AB131<$G$449,0,MIN($G$446,1+IFERROR(INT((AB131-$G$449)/$G$463),0))) -> 0 | AW104: =IF(AC131<$G$449,0,MIN($G$446,1+IFERROR(INT((AC131-$G$449)/$G$463),0))) -> 0 | AX104: =IF(AD131<$G$449,0,MIN($G$446,1+IFERROR(INT((AD131-$G$449)/$G$463),0))) -> 1 | AY104: =IF(AE131<$G$449,0,MIN($G$446,1+IFERROR(INT((AE131-$G$449)/$G$463),0))) -> 2 | AZ104: =IF(AF131<$G$449,0,MIN($G$446,1+IFERROR(INT((AF131-$G$449)/$G$463),0))) -> 4 | BA104: =IF(AG131<$G$449,0,MIN($G$446,1+IFERROR(INT((AG131-$G$449)/$G$463),0))) -> 5 | BB104: =IF(AH131<$G$449,0,MIN($G$446,1+IFERROR(INT((AH131-$G$449)/$G$463),0))) -> 7
C105: =C106-$G$439 -> 0.25 | D105: =IFERROR(Z92/$G$430,0) -> 2.1812655 | E105: =IFERROR(AA92/$G$430,0) -> 2.1217233 | F105: =IFERROR(AB92/$G$430,0) -> 2.0621812 | G105: =IFERROR(AC92/$G$430,0) -> 2.0026391 | H105: =IFERROR(AD92/$G$430,0) -> 1.943097 | I105: =IFERROR(AE92/$G$430,0) -> 1.8835549 | J105: =IFERROR(AF92/$G$430,0) -> 1.8240128 | K105: =IFERROR(AG92/$G$430,0) -> 1.7644707 | L105: =IFERROR(AH92/$G$430,0) -> 1.7049286 | AT105: =IF(Z132<$G$449,0,MIN($G$446,1+IFERROR(INT((Z132-$G$449)/$G$463),0))) -> 0 | AU105: =IF(AA132<$G$449,0,MIN($G$446,1+IFERROR(INT((AA132-$G$449)/$G$463),0))) -> 0 | AV105: =IF(AB132<$G$449,0,MIN($G$446,1+IFERROR(INT((AB132-$G$449)/$G$463),0))) -> 0 | AW105: =IF(AC132<$G$449,0,MIN($G$446,1+IFERROR(INT((AC132-$G$449)/$G$463),0))) -> 1 | AX105: =IF(AD132<$G$449,0,MIN($G$446,1+IFERROR(INT((AD132-$G$449)/$G$463),0))) -> 2 | AY105: =IF(AE132<$G$449,0,MIN($G$446,1+IFERROR(INT((AE132-$G$449)/$G$463),0))) -> 4 | AZ105: =IF(AF132<$G$449,0,MIN($G$446,1+IFERROR(INT((AF132-$G$449)/$G$463),0))) -> 5 | BA105: =IF(AG132<$G$449,0,MIN($G$446,1+IFERROR(INT((AG132-$G$449)/$G$463),0))) -> 6 | BB105: =IF(AH132<$G$449,0,MIN($G$446,1+IFERROR(INT((AH132-$G$449)/$G$463),0))) -> 8
C106: =$G$438 -> 0.3 | D106: =IFERROR(Z93/$G$430,0) -> 2.3079707 | E106: =IFERROR(AA93/$G$430,0) -> 2.2379652 | F106: =IFERROR(AB93/$G$430,0) -> 2.1679596 | G106: =IFERROR(AC93/$G$430,0) -> 2.0979541 | H106: =IFERROR(AD93/$G$430,0) -> 2.0279485 | I106: =IFERROR(AE93/$G$430,0) -> 1.957943 | J106: =IFERROR(AF93/$G$430,0) -> 1.8879374 | K106: =IFERROR(AG93/$G$430,0) -> 1.8179318 | L106: =IFERROR(AH93/$G$430,0) -> 1.7479263 | AT106: =IF(Z133<$G$449,0,MIN($G$446,1+IFERROR(INT((Z133-$G$449)/$G$463),0))) -> 0 | AU106: =IF(AA133<$G$449,0,MIN($G$446,1+IFERROR(INT((AA133-$G$449)/$G$463),0))) -> 0 | AV106: =IF(AB133<$G$449,0,MIN($G$446,1+IFERROR(INT((AB133-$G$449)/$G$463),0))) -> 2 | AW106: =IF(AC133<$G$449,0,MIN($G$446,1+IFERROR(INT((AC133-$G$449)/$G$463),0))) -> 3 | AX106: =IF(AD133<$G$449,0,MIN($G$446,1+IFERROR(INT((AD133-$G$449)/$G$463),0))) -> 4 | AY106: =IF(AE133<$G$449,0,MIN($G$446,1+IFERROR(INT((AE133-$G$449)/$G$463),0))) -> 5 | AZ106: =IF(AF133<$G$449,0,MIN($G$446,1+IFERROR(INT((AF133-$G$449)/$G$463),0))) -> 6 | BA106: =IF(AG133<$G$449,0,MIN($G$446,1+IFERROR(INT((AG133-$G$449)/$G$463),0))) -> 7 | BB106: =IF(AH133<$G$449,0,MIN($G$446,1+IFERROR(INT((AH133-$G$449)/$G$463),0))) -> 8
C107: =C106+$G$439 -> 0.35 | D107: =IFERROR(Z94/$G$430,0) -> 2.4352282 | E107: =IFERROR(AA94/$G$430,0) -> 2.3547107 | F107: =IFERROR(AB94/$G$430,0) -> 2.2741932 | G107: =IFERROR(AC94/$G$430,0) -> 2.1936757 | H107: =IFERROR(AD94/$G$430,0) -> 2.1131583 | I107: =IFERROR(AE94/$G$430,0) -> 2.0326408 | J107: =IFERROR(AF94/$G$430,0) -> 1.9521233 | K107: =IFERROR(AG94/$G$430,0) -> 1.8716058 | L107: =IFERROR(AH94/$G$430,0) -> 1.7910883 | AT107: =IF(Z134<$G$449,0,MIN($G$446,1+IFERROR(INT((Z134-$G$449)/$G$463),0))) -> 1 | AU107: =IF(AA134<$G$449,0,MIN($G$446,1+IFERROR(INT((AA134-$G$449)/$G$463),0))) -> 2 | AV107: =IF(AB134<$G$449,0,MIN($G$446,1+IFERROR(INT((AB134-$G$449)/$G$463),0))) -> 3 | AW107: =IF(AC134<$G$449,0,MIN($G$446,1+IFERROR(INT((AC134-$G$449)/$G$463),0))) -> 4 | AX107: =IF(AD134<$G$449,0,MIN($G$446,1+IFERROR(INT((AD134-$G$449)/$G$463),0))) -> 5 | AY107: =IF(AE134<$G$449,0,MIN($G$446,1+IFERROR(INT((AE134-$G$449)/$G$463),0))) -> 6 | AZ107: =IF(AF134<$G$449,0,MIN($G$446,1+IFERROR(INT((AF134-$G$449)/$G$463),0))) -> 7 | BA107: =IF(AG134<$G$449,0,MIN($G$446,1+IFERROR(INT((AG134-$G$449)/$G$463),0))) -> 8 | BB107: =IF(AH134<$G$449,0,MIN($G$446,1+IFERROR(INT((AH134-$G$449)/$G$463),0))) -> 9
C108: =C107+$G$439 -> 0.4 | D108: =IFERROR(Z95/$G$430,0) -> 2.563042 | E108: =IFERROR(AA95/$G$430,0) -> 2.4719637 | F108: =IFERROR(AB95/$G$430,0) -> 2.3808854 | G108: =IFERROR(AC95/$G$430,0) -> 2.2898072 | H108: =IFERROR(AD95/$G$430,0) -> 2.1987289 | I108: =IFERROR(AE95/$G$430,0) -> 2.1076506 | J108: =IFERROR(AF95/$G$430,0) -> 2.0165723 | K108: =IFERROR(AG95/$G$430,0) -> 1.925494 | L108: =IFERROR(AH95/$G$430,0) -> 1.8344158 | AT108: =IF(Z135<$G$449,0,MIN($G$446,1+IFERROR(INT((Z135-$G$449)/$G$463),0))) -> 3 | AU108: =IF(AA135<$G$449,0,MIN($G$446,1+IFERROR(INT((AA135-$G$449)/$G$463),0))) -> 4 | AV108: =IF(AB135<$G$449,0,MIN($G$446,1+IFERROR(INT((AB135-$G$449)/$G$463),0))) -> 5 | AW108: =IF(AC135<$G$449,0,MIN($G$446,1+IFERROR(INT((AC135-$G$449)/$G$463),0))) -> 6 | AX108: =IF(AD135<$G$449,0,MIN($G$446,1+IFERROR(INT((AD135-$G$449)/$G$463),0))) -> 7 | AY108: =IF(AE135<$G$449,0,MIN($G$446,1+IFERROR(INT((AE135-$G$449)/$G$463),0))) -> 7 | AZ108: =IF(AF135<$G$449,0,MIN($G$446,1+IFERROR(INT((AF135-$G$449)/$G$463),0))) -> 8 | BA108: =IF(AG135<$G$449,0,MIN($G$446,1+IFERROR(INT((AG135-$G$449)/$G$463),0))) -> 9 | BB108: =IF(AH135<$G$449,0,MIN($G$446,1+IFERROR(INT((AH135-$G$449)/$G$463),0))) -> 10
C109: =C108+$G$439 -> 0.45 | D109: =IFERROR(Z96/$G$430,0) -> 2.6914162 | E109: =IFERROR(AA96/$G$430,0) -> 2.5897279 | F109: =IFERROR(AB96/$G$430,0) -> 2.4880396 | G109: =IFERROR(AC96/$G$430,0) -> 2.3863513 | H109: =IFERROR(AD96/$G$430,0) -> 2.2846631 | I109: =IFERROR(AE96/$G$430,0) -> 2.1829748 | J109: =IFERROR(AF96/$G$430,0) -> 2.0812865 | K109: =IFERROR(AG96/$G$430,0) -> 1.9795982 | L109: =IFERROR(AH96/$G$430,0) -> 1.8779099 | AT109: =IF(Z136<$G$449,0,MIN($G$446,1+IFERROR(INT((Z136-$G$449)/$G$463),0))) -> 6 | AU109: =IF(AA136<$G$449,0,MIN($G$446,1+IFERROR(INT((AA136-$G$449)/$G$463),0))) -> 6 | AV109: =IF(AB136<$G$449,0,MIN($G$446,1+IFERROR(INT((AB136-$G$449)/$G$463),0))) -> 7 | AW109: =IF(AC136<$G$449,0,MIN($G$446,1+IFERROR(INT((AC136-$G$449)/$G$463),0))) -> 7 | AX109: =IF(AD136<$G$449,0,MIN($G$446,1+IFERROR(INT((AD136-$G$449)/$G$463),0))) -> 8 | AY109: =IF(AE136<$G$449,0,MIN($G$446,1+IFERROR(INT((AE136-$G$449)/$G$463),0))) -> 9 | AZ109: =IF(AF136<$G$449,0,MIN($G$446,1+IFERROR(INT((AF136-$G$449)/$G$463),0))) -> 9 | BA109: =IF(AG136<$G$449,0,MIN($G$446,1+IFERROR(INT((AG136-$G$449)/$G$463),0))) -> 10 | BB109: =IF(AH136<$G$449,0,MIN($G$446,1+IFERROR(INT((AH136-$G$449)/$G$463),0))) -> 10
B110: Ben's Year 5 total value ÷ Keystone value today (G430), less 1
B112: Ben's IRR Based on Net Client Wins & Rollover %
D114: Keystone Total Annual Net Client Wins — Partnership (#) | BD114: Helper: IRR CF — Col D | BJ114: Helper: IRR CF — Col E | BP114: Helper: IRR CF — Col F | BV114: Helper: IRR CF — Col G | CB114: Helper: IRR CF — Col H | CH114: Helper: IRR CF — Col I | CN114: Helper: IRR CF — Col J | CT114: Helper: IRR CF — Col K | CZ114: Helper: IRR CF — Col L
D115: =E115+$G$458 -> 64 | E115: =F115+$G$458 -> 60 | F115: =G115+$G$458 -> 56 | G115: =H115+$G$458 -> 52 | H115: =$G$457 -> 48 | I115: =H115-$G$458 -> 44 | J115: =I115-$G$458 -> 40 | K115: =J115-$G$458 -> 36 | L115: =K115-$G$458 -> 32 | AT115: Helper: Gradient Band (0 = below $1M hurdle) | BD115: =$S$9 -> 0 | BE115: =$T$9 -> 1 | BF115: =$U$9 -> 2 | BG115: =$V$9 -> 3 | BH115: =$W$9 -> 4 | BI115: =$X$9 -> 5 | BJ115: =$S$9 -> 0 | BK115: =$T$9 -> 1 | BL115: =$U$9 -> 2 | BM115: =$V$9 -> 3 | BN115: =$W$9 -> 4 | BO115: =$X$9 -> 5 | BP115: =$S$9 -> 0 | BQ115: =$T$9 -> 1 | BR115: =$U$9 -> 2 | BS115: =$V$9 -> 3 | BT115: =$W$9 -> 4 | BU115: =$X$9 -> 5 | BV115: =$S$9 -> 0 | BW115: =$T$9 -> 1 | BX115: =$U$9 -> 2 | BY115: =$V$9 -> 3 | BZ115: =$W$9 -> 4 | CA115: =$X$9 -> 5 | CB115: =$S$9 -> 0 | CC115: =$T$9 -> 1 | CD115: =$U$9 -> 2 | CE115: =$V$9 -> 3 | CF115: =$W$9 -> 4 | CG115: =$X$9 -> 5 | CH115: =$S$9 -> 0 | CI115: =$T$9 -> 1 | CJ115: =$U$9 -> 2 | CK115: =$V$9 -> 3 | CL115: =$W$9 -> 4 | CM115: =$X$9 -> 5 | CN115: =$S$9 -> 0 | CO115: =$T$9 -> 1 | CP115: =$U$9 -> 2 | CQ115: =$V$9 -> 3 | CR115: =$W$9 -> 4 | CS115: =$X$9 -> 5 | CT115: =$S$9 -> 0 | CU115: =$T$9 -> 1 | CV115: =$U$9 -> 2 | CW115: =$V$9 -> 3 | CX115: =$W$9 -> 4 | CY115: =$X$9 -> 5 | CZ115: =$S$9 -> 0 | DA115: =$T$9 -> 1 | DB115: =$U$9 -> 2 | DC115: =$V$9 -> 3 | DD115: =$W$9 -> 4 | DE115: =$X$9 -> 5
B116: Ben's Rollover % | C116: =C117-$G$439 -> 0.15 | D116: =IFERROR(IRR(BD116:BI116),0) -> 0.28202106 | E116: =IFERROR(IRR(BJ116:BO116),0) -> 0.27833659 | F116: =IFERROR(IRR(BP116:BU116),0) -> 0.27460914 | G116: =IFERROR(IRR(BV116:CA116),0) -> 0.27083758 | H116: =IFERROR(IRR(CB116:CG116),0) -> 0.2670207 | I116: =IFERROR(IRR(CH116:CM116),0) -> 0.26315727 | J116: =IFERROR(IRR(CN116:CS116),0) -> 0.25924599 | K116: =IFERROR(IRR(CT116:CY116),0) -> 0.2552855 | L116: =IFERROR(IRR(CZ116:DE116),0) -> 0.25127439 | AT116: =IF(Z130<$G$449,0,MIN($G$446,1+IFERROR(INT((Z130-$G$449)/$G$463),0))) -> 0 | AU116: =IF(AA130<$G$449,0,MIN($G$446,1+IFERROR(INT((AA130-$G$449)/$G$463),0))) -> 0 | AV116: =IF(AB130<$G$449,0,MIN($G$446,1+IFERROR(INT((AB130-$G$449)/$G$463),0))) -> 0 | AW116: =IF(AC130<$G$449,0,MIN($G$446,1+IFERROR(INT((AC130-$G$449)/$G$463),0))) -> 0 | AX116: =IF(AD130<$G$449,0,MIN($G$446,1+IFERROR(INT((AD130-$G$449)/$G$463),0))) -> 0 | AY116: =IF(AE130<$G$449,0,MIN($G$446,1+IFERROR(INT((AE130-$G$449)/$G$463),0))) -> 1 | AZ116: =IF(AF130<$G$449,0,MIN($G$446,1+IFERROR(INT((AF130-$G$449)/$G$463),0))) -> 3 | BA116: =IF(AG130<$G$449,0,MIN($G$446,1+IFERROR(INT((AG130-$G$449)/$G$463),0))) -> 5 | BB116: =IF(AH130<$G$449,0,MIN($G$446,1+IFERROR(INT((AH130-$G$449)/$G$463),0))) -> 6 | BD116: =(BD$115=0)*($O90-$G$430)+(BD$115=$G$444)*$G$435+(BD$115=$G$445)*(Z90+$G$430-$O90-$G$435) -> -2350 | BE116: =(BE$115=0)*($O90-$G$430)+(BE$115=$G$444)*$G$435+(BE$115=$G$445)*(Z90+$G$430-$O90-$G$435) -> 0 | BF116: =(BF$115=0)*($O90-$G$430)+(BF$115=$G$444)*$G$435+(BF$115=$G$445)*(Z90+$G$430-$O90-$G$435) -> 0 | BG116: =(BG$115=0)*($O90-$G$430)+(BG$115=$G$444)*$G$435+(BG$115=$G$445)*(Z90+$G$430-$O90-$G$435) -> 0 | BH116: =(BH$115=0)*($O90-$G$430)+(BH$115=$G$444)*$G$435+(BH$115=$G$445)*(Z90+$G$430-$O90-$G$435) -> 0 | BI116: =(BI$115=0)*($O90-$G$430)+(BI$115=$G$444)*$G$435+(BI$115=$G$445)*(Z90+$G$430-$O90-$G$435) -> 8138.4866 | BJ116: =(BJ$115=0)*($O90-$G$430)+(BJ$115=$G$444)*$G$435+(BJ$115=$G$445)*(AA90+$G$430-$O90-$G$435) -> -2350 | BK116: =(BK$115=0)*($O90-$G$430)+(BK$115=$G$444)*$G$435+(BK$115=$G$445)*(AA90+$G$430-$O90-$G$435) -> 0 | BL116: =(BL$115=0)*($O90-$G$430)+(BL$115=$G$444)*$G$435+(BL$115=$G$445)*(AA90+$G$430-$O90-$G$435) -> 0 | BM116: =(BM$115=0)*($O90-$G$430)+(BM$115=$G$444)*$G$435+(BM$115=$G$445)*(AA90+$G$430-$O90-$G$435) -> 0 | BN116: =(BN$115=0)*($O90-$G$430)+(BN$115=$G$444)*$G$435+(BN$115=$G$445)*(AA90+$G$430-$O90-$G$435) -> 0 | BO116: =(BO$115=0)*($O90-$G$430)+(BO$115=$G$444)*$G$435+(BO$115=$G$445)*(AA90+$G$430-$O90-$G$435) -> 8022.2087 | BP116: =(BP$115=0)*($O90-$G$430)+(BP$115=$G$444)*$G$435+(BP$115=$G$445)*(AB90+$G$430-$O90-$G$435) -> -2350 | BQ116: =(BQ$115=0)*($O90-$G$430)+(BQ$115=$G$444)*$G$435+(BQ$115=$G$445)*(AB90+$G$430-$O90-$G$435) -> 0 | BR116: =(BR$115=0)*($O90-$G$430)+(BR$115=$G$444)*$G$435+(BR$115=$G$445)*(AB90+$G$430-$O90-$G$435) -> 0 | BS116: =(BS$115=0)*($O90-$G$430)+(BS$115=$G$444)*$G$435+(BS$115=$G$445)*(AB90+$G$430-$O90-$G$435) -> 0 | BT116: =(BT$115=0)*($O90-$G$430)+(BT$115=$G$444)*$G$435+(BT$115=$G$445)*(AB90+$G$430-$O90-$G$435) -> 0 | BU116: =(BU$115=0)*($O90-$G$430)+(BU$115=$G$444)*$G$435+(BU$115=$G$445)*(AB90+$G$430-$O90-$G$435) -> 7905.9308 | BV116: =(BV$115=0)*($O90-$G$430)+(BV$115=$G$444)*$G$435+(BV$115=$G$445)*(AC90+$G$430-$O90-$G$435) -> -2350 | BW116: =(BW$115=0)*($O90-$G$430)+(BW$115=$G$444)*$G$435+(BW$115=$G$445)*(AC90+$G$430-$O90-$G$435) -> 0 | BX116: =(BX$115=0)*($O90-$G$430)+(BX$115=$G$444)*$G$435+(BX$115=$G$445)*(AC90+$G$430-$O90-$G$435) -> 0 | BY116: =(BY$115=0)*($O90-$G$430)+(BY$115=$G$444)*$G$435+(BY$115=$G$445)*(AC90+$G$430-$O90-$G$435) -> 0 | BZ116: =(BZ$115=0)*($O90-$G$430)+(BZ$115=$G$444)*$G$435+(BZ$115=$G$445)*(AC90+$G$430-$O90-$G$435) -> 0 | CA116: =(CA$115=0)*($O90-$G$430)+(CA$115=$G$444)*$G$435+(CA$115=$G$445)*(AC90+$G$430-$O90-$G$435) -> 7789.6529 | CB116: =(CB$115=0)*($O90-$G$430)+(CB$115=$G$444)*$G$435+(CB$115=$G$445)*(AD90+$G$430-$O90-$G$435) -> -2350 | CC116: =(CC$115=0)*($O90-$G$430)+(CC$115=$G$444)*$G$435+(CC$115=$G$445)*(AD90+$G$430-$O90-$G$435) -> 0 | CD116: =(CD$115=0)*($O90-$G$430)+(CD$115=$G$444)*$G$435+(CD$115=$G$445)*(AD90+$G$430-$O90-$G$435) -> 0 | CE116: =(CE$115=0)*($O90-$G$430)+(CE$115=$G$444)*$G$435+(CE$115=$G$445)*(AD90+$G$430-$O90-$G$435) -> 0 | CF116: =(CF$115=0)*($O90-$G$430)+(CF$115=$G$444)*$G$435+(CF$115=$G$445)*(AD90+$G$430-$O90-$G$435) -> 0 | CG116: =(CG$115=0)*($O90-$G$430)+(CG$115=$G$444)*$G$435+(CG$115=$G$445)*(AD90+$G$430-$O90-$G$435) -> 7673.375 | CH116: =(CH$115=0)*($O90-$G$430)+(CH$115=$G$444)*$G$435+(CH$115=$G$445)*(AE90+$G$430-$O90-$G$435) -> -2350 | CI116: =(CI$115=0)*($O90-$G$430)+(CI$115=$G$444)*$G$435+(CI$115=$G$445)*(AE90+$G$430-$O90-$G$435) -> 0 | CJ116: =(CJ$115=0)*($O90-$G$430)+(CJ$115=$G$444)*$G$435+(CJ$115=$G$445)*(AE90+$G$430-$O90-$G$435) -> 0 | CK116: =(CK$115=0)*($O90-$G$430)+(CK$115=$G$444)*$G$435+(CK$115=$G$445)*(AE90+$G$430-$O90-$G$435) -> 0 | CL116: =(CL$115=0)*($O90-$G$430)+(CL$115=$G$444)*$G$435+(CL$115=$G$445)*(AE90+$G$430-$O90-$G$435) -> 0 | CM116: =(CM$115=0)*($O90-$G$430)+(CM$115=$G$444)*$G$435+(CM$115=$G$445)*(AE90+$G$430-$O90-$G$435) -> 7557.0971 | CN116: =(CN$115=0)*($O90-$G$430)+(CN$115=$G$444)*$G$435+(CN$115=$G$445)*(AF90+$G$430-$O90-$G$435) -> -2350 | CO116: =(CO$115=0)*($O90-$G$430)+(CO$115=$G$444)*$G$435+(CO$115=$G$445)*(AF90+$G$430-$O90-$G$435) -> 0 | CP116: =(CP$115=0)*($O90-$G$430)+(CP$115=$G$444)*$G$435+(CP$115=$G$445)*(AF90+$G$430-$O90-$G$435) -> 0 | CQ116: =(CQ$115=0)*($O90-$G$430)+(CQ$115=$G$444)*$G$435+(CQ$115=$G$445)*(AF90+$G$430-$O90-$G$435) -> 0 | CR116: =(CR$115=0)*($O90-$G$430)+(CR$115=$G$444)*$G$435+(CR$115=$G$445)*(AF90+$G$430-$O90-$G$435) -> 0 | CS116: =(CS$115=0)*($O90-$G$430)+(CS$115=$G$444)*$G$435+(CS$115=$G$445)*(AF90+$G$430-$O90-$G$435) -> 7440.8192 | CT116: =(CT$115=0)*($O90-$G$430)+(CT$115=$G$444)*$G$435+(CT$115=$G$445)*(AG90+$G$430-$O90-$G$435) -> -2350 | CU116: =(CU$115=0)*($O90-$G$430)+(CU$115=$G$444)*$G$435+(CU$115=$G$445)*(AG90+$G$430-$O90-$G$435) -> 0 | CV116: =(CV$115=0)*($O90-$G$430)+(CV$115=$G$444)*$G$435+(CV$115=$G$445)*(AG90+$G$430-$O90-$G$435) -> 0 | CW116: =(CW$115=0)*($O90-$G$430)+(CW$115=$G$444)*$G$435+(CW$115=$G$445)*(AG90+$G$430-$O90-$G$435) -> 0 | CX116: =(CX$115=0)*($O90-$G$430)+(CX$115=$G$444)*$G$435+(CX$115=$G$445)*(AG90+$G$430-$O90-$G$435) -> 0 | CY116: =(CY$115=0)*($O90-$G$430)+(CY$115=$G$444)*$G$435+(CY$115=$G$445)*(AG90+$G$430-$O90-$G$435) -> 7324.5412 | CZ116: =(CZ$115=0)*($O90-$G$430)+(CZ$115=$G$444)*$G$435+(CZ$115=$G$445)*(AH90+$G$430-$O90-$G$435) -> -2350 | DA116: =(DA$115=0)*($O90-$G$430)+(DA$115=$G$444)*$G$435+(DA$115=$G$445)*(AH90+$G$430-$O90-$G$435) -> 0 | DB116: =(DB$115=0)*($O90-$G$430)+(DB$115=$G$444)*$G$435+(DB$115=$G$445)*(AH90+$G$430-$O90-$G$435) -> 0 | DC116: =(DC$115=0)*($O90-$G$430)+(DC$115=$G$444)*$G$435+(DC$115=$G$445)*(AH90+$G$430-$O90-$G$435) -> 0 | DD116: =(DD$115=0)*($O90-$G$430)+(DD$115=$G$444)*$G$435+(DD$115=$G$445)*(AH90+$G$430-$O90-$G$435) -> 0 | DE116: =(DE$115=0)*($O90-$G$430)+(DE$115=$G$444)*$G$435+(DE$115=$G$445)*(AH90+$G$430-$O90-$G$435) -> 7208.2633
C117: =C118-$G$439 -> 0.2 | D117: =IFERROR(IRR(BD117:BI117),0) -> 0.29367944 | E117: =IFERROR(IRR(BJ117:BO117),0) -> 0.28916999 | F117: =IFERROR(IRR(BP117:BU117),0) -> 0.28459656 | G117: =IFERROR(IRR(BV117:CA117),0) -> 0.27995705 | H117: =IFERROR(IRR(CB117:CG117),0) -> 0.27524928 | I117: =IFERROR(IRR(CH117:CM117),0) -> 0.27047095 | J117: =IFERROR(IRR(CN117:CS117),0) -> 0.26561963 | K117: =IFERROR(IRR(CT117:CY117),0) -> 0.26069277 | L117: =IFERROR(IRR(CZ117:DE117),0) -> 0.25568766 | AT117: =IF(Z131<$G$449,0,MIN($G$446,1+IFERROR(INT((Z131-$G$449)/$G$463),0))) -> 0 | AU117: =IF(AA131<$G$449,0,MIN($G$446,1+IFERROR(INT((AA131-$G$449)/$G$463),0))) -> 0 | AV117: =IF(AB131<$G$449,0,MIN($G$446,1+IFERROR(INT((AB131-$G$449)/$G$463),0))) -> 0 | AW117: =IF(AC131<$G$449,0,MIN($G$446,1+IFERROR(INT((AC131-$G$449)/$G$463),0))) -> 0 | AX117: =IF(AD131<$G$449,0,MIN($G$446,1+IFERROR(INT((AD131-$G$449)/$G$463),0))) -> 1 | AY117: =IF(AE131<$G$449,0,MIN($G$446,1+IFERROR(INT((AE131-$G$449)/$G$463),0))) -> 2 | AZ117: =IF(AF131<$G$449,0,MIN($G$446,1+IFERROR(INT((AF131-$G$449)/$G$463),0))) -> 4 | BA117: =IF(AG131<$G$449,0,MIN($G$446,1+IFERROR(INT((AG131-$G$449)/$G$463),0))) -> 5 | BB117: =IF(AH131<$G$449,0,MIN($G$446,1+IFERROR(INT((AH131-$G$449)/$G$463),0))) -> 7 | BD117: =(BD$115=0)*($O91-$G$430)+(BD$115=$G$444)*$G$435+(BD$115=$G$445)*(Z91+$G$430-$O91-$G$435) -> -2350 | BE117: =(BE$115=0)*($O91-$G$430)+(BE$115=$G$444)*$G$435+(BE$115=$G$445)*(Z91+$G$430-$O91-$G$435) -> 0 | BF117: =(BF$115=0)*($O91-$G$430)+(BF$115=$G$444)*$G$435+(BF$115=$G$445)*(Z91+$G$430-$O91-$G$435) -> 0 | BG117: =(BG$115=0)*($O91-$G$430)+(BG$115=$G$444)*$G$435+(BG$115=$G$445)*(Z91+$G$430-$O91-$G$435) -> 0 | BH117: =(BH$115=0)*($O91-$G$430)+(BH$115=$G$444)*$G$435+(BH$115=$G$445)*(Z91+$G$430-$O91-$G$435) -> 0 | BI117: =(BI$115=0)*($O91-$G$430)+(BI$115=$G$444)*$G$435+(BI$115=$G$445)*(Z91+$G$430-$O91-$G$435) -> 8515.3252 | BJ117: =(BJ$115=0)*($O91-$G$430)+(BJ$115=$G$444)*$G$435+(BJ$115=$G$445)*(AA91+$G$430-$O91-$G$435) -> -2350 | BK117: =(BK$115=0)*($O91-$G$430)+(BK$115=$G$444)*$G$435+(BK$115=$G$445)*(AA91+$G$430-$O91-$G$435) -> 0 | BL117: =(BL$115=0)*($O91-$G$430)+(BL$115=$G$444)*$G$435+(BL$115=$G$445)*(AA91+$G$430-$O91-$G$435) -> 0 | BM117: =(BM$115=0)*($O91-$G$430)+(BM$115=$G$444)*$G$435+(BM$115=$G$445)*(AA91+$G$430-$O91-$G$435) -> 0 | BN117: =(BN$115=0)*($O91-$G$430)+(BN$115=$G$444)*$G$435+(BN$115=$G$445)*(AA91+$G$430-$O91-$G$435) -> 0 | BO117: =(BO$115=0)*($O91-$G$430)+(BO$115=$G$444)*$G$435+(BO$115=$G$445)*(AA91+$G$430-$O91-$G$435) -> 8367.9447 | BP117: =(BP$115=0)*($O91-$G$430)+(BP$115=$G$444)*$G$435+(BP$115=$G$445)*(AB91+$G$430-$O91-$G$435) -> -2350 | BQ117: =(BQ$115=0)*($O91-$G$430)+(BQ$115=$G$444)*$G$435+(BQ$115=$G$445)*(AB91+$G$430-$O91-$G$435) -> 0 | BR117: =(BR$115=0)*($O91-$G$430)+(BR$115=$G$444)*$G$435+(BR$115=$G$445)*(AB91+$G$430-$O91-$G$435) -> 0 | BS117: =(BS$115=0)*($O91-$G$430)+(BS$115=$G$444)*$G$435+(BS$115=$G$445)*(AB91+$G$430-$O91-$G$435) -> 0 | BT117: =(BT$115=0)*($O91-$G$430)+(BT$115=$G$444)*$G$435+(BT$115=$G$445)*(AB91+$G$430-$O91-$G$435) -> 0 | BU117: =(BU$115=0)*($O91-$G$430)+(BU$115=$G$444)*$G$435+(BU$115=$G$445)*(AB91+$G$430-$O91-$G$435) -> 8220.5643 | BV117: =(BV$115=0)*($O91-$G$430)+(BV$115=$G$444)*$G$435+(BV$115=$G$445)*(AC91+$G$430-$O91-$G$435) -> -2350 | BW117: =(BW$115=0)*($O91-$G$430)+(BW$115=$G$444)*$G$435+(BW$115=$G$445)*(AC91+$G$430-$O91-$G$435) -> 0 | BX117: =(BX$115=0)*($O91-$G$430)+(BX$115=$G$444)*$G$435+(BX$115=$G$445)*(AC91+$G$430-$O91-$G$435) -> 0 | BY117: =(BY$115=0)*($O91-$G$430)+(BY$115=$G$444)*$G$435+(BY$115=$G$445)*(AC91+$G$430-$O91-$G$435) -> 0 | BZ117: =(BZ$115=0)*($O91-$G$430)+(BZ$115=$G$444)*$G$435+(BZ$115=$G$445)*(AC91+$G$430-$O91-$G$435) -> 0 | CA117: =(CA$115=0)*($O91-$G$430)+(CA$115=$G$444)*$G$435+(CA$115=$G$445)*(AC91+$G$430-$O91-$G$435) -> 8073.1839 | CB117: =(CB$115=0)*($O91-$G$430)+(CB$115=$G$444)*$G$435+(CB$115=$G$445)*(AD91+$G$430-$O91-$G$435) -> -2350 | CC117: =(CC$115=0)*($O91-$G$430)+(CC$115=$G$444)*$G$435+(CC$115=$G$445)*(AD91+$G$430-$O91-$G$435) -> 0 | CD117: =(CD$115=0)*($O91-$G$430)+(CD$115=$G$444)*$G$435+(CD$115=$G$445)*(AD91+$G$430-$O91-$G$435) -> 0 | CE117: =(CE$115=0)*($O91-$G$430)+(CE$115=$G$444)*$G$435+(CE$115=$G$445)*(AD91+$G$430-$O91-$G$435) -> 0 | CF117: =(CF$115=0)*($O91-$G$430)+(CF$115=$G$444)*$G$435+(CF$115=$G$445)*(AD91+$G$430-$O91-$G$435) -> 0 | CG117: =(CG$115=0)*($O91-$G$430)+(CG$115=$G$444)*$G$435+(CG$115=$G$445)*(AD91+$G$430-$O91-$G$435) -> 7925.8034 | CH117: =(CH$115=0)*($O91-$G$430)+(CH$115=$G$444)*$G$435+(CH$115=$G$445)*(AE91+$G$430-$O91-$G$435) -> -2350 | CI117: =(CI$115=0)*($O91-$G$430)+(CI$115=$G$444)*$G$435+(CI$115=$G$445)*(AE91+$G$430-$O91-$G$435) -> 0 | CJ117: =(CJ$115=0)*($O91-$G$430)+(CJ$115=$G$444)*$G$435+(CJ$115=$G$445)*(AE91+$G$430-$O91-$G$435) -> 0 | CK117: =(CK$115=0)*($O91-$G$430)+(CK$115=$G$444)*$G$435+(CK$115=$G$445)*(AE91+$G$430-$O91-$G$435) -> 0 | CL117: =(CL$115=0)*($O91-$G$430)+(CL$115=$G$444)*$G$435+(CL$115=$G$445)*(AE91+$G$430-$O91-$G$435) -> 0 | CM117: =(CM$115=0)*($O91-$G$430)+(CM$115=$G$444)*$G$435+(CM$115=$G$445)*(AE91+$G$430-$O91-$G$435) -> 7778.423 | CN117: =(CN$115=0)*($O91-$G$430)+(CN$115=$G$444)*$G$435+(CN$115=$G$445)*(AF91+$G$430-$O91-$G$435) -> -2350 | CO117: =(CO$115=0)*($O91-$G$430)+(CO$115=$G$444)*$G$435+(CO$115=$G$445)*(AF91+$G$430-$O91-$G$435) -> 0 | CP117: =(CP$115=0)*($O91-$G$430)+(CP$115=$G$444)*$G$435+(CP$115=$G$445)*(AF91+$G$430-$O91-$G$435) -> 0 | CQ117: =(CQ$115=0)*($O91-$G$430)+(CQ$115=$G$444)*$G$435+(CQ$115=$G$445)*(AF91+$G$430-$O91-$G$435) -> 0 | CR117: =(CR$115=0)*($O91-$G$430)+(CR$115=$G$444)*$G$435+(CR$115=$G$445)*(AF91+$G$430-$O91-$G$435) -> 0 | CS117: =(CS$115=0)*($O91-$G$430)+(CS$115=$G$444)*$G$435+(CS$115=$G$445)*(AF91+$G$430-$O91-$G$435) -> 7631.0426 | CT117: =(CT$115=0)*($O91-$G$430)+(CT$115=$G$444)*$G$435+(CT$115=$G$445)*(AG91+$G$430-$O91-$G$435) -> -2350 | CU117: =(CU$115=0)*($O91-$G$430)+(CU$115=$G$444)*$G$435+(CU$115=$G$445)*(AG91+$G$430-$O91-$G$435) -> 0 | CV117: =(CV$115=0)*($O91-$G$430)+(CV$115=$G$444)*$G$435+(CV$115=$G$445)*(AG91+$G$430-$O91-$G$435) -> 0 | CW117: =(CW$115=0)*($O91-$G$430)+(CW$115=$G$444)*$G$435+(CW$115=$G$445)*(AG91+$G$430-$O91-$G$435) -> 0 | CX117: =(CX$115=0)*($O91-$G$430)+(CX$115=$G$444)*$G$435+(CX$115=$G$445)*(AG91+$G$430-$O91-$G$435) -> 0 | CY117: =(CY$115=0)*($O91-$G$430)+(CY$115=$G$444)*$G$435+(CY$115=$G$445)*(AG91+$G$430-$O91-$G$435) -> 7483.6621 | CZ117: =(CZ$115=0)*($O91-$G$430)+(CZ$115=$G$444)*$G$435+(CZ$115=$G$445)*(AH91+$G$430-$O91-$G$435) -> -2350 | DA117: =(DA$115=0)*($O91-$G$430)+(DA$115=$G$444)*$G$435+(DA$115=$G$445)*(AH91+$G$430-$O91-$G$435) -> 0 | DB117: =(DB$115=0)*($O91-$G$430)+(DB$115=$G$444)*$G$435+(DB$115=$G$445)*(AH91+$G$430-$O91-$G$435) -> 0 | DC117: =(DC$115=0)*($O91-$G$430)+(DC$115=$G$444)*$G$435+(DC$115=$G$445)*(AH91+$G$430-$O91-$G$435) -> 0 | DD117: =(DD$115=0)*($O91-$G$430)+(DD$115=$G$444)*$G$435+(DD$115=$G$445)*(AH91+$G$430-$O91-$G$435) -> 0 | DE117: =(DE$115=0)*($O91-$G$430)+(DE$115=$G$444)*$G$435+(DE$115=$G$445)*(AH91+$G$430-$O91-$G$435) -> 7336.2817
C118: =C119-$G$439 -> 0.25 | D118: =IFERROR(IRR(BD118:BI118),0) -> 0.30498002 | E118: =IFERROR(IRR(BJ118:BO118),0) -> 0.29969546 | F118: =IFERROR(IRR(BP118:BU118),0) -> 0.29432351 | G118: =IFERROR(IRR(BV118:CA118),0) -> 0.28886088 | H118: =IFERROR(IRR(CB118:CG118),0) -> 0.28330403 | I118: =IFERROR(IRR(CH118:CM118),0) -> 0.27764924 | J118: =IFERROR(IRR(CN118:CS118),0) -> 0.27189253 | K118: =IFERROR(IRR(CT118:CY118),0) -> 0.26602966 | L118: =IFERROR(IRR(CZ118:DE118),0) -> 0.26005614 | AT118: =IF(Z132<$G$449,0,MIN($G$446,1+IFERROR(INT((Z132-$G$449)/$G$463),0))) -> 0 | AU118: =IF(AA132<$G$449,0,MIN($G$446,1+IFERROR(INT((AA132-$G$449)/$G$463),0))) -> 0 | AV118: =IF(AB132<$G$449,0,MIN($G$446,1+IFERROR(INT((AB132-$G$449)/$G$463),0))) -> 0 | AW118: =IF(AC132<$G$449,0,MIN($G$446,1+IFERROR(INT((AC132-$G$449)/$G$463),0))) -> 1 | AX118: =IF(AD132<$G$449,0,MIN($G$446,1+IFERROR(INT((AD132-$G$449)/$G$463),0))) -> 2 | AY118: =IF(AE132<$G$449,0,MIN($G$446,1+IFERROR(INT((AE132-$G$449)/$G$463),0))) -> 4 | AZ118: =IF(AF132<$G$449,0,MIN($G$446,1+IFERROR(INT((AF132-$G$449)/$G$463),0))) -> 5 | BA118: =IF(AG132<$G$449,0,MIN($G$446,1+IFERROR(INT((AG132-$G$449)/$G$463),0))) -> 6 | BB118: =IF(AH132<$G$449,0,MIN($G$446,1+IFERROR(INT((AH132-$G$449)/$G$463),0))) -> 8 | BD118: =(BD$115=0)*($O92-$G$430)+(BD$115=$G$444)*$G$435+(BD$115=$G$445)*(Z92+$G$430-$O92-$G$435) -> -2350 | BE118: =(BE$115=0)*($O92-$G$430)+(BE$115=$G$444)*$G$435+(BE$115=$G$445)*(Z92+$G$430-$O92-$G$435) -> 0 | BF118: =(BF$115=0)*($O92-$G$430)+(BF$115=$G$444)*$G$435+(BF$115=$G$445)*(Z92+$G$430-$O92-$G$435) -> 0 | BG118: =(BG$115=0)*($O92-$G$430)+(BG$115=$G$444)*$G$435+(BG$115=$G$445)*(Z92+$G$430-$O92-$G$435) -> 0 | BH118: =(BH$115=0)*($O92-$G$430)+(BH$115=$G$444)*$G$435+(BH$115=$G$445)*(Z92+$G$430-$O92-$G$435) -> 0 | BI118: =(BI$115=0)*($O92-$G$430)+(BI$115=$G$444)*$G$435+(BI$115=$G$445)*(Z92+$G$430-$O92-$G$435) -> 8893.7964 | BJ118: =(BJ$115=0)*($O92-$G$430)+(BJ$115=$G$444)*$G$435+(BJ$115=$G$445)*(AA92+$G$430-$O92-$G$435) -> -2350 | BK118: =(BK$115=0)*($O92-$G$430)+(BK$115=$G$444)*$G$435+(BK$115=$G$445)*(AA92+$G$430-$O92-$G$435) -> 0 | BL118: =(BL$115=0)*($O92-$G$430)+(BL$115=$G$444)*$G$435+(BL$115=$G$445)*(AA92+$G$430-$O92-$G$435) -> 0 | BM118: =(BM$115=0)*($O92-$G$430)+(BM$115=$G$444)*$G$435+(BM$115=$G$445)*(AA92+$G$430-$O92-$G$435) -> 0 | BN118: =(BN$115=0)*($O92-$G$430)+(BN$115=$G$444)*$G$435+(BN$115=$G$445)*(AA92+$G$430-$O92-$G$435) -> 0 | BO118: =(BO$115=0)*($O92-$G$430)+(BO$115=$G$444)*$G$435+(BO$115=$G$445)*(AA92+$G$430-$O92-$G$435) -> 8715.17 | BP118: =(BP$115=0)*($O92-$G$430)+(BP$115=$G$444)*$G$435+(BP$115=$G$445)*(AB92+$G$430-$O92-$G$435) -> -2350 | BQ118: =(BQ$115=0)*($O92-$G$430)+(BQ$115=$G$444)*$G$435+(BQ$115=$G$445)*(AB92+$G$430-$O92-$G$435) -> 0 | BR118: =(BR$115=0)*($O92-$G$430)+(BR$115=$G$444)*$G$435+(BR$115=$G$445)*(AB92+$G$430-$O92-$G$435) -> 0 | BS118: =(BS$115=0)*($O92-$G$430)+(BS$115=$G$444)*$G$435+(BS$115=$G$445)*(AB92+$G$430-$O92-$G$435) -> 0 | BT118: =(BT$115=0)*($O92-$G$430)+(BT$115=$G$444)*$G$435+(BT$115=$G$445)*(AB92+$G$430-$O92-$G$435) -> 0 | BU118: =(BU$115=0)*($O92-$G$430)+(BU$115=$G$444)*$G$435+(BU$115=$G$445)*(AB92+$G$430-$O92-$G$435) -> 8536.5437 | BV118: =(BV$115=0)*($O92-$G$430)+(BV$115=$G$444)*$G$435+(BV$115=$G$445)*(AC92+$G$430-$O92-$G$435) -> -2350 | BW118: =(BW$115=0)*($O92-$G$430)+(BW$115=$G$444)*$G$435+(BW$115=$G$445)*(AC92+$G$430-$O92-$G$435) -> 0 | BX118: =(BX$115=0)*($O92-$G$430)+(BX$115=$G$444)*$G$435+(BX$115=$G$445)*(AC92+$G$430-$O92-$G$435) -> 0 | BY118: =(BY$115=0)*($O92-$G$430)+(BY$115=$G$444)*$G$435+(BY$115=$G$445)*(AC92+$G$430-$O92-$G$435) -> 0 | BZ118: =(BZ$115=0)*($O92-$G$430)+(BZ$115=$G$444)*$G$435+(BZ$115=$G$445)*(AC92+$G$430-$O92-$G$435) -> 0 | CA118: =(CA$115=0)*($O92-$G$430)+(CA$115=$G$444)*$G$435+(CA$115=$G$445)*(AC92+$G$430-$O92-$G$435) -> 8357.9174 | CB118: =(CB$115=0)*($O92-$G$430)+(CB$115=$G$444)*$G$435+(CB$115=$G$445)*(AD92+$G$430-$O92-$G$435) -> -2350 | CC118: =(CC$115=0)*($O92-$G$430)+(CC$115=$G$444)*$G$435+(CC$115=$G$445)*(AD92+$G$430-$O92-$G$435) -> 0 | CD118: =(CD$115=0)*($O92-$G$430)+(CD$115=$G$444)*$G$435+(CD$115=$G$445)*(AD92+$G$430-$O92-$G$435) -> 0 | CE118: =(CE$115=0)*($O92-$G$430)+(CE$115=$G$444)*$G$435+(CE$115=$G$445)*(AD92+$G$430-$O92-$G$435) -> 0 | CF118: =(CF$115=0)*($O92-$G$430)+(CF$115=$G$444)*$G$435+(CF$115=$G$445)*(AD92+$G$430-$O92-$G$435) -> 0 | CG118: =(CG$115=0)*($O92-$G$430)+(CG$115=$G$444)*$G$435+(CG$115=$G$445)*(AD92+$G$430-$O92-$G$435) -> 8179.291 | CH118: =(CH$115=0)*($O92-$G$430)+(CH$115=$G$444)*$G$435+(CH$115=$G$445)*(AE92+$G$430-$O92-$G$435) -> -2350 | CI118: =(CI$115=0)*($O92-$G$430)+(CI$115=$G$444)*$G$435+(CI$115=$G$445)*(AE92+$G$430-$O92-$G$435) -> 0 | CJ118: =(CJ$115=0)*($O92-$G$430)+(CJ$115=$G$444)*$G$435+(CJ$115=$G$445)*(AE92+$G$430-$O92-$G$435) -> 0 | CK118: =(CK$115=0)*($O92-$G$430)+(CK$115=$G$444)*$G$435+(CK$115=$G$445)*(AE92+$G$430-$O92-$G$435) -> 0 | CL118: =(CL$115=0)*($O92-$G$430)+(CL$115=$G$444)*$G$435+(CL$115=$G$445)*(AE92+$G$430-$O92-$G$435) -> 0 | CM118: =(CM$115=0)*($O92-$G$430)+(CM$115=$G$444)*$G$435+(CM$115=$G$445)*(AE92+$G$430-$O92-$G$435) -> 8000.6647 | CN118: =(CN$115=0)*($O92-$G$430)+(CN$115=$G$444)*$G$435+(CN$115=$G$445)*(AF92+$G$430-$O92-$G$435) -> -2350 | CO118: =(CO$115=0)*($O92-$G$430)+(CO$115=$G$444)*$G$435+(CO$115=$G$445)*(AF92+$G$430-$O92-$G$435) -> 0 | CP118: =(CP$115=0)*($O92-$G$430)+(CP$115=$G$444)*$G$435+(CP$115=$G$445)*(AF92+$G$430-$O92-$G$435) -> 0 | CQ118: =(CQ$115=0)*($O92-$G$430)+(CQ$115=$G$444)*$G$435+(CQ$115=$G$445)*(AF92+$G$430-$O92-$G$435) -> 0 | CR118: =(CR$115=0)*($O92-$G$430)+(CR$115=$G$444)*$G$435+(CR$115=$G$445)*(AF92+$G$430-$O92-$G$435) -> 0 | CS118: =(CS$115=0)*($O92-$G$430)+(CS$115=$G$444)*$G$435+(CS$115=$G$445)*(AF92+$G$430-$O92-$G$435) -> 7822.0383 | CT118: =(CT$115=0)*($O92-$G$430)+(CT$115=$G$444)*$G$435+(CT$115=$G$445)*(AG92+$G$430-$O92-$G$435) -> -2350 | CU118: =(CU$115=0)*($O92-$G$430)+(CU$115=$G$444)*$G$435+(CU$115=$G$445)*(AG92+$G$430-$O92-$G$435) -> 0 | CV118: =(CV$115=0)*($O92-$G$430)+(CV$115=$G$444)*$G$435+(CV$115=$G$445)*(AG92+$G$430-$O92-$G$435) -> 0 | CW118: =(CW$115=0)*($O92-$G$430)+(CW$115=$G$444)*$G$435+(CW$115=$G$445)*(AG92+$G$430-$O92-$G$435) -> 0 | CX118: =(CX$115=0)*($O92-$G$430)+(CX$115=$G$444)*$G$435+(CX$115=$G$445)*(AG92+$G$430-$O92-$G$435) -> 0 | CY118: =(CY$115=0)*($O92-$G$430)+(CY$115=$G$444)*$G$435+(CY$115=$G$445)*(AG92+$G$430-$O92-$G$435) -> 7643.412 | CZ118: =(CZ$115=0)*($O92-$G$430)+(CZ$115=$G$444)*$G$435+(CZ$115=$G$445)*(AH92+$G$430-$O92-$G$435) -> -2350 | DA118: =(DA$115=0)*($O92-$G$430)+(DA$115=$G$444)*$G$435+(DA$115=$G$445)*(AH92+$G$430-$O92-$G$435) -> 0 | DB118: =(DB$115=0)*($O92-$G$430)+(DB$115=$G$444)*$G$435+(DB$115=$G$445)*(AH92+$G$430-$O92-$G$435) -> 0 | DC118: =(DC$115=0)*($O92-$G$430)+(DC$115=$G$444)*$G$435+(DC$115=$G$445)*(AH92+$G$430-$O92-$G$435) -> 0 | DD118: =(DD$115=0)*($O92-$G$430)+(DD$115=$G$444)*$G$435+(DD$115=$G$445)*(AH92+$G$430-$O92-$G$435) -> 0 | DE118: =(DE$115=0)*($O92-$G$430)+(DE$115=$G$444)*$G$435+(DE$115=$G$445)*(AH92+$G$430-$O92-$G$435) -> 7464.7857
...

Sheet 100% Buyout Analysis
B2: =Cover!$B$24 -> Keystone Bookkeepers
B3: Valuation Growth Scenarios ($000s) | G3: Print | H3: 1
B5: Revenue Growth Assumptions | C5: Value | F5: Rationale / Notes
B6: General Assumptions
B7: Horizon (Years) | C7: ='Offer Comparison'!$D$7 -> 5 | F7: ="Linked to Offer Comparison ("&ADDRESS(ROW('Offer Comparison'!D7),COLUMN('Offer Comparison'!D7),4)&"). Projection horizon for the Year "&$C$7&" columns" -> Linked to Offer Comparison (D7). Projection horizon for the Year 5 columns
B8: Est. Topkey Dilution — Ben's Stake (Year 5) | C8: ='Offer Comparison'!$D$8 -> 0.05 | F8: ="Linked to Offer Comparison ("&ADDRESS(ROW('Offer Comparison'!D8),COLUMN('Offer Comparison'!D8),4)&"). AMB estimate: future Topkey equity issuance (capital raise, option pool, acquisitions) reduces Ben's Topkey % by this share by Year "&$C$7 -> Linked to Offer Comparison (D8). AMB estimate: future Topkey equity issuance (capital raise, option pool, acquisitions) reduces Ben's Topkey % by this share by Year 5
B9: Topkey - Current Monthly Revenue | C9: ='Offer Comparison'!$D$18 -> 261 | F9: ="Input on Offer Comparison ("&ADDRESS(ROW('Offer Comparison'!D18),COLUMN('Offer Comparison'!D18),4)&"). Topkey-provided monthly revenue ($000s); pending confirmation" -> Input on Offer Comparison (D18). Topkey-provided monthly revenue ($000s); pending confirmation
B10: Topkey - Current Run-Rate Revenue | C10: =C9*12 -> 3132
B11: Topkey - Current Revenue Multiple | C11: =IFERROR(C167/C10,0) -> 19.157088 | F11: ="Implied: Topkey pre-deal valuation ("&ADDRESS(ROW(C167),COLUMN(C167),4)&") ÷ run-rate revenue ("&ADDRESS(ROW(C10),COLUMN(C10),4)&")" -> Implied: Topkey pre-deal valuation (C167) ÷ run-rate revenue (C10)
B12: Topkey - Future Revenue Multiple | C12: =C11 -> 19.157088 | F12: Held flat at the current implied multiple
B13: Topkey - Current Client Count | C13: ='Offer Comparison'!$D$19 -> 325 | F13: ="Input on Offer Comparison ("&ADDRESS(ROW('Offer Comparison'!D19),COLUMN('Offer Comparison'!D19),4)&"). Topkey-provided client count; pending confirmation" -> Input on Offer Comparison (D19). Topkey-provided client count; pending confirmation
B14: Topkey - Avg. Revenue Per Client | C14: =C10/C13 -> 9.6369231
B15: Topkey - Annual Net Client Wins | C15: ='Offer Comparison'!$D$20 -> 130 | F15: ="Input on Offer Comparison ("&ADDRESS(ROW('Offer Comparison'!D20),COLUMN('Offer Comparison'!D20),4)&"). AMB placeholder; pending confirmation" -> Input on Offer Comparison (D20). AMB placeholder; pending confirmation
B16: Total Net Client Wins | C16: =C15*$C$7 -> 650
B17: Total Additional Revenue | C17: =C16*C14 -> 6264
B18: ="Check - "&$C$7&" Year Topkey Valuation Growth" -> Check - 5 Year Topkey Valuation Growth | C18: =IFERROR(D73/C73-1,0) -> 2.0084034 | F18: ="% growth in Topkey ex-Keystone value (row "&ROW($B$73)&"), today → Year "&$C$7&"; value net of cash paid, not revenue" -> % growth in Topkey ex-Keystone value (row 73), today → Year 5; value net of cash paid, not revenue
B20: Keystone Standalone Assumptions
B21: Revenue Multiple | C21: ='Offer Comparison'!$D$13 -> 1 | F21: ="Linked to Offer Comparison ("&ADDRESS(ROW('Offer Comparison'!D13),COLUMN('Offer Comparison'!D13),4)&"). Keystone valued at "&TEXT(C21,"0.0")&"x revenue"&" today (offer implies "&"~"&TEXT(C164/C163,"0.0")&"x"&")" -> Linked to Offer Comparison (D13). Keystone valued at 1.0x revenue today (offer implies ~1.0x)
B22: Scaled Revenue Multiple | C22: ='Offer Comparison'!$D$14 -> 1.25 | F22: ="Linked to Offer Comparison ("&ADDRESS(ROW('Offer Comparison'!D14),COLUMN('Offer Comparison'!D14),4)&"). Keystone standalone revenue multiple at Year "&$C$7 -> Linked to Offer Comparison (D14). Keystone standalone revenue multiple at Year 5
B23: Avg. Revenue Per Client | C23: ='Offer Comparison'!$D$22 -> 16.631473 | F23: ="Input on Offer Comparison ("&ADDRESS(ROW('Offer Comparison'!D22),COLUMN('Offer Comparison'!D22),4)&"). Sep'26 annualized fee per non-tax client (Steady-State Staffing AB8)" -> Input on Offer Comparison (D22). Sep'26 annualized fee per non-tax client (Steady-State Staffing AB8)
B24: Target Monthly Net Client Wins | C24: ='Offer Comparison'!$D$23 -> 3 | F24: ="Input on Offer Comparison ("&ADDRESS(ROW('Offer Comparison'!D23),COLUMN('Offer Comparison'!D23),4)&"). AMB target pace; LTM actual is "&TEXT(C179,"0")&"/yr (~"&TEXT(C179/12,"0.0")&"/month)"&", see build at rows "&ROW($B$175)&"-"&ROW($B$179) -> Input on Offer Comparison (D23). AMB target pace; LTM actual is 26/yr (~2.2/month), see build at rows 175-179
B25: Annual Net Client Wins | C25: =C24*12 -> 36 | F25: Target monthly pace × 12
B26: Total Net Client Wins | C26: =C25*$C$7 -> 180
B27: Total Additional Revenue | C27: =C26*C23 -> 2993.6651
B29: Keystone Partnership Assumptions
B30: Software-Integration Revenue Multiple | C30: ='Offer Comparison'!$D$15 -> 2 | F30: ="Linked to Offer Comparison ("&ADDRESS(ROW('Offer Comparison'!D15),COLUMN('Offer Comparison'!D15),4)&"). Revenue multiple with Topkey software integration" -> Linked to Offer Comparison (D15). Revenue multiple with Topkey software integration
B31: VR Platform Run-Rate Tech Cost | C31: ='Offer Comparison'!$D$25 -> 240 | F31: ="Input on Offer Comparison ("&ADDRESS(ROW('Offer Comparison'!D25),COLUMN('Offer Comparison'!D25),4)&"). Memo only; VR savings assumed captured in the "&TEXT(C109,"0%")&" partnership margin ("&ADDRESS(ROW(C109),COLUMN(C109),4)&") and revenue multiple" -> Input on Offer Comparison (D25). Memo only; VR savings assumed captured in the 20% partnership margin (C109) and revenue multiple
B33: =B23 -> Avg. Revenue Per Client | C33: =C23 -> 16.631473
B35: =+B25 -> Annual Net Client Wins | C35: =+C25 -> 36
B36: (+) Additional Annual Net Client Wins From Topkey | C36: ='Offer Comparison'!$D$26 -> 12 | F36: ="Input on Offer Comparison ("&ADDRESS(ROW('Offer Comparison'!D26),COLUMN('Offer Comparison'!D26),4)&"). Topkey-provided; pending confirmation" -> Input on Offer Comparison (D26). Topkey-provided; pending confirmation
B37: Total Annual Net Client Wins | C37: =SUM(C35:C36) -> 48
B38: Total Net Client Wins | C38: =C37*$C$7 -> 240
B39: Total Additional Revenue | C39: =C38*C33 -> 3991.5535
B40: Increase in Keystone Revenue vs. Standalone | C40: =C39-C27 -> 997.88838
B42: Cash Earnout — Year 3 Keystone Revenue (Sliding Scale)
B43: Earnout Measurement Year | C43: 3 | F43: ="Earnout measured on Year "&$C$43&" run-rate: average of "&"months "&TEXT($C$43*12-$C$54+1,"0")&"–"&TEXT($C$43*12,"0")&" × 12 (window in "&ADDRESS(ROW(C54),COLUMN(C54),4)&")" -> Earnout measured on Year 3 run-rate: average of months 34–36 × 12 (window in C54)
B44: Keystone Revenue at Close | C44: =C163 -> 2998.541 | F44: ="PF Jul'26 run-rate revenue at close ("&ADDRESS(ROW(C163),COLUMN(C163),4)&")" -> PF Jul'26 run-rate revenue at close (C163)
B45: Year 3 Run-Rate Revenue Target | C45: =C44+C39*(C43-(C54-1)/2/12)/C7 -> 5326.9472 | F45: ="Run-rate at close + partnership added revenue ramped to the midpoint of the averaging window "&"(month "&ROUND($C$43*12-($C$54-1)/2,1)&" ÷ "&$C$7*12&")"&"; same basis as the earnout measurement" -> Run-rate at close + partnership added revenue ramped to the midpoint of the averaging window (month 35 ÷ 60); same basis as the earnout measurement
B46: (x) Achievement vs. Target | C46: 1 | F46: ="Base case assumes the model's Year "&$C$43&" revenue is achieved; flex to test payout" -> Base case assumes the model's Year 3 revenue is achieved; flex to test payout
B47: Year 3 Run-Rate Revenue — Achieved | C47: =C45*C46 -> 5326.9472
B48: Threshold — % of Target | C48: 0.8 | F48: No earnout below this share of target; payout starts at the threshold % below
B49: Target Earnout — at 100% of Target | C49: 500 | F49: ="Opening ask: "&TEXT(C49,"$#,##0")&"K"&" at target (AMB internal range $750K–$1M)" -> Opening ask: $500K at target (AMB internal range $750K–$1M)
B50: Payout at Threshold — % of Target Earnout | C50: 0.5 | F50: ="Share of target earnout paid at the "&TEXT(C48,"0%")&" threshold" -> Share of target earnout paid at the 80% threshold
B51: Cap — % of Target Earnout | C51: 1.5 | F51: ="Payout capped at "&TEXT(C51,"0%")&" of target earnout, reached at "&TEXT(C48+(C51-C50)*(1-C48)/(1-C50),"0%")&" of target revenue (mirrors the "&TEXT(C48,"0%")&" threshold)" -> Payout capped at 150% of target earnout, reached at 120% of target revenue (mirrors the 80% threshold)
B52: Payout % Earned | C52: =IF(C46<C48,0,MIN(C51,C50+(1-C50)*(C46-C48)/(1-C48))) -> 1 | F52: ="Straight line from threshold payout at "&TEXT(C48,"0%")&" to 100% at target, continuing above target until the cap" -> Straight line from threshold payout at 80% to 100% at target, continuing above target until the cap
B53: Maximum Earnout (Cap) | C53: =C49*C51 -> 750 | F53: Topkey's maximum earnout exposure
