Workbook

Sheet Cover
B24: Sunshine Commercial Investments
B25: Diligence Workbook
B26: ="As of "&TEXT(TODAY(),"mm/dd/yy") -> As of 08/12/26

Sheet Laundromat Valuation
B2: =+Cover!B24 -> Sunshine Commercial Investments
B3: Laundromat P&L Summary & Valuation ($000s) | H3: Print | I3: 1
B5: Laundromat P&L Summary
C7: FY22 | D7: FY23 | E7: FY24 | F7: Pro Forma
B9: Revenue | C9: 338.594 | D9: 357.943 | E9: 376.06 | F9: =E9*(1+C59) -> 338.454
B10: % Growth | D10: =D9/C9-1 -> 0.057145135 | E10: =E9/D9-1 -> 0.050614204 | F10: =F9/E9-1 -> -0.1
B12: Expenses
B13: Utilities | C13: 90.936 | D13: 91.989 | E13: 91.269 | F13: =F9*C60 -> 86.520898
B14: % Sales | C14: =C13/C$9 -> 0.26856944 | D14: =D13/D$9 -> 0.25699343 | E14: =E13/E$9 -> 0.24269797 | F14: =F13/F$9 -> 0.25563562
B15: Labor | C15: 0 | D15: 0 | E15: 55 | F15: =+C62 -> 55
B16: % Sales | C16: =C15/C$9 -> 0 | D16: =D15/D$9 -> 0 | E16: =E15/E$9 -> 0.14625326 | F16: =F15/F$9 -> 0.16250362
B17: Repairs & Maintenance | C17: 22.728 | D17: 46.544 | E17: 30.54 | F17: =+C63 -> 33.270667
B18: % Sales | C18: =C17/C$9 -> 0.067124639 | D18: =D17/D$9 -> 0.13003188 | E18: =E17/E$9 -> 0.081210445 | F18: =F17/F$9 -> 0.098301886
B19: Lease | C19: 14.4 | D19: 13.2 | E19: 14.412 | F19: =+C76 -> 28.824
B20: % Sales | C20: =C19/C$9 -> 0.04252881 | D20: =D19/D$9 -> 0.03687738 | E20: =E19/E$9 -> 0.038323672 | F20: =F19/F$9 -> 0.085163715
B21: Insurance | C21: 0 | D21: 14.958 | E21: 4.384 | F21: =+C66 -> 4.384
B22: % Sales | C22: =C21/C$9 -> 0 | D22: =D21/D$9 -> 0.041788776 | E22: =E21/E$9 -> 0.011657714 | F22: =F21/F$9 -> 0.012953016
B23: Debt Servicing | C23: 0 | D23: 12.608 | E23: 14.67 | F23: =(C73/C74)+(C73*C75) -> 48.97366 | H23: Note: The increased interest is due to including half of the total mortgage interest allocated to the laundromat
B24: % Sales | C24: =C23/C$9 -> 0 | D24: =D23/D$9 -> 0.035223485 | E24: =E23/E$9 -> 0.039009732 | F24: =F23/F$9 -> 0.14469813
B25: Depreciation | C25: 8.661 | D25: 27.542 | E25: 28.555 | F25: =+C65 -> 8.661 | H25: Note: The increased depreciation is due to acquiring the CRE in Feb'23
B26: % Sales | C26: =C25/C$9 -> 0.025579307 | D26: =D25/D$9 -> 0.076945212 | E26: =E25/E$9 -> 0.075932032 | F26: =F25/F$9 -> 0.025589888
B27: Taxes | C27: 0 | D27: 0 | E27: 0 | F27: =+F9*C68 -> 0
B28: % Sales | C28: =C27/C$9 -> 0 | D28: =D27/D$9 -> 0 | E28: =E27/E$9 -> 0 | F28: =F27/F$9 -> 0
B29: Other Expenses | C29: =+C31-C25-C23-C21-C19-C17-C15-C13-C27 -> 10.552 | D29: =+D31-D25-D23-D21-D19-D17-D15-D13-D27 -> 9.92 | E29: =+E31-E25-E23-E21-E19-E17-E15-E13-E27 -> 8.899 | F29: =+C69 -> 9.7903333
B30: % Sales | C30: =C29/C$9 -> 0.031164167 | D30: =D29/D$9 -> 0.02771391 | E30: =E29/E$9 -> 0.023663777 | F30: =F29/F$9 -> 0.028926629
B31: Total Expenses | C31: 147.277 | D31: 216.761 | E31: 247.729 | F31: =+F29+F25+F23+F21+F19+F17+F15+F13 -> 275.42456
B32: % Sales | C32: =C31/C$9 -> 0.43496636 | D32: =D31/D$9 -> 0.60557407 | E32: =E31/E$9 -> 0.6587486 | F32: =F31/F$9 -> 0.8137725
B34: Reported Net Income | C34: =+C9-C31 -> 191.317 | D34: =+D9-D31 -> 141.182 | E34: =+E9-E31 -> 128.331 | F34: =+F9-F31 -> 63.029442
B36: EBITDA Bridge
B37: Net Income | C37: =+C34 -> 191.317 | D37: =+D34 -> 141.182 | E37: =+E34 -> 128.331 | F37: =+F34 -> 63.029442
B38: (+) Interest | C38: =+C23 -> 0 | D38: =+D23 -> 12.608 | E38: =+E23 -> 14.67 | F38: =+F23 -> 48.97366
B39: (+) Depreciation | C39: =+C25 -> 8.661 | D39: =+D25 -> 27.542 | E39: =+E25 -> 28.555 | F39: =+F25 -> 8.661
B40: (-) Capital Reserve | C40: =-$C$65 -> -8.661 | D40: =-$C$65 -> -8.661 | E40: =-$C$65 -> -8.661 | F40: =-$C$65 -> -8.661
B41: (+) Taxes | C41: =+C27 -> 0 | D41: =+D27 -> 0 | E41: =+E27 -> 0 | F41: =+F27 -> 0
B42: Adj. EBITDA | C42: =SUM(C37:C41) -> 191.317 | D42: =SUM(D37:D41) -> 172.671 | E42: =SUM(E37:E41) -> 162.895 | F42: =SUM(F37:F41) -> 112.0031
B43: % Margin | C43: =C42/C$9 -> 0.56503364 | D43: =D42/D$9 -> 0.48239804 | E43: =E42/E$9 -> 0.43316226 | F43: =F42/F$9 -> 0.33092563
B45: (+) Owner Compensation | C45: =+C15 -> 0 | D45: =+D15 -> 0 | E45: =+E15 -> 55 | F45: =+F15 -> 55
B47: SDE | C47: =+C42+C45 -> 191.317 | D47: =+D42+D45 -> 172.671 | E47: =+E42+E45 -> 217.895 | F47: =+F42+F45 -> 167.0031
B48: % Margin | C48: =C47/C$9 -> 0.56503364 | D48: =D47/D$9 -> 0.48239804 | E48: =E47/E$9 -> 0.57941552 | F48: =F47/F$9 -> 0.49342924
B50: Business Valuation
B51: SDE | C51: =+C47 -> 191.317 | D51: =+D47 -> 172.671 | E51: =+E47 -> 217.895 | F51: =+F47 -> 167.0031
B52: (x) Valuation Multiple | C52: =+$C$70 -> 3 | D52: =+$C$70 -> 3 | E52: =+$C$70 -> 3 | F52: =+$C$70 -> 3
B53: Laundromat Valuation | C53: =C51*C52 -> 573.951 | D53: =D51*D52 -> 518.013 | E53: =E51*E52 -> 653.685 | F53: =F51*F52 -> 501.0093
B54: (-) Rennovation Cost | C54: =-C77 -> -350 | D54: =C54 -> -350 | E54: =D54 -> -350 | F54: =E54 -> -350
B55: Laundromat Valuation | C55: =C53+C54 -> 223.951 | D55: =D53+D54 -> 168.013 | E55: =E53+E54 -> 303.685 | F55: =ROUND(F53+F54,-1) -> 150
B57: Laundromat Pro Forma Assumptions
B59: 18-Month Revenue Growth | C59: -0.1
B60: Utilities Margin | C60: =SUM(C13:E13)/SUM(C9:E9) -> 0.25563562
B61: Go-Forward Labor Cost | C61: 0
B62: Monica's Compensation | C62: 55
B63: Go-Forward Repairs | C63: =AVERAGE(C17:E17) -> 33.270667
B64: Normalized Lease | C64: =+'Tennant View'!G29/1000 -> 17.261084
B65: Go-Forward Depreciation | C65: =+C25 -> 8.661
B66: Go-Forward Insurance | C66: =+E21 -> 4.384
B67: Go-Forward Interest | C67: 0
B68: Taxes (% Sales) | C68: 0
B69: Go-Forward Other Expenses | C69: =AVERAGE(C29:E29) -> 9.7903333
B70: Valuation Multiple | C70: 3
B71: Down Payment (%) | C71: 0.15
B72: Down Payment ($) | C72: =+F53*C71 -> 75.151396
B73: Principal | C73: =+F53*(1-C71) -> 425.85791
B74: Loan Term (Years) | C74: 20
B75: Interest Rate | C75: 0.065
B76: Go-Forward Lease | C76: =E19*2 -> 28.824
B77: Rennovation Cost | C77: 350

Sheet CRE Valuation
B2: =+'CRE P&L'!B2 -> Sunshine Commercial Investments
B3: CRE Valuation Overview ($000s) | L3: Print | M3: 1
B5: CRE Valuation Sensitivity Table
D7: Valuation Cap Rate Range | L7: Total Usable Sq. Ft. | N7: =+'Market Rent Analysis'!$C$7 -> 8400
D8: 0.08 | E8: =D8+0.5% -> 0.085 | F8: =E8+0.5% -> 0.09 | G8: =F8+0.5% -> 0.095 | H8: =G8+0.5% -> 0.1 | I8: =H8+0.5% -> 0.105 | J8: =I8+0.5% -> 0.11 | L8: Estimated Corporate Expenses | N8: =+'CRE P&L'!C53/1000 -> 9.235
B9: NOI Range | C9: 5 | D9: =$C9/D$8 -> 62.5 | E9: =$C9/E$8 -> 58.823529 | F9: =$C9/F$8 -> 55.555556 | G9: =$C9/G$8 -> 52.631579 | H9: =$C9/H$8 -> 50 | I9: =$C9/I$8 -> 47.619048 | J9: =$C9/J$8 -> 45.454545
C10: =C9+5 -> 10 | D10: =$C10/D$8 -> 125 | E10: =$C10/E$8 -> 117.64706 | F10: =$C10/F$8 -> 111.11111 | G10: =$C10/G$8 -> 105.26316 | H10: =$C10/H$8 -> 100 | I10: =$C10/I$8 -> 95.238095 | J10: =$C10/J$8 -> 90.909091
C11: =C10+5 -> 15 | D11: =$C11/D$8 -> 187.5 | E11: =$C11/E$8 -> 176.47059 | F11: =$C11/F$8 -> 166.66667 | G11: =$C11/G$8 -> 157.89474 | H11: =$C11/H$8 -> 150 | I11: =$C11/I$8 -> 142.85714 | J11: =$C11/J$8 -> 136.36364
C12: =C11+5 -> 20 | D12: =$C12/D$8 -> 250 | E12: =$C12/E$8 -> 235.29412 | F12: =$C12/F$8 -> 222.22222 | G12: =$C12/G$8 -> 210.52632 | H12: =$C12/H$8 -> 200 | I12: =$C12/I$8 -> 190.47619 | J12: =$C12/J$8 -> 181.81818
C13: =C12+5 -> 25 | D13: =$C13/D$8 -> 312.5 | E13: =$C13/E$8 -> 294.11765 | F13: =$C13/F$8 -> 277.77778 | G13: =$C13/G$8 -> 263.15789 | H13: =$C13/H$8 -> 250 | I13: =$C13/I$8 -> 238.09524 | J13: =$C13/J$8 -> 227.27273
C14: =C13+5 -> 30 | D14: =$C14/D$8 -> 375 | E14: =$C14/E$8 -> 352.94118 | F14: =$C14/F$8 -> 333.33333 | G14: =$C14/G$8 -> 315.78947 | H14: =$C14/H$8 -> 300 | I14: =$C14/I$8 -> 285.71429 | J14: =$C14/J$8 -> 272.72727
C15: =C14+5 -> 35 | D15: =$C15/D$8 -> 437.5 | E15: =$C15/E$8 -> 411.76471 | F15: =$C15/F$8 -> 388.88889 | G15: =$C15/G$8 -> 368.42105 | H15: =$C15/H$8 -> 350 | I15: =$C15/I$8 -> 333.33333 | J15: =$C15/J$8 -> 318.18182
C16: =C15+5 -> 40 | D16: =$C16/D$8 -> 500 | E16: =$C16/E$8 -> 470.58824 | F16: =$C16/F$8 -> 444.44444 | G16: =$C16/G$8 -> 421.05263 | H16: =$C16/H$8 -> 400 | I16: =$C16/I$8 -> 380.95238 | J16: =$C16/J$8 -> 363.63636
B18: Consolidated Valuation
B20: Commercial Real Estate | F20: 450
B21: (+) Signed Leases | F21: =F22-F20 -> 150 | G21: 33% increase in valuation | L21: =F21/F20 -> 0.33333333
B22: Estimated CRE Valuation | F22: 600
B23: (+) Laundromat Valuation | F23: =+'Laundromat Valuation'!F55 -> 150
B24: Total Valuation | F24: =+F22+F23 -> 750

Sheet Sensitivity Analysis
B2: =+'CRE P&L'!B2 -> Sunshine Commercial Investments
B3: CRE Sensitivity Analysis | L3: Print | M3: 1
B5: Valuation Sensitivity Table
D7: Valuation Cap Rate Range | L7: Total Usable Sq. Ft. | N7: =+'Market Rent Analysis'!$C$7 -> 8400
D8: 0.07 | E8: =D8+0.5% -> 0.075 | F8: =E8+0.5% -> 0.08 | G8: =F8+0.5% -> 0.085 | H8: =G8+0.5% -> 0.09 | I8: =H8+0.5% -> 0.095 | J8: =I8+0.5% -> 0.1 | L8: Estimated Corporate Expenses | N8: =+'CRE P&L'!C53/1000 -> 9.235
B9: Net Operating Income Range ($000s) | C9: 20 | D9: =$C9/D$8 -> 285.71429 | E9: =$C9/E$8 -> 266.66667 | F9: =$C9/F$8 -> 250 | G9: =$C9/G$8 -> 235.29412 | H9: =$C9/H$8 -> 222.22222 | I9: =$C9/I$8 -> 210.52632 | J9: =$C9/J$8 -> 200
C10: =C9+10 -> 30 | D10: =$C10/D$8 -> 428.57143 | E10: =$C10/E$8 -> 400 | F10: =$C10/F$8 -> 375 | G10: =$C10/G$8 -> 352.94118 | H10: =$C10/H$8 -> 333.33333 | I10: =$C10/I$8 -> 315.78947 | J10: =$C10/J$8 -> 300
C11: =C10+10 -> 40 | D11: =$C11/D$8 -> 571.42857 | E11: =$C11/E$8 -> 533.33333 | F11: =$C11/F$8 -> 500 | G11: =$C11/G$8 -> 470.58824 | H11: =$C11/H$8 -> 444.44444 | I11: =$C11/I$8 -> 421.05263 | J11: =$C11/J$8 -> 400
C12: =C11+10 -> 50 | D12: =$C12/D$8 -> 714.28571 | E12: =$C12/E$8 -> 666.66667 | F12: =$C12/F$8 -> 625 | G12: =$C12/G$8 -> 588.23529 | H12: =$C12/H$8 -> 555.55556 | I12: =$C12/I$8 -> 526.31579 | J12: =$C12/J$8 -> 500
C13: =C12+10 -> 60 | D13: =$C13/D$8 -> 857.14286 | E13: =$C13/E$8 -> 800 | F13: =$C13/F$8 -> 750 | G13: =$C13/G$8 -> 705.88235 | H13: =$C13/H$8 -> 666.66667 | I13: =$C13/I$8 -> 631.57895 | J13: =$C13/J$8 -> 600
C14: =C13+10 -> 70 | D14: =$C14/D$8 -> 1000 | E14: =$C14/E$8 -> 933.33333 | F14: =$C14/F$8 -> 875 | G14: =$C14/G$8 -> 823.52941 | H14: =$C14/H$8 -> 777.77778 | I14: =$C14/I$8 -> 736.84211 | J14: =$C14/J$8 -> 700
C15: =C14+10 -> 80 | D15: =$C15/D$8 -> 1142.8571 | E15: =$C15/E$8 -> 1066.6667 | F15: =$C15/F$8 -> 1000 | G15: =$C15/G$8 -> 941.17647 | H15: =$C15/H$8 -> 888.88889 | I15: =$C15/I$8 -> 842.10526 | J15: =$C15/J$8 -> 800
C16: =C15+10 -> 90 | D16: =$C16/D$8 -> 1285.7143 | E16: =$C16/E$8 -> 1200 | F16: =$C16/F$8 -> 1125 | G16: =$C16/G$8 -> 1058.8235 | H16: =$C16/H$8 -> 1000 | I16: =$C16/I$8 -> 947.36842 | J16: =$C16/J$8 -> 900
C17: =C16+10 -> 100 | D17: =$C17/D$8 -> 1428.5714 | E17: =$C17/E$8 -> 1333.3333 | F17: =$C17/F$8 -> 1250 | G17: =$C17/G$8 -> 1176.4706 | H17: =$C17/H$8 -> 1111.1111 | I17: =$C17/I$8 -> 1052.6316 | J17: =$C17/J$8 -> 1000
B19: 8% Cap Rate - Clearance NOI Based on Extimated Expenses
D21: Total Rent Sq. Ft. Range
D22: % Inc. | E22: =E23/$D23-1 -> 0.16666667 | F22: =F23/$D23-1 -> 0.33333333 | G22: =G23/$D23-1 -> 0.5 | H22: =H23/$D23-1 -> 0.66666667 | I22: =I23/$D23-1 -> 0.83333333 | J22: =J23/$D23-1 -> 1
D23: 7.25 | E23: =($J$23-$D$23)/6+D23 -> 8.4583333 | F23: =($J$23-$D$23)/6+E23 -> 9.6666667 | G23: =($J$23-$D$23)/6+F23 -> 10.875 | H23: =($J$23-$D$23)/6+G23 -> 12.083333 | I23: =($J$23-$D$23)/6+H23 -> 13.291667 | J23: =D23*2 -> 14.5
B24: NNN + Corporate Cost Range ($000s) | C24: 20 | D24: =D$23*$N$7/1000-$C24 -> 40.9 | E24: =E$23*$N$7/1000-$C24 -> 51.05 | F24: =F$23*$N$7/1000-$C24 -> 61.2 | G24: =G$23*$N$7/1000-$C24 -> 71.35 | H24: =H$23*$N$7/1000-$C24 -> 81.5 | I24: =I$23*$N$7/1000-$C24 -> 91.65 | J24: =J$23*$N$7/1000-$C24 -> 101.8
C25: =($C$32-$C$24)/8+C24 -> 27.5 | D25: =D$23*$N$7/1000-$C25 -> 33.4 | E25: =E$23*$N$7/1000-$C25 -> 43.55 | F25: =F$23*$N$7/1000-$C25 -> 53.7 | G25: =G$23*$N$7/1000-$C25 -> 63.85 | H25: =H$23*$N$7/1000-$C25 -> 74 | I25: =I$23*$N$7/1000-$C25 -> 84.15 | J25: =J$23*$N$7/1000-$C25 -> 94.3
C26: =($C$32-$C$24)/8+C25 -> 35 | D26: =D$23*$N$7/1000-$C26 -> 25.9 | E26: =E$23*$N$7/1000-$C26 -> 36.05 | F26: =F$23*$N$7/1000-$C26 -> 46.2 | G26: =G$23*$N$7/1000-$C26 -> 56.35 | H26: =H$23*$N$7/1000-$C26 -> 66.5 | I26: =I$23*$N$7/1000-$C26 -> 76.65 | J26: =J$23*$N$7/1000-$C26 -> 86.8
C27: =($C$32-$C$24)/8+C26 -> 42.5 | D27: =D$23*$N$7/1000-$C27 -> 18.4 | E27: =E$23*$N$7/1000-$C27 -> 28.55 | F27: =F$23*$N$7/1000-$C27 -> 38.7 | G27: =G$23*$N$7/1000-$C27 -> 48.85 | H27: =H$23*$N$7/1000-$C27 -> 59 | I27: =I$23*$N$7/1000-$C27 -> 69.15 | J27: =J$23*$N$7/1000-$C27 -> 79.3
C28: =($C$32-$C$24)/8+C27 -> 50 | D28: =D$23*$N$7/1000-$C28 -> 10.9 | E28: =E$23*$N$7/1000-$C28 -> 21.05 | F28: =F$23*$N$7/1000-$C28 -> 31.2 | G28: =G$23*$N$7/1000-$C28 -> 41.35 | H28: =H$23*$N$7/1000-$C28 -> 51.5 | I28: =I$23*$N$7/1000-$C28 -> 61.65 | J28: =J$23*$N$7/1000-$C28 -> 71.8
C29: =($C$32-$C$24)/8+C28 -> 57.5 | D29: =D$23*$N$7/1000-$C29 -> 3.4 | E29: =E$23*$N$7/1000-$C29 -> 13.55 | F29: =F$23*$N$7/1000-$C29 -> 23.7 | G29: =G$23*$N$7/1000-$C29 -> 33.85 | H29: =H$23*$N$7/1000-$C29 -> 44 | I29: =I$23*$N$7/1000-$C29 -> 54.15 | J29: =J$23*$N$7/1000-$C29 -> 64.3
C30: =($C$32-$C$24)/8+C29 -> 65 | D30: =D$23*$N$7/1000-$C30 -> -4.1 | E30: =E$23*$N$7/1000-$C30 -> 6.05 | F30: =F$23*$N$7/1000-$C30 -> 16.2 | G30: =G$23*$N$7/1000-$C30 -> 26.35 | H30: =H$23*$N$7/1000-$C30 -> 36.5 | I30: =I$23*$N$7/1000-$C30 -> 46.65 | J30: =J$23*$N$7/1000-$C30 -> 56.8
C31: =($C$32-$C$24)/8+C30 -> 72.5 | D31: =D$23*$N$7/1000-$C31 -> -11.6 | E31: =E$23*$N$7/1000-$C31 -> -1.45 | F31: =F$23*$N$7/1000-$C31 -> 8.7 | G31: =G$23*$N$7/1000-$C31 -> 18.85 | H31: =H$23*$N$7/1000-$C31 -> 29 | I31: =I$23*$N$7/1000-$C31 -> 39.15 | J31: =J$23*$N$7/1000-$C31 -> 49.3
C32: 80 | D32: =D$23*$N$7/1000-$C32 -> -19.1 | E32: =E$23*$N$7/1000-$C32 -> -8.95 | F32: =F$23*$N$7/1000-$C32 -> 1.2 | G32: =G$23*$N$7/1000-$C32 -> 11.35 | H32: =H$23*$N$7/1000-$C32 -> 21.5 | I32: =I$23*$N$7/1000-$C32 -> 31.65 | J32: =J$23*$N$7/1000-$C32 -> 41.8
B34: 9% Cap Rate - Clearance NOI Based on Extimated Expenses
D36: Total Rent Sq. Ft. Range
D37: % Inc. | E37: =E38/$D38-1 -> 0.16666667 | F37: =F38/$D38-1 -> 0.33333333 | G37: =G38/$D38-1 -> 0.5 | H37: =H38/$D38-1 -> 0.66666667 | I37: =I38/$D38-1 -> 0.83333333 | J37: =J38/$D38-1 -> 1
D38: 7.25 | E38: =($J$23-$D$23)/6+D38 -> 8.4583333 | F38: =($J$23-$D$23)/6+E38 -> 9.6666667 | G38: =($J$23-$D$23)/6+F38 -> 10.875 | H38: =($J$23-$D$23)/6+G38 -> 12.083333 | I38: =($J$23-$D$23)/6+H38 -> 13.291667 | J38: =D38*2 -> 14.5
B39: NNN + Corporate Cost Range ($000s) | C39: 20 | D39: =D$23*$N$7/1000-$C39 -> 40.9 | E39: =E$23*$N$7/1000-$C39 -> 51.05 | F39: =F$23*$N$7/1000-$C39 -> 61.2 | G39: =G$23*$N$7/1000-$C39 -> 71.35 | H39: =H$23*$N$7/1000-$C39 -> 81.5 | I39: =I$23*$N$7/1000-$C39 -> 91.65 | J39: =J$23*$N$7/1000-$C39 -> 101.8
C40: =($C$32-$C$24)/8+C39 -> 27.5 | D40: =D$23*$N$7/1000-$C40 -> 33.4 | E40: =E$23*$N$7/1000-$C40 -> 43.55 | F40: =F$23*$N$7/1000-$C40 -> 53.7 | G40: =G$23*$N$7/1000-$C40 -> 63.85 | H40: =H$23*$N$7/1000-$C40 -> 74 | I40: =I$23*$N$7/1000-$C40 -> 84.15 | J40: =J$23*$N$7/1000-$C40 -> 94.3
C41: =($C$32-$C$24)/8+C40 -> 35 | D41: =D$23*$N$7/1000-$C41 -> 25.9 | E41: =E$23*$N$7/1000-$C41 -> 36.05 | F41: =F$23*$N$7/1000-$C41 -> 46.2 | G41: =G$23*$N$7/1000-$C41 -> 56.35 | H41: =H$23*$N$7/1000-$C41 -> 66.5 | I41: =I$23*$N$7/1000-$C41 -> 76.65 | J41: =J$23*$N$7/1000-$C41 -> 86.8
C42: =($C$32-$C$24)/8+C41 -> 42.5 | D42: =D$23*$N$7/1000-$C42 -> 18.4 | E42: =E$23*$N$7/1000-$C42 -> 28.55 | F42: =F$23*$N$7/1000-$C42 -> 38.7 | G42: =G$23*$N$7/1000-$C42 -> 48.85 | H42: =H$23*$N$7/1000-$C42 -> 59 | I42: =I$23*$N$7/1000-$C42 -> 69.15 | J42: =J$23*$N$7/1000-$C42 -> 79.3
C43: =($C$32-$C$24)/8+C42 -> 50 | D43: =D$23*$N$7/1000-$C43 -> 10.9 | E43: =E$23*$N$7/1000-$C43 -> 21.05 | F43: =F$23*$N$7/1000-$C43 -> 31.2 | G43: =G$23*$N$7/1000-$C43 -> 41.35 | H43: =H$23*$N$7/1000-$C43 -> 51.5 | I43: =I$23*$N$7/1000-$C43 -> 61.65 | J43: =J$23*$N$7/1000-$C43 -> 71.8
C44: =($C$32-$C$24)/8+C43 -> 57.5 | D44: =D$23*$N$7/1000-$C44 -> 3.4 | E44: =E$23*$N$7/1000-$C44 -> 13.55 | F44: =F$23*$N$7/1000-$C44 -> 23.7 | G44: =G$23*$N$7/1000-$C44 -> 33.85 | H44: =H$23*$N$7/1000-$C44 -> 44 | I44: =I$23*$N$7/1000-$C44 -> 54.15 | J44: =J$23*$N$7/1000-$C44 -> 64.3
C45: =($C$32-$C$24)/8+C44 -> 65 | D45: =D$23*$N$7/1000-$C45 -> -4.1 | E45: =E$23*$N$7/1000-$C45 -> 6.05 | F45: =F$23*$N$7/1000-$C45 -> 16.2 | G45: =G$23*$N$7/1000-$C45 -> 26.35 | H45: =H$23*$N$7/1000-$C45 -> 36.5 | I45: =I$23*$N$7/1000-$C45 -> 46.65 | J45: =J$23*$N$7/1000-$C45 -> 56.8
C46: =($C$32-$C$24)/8+C45 -> 72.5 | D46: =D$23*$N$7/1000-$C46 -> -11.6 | E46: =E$23*$N$7/1000-$C46 -> -1.45 | F46: =F$23*$N$7/1000-$C46 -> 8.7 | G46: =G$23*$N$7/1000-$C46 -> 18.85 | H46: =H$23*$N$7/1000-$C46 -> 29 | I46: =I$23*$N$7/1000-$C46 -> 39.15 | J46: =J$23*$N$7/1000-$C46 -> 49.3
C47: 80 | D47: =D$23*$N$7/1000-$C47 -> -19.1 | E47: =E$23*$N$7/1000-$C47 -> -8.95 | F47: =F$23*$N$7/1000-$C47 -> 1.2 | G47: =G$23*$N$7/1000-$C47 -> 11.35 | H47: =H$23*$N$7/1000-$C47 -> 21.5 | I47: =I$23*$N$7/1000-$C47 -> 31.65 | J47: =J$23*$N$7/1000-$C47 -> 41.8
B49: Note: Cells highligted in green clear the $1M CRE valuation threshhold
B51: Post-Debt Service Cash Flow ($350K - $650K Valuation)
D53: Valuation ($000s)
D54: 350 | E54: =D54+50 -> 400 | F54: =E54+50 -> 450 | G54: =F54+50 -> 500 | H54: =G54+50 -> 550 | I54: =H54+50 -> 600 | J54: =I54+50 -> 650
B55: Net Operating Income Range ($000s) | C55: 20 | D55: =$C55-((D$54*$M$55/$M$56)+(D$54*$M$55*$M$57)) -> -14.2125 | E55: =$C55-((E$54*$M$55/$M$56)+(E$54*$M$55*$M$57)) -> -19.1 | F55: =$C55-((F$54*$M$55/$M$56)+(F$54*$M$55*$M$57)) -> -23.9875 | G55: =$C55-((G$54*$M$55/$M$56)+(G$54*$M$55*$M$57)) -> -28.875 | H55: =$C55-((H$54*$M$55/$M$56)+(H$54*$M$55*$M$57)) -> -33.7625 | I55: =$C55-((I$54*$M$55/$M$56)+(I$54*$M$55*$M$57)) -> -38.65 | J55: =$C55-((J$54*$M$55/$M$56)+(J$54*$M$55*$M$57)) -> -43.5375 | L55: LTV | M55: 0.85
C56: =C55+10 -> 30 | D56: =$C56-((D$54*$M$55/$M$56)+(D$54*$M$55*$M$57)) -> -4.2125 | E56: =$C56-((E$54*$M$55/$M$56)+(E$54*$M$55*$M$57)) -> -9.1 | F56: =$C56-((F$54*$M$55/$M$56)+(F$54*$M$55*$M$57)) -> -13.9875 | G56: =$C56-((G$54*$M$55/$M$56)+(G$54*$M$55*$M$57)) -> -18.875 | H56: =$C56-((H$54*$M$55/$M$56)+(H$54*$M$55*$M$57)) -> -23.7625 | I56: =$C56-((I$54*$M$55/$M$56)+(I$54*$M$55*$M$57)) -> -28.65 | J56: =$C56-((J$54*$M$55/$M$56)+(J$54*$M$55*$M$57)) -> -33.5375 | L56: Term | M56: 20
C57: =C56+10 -> 40 | D57: =$C57-((D$54*$M$55/$M$56)+(D$54*$M$55*$M$57)) -> 5.7875 | E57: =$C57-((E$54*$M$55/$M$56)+(E$54*$M$55*$M$57)) -> 0.9 | F57: =$C57-((F$54*$M$55/$M$56)+(F$54*$M$55*$M$57)) -> -3.9875 | G57: =$C57-((G$54*$M$55/$M$56)+(G$54*$M$55*$M$57)) -> -8.875 | H57: =$C57-((H$54*$M$55/$M$56)+(H$54*$M$55*$M$57)) -> -13.7625 | I57: =$C57-((I$54*$M$55/$M$56)+(I$54*$M$55*$M$57)) -> -18.65 | J57: =$C57-((J$54*$M$55/$M$56)+(J$54*$M$55*$M$57)) -> -23.5375 | L57: Rate | M57: 0.065
C58: =C57+10 -> 50 | D58: =$C58-((D$54*$M$55/$M$56)+(D$54*$M$55*$M$57)) -> 15.7875 | E58: =$C58-((E$54*$M$55/$M$56)+(E$54*$M$55*$M$57)) -> 10.9 | F58: =$C58-((F$54*$M$55/$M$56)+(F$54*$M$55*$M$57)) -> 6.0125 | G58: =$C58-((G$54*$M$55/$M$56)+(G$54*$M$55*$M$57)) -> 1.125 | H58: =$C58-((H$54*$M$55/$M$56)+(H$54*$M$55*$M$57)) -> -3.7625 | I58: =$C58-((I$54*$M$55/$M$56)+(I$54*$M$55*$M$57)) -> -8.65 | J58: =$C58-((J$54*$M$55/$M$56)+(J$54*$M$55*$M$57)) -> -13.5375
C59: =C58+10 -> 60 | D59: =$C59-((D$54*$M$55/$M$56)+(D$54*$M$55*$M$57)) -> 25.7875 | E59: =$C59-((E$54*$M$55/$M$56)+(E$54*$M$55*$M$57)) -> 20.9 | F59: =$C59-((F$54*$M$55/$M$56)+(F$54*$M$55*$M$57)) -> 16.0125 | G59: =$C59-((G$54*$M$55/$M$56)+(G$54*$M$55*$M$57)) -> 11.125 | H59: =$C59-((H$54*$M$55/$M$56)+(H$54*$M$55*$M$57)) -> 6.2375 | I59: =$C59-((I$54*$M$55/$M$56)+(I$54*$M$55*$M$57)) -> 1.35 | J59: =$C59-((J$54*$M$55/$M$56)+(J$54*$M$55*$M$57)) -> -3.5375
C60: =C59+10 -> 70 | D60: =$C60-((D$54*$M$55/$M$56)+(D$54*$M$55*$M$57)) -> 35.7875 | E60: =$C60-((E$54*$M$55/$M$56)+(E$54*$M$55*$M$57)) -> 30.9 | F60: =$C60-((F$54*$M$55/$M$56)+(F$54*$M$55*$M$57)) -> 26.0125 | G60: =$C60-((G$54*$M$55/$M$56)+(G$54*$M$55*$M$57)) -> 21.125 | H60: =$C60-((H$54*$M$55/$M$56)+(H$54*$M$55*$M$57)) -> 16.2375 | I60: =$C60-((I$54*$M$55/$M$56)+(I$54*$M$55*$M$57)) -> 11.35 | J60: =$C60-((J$54*$M$55/$M$56)+(J$54*$M$55*$M$57)) -> 6.4625
C61: =C60+10 -> 80 | D61: =$C61-((D$54*$M$55/$M$56)+(D$54*$M$55*$M$57)) -> 45.7875 | E61: =$C61-((E$54*$M$55/$M$56)+(E$54*$M$55*$M$57)) -> 40.9 | F61: =$C61-((F$54*$M$55/$M$56)+(F$54*$M$55*$M$57)) -> 36.0125 | G61: =$C61-((G$54*$M$55/$M$56)+(G$54*$M$55*$M$57)) -> 31.125 | H61: =$C61-((H$54*$M$55/$M$56)+(H$54*$M$55*$M$57)) -> 26.2375 | I61: =$C61-((I$54*$M$55/$M$56)+(I$54*$M$55*$M$57)) -> 21.35 | J61: =$C61-((J$54*$M$55/$M$56)+(J$54*$M$55*$M$57)) -> 16.4625
C62: =C61+10 -> 90 | D62: =$C62-((D$54*$M$55/$M$56)+(D$54*$M$55*$M$57)) -> 55.7875 | E62: =$C62-((E$54*$M$55/$M$56)+(E$54*$M$55*$M$57)) -> 50.9 | F62: =$C62-((F$54*$M$55/$M$56)+(F$54*$M$55*$M$57)) -> 46.0125 | G62: =$C62-((G$54*$M$55/$M$56)+(G$54*$M$55*$M$57)) -> 41.125 | H62: =$C62-((H$54*$M$55/$M$56)+(H$54*$M$55*$M$57)) -> 36.2375 | I62: =$C62-((I$54*$M$55/$M$56)+(I$54*$M$55*$M$57)) -> 31.35 | J62: =$C62-((J$54*$M$55/$M$56)+(J$54*$M$55*$M$57)) -> 26.4625
C63: =C62+10 -> 100 | D63: =$C63-((D$54*$M$55/$M$56)+(D$54*$M$55*$M$57)) -> 65.7875 | E63: =$C63-((E$54*$M$55/$M$56)+(E$54*$M$55*$M$57)) -> 60.9 | F63: =$C63-((F$54*$M$55/$M$56)+(F$54*$M$55*$M$57)) -> 56.0125 | G63: =$C63-((G$54*$M$55/$M$56)+(G$54*$M$55*$M$57)) -> 51.125 | H63: =$C63-((H$54*$M$55/$M$56)+(H$54*$M$55*$M$57)) -> 46.2375 | I63: =$C63-((I$54*$M$55/$M$56)+(I$54*$M$55*$M$57)) -> 41.35 | J63: =$C63-((J$54*$M$55/$M$56)+(J$54*$M$55*$M$57)) -> 36.4625
B65: Assumes a 20-year amortization schedule with 6.50% interest rate
B67: Post-Debt Service Cash Flow ($700K - $1M Valuation)
D69: Valuation ($000s)
D70: 700 | E70: =D70+50 -> 750 | F70: =E70+50 -> 800 | G70: =F70+50 -> 850 | H70: =G70+50 -> 900 | I70: =H70+50 -> 950 | J70: =I70+50 -> 1000
B71: Net Operating Income Range ($000s) | C71: 20 | D71: =$C71-((D$70*$M$71/$M$72)+(D$70*$M$71*$M$73)) -> -48.425 | E71: =$C71-((E$70*$M$71/$M$72)+(E$70*$M$71*$M$73)) -> -53.3125 | F71: =$C71-((F$70*$M$71/$M$72)+(F$70*$M$71*$M$73)) -> -58.2 | G71: =$C71-((G$70*$M$71/$M$72)+(G$70*$M$71*$M$73)) -> -63.0875 | H71: =$C71-((H$70*$M$71/$M$72)+(H$70*$M$71*$M$73)) -> -67.975 | I71: =$C71-((I$70*$M$71/$M$72)+(I$70*$M$71*$M$73)) -> -72.8625 | J71: =$C71-((J$70*$M$71/$M$72)+(J$70*$M$71*$M$73)) -> -77.75 | L71: LTV | M71: =+M55 -> 0.85
C72: =C71+10 -> 30 | D72: =$C72-((D$70*$M$71/$M$72)+(D$70*$M$71*$M$73)) -> -38.425 | E72: =$C72-((E$70*$M$71/$M$72)+(E$70*$M$71*$M$73)) -> -43.3125 | F72: =$C72-((F$70*$M$71/$M$72)+(F$70*$M$71*$M$73)) -> -48.2 | G72: =$C72-((G$70*$M$71/$M$72)+(G$70*$M$71*$M$73)) -> -53.0875 | H72: =$C72-((H$70*$M$71/$M$72)+(H$70*$M$71*$M$73)) -> -57.975 | I72: =$C72-((I$70*$M$71/$M$72)+(I$70*$M$71*$M$73)) -> -62.8625 | J72: =$C72-((J$70*$M$71/$M$72)+(J$70*$M$71*$M$73)) -> -67.75 | L72: Term | M72: =+M56 -> 20
C73: =C72+10 -> 40 | D73: =$C73-((D$70*$M$71/$M$72)+(D$70*$M$71*$M$73)) -> -28.425 | E73: =$C73-((E$70*$M$71/$M$72)+(E$70*$M$71*$M$73)) -> -33.3125 | F73: =$C73-((F$70*$M$71/$M$72)+(F$70*$M$71*$M$73)) -> -38.2 | G73: =$C73-((G$70*$M$71/$M$72)+(G$70*$M$71*$M$73)) -> -43.0875 | H73: =$C73-((H$70*$M$71/$M$72)+(H$70*$M$71*$M$73)) -> -47.975 | I73: =$C73-((I$70*$M$71/$M$72)+(I$70*$M$71*$M$73)) -> -52.8625 | J73: =$C73-((J$70*$M$71/$M$72)+(J$70*$M$71*$M$73)) -> -57.75 | L73: Rate | M73: =+M57 -> 0.065
C74: =C73+10 -> 50 | D74: =$C74-((D$70*$M$71/$M$72)+(D$70*$M$71*$M$73)) -> -18.425 | E74: =$C74-((E$70*$M$71/$M$72)+(E$70*$M$71*$M$73)) -> -23.3125 | F74: =$C74-((F$70*$M$71/$M$72)+(F$70*$M$71*$M$73)) -> -28.2 | G74: =$C74-((G$70*$M$71/$M$72)+(G$70*$M$71*$M$73)) -> -33.0875 | H74: =$C74-((H$70*$M$71/$M$72)+(H$70*$M$71*$M$73)) -> -37.975 | I74: =$C74-((I$70*$M$71/$M$72)+(I$70*$M$71*$M$73)) -> -42.8625 | J74: =$C74-((J$70*$M$71/$M$72)+(J$70*$M$71*$M$73)) -> -47.75
C75: =C74+10 -> 60 | D75: =$C75-((D$70*$M$71/$M$72)+(D$70*$M$71*$M$73)) -> -8.425 | E75: =$C75-((E$70*$M$71/$M$72)+(E$70*$M$71*$M$73)) -> -13.3125 | F75: =$C75-((F$70*$M$71/$M$72)+(F$70*$M$71*$M$73)) -> -18.2 | G75: =$C75-((G$70*$M$71/$M$72)+(G$70*$M$71*$M$73)) -> -23.0875 | H75: =$C75-((H$70*$M$71/$M$72)+(H$70*$M$71*$M$73)) -> -27.975 | I75: =$C75-((I$70*$M$71/$M$72)+(I$70*$M$71*$M$73)) -> -32.8625 | J75: =$C75-((J$70*$M$71/$M$72)+(J$70*$M$71*$M$73)) -> -37.75
C76: =C75+10 -> 70 | D76: =$C76-((D$70*$M$71/$M$72)+(D$70*$M$71*$M$73)) -> 1.575 | E76: =$C76-((E$70*$M$71/$M$72)+(E$70*$M$71*$M$73)) -> -3.3125 | F76: =$C76-((F$70*$M$71/$M$72)+(F$70*$M$71*$M$73)) -> -8.2 | G76: =$C76-((G$70*$M$71/$M$72)+(G$70*$M$71*$M$73)) -> -13.0875 | H76: =$C76-((H$70*$M$71/$M$72)+(H$70*$M$71*$M$73)) -> -17.975 | I76: =$C76-((I$70*$M$71/$M$72)+(I$70*$M$71*$M$73)) -> -22.8625 | J76: =$C76-((J$70*$M$71/$M$72)+(J$70*$M$71*$M$73)) -> -27.75
C77: =C76+10 -> 80 | D77: =$C77-((D$70*$M$71/$M$72)+(D$70*$M$71*$M$73)) -> 11.575 | E77: =$C77-((E$70*$M$71/$M$72)+(E$70*$M$71*$M$73)) -> 6.6875 | F77: =$C77-((F$70*$M$71/$M$72)+(F$70*$M$71*$M$73)) -> 1.8 | G77: =$C77-((G$70*$M$71/$M$72)+(G$70*$M$71*$M$73)) -> -3.0875 | H77: =$C77-((H$70*$M$71/$M$72)+(H$70*$M$71*$M$73)) -> -7.975 | I77: =$C77-((I$70*$M$71/$M$72)+(I$70*$M$71*$M$73)) -> -12.8625 | J77: =$C77-((J$70*$M$71/$M$72)+(J$70*$M$71*$M$73)) -> -17.75
C78: =C77+10 -> 90 | D78: =$C78-((D$70*$M$71/$M$72)+(D$70*$M$71*$M$73)) -> 21.575 | E78: =$C78-((E$70*$M$71/$M$72)+(E$70*$M$71*$M$73)) -> 16.6875 | F78: =$C78-((F$70*$M$71/$M$72)+(F$70*$M$71*$M$73)) -> 11.8 | G78: =$C78-((G$70*$M$71/$M$72)+(G$70*$M$71*$M$73)) -> 6.9125 | H78: =$C78-((H$70*$M$71/$M$72)+(H$70*$M$71*$M$73)) -> 2.025 | I78: =$C78-((I$70*$M$71/$M$72)+(I$70*$M$71*$M$73)) -> -2.8625 | J78: =$C78-((J$70*$M$71/$M$72)+(J$70*$M$71*$M$73)) -> -7.75
C79: =C78+10 -> 100 | D79: =$C79-((D$70*$M$71/$M$72)+(D$70*$M$71*$M$73)) -> 31.575 | E79: =$C79-((E$70*$M$71/$M$72)+(E$70*$M$71*$M$73)) -> 26.6875 | F79: =$C79-((F$70*$M$71/$M$72)+(F$70*$M$71*$M$73)) -> 21.8 | G79: =$C79-((G$70*$M$71/$M$72)+(G$70*$M$71*$M$73)) -> 16.9125 | H79: =$C79-((H$70*$M$71/$M$72)+(H$70*$M$71*$M$73)) -> 12.025 | I79: =$C79-((I$70*$M$71/$M$72)+(I$70*$M$71*$M$73)) -> 7.1375 | J79: =$C79-((J$70*$M$71/$M$72)+(J$70*$M$71*$M$73)) -> 2.25
B81: Cash-On-Cash Return ($350K - $650K Valuation)
D83: Valuation ($000s)
D84: 350 | E84: =D84+50 -> 400 | F84: =E84+50 -> 450 | G84: =F84+50 -> 500 | H84: =G84+50 -> 550 | I84: =H84+50 -> 600 | J84: =I84+50 -> 650
B85: Net Operating Income Range ($000s) | C85: 20 | D85: =D55/(D$84*(1-$M$85)) -> -0.27071429 | E85: =E55/(E$84*(1-$M$85)) -> -0.31833333 | F85: =F55/(F$84*(1-$M$85)) -> -0.35537037 | G85: =G55/(G$84*(1-$M$85)) -> -0.385 | H85: =H55/(H$84*(1-$M$85)) -> -0.40924242 | I85: =I55/(I$84*(1-$M$85)) -> -0.42944444 | J85: =J55/(J$84*(1-$M$85)) -> -0.44653846 | L85: LTV | M85: =+M71 -> 0.85
C86: =C85+10 -> 30 | D86: =D56/(D$84*(1-$M$85)) -> -0.080238095 | E86: =E56/(E$84*(1-$M$85)) -> -0.15166667 | F86: =F56/(F$84*(1-$M$85)) -> -0.20722222 | G86: =G56/(G$84*(1-$M$85)) -> -0.25166667 | H86: =H56/(H$84*(1-$M$85)) -> -0.2880303 | I86: =I56/(I$84*(1-$M$85)) -> -0.31833333 | J86: =J56/(J$84*(1-$M$85)) -> -0.34397436 | L86: Term | M86: =+M72 -> 20
C87: =C86+10 -> 40 | D87: =D57/(D$84*(1-$M$85)) -> 0.1102381 | E87: =E57/(E$84*(1-$M$85)) -> 0.015 | F87: =F57/(F$84*(1-$M$85)) -> -0.059074074 | G87: =G57/(G$84*(1-$M$85)) -> -0.11833333 | H87: =H57/(H$84*(1-$M$85)) -> -0.16681818 | I87: =I57/(I$84*(1-$M$85)) -> -0.20722222 | J87: =J57/(J$84*(1-$M$85)) -> -0.24141026 | L87: Rate | M87: =+M73 -> 0.065
C88: =C87+10 -> 50 | D88: =D58/(D$84*(1-$M$85)) -> 0.30071429 | E88: =E58/(E$84*(1-$M$85)) -> 0.18166667 | F88: =F58/(F$84*(1-$M$85)) -> 0.089074074 | G88: =G58/(G$84*(1-$M$85)) -> 0.015 | H88: =H58/(H$84*(1-$M$85)) -> -0.045606061 | I88: =I58/(I$84*(1-$M$85)) -> -0.096111111 | J88: =J58/(J$84*(1-$M$85)) -> -0.13884615
C89: =C88+10 -> 60 | D89: =D59/(D$84*(1-$M$85)) -> 0.49119048 | E89: =E59/(E$84*(1-$M$85)) -> 0.34833333 | F89: =F59/(F$84*(1-$M$85)) -> 0.23722222 | G89: =G59/(G$84*(1-$M$85)) -> 0.14833333 | H89: =H59/(H$84*(1-$M$85)) -> 0.075606061 | I89: =I59/(I$84*(1-$M$85)) -> 0.015 | J89: =J59/(J$84*(1-$M$85)) -> -0.036282051
C90: =C89+10 -> 70 | D90: =D60/(D$84*(1-$M$85)) -> 0.68166667 | E90: =E60/(E$84*(1-$M$85)) -> 0.515 | F90: =F60/(F$84*(1-$M$85)) -> 0.38537037 | G90: =G60/(G$84*(1-$M$85)) -> 0.28166667 | H90: =H60/(H$84*(1-$M$85)) -> 0.19681818 | I90: =I60/(I$84*(1-$M$85)) -> 0.12611111 | J90: =J60/(J$84*(1-$M$85)) -> 0.066282051
C91: =C90+10 -> 80 | D91: =D61/(D$84*(1-$M$85)) -> 0.87214286 | E91: =E61/(E$84*(1-$M$85)) -> 0.68166667 | F91: =F61/(F$84*(1-$M$85)) -> 0.53351852 | G91: =G61/(G$84*(1-$M$85)) -> 0.415 | H91: =H61/(H$84*(1-$M$85)) -> 0.3180303 | I91: =I61/(I$84*(1-$M$85)) -> 0.23722222 | J91: =J61/(J$84*(1-$M$85)) -> 0.16884615
C92: =C91+10 -> 90 | D92: =D62/(D$84*(1-$M$85)) -> 1.062619 | E92: =E62/(E$84*(1-$M$85)) -> 0.84833333 | F92: =F62/(F$84*(1-$M$85)) -> 0.68166667 | G92: =G62/(G$84*(1-$M$85)) -> 0.54833333 | H92: =H62/(H$84*(1-$M$85)) -> 0.43924242 | I92: =I62/(I$84*(1-$M$85)) -> 0.34833333 | J92: =J62/(J$84*(1-$M$85)) -> 0.27141026
C93: =C92+10 -> 100 | D93: =D63/(D$84*(1-$M$85)) -> 1.2530952 | E93: =E63/(E$84*(1-$M$85)) -> 1.015 | F93: =F63/(F$84*(1-$M$85)) -> 0.82981481 | G93: =G63/(G$84*(1-$M$85)) -> 0.68166667 | H93: =H63/(H$84*(1-$M$85)) -> 0.56045455 | I93: =I63/(I$84*(1-$M$85)) -> 0.45944444 | J93: =J63/(J$84*(1-$M$85)) -> 0.37397436
B95: Cash-On-Cash Return ($700K - $1M Valuation)
D97: Valuation ($000s)
D98: 700 | E98: =D98+50 -> 750 | F98: =E98+50 -> 800 | G98: =F98+50 -> 850 | H98: =G98+50 -> 900 | I98: =H98+50 -> 950 | J98: =I98+50 -> 1000
B99: Net Operating Income Range ($000s) | C99: 20 | D99: =D71/(D$98*(1-$M$99)) -> -0.46119048 | E99: =E71/(E$98*(1-$M$99)) -> -0.47388889 | F99: =F71/(F$98*(1-$M$99)) -> -0.485 | G99: =G71/(G$98*(1-$M$99)) -> -0.49480392 | H99: =H71/(H$98*(1-$M$99)) -> -0.50351852 | I99: =I71/(I$98*(1-$M$99)) -> -0.51131579 | J99: =J71/(J$98*(1-$M$99)) -> -0.51833333 | L99: LTV | M99: =+M85 -> 0.85
C100: =C99+10 -> 30 | D100: =D72/(D$98*(1-$M$99)) -> -0.36595238 | E100: =E72/(E$98*(1-$M$99)) -> -0.385 | F100: =F72/(F$98*(1-$M$99)) -> -0.40166667 | G100: =G72/(G$98*(1-$M$99)) -> -0.41637255 | H100: =H72/(H$98*(1-$M$99)) -> -0.42944444 | I100: =I72/(I$98*(1-$M$99)) -> -0.44114035 | J100: =J72/(J$98*(1-$M$99)) -> -0.45166667 | L100: Term | M100: =+M86 -> 20
C101: =C100+10 -> 40 | D101: =D73/(D$98*(1-$M$99)) -> -0.27071429 | E101: =E73/(E$98*(1-$M$99)) -> -0.29611111 | F101: =F73/(F$98*(1-$M$99)) -> -0.31833333 | G101: =G73/(G$98*(1-$M$99)) -> -0.33794118 | H101: =H73/(H$98*(1-$M$99)) -> -0.35537037 | I101: =I73/(I$98*(1-$M$99)) -> -0.37096491 | J101: =J73/(J$98*(1-$M$99)) -> -0.385 | L101: Rate | M101: =+M87 -> 0.065
C102: =C101+10 -> 50 | D102: =D74/(D$98*(1-$M$99)) -> -0.17547619 | E102: =E74/(E$98*(1-$M$99)) -> -0.20722222 | F102: =F74/(F$98*(1-$M$99)) -> -0.235 | G102: =G74/(G$98*(1-$M$99)) -> -0.2595098 | H102: =H74/(H$98*(1-$M$99)) -> -0.2812963 | I102: =I74/(I$98*(1-$M$99)) -> -0.30078947 | J102: =J74/(J$98*(1-$M$99)) -> -0.31833333
C103: =C102+10 -> 60 | D103: =D75/(D$98*(1-$M$99)) -> -0.080238095 | E103: =E75/(E$98*(1-$M$99)) -> -0.11833333 | F103: =F75/(F$98*(1-$M$99)) -> -0.15166667 | G103: =G75/(G$98*(1-$M$99)) -> -0.18107843 | H103: =H75/(H$98*(1-$M$99)) -> -0.20722222 | I103: =I75/(I$98*(1-$M$99)) -> -0.23061404 | J103: =J75/(J$98*(1-$M$99)) -> -0.25166667
C104: =C103+10 -> 70 | D104: =D76/(D$98*(1-$M$99)) -> 0.015 | E104: =E76/(E$98*(1-$M$99)) -> -0.029444444 | F104: =F76/(F$98*(1-$M$99)) -> -0.068333333 | G104: =G76/(G$98*(1-$M$99)) -> -0.10264706 | H104: =H76/(H$98*(1-$M$99)) -> -0.13314815 | I104: =I76/(I$98*(1-$M$99)) -> -0.1604386 | J104: =J76/(J$98*(1-$M$99)) -> -0.185
C105: =C104+10 -> 80 | D105: =D77/(D$98*(1-$M$99)) -> 0.1102381 | E105: =E77/(E$98*(1-$M$99)) -> 0.059444444 | F105: =F77/(F$98*(1-$M$99)) -> 0.015 | G105: =G77/(G$98*(1-$M$99)) -> -0.024215686 | H105: =H77/(H$98*(1-$M$99)) -> -0.059074074 | I105: =I77/(I$98*(1-$M$99)) -> -0.090263158 | J105: =J77/(J$98*(1-$M$99)) -> -0.11833333
C106: =C105+10 -> 90 | D106: =D78/(D$98*(1-$M$99)) -> 0.20547619 | E106: =E78/(E$98*(1-$M$99)) -> 0.14833333 | F106: =F78/(F$98*(1-$M$99)) -> 0.098333333 | G106: =G78/(G$98*(1-$M$99)) -> 0.054215686 | H106: =H78/(H$98*(1-$M$99)) -> 0.015 | I106: =I78/(I$98*(1-$M$99)) -> -0.020087719 | J106: =J78/(J$98*(1-$M$99)) -> -0.051666667
C107: =C106+10 -> 100 | D107: =D79/(D$98*(1-$M$99)) -> 0.30071429 | E107: =E79/(E$98*(1-$M$99)) -> 0.23722222 | F107: =F79/(F$98*(1-$M$99)) -> 0.18166667 | G107: =G79/(G$98*(1-$M$99)) -> 0.13264706 | H107: =H79/(H$98*(1-$M$99)) -> 0.089074074 | I107: =I79/(I$98*(1-$M$99)) -> 0.050087719 | J107: =J79/(J$98*(1-$M$99)) -> 0.015

Sheet CRE P&L
B2: =+Cover!B24 -> Sunshine Commercial Investments
B3: Commercial Real Estate Valuation ($) | K3: Print | L3: 0
B5: Pro Forma Rent Build
C7: FY25 | D7: NNN | E7: Low-End | F7: High-End
B8: Base Rent | C8: =+'Tennant View'!C33 -> 60900 | D8: =C8 -> 60900 | E8: =+C19*C65 -> 95050 | F8: =+C65*C20 -> 135450
B9: (+) NNN Rent | C9: 0 | D9: =C38 -> 26750 | E9: =D9 -> 26750 | F9: =E9 -> 26750
B10: Total Rent | C10: =+C8+C9 -> 60900 | D10: =+D8+D9 -> 87650 | E10: =+E8+E9 -> 121800 | F10: =+F8+F9 -> 162200
B11: (-) Corporate NNN | C11: =-C38 -> -26750 | D11: =C11 -> -26750 | E11: =D11 -> -26750 | F11: =E11 -> -26750
B12: (-) Corporate Expenses | C12: =-C53 -> -9235 | D12: =C12 -> -9235 | E12: =D12 -> -9235 | F12: =E12 -> -9235
B13: NOI | C13: =SUM(C10:C12) -> 24915 | D13: =SUM(D10:D12) -> 51665 | E13: =SUM(E10:E12) -> 85815 | F13: =SUM(F10:F12) -> 126215
C15: Estimated Pro Forma Rent Build
C16: Base Rent | D16: Insurance | E16: Taxes | F16: CAM | G16: Utilities | H16: Total Rent
B17: Current (FY25) Rent | C17: =+'Market Rent Analysis'!$C$8 -> 7.25 | D17: 0 | E17: 0 | F17: 0 | G17: 0 | H17: =SUM(C17:G17) -> 7.25
B18: NNN Rent | C18: =+'Market Rent Analysis'!$C$8 -> 7.25 | D18: =+D34 -> 0.5952381 | E18: =+D35 -> 1.2797619 | F18: =+D36 -> 0.5952381 | G18: =+D37 -> 0.71428571 | H18: =SUM(C18:G18) -> 10.434524
B19: NNN + Low-End Rent | C19: =+'Sensitivity Analysis'!J23-'CRE P&L'!D38 -> 11.315476 | D19: =D18 -> 0.5952381 | E19: =E18 -> 1.2797619 | F19: =F18 -> 0.5952381 | G19: =G18 -> 0.71428571 | H19: =SUM(C19:G19) -> 14.5
B20: NNN + Base-Rate Rent | C20: =+'Market Rent Analysis'!G25 -> 16.125 | D20: =D19 -> 0.5952381 | E20: =E19 -> 1.2797619 | F20: =F19 -> 0.5952381 | G20: =G19 -> 0.71428571 | H20: =SUM(C20:G20) -> 19.309524
C22: Actual Pro Forma Rent Build
C23: Base Rent | D23: Insurance | E23: Taxes | F23: CAM | G23: Utilities | H23: Total Rent
B24: Current (FY25) Rent | C24: =+C17 -> 7.25 | D24: 0 | E24: 0 | F24: 0 | G24: 0 | H24: =SUM(C24:G24) -> 7.25
B25: Clearing Price Rent | C25: =+#REF! -> #REF! | D25: =+F34 -> 0 | E25: =+F35 -> 0 | F25: =+F36 -> 0 | G25: =+F37 -> 0 | H25: =SUM(C25:G25) -> #REF!
B26: NNN Rent | C26: =+C18 -> 7.25 | D26: =D25 -> 0 | E26: =E25 -> 0 | F26: =F25 -> 0 | G26: =G25 -> 0 | H26: =SUM(C26:G26) -> 7.25
B27: NNN + Low-End Rent | C27: =+C19 -> 11.315476 | D27: =D26 -> 0 | E27: =E26 -> 0 | F27: =F26 -> 0 | G27: =G26 -> 0 | H27: =SUM(C27:G27) -> 11.315476
B28: NNN + Base-Rate Rent | C28: =+C20 -> 16.125 | D28: =D27 -> 0 | E28: =E27 -> 0 | F28: =F27 -> 0 | G28: =G27 -> 0 | H28: =SUM(C28:G28) -> 16.125
B30: NNN Build
C32: NNN Allocation Overview
C33: Estimate | D33: Per Sq. Ft. | E33: Actuals | F33: Per Sq. Ft. | G33: Delta | H33: Per Sq. Ft.
B34: Insurance | C34: 5000 | D34: =C34/$C$65 -> 0.5952381 | F34: =E34/$C$65 -> 0 | G34: =E34-C34 -> -5000 | H34: =G34/$C$65 -> -0.5952381
B35: Taxes2 | C35: 10750 | D35: =C35/$C$65 -> 1.2797619 | F35: =E35/$C$65 -> 0 | G35: =E35-C35 -> -10750 | H35: =G35/$C$65 -> -1.2797619 | J35: Based on this calculator
B36: Maintenance / CAM | C36: 5000 | D36: =C36/$C$65 -> 0.5952381 | F36: =E36/$C$65 -> 0 | G36: =E36-C36 -> -5000 | H36: =G36/$C$65 -> -0.5952381
B37: Utilities | C37: 6000 | D37: =C37/$C$65 -> 0.71428571 | F37: =E37/$C$65 -> 0 | G37: =E37-C37 -> -6000 | H37: =G37/$C$65 -> -0.71428571 | J37: Make sure this is allocated to laundromat in accordance with usage
B38: Total NNN Charges | C38: =SUM(C34:C37) -> 26750 | D38: =SUM(D34:D37) -> 3.1845238 | E38: =SUM(E34:E37) -> 0 | F38: =SUM(F34:F37) -> 0 | G38: =SUM(G34:G37) -> -26750 | H38: =SUM(H34:H37) -> -3.1845238
B39: 2) Depends on go-forward tax basis
B41: Corporate Expense Build
C43: CRE Corporate Expense Overview
C44: Estimate | D44: Per Sq. Ft. | E44: Actuals | F44: Per Sq. Ft. | G44: Delta | H44: Per Sq. Ft.
B45: Vacancy Allowance | C45: =C56*C57 -> 3045 | D45: =C45/$C$65 -> 0.3625 | F45: =E45/$C$65 -> 0 | G45: =E45-C45 -> -3045 | H45: =G45/$C$65 -> -0.3625
B46: Property Management Fee | C46: =+C58 -> 0 | D46: =C46/$C$65 -> 0 | E46: 0 | F46: =E46/$C$65 -> 0 | G46: =E46-C46 -> 0 | H46: =G46/$C$65 -> 0
B47: Capital Reserves | C47: =C59*$C$65 -> 1680 | D47: =C47/$C$65 -> 0.2 | F47: =E47/$C$65 -> 0 | G47: =E47-C47 -> -1680 | H47: =G47/$C$65 -> -0.2
B48: TI Reserves | C48: =C60*$C$65 -> 1260 | D48: =C48/$C$65 -> 0.15 | F48: =E48/$C$65 -> 0 | G48: =E48-C48 -> -1260 | H48: =G48/$C$65 -> -0.15
B49: Non-NNN Owner Insurance | C49: =+C61 -> 2500 | D49: =C49/$C$65 -> 0.29761905 | F49: =E49/$C$65 -> 0 | G49: =E49-C49 -> -2500 | H49: =G49/$C$65 -> -0.29761905
B50: Entity-Level Tax | C50: =+C62 -> 750 | D50: =C50/$C$65 -> 0.089285714 | F50: =E50/$C$65 -> 0 | G50: =E50-C50 -> -750 | H50: =G50/$C$65 -> -0.089285714
B51: Entity-Level Accounting | C51: =+C63 -> 0 | D51: =C51/$C$65 -> 0 | F51: =E51/$C$65 -> 0 | G51: =E51-C51 -> 0 | H51: =G51/$C$65 -> 0
B52: Maintenance Shortfall | C52: =+C64 -> 0 | D52: =C52/$C$65 -> 0 | F52: =E52/$C$65 -> 0 | G52: =E52-C52 -> 0 | H52: =G52/$C$65 -> 0
B53: Total Corporate Costs | C53: =SUM(C45:C52) -> 9235 | D53: =SUM(D45:D52) -> 1.0994048 | E53: =SUM(E45:E52) -> 0 | F53: =SUM(F45:F52) -> 0 | G53: =SUM(G45:G52) -> -9235 | H53: =SUM(H45:H52) -> -1.0994048
C55: Input | D55: Notes
B56: Current Gross Rent | C56: =+'Tennant View'!C33 -> 60900 | D56: As of 2025
B57: Vacancy Allowance | C57: 0.05 | D57: % of gross rent
B58: Property Management Fee | C58: 0 | D58: Taken from current property manager
B59: Capital Reserves | C59: 0.2 | D59: % of leasable sq. ft. | J59: Exclude laundromat?
B60: TI Reserves | C60: 0.15 | D60: % of leasable sq. ft. | J60: Exclude laundromat?
B61: Non-NNN Owner Insurance | C61: 2500 | D61: % per year
B62: Entity-Level Tax | C62: 750 | D62: Assumes $750 for annual corporate taxes
B63: Entity-Level Accounting | C63: 0 | D63: Could assume $100 per month for financials
B64: Maintenance Shortfall | C64: 0 | D64: % per year
B65: Total Usable Sq. Ft. | C65: =+'Market Rent Analysis'!$C$7 -> 8400
C75: FY25 | D75: Clearing | E75: NNN | F75: Low-End | G75: Base-Rate
B77: =+'Tennant View'!B23 -> Total Current Rent | C77: =+'Tennant View'!C33 -> 60900 | D77: =D92-D36-D80 -> 83422.405 | E77: =+'Tennant View'!C33-$C$34-$N$35-$C$37 -> 49900 | F77: =+'Market Rent Analysis'!C48-$C$34-$N$35-$C$37 -> 56200 | G77: =+'Market Rent Analysis'!D48-$C$34-$N$35-$C$37 -> 73000
B80: (-) Property Management | C80: -3423 | D80: =C80 -> -3423 | E80: =C80 -> -3423 | F80: =E80 -> -3423 | G80: =F80 -> -3423
B83: Net Operating Income | C83: =SUM(C77:C82) -> 57477 | D83: =SUM(D77:D82) -> 79999.405 | E83: =SUM(E77:E82) -> 46477 | F83: =SUM(F77:F82) -> 52777 | G83: =SUM(G77:G82) -> 69577
B87: =+B83 -> Net Operating Income | C87: =+C83 -> 57477 | D87: =+D83 -> 79999.405 | E87: =+E83 -> 46477 | F87: =+F83 -> 52777 | G87: =+G83 -> 69577
B88: (/) Prior Transaction Value | C88: 580000 | D88: =C88 -> 580000 | E88: =C88 -> 580000 | F88: =E88 -> 580000 | G88: =F88 -> 580000
B89: Implied Cap Rate | C89: =C87/C88 -> 0.099098276 | D89: =D87/D88 -> 0.13793001 | E89: =E87/E88 -> 0.080132759 | F89: =F87/F88 -> 0.090994828 | G89: =G87/G88 -> 0.11996034
C91: =+C75 -> FY25 | D91: =+D75 -> Clearing | E91: =+E75 -> NNN | F91: =+F75 -> Low-End | G91: =+G75 -> Base-Rate
B92: Pro Forma NOI | C92: =+C83 -> 57477 | D92: =D94*D93 -> 80000 | E92: =+E83 -> 46477 | F92: =+F83 -> 52777 | G92: =+G83 -> 69577
B93: (/) Estimated Cap Rate | C93: 0.08 | D93: =C93 -> 0.08 | E93: =C93 -> 0.08 | F93: =E93 -> 0.08 | G93: =F93 -> 0.08
B94: Implied Valuation | C94: =C92/C93 -> 718462.5 | D94: 1000000 | E94: =E92/E93 -> 580962.5 | F94: =F92/F93 -> 659712.5 | G94: =G92/G93 -> 869712.5

Sheet Market Rent Analysis
B2: =+Cover!B24 -> Sunshine Commercial Investments
B3: CRE Market Rent Analysis ($)
K4: Print | L4: 1
B5: Current Rent / Sq. Ft.
B6: =+'Tennant View'!B23 -> Total Current Rent | C6: =+'Tennant View'!C33 -> 60900
B7: Total Leasable Square Footage | C7: 8400
B8: Current Rent / Sq. Ft. | C8: =C6/C7 -> 7.25
B10: Property | C10: City | D10: Size (SF) | E10: Built | F10: Type | G10: Base Rent | H10: NNN Rate | I10: Total Rent
B11: 2115 W 9 Mile Rd | C11: Pensacola | D11: 800 | E11: 1998 | F11: Retail | G11: 19.5 | H11: 4.97 | I11: 24.47 | N11: 2115 W 9 Mile Rd
B12: 4628 Summerdale Blvd | C12: Pace | D12: 1062 | E12: 2004 | F12: Office | G12: 18.5 | H12: - | I12: - | N12: 4628 Summerdale Blvd
B13: 6317–6327 Dogwood Dr | C13: Milton | D13: 1291 | E13: 2004 | F13: Retail/flex | G13: 18 | H13: 2.93 | I13: =G13+H13 -> 20.93 | N13: 6317–6327 Dogwood Dr
B14: 5118 Canal St | C14: Milton | D14: 3110 | E14: 1951 | F14: Retail | G14: 18 | H14: - | I14: - | N14: 5118 Canal St
B15: 5700 N Davis Hwy | C15: Pensacola | D15: 1452 | E15: 1987 | F15: Retail | G15: 17.5 | H15: 3.5 | I15: =G15+H15 -> 21 | N15: 5700 N Davis Hwy
B16: 7000 Pine Forest Rd | C16: Pensacola | D16: 1200 | E16: 1990 | F16: Retail | G16: 16.5 | H16: - | I16: - | N16: 7000 Pine Forest Rd
B17: Quietwater Bldg 1 Suite 360 | C17: Gulf Breeze | D17: 1861 | E17: 1985 | F17: Office | G17: 16 | H17: - | I17: - | N17: Quietwater Bldg 1 Suite 360
B18: 5022 W Fairfield Dr | C18: Pensacola | D18: 1100 | E18: 2004 | F18: Office | G18: 16 | H18: 4.5 | I18: 20.5 | N18: 5022 W Fairfield Dr
B19: 275 W Airport Blvd | C19: Pensacola | D19: 3600 | E19: 1995 | F19: Retail | G19: 15.25 | H19: 4 | I19: =H19+G19 -> 19.25 | N19: 275 W Airport Blvd
B20: 4848 Ward Basin Rd | C20: Milton | D20: 2147 | E20: 1960 | F20: Office/Retail | G20: 15 | H20: 2.25 | I20: =G20+H20 -> 17.25 | N20: 4848 Ward Basin Rd
B21: 8602-8612 Pensacola Blvd | C21: Pensacola | D21: 1300 | E21: 1974 | F21: Retail | G21: 14.5 | H21: - | I21: - | N21: 8602-8612 Pensacola Blvd
B22: 4455-4497 Mobile Hwy | C22: Pensacola | D22: 7800 | E22: 1985 | F22: Retail | G22: 14 | H22: 4.5 | I22: =+H22+G22 -> 18.5 | N22: 4455-4497 Mobile Hwy
B23: 3620-3642 Barrancas Ave | C23: Pensacola | D23: 900 | E23: 1952 | F23: Retail | G23: 13.5 | H23: 3.75 | I23: =+H23+G23 -> 17.25 | N23: 3620-3642 Barrancas Ave
B24: 3960 W Navy Blvd | C24: Pensacola | D24: 1300 | E24: 1984 | F24: Retail | G24: 13.5 | H24: 3 | I24: 16.5 | N24: 3960 W Navy Blvd
B25: Average | G25: =AVERAGE(G11:G24) -> 16.125 | H25: =AVERAGE(H11:H24) -> 3.7111111 | I25: =AVERAGE(I11:I24) -> 19.516667
B26: Target Property | C26: Milton | D26: =+C7 -> 8400 | E26: 1965 | F26: Retail | G26: 7.25 | H26: 0 | I26: 7.25
B28: Implied Upside ($000s)
C30: Current | D30: Pro Forma
C31: Total Rent | D31: Base Rent | E31: Total Rent
B32: Annual Rental Income | C32: =+C6/1000 -> 60.9 | D32: =$C$32*(1+D$33) -> 135.45 | E32: =$C$32*(1+E$33) -> 163.94
B33: % Increase | D33: =G25/G26-1 -> 1.2241379 | E33: =I25/I26-1 -> 1.691954
G37: 1000
G38: =G37/20 -> 50
B39: Market Rent Analysis | G39: =G37*0.065 -> 65 | AB39: Source
B40: Low-End Rate | C40: 8 | G40: =+G39+G38 -> 115
B41: Base-Rate | C41: 10
B42: High-End Rate | C42: 14
C44: Low-End | D44: Base-Rate
B45: Implied Annual Rent Calculation
B46: Estimated Rent / Sq. Ft | C46: =+'Market Rent Analysis'!C40 -> 8 | D46: =+'Market Rent Analysis'!C41 -> 10
B47: (x) Leasable Sq. Ft. | C47: =+'Market Rent Analysis'!C7 -> 8400 | D47: =C47 -> 8400
B48: Implied Annual Rent | C48: =C46*C47 -> 67200 | D48: =D46*D47 -> 84000
B49: % Increase | C49: =C48/'Market Rent Analysis'!$C$6-1 -> 0.10344828 | D49: =D48/'Market Rent Analysis'!$C$6-1 -> 0.37931034
B53: Property | C53: City | D53: State | E53: Size (SF) | F53: Built | G53: Type | H53: Base Rent | I53: NNN Rate | J53: Total Rent
B54: 50 S Blue Angel Pky | C54: Pensacola | D54: Florida | E54: 26000 | F54: 1998 | G54: Storefront | H54: - | I54: - | J54: 10
B55: 8165 Progress Dr | C55: Milton | D55: Florida | E55: 23800 | F55: 1998 | G55: Retail | H55: - | I55: - | J55: 9.07
B56: 5941 Berryhill Road | C56: Milton | D56: Florida | E56: 17147 | F56: 2004 | G56: Retail | H56: - | I56: - | J56: 20.25
B57: 1421 E Nine Mile Rd | C57: Pensacola | D57: 4380 | E57: 2000 | F57: Medical | I57: 19.5

Sheet Tennant View
B2: =+Cover!B24 -> Sunshine Commercial Investments
B3: Commercial Real Estate Valuation ($) | K3: Print | L3: 0
B5: CRE Rent Overview
C7: Rent / Sq. Ft. For Each Scenario
C8: FY25 | D8: Clearing | E8: NNN | F8: Low-End | G8: Base-Rate
B9: Base Rent / Sq. Ft. | C9: =+'CRE P&L'!C17 -> 7.25 | E9: =+'CRE P&L'!C17 -> 7.25
B10: NNN Rent / Sq. Ft. | C10: 0 | E10: =+'CRE P&L'!D38 -> 3.1845238 | F10: =E10 -> 3.1845238 | G10: =F10 -> 3.1845238
B11: Total Rent / Sq. Ft. | C11: =SUM(C9:C10) -> 7.25 | D11: =SUM(D9:D10) -> 0 | E11: =SUM(E9:E10) -> 10.434524 | F11: =SUM(F9:F10) -> 3.1845238 | G11: =SUM(G9:G10) -> 3.1845238
B13: Total Rent Increase | C13: ='CRE P&L'!C77/'CRE P&L'!$C$77-1 -> 0 | D13: ='CRE P&L'!D77/'CRE P&L'!$C$77-1 -> 0.36982602 | E13: ='CRE P&L'!E77/'CRE P&L'!$C$77-1 -> -0.18062397 | F13: ='CRE P&L'!F77/'CRE P&L'!$C$77-1 -> -0.077175698 | G13: ='CRE P&L'!G77/'CRE P&L'!$C$77-1 -> 0.19868637
C15: Total Monthly Rent (Base + NNN)
C16: FY25 | D16: Clearing | E16: NNN | F16: Low-End | G16: Base-Rate
B18: Community Theater | C18: 1800 | G18: =C18*(1+$G$13) -> 2157.6355
B19: Laundromat | C19: 1200 | G19: =C19*(1+$G$13) -> 1438.4236
B20: Turnaround Testron* | C20: 775 | G20: =C20*(1+$G$13) -> 928.98194 | K20: Make sure this is allocated to laundromat in accordance with usage
B21: Consignment Shop | C21: 700 | G21: =C21*(1+$G$13) -> 839.08046
B22: Book Store | C22: 600 | G22: =C22*(1+$G$13) -> 719.21182
B23: Total Current Rent | C23: =SUM(C18:C22) -> 5075 | D23: =SUM(D18:D22) -> 0 | E23: =SUM(E18:E22) -> 0 | F23: =SUM(F18:F22) -> 0 | G23: =SUM(G18:G22) -> 6083.3333
C25: Total Annual Rent (Base + NNN)
C26: FY25 | D26: Clearing | E26: NNN | F26: Low-End | G26: Base-Rate
B28: Community Theater | C28: =C18*12 -> 21600 | G28: =G18*12 -> 25891.626
B29: Laundromat | C29: =C19*12 -> 14400 | G29: =G19*12 -> 17261.084
B30: Turnaround Testron* | C30: =C20*12 -> 9300 | G30: =G20*12 -> 11147.783
B31: Consignment Shop | C31: =C21*12 -> 8400 | G31: =G21*12 -> 10068.966
B32: Book Store | C32: =C22*12 -> 7200 | G32: =G22*12 -> 8630.5419
B33: Total Current Rent | C33: =SUM(C28:C32) -> 60900 | D33: =SUM(D28:D32) -> 0 | E33: =SUM(E28:E32) -> 0 | F33: =SUM(F28:F32) -> 0 | G33: =G23*12 -> 73000
B34: 1) Cannot verify through Google Maps -- appears to be Carrie’s Beauty Salon
B36: Breakdown base rent vs. the triple net cost allocation to each tennant

Sheet Valuation Overview
B2: =+Cover!B24 -> Sunshine Commercial Investments
B3: Valuation Overview ($000s) | H3: Print | I3: 1
C5: Current Valuation | D5: Clearing Price | E5: NNN Valuation | F5: Base-Rate Valuation
B7: Laundromat | C7: =ROUND(+'Laundromat Valuation'!F53,-2) -> 500 | D7: =C7 -> 500 | E7: =C7 -> 500 | F7: =E7 -> 500
B8: Commercial Real Estate | C8: =+'CRE P&L'!C94/1000 -> 718.4625 | D8: =+'CRE P&L'!D94/1000 -> 1000 | E8: =+'CRE P&L'!E94/1000 -> 580.9625 | F8: =+'CRE P&L'!F94/1000 -> 659.7125
B9: Total Valuation | C9: =+C8+C7 -> 1218.4625 | D9: =+D8+D7 -> 1500 | E9: =+E8+E7 -> 1080.9625 | F9: =+F8+F7 -> 1159.7125
B10: (-) Asking Price | C10: -1600 | D10: =C10 -> -1600 | E10: =C10 -> -1600 | F10: =E10 -> -1600
B11: Delta | C11: =+C9+C10 -> -381.5375 | D11: =+D9+D10 -> -100 | E11: =+E9+E10 -> -519.0375 | F11: =+F9+F10 -> -440.2875
B13: Annual Rent Impact
C15: =+C$5 -> Current Valuation | D15: =+D$5 -> Clearing Price | E15: =+E$5 -> NNN Valuation | F15: =+F$5 -> Base-Rate Valuation
B17: =+'Tennant View'!B18 -> Community Theater | C17: =+'Tennant View'!C28/1000 -> 21.6 | D17: =D$22*$H17 -> 29.588242 | E17: =E$22*$H17 -> 17.698522 | F17: =F$22*$H17 -> 25.891626 | H17: =C17/$C$22 -> 0.3546798
B18: =+'Tennant View'!B19 -> Laundromat | C18: =+'Tennant View'!C29/1000 -> 14.4 | D18: =D$22*$H18 -> 19.725495 | E18: =E$22*$H18 -> 11.799015 | F18: =F$22*$H18 -> 17.261084 | H18: =C18/$C$22 -> 0.2364532
B19: =+'Tennant View'!B20 -> Turnaround Testron* | C19: =+'Tennant View'!C30/1000 -> 9.3 | D19: =D$22*$H19 -> 12.739382 | E19: =E$22*$H19 -> 7.620197 | F19: =F$22*$H19 -> 11.147783 | H19: =C19/$C$22 -> 0.15270936
B20: =+'Tennant View'!B21 -> Consignment Shop | C20: =+'Tennant View'!C31/1000 -> 8.4 | D20: =D$22*$H20 -> 11.506539 | E20: =E$22*$H20 -> 6.8827586 | F20: =F$22*$H20 -> 10.068966 | H20: =C20/$C$22 -> 0.13793103
B21: =+'Tennant View'!B22 -> Book Store | C21: =+'Tennant View'!C32/1000 -> 7.2 | D21: =D$22*$H21 -> 9.8627474 | E21: =E$22*$H21 -> 5.8995074 | F21: =F$22*$H21 -> 8.6305419 | H21: =C21/$C$22 -> 0.1182266
B22: Total Annual Rent | C22: =SUM(C17:C21) -> 60.9 | D22: =+'CRE P&L'!D77/1000 -> 83.422405 | E22: =+'CRE P&L'!E77/1000 -> 49.9 | F22: =+'CRE P&L'!G77/1000 -> 73
B23: % Increase | D23: =D22/$C$22-1 -> 0.36982602 | E23: =E22/$C$22-1 -> -0.18062397 | F23: =F22/$C$22-1 -> 0.19868637
B25: Monthly Rent Impact
C27: =+C$5 -> Current Valuation | D27: =+D$5 -> Clearing Price | E27: =+E$5 -> NNN Valuation | F27: =+F$5 -> Base-Rate Valuation
B29: =+B17 -> Community Theater | C29: =+'Tennant View'!C18 -> 1800 | D29: =D$34*$H29 -> 2465.6868 | E29: =E$34*$H29 -> 1474.8768 | F29: =F$34*$H29 -> 2157.6355 | H29: =C29/$C$34 -> 0.3546798
B30: =+B18 -> Laundromat | C30: =+'Tennant View'!C19 -> 1200 | D30: =D$34*$H30 -> 1643.7912 | E30: =E$34*$H30 -> 983.25123 | F30: =F$34*$H30 -> 1438.4236 | H30: =C30/$C$34 -> 0.2364532
B31: =+B19 -> Turnaround Testron* | C31: =+'Tennant View'!C20 -> 775 | D31: =D$34*$H31 -> 1061.6152 | E31: =E$34*$H31 -> 635.01642 | F31: =F$34*$H31 -> 928.98194 | H31: =C31/$C$34 -> 0.15270936
B32: =+B20 -> Consignment Shop | C32: =+'Tennant View'!C21 -> 700 | D32: =D$34*$H32 -> 958.87822 | E32: =E$34*$H32 -> 573.56322 | F32: =F$34*$H32 -> 839.08046 | H32: =C32/$C$34 -> 0.13793103
B33: =+B21 -> Book Store | C33: =+'Tennant View'!C22 -> 600 | D33: =D$34*$H33 -> 821.89561 | E33: =E$34*$H33 -> 491.62562 | F33: =F$34*$H33 -> 719.21182 | H33: =C33/$C$34 -> 0.1182266
B34: Total Monthly Rent | C34: =SUM(C29:C33) -> 5075 | D34: =+D22/12*1000 -> 6951.8671 | E34: =+E22/12*1000 -> 4158.3333 | F34: =+F22/12*1000 -> 6083.3333
B35: % Increase | D35: =D34/$C$34-1 -> 0.36982602 | E35: =E34/$C$34-1 -> -0.18062397 | F35: =F34/$C$34-1 -> 0.19868637
C72: Valuation | D72: % Delta | E72: % Delta
B73: Prior Transaction Consideration | C73: 580000
B74: County Cost-Approach | C74: 435734
B75: Precedent Transactions
B76: Average Valuation
B78: Income Capitalization Approach
B80: 2024 Net Income | C80: 128331
B81: Mortgage Interest | C81: 14670
B82: Total Earnings | C82: =+C80+C81 -> 143001
C83: 3
B84: Implied Valuation | C84: =C82*C83 -> 429003
B85: Less Accumulated Depreciation
B90: Depreciation | C90: 28555
