Workbook

Sheet Assumptions
A1: Corsair Plaza — Key Assumptions
A2: 5400 Dogwood Dr / 6416 Park Ave NW, Milton, FL | Yellow cells are illustrative placeholders — replace with actual figures as leases and reserve requirements firm up.
A4: Assumption | B4: Value | C4: Notes
A5: Vacancy & Credit Loss (% of Gross Rent) | B5: 0.05 | C5: Applied against gross rent even at full current occupancy, per typical lender underwriting convention
A6: Property Management Fee (% of EGI) | B6: 0.06 | C6: Standard market range 4%–8%; typically NOT reimbursable by tenants even under a NNN structure
A7: Capital Reserves ($ / sq ft / yr — NNN units) | B7: 0.2 | C7: Roof, HVAC, parking lot resurfacing; ServisFirst will likely require an underwritten reserve
A8: TI / Leasing Commission Reserve ($ / sq ft / yr — NNN units) | B8: 0.15 | C8: Reserve for future re-leasing risk across the 4 NNN suites
A9: Non-Reimbursed Owner Insurance ($ / yr) | B9: 2500 | C9: Umbrella / excess liability carried by landlord beyond tenant-billed premium
A10: Entity-Level Legal & Accounting ($ / yr) | B10: 3500 | C10: Corsair Plaza LLC bookkeeping/tax prep — not billable to tenants
A11: CAM / Tax / Insurance Gross-Up or Cap Shortfall ($ / yr) | B11: 0 | C11: Set > 0 if executed leases include a CAM cap; landlord absorbs any overage above the cap

Sheet Rent Roll
A1: Corsair Plaza — Rent Roll
A2: ILLUSTRATIVE PLACEHOLDER FIGURES — no leases are executed yet. Replace blue cells with actual terms as each NNN lease is signed.
A4: Suite / Tenant | B4: Type | C4: Sq Ft | D4: Annual Base Rent | E4: Taxes Reimb. | F4: Insurance Reimb. | G4: CAM Reimb. | H4: Total NNN Reimb. | I4: Total Annual Rent | J4: Lease Status
A5: Tenant 1 (Suite ___) | B5: NNN Tenant | C5: 1200 | D5: 18000 | E5: 2400 | F5: 1200 | G5: 3600 | H5: =SUM(E5:G5) -> 7200 | I5: =D5+H5 -> 25200 | J5: Not Executed
A6: Tenant 2 (Suite ___) | B6: NNN Tenant | C6: 1000 | D6: 15000 | E6: 2000 | F6: 1000 | G6: 3000 | H6: =SUM(E6:G6) -> 6000 | I6: =D6+H6 -> 21000 | J6: Not Executed
A7: Tenant 3 (Suite ___) | B7: NNN Tenant | C7: 900 | D7: 13500 | E7: 1800 | F7: 900 | G7: 2700 | H7: =SUM(E7:G7) -> 5400 | I7: =D7+H7 -> 18900 | J7: Not Executed
A8: Tenant 4 (Suite ___) | B8: NNN Tenant | C8: 1100 | D8: 16500 | E8: 2200 | F8: 1100 | G8: 3300 | H8: =SUM(E8:G8) -> 6600 | I8: =D8+H8 -> 23100 | J8: Not Executed
A9: Laundromat (Quik Wash CL LLC) | B9: Owner-Operated | C9: 2800 | D9: N/A — see NOI Bridge tab (Schedule C / SDE basis) | E9: N/A — see NOI Bridge tab (Schedule C / SDE basis) | F9: N/A — see NOI Bridge tab (Schedule C / SDE basis) | G9: N/A — see NOI Bridge tab (Schedule C / SDE basis) | H9: N/A — see NOI Bridge tab (Schedule C / SDE basis) | I9: N/A — see NOI Bridge tab (Schedule C / SDE basis) | J9: Owner-Operated
A11: TOTAL — NNN Units Only (Tenants 1–4) | C11: =SUM(C5:C8) -> 4200 | D11: =SUM(D5:D8) -> 63000 | E11: =SUM(E5:E8) -> 8400 | F11: =SUM(F5:F8) -> 4200 | G11: =SUM(G5:G8) -> 12600 | H11: =SUM(H5:H8) -> 25200 | I11: =SUM(I5:I8) -> 88200
A12: TOTAL GLA — All 5 Units (incl. Laundromat) | C12: =C11+C9 -> 7000
A14: Legend: Blue text on yellow fill = fill in with actual lease terms. Black text = calculated automatically.

Sheet NOI Bridge
A1: Corsair Plaza — Rent Roll to NOI Bridge
A2: All figures flow from the Rent Roll and Assumptions tabs — update those, not the numbers here.
A4: SECTION 1 — NNN UNITS (Tenants 1–4)
A5: Total Scheduled Rent (Base + NNN Reimbursements) | B5: ='Rent Roll'!I11 -> 88200
A6: Less: Vacancy & Credit Loss | B6: =-B5*Assumptions!$B$5 -> -4410
A7: → Effective Gross Income (EGI) | B7: =B5+B6 -> 83790
A9: Less: Operating Expenses Not Recoverable from Tenants
A10: Property Management Fee | B10: =-B7*Assumptions!$B$6 -> -5027.4
A11: Non-Reimbursed Owner Insurance | B11: =-Assumptions!$B$9 -> -2500
A12: Entity-Level Legal & Accounting | B12: =-Assumptions!$B$10 -> -3500
A13: CAM / Tax / Insurance Gross-Up Shortfall | B13: =-Assumptions!$B$11 -> 0
A14: → NOI — NNN Units (Before Reserves) | B14: =B7+B10+B11+B12+B13 -> 72762.6
A16: Less: Capital Reserves | B16: =-'Rent Roll'!C11*Assumptions!$B$7 -> -840
A17: Less: TI / Leasing Commission Reserves | B17: =-'Rent Roll'!C11*Assumptions!$B$8 -> -630
A18: → Cash Flow Before Debt Service — NNN Units | B18: =B14+B16+B17 -> 71292.6
A20: SECTION 2 — LAUNDROMAT (OWNER-OPERATED UNIT)
A21: Not a NNN tenant — no lease, no rent roll income. Its economics run through the business's own Schedule C, so it should be valued on a Seller's Discretionary Earnings (SDE) basis, not blended into the NNN units' cap-rate-based NOI. Confirm the Schedule C insurance-expense anomaly before relying on this figure.
A22: Laundromat Sq Ft | B22: ='Rent Roll'!C9 -> 2800
A23: Reported Schedule C Net Income | B23: 45000
A24: + Owner Addbacks (D&A, Owner Comp, One-Time Items) | B24: 18000
A25: → Seller's Discretionary Earnings (SDE) — Laundromat | B25: =B23+B24 -> 63000
A27: SECTION 3 — COMBINED PROPERTY-LEVEL SUMMARY
A28: NOI — NNN Units (Before Reserves) | B28: =B14 -> 72762.6
A29: Cash Flow Before Debt Service — NNN Units | B29: =B18 -> 71292.6
A30: Laundromat SDE (Separate Valuation Track) | B30: =B25 -> 63000
A32: Do not sum these onto one blended NOI and apply a single cap rate. Value the CRE (NNN units) at a market cap rate and the laundromat business separately at an SDE multiple, then combine the two resulting values — or confirm with Monica how Sunshine Commercial Investments wants the combined deal structured.
