Workbook

Sheet Cover
B24: Keystone Bookkeepers
B25: Initial Financial Review
B26: ="As of "&TEXT(TODAY(),"mm/dd/yy") -> As of 09/03/26

Sheet P&L Overview
B2: =+Cover!B24 -> Keystone Bookkeepers
B3: Summary P&L Overview ($000s)
B5: P&L Summary ($000s) | C5: FY2024 | D5: FY2025 | F5: July'25 YTD | G5: July'26 YTD | I5: Jul'25 LTM | J5: Jul'26 LTM | L5: 45292 | M5: =EOMONTH(L5,0)+1 -> 45323 | N5: =EOMONTH(M5,0)+1 -> 45352 | O5: =EOMONTH(N5,0)+1 -> 45383 | P5: =EOMONTH(O5,0)+1 -> 45413 | Q5: =EOMONTH(P5,0)+1 -> 45444 | R5: =EOMONTH(Q5,0)+1 -> 45474 | S5: =EOMONTH(R5,0)+1 -> 45505 | T5: =EOMONTH(S5,0)+1 -> 45536 | ... AP5: =EOMONTH(AO5,0)+1 -> 46204
B6: Revenue
B7: STR Subscription | C7: =SUMIFS($L7:$AP7,$L$5:$AP$5,">"&C$42,$L$5:$AP$5,"<"&C$43) -> 793.47225 | D7: =SUMIFS($L7:$AP7,$L$5:$AP$5,">"&D$42,$L$5:$AP$5,"<"&D$43) -> 1450.4923 | F7: =SUMIFS($L7:$AP7,$L$5:$AP$5,">"&F$42,$L$5:$AP$5,"<"&F$43) -> 751.5286 | G7: =SUMIFS($L7:$AP7,$L$5:$AP$5,">"&G$42,$L$5:$AP$5,"<"&G$43) -> 1261.4769 | I7: =SUMIFS($L7:$AP7,$L$5:$AP$5,">"&I$42,$L$5:$AP$5,"<"&I$43) -> 1098.5075 | J7: =SUMIFS($L7:$AP7,$L$5:$AP$5,">"&J$42,$L$5:$AP$5,"<"&J$43) -> 1881.6971 | L7: =SUMIFS('Combined P&L'!N:N,'Combined P&L'!$C:$C,'P&L Overview'!$B7) -> 44.6835 | M7: =SUMIFS('Combined P&L'!O:O,'Combined P&L'!$C:$C,'P&L Overview'!$B7) -> 47.046 | N7: =SUMIFS('Combined P&L'!P:P,'Combined P&L'!$C:$C,'P&L Overview'!$B7) -> 52.47 | O7: =SUMIFS('Combined P&L'!Q:Q,'Combined P&L'!$C:$C,'P&L Overview'!$B7) -> 57.1697 | P7: =SUMIFS('Combined P&L'!R:R,'Combined P&L'!$C:$C,'P&L Overview'!$B7) -> 57.51415 | Q7: =SUMIFS('Combined P&L'!S:S,'Combined P&L'!$C:$C,'P&L Overview'!$B7) -> 65.516 | R7: =SUMIFS('Combined P&L'!T:T,'Combined P&L'!$C:$C,'P&L Overview'!$B7) -> 68.28125 | S7: =SUMIFS('Combined P&L'!U:U,'Combined P&L'!$C:$C,'P&L Overview'!$B7) -> 73.25135 | T7: =SUMIFS('Combined P&L'!V:V,'Combined P&L'!$C:$C,'P&L Overview'!$B7) -> 75.5517 | U7: =SUMIFS('Combined P&L'!W:W,'Combined P&L'!$C:$C,'P&L Overview'!$B7) -> 79.11325 | V7: =SUMIFS('Combined P&L'!X:X,'Combined P&L'!$C:$C,'P&L Overview'!$B7) -> 83.2908 | W7: =SUMIFS('Combined P&L'!Y:Y,'Combined P&L'!$C:$C,'P&L Overview'!$B7) -> 89.58455 | X7: =SUMIFS('Combined P&L'!Z:Z,'Combined P&L'!$C:$C,'P&L Overview'!$B7) -> 92.4189 | Y7: =SUMIFS('Combined P&L'!AA:AA,'Combined P&L'!$C:$C,'P&L Overview'!$B7) -> 94.00215 | Z7: =SUMIFS('Combined P&L'!AB:AB,'Combined P&L'!$C:$C,'P&L Overview'!$B7) -> 101.50605 | AA7: =SUMIFS('Combined P&L'!AC:AC,'Combined P&L'!$C:$C,'P&L Overview'!$B7) -> 106.1375 | AB7: =SUMIFS('Combined P&L'!AD:AD,'Combined P&L'!$C:$C,'P&L Overview'!$B7) -> 115.93875 | AC7: =SUMIFS('Combined P&L'!AE:AE,'Combined P&L'!$C:$C,'P&L Overview'!$B7) -> 119.43125 | AD7: =SUMIFS('Combined P&L'!AF:AF,'Combined P&L'!$C:$C,'P&L Overview'!$B7) -> 122.094 | AE7: =SUMIFS('Combined P&L'!AG:AG,'Combined P&L'!$C:$C,'P&L Overview'!$B7) -> 130.08525 | AF7: =SUMIFS('Combined P&L'!AH:AH,'Combined P&L'!$C:$C,'P&L Overview'!$B7) -> 133.5905 | AG7: =SUMIFS('Combined P&L'!AI:AI,'Combined P&L'!$C:$C,'P&L Overview'!$B7) -> 139.609 | AH7: =SUMIFS('Combined P&L'!AJ:AJ,'Combined P&L'!$C:$C,'P&L Overview'!$B7) -> 145.28075 | AI7: =SUMIFS('Combined P&L'!AK:AK,'Combined P&L'!$C:$C,'P&L Overview'!$B7) -> 150.39825 | AJ7: =SUMIFS('Combined P&L'!AL:AL,'Combined P&L'!$C:$C,'P&L Overview'!$B7) -> 156.5388 | AK7: =SUMIFS('Combined P&L'!AM:AM,'Combined P&L'!$C:$C,'P&L Overview'!$B7) -> 164.9034 | AL7: =SUMIFS('Combined P&L'!AN:AN,'Combined P&L'!$C:$C,'P&L Overview'!$B7) -> 170.34425 | AM7: =SUMIFS('Combined P&L'!AO:AO,'Combined P&L'!$C:$C,'P&L Overview'!$B7) -> 183.662 | AN7: =SUMIFS('Combined P&L'!AP:AP,'Combined P&L'!$C:$C,'P&L Overview'!$B7) -> 190.7844 | AO7: =SUMIFS('Combined P&L'!AQ:AQ,'Combined P&L'!$C:$C,'P&L Overview'!$B7) -> 194.4065 | AP7: =SUMIFS('Combined P&L'!AR:AR,'Combined P&L'!$C:$C,'P&L Overview'!$B7) -> 200.8375
B8: SMB Subscription | C8: =SUMIFS($L8:$AP8,$L$5:$AP$5,">"&C$42,$L$5:$AP$5,"<"&C$43) -> 224.791 | D8: =SUMIFS($L8:$AP8,$L$5:$AP$5,">"&D$42,$L$5:$AP$5,"<"&D$43) -> 149.77 | F8: =SUMIFS($L8:$AP8,$L$5:$AP$5,">"&F$42,$L$5:$AP$5,"<"&F$43) -> 90.4525 | G8: =SUMIFS($L8:$AP8,$L$5:$AP$5,">"&G$42,$L$5:$AP$5,"<"&G$43) -> 73.4185 | I8: =SUMIFS($L8:$AP8,$L$5:$AP$5,">"&I$42,$L$5:$AP$5,"<"&I$43) -> 174.63 | J8: =SUMIFS($L8:$AP8,$L$5:$AP$5,">"&J$42,$L$5:$AP$5,"<"&J$43) -> 135.298 | L8: =SUMIFS('Combined P&L'!N:N,'Combined P&L'!$C:$C,'P&L Overview'!$B8) -> 22.001 | M8: =SUMIFS('Combined P&L'!O:O,'Combined P&L'!$C:$C,'P&L Overview'!$B8) -> 22.036 | N8: =SUMIFS('Combined P&L'!P:P,'Combined P&L'!$C:$C,'P&L Overview'!$B8) -> 22.111 | O8: =SUMIFS('Combined P&L'!Q:Q,'Combined P&L'!$C:$C,'P&L Overview'!$B8) -> 22.146 | P8: =SUMIFS('Combined P&L'!R:R,'Combined P&L'!$C:$C,'P&L Overview'!$B8) -> 21.966 | Q8: =SUMIFS('Combined P&L'!S:S,'Combined P&L'!$C:$C,'P&L Overview'!$B8) -> 17.816 | R8: =SUMIFS('Combined P&L'!T:T,'Combined P&L'!$C:$C,'P&L Overview'!$B8) -> 17.621 | S8: =SUMIFS('Combined P&L'!U:U,'Combined P&L'!$C:$C,'P&L Overview'!$B8) -> 17.536 | T8: =SUMIFS('Combined P&L'!V:V,'Combined P&L'!$C:$C,'P&L Overview'!$B8) -> 16.426 | U8: =SUMIFS('Combined P&L'!W:W,'Combined P&L'!$C:$C,'P&L Overview'!$B8) -> 15.381 | V8: =SUMIFS('Combined P&L'!X:X,'Combined P&L'!$C:$C,'P&L Overview'!$B8) -> 14.6755 | W8: =SUMIFS('Combined P&L'!Y:Y,'Combined P&L'!$C:$C,'P&L Overview'!$B8) -> 15.0755 | X8: =SUMIFS('Combined P&L'!Z:Z,'Combined P&L'!$C:$C,'P&L Overview'!$B8) -> 14.5625 | Y8: =SUMIFS('Combined P&L'!AA:AA,'Combined P&L'!$C:$C,'P&L Overview'!$B8) -> 12.8025 | Z8: =SUMIFS('Combined P&L'!AB:AB,'Combined P&L'!$C:$C,'P&L Overview'!$B8) -> 12.4025 | AA8: =SUMIFS('Combined P&L'!AC:AC,'Combined P&L'!$C:$C,'P&L Overview'!$B8) -> 12.6025 | AB8: =SUMIFS('Combined P&L'!AD:AD,'Combined P&L'!$C:$C,'P&L Overview'!$B8) -> 12.7525 | AC8: =SUMIFS('Combined P&L'!AE:AE,'Combined P&L'!$C:$C,'P&L Overview'!$B8) -> 12.7925 | AD8: =SUMIFS('Combined P&L'!AF:AF,'Combined P&L'!$C:$C,'P&L Overview'!$B8) -> 12.5375 | AE8: =SUMIFS('Combined P&L'!AG:AG,'Combined P&L'!$C:$C,'P&L Overview'!$B8) -> 11.8575 | AF8: =SUMIFS('Combined P&L'!AH:AH,'Combined P&L'!$C:$C,'P&L Overview'!$B8) -> 12.3025 | AG8: =SUMIFS('Combined P&L'!AI:AI,'Combined P&L'!$C:$C,'P&L Overview'!$B8) -> 11.6925 | AH8: =SUMIFS('Combined P&L'!AJ:AJ,'Combined P&L'!$C:$C,'P&L Overview'!$B8) -> 11.7175 | AI8: =SUMIFS('Combined P&L'!AK:AK,'Combined P&L'!$C:$C,'P&L Overview'!$B8) -> 11.7475 | AJ8: =SUMIFS('Combined P&L'!AL:AL,'Combined P&L'!$C:$C,'P&L Overview'!$B8) -> 11.2805 | AK8: =SUMIFS('Combined P&L'!AM:AM,'Combined P&L'!$C:$C,'P&L Overview'!$B8) -> 10.9305 | AL8: =SUMIFS('Combined P&L'!AN:AN,'Combined P&L'!$C:$C,'P&L Overview'!$B8) -> 10.6255 | AM8: =SUMIFS('Combined P&L'!AO:AO,'Combined P&L'!$C:$C,'P&L Overview'!$B8) -> 10.3155 | AN8: =SUMIFS('Combined P&L'!AP:AP,'Combined P&L'!$C:$C,'P&L Overview'!$B8) -> 10.3155 | AO8: =SUMIFS('Combined P&L'!AQ:AQ,'Combined P&L'!$C:$C,'P&L Overview'!$B8) -> 9.9755 | AP8: =SUMIFS('Combined P&L'!AR:AR,'Combined P&L'!$C:$C,'P&L Overview'!$B8) -> 9.9755
B9: Occupancy Taxes | C9: =SUMIFS($L9:$AP9,$L$5:$AP$5,">"&C$42,$L$5:$AP$5,"<"&C$43) -> 0.56 | D9: =SUMIFS($L9:$AP9,$L$5:$AP$5,">"&D$42,$L$5:$AP$5,"<"&D$43) -> 55.0805 | F9: =SUMIFS($L9:$AP9,$L$5:$AP$5,">"&F$42,$L$5:$AP$5,"<"&F$43) -> 23.2255 | G9: =SUMIFS($L9:$AP9,$L$5:$AP$5,">"&G$42,$L$5:$AP$5,"<"&G$43) -> 91.65114 | I9: =SUMIFS($L9:$AP9,$L$5:$AP$5,">"&I$42,$L$5:$AP$5,"<"&I$43) -> 18.727 | J9: =SUMIFS($L9:$AP9,$L$5:$AP$5,">"&J$42,$L$5:$AP$5,"<"&J$43) -> 112.49549 | L9: =SUMIFS('Combined P&L'!N:N,'Combined P&L'!$C:$C,'P&L Overview'!$B9) -> 0 | M9: =SUMIFS('Combined P&L'!O:O,'Combined P&L'!$C:$C,'P&L Overview'!$B9) -> 0 | N9: =SUMIFS('Combined P&L'!P:P,'Combined P&L'!$C:$C,'P&L Overview'!$B9) -> 0 | O9: =SUMIFS('Combined P&L'!Q:Q,'Combined P&L'!$C:$C,'P&L Overview'!$B9) -> 0 | P9: =SUMIFS('Combined P&L'!R:R,'Combined P&L'!$C:$C,'P&L Overview'!$B9) -> 0 | Q9: =SUMIFS('Combined P&L'!S:S,'Combined P&L'!$C:$C,'P&L Overview'!$B9) -> 0 | R9: =SUMIFS('Combined P&L'!T:T,'Combined P&L'!$C:$C,'P&L Overview'!$B9) -> 0 | S9: =SUMIFS('Combined P&L'!U:U,'Combined P&L'!$C:$C,'P&L Overview'!$B9) -> 0 | T9: =SUMIFS('Combined P&L'!V:V,'Combined P&L'!$C:$C,'P&L Overview'!$B9) -> 0 | U9: =SUMIFS('Combined P&L'!W:W,'Combined P&L'!$C:$C,'P&L Overview'!$B9) -> 0 | V9: =SUMIFS('Combined P&L'!X:X,'Combined P&L'!$C:$C,'P&L Overview'!$B9) -> 0.08 | W9: =SUMIFS('Combined P&L'!Y:Y,'Combined P&L'!$C:$C,'P&L Overview'!$B9) -> 0.48 | X9: =SUMIFS('Combined P&L'!Z:Z,'Combined P&L'!$C:$C,'P&L Overview'!$B9) -> 1.13 | Y9: =SUMIFS('Combined P&L'!AA:AA,'Combined P&L'!$C:$C,'P&L Overview'!$B9) -> 2.14 | Z9: =SUMIFS('Combined P&L'!AB:AB,'Combined P&L'!$C:$C,'P&L Overview'!$B9) -> 2.66 | AA9: =SUMIFS('Combined P&L'!AC:AC,'Combined P&L'!$C:$C,'P&L Overview'!$B9) -> 3.65 | AB9: =SUMIFS('Combined P&L'!AD:AD,'Combined P&L'!$C:$C,'P&L Overview'!$B9) -> 3.623 | AC9: =SUMIFS('Combined P&L'!AE:AE,'Combined P&L'!$C:$C,'P&L Overview'!$B9) -> 4.964 | AD9: =SUMIFS('Combined P&L'!AF:AF,'Combined P&L'!$C:$C,'P&L Overview'!$B9) -> 5.0585 | AE9: =SUMIFS('Combined P&L'!AG:AG,'Combined P&L'!$C:$C,'P&L Overview'!$B9) -> 4.73 | AF9: =SUMIFS('Combined P&L'!AH:AH,'Combined P&L'!$C:$C,'P&L Overview'!$B9) -> 4.82 | AG9: =SUMIFS('Combined P&L'!AI:AI,'Combined P&L'!$C:$C,'P&L Overview'!$B9) -> 5.37 | AH9: =SUMIFS('Combined P&L'!AJ:AJ,'Combined P&L'!$C:$C,'P&L Overview'!$B9) -> 8.05 | AI9: =SUMIFS('Combined P&L'!AK:AK,'Combined P&L'!$C:$C,'P&L Overview'!$B9) -> 8.885 | AJ9: =SUMIFS('Combined P&L'!AL:AL,'Combined P&L'!$C:$C,'P&L Overview'!$B9) -> 10.90952 | AK9: =SUMIFS('Combined P&L'!AM:AM,'Combined P&L'!$C:$C,'P&L Overview'!$B9) -> 10.33497 | AL9: =SUMIFS('Combined P&L'!AN:AN,'Combined P&L'!$C:$C,'P&L Overview'!$B9) -> 11.175 | AM9: =SUMIFS('Combined P&L'!AO:AO,'Combined P&L'!$C:$C,'P&L Overview'!$B9) -> 11.95311 | AN9: =SUMIFS('Combined P&L'!AP:AP,'Combined P&L'!$C:$C,'P&L Overview'!$B9) -> 15.04071 | AO9: =SUMIFS('Combined P&L'!AQ:AQ,'Combined P&L'!$C:$C,'P&L Overview'!$B9) -> 16.16868 | AP9: =SUMIFS('Combined P&L'!AR:AR,'Combined P&L'!$C:$C,'P&L Overview'!$B9) -> 16.06915
B10: Onboarding | C10: =SUMIFS($L10:$AP10,$L$5:$AP$5,">"&C$42,$L$5:$AP$5,"<"&C$43) -> 44.0585 | D10: =SUMIFS($L10:$AP10,$L$5:$AP$5,">"&D$42,$L$5:$AP$5,"<"&D$43) -> 74.5193 | F10: =SUMIFS($L10:$AP10,$L$5:$AP$5,">"&F$42,$L$5:$AP$5,"<"&F$43) -> 42.25405 | G10: =SUMIFS($L10:$AP10,$L$5:$AP$5,">"&G$42,$L$5:$AP$5,"<"&G$43) -> 59.055 | I10: =SUMIFS($L10:$AP10,$L$5:$AP$5,">"&I$42,$L$5:$AP$5,"<"&I$43) -> 55.66055 | J10: =SUMIFS($L10:$AP10,$L$5:$AP$5,">"&J$42,$L$5:$AP$5,"<"&J$43) -> 91.65575 | L10: =SUMIFS('Combined P&L'!N:N,'Combined P&L'!$C:$C,'P&L Overview'!$B10) -> 5.465 | M10: =SUMIFS('Combined P&L'!O:O,'Combined P&L'!$C:$C,'P&L Overview'!$B10) -> 3.9 | N10: =SUMIFS('Combined P&L'!P:P,'Combined P&L'!$C:$C,'P&L Overview'!$B10) -> 2.755 | O10: =SUMIFS('Combined P&L'!Q:Q,'Combined P&L'!$C:$C,'P&L Overview'!$B10) -> 3.502 | P10: =SUMIFS('Combined P&L'!R:R,'Combined P&L'!$C:$C,'P&L Overview'!$B10) -> 4.659 | Q10: =SUMIFS('Combined P&L'!S:S,'Combined P&L'!$C:$C,'P&L Overview'!$B10) -> 3.937 | R10: =SUMIFS('Combined P&L'!T:T,'Combined P&L'!$C:$C,'P&L Overview'!$B10) -> 4.602 | S10: =SUMIFS('Combined P&L'!U:U,'Combined P&L'!$C:$C,'P&L Overview'!$B10) -> 4.738 | T10: =SUMIFS('Combined P&L'!V:V,'Combined P&L'!$C:$C,'P&L Overview'!$B10) -> 2.119 | U10: =SUMIFS('Combined P&L'!W:W,'Combined P&L'!$C:$C,'P&L Overview'!$B10) -> 2.064 | V10: =SUMIFS('Combined P&L'!X:X,'Combined P&L'!$C:$C,'P&L Overview'!$B10) -> 3.0125 | W10: =SUMIFS('Combined P&L'!Y:Y,'Combined P&L'!$C:$C,'P&L Overview'!$B10) -> 3.305 | X10: =SUMIFS('Combined P&L'!Z:Z,'Combined P&L'!$C:$C,'P&L Overview'!$B10) -> 3.079 | Y10: =SUMIFS('Combined P&L'!AA:AA,'Combined P&L'!$C:$C,'P&L Overview'!$B10) -> 0.7 | Z10: =SUMIFS('Combined P&L'!AB:AB,'Combined P&L'!$C:$C,'P&L Overview'!$B10) -> 10.43855 | AA10: =SUMIFS('Combined P&L'!AC:AC,'Combined P&L'!$C:$C,'P&L Overview'!$B10) -> 4.3 | AB10: =SUMIFS('Combined P&L'!AD:AD,'Combined P&L'!$C:$C,'P&L Overview'!$B10) -> 11.14 | AC10: =SUMIFS('Combined P&L'!AE:AE,'Combined P&L'!$C:$C,'P&L Overview'!$B10) -> 6.1625 | AD10: =SUMIFS('Combined P&L'!AF:AF,'Combined P&L'!$C:$C,'P&L Overview'!$B10) -> 6.434 | AE10: =SUMIFS('Combined P&L'!AG:AG,'Combined P&L'!$C:$C,'P&L Overview'!$B10) -> 3.965 | AF10: =SUMIFS('Combined P&L'!AH:AH,'Combined P&L'!$C:$C,'P&L Overview'!$B10) -> 3.92 | AG10: =SUMIFS('Combined P&L'!AI:AI,'Combined P&L'!$C:$C,'P&L Overview'!$B10) -> 9.1365 | AH10: =SUMIFS('Combined P&L'!AJ:AJ,'Combined P&L'!$C:$C,'P&L Overview'!$B10) -> 5.25375 | AI10: =SUMIFS('Combined P&L'!AK:AK,'Combined P&L'!$C:$C,'P&L Overview'!$B10) -> 9.99 | AJ10: =SUMIFS('Combined P&L'!AL:AL,'Combined P&L'!$C:$C,'P&L Overview'!$B10) -> 10.2105 | AK10: =SUMIFS('Combined P&L'!AM:AM,'Combined P&L'!$C:$C,'P&L Overview'!$B10) -> 6.675 | AL10: =SUMIFS('Combined P&L'!AN:AN,'Combined P&L'!$C:$C,'P&L Overview'!$B10) -> 9.099 | AM10: =SUMIFS('Combined P&L'!AO:AO,'Combined P&L'!$C:$C,'P&L Overview'!$B10) -> 8.9545 | AN10: =SUMIFS('Combined P&L'!AP:AP,'Combined P&L'!$C:$C,'P&L Overview'!$B10) -> 12.606 | AO10: =SUMIFS('Combined P&L'!AQ:AQ,'Combined P&L'!$C:$C,'P&L Overview'!$B10) -> 5.4115 | AP10: =SUMIFS('Combined P&L'!AR:AR,'Combined P&L'!$C:$C,'P&L Overview'!$B10) -> 6.0985
B11: STR Bill Pay | C11: =SUMIFS($L11:$AP11,$L$5:$AP$5,">"&C$42,$L$5:$AP$5,"<"&C$43) -> 0.06 | D11: =SUMIFS($L11:$AP11,$L$5:$AP$5,">"&D$42,$L$5:$AP$5,"<"&D$43) -> 36.6065 | F11: =SUMIFS($L11:$AP11,$L$5:$AP$5,">"&F$42,$L$5:$AP$5,"<"&F$43) -> 15.4915 | G11: =SUMIFS($L11:$AP11,$L$5:$AP$5,">"&G$42,$L$5:$AP$5,"<"&G$43) -> 45.13 | I11: =SUMIFS($L11:$AP11,$L$5:$AP$5,">"&I$42,$L$5:$AP$5,"<"&I$43) -> 11.6315 | J11: =SUMIFS($L11:$AP11,$L$5:$AP$5,">"&J$42,$L$5:$AP$5,"<"&J$43) -> 63.21 | L11: =SUMIFS('Combined P&L'!N:N,'Combined P&L'!$C:$C,'P&L Overview'!$B11) -> 0 | M11: =SUMIFS('Combined P&L'!O:O,'Combined P&L'!$C:$C,'P&L Overview'!$B11) -> 0 | N11: =SUMIFS('Combined P&L'!P:P,'Combined P&L'!$C:$C,'P&L Overview'!$B11) -> 0 | O11: =SUMIFS('Combined P&L'!Q:Q,'Combined P&L'!$C:$C,'P&L Overview'!$B11) -> 0 | P11: =SUMIFS('Combined P&L'!R:R,'Combined P&L'!$C:$C,'P&L Overview'!$B11) -> 0 | Q11: =SUMIFS('Combined P&L'!S:S,'Combined P&L'!$C:$C,'P&L Overview'!$B11) -> 0 | R11: =SUMIFS('Combined P&L'!T:T,'Combined P&L'!$C:$C,'P&L Overview'!$B11) -> 0 | S11: =SUMIFS('Combined P&L'!U:U,'Combined P&L'!$C:$C,'P&L Overview'!$B11) -> 0 | T11: =SUMIFS('Combined P&L'!V:V,'Combined P&L'!$C:$C,'P&L Overview'!$B11) -> 0 | U11: =SUMIFS('Combined P&L'!W:W,'Combined P&L'!$C:$C,'P&L Overview'!$B11) -> 0 | V11: =SUMIFS('Combined P&L'!X:X,'Combined P&L'!$C:$C,'P&L Overview'!$B11) -> 0 | W11: =SUMIFS('Combined P&L'!Y:Y,'Combined P&L'!$C:$C,'P&L Overview'!$B11) -> 0.06 | X11: =SUMIFS('Combined P&L'!Z:Z,'Combined P&L'!$C:$C,'P&L Overview'!$B11) -> 0.97 | Y11: =SUMIFS('Combined P&L'!AA:AA,'Combined P&L'!$C:$C,'P&L Overview'!$B11) -> 1.1 | Z11: =SUMIFS('Combined P&L'!AB:AB,'Combined P&L'!$C:$C,'P&L Overview'!$B11) -> 1.735 | AA11: =SUMIFS('Combined P&L'!AC:AC,'Combined P&L'!$C:$C,'P&L Overview'!$B11) -> 2.14 | AB11: =SUMIFS('Combined P&L'!AD:AD,'Combined P&L'!$C:$C,'P&L Overview'!$B11) -> 2.363 | AC11: =SUMIFS('Combined P&L'!AE:AE,'Combined P&L'!$C:$C,'P&L Overview'!$B11) -> 3.2635 | AD11: =SUMIFS('Combined P&L'!AF:AF,'Combined P&L'!$C:$C,'P&L Overview'!$B11) -> 3.92 | AE11: =SUMIFS('Combined P&L'!AG:AG,'Combined P&L'!$C:$C,'P&L Overview'!$B11) -> 3.905 | AF11: =SUMIFS('Combined P&L'!AH:AH,'Combined P&L'!$C:$C,'P&L Overview'!$B11) -> 3.78 | AG11: =SUMIFS('Combined P&L'!AI:AI,'Combined P&L'!$C:$C,'P&L Overview'!$B11) -> 3.795 | AH11: =SUMIFS('Combined P&L'!AJ:AJ,'Combined P&L'!$C:$C,'P&L Overview'!$B11) -> 4.33 | AI11: =SUMIFS('Combined P&L'!AK:AK,'Combined P&L'!$C:$C,'P&L Overview'!$B11) -> 5.305 | AJ11: =SUMIFS('Combined P&L'!AL:AL,'Combined P&L'!$C:$C,'P&L Overview'!$B11) -> 6.3 | AK11: =SUMIFS('Combined P&L'!AM:AM,'Combined P&L'!$C:$C,'P&L Overview'!$B11) -> 6.39 | AL11: =SUMIFS('Combined P&L'!AN:AN,'Combined P&L'!$C:$C,'P&L Overview'!$B11) -> 6.425 | AM11: =SUMIFS('Combined P&L'!AO:AO,'Combined P&L'!$C:$C,'P&L Overview'!$B11) -> 6.08 | AN11: =SUMIFS('Combined P&L'!AP:AP,'Combined P&L'!$C:$C,'P&L Overview'!$B11) -> 6.325 | AO11: =SUMIFS('Combined P&L'!AQ:AQ,'Combined P&L'!$C:$C,'P&L Overview'!$B11) -> 6.655 | AP11: =SUMIFS('Combined P&L'!AR:AR,'Combined P&L'!$C:$C,'P&L Overview'!$B11) -> 6.955
B12: Topkey Subscription | C12: =SUMIFS($L12:$AP12,$L$5:$AP$5,">"&C$42,$L$5:$AP$5,"<"&C$43) -> 0 | D12: =SUMIFS($L12:$AP12,$L$5:$AP$5,">"&D$42,$L$5:$AP$5,"<"&D$43) -> 9.947 | F12: =SUMIFS($L12:$AP12,$L$5:$AP$5,">"&F$42,$L$5:$AP$5,"<"&F$43) -> 0 | G12: =SUMIFS($L12:$AP12,$L$5:$AP$5,">"&G$42,$L$5:$AP$5,"<"&G$43) -> 45.086 | I12: =SUMIFS($L12:$AP12,$L$5:$AP$5,">"&I$42,$L$5:$AP$5,"<"&I$43) -> 0 | J12: =SUMIFS($L12:$AP12,$L$5:$AP$5,">"&J$42,$L$5:$AP$5,"<"&J$43) -> 47.13 | L12: =SUMIFS('Combined P&L'!N:N,'Combined P&L'!$C:$C,'P&L Overview'!$B12) -> 0 | M12: =SUMIFS('Combined P&L'!O:O,'Combined P&L'!$C:$C,'P&L Overview'!$B12) -> 0 | N12: =SUMIFS('Combined P&L'!P:P,'Combined P&L'!$C:$C,'P&L Overview'!$B12) -> 0 | O12: =SUMIFS('Combined P&L'!Q:Q,'Combined P&L'!$C:$C,'P&L Overview'!$B12) -> 0 | P12: =SUMIFS('Combined P&L'!R:R,'Combined P&L'!$C:$C,'P&L Overview'!$B12) -> 0 | Q12: =SUMIFS('Combined P&L'!S:S,'Combined P&L'!$C:$C,'P&L Overview'!$B12) -> 0 | R12: =SUMIFS('Combined P&L'!T:T,'Combined P&L'!$C:$C,'P&L Overview'!$B12) -> 0 | S12: =SUMIFS('Combined P&L'!U:U,'Combined P&L'!$C:$C,'P&L Overview'!$B12) -> 0 | T12: =SUMIFS('Combined P&L'!V:V,'Combined P&L'!$C:$C,'P&L Overview'!$B12) -> 0 | U12: =SUMIFS('Combined P&L'!W:W,'Combined P&L'!$C:$C,'P&L Overview'!$B12) -> 0 | V12: =SUMIFS('Combined P&L'!X:X,'Combined P&L'!$C:$C,'P&L Overview'!$B12) -> 0 | W12: =SUMIFS('Combined P&L'!Y:Y,'Combined P&L'!$C:$C,'P&L Overview'!$B12) -> 0 | X12: =SUMIFS('Combined P&L'!Z:Z,'Combined P&L'!$C:$C,'P&L Overview'!$B12) -> 0 | Y12: =SUMIFS('Combined P&L'!AA:AA,'Combined P&L'!$C:$C,'P&L Overview'!$B12) -> 0 | Z12: =SUMIFS('Combined P&L'!AB:AB,'Combined P&L'!$C:$C,'P&L Overview'!$B12) -> 0 | AA12: =SUMIFS('Combined P&L'!AC:AC,'Combined P&L'!$C:$C,'P&L Overview'!$B12) -> 0 | AB12: =SUMIFS('Combined P&L'!AD:AD,'Combined P&L'!$C:$C,'P&L Overview'!$B12) -> 0 | AC12: =SUMIFS('Combined P&L'!AE:AE,'Combined P&L'!$C:$C,'P&L Overview'!$B12) -> 0 | AD12: =SUMIFS('Combined P&L'!AF:AF,'Combined P&L'!$C:$C,'P&L Overview'!$B12) -> 0 | AE12: =SUMIFS('Combined P&L'!AG:AG,'Combined P&L'!$C:$C,'P&L Overview'!$B12) -> 0 | AF12: =SUMIFS('Combined P&L'!AH:AH,'Combined P&L'!$C:$C,'P&L Overview'!$B12) -> 0.52 | AG12: =SUMIFS('Combined P&L'!AI:AI,'Combined P&L'!$C:$C,'P&L Overview'!$B12) -> 2.357 | AH12: =SUMIFS('Combined P&L'!AJ:AJ,'Combined P&L'!$C:$C,'P&L Overview'!$B12) -> 2.811 | AI12: =SUMIFS('Combined P&L'!AK:AK,'Combined P&L'!$C:$C,'P&L Overview'!$B12) -> 4.259 | AJ12: =SUMIFS('Combined P&L'!AL:AL,'Combined P&L'!$C:$C,'P&L Overview'!$B12) -> 5.254 | AK12: =SUMIFS('Combined P&L'!AM:AM,'Combined P&L'!$C:$C,'P&L Overview'!$B12) -> 5.652 | AL12: =SUMIFS('Combined P&L'!AN:AN,'Combined P&L'!$C:$C,'P&L Overview'!$B12) -> 5.324 | AM12: =SUMIFS('Combined P&L'!AO:AO,'Combined P&L'!$C:$C,'P&L Overview'!$B12) -> 6.321 | AN12: =SUMIFS('Combined P&L'!AP:AP,'Combined P&L'!$C:$C,'P&L Overview'!$B12) -> 6.959 | AO12: =SUMIFS('Combined P&L'!AQ:AQ,'Combined P&L'!$C:$C,'P&L Overview'!$B12) -> 7.673 | AP12: =SUMIFS('Combined P&L'!AR:AR,'Combined P&L'!$C:$C,'P&L Overview'!$B12) -> 7.903
B13: Controller Services | C13: =SUMIFS($L13:$AP13,$L$5:$AP$5,">"&C$42,$L$5:$AP$5,"<"&C$43) -> 13.75 | D13: =SUMIFS($L13:$AP13,$L$5:$AP$5,">"&D$42,$L$5:$AP$5,"<"&D$43) -> 46.4 | F13: =SUMIFS($L13:$AP13,$L$5:$AP$5,">"&F$42,$L$5:$AP$5,"<"&F$43) -> 31.5 | G13: =SUMIFS($L13:$AP13,$L$5:$AP$5,">"&G$42,$L$5:$AP$5,"<"&G$43) -> 24.25 | I13: =SUMIFS($L13:$AP13,$L$5:$AP$5,">"&I$42,$L$5:$AP$5,"<"&I$43) -> 41.25 | J13: =SUMIFS($L13:$AP13,$L$5:$AP$5,">"&J$42,$L$5:$AP$5,"<"&J$43) -> 39.65 | L13: =SUMIFS('Combined P&L'!N:N,'Combined P&L'!$C:$C,'P&L Overview'!$B13) -> 0 | M13: =SUMIFS('Combined P&L'!O:O,'Combined P&L'!$C:$C,'P&L Overview'!$B13) -> 0 | N13: =SUMIFS('Combined P&L'!P:P,'Combined P&L'!$C:$C,'P&L Overview'!$B13) -> 0 | O13: =SUMIFS('Combined P&L'!Q:Q,'Combined P&L'!$C:$C,'P&L Overview'!$B13) -> 0 | P13: =SUMIFS('Combined P&L'!R:R,'Combined P&L'!$C:$C,'P&L Overview'!$B13) -> 0 | Q13: =SUMIFS('Combined P&L'!S:S,'Combined P&L'!$C:$C,'P&L Overview'!$B13) -> 0 | R13: =SUMIFS('Combined P&L'!T:T,'Combined P&L'!$C:$C,'P&L Overview'!$B13) -> 1.25 | S13: =SUMIFS('Combined P&L'!U:U,'Combined P&L'!$C:$C,'P&L Overview'!$B13) -> 1.25 | T13: =SUMIFS('Combined P&L'!V:V,'Combined P&L'!$C:$C,'P&L Overview'!$B13) -> 1.25 | U13: =SUMIFS('Combined P&L'!W:W,'Combined P&L'!$C:$C,'P&L Overview'!$B13) -> 1.25 | V13: =SUMIFS('Combined P&L'!X:X,'Combined P&L'!$C:$C,'P&L Overview'!$B13) -> 5.75 | W13: =SUMIFS('Combined P&L'!Y:Y,'Combined P&L'!$C:$C,'P&L Overview'!$B13) -> 3 | X13: =SUMIFS('Combined P&L'!Z:Z,'Combined P&L'!$C:$C,'P&L Overview'!$B13) -> 4.45 | Y13: =SUMIFS('Combined P&L'!AA:AA,'Combined P&L'!$C:$C,'P&L Overview'!$B13) -> 3.45 | Z13: =SUMIFS('Combined P&L'!AB:AB,'Combined P&L'!$C:$C,'P&L Overview'!$B13) -> 3.45 | AA13: =SUMIFS('Combined P&L'!AC:AC,'Combined P&L'!$C:$C,'P&L Overview'!$B13) -> 5.95 | AB13: =SUMIFS('Combined P&L'!AD:AD,'Combined P&L'!$C:$C,'P&L Overview'!$B13) -> 5.2 | AC13: =SUMIFS('Combined P&L'!AE:AE,'Combined P&L'!$C:$C,'P&L Overview'!$B13) -> 5 | AD13: =SUMIFS('Combined P&L'!AF:AF,'Combined P&L'!$C:$C,'P&L Overview'!$B13) -> 4 | AE13: =SUMIFS('Combined P&L'!AG:AG,'Combined P&L'!$C:$C,'P&L Overview'!$B13) -> 2.95 | AF13: =SUMIFS('Combined P&L'!AH:AH,'Combined P&L'!$C:$C,'P&L Overview'!$B13) -> 3.025 | AG13: =SUMIFS('Combined P&L'!AI:AI,'Combined P&L'!$C:$C,'P&L Overview'!$B13) -> 3.025 | AH13: =SUMIFS('Combined P&L'!AJ:AJ,'Combined P&L'!$C:$C,'P&L Overview'!$B13) -> 2.95 | AI13: =SUMIFS('Combined P&L'!AK:AK,'Combined P&L'!$C:$C,'P&L Overview'!$B13) -> 2.95 | AJ13: =SUMIFS('Combined P&L'!AL:AL,'Combined P&L'!$C:$C,'P&L Overview'!$B13) -> 2.75 | AK13: =SUMIFS('Combined P&L'!AM:AM,'Combined P&L'!$C:$C,'P&L Overview'!$B13) -> 3.5 | AL13: =SUMIFS('Combined P&L'!AN:AN,'Combined P&L'!$C:$C,'P&L Overview'!$B13) -> 2.75 | AM13: =SUMIFS('Combined P&L'!AO:AO,'Combined P&L'!$C:$C,'P&L Overview'!$B13) -> 4.75 | AN13: =SUMIFS('Combined P&L'!AP:AP,'Combined P&L'!$C:$C,'P&L Overview'!$B13) -> 3.5 | AO13: =SUMIFS('Combined P&L'!AQ:AQ,'Combined P&L'!$C:$C,'P&L Overview'!$B13) -> 3.5 | AP13: =SUMIFS('Combined P&L'!AR:AR,'Combined P&L'!$C:$C,'P&L Overview'!$B13) -> 3.5
B14: Historical Cleanup | C14: =SUMIFS($L14:$AP14,$L$5:$AP$5,">"&C$42,$L$5:$AP$5,"<"&C$43) -> 17.624 | D14: =SUMIFS($L14:$AP14,$L$5:$AP$5,">"&D$42,$L$5:$AP$5,"<"&D$43) -> 5.03375 | F14: =SUMIFS($L14:$AP14,$L$5:$AP$5,">"&F$42,$L$5:$AP$5,"<"&F$43) -> 4.43875 | G14: =SUMIFS($L14:$AP14,$L$5:$AP$5,">"&G$42,$L$5:$AP$5,"<"&G$43) -> 0 | I14: =SUMIFS($L14:$AP14,$L$5:$AP$5,">"&I$42,$L$5:$AP$5,"<"&I$43) -> 14.30525 | J14: =SUMIFS($L14:$AP14,$L$5:$AP$5,">"&J$42,$L$5:$AP$5,"<"&J$43) -> 0.595 | L14: =SUMIFS('Combined P&L'!N:N,'Combined P&L'!$C:$C,'P&L Overview'!$B14) -> 1.2 | M14: =SUMIFS('Combined P&L'!O:O,'Combined P&L'!$C:$C,'P&L Overview'!$B14) -> 1.7625 | N14: =SUMIFS('Combined P&L'!P:P,'Combined P&L'!$C:$C,'P&L Overview'!$B14) -> 0.66 | O14: =SUMIFS('Combined P&L'!Q:Q,'Combined P&L'!$C:$C,'P&L Overview'!$B14) -> 0.395 | P14: =SUMIFS('Combined P&L'!R:R,'Combined P&L'!$C:$C,'P&L Overview'!$B14) -> 2.465 | Q14: =SUMIFS('Combined P&L'!S:S,'Combined P&L'!$C:$C,'P&L Overview'!$B14) -> 1.275 | R14: =SUMIFS('Combined P&L'!T:T,'Combined P&L'!$C:$C,'P&L Overview'!$B14) -> 1.4625 | S14: =SUMIFS('Combined P&L'!U:U,'Combined P&L'!$C:$C,'P&L Overview'!$B14) -> 0 | T14: =SUMIFS('Combined P&L'!V:V,'Combined P&L'!$C:$C,'P&L Overview'!$B14) -> 1.14525 | U14: =SUMIFS('Combined P&L'!W:W,'Combined P&L'!$C:$C,'P&L Overview'!$B14) -> 1.35525 | V14: =SUMIFS('Combined P&L'!X:X,'Combined P&L'!$C:$C,'P&L Overview'!$B14) -> 1.9035 | W14: =SUMIFS('Combined P&L'!Y:Y,'Combined P&L'!$C:$C,'P&L Overview'!$B14) -> 4 | X14: =SUMIFS('Combined P&L'!Z:Z,'Combined P&L'!$C:$C,'P&L Overview'!$B14) -> 1.08375 | Y14: =SUMIFS('Combined P&L'!AA:AA,'Combined P&L'!$C:$C,'P&L Overview'!$B14) -> 2 | Z14: =SUMIFS('Combined P&L'!AB:AB,'Combined P&L'!$C:$C,'P&L Overview'!$B14) -> 1.355 | AA14: =SUMIFS('Combined P&L'!AC:AC,'Combined P&L'!$C:$C,'P&L Overview'!$B14) -> 0 | AB14: =SUMIFS('Combined P&L'!AD:AD,'Combined P&L'!$C:$C,'P&L Overview'!$B14) -> 0 | AC14: =SUMIFS('Combined P&L'!AE:AE,'Combined P&L'!$C:$C,'P&L Overview'!$B14) -> 0 | AD14: =SUMIFS('Combined P&L'!AF:AF,'Combined P&L'!$C:$C,'P&L Overview'!$B14) -> 0 | AE14: =SUMIFS('Combined P&L'!AG:AG,'Combined P&L'!$C:$C,'P&L Overview'!$B14) -> 0 | AF14: =SUMIFS('Combined P&L'!AH:AH,'Combined P&L'!$C:$C,'P&L Overview'!$B14) -> 0 | AG14: =SUMIFS('Combined P&L'!AI:AI,'Combined P&L'!$C:$C,'P&L Overview'!$B14) -> 0.595 | AH14: =SUMIFS('Combined P&L'!AJ:AJ,'Combined P&L'!$C:$C,'P&L Overview'!$B14) -> 0 | AI14: =SUMIFS('Combined P&L'!AK:AK,'Combined P&L'!$C:$C,'P&L Overview'!$B14) -> 0 | AJ14: =SUMIFS('Combined P&L'!AL:AL,'Combined P&L'!$C:$C,'P&L Overview'!$B14) -> 0 | AK14: =SUMIFS('Combined P&L'!AM:AM,'Combined P&L'!$C:$C,'P&L Overview'!$B14) -> 0 | AL14: =SUMIFS('Combined P&L'!AN:AN,'Combined P&L'!$C:$C,'P&L Overview'!$B14) -> 0 | AM14: =SUMIFS('Combined P&L'!AO:AO,'Combined P&L'!$C:$C,'P&L Overview'!$B14) -> 0 | AN14: =SUMIFS('Combined P&L'!AP:AP,'Combined P&L'!$C:$C,'P&L Overview'!$B14) -> 0 | AO14: =SUMIFS('Combined P&L'!AQ:AQ,'Combined P&L'!$C:$C,'P&L Overview'!$B14) -> 0 | AP14: =SUMIFS('Combined P&L'!AR:AR,'Combined P&L'!$C:$C,'P&L Overview'!$B14) -> 0
B15: Total Recurring Revenue | C15: =SUM(C7:C14) -> 1094.3157 | D15: =SUM(D7:D14) -> 1827.8494 | F15: =SUM(F7:F14) -> 958.8909 | G15: =SUM(G7:G14) -> 1600.0675 | I15: =SUM(I7:I14) -> 1414.7118 | J15: =SUM(J7:J14) -> 2371.7313 | L15: =SUM(L7:L14) -> 73.3495 | M15: =SUM(M7:M14) -> 74.7445 | N15: =SUM(N7:N14) -> 77.996 | O15: =SUM(O7:O14) -> 83.2127 | P15: =SUM(P7:P14) -> 86.60415 | Q15: =SUM(Q7:Q14) -> 88.544 | R15: =SUM(R7:R14) -> 93.21675 | S15: =SUM(S7:S14) -> 96.77535 | ... AP15: =SUM(AP7:AP14) -> 251.33865
B17: 1099 Filing | C17: =SUMIFS($L17:$AP17,$L$5:$AP$5,">"&C$42,$L$5:$AP$5,"<"&C$43) -> 10.475 | D17: =SUMIFS($L17:$AP17,$L$5:$AP$5,">"&D$42,$L$5:$AP$5,"<"&D$43) -> 23.55 | F17: =SUMIFS($L17:$AP17,$L$5:$AP$5,">"&F$42,$L$5:$AP$5,"<"&F$43) -> 23.49 | G17: =SUMIFS($L17:$AP17,$L$5:$AP$5,">"&G$42,$L$5:$AP$5,"<"&G$43) -> 38.7015 | I17: =SUMIFS($L17:$AP17,$L$5:$AP$5,">"&I$42,$L$5:$AP$5,"<"&I$43) -> 23.52 | J17: =SUMIFS($L17:$AP17,$L$5:$AP$5,">"&J$42,$L$5:$AP$5,"<"&J$43) -> 38.7615 | L17: =SUMIFS('Combined P&L'!N:N,'Combined P&L'!$C:$C,'P&L Overview'!$B17) -> 6.945 | M17: =SUMIFS('Combined P&L'!O:O,'Combined P&L'!$C:$C,'P&L Overview'!$B17) -> 3.38 | N17: =SUMIFS('Combined P&L'!P:P,'Combined P&L'!$C:$C,'P&L Overview'!$B17) -> 0.045 | O17: =SUMIFS('Combined P&L'!Q:Q,'Combined P&L'!$C:$C,'P&L Overview'!$B17) -> 0.06 | P17: =SUMIFS('Combined P&L'!R:R,'Combined P&L'!$C:$C,'P&L Overview'!$B17) -> 0.015 | Q17: =SUMIFS('Combined P&L'!S:S,'Combined P&L'!$C:$C,'P&L Overview'!$B17) -> 0 | R17: =SUMIFS('Combined P&L'!T:T,'Combined P&L'!$C:$C,'P&L Overview'!$B17) -> 0 | S17: =SUMIFS('Combined P&L'!U:U,'Combined P&L'!$C:$C,'P&L Overview'!$B17) -> 0.015 | T17: =SUMIFS('Combined P&L'!V:V,'Combined P&L'!$C:$C,'P&L Overview'!$B17) -> 0 | U17: =SUMIFS('Combined P&L'!W:W,'Combined P&L'!$C:$C,'P&L Overview'!$B17) -> 0 | V17: =SUMIFS('Combined P&L'!X:X,'Combined P&L'!$C:$C,'P&L Overview'!$B17) -> 0.015 | W17: =SUMIFS('Combined P&L'!Y:Y,'Combined P&L'!$C:$C,'P&L Overview'!$B17) -> 0 | X17: =SUMIFS('Combined P&L'!Z:Z,'Combined P&L'!$C:$C,'P&L Overview'!$B17) -> 13.485 | Y17: =SUMIFS('Combined P&L'!AA:AA,'Combined P&L'!$C:$C,'P&L Overview'!$B17) -> 9.915 | Z17: =SUMIFS('Combined P&L'!AB:AB,'Combined P&L'!$C:$C,'P&L Overview'!$B17) -> 0.06 | AA17: =SUMIFS('Combined P&L'!AC:AC,'Combined P&L'!$C:$C,'P&L Overview'!$B17) -> 0.03 | AB17: =SUMIFS('Combined P&L'!AD:AD,'Combined P&L'!$C:$C,'P&L Overview'!$B17) -> 0 | AC17: =SUMIFS('Combined P&L'!AE:AE,'Combined P&L'!$C:$C,'P&L Overview'!$B17) -> 0 | AD17: =SUMIFS('Combined P&L'!AF:AF,'Combined P&L'!$C:$C,'P&L Overview'!$B17) -> 0 | AE17: =SUMIFS('Combined P&L'!AG:AG,'Combined P&L'!$C:$C,'P&L Overview'!$B17) -> 0.03 | AF17: =SUMIFS('Combined P&L'!AH:AH,'Combined P&L'!$C:$C,'P&L Overview'!$B17) -> 0.03 | AG17: =SUMIFS('Combined P&L'!AI:AI,'Combined P&L'!$C:$C,'P&L Overview'!$B17) -> 0 | AH17: =SUMIFS('Combined P&L'!AJ:AJ,'Combined P&L'!$C:$C,'P&L Overview'!$B17) -> 0 | AI17: =SUMIFS('Combined P&L'!AK:AK,'Combined P&L'!$C:$C,'P&L Overview'!$B17) -> 0 | AJ17: =SUMIFS('Combined P&L'!AL:AL,'Combined P&L'!$C:$C,'P&L Overview'!$B17) -> 6.105 | AK17: =SUMIFS('Combined P&L'!AM:AM,'Combined P&L'!$C:$C,'P&L Overview'!$B17) -> 31.1565 | AL17: =SUMIFS('Combined P&L'!AN:AN,'Combined P&L'!$C:$C,'P&L Overview'!$B17) -> 1.26 | AM17: =SUMIFS('Combined P&L'!AO:AO,'Combined P&L'!$C:$C,'P&L Overview'!$B17) -> 0.18 | AN17: =SUMIFS('Combined P&L'!AP:AP,'Combined P&L'!$C:$C,'P&L Overview'!$B17) -> 0 | AO17: =SUMIFS('Combined P&L'!AQ:AQ,'Combined P&L'!$C:$C,'P&L Overview'!$B17) -> 0 | AP17: =SUMIFS('Combined P&L'!AR:AR,'Combined P&L'!$C:$C,'P&L Overview'!$B17) -> 0
B18: Income Tax | C18: =SUMIFS($L18:$AP18,$L$5:$AP$5,">"&C$42,$L$5:$AP$5,"<"&C$43) -> 0 | D18: =SUMIFS($L18:$AP18,$L$5:$AP$5,">"&D$42,$L$5:$AP$5,"<"&D$43) -> 3.4 | F18: =SUMIFS($L18:$AP18,$L$5:$AP$5,">"&F$42,$L$5:$AP$5,"<"&F$43) -> 0 | G18: =SUMIFS($L18:$AP18,$L$5:$AP$5,">"&G$42,$L$5:$AP$5,"<"&G$43) -> 23.915 | I18: =SUMIFS($L18:$AP18,$L$5:$AP$5,">"&I$42,$L$5:$AP$5,"<"&I$43) -> 0 | J18: =SUMIFS($L18:$AP18,$L$5:$AP$5,">"&J$42,$L$5:$AP$5,"<"&J$43) -> 27.315 | L18: =SUMIFS('Combined P&L'!N:N,'Combined P&L'!$C:$C,'P&L Overview'!$B18) -> 0 | M18: =SUMIFS('Combined P&L'!O:O,'Combined P&L'!$C:$C,'P&L Overview'!$B18) -> 0 | N18: =SUMIFS('Combined P&L'!P:P,'Combined P&L'!$C:$C,'P&L Overview'!$B18) -> 0 | O18: =SUMIFS('Combined P&L'!Q:Q,'Combined P&L'!$C:$C,'P&L Overview'!$B18) -> 0 | P18: =SUMIFS('Combined P&L'!R:R,'Combined P&L'!$C:$C,'P&L Overview'!$B18) -> 0 | Q18: =SUMIFS('Combined P&L'!S:S,'Combined P&L'!$C:$C,'P&L Overview'!$B18) -> 0 | R18: =SUMIFS('Combined P&L'!T:T,'Combined P&L'!$C:$C,'P&L Overview'!$B18) -> 0 | S18: =SUMIFS('Combined P&L'!U:U,'Combined P&L'!$C:$C,'P&L Overview'!$B18) -> 0 | T18: =SUMIFS('Combined P&L'!V:V,'Combined P&L'!$C:$C,'P&L Overview'!$B18) -> 0 | U18: =SUMIFS('Combined P&L'!W:W,'Combined P&L'!$C:$C,'P&L Overview'!$B18) -> 0 | V18: =SUMIFS('Combined P&L'!X:X,'Combined P&L'!$C:$C,'P&L Overview'!$B18) -> 0 | W18: =SUMIFS('Combined P&L'!Y:Y,'Combined P&L'!$C:$C,'P&L Overview'!$B18) -> 0 | X18: =SUMIFS('Combined P&L'!Z:Z,'Combined P&L'!$C:$C,'P&L Overview'!$B18) -> 0 | Y18: =SUMIFS('Combined P&L'!AA:AA,'Combined P&L'!$C:$C,'P&L Overview'!$B18) -> 0 | Z18: =SUMIFS('Combined P&L'!AB:AB,'Combined P&L'!$C:$C,'P&L Overview'!$B18) -> 0 | AA18: =SUMIFS('Combined P&L'!AC:AC,'Combined P&L'!$C:$C,'P&L Overview'!$B18) -> 0 | AB18: =SUMIFS('Combined P&L'!AD:AD,'Combined P&L'!$C:$C,'P&L Overview'!$B18) -> 0 | AC18: =SUMIFS('Combined P&L'!AE:AE,'Combined P&L'!$C:$C,'P&L Overview'!$B18) -> 0 | AD18: =SUMIFS('Combined P&L'!AF:AF,'Combined P&L'!$C:$C,'P&L Overview'!$B18) -> 0 | AE18: =SUMIFS('Combined P&L'!AG:AG,'Combined P&L'!$C:$C,'P&L Overview'!$B18) -> 0 | AF18: =SUMIFS('Combined P&L'!AH:AH,'Combined P&L'!$C:$C,'P&L Overview'!$B18) -> 0.875 | AG18: =SUMIFS('Combined P&L'!AI:AI,'Combined P&L'!$C:$C,'P&L Overview'!$B18) -> 1.65 | AH18: =SUMIFS('Combined P&L'!AJ:AJ,'Combined P&L'!$C:$C,'P&L Overview'!$B18) -> 0 | AI18: =SUMIFS('Combined P&L'!AK:AK,'Combined P&L'!$C:$C,'P&L Overview'!$B18) -> 0.875 | AJ18: =SUMIFS('Combined P&L'!AL:AL,'Combined P&L'!$C:$C,'P&L Overview'!$B18) -> 0 | AK18: =SUMIFS('Combined P&L'!AM:AM,'Combined P&L'!$C:$C,'P&L Overview'!$B18) -> 0 | AL18: =SUMIFS('Combined P&L'!AN:AN,'Combined P&L'!$C:$C,'P&L Overview'!$B18) -> 14.19 | AM18: =SUMIFS('Combined P&L'!AO:AO,'Combined P&L'!$C:$C,'P&L Overview'!$B18) -> 6.625 | AN18: =SUMIFS('Combined P&L'!AP:AP,'Combined P&L'!$C:$C,'P&L Overview'!$B18) -> 0 | AO18: =SUMIFS('Combined P&L'!AQ:AQ,'Combined P&L'!$C:$C,'P&L Overview'!$B18) -> 3.1 | AP18: =SUMIFS('Combined P&L'!AR:AR,'Combined P&L'!$C:$C,'P&L Overview'!$B18) -> 0
B19: Profit Share | C19: =SUMIFS($L19:$AP19,$L$5:$AP$5,">"&C$42,$L$5:$AP$5,"<"&C$43) -> 6.2004 | D19: =SUMIFS($L19:$AP19,$L$5:$AP$5,">"&D$42,$L$5:$AP$5,"<"&D$43) -> 23.26179 | F19: =SUMIFS($L19:$AP19,$L$5:$AP$5,">"&F$42,$L$5:$AP$5,"<"&F$43) -> 14.50495 | G19: =SUMIFS($L19:$AP19,$L$5:$AP$5,">"&G$42,$L$5:$AP$5,"<"&G$43) -> 8.07938 | I19: =SUMIFS($L19:$AP19,$L$5:$AP$5,">"&I$42,$L$5:$AP$5,"<"&I$43) -> 17.94788 | J19: =SUMIFS($L19:$AP19,$L$5:$AP$5,">"&J$42,$L$5:$AP$5,"<"&J$43) -> 17.79609 | L19: =SUMIFS('Combined P&L'!N:N,'Combined P&L'!$C:$C,'P&L Overview'!$B19) -> 0.0686 | M19: =SUMIFS('Combined P&L'!O:O,'Combined P&L'!$C:$C,'P&L Overview'!$B19) -> 0.1312 | N19: =SUMIFS('Combined P&L'!P:P,'Combined P&L'!$C:$C,'P&L Overview'!$B19) -> 0.0712 | O19: =SUMIFS('Combined P&L'!Q:Q,'Combined P&L'!$C:$C,'P&L Overview'!$B19) -> 0.0556 | P19: =SUMIFS('Combined P&L'!R:R,'Combined P&L'!$C:$C,'P&L Overview'!$B19) -> 0.577 | Q19: =SUMIFS('Combined P&L'!S:S,'Combined P&L'!$C:$C,'P&L Overview'!$B19) -> 0.8068 | R19: =SUMIFS('Combined P&L'!T:T,'Combined P&L'!$C:$C,'P&L Overview'!$B19) -> 0.6656 | S19: =SUMIFS('Combined P&L'!U:U,'Combined P&L'!$C:$C,'P&L Overview'!$B19) -> 0.8264 | T19: =SUMIFS('Combined P&L'!V:V,'Combined P&L'!$C:$C,'P&L Overview'!$B19) -> 1.3808 | U19: =SUMIFS('Combined P&L'!W:W,'Combined P&L'!$C:$C,'P&L Overview'!$B19) -> 0.8604 | V19: =SUMIFS('Combined P&L'!X:X,'Combined P&L'!$C:$C,'P&L Overview'!$B19) -> 0.51 | W19: =SUMIFS('Combined P&L'!Y:Y,'Combined P&L'!$C:$C,'P&L Overview'!$B19) -> 0.2468 | X19: =SUMIFS('Combined P&L'!Z:Z,'Combined P&L'!$C:$C,'P&L Overview'!$B19) -> 7.3584 | Y19: =SUMIFS('Combined P&L'!AA:AA,'Combined P&L'!$C:$C,'P&L Overview'!$B19) -> 1.29335 | Z19: =SUMIFS('Combined P&L'!AB:AB,'Combined P&L'!$C:$C,'P&L Overview'!$B19) -> 0.96833 | AA19: =SUMIFS('Combined P&L'!AC:AC,'Combined P&L'!$C:$C,'P&L Overview'!$B19) -> 1.1656 | AB19: =SUMIFS('Combined P&L'!AD:AD,'Combined P&L'!$C:$C,'P&L Overview'!$B19) -> 0.96093 | AC19: =SUMIFS('Combined P&L'!AE:AE,'Combined P&L'!$C:$C,'P&L Overview'!$B19) -> 1.71127 | AD19: =SUMIFS('Combined P&L'!AF:AF,'Combined P&L'!$C:$C,'P&L Overview'!$B19) -> 1.04707 | AE19: =SUMIFS('Combined P&L'!AG:AG,'Combined P&L'!$C:$C,'P&L Overview'!$B19) -> 2.04088 | AF19: =SUMIFS('Combined P&L'!AH:AH,'Combined P&L'!$C:$C,'P&L Overview'!$B19) -> 1.13621 | AG19: =SUMIFS('Combined P&L'!AI:AI,'Combined P&L'!$C:$C,'P&L Overview'!$B19) -> 2.01424 | AH19: =SUMIFS('Combined P&L'!AJ:AJ,'Combined P&L'!$C:$C,'P&L Overview'!$B19) -> 1.29758 | AI19: =SUMIFS('Combined P&L'!AK:AK,'Combined P&L'!$C:$C,'P&L Overview'!$B19) -> 2.26793 | AJ19: =SUMIFS('Combined P&L'!AL:AL,'Combined P&L'!$C:$C,'P&L Overview'!$B19) -> 2.67784 | AK19: =SUMIFS('Combined P&L'!AM:AM,'Combined P&L'!$C:$C,'P&L Overview'!$B19) -> 2.35401 | AL19: =SUMIFS('Combined P&L'!AN:AN,'Combined P&L'!$C:$C,'P&L Overview'!$B19) -> 0.2276 | AM19: =SUMIFS('Combined P&L'!AO:AO,'Combined P&L'!$C:$C,'P&L Overview'!$B19) -> 1.47836 | AN19: =SUMIFS('Combined P&L'!AP:AP,'Combined P&L'!$C:$C,'P&L Overview'!$B19) -> 0.66824 | AO19: =SUMIFS('Combined P&L'!AQ:AQ,'Combined P&L'!$C:$C,'P&L Overview'!$B19) -> 0.58613 | AP19: =SUMIFS('Combined P&L'!AR:AR,'Combined P&L'!$C:$C,'P&L Overview'!$B19) -> 0.0872
B20: Billable Expense Income | C20: =SUMIFS($L20:$AP20,$L$5:$AP$5,">"&C$42,$L$5:$AP$5,"<"&C$43) -> 0.3747 | D20: =SUMIFS($L20:$AP20,$L$5:$AP$5,">"&D$42,$L$5:$AP$5,"<"&D$43) -> 1.12194 | F20: =SUMIFS($L20:$AP20,$L$5:$AP$5,">"&F$42,$L$5:$AP$5,"<"&F$43) -> 0.78725 | G20: =SUMIFS($L20:$AP20,$L$5:$AP$5,">"&G$42,$L$5:$AP$5,"<"&G$43) -> 0.25783 | I20: =SUMIFS($L20:$AP20,$L$5:$AP$5,">"&I$42,$L$5:$AP$5,"<"&I$43) -> 0.79724 | J20: =SUMIFS($L20:$AP20,$L$5:$AP$5,">"&J$42,$L$5:$AP$5,"<"&J$43) -> 0.88223 | L20: =SUMIFS('Combined P&L'!N:N,'Combined P&L'!$C:$C,'P&L Overview'!$B20) -> 0.05 | M20: =SUMIFS('Combined P&L'!O:O,'Combined P&L'!$C:$C,'P&L Overview'!$B20) -> 0 | N20: =SUMIFS('Combined P&L'!P:P,'Combined P&L'!$C:$C,'P&L Overview'!$B20) -> 0 | O20: =SUMIFS('Combined P&L'!Q:Q,'Combined P&L'!$C:$C,'P&L Overview'!$B20) -> 0.025 | P20: =SUMIFS('Combined P&L'!R:R,'Combined P&L'!$C:$C,'P&L Overview'!$B20) -> 0 | Q20: =SUMIFS('Combined P&L'!S:S,'Combined P&L'!$C:$C,'P&L Overview'!$B20) -> 0 | R20: =SUMIFS('Combined P&L'!T:T,'Combined P&L'!$C:$C,'P&L Overview'!$B20) -> 0.2997 | S20: =SUMIFS('Combined P&L'!U:U,'Combined P&L'!$C:$C,'P&L Overview'!$B20) -> 0 | T20: =SUMIFS('Combined P&L'!V:V,'Combined P&L'!$C:$C,'P&L Overview'!$B20) -> 0 | U20: =SUMIFS('Combined P&L'!W:W,'Combined P&L'!$C:$C,'P&L Overview'!$B20) -> 0 | V20: =SUMIFS('Combined P&L'!X:X,'Combined P&L'!$C:$C,'P&L Overview'!$B20) -> 0 | W20: =SUMIFS('Combined P&L'!Y:Y,'Combined P&L'!$C:$C,'P&L Overview'!$B20) -> 0 | X20: =SUMIFS('Combined P&L'!Z:Z,'Combined P&L'!$C:$C,'P&L Overview'!$B20) -> 0.025 | Y20: =SUMIFS('Combined P&L'!AA:AA,'Combined P&L'!$C:$C,'P&L Overview'!$B20) -> 0.3996 | Z20: =SUMIFS('Combined P&L'!AB:AB,'Combined P&L'!$C:$C,'P&L Overview'!$B20) -> 0 | AA20: =SUMIFS('Combined P&L'!AC:AC,'Combined P&L'!$C:$C,'P&L Overview'!$B20) -> 0 | AB20: =SUMIFS('Combined P&L'!AD:AD,'Combined P&L'!$C:$C,'P&L Overview'!$B20) -> 0.07294 | AC20: =SUMIFS('Combined P&L'!AE:AE,'Combined P&L'!$C:$C,'P&L Overview'!$B20) -> 0 | AD20: =SUMIFS('Combined P&L'!AF:AF,'Combined P&L'!$C:$C,'P&L Overview'!$B20) -> 0.28971 | AE20: =SUMIFS('Combined P&L'!AG:AG,'Combined P&L'!$C:$C,'P&L Overview'!$B20) -> 0.30969 | AF20: =SUMIFS('Combined P&L'!AH:AH,'Combined P&L'!$C:$C,'P&L Overview'!$B20) -> 0 | AG20: =SUMIFS('Combined P&L'!AI:AI,'Combined P&L'!$C:$C,'P&L Overview'!$B20) -> 0 | AH20: =SUMIFS('Combined P&L'!AJ:AJ,'Combined P&L'!$C:$C,'P&L Overview'!$B20) -> 0 | AI20: =SUMIFS('Combined P&L'!AK:AK,'Combined P&L'!$C:$C,'P&L Overview'!$B20) -> 0.025 | AJ20: =SUMIFS('Combined P&L'!AL:AL,'Combined P&L'!$C:$C,'P&L Overview'!$B20) -> 0.15984 | AK20: =SUMIFS('Combined P&L'!AM:AM,'Combined P&L'!$C:$C,'P&L Overview'!$B20) -> 0 | AL20: =SUMIFS('Combined P&L'!AN:AN,'Combined P&L'!$C:$C,'P&L Overview'!$B20) -> 0.075 | AM20: =SUMIFS('Combined P&L'!AO:AO,'Combined P&L'!$C:$C,'P&L Overview'!$B20) -> 0 | AN20: =SUMIFS('Combined P&L'!AP:AP,'Combined P&L'!$C:$C,'P&L Overview'!$B20) -> 0 | AO20: =SUMIFS('Combined P&L'!AQ:AQ,'Combined P&L'!$C:$C,'P&L Overview'!$B20) -> 0.02299 | AP20: =SUMIFS('Combined P&L'!AR:AR,'Combined P&L'!$C:$C,'P&L Overview'!$B20) -> 0
B21: Offshore Recruiting | C21: =SUMIFS($L21:$AP21,$L$5:$AP$5,">"&C$42,$L$5:$AP$5,"<"&C$43) -> 23.6 | D21: =SUMIFS($L21:$AP21,$L$5:$AP$5,">"&D$42,$L$5:$AP$5,"<"&D$43) -> 0.2 | F21: =SUMIFS($L21:$AP21,$L$5:$AP$5,">"&F$42,$L$5:$AP$5,"<"&F$43) -> 0.2 | G21: =SUMIFS($L21:$AP21,$L$5:$AP$5,">"&G$42,$L$5:$AP$5,"<"&G$43) -> 0 | I21: =SUMIFS($L21:$AP21,$L$5:$AP$5,">"&I$42,$L$5:$AP$5,"<"&I$43) -> 16.735 | J21: =SUMIFS($L21:$AP21,$L$5:$AP$5,">"&J$42,$L$5:$AP$5,"<"&J$43) -> 0 | L21: =SUMIFS('Combined P&L'!N:N,'Combined P&L'!$C:$C,'P&L Overview'!$B21) -> 0.5 | M21: =SUMIFS('Combined P&L'!O:O,'Combined P&L'!$C:$C,'P&L Overview'!$B21) -> 3 | N21: =SUMIFS('Combined P&L'!P:P,'Combined P&L'!$C:$C,'P&L Overview'!$B21) -> 0 | O21: =SUMIFS('Combined P&L'!Q:Q,'Combined P&L'!$C:$C,'P&L Overview'!$B21) -> 0 | P21: =SUMIFS('Combined P&L'!R:R,'Combined P&L'!$C:$C,'P&L Overview'!$B21) -> 3 | Q21: =SUMIFS('Combined P&L'!S:S,'Combined P&L'!$C:$C,'P&L Overview'!$B21) -> 0.565 | R21: =SUMIFS('Combined P&L'!T:T,'Combined P&L'!$C:$C,'P&L Overview'!$B21) -> 10.5 | S21: =SUMIFS('Combined P&L'!U:U,'Combined P&L'!$C:$C,'P&L Overview'!$B21) -> 6.5 | T21: =SUMIFS('Combined P&L'!V:V,'Combined P&L'!$C:$C,'P&L Overview'!$B21) -> 0.5 | U21: =SUMIFS('Combined P&L'!W:W,'Combined P&L'!$C:$C,'P&L Overview'!$B21) -> -0.965 | V21: =SUMIFS('Combined P&L'!X:X,'Combined P&L'!$C:$C,'P&L Overview'!$B21) -> 0 | W21: =SUMIFS('Combined P&L'!Y:Y,'Combined P&L'!$C:$C,'P&L Overview'!$B21) -> 0 | X21: =SUMIFS('Combined P&L'!Z:Z,'Combined P&L'!$C:$C,'P&L Overview'!$B21) -> 0.1 | Y21: =SUMIFS('Combined P&L'!AA:AA,'Combined P&L'!$C:$C,'P&L Overview'!$B21) -> 0 | Z21: =SUMIFS('Combined P&L'!AB:AB,'Combined P&L'!$C:$C,'P&L Overview'!$B21) -> 0.1 | AA21: =SUMIFS('Combined P&L'!AC:AC,'Combined P&L'!$C:$C,'P&L Overview'!$B21) -> 0 | AB21: =SUMIFS('Combined P&L'!AD:AD,'Combined P&L'!$C:$C,'P&L Overview'!$B21) -> 0 | AC21: =SUMIFS('Combined P&L'!AE:AE,'Combined P&L'!$C:$C,'P&L Overview'!$B21) -> 0 | AD21: =SUMIFS('Combined P&L'!AF:AF,'Combined P&L'!$C:$C,'P&L Overview'!$B21) -> 0 | AE21: =SUMIFS('Combined P&L'!AG:AG,'Combined P&L'!$C:$C,'P&L Overview'!$B21) -> 0 | AF21: =SUMIFS('Combined P&L'!AH:AH,'Combined P&L'!$C:$C,'P&L Overview'!$B21) -> 0 | AG21: =SUMIFS('Combined P&L'!AI:AI,'Combined P&L'!$C:$C,'P&L Overview'!$B21) -> 0 | AH21: =SUMIFS('Combined P&L'!AJ:AJ,'Combined P&L'!$C:$C,'P&L Overview'!$B21) -> 0 | AI21: =SUMIFS('Combined P&L'!AK:AK,'Combined P&L'!$C:$C,'P&L Overview'!$B21) -> 0 | AJ21: =SUMIFS('Combined P&L'!AL:AL,'Combined P&L'!$C:$C,'P&L Overview'!$B21) -> 0 | AK21: =SUMIFS('Combined P&L'!AM:AM,'Combined P&L'!$C:$C,'P&L Overview'!$B21) -> 0 | AL21: =SUMIFS('Combined P&L'!AN:AN,'Combined P&L'!$C:$C,'P&L Overview'!$B21) -> 0 | AM21: =SUMIFS('Combined P&L'!AO:AO,'Combined P&L'!$C:$C,'P&L Overview'!$B21) -> 0 | AN21: =SUMIFS('Combined P&L'!AP:AP,'Combined P&L'!$C:$C,'P&L Overview'!$B21) -> 0 | AO21: =SUMIFS('Combined P&L'!AQ:AQ,'Combined P&L'!$C:$C,'P&L Overview'!$B21) -> 0 | AP21: =SUMIFS('Combined P&L'!AR:AR,'Combined P&L'!$C:$C,'P&L Overview'!$B21) -> 0
B22: Total Recurring Revenue | C22: =SUM(C17:C21) -> 40.6501 | D22: =SUM(D17:D21) -> 51.53373 | F22: =SUM(F17:F21) -> 38.9822 | G22: =SUM(G17:G21) -> 70.95371 | I22: =SUM(I17:I21) -> 59.00012 | J22: =SUM(J17:J21) -> 84.75482 | L22: =SUM(L17:L21) -> 7.5636 | M22: =SUM(M17:M21) -> 6.5112 | N22: =SUM(N17:N21) -> 0.1162 | O22: =SUM(O17:O21) -> 0.1406 | P22: =SUM(P17:P21) -> 3.592 | Q22: =SUM(Q17:Q21) -> 1.3718 | R22: =SUM(R17:R21) -> 11.4653 | S22: =SUM(S17:S21) -> 7.3414 | ... AP22: =SUM(AP17:AP21) -> 0.0872
B24: Total Revenue | C24: =+C22+C15 -> 1134.9659 | D24: =+D22+D15 -> 1879.3831 | F24: =+F22+F15 -> 997.8731 | G24: =+G22+G15 -> 1671.0212 | I24: =+I22+I15 -> 1473.7119 | J24: =+J22+J15 -> 2456.4862 | L24: =+L22+L15 -> 80.9131 | M24: =+M22+M15 -> 81.2557 | N24: =+N22+N15 -> 78.1122 | O24: =+O22+O15 -> 83.3533 | P24: =+P22+P15 -> 90.19615 | Q24: =+Q22+Q15 -> 89.9158 | R24: =+R22+R15 -> 104.68205 | S24: =+S22+S15 -> 104.11675 | ... AP24: =+AP22+AP15 -> 251.42585
B26: Expenses
B27: Indirect Labor | C27: =SUMIFS($L27:$AP27,$L$5:$AP$5,">"&C$42,$L$5:$AP$5,"<"&C$43) -> 101.3752 | D27: =SUMIFS($L27:$AP27,$L$5:$AP$5,">"&D$42,$L$5:$AP$5,"<"&D$43) -> 281.24054 | F27: =SUMIFS($L27:$AP27,$L$5:$AP$5,">"&F$42,$L$5:$AP$5,"<"&F$43) -> 136.29648 | G27: =SUMIFS($L27:$AP27,$L$5:$AP$5,">"&G$42,$L$5:$AP$5,"<"&G$43) -> 357.27472 | I27: =SUMIFS($L27:$AP27,$L$5:$AP$5,">"&I$42,$L$5:$AP$5,"<"&I$43) -> 184.76374 | J27: =SUMIFS($L27:$AP27,$L$5:$AP$5,">"&J$42,$L$5:$AP$5,"<"&J$43) -> 466.92604 | L27: =SUMIFS('Combined P&L'!N:N,'Combined P&L'!$C:$C,'P&L Overview'!$B27) -> 3.09346 | M27: =SUMIFS('Combined P&L'!O:O,'Combined P&L'!$C:$C,'P&L Overview'!$B27) -> 4.63017 | N27: =SUMIFS('Combined P&L'!P:P,'Combined P&L'!$C:$C,'P&L Overview'!$B27) -> 4.39507 | O27: =SUMIFS('Combined P&L'!Q:Q,'Combined P&L'!$C:$C,'P&L Overview'!$B27) -> 5.86387 | P27: =SUMIFS('Combined P&L'!R:R,'Combined P&L'!$C:$C,'P&L Overview'!$B27) -> 7.37233 | Q27: =SUMIFS('Combined P&L'!S:S,'Combined P&L'!$C:$C,'P&L Overview'!$B27) -> 4.9504 | R27: =SUMIFS('Combined P&L'!T:T,'Combined P&L'!$C:$C,'P&L Overview'!$B27) -> 4.9504 | S27: =SUMIFS('Combined P&L'!U:U,'Combined P&L'!$C:$C,'P&L Overview'!$B27) -> 4.70035 | T27: =SUMIFS('Combined P&L'!V:V,'Combined P&L'!$C:$C,'P&L Overview'!$B27) -> 4.9504 | U27: =SUMIFS('Combined P&L'!W:W,'Combined P&L'!$C:$C,'P&L Overview'!$B27) -> 5.99987 | V27: =SUMIFS('Combined P&L'!X:X,'Combined P&L'!$C:$C,'P&L Overview'!$B27) -> 26.02876 | W27: =SUMIFS('Combined P&L'!Y:Y,'Combined P&L'!$C:$C,'P&L Overview'!$B27) -> 24.44012 | X27: =SUMIFS('Combined P&L'!Z:Z,'Combined P&L'!$C:$C,'P&L Overview'!$B27) -> 21.05234 | Y27: =SUMIFS('Combined P&L'!AA:AA,'Combined P&L'!$C:$C,'P&L Overview'!$B27) -> 19.91603 | Z27: =SUMIFS('Combined P&L'!AB:AB,'Combined P&L'!$C:$C,'P&L Overview'!$B27) -> 11.74387 | AA27: =SUMIFS('Combined P&L'!AC:AC,'Combined P&L'!$C:$C,'P&L Overview'!$B27) -> 19.61792 | AB27: =SUMIFS('Combined P&L'!AD:AD,'Combined P&L'!$C:$C,'P&L Overview'!$B27) -> 20.66978 | AC27: =SUMIFS('Combined P&L'!AE:AE,'Combined P&L'!$C:$C,'P&L Overview'!$B27) -> 20.6939 | AD27: =SUMIFS('Combined P&L'!AF:AF,'Combined P&L'!$C:$C,'P&L Overview'!$B27) -> 22.60264 | AE27: =SUMIFS('Combined P&L'!AG:AG,'Combined P&L'!$C:$C,'P&L Overview'!$B27) -> 19.96128 | AF27: =SUMIFS('Combined P&L'!AH:AH,'Combined P&L'!$C:$C,'P&L Overview'!$B27) -> 27.60563 | AG27: =SUMIFS('Combined P&L'!AI:AI,'Combined P&L'!$C:$C,'P&L Overview'!$B27) -> 34.18589 | AH27: =SUMIFS('Combined P&L'!AJ:AJ,'Combined P&L'!$C:$C,'P&L Overview'!$B27) -> 29.73157 | AI27: =SUMIFS('Combined P&L'!AK:AK,'Combined P&L'!$C:$C,'P&L Overview'!$B27) -> 33.45969 | AJ27: =SUMIFS('Combined P&L'!AL:AL,'Combined P&L'!$C:$C,'P&L Overview'!$B27) -> 36.2536 | AK27: =SUMIFS('Combined P&L'!AM:AM,'Combined P&L'!$C:$C,'P&L Overview'!$B27) -> 33.60751 | AL27: =SUMIFS('Combined P&L'!AN:AN,'Combined P&L'!$C:$C,'P&L Overview'!$B27) -> 57.19924 | AM27: =SUMIFS('Combined P&L'!AO:AO,'Combined P&L'!$C:$C,'P&L Overview'!$B27) -> 58.24595 | AN27: =SUMIFS('Combined P&L'!AP:AP,'Combined P&L'!$C:$C,'P&L Overview'!$B27) -> 54.06923 | AO27: =SUMIFS('Combined P&L'!AQ:AQ,'Combined P&L'!$C:$C,'P&L Overview'!$B27) -> 60.00381 | AP27: =SUMIFS('Combined P&L'!AR:AR,'Combined P&L'!$C:$C,'P&L Overview'!$B27) -> 57.89538
B28: Bookkeeper Wages | C28: =SUMIFS($L28:$AP28,$L$5:$AP$5,">"&C$42,$L$5:$AP$5,"<"&C$43) -> 183.36903 | D28: =SUMIFS($L28:$AP28,$L$5:$AP$5,">"&D$42,$L$5:$AP$5,"<"&D$43) -> 316.18462 | F28: =SUMIFS($L28:$AP28,$L$5:$AP$5,">"&F$42,$L$5:$AP$5,"<"&F$43) -> 147.26813 | G28: =SUMIFS($L28:$AP28,$L$5:$AP$5,">"&G$42,$L$5:$AP$5,"<"&G$43) -> 267.7574 | I28: =SUMIFS($L28:$AP28,$L$5:$AP$5,">"&I$42,$L$5:$AP$5,"<"&I$43) -> 226.32031 | J28: =SUMIFS($L28:$AP28,$L$5:$AP$5,">"&J$42,$L$5:$AP$5,"<"&J$43) -> 420.0952 | L28: =SUMIFS('Combined P&L'!N:N,'Combined P&L'!$C:$C,'P&L Overview'!$B28) -> 9.555 | M28: =SUMIFS('Combined P&L'!O:O,'Combined P&L'!$C:$C,'P&L Overview'!$B28) -> 9.555 | N28: =SUMIFS('Combined P&L'!P:P,'Combined P&L'!$C:$C,'P&L Overview'!$B28) -> 10.3972 | O28: =SUMIFS('Combined P&L'!Q:Q,'Combined P&L'!$C:$C,'P&L Overview'!$B28) -> 14.99967 | P28: =SUMIFS('Combined P&L'!R:R,'Combined P&L'!$C:$C,'P&L Overview'!$B28) -> 18.0098 | Q28: =SUMIFS('Combined P&L'!S:S,'Combined P&L'!$C:$C,'P&L Overview'!$B28) -> 13.89127 | R28: =SUMIFS('Combined P&L'!T:T,'Combined P&L'!$C:$C,'P&L Overview'!$B28) -> 14.04824 | S28: =SUMIFS('Combined P&L'!U:U,'Combined P&L'!$C:$C,'P&L Overview'!$B28) -> 13.39091 | T28: =SUMIFS('Combined P&L'!V:V,'Combined P&L'!$C:$C,'P&L Overview'!$B28) -> 14.66931 | U28: =SUMIFS('Combined P&L'!W:W,'Combined P&L'!$C:$C,'P&L Overview'!$B28) -> 15.88253 | V28: =SUMIFS('Combined P&L'!X:X,'Combined P&L'!$C:$C,'P&L Overview'!$B28) -> 27.18867 | W28: =SUMIFS('Combined P&L'!Y:Y,'Combined P&L'!$C:$C,'P&L Overview'!$B28) -> 21.78143 | X28: =SUMIFS('Combined P&L'!Z:Z,'Combined P&L'!$C:$C,'P&L Overview'!$B28) -> 19.40233 | Y28: =SUMIFS('Combined P&L'!AA:AA,'Combined P&L'!$C:$C,'P&L Overview'!$B28) -> 16.40053 | Z28: =SUMIFS('Combined P&L'!AB:AB,'Combined P&L'!$C:$C,'P&L Overview'!$B28) -> 19.56983 | AA28: =SUMIFS('Combined P&L'!AC:AC,'Combined P&L'!$C:$C,'P&L Overview'!$B28) -> 22.1542 | AB28: =SUMIFS('Combined P&L'!AD:AD,'Combined P&L'!$C:$C,'P&L Overview'!$B28) -> 20.79154 | AC28: =SUMIFS('Combined P&L'!AE:AE,'Combined P&L'!$C:$C,'P&L Overview'!$B28) -> 21.04079 | AD28: =SUMIFS('Combined P&L'!AF:AF,'Combined P&L'!$C:$C,'P&L Overview'!$B28) -> 27.90891 | AE28: =SUMIFS('Combined P&L'!AG:AG,'Combined P&L'!$C:$C,'P&L Overview'!$B28) -> 29.547 | AF28: =SUMIFS('Combined P&L'!AH:AH,'Combined P&L'!$C:$C,'P&L Overview'!$B28) -> 33.44727 | AG28: =SUMIFS('Combined P&L'!AI:AI,'Combined P&L'!$C:$C,'P&L Overview'!$B28) -> 37.79432 | AH28: =SUMIFS('Combined P&L'!AJ:AJ,'Combined P&L'!$C:$C,'P&L Overview'!$B28) -> 34.06332 | AI28: =SUMIFS('Combined P&L'!AK:AK,'Combined P&L'!$C:$C,'P&L Overview'!$B28) -> 34.06458 | AJ28: =SUMIFS('Combined P&L'!AL:AL,'Combined P&L'!$C:$C,'P&L Overview'!$B28) -> 38.37888 | AK28: =SUMIFS('Combined P&L'!AM:AM,'Combined P&L'!$C:$C,'P&L Overview'!$B28) -> 29.70152 | AL28: =SUMIFS('Combined P&L'!AN:AN,'Combined P&L'!$C:$C,'P&L Overview'!$B28) -> 37.4225 | AM28: =SUMIFS('Combined P&L'!AO:AO,'Combined P&L'!$C:$C,'P&L Overview'!$B28) -> 38.7723 | AN28: =SUMIFS('Combined P&L'!AP:AP,'Combined P&L'!$C:$C,'P&L Overview'!$B28) -> 38.29477 | AO28: =SUMIFS('Combined P&L'!AQ:AQ,'Combined P&L'!$C:$C,'P&L Overview'!$B28) -> 40.69983 | AP28: =SUMIFS('Combined P&L'!AR:AR,'Combined P&L'!$C:$C,'P&L Overview'!$B28) -> 44.4876
B29: Client Lead Wages | C29: =SUMIFS($L29:$AP29,$L$5:$AP$5,">"&C$42,$L$5:$AP$5,"<"&C$43) -> 286.16129 | D29: =SUMIFS($L29:$AP29,$L$5:$AP$5,">"&D$42,$L$5:$AP$5,"<"&D$43) -> 352.95844 | F29: =SUMIFS($L29:$AP29,$L$5:$AP$5,">"&F$42,$L$5:$AP$5,"<"&F$43) -> 201.27983 | G29: =SUMIFS($L29:$AP29,$L$5:$AP$5,">"&G$42,$L$5:$AP$5,"<"&G$43) -> 202.05309 | I29: =SUMIFS($L29:$AP29,$L$5:$AP$5,">"&I$42,$L$5:$AP$5,"<"&I$43) -> 351.95999 | J29: =SUMIFS($L29:$AP29,$L$5:$AP$5,">"&J$42,$L$5:$AP$5,"<"&J$43) -> 350.46762 | L29: =SUMIFS('Combined P&L'!N:N,'Combined P&L'!$C:$C,'P&L Overview'!$B29) -> 9.96108 | M29: =SUMIFS('Combined P&L'!O:O,'Combined P&L'!$C:$C,'P&L Overview'!$B29) -> 13.85026 | N29: =SUMIFS('Combined P&L'!P:P,'Combined P&L'!$C:$C,'P&L Overview'!$B29) -> 12.79054 | O29: =SUMIFS('Combined P&L'!Q:Q,'Combined P&L'!$C:$C,'P&L Overview'!$B29) -> 14.57145 | P29: =SUMIFS('Combined P&L'!R:R,'Combined P&L'!$C:$C,'P&L Overview'!$B29) -> 28.28563 | Q29: =SUMIFS('Combined P&L'!S:S,'Combined P&L'!$C:$C,'P&L Overview'!$B29) -> 26.54254 | R29: =SUMIFS('Combined P&L'!T:T,'Combined P&L'!$C:$C,'P&L Overview'!$B29) -> 28.31119 | S29: =SUMIFS('Combined P&L'!U:U,'Combined P&L'!$C:$C,'P&L Overview'!$B29) -> 28.18746 | T29: =SUMIFS('Combined P&L'!V:V,'Combined P&L'!$C:$C,'P&L Overview'!$B29) -> 30.86801 | U29: =SUMIFS('Combined P&L'!W:W,'Combined P&L'!$C:$C,'P&L Overview'!$B29) -> 31.62128 | V29: =SUMIFS('Combined P&L'!X:X,'Combined P&L'!$C:$C,'P&L Overview'!$B29) -> 28.44974 | W29: =SUMIFS('Combined P&L'!Y:Y,'Combined P&L'!$C:$C,'P&L Overview'!$B29) -> 32.72211 | X29: =SUMIFS('Combined P&L'!Z:Z,'Combined P&L'!$C:$C,'P&L Overview'!$B29) -> 32.78076 | Y29: =SUMIFS('Combined P&L'!AA:AA,'Combined P&L'!$C:$C,'P&L Overview'!$B29) -> 23.36184 | Z29: =SUMIFS('Combined P&L'!AB:AB,'Combined P&L'!$C:$C,'P&L Overview'!$B29) -> 26.91427 | AA29: =SUMIFS('Combined P&L'!AC:AC,'Combined P&L'!$C:$C,'P&L Overview'!$B29) -> 28.81298 | AB29: =SUMIFS('Combined P&L'!AD:AD,'Combined P&L'!$C:$C,'P&L Overview'!$B29) -> 30.65875 | AC29: =SUMIFS('Combined P&L'!AE:AE,'Combined P&L'!$C:$C,'P&L Overview'!$B29) -> 29.2716 | AD29: =SUMIFS('Combined P&L'!AF:AF,'Combined P&L'!$C:$C,'P&L Overview'!$B29) -> 29.47963 | AE29: =SUMIFS('Combined P&L'!AG:AG,'Combined P&L'!$C:$C,'P&L Overview'!$B29) -> 26.83064 | AF29: =SUMIFS('Combined P&L'!AH:AH,'Combined P&L'!$C:$C,'P&L Overview'!$B29) -> 29.78555 | AG29: =SUMIFS('Combined P&L'!AI:AI,'Combined P&L'!$C:$C,'P&L Overview'!$B29) -> 32.89937 | AH29: =SUMIFS('Combined P&L'!AJ:AJ,'Combined P&L'!$C:$C,'P&L Overview'!$B29) -> 29.49334 | AI29: =SUMIFS('Combined P&L'!AK:AK,'Combined P&L'!$C:$C,'P&L Overview'!$B29) -> 32.66971 | AJ29: =SUMIFS('Combined P&L'!AL:AL,'Combined P&L'!$C:$C,'P&L Overview'!$B29) -> 26.1149 | AK29: =SUMIFS('Combined P&L'!AM:AM,'Combined P&L'!$C:$C,'P&L Overview'!$B29) -> 21.9055 | AL29: =SUMIFS('Combined P&L'!AN:AN,'Combined P&L'!$C:$C,'P&L Overview'!$B29) -> 30.75844 | AM29: =SUMIFS('Combined P&L'!AO:AO,'Combined P&L'!$C:$C,'P&L Overview'!$B29) -> 31.59038 | AN29: =SUMIFS('Combined P&L'!AP:AP,'Combined P&L'!$C:$C,'P&L Overview'!$B29) -> 27.69992 | AO29: =SUMIFS('Combined P&L'!AQ:AQ,'Combined P&L'!$C:$C,'P&L Overview'!$B29) -> 31.24024 | AP29: =SUMIFS('Combined P&L'!AR:AR,'Combined P&L'!$C:$C,'P&L Overview'!$B29) -> 32.74371
B30: Onboarding Team Wages | C30: =SUMIFS($L30:$AP30,$L$5:$AP$5,">"&C$42,$L$5:$AP$5,"<"&C$43) -> 122.81255 | D30: =SUMIFS($L30:$AP30,$L$5:$AP$5,">"&D$42,$L$5:$AP$5,"<"&D$43) -> 152.16972 | F30: =SUMIFS($L30:$AP30,$L$5:$AP$5,">"&F$42,$L$5:$AP$5,"<"&F$43) -> 73.94962 | G30: =SUMIFS($L30:$AP30,$L$5:$AP$5,">"&G$42,$L$5:$AP$5,"<"&G$43) -> 111.27999 | I30: =SUMIFS($L30:$AP30,$L$5:$AP$5,">"&I$42,$L$5:$AP$5,"<"&I$43) -> 115.8168 | J30: =SUMIFS($L30:$AP30,$L$5:$AP$5,">"&J$42,$L$5:$AP$5,"<"&J$43) -> 186.54354 | L30: =SUMIFS('Combined P&L'!N:N,'Combined P&L'!$C:$C,'P&L Overview'!$B30) -> 9.13728 | M30: =SUMIFS('Combined P&L'!O:O,'Combined P&L'!$C:$C,'P&L Overview'!$B30) -> 8.96296 | N30: =SUMIFS('Combined P&L'!P:P,'Combined P&L'!$C:$C,'P&L Overview'!$B30) -> 10.19584 | O30: =SUMIFS('Combined P&L'!Q:Q,'Combined P&L'!$C:$C,'P&L Overview'!$B30) -> 15.04429 | P30: =SUMIFS('Combined P&L'!R:R,'Combined P&L'!$C:$C,'P&L Overview'!$B30) -> 16.63744 | Q30: =SUMIFS('Combined P&L'!S:S,'Combined P&L'!$C:$C,'P&L Overview'!$B30) -> 7.49499 | R30: =SUMIFS('Combined P&L'!T:T,'Combined P&L'!$C:$C,'P&L Overview'!$B30) -> 7.98202 | S30: =SUMIFS('Combined P&L'!U:U,'Combined P&L'!$C:$C,'P&L Overview'!$B30) -> 5.90274 | T30: =SUMIFS('Combined P&L'!V:V,'Combined P&L'!$C:$C,'P&L Overview'!$B30) -> 7.76763 | U30: =SUMIFS('Combined P&L'!W:W,'Combined P&L'!$C:$C,'P&L Overview'!$B30) -> 8.21417 | V30: =SUMIFS('Combined P&L'!X:X,'Combined P&L'!$C:$C,'P&L Overview'!$B30) -> 12.62272 | W30: =SUMIFS('Combined P&L'!Y:Y,'Combined P&L'!$C:$C,'P&L Overview'!$B30) -> 12.85047 | X30: =SUMIFS('Combined P&L'!Z:Z,'Combined P&L'!$C:$C,'P&L Overview'!$B30) -> 10.34556 | Y30: =SUMIFS('Combined P&L'!AA:AA,'Combined P&L'!$C:$C,'P&L Overview'!$B30) -> 8.08798 | Z30: =SUMIFS('Combined P&L'!AB:AB,'Combined P&L'!$C:$C,'P&L Overview'!$B30) -> 9.75287 | AA30: =SUMIFS('Combined P&L'!AC:AC,'Combined P&L'!$C:$C,'P&L Overview'!$B30) -> 10.28 | AB30: =SUMIFS('Combined P&L'!AD:AD,'Combined P&L'!$C:$C,'P&L Overview'!$B30) -> 11.13632 | AC30: =SUMIFS('Combined P&L'!AE:AE,'Combined P&L'!$C:$C,'P&L Overview'!$B30) -> 10.87432 | AD30: =SUMIFS('Combined P&L'!AF:AF,'Combined P&L'!$C:$C,'P&L Overview'!$B30) -> 13.47257 | AE30: =SUMIFS('Combined P&L'!AG:AG,'Combined P&L'!$C:$C,'P&L Overview'!$B30) -> 12.70407 | AF30: =SUMIFS('Combined P&L'!AH:AH,'Combined P&L'!$C:$C,'P&L Overview'!$B30) -> 14.69884 | AG30: =SUMIFS('Combined P&L'!AI:AI,'Combined P&L'!$C:$C,'P&L Overview'!$B30) -> 15.54306 | AH30: =SUMIFS('Combined P&L'!AJ:AJ,'Combined P&L'!$C:$C,'P&L Overview'!$B30) -> 14.34361 | AI30: =SUMIFS('Combined P&L'!AK:AK,'Combined P&L'!$C:$C,'P&L Overview'!$B30) -> 20.93052 | AJ30: =SUMIFS('Combined P&L'!AL:AL,'Combined P&L'!$C:$C,'P&L Overview'!$B30) -> 16.55394 | AK30: =SUMIFS('Combined P&L'!AM:AM,'Combined P&L'!$C:$C,'P&L Overview'!$B30) -> 11.52661 | AL30: =SUMIFS('Combined P&L'!AN:AN,'Combined P&L'!$C:$C,'P&L Overview'!$B30) -> 14.93883 | AM30: =SUMIFS('Combined P&L'!AO:AO,'Combined P&L'!$C:$C,'P&L Overview'!$B30) -> 15.58352 | AN30: =SUMIFS('Combined P&L'!AP:AP,'Combined P&L'!$C:$C,'P&L Overview'!$B30) -> 19.6034 | AO30: =SUMIFS('Combined P&L'!AQ:AQ,'Combined P&L'!$C:$C,'P&L Overview'!$B30) -> 16.64457 | AP30: =SUMIFS('Combined P&L'!AR:AR,'Combined P&L'!$C:$C,'P&L Overview'!$B30) -> 16.42912
B31: Owner Wages | C31: =SUMIFS($L31:$AP31,$L$5:$AP$5,">"&C$42,$L$5:$AP$5,"<"&C$43) -> 0 | D31: =SUMIFS($L31:$AP31,$L$5:$AP$5,">"&D$42,$L$5:$AP$5,"<"&D$43) -> 90.66704 | F31: =SUMIFS($L31:$AP31,$L$5:$AP$5,">"&F$42,$L$5:$AP$5,"<"&F$43) -> 45.46612 | G31: =SUMIFS($L31:$AP31,$L$5:$AP$5,">"&G$42,$L$5:$AP$5,"<"&G$43) -> 63.14302 | I31: =SUMIFS($L31:$AP31,$L$5:$AP$5,">"&I$42,$L$5:$AP$5,"<"&I$43) -> 35.94325 | J31: =SUMIFS($L31:$AP31,$L$5:$AP$5,">"&J$42,$L$5:$AP$5,"<"&J$43) -> 108.34394 | L31: =SUMIFS('Combined P&L'!N:N,'Combined P&L'!$C:$C,'P&L Overview'!$B31) -> 0 | M31: =SUMIFS('Combined P&L'!O:O,'Combined P&L'!$C:$C,'P&L Overview'!$B31) -> 0 | N31: =SUMIFS('Combined P&L'!P:P,'Combined P&L'!$C:$C,'P&L Overview'!$B31) -> 0 | O31: =SUMIFS('Combined P&L'!Q:Q,'Combined P&L'!$C:$C,'P&L Overview'!$B31) -> 0 | P31: =SUMIFS('Combined P&L'!R:R,'Combined P&L'!$C:$C,'P&L Overview'!$B31) -> 0 | Q31: =SUMIFS('Combined P&L'!S:S,'Combined P&L'!$C:$C,'P&L Overview'!$B31) -> 0 | R31: =SUMIFS('Combined P&L'!T:T,'Combined P&L'!$C:$C,'P&L Overview'!$B31) -> 0 | S31: =SUMIFS('Combined P&L'!U:U,'Combined P&L'!$C:$C,'P&L Overview'!$B31) -> 0 | T31: =SUMIFS('Combined P&L'!V:V,'Combined P&L'!$C:$C,'P&L Overview'!$B31) -> 0 | U31: =SUMIFS('Combined P&L'!W:W,'Combined P&L'!$C:$C,'P&L Overview'!$B31) -> 0 | V31: =SUMIFS('Combined P&L'!X:X,'Combined P&L'!$C:$C,'P&L Overview'!$B31) -> 0 | W31: =SUMIFS('Combined P&L'!Y:Y,'Combined P&L'!$C:$C,'P&L Overview'!$B31) -> 0 | X31: =SUMIFS('Combined P&L'!Z:Z,'Combined P&L'!$C:$C,'P&L Overview'!$B31) -> 0 | Y31: =SUMIFS('Combined P&L'!AA:AA,'Combined P&L'!$C:$C,'P&L Overview'!$B31) -> 0 | Z31: =SUMIFS('Combined P&L'!AB:AB,'Combined P&L'!$C:$C,'P&L Overview'!$B31) -> 8.90639 | AA31: =SUMIFS('Combined P&L'!AC:AC,'Combined P&L'!$C:$C,'P&L Overview'!$B31) -> 9.23323 | AB31: =SUMIFS('Combined P&L'!AD:AD,'Combined P&L'!$C:$C,'P&L Overview'!$B31) -> 9.10884 | AC31: =SUMIFS('Combined P&L'!AE:AE,'Combined P&L'!$C:$C,'P&L Overview'!$B31) -> 8.69479 | AD31: =SUMIFS('Combined P&L'!AF:AF,'Combined P&L'!$C:$C,'P&L Overview'!$B31) -> 9.52287 | AE31: =SUMIFS('Combined P&L'!AG:AG,'Combined P&L'!$C:$C,'P&L Overview'!$B31) -> 8.69481 | AF31: =SUMIFS('Combined P&L'!AH:AH,'Combined P&L'!$C:$C,'P&L Overview'!$B31) -> 9.10884 | AG31: =SUMIFS('Combined P&L'!AI:AI,'Combined P&L'!$C:$C,'P&L Overview'!$B31) -> 9.52287 | AH31: =SUMIFS('Combined P&L'!AJ:AJ,'Combined P&L'!$C:$C,'P&L Overview'!$B31) -> 8.28076 | AI31: =SUMIFS('Combined P&L'!AK:AK,'Combined P&L'!$C:$C,'P&L Overview'!$B31) -> 9.59364 | AJ31: =SUMIFS('Combined P&L'!AL:AL,'Combined P&L'!$C:$C,'P&L Overview'!$B31) -> 9.27621 | AK31: =SUMIFS('Combined P&L'!AM:AM,'Combined P&L'!$C:$C,'P&L Overview'!$B31) -> 8.32263 | AL31: =SUMIFS('Combined P&L'!AN:AN,'Combined P&L'!$C:$C,'P&L Overview'!$B31) -> 9.10883 | AM31: =SUMIFS('Combined P&L'!AO:AO,'Combined P&L'!$C:$C,'P&L Overview'!$B31) -> 9.10883 | AN31: =SUMIFS('Combined P&L'!AP:AP,'Combined P&L'!$C:$C,'P&L Overview'!$B31) -> 8.69481 | AO31: =SUMIFS('Combined P&L'!AQ:AQ,'Combined P&L'!$C:$C,'P&L Overview'!$B31) -> 9.10884 | AP31: =SUMIFS('Combined P&L'!AR:AR,'Combined P&L'!$C:$C,'P&L Overview'!$B31) -> 9.52287
B32: S&M Wages | C32: =SUMIFS($L32:$AP32,$L$5:$AP$5,">"&C$42,$L$5:$AP$5,"<"&C$43) -> 0 | D32: =SUMIFS($L32:$AP32,$L$5:$AP$5,">"&D$42,$L$5:$AP$5,"<"&D$43) -> 19.14963 | F32: =SUMIFS($L32:$AP32,$L$5:$AP$5,">"&F$42,$L$5:$AP$5,"<"&F$43) -> 3.09945 | G32: =SUMIFS($L32:$AP32,$L$5:$AP$5,">"&G$42,$L$5:$AP$5,"<"&G$43) -> 51.94131 | I32: =SUMIFS($L32:$AP32,$L$5:$AP$5,">"&I$42,$L$5:$AP$5,"<"&I$43) -> 1.4668 | J32: =SUMIFS($L32:$AP32,$L$5:$AP$5,">"&J$42,$L$5:$AP$5,"<"&J$43) -> 61.42838 | L32: =SUMIFS('Combined P&L'!N:N,'Combined P&L'!$C:$C,'P&L Overview'!$B32) -> 0 | M32: =SUMIFS('Combined P&L'!O:O,'Combined P&L'!$C:$C,'P&L Overview'!$B32) -> 0 | N32: =SUMIFS('Combined P&L'!P:P,'Combined P&L'!$C:$C,'P&L Overview'!$B32) -> 0 | O32: =SUMIFS('Combined P&L'!Q:Q,'Combined P&L'!$C:$C,'P&L Overview'!$B32) -> 0 | P32: =SUMIFS('Combined P&L'!R:R,'Combined P&L'!$C:$C,'P&L Overview'!$B32) -> 0 | Q32: =SUMIFS('Combined P&L'!S:S,'Combined P&L'!$C:$C,'P&L Overview'!$B32) -> 0 | R32: =SUMIFS('Combined P&L'!T:T,'Combined P&L'!$C:$C,'P&L Overview'!$B32) -> 0 | S32: =SUMIFS('Combined P&L'!U:U,'Combined P&L'!$C:$C,'P&L Overview'!$B32) -> 0 | T32: =SUMIFS('Combined P&L'!V:V,'Combined P&L'!$C:$C,'P&L Overview'!$B32) -> 0 | U32: =SUMIFS('Combined P&L'!W:W,'Combined P&L'!$C:$C,'P&L Overview'!$B32) -> 0 | V32: =SUMIFS('Combined P&L'!X:X,'Combined P&L'!$C:$C,'P&L Overview'!$B32) -> 0 | W32: =SUMIFS('Combined P&L'!Y:Y,'Combined P&L'!$C:$C,'P&L Overview'!$B32) -> 0 | X32: =SUMIFS('Combined P&L'!Z:Z,'Combined P&L'!$C:$C,'P&L Overview'!$B32) -> 0 | Y32: =SUMIFS('Combined P&L'!AA:AA,'Combined P&L'!$C:$C,'P&L Overview'!$B32) -> 0 | Z32: =SUMIFS('Combined P&L'!AB:AB,'Combined P&L'!$C:$C,'P&L Overview'!$B32) -> 0 | AA32: =SUMIFS('Combined P&L'!AC:AC,'Combined P&L'!$C:$C,'P&L Overview'!$B32) -> 0 | AB32: =SUMIFS('Combined P&L'!AD:AD,'Combined P&L'!$C:$C,'P&L Overview'!$B32) -> 0 | AC32: =SUMIFS('Combined P&L'!AE:AE,'Combined P&L'!$C:$C,'P&L Overview'!$B32) -> 1.4668 | AD32: =SUMIFS('Combined P&L'!AF:AF,'Combined P&L'!$C:$C,'P&L Overview'!$B32) -> 1.63265 | AE32: =SUMIFS('Combined P&L'!AG:AG,'Combined P&L'!$C:$C,'P&L Overview'!$B32) -> 1.71805 | AF32: =SUMIFS('Combined P&L'!AH:AH,'Combined P&L'!$C:$C,'P&L Overview'!$B32) -> 1.9146 | AG32: =SUMIFS('Combined P&L'!AI:AI,'Combined P&L'!$C:$C,'P&L Overview'!$B32) -> 2.3529 | AH32: =SUMIFS('Combined P&L'!AJ:AJ,'Combined P&L'!$C:$C,'P&L Overview'!$B32) -> 2.24524 | AI32: =SUMIFS('Combined P&L'!AK:AK,'Combined P&L'!$C:$C,'P&L Overview'!$B32) -> 7.81939 | AJ32: =SUMIFS('Combined P&L'!AL:AL,'Combined P&L'!$C:$C,'P&L Overview'!$B32) -> 5.6534 | AK32: =SUMIFS('Combined P&L'!AM:AM,'Combined P&L'!$C:$C,'P&L Overview'!$B32) -> 5.95689 | AL32: =SUMIFS('Combined P&L'!AN:AN,'Combined P&L'!$C:$C,'P&L Overview'!$B32) -> 7.7828 | AM32: =SUMIFS('Combined P&L'!AO:AO,'Combined P&L'!$C:$C,'P&L Overview'!$B32) -> 8.13701 | AN32: =SUMIFS('Combined P&L'!AP:AP,'Combined P&L'!$C:$C,'P&L Overview'!$B32) -> 7.80825 | AO32: =SUMIFS('Combined P&L'!AQ:AQ,'Combined P&L'!$C:$C,'P&L Overview'!$B32) -> 8.4072 | AP32: =SUMIFS('Combined P&L'!AR:AR,'Combined P&L'!$C:$C,'P&L Overview'!$B32) -> 8.19576
B33: Occupancy Tax Specialist | C33: =SUMIFS($L33:$AP33,$L$5:$AP$5,">"&C$42,$L$5:$AP$5,"<"&C$43) -> 1.11335 | D33: =SUMIFS($L33:$AP33,$L$5:$AP$5,">"&D$42,$L$5:$AP$5,"<"&D$43) -> 29.56415 | F33: =SUMIFS($L33:$AP33,$L$5:$AP$5,">"&F$42,$L$5:$AP$5,"<"&F$43) -> 14.27585 | G33: =SUMIFS($L33:$AP33,$L$5:$AP$5,">"&G$42,$L$5:$AP$5,"<"&G$43) -> 42.08505 | I33: =SUMIFS($L33:$AP33,$L$5:$AP$5,">"&I$42,$L$5:$AP$5,"<"&I$43) -> 13.21003 | J33: =SUMIFS($L33:$AP33,$L$5:$AP$5,">"&J$42,$L$5:$AP$5,"<"&J$43) -> 53.87642 | L33: =SUMIFS('Combined P&L'!N:N,'Combined P&L'!$C:$C,'P&L Overview'!$B33) -> 0 | M33: =SUMIFS('Combined P&L'!O:O,'Combined P&L'!$C:$C,'P&L Overview'!$B33) -> 0 | N33: =SUMIFS('Combined P&L'!P:P,'Combined P&L'!$C:$C,'P&L Overview'!$B33) -> 0 | O33: =SUMIFS('Combined P&L'!Q:Q,'Combined P&L'!$C:$C,'P&L Overview'!$B33) -> 0 | P33: =SUMIFS('Combined P&L'!R:R,'Combined P&L'!$C:$C,'P&L Overview'!$B33) -> 0 | Q33: =SUMIFS('Combined P&L'!S:S,'Combined P&L'!$C:$C,'P&L Overview'!$B33) -> 0 | R33: =SUMIFS('Combined P&L'!T:T,'Combined P&L'!$C:$C,'P&L Overview'!$B33) -> 0 | S33: =SUMIFS('Combined P&L'!U:U,'Combined P&L'!$C:$C,'P&L Overview'!$B33) -> 0 | T33: =SUMIFS('Combined P&L'!V:V,'Combined P&L'!$C:$C,'P&L Overview'!$B33) -> 0 | U33: =SUMIFS('Combined P&L'!W:W,'Combined P&L'!$C:$C,'P&L Overview'!$B33) -> 0 | V33: =SUMIFS('Combined P&L'!X:X,'Combined P&L'!$C:$C,'P&L Overview'!$B33) -> 0 | W33: =SUMIFS('Combined P&L'!Y:Y,'Combined P&L'!$C:$C,'P&L Overview'!$B33) -> 1.11335 | X33: =SUMIFS('Combined P&L'!Z:Z,'Combined P&L'!$C:$C,'P&L Overview'!$B33) -> 2.17917 | Y33: =SUMIFS('Combined P&L'!AA:AA,'Combined P&L'!$C:$C,'P&L Overview'!$B33) -> 1.82504 | Z33: =SUMIFS('Combined P&L'!AB:AB,'Combined P&L'!$C:$C,'P&L Overview'!$B33) -> 1.97853 | AA33: =SUMIFS('Combined P&L'!AC:AC,'Combined P&L'!$C:$C,'P&L Overview'!$B33) -> 2.06213 | AB33: =SUMIFS('Combined P&L'!AD:AD,'Combined P&L'!$C:$C,'P&L Overview'!$B33) -> 2.06213 | AC33: =SUMIFS('Combined P&L'!AE:AE,'Combined P&L'!$C:$C,'P&L Overview'!$B33) -> 1.98968 | AD33: =SUMIFS('Combined P&L'!AF:AF,'Combined P&L'!$C:$C,'P&L Overview'!$B33) -> 2.17917 | AE33: =SUMIFS('Combined P&L'!AG:AG,'Combined P&L'!$C:$C,'P&L Overview'!$B33) -> 2.12293 | AF33: =SUMIFS('Combined P&L'!AH:AH,'Combined P&L'!$C:$C,'P&L Overview'!$B33) -> 3.1042 | AG33: =SUMIFS('Combined P&L'!AI:AI,'Combined P&L'!$C:$C,'P&L Overview'!$B33) -> 3.27137 | AH33: =SUMIFS('Combined P&L'!AJ:AJ,'Combined P&L'!$C:$C,'P&L Overview'!$B33) -> 3.63947 | AI33: =SUMIFS('Combined P&L'!AK:AK,'Combined P&L'!$C:$C,'P&L Overview'!$B33) -> 3.15033 | AJ33: =SUMIFS('Combined P&L'!AL:AL,'Combined P&L'!$C:$C,'P&L Overview'!$B33) -> 1.69116 | AK33: =SUMIFS('Combined P&L'!AM:AM,'Combined P&L'!$C:$C,'P&L Overview'!$B33) -> 5.54919 | AL33: =SUMIFS('Combined P&L'!AN:AN,'Combined P&L'!$C:$C,'P&L Overview'!$B33) -> 7.1999 | AM33: =SUMIFS('Combined P&L'!AO:AO,'Combined P&L'!$C:$C,'P&L Overview'!$B33) -> 8.1927 | AN33: =SUMIFS('Combined P&L'!AP:AP,'Combined P&L'!$C:$C,'P&L Overview'!$B33) -> 8.28335 | AO33: =SUMIFS('Combined P&L'!AQ:AQ,'Combined P&L'!$C:$C,'P&L Overview'!$B33) -> 5.49265 | AP33: =SUMIFS('Combined P&L'!AR:AR,'Combined P&L'!$C:$C,'P&L Overview'!$B33) -> 5.6761
B34: Sr. Client Lead Wages | C34: =SUMIFS($L34:$AP34,$L$5:$AP$5,">"&C$42,$L$5:$AP$5,"<"&C$43) -> 0 | D34: =SUMIFS($L34:$AP34,$L$5:$AP$5,">"&D$42,$L$5:$AP$5,"<"&D$43) -> 0 | F34: =SUMIFS($L34:$AP34,$L$5:$AP$5,">"&F$42,$L$5:$AP$5,"<"&F$43) -> 0 | G34: =SUMIFS($L34:$AP34,$L$5:$AP$5,">"&G$42,$L$5:$AP$5,"<"&G$43) -> 7.995 | I34: =SUMIFS($L34:$AP34,$L$5:$AP$5,">"&I$42,$L$5:$AP$5,"<"&I$43) -> 0 | J34: =SUMIFS($L34:$AP34,$L$5:$AP$5,">"&J$42,$L$5:$AP$5,"<"&J$43) -> 5.23823 | L34: =SUMIFS('Combined P&L'!N:N,'Combined P&L'!$C:$C,'P&L Overview'!$B34) -> 0 | M34: =SUMIFS('Combined P&L'!O:O,'Combined P&L'!$C:$C,'P&L Overview'!$B34) -> 0 | N34: =SUMIFS('Combined P&L'!P:P,'Combined P&L'!$C:$C,'P&L Overview'!$B34) -> 0 | O34: =SUMIFS('Combined P&L'!Q:Q,'Combined P&L'!$C:$C,'P&L Overview'!$B34) -> 0 | P34: =SUMIFS('Combined P&L'!R:R,'Combined P&L'!$C:$C,'P&L Overview'!$B34) -> 0 | Q34: =SUMIFS('Combined P&L'!S:S,'Combined P&L'!$C:$C,'P&L Overview'!$B34) -> 0 | R34: =SUMIFS('Combined P&L'!T:T,'Combined P&L'!$C:$C,'P&L Overview'!$B34) -> 0 | S34: =SUMIFS('Combined P&L'!U:U,'Combined P&L'!$C:$C,'P&L Overview'!$B34) -> 0 | T34: =SUMIFS('Combined P&L'!V:V,'Combined P&L'!$C:$C,'P&L Overview'!$B34) -> 0 | U34: =SUMIFS('Combined P&L'!W:W,'Combined P&L'!$C:$C,'P&L Overview'!$B34) -> 0 | V34: =SUMIFS('Combined P&L'!X:X,'Combined P&L'!$C:$C,'P&L Overview'!$B34) -> 0 | W34: =SUMIFS('Combined P&L'!Y:Y,'Combined P&L'!$C:$C,'P&L Overview'!$B34) -> 0 | X34: =SUMIFS('Combined P&L'!Z:Z,'Combined P&L'!$C:$C,'P&L Overview'!$B34) -> 0 | Y34: =SUMIFS('Combined P&L'!AA:AA,'Combined P&L'!$C:$C,'P&L Overview'!$B34) -> 0 | Z34: =SUMIFS('Combined P&L'!AB:AB,'Combined P&L'!$C:$C,'P&L Overview'!$B34) -> 0 | AA34: =SUMIFS('Combined P&L'!AC:AC,'Combined P&L'!$C:$C,'P&L Overview'!$B34) -> 0 | AB34: =SUMIFS('Combined P&L'!AD:AD,'Combined P&L'!$C:$C,'P&L Overview'!$B34) -> 0 | AC34: =SUMIFS('Combined P&L'!AE:AE,'Combined P&L'!$C:$C,'P&L Overview'!$B34) -> 0 | AD34: =SUMIFS('Combined P&L'!AF:AF,'Combined P&L'!$C:$C,'P&L Overview'!$B34) -> 0 | AE34: =SUMIFS('Combined P&L'!AG:AG,'Combined P&L'!$C:$C,'P&L Overview'!$B34) -> 0 | AF34: =SUMIFS('Combined P&L'!AH:AH,'Combined P&L'!$C:$C,'P&L Overview'!$B34) -> 0 | AG34: =SUMIFS('Combined P&L'!AI:AI,'Combined P&L'!$C:$C,'P&L Overview'!$B34) -> 0 | AH34: =SUMIFS('Combined P&L'!AJ:AJ,'Combined P&L'!$C:$C,'P&L Overview'!$B34) -> 0 | AI34: =SUMIFS('Combined P&L'!AK:AK,'Combined P&L'!$C:$C,'P&L Overview'!$B34) -> 0 | AJ34: =SUMIFS('Combined P&L'!AL:AL,'Combined P&L'!$C:$C,'P&L Overview'!$B34) -> 0 | AK34: =SUMIFS('Combined P&L'!AM:AM,'Combined P&L'!$C:$C,'P&L Overview'!$B34) -> 0 | AL34: =SUMIFS('Combined P&L'!AN:AN,'Combined P&L'!$C:$C,'P&L Overview'!$B34) -> 0 | AM34: =SUMIFS('Combined P&L'!AO:AO,'Combined P&L'!$C:$C,'P&L Overview'!$B34) -> 0 | AN34: =SUMIFS('Combined P&L'!AP:AP,'Combined P&L'!$C:$C,'P&L Overview'!$B34) -> 2.51706 | AO34: =SUMIFS('Combined P&L'!AQ:AQ,'Combined P&L'!$C:$C,'P&L Overview'!$B34) -> 2.72117 | AP34: =SUMIFS('Combined P&L'!AR:AR,'Combined P&L'!$C:$C,'P&L Overview'!$B34) -> 2.75677
C42: 45291 | D42: =C43 -> 45657 | F42: 45657 | G42: 46022 | I42: 45473 | J42: =I43 -> 45838
C43: =EOMONTH(C42,12) -> 45657 | D43: =EOMONTH(D42,12) -> 46022 | F43: 45869 | G43: =EOMONTH(G42,12) -> 46387 | I43: =EOMONTH(I42,12) -> 45838 | J43: =EOMONTH(J42,12) -> 46203

Sheet P&L Forecast
B2: =+Cover!B24 -> Keystone Bookkeepers
B3: Summary P&L Overview ($000s)
B5: P&L Summary ($000s) | C5: FY2024 | D5: FY2025 | F5: July'25 YTD | G5: July'26 YTD | I5: Jul'25 LTM | J5: Jul'26 LTM | K5: Jul'26 PF | M5: Delta ($) | N5: Delta (%) | P5: 45292 | Q5: =EOMONTH(P5,0)+1 -> 45323 | R5: =EOMONTH(Q5,0)+1 -> 45352 | S5: =EOMONTH(R5,0)+1 -> 45383 | T5: =EOMONTH(S5,0)+1 -> 45413 | U5: =EOMONTH(T5,0)+1 -> 45444 | V5: =EOMONTH(U5,0)+1 -> 45474 | W5: =EOMONTH(V5,0)+1 -> 45505 | X5: =EOMONTH(W5,0)+1 -> 45536 | ... AT5: =EOMONTH(AS5,0)+1 -> 46204
B6: Revenue
B7: STR Subscription | C7: =SUMIFS($P7:$AT7,$P$5:$AT$5,">"&C$172,$P$5:$AT$5,"<"&C$173) -> 793.47225 | D7: =SUMIFS($P7:$AT7,$P$5:$AT$5,">"&D$172,$P$5:$AT$5,"<"&D$173) -> 1450.4923 | F7: =SUMIFS($P7:$AT7,$P$5:$AT$5,">"&F$172,$P$5:$AT$5,"<"&F$173) -> 751.5286 | G7: =SUMIFS($P7:$AT7,$P$5:$AT$5,">"&G$172,$P$5:$AT$5,"<"&G$173) -> 1261.4769 | I7: =SUMIFS($P7:$AT7,$P$5:$AT$5,">"&I$172,$P$5:$AT$5,"<"&I$173) -> 1098.5075 | J7: =SUMIFS($P7:$AT7,$P$5:$AT$5,">"&J$172,$P$5:$AT$5,"<"&J$173) -> 1881.6971 | K7: =+C108 -> 2410.05 | M7: =K7-J7 -> 528.3529 | N7: =IFERROR(K7/J7-1,0) -> 0.28078531 | P7: =SUMIFS('Combined P&L'!N:N,'Combined P&L'!$C:$C,'P&L Forecast'!$B7) -> 44.6835 | Q7: =SUMIFS('Combined P&L'!O:O,'Combined P&L'!$C:$C,'P&L Forecast'!$B7) -> 47.046 | R7: =SUMIFS('Combined P&L'!P:P,'Combined P&L'!$C:$C,'P&L Forecast'!$B7) -> 52.47 | S7: =SUMIFS('Combined P&L'!Q:Q,'Combined P&L'!$C:$C,'P&L Forecast'!$B7) -> 57.1697 | T7: =SUMIFS('Combined P&L'!R:R,'Combined P&L'!$C:$C,'P&L Forecast'!$B7) -> 57.51415 | U7: =SUMIFS('Combined P&L'!S:S,'Combined P&L'!$C:$C,'P&L Forecast'!$B7) -> 65.516 | V7: =SUMIFS('Combined P&L'!T:T,'Combined P&L'!$C:$C,'P&L Forecast'!$B7) -> 68.28125 | W7: =SUMIFS('Combined P&L'!U:U,'Combined P&L'!$C:$C,'P&L Forecast'!$B7) -> 73.25135 | X7: =SUMIFS('Combined P&L'!V:V,'Combined P&L'!$C:$C,'P&L Forecast'!$B7) -> 75.5517 | Y7: =SUMIFS('Combined P&L'!W:W,'Combined P&L'!$C:$C,'P&L Forecast'!$B7) -> 79.11325 | Z7: =SUMIFS('Combined P&L'!X:X,'Combined P&L'!$C:$C,'P&L Forecast'!$B7) -> 83.2908 | AA7: =SUMIFS('Combined P&L'!Y:Y,'Combined P&L'!$C:$C,'P&L Forecast'!$B7) -> 89.58455 | AB7: =SUMIFS('Combined P&L'!Z:Z,'Combined P&L'!$C:$C,'P&L Forecast'!$B7) -> 92.4189 | AC7: =SUMIFS('Combined P&L'!AA:AA,'Combined P&L'!$C:$C,'P&L Forecast'!$B7) -> 94.00215 | AD7: =SUMIFS('Combined P&L'!AB:AB,'Combined P&L'!$C:$C,'P&L Forecast'!$B7) -> 101.50605 | AE7: =SUMIFS('Combined P&L'!AC:AC,'Combined P&L'!$C:$C,'P&L Forecast'!$B7) -> 106.1375 | AF7: =SUMIFS('Combined P&L'!AD:AD,'Combined P&L'!$C:$C,'P&L Forecast'!$B7) -> 115.93875 | AG7: =SUMIFS('Combined P&L'!AE:AE,'Combined P&L'!$C:$C,'P&L Forecast'!$B7) -> 119.43125 | AH7: =SUMIFS('Combined P&L'!AF:AF,'Combined P&L'!$C:$C,'P&L Forecast'!$B7) -> 122.094 | AI7: =SUMIFS('Combined P&L'!AG:AG,'Combined P&L'!$C:$C,'P&L Forecast'!$B7) -> 130.08525 | AJ7: =SUMIFS('Combined P&L'!AH:AH,'Combined P&L'!$C:$C,'P&L Forecast'!$B7) -> 133.5905 | AK7: =SUMIFS('Combined P&L'!AI:AI,'Combined P&L'!$C:$C,'P&L Forecast'!$B7) -> 139.609 | AL7: =SUMIFS('Combined P&L'!AJ:AJ,'Combined P&L'!$C:$C,'P&L Forecast'!$B7) -> 145.28075 | AM7: =SUMIFS('Combined P&L'!AK:AK,'Combined P&L'!$C:$C,'P&L Forecast'!$B7) -> 150.39825 | AN7: =SUMIFS('Combined P&L'!AL:AL,'Combined P&L'!$C:$C,'P&L Forecast'!$B7) -> 156.5388 | AO7: =SUMIFS('Combined P&L'!AM:AM,'Combined P&L'!$C:$C,'P&L Forecast'!$B7) -> 164.9034 | AP7: =SUMIFS('Combined P&L'!AN:AN,'Combined P&L'!$C:$C,'P&L Forecast'!$B7) -> 170.34425 | AQ7: =SUMIFS('Combined P&L'!AO:AO,'Combined P&L'!$C:$C,'P&L Forecast'!$B7) -> 183.662 | AR7: =SUMIFS('Combined P&L'!AP:AP,'Combined P&L'!$C:$C,'P&L Forecast'!$B7) -> 190.7844 | AS7: =SUMIFS('Combined P&L'!AQ:AQ,'Combined P&L'!$C:$C,'P&L Forecast'!$B7) -> 194.4065 | AT7: =SUMIFS('Combined P&L'!AR:AR,'Combined P&L'!$C:$C,'P&L Forecast'!$B7) -> 200.8375
B8: Occupancy Taxes | C8: =SUMIFS($P8:$AT8,$P$5:$AT$5,">"&C$172,$P$5:$AT$5,"<"&C$173) -> 0.56 | D8: =SUMIFS($P8:$AT8,$P$5:$AT$5,">"&D$172,$P$5:$AT$5,"<"&D$173) -> 55.0805 | F8: =SUMIFS($P8:$AT8,$P$5:$AT$5,">"&F$172,$P$5:$AT$5,"<"&F$173) -> 23.2255 | G8: =SUMIFS($P8:$AT8,$P$5:$AT$5,">"&G$172,$P$5:$AT$5,"<"&G$173) -> 91.65114 | I8: =SUMIFS($P8:$AT8,$P$5:$AT$5,">"&I$172,$P$5:$AT$5,"<"&I$173) -> 18.727 | J8: =SUMIFS($P8:$AT8,$P$5:$AT$5,">"&J$172,$P$5:$AT$5,"<"&J$173) -> 112.49549 | K8: =+C110 -> 192.8298 | M8: =K8-J8 -> 80.33431 | N8: =IFERROR(K8/J8-1,0) -> 0.71411138 | P8: =SUMIFS('Combined P&L'!N:N,'Combined P&L'!$C:$C,'P&L Forecast'!$B8) -> 0 | Q8: =SUMIFS('Combined P&L'!O:O,'Combined P&L'!$C:$C,'P&L Forecast'!$B8) -> 0 | R8: =SUMIFS('Combined P&L'!P:P,'Combined P&L'!$C:$C,'P&L Forecast'!$B8) -> 0 | S8: =SUMIFS('Combined P&L'!Q:Q,'Combined P&L'!$C:$C,'P&L Forecast'!$B8) -> 0 | T8: =SUMIFS('Combined P&L'!R:R,'Combined P&L'!$C:$C,'P&L Forecast'!$B8) -> 0 | U8: =SUMIFS('Combined P&L'!S:S,'Combined P&L'!$C:$C,'P&L Forecast'!$B8) -> 0 | V8: =SUMIFS('Combined P&L'!T:T,'Combined P&L'!$C:$C,'P&L Forecast'!$B8) -> 0 | W8: =SUMIFS('Combined P&L'!U:U,'Combined P&L'!$C:$C,'P&L Forecast'!$B8) -> 0 | X8: =SUMIFS('Combined P&L'!V:V,'Combined P&L'!$C:$C,'P&L Forecast'!$B8) -> 0 | Y8: =SUMIFS('Combined P&L'!W:W,'Combined P&L'!$C:$C,'P&L Forecast'!$B8) -> 0 | Z8: =SUMIFS('Combined P&L'!X:X,'Combined P&L'!$C:$C,'P&L Forecast'!$B8) -> 0.08 | AA8: =SUMIFS('Combined P&L'!Y:Y,'Combined P&L'!$C:$C,'P&L Forecast'!$B8) -> 0.48 | AB8: =SUMIFS('Combined P&L'!Z:Z,'Combined P&L'!$C:$C,'P&L Forecast'!$B8) -> 1.13 | AC8: =SUMIFS('Combined P&L'!AA:AA,'Combined P&L'!$C:$C,'P&L Forecast'!$B8) -> 2.14 | AD8: =SUMIFS('Combined P&L'!AB:AB,'Combined P&L'!$C:$C,'P&L Forecast'!$B8) -> 2.66 | AE8: =SUMIFS('Combined P&L'!AC:AC,'Combined P&L'!$C:$C,'P&L Forecast'!$B8) -> 3.65 | AF8: =SUMIFS('Combined P&L'!AD:AD,'Combined P&L'!$C:$C,'P&L Forecast'!$B8) -> 3.623 | AG8: =SUMIFS('Combined P&L'!AE:AE,'Combined P&L'!$C:$C,'P&L Forecast'!$B8) -> 4.964 | AH8: =SUMIFS('Combined P&L'!AF:AF,'Combined P&L'!$C:$C,'P&L Forecast'!$B8) -> 5.0585 | AI8: =SUMIFS('Combined P&L'!AG:AG,'Combined P&L'!$C:$C,'P&L Forecast'!$B8) -> 4.73 | AJ8: =SUMIFS('Combined P&L'!AH:AH,'Combined P&L'!$C:$C,'P&L Forecast'!$B8) -> 4.82 | AK8: =SUMIFS('Combined P&L'!AI:AI,'Combined P&L'!$C:$C,'P&L Forecast'!$B8) -> 5.37 | AL8: =SUMIFS('Combined P&L'!AJ:AJ,'Combined P&L'!$C:$C,'P&L Forecast'!$B8) -> 8.05 | AM8: =SUMIFS('Combined P&L'!AK:AK,'Combined P&L'!$C:$C,'P&L Forecast'!$B8) -> 8.885 | AN8: =SUMIFS('Combined P&L'!AL:AL,'Combined P&L'!$C:$C,'P&L Forecast'!$B8) -> 10.90952 | AO8: =SUMIFS('Combined P&L'!AM:AM,'Combined P&L'!$C:$C,'P&L Forecast'!$B8) -> 10.33497 | AP8: =SUMIFS('Combined P&L'!AN:AN,'Combined P&L'!$C:$C,'P&L Forecast'!$B8) -> 11.175 | AQ8: =SUMIFS('Combined P&L'!AO:AO,'Combined P&L'!$C:$C,'P&L Forecast'!$B8) -> 11.95311 | AR8: =SUMIFS('Combined P&L'!AP:AP,'Combined P&L'!$C:$C,'P&L Forecast'!$B8) -> 15.04071 | AS8: =SUMIFS('Combined P&L'!AQ:AQ,'Combined P&L'!$C:$C,'P&L Forecast'!$B8) -> 16.16868 | AT8: =SUMIFS('Combined P&L'!AR:AR,'Combined P&L'!$C:$C,'P&L Forecast'!$B8) -> 16.06915
B9: SMB Subscription | C9: =SUMIFS($P9:$AT9,$P$5:$AT$5,">"&C$172,$P$5:$AT$5,"<"&C$173) -> 224.791 | D9: =SUMIFS($P9:$AT9,$P$5:$AT$5,">"&D$172,$P$5:$AT$5,"<"&D$173) -> 149.77 | F9: =SUMIFS($P9:$AT9,$P$5:$AT$5,">"&F$172,$P$5:$AT$5,"<"&F$173) -> 90.4525 | G9: =SUMIFS($P9:$AT9,$P$5:$AT$5,">"&G$172,$P$5:$AT$5,"<"&G$173) -> 73.4185 | I9: =SUMIFS($P9:$AT9,$P$5:$AT$5,">"&I$172,$P$5:$AT$5,"<"&I$173) -> 174.63 | J9: =SUMIFS($P9:$AT9,$P$5:$AT$5,">"&J$172,$P$5:$AT$5,"<"&J$173) -> 135.298 | K9: =+C109 -> 119.706 | M9: =K9-J9 -> -15.592 | N9: =IFERROR(K9/J9-1,0) -> -0.11524191 | P9: =SUMIFS('Combined P&L'!N:N,'Combined P&L'!$C:$C,'P&L Forecast'!$B9) -> 22.001 | Q9: =SUMIFS('Combined P&L'!O:O,'Combined P&L'!$C:$C,'P&L Forecast'!$B9) -> 22.036 | R9: =SUMIFS('Combined P&L'!P:P,'Combined P&L'!$C:$C,'P&L Forecast'!$B9) -> 22.111 | S9: =SUMIFS('Combined P&L'!Q:Q,'Combined P&L'!$C:$C,'P&L Forecast'!$B9) -> 22.146 | T9: =SUMIFS('Combined P&L'!R:R,'Combined P&L'!$C:$C,'P&L Forecast'!$B9) -> 21.966 | U9: =SUMIFS('Combined P&L'!S:S,'Combined P&L'!$C:$C,'P&L Forecast'!$B9) -> 17.816 | V9: =SUMIFS('Combined P&L'!T:T,'Combined P&L'!$C:$C,'P&L Forecast'!$B9) -> 17.621 | W9: =SUMIFS('Combined P&L'!U:U,'Combined P&L'!$C:$C,'P&L Forecast'!$B9) -> 17.536 | X9: =SUMIFS('Combined P&L'!V:V,'Combined P&L'!$C:$C,'P&L Forecast'!$B9) -> 16.426 | Y9: =SUMIFS('Combined P&L'!W:W,'Combined P&L'!$C:$C,'P&L Forecast'!$B9) -> 15.381 | Z9: =SUMIFS('Combined P&L'!X:X,'Combined P&L'!$C:$C,'P&L Forecast'!$B9) -> 14.6755 | AA9: =SUMIFS('Combined P&L'!Y:Y,'Combined P&L'!$C:$C,'P&L Forecast'!$B9) -> 15.0755 | AB9: =SUMIFS('Combined P&L'!Z:Z,'Combined P&L'!$C:$C,'P&L Forecast'!$B9) -> 14.5625 | AC9: =SUMIFS('Combined P&L'!AA:AA,'Combined P&L'!$C:$C,'P&L Forecast'!$B9) -> 12.8025 | AD9: =SUMIFS('Combined P&L'!AB:AB,'Combined P&L'!$C:$C,'P&L Forecast'!$B9) -> 12.4025 | AE9: =SUMIFS('Combined P&L'!AC:AC,'Combined P&L'!$C:$C,'P&L Forecast'!$B9) -> 12.6025 | AF9: =SUMIFS('Combined P&L'!AD:AD,'Combined P&L'!$C:$C,'P&L Forecast'!$B9) -> 12.7525 | AG9: =SUMIFS('Combined P&L'!AE:AE,'Combined P&L'!$C:$C,'P&L Forecast'!$B9) -> 12.7925 | AH9: =SUMIFS('Combined P&L'!AF:AF,'Combined P&L'!$C:$C,'P&L Forecast'!$B9) -> 12.5375 | AI9: =SUMIFS('Combined P&L'!AG:AG,'Combined P&L'!$C:$C,'P&L Forecast'!$B9) -> 11.8575 | AJ9: =SUMIFS('Combined P&L'!AH:AH,'Combined P&L'!$C:$C,'P&L Forecast'!$B9) -> 12.3025 | AK9: =SUMIFS('Combined P&L'!AI:AI,'Combined P&L'!$C:$C,'P&L Forecast'!$B9) -> 11.6925 | AL9: =SUMIFS('Combined P&L'!AJ:AJ,'Combined P&L'!$C:$C,'P&L Forecast'!$B9) -> 11.7175 | AM9: =SUMIFS('Combined P&L'!AK:AK,'Combined P&L'!$C:$C,'P&L Forecast'!$B9) -> 11.7475 | AN9: =SUMIFS('Combined P&L'!AL:AL,'Combined P&L'!$C:$C,'P&L Forecast'!$B9) -> 11.2805 | AO9: =SUMIFS('Combined P&L'!AM:AM,'Combined P&L'!$C:$C,'P&L Forecast'!$B9) -> 10.9305 | AP9: =SUMIFS('Combined P&L'!AN:AN,'Combined P&L'!$C:$C,'P&L Forecast'!$B9) -> 10.6255 | AQ9: =SUMIFS('Combined P&L'!AO:AO,'Combined P&L'!$C:$C,'P&L Forecast'!$B9) -> 10.3155 | AR9: =SUMIFS('Combined P&L'!AP:AP,'Combined P&L'!$C:$C,'P&L Forecast'!$B9) -> 10.3155 | AS9: =SUMIFS('Combined P&L'!AQ:AQ,'Combined P&L'!$C:$C,'P&L Forecast'!$B9) -> 9.9755 | AT9: =SUMIFS('Combined P&L'!AR:AR,'Combined P&L'!$C:$C,'P&L Forecast'!$B9) -> 9.9755
B10: Onboarding | C10: =SUMIFS($P10:$AT10,$P$5:$AT$5,">"&C$172,$P$5:$AT$5,"<"&C$173) -> 44.0585 | D10: =SUMIFS($P10:$AT10,$P$5:$AT$5,">"&D$172,$P$5:$AT$5,"<"&D$173) -> 74.5193 | F10: =SUMIFS($P10:$AT10,$P$5:$AT$5,">"&F$172,$P$5:$AT$5,"<"&F$173) -> 42.25405 | G10: =SUMIFS($P10:$AT10,$P$5:$AT$5,">"&G$172,$P$5:$AT$5,"<"&G$173) -> 59.055 | I10: =SUMIFS($P10:$AT10,$P$5:$AT$5,">"&I$172,$P$5:$AT$5,"<"&I$173) -> 55.66055 | J10: =SUMIFS($P10:$AT10,$P$5:$AT$5,">"&J$172,$P$5:$AT$5,"<"&J$173) -> 91.65575 | K10: =+C111 -> 103.5675 | M10: =K10-J10 -> 11.91175 | N10: =IFERROR(K10/J10-1,0) -> 0.12996184 | P10: =SUMIFS('Combined P&L'!N:N,'Combined P&L'!$C:$C,'P&L Forecast'!$B10) -> 5.465 | Q10: =SUMIFS('Combined P&L'!O:O,'Combined P&L'!$C:$C,'P&L Forecast'!$B10) -> 3.9 | R10: =SUMIFS('Combined P&L'!P:P,'Combined P&L'!$C:$C,'P&L Forecast'!$B10) -> 2.755 | S10: =SUMIFS('Combined P&L'!Q:Q,'Combined P&L'!$C:$C,'P&L Forecast'!$B10) -> 3.502 | T10: =SUMIFS('Combined P&L'!R:R,'Combined P&L'!$C:$C,'P&L Forecast'!$B10) -> 4.659 | U10: =SUMIFS('Combined P&L'!S:S,'Combined P&L'!$C:$C,'P&L Forecast'!$B10) -> 3.937 | V10: =SUMIFS('Combined P&L'!T:T,'Combined P&L'!$C:$C,'P&L Forecast'!$B10) -> 4.602 | W10: =SUMIFS('Combined P&L'!U:U,'Combined P&L'!$C:$C,'P&L Forecast'!$B10) -> 4.738 | X10: =SUMIFS('Combined P&L'!V:V,'Combined P&L'!$C:$C,'P&L Forecast'!$B10) -> 2.119 | Y10: =SUMIFS('Combined P&L'!W:W,'Combined P&L'!$C:$C,'P&L Forecast'!$B10) -> 2.064 | Z10: =SUMIFS('Combined P&L'!X:X,'Combined P&L'!$C:$C,'P&L Forecast'!$B10) -> 3.0125 | AA10: =SUMIFS('Combined P&L'!Y:Y,'Combined P&L'!$C:$C,'P&L Forecast'!$B10) -> 3.305 | AB10: =SUMIFS('Combined P&L'!Z:Z,'Combined P&L'!$C:$C,'P&L Forecast'!$B10) -> 3.079 | AC10: =SUMIFS('Combined P&L'!AA:AA,'Combined P&L'!$C:$C,'P&L Forecast'!$B10) -> 0.7 | AD10: =SUMIFS('Combined P&L'!AB:AB,'Combined P&L'!$C:$C,'P&L Forecast'!$B10) -> 10.43855 | AE10: =SUMIFS('Combined P&L'!AC:AC,'Combined P&L'!$C:$C,'P&L Forecast'!$B10) -> 4.3 | AF10: =SUMIFS('Combined P&L'!AD:AD,'Combined P&L'!$C:$C,'P&L Forecast'!$B10) -> 11.14 | AG10: =SUMIFS('Combined P&L'!AE:AE,'Combined P&L'!$C:$C,'P&L Forecast'!$B10) -> 6.1625 | AH10: =SUMIFS('Combined P&L'!AF:AF,'Combined P&L'!$C:$C,'P&L Forecast'!$B10) -> 6.434 | AI10: =SUMIFS('Combined P&L'!AG:AG,'Combined P&L'!$C:$C,'P&L Forecast'!$B10) -> 3.965 | AJ10: =SUMIFS('Combined P&L'!AH:AH,'Combined P&L'!$C:$C,'P&L Forecast'!$B10) -> 3.92 | AK10: =SUMIFS('Combined P&L'!AI:AI,'Combined P&L'!$C:$C,'P&L Forecast'!$B10) -> 9.1365 | AL10: =SUMIFS('Combined P&L'!AJ:AJ,'Combined P&L'!$C:$C,'P&L Forecast'!$B10) -> 5.25375 | AM10: =SUMIFS('Combined P&L'!AK:AK,'Combined P&L'!$C:$C,'P&L Forecast'!$B10) -> 9.99 | AN10: =SUMIFS('Combined P&L'!AL:AL,'Combined P&L'!$C:$C,'P&L Forecast'!$B10) -> 10.2105 | AO10: =SUMIFS('Combined P&L'!AM:AM,'Combined P&L'!$C:$C,'P&L Forecast'!$B10) -> 6.675 | AP10: =SUMIFS('Combined P&L'!AN:AN,'Combined P&L'!$C:$C,'P&L Forecast'!$B10) -> 9.099 | AQ10: =SUMIFS('Combined P&L'!AO:AO,'Combined P&L'!$C:$C,'P&L Forecast'!$B10) -> 8.9545 | AR10: =SUMIFS('Combined P&L'!AP:AP,'Combined P&L'!$C:$C,'P&L Forecast'!$B10) -> 12.606 | AS10: =SUMIFS('Combined P&L'!AQ:AQ,'Combined P&L'!$C:$C,'P&L Forecast'!$B10) -> 5.4115 | AT10: =SUMIFS('Combined P&L'!AR:AR,'Combined P&L'!$C:$C,'P&L Forecast'!$B10) -> 6.0985
B11: Topkey Subscription | C11: =SUMIFS($P11:$AT11,$P$5:$AT$5,">"&C$172,$P$5:$AT$5,"<"&C$173) -> 0 | D11: =SUMIFS($P11:$AT11,$P$5:$AT$5,">"&D$172,$P$5:$AT$5,"<"&D$173) -> 9.947 | F11: =SUMIFS($P11:$AT11,$P$5:$AT$5,">"&F$172,$P$5:$AT$5,"<"&F$173) -> 0 | G11: =SUMIFS($P11:$AT11,$P$5:$AT$5,">"&G$172,$P$5:$AT$5,"<"&G$173) -> 45.086 | I11: =SUMIFS($P11:$AT11,$P$5:$AT$5,">"&I$172,$P$5:$AT$5,"<"&I$173) -> 0 | J11: =SUMIFS($P11:$AT11,$P$5:$AT$5,">"&J$172,$P$5:$AT$5,"<"&J$173) -> 47.13 | K11: =+C113 -> 94.836 | M11: =K11-J11 -> 47.706 | N11: =IFERROR(K11/J11-1,0) -> 1.0122215 | P11: =SUMIFS('Combined P&L'!N:N,'Combined P&L'!$C:$C,'P&L Forecast'!$B11) -> 0 | Q11: =SUMIFS('Combined P&L'!O:O,'Combined P&L'!$C:$C,'P&L Forecast'!$B11) -> 0 | R11: =SUMIFS('Combined P&L'!P:P,'Combined P&L'!$C:$C,'P&L Forecast'!$B11) -> 0 | S11: =SUMIFS('Combined P&L'!Q:Q,'Combined P&L'!$C:$C,'P&L Forecast'!$B11) -> 0 | T11: =SUMIFS('Combined P&L'!R:R,'Combined P&L'!$C:$C,'P&L Forecast'!$B11) -> 0 | U11: =SUMIFS('Combined P&L'!S:S,'Combined P&L'!$C:$C,'P&L Forecast'!$B11) -> 0 | V11: =SUMIFS('Combined P&L'!T:T,'Combined P&L'!$C:$C,'P&L Forecast'!$B11) -> 0 | W11: =SUMIFS('Combined P&L'!U:U,'Combined P&L'!$C:$C,'P&L Forecast'!$B11) -> 0 | X11: =SUMIFS('Combined P&L'!V:V,'Combined P&L'!$C:$C,'P&L Forecast'!$B11) -> 0 | Y11: =SUMIFS('Combined P&L'!W:W,'Combined P&L'!$C:$C,'P&L Forecast'!$B11) -> 0 | Z11: =SUMIFS('Combined P&L'!X:X,'Combined P&L'!$C:$C,'P&L Forecast'!$B11) -> 0 | AA11: =SUMIFS('Combined P&L'!Y:Y,'Combined P&L'!$C:$C,'P&L Forecast'!$B11) -> 0 | AB11: =SUMIFS('Combined P&L'!Z:Z,'Combined P&L'!$C:$C,'P&L Forecast'!$B11) -> 0 | AC11: =SUMIFS('Combined P&L'!AA:AA,'Combined P&L'!$C:$C,'P&L Forecast'!$B11) -> 0 | AD11: =SUMIFS('Combined P&L'!AB:AB,'Combined P&L'!$C:$C,'P&L Forecast'!$B11) -> 0 | AE11: =SUMIFS('Combined P&L'!AC:AC,'Combined P&L'!$C:$C,'P&L Forecast'!$B11) -> 0 | AF11: =SUMIFS('Combined P&L'!AD:AD,'Combined P&L'!$C:$C,'P&L Forecast'!$B11) -> 0 | AG11: =SUMIFS('Combined P&L'!AE:AE,'Combined P&L'!$C:$C,'P&L Forecast'!$B11) -> 0 | AH11: =SUMIFS('Combined P&L'!AF:AF,'Combined P&L'!$C:$C,'P&L Forecast'!$B11) -> 0 | AI11: =SUMIFS('Combined P&L'!AG:AG,'Combined P&L'!$C:$C,'P&L Forecast'!$B11) -> 0 | AJ11: =SUMIFS('Combined P&L'!AH:AH,'Combined P&L'!$C:$C,'P&L Forecast'!$B11) -> 0.52 | AK11: =SUMIFS('Combined P&L'!AI:AI,'Combined P&L'!$C:$C,'P&L Forecast'!$B11) -> 2.357 | AL11: =SUMIFS('Combined P&L'!AJ:AJ,'Combined P&L'!$C:$C,'P&L Forecast'!$B11) -> 2.811 | AM11: =SUMIFS('Combined P&L'!AK:AK,'Combined P&L'!$C:$C,'P&L Forecast'!$B11) -> 4.259 | AN11: =SUMIFS('Combined P&L'!AL:AL,'Combined P&L'!$C:$C,'P&L Forecast'!$B11) -> 5.254 | AO11: =SUMIFS('Combined P&L'!AM:AM,'Combined P&L'!$C:$C,'P&L Forecast'!$B11) -> 5.652 | AP11: =SUMIFS('Combined P&L'!AN:AN,'Combined P&L'!$C:$C,'P&L Forecast'!$B11) -> 5.324 | AQ11: =SUMIFS('Combined P&L'!AO:AO,'Combined P&L'!$C:$C,'P&L Forecast'!$B11) -> 6.321 | AR11: =SUMIFS('Combined P&L'!AP:AP,'Combined P&L'!$C:$C,'P&L Forecast'!$B11) -> 6.959 | AS11: =SUMIFS('Combined P&L'!AQ:AQ,'Combined P&L'!$C:$C,'P&L Forecast'!$B11) -> 7.673 | AT11: =SUMIFS('Combined P&L'!AR:AR,'Combined P&L'!$C:$C,'P&L Forecast'!$B11) -> 7.903
B12: STR Bill Pay | C12: =SUMIFS($P12:$AT12,$P$5:$AT$5,">"&C$172,$P$5:$AT$5,"<"&C$173) -> 0.06 | D12: =SUMIFS($P12:$AT12,$P$5:$AT$5,">"&D$172,$P$5:$AT$5,"<"&D$173) -> 36.6065 | F12: =SUMIFS($P12:$AT12,$P$5:$AT$5,">"&F$172,$P$5:$AT$5,"<"&F$173) -> 15.4915 | G12: =SUMIFS($P12:$AT12,$P$5:$AT$5,">"&G$172,$P$5:$AT$5,"<"&G$173) -> 45.13 | I12: =SUMIFS($P12:$AT12,$P$5:$AT$5,">"&I$172,$P$5:$AT$5,"<"&I$173) -> 11.6315 | J12: =SUMIFS($P12:$AT12,$P$5:$AT$5,">"&J$172,$P$5:$AT$5,"<"&J$173) -> 63.21 | K12: =+C112 -> 83.46 | M12: =K12-J12 -> 20.25 | N12: =IFERROR(K12/J12-1,0) -> 0.3203607 | P12: =SUMIFS('Combined P&L'!N:N,'Combined P&L'!$C:$C,'P&L Forecast'!$B12) -> 0 | Q12: =SUMIFS('Combined P&L'!O:O,'Combined P&L'!$C:$C,'P&L Forecast'!$B12) -> 0 | R12: =SUMIFS('Combined P&L'!P:P,'Combined P&L'!$C:$C,'P&L Forecast'!$B12) -> 0 | S12: =SUMIFS('Combined P&L'!Q:Q,'Combined P&L'!$C:$C,'P&L Forecast'!$B12) -> 0 | T12: =SUMIFS('Combined P&L'!R:R,'Combined P&L'!$C:$C,'P&L Forecast'!$B12) -> 0 | U12: =SUMIFS('Combined P&L'!S:S,'Combined P&L'!$C:$C,'P&L Forecast'!$B12) -> 0 | V12: =SUMIFS('Combined P&L'!T:T,'Combined P&L'!$C:$C,'P&L Forecast'!$B12) -> 0 | W12: =SUMIFS('Combined P&L'!U:U,'Combined P&L'!$C:$C,'P&L Forecast'!$B12) -> 0 | X12: =SUMIFS('Combined P&L'!V:V,'Combined P&L'!$C:$C,'P&L Forecast'!$B12) -> 0 | Y12: =SUMIFS('Combined P&L'!W:W,'Combined P&L'!$C:$C,'P&L Forecast'!$B12) -> 0 | Z12: =SUMIFS('Combined P&L'!X:X,'Combined P&L'!$C:$C,'P&L Forecast'!$B12) -> 0 | AA12: =SUMIFS('Combined P&L'!Y:Y,'Combined P&L'!$C:$C,'P&L Forecast'!$B12) -> 0.06 | AB12: =SUMIFS('Combined P&L'!Z:Z,'Combined P&L'!$C:$C,'P&L Forecast'!$B12) -> 0.97 | AC12: =SUMIFS('Combined P&L'!AA:AA,'Combined P&L'!$C:$C,'P&L Forecast'!$B12) -> 1.1 | AD12: =SUMIFS('Combined P&L'!AB:AB,'Combined P&L'!$C:$C,'P&L Forecast'!$B12) -> 1.735 | AE12: =SUMIFS('Combined P&L'!AC:AC,'Combined P&L'!$C:$C,'P&L Forecast'!$B12) -> 2.14 | AF12: =SUMIFS('Combined P&L'!AD:AD,'Combined P&L'!$C:$C,'P&L Forecast'!$B12) -> 2.363 | AG12: =SUMIFS('Combined P&L'!AE:AE,'Combined P&L'!$C:$C,'P&L Forecast'!$B12) -> 3.2635 | AH12: =SUMIFS('Combined P&L'!AF:AF,'Combined P&L'!$C:$C,'P&L Forecast'!$B12) -> 3.92 | AI12: =SUMIFS('Combined P&L'!AG:AG,'Combined P&L'!$C:$C,'P&L Forecast'!$B12) -> 3.905 | AJ12: =SUMIFS('Combined P&L'!AH:AH,'Combined P&L'!$C:$C,'P&L Forecast'!$B12) -> 3.78 | AK12: =SUMIFS('Combined P&L'!AI:AI,'Combined P&L'!$C:$C,'P&L Forecast'!$B12) -> 3.795 | AL12: =SUMIFS('Combined P&L'!AJ:AJ,'Combined P&L'!$C:$C,'P&L Forecast'!$B12) -> 4.33 | AM12: =SUMIFS('Combined P&L'!AK:AK,'Combined P&L'!$C:$C,'P&L Forecast'!$B12) -> 5.305 | AN12: =SUMIFS('Combined P&L'!AL:AL,'Combined P&L'!$C:$C,'P&L Forecast'!$B12) -> 6.3 | AO12: =SUMIFS('Combined P&L'!AM:AM,'Combined P&L'!$C:$C,'P&L Forecast'!$B12) -> 6.39 | AP12: =SUMIFS('Combined P&L'!AN:AN,'Combined P&L'!$C:$C,'P&L Forecast'!$B12) -> 6.425 | AQ12: =SUMIFS('Combined P&L'!AO:AO,'Combined P&L'!$C:$C,'P&L Forecast'!$B12) -> 6.08 | AR12: =SUMIFS('Combined P&L'!AP:AP,'Combined P&L'!$C:$C,'P&L Forecast'!$B12) -> 6.325 | AS12: =SUMIFS('Combined P&L'!AQ:AQ,'Combined P&L'!$C:$C,'P&L Forecast'!$B12) -> 6.655 | AT12: =SUMIFS('Combined P&L'!AR:AR,'Combined P&L'!$C:$C,'P&L Forecast'!$B12) -> 6.955
B13: Controller Services | C13: =SUMIFS($P13:$AT13,$P$5:$AT$5,">"&C$172,$P$5:$AT$5,"<"&C$173) -> 13.75 | D13: =SUMIFS($P13:$AT13,$P$5:$AT$5,">"&D$172,$P$5:$AT$5,"<"&D$173) -> 46.4 | F13: =SUMIFS($P13:$AT13,$P$5:$AT$5,">"&F$172,$P$5:$AT$5,"<"&F$173) -> 31.5 | G13: =SUMIFS($P13:$AT13,$P$5:$AT$5,">"&G$172,$P$5:$AT$5,"<"&G$173) -> 24.25 | I13: =SUMIFS($P13:$AT13,$P$5:$AT$5,">"&I$172,$P$5:$AT$5,"<"&I$173) -> 41.25 | J13: =SUMIFS($P13:$AT13,$P$5:$AT$5,">"&J$172,$P$5:$AT$5,"<"&J$173) -> 39.65 | K13: =+C114 -> 42 | M13: =K13-J13 -> 2.35 | N13: =IFERROR(K13/J13-1,0) -> 0.0592686 | P13: =SUMIFS('Combined P&L'!N:N,'Combined P&L'!$C:$C,'P&L Forecast'!$B13) -> 0 | Q13: =SUMIFS('Combined P&L'!O:O,'Combined P&L'!$C:$C,'P&L Forecast'!$B13) -> 0 | R13: =SUMIFS('Combined P&L'!P:P,'Combined P&L'!$C:$C,'P&L Forecast'!$B13) -> 0 | S13: =SUMIFS('Combined P&L'!Q:Q,'Combined P&L'!$C:$C,'P&L Forecast'!$B13) -> 0 | T13: =SUMIFS('Combined P&L'!R:R,'Combined P&L'!$C:$C,'P&L Forecast'!$B13) -> 0 | U13: =SUMIFS('Combined P&L'!S:S,'Combined P&L'!$C:$C,'P&L Forecast'!$B13) -> 0 | V13: =SUMIFS('Combined P&L'!T:T,'Combined P&L'!$C:$C,'P&L Forecast'!$B13) -> 1.25 | W13: =SUMIFS('Combined P&L'!U:U,'Combined P&L'!$C:$C,'P&L Forecast'!$B13) -> 1.25 | X13: =SUMIFS('Combined P&L'!V:V,'Combined P&L'!$C:$C,'P&L Forecast'!$B13) -> 1.25 | Y13: =SUMIFS('Combined P&L'!W:W,'Combined P&L'!$C:$C,'P&L Forecast'!$B13) -> 1.25 | Z13: =SUMIFS('Combined P&L'!X:X,'Combined P&L'!$C:$C,'P&L Forecast'!$B13) -> 5.75 | AA13: =SUMIFS('Combined P&L'!Y:Y,'Combined P&L'!$C:$C,'P&L Forecast'!$B13) -> 3 | AB13: =SUMIFS('Combined P&L'!Z:Z,'Combined P&L'!$C:$C,'P&L Forecast'!$B13) -> 4.45 | AC13: =SUMIFS('Combined P&L'!AA:AA,'Combined P&L'!$C:$C,'P&L Forecast'!$B13) -> 3.45 | AD13: =SUMIFS('Combined P&L'!AB:AB,'Combined P&L'!$C:$C,'P&L Forecast'!$B13) -> 3.45 | AE13: =SUMIFS('Combined P&L'!AC:AC,'Combined P&L'!$C:$C,'P&L Forecast'!$B13) -> 5.95 | AF13: =SUMIFS('Combined P&L'!AD:AD,'Combined P&L'!$C:$C,'P&L Forecast'!$B13) -> 5.2 | AG13: =SUMIFS('Combined P&L'!AE:AE,'Combined P&L'!$C:$C,'P&L Forecast'!$B13) -> 5 | AH13: =SUMIFS('Combined P&L'!AF:AF,'Combined P&L'!$C:$C,'P&L Forecast'!$B13) -> 4 | AI13: =SUMIFS('Combined P&L'!AG:AG,'Combined P&L'!$C:$C,'P&L Forecast'!$B13) -> 2.95 | AJ13: =SUMIFS('Combined P&L'!AH:AH,'Combined P&L'!$C:$C,'P&L Forecast'!$B13) -> 3.025 | AK13: =SUMIFS('Combined P&L'!AI:AI,'Combined P&L'!$C:$C,'P&L Forecast'!$B13) -> 3.025 | AL13: =SUMIFS('Combined P&L'!AJ:AJ,'Combined P&L'!$C:$C,'P&L Forecast'!$B13) -> 2.95 | AM13: =SUMIFS('Combined P&L'!AK:AK,'Combined P&L'!$C:$C,'P&L Forecast'!$B13) -> 2.95 | AN13: =SUMIFS('Combined P&L'!AL:AL,'Combined P&L'!$C:$C,'P&L Forecast'!$B13) -> 2.75 | AO13: =SUMIFS('Combined P&L'!AM:AM,'Combined P&L'!$C:$C,'P&L Forecast'!$B13) -> 3.5 | AP13: =SUMIFS('Combined P&L'!AN:AN,'Combined P&L'!$C:$C,'P&L Forecast'!$B13) -> 2.75 | AQ13: =SUMIFS('Combined P&L'!AO:AO,'Combined P&L'!$C:$C,'P&L Forecast'!$B13) -> 4.75 | AR13: =SUMIFS('Combined P&L'!AP:AP,'Combined P&L'!$C:$C,'P&L Forecast'!$B13) -> 3.5 | AS13: =SUMIFS('Combined P&L'!AQ:AQ,'Combined P&L'!$C:$C,'P&L Forecast'!$B13) -> 3.5 | AT13: =SUMIFS('Combined P&L'!AR:AR,'Combined P&L'!$C:$C,'P&L Forecast'!$B13) -> 3.5
B14: Historical Cleanup | C14: =SUMIFS($P14:$AT14,$P$5:$AT$5,">"&C$172,$P$5:$AT$5,"<"&C$173) -> 17.624 | D14: =SUMIFS($P14:$AT14,$P$5:$AT$5,">"&D$172,$P$5:$AT$5,"<"&D$173) -> 5.03375 | F14: =SUMIFS($P14:$AT14,$P$5:$AT$5,">"&F$172,$P$5:$AT$5,"<"&F$173) -> 4.43875 | G14: =SUMIFS($P14:$AT14,$P$5:$AT$5,">"&G$172,$P$5:$AT$5,"<"&G$173) -> 0 | I14: =SUMIFS($P14:$AT14,$P$5:$AT$5,">"&I$172,$P$5:$AT$5,"<"&I$173) -> 14.30525 | J14: =SUMIFS($P14:$AT14,$P$5:$AT$5,">"&J$172,$P$5:$AT$5,"<"&J$173) -> 0.595 | K14: =+C115 -> 0 | M14: =K14-J14 -> -0.595 | N14: =IFERROR(K14/J14-1,0) -> -1 | P14: =SUMIFS('Combined P&L'!N:N,'Combined P&L'!$C:$C,'P&L Forecast'!$B14) -> 1.2 | Q14: =SUMIFS('Combined P&L'!O:O,'Combined P&L'!$C:$C,'P&L Forecast'!$B14) -> 1.7625 | R14: =SUMIFS('Combined P&L'!P:P,'Combined P&L'!$C:$C,'P&L Forecast'!$B14) -> 0.66 | S14: =SUMIFS('Combined P&L'!Q:Q,'Combined P&L'!$C:$C,'P&L Forecast'!$B14) -> 0.395 | T14: =SUMIFS('Combined P&L'!R:R,'Combined P&L'!$C:$C,'P&L Forecast'!$B14) -> 2.465 | U14: =SUMIFS('Combined P&L'!S:S,'Combined P&L'!$C:$C,'P&L Forecast'!$B14) -> 1.275 | V14: =SUMIFS('Combined P&L'!T:T,'Combined P&L'!$C:$C,'P&L Forecast'!$B14) -> 1.4625 | W14: =SUMIFS('Combined P&L'!U:U,'Combined P&L'!$C:$C,'P&L Forecast'!$B14) -> 0 | X14: =SUMIFS('Combined P&L'!V:V,'Combined P&L'!$C:$C,'P&L Forecast'!$B14) -> 1.14525 | Y14: =SUMIFS('Combined P&L'!W:W,'Combined P&L'!$C:$C,'P&L Forecast'!$B14) -> 1.35525 | Z14: =SUMIFS('Combined P&L'!X:X,'Combined P&L'!$C:$C,'P&L Forecast'!$B14) -> 1.9035 | AA14: =SUMIFS('Combined P&L'!Y:Y,'Combined P&L'!$C:$C,'P&L Forecast'!$B14) -> 4 | AB14: =SUMIFS('Combined P&L'!Z:Z,'Combined P&L'!$C:$C,'P&L Forecast'!$B14) -> 1.08375 | AC14: =SUMIFS('Combined P&L'!AA:AA,'Combined P&L'!$C:$C,'P&L Forecast'!$B14) -> 2 | AD14: =SUMIFS('Combined P&L'!AB:AB,'Combined P&L'!$C:$C,'P&L Forecast'!$B14) -> 1.355 | AE14: =SUMIFS('Combined P&L'!AC:AC,'Combined P&L'!$C:$C,'P&L Forecast'!$B14) -> 0 | AF14: =SUMIFS('Combined P&L'!AD:AD,'Combined P&L'!$C:$C,'P&L Forecast'!$B14) -> 0 | AG14: =SUMIFS('Combined P&L'!AE:AE,'Combined P&L'!$C:$C,'P&L Forecast'!$B14) -> 0 | AH14: =SUMIFS('Combined P&L'!AF:AF,'Combined P&L'!$C:$C,'P&L Forecast'!$B14) -> 0 | AI14: =SUMIFS('Combined P&L'!AG:AG,'Combined P&L'!$C:$C,'P&L Forecast'!$B14) -> 0 | AJ14: =SUMIFS('Combined P&L'!AH:AH,'Combined P&L'!$C:$C,'P&L Forecast'!$B14) -> 0 | AK14: =SUMIFS('Combined P&L'!AI:AI,'Combined P&L'!$C:$C,'P&L Forecast'!$B14) -> 0.595 | AL14: =SUMIFS('Combined P&L'!AJ:AJ,'Combined P&L'!$C:$C,'P&L Forecast'!$B14) -> 0 | AM14: =SUMIFS('Combined P&L'!AK:AK,'Combined P&L'!$C:$C,'P&L Forecast'!$B14) -> 0 | AN14: =SUMIFS('Combined P&L'!AL:AL,'Combined P&L'!$C:$C,'P&L Forecast'!$B14) -> 0 | AO14: =SUMIFS('Combined P&L'!AM:AM,'Combined P&L'!$C:$C,'P&L Forecast'!$B14) -> 0 | AP14: =SUMIFS('Combined P&L'!AN:AN,'Combined P&L'!$C:$C,'P&L Forecast'!$B14) -> 0 | AQ14: =SUMIFS('Combined P&L'!AO:AO,'Combined P&L'!$C:$C,'P&L Forecast'!$B14) -> 0 | AR14: =SUMIFS('Combined P&L'!AP:AP,'Combined P&L'!$C:$C,'P&L Forecast'!$B14) -> 0 | AS14: =SUMIFS('Combined P&L'!AQ:AQ,'Combined P&L'!$C:$C,'P&L Forecast'!$B14) -> 0 | AT14: =SUMIFS('Combined P&L'!AR:AR,'Combined P&L'!$C:$C,'P&L Forecast'!$B14) -> 0
B15: Total Recurring Revenue | C15: =SUM(C7:C14) -> 1094.3157 | D15: =SUM(D7:D14) -> 1827.8494 | F15: =SUM(F7:F14) -> 958.8909 | G15: =SUM(G7:G14) -> 1600.0675 | I15: =SUM(I7:I14) -> 1414.7118 | J15: =SUM(J7:J14) -> 2371.7313 | K15: =SUM(K7:K14) -> 3046.4493 | M15: =SUM(M7:M14) -> 674.71796 | N15: =IFERROR(K15/J15-1,0) -> 0.2844833 | P15: =SUM(P7:P14) -> 73.3495 | Q15: =SUM(Q7:Q14) -> 74.7445 | R15: =SUM(R7:R14) -> 77.996 | S15: =SUM(S7:S14) -> 83.2127 | T15: =SUM(T7:T14) -> 86.60415 | U15: =SUM(U7:U14) -> 88.544 | V15: =SUM(V7:V14) -> 93.21675 | W15: =SUM(W7:W14) -> 96.77535 | ... AT15: =SUM(AT7:AT14) -> 251.33865
B17: Profit Share | C17: =SUMIFS($P17:$AT17,$P$5:$AT$5,">"&C$172,$P$5:$AT$5,"<"&C$173) -> 6.2004 | D17: =SUMIFS($P17:$AT17,$P$5:$AT$5,">"&D$172,$P$5:$AT$5,"<"&D$173) -> 23.26179 | F17: =SUMIFS($P17:$AT17,$P$5:$AT$5,">"&F$172,$P$5:$AT$5,"<"&F$173) -> 14.50495 | G17: =SUMIFS($P17:$AT17,$P$5:$AT$5,">"&G$172,$P$5:$AT$5,"<"&G$173) -> 8.07938 | I17: =SUMIFS($P17:$AT17,$P$5:$AT$5,">"&I$172,$P$5:$AT$5,"<"&I$173) -> 17.94788 | J17: =SUMIFS($P17:$AT17,$P$5:$AT$5,">"&J$172,$P$5:$AT$5,"<"&J$173) -> 17.79609 | K17: =+C120 -> 16.83622 | M17: =K17-J17 -> -0.95987 | N17: =IFERROR(K17/J17-1,0) -> -0.053937129 | P17: =SUMIFS('Combined P&L'!N:N,'Combined P&L'!$C:$C,'P&L Forecast'!$B17) -> 0.0686 | Q17: =SUMIFS('Combined P&L'!O:O,'Combined P&L'!$C:$C,'P&L Forecast'!$B17) -> 0.1312 | R17: =SUMIFS('Combined P&L'!P:P,'Combined P&L'!$C:$C,'P&L Forecast'!$B17) -> 0.0712 | S17: =SUMIFS('Combined P&L'!Q:Q,'Combined P&L'!$C:$C,'P&L Forecast'!$B17) -> 0.0556 | T17: =SUMIFS('Combined P&L'!R:R,'Combined P&L'!$C:$C,'P&L Forecast'!$B17) -> 0.577 | U17: =SUMIFS('Combined P&L'!S:S,'Combined P&L'!$C:$C,'P&L Forecast'!$B17) -> 0.8068 | V17: =SUMIFS('Combined P&L'!T:T,'Combined P&L'!$C:$C,'P&L Forecast'!$B17) -> 0.6656 | W17: =SUMIFS('Combined P&L'!U:U,'Combined P&L'!$C:$C,'P&L Forecast'!$B17) -> 0.8264 | X17: =SUMIFS('Combined P&L'!V:V,'Combined P&L'!$C:$C,'P&L Forecast'!$B17) -> 1.3808 | Y17: =SUMIFS('Combined P&L'!W:W,'Combined P&L'!$C:$C,'P&L Forecast'!$B17) -> 0.8604 | Z17: =SUMIFS('Combined P&L'!X:X,'Combined P&L'!$C:$C,'P&L Forecast'!$B17) -> 0.51 | AA17: =SUMIFS('Combined P&L'!Y:Y,'Combined P&L'!$C:$C,'P&L Forecast'!$B17) -> 0.2468 | AB17: =SUMIFS('Combined P&L'!Z:Z,'Combined P&L'!$C:$C,'P&L Forecast'!$B17) -> 7.3584 | AC17: =SUMIFS('Combined P&L'!AA:AA,'Combined P&L'!$C:$C,'P&L Forecast'!$B17) -> 1.29335 | AD17: =SUMIFS('Combined P&L'!AB:AB,'Combined P&L'!$C:$C,'P&L Forecast'!$B17) -> 0.96833 | AE17: =SUMIFS('Combined P&L'!AC:AC,'Combined P&L'!$C:$C,'P&L Forecast'!$B17) -> 1.1656 | AF17: =SUMIFS('Combined P&L'!AD:AD,'Combined P&L'!$C:$C,'P&L Forecast'!$B17) -> 0.96093 | AG17: =SUMIFS('Combined P&L'!AE:AE,'Combined P&L'!$C:$C,'P&L Forecast'!$B17) -> 1.71127 | AH17: =SUMIFS('Combined P&L'!AF:AF,'Combined P&L'!$C:$C,'P&L Forecast'!$B17) -> 1.04707 | AI17: =SUMIFS('Combined P&L'!AG:AG,'Combined P&L'!$C:$C,'P&L Forecast'!$B17) -> 2.04088 | AJ17: =SUMIFS('Combined P&L'!AH:AH,'Combined P&L'!$C:$C,'P&L Forecast'!$B17) -> 1.13621 | AK17: =SUMIFS('Combined P&L'!AI:AI,'Combined P&L'!$C:$C,'P&L Forecast'!$B17) -> 2.01424 | AL17: =SUMIFS('Combined P&L'!AJ:AJ,'Combined P&L'!$C:$C,'P&L Forecast'!$B17) -> 1.29758 | AM17: =SUMIFS('Combined P&L'!AK:AK,'Combined P&L'!$C:$C,'P&L Forecast'!$B17) -> 2.26793 | AN17: =SUMIFS('Combined P&L'!AL:AL,'Combined P&L'!$C:$C,'P&L Forecast'!$B17) -> 2.67784 | AO17: =SUMIFS('Combined P&L'!AM:AM,'Combined P&L'!$C:$C,'P&L Forecast'!$B17) -> 2.35401 | AP17: =SUMIFS('Combined P&L'!AN:AN,'Combined P&L'!$C:$C,'P&L Forecast'!$B17) -> 0.2276 | AQ17: =SUMIFS('Combined P&L'!AO:AO,'Combined P&L'!$C:$C,'P&L Forecast'!$B17) -> 1.47836 | AR17: =SUMIFS('Combined P&L'!AP:AP,'Combined P&L'!$C:$C,'P&L Forecast'!$B17) -> 0.66824 | AS17: =SUMIFS('Combined P&L'!AQ:AQ,'Combined P&L'!$C:$C,'P&L Forecast'!$B17) -> 0.58613 | AT17: =SUMIFS('Combined P&L'!AR:AR,'Combined P&L'!$C:$C,'P&L Forecast'!$B17) -> 0.0872
B18: 1099 Filing | C18: =SUMIFS($P18:$AT18,$P$5:$AT$5,">"&C$172,$P$5:$AT$5,"<"&C$173) -> 10.475 | D18: =SUMIFS($P18:$AT18,$P$5:$AT$5,">"&D$172,$P$5:$AT$5,"<"&D$173) -> 23.55 | F18: =SUMIFS($P18:$AT18,$P$5:$AT$5,">"&F$172,$P$5:$AT$5,"<"&F$173) -> 23.49 | G18: =SUMIFS($P18:$AT18,$P$5:$AT$5,">"&G$172,$P$5:$AT$5,"<"&G$173) -> 38.7015 | I18: =SUMIFS($P18:$AT18,$P$5:$AT$5,">"&I$172,$P$5:$AT$5,"<"&I$173) -> 23.52 | J18: =SUMIFS($P18:$AT18,$P$5:$AT$5,">"&J$172,$P$5:$AT$5,"<"&J$173) -> 38.7615 | K18: =+C118 -> 10 | M18: =K18-J18 -> -28.7615 | N18: =IFERROR(K18/J18-1,0) -> -0.74201205 | P18: =SUMIFS('Combined P&L'!N:N,'Combined P&L'!$C:$C,'P&L Forecast'!$B18) -> 6.945 | Q18: =SUMIFS('Combined P&L'!O:O,'Combined P&L'!$C:$C,'P&L Forecast'!$B18) -> 3.38 | R18: =SUMIFS('Combined P&L'!P:P,'Combined P&L'!$C:$C,'P&L Forecast'!$B18) -> 0.045 | S18: =SUMIFS('Combined P&L'!Q:Q,'Combined P&L'!$C:$C,'P&L Forecast'!$B18) -> 0.06 | T18: =SUMIFS('Combined P&L'!R:R,'Combined P&L'!$C:$C,'P&L Forecast'!$B18) -> 0.015 | U18: =SUMIFS('Combined P&L'!S:S,'Combined P&L'!$C:$C,'P&L Forecast'!$B18) -> 0 | V18: =SUMIFS('Combined P&L'!T:T,'Combined P&L'!$C:$C,'P&L Forecast'!$B18) -> 0 | W18: =SUMIFS('Combined P&L'!U:U,'Combined P&L'!$C:$C,'P&L Forecast'!$B18) -> 0.015 | X18: =SUMIFS('Combined P&L'!V:V,'Combined P&L'!$C:$C,'P&L Forecast'!$B18) -> 0 | Y18: =SUMIFS('Combined P&L'!W:W,'Combined P&L'!$C:$C,'P&L Forecast'!$B18) -> 0 | Z18: =SUMIFS('Combined P&L'!X:X,'Combined P&L'!$C:$C,'P&L Forecast'!$B18) -> 0.015 | AA18: =SUMIFS('Combined P&L'!Y:Y,'Combined P&L'!$C:$C,'P&L Forecast'!$B18) -> 0 | AB18: =SUMIFS('Combined P&L'!Z:Z,'Combined P&L'!$C:$C,'P&L Forecast'!$B18) -> 13.485 | AC18: =SUMIFS('Combined P&L'!AA:AA,'Combined P&L'!$C:$C,'P&L Forecast'!$B18) -> 9.915 | AD18: =SUMIFS('Combined P&L'!AB:AB,'Combined P&L'!$C:$C,'P&L Forecast'!$B18) -> 0.06 | AE18: =SUMIFS('Combined P&L'!AC:AC,'Combined P&L'!$C:$C,'P&L Forecast'!$B18) -> 0.03 | AF18: =SUMIFS('Combined P&L'!AD:AD,'Combined P&L'!$C:$C,'P&L Forecast'!$B18) -> 0 | AG18: =SUMIFS('Combined P&L'!AE:AE,'Combined P&L'!$C:$C,'P&L Forecast'!$B18) -> 0 | AH18: =SUMIFS('Combined P&L'!AF:AF,'Combined P&L'!$C:$C,'P&L Forecast'!$B18) -> 0 | AI18: =SUMIFS('Combined P&L'!AG:AG,'Combined P&L'!$C:$C,'P&L Forecast'!$B18) -> 0.03 | AJ18: =SUMIFS('Combined P&L'!AH:AH,'Combined P&L'!$C:$C,'P&L Forecast'!$B18) -> 0.03 | AK18: =SUMIFS('Combined P&L'!AI:AI,'Combined P&L'!$C:$C,'P&L Forecast'!$B18) -> 0 | AL18: =SUMIFS('Combined P&L'!AJ:AJ,'Combined P&L'!$C:$C,'P&L Forecast'!$B18) -> 0 | AM18: =SUMIFS('Combined P&L'!AK:AK,'Combined P&L'!$C:$C,'P&L Forecast'!$B18) -> 0 | AN18: =SUMIFS('Combined P&L'!AL:AL,'Combined P&L'!$C:$C,'P&L Forecast'!$B18) -> 6.105 | AO18: =SUMIFS('Combined P&L'!AM:AM,'Combined P&L'!$C:$C,'P&L Forecast'!$B18) -> 31.1565 | AP18: =SUMIFS('Combined P&L'!AN:AN,'Combined P&L'!$C:$C,'P&L Forecast'!$B18) -> 1.26 | AQ18: =SUMIFS('Combined P&L'!AO:AO,'Combined P&L'!$C:$C,'P&L Forecast'!$B18) -> 0.18 | AR18: =SUMIFS('Combined P&L'!AP:AP,'Combined P&L'!$C:$C,'P&L Forecast'!$B18) -> 0 | AS18: =SUMIFS('Combined P&L'!AQ:AQ,'Combined P&L'!$C:$C,'P&L Forecast'!$B18) -> 0 | AT18: =SUMIFS('Combined P&L'!AR:AR,'Combined P&L'!$C:$C,'P&L Forecast'!$B18) -> 0
B19: Income Tax | C19: =SUMIFS($P19:$AT19,$P$5:$AT$5,">"&C$172,$P$5:$AT$5,"<"&C$173) -> 0 | D19: =SUMIFS($P19:$AT19,$P$5:$AT$5,">"&D$172,$P$5:$AT$5,"<"&D$173) -> 3.4 | F19: =SUMIFS($P19:$AT19,$P$5:$AT$5,">"&F$172,$P$5:$AT$5,"<"&F$173) -> 0 | G19: =SUMIFS($P19:$AT19,$P$5:$AT$5,">"&G$172,$P$5:$AT$5,"<"&G$173) -> 23.915 | I19: =SUMIFS($P19:$AT19,$P$5:$AT$5,">"&I$172,$P$5:$AT$5,"<"&I$173) -> 0 | J19: =SUMIFS($P19:$AT19,$P$5:$AT$5,">"&J$172,$P$5:$AT$5,"<"&J$173) -> 27.315 | K19: =+C119 -> 0 | M19: =K19-J19 -> -27.315 | N19: =IFERROR(K19/J19-1,0) -> -1 | P19: =SUMIFS('Combined P&L'!N:N,'Combined P&L'!$C:$C,'P&L Forecast'!$B19) -> 0 | Q19: =SUMIFS('Combined P&L'!O:O,'Combined P&L'!$C:$C,'P&L Forecast'!$B19) -> 0 | R19: =SUMIFS('Combined P&L'!P:P,'Combined P&L'!$C:$C,'P&L Forecast'!$B19) -> 0 | S19: =SUMIFS('Combined P&L'!Q:Q,'Combined P&L'!$C:$C,'P&L Forecast'!$B19) -> 0 | T19: =SUMIFS('Combined P&L'!R:R,'Combined P&L'!$C:$C,'P&L Forecast'!$B19) -> 0 | U19: =SUMIFS('Combined P&L'!S:S,'Combined P&L'!$C:$C,'P&L Forecast'!$B19) -> 0 | V19: =SUMIFS('Combined P&L'!T:T,'Combined P&L'!$C:$C,'P&L Forecast'!$B19) -> 0 | W19: =SUMIFS('Combined P&L'!U:U,'Combined P&L'!$C:$C,'P&L Forecast'!$B19) -> 0 | X19: =SUMIFS('Combined P&L'!V:V,'Combined P&L'!$C:$C,'P&L Forecast'!$B19) -> 0 | Y19: =SUMIFS('Combined P&L'!W:W,'Combined P&L'!$C:$C,'P&L Forecast'!$B19) -> 0 | Z19: =SUMIFS('Combined P&L'!X:X,'Combined P&L'!$C:$C,'P&L Forecast'!$B19) -> 0 | AA19: =SUMIFS('Combined P&L'!Y:Y,'Combined P&L'!$C:$C,'P&L Forecast'!$B19) -> 0 | AB19: =SUMIFS('Combined P&L'!Z:Z,'Combined P&L'!$C:$C,'P&L Forecast'!$B19) -> 0 | AC19: =SUMIFS('Combined P&L'!AA:AA,'Combined P&L'!$C:$C,'P&L Forecast'!$B19) -> 0 | AD19: =SUMIFS('Combined P&L'!AB:AB,'Combined P&L'!$C:$C,'P&L Forecast'!$B19) -> 0 | AE19: =SUMIFS('Combined P&L'!AC:AC,'Combined P&L'!$C:$C,'P&L Forecast'!$B19) -> 0 | AF19: =SUMIFS('Combined P&L'!AD:AD,'Combined P&L'!$C:$C,'P&L Forecast'!$B19) -> 0 | AG19: =SUMIFS('Combined P&L'!AE:AE,'Combined P&L'!$C:$C,'P&L Forecast'!$B19) -> 0 | AH19: =SUMIFS('Combined P&L'!AF:AF,'Combined P&L'!$C:$C,'P&L Forecast'!$B19) -> 0 | AI19: =SUMIFS('Combined P&L'!AG:AG,'Combined P&L'!$C:$C,'P&L Forecast'!$B19) -> 0 | AJ19: =SUMIFS('Combined P&L'!AH:AH,'Combined P&L'!$C:$C,'P&L Forecast'!$B19) -> 0.875 | AK19: =SUMIFS('Combined P&L'!AI:AI,'Combined P&L'!$C:$C,'P&L Forecast'!$B19) -> 1.65 | AL19: =SUMIFS('Combined P&L'!AJ:AJ,'Combined P&L'!$C:$C,'P&L Forecast'!$B19) -> 0 | AM19: =SUMIFS('Combined P&L'!AK:AK,'Combined P&L'!$C:$C,'P&L Forecast'!$B19) -> 0.875 | AN19: =SUMIFS('Combined P&L'!AL:AL,'Combined P&L'!$C:$C,'P&L Forecast'!$B19) -> 0 | AO19: =SUMIFS('Combined P&L'!AM:AM,'Combined P&L'!$C:$C,'P&L Forecast'!$B19) -> 0 | AP19: =SUMIFS('Combined P&L'!AN:AN,'Combined P&L'!$C:$C,'P&L Forecast'!$B19) -> 14.19 | AQ19: =SUMIFS('Combined P&L'!AO:AO,'Combined P&L'!$C:$C,'P&L Forecast'!$B19) -> 6.625 | AR19: =SUMIFS('Combined P&L'!AP:AP,'Combined P&L'!$C:$C,'P&L Forecast'!$B19) -> 0 | AS19: =SUMIFS('Combined P&L'!AQ:AQ,'Combined P&L'!$C:$C,'P&L Forecast'!$B19) -> 3.1 | AT19: =SUMIFS('Combined P&L'!AR:AR,'Combined P&L'!$C:$C,'P&L Forecast'!$B19) -> 0
B20: Billable Expense Income | C20: =SUMIFS($P20:$AT20,$P$5:$AT$5,">"&C$172,$P$5:$AT$5,"<"&C$173) -> 0.3747 | D20: =SUMIFS($P20:$AT20,$P$5:$AT$5,">"&D$172,$P$5:$AT$5,"<"&D$173) -> 1.12194 | F20: =SUMIFS($P20:$AT20,$P$5:$AT$5,">"&F$172,$P$5:$AT$5,"<"&F$173) -> 0.78725 | G20: =SUMIFS($P20:$AT20,$P$5:$AT$5,">"&G$172,$P$5:$AT$5,"<"&G$173) -> 0.25783 | I20: =SUMIFS($P20:$AT20,$P$5:$AT$5,">"&I$172,$P$5:$AT$5,"<"&I$173) -> 0.79724 | J20: =SUMIFS($P20:$AT20,$P$5:$AT$5,">"&J$172,$P$5:$AT$5,"<"&J$173) -> 0.88223 | K20: =+C121 -> 0 | M20: =K20-J20 -> -0.88223 | N20: =IFERROR(K20/J20-1,0) -> -1 | P20: =SUMIFS('Combined P&L'!N:N,'Combined P&L'!$C:$C,'P&L Forecast'!$B20) -> 0.05 | Q20: =SUMIFS('Combined P&L'!O:O,'Combined P&L'!$C:$C,'P&L Forecast'!$B20) -> 0 | R20: =SUMIFS('Combined P&L'!P:P,'Combined P&L'!$C:$C,'P&L Forecast'!$B20) -> 0 | S20: =SUMIFS('Combined P&L'!Q:Q,'Combined P&L'!$C:$C,'P&L Forecast'!$B20) -> 0.025 | T20: =SUMIFS('Combined P&L'!R:R,'Combined P&L'!$C:$C,'P&L Forecast'!$B20) -> 0 | U20: =SUMIFS('Combined P&L'!S:S,'Combined P&L'!$C:$C,'P&L Forecast'!$B20) -> 0 | V20: =SUMIFS('Combined P&L'!T:T,'Combined P&L'!$C:$C,'P&L Forecast'!$B20) -> 0.2997 | W20: =SUMIFS('Combined P&L'!U:U,'Combined P&L'!$C:$C,'P&L Forecast'!$B20) -> 0 | X20: =SUMIFS('Combined P&L'!V:V,'Combined P&L'!$C:$C,'P&L Forecast'!$B20) -> 0 | Y20: =SUMIFS('Combined P&L'!W:W,'Combined P&L'!$C:$C,'P&L Forecast'!$B20) -> 0 | Z20: =SUMIFS('Combined P&L'!X:X,'Combined P&L'!$C:$C,'P&L Forecast'!$B20) -> 0 | AA20: =SUMIFS('Combined P&L'!Y:Y,'Combined P&L'!$C:$C,'P&L Forecast'!$B20) -> 0 | AB20: =SUMIFS('Combined P&L'!Z:Z,'Combined P&L'!$C:$C,'P&L Forecast'!$B20) -> 0.025 | AC20: =SUMIFS('Combined P&L'!AA:AA,'Combined P&L'!$C:$C,'P&L Forecast'!$B20) -> 0.3996 | AD20: =SUMIFS('Combined P&L'!AB:AB,'Combined P&L'!$C:$C,'P&L Forecast'!$B20) -> 0 | AE20: =SUMIFS('Combined P&L'!AC:AC,'Combined P&L'!$C:$C,'P&L Forecast'!$B20) -> 0 | AF20: =SUMIFS('Combined P&L'!AD:AD,'Combined P&L'!$C:$C,'P&L Forecast'!$B20) -> 0.07294 | AG20: =SUMIFS('Combined P&L'!AE:AE,'Combined P&L'!$C:$C,'P&L Forecast'!$B20) -> 0 | AH20: =SUMIFS('Combined P&L'!AF:AF,'Combined P&L'!$C:$C,'P&L Forecast'!$B20) -> 0.28971 | AI20: =SUMIFS('Combined P&L'!AG:AG,'Combined P&L'!$C:$C,'P&L Forecast'!$B20) -> 0.30969 | AJ20: =SUMIFS('Combined P&L'!AH:AH,'Combined P&L'!$C:$C,'P&L Forecast'!$B20) -> 0 | AK20: =SUMIFS('Combined P&L'!AI:AI,'Combined P&L'!$C:$C,'P&L Forecast'!$B20) -> 0 | AL20: =SUMIFS('Combined P&L'!AJ:AJ,'Combined P&L'!$C:$C,'P&L Forecast'!$B20) -> 0 | AM20: =SUMIFS('Combined P&L'!AK:AK,'Combined P&L'!$C:$C,'P&L Forecast'!$B20) -> 0.025 | AN20: =SUMIFS('Combined P&L'!AL:AL,'Combined P&L'!$C:$C,'P&L Forecast'!$B20) -> 0.15984 | AO20: =SUMIFS('Combined P&L'!AM:AM,'Combined P&L'!$C:$C,'P&L Forecast'!$B20) -> 0 | AP20: =SUMIFS('Combined P&L'!AN:AN,'Combined P&L'!$C:$C,'P&L Forecast'!$B20) -> 0.075 | AQ20: =SUMIFS('Combined P&L'!AO:AO,'Combined P&L'!$C:$C,'P&L Forecast'!$B20) -> 0 | AR20: =SUMIFS('Combined P&L'!AP:AP,'Combined P&L'!$C:$C,'P&L Forecast'!$B20) -> 0 | AS20: =SUMIFS('Combined P&L'!AQ:AQ,'Combined P&L'!$C:$C,'P&L Forecast'!$B20) -> 0.02299 | AT20: =SUMIFS('Combined P&L'!AR:AR,'Combined P&L'!$C:$C,'P&L Forecast'!$B20) -> 0
B21: Offshore Recruiting | C21: =SUMIFS($P21:$AT21,$P$5:$AT$5,">"&C$172,$P$5:$AT$5,"<"&C$173) -> 23.6 | D21: =SUMIFS($P21:$AT21,$P$5:$AT$5,">"&D$172,$P$5:$AT$5,"<"&D$173) -> 0.2 | F21: =SUMIFS($P21:$AT21,$P$5:$AT$5,">"&F$172,$P$5:$AT$5,"<"&F$173) -> 0.2 | G21: =SUMIFS($P21:$AT21,$P$5:$AT$5,">"&G$172,$P$5:$AT$5,"<"&G$173) -> 0 | I21: =SUMIFS($P21:$AT21,$P$5:$AT$5,">"&I$172,$P$5:$AT$5,"<"&I$173) -> 16.735 | J21: =SUMIFS($P21:$AT21,$P$5:$AT$5,">"&J$172,$P$5:$AT$5,"<"&J$173) -> 0 | K21: =+C122 -> 0 | M21: =K21-J21 -> 0 | N21: =IFERROR(K21/J21-1,0) -> 0 | P21: =SUMIFS('Combined P&L'!N:N,'Combined P&L'!$C:$C,'P&L Forecast'!$B21) -> 0.5 | Q21: =SUMIFS('Combined P&L'!O:O,'Combined P&L'!$C:$C,'P&L Forecast'!$B21) -> 3 | R21: =SUMIFS('Combined P&L'!P:P,'Combined P&L'!$C:$C,'P&L Forecast'!$B21) -> 0 | S21: =SUMIFS('Combined P&L'!Q:Q,'Combined P&L'!$C:$C,'P&L Forecast'!$B21) -> 0 | T21: =SUMIFS('Combined P&L'!R:R,'Combined P&L'!$C:$C,'P&L Forecast'!$B21) -> 3 | U21: =SUMIFS('Combined P&L'!S:S,'Combined P&L'!$C:$C,'P&L Forecast'!$B21) -> 0.565 | V21: =SUMIFS('Combined P&L'!T:T,'Combined P&L'!$C:$C,'P&L Forecast'!$B21) -> 10.5 | W21: =SUMIFS('Combined P&L'!U:U,'Combined P&L'!$C:$C,'P&L Forecast'!$B21) -> 6.5 | X21: =SUMIFS('Combined P&L'!V:V,'Combined P&L'!$C:$C,'P&L Forecast'!$B21) -> 0.5 | Y21: =SUMIFS('Combined P&L'!W:W,'Combined P&L'!$C:$C,'P&L Forecast'!$B21) -> -0.965 | Z21: =SUMIFS('Combined P&L'!X:X,'Combined P&L'!$C:$C,'P&L Forecast'!$B21) -> 0 | AA21: =SUMIFS('Combined P&L'!Y:Y,'Combined P&L'!$C:$C,'P&L Forecast'!$B21) -> 0 | AB21: =SUMIFS('Combined P&L'!Z:Z,'Combined P&L'!$C:$C,'P&L Forecast'!$B21) -> 0.1 | AC21: =SUMIFS('Combined P&L'!AA:AA,'Combined P&L'!$C:$C,'P&L Forecast'!$B21) -> 0 | AD21: =SUMIFS('Combined P&L'!AB:AB,'Combined P&L'!$C:$C,'P&L Forecast'!$B21) -> 0.1 | AE21: =SUMIFS('Combined P&L'!AC:AC,'Combined P&L'!$C:$C,'P&L Forecast'!$B21) -> 0 | AF21: =SUMIFS('Combined P&L'!AD:AD,'Combined P&L'!$C:$C,'P&L Forecast'!$B21) -> 0 | AG21: =SUMIFS('Combined P&L'!AE:AE,'Combined P&L'!$C:$C,'P&L Forecast'!$B21) -> 0 | AH21: =SUMIFS('Combined P&L'!AF:AF,'Combined P&L'!$C:$C,'P&L Forecast'!$B21) -> 0 | AI21: =SUMIFS('Combined P&L'!AG:AG,'Combined P&L'!$C:$C,'P&L Forecast'!$B21) -> 0 | AJ21: =SUMIFS('Combined P&L'!AH:AH,'Combined P&L'!$C:$C,'P&L Forecast'!$B21) -> 0 | AK21: =SUMIFS('Combined P&L'!AI:AI,'Combined P&L'!$C:$C,'P&L Forecast'!$B21) -> 0 | AL21: =SUMIFS('Combined P&L'!AJ:AJ,'Combined P&L'!$C:$C,'P&L Forecast'!$B21) -> 0 | AM21: =SUMIFS('Combined P&L'!AK:AK,'Combined P&L'!$C:$C,'P&L Forecast'!$B21) -> 0 | AN21: =SUMIFS('Combined P&L'!AL:AL,'Combined P&L'!$C:$C,'P&L Forecast'!$B21) -> 0 | AO21: =SUMIFS('Combined P&L'!AM:AM,'Combined P&L'!$C:$C,'P&L Forecast'!$B21) -> 0 | AP21: =SUMIFS('Combined P&L'!AN:AN,'Combined P&L'!$C:$C,'P&L Forecast'!$B21) -> 0 | AQ21: =SUMIFS('Combined P&L'!AO:AO,'Combined P&L'!$C:$C,'P&L Forecast'!$B21) -> 0 | AR21: =SUMIFS('Combined P&L'!AP:AP,'Combined P&L'!$C:$C,'P&L Forecast'!$B21) -> 0 | AS21: =SUMIFS('Combined P&L'!AQ:AQ,'Combined P&L'!$C:$C,'P&L Forecast'!$B21) -> 0 | AT21: =SUMIFS('Combined P&L'!AR:AR,'Combined P&L'!$C:$C,'P&L Forecast'!$B21) -> 0
B22: Total Nonrecurring Revenue | C22: =SUM(C17:C21) -> 40.6501 | D22: =SUM(D17:D21) -> 51.53373 | F22: =SUM(F17:F21) -> 38.9822 | G22: =SUM(G17:G21) -> 70.95371 | I22: =SUM(I17:I21) -> 59.00012 | J22: =SUM(J17:J21) -> 84.75482 | K22: =SUM(K17:K21) -> 26.83622 | M22: =SUM(M17:M21) -> -57.9186 | N22: =IFERROR(K22/J22-1,0) -> -0.68336644 | P22: =SUM(P17:P21) -> 7.5636 | Q22: =SUM(Q17:Q21) -> 6.5112 | R22: =SUM(R17:R21) -> 0.1162 | S22: =SUM(S17:S21) -> 0.1406 | T22: =SUM(T17:T21) -> 3.592 | U22: =SUM(U17:U21) -> 1.3718 | V22: =SUM(V17:V21) -> 11.4653 | W22: =SUM(W17:W21) -> 7.3414 | ... AT22: =SUM(AT17:AT21) -> 0.0872
B24: Total Revenue | C24: =+C22+C15 -> 1134.9659 | D24: =+D22+D15 -> 1879.3831 | F24: =+F22+F15 -> 997.8731 | G24: =+G22+G15 -> 1671.0212 | I24: =+I22+I15 -> 1473.7119 | J24: =+J22+J15 -> 2456.4862 | K24: =+K22+K15 -> 3073.2855 | M24: =+M22+M15 -> 616.79936 | N24: =IFERROR(K24/J24-1,0) -> 0.2510901 | P24: =+P22+P15 -> 80.9131 | Q24: =+Q22+Q15 -> 81.2557 | R24: =+R22+R15 -> 78.1122 | S24: =+S22+S15 -> 83.3533 | T24: =+T22+T15 -> 90.19615 | U24: =+U22+U15 -> 89.9158 | V24: =+V22+V15 -> 104.68205 | W24: =+W22+W15 -> 104.11675 | ... AT24: =+AT22+AT15 -> 251.42585
B26: Expenses
B27: Indirect Labor | C27: =SUMIFS($P27:$AT27,$P$5:$AT$5,">"&C$172,$P$5:$AT$5,"<"&C$173) -> 101.3752 | D27: =SUMIFS($P27:$AT27,$P$5:$AT$5,">"&D$172,$P$5:$AT$5,"<"&D$173) -> 281.24054 | F27: =SUMIFS($P27:$AT27,$P$5:$AT$5,">"&F$172,$P$5:$AT$5,"<"&F$173) -> 136.29648 | G27: =SUMIFS($P27:$AT27,$P$5:$AT$5,">"&G$172,$P$5:$AT$5,"<"&G$173) -> 357.27472 | I27: =SUMIFS($P27:$AT27,$P$5:$AT$5,">"&I$172,$P$5:$AT$5,"<"&I$173) -> 184.76374 | J27: =SUMIFS($P27:$AT27,$P$5:$AT$5,">"&J$172,$P$5:$AT$5,"<"&J$173) -> 466.92604 | K27: =+C126 -> 694.74456 | M27: =+J27-K27 -> -227.81852 | N27: =IFERROR(K27/J27-1,0) -> 0.48791136 | P27: =SUMIFS('Combined P&L'!N:N,'Combined P&L'!$C:$C,'P&L Forecast'!$B27) -> 3.09346 | Q27: =SUMIFS('Combined P&L'!O:O,'Combined P&L'!$C:$C,'P&L Forecast'!$B27) -> 4.63017 | R27: =SUMIFS('Combined P&L'!P:P,'Combined P&L'!$C:$C,'P&L Forecast'!$B27) -> 4.39507 | S27: =SUMIFS('Combined P&L'!Q:Q,'Combined P&L'!$C:$C,'P&L Forecast'!$B27) -> 5.86387 | T27: =SUMIFS('Combined P&L'!R:R,'Combined P&L'!$C:$C,'P&L Forecast'!$B27) -> 7.37233 | U27: =SUMIFS('Combined P&L'!S:S,'Combined P&L'!$C:$C,'P&L Forecast'!$B27) -> 4.9504 | V27: =SUMIFS('Combined P&L'!T:T,'Combined P&L'!$C:$C,'P&L Forecast'!$B27) -> 4.9504 | W27: =SUMIFS('Combined P&L'!U:U,'Combined P&L'!$C:$C,'P&L Forecast'!$B27) -> 4.70035 | X27: =SUMIFS('Combined P&L'!V:V,'Combined P&L'!$C:$C,'P&L Forecast'!$B27) -> 4.9504 | Y27: =SUMIFS('Combined P&L'!W:W,'Combined P&L'!$C:$C,'P&L Forecast'!$B27) -> 5.99987 | Z27: =SUMIFS('Combined P&L'!X:X,'Combined P&L'!$C:$C,'P&L Forecast'!$B27) -> 26.02876 | AA27: =SUMIFS('Combined P&L'!Y:Y,'Combined P&L'!$C:$C,'P&L Forecast'!$B27) -> 24.44012 | AB27: =SUMIFS('Combined P&L'!Z:Z,'Combined P&L'!$C:$C,'P&L Forecast'!$B27) -> 21.05234 | AC27: =SUMIFS('Combined P&L'!AA:AA,'Combined P&L'!$C:$C,'P&L Forecast'!$B27) -> 19.91603 | AD27: =SUMIFS('Combined P&L'!AB:AB,'Combined P&L'!$C:$C,'P&L Forecast'!$B27) -> 11.74387 | AE27: =SUMIFS('Combined P&L'!AC:AC,'Combined P&L'!$C:$C,'P&L Forecast'!$B27) -> 19.61792 | AF27: =SUMIFS('Combined P&L'!AD:AD,'Combined P&L'!$C:$C,'P&L Forecast'!$B27) -> 20.66978 | AG27: =SUMIFS('Combined P&L'!AE:AE,'Combined P&L'!$C:$C,'P&L Forecast'!$B27) -> 20.6939 | AH27: =SUMIFS('Combined P&L'!AF:AF,'Combined P&L'!$C:$C,'P&L Forecast'!$B27) -> 22.60264 | AI27: =SUMIFS('Combined P&L'!AG:AG,'Combined P&L'!$C:$C,'P&L Forecast'!$B27) -> 19.96128 | AJ27: =SUMIFS('Combined P&L'!AH:AH,'Combined P&L'!$C:$C,'P&L Forecast'!$B27) -> 27.60563 | AK27: =SUMIFS('Combined P&L'!AI:AI,'Combined P&L'!$C:$C,'P&L Forecast'!$B27) -> 34.18589 | AL27: =SUMIFS('Combined P&L'!AJ:AJ,'Combined P&L'!$C:$C,'P&L Forecast'!$B27) -> 29.73157 | AM27: =SUMIFS('Combined P&L'!AK:AK,'Combined P&L'!$C:$C,'P&L Forecast'!$B27) -> 33.45969 | AN27: =SUMIFS('Combined P&L'!AL:AL,'Combined P&L'!$C:$C,'P&L Forecast'!$B27) -> 36.2536 | AO27: =SUMIFS('Combined P&L'!AM:AM,'Combined P&L'!$C:$C,'P&L Forecast'!$B27) -> 33.60751 | AP27: =SUMIFS('Combined P&L'!AN:AN,'Combined P&L'!$C:$C,'P&L Forecast'!$B27) -> 57.19924 | AQ27: =SUMIFS('Combined P&L'!AO:AO,'Combined P&L'!$C:$C,'P&L Forecast'!$B27) -> 58.24595 | AR27: =SUMIFS('Combined P&L'!AP:AP,'Combined P&L'!$C:$C,'P&L Forecast'!$B27) -> 54.06923 | AS27: =SUMIFS('Combined P&L'!AQ:AQ,'Combined P&L'!$C:$C,'P&L Forecast'!$B27) -> 60.00381 | AT27: =SUMIFS('Combined P&L'!AR:AR,'Combined P&L'!$C:$C,'P&L Forecast'!$B27) -> 57.89538
B28: Bookkeeper Wages | C28: =SUMIFS($P28:$AT28,$P$5:$AT$5,">"&C$172,$P$5:$AT$5,"<"&C$173) -> 183.36903 | D28: =SUMIFS($P28:$AT28,$P$5:$AT$5,">"&D$172,$P$5:$AT$5,"<"&D$173) -> 316.18462 | F28: =SUMIFS($P28:$AT28,$P$5:$AT$5,">"&F$172,$P$5:$AT$5,"<"&F$173) -> 147.26813 | G28: =SUMIFS($P28:$AT28,$P$5:$AT$5,">"&G$172,$P$5:$AT$5,"<"&G$173) -> 267.7574 | I28: =SUMIFS($P28:$AT28,$P$5:$AT$5,">"&I$172,$P$5:$AT$5,"<"&I$173) -> 226.32031 | J28: =SUMIFS($P28:$AT28,$P$5:$AT$5,">"&J$172,$P$5:$AT$5,"<"&J$173) -> 420.0952 | K28: =+C127 -> 533.8512 | M28: =+J28-K28 -> -113.756 | N28: =IFERROR(K28/J28-1,0) -> 0.27078624 | P28: =SUMIFS('Combined P&L'!N:N,'Combined P&L'!$C:$C,'P&L Forecast'!$B28) -> 9.555 | Q28: =SUMIFS('Combined P&L'!O:O,'Combined P&L'!$C:$C,'P&L Forecast'!$B28) -> 9.555 | R28: =SUMIFS('Combined P&L'!P:P,'Combined P&L'!$C:$C,'P&L Forecast'!$B28) -> 10.3972 | S28: =SUMIFS('Combined P&L'!Q:Q,'Combined P&L'!$C:$C,'P&L Forecast'!$B28) -> 14.99967 | T28: =SUMIFS('Combined P&L'!R:R,'Combined P&L'!$C:$C,'P&L Forecast'!$B28) -> 18.0098 | U28: =SUMIFS('Combined P&L'!S:S,'Combined P&L'!$C:$C,'P&L Forecast'!$B28) -> 13.89127 | V28: =SUMIFS('Combined P&L'!T:T,'Combined P&L'!$C:$C,'P&L Forecast'!$B28) -> 14.04824 | W28: =SUMIFS('Combined P&L'!U:U,'Combined P&L'!$C:$C,'P&L Forecast'!$B28) -> 13.39091 | X28: =SUMIFS('Combined P&L'!V:V,'Combined P&L'!$C:$C,'P&L Forecast'!$B28) -> 14.66931 | Y28: =SUMIFS('Combined P&L'!W:W,'Combined P&L'!$C:$C,'P&L Forecast'!$B28) -> 15.88253 | Z28: =SUMIFS('Combined P&L'!X:X,'Combined P&L'!$C:$C,'P&L Forecast'!$B28) -> 27.18867 | AA28: =SUMIFS('Combined P&L'!Y:Y,'Combined P&L'!$C:$C,'P&L Forecast'!$B28) -> 21.78143 | AB28: =SUMIFS('Combined P&L'!Z:Z,'Combined P&L'!$C:$C,'P&L Forecast'!$B28) -> 19.40233 | AC28: =SUMIFS('Combined P&L'!AA:AA,'Combined P&L'!$C:$C,'P&L Forecast'!$B28) -> 16.40053 | AD28: =SUMIFS('Combined P&L'!AB:AB,'Combined P&L'!$C:$C,'P&L Forecast'!$B28) -> 19.56983 | AE28: =SUMIFS('Combined P&L'!AC:AC,'Combined P&L'!$C:$C,'P&L Forecast'!$B28) -> 22.1542 | AF28: =SUMIFS('Combined P&L'!AD:AD,'Combined P&L'!$C:$C,'P&L Forecast'!$B28) -> 20.79154 | AG28: =SUMIFS('Combined P&L'!AE:AE,'Combined P&L'!$C:$C,'P&L Forecast'!$B28) -> 21.04079 | AH28: =SUMIFS('Combined P&L'!AF:AF,'Combined P&L'!$C:$C,'P&L Forecast'!$B28) -> 27.90891 | AI28: =SUMIFS('Combined P&L'!AG:AG,'Combined P&L'!$C:$C,'P&L Forecast'!$B28) -> 29.547 | AJ28: =SUMIFS('Combined P&L'!AH:AH,'Combined P&L'!$C:$C,'P&L Forecast'!$B28) -> 33.44727 | AK28: =SUMIFS('Combined P&L'!AI:AI,'Combined P&L'!$C:$C,'P&L Forecast'!$B28) -> 37.79432 | AL28: =SUMIFS('Combined P&L'!AJ:AJ,'Combined P&L'!$C:$C,'P&L Forecast'!$B28) -> 34.06332 | AM28: =SUMIFS('Combined P&L'!AK:AK,'Combined P&L'!$C:$C,'P&L Forecast'!$B28) -> 34.06458 | AN28: =SUMIFS('Combined P&L'!AL:AL,'Combined P&L'!$C:$C,'P&L Forecast'!$B28) -> 38.37888 | AO28: =SUMIFS('Combined P&L'!AM:AM,'Combined P&L'!$C:$C,'P&L Forecast'!$B28) -> 29.70152 | AP28: =SUMIFS('Combined P&L'!AN:AN,'Combined P&L'!$C:$C,'P&L Forecast'!$B28) -> 37.4225 | AQ28: =SUMIFS('Combined P&L'!AO:AO,'Combined P&L'!$C:$C,'P&L Forecast'!$B28) -> 38.7723 | AR28: =SUMIFS('Combined P&L'!AP:AP,'Combined P&L'!$C:$C,'P&L Forecast'!$B28) -> 38.29477 | AS28: =SUMIFS('Combined P&L'!AQ:AQ,'Combined P&L'!$C:$C,'P&L Forecast'!$B28) -> 40.69983 | AT28: =SUMIFS('Combined P&L'!AR:AR,'Combined P&L'!$C:$C,'P&L Forecast'!$B28) -> 44.4876
B29: Client Lead Wages | C29: =SUMIFS($P29:$AT29,$P$5:$AT$5,">"&C$172,$P$5:$AT$5,"<"&C$173) -> 286.16129 | D29: =SUMIFS($P29:$AT29,$P$5:$AT$5,">"&D$172,$P$5:$AT$5,"<"&D$173) -> 352.95844 | F29: =SUMIFS($P29:$AT29,$P$5:$AT$5,">"&F$172,$P$5:$AT$5,"<"&F$173) -> 201.27983 | G29: =SUMIFS($P29:$AT29,$P$5:$AT$5,">"&G$172,$P$5:$AT$5,"<"&G$173) -> 202.05309 | I29: =SUMIFS($P29:$AT29,$P$5:$AT$5,">"&I$172,$P$5:$AT$5,"<"&I$173) -> 351.95999 | J29: =SUMIFS($P29:$AT29,$P$5:$AT$5,">"&J$172,$P$5:$AT$5,"<"&J$173) -> 350.46762 | K29: =+C129 -> 392.92452 | M29: =+J29-K29 -> -42.4569 | N29: =IFERROR(K29/J29-1,0) -> 0.12114357 | P29: =SUMIFS('Combined P&L'!N:N,'Combined P&L'!$C:$C,'P&L Forecast'!$B29) -> 9.96108 | Q29: =SUMIFS('Combined P&L'!O:O,'Combined P&L'!$C:$C,'P&L Forecast'!$B29) -> 13.85026 | R29: =SUMIFS('Combined P&L'!P:P,'Combined P&L'!$C:$C,'P&L Forecast'!$B29) -> 12.79054 | S29: =SUMIFS('Combined P&L'!Q:Q,'Combined P&L'!$C:$C,'P&L Forecast'!$B29) -> 14.57145 | T29: =SUMIFS('Combined P&L'!R:R,'Combined P&L'!$C:$C,'P&L Forecast'!$B29) -> 28.28563 | U29: =SUMIFS('Combined P&L'!S:S,'Combined P&L'!$C:$C,'P&L Forecast'!$B29) -> 26.54254 | V29: =SUMIFS('Combined P&L'!T:T,'Combined P&L'!$C:$C,'P&L Forecast'!$B29) -> 28.31119 | W29: =SUMIFS('Combined P&L'!U:U,'Combined P&L'!$C:$C,'P&L Forecast'!$B29) -> 28.18746 | X29: =SUMIFS('Combined P&L'!V:V,'Combined P&L'!$C:$C,'P&L Forecast'!$B29) -> 30.86801 | Y29: =SUMIFS('Combined P&L'!W:W,'Combined P&L'!$C:$C,'P&L Forecast'!$B29) -> 31.62128 | Z29: =SUMIFS('Combined P&L'!X:X,'Combined P&L'!$C:$C,'P&L Forecast'!$B29) -> 28.44974 | AA29: =SUMIFS('Combined P&L'!Y:Y,'Combined P&L'!$C:$C,'P&L Forecast'!$B29) -> 32.72211 | AB29: =SUMIFS('Combined P&L'!Z:Z,'Combined P&L'!$C:$C,'P&L Forecast'!$B29) -> 32.78076 | AC29: =SUMIFS('Combined P&L'!AA:AA,'Combined P&L'!$C:$C,'P&L Forecast'!$B29) -> 23.36184 | AD29: =SUMIFS('Combined P&L'!AB:AB,'Combined P&L'!$C:$C,'P&L Forecast'!$B29) -> 26.91427 | AE29: =SUMIFS('Combined P&L'!AC:AC,'Combined P&L'!$C:$C,'P&L Forecast'!$B29) -> 28.81298 | AF29: =SUMIFS('Combined P&L'!AD:AD,'Combined P&L'!$C:$C,'P&L Forecast'!$B29) -> 30.65875 | AG29: =SUMIFS('Combined P&L'!AE:AE,'Combined P&L'!$C:$C,'P&L Forecast'!$B29) -> 29.2716 | AH29: =SUMIFS('Combined P&L'!AF:AF,'Combined P&L'!$C:$C,'P&L Forecast'!$B29) -> 29.47963 | AI29: =SUMIFS('Combined P&L'!AG:AG,'Combined P&L'!$C:$C,'P&L Forecast'!$B29) -> 26.83064 | AJ29: =SUMIFS('Combined P&L'!AH:AH,'Combined P&L'!$C:$C,'P&L Forecast'!$B29) -> 29.78555 | AK29: =SUMIFS('Combined P&L'!AI:AI,'Combined P&L'!$C:$C,'P&L Forecast'!$B29) -> 32.89937 | AL29: =SUMIFS('Combined P&L'!AJ:AJ,'Combined P&L'!$C:$C,'P&L Forecast'!$B29) -> 29.49334 | AM29: =SUMIFS('Combined P&L'!AK:AK,'Combined P&L'!$C:$C,'P&L Forecast'!$B29) -> 32.66971 | AN29: =SUMIFS('Combined P&L'!AL:AL,'Combined P&L'!$C:$C,'P&L Forecast'!$B29) -> 26.1149 | AO29: =SUMIFS('Combined P&L'!AM:AM,'Combined P&L'!$C:$C,'P&L Forecast'!$B29) -> 21.9055 | AP29: =SUMIFS('Combined P&L'!AN:AN,'Combined P&L'!$C:$C,'P&L Forecast'!$B29) -> 30.75844 | AQ29: =SUMIFS('Combined P&L'!AO:AO,'Combined P&L'!$C:$C,'P&L Forecast'!$B29) -> 31.59038 | AR29: =SUMIFS('Combined P&L'!AP:AP,'Combined P&L'!$C:$C,'P&L Forecast'!$B29) -> 27.69992 | AS29: =SUMIFS('Combined P&L'!AQ:AQ,'Combined P&L'!$C:$C,'P&L Forecast'!$B29) -> 31.24024 | AT29: =SUMIFS('Combined P&L'!AR:AR,'Combined P&L'!$C:$C,'P&L Forecast'!$B29) -> 32.74371
B30: Onboarding Team Wages | C30: =SUMIFS($P30:$AT30,$P$5:$AT$5,">"&C$172,$P$5:$AT$5,"<"&C$173) -> 122.81255 | D30: =SUMIFS($P30:$AT30,$P$5:$AT$5,">"&D$172,$P$5:$AT$5,"<"&D$173) -> 152.16972 | F30: =SUMIFS($P30:$AT30,$P$5:$AT$5,">"&F$172,$P$5:$AT$5,"<"&F$173) -> 73.94962 | G30: =SUMIFS($P30:$AT30,$P$5:$AT$5,">"&G$172,$P$5:$AT$5,"<"&G$173) -> 111.27999 | I30: =SUMIFS($P30:$AT30,$P$5:$AT$5,">"&I$172,$P$5:$AT$5,"<"&I$173) -> 115.8168 | J30: =SUMIFS($P30:$AT30,$P$5:$AT$5,">"&J$172,$P$5:$AT$5,"<"&J$173) -> 186.54354 | K30: =+C133 -> 197.14944 | M30: =+J30-K30 -> -10.6059 | N30: =IFERROR(K30/J30-1,0) -> 0.056854823 | P30: =SUMIFS('Combined P&L'!N:N,'Combined P&L'!$C:$C,'P&L Forecast'!$B30) -> 9.13728 | Q30: =SUMIFS('Combined P&L'!O:O,'Combined P&L'!$C:$C,'P&L Forecast'!$B30) -> 8.96296 | R30: =SUMIFS('Combined P&L'!P:P,'Combined P&L'!$C:$C,'P&L Forecast'!$B30) -> 10.19584 | S30: =SUMIFS('Combined P&L'!Q:Q,'Combined P&L'!$C:$C,'P&L Forecast'!$B30) -> 15.04429 | T30: =SUMIFS('Combined P&L'!R:R,'Combined P&L'!$C:$C,'P&L Forecast'!$B30) -> 16.63744 | U30: =SUMIFS('Combined P&L'!S:S,'Combined P&L'!$C:$C,'P&L Forecast'!$B30) -> 7.49499 | V30: =SUMIFS('Combined P&L'!T:T,'Combined P&L'!$C:$C,'P&L Forecast'!$B30) -> 7.98202 | W30: =SUMIFS('Combined P&L'!U:U,'Combined P&L'!$C:$C,'P&L Forecast'!$B30) -> 5.90274 | X30: =SUMIFS('Combined P&L'!V:V,'Combined P&L'!$C:$C,'P&L Forecast'!$B30) -> 7.76763 | Y30: =SUMIFS('Combined P&L'!W:W,'Combined P&L'!$C:$C,'P&L Forecast'!$B30) -> 8.21417 | Z30: =SUMIFS('Combined P&L'!X:X,'Combined P&L'!$C:$C,'P&L Forecast'!$B30) -> 12.62272 | AA30: =SUMIFS('Combined P&L'!Y:Y,'Combined P&L'!$C:$C,'P&L Forecast'!$B30) -> 12.85047 | AB30: =SUMIFS('Combined P&L'!Z:Z,'Combined P&L'!$C:$C,'P&L Forecast'!$B30) -> 10.34556 | AC30: =SUMIFS('Combined P&L'!AA:AA,'Combined P&L'!$C:$C,'P&L Forecast'!$B30) -> 8.08798 | AD30: =SUMIFS('Combined P&L'!AB:AB,'Combined P&L'!$C:$C,'P&L Forecast'!$B30) -> 9.75287 | AE30: =SUMIFS('Combined P&L'!AC:AC,'Combined P&L'!$C:$C,'P&L Forecast'!$B30) -> 10.28 | AF30: =SUMIFS('Combined P&L'!AD:AD,'Combined P&L'!$C:$C,'P&L Forecast'!$B30) -> 11.13632 | AG30: =SUMIFS('Combined P&L'!AE:AE,'Combined P&L'!$C:$C,'P&L Forecast'!$B30) -> 10.87432 | AH30: =SUMIFS('Combined P&L'!AF:AF,'Combined P&L'!$C:$C,'P&L Forecast'!$B30) -> 13.47257 | AI30: =SUMIFS('Combined P&L'!AG:AG,'Combined P&L'!$C:$C,'P&L Forecast'!$B30) -> 12.70407 | AJ30: =SUMIFS('Combined P&L'!AH:AH,'Combined P&L'!$C:$C,'P&L Forecast'!$B30) -> 14.69884 | AK30: =SUMIFS('Combined P&L'!AI:AI,'Combined P&L'!$C:$C,'P&L Forecast'!$B30) -> 15.54306 | AL30: =SUMIFS('Combined P&L'!AJ:AJ,'Combined P&L'!$C:$C,'P&L Forecast'!$B30) -> 14.34361 | AM30: =SUMIFS('Combined P&L'!AK:AK,'Combined P&L'!$C:$C,'P&L Forecast'!$B30) -> 20.93052 | AN30: =SUMIFS('Combined P&L'!AL:AL,'Combined P&L'!$C:$C,'P&L Forecast'!$B30) -> 16.55394 | AO30: =SUMIFS('Combined P&L'!AM:AM,'Combined P&L'!$C:$C,'P&L Forecast'!$B30) -> 11.52661 | AP30: =SUMIFS('Combined P&L'!AN:AN,'Combined P&L'!$C:$C,'P&L Forecast'!$B30) -> 14.93883 | AQ30: =SUMIFS('Combined P&L'!AO:AO,'Combined P&L'!$C:$C,'P&L Forecast'!$B30) -> 15.58352 | AR30: =SUMIFS('Combined P&L'!AP:AP,'Combined P&L'!$C:$C,'P&L Forecast'!$B30) -> 19.6034 | AS30: =SUMIFS('Combined P&L'!AQ:AQ,'Combined P&L'!$C:$C,'P&L Forecast'!$B30) -> 16.64457 | AT30: =SUMIFS('Combined P&L'!AR:AR,'Combined P&L'!$C:$C,'P&L Forecast'!$B30) -> 16.42912
B31: Owner Wages | C31: =SUMIFS($P31:$AT31,$P$5:$AT$5,">"&C$172,$P$5:$AT$5,"<"&C$173) -> 0 | D31: =SUMIFS($P31:$AT31,$P$5:$AT$5,">"&D$172,$P$5:$AT$5,"<"&D$173) -> 90.66704 | F31: =SUMIFS($P31:$AT31,$P$5:$AT$5,">"&F$172,$P$5:$AT$5,"<"&F$173) -> 45.46612 | G31: =SUMIFS($P31:$AT31,$P$5:$AT$5,">"&G$172,$P$5:$AT$5,"<"&G$173) -> 63.14302 | I31: =SUMIFS($P31:$AT31,$P$5:$AT$5,">"&I$172,$P$5:$AT$5,"<"&I$173) -> 35.94325 | J31: =SUMIFS($P31:$AT31,$P$5:$AT$5,">"&J$172,$P$5:$AT$5,"<"&J$173) -> 108.34394 | K31: =+C128 -> 108.34394 | M31: =+J31-K31 -> 0 | N31: =IFERROR(K31/J31-1,0) -> 0 | P31: =SUMIFS('Combined P&L'!N:N,'Combined P&L'!$C:$C,'P&L Forecast'!$B31) -> 0 | Q31: =SUMIFS('Combined P&L'!O:O,'Combined P&L'!$C:$C,'P&L Forecast'!$B31) -> 0 | R31: =SUMIFS('Combined P&L'!P:P,'Combined P&L'!$C:$C,'P&L Forecast'!$B31) -> 0 | S31: =SUMIFS('Combined P&L'!Q:Q,'Combined P&L'!$C:$C,'P&L Forecast'!$B31) -> 0 | T31: =SUMIFS('Combined P&L'!R:R,'Combined P&L'!$C:$C,'P&L Forecast'!$B31) -> 0 | U31: =SUMIFS('Combined P&L'!S:S,'Combined P&L'!$C:$C,'P&L Forecast'!$B31) -> 0 | V31: =SUMIFS('Combined P&L'!T:T,'Combined P&L'!$C:$C,'P&L Forecast'!$B31) -> 0 | W31: =SUMIFS('Combined P&L'!U:U,'Combined P&L'!$C:$C,'P&L Forecast'!$B31) -> 0 | X31: =SUMIFS('Combined P&L'!V:V,'Combined P&L'!$C:$C,'P&L Forecast'!$B31) -> 0 | Y31: =SUMIFS('Combined P&L'!W:W,'Combined P&L'!$C:$C,'P&L Forecast'!$B31) -> 0 | Z31: =SUMIFS('Combined P&L'!X:X,'Combined P&L'!$C:$C,'P&L Forecast'!$B31) -> 0 | AA31: =SUMIFS('Combined P&L'!Y:Y,'Combined P&L'!$C:$C,'P&L Forecast'!$B31) -> 0 | AB31: =SUMIFS('Combined P&L'!Z:Z,'Combined P&L'!$C:$C,'P&L Forecast'!$B31) -> 0 | AC31: =SUMIFS('Combined P&L'!AA:AA,'Combined P&L'!$C:$C,'P&L Forecast'!$B31) -> 0 | AD31: =SUMIFS('Combined P&L'!AB:AB,'Combined P&L'!$C:$C,'P&L Forecast'!$B31) -> 8.90639 | AE31: =SUMIFS('Combined P&L'!AC:AC,'Combined P&L'!$C:$C,'P&L Forecast'!$B31) -> 9.23323 | AF31: =SUMIFS('Combined P&L'!AD:AD,'Combined P&L'!$C:$C,'P&L Forecast'!$B31) -> 9.10884 | AG31: =SUMIFS('Combined P&L'!AE:AE,'Combined P&L'!$C:$C,'P&L Forecast'!$B31) -> 8.69479 | AH31: =SUMIFS('Combined P&L'!AF:AF,'Combined P&L'!$C:$C,'P&L Forecast'!$B31) -> 9.52287 | AI31: =SUMIFS('Combined P&L'!AG:AG,'Combined P&L'!$C:$C,'P&L Forecast'!$B31) -> 8.69481 | AJ31: =SUMIFS('Combined P&L'!AH:AH,'Combined P&L'!$C:$C,'P&L Forecast'!$B31) -> 9.10884 | AK31: =SUMIFS('Combined P&L'!AI:AI,'Combined P&L'!$C:$C,'P&L Forecast'!$B31) -> 9.52287 | AL31: =SUMIFS('Combined P&L'!AJ:AJ,'Combined P&L'!$C:$C,'P&L Forecast'!$B31) -> 8.28076 | AM31: =SUMIFS('Combined P&L'!AK:AK,'Combined P&L'!$C:$C,'P&L Forecast'!$B31) -> 9.59364 | AN31: =SUMIFS('Combined P&L'!AL:AL,'Combined P&L'!$C:$C,'P&L Forecast'!$B31) -> 9.27621 | AO31: =SUMIFS('Combined P&L'!AM:AM,'Combined P&L'!$C:$C,'P&L Forecast'!$B31) -> 8.32263 | AP31: =SUMIFS('Combined P&L'!AN:AN,'Combined P&L'!$C:$C,'P&L Forecast'!$B31) -> 9.10883 | AQ31: =SUMIFS('Combined P&L'!AO:AO,'Combined P&L'!$C:$C,'P&L Forecast'!$B31) -> 9.10883 | AR31: =SUMIFS('Combined P&L'!AP:AP,'Combined P&L'!$C:$C,'P&L Forecast'!$B31) -> 8.69481 | AS31: =SUMIFS('Combined P&L'!AQ:AQ,'Combined P&L'!$C:$C,'P&L Forecast'!$B31) -> 9.10884 | AT31: =SUMIFS('Combined P&L'!AR:AR,'Combined P&L'!$C:$C,'P&L Forecast'!$B31) -> 9.52287
B32: S&M Wages | C32: =SUMIFS($P32:$AT32,$P$5:$AT$5,">"&C$172,$P$5:$AT$5,"<"&C$173) -> 0 | D32: =SUMIFS($P32:$AT32,$P$5:$AT$5,">"&D$172,$P$5:$AT$5,"<"&D$173) -> 19.14963 | F32: =SUMIFS($P32:$AT32,$P$5:$AT$5,">"&F$172,$P$5:$AT$5,"<"&F$173) -> 3.09945 | G32: =SUMIFS($P32:$AT32,$P$5:$AT$5,">"&G$172,$P$5:$AT$5,"<"&G$173) -> 51.94131 | I32: =SUMIFS($P32:$AT32,$P$5:$AT$5,">"&I$172,$P$5:$AT$5,"<"&I$173) -> 1.4668 | J32: =SUMIFS($P32:$AT32,$P$5:$AT$5,">"&J$172,$P$5:$AT$5,"<"&J$173) -> 61.42838 | K32: =+C130 -> 98.34912 | M32: =+J32-K32 -> -36.92074 | N32: =IFERROR(K32/J32-1,0) -> 0.60103718 | P32: =SUMIFS('Combined P&L'!N:N,'Combined P&L'!$C:$C,'P&L Forecast'!$B32) -> 0 | Q32: =SUMIFS('Combined P&L'!O:O,'Combined P&L'!$C:$C,'P&L Forecast'!$B32) -> 0 | R32: =SUMIFS('Combined P&L'!P:P,'Combined P&L'!$C:$C,'P&L Forecast'!$B32) -> 0 | S32: =SUMIFS('Combined P&L'!Q:Q,'Combined P&L'!$C:$C,'P&L Forecast'!$B32) -> 0 | T32: =SUMIFS('Combined P&L'!R:R,'Combined P&L'!$C:$C,'P&L Forecast'!$B32) -> 0 | U32: =SUMIFS('Combined P&L'!S:S,'Combined P&L'!$C:$C,'P&L Forecast'!$B32) -> 0 | V32: =SUMIFS('Combined P&L'!T:T,'Combined P&L'!$C:$C,'P&L Forecast'!$B32) -> 0 | W32: =SUMIFS('Combined P&L'!U:U,'Combined P&L'!$C:$C,'P&L Forecast'!$B32) -> 0 | X32: =SUMIFS('Combined P&L'!V:V,'Combined P&L'!$C:$C,'P&L Forecast'!$B32) -> 0 | Y32: =SUMIFS('Combined P&L'!W:W,'Combined P&L'!$C:$C,'P&L Forecast'!$B32) -> 0 | Z32: =SUMIFS('Combined P&L'!X:X,'Combined P&L'!$C:$C,'P&L Forecast'!$B32) -> 0 | AA32: =SUMIFS('Combined P&L'!Y:Y,'Combined P&L'!$C:$C,'P&L Forecast'!$B32) -> 0 | AB32: =SUMIFS('Combined P&L'!Z:Z,'Combined P&L'!$C:$C,'P&L Forecast'!$B32) -> 0 | AC32: =SUMIFS('Combined P&L'!AA:AA,'Combined P&L'!$C:$C,'P&L Forecast'!$B32) -> 0 | AD32: =SUMIFS('Combined P&L'!AB:AB,'Combined P&L'!$C:$C,'P&L Forecast'!$B32) -> 0 | AE32: =SUMIFS('Combined P&L'!AC:AC,'Combined P&L'!$C:$C,'P&L Forecast'!$B32) -> 0 | AF32: =SUMIFS('Combined P&L'!AD:AD,'Combined P&L'!$C:$C,'P&L Forecast'!$B32) -> 0 | AG32: =SUMIFS('Combined P&L'!AE:AE,'Combined P&L'!$C:$C,'P&L Forecast'!$B32) -> 1.4668 | AH32: =SUMIFS('Combined P&L'!AF:AF,'Combined P&L'!$C:$C,'P&L Forecast'!$B32) -> 1.63265 | AI32: =SUMIFS('Combined P&L'!AG:AG,'Combined P&L'!$C:$C,'P&L Forecast'!$B32) -> 1.71805 | AJ32: =SUMIFS('Combined P&L'!AH:AH,'Combined P&L'!$C:$C,'P&L Forecast'!$B32) -> 1.9146 | AK32: =SUMIFS('Combined P&L'!AI:AI,'Combined P&L'!$C:$C,'P&L Forecast'!$B32) -> 2.3529 | AL32: =SUMIFS('Combined P&L'!AJ:AJ,'Combined P&L'!$C:$C,'P&L Forecast'!$B32) -> 2.24524 | AM32: =SUMIFS('Combined P&L'!AK:AK,'Combined P&L'!$C:$C,'P&L Forecast'!$B32) -> 7.81939 | AN32: =SUMIFS('Combined P&L'!AL:AL,'Combined P&L'!$C:$C,'P&L Forecast'!$B32) -> 5.6534 | AO32: =SUMIFS('Combined P&L'!AM:AM,'Combined P&L'!$C:$C,'P&L Forecast'!$B32) -> 5.95689 | AP32: =SUMIFS('Combined P&L'!AN:AN,'Combined P&L'!$C:$C,'P&L Forecast'!$B32) -> 7.7828 | AQ32: =SUMIFS('Combined P&L'!AO:AO,'Combined P&L'!$C:$C,'P&L Forecast'!$B32) -> 8.13701 | AR32: =SUMIFS('Combined P&L'!AP:AP,'Combined P&L'!$C:$C,'P&L Forecast'!$B32) -> 7.80825 | AS32: =SUMIFS('Combined P&L'!AQ:AQ,'Combined P&L'!$C:$C,'P&L Forecast'!$B32) -> 8.4072 | AT32: =SUMIFS('Combined P&L'!AR:AR,'Combined P&L'!$C:$C,'P&L Forecast'!$B32) -> 8.19576
B33: Occupancy Tax Specialist | C33: =SUMIFS($P33:$AT33,$P$5:$AT$5,">"&C$172,$P$5:$AT$5,"<"&C$173) -> 1.11335 | D33: =SUMIFS($P33:$AT33,$P$5:$AT$5,">"&D$172,$P$5:$AT$5,"<"&D$173) -> 29.56415 | F33: =SUMIFS($P33:$AT33,$P$5:$AT$5,">"&F$172,$P$5:$AT$5,"<"&F$173) -> 14.27585 | G33: =SUMIFS($P33:$AT33,$P$5:$AT$5,">"&G$172,$P$5:$AT$5,"<"&G$173) -> 42.08505 | I33: =SUMIFS($P33:$AT33,$P$5:$AT$5,">"&I$172,$P$5:$AT$5,"<"&I$173) -> 13.21003 | J33: =SUMIFS($P33:$AT33,$P$5:$AT$5,">"&J$172,$P$5:$AT$5,"<"&J$173) -> 53.87642 | K33: =+C131 -> 68.1132 | M33: =+J33-K33 -> -14.23678 | N33: =IFERROR(K33/J33-1,0) -> 0.26424881 | P33: =SUMIFS('Combined P&L'!N:N,'Combined P&L'!$C:$C,'P&L Forecast'!$B33) -> 0 | Q33: =SUMIFS('Combined P&L'!O:O,'Combined P&L'!$C:$C,'P&L Forecast'!$B33) -> 0 | R33: =SUMIFS('Combined P&L'!P:P,'Combined P&L'!$C:$C,'P&L Forecast'!$B33) -> 0 | S33: =SUMIFS('Combined P&L'!Q:Q,'Combined P&L'!$C:$C,'P&L Forecast'!$B33) -> 0 | T33: =SUMIFS('Combined P&L'!R:R,'Combined P&L'!$C:$C,'P&L Forecast'!$B33) -> 0 | U33: =SUMIFS('Combined P&L'!S:S,'Combined P&L'!$C:$C,'P&L Forecast'!$B33) -> 0 | V33: =SUMIFS('Combined P&L'!T:T,'Combined P&L'!$C:$C,'P&L Forecast'!$B33) -> 0 | W33: =SUMIFS('Combined P&L'!U:U,'Combined P&L'!$C:$C,'P&L Forecast'!$B33) -> 0 | X33: =SUMIFS('Combined P&L'!V:V,'Combined P&L'!$C:$C,'P&L Forecast'!$B33) -> 0 | Y33: =SUMIFS('Combined P&L'!W:W,'Combined P&L'!$C:$C,'P&L Forecast'!$B33) -> 0 | Z33: =SUMIFS('Combined P&L'!X:X,'Combined P&L'!$C:$C,'P&L Forecast'!$B33) -> 0 | AA33: =SUMIFS('Combined P&L'!Y:Y,'Combined P&L'!$C:$C,'P&L Forecast'!$B33) -> 1.11335 | AB33: =SUMIFS('Combined P&L'!Z:Z,'Combined P&L'!$C:$C,'P&L Forecast'!$B33) -> 2.17917 | AC33: =SUMIFS('Combined P&L'!AA:AA,'Combined P&L'!$C:$C,'P&L Forecast'!$B33) -> 1.82504 | AD33: =SUMIFS('Combined P&L'!AB:AB,'Combined P&L'!$C:$C,'P&L Forecast'!$B33) -> 1.97853 | AE33: =SUMIFS('Combined P&L'!AC:AC,'Combined P&L'!$C:$C,'P&L Forecast'!$B33) -> 2.06213 | AF33: =SUMIFS('Combined P&L'!AD:AD,'Combined P&L'!$C:$C,'P&L Forecast'!$B33) -> 2.06213 | AG33: =SUMIFS('Combined P&L'!AE:AE,'Combined P&L'!$C:$C,'P&L Forecast'!$B33) -> 1.98968 | AH33: =SUMIFS('Combined P&L'!AF:AF,'Combined P&L'!$C:$C,'P&L Forecast'!$B33) -> 2.17917 | AI33: =SUMIFS('Combined P&L'!AG:AG,'Combined P&L'!$C:$C,'P&L Forecast'!$B33) -> 2.12293 | AJ33: =SUMIFS('Combined P&L'!AH:AH,'Combined P&L'!$C:$C,'P&L Forecast'!$B33) -> 3.1042 | AK33: =SUMIFS('Combined P&L'!AI:AI,'Combined P&L'!$C:$C,'P&L Forecast'!$B33) -> 3.27137 | AL33: =SUMIFS('Combined P&L'!AJ:AJ,'Combined P&L'!$C:$C,'P&L Forecast'!$B33) -> 3.63947 | AM33: =SUMIFS('Combined P&L'!AK:AK,'Combined P&L'!$C:$C,'P&L Forecast'!$B33) -> 3.15033 | AN33: =SUMIFS('Combined P&L'!AL:AL,'Combined P&L'!$C:$C,'P&L Forecast'!$B33) -> 1.69116 | AO33: =SUMIFS('Combined P&L'!AM:AM,'Combined P&L'!$C:$C,'P&L Forecast'!$B33) -> 5.54919 | AP33: =SUMIFS('Combined P&L'!AN:AN,'Combined P&L'!$C:$C,'P&L Forecast'!$B33) -> 7.1999 | AQ33: =SUMIFS('Combined P&L'!AO:AO,'Combined P&L'!$C:$C,'P&L Forecast'!$B33) -> 8.1927 | AR33: =SUMIFS('Combined P&L'!AP:AP,'Combined P&L'!$C:$C,'P&L Forecast'!$B33) -> 8.28335 | AS33: =SUMIFS('Combined P&L'!AQ:AQ,'Combined P&L'!$C:$C,'P&L Forecast'!$B33) -> 5.49265 | AT33: =SUMIFS('Combined P&L'!AR:AR,'Combined P&L'!$C:$C,'P&L Forecast'!$B33) -> 5.6761
B34: Sr. Client Lead Wages | C34: =SUMIFS($P34:$AT34,$P$5:$AT$5,">"&C$172,$P$5:$AT$5,"<"&C$173) -> 0 | D34: =SUMIFS($P34:$AT34,$P$5:$AT$5,">"&D$172,$P$5:$AT$5,"<"&D$173) -> 0 | F34: =SUMIFS($P34:$AT34,$P$5:$AT$5,">"&F$172,$P$5:$AT$5,"<"&F$173) -> 0 | G34: =SUMIFS($P34:$AT34,$P$5:$AT$5,">"&G$172,$P$5:$AT$5,"<"&G$173) -> 7.995 | I34: =SUMIFS($P34:$AT34,$P$5:$AT$5,">"&I$172,$P$5:$AT$5,"<"&I$173) -> 0 | J34: =SUMIFS($P34:$AT34,$P$5:$AT$5,">"&J$172,$P$5:$AT$5,"<"&J$173) -> 5.23823 | K34: =+C132 -> 33.08124 | M34: =+J34-K34 -> -27.84301 | N34: =IFERROR(K34/J34-1,0) -> 5.315347 | P34: =SUMIFS('Combined P&L'!N:N,'Combined P&L'!$C:$C,'P&L Forecast'!$B34) -> 0 | Q34: =SUMIFS('Combined P&L'!O:O,'Combined P&L'!$C:$C,'P&L Forecast'!$B34) -> 0 | R34: =SUMIFS('Combined P&L'!P:P,'Combined P&L'!$C:$C,'P&L Forecast'!$B34) -> 0 | S34: =SUMIFS('Combined P&L'!Q:Q,'Combined P&L'!$C:$C,'P&L Forecast'!$B34) -> 0 | T34: =SUMIFS('Combined P&L'!R:R,'Combined P&L'!$C:$C,'P&L Forecast'!$B34) -> 0 | U34: =SUMIFS('Combined P&L'!S:S,'Combined P&L'!$C:$C,'P&L Forecast'!$B34) -> 0 | V34: =SUMIFS('Combined P&L'!T:T,'Combined P&L'!$C:$C,'P&L Forecast'!$B34) -> 0 | W34: =SUMIFS('Combined P&L'!U:U,'Combined P&L'!$C:$C,'P&L Forecast'!$B34) -> 0 | X34: =SUMIFS('Combined P&L'!V:V,'Combined P&L'!$C:$C,'P&L Forecast'!$B34) -> 0 | Y34: =SUMIFS('Combined P&L'!W:W,'Combined P&L'!$C:$C,'P&L Forecast'!$B34) -> 0 | Z34: =SUMIFS('Combined P&L'!X:X,'Combined P&L'!$C:$C,'P&L Forecast'!$B34) -> 0 | AA34: =SUMIFS('Combined P&L'!Y:Y,'Combined P&L'!$C:$C,'P&L Forecast'!$B34) -> 0 | AB34: =SUMIFS('Combined P&L'!Z:Z,'Combined P&L'!$C:$C,'P&L Forecast'!$B34) -> 0 | AC34: =SUMIFS('Combined P&L'!AA:AA,'Combined P&L'!$C:$C,'P&L Forecast'!$B34) -> 0 | AD34: =SUMIFS('Combined P&L'!AB:AB,'Combined P&L'!$C:$C,'P&L Forecast'!$B34) -> 0 | AE34: =SUMIFS('Combined P&L'!AC:AC,'Combined P&L'!$C:$C,'P&L Forecast'!$B34) -> 0 | AF34: =SUMIFS('Combined P&L'!AD:AD,'Combined P&L'!$C:$C,'P&L Forecast'!$B34) -> 0 | AG34: =SUMIFS('Combined P&L'!AE:AE,'Combined P&L'!$C:$C,'P&L Forecast'!$B34) -> 0 | AH34: =SUMIFS('Combined P&L'!AF:AF,'Combined P&L'!$C:$C,'P&L Forecast'!$B34) -> 0 | AI34: =SUMIFS('Combined P&L'!AG:AG,'Combined P&L'!$C:$C,'P&L Forecast'!$B34) -> 0 | AJ34: =SUMIFS('Combined P&L'!AH:AH,'Combined P&L'!$C:$C,'P&L Forecast'!$B34) -> 0 | AK34: =SUMIFS('Combined P&L'!AI:AI,'Combined P&L'!$C:$C,'P&L Forecast'!$B34) -> 0 | AL34: =SUMIFS('Combined P&L'!AJ:AJ,'Combined P&L'!$C:$C,'P&L Forecast'!$B34) -> 0 | AM34: =SUMIFS('Combined P&L'!AK:AK,'Combined P&L'!$C:$C,'P&L Forecast'!$B34) -> 0 | AN34: =SUMIFS('Combined P&L'!AL:AL,'Combined P&L'!$C:$C,'P&L Forecast'!$B34) -> 0 | AO34: =SUMIFS('Combined P&L'!AM:AM,'Combined P&L'!$C:$C,'P&L Forecast'!$B34) -> 0 | AP34: =SUMIFS('Combined P&L'!AN:AN,'Combined P&L'!$C:$C,'P&L Forecast'!$B34) -> 0 | AQ34: =SUMIFS('Combined P&L'!AO:AO,'Combined P&L'!$C:$C,'P&L Forecast'!$B34) -> 0 | AR34: =SUMIFS('Combined P&L'!AP:AP,'Combined P&L'!$C:$C,'P&L Forecast'!$B34) -> 2.51706 | AS34: =SUMIFS('Combined P&L'!AQ:AQ,'Combined P&L'!$C:$C,'P&L Forecast'!$B34) -> 2.72117 | AT34: =SUMIFS('Combined P&L'!AR:AR,'Combined P&L'!$C:$C,'P&L Forecast'!$B34) -> 2.75677
B35: Employee Benefits | C35: =SUMIFS($P35:$AT35,$P$5:$AT$5,">"&C$172,$P$5:$AT$5,"<"&C$173) -> 5.37405 | D35: =SUMIFS($P35:$AT35,$P$5:$AT$5,">"&D$172,$P$5:$AT$5,"<"&D$173) -> 19.23245 | F35: =SUMIFS($P35:$AT35,$P$5:$AT$5,">"&F$172,$P$5:$AT$5,"<"&F$173) -> 9.02166 | G35: =SUMIFS($P35:$AT35,$P$5:$AT$5,">"&G$172,$P$5:$AT$5,"<"&G$173) -> 17.36251 | I35: =SUMIFS($P35:$AT35,$P$5:$AT$5,">"&I$172,$P$5:$AT$5,"<"&I$173) -> 11.46793 | J35: =SUMIFS($P35:$AT35,$P$5:$AT$5,">"&J$172,$P$5:$AT$5,"<"&J$173) -> 26.4526 | K35: =+C134 -> 32.17836 | M35: =+J35-K35 -> -5.72576 | N35: =IFERROR(K35/J35-1,0) -> 0.21645358 | P35: =SUMIFS('Combined P&L'!N:N,'Combined P&L'!$C:$C,'P&L Forecast'!$B35) -> 0 | Q35: =SUMIFS('Combined P&L'!O:O,'Combined P&L'!$C:$C,'P&L Forecast'!$B35) -> 0.6277 | R35: =SUMIFS('Combined P&L'!P:P,'Combined P&L'!$C:$C,'P&L Forecast'!$B35) -> 0 | S35: =SUMIFS('Combined P&L'!Q:Q,'Combined P&L'!$C:$C,'P&L Forecast'!$B35) -> 0.3389 | T35: =SUMIFS('Combined P&L'!R:R,'Combined P&L'!$C:$C,'P&L Forecast'!$B35) -> 0.3389 | U35: =SUMIFS('Combined P&L'!S:S,'Combined P&L'!$C:$C,'P&L Forecast'!$B35) -> 0.06145 | V35: =SUMIFS('Combined P&L'!T:T,'Combined P&L'!$C:$C,'P&L Forecast'!$B35) -> 0.8619 | W35: =SUMIFS('Combined P&L'!U:U,'Combined P&L'!$C:$C,'P&L Forecast'!$B35) -> 0.35956 | X35: =SUMIFS('Combined P&L'!V:V,'Combined P&L'!$C:$C,'P&L Forecast'!$B35) -> 0.38745 | Y35: =SUMIFS('Combined P&L'!W:W,'Combined P&L'!$C:$C,'P&L Forecast'!$B35) -> 0.6989 | Z35: =SUMIFS('Combined P&L'!X:X,'Combined P&L'!$C:$C,'P&L Forecast'!$B35) -> 0.917 | AA35: =SUMIFS('Combined P&L'!Y:Y,'Combined P&L'!$C:$C,'P&L Forecast'!$B35) -> 0.78229 | AB35: =SUMIFS('Combined P&L'!Z:Z,'Combined P&L'!$C:$C,'P&L Forecast'!$B35) -> 0.93724 | AC35: =SUMIFS('Combined P&L'!AA:AA,'Combined P&L'!$C:$C,'P&L Forecast'!$B35) -> 1.03107 | AD35: =SUMIFS('Combined P&L'!AB:AB,'Combined P&L'!$C:$C,'P&L Forecast'!$B35) -> 0.66153 | AE35: =SUMIFS('Combined P&L'!AC:AC,'Combined P&L'!$C:$C,'P&L Forecast'!$B35) -> 0.71453 | AF35: =SUMIFS('Combined P&L'!AD:AD,'Combined P&L'!$C:$C,'P&L Forecast'!$B35) -> 2.25493 | AG35: =SUMIFS('Combined P&L'!AE:AE,'Combined P&L'!$C:$C,'P&L Forecast'!$B35) -> 1.86153 | AH35: =SUMIFS('Combined P&L'!AF:AF,'Combined P&L'!$C:$C,'P&L Forecast'!$B35) -> 1.56083 | AI35: =SUMIFS('Combined P&L'!AG:AG,'Combined P&L'!$C:$C,'P&L Forecast'!$B35) -> 1.74767 | AJ35: =SUMIFS('Combined P&L'!AH:AH,'Combined P&L'!$C:$C,'P&L Forecast'!$B35) -> 0.90753 | AK35: =SUMIFS('Combined P&L'!AI:AI,'Combined P&L'!$C:$C,'P&L Forecast'!$B35) -> 2.51353 | AL35: =SUMIFS('Combined P&L'!AJ:AJ,'Combined P&L'!$C:$C,'P&L Forecast'!$B35) -> 1.03753 | AM35: =SUMIFS('Combined P&L'!AK:AK,'Combined P&L'!$C:$C,'P&L Forecast'!$B35) -> 4.00453 | AN35: =SUMIFS('Combined P&L'!AL:AL,'Combined P&L'!$C:$C,'P&L Forecast'!$B35) -> 1.57873 | AO35: =SUMIFS('Combined P&L'!AM:AM,'Combined P&L'!$C:$C,'P&L Forecast'!$B35) -> 1.14553 | AP35: =SUMIFS('Combined P&L'!AN:AN,'Combined P&L'!$C:$C,'P&L Forecast'!$B35) -> 5.13853 | AQ35: =SUMIFS('Combined P&L'!AO:AO,'Combined P&L'!$C:$C,'P&L Forecast'!$B35) -> 1.92353 | AR35: =SUMIFS('Combined P&L'!AP:AP,'Combined P&L'!$C:$C,'P&L Forecast'!$B35) -> 1.46353 | AS35: =SUMIFS('Combined P&L'!AQ:AQ,'Combined P&L'!$C:$C,'P&L Forecast'!$B35) -> 3.43113 | AT35: =SUMIFS('Combined P&L'!AR:AR,'Combined P&L'!$C:$C,'P&L Forecast'!$B35) -> 2.68153
B36: Total Payroll Expenses | C36: =SUM(C27:C35) -> 700.20547 | D36: =SUM(D27:D35) -> 1261.1666 | F36: =SUM(F27:F35) -> 630.65714 | G36: =SUM(G27:G35) -> 1120.8921 | I36: =SUM(I27:I35) -> 940.94885 | J36: =SUM(J27:J35) -> 1679.372 | K36: =SUM(K27:K35) -> 2158.7356 | M36: =SUM(M27:M35) -> -479.36361 | N36: =IFERROR(K36/J36-1,0) -> 0.28544219 | P36: =SUM(P27:P35) -> 31.74682 | Q36: =SUM(Q27:Q35) -> 37.62609 | R36: =SUM(R27:R35) -> 37.77865 | S36: =SUM(S27:S35) -> 50.81818 | T36: =SUM(T27:T35) -> 70.6441 | U36: =SUM(U27:U35) -> 52.94065 | V36: =SUM(V27:V35) -> 56.15375 | W36: =SUM(W27:W35) -> 52.54102 | ... AT36: =SUM(AT27:AT35) -> 180.38884
B38: Software & Apps - COGS | C38: =SUMIFS($P38:$AT38,$P$5:$AT$5,">"&C$172,$P$5:$AT$5,"<"&C$173) -> 114.42269 | D38: =SUMIFS($P38:$AT38,$P$5:$AT$5,">"&D$172,$P$5:$AT$5,"<"&D$173) -> 157.49471 | F38: =SUMIFS($P38:$AT38,$P$5:$AT$5,">"&F$172,$P$5:$AT$5,"<"&F$173) -> 84.96859 | G38: =SUMIFS($P38:$AT38,$P$5:$AT$5,">"&G$172,$P$5:$AT$5,"<"&G$173) -> 152.28157 | I38: =SUMIFS($P38:$AT38,$P$5:$AT$5,">"&I$172,$P$5:$AT$5,"<"&I$173) -> 139.99468 | J38: =SUMIFS($P38:$AT38,$P$5:$AT$5,">"&J$172,$P$5:$AT$5,"<"&J$173) -> 209.96746 | K38: =+C138 -> 335.70816 | M38: =+J38-K38 -> -125.7407 | N38: =IFERROR(K38/J38-1,0) -> 0.59885803 | P38: =SUMIFS('Combined P&L'!N:N,'Combined P&L'!$C:$C,'P&L Forecast'!$B38) -> 7.073 | Q38: =SUMIFS('Combined P&L'!O:O,'Combined P&L'!$C:$C,'P&L Forecast'!$B38) -> 7.01818 | R38: =SUMIFS('Combined P&L'!P:P,'Combined P&L'!$C:$C,'P&L Forecast'!$B38) -> 7.77788 | S38: =SUMIFS('Combined P&L'!Q:Q,'Combined P&L'!$C:$C,'P&L Forecast'!$B38) -> 7.76124 | T38: =SUMIFS('Combined P&L'!R:R,'Combined P&L'!$C:$C,'P&L Forecast'!$B38) -> 7.71821 | U38: =SUMIFS('Combined P&L'!S:S,'Combined P&L'!$C:$C,'P&L Forecast'!$B38) -> 8.91264 | V38: =SUMIFS('Combined P&L'!T:T,'Combined P&L'!$C:$C,'P&L Forecast'!$B38) -> 10.84668 | W38: =SUMIFS('Combined P&L'!U:U,'Combined P&L'!$C:$C,'P&L Forecast'!$B38) -> 11.13514 | X38: =SUMIFS('Combined P&L'!V:V,'Combined P&L'!$C:$C,'P&L Forecast'!$B38) -> 11.0345 | Y38: =SUMIFS('Combined P&L'!W:W,'Combined P&L'!$C:$C,'P&L Forecast'!$B38) -> 11.72873 | Z38: =SUMIFS('Combined P&L'!X:X,'Combined P&L'!$C:$C,'P&L Forecast'!$B38) -> 11.44691 | AA38: =SUMIFS('Combined P&L'!Y:Y,'Combined P&L'!$C:$C,'P&L Forecast'!$B38) -> 11.96958 | AB38: =SUMIFS('Combined P&L'!Z:Z,'Combined P&L'!$C:$C,'P&L Forecast'!$B38) -> 10.84853 | AC38: =SUMIFS('Combined P&L'!AA:AA,'Combined P&L'!$C:$C,'P&L Forecast'!$B38) -> 12.21311 | AD38: =SUMIFS('Combined P&L'!AB:AB,'Combined P&L'!$C:$C,'P&L Forecast'!$B38) -> 11.57167 | AE38: =SUMIFS('Combined P&L'!AC:AC,'Combined P&L'!$C:$C,'P&L Forecast'!$B38) -> 11.81087 | AF38: =SUMIFS('Combined P&L'!AD:AD,'Combined P&L'!$C:$C,'P&L Forecast'!$B38) -> 12.52563 | AG38: =SUMIFS('Combined P&L'!AE:AE,'Combined P&L'!$C:$C,'P&L Forecast'!$B38) -> 12.86333 | AH38: =SUMIFS('Combined P&L'!AF:AF,'Combined P&L'!$C:$C,'P&L Forecast'!$B38) -> 13.13545 | AI38: =SUMIFS('Combined P&L'!AG:AG,'Combined P&L'!$C:$C,'P&L Forecast'!$B38) -> 14.25715 | AJ38: =SUMIFS('Combined P&L'!AH:AH,'Combined P&L'!$C:$C,'P&L Forecast'!$B38) -> 13.59512 | AK38: =SUMIFS('Combined P&L'!AI:AI,'Combined P&L'!$C:$C,'P&L Forecast'!$B38) -> 12.34762 | AL38: =SUMIFS('Combined P&L'!AJ:AJ,'Combined P&L'!$C:$C,'P&L Forecast'!$B38) -> 15.21781 | AM38: =SUMIFS('Combined P&L'!AK:AK,'Combined P&L'!$C:$C,'P&L Forecast'!$B38) -> 17.10842 | AN38: =SUMIFS('Combined P&L'!AL:AL,'Combined P&L'!$C:$C,'P&L Forecast'!$B38) -> 18.4683 | AO38: =SUMIFS('Combined P&L'!AM:AM,'Combined P&L'!$C:$C,'P&L Forecast'!$B38) -> 17.92027 | AP38: =SUMIFS('Combined P&L'!AN:AN,'Combined P&L'!$C:$C,'P&L Forecast'!$B38) -> 18.40906 | AQ38: =SUMIFS('Combined P&L'!AO:AO,'Combined P&L'!$C:$C,'P&L Forecast'!$B38) -> 21.38775 | AR38: =SUMIFS('Combined P&L'!AP:AP,'Combined P&L'!$C:$C,'P&L Forecast'!$B38) -> 23.44584 | AS38: =SUMIFS('Combined P&L'!AQ:AQ,'Combined P&L'!$C:$C,'P&L Forecast'!$B38) -> 24.67467 | AT38: =SUMIFS('Combined P&L'!AR:AR,'Combined P&L'!$C:$C,'P&L Forecast'!$B38) -> 27.97568
B39: Software & Apps - G&A | C39: =SUMIFS($P39:$AT39,$P$5:$AT$5,">"&C$172,$P$5:$AT$5,"<"&C$173) -> 60.91594 | D39: =SUMIFS($P39:$AT39,$P$5:$AT$5,">"&D$172,$P$5:$AT$5,"<"&D$173) -> 117.05866 | F39: =SUMIFS($P39:$AT39,$P$5:$AT$5,">"&F$172,$P$5:$AT$5,"<"&F$173) -> 56.8115 | G39: =SUMIFS($P39:$AT39,$P$5:$AT$5,">"&G$172,$P$5:$AT$5,"<"&G$173) -> 97.04798 | I39: =SUMIFS($P39:$AT39,$P$5:$AT$5,">"&I$172,$P$5:$AT$5,"<"&I$173) -> 83.0439 | J39: =SUMIFS($P39:$AT39,$P$5:$AT$5,">"&J$172,$P$5:$AT$5,"<"&J$173) -> 153.2946 | K39: =+C139 -> 155.82264 | M39: =+J39-K39 -> -2.52804 | N39: =IFERROR(K39/J39-1,0) -> 0.016491383 | P39: =SUMIFS('Combined P&L'!N:N,'Combined P&L'!$C:$C,'P&L Forecast'!$B39) -> 3.45285 | Q39: =SUMIFS('Combined P&L'!O:O,'Combined P&L'!$C:$C,'P&L Forecast'!$B39) -> 3.61753 | R39: =SUMIFS('Combined P&L'!P:P,'Combined P&L'!$C:$C,'P&L Forecast'!$B39) -> 3.97407 | S39: =SUMIFS('Combined P&L'!Q:Q,'Combined P&L'!$C:$C,'P&L Forecast'!$B39) -> 4.22365 | T39: =SUMIFS('Combined P&L'!R:R,'Combined P&L'!$C:$C,'P&L Forecast'!$B39) -> 5.09725 | U39: =SUMIFS('Combined P&L'!S:S,'Combined P&L'!$C:$C,'P&L Forecast'!$B39) -> 5.33351 | V39: =SUMIFS('Combined P&L'!T:T,'Combined P&L'!$C:$C,'P&L Forecast'!$B39) -> 5.51369 | W39: =SUMIFS('Combined P&L'!U:U,'Combined P&L'!$C:$C,'P&L Forecast'!$B39) -> 5.23169 | X39: =SUMIFS('Combined P&L'!V:V,'Combined P&L'!$C:$C,'P&L Forecast'!$B39) -> 5.51622 | Y39: =SUMIFS('Combined P&L'!W:W,'Combined P&L'!$C:$C,'P&L Forecast'!$B39) -> 6.12797 | Z39: =SUMIFS('Combined P&L'!X:X,'Combined P&L'!$C:$C,'P&L Forecast'!$B39) -> 6.15097 | AA39: =SUMIFS('Combined P&L'!Y:Y,'Combined P&L'!$C:$C,'P&L Forecast'!$B39) -> 6.67654 | AB39: =SUMIFS('Combined P&L'!Z:Z,'Combined P&L'!$C:$C,'P&L Forecast'!$B39) -> 7.74646 | AC39: =SUMIFS('Combined P&L'!AA:AA,'Combined P&L'!$C:$C,'P&L Forecast'!$B39) -> 7.89181 | AD39: =SUMIFS('Combined P&L'!AB:AB,'Combined P&L'!$C:$C,'P&L Forecast'!$B39) -> 7.89085 | AE39: =SUMIFS('Combined P&L'!AC:AC,'Combined P&L'!$C:$C,'P&L Forecast'!$B39) -> 7.83463 | AF39: =SUMIFS('Combined P&L'!AD:AD,'Combined P&L'!$C:$C,'P&L Forecast'!$B39) -> 8.11723 | AG39: =SUMIFS('Combined P&L'!AE:AE,'Combined P&L'!$C:$C,'P&L Forecast'!$B39) -> 8.34584 | AH39: =SUMIFS('Combined P&L'!AF:AF,'Combined P&L'!$C:$C,'P&L Forecast'!$B39) -> 8.98468 | AI39: =SUMIFS('Combined P&L'!AG:AG,'Combined P&L'!$C:$C,'P&L Forecast'!$B39) -> 9.8566 | AJ39: =SUMIFS('Combined P&L'!AH:AH,'Combined P&L'!$C:$C,'P&L Forecast'!$B39) -> 10.73391 | AK39: =SUMIFS('Combined P&L'!AI:AI,'Combined P&L'!$C:$C,'P&L Forecast'!$B39) -> 12.08939 | AL39: =SUMIFS('Combined P&L'!AJ:AJ,'Combined P&L'!$C:$C,'P&L Forecast'!$B39) -> 13.14583 | AM39: =SUMIFS('Combined P&L'!AK:AK,'Combined P&L'!$C:$C,'P&L Forecast'!$B39) -> 14.42143 | AN39: =SUMIFS('Combined P&L'!AL:AL,'Combined P&L'!$C:$C,'P&L Forecast'!$B39) -> 13.26316 | AO39: =SUMIFS('Combined P&L'!AM:AM,'Combined P&L'!$C:$C,'P&L Forecast'!$B39) -> 14.7201 | AP39: =SUMIFS('Combined P&L'!AN:AN,'Combined P&L'!$C:$C,'P&L Forecast'!$B39) -> 14.99072 | AQ39: =SUMIFS('Combined P&L'!AO:AO,'Combined P&L'!$C:$C,'P&L Forecast'!$B39) -> 14.74459 | AR39: =SUMIFS('Combined P&L'!AP:AP,'Combined P&L'!$C:$C,'P&L Forecast'!$B39) -> 13.2292 | AS39: =SUMIFS('Combined P&L'!AQ:AQ,'Combined P&L'!$C:$C,'P&L Forecast'!$B39) -> 13.11499 | AT39: =SUMIFS('Combined P&L'!AR:AR,'Combined P&L'!$C:$C,'P&L Forecast'!$B39) -> 12.98522
B40: Software & Apps - Topkey | C40: =SUMIFS($P40:$AT40,$P$5:$AT$5,">"&C$172,$P$5:$AT$5,"<"&C$173) -> 0 | D40: =SUMIFS($P40:$AT40,$P$5:$AT$5,">"&D$172,$P$5:$AT$5,"<"&D$173) -> 7.14125 | F40: =SUMIFS($P40:$AT40,$P$5:$AT$5,">"&F$172,$P$5:$AT$5,"<"&F$173) -> 0 | G40: =SUMIFS($P40:$AT40,$P$5:$AT$5,">"&G$172,$P$5:$AT$5,"<"&G$173) -> 28.82775 | I40: =SUMIFS($P40:$AT40,$P$5:$AT$5,">"&I$172,$P$5:$AT$5,"<"&I$173) -> 0 | J40: =SUMIFS($P40:$AT40,$P$5:$AT$5,">"&J$172,$P$5:$AT$5,"<"&J$173) -> 30.899 | K40: =+C140 -> 60.84 | M40: =+J40-K40 -> -29.941 | N40: =IFERROR(K40/J40-1,0) -> 0.96899576 | P40: =SUMIFS('Combined P&L'!N:N,'Combined P&L'!$C:$C,'P&L Forecast'!$B40) -> 0 | Q40: =SUMIFS('Combined P&L'!O:O,'Combined P&L'!$C:$C,'P&L Forecast'!$B40) -> 0 | R40: =SUMIFS('Combined P&L'!P:P,'Combined P&L'!$C:$C,'P&L Forecast'!$B40) -> 0 | S40: =SUMIFS('Combined P&L'!Q:Q,'Combined P&L'!$C:$C,'P&L Forecast'!$B40) -> 0 | T40: =SUMIFS('Combined P&L'!R:R,'Combined P&L'!$C:$C,'P&L Forecast'!$B40) -> 0 | U40: =SUMIFS('Combined P&L'!S:S,'Combined P&L'!$C:$C,'P&L Forecast'!$B40) -> 0 | V40: =SUMIFS('Combined P&L'!T:T,'Combined P&L'!$C:$C,'P&L Forecast'!$B40) -> 0 | W40: =SUMIFS('Combined P&L'!U:U,'Combined P&L'!$C:$C,'P&L Forecast'!$B40) -> 0 | X40: =SUMIFS('Combined P&L'!V:V,'Combined P&L'!$C:$C,'P&L Forecast'!$B40) -> 0 | Y40: =SUMIFS('Combined P&L'!W:W,'Combined P&L'!$C:$C,'P&L Forecast'!$B40) -> 0 | Z40: =SUMIFS('Combined P&L'!X:X,'Combined P&L'!$C:$C,'P&L Forecast'!$B40) -> 0 | AA40: =SUMIFS('Combined P&L'!Y:Y,'Combined P&L'!$C:$C,'P&L Forecast'!$B40) -> 0 | AB40: =SUMIFS('Combined P&L'!Z:Z,'Combined P&L'!$C:$C,'P&L Forecast'!$B40) -> 0 | AC40: =SUMIFS('Combined P&L'!AA:AA,'Combined P&L'!$C:$C,'P&L Forecast'!$B40) -> 0 | AD40: =SUMIFS('Combined P&L'!AB:AB,'Combined P&L'!$C:$C,'P&L Forecast'!$B40) -> 0 | AE40: =SUMIFS('Combined P&L'!AC:AC,'Combined P&L'!$C:$C,'P&L Forecast'!$B40) -> 0 | AF40: =SUMIFS('Combined P&L'!AD:AD,'Combined P&L'!$C:$C,'P&L Forecast'!$B40) -> 0 | AG40: =SUMIFS('Combined P&L'!AE:AE,'Combined P&L'!$C:$C,'P&L Forecast'!$B40) -> 0 | AH40: =SUMIFS('Combined P&L'!AF:AF,'Combined P&L'!$C:$C,'P&L Forecast'!$B40) -> 0 | AI40: =SUMIFS('Combined P&L'!AG:AG,'Combined P&L'!$C:$C,'P&L Forecast'!$B40) -> 0 | AJ40: =SUMIFS('Combined P&L'!AH:AH,'Combined P&L'!$C:$C,'P&L Forecast'!$B40) -> 0.93725 | AK40: =SUMIFS('Combined P&L'!AI:AI,'Combined P&L'!$C:$C,'P&L Forecast'!$B40) -> 1.39225 | AL40: =SUMIFS('Combined P&L'!AJ:AJ,'Combined P&L'!$C:$C,'P&L Forecast'!$B40) -> 2.36125 | AM40: =SUMIFS('Combined P&L'!AK:AK,'Combined P&L'!$C:$C,'P&L Forecast'!$B40) -> 2.4505 | AN40: =SUMIFS('Combined P&L'!AL:AL,'Combined P&L'!$C:$C,'P&L Forecast'!$B40) -> 2.94975 | AO40: =SUMIFS('Combined P&L'!AM:AM,'Combined P&L'!$C:$C,'P&L Forecast'!$B40) -> 3.42 | AP40: =SUMIFS('Combined P&L'!AN:AN,'Combined P&L'!$C:$C,'P&L Forecast'!$B40) -> 3.678 | AQ40: =SUMIFS('Combined P&L'!AO:AO,'Combined P&L'!$C:$C,'P&L Forecast'!$B40) -> 4.218 | AR40: =SUMIFS('Combined P&L'!AP:AP,'Combined P&L'!$C:$C,'P&L Forecast'!$B40) -> 4.284 | AS40: =SUMIFS('Combined P&L'!AQ:AQ,'Combined P&L'!$C:$C,'P&L Forecast'!$B40) -> 5.208 | AT40: =SUMIFS('Combined P&L'!AR:AR,'Combined P&L'!$C:$C,'P&L Forecast'!$B40) -> 5.07
B41: Software & Apps - AI tools | C41: =SUMIFS($P41:$AT41,$P$5:$AT$5,">"&C$172,$P$5:$AT$5,"<"&C$173) -> 0 | D41: =SUMIFS($P41:$AT41,$P$5:$AT$5,">"&D$172,$P$5:$AT$5,"<"&D$173) -> 0 | F41: =SUMIFS($P41:$AT41,$P$5:$AT$5,">"&F$172,$P$5:$AT$5,"<"&F$173) -> 0 | G41: =SUMIFS($P41:$AT41,$P$5:$AT$5,">"&G$172,$P$5:$AT$5,"<"&G$173) -> 6.52752 | I41: =SUMIFS($P41:$AT41,$P$5:$AT$5,">"&I$172,$P$5:$AT$5,"<"&I$173) -> 0 | J41: =SUMIFS($P41:$AT41,$P$5:$AT$5,">"&J$172,$P$5:$AT$5,"<"&J$173) -> 5.21554 | K41: =+C141 -> 15.74376 | M41: =+J41-K41 -> -10.52822 | N41: =IFERROR(K41/J41-1,0) -> 2.0186251 | P41: =SUMIFS('Combined P&L'!N:N,'Combined P&L'!$C:$C,'P&L Forecast'!$B41) -> 0 | Q41: =SUMIFS('Combined P&L'!O:O,'Combined P&L'!$C:$C,'P&L Forecast'!$B41) -> 0 | R41: =SUMIFS('Combined P&L'!P:P,'Combined P&L'!$C:$C,'P&L Forecast'!$B41) -> 0 | S41: =SUMIFS('Combined P&L'!Q:Q,'Combined P&L'!$C:$C,'P&L Forecast'!$B41) -> 0 | T41: =SUMIFS('Combined P&L'!R:R,'Combined P&L'!$C:$C,'P&L Forecast'!$B41) -> 0 | U41: =SUMIFS('Combined P&L'!S:S,'Combined P&L'!$C:$C,'P&L Forecast'!$B41) -> 0 | V41: =SUMIFS('Combined P&L'!T:T,'Combined P&L'!$C:$C,'P&L Forecast'!$B41) -> 0 | W41: =SUMIFS('Combined P&L'!U:U,'Combined P&L'!$C:$C,'P&L Forecast'!$B41) -> 0 | X41: =SUMIFS('Combined P&L'!V:V,'Combined P&L'!$C:$C,'P&L Forecast'!$B41) -> 0 | Y41: =SUMIFS('Combined P&L'!W:W,'Combined P&L'!$C:$C,'P&L Forecast'!$B41) -> 0 | Z41: =SUMIFS('Combined P&L'!X:X,'Combined P&L'!$C:$C,'P&L Forecast'!$B41) -> 0 | AA41: =SUMIFS('Combined P&L'!Y:Y,'Combined P&L'!$C:$C,'P&L Forecast'!$B41) -> 0 | AB41: =SUMIFS('Combined P&L'!Z:Z,'Combined P&L'!$C:$C,'P&L Forecast'!$B41) -> 0 | AC41: =SUMIFS('Combined P&L'!AA:AA,'Combined P&L'!$C:$C,'P&L Forecast'!$B41) -> 0 | AD41: =SUMIFS('Combined P&L'!AB:AB,'Combined P&L'!$C:$C,'P&L Forecast'!$B41) -> 0 | AE41: =SUMIFS('Combined P&L'!AC:AC,'Combined P&L'!$C:$C,'P&L Forecast'!$B41) -> 0 | AF41: =SUMIFS('Combined P&L'!AD:AD,'Combined P&L'!$C:$C,'P&L Forecast'!$B41) -> 0 | AG41: =SUMIFS('Combined P&L'!AE:AE,'Combined P&L'!$C:$C,'P&L Forecast'!$B41) -> 0 | AH41: =SUMIFS('Combined P&L'!AF:AF,'Combined P&L'!$C:$C,'P&L Forecast'!$B41) -> 0 | AI41: =SUMIFS('Combined P&L'!AG:AG,'Combined P&L'!$C:$C,'P&L Forecast'!$B41) -> 0 | AJ41: =SUMIFS('Combined P&L'!AH:AH,'Combined P&L'!$C:$C,'P&L Forecast'!$B41) -> 0 | AK41: =SUMIFS('Combined P&L'!AI:AI,'Combined P&L'!$C:$C,'P&L Forecast'!$B41) -> 0 | AL41: =SUMIFS('Combined P&L'!AJ:AJ,'Combined P&L'!$C:$C,'P&L Forecast'!$B41) -> 0 | AM41: =SUMIFS('Combined P&L'!AK:AK,'Combined P&L'!$C:$C,'P&L Forecast'!$B41) -> 0 | AN41: =SUMIFS('Combined P&L'!AL:AL,'Combined P&L'!$C:$C,'P&L Forecast'!$B41) -> 0.12 | AO41: =SUMIFS('Combined P&L'!AM:AM,'Combined P&L'!$C:$C,'P&L Forecast'!$B41) -> 0.12 | AP41: =SUMIFS('Combined P&L'!AN:AN,'Combined P&L'!$C:$C,'P&L Forecast'!$B41) -> 0.70166 | AQ41: =SUMIFS('Combined P&L'!AO:AO,'Combined P&L'!$C:$C,'P&L Forecast'!$B41) -> 2.20736 | AR41: =SUMIFS('Combined P&L'!AP:AP,'Combined P&L'!$C:$C,'P&L Forecast'!$B41) -> 0.91487 | AS41: =SUMIFS('Combined P&L'!AQ:AQ,'Combined P&L'!$C:$C,'P&L Forecast'!$B41) -> 1.15165 | AT41: =SUMIFS('Combined P&L'!AR:AR,'Combined P&L'!$C:$C,'P&L Forecast'!$B41) -> 1.31198
B42: Total Software Expenses | C42: =SUM(C38:C41) -> 175.33863 | D42: =SUM(D38:D41) -> 281.69462 | F42: =SUM(F38:F41) -> 141.78009 | G42: =SUM(G38:G41) -> 284.68482 | I42: =SUM(I38:I41) -> 223.03858 | J42: =SUM(J38:J41) -> 399.3766 | K42: =SUM(K38:K41) -> 568.11456 | M42: =SUM(M38:M41) -> -168.73796 | N42: =IFERROR(K42/J42-1,0) -> 0.42250337 | P42: =SUM(P38:P41) -> 10.52585 | Q42: =SUM(Q38:Q41) -> 10.63571 | R42: =SUM(R38:R41) -> 11.75195 | S42: =SUM(S38:S41) -> 11.98489 | T42: =SUM(T38:T41) -> 12.81546 | U42: =SUM(U38:U41) -> 14.24615 | V42: =SUM(V38:V41) -> 16.36037 | W42: =SUM(W38:W41) -> 16.36683 | ... AT42: =SUM(AT38:AT41) -> 47.34288
B44: Other Professional Fees | C44: =SUMIFS($P44:$AT44,$P$5:$AT$5,">"&C$172,$P$5:$AT$5,"<"&C$173) -> 18.23425 | D44: =SUMIFS($P44:$AT44,$P$5:$AT$5,">"&D$172,$P$5:$AT$5,"<"&D$173) -> 27.04095 | F44: =SUMIFS($P44:$AT44,$P$5:$AT$5,">"&F$172,$P$5:$AT$5,"<"&F$173) -> 12.014 | G44: =SUMIFS($P44:$AT44,$P$5:$AT$5,">"&G$172,$P$5:$AT$5,"<"&G$173) -> 57.55 | I44: =SUMIFS($P44:$AT44,$P$5:$AT$5,">"&I$172,$P$5:$AT$5,"<"&I$173) -> 22.91525 | J44: =SUMIFS($P44:$AT44,$P$5:$AT$5,">"&J$172,$P$5:$AT$5,"<"&J$173) -> 53.62695 | K44: =+C145 -> 53.62695 | M44: =+J44-K44 -> 0 | N44: =IFERROR(K44/J44-1,0) -> 0 | P44: =SUMIFS('Combined P&L'!N:N,'Combined P&L'!$C:$C,'P&L Forecast'!$B44) -> 0 | Q44: =SUMIFS('Combined P&L'!O:O,'Combined P&L'!$C:$C,'P&L Forecast'!$B44) -> 1.1665 | R44: =SUMIFS('Combined P&L'!P:P,'Combined P&L'!$C:$C,'P&L Forecast'!$B44) -> 1.1665 | S44: =SUMIFS('Combined P&L'!Q:Q,'Combined P&L'!$C:$C,'P&L Forecast'!$B44) -> 1.16667 | T44: =SUMIFS('Combined P&L'!R:R,'Combined P&L'!$C:$C,'P&L Forecast'!$B44) -> 1.16667 | U44: =SUMIFS('Combined P&L'!S:S,'Combined P&L'!$C:$C,'P&L Forecast'!$B44) -> 2.66666 | V44: =SUMIFS('Combined P&L'!T:T,'Combined P&L'!$C:$C,'P&L Forecast'!$B44) -> 1.16667 | W44: =SUMIFS('Combined P&L'!U:U,'Combined P&L'!$C:$C,'P&L Forecast'!$B44) -> 1.16667 | X44: =SUMIFS('Combined P&L'!V:V,'Combined P&L'!$C:$C,'P&L Forecast'!$B44) -> 3.06791 | Y44: =SUMIFS('Combined P&L'!W:W,'Combined P&L'!$C:$C,'P&L Forecast'!$B44) -> 1.16667 | Z44: =SUMIFS('Combined P&L'!X:X,'Combined P&L'!$C:$C,'P&L Forecast'!$B44) -> 2.16667 | AA44: =SUMIFS('Combined P&L'!Y:Y,'Combined P&L'!$C:$C,'P&L Forecast'!$B44) -> 2.16666 | AB44: =SUMIFS('Combined P&L'!Z:Z,'Combined P&L'!$C:$C,'P&L Forecast'!$B44) -> 2.16667 | AC44: =SUMIFS('Combined P&L'!AA:AA,'Combined P&L'!$C:$C,'P&L Forecast'!$B44) -> 2.16667 | AD44: =SUMIFS('Combined P&L'!AB:AB,'Combined P&L'!$C:$C,'P&L Forecast'!$B44) -> 2.16666 | AE44: =SUMIFS('Combined P&L'!AC:AC,'Combined P&L'!$C:$C,'P&L Forecast'!$B44) -> 2.76067 | AF44: =SUMIFS('Combined P&L'!AD:AD,'Combined P&L'!$C:$C,'P&L Forecast'!$B44) -> 1.58667 | AG44: =SUMIFS('Combined P&L'!AE:AE,'Combined P&L'!$C:$C,'P&L Forecast'!$B44) -> 1.16666 | AH44: =SUMIFS('Combined P&L'!AF:AF,'Combined P&L'!$C:$C,'P&L Forecast'!$B44) -> 0 | AI44: =SUMIFS('Combined P&L'!AG:AG,'Combined P&L'!$C:$C,'P&L Forecast'!$B44) -> 0.2 | AJ44: =SUMIFS('Combined P&L'!AH:AH,'Combined P&L'!$C:$C,'P&L Forecast'!$B44) -> 1.32695 | AK44: =SUMIFS('Combined P&L'!AI:AI,'Combined P&L'!$C:$C,'P&L Forecast'!$B44) -> 0 | AL44: =SUMIFS('Combined P&L'!AJ:AJ,'Combined P&L'!$C:$C,'P&L Forecast'!$B44) -> 6 | AM44: =SUMIFS('Combined P&L'!AK:AK,'Combined P&L'!$C:$C,'P&L Forecast'!$B44) -> 7.5 | AN44: =SUMIFS('Combined P&L'!AL:AL,'Combined P&L'!$C:$C,'P&L Forecast'!$B44) -> 0 | AO44: =SUMIFS('Combined P&L'!AM:AM,'Combined P&L'!$C:$C,'P&L Forecast'!$B44) -> 0 | AP44: =SUMIFS('Combined P&L'!AN:AN,'Combined P&L'!$C:$C,'P&L Forecast'!$B44) -> 6.6 | AQ44: =SUMIFS('Combined P&L'!AO:AO,'Combined P&L'!$C:$C,'P&L Forecast'!$B44) -> 14 | AR44: =SUMIFS('Combined P&L'!AP:AP,'Combined P&L'!$C:$C,'P&L Forecast'!$B44) -> 18 | AS44: =SUMIFS('Combined P&L'!AQ:AQ,'Combined P&L'!$C:$C,'P&L Forecast'!$B44) -> 0 | AT44: =SUMIFS('Combined P&L'!AR:AR,'Combined P&L'!$C:$C,'P&L Forecast'!$B44) -> 18.95
B45: Referral Fees | C45: =SUMIFS($P45:$AT45,$P$5:$AT$5,">"&C$172,$P$5:$AT$5,"<"&C$173) -> 24.82 | D45: =SUMIFS($P45:$AT45,$P$5:$AT$5,">"&D$172,$P$5:$AT$5,"<"&D$173) -> 27.15374 | F45: =SUMIFS($P45:$AT45,$P$5:$AT$5,">"&F$172,$P$5:$AT$5,"<"&F$173) -> 17.0895 | G45: =SUMIFS($P45:$AT45,$P$5:$AT$5,">"&G$172,$P$5:$AT$5,"<"&G$173) -> 20.62969 | I45: =SUMIFS($P45:$AT45,$P$5:$AT$5,">"&I$172,$P$5:$AT$5,"<"&I$173) -> 23.71975 | J45: =SUMIFS($P45:$AT45,$P$5:$AT$5,">"&J$172,$P$5:$AT$5,"<"&J$173) -> 30.69416 | K45: =+C146 -> 30.69416 | M45: =+J45-K45 -> 0 | N45: =IFERROR(K45/J45-1,0) -> 0 | P45: =SUMIFS('Combined P&L'!N:N,'Combined P&L'!$C:$C,'P&L Forecast'!$B45) -> 2.21 | Q45: =SUMIFS('Combined P&L'!O:O,'Combined P&L'!$C:$C,'P&L Forecast'!$B45) -> 2.735 | R45: =SUMIFS('Combined P&L'!P:P,'Combined P&L'!$C:$C,'P&L Forecast'!$B45) -> 2.715 | S45: =SUMIFS('Combined P&L'!Q:Q,'Combined P&L'!$C:$C,'P&L Forecast'!$B45) -> 2.735 | T45: =SUMIFS('Combined P&L'!R:R,'Combined P&L'!$C:$C,'P&L Forecast'!$B45) -> 0.78 | U45: =SUMIFS('Combined P&L'!S:S,'Combined P&L'!$C:$C,'P&L Forecast'!$B45) -> 3.245 | V45: =SUMIFS('Combined P&L'!T:T,'Combined P&L'!$C:$C,'P&L Forecast'!$B45) -> 1.28 | W45: =SUMIFS('Combined P&L'!U:U,'Combined P&L'!$C:$C,'P&L Forecast'!$B45) -> 1.3 | X45: =SUMIFS('Combined P&L'!V:V,'Combined P&L'!$C:$C,'P&L Forecast'!$B45) -> 1.81 | Y45: =SUMIFS('Combined P&L'!W:W,'Combined P&L'!$C:$C,'P&L Forecast'!$B45) -> 1.82 | Z45: =SUMIFS('Combined P&L'!X:X,'Combined P&L'!$C:$C,'P&L Forecast'!$B45) -> 1.835 | AA45: =SUMIFS('Combined P&L'!Y:Y,'Combined P&L'!$C:$C,'P&L Forecast'!$B45) -> 2.355 | AB45: =SUMIFS('Combined P&L'!Z:Z,'Combined P&L'!$C:$C,'P&L Forecast'!$B45) -> 1.47025 | AC45: =SUMIFS('Combined P&L'!AA:AA,'Combined P&L'!$C:$C,'P&L Forecast'!$B45) -> 1.665 | AD45: =SUMIFS('Combined P&L'!AB:AB,'Combined P&L'!$C:$C,'P&L Forecast'!$B45) -> 2.62775 | AE45: =SUMIFS('Combined P&L'!AC:AC,'Combined P&L'!$C:$C,'P&L Forecast'!$B45) -> 1.24875 | AF45: =SUMIFS('Combined P&L'!AD:AD,'Combined P&L'!$C:$C,'P&L Forecast'!$B45) -> 2.154 | AG45: =SUMIFS('Combined P&L'!AE:AE,'Combined P&L'!$C:$C,'P&L Forecast'!$B45) -> 4.154 | AH45: =SUMIFS('Combined P&L'!AF:AF,'Combined P&L'!$C:$C,'P&L Forecast'!$B45) -> 3.76975 | AI45: =SUMIFS('Combined P&L'!AG:AG,'Combined P&L'!$C:$C,'P&L Forecast'!$B45) -> 1.696 | AJ45: =SUMIFS('Combined P&L'!AH:AH,'Combined P&L'!$C:$C,'P&L Forecast'!$B45) -> 2.2275 | AK45: =SUMIFS('Combined P&L'!AI:AI,'Combined P&L'!$C:$C,'P&L Forecast'!$B45) -> 1.6645 | AL45: =SUMIFS('Combined P&L'!AJ:AJ,'Combined P&L'!$C:$C,'P&L Forecast'!$B45) -> 1.71879 | AM45: =SUMIFS('Combined P&L'!AK:AK,'Combined P&L'!$C:$C,'P&L Forecast'!$B45) -> 2.75745 | AN45: =SUMIFS('Combined P&L'!AL:AL,'Combined P&L'!$C:$C,'P&L Forecast'!$B45) -> 1.8688 | AO45: =SUMIFS('Combined P&L'!AM:AM,'Combined P&L'!$C:$C,'P&L Forecast'!$B45) -> 4.43991 | AP45: =SUMIFS('Combined P&L'!AN:AN,'Combined P&L'!$C:$C,'P&L Forecast'!$B45) -> 2.39361 | AQ45: =SUMIFS('Combined P&L'!AO:AO,'Combined P&L'!$C:$C,'P&L Forecast'!$B45) -> 3.65786 | AR45: =SUMIFS('Combined P&L'!AP:AP,'Combined P&L'!$C:$C,'P&L Forecast'!$B45) -> 2.93379 | AS45: =SUMIFS('Combined P&L'!AQ:AQ,'Combined P&L'!$C:$C,'P&L Forecast'!$B45) -> 1.5662 | AT45: =SUMIFS('Combined P&L'!AR:AR,'Combined P&L'!$C:$C,'P&L Forecast'!$B45) -> 3.76952
B46: Travel, Meals & Entertainment | C46: =SUMIFS($P46:$AT46,$P$5:$AT$5,">"&C$172,$P$5:$AT$5,"<"&C$173) -> 0 | D46: =SUMIFS($P46:$AT46,$P$5:$AT$5,">"&D$172,$P$5:$AT$5,"<"&D$173) -> 29.76122 | F46: =SUMIFS($P46:$AT46,$P$5:$AT$5,">"&F$172,$P$5:$AT$5,"<"&F$173) -> 22.29558 | G46: =SUMIFS($P46:$AT46,$P$5:$AT$5,">"&G$172,$P$5:$AT$5,"<"&G$173) -> 20.68542 | I46: =SUMIFS($P46:$AT46,$P$5:$AT$5,">"&I$172,$P$5:$AT$5,"<"&I$173) -> 22.19792 | J46: =SUMIFS($P46:$AT46,$P$5:$AT$5,">"&J$172,$P$5:$AT$5,"<"&J$173) -> 28.23873 | K46: =+C147 -> 28.23873 | M46: =+J46-K46 -> 0 | N46: =IFERROR(K46/J46-1,0) -> 0 | P46: =SUMIFS('Combined P&L'!N:N,'Combined P&L'!$C:$C,'P&L Forecast'!$B46) -> 0 | Q46: =SUMIFS('Combined P&L'!O:O,'Combined P&L'!$C:$C,'P&L Forecast'!$B46) -> 0 | R46: =SUMIFS('Combined P&L'!P:P,'Combined P&L'!$C:$C,'P&L Forecast'!$B46) -> 0 | S46: =SUMIFS('Combined P&L'!Q:Q,'Combined P&L'!$C:$C,'P&L Forecast'!$B46) -> 0 | T46: =SUMIFS('Combined P&L'!R:R,'Combined P&L'!$C:$C,'P&L Forecast'!$B46) -> 0 | U46: =SUMIFS('Combined P&L'!S:S,'Combined P&L'!$C:$C,'P&L Forecast'!$B46) -> 0 | V46: =SUMIFS('Combined P&L'!T:T,'Combined P&L'!$C:$C,'P&L Forecast'!$B46) -> 0 | W46: =SUMIFS('Combined P&L'!U:U,'Combined P&L'!$C:$C,'P&L Forecast'!$B46) -> 0 | X46: =SUMIFS('Combined P&L'!V:V,'Combined P&L'!$C:$C,'P&L Forecast'!$B46) -> 0 | Y46: =SUMIFS('Combined P&L'!W:W,'Combined P&L'!$C:$C,'P&L Forecast'!$B46) -> 0 | Z46: =SUMIFS('Combined P&L'!X:X,'Combined P&L'!$C:$C,'P&L Forecast'!$B46) -> 0 | AA46: =SUMIFS('Combined P&L'!Y:Y,'Combined P&L'!$C:$C,'P&L Forecast'!$B46) -> 0 | AB46: =SUMIFS('Combined P&L'!Z:Z,'Combined P&L'!$C:$C,'P&L Forecast'!$B46) -> 0.00691 | AC46: =SUMIFS('Combined P&L'!AA:AA,'Combined P&L'!$C:$C,'P&L Forecast'!$B46) -> 0 | AD46: =SUMIFS('Combined P&L'!AB:AB,'Combined P&L'!$C:$C,'P&L Forecast'!$B46) -> 0 | AE46: =SUMIFS('Combined P&L'!AC:AC,'Combined P&L'!$C:$C,'P&L Forecast'!$B46) -> 11.40629 | AF46: =SUMIFS('Combined P&L'!AD:AD,'Combined P&L'!$C:$C,'P&L Forecast'!$B46) -> 10.78472 | AG46: =SUMIFS('Combined P&L'!AE:AE,'Combined P&L'!$C:$C,'P&L Forecast'!$B46) -> 0 | AH46: =SUMIFS('Combined P&L'!AF:AF,'Combined P&L'!$C:$C,'P&L Forecast'!$B46) -> 0.09766 | AI46: =SUMIFS('Combined P&L'!AG:AG,'Combined P&L'!$C:$C,'P&L Forecast'!$B46) -> 0.92152 | AJ46: =SUMIFS('Combined P&L'!AH:AH,'Combined P&L'!$C:$C,'P&L Forecast'!$B46) -> 2.96423 | AK46: =SUMIFS('Combined P&L'!AI:AI,'Combined P&L'!$C:$C,'P&L Forecast'!$B46) -> 1.03679 | AL46: =SUMIFS('Combined P&L'!AJ:AJ,'Combined P&L'!$C:$C,'P&L Forecast'!$B46) -> 2.11036 | AM46: =SUMIFS('Combined P&L'!AK:AK,'Combined P&L'!$C:$C,'P&L Forecast'!$B46) -> 0.43274 | AN46: =SUMIFS('Combined P&L'!AL:AL,'Combined P&L'!$C:$C,'P&L Forecast'!$B46) -> 0 | AO46: =SUMIFS('Combined P&L'!AM:AM,'Combined P&L'!$C:$C,'P&L Forecast'!$B46) -> 0 | AP46: =SUMIFS('Combined P&L'!AN:AN,'Combined P&L'!$C:$C,'P&L Forecast'!$B46) -> 0 | AQ46: =SUMIFS('Combined P&L'!AO:AO,'Combined P&L'!$C:$C,'P&L Forecast'!$B46) -> 9.7651 | AR46: =SUMIFS('Combined P&L'!AP:AP,'Combined P&L'!$C:$C,'P&L Forecast'!$B46) -> 10.25443 | AS46: =SUMIFS('Combined P&L'!AQ:AQ,'Combined P&L'!$C:$C,'P&L Forecast'!$B46) -> 0.6559 | AT46: =SUMIFS('Combined P&L'!AR:AR,'Combined P&L'!$C:$C,'P&L Forecast'!$B46) -> 0.00999
B47: Payment Collection Fees | C47: =SUMIFS($P47:$AT47,$P$5:$AT$5,">"&C$172,$P$5:$AT$5,"<"&C$173) -> 8.67099 | D47: =SUMIFS($P47:$AT47,$P$5:$AT$5,">"&D$172,$P$5:$AT$5,"<"&D$173) -> 13.35153 | F47: =SUMIFS($P47:$AT47,$P$5:$AT$5,">"&F$172,$P$5:$AT$5,"<"&F$173) -> 6.80445 | G47: =SUMIFS($P47:$AT47,$P$5:$AT$5,">"&G$172,$P$5:$AT$5,"<"&G$173) -> 9.02684 | I47: =SUMIFS($P47:$AT47,$P$5:$AT$5,">"&I$172,$P$5:$AT$5,"<"&I$173) -> 9.9746 | J47: =SUMIFS($P47:$AT47,$P$5:$AT$5,">"&J$172,$P$5:$AT$5,"<"&J$173) -> 15.6528 | K47: =+C148 -> 15.6528 | M47: =+J47-K47 -> 0 | N47: =IFERROR(K47/J47-1,0) -> 0 | P47: =SUMIFS('Combined P&L'!N:N,'Combined P&L'!$C:$C,'P&L Forecast'!$B47) -> 0.6179 | Q47: =SUMIFS('Combined P&L'!O:O,'Combined P&L'!$C:$C,'P&L Forecast'!$B47) -> 0.8374 | R47: =SUMIFS('Combined P&L'!P:P,'Combined P&L'!$C:$C,'P&L Forecast'!$B47) -> 0.62936 | S47: =SUMIFS('Combined P&L'!Q:Q,'Combined P&L'!$C:$C,'P&L Forecast'!$B47) -> 0.68245 | T47: =SUMIFS('Combined P&L'!R:R,'Combined P&L'!$C:$C,'P&L Forecast'!$B47) -> 0.72151 | U47: =SUMIFS('Combined P&L'!S:S,'Combined P&L'!$C:$C,'P&L Forecast'!$B47) -> 0.78747 | V47: =SUMIFS('Combined P&L'!T:T,'Combined P&L'!$C:$C,'P&L Forecast'!$B47) -> 0.65562 | W47: =SUMIFS('Combined P&L'!U:U,'Combined P&L'!$C:$C,'P&L Forecast'!$B47) -> 0.79491 | X47: =SUMIFS('Combined P&L'!V:V,'Combined P&L'!$C:$C,'P&L Forecast'!$B47) -> 0.69063 | Y47: =SUMIFS('Combined P&L'!W:W,'Combined P&L'!$C:$C,'P&L Forecast'!$B47) -> 0.71761 | Z47: =SUMIFS('Combined P&L'!X:X,'Combined P&L'!$C:$C,'P&L Forecast'!$B47) -> 0.73795 | AA47: =SUMIFS('Combined P&L'!Y:Y,'Combined P&L'!$C:$C,'P&L Forecast'!$B47) -> 0.79818 | AB47: =SUMIFS('Combined P&L'!Z:Z,'Combined P&L'!$C:$C,'P&L Forecast'!$B47) -> 0.83546 | AC47: =SUMIFS('Combined P&L'!AA:AA,'Combined P&L'!$C:$C,'P&L Forecast'!$B47) -> 1.05394 | AD47: =SUMIFS('Combined P&L'!AB:AB,'Combined P&L'!$C:$C,'P&L Forecast'!$B47) -> 0.87069 | AE47: =SUMIFS('Combined P&L'!AC:AC,'Combined P&L'!$C:$C,'P&L Forecast'!$B47) -> 0.90555 | AF47: =SUMIFS('Combined P&L'!AD:AD,'Combined P&L'!$C:$C,'P&L Forecast'!$B47) -> 0.91157 | AG47: =SUMIFS('Combined P&L'!AE:AE,'Combined P&L'!$C:$C,'P&L Forecast'!$B47) -> 1.00249 | AH47: =SUMIFS('Combined P&L'!AF:AF,'Combined P&L'!$C:$C,'P&L Forecast'!$B47) -> 1.22475 | AI47: =SUMIFS('Combined P&L'!AG:AG,'Combined P&L'!$C:$C,'P&L Forecast'!$B47) -> 1.10438 | AJ47: =SUMIFS('Combined P&L'!AH:AH,'Combined P&L'!$C:$C,'P&L Forecast'!$B47) -> 1.29723 | AK47: =SUMIFS('Combined P&L'!AI:AI,'Combined P&L'!$C:$C,'P&L Forecast'!$B47) -> 1.21739 | AL47: =SUMIFS('Combined P&L'!AJ:AJ,'Combined P&L'!$C:$C,'P&L Forecast'!$B47) -> 1.62294 | AM47: =SUMIFS('Combined P&L'!AK:AK,'Combined P&L'!$C:$C,'P&L Forecast'!$B47) -> 1.30514 | AN47: =SUMIFS('Combined P&L'!AL:AL,'Combined P&L'!$C:$C,'P&L Forecast'!$B47) -> 1.22974 | AO47: =SUMIFS('Combined P&L'!AM:AM,'Combined P&L'!$C:$C,'P&L Forecast'!$B47) -> 1.73847 | AP47: =SUMIFS('Combined P&L'!AN:AN,'Combined P&L'!$C:$C,'P&L Forecast'!$B47) -> 1.35348 | AQ47: =SUMIFS('Combined P&L'!AO:AO,'Combined P&L'!$C:$C,'P&L Forecast'!$B47) -> 1.23399 | AR47: =SUMIFS('Combined P&L'!AP:AP,'Combined P&L'!$C:$C,'P&L Forecast'!$B47) -> 1.17137 | AS47: =SUMIFS('Combined P&L'!AQ:AQ,'Combined P&L'!$C:$C,'P&L Forecast'!$B47) -> 1.15392 | AT47: =SUMIFS('Combined P&L'!AR:AR,'Combined P&L'!$C:$C,'P&L Forecast'!$B47) -> 1.14587
B48: Professional Organizations | C48: =SUMIFS($P48:$AT48,$P$5:$AT$5,">"&C$172,$P$5:$AT$5,"<"&C$173) -> 5.44332 | D48: =SUMIFS($P48:$AT48,$P$5:$AT$5,">"&D$172,$P$5:$AT$5,"<"&D$173) -> 11.22296 | F48: =SUMIFS($P48:$AT48,$P$5:$AT$5,">"&F$172,$P$5:$AT$5,"<"&F$173) -> 6.191 | G48: =SUMIFS($P48:$AT48,$P$5:$AT$5,">"&G$172,$P$5:$AT$5,"<"&G$173) -> 6.57881 | I48: =SUMIFS($P48:$AT48,$P$5:$AT$5,">"&I$172,$P$5:$AT$5,"<"&I$173) -> 8.30166 | J48: =SUMIFS($P48:$AT48,$P$5:$AT$5,">"&J$172,$P$5:$AT$5,"<"&J$173) -> 12.15692 | K48: =+C149 -> 12.15692 | M48: =+J48-K48 -> 0 | N48: =IFERROR(K48/J48-1,0) -> 0 | P48: =SUMIFS('Combined P&L'!N:N,'Combined P&L'!$C:$C,'P&L Forecast'!$B48) -> 0.33417 | Q48: =SUMIFS('Combined P&L'!O:O,'Combined P&L'!$C:$C,'P&L Forecast'!$B48) -> 0.33417 | R48: =SUMIFS('Combined P&L'!P:P,'Combined P&L'!$C:$C,'P&L Forecast'!$B48) -> 0.33417 | S48: =SUMIFS('Combined P&L'!Q:Q,'Combined P&L'!$C:$C,'P&L Forecast'!$B48) -> 0.33417 | T48: =SUMIFS('Combined P&L'!R:R,'Combined P&L'!$C:$C,'P&L Forecast'!$B48) -> 0.255 | U48: =SUMIFS('Combined P&L'!S:S,'Combined P&L'!$C:$C,'P&L Forecast'!$B48) -> 0.255 | V48: =SUMIFS('Combined P&L'!T:T,'Combined P&L'!$C:$C,'P&L Forecast'!$B48) -> 0.25496 | W48: =SUMIFS('Combined P&L'!U:U,'Combined P&L'!$C:$C,'P&L Forecast'!$B48) -> 0.205 | X48: =SUMIFS('Combined P&L'!V:V,'Combined P&L'!$C:$C,'P&L Forecast'!$B48) -> 0.78417 | Y48: =SUMIFS('Combined P&L'!W:W,'Combined P&L'!$C:$C,'P&L Forecast'!$B48) -> 0.78417 | Z48: =SUMIFS('Combined P&L'!X:X,'Combined P&L'!$C:$C,'P&L Forecast'!$B48) -> 0.78417 | AA48: =SUMIFS('Combined P&L'!Y:Y,'Combined P&L'!$C:$C,'P&L Forecast'!$B48) -> 0.78417 | AB48: =SUMIFS('Combined P&L'!Z:Z,'Combined P&L'!$C:$C,'P&L Forecast'!$B48) -> 0.78417 | AC48: =SUMIFS('Combined P&L'!AA:AA,'Combined P&L'!$C:$C,'P&L Forecast'!$B48) -> 0.78417 | AD48: =SUMIFS('Combined P&L'!AB:AB,'Combined P&L'!$C:$C,'P&L Forecast'!$B48) -> 0.78417 | AE48: =SUMIFS('Combined P&L'!AC:AC,'Combined P&L'!$C:$C,'P&L Forecast'!$B48) -> 0.78417 | AF48: =SUMIFS('Combined P&L'!AD:AD,'Combined P&L'!$C:$C,'P&L Forecast'!$B48) -> 0.78417 | AG48: =SUMIFS('Combined P&L'!AE:AE,'Combined P&L'!$C:$C,'P&L Forecast'!$B48) -> 0.78417 | AH48: =SUMIFS('Combined P&L'!AF:AF,'Combined P&L'!$C:$C,'P&L Forecast'!$B48) -> 1.48598 | AI48: =SUMIFS('Combined P&L'!AG:AG,'Combined P&L'!$C:$C,'P&L Forecast'!$B48) -> 0.9633 | AJ48: =SUMIFS('Combined P&L'!AH:AH,'Combined P&L'!$C:$C,'P&L Forecast'!$B48) -> 0.98042 | AK48: =SUMIFS('Combined P&L'!AI:AI,'Combined P&L'!$C:$C,'P&L Forecast'!$B48) -> 1.02942 | AL48: =SUMIFS('Combined P&L'!AJ:AJ,'Combined P&L'!$C:$C,'P&L Forecast'!$B48) -> 1.02942 | AM48: =SUMIFS('Combined P&L'!AK:AK,'Combined P&L'!$C:$C,'P&L Forecast'!$B48) -> 1.0294 | AN48: =SUMIFS('Combined P&L'!AL:AL,'Combined P&L'!$C:$C,'P&L Forecast'!$B48) -> 0.93983 | AO48: =SUMIFS('Combined P&L'!AM:AM,'Combined P&L'!$C:$C,'P&L Forecast'!$B48) -> 0.93983 | AP48: =SUMIFS('Combined P&L'!AN:AN,'Combined P&L'!$C:$C,'P&L Forecast'!$B48) -> 0.93983 | AQ48: =SUMIFS('Combined P&L'!AO:AO,'Combined P&L'!$C:$C,'P&L Forecast'!$B48) -> 0.93983 | AR48: =SUMIFS('Combined P&L'!AP:AP,'Combined P&L'!$C:$C,'P&L Forecast'!$B48) -> 0.93983 | AS48: =SUMIFS('Combined P&L'!AQ:AQ,'Combined P&L'!$C:$C,'P&L Forecast'!$B48) -> 0.93983 | AT48: =SUMIFS('Combined P&L'!AR:AR,'Combined P&L'!$C:$C,'P&L Forecast'!$B48) -> 0.93983
B49: S&M Events | C49: =SUMIFS($P49:$AT49,$P$5:$AT$5,">"&C$172,$P$5:$AT$5,"<"&C$173) -> 0 | D49: =SUMIFS($P49:$AT49,$P$5:$AT$5,">"&D$172,$P$5:$AT$5,"<"&D$173) -> 11.4983 | F49: =SUMIFS($P49:$AT49,$P$5:$AT$5,">"&F$172,$P$5:$AT$5,"<"&F$173) -> 0 | G49: =SUMIFS($P49:$AT49,$P$5:$AT$5,">"&G$172,$P$5:$AT$5,"<"&G$173) -> 11.84548 | I49: =SUMIFS($P49:$AT49,$P$5:$AT$5,">"&I$172,$P$5:$AT$5,"<"&I$173) -> 0 | J49: =SUMIFS($P49:$AT49,$P$5:$AT$5,">"&J$172,$P$5:$AT$5,"<"&J$173) -> 11.64878 | K49: =+C150 -> 11.64878 | M49: =+J49-K49 -> 0 | N49: =IFERROR(K49/J49-1,0) -> 0 | P49: =SUMIFS('Combined P&L'!N:N,'Combined P&L'!$C:$C,'P&L Forecast'!$B49) -> 0 | Q49: =SUMIFS('Combined P&L'!O:O,'Combined P&L'!$C:$C,'P&L Forecast'!$B49) -> 0 | R49: =SUMIFS('Combined P&L'!P:P,'Combined P&L'!$C:$C,'P&L Forecast'!$B49) -> 0 | S49: =SUMIFS('Combined P&L'!Q:Q,'Combined P&L'!$C:$C,'P&L Forecast'!$B49) -> 0 | T49: =SUMIFS('Combined P&L'!R:R,'Combined P&L'!$C:$C,'P&L Forecast'!$B49) -> 0 | U49: =SUMIFS('Combined P&L'!S:S,'Combined P&L'!$C:$C,'P&L Forecast'!$B49) -> 0 | V49: =SUMIFS('Combined P&L'!T:T,'Combined P&L'!$C:$C,'P&L Forecast'!$B49) -> 0 | W49: =SUMIFS('Combined P&L'!U:U,'Combined P&L'!$C:$C,'P&L Forecast'!$B49) -> 0 | X49: =SUMIFS('Combined P&L'!V:V,'Combined P&L'!$C:$C,'P&L Forecast'!$B49) -> 0 | Y49: =SUMIFS('Combined P&L'!W:W,'Combined P&L'!$C:$C,'P&L Forecast'!$B49) -> 0 | Z49: =SUMIFS('Combined P&L'!X:X,'Combined P&L'!$C:$C,'P&L Forecast'!$B49) -> 0 | AA49: =SUMIFS('Combined P&L'!Y:Y,'Combined P&L'!$C:$C,'P&L Forecast'!$B49) -> 0 | AB49: =SUMIFS('Combined P&L'!Z:Z,'Combined P&L'!$C:$C,'P&L Forecast'!$B49) -> 0 | AC49: =SUMIFS('Combined P&L'!AA:AA,'Combined P&L'!$C:$C,'P&L Forecast'!$B49) -> 0 | AD49: =SUMIFS('Combined P&L'!AB:AB,'Combined P&L'!$C:$C,'P&L Forecast'!$B49) -> 0 | AE49: =SUMIFS('Combined P&L'!AC:AC,'Combined P&L'!$C:$C,'P&L Forecast'!$B49) -> 0 | AF49: =SUMIFS('Combined P&L'!AD:AD,'Combined P&L'!$C:$C,'P&L Forecast'!$B49) -> 0 | AG49: =SUMIFS('Combined P&L'!AE:AE,'Combined P&L'!$C:$C,'P&L Forecast'!$B49) -> 0 | AH49: =SUMIFS('Combined P&L'!AF:AF,'Combined P&L'!$C:$C,'P&L Forecast'!$B49) -> 0 | AI49: =SUMIFS('Combined P&L'!AG:AG,'Combined P&L'!$C:$C,'P&L Forecast'!$B49) -> 7.17 | AJ49: =SUMIFS('Combined P&L'!AH:AH,'Combined P&L'!$C:$C,'P&L Forecast'!$B49) -> 1.6495 | AK49: =SUMIFS('Combined P&L'!AI:AI,'Combined P&L'!$C:$C,'P&L Forecast'!$B49) -> 2.6788 | AL49: =SUMIFS('Combined P&L'!AJ:AJ,'Combined P&L'!$C:$C,'P&L Forecast'!$B49) -> 0 | AM49: =SUMIFS('Combined P&L'!AK:AK,'Combined P&L'!$C:$C,'P&L Forecast'!$B49) -> 0 | AN49: =SUMIFS('Combined P&L'!AL:AL,'Combined P&L'!$C:$C,'P&L Forecast'!$B49) -> 0.05 | AO49: =SUMIFS('Combined P&L'!AM:AM,'Combined P&L'!$C:$C,'P&L Forecast'!$B49) -> 0 | AP49: =SUMIFS('Combined P&L'!AN:AN,'Combined P&L'!$C:$C,'P&L Forecast'!$B49) -> 0 | AQ49: =SUMIFS('Combined P&L'!AO:AO,'Combined P&L'!$C:$C,'P&L Forecast'!$B49) -> 0 | AR49: =SUMIFS('Combined P&L'!AP:AP,'Combined P&L'!$C:$C,'P&L Forecast'!$B49) -> 0.09805 | AS49: =SUMIFS('Combined P&L'!AQ:AQ,'Combined P&L'!$C:$C,'P&L Forecast'!$B49) -> 0.00243 | AT49: =SUMIFS('Combined P&L'!AR:AR,'Combined P&L'!$C:$C,'P&L Forecast'!$B49) -> 11.695
B50: Recruiting Fees | C50: =SUMIFS($P50:$AT50,$P$5:$AT$5,">"&C$172,$P$5:$AT$5,"<"&C$173) -> 14.90205 | D50: =SUMIFS($P50:$AT50,$P$5:$AT$5,">"&D$172,$P$5:$AT$5,"<"&D$173) -> 31.6041 | F50: =SUMIFS($P50:$AT50,$P$5:$AT$5,">"&F$172,$P$5:$AT$5,"<"&F$173) -> 28.29994 | G50: =SUMIFS($P50:$AT50,$P$5:$AT$5,">"&G$172,$P$5:$AT$5,"<"&G$173) -> 5.5646 | I50: =SUMIFS($P50:$AT50,$P$5:$AT$5,">"&I$172,$P$5:$AT$5,"<"&I$173) -> 36.58249 | J50: =SUMIFS($P50:$AT50,$P$5:$AT$5,">"&J$172,$P$5:$AT$5,"<"&J$173) -> 8.84585 | K50: =+C152 -> 8.84585 | M50: =+J50-K50 -> 0 | N50: =IFERROR(K50/J50-1,0) -> 0 | P50: =SUMIFS('Combined P&L'!N:N,'Combined P&L'!$C:$C,'P&L Forecast'!$B50) -> 0.02492 | Q50: =SUMIFS('Combined P&L'!O:O,'Combined P&L'!$C:$C,'P&L Forecast'!$B50) -> 1.02492 | R50: =SUMIFS('Combined P&L'!P:P,'Combined P&L'!$C:$C,'P&L Forecast'!$B50) -> 1.02492 | S50: =SUMIFS('Combined P&L'!Q:Q,'Combined P&L'!$C:$C,'P&L Forecast'!$B50) -> 1.22492 | T50: =SUMIFS('Combined P&L'!R:R,'Combined P&L'!$C:$C,'P&L Forecast'!$B50) -> 1.02492 | U50: =SUMIFS('Combined P&L'!S:S,'Combined P&L'!$C:$C,'P&L Forecast'!$B50) -> 1.51802 | V50: =SUMIFS('Combined P&L'!T:T,'Combined P&L'!$C:$C,'P&L Forecast'!$B50) -> 2.01331 | W50: =SUMIFS('Combined P&L'!U:U,'Combined P&L'!$C:$C,'P&L Forecast'!$B50) -> 1.6009 | X50: =SUMIFS('Combined P&L'!V:V,'Combined P&L'!$C:$C,'P&L Forecast'!$B50) -> 1.58969 | Y50: =SUMIFS('Combined P&L'!W:W,'Combined P&L'!$C:$C,'P&L Forecast'!$B50) -> 1.12582 | Z50: =SUMIFS('Combined P&L'!X:X,'Combined P&L'!$C:$C,'P&L Forecast'!$B50) -> 1.44199 | AA50: =SUMIFS('Combined P&L'!Y:Y,'Combined P&L'!$C:$C,'P&L Forecast'!$B50) -> 1.28772 | AB50: =SUMIFS('Combined P&L'!Z:Z,'Combined P&L'!$C:$C,'P&L Forecast'!$B50) -> 2.41295 | AC50: =SUMIFS('Combined P&L'!AA:AA,'Combined P&L'!$C:$C,'P&L Forecast'!$B50) -> 22.3793 | AD50: =SUMIFS('Combined P&L'!AB:AB,'Combined P&L'!$C:$C,'P&L Forecast'!$B50) -> 0.72983 | AE50: =SUMIFS('Combined P&L'!AC:AC,'Combined P&L'!$C:$C,'P&L Forecast'!$B50) -> 0.59597 | AF50: =SUMIFS('Combined P&L'!AD:AD,'Combined P&L'!$C:$C,'P&L Forecast'!$B50) -> 0.87534 | AG50: =SUMIFS('Combined P&L'!AE:AE,'Combined P&L'!$C:$C,'P&L Forecast'!$B50) -> 0.52967 | AH50: =SUMIFS('Combined P&L'!AF:AF,'Combined P&L'!$C:$C,'P&L Forecast'!$B50) -> 0.77688 | AI50: =SUMIFS('Combined P&L'!AG:AG,'Combined P&L'!$C:$C,'P&L Forecast'!$B50) -> 0.21671 | AJ50: =SUMIFS('Combined P&L'!AH:AH,'Combined P&L'!$C:$C,'P&L Forecast'!$B50) -> 0.74952 | AK50: =SUMIFS('Combined P&L'!AI:AI,'Combined P&L'!$C:$C,'P&L Forecast'!$B50) -> 0.92573 | AL50: =SUMIFS('Combined P&L'!AJ:AJ,'Combined P&L'!$C:$C,'P&L Forecast'!$B50) -> 0.66044 | AM50: =SUMIFS('Combined P&L'!AK:AK,'Combined P&L'!$C:$C,'P&L Forecast'!$B50) -> 0.75176 | AN50: =SUMIFS('Combined P&L'!AL:AL,'Combined P&L'!$C:$C,'P&L Forecast'!$B50) -> 0.8203 | AO50: =SUMIFS('Combined P&L'!AM:AM,'Combined P&L'!$C:$C,'P&L Forecast'!$B50) -> 0.68046 | AP50: =SUMIFS('Combined P&L'!AN:AN,'Combined P&L'!$C:$C,'P&L Forecast'!$B50) -> 0.77239 | AQ50: =SUMIFS('Combined P&L'!AO:AO,'Combined P&L'!$C:$C,'P&L Forecast'!$B50) -> 0.71608 | AR50: =SUMIFS('Combined P&L'!AP:AP,'Combined P&L'!$C:$C,'P&L Forecast'!$B50) -> 0.6402 | AS50: =SUMIFS('Combined P&L'!AQ:AQ,'Combined P&L'!$C:$C,'P&L Forecast'!$B50) -> 1.13538 | AT50: =SUMIFS('Combined P&L'!AR:AR,'Combined P&L'!$C:$C,'P&L Forecast'!$B50) -> 0.79979
B51: Amortization | C51: =SUMIFS($P51:$AT51,$P$5:$AT$5,">"&C$172,$P$5:$AT$5,"<"&C$173) -> 6.673 | D51: =SUMIFS($P51:$AT51,$P$5:$AT$5,">"&D$172,$P$5:$AT$5,"<"&D$173) -> 6.673 | F51: =SUMIFS($P51:$AT51,$P$5:$AT$5,">"&F$172,$P$5:$AT$5,"<"&F$173) -> 0 | G51: =SUMIFS($P51:$AT51,$P$5:$AT$5,">"&G$172,$P$5:$AT$5,"<"&G$173) -> 0 | I51: =SUMIFS($P51:$AT51,$P$5:$AT$5,">"&I$172,$P$5:$AT$5,"<"&I$173) -> 6.673 | J51: =SUMIFS($P51:$AT51,$P$5:$AT$5,">"&J$172,$P$5:$AT$5,"<"&J$173) -> 6.673 | K51: =+C153 -> 6.673 | M51: =+J51-K51 -> 0 | N51: =IFERROR(K51/J51-1,0) -> 0 | P51: =SUMIFS('Combined P&L'!N:N,'Combined P&L'!$C:$C,'P&L Forecast'!$B51) -> 0 | Q51: =SUMIFS('Combined P&L'!O:O,'Combined P&L'!$C:$C,'P&L Forecast'!$B51) -> 0 | R51: =SUMIFS('Combined P&L'!P:P,'Combined P&L'!$C:$C,'P&L Forecast'!$B51) -> 0 | S51: =SUMIFS('Combined P&L'!Q:Q,'Combined P&L'!$C:$C,'P&L Forecast'!$B51) -> 0 | T51: =SUMIFS('Combined P&L'!R:R,'Combined P&L'!$C:$C,'P&L Forecast'!$B51) -> 0 | U51: =SUMIFS('Combined P&L'!S:S,'Combined P&L'!$C:$C,'P&L Forecast'!$B51) -> 0 | V51: =SUMIFS('Combined P&L'!T:T,'Combined P&L'!$C:$C,'P&L Forecast'!$B51) -> 0 | W51: =SUMIFS('Combined P&L'!U:U,'Combined P&L'!$C:$C,'P&L Forecast'!$B51) -> 0 | X51: =SUMIFS('Combined P&L'!V:V,'Combined P&L'!$C:$C,'P&L Forecast'!$B51) -> 0 | Y51: =SUMIFS('Combined P&L'!W:W,'Combined P&L'!$C:$C,'P&L Forecast'!$B51) -> 0 | Z51: =SUMIFS('Combined P&L'!X:X,'Combined P&L'!$C:$C,'P&L Forecast'!$B51) -> 0 | AA51: =SUMIFS('Combined P&L'!Y:Y,'Combined P&L'!$C:$C,'P&L Forecast'!$B51) -> 6.673 | AB51: =SUMIFS('Combined P&L'!Z:Z,'Combined P&L'!$C:$C,'P&L Forecast'!$B51) -> 0 | AC51: =SUMIFS('Combined P&L'!AA:AA,'Combined P&L'!$C:$C,'P&L Forecast'!$B51) -> 0 | AD51: =SUMIFS('Combined P&L'!AB:AB,'Combined P&L'!$C:$C,'P&L Forecast'!$B51) -> 0 | AE51: =SUMIFS('Combined P&L'!AC:AC,'Combined P&L'!$C:$C,'P&L Forecast'!$B51) -> 0 | AF51: =SUMIFS('Combined P&L'!AD:AD,'Combined P&L'!$C:$C,'P&L Forecast'!$B51) -> 0 | AG51: =SUMIFS('Combined P&L'!AE:AE,'Combined P&L'!$C:$C,'P&L Forecast'!$B51) -> 0 | AH51: =SUMIFS('Combined P&L'!AF:AF,'Combined P&L'!$C:$C,'P&L Forecast'!$B51) -> 0 | AI51: =SUMIFS('Combined P&L'!AG:AG,'Combined P&L'!$C:$C,'P&L Forecast'!$B51) -> 0 | AJ51: =SUMIFS('Combined P&L'!AH:AH,'Combined P&L'!$C:$C,'P&L Forecast'!$B51) -> 0 | AK51: =SUMIFS('Combined P&L'!AI:AI,'Combined P&L'!$C:$C,'P&L Forecast'!$B51) -> 0 | AL51: =SUMIFS('Combined P&L'!AJ:AJ,'Combined P&L'!$C:$C,'P&L Forecast'!$B51) -> 0 | AM51: =SUMIFS('Combined P&L'!AK:AK,'Combined P&L'!$C:$C,'P&L Forecast'!$B51) -> 6.673 | AN51: =SUMIFS('Combined P&L'!AL:AL,'Combined P&L'!$C:$C,'P&L Forecast'!$B51) -> 0 | AO51: =SUMIFS('Combined P&L'!AM:AM,'Combined P&L'!$C:$C,'P&L Forecast'!$B51) -> 0 | AP51: =SUMIFS('Combined P&L'!AN:AN,'Combined P&L'!$C:$C,'P&L Forecast'!$B51) -> 0 | AQ51: =SUMIFS('Combined P&L'!AO:AO,'Combined P&L'!$C:$C,'P&L Forecast'!$B51) -> 0 | AR51: =SUMIFS('Combined P&L'!AP:AP,'Combined P&L'!$C:$C,'P&L Forecast'!$B51) -> 0 | AS51: =SUMIFS('Combined P&L'!AQ:AQ,'Combined P&L'!$C:$C,'P&L Forecast'!$B51) -> 0 | AT51: =SUMIFS('Combined P&L'!AR:AR,'Combined P&L'!$C:$C,'P&L Forecast'!$B51) -> 0
B52: Website | C52: =SUMIFS($P52:$AT52,$P$5:$AT$5,">"&C$172,$P$5:$AT$5,"<"&C$173) -> 7.26173 | D52: =SUMIFS($P52:$AT52,$P$5:$AT$5,">"&D$172,$P$5:$AT$5,"<"&D$173) -> 4.91967 | F52: =SUMIFS($P52:$AT52,$P$5:$AT$5,">"&F$172,$P$5:$AT$5,"<"&F$173) -> 2.92467 | G52: =SUMIFS($P52:$AT52,$P$5:$AT$5,">"&G$172,$P$5:$AT$5,"<"&G$173) -> 2.90857 | I52: =SUMIFS($P52:$AT52,$P$5:$AT$5,">"&I$172,$P$5:$AT$5,"<"&I$173) -> 5.83631 | J52: =SUMIFS($P52:$AT52,$P$5:$AT$5,">"&J$172,$P$5:$AT$5,"<"&J$173) -> 4.90357 | K52: =+C154 -> 4.90357 | M52: =+J52-K52 -> 0 | N52: =IFERROR(K52/J52-1,0) -> 0 | P52: =SUMIFS('Combined P&L'!N:N,'Combined P&L'!$C:$C,'P&L Forecast'!$B52) -> 0.43326 | Q52: =SUMIFS('Combined P&L'!O:O,'Combined P&L'!$C:$C,'P&L Forecast'!$B52) -> 1.63176 | R52: =SUMIFS('Combined P&L'!P:P,'Combined P&L'!$C:$C,'P&L Forecast'!$B52) -> 0.43368 | S52: =SUMIFS('Combined P&L'!Q:Q,'Combined P&L'!$C:$C,'P&L Forecast'!$B52) -> 0.48413 | T52: =SUMIFS('Combined P&L'!R:R,'Combined P&L'!$C:$C,'P&L Forecast'!$B52) -> 0.48413 | U52: =SUMIFS('Combined P&L'!S:S,'Combined P&L'!$C:$C,'P&L Forecast'!$B52) -> 0.48413 | V52: =SUMIFS('Combined P&L'!T:T,'Combined P&L'!$C:$C,'P&L Forecast'!$B52) -> 0.49344 | W52: =SUMIFS('Combined P&L'!U:U,'Combined P&L'!$C:$C,'P&L Forecast'!$B52) -> 0.84344 | X52: =SUMIFS('Combined P&L'!V:V,'Combined P&L'!$C:$C,'P&L Forecast'!$B52) -> 0.49344 | Y52: =SUMIFS('Combined P&L'!W:W,'Combined P&L'!$C:$C,'P&L Forecast'!$B52) -> 0.49344 | Z52: =SUMIFS('Combined P&L'!X:X,'Combined P&L'!$C:$C,'P&L Forecast'!$B52) -> 0.49344 | AA52: =SUMIFS('Combined P&L'!Y:Y,'Combined P&L'!$C:$C,'P&L Forecast'!$B52) -> 0.49344 | AB52: =SUMIFS('Combined P&L'!Z:Z,'Combined P&L'!$C:$C,'P&L Forecast'!$B52) -> 0.53067 | AC52: =SUMIFS('Combined P&L'!AA:AA,'Combined P&L'!$C:$C,'P&L Forecast'!$B52) -> 0.399 | AD52: =SUMIFS('Combined P&L'!AB:AB,'Combined P&L'!$C:$C,'P&L Forecast'!$B52) -> 0.399 | AE52: =SUMIFS('Combined P&L'!AC:AC,'Combined P&L'!$C:$C,'P&L Forecast'!$B52) -> 0.399 | AF52: =SUMIFS('Combined P&L'!AD:AD,'Combined P&L'!$C:$C,'P&L Forecast'!$B52) -> 0.399 | AG52: =SUMIFS('Combined P&L'!AE:AE,'Combined P&L'!$C:$C,'P&L Forecast'!$B52) -> 0.399 | AH52: =SUMIFS('Combined P&L'!AF:AF,'Combined P&L'!$C:$C,'P&L Forecast'!$B52) -> 0.399 | AI52: =SUMIFS('Combined P&L'!AG:AG,'Combined P&L'!$C:$C,'P&L Forecast'!$B52) -> 0.399 | AJ52: =SUMIFS('Combined P&L'!AH:AH,'Combined P&L'!$C:$C,'P&L Forecast'!$B52) -> 0.399 | AK52: =SUMIFS('Combined P&L'!AI:AI,'Combined P&L'!$C:$C,'P&L Forecast'!$B52) -> 0.399 | AL52: =SUMIFS('Combined P&L'!AJ:AJ,'Combined P&L'!$C:$C,'P&L Forecast'!$B52) -> 0.399 | AM52: =SUMIFS('Combined P&L'!AK:AK,'Combined P&L'!$C:$C,'P&L Forecast'!$B52) -> 0.399 | AN52: =SUMIFS('Combined P&L'!AL:AL,'Combined P&L'!$C:$C,'P&L Forecast'!$B52) -> 0.43619 | AO52: =SUMIFS('Combined P&L'!AM:AM,'Combined P&L'!$C:$C,'P&L Forecast'!$B52) -> 0.399 | AP52: =SUMIFS('Combined P&L'!AN:AN,'Combined P&L'!$C:$C,'P&L Forecast'!$B52) -> 0.47738 | AQ52: =SUMIFS('Combined P&L'!AO:AO,'Combined P&L'!$C:$C,'P&L Forecast'!$B52) -> 0.399 | AR52: =SUMIFS('Combined P&L'!AP:AP,'Combined P&L'!$C:$C,'P&L Forecast'!$B52) -> 0.399 | AS52: =SUMIFS('Combined P&L'!AQ:AQ,'Combined P&L'!$C:$C,'P&L Forecast'!$B52) -> 0.399 | AT52: =SUMIFS('Combined P&L'!AR:AR,'Combined P&L'!$C:$C,'P&L Forecast'!$B52) -> 0.399
B53: State Taxes | C53: =SUMIFS($P53:$AT53,$P$5:$AT$5,">"&C$172,$P$5:$AT$5,"<"&C$173) -> 7.497 | D53: =SUMIFS($P53:$AT53,$P$5:$AT$5,">"&D$172,$P$5:$AT$5,"<"&D$173) -> 9.984 | F53: =SUMIFS($P53:$AT53,$P$5:$AT$5,">"&F$172,$P$5:$AT$5,"<"&F$173) -> 5.894 | G53: =SUMIFS($P53:$AT53,$P$5:$AT$5,">"&G$172,$P$5:$AT$5,"<"&G$173) -> 1.172 | I53: =SUMIFS($P53:$AT53,$P$5:$AT$5,">"&I$172,$P$5:$AT$5,"<"&I$173) -> 4.673 | J53: =SUMIFS($P53:$AT53,$P$5:$AT$5,">"&J$172,$P$5:$AT$5,"<"&J$173) -> 5.262 | K53: =+C155 -> 5.262 | M53: =+J53-K53 -> 0 | N53: =IFERROR(K53/J53-1,0) -> 0 | P53: =SUMIFS('Combined P&L'!N:N,'Combined P&L'!$C:$C,'P&L Forecast'!$B53) -> 0 | Q53: =SUMIFS('Combined P&L'!O:O,'Combined P&L'!$C:$C,'P&L Forecast'!$B53) -> 0 | R53: =SUMIFS('Combined P&L'!P:P,'Combined P&L'!$C:$C,'P&L Forecast'!$B53) -> 0 | S53: =SUMIFS('Combined P&L'!Q:Q,'Combined P&L'!$C:$C,'P&L Forecast'!$B53) -> 6.246 | T53: =SUMIFS('Combined P&L'!R:R,'Combined P&L'!$C:$C,'P&L Forecast'!$B53) -> 0 | U53: =SUMIFS('Combined P&L'!S:S,'Combined P&L'!$C:$C,'P&L Forecast'!$B53) -> 2.472 | V53: =SUMIFS('Combined P&L'!T:T,'Combined P&L'!$C:$C,'P&L Forecast'!$B53) -> 0 | W53: =SUMIFS('Combined P&L'!U:U,'Combined P&L'!$C:$C,'P&L Forecast'!$B53) -> 0 | X53: =SUMIFS('Combined P&L'!V:V,'Combined P&L'!$C:$C,'P&L Forecast'!$B53) -> 2.472 | Y53: =SUMIFS('Combined P&L'!W:W,'Combined P&L'!$C:$C,'P&L Forecast'!$B53) -> 0 | Z53: =SUMIFS('Combined P&L'!X:X,'Combined P&L'!$C:$C,'P&L Forecast'!$B53) -> 0 | AA53: =SUMIFS('Combined P&L'!Y:Y,'Combined P&L'!$C:$C,'P&L Forecast'!$B53) -> -3.693 | AB53: =SUMIFS('Combined P&L'!Z:Z,'Combined P&L'!$C:$C,'P&L Forecast'!$B53) -> 2.472 | AC53: =SUMIFS('Combined P&L'!AA:AA,'Combined P&L'!$C:$C,'P&L Forecast'!$B53) -> 0 | AD53: =SUMIFS('Combined P&L'!AB:AB,'Combined P&L'!$C:$C,'P&L Forecast'!$B53) -> 0 | AE53: =SUMIFS('Combined P&L'!AC:AC,'Combined P&L'!$C:$C,'P&L Forecast'!$B53) -> 3.649 | AF53: =SUMIFS('Combined P&L'!AD:AD,'Combined P&L'!$C:$C,'P&L Forecast'!$B53) -> -2.272 | AG53: =SUMIFS('Combined P&L'!AE:AE,'Combined P&L'!$C:$C,'P&L Forecast'!$B53) -> 2.045 | AH53: =SUMIFS('Combined P&L'!AF:AF,'Combined P&L'!$C:$C,'P&L Forecast'!$B53) -> 0 | AI53: =SUMIFS('Combined P&L'!AG:AG,'Combined P&L'!$C:$C,'P&L Forecast'!$B53) -> 0 | AJ53: =SUMIFS('Combined P&L'!AH:AH,'Combined P&L'!$C:$C,'P&L Forecast'!$B53) -> 2.045 | AK53: =SUMIFS('Combined P&L'!AI:AI,'Combined P&L'!$C:$C,'P&L Forecast'!$B53) -> 0 | AL53: =SUMIFS('Combined P&L'!AJ:AJ,'Combined P&L'!$C:$C,'P&L Forecast'!$B53) -> 0 | AM53: =SUMIFS('Combined P&L'!AK:AK,'Combined P&L'!$C:$C,'P&L Forecast'!$B53) -> 2.045 | AN53: =SUMIFS('Combined P&L'!AL:AL,'Combined P&L'!$C:$C,'P&L Forecast'!$B53) -> 0 | AO53: =SUMIFS('Combined P&L'!AM:AM,'Combined P&L'!$C:$C,'P&L Forecast'!$B53) -> 0 | AP53: =SUMIFS('Combined P&L'!AN:AN,'Combined P&L'!$C:$C,'P&L Forecast'!$B53) -> 5.036 | AQ53: =SUMIFS('Combined P&L'!AO:AO,'Combined P&L'!$C:$C,'P&L Forecast'!$B53) -> -4.864 | AR53: =SUMIFS('Combined P&L'!AP:AP,'Combined P&L'!$C:$C,'P&L Forecast'!$B53) -> 0 | AS53: =SUMIFS('Combined P&L'!AQ:AQ,'Combined P&L'!$C:$C,'P&L Forecast'!$B53) -> 1 | AT53: =SUMIFS('Combined P&L'!AR:AR,'Combined P&L'!$C:$C,'P&L Forecast'!$B53) -> 0
B54: Insurance | C54: =SUMIFS($P54:$AT54,$P$5:$AT$5,">"&C$172,$P$5:$AT$5,"<"&C$173) -> 2.08994 | D54: =SUMIFS($P54:$AT54,$P$5:$AT$5,">"&D$172,$P$5:$AT$5,"<"&D$173) -> 2.61982 | F54: =SUMIFS($P54:$AT54,$P$5:$AT$5,">"&F$172,$P$5:$AT$5,"<"&F$173) -> 1.44049 | G54: =SUMIFS($P54:$AT54,$P$5:$AT$5,">"&G$172,$P$5:$AT$5,"<"&G$173) -> 3.70971 | I54: =SUMIFS($P54:$AT54,$P$5:$AT$5,">"&I$172,$P$5:$AT$5,"<"&I$173) -> 2.28315 | J54: =SUMIFS($P54:$AT54,$P$5:$AT$5,">"&J$172,$P$5:$AT$5,"<"&J$173) -> 4.89769 | K54: =+C156 -> 4.89769 | M54: =+J54-K54 -> 0 | N54: =IFERROR(K54/J54-1,0) -> 0 | P54: =SUMIFS('Combined P&L'!N:N,'Combined P&L'!$C:$C,'P&L Forecast'!$B54) -> 0.14747 | Q54: =SUMIFS('Combined P&L'!O:O,'Combined P&L'!$C:$C,'P&L Forecast'!$B54) -> 0.14747 | R54: =SUMIFS('Combined P&L'!P:P,'Combined P&L'!$C:$C,'P&L Forecast'!$B54) -> 0.17755 | S54: =SUMIFS('Combined P&L'!Q:Q,'Combined P&L'!$C:$C,'P&L Forecast'!$B54) -> 0.19167 | T54: =SUMIFS('Combined P&L'!R:R,'Combined P&L'!$C:$C,'P&L Forecast'!$B54) -> 0.18014 | U54: =SUMIFS('Combined P&L'!S:S,'Combined P&L'!$C:$C,'P&L Forecast'!$B54) -> 0.17622 | V54: =SUMIFS('Combined P&L'!T:T,'Combined P&L'!$C:$C,'P&L Forecast'!$B54) -> 0.1762 | W54: =SUMIFS('Combined P&L'!U:U,'Combined P&L'!$C:$C,'P&L Forecast'!$B54) -> 0.17622 | X54: =SUMIFS('Combined P&L'!V:V,'Combined P&L'!$C:$C,'P&L Forecast'!$B54) -> 0.18712 | Y54: =SUMIFS('Combined P&L'!W:W,'Combined P&L'!$C:$C,'P&L Forecast'!$B54) -> 0.17744 | Z54: =SUMIFS('Combined P&L'!X:X,'Combined P&L'!$C:$C,'P&L Forecast'!$B54) -> 0.17622 | AA54: =SUMIFS('Combined P&L'!Y:Y,'Combined P&L'!$C:$C,'P&L Forecast'!$B54) -> 0.17622 | AB54: =SUMIFS('Combined P&L'!Z:Z,'Combined P&L'!$C:$C,'P&L Forecast'!$B54) -> 0.17678 | AC54: =SUMIFS('Combined P&L'!AA:AA,'Combined P&L'!$C:$C,'P&L Forecast'!$B54) -> 0.20899 | AD54: =SUMIFS('Combined P&L'!AB:AB,'Combined P&L'!$C:$C,'P&L Forecast'!$B54) -> 0.1896 | AE54: =SUMIFS('Combined P&L'!AC:AC,'Combined P&L'!$C:$C,'P&L Forecast'!$B54) -> 0.1759 | AF54: =SUMIFS('Combined P&L'!AD:AD,'Combined P&L'!$C:$C,'P&L Forecast'!$B54) -> 0.2357 | AG54: =SUMIFS('Combined P&L'!AE:AE,'Combined P&L'!$C:$C,'P&L Forecast'!$B54) -> 0.22676 | AH54: =SUMIFS('Combined P&L'!AF:AF,'Combined P&L'!$C:$C,'P&L Forecast'!$B54) -> 0.22676 | AI54: =SUMIFS('Combined P&L'!AG:AG,'Combined P&L'!$C:$C,'P&L Forecast'!$B54) -> 0.22676 | AJ54: =SUMIFS('Combined P&L'!AH:AH,'Combined P&L'!$C:$C,'P&L Forecast'!$B54) -> 0.24325 | AK54: =SUMIFS('Combined P&L'!AI:AI,'Combined P&L'!$C:$C,'P&L Forecast'!$B54) -> 0.24228 | AL54: =SUMIFS('Combined P&L'!AJ:AJ,'Combined P&L'!$C:$C,'P&L Forecast'!$B54) -> 0.23352 | AM54: =SUMIFS('Combined P&L'!AK:AK,'Combined P&L'!$C:$C,'P&L Forecast'!$B54) -> 0.23352 | AN54: =SUMIFS('Combined P&L'!AL:AL,'Combined P&L'!$C:$C,'P&L Forecast'!$B54) -> 0.22943 | AO54: =SUMIFS('Combined P&L'!AM:AM,'Combined P&L'!$C:$C,'P&L Forecast'!$B54) -> 2.22858 | AP54: =SUMIFS('Combined P&L'!AN:AN,'Combined P&L'!$C:$C,'P&L Forecast'!$B54) -> 0.25448 | AQ54: =SUMIFS('Combined P&L'!AO:AO,'Combined P&L'!$C:$C,'P&L Forecast'!$B54) -> 0.25564 | AR54: =SUMIFS('Combined P&L'!AP:AP,'Combined P&L'!$C:$C,'P&L Forecast'!$B54) -> 0.26164 | AS54: =SUMIFS('Combined P&L'!AQ:AQ,'Combined P&L'!$C:$C,'P&L Forecast'!$B54) -> 0.26183 | AT54: =SUMIFS('Combined P&L'!AR:AR,'Combined P&L'!$C:$C,'P&L Forecast'!$B54) -> 0.21811
B55: Occupancy Tax Filing Fees | C55: =SUMIFS($P55:$AT55,$P$5:$AT$5,">"&C$172,$P$5:$AT$5,"<"&C$173) -> 0 | D55: =SUMIFS($P55:$AT55,$P$5:$AT$5,">"&D$172,$P$5:$AT$5,"<"&D$173) -> 1.75591 | F55: =SUMIFS($P55:$AT55,$P$5:$AT$5,">"&F$172,$P$5:$AT$5,"<"&F$173) -> 0.53895 | G55: =SUMIFS($P55:$AT55,$P$5:$AT$5,">"&G$172,$P$5:$AT$5,"<"&G$173) -> 1.53949 | I55: =SUMIFS($P55:$AT55,$P$5:$AT$5,">"&I$172,$P$5:$AT$5,"<"&I$173) -> 0.37925 | J55: =SUMIFS($P55:$AT55,$P$5:$AT$5,">"&J$172,$P$5:$AT$5,"<"&J$173) -> 2.20859 | K55: =+C157 -> 3.516 | M55: =+J55-K55 -> -1.30741 | N55: =IFERROR(K55/J55-1,0) -> 0.59196591 | P55: =SUMIFS('Combined P&L'!N:N,'Combined P&L'!$C:$C,'P&L Forecast'!$B55) -> 0 | Q55: =SUMIFS('Combined P&L'!O:O,'Combined P&L'!$C:$C,'P&L Forecast'!$B55) -> 0 | R55: =SUMIFS('Combined P&L'!P:P,'Combined P&L'!$C:$C,'P&L Forecast'!$B55) -> 0 | S55: =SUMIFS('Combined P&L'!Q:Q,'Combined P&L'!$C:$C,'P&L Forecast'!$B55) -> 0 | T55: =SUMIFS('Combined P&L'!R:R,'Combined P&L'!$C:$C,'P&L Forecast'!$B55) -> 0 | U55: =SUMIFS('Combined P&L'!S:S,'Combined P&L'!$C:$C,'P&L Forecast'!$B55) -> 0 | V55: =SUMIFS('Combined P&L'!T:T,'Combined P&L'!$C:$C,'P&L Forecast'!$B55) -> 0 | W55: =SUMIFS('Combined P&L'!U:U,'Combined P&L'!$C:$C,'P&L Forecast'!$B55) -> 0 | X55: =SUMIFS('Combined P&L'!V:V,'Combined P&L'!$C:$C,'P&L Forecast'!$B55) -> 0 | Y55: =SUMIFS('Combined P&L'!W:W,'Combined P&L'!$C:$C,'P&L Forecast'!$B55) -> 0 | Z55: =SUMIFS('Combined P&L'!X:X,'Combined P&L'!$C:$C,'P&L Forecast'!$B55) -> 0 | AA55: =SUMIFS('Combined P&L'!Y:Y,'Combined P&L'!$C:$C,'P&L Forecast'!$B55) -> 0 | AB55: =SUMIFS('Combined P&L'!Z:Z,'Combined P&L'!$C:$C,'P&L Forecast'!$B55) -> 0.1 | AC55: =SUMIFS('Combined P&L'!AA:AA,'Combined P&L'!$C:$C,'P&L Forecast'!$B55) -> 0 | AD55: =SUMIFS('Combined P&L'!AB:AB,'Combined P&L'!$C:$C,'P&L Forecast'!$B55) -> 0 | AE55: =SUMIFS('Combined P&L'!AC:AC,'Combined P&L'!$C:$C,'P&L Forecast'!$B55) -> 0.1498 | AF55: =SUMIFS('Combined P&L'!AD:AD,'Combined P&L'!$C:$C,'P&L Forecast'!$B55) -> 0.05975 | AG55: =SUMIFS('Combined P&L'!AE:AE,'Combined P&L'!$C:$C,'P&L Forecast'!$B55) -> 0.0697 | AH55: =SUMIFS('Combined P&L'!AF:AF,'Combined P&L'!$C:$C,'P&L Forecast'!$B55) -> 0.1597 | AI55: =SUMIFS('Combined P&L'!AG:AG,'Combined P&L'!$C:$C,'P&L Forecast'!$B55) -> 0.31085 | AJ55: =SUMIFS('Combined P&L'!AH:AH,'Combined P&L'!$C:$C,'P&L Forecast'!$B55) -> 0.46751 | AK55: =SUMIFS('Combined P&L'!AI:AI,'Combined P&L'!$C:$C,'P&L Forecast'!$B55) -> 0.51751 | AL55: =SUMIFS('Combined P&L'!AJ:AJ,'Combined P&L'!$C:$C,'P&L Forecast'!$B55) -> -0.18841 | AM55: =SUMIFS('Combined P&L'!AK:AK,'Combined P&L'!$C:$C,'P&L Forecast'!$B55) -> 0.1095 | AN55: =SUMIFS('Combined P&L'!AL:AL,'Combined P&L'!$C:$C,'P&L Forecast'!$B55) -> 0.2294 | AO55: =SUMIFS('Combined P&L'!AM:AM,'Combined P&L'!$C:$C,'P&L Forecast'!$B55) -> 0.1194 | AP55: =SUMIFS('Combined P&L'!AN:AN,'Combined P&L'!$C:$C,'P&L Forecast'!$B55) -> 0.17935 | AQ55: =SUMIFS('Combined P&L'!AO:AO,'Combined P&L'!$C:$C,'P&L Forecast'!$B55) -> 0.0699 | AR55: =SUMIFS('Combined P&L'!AP:AP,'Combined P&L'!$C:$C,'P&L Forecast'!$B55) -> 0.0699 | AS55: =SUMIFS('Combined P&L'!AQ:AQ,'Combined P&L'!$C:$C,'P&L Forecast'!$B55) -> 0.16398 | AT55: =SUMIFS('Combined P&L'!AR:AR,'Combined P&L'!$C:$C,'P&L Forecast'!$B55) -> 0.70756
B56: Utilities | C56: =SUMIFS($P56:$AT56,$P$5:$AT$5,">"&C$172,$P$5:$AT$5,"<"&C$173) -> 1.05983 | D56: =SUMIFS($P56:$AT56,$P$5:$AT$5,">"&D$172,$P$5:$AT$5,"<"&D$173) -> 3.29133 | F56: =SUMIFS($P56:$AT56,$P$5:$AT$5,">"&F$172,$P$5:$AT$5,"<"&F$173) -> 2.02633 | G56: =SUMIFS($P56:$AT56,$P$5:$AT$5,">"&G$172,$P$5:$AT$5,"<"&G$173) -> 1.943 | I56: =SUMIFS($P56:$AT56,$P$5:$AT$5,">"&I$172,$P$5:$AT$5,"<"&I$173) -> 2.28333 | J56: =SUMIFS($P56:$AT56,$P$5:$AT$5,">"&J$172,$P$5:$AT$5,"<"&J$173) -> 3.168 | K56: =+C158 -> 3.168 | M56: =+J56-K56 -> 0 | N56: =IFERROR(K56/J56-1,0) -> 0 | P56: =SUMIFS('Combined P&L'!N:N,'Combined P&L'!$C:$C,'P&L Forecast'!$B56) -> 0.085 | Q56: =SUMIFS('Combined P&L'!O:O,'Combined P&L'!$C:$C,'P&L Forecast'!$B56) -> 0.085 | R56: =SUMIFS('Combined P&L'!P:P,'Combined P&L'!$C:$C,'P&L Forecast'!$B56) -> 0.097 | S56: =SUMIFS('Combined P&L'!Q:Q,'Combined P&L'!$C:$C,'P&L Forecast'!$B56) -> 0.11283 | T56: =SUMIFS('Combined P&L'!R:R,'Combined P&L'!$C:$C,'P&L Forecast'!$B56) -> 0.085 | U56: =SUMIFS('Combined P&L'!S:S,'Combined P&L'!$C:$C,'P&L Forecast'!$B56) -> 0.085 | V56: =SUMIFS('Combined P&L'!T:T,'Combined P&L'!$C:$C,'P&L Forecast'!$B56) -> 0.085 | W56: =SUMIFS('Combined P&L'!U:U,'Combined P&L'!$C:$C,'P&L Forecast'!$B56) -> 0.085 | X56: =SUMIFS('Combined P&L'!V:V,'Combined P&L'!$C:$C,'P&L Forecast'!$B56) -> 0.085 | Y56: =SUMIFS('Combined P&L'!W:W,'Combined P&L'!$C:$C,'P&L Forecast'!$B56) -> 0.085 | Z56: =SUMIFS('Combined P&L'!X:X,'Combined P&L'!$C:$C,'P&L Forecast'!$B56) -> 0.085 | AA56: =SUMIFS('Combined P&L'!Y:Y,'Combined P&L'!$C:$C,'P&L Forecast'!$B56) -> 0.085 | AB56: =SUMIFS('Combined P&L'!Z:Z,'Combined P&L'!$C:$C,'P&L Forecast'!$B56) -> 0.085 | AC56: =SUMIFS('Combined P&L'!AA:AA,'Combined P&L'!$C:$C,'P&L Forecast'!$B56) -> 0.09449 | AD56: =SUMIFS('Combined P&L'!AB:AB,'Combined P&L'!$C:$C,'P&L Forecast'!$B56) -> 0.82489 | AE56: =SUMIFS('Combined P&L'!AC:AC,'Combined P&L'!$C:$C,'P&L Forecast'!$B56) -> 0.253 | AF56: =SUMIFS('Combined P&L'!AD:AD,'Combined P&L'!$C:$C,'P&L Forecast'!$B56) -> 0.26295 | AG56: =SUMIFS('Combined P&L'!AE:AE,'Combined P&L'!$C:$C,'P&L Forecast'!$B56) -> 0.253 | AH56: =SUMIFS('Combined P&L'!AF:AF,'Combined P&L'!$C:$C,'P&L Forecast'!$B56) -> 0.253 | AI56: =SUMIFS('Combined P&L'!AG:AG,'Combined P&L'!$C:$C,'P&L Forecast'!$B56) -> 0.253 | AJ56: =SUMIFS('Combined P&L'!AH:AH,'Combined P&L'!$C:$C,'P&L Forecast'!$B56) -> 0.253 | AK56: =SUMIFS('Combined P&L'!AI:AI,'Combined P&L'!$C:$C,'P&L Forecast'!$B56) -> 0.253 | AL56: =SUMIFS('Combined P&L'!AJ:AJ,'Combined P&L'!$C:$C,'P&L Forecast'!$B56) -> 0.253 | AM56: =SUMIFS('Combined P&L'!AK:AK,'Combined P&L'!$C:$C,'P&L Forecast'!$B56) -> 0.253 | AN56: =SUMIFS('Combined P&L'!AL:AL,'Combined P&L'!$C:$C,'P&L Forecast'!$B56) -> 0.253 | AO56: =SUMIFS('Combined P&L'!AM:AM,'Combined P&L'!$C:$C,'P&L Forecast'!$B56) -> 0.255 | AP56: =SUMIFS('Combined P&L'!AN:AN,'Combined P&L'!$C:$C,'P&L Forecast'!$B56) -> 0.283 | AQ56: =SUMIFS('Combined P&L'!AO:AO,'Combined P&L'!$C:$C,'P&L Forecast'!$B56) -> 0.283 | AR56: =SUMIFS('Combined P&L'!AP:AP,'Combined P&L'!$C:$C,'P&L Forecast'!$B56) -> 0.283 | AS56: =SUMIFS('Combined P&L'!AQ:AQ,'Combined P&L'!$C:$C,'P&L Forecast'!$B56) -> 0.293 | AT56: =SUMIFS('Combined P&L'!AR:AR,'Combined P&L'!$C:$C,'P&L Forecast'!$B56) -> 0.293
