Workbook

Sheet Cover
B24: Keystone Bookkeepers
B25: Pre-LOI Business Analysis
B26: ="As of "&TEXT(TODAY(),"mm/dd/yy") -> As of 09/24/26

Sheet Offer Overview
B2: =Cover!$B$24 -> Keystone Bookkeepers
B3: Offer & Equity Upside Scenarios ($000s) | G3: Print | H3: 1
B5: Offer Breakdown | C5: Today
B6: Recurring Revenue (PF Jul'26) | C6: ='Revenue Analysis'!$E$16 -> 2942.9433
B7: (x) Revenue Multiple — Implied | C7: =IFERROR($C$8/$C$6,0) -> 1.0193876
B8: Total Valuation — Offer Price | C8: 3000
B9: (-) Cash at Close | C9: 500
B10: Topkey Equity Consideration | C10: =C8-C9 -> 2500
B12: Topkey Pre-Deal Valuation | C12: 60000
B13: (+) Keystone Value Acquired | C13: =$C$8 -> 3000
B14: (-) Cash Paid at Close | C14: =$C$9 -> 500
B15: Topkey Post-Money Valuation | C15: =C12+C13-C14 -> 62500
B16: Ben's Implied Topkey Ownership % | C16: =IFERROR($C$10/$C$15,0) -> 0.04
B17: Keystone Enterprise Value Today | C17: =$C$8 -> 3000
B18: Existing Shareholders' Value Post-Close | C18: =(1-$C$16)*$C$15 -> 60000
B20: Topkey Pre-Deal Valuation | C20: =$C$12 -> 60000
B21: (-) Cash Paid at Close | C21: =$C$14 -> 500
B22: Topkey ex-Keystone Growth Base | C22: =C20-C21 -> 59500
B24: Scenario 1 — Ben Retains 100% of Keystone | C24: Today | D24: 2.0x Valuation | E24: 3.0x Valuation
B25: Keystone Growth Multiple | C25: 1 | D25: 2 | E25: 3
B26: Keystone Enterprise Value | C26: =$C$17*C$25 -> 3000 | D26: =$C$17*D$25 -> 6000 | E26: =$C$17*E$25 -> 9000
B27: Ben's Ownership % — Keystone | C27: 1 | D27: =$C$27 -> 1 | E27: =$C$27 -> 1
B28: Ben's Keystone Equity Value | C28: =C26*$C$27 -> 3000 | D28: =D26*$C$27 -> 6000 | E28: =E26*$C$27 -> 9000
B29: (-) Value at Offer Today | C29: =$C$28 -> 3000 | D29: =$C$28 -> 3000 | E29: =$C$28 -> 3000
B30: Ben's Net Gain vs. Today | C30: =C28-C29 -> 0 | D30: =D28-D29 -> 3000 | E30: =E28-E29 -> 6000
B32: Combined Topkey + Keystone TEV | C32: Growth (ex-Keystone) | D32: =D$24 -> 2.0x Valuation | E32: =E$24 -> 3.0x Valuation
B33: Topkey Grows Half as Fast as Keystone | C33: 0.5 | D33: =$C$22*(1+(D$25-1)*$C33)+$C$17*D$25 -> 95250 | E33: =$C$22*(1+(E$25-1)*$C33)+$C$17*E$25 -> 128000
B34: Topkey Keeps Pace with Keystone | C34: 1 | D34: =$C$22*(1+(D$25-1)*$C34)+$C$17*D$25 -> 125000 | E34: =$C$22*(1+(E$25-1)*$C34)+$C$17*E$25 -> 187500
B35: Topkey Outgrows Keystone | C35: 1.5 | D35: =$C$22*(1+(D$25-1)*$C35)+$C$17*D$25 -> 154750 | E35: =$C$22*(1+(E$25-1)*$C35)+$C$17*E$25 -> 247000
B37: Ben's Total Value — Cash + Topkey Equity | D37: =+D$32 -> 2.0x Valuation | E37: =+E$32 -> 3.0x Valuation
B38: =$B33 -> Topkey Grows Half as Fast as Keystone | D38: =$C$9+$C$16*D33 -> 4310 | E38: =$C$9+$C$16*E33 -> 5620
B39: =$B34 -> Topkey Keeps Pace with Keystone | D39: =$C$9+$C$16*D34 -> 5500 | E39: =$C$9+$C$16*E34 -> 8000
B40: =$B35 -> Topkey Outgrows Keystone | D40: =$C$9+$C$16*D35 -> 6690 | E40: =$C$9+$C$16*E35 -> 10380
B42: Delta vs. Scenario 1 | D42: =+D$32 -> 2.0x Valuation | E42: =+E$32 -> 3.0x Valuation
B43: =$B33 -> Topkey Grows Half as Fast as Keystone | D43: =D38-D$28 -> -1690 | E43: =E38-E$28 -> -3380
B44: =$B34 -> Topkey Keeps Pace with Keystone | D44: =D39-D$28 -> -500 | E44: =E39-E$28 -> -1000
B45: =$B35 -> Topkey Outgrows Keystone | D45: =D40-D$28 -> 690 | E45: =E40-E$28 -> 1380
B47: Topkey Growth Required for Parity | D47: =+D$32 -> 2.0x Valuation | E47: =+E$32 -> 3.0x Valuation
B48: Ben's Value — Scenario 1 (Retain 100%) | D48: =D$28 -> 6000 | E48: =E$28 -> 9000
B49: (-) Ben's Cash at Close | D49: =$C$9 -> 500 | E49: =$C$9 -> 500
B50: Required Topkey Equity Value | D50: =D48-D49 -> 5500 | E50: =E48-E49 -> 8500
B51: Required Combined Enterprise Value | D51: =IFERROR(D50/$C$16,0) -> 137500 | E51: =IFERROR(E50/$C$16,0) -> 212500
B52: (-) Keystone Value at Growth | D52: =$C$17*D$25 -> 6000 | E52: =$C$17*E$25 -> 9000
B53: Required Topkey ex-Keystone Value | D53: =D51-D52 -> 131500 | E53: =E51-E52 -> 203500
B54: Required Growth Share for Ben to Break Even | D54: =IFERROR((D53/$C$22-1)/(D$25-1),0) -> 1.210084 | E54: =IFERROR((E53/$C$22-1)/(E$25-1),0) -> 1.210084
B56: Offer & Scenario Assumptions
B57: Assumption | C57: Value | D57: Rationale
B58: Recurring Revenue (PF Jul'26) ($000s) | C58: =$C$6 -> 2942.9433 | D58: PF Jul'26 total recurring revenue per Revenue Analysis
B59: Revenue Multiple | C59: =$C$7 -> 1.0193876 | D59: Implied by rounded offer ÷ PF Jul'26 RR
B60: Total Valuation — Offer Price ($000s) | C60: =$C$8 -> 3000 | D60: Rounded $3.0M offer price; Keystone value today
B61: Cash at Close ($000s) | C61: =$C$9 -> 500 | D61: Per Topkey offer; balance paid in Topkey equity
B62: Topkey Pre-Deal Valuation ($000s) | C62: =$C$12 -> 60000 | D62: Topkey stated valuation before Keystone; pending confirmation
B63: Ben's Keystone Ownership % | C63: =$C$27 -> 1 | D63: Sole owner; retains full upside in Scenario 1
B64: Topkey ex-Keystone Growth Share — Half Pace | C64: =$C$33 -> 0.5 | D64: Topkey ex-Keystone grows at half Keystone's rate
B65: Topkey ex-Keystone Growth Share — Keeps Pace | C65: =$C$34 -> 1 | D65: Topkey ex-Keystone grows at Keystone's rate
B66: Topkey ex-Keystone Growth Share — Outgrows | C66: =$C$35 -> 1.5 | D66: Default 1.5x Keystone's growth rate
B67: Valuation Growth Multiples | C67: =D$25&"x / "&E$25&"x" -> 2x / 3x | D67: Business doubles / triples in value
B68: Topkey ex-Keystone Growth Base ($000s) | C68: =$C$22 -> 59500 | D68: Pre-deal Topkey less the $500K cash paid to Ben
B69: Topkey Post-Money Valuation ($000s) | C69: =$C$15 -> 62500 | D69: Pre-deal + Keystone acquired − cash paid at close

Sheet 100% Buyout Analysis
B2: =Cover!$B$24 -> Keystone Bookkeepers
B3: Valuation Growth Scenarios ($000s) | G3: Print | H3: 1
B5: Revenue Growth Assumptions | C5: Value | F5: Rationale / Notes
B6: General Assumptions
B7: Horizon (Years) | C7: 5 | F7: Projection horizon for Year 5 columns
B8: Topkey - Current Monthly Revenue | C8: 261 | F8: Topkey-provided monthly revenue ($000s). Red: source pending confirmation
B9: Topkey - Current Run-Rate Revenue | C9: =C8*12 -> 3132
B10: Topkey - Current Revenue Multiple | C10: =IFERROR(C156/C9,0) -> 19.157088 | F10: Implied multiple: Topkey pre-deal valuation (C156) ÷ run-rate revenue (C9)
B11: Topkey - Future Revenue Multiple | C11: =C10 -> 19.157088 | F11: Assumed flat at current multiple
B12: Topkey - Current Client Count | C12: 325 | F12: Topkey-provided client count. Red: source pending confirmation
B13: Topkey - Avg. Revenue Per Client | C13: =C9/C12 -> 9.6369231
B14: Topkey - Annual Net Client Wins | C14: 130 | F14: AMB placeholder. Red: source pending confirmation
B15: Total Net Client Wins | C15: =C14*$C$7 -> 650
B16: Total Additional Revenue | C16: =C15*C13 -> 6264
B18: Keystone Standalone Assumptions
B19: Revenue Multiple | C19: 1 | F19: Keystone standalone valued at 1.0x revenue (offer implies ~1.02x)
B20: Scaled Revenue Multiple | C20: 1.25 | F20: Future revenue multiple for Keystone
B21: Avg. Revenue Per Client | C21: =+'Steady-State Staffing'!AB8 -> 16.631473 | F21: Sep'26 annualized fee per non-tax client (Steady-State Staffing AB8)
B22: Target Monthly Net Client Wins | C22: 3 | F22: Target pace per AMB; LTM actual is 26/yr (~2.2/month), see build at rows 163-168
B23: Annual Net Client Wins | C23: =C22*12 -> 36 | F23: Target monthly pace × 12
B24: Total Net Client Wins | C24: =C23*$C$7 -> 180
B25: Total Additional Revenue | C25: =C24*C21 -> 2993.6651
B27: Keystone Partnership Assumptions
B28: Software-Integration Revenue Multiple | C28: 3 | F28: Assumed revenue multiple for software-integrated partnership
B29: VR Platform Run-Rate Tech Cost | C29: 240 | F29: Run-rate tech cost provided by the target; memo only — VR savings assumed captured in the 25% partnership margin and revenue multiple
B31: =+B21 -> Avg. Revenue Per Client | C31: =+C21 -> 16.631473
B32: (+) Software-Enabled Price Increase / Client | C32: 0 | F32: Only if Topkey software supports higher client fees; VR platform cost no longer added to revenue per client
B33: Total Avg. Revenue Per Client | C33: =+C31+C32 -> 16.631473
B35: =+B23 -> Annual Net Client Wins | C35: =+C23 -> 36
B36: (+) Additional Annual Net Client Wins From Topkey | C36: 12 | F36: Topkey-provided. Red: source pending confirmation
B37: Total Annual Net Client Wins | C37: =SUM(C35:C36) -> 48
B38: Total Net Client Wins | C38: =C37*$C$7 -> 240
B39: Total Additional Revenue | C39: =C38*C33 -> 3991.5535
B40: Increase in Keystone Revenue vs. Standalone | C40: =C39-C25 -> 997.88838
B42: Cash Earnout — Year 3 Keystone Revenue (Sliding Scale)
B43: Earnout Measurement Year | C43: 3 | F43: Earnout measured on Year 3 run-rate: average of months 34–36 × 12 (see C54)
B44: Keystone Revenue at Close | C44: =C152 -> 2998.541 | F44: PF Jul'26 run-rate revenue at close (C152); unchanged
B45: Year 3 Run-Rate Revenue Target | C45: =C44+C39*(C43-(C54-1)/2/12)/C7 -> 5326.9472 | F45: Run-rate at close + partnership added revenue ramped to the midpoint of the averaging window (month 35 ÷ 60); same basis as the earnout measurement
B46: (x) Achievement vs. Target | C46: 1 | F46: Base case assumes the model's Year 3 revenue is achieved; flex to test payout
B47: Year 3 Run-Rate Revenue — Achieved | C47: =C45*C46 -> 5326.9472
B48: Threshold — % of Target | C48: 0.8 | F48: No earnout below this share of target; payout starts at the threshold % below
B49: Target Earnout — at 100% of Target | C49: 500 | F49: Opening ask: $500K at target (AMB internal range $750K–$1M)
B50: Payout at Threshold — % of Target Earnout | C50: 0.5 | F50: Share of target earnout paid at the 80% threshold
B51: Cap — % of Target Earnout | C51: 1.5 | F51: Payout capped at 120% of target, symmetric with the 80% threshold (50% at 80%, 150% at 120%)
B52: Payout % Earned | C52: =IF(C46<C48,0,MIN(C51,C50+(1-C50)*(C46-C48)/(1-C48))) -> 1 | F52: Straight line from threshold payout at 80% to 100% at target, continuing above target until the cap
B53: Maximum Earnout (Cap) | C53: =C49*C51 -> 750 | F53: Topkey's maximum earnout exposure
B54: Run-Rate Window — Months Averaged | C54: 3 | F54: Earnout measured on average monthly recurring revenue for the last 3 months of Year 3 (months 34–36) × 12; averaging prevents one strong month from triggering the payout
B55: Cash Earnout Payable — Year 3 | C55: =C49*C52 -> 500 | F55: Paid in cash by Topkey; flows into Scenario 2 (row 71), Ben's MOIC/IRR (rows 77-78) and Topkey's return (row 85)
B56: Probability of Achievement | C56: 0.7 | F56: AMB estimate for the memo line below
B57: Discount Rate | C57: 0.15 | F57: AMB estimate for the memo line below
B58: Risk-Weighted Earnout — PV at Close (Memo) | C58: =C55*C56/(1+C57)^C43 -> 230.13068 | F58: Memo only; not used in Scenario 2
B60: Scenario 1 — Ben Retains 100% of Keystone | C60: =C$151 -> Today | D60: ="Year "&$C$7 -> Year 5
B61: Keystone Enterprise Value | C61: =ROUND(C152*C19,-1) -> 3000 | D61: =(C152+C25)*$C$20 -> 7490.2577 | F61: Today at offer value; Year 5 = (PF run-rate revenue + standalone added revenue) x standalone multiple
B62: Ben's Ownership % — Keystone | C62: ='Offer Overview'!$C$27 -> 1 | D62: =$C$62 -> 1
B63: Ben's Value — Scenario 1 | C63: =C61*C62 -> 3000 | D63: =D61*D62 -> 7490.2577
B65: Scenario 2 — Ben Accepts the Topkey Offer | C65: =C$151 -> Today | D65: =D$60 -> Year 5
B66: Topkey ex-Keystone Value | C66: =C159 -> 59500 | D66: =(C9+C16)*C11-C154-$C$55 -> 179000
B67: (+) Keystone Value — Post-Acquisition | C67: =C61 -> 3000 | D67: =(C39+C152)*C28 -> 20970.284 | F67: Today at offer value (same as Scenario 1)
B68: Combined Enterprise Value | C68: =C66+C67 -> 62500 | D68: =D66+D67 -> 199970.28
B69: Ben's Topkey Equity Value | C69: =C68*$C$158 -> 2500 | D69: =D68*$C$158 -> 7998.8113
B70: (+) Cash at Close | C70: =$C$154 -> 500 | D70: =$C$154 -> 500
B71: (+) Cash Earnout — Year 3 | D71: =$C$55 -> 500
B72: Ben's Value — Scenario 2 | C72: =C69+C70+C71 -> 3000 | D72: =D69+D70+D71 -> 8998.8113
B74: Scenario 2 vs. Scenario 1 | C74: =C$151 -> Today | D74: =D$60 -> Year 5
B75: Increase in Proceeds | C75: =C72-C63 -> 0 | D75: =D72-D63 -> 1508.5536
B76: Delta (%) | C76: =IFERROR(C72/C63-1,0) -> 0 | D76: =IFERROR(D72/D63-1,0) -> 0.2014021
B77: Buyout MOIC — Keystone (Ben) | D77: =IFERROR(D72/C153,0) -> 2.9996038 | F77: Ben's Year 5 value (D72: cash + earnout + Topkey stock) ÷ Keystone value given up at close (C153)
B78: Buyout IRR — Keystone (Ben) | D78: =IFERROR(IRR(D179:D184),0) -> 0.28698779 | F78: IRR on Ben's Scenario 2 cash flows (supporting table at rows 178-184); Year 5 = stake value, not a cash exit
B79: Break-Even Topkey CAGR | D79: =IFERROR((((D63-$C$154-$C$55)/$C$158-D67+$C$55)/$C$159)^(1/C$7)-1,0) -> 0.18966141
B80: Estimated Topkey CAGR | D80: =IFERROR(((D66+$C$55)/$C$159)^(1/$C$7)-1,0) -> 0.2471236
B82: Topkey's Return on the Keystone Acquisition | C82: Value
B83: Cash Paid at Close | C83: =C154 -> 500 | F83: Cash portion of offer (C154)
B84: (+) Topkey Equity Issued to Ben | C84: =C155 -> 2500 | F84: Topkey stock issued, at issue value (C155)
B85: (+) Cash Earnout — Year 3 | C85: =C55 -> 500 | F85: Cash earnout at base-case achievement (C55)
B86: Total Consideration Paid by Topkey | C86: =SUM(C83:C85) -> 3500 | F86: Everything Topkey gives up for Keystone
B87: (x) Topkey's Keystone Stake % | C87: 1 | F87: 100% buyout
B88: Keystone Enterprise Value — Year 5 | C88: =D67 -> 20970.284 | F88: Year 5 partnership value of Keystone (D67)
B89: Value of Topkey's Keystone Stake — Year 5 | C89: =C87*C88 -> 20970.284 | F89: Topkey's Year 5 value of Keystone
B90: MOIC — Topkey | C90: =IFERROR(C89/C86,0) -> 5.9915096 | F90: Year 5 stake value ÷ total consideration
B91: IRR — Topkey | C91: =IFERROR(IRR(D171:D176),0) -> 0.46004304 | F91: IRR on Topkey's cash flows (supporting table at rows 170-176); excludes software fee income and Keystone profits, so understated
B93: Internal - Implied Keystone Standalone Multiple | C93: =D$60 -> Year 5
B94: Year 5 Keystone Standalone Revenue | C94: =+C25+C152 -> 5992.2062
B95: (x) Steady-State Margins | C95: 0.15 | F95: Assumed steady-state EBITDA margin
B96: Year 5 EBITDA | C96: =C95*C94 -> 898.83092
B97: Year 5 Keystone Valuation | C97: =+D63 -> 7490.2577
B98: Implied EBITDA Multiple | C98: =C97/C96 -> 8.3333333
B100: Internal - Implied Keystone Partnership Multiple | C100: =D$60 -> Year 5
B101: Year 5 Keystone Partnership Revenue | C101: =+C39+C152 -> 6990.0945
B102: (x) Steady-State Margins | C102: 0.2 | F102: Assumed steady-state EBITDA margin with software integration
B103: Year 5 EBITDA | C103: =C102*C101 -> 1398.0189
B104: Year 5 Keystone Valuation | C104: =D67 -> 20970.284
B105: Implied EBITDA Multiple | C105: =C104/C103 -> 15
B107: Where Ben's Year 5 Value Comes From | C107: ="Year "&$C$7 -> Year 5 | D107: % of Total
B108: Ben's Share of Topkey ex-Keystone Value | C108: =D66*$C$158 -> 7160 | D108: =IFERROR(C108/C$112,0) -> 0.79566064 | F108: Ben's 4% of Topkey's own Year 5 value, net of cash and earnout paid (D66)
B109: (+) Ben's Share of Keystone Post-Acquisition Value | C109: =D67*$C$158 -> 838.81134 | D109: =IFERROR(C109/C$112,0) -> 0.093213571 | F109: Ben's 4% of the partnership-valued Keystone (D67)
B110: (+) Cash at Close | C110: =D70 -> 500 | D110: =IFERROR(C110/C$112,0) -> 0.055562894 | F110: Cash at close (D70)
B111: (+) Cash Earnout — Year 3 | C111: =D71 -> 500 | D111: =IFERROR(C111/C$112,0) -> 0.055562894 | F111: Year 3 cash earnout (D71)
B112: Ben's Value — Scenario 2 | C112: =SUM(C108:C111) -> 8998.8113 | D112: =SUM(D108:D111) -> 1 | F112: Ties to D72
B113: Ben's Value per 1.0x of Partnership Multiple | C113: =(C39+C152)*$C$158 -> 279.60378 | F113: Year 5 Keystone partnership revenue × Ben's ownership; each 1.0x of C28 is worth this much to Ben
B115: Price Paid vs. Price Received | C115: =C$151 -> Today
...

Sheet Partnership Analysis
B2: =Cover!$B$24 -> Keystone Bookkeepers
B3: Partnership Rollover Scenarios ($000s) | G3: Print | H3: 1
B5: Revenue Growth Assumptions | C5: Value | F5: Rationale / Notes
B6: General Assumptions
B7: Ben's Rollover % — Keystone | C7: 0.3 | F7: Share of Keystone Ben keeps; Topkey buys the rest for cash + Topkey equity (per AMB)
B8: Horizon (Years) | C8: 5 | F8: Projection horizon for Year 5 columns
B9: Topkey - Current Monthly Revenue | C9: 261 | F9: Topkey-provided monthly revenue ($000s). Red: source pending confirmation
B10: Topkey - Current Run-Rate Revenue | C10: =C9*12 -> 3132
B11: Topkey - Current Revenue Multiple | C11: =IFERROR(C167/C10,0) -> 19.157088 | F11: Implied multiple: Topkey pre-deal valuation (C167) ÷ run-rate revenue (C10)
B12: Topkey - Future Revenue Multiple | C12: =C11 -> 19.157088 | F12: Assumed flat at current multiple
B13: Topkey - Current Client Count | C13: 325 | F13: Topkey-provided client count. Red: source pending confirmation
B14: Topkey - Avg. Revenue Per Client | C14: =C10/C13 -> 9.6369231
B15: Topkey - Annual Net Client Wins | C15: 130 | F15: AMB placeholder. Red: source pending confirmation
B16: Total Net Client Wins | C16: =C15*$C$8 -> 650
B17: Total Additional Revenue | C17: =C16*C14 -> 6264
B19: Keystone Standalone Assumptions
B20: Revenue Multiple | C20: 1 | F20: Keystone standalone valued at 1.0x revenue (offer implies ~1.02x)
B21: Scaled Revenue Multiple | C21: 1.25 | F21: Future revenue multiple for Keystone
B22: Avg. Revenue Per Client | C22: =+'Steady-State Staffing'!AB8 -> 16.631473 | F22: Sep'26 annualized fee per non-tax client (Steady-State Staffing AB8)
B23: Target Monthly Net Client Wins | C23: 3 | F23: Target pace per AMB; LTM actual is 26/yr (~2.2/month), see build at rows 175-180
B24: Annual Net Client Wins | C24: =C23*12 -> 36 | F24: Target monthly pace × 12
B25: Total Net Client Wins | C25: =C24*$C$8 -> 180
B26: Total Additional Revenue | C26: =C25*C22 -> 2993.6651
B28: Keystone Partnership Assumptions
B29: Software-Integration Revenue Multiple | C29: 2 | F29: Assumed revenue multiple for software-integrated partnership
B30: VR Platform Run-Rate Tech Cost | C30: 240 | F30: Run-rate tech cost provided by the target
B32: =+B22 -> Avg. Revenue Per Client | C32: =+C22 -> 16.631473
B33: (+) Software-Enabled Price Increase / Client | C33: 0 | F33: Only if Topkey software supports higher client fees; VR cost treated as a cost (memo block at rows 182-192)
B34: Total Avg. Revenue Per Client | C34: =+C32+C33 -> 16.631473
B36: =+B24 -> Annual Net Client Wins | C36: =+C24 -> 36
B37: (+) Additional Annual Net Client Wins From Topkey | C37: 12 | F37: Topkey-provided. Red: source pending confirmation
B38: Total Annual Net Client Wins | C38: =SUM(C36:C37) -> 48
B39: Total Net Client Wins | C39: =C38*$C$8 -> 240
B40: Total Additional Revenue | C40: =C39*C34 -> 3991.5535
B41: Increase in Keystone Revenue vs. Standalone | C41: =C40-C26 -> 997.88838
B43: Cash Earnout — Year 3 Keystone Revenue (Sliding Scale)
B44: Earnout Measurement Year | C44: 3 | F44: Earnout measured on Year 3 run-rate: average of months 34–36 × 12 (see C55)
B45: Keystone Revenue at Close | C45: =C160 -> 2998.541 | F45: PF Jul'26 run-rate revenue at close (C160); unchanged
B46: Year 3 Run-Rate Revenue Target | C46: =C45+C40*(C44-(C55-1)/2/12)/C8 -> 5326.9472 | F46: Run-rate at close + partnership added revenue ramped to the midpoint of the averaging window (month 35 ÷ 60); same basis as the earnout measurement
B47: (x) Achievement vs. Target | C47: 1 | F47: Base case assumes the model's Year 3 revenue is achieved; flex to test payout
B48: Year 3 Run-Rate Revenue — Achieved | C48: =C46*C47 -> 5326.9472
B49: Threshold — % of Target | C49: 0.8 | F49: No earnout below this share of target; payout starts at the threshold % below
B50: Target Earnout — at 100% of Target | C50: 500 | F50: Opening ask: $500K at target (AMB internal range $750K–$1M)
B51: Payout at Threshold — % of Target Earnout | C51: 0.5 | F51: Share of target earnout paid at the 80% threshold
B52: Cap — % of Target Earnout | C52: 1.5 | F52: Payout capped at 120% of target, symmetric with the 80% threshold (50% at 80%, 150% at 120%)
B53: Payout % Earned | C53: =IF(C47<C49,0,MIN(C52,C51+(1-C51)*(C47-C49)/(1-C49))) -> 1 | F53: Straight line from threshold payout at 80% to 100% at target, continuing above target until the cap
B54: Maximum Earnout (Cap) | C54: =C50*C52 -> 750 | F54: Topkey's maximum earnout exposure
B55: Run-Rate Window — Months Averaged | C55: 3 | F55: Earnout measured on average monthly recurring revenue for the last 3 months of Year 3 (months 34–36) × 12; averaging prevents one strong month from triggering the payout
B56: Cash Earnout Payable — Year 3 | C56: =C50*C53 -> 500 | F56: Paid in cash by Topkey; flows into Scenario 2 (row 81), Ben's MOIC/IRR and Topkey's return (row 95)
B57: Probability of Achievement | C57: 0.7 | F57: AMB estimate for the memo line below
B58: Discount Rate | C58: 0.15 | F58: AMB estimate for the memo line below
B59: Risk-Weighted Earnout — PV at Close (Memo) | C59: =C56*C57/(1+C58)^C44 -> 230.13068 | F59: Memo only; not used in Scenario 2
B61: Scenario 1 — Ben Retains 100% of Keystone | C61: =C$159 -> Today | D61: ="Year "&$C$8 -> Year 5
B62: Keystone Enterprise Value | C62: =ROUND(C160*C20,-1) -> 3000 | D62: =(C160+C26)*$C$21 -> 7490.2577 | F62: Today at offer value; Year 5 = (PF run-rate revenue + standalone added revenue) x standalone multiple
B63: Ben's Ownership % — Keystone | C63: ='Offer Overview'!$C$27 -> 1 | D63: =$C$63 -> 1
B64: Ben's Value — Scenario 1 | C64: =C62*C63 -> 3000 | D64: =D62*D63 -> 7490.2577
B66: ="Scenario 2 — Ben Rolls "&TEXT($C$162,"0%")&" of Keystone Equity" -> Scenario 2 — Ben Rolls 30% of Keystone Equity | C66: =C$159 -> Today | D66: =D$61 -> Year 5
B67: Keystone Enterprise Value — Partnership | C67: =C161 -> 3000 | D67: =(C40+C160)*C29 -> 13980.189 | F67: Today at offer value; Year 5 = partnership revenue × partnership multiple (C29)
B68: (x) Ben's Retained Keystone % | C68: =$C$162 -> 0.3 | D68: =$C$162 -> 0.3
B69: Ben's Keystone Equity Value | C69: =C67*C68 -> 900 | D69: =D67*D68 -> 4194.0567 | F69: Ben's retained Keystone stake (C7 × Keystone value)
B71: Topkey ex-Keystone Value | C71: =C170 -> 59500 | D71: =(C10+C17)*C12-$C$165-$C$56 -> 179000
B72: (+) Topkey's Share of Keystone Value | C72: =C67*$C$163 -> 2100 | D72: =D67*$C$163 -> 9786.1324 | F72: Topkey's stake in Keystone is part of Topkey's value
B73: Topkey Combined Enterprise Value | C73: =C71+C72 -> 61600 | D73: =D71+D72 -> 188786.13
B74: (x) Ben's Topkey Ownership % | C74: =$C$169 -> 0.025974026 | D74: =$C$169 -> 0.025974026
B75: Ben's Topkey Equity Value | C75: =C73*C74 -> 1600 | D75: =D73*D74 -> 4903.5359 | F75: Ties to Topkey equity issued (tie-out row 172)
B76: Ben's Value by Source
B77: Keystone — Ben's Direct Retained Stake | C77: =C69 -> 900 | D77: =D69 -> 4194.0567 | F77: Keystone value Ben owns directly
B78: (+) Keystone — Ben's Indirect Share via Topkey | C78: =C72*C74 -> 54.545455 | D78: =D72*D74 -> 254.18526 | F78: Ben's Topkey % × Topkey's Keystone stake
B79: (+) Topkey ex-Keystone — Ben's Share | C79: =C71*C74 -> 1545.4545 | D79: =D71*D74 -> 4649.3506 | F79: Ben's Topkey % × Topkey's own business
B80: (+) Cash at Close | C80: =$C$165 -> 500 | D80: =$C$165 -> 500
B81: (+) Cash Earnout — Year 3 | D81: =$C$56 -> 500
B82: Ben's Value — Scenario 2 | C82: =SUM(C77:C81) -> 3000 | D82: =SUM(D77:D81) -> 10097.593 | F82: Direct Keystone + indirect Keystone + Topkey + cash
B84: Scenario 2 vs. Scenario 1 | C84: =C$159 -> Today | D84: =D$61 -> Year 5
B85: Increase in Proceeds | C85: =C82-C64 -> 0 | D85: =D82-D64 -> 2607.3349
B86: Delta (%) | C86: 0 | D86: =IFERROR(D82/D64-1,0) -> 0.34809683
B87: Partnership MOIC — Keystone (Ben) | D87: =IFERROR(D82/C161,0) -> 3.3658642 | F87: Ben's Year 5 value (D82: cash + earnout + retained stake + Topkey stock) ÷ Keystone value given up at close (C161)
B88: Partnership IRR — Keystone (Ben) | D88: =IFERROR(IRR(D203:D208),0) -> 0.31863569 | F88: IRR on Ben's Scenario 2 cash flows (supporting table at rows 202-208); Year 5 = stake values, not a cash exit
B89: Required Topkey CAGR | C89: 0 | D89: =MAX(0,IFERROR(((C127+$C$56)/$C$170)^(1/$C$8)-1,0)) -> 0.058647152 | F89: Topkey revenue CAGR needed for Scenario 2 to equal Scenario 1 (from required value in C127, before earnout paid); floored at zero
B90: Estimated Topkey CAGR | C90: 0 | D90: =IFERROR(((D71+$C$56)/$C$170)^(1/$C$8)-1,0) -> 0.2471236
B92: Topkey's Return on the Keystone Stake | C92: Value
B93: Cash Paid at Close | C93: =C165 -> 500 | F93: Cash portion of stake price (C165)
B94: (+) Topkey Equity Issued to Ben | C94: =C166 -> 1600 | F94: Topkey stock issued, at issue value (C166)
B95: (+) Cash Earnout — Year 3 | C95: =C56 -> 500 | F95: Cash earnout at base-case achievement (C56)
B96: Total Consideration Paid by Topkey | C96: =SUM(C93:C95) -> 2600 | F96: Everything Topkey gives up for its Keystone stake
B97: (x) Topkey's Keystone Stake % | C97: =C163 -> 0.7 | F97: Topkey's share of Keystone (C163)
B98: Keystone Enterprise Value — Year 5 | C98: =D67 -> 13980.189 | F98: Year 5 partnership value of 100% of Keystone (D67)
B99: Value of Topkey's Keystone Stake — Year 5 | C99: =C97*C98 -> 9786.1324 | F99: Ties to Topkey's share of Keystone in Scenario 2 (D72)
B100: MOIC — Topkey | C100: =IFERROR(C99/C96,0) -> 3.7638971 | F100: Year 5 stake value ÷ total consideration
B101: IRR — Topkey | C101: =IFERROR(IRR(D195:D200),0) -> 0.33471707 | F101: IRR on Topkey's cash flows (supporting table at rows 194-200); excludes software fee income and Keystone distributions, so understated
B103: Internal - Implied Keystone Standalone Multiple | C103: =D$61 -> Year 5
B104: Year 5 Keystone Standalone Revenue | C104: =+C26+C160 -> 5992.2062
B105: (x) Steady-State Margins | C105: 0.15 | F105: Assumed steady-state EBITDA margin
B106: Year 5 EBITDA | C106: =C105*C104 -> 898.83092
B107: Year 5 Keystone Valuation | C107: =+D64 -> 7490.2577
B108: Implied EBITDA Multiple | C108: =C107/C106 -> 8.3333333
B110: Internal - Implied Keystone Partnership Multiple | C110: =D$61 -> Year 5
B111: Year 5 Keystone Partnership Revenue | C111: =+C40+C160 -> 6990.0945
B112: (x) Steady-State Margins | C112: 0.2 | F112: AMB estimate of steady-state EBITDA margin
B113: Year 5 EBITDA | C113: =C112*C111 -> 1398.0189
B114: Year 5 Keystone Valuation | C114: =D67 -> 13980.189
...

Sheet Valuation Growth Tables
B2: =Cover!$B$24 -> Keystone Bookkeepers
B3: Valuation Growth Sensitivity Tables ($000s) | I3: Print | J3: 1
B5: ="Table 1 — Ben's Net Gain: Scenario 2 vs. Scenario 1, Year "&$C$31&" ($000s)" -> Table 1 — Ben's Net Gain: Scenario 2 vs. Scenario 1, Year 5 ($000s)
B6: Standalone Multiple ↓ | Partnership Multiple → | C6: =D6-$C$44 -> 2 | D6: =E6-$C$44 -> 2.5 | E6: =$C$38 -> 3 | F6: =E6+$C$44 -> 3.5 | G6: =F6+$C$44 -> 4
B7: =B8-$C$45 -> 0.75 | C7: =$C$42*($C$41+$C$50*C$6)+$C$43-$C$51*$B7*$C$34 -> 4225.0529 | D7: =$C$42*($C$41+$C$50*D$6)+$C$43-$C$51*$B7*$C$34 -> 4364.8548 | E7: =$C$42*($C$41+$C$50*E$6)+$C$43-$C$51*$B7*$C$34 -> 4504.6567 | F7: =$C$42*($C$41+$C$50*F$6)+$C$43-$C$51*$B7*$C$34 -> 4644.4586 | G7: =$C$42*($C$41+$C$50*G$6)+$C$43-$C$51*$B7*$C$34 -> 4784.2605
B8: =B9-$C$45 -> 1 | C8: =$C$42*($C$41+$C$50*C$6)+$C$43-$C$51*$B8*$C$34 -> 2727.0014 | D8: =$C$42*($C$41+$C$50*D$6)+$C$43-$C$51*$B8*$C$34 -> 2866.8033 | E8: =$C$42*($C$41+$C$50*E$6)+$C$43-$C$51*$B8*$C$34 -> 3006.6052 | F8: =$C$42*($C$41+$C$50*F$6)+$C$43-$C$51*$B8*$C$34 -> 3146.4071 | G8: =$C$42*($C$41+$C$50*G$6)+$C$43-$C$51*$B8*$C$34 -> 3286.209
B9: =$C$35 -> 1.25 | C9: =$C$42*($C$41+$C$50*C$6)+$C$43-$C$51*$B9*$C$34 -> 1228.9499 | D9: =$C$42*($C$41+$C$50*D$6)+$C$43-$C$51*$B9*$C$34 -> 1368.7518 | E9: =$C$42*($C$41+$C$50*E$6)+$C$43-$C$51*$B9*$C$34 -> 1508.5536 | F9: =$C$42*($C$41+$C$50*F$6)+$C$43-$C$51*$B9*$C$34 -> 1648.3555 | G9: =$C$42*($C$41+$C$50*G$6)+$C$43-$C$51*$B9*$C$34 -> 1788.1574
B10: =B9+$C$45 -> 1.5 | C10: =$C$42*($C$41+$C$50*C$6)+$C$43-$C$51*$B10*$C$34 -> -269.10168 | D10: =$C$42*($C$41+$C$50*D$6)+$C$43-$C$51*$B10*$C$34 -> -129.29978 | E10: =$C$42*($C$41+$C$50*E$6)+$C$43-$C$51*$B10*$C$34 -> 10.502106 | F10: =$C$42*($C$41+$C$50*F$6)+$C$43-$C$51*$B10*$C$34 -> 150.304 | G10: =$C$42*($C$41+$C$50*G$6)+$C$43-$C$51*$B10*$C$34 -> 290.10589
B11: =B10+$C$45 -> 1.75 | C11: =$C$42*($C$41+$C$50*C$6)+$C$43-$C$51*$B11*$C$34 -> -1767.1532 | D11: =$C$42*($C$41+$C$50*D$6)+$C$43-$C$51*$B11*$C$34 -> -1627.3513 | E11: =$C$42*($C$41+$C$50*E$6)+$C$43-$C$51*$B11*$C$34 -> -1487.5494 | F11: =$C$42*($C$41+$C$50*F$6)+$C$43-$C$51*$B11*$C$34 -> -1347.7475 | G11: =$C$42*($C$41+$C$50*G$6)+$C$43-$C$51*$B11*$C$34 -> -1207.9457
B13: ="Table 2 — Partnership Value Increase vs. Base Standalone Increase, Year "&$C$31&" ($000s)" -> Table 2 — Partnership Value Increase vs. Base Standalone Increase, Year 5 ($000s)
B14: Avg. Rev. / Client ↓ | Annual Net Wins → | C14: =D14-$C$46 -> 38 | D14: =E14-$C$46 -> 43 | E14: =$C$40 -> 48 | F14: =E14+$C$46 -> 53 | G14: =F14+$C$46 -> 58
B15: =B16-$C$47 -> 14.631473 | C15: =($C$32+C$14*$C$31*$B15)*$C$38-$C$33-$C$52 -> 9845.305 | D15: =($C$32+D$14*$C$31*$B15)*$C$38-$C$33-$C$52 -> 10942.665 | E15: =($C$32+E$14*$C$31*$B15)*$C$38-$C$33-$C$52 -> 12040.026 | F15: =($C$32+F$14*$C$31*$B15)*$C$38-$C$33-$C$52 -> 13137.386 | G15: =($C$32+G$14*$C$31*$B15)*$C$38-$C$33-$C$52 -> 14234.747
B16: =B17-$C$47 -> 15.631473 | C16: =($C$32+C$14*$C$31*$B16)*$C$38-$C$33-$C$52 -> 10415.305 | D16: =($C$32+D$14*$C$31*$B16)*$C$38-$C$33-$C$52 -> 11587.665 | E16: =($C$32+E$14*$C$31*$B16)*$C$38-$C$33-$C$52 -> 12760.026 | F16: =($C$32+F$14*$C$31*$B16)*$C$38-$C$33-$C$52 -> 13932.386 | G16: =($C$32+G$14*$C$31*$B16)*$C$38-$C$33-$C$52 -> 15104.747
B17: =$C$39 -> 16.631473 | C17: =($C$32+C$14*$C$31*$B17)*$C$38-$C$33-$C$52 -> 10985.305 | D17: =($C$32+D$14*$C$31*$B17)*$C$38-$C$33-$C$52 -> 12232.665 | E17: =($C$32+E$14*$C$31*$B17)*$C$38-$C$33-$C$52 -> 13480.026 | F17: =($C$32+F$14*$C$31*$B17)*$C$38-$C$33-$C$52 -> 14727.386 | G17: =($C$32+G$14*$C$31*$B17)*$C$38-$C$33-$C$52 -> 15974.747
B18: =B17+$C$47 -> 17.631473 | C18: =($C$32+C$14*$C$31*$B18)*$C$38-$C$33-$C$52 -> 11555.305 | D18: =($C$32+D$14*$C$31*$B18)*$C$38-$C$33-$C$52 -> 12877.665 | E18: =($C$32+E$14*$C$31*$B18)*$C$38-$C$33-$C$52 -> 14200.026 | F18: =($C$32+F$14*$C$31*$B18)*$C$38-$C$33-$C$52 -> 15522.386 | G18: =($C$32+G$14*$C$31*$B18)*$C$38-$C$33-$C$52 -> 16844.747
B19: =B18+$C$47 -> 18.631473 | C19: =($C$32+C$14*$C$31*$B19)*$C$38-$C$33-$C$52 -> 12125.305 | D19: =($C$32+D$14*$C$31*$B19)*$C$38-$C$33-$C$52 -> 13522.665 | E19: =($C$32+E$14*$C$31*$B19)*$C$38-$C$33-$C$52 -> 14920.026 | F19: =($C$32+F$14*$C$31*$B19)*$C$38-$C$33-$C$52 -> 16317.386 | G19: =($C$32+G$14*$C$31*$B19)*$C$38-$C$33-$C$52 -> 17714.747
B21: ="Table 3 — Standalone: Keystone Value Increase vs. Today, Year "&$C$31&" ($000s)" -> Table 3 — Standalone: Keystone Value Increase vs. Today, Year 5 ($000s)
B22: Avg. Rev. / Client ↓ | Annual Net Wins → | C22: =D22-$C$46 -> 26 | D22: =E22-$C$46 -> 31 | E22: =$C$37 -> 36 | F22: =E22+$C$46 -> 41 | G22: =F22+$C$46 -> 46
B23: =B24-$C$47 -> 14.631473 | C23: =($C$32+C$22*$C$31*$B23)*$C$35-$C$33 -> 3125.7906 | D23: =($C$32+D$22*$C$31*$B23)*$C$35-$C$33 -> 3583.0242 | E23: =($C$32+E$22*$C$31*$B23)*$C$35-$C$33 -> 4040.2577 | F23: =($C$32+F$22*$C$31*$B23)*$C$35-$C$33 -> 4497.4912 | G23: =($C$32+G$22*$C$31*$B23)*$C$35-$C$33 -> 4954.7248
B24: =B25-$C$47 -> 15.631473 | C24: =($C$32+C$22*$C$31*$B24)*$C$35-$C$33 -> 3288.2906 | D24: =($C$32+D$22*$C$31*$B24)*$C$35-$C$33 -> 3776.7742 | E24: =($C$32+E$22*$C$31*$B24)*$C$35-$C$33 -> 4265.2577 | F24: =($C$32+F$22*$C$31*$B24)*$C$35-$C$33 -> 4753.7412 | G24: =($C$32+G$22*$C$31*$B24)*$C$35-$C$33 -> 5242.2248
B25: =$C$36 -> 16.631473 | C25: =($C$32+C$22*$C$31*$B25)*$C$35-$C$33 -> 3450.7906 | D25: =($C$32+D$22*$C$31*$B25)*$C$35-$C$33 -> 3970.5242 | E25: =($C$32+E$22*$C$31*$B25)*$C$35-$C$33 -> 4490.2577 | F25: =($C$32+F$22*$C$31*$B25)*$C$35-$C$33 -> 5009.9912 | G25: =($C$32+G$22*$C$31*$B25)*$C$35-$C$33 -> 5529.7248
B26: =B25+$C$47 -> 17.631473 | C26: =($C$32+C$22*$C$31*$B26)*$C$35-$C$33 -> 3613.2906 | D26: =($C$32+D$22*$C$31*$B26)*$C$35-$C$33 -> 4164.2742 | E26: =($C$32+E$22*$C$31*$B26)*$C$35-$C$33 -> 4715.2577 | F26: =($C$32+F$22*$C$31*$B26)*$C$35-$C$33 -> 5266.2412 | G26: =($C$32+G$22*$C$31*$B26)*$C$35-$C$33 -> 5817.2248
B27: =B26+$C$47 -> 18.631473 | C27: =($C$32+C$22*$C$31*$B27)*$C$35-$C$33 -> 3775.7906 | D27: =($C$32+D$22*$C$31*$B27)*$C$35-$C$33 -> 4358.0242 | E27: =($C$32+E$22*$C$31*$B27)*$C$35-$C$33 -> 4940.2577 | F27: =($C$32+F$22*$C$31*$B27)*$C$35-$C$33 -> 5522.4912 | G27: =($C$32+G$22*$C$31*$B27)*$C$35-$C$33 -> 6104.7248
B29: Sensitivity Assumptions
B30: Assumption | C30: Value | D30: Rationale
B31: Horizon (Years) | C31: ='100% Buyout Analysis'!$C$7 -> 5 | D31: Linked from Valuation Growth C7
B32: Keystone Revenue Today | C32: ='100% Buyout Analysis'!$C$152 -> 2998.541 | D32: Linked from 100% Buyout Analysis C125
B33: Keystone Value Today | C33: ='100% Buyout Analysis'!$C$153 -> 3000 | D33: Linked from 100% Buyout Analysis C126
B34: Ben's Ownership % — Keystone | C34: ='100% Buyout Analysis'!$C$62 -> 1 | D34: Linked from Valuation Growth C44
B35: Standalone Revenue Multiple (Year 5) | C35: ='100% Buyout Analysis'!$C$20 -> 1.25 | D35: Linked from Valuation Growth C20 (Scaled Revenue Multiple)
B36: Standalone Avg. Revenue Per Client | C36: ='100% Buyout Analysis'!$C$21 -> 16.631473 | D36: Linked from Valuation Growth C21
B37: Standalone Annual Net Client Wins | C37: ='100% Buyout Analysis'!$C$23 -> 36 | D37: Linked from Valuation Growth C23
B38: Partnership Revenue Multiple | C38: ='100% Buyout Analysis'!$C$28 -> 3 | D38: Linked from Valuation Growth C28
B39: Partnership Total Avg. Revenue Per Client | C39: ='100% Buyout Analysis'!$C$33 -> 16.631473 | D39: Linked from Valuation Growth C33
B40: Partnership Total Annual Net Client Wins | C40: ='100% Buyout Analysis'!$C$37 -> 48 | D40: Linked from Valuation Growth C37
B41: Topkey ex-Keystone Value — Year 5 | C41: ='100% Buyout Analysis'!$D$66 -> 179000 | D41: Linked from 100% Buyout Analysis D66 (net of cash and earnout paid)
B42: Ben's Topkey Ownership % | C42: ='100% Buyout Analysis'!$C$158 -> 0.04 | D42: Linked from 100% Buyout Analysis C151
B43: Cash at Close + Earnout | C43: ='100% Buyout Analysis'!$C$154+'100% Buyout Analysis'!$C$55 -> 1000 | D43: Linked from 100% Buyout Analysis C147 + C55 (Year 3 cash earnout)
B44: Step — Partnership Multiple (x) | C44: 0.5 | D44: ="Gives "&TEXT($C$38-2*$C$44,"0.00")&"x–"&TEXT($C$38+2*$C$44,"0.00")&"x around the "&TEXT($C$38,"0.00")&"x base" -> Gives 2.00x–4.00x around the 3.00x base
B45: Step — Standalone Multiple (x) | C45: 0.25 | D45: ="Gives "&TEXT($C$35-2*$C$45,"0.00")&"x–"&TEXT($C$35+2*$C$45,"0.00")&"x around the "&TEXT($C$35,"0.00")&"x base" -> Gives 0.75x–1.75x around the 1.25x base
B46: Step — Annual Net Client Wins (#) | C46: 5 | D46: ±5 wins per year per step
B47: Step — Avg. Revenue Per Client ($000s) | C47: 1 | D47: ±$1K per client per step
B49: Base Case Build
B50: ="Partnership Year "&$C$31&" Revenue" -> Partnership Year 5 Revenue | C50: =$C$32+$C$40*$C$31*$C$39 -> 6990.0945 | D50: Revenue today + wins × horizon × price
B51: ="Standalone Year "&$C$31&" Revenue" -> Standalone Year 5 Revenue | C51: =$C$32+$C$37*$C$31*$C$36 -> 5992.2062 | D51: Revenue today + wins × horizon × price
B52: Standalone Value Increase vs. Today (Base) | C52: =$C$51*$C$35-$C$33 -> 4490.2577 | D52: Held constant in Table 2
B53: Tie Outs
B54: Tie Out — Table 1 vs. Valuation Growth | C54: =E9-('100% Buyout Analysis'!$D$72-'100% Buyout Analysis'!$D$63) -> 0 | D54: Base vs. VG D50 − D42; must be zero
B55: Tie Out — Table 2 vs. Valuation Growth | C55: =E17-(('100% Buyout Analysis'!$D$67-'100% Buyout Analysis'!$C$67)-('100% Buyout Analysis'!$D$61-'100% Buyout Analysis'!$C$61)) -> 0 | D55: Base vs. VG (D46 − C46) − (D40 − C40); must be zero
B56: Tie Out — Table 3 vs. Valuation Growth | C56: =E25-('100% Buyout Analysis'!$D$61-'100% Buyout Analysis'!$C$61) -> 0 | D56: Base vs. VG D40 − C40; must be zero

Sheet P&L Overview
B2: =+Cover!B24 -> Keystone Bookkeepers
B3: Summary P&L Overview ($000s) | P3: Print | Q3: 1
C5: Full Year | F5: YTD | I5: LTM | K5: PF | M5: PF Delta
B6: P&L Summary | C6: 2024 | D6: 2025 | F6: July'25 | G6: July'26 | I6: July'25 | J6: July'26 | K6: July'26 | M6: ($) | N6: (%)
B7: Revenue
B8: =+'P&L Forecast'!B7 -> STR Subscription | C8: =+'P&L Forecast'!C7 -> 793.47225 | D8: =+'P&L Forecast'!D7 -> 1450.4923 | F8: =+'P&L Forecast'!F7 -> 751.5286 | G8: =+'P&L Forecast'!G7 -> 1261.4769 | I8: =+'P&L Forecast'!I7 -> 1152.3203 | J8: =+'P&L Forecast'!J7 -> 1960.4406 | K8: =+'P&L Forecast'!K7 -> 2410.05 | M8: =K8-J8 -> 449.6094 | N8: =IFERROR(K8/J8-1,0) -> 0.229341
B9: =+'P&L Forecast'!B8 -> Occupancy Taxes | C9: =+'P&L Forecast'!C8 -> 0.56 | D9: =+'P&L Forecast'!D8 -> 55.0805 | F9: =+'P&L Forecast'!F8 -> 23.2255 | G9: =+'P&L Forecast'!G8 -> 91.65114 | I9: =+'P&L Forecast'!I8 -> 23.7855 | J9: =+'P&L Forecast'!J8 -> 123.50614 | K9: =+'P&L Forecast'!K8 -> 192.8298 | M9: =K9-J9 -> 69.32366 | N9: =IFERROR(K9/J9-1,0) -> 0.56129728
B10: =+'P&L Forecast'!B9 -> SMB Subscription | C10: =+'P&L Forecast'!C9 -> 224.791 | D10: =+'P&L Forecast'!D9 -> 149.77 | F10: =+'P&L Forecast'!F9 -> 90.4525 | G10: =+'P&L Forecast'!G9 -> 73.4185 | I10: =+'P&L Forecast'!I9 -> 169.5465 | J10: =+'P&L Forecast'!J9 -> 132.736 | K10: =+'P&L Forecast'!K9 -> 16.2 | M10: =K10-J10 -> -116.536 | N10: =IFERROR(K10/J10-1,0) -> -0.87795323
B11: =+'P&L Forecast'!B10 -> Onboarding | C11: =+'P&L Forecast'!C10 -> 44.0585 | D11: =+'P&L Forecast'!D10 -> 74.5193 | F11: =+'P&L Forecast'!F10 -> 42.25405 | G11: =+'P&L Forecast'!G10 -> 59.055 | I11: =+'P&L Forecast'!I10 -> 57.49255 | J11: =+'P&L Forecast'!J10 -> 91.32025 | K11: =+'P&L Forecast'!K10 -> 103.5675 | M11: =K11-J11 -> 12.24725 | N11: =IFERROR(K11/J11-1,0) -> 0.13411319
B12: =+'P&L Forecast'!B11 -> Topkey Subscription | C12: =+'P&L Forecast'!C11 -> 0 | D12: =+'P&L Forecast'!D11 -> 9.947 | F12: =+'P&L Forecast'!F11 -> 0 | G12: =+'P&L Forecast'!G11 -> 45.086 | I12: =+'P&L Forecast'!I11 -> 0 | J12: =+'P&L Forecast'!J11 -> 55.033 | K12: =+'P&L Forecast'!K11 -> 94.836 | M12: =K12-J12 -> 39.803 | N12: =IFERROR(K12/J12-1,0) -> 0.72325695
B13: =+'P&L Forecast'!B12 -> STR Bill Pay | C13: =+'P&L Forecast'!C12 -> 0.06 | D13: =+'P&L Forecast'!D12 -> 36.6065 | F13: =+'P&L Forecast'!F12 -> 15.4915 | G13: =+'P&L Forecast'!G12 -> 45.13 | I13: =+'P&L Forecast'!I12 -> 15.5515 | J13: =+'P&L Forecast'!J12 -> 66.245 | K13: =+'P&L Forecast'!K12 -> 83.46 | M13: =K13-J13 -> 17.215 | N13: =IFERROR(K13/J13-1,0) -> 0.25986867
B14: =+'P&L Forecast'!B13 -> Controller Services | C14: =+'P&L Forecast'!C13 -> 13.75 | D14: =+'P&L Forecast'!D13 -> 46.4 | F14: =+'P&L Forecast'!F13 -> 31.5 | G14: =+'P&L Forecast'!G13 -> 24.25 | I14: =+'P&L Forecast'!I13 -> 44 | J14: =+'P&L Forecast'!J13 -> 39.15 | K14: =+'P&L Forecast'!K13 -> 42 | M14: =K14-J14 -> 2.85 | N14: =IFERROR(K14/J14-1,0) -> 0.072796935
B15: Other Revenue | C15: =+C16-SUM(C8:C14) -> 58.2741 | D15: =+D16-SUM(D8:D14) -> 56.56748 | F15: =+F16-SUM(F8:F14) -> 43.42095 | G15: =+G16-SUM(G8:G14) -> 70.95371 | I15: =+I16-SUM(I8:I14) -> 61.71435 | J15: =+J16-SUM(J8:J14) -> 84.10024 | K15: =+K16-SUM(K8:K14) -> 55.59772 | M15: =K15-J15 -> -28.50252 | N15: =IFERROR(K15/J15-1,0) -> -0.33891128
B16: Total Run-Rate Revenue | C16: =+'P&L Forecast'!C24 -> 1134.9659 | D16: =+'P&L Forecast'!D24 -> 1879.3831 | F16: =+'P&L Forecast'!F24 -> 997.8731 | G16: =+'P&L Forecast'!G24 -> 1671.0212 | I16: =+'P&L Forecast'!I24 -> 1524.4107 | J16: =+'P&L Forecast'!J24 -> 2552.5312 | K16: =+'P&L Forecast'!K24 -> 2998.541 | M16: =SUM(M8:M15) -> 446.00979 | N16: =IFERROR(K16/J16-1,0) -> 0.17473235
B17: Unclassified Active Client Revenue | C17: =+'P&L Forecast'!C26 -> 0 | D17: =+'P&L Forecast'!D26 -> 0 | F17: =+'P&L Forecast'!F26 -> 0 | G17: =+'P&L Forecast'!G26 -> 0 | I17: =+'P&L Forecast'!I26 -> 0 | J17: =+'P&L Forecast'!J26 -> 0 | K17: =+'P&L Forecast'!K26 -> 93.9827 | M17: =K17-J17 -> 93.9827 | N17: =IFERROR(K17/J17-1,0) -> 0
B18: Total Adj. Revenue | C18: =+'P&L Forecast'!C28 -> 1134.9659 | D18: =+'P&L Forecast'!D28 -> 1879.3831 | F18: =+'P&L Forecast'!F28 -> 997.8731 | G18: =+'P&L Forecast'!G28 -> 1671.0212 | I18: =+'P&L Forecast'!I28 -> 1524.4107 | J18: =+'P&L Forecast'!J28 -> 2552.5312 | K18: =+'P&L Forecast'!K28 -> 3092.5237 | M18: =SUM(M16:M17) -> 539.99249 | N18: =IFERROR(K18/J18-1,0) -> 0.21155177
B20: Expenses
B21: =+'P&L Forecast'!B31 -> Indirect Labor | C21: =+'P&L Forecast'!C31 -> 101.3752 | D21: =+'P&L Forecast'!D31 -> 281.24054 | F21: =+'P&L Forecast'!F31 -> 136.29648 | G21: =+'P&L Forecast'!G31 -> 357.27472 | I21: =+'P&L Forecast'!I31 -> 202.41598 | J21: =+'P&L Forecast'!J31 -> 502.21878 | K21: =+'P&L Forecast'!K31 -> 681.3 | M21: =K21-J21 -> 179.08122 | N21: =IFERROR(K21/J21-1,0) -> 0.35658009 | P21: =K21/$K$30 -> 0.32533849
B22: =+'P&L Forecast'!B32 -> Bookkeeper Wages | C22: =+'P&L Forecast'!C32 -> 183.36903 | D22: =+'P&L Forecast'!D32 -> 316.18462 | F22: =+'P&L Forecast'!F32 -> 147.26813 | G22: =+'P&L Forecast'!G32 -> 267.7574 | I22: =+'P&L Forecast'!I32 -> 240.18098 | J22: =+'P&L Forecast'!J32 -> 436.67389 | K22: =+'P&L Forecast'!K32 -> 492.6 | M22: =K22-J22 -> 55.92611 | N22: =IFERROR(K22/J22-1,0) -> 0.12807294 | P22: =K22/$K$30 -> 0.23522933
B23: =+'P&L Forecast'!B33 -> Client Lead Wages | C23: =+'P&L Forecast'!C33 -> 286.16129 | D23: =+'P&L Forecast'!D33 -> 352.95844 | F23: =+'P&L Forecast'!F33 -> 201.27983 | G23: =+'P&L Forecast'!G33 -> 202.05309 | I23: =+'P&L Forecast'!I33 -> 353.12843 | J23: =+'P&L Forecast'!J33 -> 353.7317 | K23: =+'P&L Forecast'!K33 -> 392.92452 | M23: =K23-J23 -> 39.19282 | N23: =IFERROR(K23/J23-1,0) -> 0.11079816 | P23: =K23/$K$30 -> 0.18763169
B24: =+'P&L Forecast'!B34 -> Onboarding Team Wages | C24: =+'P&L Forecast'!C34 -> 122.81255 | D24: =+'P&L Forecast'!D34 -> 152.16972 | F24: =+'P&L Forecast'!F34 -> 73.94962 | G24: =+'P&L Forecast'!G34 -> 111.27999 | I24: =+'P&L Forecast'!I34 -> 121.30735 | J24: =+'P&L Forecast'!J34 -> 189.50009 | K24: =+'P&L Forecast'!K34 -> 197.14944 | M24: =K24-J24 -> 7.64935 | N24: =IFERROR(K24/J24-1,0) -> 0.040365944 | P24: =K24/$K$30 -> 0.094143992
B25: =+'P&L Forecast'!B35 -> Owner Wages | C25: =+'P&L Forecast'!C35 -> 0 | D25: =+'P&L Forecast'!D35 -> 90.66704 | F25: =+'P&L Forecast'!F35 -> 45.46612 | G25: =+'P&L Forecast'!G35 -> 63.14302 | I25: =+'P&L Forecast'!I35 -> 45.46612 | J25: =+'P&L Forecast'!J35 -> 108.34394 | K25: =+'P&L Forecast'!K35 -> 108.34394 | M25: =K25-J25 -> 0 | N25: =IFERROR(K25/J25-1,0) -> 0 | P25: =K25/$K$30 -> 0.051737053
B26: =+'P&L Forecast'!B36 -> S&M Wages | C26: =+'P&L Forecast'!C36 -> 0 | D26: =+'P&L Forecast'!D36 -> 19.14963 | F26: =+'P&L Forecast'!F36 -> 3.09945 | G26: =+'P&L Forecast'!G36 -> 51.94131 | I26: =+'P&L Forecast'!I36 -> 3.09945 | J26: =+'P&L Forecast'!J36 -> 67.99149 | K26: =+'P&L Forecast'!K36 -> 98.34912 | M26: =K26-J26 -> 30.35763 | N26: =IFERROR(K26/J26-1,0) -> 0.44649161 | P26: =K26/$K$30 -> 0.046964266
B27: =+'P&L Forecast'!B37 -> Occupancy Tax Specialist | C27: =+'P&L Forecast'!C37 -> 1.11335 | D27: =+'P&L Forecast'!D37 -> 29.56415 | F27: =+'P&L Forecast'!F37 -> 14.27585 | G27: =+'P&L Forecast'!G37 -> 42.08505 | I27: =+'P&L Forecast'!I37 -> 15.3892 | J27: =+'P&L Forecast'!J37 -> 57.37335 | K27: =+'P&L Forecast'!K37 -> 58.2 | M27: =K27-J27 -> 0.82665 | N27: =IFERROR(K27/J27-1,0) -> 0.014408257 | P27: =K27/$K$30 -> 0.027792016
B28: =+'P&L Forecast'!B38 -> Sr. Client Lead Wages | C28: =+'P&L Forecast'!C38 -> 0 | D28: =+'P&L Forecast'!D38 -> 0 | F28: =+'P&L Forecast'!F38 -> 0 | G28: =+'P&L Forecast'!G38 -> 7.995 | I28: =+'P&L Forecast'!I38 -> 0 | J28: =+'P&L Forecast'!J38 -> 7.995 | K28: =+'P&L Forecast'!K38 -> 33.08124 | M28: =K28-J28 -> 25.08624 | N28: =IFERROR(K28/J28-1,0) -> 3.1377411 | P28: =K28/$K$30 -> 0.015797154
B29: =+'P&L Forecast'!B39 -> Employee Benefits | C29: =+'P&L Forecast'!C39 -> 5.37405 | D29: =+'P&L Forecast'!D39 -> 19.23245 | F29: =+'P&L Forecast'!F39 -> 9.02166 | G29: =+'P&L Forecast'!G39 -> 17.36251 | I29: =+'P&L Forecast'!I39 -> 12.16686 | J29: =+'P&L Forecast'!J39 -> 27.5733 | K29: =+'P&L Forecast'!K39 -> 32.17836 | M29: =K29-J29 -> 4.60506 | N29: =IFERROR(K29/J29-1,0) -> 0.16701157 | P29: =K29/$K$30 -> 0.015366005
B30: =+'P&L Forecast'!B40 -> Total Payroll Expenses | C30: =SUM(C21:C29) -> 700.20547 | D30: =SUM(D21:D29) -> 1261.1666 | F30: =SUM(F21:F29) -> 630.65714 | G30: =SUM(G21:G29) -> 1120.8921 | I30: =SUM(I21:I29) -> 993.15437 | J30: =SUM(J21:J29) -> 1751.4015 | K30: =SUM(K21:K29) -> 2094.1266 | M30: =SUM(M21:M29) -> 342.72508 | N30: =K30/J30-1 -> 0.19568618
B32: =+'P&L Forecast'!B42 -> Software & Apps - COGS | C32: =+'P&L Forecast'!C42 -> 114.42269 | D32: =+'P&L Forecast'!D42 -> 157.49471 | F32: =+'P&L Forecast'!F42 -> 84.96859 | G32: =+'P&L Forecast'!G42 -> 152.28157 | I32: =+'P&L Forecast'!I42 -> 142.28345 | J32: =+'P&L Forecast'!J42 -> 224.80769 | K32: =+'P&L Forecast'!K42 -> 335.70816 | M32: =K32-J32 -> 110.90047 | N32: =IFERROR(K32/J32-1,0) -> 0.49331262
B33: =+'P&L Forecast'!B43 -> Software & Apps - G&A | C33: =+'P&L Forecast'!C43 -> 60.91594 | D33: =+'P&L Forecast'!D43 -> 117.05866 | F33: =+'P&L Forecast'!F43 -> 56.8115 | G33: =+'P&L Forecast'!G43 -> 97.04798 | I33: =+'P&L Forecast'!I43 -> 86.51489 | J33: =+'P&L Forecast'!J43 -> 157.29514 | K33: =+'P&L Forecast'!K43 -> 155.82264 | M33: =K33-J33 -> -1.4725 | N33: =IFERROR(K33/J33-1,0) -> -0.0093613827
B34: =+'P&L Forecast'!B44 -> Software & Apps - Topkey | C34: =+'P&L Forecast'!C44 -> 0 | D34: =+'P&L Forecast'!D44 -> 7.14125 | F34: =+'P&L Forecast'!F44 -> 0 | G34: =+'P&L Forecast'!G44 -> 28.82775 | I34: =+'P&L Forecast'!I44 -> 0 | J34: =+'P&L Forecast'!J44 -> 35.969 | K34: =+'P&L Forecast'!K44 -> 60.84 | M34: =K34-J34 -> 24.871 | N34: =IFERROR(K34/J34-1,0) -> 0.69145653
B35: =+'P&L Forecast'!B45 -> Software & Apps - AI tools | C35: =+'P&L Forecast'!C45 -> 0 | D35: =+'P&L Forecast'!D45 -> 0 | F35: =+'P&L Forecast'!F45 -> 0 | G35: =+'P&L Forecast'!G45 -> 6.52752 | I35: =+'P&L Forecast'!I45 -> 0 | J35: =+'P&L Forecast'!J45 -> 6.52752 | K35: =+'P&L Forecast'!K45 -> 15.74376 | M35: =K35-J35 -> 9.21624 | N35: =IFERROR(K35/J35-1,0) -> 1.4119053
B36: =+'P&L Forecast'!B46 -> Total Software Expenses | C36: =SUM(C32:C35) -> 175.33863 | D36: =SUM(D32:D35) -> 281.69462 | F36: =SUM(F32:F35) -> 141.78009 | G36: =SUM(G32:G35) -> 284.68482 | I36: =SUM(I32:I35) -> 228.79834 | J36: =SUM(J32:J35) -> 424.59935 | K36: =SUM(K32:K35) -> 568.11456 | M36: =SUM(M32:M35) -> 143.51521 | N36: =K36/J36-1 -> 0.33800148
B38: =+'P&L Forecast'!B48 -> Other Professional Fees | C38: =+'P&L Forecast'!C48 -> 18.23425 | D38: =+'P&L Forecast'!D48 -> 27.04095 | F38: =+'P&L Forecast'!F48 -> 12.014 | G38: =+'P&L Forecast'!G48 -> 57.55 | I38: =+'P&L Forecast'!I48 -> 21.74858 | J38: =+'P&L Forecast'!J48 -> 72.57695 | K38: =+'P&L Forecast'!K48 -> 72.57695 | M38: =K38-J38 -> 0 | N38: =IFERROR(K38/J38-1,0) -> 0
B39: =+'P&L Forecast'!B49 -> Referral Fees | C39: =+'P&L Forecast'!C49 -> 24.82 | D39: =+'P&L Forecast'!D49 -> 27.15374 | F39: =+'P&L Forecast'!F49 -> 17.0895 | G39: =+'P&L Forecast'!G49 -> 20.62969 | I39: =+'P&L Forecast'!I49 -> 26.2095 | J39: =+'P&L Forecast'!J49 -> 30.69393 | K39: =+'P&L Forecast'!K49 -> 30.69393 | M39: =K39-J39 -> 0 | N39: =IFERROR(K39/J39-1,0) -> 0
B40: =+'P&L Forecast'!B50 -> Travel, Meals & Entertainment | C40: =+'P&L Forecast'!C50 -> 0 | D40: =+'P&L Forecast'!D50 -> 29.76122 | F40: =+'P&L Forecast'!F50 -> 22.29558 | G40: =+'P&L Forecast'!G50 -> 20.68542 | I40: =+'P&L Forecast'!I50 -> 22.29558 | J40: =+'P&L Forecast'!J50 -> 28.15106 | K40: =+'P&L Forecast'!K50 -> 28.15106 | M40: =K40-J40 -> 0 | N40: =IFERROR(K40/J40-1,0) -> 0
B41: =+'P&L Forecast'!B51 -> Payment Collection Fees | C41: =+'P&L Forecast'!C51 -> 8.67099 | D41: =+'P&L Forecast'!D51 -> 13.35153 | F41: =+'P&L Forecast'!F51 -> 6.80445 | G41: =+'P&L Forecast'!G51 -> 9.02684 | I41: =+'P&L Forecast'!I51 -> 10.54373 | J41: =+'P&L Forecast'!J51 -> 15.57392 | K41: =+'P&L Forecast'!K51 -> 15.57392 | M41: =K41-J41 -> 0 | N41: =IFERROR(K41/J41-1,0) -> 0
B42: =+'P&L Forecast'!B52 -> Professional Organizations | C42: =+'P&L Forecast'!C52 -> 5.44332 | D42: =+'P&L Forecast'!D52 -> 11.22296 | F42: =+'P&L Forecast'!F52 -> 6.191 | G42: =+'P&L Forecast'!G52 -> 6.57881 | I42: =+'P&L Forecast'!I52 -> 9.53268 | J42: =+'P&L Forecast'!J52 -> 11.61077 | K42: =+'P&L Forecast'!K52 -> 11.61077 | M42: =K42-J42 -> 0 | N42: =IFERROR(K42/J42-1,0) -> 0
B43: =+'P&L Forecast'!B53 -> S&M Events | C43: =+'P&L Forecast'!C53 -> 0 | D43: =+'P&L Forecast'!D53 -> 11.4983 | F43: =+'P&L Forecast'!F53 -> 0 | G43: =+'P&L Forecast'!G53 -> 11.84548 | I43: =+'P&L Forecast'!I53 -> 0 | J43: =+'P&L Forecast'!J53 -> 23.34378 | K43: =+'P&L Forecast'!K53 -> 23.34378 | M43: =K43-J43 -> 0 | N43: =IFERROR(K43/J43-1,0) -> 0
B44: =+'P&L Forecast'!B54 -> Contract Labor - Tax | C44: =+'P&L Forecast'!C54 -> 0 | D44: =+'P&L Forecast'!D54 -> 1.5875 | F44: =+'P&L Forecast'!F54 -> 0 | G44: =+'P&L Forecast'!G54 -> 30.5155 | I44: =+'P&L Forecast'!I54 -> 0 | J44: =+'P&L Forecast'!J54 -> 32.103 | K44: =+'P&L Forecast'!K54 -> 38.7615 | M44: =K44-J44 -> 6.6585 | N44: =IFERROR(K44/J44-1,0) -> 0.20741052
B45: =+'P&L Forecast'!B55 -> Recruiting Fees | C45: =+'P&L Forecast'!C55 -> 14.90205 | D45: =+'P&L Forecast'!D55 -> 31.6041 | F45: =+'P&L Forecast'!F55 -> 28.29994 | G45: =+'P&L Forecast'!G55 -> 5.5646 | I45: =+'P&L Forecast'!I55 -> 35.34606 | J45: =+'P&L Forecast'!J55 -> 8.86876 | K45: =+'P&L Forecast'!K55 -> 8.86876 | M45: =K45-J45 -> 0 | N45: =IFERROR(K45/J45-1,0) -> 0
B46: Other Expenses | C46: =+C47-SUM(C38:C45) -> 41.87929 | D46: =+D47-SUM(D38:D45) -> 52.32132 | F46: =+F47-SUM(F38:F45) -> 28.90542 | G46: =+G47-SUM(G38:G45) -> 26.90445 | I46: =+I47-SUM(I38:I45) -> 41.76881 | J46: =+J47-SUM(J38:J45) -> 50.32035 | K46: =+K47-SUM(K38:K45) -> 56.05462 | M46: =K46-J46 -> 5.73427 | N46: =IFERROR(K46/J46-1,0) -> 0.11395529
B47: Total Overhead | C47: =+'P&L Forecast'!C66 -> 113.9499 | D47: =+'P&L Forecast'!D66 -> 205.54162 | F47: =+'P&L Forecast'!F66 -> 121.59989 | G47: =+'P&L Forecast'!G66 -> 189.30079 | I47: =+'P&L Forecast'!I66 -> 167.44494 | J47: =+'P&L Forecast'!J66 -> 273.24252 | K47: =+'P&L Forecast'!K66 -> 285.63529 | M47: =SUM(M38:M46) -> 12.39277 | N47: =K47/J47-1 -> 0.045354471
B49: Net Income | C49: =+C16-C30-C36-C47 -> 145.47185 | D49: =+D16-D30-D36-D47 -> 130.9803 | F49: =+F16-F30-F36-F47 -> 103.83598 | G49: =+G16-G30-G36-G47 -> 76.1435 | I49: =+I16-I30-I36-I47 -> 135.013 | J49: =+J16-J30-J36-J47 -> 103.28782 | K49: =+K16-K30-K36-K47 -> 50.66455 | M49: =+M16-M30-M36-M47 -> -52.62327 | N49: =IFERROR(K49/J49-1,0) -> -0.50948185
B50: % Margin | C50: =C49/C$16 -> 0.12817289 | D50: =D49/D$16 -> 0.06969324 | F50: =F49/F$16 -> 0.1040573 | G50: =G49/G$16 -> 0.045567046 | I50: =I49/I$16 -> 0.088567342 | J50: =J49/J$16 -> 0.04046486 | K50: =K49/K$16 -> 0.016896401 | M50: =M49/M$16 -> -0.1179868 | N50: 0
B52: P&L Adjustments
B53: Karbon, Uncat, & Xenett Savings | C53: =+'P&L Forecast'!C91 -> 0 | D53: =+'P&L Forecast'!D91 -> 0 | F53: =+'P&L Forecast'!F91 -> 0 | G53: =+'P&L Forecast'!G91 -> 0 | I53: =+'P&L Forecast'!I91 -> 0 | J53: =+'P&L Forecast'!J91 -> 0 | K53: =+'P&L Forecast'!K91 -> 96.8 | M53: =K53-J53 -> 96.8 | N53: =IFERROR(K53/J53-1,0) -> 0
B54: Other Professional Fees | C54: =+'P&L Forecast'!C90 -> 18.23425 | D54: =+'P&L Forecast'!D90 -> 27.04095 | F54: =+'P&L Forecast'!F90 -> 12.014 | G54: =+'P&L Forecast'!G90 -> 57.55 | I54: =+'P&L Forecast'!I90 -> 21.74858 | J54: =+'P&L Forecast'!J90 -> 72.57695 | K54: =+'P&L Forecast'!K90 -> 72.57695 | M54: =K54-J54 -> 0 | N54: =IFERROR(K54/J54-1,0) -> 0
B55: Unclassified Active Client Contribution | C55: =+'P&L Forecast'!C92 -> 0 | D55: =+'P&L Forecast'!D92 -> 0 | F55: =+'P&L Forecast'!F92 -> 0 | G55: =+'P&L Forecast'!G92 -> 0 | I55: =+'P&L Forecast'!I92 -> 0 | J55: =+'P&L Forecast'!J92 -> 0 | K55: =+'P&L Forecast'!K92 -> 50.703313 | M55: =K55-J55 -> 50.703313 | N55: =IFERROR(K55/J55-1,0) -> 0
B56: Definitional EBITDA Adj. | C56: =SUM('P&L Forecast'!C75:C77) -> 14.24964 | D56: =SUM('P&L Forecast'!D75:D77) -> 18.07948 | F56: =SUM('P&L Forecast'!F75:F77) -> 6.97104 | G56: =SUM('P&L Forecast'!G75:G77) -> 1.98303 | I56: =SUM('P&L Forecast'!I75:I77) -> 12.50268 | J56: =SUM('P&L Forecast'!J75:J77) -> 13.09147 | K56: =SUM('P&L Forecast'!K75:K77) -> 13.09147 | M56: =K56-J56 -> 0 | N56: =IFERROR(K56/J56-1,0) -> 0
B57: Personal Expenses | C57: =+'P&L Forecast'!C82+'P&L Forecast'!C83 -> 1.05983 | D57: =+'P&L Forecast'!D82+'P&L Forecast'!D83 -> 5.99533 | F57: =+'P&L Forecast'!F82+'P&L Forecast'!F83 -> 2.02633 | G57: =+'P&L Forecast'!G82+'P&L Forecast'!G83 -> 1.943 | I57: =+'P&L Forecast'!I82+'P&L Forecast'!I83 -> 2.45133 | J57: =+'P&L Forecast'!J82+'P&L Forecast'!J83 -> 5.912 | K57: =+'P&L Forecast'!K82+'P&L Forecast'!K83 -> 5.912 | M57: =K57-J57 -> 0 | N57: =IFERROR(K57/J57-1,0) -> 0
B58: Onboarding Manager | C58: =+'P&L Forecast'!C89 -> 0 | D58: =+'P&L Forecast'!D89 -> 0 | F58: =+'P&L Forecast'!F89 -> 0 | G58: =+'P&L Forecast'!G89 -> 0 | I58: =+'P&L Forecast'!I89 -> 0 | J58: =+'P&L Forecast'!J89 -> 0 | K58: =+'P&L Forecast'!K89 -> -116.25 | M58: =K58-J58 -> -116.25 | N58: =IFERROR(K58/J58-1,0) -> 0
B59: Go-Forward Owner Comp | C59: =+'P&L Forecast'!C88 -> -228.245 | D59: =+'P&L Forecast'!D88 -> -137.57796 | F59: =+'P&L Forecast'!F88 -> -182.77888 | G59: =+'P&L Forecast'!G88 -> -165.10198 | I59: =+'P&L Forecast'!I88 -> -182.77888 | J59: =+'P&L Forecast'!J88 -> -119.90106 | K59: =+'P&L Forecast'!K88 -> -119.90106 | M59: =K59-J59 -> 0 | N59: =IFERROR(K59/J59-1,0) -> 0
B60: Total Near-Term Adjustments | C60: =SUM(C53:C59) -> -194.70128 | D60: =SUM(D53:D59) -> -86.4622 | F60: =SUM(F53:F59) -> -161.76751 | G60: =SUM(G53:G59) -> -103.62595 | I60: =SUM(I53:I59) -> -146.07629 | J60: =SUM(J53:J59) -> -28.32064 | K60: =SUM(K53:K59) -> 2.9326728 | M60: =SUM(M53:M59) -> 31.253313 | N60: =K60/J60-1 -> -1.1035525
B62: =+'P&L Forecast'!B95 -> Near-Term Adj. EBITDA | C62: =+C49+C60 -> -49.22943 | D62: =+D49+D60 -> 44.5181 | F62: =+F49+F60 -> -57.93153 | G62: =+G49+G60 -> -27.48245 | I62: =+I49+I60 -> -11.06329 | J62: =+J49+J60 -> 74.96718 | K62: =+K49+K60 -> 53.597223 | M62: =+M49+M60 -> -21.369957 | N62: =IFERROR(K62/J62-1,0) -> -0.2850575
B63: % Margin | C63: =C62/C$18 -> -0.043375252 | D63: =D62/D$18 -> 0.023687613 | F63: =F62/F$18 -> -0.058055007 | G63: =G62/G$18 -> -0.0164465 | I63: =I62/I$18 -> -0.0072574211 | J63: =J62/J$18 -> 0.029369741 | K63: =K62/K$18 -> 0.017331224 | M63: =M62/M$16 -> -0.047913651 | N63: 0
B65: Normalized Bookkeeper Staffing | C65: =+'P&L Forecast'!C101 -> 0 | D65: =+'P&L Forecast'!D101 -> 0 | F65: =+'P&L Forecast'!F101 -> 0 | G65: =+'P&L Forecast'!G101 -> 0 | I65: =+'P&L Forecast'!I101 -> 0 | J65: =+'P&L Forecast'!J101 -> 0 | K65: =+'P&L Forecast'!K101 -> 220.13063 | M65: =K65-J65 -> 220.13063 | N65: =IFERROR(K65/J65-1,0) -> 0
B66: VR Platform Cost Savings | C66: =+'P&L Forecast'!C102 -> 0 | D66: =+'P&L Forecast'!D102 -> 0 | F66: =+'P&L Forecast'!F102 -> 0 | G66: =+'P&L Forecast'!G102 -> 0 | I66: =+'P&L Forecast'!I102 -> 0 | J66: =+'P&L Forecast'!J102 -> 0 | K66: =+'P&L Forecast'!K102 -> 143.23972 | M66: =K66-J66 -> 143.23972 | N66: =IFERROR(K66/J66-1,0) -> 0
B67: Onboarding Team Wages | C67: =+'P&L Forecast'!C100 -> 0 | D67: =+'P&L Forecast'!D100 -> 0 | F67: =+'P&L Forecast'!F100 -> 0 | G67: =+'P&L Forecast'!G100 -> 0 | I67: =+'P&L Forecast'!I100 -> 0 | J67: =+'P&L Forecast'!J100 -> 0 | K67: =+'P&L Forecast'!K100 -> 49.28736 | M67: =K67-J67 -> 49.28736 | N67: =IFERROR(K67/J67-1,0) -> 0
B68: S&M Wages | C68: =+'P&L Forecast'!C103 -> 0 | D68: =+'P&L Forecast'!D103 -> 0 | F68: =+'P&L Forecast'!F103 -> 0 | G68: =+'P&L Forecast'!G103 -> 0 | I68: =+'P&L Forecast'!I103 -> 0 | J68: =+'P&L Forecast'!J103 -> 0 | K68: =+'P&L Forecast'!K103 -> 28.2 | M68: =K68-J68 -> 28.2 | N68: =IFERROR(K68/J68-1,0) -> 0
B69: Onboarding Revenue | C69: =+'P&L Forecast'!C99 -> 0 | D69: =+'P&L Forecast'!D99 -> 0 | F69: =+'P&L Forecast'!F99 -> 0 | G69: =+'P&L Forecast'!G99 -> 0 | I69: =+'P&L Forecast'!I99 -> 0 | J69: =+'P&L Forecast'!J99 -> 0 | K69: =+'P&L Forecast'!K99 -> -25.891875 | M69: =K69-J69 -> -25.891875 | N69: =IFERROR(K69/J69-1,0) -> 0
B70: Total Steady-State Adj. | C70: =SUM(C65:C69) -> 0 | D70: =SUM(D65:D69) -> 0 | F70: =SUM(F65:F69) -> 0 | G70: =SUM(G65:G69) -> 0 | I70: =SUM(I65:I69) -> 0 | J70: =SUM(J65:J69) -> 0 | K70: =SUM(K65:K69) -> 414.96583 | M70: =SUM(M65:M69) -> 414.96583 | N70: =IFERROR(K70/J70-1,0) -> 0
B72: =+'P&L Forecast'!B106 -> Steady-State Adj. EBITDA | C72: =+C70+C62 -> -49.22943 | D72: =+D70+D62 -> 44.5181 | F72: =+F70+F62 -> -57.93153 | G72: =+G70+G62 -> -27.48245 | I72: =+I70+I62 -> -11.06329 | J72: =+J70+J62 -> 74.96718 | K72: =+K70+K62 -> 468.56306 | M72: =+M70+M62 -> 393.59588 | N72: =IFERROR(K72/J72-1,0) -> 5.2502425
B73: % Margin | C73: =C72/C$18 -> -0.043375252 | D73: =D72/D$18 -> 0.023687613 | F73: =F72/F$18 -> -0.058055007 | G73: =G72/G$18 -> -0.0164465 | I73: =I72/I$18 -> -0.0072574211 | J73: =J72/J$18 -> 0.029369741 | K73: =K72/K$18 -> 0.15151478 | M73: =M72/M$16 -> 0.8824826 | N73: 0

Sheet Software Overview
B2: =+Cover!B24 -> Keystone Bookkeepers
B3: Software Utilization Overview ($)
B5: Software Utilization | C5: Current Clients | G5: Former Clients | K5: Total
B6: Bill Pay | C6: Clients | D6: Properties | E6: Avg. Monthly Fee | G6: Clients | H6: Properties | I6: Avg. Monthly Fee | K6: Clients | L6: Properties | M6: % of Clients
B7: Yes | C7: =COUNTIFS('Customer List w Software'!$B$4:$B$310,"<>Former client",'Customer List w Software'!$V$4:$V$310,$B7) -> 41 | D7: =SUMIFS('Customer List w Software'!$K$4:$K$310,'Customer List w Software'!$B$4:$B$310,"<>Former client",'Customer List w Software'!$V$4:$V$310,$B7) -> 1285 | E7: =IFERROR(AVERAGEIFS('Customer List w Software'!$J$4:$J$310,'Customer List w Software'!$B$4:$B$310,"<>Former client",'Customer List w Software'!$V$4:$V$310,$B7),0) -> 2011.8227 | G7: =COUNTIFS('Customer List w Software'!$B$4:$B$310,"Former client",'Customer List w Software'!$V$4:$V$310,$B7) -> 4 | H7: =SUMIFS('Customer List w Software'!$K$4:$K$310,'Customer List w Software'!$B$4:$B$310,"Former client",'Customer List w Software'!$V$4:$V$310,$B7) -> 72 | I7: =IFERROR(AVERAGEIFS('Customer List w Software'!$J$4:$J$310,'Customer List w Software'!$B$4:$B$310,"Former client",'Customer List w Software'!$V$4:$V$310,$B7),0) -> 1602.6667 | K7: =C7+G7 -> 45 | L7: =D7+H7 -> 1357 | M7: =K7/K$10 -> 0.1465798
B8: No | C8: =COUNTIFS('Customer List w Software'!$B$4:$B$310,"<>Former client",'Customer List w Software'!$V$4:$V$310,$B8) -> 133 | D8: =SUMIFS('Customer List w Software'!$K$4:$K$310,'Customer List w Software'!$B$4:$B$310,"<>Former client",'Customer List w Software'!$V$4:$V$310,$B8) -> 2472 | E8: =IFERROR(AVERAGEIFS('Customer List w Software'!$J$4:$J$310,'Customer List w Software'!$B$4:$B$310,"<>Former client",'Customer List w Software'!$V$4:$V$310,$B8),0) -> 1186.0576 | G8: =COUNTIFS('Customer List w Software'!$B$4:$B$310,"Former client",'Customer List w Software'!$V$4:$V$310,$B8) -> 52 | H8: =SUMIFS('Customer List w Software'!$K$4:$K$310,'Customer List w Software'!$B$4:$B$310,"Former client",'Customer List w Software'!$V$4:$V$310,$B8) -> 352 | I8: =IFERROR(AVERAGEIFS('Customer List w Software'!$J$4:$J$310,'Customer List w Software'!$B$4:$B$310,"Former client",'Customer List w Software'!$V$4:$V$310,$B8),0) -> 631.64103 | K8: =C8+G8 -> 185 | L8: =D8+H8 -> 2824 | M8: =K8/K$10 -> 0.60260586
B9: Not Designated | C9: =COUNTIFS('Customer List w Software'!$B$4:$B$310,"<>Former client",'Customer List w Software'!$V$4:$V$310,"") -> 0 | D9: =SUMIFS('Customer List w Software'!$K$4:$K$310,'Customer List w Software'!$B$4:$B$310,"<>Former client",'Customer List w Software'!$V$4:$V$310,"") -> 0 | E9: =IFERROR(AVERAGEIFS('Customer List w Software'!$J$4:$J$310,'Customer List w Software'!$B$4:$B$310,"<>Former client",'Customer List w Software'!$V$4:$V$310,""),0) -> 0 | G9: =COUNTIFS('Customer List w Software'!$B$4:$B$310,"Former client",'Customer List w Software'!$V$4:$V$310,"") -> 77 | H9: =SUMIFS('Customer List w Software'!$K$4:$K$310,'Customer List w Software'!$B$4:$B$310,"Former client",'Customer List w Software'!$V$4:$V$310,"") -> 30 | I9: =IFERROR(AVERAGEIFS('Customer List w Software'!$J$4:$J$310,'Customer List w Software'!$B$4:$B$310,"Former client",'Customer List w Software'!$V$4:$V$310,""),0) -> 592.10266 | K9: =C9+G9 -> 77 | L9: =D9+H9 -> 30 | M9: =K9/K$10 -> 0.25081433
B10: Total Clients | C10: =COUNTIFS('Customer List w Software'!$B$4:$B$310,"<>Former client") -> 174 | D10: =SUMIFS('Customer List w Software'!$K$4:$K$310,'Customer List w Software'!$B$4:$B$310,"<>Former client") -> 3757 | E10: =AVERAGEIFS('Customer List w Software'!$J$4:$J$310,'Customer List w Software'!$B$4:$B$310,"<>Former client") -> 1380.6344 | G10: =COUNTIFS('Customer List w Software'!$B$4:$B$310,"Former client") -> 133 | H10: =SUMIFS('Customer List w Software'!$K$4:$K$310,'Customer List w Software'!$B$4:$B$310,"Former client") -> 454 | I10: =AVERAGEIFS('Customer List w Software'!$J$4:$J$310,'Customer List w Software'!$B$4:$B$310,"Former client") -> 637.95417 | K10: =C10+G10 -> 307 | L10: =D10+H10 -> 4211 | M10: =K10/K$10 -> 1
B12: Trust / Accounting Software
B13: VRT | C13: =COUNTIFS('Customer List w Software'!$B$4:$B$310,"<>Former client",'Customer List w Software'!$W$4:$W$310,$B13) -> 117 | D13: =SUMIFS('Customer List w Software'!$K$4:$K$310,'Customer List w Software'!$B$4:$B$310,"<>Former client",'Customer List w Software'!$W$4:$W$310,$B13) -> 2999 | E13: =IFERROR(AVERAGEIFS('Customer List w Software'!$J$4:$J$310,'Customer List w Software'!$B$4:$B$310,"<>Former client",'Customer List w Software'!$W$4:$W$310,$B13),0) -> 1521.7699 | G13: =COUNTIFS('Customer List w Software'!$B$4:$B$310,"Former client",'Customer List w Software'!$W$4:$W$310,$B13) -> 6 | H13: =SUMIFS('Customer List w Software'!$K$4:$K$310,'Customer List w Software'!$B$4:$B$310,"Former client",'Customer List w Software'!$W$4:$W$310,$B13) -> 84 | I13: =IFERROR(AVERAGEIFS('Customer List w Software'!$J$4:$J$310,'Customer List w Software'!$B$4:$B$310,"Former client",'Customer List w Software'!$W$4:$W$310,$B13),0) -> 1230.2222 | K13: =C13+G13 -> 123 | L13: =D13+H13 -> 3083 | M13: =K13/K$18 -> 0.40065147
B14: VRP | C14: =COUNTIFS('Customer List w Software'!$B$4:$B$310,"<>Former client",'Customer List w Software'!$W$4:$W$310,$B14) -> 36 | D14: =SUMIFS('Customer List w Software'!$K$4:$K$310,'Customer List w Software'!$B$4:$B$310,"<>Former client",'Customer List w Software'!$W$4:$W$310,$B14) -> 659 | E14: =IFERROR(AVERAGEIFS('Customer List w Software'!$J$4:$J$310,'Customer List w Software'!$B$4:$B$310,"<>Former client",'Customer List w Software'!$W$4:$W$310,$B14),0) -> 1378.1986 | G14: =COUNTIFS('Customer List w Software'!$B$4:$B$310,"Former client",'Customer List w Software'!$W$4:$W$310,$B14) -> 8 | H14: =SUMIFS('Customer List w Software'!$K$4:$K$310,'Customer List w Software'!$B$4:$B$310,"Former client",'Customer List w Software'!$W$4:$W$310,$B14) -> 123 | I14: =IFERROR(AVERAGEIFS('Customer List w Software'!$J$4:$J$310,'Customer List w Software'!$B$4:$B$310,"Former client",'Customer List w Software'!$W$4:$W$310,$B14),0) -> 1073.6042 | K14: =C14+G14 -> 44 | L14: =D14+H14 -> 782 | M14: =K14/K$18 -> 0.14332248
B15: Guesty | C15: =COUNTIFS('Customer List w Software'!$B$4:$B$310,"<>Former client",'Customer List w Software'!$W$4:$W$310,$B15) -> 2 | D15: =SUMIFS('Customer List w Software'!$K$4:$K$310,'Customer List w Software'!$B$4:$B$310,"<>Former client",'Customer List w Software'!$W$4:$W$310,$B15) -> 47 | E15: =IFERROR(AVERAGEIFS('Customer List w Software'!$J$4:$J$310,'Customer List w Software'!$B$4:$B$310,"<>Former client",'Customer List w Software'!$W$4:$W$310,$B15),0) -> 1226.1667 | G15: =COUNTIFS('Customer List w Software'!$B$4:$B$310,"Former client",'Customer List w Software'!$W$4:$W$310,$B15) -> 2 | H15: =SUMIFS('Customer List w Software'!$K$4:$K$310,'Customer List w Software'!$B$4:$B$310,"Former client",'Customer List w Software'!$W$4:$W$310,$B15) -> 17 | I15: =IFERROR(AVERAGEIFS('Customer List w Software'!$J$4:$J$310,'Customer List w Software'!$B$4:$B$310,"Former client",'Customer List w Software'!$W$4:$W$310,$B15),0) -> 841.83333 | K15: =C15+G15 -> 4 | L15: =D15+H15 -> 64 | M15: =K15/K$18 -> 0.013029316
B16: Clearing | C16: =COUNTIFS('Customer List w Software'!$B$4:$B$310,"<>Former client",'Customer List w Software'!$W$4:$W$310,$B16) -> 1 | D16: =SUMIFS('Customer List w Software'!$K$4:$K$310,'Customer List w Software'!$B$4:$B$310,"<>Former client",'Customer List w Software'!$W$4:$W$310,$B16) -> 15 | E16: =IFERROR(AVERAGEIFS('Customer List w Software'!$J$4:$J$310,'Customer List w Software'!$B$4:$B$310,"<>Former client",'Customer List w Software'!$W$4:$W$310,$B16),0) -> 1662.5 | G16: =COUNTIFS('Customer List w Software'!$B$4:$B$310,"Former client",'Customer List w Software'!$W$4:$W$310,$B16) -> 3 | H16: =SUMIFS('Customer List w Software'!$K$4:$K$310,'Customer List w Software'!$B$4:$B$310,"Former client",'Customer List w Software'!$W$4:$W$310,$B16) -> 34 | I16: =IFERROR(AVERAGEIFS('Customer List w Software'!$J$4:$J$310,'Customer List w Software'!$B$4:$B$310,"Former client",'Customer List w Software'!$W$4:$W$310,$B16),0) -> 723.22222 | K16: =C16+G16 -> 4 | L16: =D16+H16 -> 49 | M16: =K16/K$18 -> 0.013029316
B17: None | C17: =COUNTIFS('Customer List w Software'!$B$4:$B$310,"<>Former client",'Customer List w Software'!$W$4:$W$310,"") -> 18 | D17: =SUMIFS('Customer List w Software'!$K$4:$K$310,'Customer List w Software'!$B$4:$B$310,"<>Former client",'Customer List w Software'!$W$4:$W$310,"") -> 37 | E17: =IFERROR(AVERAGEIFS('Customer List w Software'!$J$4:$J$310,'Customer List w Software'!$B$4:$B$310,"<>Former client",'Customer List w Software'!$W$4:$W$310,""),0) -> 469.62963 | G17: =COUNTIFS('Customer List w Software'!$B$4:$B$310,"Former client",'Customer List w Software'!$W$4:$W$310,"") -> 114 | H17: =SUMIFS('Customer List w Software'!$K$4:$K$310,'Customer List w Software'!$B$4:$B$310,"Former client",'Customer List w Software'!$W$4:$W$310,"") -> 196 | I17: =IFERROR(AVERAGEIFS('Customer List w Software'!$J$4:$J$310,'Customer List w Software'!$B$4:$B$310,"Former client",'Customer List w Software'!$W$4:$W$310,""),0) -> 570.38952 | K17: =C17+G17 -> 132 | L17: =D17+H17 -> 233 | M17: =K17/K$18 -> 0.42996743
B18: Total Clients | C18: =COUNTIFS('Customer List w Software'!$B$4:$B$310,"<>Former client") -> 174 | D18: =SUMIFS('Customer List w Software'!$K$4:$K$310,'Customer List w Software'!$B$4:$B$310,"<>Former client") -> 3757 | E18: =AVERAGEIFS('Customer List w Software'!$J$4:$J$310,'Customer List w Software'!$B$4:$B$310,"<>Former client") -> 1380.6344 | G18: =COUNTIFS('Customer List w Software'!$B$4:$B$310,"Former client") -> 133 | H18: =SUMIFS('Customer List w Software'!$K$4:$K$310,'Customer List w Software'!$B$4:$B$310,"Former client") -> 454 | I18: =AVERAGEIFS('Customer List w Software'!$J$4:$J$310,'Customer List w Software'!$B$4:$B$310,"Former client") -> 637.95417 | K18: =C18+G18 -> 307 | L18: =D18+H18 -> 4211 | M18: =K18/K$18 -> 1
B20: Property Management System (PMS)
B21: Guesty | C21: =COUNTIFS('Customer List w Software'!$B$4:$B$310,"<>Former client",'Customer List w Software'!$X$4:$X$310,$B21) -> 51 | D21: =SUMIFS('Customer List w Software'!$K$4:$K$310,'Customer List w Software'!$B$4:$B$310,"<>Former client",'Customer List w Software'!$X$4:$X$310,$B21) -> 1338 | E21: =IFERROR(AVERAGEIFS('Customer List w Software'!$J$4:$J$310,'Customer List w Software'!$B$4:$B$310,"<>Former client",'Customer List w Software'!$X$4:$X$310,$B21),0) -> 1661.0776 | G21: =COUNTIFS('Customer List w Software'!$B$4:$B$310,"Former client",'Customer List w Software'!$X$4:$X$310,$B21) -> 6 | H21: =SUMIFS('Customer List w Software'!$K$4:$K$310,'Customer List w Software'!$B$4:$B$310,"Former client",'Customer List w Software'!$X$4:$X$310,$B21) -> 70 | I21: =IFERROR(AVERAGEIFS('Customer List w Software'!$J$4:$J$310,'Customer List w Software'!$B$4:$B$310,"Former client",'Customer List w Software'!$X$4:$X$310,$B21),0) -> 976.33333 | K21: =C21+G21 -> 57 | L21: =D21+H21 -> 1408 | M21: =K21/K$29 -> 0.18566775
B22: Hospitable | C22: =COUNTIFS('Customer List w Software'!$B$4:$B$310,"<>Former client",'Customer List w Software'!$X$4:$X$310,$B22) -> 48 | D22: =SUMIFS('Customer List w Software'!$K$4:$K$310,'Customer List w Software'!$B$4:$B$310,"<>Former client",'Customer List w Software'!$X$4:$X$310,$B22) -> 829 | E22: =IFERROR(AVERAGEIFS('Customer List w Software'!$J$4:$J$310,'Customer List w Software'!$B$4:$B$310,"<>Former client",'Customer List w Software'!$X$4:$X$310,$B22),0) -> 1090.3717 | G22: =COUNTIFS('Customer List w Software'!$B$4:$B$310,"Former client",'Customer List w Software'!$X$4:$X$310,$B22) -> 2 | H22: =SUMIFS('Customer List w Software'!$K$4:$K$310,'Customer List w Software'!$B$4:$B$310,"Former client",'Customer List w Software'!$X$4:$X$310,$B22) -> 0 | I22: =IFERROR(AVERAGEIFS('Customer List w Software'!$J$4:$J$310,'Customer List w Software'!$B$4:$B$310,"Former client",'Customer List w Software'!$X$4:$X$310,$B22),0) -> 459 | K22: =C22+G22 -> 50 | L22: =D22+H22 -> 829 | M22: =K22/K$29 -> 0.16286645
B23: OwnerRez | C23: =COUNTIFS('Customer List w Software'!$B$4:$B$310,"<>Former client",'Customer List w Software'!$X$4:$X$310,$B23) -> 24 | D23: =SUMIFS('Customer List w Software'!$K$4:$K$310,'Customer List w Software'!$B$4:$B$310,"<>Former client",'Customer List w Software'!$X$4:$X$310,$B23) -> 438 | E23: =IFERROR(AVERAGEIFS('Customer List w Software'!$J$4:$J$310,'Customer List w Software'!$B$4:$B$310,"<>Former client",'Customer List w Software'!$X$4:$X$310,$B23),0) -> 1275.3854 | G23: =COUNTIFS('Customer List w Software'!$B$4:$B$310,"Former client",'Customer List w Software'!$X$4:$X$310,$B23) -> 5 | H23: =SUMIFS('Customer List w Software'!$K$4:$K$310,'Customer List w Software'!$B$4:$B$310,"Former client",'Customer List w Software'!$X$4:$X$310,$B23) -> 48 | I23: =IFERROR(AVERAGEIFS('Customer List w Software'!$J$4:$J$310,'Customer List w Software'!$B$4:$B$310,"Former client",'Customer List w Software'!$X$4:$X$310,$B23),0) -> 833.16667 | K23: =C23+G23 -> 29 | L23: =D23+H23 -> 486 | M23: =K23/K$29 -> 0.094462541
B24: Hostaway | C24: =COUNTIFS('Customer List w Software'!$B$4:$B$310,"<>Former client",'Customer List w Software'!$X$4:$X$310,$B24) -> 20 | D24: =SUMIFS('Customer List w Software'!$K$4:$K$310,'Customer List w Software'!$B$4:$B$310,"<>Former client",'Customer List w Software'!$X$4:$X$310,$B24) -> 544 | E24: =IFERROR(AVERAGEIFS('Customer List w Software'!$J$4:$J$310,'Customer List w Software'!$B$4:$B$310,"<>Former client",'Customer List w Software'!$X$4:$X$310,$B24),0) -> 1667.55 | G24: =COUNTIFS('Customer List w Software'!$B$4:$B$310,"Former client",'Customer List w Software'!$X$4:$X$310,$B24) -> 2 | H24: =SUMIFS('Customer List w Software'!$K$4:$K$310,'Customer List w Software'!$B$4:$B$310,"Former client",'Customer List w Software'!$X$4:$X$310,$B24) -> 29 | I24: =IFERROR(AVERAGEIFS('Customer List w Software'!$J$4:$J$310,'Customer List w Software'!$B$4:$B$310,"Former client",'Customer List w Software'!$X$4:$X$310,$B24),0) -> 375 | K24: =C24+G24 -> 22 | L24: =D24+H24 -> 573 | M24: =K24/K$29 -> 0.071661238
B25: Hostfully | C25: =COUNTIFS('Customer List w Software'!$B$4:$B$310,"<>Former client",'Customer List w Software'!$X$4:$X$310,$B25) -> 8 | D25: =SUMIFS('Customer List w Software'!$K$4:$K$310,'Customer List w Software'!$B$4:$B$310,"<>Former client",'Customer List w Software'!$X$4:$X$310,$B25) -> 152 | E25: =IFERROR(AVERAGEIFS('Customer List w Software'!$J$4:$J$310,'Customer List w Software'!$B$4:$B$310,"<>Former client",'Customer List w Software'!$X$4:$X$310,$B25),0) -> 1303.4375 | G25: =COUNTIFS('Customer List w Software'!$B$4:$B$310,"Former client",'Customer List w Software'!$X$4:$X$310,$B25) -> 0 | H25: =SUMIFS('Customer List w Software'!$K$4:$K$310,'Customer List w Software'!$B$4:$B$310,"Former client",'Customer List w Software'!$X$4:$X$310,$B25) -> 0 | I25: =IFERROR(AVERAGEIFS('Customer List w Software'!$J$4:$J$310,'Customer List w Software'!$B$4:$B$310,"Former client",'Customer List w Software'!$X$4:$X$310,$B25),0) -> 0 | K25: =C25+G25 -> 8 | L25: =D25+H25 -> 152 | M25: =K25/K$29 -> 0.026058632
B26: Lodgify | C26: =COUNTIFS('Customer List w Software'!$B$4:$B$310,"<>Former client",'Customer List w Software'!$X$4:$X$310,$B26) -> 1 | D26: =SUMIFS('Customer List w Software'!$K$4:$K$310,'Customer List w Software'!$B$4:$B$310,"<>Former client",'Customer List w Software'!$X$4:$X$310,$B26) -> 29 | E26: =IFERROR(AVERAGEIFS('Customer List w Software'!$J$4:$J$310,'Customer List w Software'!$B$4:$B$310,"<>Former client",'Customer List w Software'!$X$4:$X$310,$B26),0) -> 2639 | G26: =COUNTIFS('Customer List w Software'!$B$4:$B$310,"Former client",'Customer List w Software'!$X$4:$X$310,$B26) -> 0 | H26: =SUMIFS('Customer List w Software'!$K$4:$K$310,'Customer List w Software'!$B$4:$B$310,"Former client",'Customer List w Software'!$X$4:$X$310,$B26) -> 0 | I26: =IFERROR(AVERAGEIFS('Customer List w Software'!$J$4:$J$310,'Customer List w Software'!$B$4:$B$310,"Former client",'Customer List w Software'!$X$4:$X$310,$B26),0) -> 0 | K26: =C26+G26 -> 1 | L26: =D26+H26 -> 29 | M26: =K26/K$29 -> 0.003257329
B27: Multiple Platforms | C27: =COUNTIFS('Customer List w Software'!$B$4:$B$310,"<>Former client",'Customer List w Software'!$X$4:$X$310,"*,*") -> 4 | D27: =SUMIFS('Customer List w Software'!$K$4:$K$310,'Customer List w Software'!$B$4:$B$310,"<>Former client",'Customer List w Software'!$X$4:$X$310,"*,*") -> 98 | E27: =IFERROR(AVERAGEIFS('Customer List w Software'!$J$4:$J$310,'Customer List w Software'!$B$4:$B$310,"<>Former client",'Customer List w Software'!$X$4:$X$310,"*,*"),0) -> 1695.7042 | G27: =COUNTIFS('Customer List w Software'!$B$4:$B$310,"Former client",'Customer List w Software'!$X$4:$X$310,"*,*") -> 0 | H27: =SUMIFS('Customer List w Software'!$K$4:$K$310,'Customer List w Software'!$B$4:$B$310,"Former client",'Customer List w Software'!$X$4:$X$310,"*,*") -> 0 | I27: =IFERROR(AVERAGEIFS('Customer List w Software'!$J$4:$J$310,'Customer List w Software'!$B$4:$B$310,"Former client",'Customer List w Software'!$X$4:$X$310,"*,*"),0) -> 0 | K27: =C27+G27 -> 4 | L27: =D27+H27 -> 98 | M27: =K27/K$29 -> 0.013029316
B28: None | C28: =COUNTIFS('Customer List w Software'!$B$4:$B$310,"<>Former client",'Customer List w Software'!$X$4:$X$310,"") -> 18 | D28: =SUMIFS('Customer List w Software'!$K$4:$K$310,'Customer List w Software'!$B$4:$B$310,"<>Former client",'Customer List w Software'!$X$4:$X$310,"") -> 329 | E28: =IFERROR(AVERAGEIFS('Customer List w Software'!$J$4:$J$310,'Customer List w Software'!$B$4:$B$310,"<>Former client",'Customer List w Software'!$X$4:$X$310,""),0) -> 1076.0017 | G28: =COUNTIFS('Customer List w Software'!$B$4:$B$310,"Former client",'Customer List w Software'!$X$4:$X$310,"") -> 118 | H28: =SUMIFS('Customer List w Software'!$K$4:$K$310,'Customer List w Software'!$B$4:$B$310,"Former client",'Customer List w Software'!$X$4:$X$310,"") -> 307 | I28: =IFERROR(AVERAGEIFS('Customer List w Software'!$J$4:$J$310,'Customer List w Software'!$B$4:$B$310,"Former client",'Customer List w Software'!$X$4:$X$310,""),0) -> 619.96671 | K28: =C28+G28 -> 136 | L28: =D28+H28 -> 636 | M28: =K28/K$29 -> 0.44299674
B29: Total Clients | C29: =COUNTIFS('Customer List w Software'!$B$4:$B$310,"<>Former client") -> 174 | D29: =SUMIFS('Customer List w Software'!$K$4:$K$310,'Customer List w Software'!$B$4:$B$310,"<>Former client") -> 3757 | E29: =AVERAGEIFS('Customer List w Software'!$J$4:$J$310,'Customer List w Software'!$B$4:$B$310,"<>Former client") -> 1380.6344 | G29: =COUNTIFS('Customer List w Software'!$B$4:$B$310,"Former client") -> 133 | H29: =SUMIFS('Customer List w Software'!$K$4:$K$310,'Customer List w Software'!$B$4:$B$310,"Former client") -> 454 | I29: =AVERAGEIFS('Customer List w Software'!$J$4:$J$310,'Customer List w Software'!$B$4:$B$310,"Former client") -> 637.95417 | K29: =C29+G29 -> 307 | L29: =D29+H29 -> 4211 | M29: =K29/K$29 -> 1
B31: Expense Tool
B32: Topkey | C32: =COUNTIFS('Customer List w Software'!$B$4:$B$310,"<>Former client",'Customer List w Software'!$Y$4:$Y$310,$B32) -> 48 | D32: =SUMIFS('Customer List w Software'!$K$4:$K$310,'Customer List w Software'!$B$4:$B$310,"<>Former client",'Customer List w Software'!$Y$4:$Y$310,$B32) -> 1841 | E32: =IFERROR(AVERAGEIFS('Customer List w Software'!$J$4:$J$310,'Customer List w Software'!$B$4:$B$310,"<>Former client",'Customer List w Software'!$Y$4:$Y$310,$B32),0) -> 2389.2051 | G32: =COUNTIFS('Customer List w Software'!$B$4:$B$310,"Former client",'Customer List w Software'!$Y$4:$Y$310,$B32) -> 4 | H32: =SUMIFS('Customer List w Software'!$K$4:$K$310,'Customer List w Software'!$B$4:$B$310,"Former client",'Customer List w Software'!$Y$4:$Y$310,$B32) -> 120 | I32: =IFERROR(AVERAGEIFS('Customer List w Software'!$J$4:$J$310,'Customer List w Software'!$B$4:$B$310,"Former client",'Customer List w Software'!$Y$4:$Y$310,$B32),0) -> 2159.8333 | K32: =C32+G32 -> 52 | L32: =D32+H32 -> 1961 | M32: =K32/K$36 -> 0.16938111
B33: Bill.com | C33: =COUNTIFS('Customer List w Software'!$B$4:$B$310,"<>Former client",'Customer List w Software'!$Y$4:$Y$310,$B33) -> 12 | D33: =SUMIFS('Customer List w Software'!$K$4:$K$310,'Customer List w Software'!$B$4:$B$310,"<>Former client",'Customer List w Software'!$Y$4:$Y$310,$B33) -> 231 | E33: =IFERROR(AVERAGEIFS('Customer List w Software'!$J$4:$J$310,'Customer List w Software'!$B$4:$B$310,"<>Former client",'Customer List w Software'!$Y$4:$Y$310,$B33),0) -> 1409.9444 | G33: =COUNTIFS('Customer List w Software'!$B$4:$B$310,"Former client",'Customer List w Software'!$Y$4:$Y$310,$B33) -> 1 | H33: =SUMIFS('Customer List w Software'!$K$4:$K$310,'Customer List w Software'!$B$4:$B$310,"Former client",'Customer List w Software'!$Y$4:$Y$310,$B33) -> 0 | I33: =IFERROR(AVERAGEIFS('Customer List w Software'!$J$4:$J$310,'Customer List w Software'!$B$4:$B$310,"Former client",'Customer List w Software'!$Y$4:$Y$310,$B33),0) -> 540 | K33: =C33+G33 -> 13 | L33: =D33+H33 -> 231 | M33: =K33/K$36 -> 0.042345277
B34: Ramp | C34: =COUNTIFS('Customer List w Software'!$B$4:$B$310,"<>Former client",'Customer List w Software'!$Y$4:$Y$310,$B34) -> 0 | D34: =SUMIFS('Customer List w Software'!$K$4:$K$310,'Customer List w Software'!$B$4:$B$310,"<>Former client",'Customer List w Software'!$Y$4:$Y$310,$B34) -> 0 | E34: =IFERROR(AVERAGEIFS('Customer List w Software'!$J$4:$J$310,'Customer List w Software'!$B$4:$B$310,"<>Former client",'Customer List w Software'!$Y$4:$Y$310,$B34),0) -> 0 | G34: =COUNTIFS('Customer List w Software'!$B$4:$B$310,"Former client",'Customer List w Software'!$Y$4:$Y$310,$B34) -> 1 | H34: =SUMIFS('Customer List w Software'!$K$4:$K$310,'Customer List w Software'!$B$4:$B$310,"Former client",'Customer List w Software'!$Y$4:$Y$310,$B34) -> 0 | I34: =IFERROR(AVERAGEIFS('Customer List w Software'!$J$4:$J$310,'Customer List w Software'!$B$4:$B$310,"Former client",'Customer List w Software'!$Y$4:$Y$310,$B34),0) -> 486.33333 | K34: =C34+G34 -> 1 | L34: =D34+H34 -> 0 | M34: =K34/K$36 -> 0.003257329
B35: None | C35: =COUNTIFS('Customer List w Software'!$B$4:$B$310,"<>Former client",'Customer List w Software'!$Y$4:$Y$310,"") -> 114 | D35: =SUMIFS('Customer List w Software'!$K$4:$K$310,'Customer List w Software'!$B$4:$B$310,"<>Former client",'Customer List w Software'!$Y$4:$Y$310,"") -> 1685 | E35: =IFERROR(AVERAGEIFS('Customer List w Software'!$J$4:$J$310,'Customer List w Software'!$B$4:$B$310,"<>Former client",'Customer List w Software'!$Y$4:$Y$310,""),0) -> 952.88787 | G35: =COUNTIFS('Customer List w Software'!$B$4:$B$310,"Former client",'Customer List w Software'!$Y$4:$Y$310,"") -> 127 | H35: =SUMIFS('Customer List w Software'!$K$4:$K$310,'Customer List w Software'!$B$4:$B$310,"Former client",'Customer List w Software'!$Y$4:$Y$310,"") -> 334 | I35: =IFERROR(AVERAGEIFS('Customer List w Software'!$J$4:$J$310,'Customer List w Software'!$B$4:$B$310,"Former client",'Customer List w Software'!$Y$4:$Y$310,""),0) -> 591.98613 | K35: =C35+G35 -> 241 | L35: =D35+H35 -> 2019 | M35: =K35/K$36 -> 0.78501629
B36: Total Clients | C36: =COUNTIFS('Customer List w Software'!$B$4:$B$310,"<>Former client") -> 174 | D36: =SUMIFS('Customer List w Software'!$K$4:$K$310,'Customer List w Software'!$B$4:$B$310,"<>Former client") -> 3757 | E36: =AVERAGEIFS('Customer List w Software'!$J$4:$J$310,'Customer List w Software'!$B$4:$B$310,"<>Former client") -> 1380.6344 | G36: =COUNTIFS('Customer List w Software'!$B$4:$B$310,"Former client") -> 133 | H36: =SUMIFS('Customer List w Software'!$K$4:$K$310,'Customer List w Software'!$B$4:$B$310,"Former client") -> 454 | I36: =AVERAGEIFS('Customer List w Software'!$J$4:$J$310,'Customer List w Software'!$B$4:$B$310,"Former client") -> 637.95417 | K36: =C36+G36 -> 307 | L36: =D36+H36 -> 4211 | M36: =K36/K$36 -> 1
B38: Reference
B39: Current clients = status "Active" or "Onboarding"; Former clients = status "Former client"
B40: Active clients | C40: =COUNTIFS('Customer List w Software'!$B$4:$B$310,"Active") -> 163
B41: Onboarding clients | C41: =COUNTIFS('Customer List w Software'!$B$4:$B$310,"Onboarding") -> 11
B42: Note: "Multiple Platforms" captures clients listing two PMS platforms; property counts are blank for clients with no listing data, so Properties will understate for those rows.
B44: Tie-Out: Avg. Fee per Current Client | C44: Monthly | D44: Annual
B45: Software Overview — current clients (row 10) | C45: =+E10 -> 1380.6344 | D45: =C45*12 -> 16567.613
B46: Client Retention $ — avg. annual fee per client (Sep-26) | C46: =D46/12 -> 1355.1213 | D46: =+'Client Retention $'!AD16*1000 -> 16261.456
B47: Variance | C47: =C45-C46 -> 25.513115 | D47: =D45-D46 -> 306.15738
B48: Variance % | D48: =D47/D46 -> 0.018827181
B50: Reconciliation Drivers
B51: Client count — Customer List w Software (current) | C51: =+C10 -> 174
B52: Client count — Client Retention (Sep-26 avg. clients) | C52: =+'Client Retention'!AD15 -> 188
B53: Total monthly fees — Customer List w Software (current) | C53: =SUMIFS('Customer List w Software'!$J$4:$J$310,'Customer List w Software'!$B$4:$B$310,"<>Former client") -> 240230.39
B54: Total monthly fees — Client Retention $ (Sep-26 avg.) | C54: =+'Client Retention $'!AD15*1000 -> 254762.81
B55: Note: Client Retention $ is built on the Full Customer List "Active" flag (190 clients, ties to its ending monthly fees); this tab uses the status column on Customer List w Software (163 Active + 11 Onboarding). The 16-client / $17k monthly gap is the difference between those two universes.

Sheet Earnings Sensitivity Table
B2: =+Cover!B24 -> Keystone Bookkeepers
B3: Earnings & Valuation Sensitivity ($000s)
B5: Base Case Inputs
B6: Steady-State Adj. EBITDA (PF July'26) | C6: ='P&L Forecast'!$K$106 -> 468.56306
B7: Normalized Bookkeeper Staffing Cost | C7: ='P&L Forecast'!$C$185 -> 272.46938
B8: Current Bookkeeping Clients | C8: ='P&L Forecast'!$C$181 -> 177
B9: Target Load (Clients per Bookkeeper) | C9: ='P&L Forecast'!$C$182 -> 8
B10: Avg. Bookkeeper Compensation | C10: ='P&L Forecast'!$C$184 -> 12.315
B11: EV / EBITDA Multiple (base) | C11: 7
B13: Implied Valuation — Steady-State Adj. EBITDA × Multiple
C14: Steady-State Bookkeeper Load (Clients per Bookkeeper)
B15: EV / EBITDA Multiple | C15: =$C$9-3 -> 5 | D15: =$C$9-2 -> 6 | E15: =$C$9-1 -> 7 | F15: =$C$9+0 -> 8 | G15: =$C$9+1 -> 9 | H15: =$C$9+2 -> 10 | I15: =$C$9+3 -> 11
B16: =$C$11-2 -> 5 | C16: =($C$6+$C$7-($C$8/C$15)*$C$10)*$B16 -> 1525.4072 | D16: =($C$6+$C$7-($C$8/D$15)*$C$10)*$B16 -> 1888.6997 | E16: =($C$6+$C$7-($C$8/E$15)*$C$10)*$B16 -> 2148.1943 | F16: =($C$6+$C$7-($C$8/F$15)*$C$10)*$B16 -> 2342.8153 | G16: =($C$6+$C$7-($C$8/G$15)*$C$10)*$B16 -> 2494.1872 | H16: =($C$6+$C$7-($C$8/H$15)*$C$10)*$B16 -> 2615.2847 | I16: =($C$6+$C$7-($C$8/I$15)*$C$10)*$B16 -> 2714.3644
B17: =$C$11-1 -> 6 | C17: =($C$6+$C$7-($C$8/C$15)*$C$10)*$B17 -> 1830.4886 | D17: =($C$6+$C$7-($C$8/D$15)*$C$10)*$B17 -> 2266.4396 | E17: =($C$6+$C$7-($C$8/E$15)*$C$10)*$B17 -> 2577.8332 | F17: =($C$6+$C$7-($C$8/F$15)*$C$10)*$B17 -> 2811.3783 | G17: =($C$6+$C$7-($C$8/G$15)*$C$10)*$B17 -> 2993.0246 | H17: =($C$6+$C$7-($C$8/H$15)*$C$10)*$B17 -> 3138.3416 | I17: =($C$6+$C$7-($C$8/I$15)*$C$10)*$B17 -> 3257.2373
B18: =$C$11+0 -> 7 | C18: =($C$6+$C$7-($C$8/C$15)*$C$10)*$B18 -> 2135.57 | D18: =($C$6+$C$7-($C$8/D$15)*$C$10)*$B18 -> 2644.1795 | E18: =($C$6+$C$7-($C$8/E$15)*$C$10)*$B18 -> 3007.472 | F18: =($C$6+$C$7-($C$8/F$15)*$C$10)*$B18 -> 3279.9414 | G18: =($C$6+$C$7-($C$8/G$15)*$C$10)*$B18 -> 3491.862 | H18: =($C$6+$C$7-($C$8/H$15)*$C$10)*$B18 -> 3661.3985 | I18: =($C$6+$C$7-($C$8/I$15)*$C$10)*$B18 -> 3800.1102
B19: =$C$11+1 -> 8 | C19: =($C$6+$C$7-($C$8/C$15)*$C$10)*$B19 -> 2440.6515 | D19: =($C$6+$C$7-($C$8/D$15)*$C$10)*$B19 -> 3021.9195 | E19: =($C$6+$C$7-($C$8/E$15)*$C$10)*$B19 -> 3437.1109 | F19: =($C$6+$C$7-($C$8/F$15)*$C$10)*$B19 -> 3748.5045 | G19: =($C$6+$C$7-($C$8/G$15)*$C$10)*$B19 -> 3990.6995 | H19: =($C$6+$C$7-($C$8/H$15)*$C$10)*$B19 -> 4184.4555 | I19: =($C$6+$C$7-($C$8/I$15)*$C$10)*$B19 -> 4342.9831
B20: =$C$11+2 -> 9 | C20: =($C$6+$C$7-($C$8/C$15)*$C$10)*$B20 -> 2745.7329 | D20: =($C$6+$C$7-($C$8/D$15)*$C$10)*$B20 -> 3399.6594 | E20: =($C$6+$C$7-($C$8/E$15)*$C$10)*$B20 -> 3866.7497 | F20: =($C$6+$C$7-($C$8/F$15)*$C$10)*$B20 -> 4217.0675 | G20: =($C$6+$C$7-($C$8/G$15)*$C$10)*$B20 -> 4489.5369 | H20: =($C$6+$C$7-($C$8/H$15)*$C$10)*$B20 -> 4707.5124 | I20: =($C$6+$C$7-($C$8/I$15)*$C$10)*$B20 -> 4885.856
B22: Estimated Steady-State Adj. EBITDA
C23: Steady-State Bookkeeper Load (Clients per Bookkeeper)
B24: Avg. Bookkeeper Compensation | C24: =C$15 -> 5 | D24: =D$15 -> 6 | E24: =E$15 -> 7 | F24: =F$15 -> 8 | G24: =G$15 -> 9 | H24: =H$15 -> 10 | I24: =I$15 -> 11
B25: =$C$10-2 -> 10.315 | C25: =$C$6+$C$7-($C$8/C$24)*$B25 -> 375.88143 | D25: =$C$6+$C$7-($C$8/D$24)*$B25 -> 436.73993 | E25: =$C$6+$C$7-($C$8/E$24)*$B25 -> 480.21029 | F25: =$C$6+$C$7-($C$8/F$24)*$B25 -> 512.81306 | G25: =$C$6+$C$7-($C$8/G$24)*$B25 -> 538.17077 | H25: =$C$6+$C$7-($C$8/H$24)*$B25 -> 558.45693 | I25: =$C$6+$C$7-($C$8/I$24)*$B25 -> 575.0547
B26: =$C$10-1 -> 11.315 | C26: =$C$6+$C$7-($C$8/C$24)*$B26 -> 340.48143 | D26: =$C$6+$C$7-($C$8/D$24)*$B26 -> 407.23993 | E26: =$C$6+$C$7-($C$8/E$24)*$B26 -> 454.92458 | F26: =$C$6+$C$7-($C$8/F$24)*$B26 -> 490.68806 | G26: =$C$6+$C$7-($C$8/G$24)*$B26 -> 518.5041 | H26: =$C$6+$C$7-($C$8/H$24)*$B26 -> 540.75693 | I26: =$C$6+$C$7-($C$8/I$24)*$B26 -> 558.9638
B27: =$C$10+0 -> 12.315 | C27: =$C$6+$C$7-($C$8/C$24)*$B27 -> 305.08143 | D27: =$C$6+$C$7-($C$8/D$24)*$B27 -> 377.73993 | E27: =$C$6+$C$7-($C$8/E$24)*$B27 -> 429.63886 | F27: =$C$6+$C$7-($C$8/F$24)*$B27 -> 468.56306 | G27: =$C$6+$C$7-($C$8/G$24)*$B27 -> 498.83743 | H27: =$C$6+$C$7-($C$8/H$24)*$B27 -> 523.05693 | I27: =$C$6+$C$7-($C$8/I$24)*$B27 -> 542.87289
B28: =$C$10+1 -> 13.315 | C28: =$C$6+$C$7-($C$8/C$24)*$B28 -> 269.68143 | D28: =$C$6+$C$7-($C$8/D$24)*$B28 -> 348.23993 | E28: =$C$6+$C$7-($C$8/E$24)*$B28 -> 404.35315 | F28: =$C$6+$C$7-($C$8/F$24)*$B28 -> 446.43806 | G28: =$C$6+$C$7-($C$8/G$24)*$B28 -> 479.17077 | H28: =$C$6+$C$7-($C$8/H$24)*$B28 -> 505.35693 | I28: =$C$6+$C$7-($C$8/I$24)*$B28 -> 526.78198
B29: =$C$10+2 -> 14.315 | C29: =$C$6+$C$7-($C$8/C$24)*$B29 -> 234.28143 | D29: =$C$6+$C$7-($C$8/D$24)*$B29 -> 318.73993 | E29: =$C$6+$C$7-($C$8/E$24)*$B29 -> 379.06743 | F29: =$C$6+$C$7-($C$8/F$24)*$B29 -> 424.31306 | G29: =$C$6+$C$7-($C$8/G$24)*$B29 -> 459.5041 | H29: =$C$6+$C$7-($C$8/H$24)*$B29 -> 487.65693 | I29: =$C$6+$C$7-($C$8/I$24)*$B29 -> 510.69107
B31: Reference — Observed Bookkeeper Load (Steady-State Staffing tab)
B32: FY2025 | C32: ='Steady-State Staffing'!C21 -> 7.3863636
B33: YTD2026 | C33: ='Steady-State Staffing'!D21 -> 5.056338
B34: LTM Sep'26 | C34: ='Steady-State Staffing'!F21 -> 5.3134328
B35: Jan-25 (peak) | C35: ='Steady-State Staffing'!H21 -> 11.230769
B36: Sep-26 (latest) | C36: ='Steady-State Staffing'!AB21 -> 4.4810127
B37: Note: load axis is the P&L Forecast target load (row 182) ±3 clients, bracketing the observed range above. Only the normalized bookkeeper staffing cost flexes; all other PF adj. EBITDA items are held constant.

Sheet P&L Overview (Target Version)
B2: =+Cover!B24 -> Keystone Bookkeepers
B3: Summary P&L Overview ($000s) | P3: Print | Q3: 1
C5: Full Year | F5: YTD | I5: LTM | K5: PF | M5: PF Delta
B6: P&L Summary | C6: 2024 | D6: 2025 | F6: July'25 | G6: July'26 | I6: July'25 | J6: July'26 | K6: July'26 | M6: ($) | N6: (%)
B7: Revenue
B8: =+'P&L Forecast'!B7 -> STR Subscription | C8: =+'P&L Forecast'!C7 -> 793.47225 | D8: =+'P&L Forecast'!D7 -> 1450.4923 | F8: =+'P&L Forecast'!F7 -> 751.5286 | G8: =+'P&L Forecast'!G7 -> 1261.4769 | I8: =+'P&L Forecast'!I7 -> 1152.3203 | J8: =+'P&L Forecast'!J7 -> 1960.4406 | K8: =+'P&L Forecast'!K7 -> 2410.05 | M8: =K8-J8 -> 449.6094 | N8: =IFERROR(K8/J8-1,0) -> 0.229341
B9: =+'P&L Forecast'!B8 -> Occupancy Taxes | C9: =+'P&L Forecast'!C8 -> 0.56 | D9: =+'P&L Forecast'!D8 -> 55.0805 | F9: =+'P&L Forecast'!F8 -> 23.2255 | G9: =+'P&L Forecast'!G8 -> 91.65114 | I9: =+'P&L Forecast'!I8 -> 23.7855 | J9: =+'P&L Forecast'!J8 -> 123.50614 | K9: =+'P&L Forecast'!K8 -> 192.8298 | M9: =K9-J9 -> 69.32366 | N9: =IFERROR(K9/J9-1,0) -> 0.56129728
B10: =+'P&L Forecast'!B9 -> SMB Subscription | C10: =+'P&L Forecast'!C9 -> 224.791 | D10: =+'P&L Forecast'!D9 -> 149.77 | F10: =+'P&L Forecast'!F9 -> 90.4525 | G10: =+'P&L Forecast'!G9 -> 73.4185 | I10: =+'P&L Forecast'!I9 -> 169.5465 | J10: =+'P&L Forecast'!J9 -> 132.736 | K10: =+'P&L Forecast'!K9 -> 16.2 | M10: =K10-J10 -> -116.536 | N10: =IFERROR(K10/J10-1,0) -> -0.87795323
B11: =+'P&L Forecast'!B10 -> Onboarding | C11: =+'P&L Forecast'!C10 -> 44.0585 | D11: =+'P&L Forecast'!D10 -> 74.5193 | F11: =+'P&L Forecast'!F10 -> 42.25405 | G11: =+'P&L Forecast'!G10 -> 59.055 | I11: =+'P&L Forecast'!I10 -> 57.49255 | J11: =+'P&L Forecast'!J10 -> 91.32025 | K11: =+'P&L Forecast'!K10 -> 103.5675 | M11: =K11-J11 -> 12.24725 | N11: =IFERROR(K11/J11-1,0) -> 0.13411319
B12: =+'P&L Forecast'!B11 -> Topkey Subscription | C12: =+'P&L Forecast'!C11 -> 0 | D12: =+'P&L Forecast'!D11 -> 9.947 | F12: =+'P&L Forecast'!F11 -> 0 | G12: =+'P&L Forecast'!G11 -> 45.086 | I12: =+'P&L Forecast'!I11 -> 0 | J12: =+'P&L Forecast'!J11 -> 55.033 | K12: =+'P&L Forecast'!K11 -> 94.836 | M12: =K12-J12 -> 39.803 | N12: =IFERROR(K12/J12-1,0) -> 0.72325695
B13: =+'P&L Forecast'!B12 -> STR Bill Pay | C13: =+'P&L Forecast'!C12 -> 0.06 | D13: =+'P&L Forecast'!D12 -> 36.6065 | F13: =+'P&L Forecast'!F12 -> 15.4915 | G13: =+'P&L Forecast'!G12 -> 45.13 | I13: =+'P&L Forecast'!I12 -> 15.5515 | J13: =+'P&L Forecast'!J12 -> 66.245 | K13: =+'P&L Forecast'!K12 -> 83.46 | M13: =K13-J13 -> 17.215 | N13: =IFERROR(K13/J13-1,0) -> 0.25986867
B14: =+'P&L Forecast'!B13 -> Controller Services | C14: =+'P&L Forecast'!C13 -> 13.75 | D14: =+'P&L Forecast'!D13 -> 46.4 | F14: =+'P&L Forecast'!F13 -> 31.5 | G14: =+'P&L Forecast'!G13 -> 24.25 | I14: =+'P&L Forecast'!I13 -> 44 | J14: =+'P&L Forecast'!J13 -> 39.15 | K14: =+'P&L Forecast'!K13 -> 42 | M14: =K14-J14 -> 2.85 | N14: =IFERROR(K14/J14-1,0) -> 0.072796935
B15: Other Revenue | C15: =+C16-SUM(C8:C14) -> 58.2741 | D15: =+D16-SUM(D8:D14) -> 56.56748 | F15: =+F16-SUM(F8:F14) -> 43.42095 | G15: =+G16-SUM(G8:G14) -> 70.95371 | I15: =+I16-SUM(I8:I14) -> 61.71435 | J15: =+J16-SUM(J8:J14) -> 84.10024 | K15: =+K16-SUM(K8:K14) -> 55.59772 | M15: =K15-J15 -> -28.50252 | N15: =IFERROR(K15/J15-1,0) -> -0.33891128
B16: Total Revenue | C16: =+'P&L Forecast'!C24 -> 1134.9659 | D16: =+'P&L Forecast'!D24 -> 1879.3831 | F16: =+'P&L Forecast'!F24 -> 997.8731 | G16: =+'P&L Forecast'!G24 -> 1671.0212 | I16: =+'P&L Forecast'!I24 -> 1524.4107 | J16: =+'P&L Forecast'!J24 -> 2552.5312 | K16: =+'P&L Forecast'!K24 -> 2998.541 | M16: =SUM(M8:M15) -> 446.00979 | N16: =IFERROR(K16/J16-1,0) -> 0.17473235
B18: Expenses
B19: =+'P&L Forecast'!B31 -> Indirect Labor | C19: =+'P&L Forecast'!C31 -> 101.3752 | D19: =+'P&L Forecast'!D31 -> 281.24054 | F19: =+'P&L Forecast'!F31 -> 136.29648 | G19: =+'P&L Forecast'!G31 -> 357.27472 | I19: =+'P&L Forecast'!I31 -> 202.41598 | J19: =+'P&L Forecast'!J31 -> 502.21878 | K19: =+'P&L Forecast'!K31 -> 681.3 | M19: =K19-J19 -> 179.08122 | N19: =IFERROR(K19/J19-1,0) -> 0.35658009
B20: =+'P&L Forecast'!B32 -> Bookkeeper Wages | C20: =+'P&L Forecast'!C32 -> 183.36903 | D20: =+'P&L Forecast'!D32 -> 316.18462 | F20: =+'P&L Forecast'!F32 -> 147.26813 | G20: =+'P&L Forecast'!G32 -> 267.7574 | I20: =+'P&L Forecast'!I32 -> 240.18098 | J20: =+'P&L Forecast'!J32 -> 436.67389 | K20: =+'P&L Forecast'!K32 -> 492.6 | M20: =K20-J20 -> 55.92611 | N20: =IFERROR(K20/J20-1,0) -> 0.12807294
B21: =+'P&L Forecast'!B33 -> Client Lead Wages | C21: =+'P&L Forecast'!C33 -> 286.16129 | D21: =+'P&L Forecast'!D33 -> 352.95844 | F21: =+'P&L Forecast'!F33 -> 201.27983 | G21: =+'P&L Forecast'!G33 -> 202.05309 | I21: =+'P&L Forecast'!I33 -> 353.12843 | J21: =+'P&L Forecast'!J33 -> 353.7317 | K21: =+'P&L Forecast'!K33 -> 392.92452 | M21: =K21-J21 -> 39.19282 | N21: =IFERROR(K21/J21-1,0) -> 0.11079816
B22: =+'P&L Forecast'!B34 -> Onboarding Team Wages | C22: =+'P&L Forecast'!C34 -> 122.81255 | D22: =+'P&L Forecast'!D34 -> 152.16972 | F22: =+'P&L Forecast'!F34 -> 73.94962 | G22: =+'P&L Forecast'!G34 -> 111.27999 | I22: =+'P&L Forecast'!I34 -> 121.30735 | J22: =+'P&L Forecast'!J34 -> 189.50009 | K22: =+'P&L Forecast'!K34 -> 197.14944 | M22: =K22-J22 -> 7.64935 | N22: =IFERROR(K22/J22-1,0) -> 0.040365944
B23: =+'P&L Forecast'!B35 -> Owner Wages | C23: =+'P&L Forecast'!C35 -> 0 | D23: =+'P&L Forecast'!D35 -> 90.66704 | F23: =+'P&L Forecast'!F35 -> 45.46612 | G23: =+'P&L Forecast'!G35 -> 63.14302 | I23: =+'P&L Forecast'!I35 -> 45.46612 | J23: =+'P&L Forecast'!J35 -> 108.34394 | K23: =+'P&L Forecast'!K35 -> 108.34394 | M23: =K23-J23 -> 0 | N23: =IFERROR(K23/J23-1,0) -> 0
B24: =+'P&L Forecast'!B36 -> S&M Wages | C24: =+'P&L Forecast'!C36 -> 0 | D24: =+'P&L Forecast'!D36 -> 19.14963 | F24: =+'P&L Forecast'!F36 -> 3.09945 | G24: =+'P&L Forecast'!G36 -> 51.94131 | I24: =+'P&L Forecast'!I36 -> 3.09945 | J24: =+'P&L Forecast'!J36 -> 67.99149 | K24: =+'P&L Forecast'!K36 -> 98.34912 | M24: =K24-J24 -> 30.35763 | N24: =IFERROR(K24/J24-1,0) -> 0.44649161
B25: =+'P&L Forecast'!B37 -> Occupancy Tax Specialist | C25: =+'P&L Forecast'!C37 -> 1.11335 | D25: =+'P&L Forecast'!D37 -> 29.56415 | F25: =+'P&L Forecast'!F37 -> 14.27585 | G25: =+'P&L Forecast'!G37 -> 42.08505 | I25: =+'P&L Forecast'!I37 -> 15.3892 | J25: =+'P&L Forecast'!J37 -> 57.37335 | K25: =+'P&L Forecast'!K37 -> 58.2 | M25: =K25-J25 -> 0.82665 | N25: =IFERROR(K25/J25-1,0) -> 0.014408257
B26: =+'P&L Forecast'!B38 -> Sr. Client Lead Wages | C26: =+'P&L Forecast'!C38 -> 0 | D26: =+'P&L Forecast'!D38 -> 0 | F26: =+'P&L Forecast'!F38 -> 0 | G26: =+'P&L Forecast'!G38 -> 7.995 | I26: =+'P&L Forecast'!I38 -> 0 | J26: =+'P&L Forecast'!J38 -> 7.995 | K26: =+'P&L Forecast'!K38 -> 33.08124 | M26: =K26-J26 -> 25.08624 | N26: =IFERROR(K26/J26-1,0) -> 3.1377411
B27: =+'P&L Forecast'!B39 -> Employee Benefits | C27: =+'P&L Forecast'!C39 -> 5.37405 | D27: =+'P&L Forecast'!D39 -> 19.23245 | F27: =+'P&L Forecast'!F39 -> 9.02166 | G27: =+'P&L Forecast'!G39 -> 17.36251 | I27: =+'P&L Forecast'!I39 -> 12.16686 | J27: =+'P&L Forecast'!J39 -> 27.5733 | K27: =+'P&L Forecast'!K39 -> 32.17836 | M27: =K27-J27 -> 4.60506 | N27: =IFERROR(K27/J27-1,0) -> 0.16701157
B28: =+'P&L Forecast'!B40 -> Total Payroll Expenses | C28: =SUM(C19:C27) -> 700.20547 | D28: =SUM(D19:D27) -> 1261.1666 | F28: =SUM(F19:F27) -> 630.65714 | G28: =SUM(G19:G27) -> 1120.8921 | I28: =SUM(I19:I27) -> 993.15437 | J28: =SUM(J19:J27) -> 1751.4015 | K28: =SUM(K19:K27) -> 2094.1266 | M28: =SUM(M19:M27) -> 342.72508 | N28: =K28/J28-1 -> 0.19568618
B30: =+'P&L Forecast'!B42 -> Software & Apps - COGS | C30: =+'P&L Forecast'!C42 -> 114.42269 | D30: =+'P&L Forecast'!D42 -> 157.49471 | F30: =+'P&L Forecast'!F42 -> 84.96859 | G30: =+'P&L Forecast'!G42 -> 152.28157 | I30: =+'P&L Forecast'!I42 -> 142.28345 | J30: =+'P&L Forecast'!J42 -> 224.80769 | K30: =+'P&L Forecast'!K42 -> 335.70816 | M30: =K30-J30 -> 110.90047 | N30: =IFERROR(K30/J30-1,0) -> 0.49331262
B31: =+'P&L Forecast'!B43 -> Software & Apps - G&A | C31: =+'P&L Forecast'!C43 -> 60.91594 | D31: =+'P&L Forecast'!D43 -> 117.05866 | F31: =+'P&L Forecast'!F43 -> 56.8115 | G31: =+'P&L Forecast'!G43 -> 97.04798 | I31: =+'P&L Forecast'!I43 -> 86.51489 | J31: =+'P&L Forecast'!J43 -> 157.29514 | K31: =+'P&L Forecast'!K43 -> 155.82264 | M31: =K31-J31 -> -1.4725 | N31: =IFERROR(K31/J31-1,0) -> -0.0093613827
B32: =+'P&L Forecast'!B44 -> Software & Apps - Topkey | C32: =+'P&L Forecast'!C44 -> 0 | D32: =+'P&L Forecast'!D44 -> 7.14125 | F32: =+'P&L Forecast'!F44 -> 0 | G32: =+'P&L Forecast'!G44 -> 28.82775 | I32: =+'P&L Forecast'!I44 -> 0 | J32: =+'P&L Forecast'!J44 -> 35.969 | K32: =+'P&L Forecast'!K44 -> 60.84 | M32: =K32-J32 -> 24.871 | N32: =IFERROR(K32/J32-1,0) -> 0.69145653
B33: =+'P&L Forecast'!B45 -> Software & Apps - AI tools | C33: =+'P&L Forecast'!C45 -> 0 | D33: =+'P&L Forecast'!D45 -> 0 | F33: =+'P&L Forecast'!F45 -> 0 | G33: =+'P&L Forecast'!G45 -> 6.52752 | I33: =+'P&L Forecast'!I45 -> 0 | J33: =+'P&L Forecast'!J45 -> 6.52752 | K33: =+'P&L Forecast'!K45 -> 15.74376 | M33: =K33-J33 -> 9.21624 | N33: =IFERROR(K33/J33-1,0) -> 1.4119053
B34: =+'P&L Forecast'!B46 -> Total Software Expenses | C34: =SUM(C30:C33) -> 175.33863 | D34: =SUM(D30:D33) -> 281.69462 | F34: =SUM(F30:F33) -> 141.78009 | G34: =SUM(G30:G33) -> 284.68482 | I34: =SUM(I30:I33) -> 228.79834 | J34: =SUM(J30:J33) -> 424.59935 | K34: =SUM(K30:K33) -> 568.11456 | M34: =SUM(M30:M33) -> 143.51521 | N34: =K34/J34-1 -> 0.33800148
B36: =+'P&L Forecast'!B48 -> Other Professional Fees | C36: =+'P&L Forecast'!C48 -> 18.23425 | D36: =+'P&L Forecast'!D48 -> 27.04095 | F36: =+'P&L Forecast'!F48 -> 12.014 | G36: =+'P&L Forecast'!G48 -> 57.55 | I36: =+'P&L Forecast'!I48 -> 21.74858 | J36: =+'P&L Forecast'!J48 -> 72.57695 | K36: =+'P&L Forecast'!K48 -> 72.57695 | M36: =K36-J36 -> 0 | N36: =IFERROR(K36/J36-1,0) -> 0
B37: =+'P&L Forecast'!B49 -> Referral Fees | C37: =+'P&L Forecast'!C49 -> 24.82 | D37: =+'P&L Forecast'!D49 -> 27.15374 | F37: =+'P&L Forecast'!F49 -> 17.0895 | G37: =+'P&L Forecast'!G49 -> 20.62969 | I37: =+'P&L Forecast'!I49 -> 26.2095 | J37: =+'P&L Forecast'!J49 -> 30.69393 | K37: =+'P&L Forecast'!K49 -> 30.69393 | M37: =K37-J37 -> 0 | N37: =IFERROR(K37/J37-1,0) -> 0
B38: =+'P&L Forecast'!B50 -> Travel, Meals & Entertainment | C38: =+'P&L Forecast'!C50 -> 0 | D38: =+'P&L Forecast'!D50 -> 29.76122 | F38: =+'P&L Forecast'!F50 -> 22.29558 | G38: =+'P&L Forecast'!G50 -> 20.68542 | I38: =+'P&L Forecast'!I50 -> 22.29558 | J38: =+'P&L Forecast'!J50 -> 28.15106 | K38: =+'P&L Forecast'!K50 -> 28.15106 | M38: =K38-J38 -> 0 | N38: =IFERROR(K38/J38-1,0) -> 0
B39: =+'P&L Forecast'!B51 -> Payment Collection Fees | C39: =+'P&L Forecast'!C51 -> 8.67099 | D39: =+'P&L Forecast'!D51 -> 13.35153 | F39: =+'P&L Forecast'!F51 -> 6.80445 | G39: =+'P&L Forecast'!G51 -> 9.02684 | I39: =+'P&L Forecast'!I51 -> 10.54373 | J39: =+'P&L Forecast'!J51 -> 15.57392 | K39: =+'P&L Forecast'!K51 -> 15.57392 | M39: =K39-J39 -> 0 | N39: =IFERROR(K39/J39-1,0) -> 0
B40: =+'P&L Forecast'!B52 -> Professional Organizations | C40: =+'P&L Forecast'!C52 -> 5.44332 | D40: =+'P&L Forecast'!D52 -> 11.22296 | F40: =+'P&L Forecast'!F52 -> 6.191 | G40: =+'P&L Forecast'!G52 -> 6.57881 | I40: =+'P&L Forecast'!I52 -> 9.53268 | J40: =+'P&L Forecast'!J52 -> 11.61077 | K40: =+'P&L Forecast'!K52 -> 11.61077 | M40: =K40-J40 -> 0 | N40: =IFERROR(K40/J40-1,0) -> 0
B41: =+'P&L Forecast'!B53 -> S&M Events | C41: =+'P&L Forecast'!C53 -> 0 | D41: =+'P&L Forecast'!D53 -> 11.4983 | F41: =+'P&L Forecast'!F53 -> 0 | G41: =+'P&L Forecast'!G53 -> 11.84548 | I41: =+'P&L Forecast'!I53 -> 0 | J41: =+'P&L Forecast'!J53 -> 23.34378 | K41: =+'P&L Forecast'!K53 -> 23.34378 | M41: =K41-J41 -> 0 | N41: =IFERROR(K41/J41-1,0) -> 0
B42: =+'P&L Forecast'!B54 -> Contract Labor - Tax | C42: =+'P&L Forecast'!C54 -> 0 | D42: =+'P&L Forecast'!D54 -> 1.5875 | F42: =+'P&L Forecast'!F54 -> 0 | G42: =+'P&L Forecast'!G54 -> 30.5155 | I42: =+'P&L Forecast'!I54 -> 0 | J42: =+'P&L Forecast'!J54 -> 32.103 | K42: =+'P&L Forecast'!K54 -> 38.7615 | M42: =K42-J42 -> 6.6585 | N42: =IFERROR(K42/J42-1,0) -> 0.20741052
B43: =+'P&L Forecast'!B55 -> Recruiting Fees | C43: =+'P&L Forecast'!C55 -> 14.90205 | D43: =+'P&L Forecast'!D55 -> 31.6041 | F43: =+'P&L Forecast'!F55 -> 28.29994 | G43: =+'P&L Forecast'!G55 -> 5.5646 | I43: =+'P&L Forecast'!I55 -> 35.34606 | J43: =+'P&L Forecast'!J55 -> 8.86876 | K43: =+'P&L Forecast'!K55 -> 8.86876 | M43: =K43-J43 -> 0 | N43: =IFERROR(K43/J43-1,0) -> 0
B44: Other Expenses | C44: =+C45-SUM(C36:C43) -> 41.87929 | D44: =+D45-SUM(D36:D43) -> 52.32132 | F44: =+F45-SUM(F36:F43) -> 28.90542 | G44: =+G45-SUM(G36:G43) -> 26.90445 | I44: =+I45-SUM(I36:I43) -> 41.76881 | J44: =+J45-SUM(J36:J43) -> 50.32035 | K44: =+K45-SUM(K36:K43) -> 56.05462 | M44: =K44-J44 -> 5.73427 | N44: =IFERROR(K44/J44-1,0) -> 0.11395529
B45: Total Overhead | C45: =+'P&L Forecast'!C66 -> 113.9499 | D45: =+'P&L Forecast'!D66 -> 205.54162 | F45: =+'P&L Forecast'!F66 -> 121.59989 | G45: =+'P&L Forecast'!G66 -> 189.30079 | I45: =+'P&L Forecast'!I66 -> 167.44494 | J45: =+'P&L Forecast'!J66 -> 273.24252 | K45: =+'P&L Forecast'!K66 -> 285.63529 | M45: =SUM(M36:M44) -> 12.39277 | N45: =K45/J45-1 -> 0.045354471
B47: Net Income | C47: =+C16-C28-C34-C45 -> 145.47185 | D47: =+D16-D28-D34-D45 -> 130.9803 | F47: =+F16-F28-F34-F45 -> 103.83598 | G47: =+G16-G28-G34-G45 -> 76.1435 | I47: =+I16-I28-I34-I45 -> 135.013 | J47: =+J16-J28-J34-J45 -> 103.28782 | K47: =+K16-K28-K34-K45 -> 50.66455 | M47: =+M16-M28-M34-M45 -> -52.62327 | N47: =IFERROR(K47/J47-1,0) -> -0.50948185
B48: % Margin | C48: =C47/C$16 -> 0.12817289 | D48: =D47/D$16 -> 0.06969324 | F48: =F47/F$16 -> 0.1040573 | G48: =G47/G$16 -> 0.045567046 | I48: =I47/I$16 -> 0.088567342 | J48: =J47/J$16 -> 0.04046486 | K48: =K47/K$16 -> 0.016896401 | M48: =M47/M$16 -> -0.1179868 | N48: 0

Sheet P&L Forecast
B2: =+Cover!B24 -> Keystone Bookkeepers
B3: Pre-LOI P&L Forecast ($000s)
B5: P&L Summary ($000s) | C5: FY2024 | D5: FY2025 | F5: July'25 YTD | G5: July'26 YTD | I5: Jul'25 LTM | J5: Jul'26 LTM | K5: Jul'26 PF | M5: Delta ($) | N5: Delta (%) | P5: 45292 | Q5: =EOMONTH(P5,0)+1 -> 45323 | R5: =EOMONTH(Q5,0)+1 -> 45352 | S5: =EOMONTH(R5,0)+1 -> 45383 | T5: =EOMONTH(S5,0)+1 -> 45413 | U5: =EOMONTH(T5,0)+1 -> 45444 | V5: =EOMONTH(U5,0)+1 -> 45474 | W5: =EOMONTH(V5,0)+1 -> 45505 | X5: =EOMONTH(W5,0)+1 -> 45536 | ... AT5: =EOMONTH(AS5,0)+1 -> 46204
A6: x | B6: Revenue
B7: STR Subscription | C7: =SUMIFS($P7:$AT7,$P$5:$AT$5,">"&C$199,$P$5:$AT$5,"<"&C$200) -> 793.47225 | D7: =SUMIFS($P7:$AT7,$P$5:$AT$5,">"&D$199,$P$5:$AT$5,"<"&D$200) -> 1450.4923 | F7: =SUMIFS($P7:$AT7,$P$5:$AT$5,">"&F$199,$P$5:$AT$5,"<"&F$200) -> 751.5286 | G7: =SUMIFS($P7:$AT7,$P$5:$AT$5,">"&G$199,$P$5:$AT$5,"<"&G$200) -> 1261.4769 | I7: =SUMIFS($P7:$AT7,$P$5:$AT$5,">"&I$199,$P$5:$AT$5,"<"&I$200) -> 1152.3203 | J7: =SUMIFS($P7:$AT7,$P$5:$AT$5,">"&J$199,$P$5:$AT$5,"<"&J$200) -> 1960.4406 | K7: =+C111 -> 2410.05 | M7: =K7-J7 -> 449.6094 | N7: =IFERROR(K7/J7-1,0) -> 0.229341 | P7: =SUMIFS('Combined P&L'!N:N,'Combined P&L'!$C:$C,'P&L Forecast'!$B7) -> 44.6835 | Q7: =SUMIFS('Combined P&L'!O:O,'Combined P&L'!$C:$C,'P&L Forecast'!$B7) -> 47.046 | R7: =SUMIFS('Combined P&L'!P:P,'Combined P&L'!$C:$C,'P&L Forecast'!$B7) -> 52.47 | S7: =SUMIFS('Combined P&L'!Q:Q,'Combined P&L'!$C:$C,'P&L Forecast'!$B7) -> 57.1697 | T7: =SUMIFS('Combined P&L'!R:R,'Combined P&L'!$C:$C,'P&L Forecast'!$B7) -> 57.51415 | U7: =SUMIFS('Combined P&L'!S:S,'Combined P&L'!$C:$C,'P&L Forecast'!$B7) -> 65.516 | V7: =SUMIFS('Combined P&L'!T:T,'Combined P&L'!$C:$C,'P&L Forecast'!$B7) -> 68.28125 | W7: =SUMIFS('Combined P&L'!U:U,'Combined P&L'!$C:$C,'P&L Forecast'!$B7) -> 73.25135 | X7: =SUMIFS('Combined P&L'!V:V,'Combined P&L'!$C:$C,'P&L Forecast'!$B7) -> 75.5517 | Y7: =SUMIFS('Combined P&L'!W:W,'Combined P&L'!$C:$C,'P&L Forecast'!$B7) -> 79.11325 | Z7: =SUMIFS('Combined P&L'!X:X,'Combined P&L'!$C:$C,'P&L Forecast'!$B7) -> 83.2908 | AA7: =SUMIFS('Combined P&L'!Y:Y,'Combined P&L'!$C:$C,'P&L Forecast'!$B7) -> 89.58455 | AB7: =SUMIFS('Combined P&L'!Z:Z,'Combined P&L'!$C:$C,'P&L Forecast'!$B7) -> 92.4189 | AC7: =SUMIFS('Combined P&L'!AA:AA,'Combined P&L'!$C:$C,'P&L Forecast'!$B7) -> 94.00215 | AD7: =SUMIFS('Combined P&L'!AB:AB,'Combined P&L'!$C:$C,'P&L Forecast'!$B7) -> 101.50605 | AE7: =SUMIFS('Combined P&L'!AC:AC,'Combined P&L'!$C:$C,'P&L Forecast'!$B7) -> 106.1375 | AF7: =SUMIFS('Combined P&L'!AD:AD,'Combined P&L'!$C:$C,'P&L Forecast'!$B7) -> 115.93875 | AG7: =SUMIFS('Combined P&L'!AE:AE,'Combined P&L'!$C:$C,'P&L Forecast'!$B7) -> 119.43125 | AH7: =SUMIFS('Combined P&L'!AF:AF,'Combined P&L'!$C:$C,'P&L Forecast'!$B7) -> 122.094 | AI7: =SUMIFS('Combined P&L'!AG:AG,'Combined P&L'!$C:$C,'P&L Forecast'!$B7) -> 130.08525 | AJ7: =SUMIFS('Combined P&L'!AH:AH,'Combined P&L'!$C:$C,'P&L Forecast'!$B7) -> 133.5905 | AK7: =SUMIFS('Combined P&L'!AI:AI,'Combined P&L'!$C:$C,'P&L Forecast'!$B7) -> 139.609 | AL7: =SUMIFS('Combined P&L'!AJ:AJ,'Combined P&L'!$C:$C,'P&L Forecast'!$B7) -> 145.28075 | AM7: =SUMIFS('Combined P&L'!AK:AK,'Combined P&L'!$C:$C,'P&L Forecast'!$B7) -> 150.39825 | AN7: =SUMIFS('Combined P&L'!AL:AL,'Combined P&L'!$C:$C,'P&L Forecast'!$B7) -> 156.5388 | AO7: =SUMIFS('Combined P&L'!AM:AM,'Combined P&L'!$C:$C,'P&L Forecast'!$B7) -> 164.9034 | AP7: =SUMIFS('Combined P&L'!AN:AN,'Combined P&L'!$C:$C,'P&L Forecast'!$B7) -> 170.34425 | AQ7: =SUMIFS('Combined P&L'!AO:AO,'Combined P&L'!$C:$C,'P&L Forecast'!$B7) -> 183.662 | AR7: =SUMIFS('Combined P&L'!AP:AP,'Combined P&L'!$C:$C,'P&L Forecast'!$B7) -> 190.7844 | AS7: =SUMIFS('Combined P&L'!AQ:AQ,'Combined P&L'!$C:$C,'P&L Forecast'!$B7) -> 194.4065 | AT7: =SUMIFS('Combined P&L'!AR:AR,'Combined P&L'!$C:$C,'P&L Forecast'!$B7) -> 200.8375
B8: Occupancy Taxes | C8: =SUMIFS($P8:$AT8,$P$5:$AT$5,">"&C$199,$P$5:$AT$5,"<"&C$200) -> 0.56 | D8: =SUMIFS($P8:$AT8,$P$5:$AT$5,">"&D$199,$P$5:$AT$5,"<"&D$200) -> 55.0805 | F8: =SUMIFS($P8:$AT8,$P$5:$AT$5,">"&F$199,$P$5:$AT$5,"<"&F$200) -> 23.2255 | G8: =SUMIFS($P8:$AT8,$P$5:$AT$5,">"&G$199,$P$5:$AT$5,"<"&G$200) -> 91.65114 | I8: =SUMIFS($P8:$AT8,$P$5:$AT$5,">"&I$199,$P$5:$AT$5,"<"&I$200) -> 23.7855 | J8: =SUMIFS($P8:$AT8,$P$5:$AT$5,">"&J$199,$P$5:$AT$5,"<"&J$200) -> 123.50614 | K8: =+C113 -> 192.8298 | M8: =K8-J8 -> 69.32366 | N8: =IFERROR(K8/J8-1,0) -> 0.56129728 | P8: =SUMIFS('Combined P&L'!N:N,'Combined P&L'!$C:$C,'P&L Forecast'!$B8) -> 0 | Q8: =SUMIFS('Combined P&L'!O:O,'Combined P&L'!$C:$C,'P&L Forecast'!$B8) -> 0 | R8: =SUMIFS('Combined P&L'!P:P,'Combined P&L'!$C:$C,'P&L Forecast'!$B8) -> 0 | S8: =SUMIFS('Combined P&L'!Q:Q,'Combined P&L'!$C:$C,'P&L Forecast'!$B8) -> 0 | T8: =SUMIFS('Combined P&L'!R:R,'Combined P&L'!$C:$C,'P&L Forecast'!$B8) -> 0 | U8: =SUMIFS('Combined P&L'!S:S,'Combined P&L'!$C:$C,'P&L Forecast'!$B8) -> 0 | V8: =SUMIFS('Combined P&L'!T:T,'Combined P&L'!$C:$C,'P&L Forecast'!$B8) -> 0 | W8: =SUMIFS('Combined P&L'!U:U,'Combined P&L'!$C:$C,'P&L Forecast'!$B8) -> 0 | X8: =SUMIFS('Combined P&L'!V:V,'Combined P&L'!$C:$C,'P&L Forecast'!$B8) -> 0 | Y8: =SUMIFS('Combined P&L'!W:W,'Combined P&L'!$C:$C,'P&L Forecast'!$B8) -> 0 | Z8: =SUMIFS('Combined P&L'!X:X,'Combined P&L'!$C:$C,'P&L Forecast'!$B8) -> 0.08 | AA8: =SUMIFS('Combined P&L'!Y:Y,'Combined P&L'!$C:$C,'P&L Forecast'!$B8) -> 0.48 | AB8: =SUMIFS('Combined P&L'!Z:Z,'Combined P&L'!$C:$C,'P&L Forecast'!$B8) -> 1.13 | AC8: =SUMIFS('Combined P&L'!AA:AA,'Combined P&L'!$C:$C,'P&L Forecast'!$B8) -> 2.14 | AD8: =SUMIFS('Combined P&L'!AB:AB,'Combined P&L'!$C:$C,'P&L Forecast'!$B8) -> 2.66 | AE8: =SUMIFS('Combined P&L'!AC:AC,'Combined P&L'!$C:$C,'P&L Forecast'!$B8) -> 3.65 | AF8: =SUMIFS('Combined P&L'!AD:AD,'Combined P&L'!$C:$C,'P&L Forecast'!$B8) -> 3.623 | AG8: =SUMIFS('Combined P&L'!AE:AE,'Combined P&L'!$C:$C,'P&L Forecast'!$B8) -> 4.964 | AH8: =SUMIFS('Combined P&L'!AF:AF,'Combined P&L'!$C:$C,'P&L Forecast'!$B8) -> 5.0585 | AI8: =SUMIFS('Combined P&L'!AG:AG,'Combined P&L'!$C:$C,'P&L Forecast'!$B8) -> 4.73 | AJ8: =SUMIFS('Combined P&L'!AH:AH,'Combined P&L'!$C:$C,'P&L Forecast'!$B8) -> 4.82 | AK8: =SUMIFS('Combined P&L'!AI:AI,'Combined P&L'!$C:$C,'P&L Forecast'!$B8) -> 5.37 | AL8: =SUMIFS('Combined P&L'!AJ:AJ,'Combined P&L'!$C:$C,'P&L Forecast'!$B8) -> 8.05 | AM8: =SUMIFS('Combined P&L'!AK:AK,'Combined P&L'!$C:$C,'P&L Forecast'!$B8) -> 8.885 | AN8: =SUMIFS('Combined P&L'!AL:AL,'Combined P&L'!$C:$C,'P&L Forecast'!$B8) -> 10.90952 | AO8: =SUMIFS('Combined P&L'!AM:AM,'Combined P&L'!$C:$C,'P&L Forecast'!$B8) -> 10.33497 | AP8: =SUMIFS('Combined P&L'!AN:AN,'Combined P&L'!$C:$C,'P&L Forecast'!$B8) -> 11.175 | AQ8: =SUMIFS('Combined P&L'!AO:AO,'Combined P&L'!$C:$C,'P&L Forecast'!$B8) -> 11.95311 | AR8: =SUMIFS('Combined P&L'!AP:AP,'Combined P&L'!$C:$C,'P&L Forecast'!$B8) -> 15.04071 | AS8: =SUMIFS('Combined P&L'!AQ:AQ,'Combined P&L'!$C:$C,'P&L Forecast'!$B8) -> 16.16868 | AT8: =SUMIFS('Combined P&L'!AR:AR,'Combined P&L'!$C:$C,'P&L Forecast'!$B8) -> 16.06915
B9: SMB Subscription | C9: =SUMIFS($P9:$AT9,$P$5:$AT$5,">"&C$199,$P$5:$AT$5,"<"&C$200) -> 224.791 | D9: =SUMIFS($P9:$AT9,$P$5:$AT$5,">"&D$199,$P$5:$AT$5,"<"&D$200) -> 149.77 | F9: =SUMIFS($P9:$AT9,$P$5:$AT$5,">"&F$199,$P$5:$AT$5,"<"&F$200) -> 90.4525 | G9: =SUMIFS($P9:$AT9,$P$5:$AT$5,">"&G$199,$P$5:$AT$5,"<"&G$200) -> 73.4185 | I9: =SUMIFS($P9:$AT9,$P$5:$AT$5,">"&I$199,$P$5:$AT$5,"<"&I$200) -> 169.5465 | J9: =SUMIFS($P9:$AT9,$P$5:$AT$5,">"&J$199,$P$5:$AT$5,"<"&J$200) -> 132.736 | K9: =+C112 -> 16.2 | M9: =K9-J9 -> -116.536 | N9: =IFERROR(K9/J9-1,0) -> -0.87795323 | P9: =SUMIFS('Combined P&L'!N:N,'Combined P&L'!$C:$C,'P&L Forecast'!$B9) -> 22.001 | Q9: =SUMIFS('Combined P&L'!O:O,'Combined P&L'!$C:$C,'P&L Forecast'!$B9) -> 22.036 | R9: =SUMIFS('Combined P&L'!P:P,'Combined P&L'!$C:$C,'P&L Forecast'!$B9) -> 22.111 | S9: =SUMIFS('Combined P&L'!Q:Q,'Combined P&L'!$C:$C,'P&L Forecast'!$B9) -> 22.146 | T9: =SUMIFS('Combined P&L'!R:R,'Combined P&L'!$C:$C,'P&L Forecast'!$B9) -> 21.966 | U9: =SUMIFS('Combined P&L'!S:S,'Combined P&L'!$C:$C,'P&L Forecast'!$B9) -> 17.816 | V9: =SUMIFS('Combined P&L'!T:T,'Combined P&L'!$C:$C,'P&L Forecast'!$B9) -> 17.621 | W9: =SUMIFS('Combined P&L'!U:U,'Combined P&L'!$C:$C,'P&L Forecast'!$B9) -> 17.536 | X9: =SUMIFS('Combined P&L'!V:V,'Combined P&L'!$C:$C,'P&L Forecast'!$B9) -> 16.426 | Y9: =SUMIFS('Combined P&L'!W:W,'Combined P&L'!$C:$C,'P&L Forecast'!$B9) -> 15.381 | Z9: =SUMIFS('Combined P&L'!X:X,'Combined P&L'!$C:$C,'P&L Forecast'!$B9) -> 14.6755 | AA9: =SUMIFS('Combined P&L'!Y:Y,'Combined P&L'!$C:$C,'P&L Forecast'!$B9) -> 15.0755 | AB9: =SUMIFS('Combined P&L'!Z:Z,'Combined P&L'!$C:$C,'P&L Forecast'!$B9) -> 14.5625 | AC9: =SUMIFS('Combined P&L'!AA:AA,'Combined P&L'!$C:$C,'P&L Forecast'!$B9) -> 12.8025 | AD9: =SUMIFS('Combined P&L'!AB:AB,'Combined P&L'!$C:$C,'P&L Forecast'!$B9) -> 12.4025 | AE9: =SUMIFS('Combined P&L'!AC:AC,'Combined P&L'!$C:$C,'P&L Forecast'!$B9) -> 12.6025 | AF9: =SUMIFS('Combined P&L'!AD:AD,'Combined P&L'!$C:$C,'P&L Forecast'!$B9) -> 12.7525 | AG9: =SUMIFS('Combined P&L'!AE:AE,'Combined P&L'!$C:$C,'P&L Forecast'!$B9) -> 12.7925 | AH9: =SUMIFS('Combined P&L'!AF:AF,'Combined P&L'!$C:$C,'P&L Forecast'!$B9) -> 12.5375 | AI9: =SUMIFS('Combined P&L'!AG:AG,'Combined P&L'!$C:$C,'P&L Forecast'!$B9) -> 11.8575 | AJ9: =SUMIFS('Combined P&L'!AH:AH,'Combined P&L'!$C:$C,'P&L Forecast'!$B9) -> 12.3025 | AK9: =SUMIFS('Combined P&L'!AI:AI,'Combined P&L'!$C:$C,'P&L Forecast'!$B9) -> 11.6925 | AL9: =SUMIFS('Combined P&L'!AJ:AJ,'Combined P&L'!$C:$C,'P&L Forecast'!$B9) -> 11.7175 | AM9: =SUMIFS('Combined P&L'!AK:AK,'Combined P&L'!$C:$C,'P&L Forecast'!$B9) -> 11.7475 | AN9: =SUMIFS('Combined P&L'!AL:AL,'Combined P&L'!$C:$C,'P&L Forecast'!$B9) -> 11.2805 | AO9: =SUMIFS('Combined P&L'!AM:AM,'Combined P&L'!$C:$C,'P&L Forecast'!$B9) -> 10.9305 | AP9: =SUMIFS('Combined P&L'!AN:AN,'Combined P&L'!$C:$C,'P&L Forecast'!$B9) -> 10.6255 | AQ9: =SUMIFS('Combined P&L'!AO:AO,'Combined P&L'!$C:$C,'P&L Forecast'!$B9) -> 10.3155 | AR9: =SUMIFS('Combined P&L'!AP:AP,'Combined P&L'!$C:$C,'P&L Forecast'!$B9) -> 10.3155 | AS9: =SUMIFS('Combined P&L'!AQ:AQ,'Combined P&L'!$C:$C,'P&L Forecast'!$B9) -> 9.9755 | AT9: =SUMIFS('Combined P&L'!AR:AR,'Combined P&L'!$C:$C,'P&L Forecast'!$B9) -> 9.9755
B10: Onboarding | C10: =SUMIFS($P10:$AT10,$P$5:$AT$5,">"&C$199,$P$5:$AT$5,"<"&C$200) -> 44.0585 | D10: =SUMIFS($P10:$AT10,$P$5:$AT$5,">"&D$199,$P$5:$AT$5,"<"&D$200) -> 74.5193 | F10: =SUMIFS($P10:$AT10,$P$5:$AT$5,">"&F$199,$P$5:$AT$5,"<"&F$200) -> 42.25405 | G10: =SUMIFS($P10:$AT10,$P$5:$AT$5,">"&G$199,$P$5:$AT$5,"<"&G$200) -> 59.055 | I10: =SUMIFS($P10:$AT10,$P$5:$AT$5,">"&I$199,$P$5:$AT$5,"<"&I$200) -> 57.49255 | J10: =SUMIFS($P10:$AT10,$P$5:$AT$5,">"&J$199,$P$5:$AT$5,"<"&J$200) -> 91.32025 | K10: =+C114 -> 103.5675 | M10: =K10-J10 -> 12.24725 | N10: =IFERROR(K10/J10-1,0) -> 0.13411319 | P10: =SUMIFS('Combined P&L'!N:N,'Combined P&L'!$C:$C,'P&L Forecast'!$B10) -> 5.465 | Q10: =SUMIFS('Combined P&L'!O:O,'Combined P&L'!$C:$C,'P&L Forecast'!$B10) -> 3.9 | R10: =SUMIFS('Combined P&L'!P:P,'Combined P&L'!$C:$C,'P&L Forecast'!$B10) -> 2.755 | S10: =SUMIFS('Combined P&L'!Q:Q,'Combined P&L'!$C:$C,'P&L Forecast'!$B10) -> 3.502 | T10: =SUMIFS('Combined P&L'!R:R,'Combined P&L'!$C:$C,'P&L Forecast'!$B10) -> 4.659 | U10: =SUMIFS('Combined P&L'!S:S,'Combined P&L'!$C:$C,'P&L Forecast'!$B10) -> 3.937 | V10: =SUMIFS('Combined P&L'!T:T,'Combined P&L'!$C:$C,'P&L Forecast'!$B10) -> 4.602 | W10: =SUMIFS('Combined P&L'!U:U,'Combined P&L'!$C:$C,'P&L Forecast'!$B10) -> 4.738 | X10: =SUMIFS('Combined P&L'!V:V,'Combined P&L'!$C:$C,'P&L Forecast'!$B10) -> 2.119 | Y10: =SUMIFS('Combined P&L'!W:W,'Combined P&L'!$C:$C,'P&L Forecast'!$B10) -> 2.064 | Z10: =SUMIFS('Combined P&L'!X:X,'Combined P&L'!$C:$C,'P&L Forecast'!$B10) -> 3.0125 | AA10: =SUMIFS('Combined P&L'!Y:Y,'Combined P&L'!$C:$C,'P&L Forecast'!$B10) -> 3.305 | AB10: =SUMIFS('Combined P&L'!Z:Z,'Combined P&L'!$C:$C,'P&L Forecast'!$B10) -> 3.079 | AC10: =SUMIFS('Combined P&L'!AA:AA,'Combined P&L'!$C:$C,'P&L Forecast'!$B10) -> 0.7 | AD10: =SUMIFS('Combined P&L'!AB:AB,'Combined P&L'!$C:$C,'P&L Forecast'!$B10) -> 10.43855 | AE10: =SUMIFS('Combined P&L'!AC:AC,'Combined P&L'!$C:$C,'P&L Forecast'!$B10) -> 4.3 | AF10: =SUMIFS('Combined P&L'!AD:AD,'Combined P&L'!$C:$C,'P&L Forecast'!$B10) -> 11.14 | AG10: =SUMIFS('Combined P&L'!AE:AE,'Combined P&L'!$C:$C,'P&L Forecast'!$B10) -> 6.1625 | AH10: =SUMIFS('Combined P&L'!AF:AF,'Combined P&L'!$C:$C,'P&L Forecast'!$B10) -> 6.434 | AI10: =SUMIFS('Combined P&L'!AG:AG,'Combined P&L'!$C:$C,'P&L Forecast'!$B10) -> 3.965 | AJ10: =SUMIFS('Combined P&L'!AH:AH,'Combined P&L'!$C:$C,'P&L Forecast'!$B10) -> 3.92 | AK10: =SUMIFS('Combined P&L'!AI:AI,'Combined P&L'!$C:$C,'P&L Forecast'!$B10) -> 9.1365 | AL10: =SUMIFS('Combined P&L'!AJ:AJ,'Combined P&L'!$C:$C,'P&L Forecast'!$B10) -> 5.25375 | AM10: =SUMIFS('Combined P&L'!AK:AK,'Combined P&L'!$C:$C,'P&L Forecast'!$B10) -> 9.99 | AN10: =SUMIFS('Combined P&L'!AL:AL,'Combined P&L'!$C:$C,'P&L Forecast'!$B10) -> 10.2105 | AO10: =SUMIFS('Combined P&L'!AM:AM,'Combined P&L'!$C:$C,'P&L Forecast'!$B10) -> 6.675 | AP10: =SUMIFS('Combined P&L'!AN:AN,'Combined P&L'!$C:$C,'P&L Forecast'!$B10) -> 9.099 | AQ10: =SUMIFS('Combined P&L'!AO:AO,'Combined P&L'!$C:$C,'P&L Forecast'!$B10) -> 8.9545 | AR10: =SUMIFS('Combined P&L'!AP:AP,'Combined P&L'!$C:$C,'P&L Forecast'!$B10) -> 12.606 | AS10: =SUMIFS('Combined P&L'!AQ:AQ,'Combined P&L'!$C:$C,'P&L Forecast'!$B10) -> 5.4115 | AT10: =SUMIFS('Combined P&L'!AR:AR,'Combined P&L'!$C:$C,'P&L Forecast'!$B10) -> 6.0985
B11: Topkey Subscription | C11: =SUMIFS($P11:$AT11,$P$5:$AT$5,">"&C$199,$P$5:$AT$5,"<"&C$200) -> 0 | D11: =SUMIFS($P11:$AT11,$P$5:$AT$5,">"&D$199,$P$5:$AT$5,"<"&D$200) -> 9.947 | F11: =SUMIFS($P11:$AT11,$P$5:$AT$5,">"&F$199,$P$5:$AT$5,"<"&F$200) -> 0 | G11: =SUMIFS($P11:$AT11,$P$5:$AT$5,">"&G$199,$P$5:$AT$5,"<"&G$200) -> 45.086 | I11: =SUMIFS($P11:$AT11,$P$5:$AT$5,">"&I$199,$P$5:$AT$5,"<"&I$200) -> 0 | J11: =SUMIFS($P11:$AT11,$P$5:$AT$5,">"&J$199,$P$5:$AT$5,"<"&J$200) -> 55.033 | K11: =+C116 -> 94.836 | M11: =K11-J11 -> 39.803 | N11: =IFERROR(K11/J11-1,0) -> 0.72325695 | P11: =SUMIFS('Combined P&L'!N:N,'Combined P&L'!$C:$C,'P&L Forecast'!$B11) -> 0 | Q11: =SUMIFS('Combined P&L'!O:O,'Combined P&L'!$C:$C,'P&L Forecast'!$B11) -> 0 | R11: =SUMIFS('Combined P&L'!P:P,'Combined P&L'!$C:$C,'P&L Forecast'!$B11) -> 0 | S11: =SUMIFS('Combined P&L'!Q:Q,'Combined P&L'!$C:$C,'P&L Forecast'!$B11) -> 0 | T11: =SUMIFS('Combined P&L'!R:R,'Combined P&L'!$C:$C,'P&L Forecast'!$B11) -> 0 | U11: =SUMIFS('Combined P&L'!S:S,'Combined P&L'!$C:$C,'P&L Forecast'!$B11) -> 0 | V11: =SUMIFS('Combined P&L'!T:T,'Combined P&L'!$C:$C,'P&L Forecast'!$B11) -> 0 | W11: =SUMIFS('Combined P&L'!U:U,'Combined P&L'!$C:$C,'P&L Forecast'!$B11) -> 0 | X11: =SUMIFS('Combined P&L'!V:V,'Combined P&L'!$C:$C,'P&L Forecast'!$B11) -> 0 | Y11: =SUMIFS('Combined P&L'!W:W,'Combined P&L'!$C:$C,'P&L Forecast'!$B11) -> 0 | Z11: =SUMIFS('Combined P&L'!X:X,'Combined P&L'!$C:$C,'P&L Forecast'!$B11) -> 0 | AA11: =SUMIFS('Combined P&L'!Y:Y,'Combined P&L'!$C:$C,'P&L Forecast'!$B11) -> 0 | AB11: =SUMIFS('Combined P&L'!Z:Z,'Combined P&L'!$C:$C,'P&L Forecast'!$B11) -> 0 | AC11: =SUMIFS('Combined P&L'!AA:AA,'Combined P&L'!$C:$C,'P&L Forecast'!$B11) -> 0 | AD11: =SUMIFS('Combined P&L'!AB:AB,'Combined P&L'!$C:$C,'P&L Forecast'!$B11) -> 0 | AE11: =SUMIFS('Combined P&L'!AC:AC,'Combined P&L'!$C:$C,'P&L Forecast'!$B11) -> 0 | AF11: =SUMIFS('Combined P&L'!AD:AD,'Combined P&L'!$C:$C,'P&L Forecast'!$B11) -> 0 | AG11: =SUMIFS('Combined P&L'!AE:AE,'Combined P&L'!$C:$C,'P&L Forecast'!$B11) -> 0 | AH11: =SUMIFS('Combined P&L'!AF:AF,'Combined P&L'!$C:$C,'P&L Forecast'!$B11) -> 0 | AI11: =SUMIFS('Combined P&L'!AG:AG,'Combined P&L'!$C:$C,'P&L Forecast'!$B11) -> 0 | AJ11: =SUMIFS('Combined P&L'!AH:AH,'Combined P&L'!$C:$C,'P&L Forecast'!$B11) -> 0.52 | AK11: =SUMIFS('Combined P&L'!AI:AI,'Combined P&L'!$C:$C,'P&L Forecast'!$B11) -> 2.357 | AL11: =SUMIFS('Combined P&L'!AJ:AJ,'Combined P&L'!$C:$C,'P&L Forecast'!$B11) -> 2.811 | AM11: =SUMIFS('Combined P&L'!AK:AK,'Combined P&L'!$C:$C,'P&L Forecast'!$B11) -> 4.259 | AN11: =SUMIFS('Combined P&L'!AL:AL,'Combined P&L'!$C:$C,'P&L Forecast'!$B11) -> 5.254 | AO11: =SUMIFS('Combined P&L'!AM:AM,'Combined P&L'!$C:$C,'P&L Forecast'!$B11) -> 5.652 | AP11: =SUMIFS('Combined P&L'!AN:AN,'Combined P&L'!$C:$C,'P&L Forecast'!$B11) -> 5.324 | AQ11: =SUMIFS('Combined P&L'!AO:AO,'Combined P&L'!$C:$C,'P&L Forecast'!$B11) -> 6.321 | AR11: =SUMIFS('Combined P&L'!AP:AP,'Combined P&L'!$C:$C,'P&L Forecast'!$B11) -> 6.959 | AS11: =SUMIFS('Combined P&L'!AQ:AQ,'Combined P&L'!$C:$C,'P&L Forecast'!$B11) -> 7.673 | AT11: =SUMIFS('Combined P&L'!AR:AR,'Combined P&L'!$C:$C,'P&L Forecast'!$B11) -> 7.903
B12: STR Bill Pay | C12: =SUMIFS($P12:$AT12,$P$5:$AT$5,">"&C$199,$P$5:$AT$5,"<"&C$200) -> 0.06 | D12: =SUMIFS($P12:$AT12,$P$5:$AT$5,">"&D$199,$P$5:$AT$5,"<"&D$200) -> 36.6065 | F12: =SUMIFS($P12:$AT12,$P$5:$AT$5,">"&F$199,$P$5:$AT$5,"<"&F$200) -> 15.4915 | G12: =SUMIFS($P12:$AT12,$P$5:$AT$5,">"&G$199,$P$5:$AT$5,"<"&G$200) -> 45.13 | I12: =SUMIFS($P12:$AT12,$P$5:$AT$5,">"&I$199,$P$5:$AT$5,"<"&I$200) -> 15.5515 | J12: =SUMIFS($P12:$AT12,$P$5:$AT$5,">"&J$199,$P$5:$AT$5,"<"&J$200) -> 66.245 | K12: =+C115 -> 83.46 | M12: =K12-J12 -> 17.215 | N12: =IFERROR(K12/J12-1,0) -> 0.25986867 | P12: =SUMIFS('Combined P&L'!N:N,'Combined P&L'!$C:$C,'P&L Forecast'!$B12) -> 0 | Q12: =SUMIFS('Combined P&L'!O:O,'Combined P&L'!$C:$C,'P&L Forecast'!$B12) -> 0 | R12: =SUMIFS('Combined P&L'!P:P,'Combined P&L'!$C:$C,'P&L Forecast'!$B12) -> 0 | S12: =SUMIFS('Combined P&L'!Q:Q,'Combined P&L'!$C:$C,'P&L Forecast'!$B12) -> 0 | T12: =SUMIFS('Combined P&L'!R:R,'Combined P&L'!$C:$C,'P&L Forecast'!$B12) -> 0 | U12: =SUMIFS('Combined P&L'!S:S,'Combined P&L'!$C:$C,'P&L Forecast'!$B12) -> 0 | V12: =SUMIFS('Combined P&L'!T:T,'Combined P&L'!$C:$C,'P&L Forecast'!$B12) -> 0 | W12: =SUMIFS('Combined P&L'!U:U,'Combined P&L'!$C:$C,'P&L Forecast'!$B12) -> 0 | X12: =SUMIFS('Combined P&L'!V:V,'Combined P&L'!$C:$C,'P&L Forecast'!$B12) -> 0 | Y12: =SUMIFS('Combined P&L'!W:W,'Combined P&L'!$C:$C,'P&L Forecast'!$B12) -> 0 | Z12: =SUMIFS('Combined P&L'!X:X,'Combined P&L'!$C:$C,'P&L Forecast'!$B12) -> 0 | AA12: =SUMIFS('Combined P&L'!Y:Y,'Combined P&L'!$C:$C,'P&L Forecast'!$B12) -> 0.06 | AB12: =SUMIFS('Combined P&L'!Z:Z,'Combined P&L'!$C:$C,'P&L Forecast'!$B12) -> 0.97 | AC12: =SUMIFS('Combined P&L'!AA:AA,'Combined P&L'!$C:$C,'P&L Forecast'!$B12) -> 1.1 | AD12: =SUMIFS('Combined P&L'!AB:AB,'Combined P&L'!$C:$C,'P&L Forecast'!$B12) -> 1.735 | AE12: =SUMIFS('Combined P&L'!AC:AC,'Combined P&L'!$C:$C,'P&L Forecast'!$B12) -> 2.14 | AF12: =SUMIFS('Combined P&L'!AD:AD,'Combined P&L'!$C:$C,'P&L Forecast'!$B12) -> 2.363 | AG12: =SUMIFS('Combined P&L'!AE:AE,'Combined P&L'!$C:$C,'P&L Forecast'!$B12) -> 3.2635 | AH12: =SUMIFS('Combined P&L'!AF:AF,'Combined P&L'!$C:$C,'P&L Forecast'!$B12) -> 3.92 | AI12: =SUMIFS('Combined P&L'!AG:AG,'Combined P&L'!$C:$C,'P&L Forecast'!$B12) -> 3.905 | AJ12: =SUMIFS('Combined P&L'!AH:AH,'Combined P&L'!$C:$C,'P&L Forecast'!$B12) -> 3.78 | AK12: =SUMIFS('Combined P&L'!AI:AI,'Combined P&L'!$C:$C,'P&L Forecast'!$B12) -> 3.795 | AL12: =SUMIFS('Combined P&L'!AJ:AJ,'Combined P&L'!$C:$C,'P&L Forecast'!$B12) -> 4.33 | AM12: =SUMIFS('Combined P&L'!AK:AK,'Combined P&L'!$C:$C,'P&L Forecast'!$B12) -> 5.305 | AN12: =SUMIFS('Combined P&L'!AL:AL,'Combined P&L'!$C:$C,'P&L Forecast'!$B12) -> 6.3 | AO12: =SUMIFS('Combined P&L'!AM:AM,'Combined P&L'!$C:$C,'P&L Forecast'!$B12) -> 6.39 | AP12: =SUMIFS('Combined P&L'!AN:AN,'Combined P&L'!$C:$C,'P&L Forecast'!$B12) -> 6.425 | AQ12: =SUMIFS('Combined P&L'!AO:AO,'Combined P&L'!$C:$C,'P&L Forecast'!$B12) -> 6.08 | AR12: =SUMIFS('Combined P&L'!AP:AP,'Combined P&L'!$C:$C,'P&L Forecast'!$B12) -> 6.325 | AS12: =SUMIFS('Combined P&L'!AQ:AQ,'Combined P&L'!$C:$C,'P&L Forecast'!$B12) -> 6.655 | AT12: =SUMIFS('Combined P&L'!AR:AR,'Combined P&L'!$C:$C,'P&L Forecast'!$B12) -> 6.955
B13: Controller Services | C13: =SUMIFS($P13:$AT13,$P$5:$AT$5,">"&C$199,$P$5:$AT$5,"<"&C$200) -> 13.75 | D13: =SUMIFS($P13:$AT13,$P$5:$AT$5,">"&D$199,$P$5:$AT$5,"<"&D$200) -> 46.4 | F13: =SUMIFS($P13:$AT13,$P$5:$AT$5,">"&F$199,$P$5:$AT$5,"<"&F$200) -> 31.5 | G13: =SUMIFS($P13:$AT13,$P$5:$AT$5,">"&G$199,$P$5:$AT$5,"<"&G$200) -> 24.25 | I13: =SUMIFS($P13:$AT13,$P$5:$AT$5,">"&I$199,$P$5:$AT$5,"<"&I$200) -> 44 | J13: =SUMIFS($P13:$AT13,$P$5:$AT$5,">"&J$199,$P$5:$AT$5,"<"&J$200) -> 39.15 | K13: =+C117 -> 42 | M13: =K13-J13 -> 2.85 | N13: =IFERROR(K13/J13-1,0) -> 0.072796935 | P13: =SUMIFS('Combined P&L'!N:N,'Combined P&L'!$C:$C,'P&L Forecast'!$B13) -> 0 | Q13: =SUMIFS('Combined P&L'!O:O,'Combined P&L'!$C:$C,'P&L Forecast'!$B13) -> 0 | R13: =SUMIFS('Combined P&L'!P:P,'Combined P&L'!$C:$C,'P&L Forecast'!$B13) -> 0 | S13: =SUMIFS('Combined P&L'!Q:Q,'Combined P&L'!$C:$C,'P&L Forecast'!$B13) -> 0 | T13: =SUMIFS('Combined P&L'!R:R,'Combined P&L'!$C:$C,'P&L Forecast'!$B13) -> 0 | U13: =SUMIFS('Combined P&L'!S:S,'Combined P&L'!$C:$C,'P&L Forecast'!$B13) -> 0 | V13: =SUMIFS('Combined P&L'!T:T,'Combined P&L'!$C:$C,'P&L Forecast'!$B13) -> 1.25 | W13: =SUMIFS('Combined P&L'!U:U,'Combined P&L'!$C:$C,'P&L Forecast'!$B13) -> 1.25 | X13: =SUMIFS('Combined P&L'!V:V,'Combined P&L'!$C:$C,'P&L Forecast'!$B13) -> 1.25 | Y13: =SUMIFS('Combined P&L'!W:W,'Combined P&L'!$C:$C,'P&L Forecast'!$B13) -> 1.25 | Z13: =SUMIFS('Combined P&L'!X:X,'Combined P&L'!$C:$C,'P&L Forecast'!$B13) -> 5.75 | AA13: =SUMIFS('Combined P&L'!Y:Y,'Combined P&L'!$C:$C,'P&L Forecast'!$B13) -> 3 | AB13: =SUMIFS('Combined P&L'!Z:Z,'Combined P&L'!$C:$C,'P&L Forecast'!$B13) -> 4.45 | AC13: =SUMIFS('Combined P&L'!AA:AA,'Combined P&L'!$C:$C,'P&L Forecast'!$B13) -> 3.45 | AD13: =SUMIFS('Combined P&L'!AB:AB,'Combined P&L'!$C:$C,'P&L Forecast'!$B13) -> 3.45 | AE13: =SUMIFS('Combined P&L'!AC:AC,'Combined P&L'!$C:$C,'P&L Forecast'!$B13) -> 5.95 | AF13: =SUMIFS('Combined P&L'!AD:AD,'Combined P&L'!$C:$C,'P&L Forecast'!$B13) -> 5.2 | AG13: =SUMIFS('Combined P&L'!AE:AE,'Combined P&L'!$C:$C,'P&L Forecast'!$B13) -> 5 | AH13: =SUMIFS('Combined P&L'!AF:AF,'Combined P&L'!$C:$C,'P&L Forecast'!$B13) -> 4 | AI13: =SUMIFS('Combined P&L'!AG:AG,'Combined P&L'!$C:$C,'P&L Forecast'!$B13) -> 2.95 | AJ13: =SUMIFS('Combined P&L'!AH:AH,'Combined P&L'!$C:$C,'P&L Forecast'!$B13) -> 3.025 | AK13: =SUMIFS('Combined P&L'!AI:AI,'Combined P&L'!$C:$C,'P&L Forecast'!$B13) -> 3.025 | AL13: =SUMIFS('Combined P&L'!AJ:AJ,'Combined P&L'!$C:$C,'P&L Forecast'!$B13) -> 2.95 | AM13: =SUMIFS('Combined P&L'!AK:AK,'Combined P&L'!$C:$C,'P&L Forecast'!$B13) -> 2.95 | AN13: =SUMIFS('Combined P&L'!AL:AL,'Combined P&L'!$C:$C,'P&L Forecast'!$B13) -> 2.75 | AO13: =SUMIFS('Combined P&L'!AM:AM,'Combined P&L'!$C:$C,'P&L Forecast'!$B13) -> 3.5 | AP13: =SUMIFS('Combined P&L'!AN:AN,'Combined P&L'!$C:$C,'P&L Forecast'!$B13) -> 2.75 | AQ13: =SUMIFS('Combined P&L'!AO:AO,'Combined P&L'!$C:$C,'P&L Forecast'!$B13) -> 4.75 | AR13: =SUMIFS('Combined P&L'!AP:AP,'Combined P&L'!$C:$C,'P&L Forecast'!$B13) -> 3.5 | AS13: =SUMIFS('Combined P&L'!AQ:AQ,'Combined P&L'!$C:$C,'P&L Forecast'!$B13) -> 3.5 | AT13: =SUMIFS('Combined P&L'!AR:AR,'Combined P&L'!$C:$C,'P&L Forecast'!$B13) -> 3.5
B14: Historical Cleanup | C14: =SUMIFS($P14:$AT14,$P$5:$AT$5,">"&C$199,$P$5:$AT$5,"<"&C$200) -> 17.624 | D14: =SUMIFS($P14:$AT14,$P$5:$AT$5,">"&D$199,$P$5:$AT$5,"<"&D$200) -> 5.03375 | F14: =SUMIFS($P14:$AT14,$P$5:$AT$5,">"&F$199,$P$5:$AT$5,"<"&F$200) -> 4.43875 | G14: =SUMIFS($P14:$AT14,$P$5:$AT$5,">"&G$199,$P$5:$AT$5,"<"&G$200) -> 0 | I14: =SUMIFS($P14:$AT14,$P$5:$AT$5,">"&I$199,$P$5:$AT$5,"<"&I$200) -> 12.84275 | J14: =SUMIFS($P14:$AT14,$P$5:$AT$5,">"&J$199,$P$5:$AT$5,"<"&J$200) -> 0.595 | K14: =+C118 -> 0 | M14: =K14-J14 -> -0.595 | N14: =IFERROR(K14/J14-1,0) -> -1 | P14: =SUMIFS('Combined P&L'!N:N,'Combined P&L'!$C:$C,'P&L Forecast'!$B14) -> 1.2 | Q14: =SUMIFS('Combined P&L'!O:O,'Combined P&L'!$C:$C,'P&L Forecast'!$B14) -> 1.7625 | R14: =SUMIFS('Combined P&L'!P:P,'Combined P&L'!$C:$C,'P&L Forecast'!$B14) -> 0.66 | S14: =SUMIFS('Combined P&L'!Q:Q,'Combined P&L'!$C:$C,'P&L Forecast'!$B14) -> 0.395 | T14: =SUMIFS('Combined P&L'!R:R,'Combined P&L'!$C:$C,'P&L Forecast'!$B14) -> 2.465 | U14: =SUMIFS('Combined P&L'!S:S,'Combined P&L'!$C:$C,'P&L Forecast'!$B14) -> 1.275 | V14: =SUMIFS('Combined P&L'!T:T,'Combined P&L'!$C:$C,'P&L Forecast'!$B14) -> 1.4625 | W14: =SUMIFS('Combined P&L'!U:U,'Combined P&L'!$C:$C,'P&L Forecast'!$B14) -> 0 | X14: =SUMIFS('Combined P&L'!V:V,'Combined P&L'!$C:$C,'P&L Forecast'!$B14) -> 1.14525 | Y14: =SUMIFS('Combined P&L'!W:W,'Combined P&L'!$C:$C,'P&L Forecast'!$B14) -> 1.35525 | Z14: =SUMIFS('Combined P&L'!X:X,'Combined P&L'!$C:$C,'P&L Forecast'!$B14) -> 1.9035 | AA14: =SUMIFS('Combined P&L'!Y:Y,'Combined P&L'!$C:$C,'P&L Forecast'!$B14) -> 4 | AB14: =SUMIFS('Combined P&L'!Z:Z,'Combined P&L'!$C:$C,'P&L Forecast'!$B14) -> 1.08375 | AC14: =SUMIFS('Combined P&L'!AA:AA,'Combined P&L'!$C:$C,'P&L Forecast'!$B14) -> 2 | AD14: =SUMIFS('Combined P&L'!AB:AB,'Combined P&L'!$C:$C,'P&L Forecast'!$B14) -> 1.355 | AE14: =SUMIFS('Combined P&L'!AC:AC,'Combined P&L'!$C:$C,'P&L Forecast'!$B14) -> 0 | AF14: =SUMIFS('Combined P&L'!AD:AD,'Combined P&L'!$C:$C,'P&L Forecast'!$B14) -> 0 | AG14: =SUMIFS('Combined P&L'!AE:AE,'Combined P&L'!$C:$C,'P&L Forecast'!$B14) -> 0 | AH14: =SUMIFS('Combined P&L'!AF:AF,'Combined P&L'!$C:$C,'P&L Forecast'!$B14) -> 0 | AI14: =SUMIFS('Combined P&L'!AG:AG,'Combined P&L'!$C:$C,'P&L Forecast'!$B14) -> 0 | AJ14: =SUMIFS('Combined P&L'!AH:AH,'Combined P&L'!$C:$C,'P&L Forecast'!$B14) -> 0 | AK14: =SUMIFS('Combined P&L'!AI:AI,'Combined P&L'!$C:$C,'P&L Forecast'!$B14) -> 0.595 | AL14: =SUMIFS('Combined P&L'!AJ:AJ,'Combined P&L'!$C:$C,'P&L Forecast'!$B14) -> 0 | AM14: =SUMIFS('Combined P&L'!AK:AK,'Combined P&L'!$C:$C,'P&L Forecast'!$B14) -> 0 | AN14: =SUMIFS('Combined P&L'!AL:AL,'Combined P&L'!$C:$C,'P&L Forecast'!$B14) -> 0 | AO14: =SUMIFS('Combined P&L'!AM:AM,'Combined P&L'!$C:$C,'P&L Forecast'!$B14) -> 0 | AP14: =SUMIFS('Combined P&L'!AN:AN,'Combined P&L'!$C:$C,'P&L Forecast'!$B14) -> 0 | AQ14: =SUMIFS('Combined P&L'!AO:AO,'Combined P&L'!$C:$C,'P&L Forecast'!$B14) -> 0 | AR14: =SUMIFS('Combined P&L'!AP:AP,'Combined P&L'!$C:$C,'P&L Forecast'!$B14) -> 0 | AS14: =SUMIFS('Combined P&L'!AQ:AQ,'Combined P&L'!$C:$C,'P&L Forecast'!$B14) -> 0 | AT14: =SUMIFS('Combined P&L'!AR:AR,'Combined P&L'!$C:$C,'P&L Forecast'!$B14) -> 0
B15: Total Recurring Revenue | C15: =SUM(C7:C14) -> 1094.3157 | D15: =SUM(D7:D14) -> 1827.8494 | F15: =SUM(F7:F14) -> 958.8909 | G15: =SUM(G7:G14) -> 1600.0675 | I15: =SUM(I7:I14) -> 1475.5391 | J15: =SUM(J7:J14) -> 2469.026 | K15: =SUM(K7:K14) -> 2942.9433 | M15: =SUM(M7:M14) -> 473.91731 | N15: =IFERROR(K15/J15-1,0) -> 0.19194505 | P15: =SUM(P7:P14) -> 73.3495 | Q15: =SUM(Q7:Q14) -> 74.7445 | R15: =SUM(R7:R14) -> 77.996 | S15: =SUM(S7:S14) -> 83.2127 | T15: =SUM(T7:T14) -> 86.60415 | U15: =SUM(U7:U14) -> 88.544 | V15: =SUM(V7:V14) -> 93.21675 | W15: =SUM(W7:W14) -> 96.77535 | ... AT15: =SUM(AT7:AT14) -> 251.33865
B17: Profit Share | C17: =SUMIFS($P17:$AT17,$P$5:$AT$5,">"&C$199,$P$5:$AT$5,"<"&C$200) -> 6.2004 | D17: =SUMIFS($P17:$AT17,$P$5:$AT$5,">"&D$199,$P$5:$AT$5,"<"&D$200) -> 23.26179 | F17: =SUMIFS($P17:$AT17,$P$5:$AT$5,">"&F$199,$P$5:$AT$5,"<"&F$200) -> 14.50495 | G17: =SUMIFS($P17:$AT17,$P$5:$AT$5,">"&G$199,$P$5:$AT$5,"<"&G$200) -> 8.07938 | I17: =SUMIFS($P17:$AT17,$P$5:$AT$5,">"&I$199,$P$5:$AT$5,"<"&I$200) -> 18.32935 | J17: =SUMIFS($P17:$AT17,$P$5:$AT$5,">"&J$199,$P$5:$AT$5,"<"&J$200) -> 16.83622 | K17: =+C123 -> 16.83622 | M17: =K17-J17 -> 0 | N17: =IFERROR(K17/J17-1,0) -> 0 | P17: =SUMIFS('Combined P&L'!N:N,'Combined P&L'!$C:$C,'P&L Forecast'!$B17) -> 0.0686 | Q17: =SUMIFS('Combined P&L'!O:O,'Combined P&L'!$C:$C,'P&L Forecast'!$B17) -> 0.1312 | R17: =SUMIFS('Combined P&L'!P:P,'Combined P&L'!$C:$C,'P&L Forecast'!$B17) -> 0.0712 | S17: =SUMIFS('Combined P&L'!Q:Q,'Combined P&L'!$C:$C,'P&L Forecast'!$B17) -> 0.0556 | T17: =SUMIFS('Combined P&L'!R:R,'Combined P&L'!$C:$C,'P&L Forecast'!$B17) -> 0.577 | U17: =SUMIFS('Combined P&L'!S:S,'Combined P&L'!$C:$C,'P&L Forecast'!$B17) -> 0.8068 | V17: =SUMIFS('Combined P&L'!T:T,'Combined P&L'!$C:$C,'P&L Forecast'!$B17) -> 0.6656 | W17: =SUMIFS('Combined P&L'!U:U,'Combined P&L'!$C:$C,'P&L Forecast'!$B17) -> 0.8264 | X17: =SUMIFS('Combined P&L'!V:V,'Combined P&L'!$C:$C,'P&L Forecast'!$B17) -> 1.3808 | Y17: =SUMIFS('Combined P&L'!W:W,'Combined P&L'!$C:$C,'P&L Forecast'!$B17) -> 0.8604 | Z17: =SUMIFS('Combined P&L'!X:X,'Combined P&L'!$C:$C,'P&L Forecast'!$B17) -> 0.51 | AA17: =SUMIFS('Combined P&L'!Y:Y,'Combined P&L'!$C:$C,'P&L Forecast'!$B17) -> 0.2468 | AB17: =SUMIFS('Combined P&L'!Z:Z,'Combined P&L'!$C:$C,'P&L Forecast'!$B17) -> 7.3584 | AC17: =SUMIFS('Combined P&L'!AA:AA,'Combined P&L'!$C:$C,'P&L Forecast'!$B17) -> 1.29335 | AD17: =SUMIFS('Combined P&L'!AB:AB,'Combined P&L'!$C:$C,'P&L Forecast'!$B17) -> 0.96833 | AE17: =SUMIFS('Combined P&L'!AC:AC,'Combined P&L'!$C:$C,'P&L Forecast'!$B17) -> 1.1656 | AF17: =SUMIFS('Combined P&L'!AD:AD,'Combined P&L'!$C:$C,'P&L Forecast'!$B17) -> 0.96093 | AG17: =SUMIFS('Combined P&L'!AE:AE,'Combined P&L'!$C:$C,'P&L Forecast'!$B17) -> 1.71127 | AH17: =SUMIFS('Combined P&L'!AF:AF,'Combined P&L'!$C:$C,'P&L Forecast'!$B17) -> 1.04707 | AI17: =SUMIFS('Combined P&L'!AG:AG,'Combined P&L'!$C:$C,'P&L Forecast'!$B17) -> 2.04088 | AJ17: =SUMIFS('Combined P&L'!AH:AH,'Combined P&L'!$C:$C,'P&L Forecast'!$B17) -> 1.13621 | AK17: =SUMIFS('Combined P&L'!AI:AI,'Combined P&L'!$C:$C,'P&L Forecast'!$B17) -> 2.01424 | AL17: =SUMIFS('Combined P&L'!AJ:AJ,'Combined P&L'!$C:$C,'P&L Forecast'!$B17) -> 1.29758 | AM17: =SUMIFS('Combined P&L'!AK:AK,'Combined P&L'!$C:$C,'P&L Forecast'!$B17) -> 2.26793 | AN17: =SUMIFS('Combined P&L'!AL:AL,'Combined P&L'!$C:$C,'P&L Forecast'!$B17) -> 2.67784 | AO17: =SUMIFS('Combined P&L'!AM:AM,'Combined P&L'!$C:$C,'P&L Forecast'!$B17) -> 2.35401 | AP17: =SUMIFS('Combined P&L'!AN:AN,'Combined P&L'!$C:$C,'P&L Forecast'!$B17) -> 0.2276 | AQ17: =SUMIFS('Combined P&L'!AO:AO,'Combined P&L'!$C:$C,'P&L Forecast'!$B17) -> 1.47836 | AR17: =SUMIFS('Combined P&L'!AP:AP,'Combined P&L'!$C:$C,'P&L Forecast'!$B17) -> 0.66824 | AS17: =SUMIFS('Combined P&L'!AQ:AQ,'Combined P&L'!$C:$C,'P&L Forecast'!$B17) -> 0.58613 | AT17: =SUMIFS('Combined P&L'!AR:AR,'Combined P&L'!$C:$C,'P&L Forecast'!$B17) -> 0.0872
B18: 1099 Filing | C18: =SUMIFS($P18:$AT18,$P$5:$AT$5,">"&C$199,$P$5:$AT$5,"<"&C$200) -> 10.475 | D18: =SUMIFS($P18:$AT18,$P$5:$AT$5,">"&D$199,$P$5:$AT$5,"<"&D$200) -> 23.55 | F18: =SUMIFS($P18:$AT18,$P$5:$AT$5,">"&F$199,$P$5:$AT$5,"<"&F$200) -> 23.49 | G18: =SUMIFS($P18:$AT18,$P$5:$AT$5,">"&G$199,$P$5:$AT$5,"<"&G$200) -> 38.7015 | I18: =SUMIFS($P18:$AT18,$P$5:$AT$5,">"&I$199,$P$5:$AT$5,"<"&I$200) -> 23.52 | J18: =SUMIFS($P18:$AT18,$P$5:$AT$5,">"&J$199,$P$5:$AT$5,"<"&J$200) -> 38.7615 | K18: =+C121 -> 38.7615 | M18: =K18-J18 -> 0 | N18: =IFERROR(K18/J18-1,0) -> 0 | P18: =SUMIFS('Combined P&L'!N:N,'Combined P&L'!$C:$C,'P&L Forecast'!$B18) -> 6.945 | Q18: =SUMIFS('Combined P&L'!O:O,'Combined P&L'!$C:$C,'P&L Forecast'!$B18) -> 3.38 | R18: =SUMIFS('Combined P&L'!P:P,'Combined P&L'!$C:$C,'P&L Forecast'!$B18) -> 0.045 | S18: =SUMIFS('Combined P&L'!Q:Q,'Combined P&L'!$C:$C,'P&L Forecast'!$B18) -> 0.06 | T18: =SUMIFS('Combined P&L'!R:R,'Combined P&L'!$C:$C,'P&L Forecast'!$B18) -> 0.015 | U18: =SUMIFS('Combined P&L'!S:S,'Combined P&L'!$C:$C,'P&L Forecast'!$B18) -> 0 | V18: =SUMIFS('Combined P&L'!T:T,'Combined P&L'!$C:$C,'P&L Forecast'!$B18) -> 0 | W18: =SUMIFS('Combined P&L'!U:U,'Combined P&L'!$C:$C,'P&L Forecast'!$B18) -> 0.015 | X18: =SUMIFS('Combined P&L'!V:V,'Combined P&L'!$C:$C,'P&L Forecast'!$B18) -> 0 | Y18: =SUMIFS('Combined P&L'!W:W,'Combined P&L'!$C:$C,'P&L Forecast'!$B18) -> 0 | Z18: =SUMIFS('Combined P&L'!X:X,'Combined P&L'!$C:$C,'P&L Forecast'!$B18) -> 0.015 | AA18: =SUMIFS('Combined P&L'!Y:Y,'Combined P&L'!$C:$C,'P&L Forecast'!$B18) -> 0 | AB18: =SUMIFS('Combined P&L'!Z:Z,'Combined P&L'!$C:$C,'P&L Forecast'!$B18) -> 13.485 | AC18: =SUMIFS('Combined P&L'!AA:AA,'Combined P&L'!$C:$C,'P&L Forecast'!$B18) -> 9.915 | AD18: =SUMIFS('Combined P&L'!AB:AB,'Combined P&L'!$C:$C,'P&L Forecast'!$B18) -> 0.06 | AE18: =SUMIFS('Combined P&L'!AC:AC,'Combined P&L'!$C:$C,'P&L Forecast'!$B18) -> 0.03 | AF18: =SUMIFS('Combined P&L'!AD:AD,'Combined P&L'!$C:$C,'P&L Forecast'!$B18) -> 0 | AG18: =SUMIFS('Combined P&L'!AE:AE,'Combined P&L'!$C:$C,'P&L Forecast'!$B18) -> 0 | AH18: =SUMIFS('Combined P&L'!AF:AF,'Combined P&L'!$C:$C,'P&L Forecast'!$B18) -> 0 | AI18: =SUMIFS('Combined P&L'!AG:AG,'Combined P&L'!$C:$C,'P&L Forecast'!$B18) -> 0.03 | AJ18: =SUMIFS('Combined P&L'!AH:AH,'Combined P&L'!$C:$C,'P&L Forecast'!$B18) -> 0.03 | AK18: =SUMIFS('Combined P&L'!AI:AI,'Combined P&L'!$C:$C,'P&L Forecast'!$B18) -> 0 | AL18: =SUMIFS('Combined P&L'!AJ:AJ,'Combined P&L'!$C:$C,'P&L Forecast'!$B18) -> 0 | AM18: =SUMIFS('Combined P&L'!AK:AK,'Combined P&L'!$C:$C,'P&L Forecast'!$B18) -> 0 | AN18: =SUMIFS('Combined P&L'!AL:AL,'Combined P&L'!$C:$C,'P&L Forecast'!$B18) -> 6.105 | AO18: =SUMIFS('Combined P&L'!AM:AM,'Combined P&L'!$C:$C,'P&L Forecast'!$B18) -> 31.1565 | AP18: =SUMIFS('Combined P&L'!AN:AN,'Combined P&L'!$C:$C,'P&L Forecast'!$B18) -> 1.26 | AQ18: =SUMIFS('Combined P&L'!AO:AO,'Combined P&L'!$C:$C,'P&L Forecast'!$B18) -> 0.18 | AR18: =SUMIFS('Combined P&L'!AP:AP,'Combined P&L'!$C:$C,'P&L Forecast'!$B18) -> 0 | AS18: =SUMIFS('Combined P&L'!AQ:AQ,'Combined P&L'!$C:$C,'P&L Forecast'!$B18) -> 0 | AT18: =SUMIFS('Combined P&L'!AR:AR,'Combined P&L'!$C:$C,'P&L Forecast'!$B18) -> 0
B19: Income Tax | C19: =SUMIFS($P19:$AT19,$P$5:$AT$5,">"&C$199,$P$5:$AT$5,"<"&C$200) -> 0 | D19: =SUMIFS($P19:$AT19,$P$5:$AT$5,">"&D$199,$P$5:$AT$5,"<"&D$200) -> 3.4 | F19: =SUMIFS($P19:$AT19,$P$5:$AT$5,">"&F$199,$P$5:$AT$5,"<"&F$200) -> 0 | G19: =SUMIFS($P19:$AT19,$P$5:$AT$5,">"&G$199,$P$5:$AT$5,"<"&G$200) -> 23.915 | I19: =SUMIFS($P19:$AT19,$P$5:$AT$5,">"&I$199,$P$5:$AT$5,"<"&I$200) -> 0 | J19: =SUMIFS($P19:$AT19,$P$5:$AT$5,">"&J$199,$P$5:$AT$5,"<"&J$200) -> 27.315 | K19: =+C122 -> 0 | M19: =K19-J19 -> -27.315 | N19: =IFERROR(K19/J19-1,0) -> -1 | P19: =SUMIFS('Combined P&L'!N:N,'Combined P&L'!$C:$C,'P&L Forecast'!$B19) -> 0 | Q19: =SUMIFS('Combined P&L'!O:O,'Combined P&L'!$C:$C,'P&L Forecast'!$B19) -> 0 | R19: =SUMIFS('Combined P&L'!P:P,'Combined P&L'!$C:$C,'P&L Forecast'!$B19) -> 0 | S19: =SUMIFS('Combined P&L'!Q:Q,'Combined P&L'!$C:$C,'P&L Forecast'!$B19) -> 0 | T19: =SUMIFS('Combined P&L'!R:R,'Combined P&L'!$C:$C,'P&L Forecast'!$B19) -> 0 | U19: =SUMIFS('Combined P&L'!S:S,'Combined P&L'!$C:$C,'P&L Forecast'!$B19) -> 0 | V19: =SUMIFS('Combined P&L'!T:T,'Combined P&L'!$C:$C,'P&L Forecast'!$B19) -> 0 | W19: =SUMIFS('Combined P&L'!U:U,'Combined P&L'!$C:$C,'P&L Forecast'!$B19) -> 0 | X19: =SUMIFS('Combined P&L'!V:V,'Combined P&L'!$C:$C,'P&L Forecast'!$B19) -> 0 | Y19: =SUMIFS('Combined P&L'!W:W,'Combined P&L'!$C:$C,'P&L Forecast'!$B19) -> 0 | Z19: =SUMIFS('Combined P&L'!X:X,'Combined P&L'!$C:$C,'P&L Forecast'!$B19) -> 0 | AA19: =SUMIFS('Combined P&L'!Y:Y,'Combined P&L'!$C:$C,'P&L Forecast'!$B19) -> 0 | AB19: =SUMIFS('Combined P&L'!Z:Z,'Combined P&L'!$C:$C,'P&L Forecast'!$B19) -> 0 | AC19: =SUMIFS('Combined P&L'!AA:AA,'Combined P&L'!$C:$C,'P&L Forecast'!$B19) -> 0 | AD19: =SUMIFS('Combined P&L'!AB:AB,'Combined P&L'!$C:$C,'P&L Forecast'!$B19) -> 0 | AE19: =SUMIFS('Combined P&L'!AC:AC,'Combined P&L'!$C:$C,'P&L Forecast'!$B19) -> 0 | AF19: =SUMIFS('Combined P&L'!AD:AD,'Combined P&L'!$C:$C,'P&L Forecast'!$B19) -> 0 | AG19: =SUMIFS('Combined P&L'!AE:AE,'Combined P&L'!$C:$C,'P&L Forecast'!$B19) -> 0 | AH19: =SUMIFS('Combined P&L'!AF:AF,'Combined P&L'!$C:$C,'P&L Forecast'!$B19) -> 0 | AI19: =SUMIFS('Combined P&L'!AG:AG,'Combined P&L'!$C:$C,'P&L Forecast'!$B19) -> 0 | AJ19: =SUMIFS('Combined P&L'!AH:AH,'Combined P&L'!$C:$C,'P&L Forecast'!$B19) -> 0.875 | AK19: =SUMIFS('Combined P&L'!AI:AI,'Combined P&L'!$C:$C,'P&L Forecast'!$B19) -> 1.65 | AL19: =SUMIFS('Combined P&L'!AJ:AJ,'Combined P&L'!$C:$C,'P&L Forecast'!$B19) -> 0 | AM19: =SUMIFS('Combined P&L'!AK:AK,'Combined P&L'!$C:$C,'P&L Forecast'!$B19) -> 0.875 | AN19: =SUMIFS('Combined P&L'!AL:AL,'Combined P&L'!$C:$C,'P&L Forecast'!$B19) -> 0 | AO19: =SUMIFS('Combined P&L'!AM:AM,'Combined P&L'!$C:$C,'P&L Forecast'!$B19) -> 0 | AP19: =SUMIFS('Combined P&L'!AN:AN,'Combined P&L'!$C:$C,'P&L Forecast'!$B19) -> 14.19 | AQ19: =SUMIFS('Combined P&L'!AO:AO,'Combined P&L'!$C:$C,'P&L Forecast'!$B19) -> 6.625 | AR19: =SUMIFS('Combined P&L'!AP:AP,'Combined P&L'!$C:$C,'P&L Forecast'!$B19) -> 0 | AS19: =SUMIFS('Combined P&L'!AQ:AQ,'Combined P&L'!$C:$C,'P&L Forecast'!$B19) -> 3.1 | AT19: =SUMIFS('Combined P&L'!AR:AR,'Combined P&L'!$C:$C,'P&L Forecast'!$B19) -> 0
B20: Billable Expense Income | C20: =SUMIFS($P20:$AT20,$P$5:$AT$5,">"&C$199,$P$5:$AT$5,"<"&C$200) -> 0.3747 | D20: =SUMIFS($P20:$AT20,$P$5:$AT$5,">"&D$199,$P$5:$AT$5,"<"&D$200) -> 1.12194 | F20: =SUMIFS($P20:$AT20,$P$5:$AT$5,">"&F$199,$P$5:$AT$5,"<"&F$200) -> 0.78725 | G20: =SUMIFS($P20:$AT20,$P$5:$AT$5,">"&G$199,$P$5:$AT$5,"<"&G$200) -> 0.25783 | I20: =SUMIFS($P20:$AT20,$P$5:$AT$5,">"&I$199,$P$5:$AT$5,"<"&I$200) -> 0.78725 | J20: =SUMIFS($P20:$AT20,$P$5:$AT$5,">"&J$199,$P$5:$AT$5,"<"&J$200) -> 0.59252 | K20: =+C124 -> 0 | M20: =K20-J20 -> -0.59252 | N20: =IFERROR(K20/J20-1,0) -> -1 | P20: =SUMIFS('Combined P&L'!N:N,'Combined P&L'!$C:$C,'P&L Forecast'!$B20) -> 0.05 | Q20: =SUMIFS('Combined P&L'!O:O,'Combined P&L'!$C:$C,'P&L Forecast'!$B20) -> 0 | R20: =SUMIFS('Combined P&L'!P:P,'Combined P&L'!$C:$C,'P&L Forecast'!$B20) -> 0 | S20: =SUMIFS('Combined P&L'!Q:Q,'Combined P&L'!$C:$C,'P&L Forecast'!$B20) -> 0.025 | T20: =SUMIFS('Combined P&L'!R:R,'Combined P&L'!$C:$C,'P&L Forecast'!$B20) -> 0 | U20: =SUMIFS('Combined P&L'!S:S,'Combined P&L'!$C:$C,'P&L Forecast'!$B20) -> 0 | V20: =SUMIFS('Combined P&L'!T:T,'Combined P&L'!$C:$C,'P&L Forecast'!$B20) -> 0.2997 | W20: =SUMIFS('Combined P&L'!U:U,'Combined P&L'!$C:$C,'P&L Forecast'!$B20) -> 0 | X20: =SUMIFS('Combined P&L'!V:V,'Combined P&L'!$C:$C,'P&L Forecast'!$B20) -> 0 | Y20: =SUMIFS('Combined P&L'!W:W,'Combined P&L'!$C:$C,'P&L Forecast'!$B20) -> 0 | Z20: =SUMIFS('Combined P&L'!X:X,'Combined P&L'!$C:$C,'P&L Forecast'!$B20) -> 0 | AA20: =SUMIFS('Combined P&L'!Y:Y,'Combined P&L'!$C:$C,'P&L Forecast'!$B20) -> 0 | AB20: =SUMIFS('Combined P&L'!Z:Z,'Combined P&L'!$C:$C,'P&L Forecast'!$B20) -> 0.025 | AC20: =SUMIFS('Combined P&L'!AA:AA,'Combined P&L'!$C:$C,'P&L Forecast'!$B20) -> 0.3996 | AD20: =SUMIFS('Combined P&L'!AB:AB,'Combined P&L'!$C:$C,'P&L Forecast'!$B20) -> 0 | AE20: =SUMIFS('Combined P&L'!AC:AC,'Combined P&L'!$C:$C,'P&L Forecast'!$B20) -> 0 | AF20: =SUMIFS('Combined P&L'!AD:AD,'Combined P&L'!$C:$C,'P&L Forecast'!$B20) -> 0.07294 | AG20: =SUMIFS('Combined P&L'!AE:AE,'Combined P&L'!$C:$C,'P&L Forecast'!$B20) -> 0 | AH20: =SUMIFS('Combined P&L'!AF:AF,'Combined P&L'!$C:$C,'P&L Forecast'!$B20) -> 0.28971 | AI20: =SUMIFS('Combined P&L'!AG:AG,'Combined P&L'!$C:$C,'P&L Forecast'!$B20) -> 0.30969 | AJ20: =SUMIFS('Combined P&L'!AH:AH,'Combined P&L'!$C:$C,'P&L Forecast'!$B20) -> 0 | AK20: =SUMIFS('Combined P&L'!AI:AI,'Combined P&L'!$C:$C,'P&L Forecast'!$B20) -> 0 | AL20: =SUMIFS('Combined P&L'!AJ:AJ,'Combined P&L'!$C:$C,'P&L Forecast'!$B20) -> 0 | AM20: =SUMIFS('Combined P&L'!AK:AK,'Combined P&L'!$C:$C,'P&L Forecast'!$B20) -> 0.025 | AN20: =SUMIFS('Combined P&L'!AL:AL,'Combined P&L'!$C:$C,'P&L Forecast'!$B20) -> 0.15984 | AO20: =SUMIFS('Combined P&L'!AM:AM,'Combined P&L'!$C:$C,'P&L Forecast'!$B20) -> 0 | AP20: =SUMIFS('Combined P&L'!AN:AN,'Combined P&L'!$C:$C,'P&L Forecast'!$B20) -> 0.075 | AQ20: =SUMIFS('Combined P&L'!AO:AO,'Combined P&L'!$C:$C,'P&L Forecast'!$B20) -> 0 | AR20: =SUMIFS('Combined P&L'!AP:AP,'Combined P&L'!$C:$C,'P&L Forecast'!$B20) -> 0 | AS20: =SUMIFS('Combined P&L'!AQ:AQ,'Combined P&L'!$C:$C,'P&L Forecast'!$B20) -> 0.02299 | AT20: =SUMIFS('Combined P&L'!AR:AR,'Combined P&L'!$C:$C,'P&L Forecast'!$B20) -> 0
B21: Offshore Recruiting | C21: =SUMIFS($P21:$AT21,$P$5:$AT$5,">"&C$199,$P$5:$AT$5,"<"&C$200) -> 23.6 | D21: =SUMIFS($P21:$AT21,$P$5:$AT$5,">"&D$199,$P$5:$AT$5,"<"&D$200) -> 0.2 | F21: =SUMIFS($P21:$AT21,$P$5:$AT$5,">"&F$199,$P$5:$AT$5,"<"&F$200) -> 0.2 | G21: =SUMIFS($P21:$AT21,$P$5:$AT$5,">"&G$199,$P$5:$AT$5,"<"&G$200) -> 0 | I21: =SUMIFS($P21:$AT21,$P$5:$AT$5,">"&I$199,$P$5:$AT$5,"<"&I$200) -> 6.235 | J21: =SUMIFS($P21:$AT21,$P$5:$AT$5,">"&J$199,$P$5:$AT$5,"<"&J$200) -> 0 | K21: =+C125 -> 0 | M21: =K21-J21 -> 0 | N21: =IFERROR(K21/J21-1,0) -> 0 | P21: =SUMIFS('Combined P&L'!N:N,'Combined P&L'!$C:$C,'P&L Forecast'!$B21) -> 0.5 | Q21: =SUMIFS('Combined P&L'!O:O,'Combined P&L'!$C:$C,'P&L Forecast'!$B21) -> 3 | R21: =SUMIFS('Combined P&L'!P:P,'Combined P&L'!$C:$C,'P&L Forecast'!$B21) -> 0 | S21: =SUMIFS('Combined P&L'!Q:Q,'Combined P&L'!$C:$C,'P&L Forecast'!$B21) -> 0 | T21: =SUMIFS('Combined P&L'!R:R,'Combined P&L'!$C:$C,'P&L Forecast'!$B21) -> 3 | U21: =SUMIFS('Combined P&L'!S:S,'Combined P&L'!$C:$C,'P&L Forecast'!$B21) -> 0.565 | V21: =SUMIFS('Combined P&L'!T:T,'Combined P&L'!$C:$C,'P&L Forecast'!$B21) -> 10.5 | W21: =SUMIFS('Combined P&L'!U:U,'Combined P&L'!$C:$C,'P&L Forecast'!$B21) -> 6.5 | X21: =SUMIFS('Combined P&L'!V:V,'Combined P&L'!$C:$C,'P&L Forecast'!$B21) -> 0.5 | Y21: =SUMIFS('Combined P&L'!W:W,'Combined P&L'!$C:$C,'P&L Forecast'!$B21) -> -0.965 | Z21: =SUMIFS('Combined P&L'!X:X,'Combined P&L'!$C:$C,'P&L Forecast'!$B21) -> 0 | AA21: =SUMIFS('Combined P&L'!Y:Y,'Combined P&L'!$C:$C,'P&L Forecast'!$B21) -> 0 | AB21: =SUMIFS('Combined P&L'!Z:Z,'Combined P&L'!$C:$C,'P&L Forecast'!$B21) -> 0.1 | AC21: =SUMIFS('Combined P&L'!AA:AA,'Combined P&L'!$C:$C,'P&L Forecast'!$B21) -> 0 | AD21: =SUMIFS('Combined P&L'!AB:AB,'Combined P&L'!$C:$C,'P&L Forecast'!$B21) -> 0.1 | AE21: =SUMIFS('Combined P&L'!AC:AC,'Combined P&L'!$C:$C,'P&L Forecast'!$B21) -> 0 | AF21: =SUMIFS('Combined P&L'!AD:AD,'Combined P&L'!$C:$C,'P&L Forecast'!$B21) -> 0 | AG21: =SUMIFS('Combined P&L'!AE:AE,'Combined P&L'!$C:$C,'P&L Forecast'!$B21) -> 0 | AH21: =SUMIFS('Combined P&L'!AF:AF,'Combined P&L'!$C:$C,'P&L Forecast'!$B21) -> 0 | AI21: =SUMIFS('Combined P&L'!AG:AG,'Combined P&L'!$C:$C,'P&L Forecast'!$B21) -> 0 | AJ21: =SUMIFS('Combined P&L'!AH:AH,'Combined P&L'!$C:$C,'P&L Forecast'!$B21) -> 0 | AK21: =SUMIFS('Combined P&L'!AI:AI,'Combined P&L'!$C:$C,'P&L Forecast'!$B21) -> 0 | AL21: =SUMIFS('Combined P&L'!AJ:AJ,'Combined P&L'!$C:$C,'P&L Forecast'!$B21) -> 0 | AM21: =SUMIFS('Combined P&L'!AK:AK,'Combined P&L'!$C:$C,'P&L Forecast'!$B21) -> 0 | AN21: =SUMIFS('Combined P&L'!AL:AL,'Combined P&L'!$C:$C,'P&L Forecast'!$B21) -> 0 | AO21: =SUMIFS('Combined P&L'!AM:AM,'Combined P&L'!$C:$C,'P&L Forecast'!$B21) -> 0 | AP21: =SUMIFS('Combined P&L'!AN:AN,'Combined P&L'!$C:$C,'P&L Forecast'!$B21) -> 0 | AQ21: =SUMIFS('Combined P&L'!AO:AO,'Combined P&L'!$C:$C,'P&L Forecast'!$B21) -> 0 | AR21: =SUMIFS('Combined P&L'!AP:AP,'Combined P&L'!$C:$C,'P&L Forecast'!$B21) -> 0 | AS21: =SUMIFS('Combined P&L'!AQ:AQ,'Combined P&L'!$C:$C,'P&L Forecast'!$B21) -> 0 | AT21: =SUMIFS('Combined P&L'!AR:AR,'Combined P&L'!$C:$C,'P&L Forecast'!$B21) -> 0
B22: Total Nonrecurring Revenue | C22: =SUM(C17:C21) -> 40.6501 | D22: =SUM(D17:D21) -> 51.53373 | F22: =SUM(F17:F21) -> 38.9822 | G22: =SUM(G17:G21) -> 70.95371 | I22: =SUM(I17:I21) -> 48.8716 | J22: =SUM(J17:J21) -> 83.50524 | K22: =SUM(K17:K21) -> 55.59772 | M22: =SUM(M17:M21) -> -27.90752 | N22: =IFERROR(K22/J22-1,0) -> -0.33420082 | P22: =SUM(P17:P21) -> 7.5636 | Q22: =SUM(Q17:Q21) -> 6.5112 | R22: =SUM(R17:R21) -> 0.1162 | S22: =SUM(S17:S21) -> 0.1406 | T22: =SUM(T17:T21) -> 3.592 | U22: =SUM(U17:U21) -> 1.3718 | V22: =SUM(V17:V21) -> 11.4653 | W22: =SUM(W17:W21) -> 7.3414 | ... AT22: =SUM(AT17:AT21) -> 0.0872
B24: Total Run-Rate Revenue | C24: =+C22+C15 -> 1134.9659 | D24: =+D22+D15 -> 1879.3831 | F24: =+F22+F15 -> 997.8731 | G24: =+G22+G15 -> 1671.0212 | I24: =+I22+I15 -> 1524.4107 | J24: =+J22+J15 -> 2552.5312 | K24: =+K22+K15 -> 2998.541 | M24: =+M22+M15 -> 446.00979 | N24: =IFERROR(K24/J24-1,0) -> 0.17473235 | P24: =+P22+P15 -> 80.9131 | Q24: =+Q22+Q15 -> 81.2557 | R24: =+R22+R15 -> 78.1122 | S24: =+S22+S15 -> 83.3533 | T24: =+T22+T15 -> 90.19615 | U24: =+U22+U15 -> 89.9158 | V24: =+V22+V15 -> 104.68205 | W24: =+W22+W15 -> 104.11675 | ... AT24: =+AT22+AT15 -> 251.42585
B26: Unclassified Active Client Revenue | C26: 0 | D26: 0 | F26: 0 | G26: 0 | I26: 0 | J26: 0 | K26: =+'Client Retention $'!F13-'P&L Forecast'!K24 -> 93.9827 | M26: =K26-J26 -> 93.9827 | N26: =IFERROR(K26/J26-1,0) -> 0 | P26: 0 | Q26: 0 | R26: 0 | S26: 0 | T26: 0 | U26: 0 | V26: 0 | W26: 0 | X26: 0 | Y26: 0 | Z26: 0 | AA26: 0 | AB26: 0 | AC26: 0 | AD26: 0 | AE26: 0 | AF26: 0 | AG26: 0 | AH26: 0 | AI26: 0 | AJ26: 0 | AK26: 0 | AL26: 0 | AM26: 0 | AN26: 0 | AO26: 0 | AP26: 0 | AQ26: 0 | AR26: 0 | AS26: 0 | AT26: 0
B28: Total Adj. Revenue | C28: =+C26+C24 -> 1134.9659 | D28: =+D26+D24 -> 1879.3831 | F28: =+F26+F24 -> 997.8731 | G28: =+G26+G24 -> 1671.0212 | I28: =+I26+I24 -> 1524.4107 | J28: =+J26+J24 -> 2552.5312 | K28: =+K26+K24 -> 3092.5237 | M28: =+M26+M24 -> 539.99249 | N28: =IFERROR(K28/J28-1,0) -> 0.21155177 | P28: =+P26+P19 -> 0 | Q28: =+Q26+Q19 -> 0 | R28: =+R26+R19 -> 0 | S28: =+S26+S19 -> 0 | T28: =+T26+T19 -> 0 | U28: =+U26+U19 -> 0 | V28: =+V26+V19 -> 0 | W28: =+W26+W19 -> 0 | ... AT28: =+AT26+AT19 -> 0
B30: Expenses
B31: Indirect Labor | C31: =SUMIFS($P31:$AT31,$P$5:$AT$5,">"&C$199,$P$5:$AT$5,"<"&C$200) -> 101.3752 | D31: =SUMIFS($P31:$AT31,$P$5:$AT$5,">"&D$199,$P$5:$AT$5,"<"&D$200) -> 281.24054 | F31: =SUMIFS($P31:$AT31,$P$5:$AT$5,">"&F$199,$P$5:$AT$5,"<"&F$200) -> 136.29648 | G31: =SUMIFS($P31:$AT31,$P$5:$AT$5,">"&G$199,$P$5:$AT$5,"<"&G$200) -> 357.27472 | I31: =SUMIFS($P31:$AT31,$P$5:$AT$5,">"&I$199,$P$5:$AT$5,"<"&I$200) -> 202.41598 | J31: =SUMIFS($P31:$AT31,$P$5:$AT$5,">"&J$199,$P$5:$AT$5,"<"&J$200) -> 502.21878 | K31: =+C129 -> 681.3 | M31: =K31-J31 -> 179.08122 | N31: =IFERROR(K31/J31-1,0) -> 0.35658009 | P31: =SUMIFS('Combined P&L'!N:N,'Combined P&L'!$C:$C,'P&L Forecast'!$B31) -> 3.09346 | Q31: =SUMIFS('Combined P&L'!O:O,'Combined P&L'!$C:$C,'P&L Forecast'!$B31) -> 4.63017 | R31: =SUMIFS('Combined P&L'!P:P,'Combined P&L'!$C:$C,'P&L Forecast'!$B31) -> 4.39507 | S31: =SUMIFS('Combined P&L'!Q:Q,'Combined P&L'!$C:$C,'P&L Forecast'!$B31) -> 5.86387 | T31: =SUMIFS('Combined P&L'!R:R,'Combined P&L'!$C:$C,'P&L Forecast'!$B31) -> 7.37233 | U31: =SUMIFS('Combined P&L'!S:S,'Combined P&L'!$C:$C,'P&L Forecast'!$B31) -> 4.9504 | V31: =SUMIFS('Combined P&L'!T:T,'Combined P&L'!$C:$C,'P&L Forecast'!$B31) -> 4.9504 | W31: =SUMIFS('Combined P&L'!U:U,'Combined P&L'!$C:$C,'P&L Forecast'!$B31) -> 4.70035 | X31: =SUMIFS('Combined P&L'!V:V,'Combined P&L'!$C:$C,'P&L Forecast'!$B31) -> 4.9504 | Y31: =SUMIFS('Combined P&L'!W:W,'Combined P&L'!$C:$C,'P&L Forecast'!$B31) -> 5.99987 | Z31: =SUMIFS('Combined P&L'!X:X,'Combined P&L'!$C:$C,'P&L Forecast'!$B31) -> 26.02876 | AA31: =SUMIFS('Combined P&L'!Y:Y,'Combined P&L'!$C:$C,'P&L Forecast'!$B31) -> 24.44012 | AB31: =SUMIFS('Combined P&L'!Z:Z,'Combined P&L'!$C:$C,'P&L Forecast'!$B31) -> 21.05234 | AC31: =SUMIFS('Combined P&L'!AA:AA,'Combined P&L'!$C:$C,'P&L Forecast'!$B31) -> 19.91603 | AD31: =SUMIFS('Combined P&L'!AB:AB,'Combined P&L'!$C:$C,'P&L Forecast'!$B31) -> 11.74387 | AE31: =SUMIFS('Combined P&L'!AC:AC,'Combined P&L'!$C:$C,'P&L Forecast'!$B31) -> 19.61792 | AF31: =SUMIFS('Combined P&L'!AD:AD,'Combined P&L'!$C:$C,'P&L Forecast'!$B31) -> 20.66978 | AG31: =SUMIFS('Combined P&L'!AE:AE,'Combined P&L'!$C:$C,'P&L Forecast'!$B31) -> 20.6939 | AH31: =SUMIFS('Combined P&L'!AF:AF,'Combined P&L'!$C:$C,'P&L Forecast'!$B31) -> 22.60264 | AI31: =SUMIFS('Combined P&L'!AG:AG,'Combined P&L'!$C:$C,'P&L Forecast'!$B31) -> 19.96128 | AJ31: =SUMIFS('Combined P&L'!AH:AH,'Combined P&L'!$C:$C,'P&L Forecast'!$B31) -> 27.60563 | AK31: =SUMIFS('Combined P&L'!AI:AI,'Combined P&L'!$C:$C,'P&L Forecast'!$B31) -> 34.18589 | AL31: =SUMIFS('Combined P&L'!AJ:AJ,'Combined P&L'!$C:$C,'P&L Forecast'!$B31) -> 29.73157 | AM31: =SUMIFS('Combined P&L'!AK:AK,'Combined P&L'!$C:$C,'P&L Forecast'!$B31) -> 33.45969 | AN31: =SUMIFS('Combined P&L'!AL:AL,'Combined P&L'!$C:$C,'P&L Forecast'!$B31) -> 36.2536 | AO31: =SUMIFS('Combined P&L'!AM:AM,'Combined P&L'!$C:$C,'P&L Forecast'!$B31) -> 33.60751 | AP31: =SUMIFS('Combined P&L'!AN:AN,'Combined P&L'!$C:$C,'P&L Forecast'!$B31) -> 57.19924 | AQ31: =SUMIFS('Combined P&L'!AO:AO,'Combined P&L'!$C:$C,'P&L Forecast'!$B31) -> 58.24595 | AR31: =SUMIFS('Combined P&L'!AP:AP,'Combined P&L'!$C:$C,'P&L Forecast'!$B31) -> 54.06923 | AS31: =SUMIFS('Combined P&L'!AQ:AQ,'Combined P&L'!$C:$C,'P&L Forecast'!$B31) -> 60.00381 | AT31: =SUMIFS('Combined P&L'!AR:AR,'Combined P&L'!$C:$C,'P&L Forecast'!$B31) -> 57.89538
B32: Bookkeeper Wages | C32: =SUMIFS($P32:$AT32,$P$5:$AT$5,">"&C$199,$P$5:$AT$5,"<"&C$200) -> 183.36903 | D32: =SUMIFS($P32:$AT32,$P$5:$AT$5,">"&D$199,$P$5:$AT$5,"<"&D$200) -> 316.18462 | F32: =SUMIFS($P32:$AT32,$P$5:$AT$5,">"&F$199,$P$5:$AT$5,"<"&F$200) -> 147.26813 | G32: =SUMIFS($P32:$AT32,$P$5:$AT$5,">"&G$199,$P$5:$AT$5,"<"&G$200) -> 267.7574 | I32: =SUMIFS($P32:$AT32,$P$5:$AT$5,">"&I$199,$P$5:$AT$5,"<"&I$200) -> 240.18098 | J32: =SUMIFS($P32:$AT32,$P$5:$AT$5,">"&J$199,$P$5:$AT$5,"<"&J$200) -> 436.67389 | K32: =+C130 -> 492.6 | M32: =K32-J32 -> 55.92611 | N32: =IFERROR(K32/J32-1,0) -> 0.12807294 | P32: =SUMIFS('Combined P&L'!N:N,'Combined P&L'!$C:$C,'P&L Forecast'!$B32) -> 9.555 | Q32: =SUMIFS('Combined P&L'!O:O,'Combined P&L'!$C:$C,'P&L Forecast'!$B32) -> 9.555 | R32: =SUMIFS('Combined P&L'!P:P,'Combined P&L'!$C:$C,'P&L Forecast'!$B32) -> 10.3972 | S32: =SUMIFS('Combined P&L'!Q:Q,'Combined P&L'!$C:$C,'P&L Forecast'!$B32) -> 14.99967 | T32: =SUMIFS('Combined P&L'!R:R,'Combined P&L'!$C:$C,'P&L Forecast'!$B32) -> 18.0098 | U32: =SUMIFS('Combined P&L'!S:S,'Combined P&L'!$C:$C,'P&L Forecast'!$B32) -> 13.89127 | V32: =SUMIFS('Combined P&L'!T:T,'Combined P&L'!$C:$C,'P&L Forecast'!$B32) -> 14.04824 | W32: =SUMIFS('Combined P&L'!U:U,'Combined P&L'!$C:$C,'P&L Forecast'!$B32) -> 13.39091 | X32: =SUMIFS('Combined P&L'!V:V,'Combined P&L'!$C:$C,'P&L Forecast'!$B32) -> 14.66931 | Y32: =SUMIFS('Combined P&L'!W:W,'Combined P&L'!$C:$C,'P&L Forecast'!$B32) -> 15.88253 | Z32: =SUMIFS('Combined P&L'!X:X,'Combined P&L'!$C:$C,'P&L Forecast'!$B32) -> 27.18867 | AA32: =SUMIFS('Combined P&L'!Y:Y,'Combined P&L'!$C:$C,'P&L Forecast'!$B32) -> 21.78143 | AB32: =SUMIFS('Combined P&L'!Z:Z,'Combined P&L'!$C:$C,'P&L Forecast'!$B32) -> 19.40233 | AC32: =SUMIFS('Combined P&L'!AA:AA,'Combined P&L'!$C:$C,'P&L Forecast'!$B32) -> 16.40053 | AD32: =SUMIFS('Combined P&L'!AB:AB,'Combined P&L'!$C:$C,'P&L Forecast'!$B32) -> 19.56983 | AE32: =SUMIFS('Combined P&L'!AC:AC,'Combined P&L'!$C:$C,'P&L Forecast'!$B32) -> 22.1542 | AF32: =SUMIFS('Combined P&L'!AD:AD,'Combined P&L'!$C:$C,'P&L Forecast'!$B32) -> 20.79154 | AG32: =SUMIFS('Combined P&L'!AE:AE,'Combined P&L'!$C:$C,'P&L Forecast'!$B32) -> 21.04079 | AH32: =SUMIFS('Combined P&L'!AF:AF,'Combined P&L'!$C:$C,'P&L Forecast'!$B32) -> 27.90891 | AI32: =SUMIFS('Combined P&L'!AG:AG,'Combined P&L'!$C:$C,'P&L Forecast'!$B32) -> 29.547 | AJ32: =SUMIFS('Combined P&L'!AH:AH,'Combined P&L'!$C:$C,'P&L Forecast'!$B32) -> 33.44727 | AK32: =SUMIFS('Combined P&L'!AI:AI,'Combined P&L'!$C:$C,'P&L Forecast'!$B32) -> 37.79432 | AL32: =SUMIFS('Combined P&L'!AJ:AJ,'Combined P&L'!$C:$C,'P&L Forecast'!$B32) -> 34.06332 | AM32: =SUMIFS('Combined P&L'!AK:AK,'Combined P&L'!$C:$C,'P&L Forecast'!$B32) -> 34.06458 | AN32: =SUMIFS('Combined P&L'!AL:AL,'Combined P&L'!$C:$C,'P&L Forecast'!$B32) -> 38.37888 | AO32: =SUMIFS('Combined P&L'!AM:AM,'Combined P&L'!$C:$C,'P&L Forecast'!$B32) -> 29.70152 | AP32: =SUMIFS('Combined P&L'!AN:AN,'Combined P&L'!$C:$C,'P&L Forecast'!$B32) -> 37.4225 | AQ32: =SUMIFS('Combined P&L'!AO:AO,'Combined P&L'!$C:$C,'P&L Forecast'!$B32) -> 38.7723 | AR32: =SUMIFS('Combined P&L'!AP:AP,'Combined P&L'!$C:$C,'P&L Forecast'!$B32) -> 38.29477 | AS32: =SUMIFS('Combined P&L'!AQ:AQ,'Combined P&L'!$C:$C,'P&L Forecast'!$B32) -> 40.69983 | AT32: =SUMIFS('Combined P&L'!AR:AR,'Combined P&L'!$C:$C,'P&L Forecast'!$B32) -> 44.4876
B33: Client Lead Wages | C33: =SUMIFS($P33:$AT33,$P$5:$AT$5,">"&C$199,$P$5:$AT$5,"<"&C$200) -> 286.16129 | D33: =SUMIFS($P33:$AT33,$P$5:$AT$5,">"&D$199,$P$5:$AT$5,"<"&D$200) -> 352.95844 | F33: =SUMIFS($P33:$AT33,$P$5:$AT$5,">"&F$199,$P$5:$AT$5,"<"&F$200) -> 201.27983 | G33: =SUMIFS($P33:$AT33,$P$5:$AT$5,">"&G$199,$P$5:$AT$5,"<"&G$200) -> 202.05309 | I33: =SUMIFS($P33:$AT33,$P$5:$AT$5,">"&I$199,$P$5:$AT$5,"<"&I$200) -> 353.12843 | J33: =SUMIFS($P33:$AT33,$P$5:$AT$5,">"&J$199,$P$5:$AT$5,"<"&J$200) -> 353.7317 | K33: =+C132 -> 392.92452 | M33: =K33-J33 -> 39.19282 | N33: =IFERROR(K33/J33-1,0) -> 0.11079816 | P33: =SUMIFS('Combined P&L'!N:N,'Combined P&L'!$C:$C,'P&L Forecast'!$B33) -> 9.96108 | Q33: =SUMIFS('Combined P&L'!O:O,'Combined P&L'!$C:$C,'P&L Forecast'!$B33) -> 13.85026 | R33: =SUMIFS('Combined P&L'!P:P,'Combined P&L'!$C:$C,'P&L Forecast'!$B33) -> 12.79054 | S33: =SUMIFS('Combined P&L'!Q:Q,'Combined P&L'!$C:$C,'P&L Forecast'!$B33) -> 14.57145 | T33: =SUMIFS('Combined P&L'!R:R,'Combined P&L'!$C:$C,'P&L Forecast'!$B33) -> 28.28563 | U33: =SUMIFS('Combined P&L'!S:S,'Combined P&L'!$C:$C,'P&L Forecast'!$B33) -> 26.54254 | V33: =SUMIFS('Combined P&L'!T:T,'Combined P&L'!$C:$C,'P&L Forecast'!$B33) -> 28.31119 | W33: =SUMIFS('Combined P&L'!U:U,'Combined P&L'!$C:$C,'P&L Forecast'!$B33) -> 28.18746 | X33: =SUMIFS('Combined P&L'!V:V,'Combined P&L'!$C:$C,'P&L Forecast'!$B33) -> 30.86801 | Y33: =SUMIFS('Combined P&L'!W:W,'Combined P&L'!$C:$C,'P&L Forecast'!$B33) -> 31.62128 | Z33: =SUMIFS('Combined P&L'!X:X,'Combined P&L'!$C:$C,'P&L Forecast'!$B33) -> 28.44974 | AA33: =SUMIFS('Combined P&L'!Y:Y,'Combined P&L'!$C:$C,'P&L Forecast'!$B33) -> 32.72211 | AB33: =SUMIFS('Combined P&L'!Z:Z,'Combined P&L'!$C:$C,'P&L Forecast'!$B33) -> 32.78076 | AC33: =SUMIFS('Combined P&L'!AA:AA,'Combined P&L'!$C:$C,'P&L Forecast'!$B33) -> 23.36184 | AD33: =SUMIFS('Combined P&L'!AB:AB,'Combined P&L'!$C:$C,'P&L Forecast'!$B33) -> 26.91427 | AE33: =SUMIFS('Combined P&L'!AC:AC,'Combined P&L'!$C:$C,'P&L Forecast'!$B33) -> 28.81298 | AF33: =SUMIFS('Combined P&L'!AD:AD,'Combined P&L'!$C:$C,'P&L Forecast'!$B33) -> 30.65875 | AG33: =SUMIFS('Combined P&L'!AE:AE,'Combined P&L'!$C:$C,'P&L Forecast'!$B33) -> 29.2716 | AH33: =SUMIFS('Combined P&L'!AF:AF,'Combined P&L'!$C:$C,'P&L Forecast'!$B33) -> 29.47963 | AI33: =SUMIFS('Combined P&L'!AG:AG,'Combined P&L'!$C:$C,'P&L Forecast'!$B33) -> 26.83064 | AJ33: =SUMIFS('Combined P&L'!AH:AH,'Combined P&L'!$C:$C,'P&L Forecast'!$B33) -> 29.78555 | AK33: =SUMIFS('Combined P&L'!AI:AI,'Combined P&L'!$C:$C,'P&L Forecast'!$B33) -> 32.89937 | AL33: =SUMIFS('Combined P&L'!AJ:AJ,'Combined P&L'!$C:$C,'P&L Forecast'!$B33) -> 29.49334 | AM33: =SUMIFS('Combined P&L'!AK:AK,'Combined P&L'!$C:$C,'P&L Forecast'!$B33) -> 32.66971 | AN33: =SUMIFS('Combined P&L'!AL:AL,'Combined P&L'!$C:$C,'P&L Forecast'!$B33) -> 26.1149 | AO33: =SUMIFS('Combined P&L'!AM:AM,'Combined P&L'!$C:$C,'P&L Forecast'!$B33) -> 21.9055 | AP33: =SUMIFS('Combined P&L'!AN:AN,'Combined P&L'!$C:$C,'P&L Forecast'!$B33) -> 30.75844 | AQ33: =SUMIFS('Combined P&L'!AO:AO,'Combined P&L'!$C:$C,'P&L Forecast'!$B33) -> 31.59038 | AR33: =SUMIFS('Combined P&L'!AP:AP,'Combined P&L'!$C:$C,'P&L Forecast'!$B33) -> 27.69992 | AS33: =SUMIFS('Combined P&L'!AQ:AQ,'Combined P&L'!$C:$C,'P&L Forecast'!$B33) -> 31.24024 | AT33: =SUMIFS('Combined P&L'!AR:AR,'Combined P&L'!$C:$C,'P&L Forecast'!$B33) -> 32.74371
B34: Onboarding Team Wages | C34: =SUMIFS($P34:$AT34,$P$5:$AT$5,">"&C$199,$P$5:$AT$5,"<"&C$200) -> 122.81255 | D34: =SUMIFS($P34:$AT34,$P$5:$AT$5,">"&D$199,$P$5:$AT$5,"<"&D$200) -> 152.16972 | F34: =SUMIFS($P34:$AT34,$P$5:$AT$5,">"&F$199,$P$5:$AT$5,"<"&F$200) -> 73.94962 | G34: =SUMIFS($P34:$AT34,$P$5:$AT$5,">"&G$199,$P$5:$AT$5,"<"&G$200) -> 111.27999 | I34: =SUMIFS($P34:$AT34,$P$5:$AT$5,">"&I$199,$P$5:$AT$5,"<"&I$200) -> 121.30735 | J34: =SUMIFS($P34:$AT34,$P$5:$AT$5,">"&J$199,$P$5:$AT$5,"<"&J$200) -> 189.50009 | K34: =+C136 -> 197.14944 | M34: =K34-J34 -> 7.64935 | N34: =IFERROR(K34/J34-1,0) -> 0.040365944 | P34: =SUMIFS('Combined P&L'!N:N,'Combined P&L'!$C:$C,'P&L Forecast'!$B34) -> 9.13728 | Q34: =SUMIFS('Combined P&L'!O:O,'Combined P&L'!$C:$C,'P&L Forecast'!$B34) -> 8.96296 | R34: =SUMIFS('Combined P&L'!P:P,'Combined P&L'!$C:$C,'P&L Forecast'!$B34) -> 10.19584 | S34: =SUMIFS('Combined P&L'!Q:Q,'Combined P&L'!$C:$C,'P&L Forecast'!$B34) -> 15.04429 | T34: =SUMIFS('Combined P&L'!R:R,'Combined P&L'!$C:$C,'P&L Forecast'!$B34) -> 16.63744 | U34: =SUMIFS('Combined P&L'!S:S,'Combined P&L'!$C:$C,'P&L Forecast'!$B34) -> 7.49499 | V34: =SUMIFS('Combined P&L'!T:T,'Combined P&L'!$C:$C,'P&L Forecast'!$B34) -> 7.98202 | W34: =SUMIFS('Combined P&L'!U:U,'Combined P&L'!$C:$C,'P&L Forecast'!$B34) -> 5.90274 | X34: =SUMIFS('Combined P&L'!V:V,'Combined P&L'!$C:$C,'P&L Forecast'!$B34) -> 7.76763 | Y34: =SUMIFS('Combined P&L'!W:W,'Combined P&L'!$C:$C,'P&L Forecast'!$B34) -> 8.21417 | Z34: =SUMIFS('Combined P&L'!X:X,'Combined P&L'!$C:$C,'P&L Forecast'!$B34) -> 12.62272 | AA34: =SUMIFS('Combined P&L'!Y:Y,'Combined P&L'!$C:$C,'P&L Forecast'!$B34) -> 12.85047 | AB34: =SUMIFS('Combined P&L'!Z:Z,'Combined P&L'!$C:$C,'P&L Forecast'!$B34) -> 10.34556 | AC34: =SUMIFS('Combined P&L'!AA:AA,'Combined P&L'!$C:$C,'P&L Forecast'!$B34) -> 8.08798 | AD34: =SUMIFS('Combined P&L'!AB:AB,'Combined P&L'!$C:$C,'P&L Forecast'!$B34) -> 9.75287 | AE34: =SUMIFS('Combined P&L'!AC:AC,'Combined P&L'!$C:$C,'P&L Forecast'!$B34) -> 10.28 | AF34: =SUMIFS('Combined P&L'!AD:AD,'Combined P&L'!$C:$C,'P&L Forecast'!$B34) -> 11.13632 | AG34: =SUMIFS('Combined P&L'!AE:AE,'Combined P&L'!$C:$C,'P&L Forecast'!$B34) -> 10.87432 | AH34: =SUMIFS('Combined P&L'!AF:AF,'Combined P&L'!$C:$C,'P&L Forecast'!$B34) -> 13.47257 | AI34: =SUMIFS('Combined P&L'!AG:AG,'Combined P&L'!$C:$C,'P&L Forecast'!$B34) -> 12.70407 | AJ34: =SUMIFS('Combined P&L'!AH:AH,'Combined P&L'!$C:$C,'P&L Forecast'!$B34) -> 14.69884 | AK34: =SUMIFS('Combined P&L'!AI:AI,'Combined P&L'!$C:$C,'P&L Forecast'!$B34) -> 15.54306 | AL34: =SUMIFS('Combined P&L'!AJ:AJ,'Combined P&L'!$C:$C,'P&L Forecast'!$B34) -> 14.34361 | AM34: =SUMIFS('Combined P&L'!AK:AK,'Combined P&L'!$C:$C,'P&L Forecast'!$B34) -> 20.93052 | AN34: =SUMIFS('Combined P&L'!AL:AL,'Combined P&L'!$C:$C,'P&L Forecast'!$B34) -> 16.55394 | AO34: =SUMIFS('Combined P&L'!AM:AM,'Combined P&L'!$C:$C,'P&L Forecast'!$B34) -> 11.52661 | AP34: =SUMIFS('Combined P&L'!AN:AN,'Combined P&L'!$C:$C,'P&L Forecast'!$B34) -> 14.93883 | AQ34: =SUMIFS('Combined P&L'!AO:AO,'Combined P&L'!$C:$C,'P&L Forecast'!$B34) -> 15.58352 | AR34: =SUMIFS('Combined P&L'!AP:AP,'Combined P&L'!$C:$C,'P&L Forecast'!$B34) -> 19.6034 | AS34: =SUMIFS('Combined P&L'!AQ:AQ,'Combined P&L'!$C:$C,'P&L Forecast'!$B34) -> 16.64457 | AT34: =SUMIFS('Combined P&L'!AR:AR,'Combined P&L'!$C:$C,'P&L Forecast'!$B34) -> 16.42912
B35: Owner Wages | C35: =SUMIFS($P35:$AT35,$P$5:$AT$5,">"&C$199,$P$5:$AT$5,"<"&C$200) -> 0 | D35: =SUMIFS($P35:$AT35,$P$5:$AT$5,">"&D$199,$P$5:$AT$5,"<"&D$200) -> 90.66704 | F35: =SUMIFS($P35:$AT35,$P$5:$AT$5,">"&F$199,$P$5:$AT$5,"<"&F$200) -> 45.46612 | G35: =SUMIFS($P35:$AT35,$P$5:$AT$5,">"&G$199,$P$5:$AT$5,"<"&G$200) -> 63.14302 | I35: =SUMIFS($P35:$AT35,$P$5:$AT$5,">"&I$199,$P$5:$AT$5,"<"&I$200) -> 45.46612 | J35: =SUMIFS($P35:$AT35,$P$5:$AT$5,">"&J$199,$P$5:$AT$5,"<"&J$200) -> 108.34394 | K35: =+C131 -> 108.34394 | M35: =K35-J35 -> 0 | N35: =IFERROR(K35/J35-1,0) -> 0 | P35: =SUMIFS('Combined P&L'!N:N,'Combined P&L'!$C:$C,'P&L Forecast'!$B35) -> 0 | Q35: =SUMIFS('Combined P&L'!O:O,'Combined P&L'!$C:$C,'P&L Forecast'!$B35) -> 0 | R35: =SUMIFS('Combined P&L'!P:P,'Combined P&L'!$C:$C,'P&L Forecast'!$B35) -> 0 | S35: =SUMIFS('Combined P&L'!Q:Q,'Combined P&L'!$C:$C,'P&L Forecast'!$B35) -> 0 | T35: =SUMIFS('Combined P&L'!R:R,'Combined P&L'!$C:$C,'P&L Forecast'!$B35) -> 0 | U35: =SUMIFS('Combined P&L'!S:S,'Combined P&L'!$C:$C,'P&L Forecast'!$B35) -> 0 | V35: =SUMIFS('Combined P&L'!T:T,'Combined P&L'!$C:$C,'P&L Forecast'!$B35) -> 0 | W35: =SUMIFS('Combined P&L'!U:U,'Combined P&L'!$C:$C,'P&L Forecast'!$B35) -> 0 | X35: =SUMIFS('Combined P&L'!V:V,'Combined P&L'!$C:$C,'P&L Forecast'!$B35) -> 0 | Y35: =SUMIFS('Combined P&L'!W:W,'Combined P&L'!$C:$C,'P&L Forecast'!$B35) -> 0 | Z35: =SUMIFS('Combined P&L'!X:X,'Combined P&L'!$C:$C,'P&L Forecast'!$B35) -> 0 | AA35: =SUMIFS('Combined P&L'!Y:Y,'Combined P&L'!$C:$C,'P&L Forecast'!$B35) -> 0 | AB35: =SUMIFS('Combined P&L'!Z:Z,'Combined P&L'!$C:$C,'P&L Forecast'!$B35) -> 0 | AC35: =SUMIFS('Combined P&L'!AA:AA,'Combined P&L'!$C:$C,'P&L Forecast'!$B35) -> 0 | AD35: =SUMIFS('Combined P&L'!AB:AB,'Combined P&L'!$C:$C,'P&L Forecast'!$B35) -> 8.90639 | AE35: =SUMIFS('Combined P&L'!AC:AC,'Combined P&L'!$C:$C,'P&L Forecast'!$B35) -> 9.23323 | AF35: =SUMIFS('Combined P&L'!AD:AD,'Combined P&L'!$C:$C,'P&L Forecast'!$B35) -> 9.10884 | AG35: =SUMIFS('Combined P&L'!AE:AE,'Combined P&L'!$C:$C,'P&L Forecast'!$B35) -> 8.69479 | AH35: =SUMIFS('Combined P&L'!AF:AF,'Combined P&L'!$C:$C,'P&L Forecast'!$B35) -> 9.52287 | AI35: =SUMIFS('Combined P&L'!AG:AG,'Combined P&L'!$C:$C,'P&L Forecast'!$B35) -> 8.69481 | AJ35: =SUMIFS('Combined P&L'!AH:AH,'Combined P&L'!$C:$C,'P&L Forecast'!$B35) -> 9.10884 | AK35: =SUMIFS('Combined P&L'!AI:AI,'Combined P&L'!$C:$C,'P&L Forecast'!$B35) -> 9.52287 | AL35: =SUMIFS('Combined P&L'!AJ:AJ,'Combined P&L'!$C:$C,'P&L Forecast'!$B35) -> 8.28076 | AM35: =SUMIFS('Combined P&L'!AK:AK,'Combined P&L'!$C:$C,'P&L Forecast'!$B35) -> 9.59364 | AN35: =SUMIFS('Combined P&L'!AL:AL,'Combined P&L'!$C:$C,'P&L Forecast'!$B35) -> 9.27621 | AO35: =SUMIFS('Combined P&L'!AM:AM,'Combined P&L'!$C:$C,'P&L Forecast'!$B35) -> 8.32263 | AP35: =SUMIFS('Combined P&L'!AN:AN,'Combined P&L'!$C:$C,'P&L Forecast'!$B35) -> 9.10883 | AQ35: =SUMIFS('Combined P&L'!AO:AO,'Combined P&L'!$C:$C,'P&L Forecast'!$B35) -> 9.10883 | AR35: =SUMIFS('Combined P&L'!AP:AP,'Combined P&L'!$C:$C,'P&L Forecast'!$B35) -> 8.69481 | AS35: =SUMIFS('Combined P&L'!AQ:AQ,'Combined P&L'!$C:$C,'P&L Forecast'!$B35) -> 9.10884 | AT35: =SUMIFS('Combined P&L'!AR:AR,'Combined P&L'!$C:$C,'P&L Forecast'!$B35) -> 9.52287
B36: S&M Wages | C36: =SUMIFS($P36:$AT36,$P$5:$AT$5,">"&C$199,$P$5:$AT$5,"<"&C$200) -> 0 | D36: =SUMIFS($P36:$AT36,$P$5:$AT$5,">"&D$199,$P$5:$AT$5,"<"&D$200) -> 19.14963 | F36: =SUMIFS($P36:$AT36,$P$5:$AT$5,">"&F$199,$P$5:$AT$5,"<"&F$200) -> 3.09945 | G36: =SUMIFS($P36:$AT36,$P$5:$AT$5,">"&G$199,$P$5:$AT$5,"<"&G$200) -> 51.94131 | I36: =SUMIFS($P36:$AT36,$P$5:$AT$5,">"&I$199,$P$5:$AT$5,"<"&I$200) -> 3.09945 | J36: =SUMIFS($P36:$AT36,$P$5:$AT$5,">"&J$199,$P$5:$AT$5,"<"&J$200) -> 67.99149 | K36: =+C133 -> 98.34912 | M36: =K36-J36 -> 30.35763 | N36: =IFERROR(K36/J36-1,0) -> 0.44649161 | P36: =SUMIFS('Combined P&L'!N:N,'Combined P&L'!$C:$C,'P&L Forecast'!$B36) -> 0 | Q36: =SUMIFS('Combined P&L'!O:O,'Combined P&L'!$C:$C,'P&L Forecast'!$B36) -> 0 | R36: =SUMIFS('Combined P&L'!P:P,'Combined P&L'!$C:$C,'P&L Forecast'!$B36) -> 0 | S36: =SUMIFS('Combined P&L'!Q:Q,'Combined P&L'!$C:$C,'P&L Forecast'!$B36) -> 0 | T36: =SUMIFS('Combined P&L'!R:R,'Combined P&L'!$C:$C,'P&L Forecast'!$B36) -> 0 | U36: =SUMIFS('Combined P&L'!S:S,'Combined P&L'!$C:$C,'P&L Forecast'!$B36) -> 0 | V36: =SUMIFS('Combined P&L'!T:T,'Combined P&L'!$C:$C,'P&L Forecast'!$B36) -> 0 | W36: =SUMIFS('Combined P&L'!U:U,'Combined P&L'!$C:$C,'P&L Forecast'!$B36) -> 0 | X36: =SUMIFS('Combined P&L'!V:V,'Combined P&L'!$C:$C,'P&L Forecast'!$B36) -> 0 | Y36: =SUMIFS('Combined P&L'!W:W,'Combined P&L'!$C:$C,'P&L Forecast'!$B36) -> 0 | Z36: =SUMIFS('Combined P&L'!X:X,'Combined P&L'!$C:$C,'P&L Forecast'!$B36) -> 0 | AA36: =SUMIFS('Combined P&L'!Y:Y,'Combined P&L'!$C:$C,'P&L Forecast'!$B36) -> 0 | AB36: =SUMIFS('Combined P&L'!Z:Z,'Combined P&L'!$C:$C,'P&L Forecast'!$B36) -> 0 | AC36: =SUMIFS('Combined P&L'!AA:AA,'Combined P&L'!$C:$C,'P&L Forecast'!$B36) -> 0 | AD36: =SUMIFS('Combined P&L'!AB:AB,'Combined P&L'!$C:$C,'P&L Forecast'!$B36) -> 0 | AE36: =SUMIFS('Combined P&L'!AC:AC,'Combined P&L'!$C:$C,'P&L Forecast'!$B36) -> 0 | AF36: =SUMIFS('Combined P&L'!AD:AD,'Combined P&L'!$C:$C,'P&L Forecast'!$B36) -> 0 | AG36: =SUMIFS('Combined P&L'!AE:AE,'Combined P&L'!$C:$C,'P&L Forecast'!$B36) -> 1.4668 | AH36: =SUMIFS('Combined P&L'!AF:AF,'Combined P&L'!$C:$C,'P&L Forecast'!$B36) -> 1.63265 | AI36: =SUMIFS('Combined P&L'!AG:AG,'Combined P&L'!$C:$C,'P&L Forecast'!$B36) -> 1.71805 | AJ36: =SUMIFS('Combined P&L'!AH:AH,'Combined P&L'!$C:$C,'P&L Forecast'!$B36) -> 1.9146 | AK36: =SUMIFS('Combined P&L'!AI:AI,'Combined P&L'!$C:$C,'P&L Forecast'!$B36) -> 2.3529 | AL36: =SUMIFS('Combined P&L'!AJ:AJ,'Combined P&L'!$C:$C,'P&L Forecast'!$B36) -> 2.24524 | AM36: =SUMIFS('Combined P&L'!AK:AK,'Combined P&L'!$C:$C,'P&L Forecast'!$B36) -> 7.81939 | AN36: =SUMIFS('Combined P&L'!AL:AL,'Combined P&L'!$C:$C,'P&L Forecast'!$B36) -> 5.6534 | AO36: =SUMIFS('Combined P&L'!AM:AM,'Combined P&L'!$C:$C,'P&L Forecast'!$B36) -> 5.95689 | AP36: =SUMIFS('Combined P&L'!AN:AN,'Combined P&L'!$C:$C,'P&L Forecast'!$B36) -> 7.7828 | AQ36: =SUMIFS('Combined P&L'!AO:AO,'Combined P&L'!$C:$C,'P&L Forecast'!$B36) -> 8.13701 | AR36: =SUMIFS('Combined P&L'!AP:AP,'Combined P&L'!$C:$C,'P&L Forecast'!$B36) -> 7.80825 | AS36: =SUMIFS('Combined P&L'!AQ:AQ,'Combined P&L'!$C:$C,'P&L Forecast'!$B36) -> 8.4072 | AT36: =SUMIFS('Combined P&L'!AR:AR,'Combined P&L'!$C:$C,'P&L Forecast'!$B36) -> 8.19576
B37: Occupancy Tax Specialist | C37: =SUMIFS($P37:$AT37,$P$5:$AT$5,">"&C$199,$P$5:$AT$5,"<"&C$200) -> 1.11335 | D37: =SUMIFS($P37:$AT37,$P$5:$AT$5,">"&D$199,$P$5:$AT$5,"<"&D$200) -> 29.56415 | F37: =SUMIFS($P37:$AT37,$P$5:$AT$5,">"&F$199,$P$5:$AT$5,"<"&F$200) -> 14.27585 | G37: =SUMIFS($P37:$AT37,$P$5:$AT$5,">"&G$199,$P$5:$AT$5,"<"&G$200) -> 42.08505 | I37: =SUMIFS($P37:$AT37,$P$5:$AT$5,">"&I$199,$P$5:$AT$5,"<"&I$200) -> 15.3892 | J37: =SUMIFS($P37:$AT37,$P$5:$AT$5,">"&J$199,$P$5:$AT$5,"<"&J$200) -> 57.37335 | K37: =+C134 -> 58.2 | M37: =K37-J37 -> 0.82665 | N37: =IFERROR(K37/J37-1,0) -> 0.014408257 | P37: =SUMIFS('Combined P&L'!N:N,'Combined P&L'!$C:$C,'P&L Forecast'!$B37) -> 0 | Q37: =SUMIFS('Combined P&L'!O:O,'Combined P&L'!$C:$C,'P&L Forecast'!$B37) -> 0 | R37: =SUMIFS('Combined P&L'!P:P,'Combined P&L'!$C:$C,'P&L Forecast'!$B37) -> 0 | S37: =SUMIFS('Combined P&L'!Q:Q,'Combined P&L'!$C:$C,'P&L Forecast'!$B37) -> 0 | T37: =SUMIFS('Combined P&L'!R:R,'Combined P&L'!$C:$C,'P&L Forecast'!$B37) -> 0 | U37: =SUMIFS('Combined P&L'!S:S,'Combined P&L'!$C:$C,'P&L Forecast'!$B37) -> 0 | V37: =SUMIFS('Combined P&L'!T:T,'Combined P&L'!$C:$C,'P&L Forecast'!$B37) -> 0 | W37: =SUMIFS('Combined P&L'!U:U,'Combined P&L'!$C:$C,'P&L Forecast'!$B37) -> 0 | X37: =SUMIFS('Combined P&L'!V:V,'Combined P&L'!$C:$C,'P&L Forecast'!$B37) -> 0 | Y37: =SUMIFS('Combined P&L'!W:W,'Combined P&L'!$C:$C,'P&L Forecast'!$B37) -> 0 | Z37: =SUMIFS('Combined P&L'!X:X,'Combined P&L'!$C:$C,'P&L Forecast'!$B37) -> 0 | AA37: =SUMIFS('Combined P&L'!Y:Y,'Combined P&L'!$C:$C,'P&L Forecast'!$B37) -> 1.11335 | AB37: =SUMIFS('Combined P&L'!Z:Z,'Combined P&L'!$C:$C,'P&L Forecast'!$B37) -> 2.17917 | AC37: =SUMIFS('Combined P&L'!AA:AA,'Combined P&L'!$C:$C,'P&L Forecast'!$B37) -> 1.82504 | AD37: =SUMIFS('Combined P&L'!AB:AB,'Combined P&L'!$C:$C,'P&L Forecast'!$B37) -> 1.97853 | AE37: =SUMIFS('Combined P&L'!AC:AC,'Combined P&L'!$C:$C,'P&L Forecast'!$B37) -> 2.06213 | AF37: =SUMIFS('Combined P&L'!AD:AD,'Combined P&L'!$C:$C,'P&L Forecast'!$B37) -> 2.06213 | AG37: =SUMIFS('Combined P&L'!AE:AE,'Combined P&L'!$C:$C,'P&L Forecast'!$B37) -> 1.98968 | AH37: =SUMIFS('Combined P&L'!AF:AF,'Combined P&L'!$C:$C,'P&L Forecast'!$B37) -> 2.17917 | AI37: =SUMIFS('Combined P&L'!AG:AG,'Combined P&L'!$C:$C,'P&L Forecast'!$B37) -> 2.12293 | AJ37: =SUMIFS('Combined P&L'!AH:AH,'Combined P&L'!$C:$C,'P&L Forecast'!$B37) -> 3.1042 | AK37: =SUMIFS('Combined P&L'!AI:AI,'Combined P&L'!$C:$C,'P&L Forecast'!$B37) -> 3.27137 | AL37: =SUMIFS('Combined P&L'!AJ:AJ,'Combined P&L'!$C:$C,'P&L Forecast'!$B37) -> 3.63947 | AM37: =SUMIFS('Combined P&L'!AK:AK,'Combined P&L'!$C:$C,'P&L Forecast'!$B37) -> 3.15033 | AN37: =SUMIFS('Combined P&L'!AL:AL,'Combined P&L'!$C:$C,'P&L Forecast'!$B37) -> 1.69116 | AO37: =SUMIFS('Combined P&L'!AM:AM,'Combined P&L'!$C:$C,'P&L Forecast'!$B37) -> 5.54919 | AP37: =SUMIFS('Combined P&L'!AN:AN,'Combined P&L'!$C:$C,'P&L Forecast'!$B37) -> 7.1999 | AQ37: =SUMIFS('Combined P&L'!AO:AO,'Combined P&L'!$C:$C,'P&L Forecast'!$B37) -> 8.1927 | AR37: =SUMIFS('Combined P&L'!AP:AP,'Combined P&L'!$C:$C,'P&L Forecast'!$B37) -> 8.28335 | AS37: =SUMIFS('Combined P&L'!AQ:AQ,'Combined P&L'!$C:$C,'P&L Forecast'!$B37) -> 5.49265 | AT37: =SUMIFS('Combined P&L'!AR:AR,'Combined P&L'!$C:$C,'P&L Forecast'!$B37) -> 5.6761
B38: Sr. Client Lead Wages | C38: =SUMIFS($P38:$AT38,$P$5:$AT$5,">"&C$199,$P$5:$AT$5,"<"&C$200) -> 0 | D38: =SUMIFS($P38:$AT38,$P$5:$AT$5,">"&D$199,$P$5:$AT$5,"<"&D$200) -> 0 | F38: =SUMIFS($P38:$AT38,$P$5:$AT$5,">"&F$199,$P$5:$AT$5,"<"&F$200) -> 0 | G38: =SUMIFS($P38:$AT38,$P$5:$AT$5,">"&G$199,$P$5:$AT$5,"<"&G$200) -> 7.995 | I38: =SUMIFS($P38:$AT38,$P$5:$AT$5,">"&I$199,$P$5:$AT$5,"<"&I$200) -> 0 | J38: =SUMIFS($P38:$AT38,$P$5:$AT$5,">"&J$199,$P$5:$AT$5,"<"&J$200) -> 7.995 | K38: =+C135 -> 33.08124 | M38: =K38-J38 -> 25.08624 | N38: =IFERROR(K38/J38-1,0) -> 3.1377411 | P38: =SUMIFS('Combined P&L'!N:N,'Combined P&L'!$C:$C,'P&L Forecast'!$B38) -> 0 | Q38: =SUMIFS('Combined P&L'!O:O,'Combined P&L'!$C:$C,'P&L Forecast'!$B38) -> 0 | R38: =SUMIFS('Combined P&L'!P:P,'Combined P&L'!$C:$C,'P&L Forecast'!$B38) -> 0 | S38: =SUMIFS('Combined P&L'!Q:Q,'Combined P&L'!$C:$C,'P&L Forecast'!$B38) -> 0 | T38: =SUMIFS('Combined P&L'!R:R,'Combined P&L'!$C:$C,'P&L Forecast'!$B38) -> 0 | U38: =SUMIFS('Combined P&L'!S:S,'Combined P&L'!$C:$C,'P&L Forecast'!$B38) -> 0 | V38: =SUMIFS('Combined P&L'!T:T,'Combined P&L'!$C:$C,'P&L Forecast'!$B38) -> 0 | W38: =SUMIFS('Combined P&L'!U:U,'Combined P&L'!$C:$C,'P&L Forecast'!$B38) -> 0 | X38: =SUMIFS('Combined P&L'!V:V,'Combined P&L'!$C:$C,'P&L Forecast'!$B38) -> 0 | Y38: =SUMIFS('Combined P&L'!W:W,'Combined P&L'!$C:$C,'P&L Forecast'!$B38) -> 0 | Z38: =SUMIFS('Combined P&L'!X:X,'Combined P&L'!$C:$C,'P&L Forecast'!$B38) -> 0 | AA38: =SUMIFS('Combined P&L'!Y:Y,'Combined P&L'!$C:$C,'P&L Forecast'!$B38) -> 0 | AB38: =SUMIFS('Combined P&L'!Z:Z,'Combined P&L'!$C:$C,'P&L Forecast'!$B38) -> 0 | AC38: =SUMIFS('Combined P&L'!AA:AA,'Combined P&L'!$C:$C,'P&L Forecast'!$B38) -> 0 | AD38: =SUMIFS('Combined P&L'!AB:AB,'Combined P&L'!$C:$C,'P&L Forecast'!$B38) -> 0 | AE38: =SUMIFS('Combined P&L'!AC:AC,'Combined P&L'!$C:$C,'P&L Forecast'!$B38) -> 0 | AF38: =SUMIFS('Combined P&L'!AD:AD,'Combined P&L'!$C:$C,'P&L Forecast'!$B38) -> 0 | AG38: =SUMIFS('Combined P&L'!AE:AE,'Combined P&L'!$C:$C,'P&L Forecast'!$B38) -> 0 | AH38: =SUMIFS('Combined P&L'!AF:AF,'Combined P&L'!$C:$C,'P&L Forecast'!$B38) -> 0 | AI38: =SUMIFS('Combined P&L'!AG:AG,'Combined P&L'!$C:$C,'P&L Forecast'!$B38) -> 0 | AJ38: =SUMIFS('Combined P&L'!AH:AH,'Combined P&L'!$C:$C,'P&L Forecast'!$B38) -> 0 | AK38: =SUMIFS('Combined P&L'!AI:AI,'Combined P&L'!$C:$C,'P&L Forecast'!$B38) -> 0 | AL38: =SUMIFS('Combined P&L'!AJ:AJ,'Combined P&L'!$C:$C,'P&L Forecast'!$B38) -> 0 | AM38: =SUMIFS('Combined P&L'!AK:AK,'Combined P&L'!$C:$C,'P&L Forecast'!$B38) -> 0 | AN38: =SUMIFS('Combined P&L'!AL:AL,'Combined P&L'!$C:$C,'P&L Forecast'!$B38) -> 0 | AO38: =SUMIFS('Combined P&L'!AM:AM,'Combined P&L'!$C:$C,'P&L Forecast'!$B38) -> 0 | AP38: =SUMIFS('Combined P&L'!AN:AN,'Combined P&L'!$C:$C,'P&L Forecast'!$B38) -> 0 | AQ38: =SUMIFS('Combined P&L'!AO:AO,'Combined P&L'!$C:$C,'P&L Forecast'!$B38) -> 0 | AR38: =SUMIFS('Combined P&L'!AP:AP,'Combined P&L'!$C:$C,'P&L Forecast'!$B38) -> 2.51706 | AS38: =SUMIFS('Combined P&L'!AQ:AQ,'Combined P&L'!$C:$C,'P&L Forecast'!$B38) -> 2.72117 | AT38: =SUMIFS('Combined P&L'!AR:AR,'Combined P&L'!$C:$C,'P&L Forecast'!$B38) -> 2.75677
B39: Employee Benefits | C39: =SUMIFS($P39:$AT39,$P$5:$AT$5,">"&C$199,$P$5:$AT$5,"<"&C$200) -> 5.37405 | D39: =SUMIFS($P39:$AT39,$P$5:$AT$5,">"&D$199,$P$5:$AT$5,"<"&D$200) -> 19.23245 | F39: =SUMIFS($P39:$AT39,$P$5:$AT$5,">"&F$199,$P$5:$AT$5,"<"&F$200) -> 9.02166 | G39: =SUMIFS($P39:$AT39,$P$5:$AT$5,">"&G$199,$P$5:$AT$5,"<"&G$200) -> 17.36251 | I39: =SUMIFS($P39:$AT39,$P$5:$AT$5,">"&I$199,$P$5:$AT$5,"<"&I$200) -> 12.16686 | J39: =SUMIFS($P39:$AT39,$P$5:$AT$5,">"&J$199,$P$5:$AT$5,"<"&J$200) -> 27.5733 | K39: =+C137 -> 32.17836 | M39: =K39-J39 -> 4.60506 | N39: =IFERROR(K39/J39-1,0) -> 0.16701157 | P39: =SUMIFS('Combined P&L'!N:N,'Combined P&L'!$C:$C,'P&L Forecast'!$B39) -> 0 | Q39: =SUMIFS('Combined P&L'!O:O,'Combined P&L'!$C:$C,'P&L Forecast'!$B39) -> 0.6277 | R39: =SUMIFS('Combined P&L'!P:P,'Combined P&L'!$C:$C,'P&L Forecast'!$B39) -> 0 | S39: =SUMIFS('Combined P&L'!Q:Q,'Combined P&L'!$C:$C,'P&L Forecast'!$B39) -> 0.3389 | T39: =SUMIFS('Combined P&L'!R:R,'Combined P&L'!$C:$C,'P&L Forecast'!$B39) -> 0.3389 | U39: =SUMIFS('Combined P&L'!S:S,'Combined P&L'!$C:$C,'P&L Forecast'!$B39) -> 0.06145 | V39: =SUMIFS('Combined P&L'!T:T,'Combined P&L'!$C:$C,'P&L Forecast'!$B39) -> 0.8619 | W39: =SUMIFS('Combined P&L'!U:U,'Combined P&L'!$C:$C,'P&L Forecast'!$B39) -> 0.35956 | X39: =SUMIFS('Combined P&L'!V:V,'Combined P&L'!$C:$C,'P&L Forecast'!$B39) -> 0.38745 | Y39: =SUMIFS('Combined P&L'!W:W,'Combined P&L'!$C:$C,'P&L Forecast'!$B39) -> 0.6989 | Z39: =SUMIFS('Combined P&L'!X:X,'Combined P&L'!$C:$C,'P&L Forecast'!$B39) -> 0.917 | AA39: =SUMIFS('Combined P&L'!Y:Y,'Combined P&L'!$C:$C,'P&L Forecast'!$B39) -> 0.78229 | AB39: =SUMIFS('Combined P&L'!Z:Z,'Combined P&L'!$C:$C,'P&L Forecast'!$B39) -> 0.93724 | AC39: =SUMIFS('Combined P&L'!AA:AA,'Combined P&L'!$C:$C,'P&L Forecast'!$B39) -> 1.03107 | AD39: =SUMIFS('Combined P&L'!AB:AB,'Combined P&L'!$C:$C,'P&L Forecast'!$B39) -> 0.66153 | AE39: =SUMIFS('Combined P&L'!AC:AC,'Combined P&L'!$C:$C,'P&L Forecast'!$B39) -> 0.71453 | AF39: =SUMIFS('Combined P&L'!AD:AD,'Combined P&L'!$C:$C,'P&L Forecast'!$B39) -> 2.25493 | AG39: =SUMIFS('Combined P&L'!AE:AE,'Combined P&L'!$C:$C,'P&L Forecast'!$B39) -> 1.86153 | AH39: =SUMIFS('Combined P&L'!AF:AF,'Combined P&L'!$C:$C,'P&L Forecast'!$B39) -> 1.56083 | AI39: =SUMIFS('Combined P&L'!AG:AG,'Combined P&L'!$C:$C,'P&L Forecast'!$B39) -> 1.74767 | AJ39: =SUMIFS('Combined P&L'!AH:AH,'Combined P&L'!$C:$C,'P&L Forecast'!$B39) -> 0.90753 | AK39: =SUMIFS('Combined P&L'!AI:AI,'Combined P&L'!$C:$C,'P&L Forecast'!$B39) -> 2.51353 | AL39: =SUMIFS('Combined P&L'!AJ:AJ,'Combined P&L'!$C:$C,'P&L Forecast'!$B39) -> 1.03753 | AM39: =SUMIFS('Combined P&L'!AK:AK,'Combined P&L'!$C:$C,'P&L Forecast'!$B39) -> 4.00453 | AN39: =SUMIFS('Combined P&L'!AL:AL,'Combined P&L'!$C:$C,'P&L Forecast'!$B39) -> 1.57873 | AO39: =SUMIFS('Combined P&L'!AM:AM,'Combined P&L'!$C:$C,'P&L Forecast'!$B39) -> 1.14553 | AP39: =SUMIFS('Combined P&L'!AN:AN,'Combined P&L'!$C:$C,'P&L Forecast'!$B39) -> 5.13853 | AQ39: =SUMIFS('Combined P&L'!AO:AO,'Combined P&L'!$C:$C,'P&L Forecast'!$B39) -> 1.92353 | AR39: =SUMIFS('Combined P&L'!AP:AP,'Combined P&L'!$C:$C,'P&L Forecast'!$B39) -> 1.46353 | AS39: =SUMIFS('Combined P&L'!AQ:AQ,'Combined P&L'!$C:$C,'P&L Forecast'!$B39) -> 3.43113 | AT39: =SUMIFS('Combined P&L'!AR:AR,'Combined P&L'!$C:$C,'P&L Forecast'!$B39) -> 2.68153
B40: Total Payroll Expenses | C40: =SUM(C31:C39) -> 700.20547 | D40: =SUM(D31:D39) -> 1261.1666 | F40: =SUM(F31:F39) -> 630.65714 | G40: =SUM(G31:G39) -> 1120.8921 | I40: =SUM(I31:I39) -> 993.15437 | J40: =SUM(J31:J39) -> 1751.4015 | K40: =SUM(K31:K39) -> 2094.1266 | M40: =SUM(M31:M39) -> 342.72508 | N40: =IFERROR(K40/J40-1,0) -> 0.19568618 | P40: =SUM(P31:P39) -> 31.74682 | Q40: =SUM(Q31:Q39) -> 37.62609 | R40: =SUM(R31:R39) -> 37.77865 | S40: =SUM(S31:S39) -> 50.81818 | T40: =SUM(T31:T39) -> 70.6441 | U40: =SUM(U31:U39) -> 52.94065 | V40: =SUM(V31:V39) -> 56.15375 | W40: =SUM(W31:W39) -> 52.54102 | ... AT40: =SUM(AT31:AT39) -> 180.38884
B42: Software & Apps - COGS | C42: =SUMIFS($P42:$AT42,$P$5:$AT$5,">"&C$199,$P$5:$AT$5,"<"&C$200) -> 114.42269 | D42: =SUMIFS($P42:$AT42,$P$5:$AT$5,">"&D$199,$P$5:$AT$5,"<"&D$200) -> 157.49471 | F42: =SUMIFS($P42:$AT42,$P$5:$AT$5,">"&F$199,$P$5:$AT$5,"<"&F$200) -> 84.96859 | G42: =SUMIFS($P42:$AT42,$P$5:$AT$5,">"&G$199,$P$5:$AT$5,"<"&G$200) -> 152.28157 | I42: =SUMIFS($P42:$AT42,$P$5:$AT$5,">"&I$199,$P$5:$AT$5,"<"&I$200) -> 142.28345 | J42: =SUMIFS($P42:$AT42,$P$5:$AT$5,">"&J$199,$P$5:$AT$5,"<"&J$200) -> 224.80769 | K42: =+C141 -> 335.70816 | M42: =K42-J42 -> 110.90047 | N42: =IFERROR(K42/J42-1,0) -> 0.49331262 | P42: =SUMIFS('Combined P&L'!N:N,'Combined P&L'!$C:$C,'P&L Forecast'!$B42) -> 7.073 | Q42: =SUMIFS('Combined P&L'!O:O,'Combined P&L'!$C:$C,'P&L Forecast'!$B42) -> 7.01818 | R42: =SUMIFS('Combined P&L'!P:P,'Combined P&L'!$C:$C,'P&L Forecast'!$B42) -> 7.77788 | S42: =SUMIFS('Combined P&L'!Q:Q,'Combined P&L'!$C:$C,'P&L Forecast'!$B42) -> 7.76124 | T42: =SUMIFS('Combined P&L'!R:R,'Combined P&L'!$C:$C,'P&L Forecast'!$B42) -> 7.71821 | U42: =SUMIFS('Combined P&L'!S:S,'Combined P&L'!$C:$C,'P&L Forecast'!$B42) -> 8.91264 | V42: =SUMIFS('Combined P&L'!T:T,'Combined P&L'!$C:$C,'P&L Forecast'!$B42) -> 10.84668 | W42: =SUMIFS('Combined P&L'!U:U,'Combined P&L'!$C:$C,'P&L Forecast'!$B42) -> 11.13514 | X42: =SUMIFS('Combined P&L'!V:V,'Combined P&L'!$C:$C,'P&L Forecast'!$B42) -> 11.0345 | Y42: =SUMIFS('Combined P&L'!W:W,'Combined P&L'!$C:$C,'P&L Forecast'!$B42) -> 11.72873 | Z42: =SUMIFS('Combined P&L'!X:X,'Combined P&L'!$C:$C,'P&L Forecast'!$B42) -> 11.44691 | AA42: =SUMIFS('Combined P&L'!Y:Y,'Combined P&L'!$C:$C,'P&L Forecast'!$B42) -> 11.96958 | AB42: =SUMIFS('Combined P&L'!Z:Z,'Combined P&L'!$C:$C,'P&L Forecast'!$B42) -> 10.84853 | AC42: =SUMIFS('Combined P&L'!AA:AA,'Combined P&L'!$C:$C,'P&L Forecast'!$B42) -> 12.21311 | AD42: =SUMIFS('Combined P&L'!AB:AB,'Combined P&L'!$C:$C,'P&L Forecast'!$B42) -> 11.57167 | AE42: =SUMIFS('Combined P&L'!AC:AC,'Combined P&L'!$C:$C,'P&L Forecast'!$B42) -> 11.81087 | AF42: =SUMIFS('Combined P&L'!AD:AD,'Combined P&L'!$C:$C,'P&L Forecast'!$B42) -> 12.52563 | AG42: =SUMIFS('Combined P&L'!AE:AE,'Combined P&L'!$C:$C,'P&L Forecast'!$B42) -> 12.86333 | AH42: =SUMIFS('Combined P&L'!AF:AF,'Combined P&L'!$C:$C,'P&L Forecast'!$B42) -> 13.13545 | AI42: =SUMIFS('Combined P&L'!AG:AG,'Combined P&L'!$C:$C,'P&L Forecast'!$B42) -> 14.25715 | AJ42: =SUMIFS('Combined P&L'!AH:AH,'Combined P&L'!$C:$C,'P&L Forecast'!$B42) -> 13.59512 | AK42: =SUMIFS('Combined P&L'!AI:AI,'Combined P&L'!$C:$C,'P&L Forecast'!$B42) -> 12.34762 | AL42: =SUMIFS('Combined P&L'!AJ:AJ,'Combined P&L'!$C:$C,'P&L Forecast'!$B42) -> 15.21781 | AM42: =SUMIFS('Combined P&L'!AK:AK,'Combined P&L'!$C:$C,'P&L Forecast'!$B42) -> 17.10842 | AN42: =SUMIFS('Combined P&L'!AL:AL,'Combined P&L'!$C:$C,'P&L Forecast'!$B42) -> 18.4683 | AO42: =SUMIFS('Combined P&L'!AM:AM,'Combined P&L'!$C:$C,'P&L Forecast'!$B42) -> 17.92027 | AP42: =SUMIFS('Combined P&L'!AN:AN,'Combined P&L'!$C:$C,'P&L Forecast'!$B42) -> 18.40906 | AQ42: =SUMIFS('Combined P&L'!AO:AO,'Combined P&L'!$C:$C,'P&L Forecast'!$B42) -> 21.38775 | AR42: =SUMIFS('Combined P&L'!AP:AP,'Combined P&L'!$C:$C,'P&L Forecast'!$B42) -> 23.44584 | AS42: =SUMIFS('Combined P&L'!AQ:AQ,'Combined P&L'!$C:$C,'P&L Forecast'!$B42) -> 24.67467 | AT42: =SUMIFS('Combined P&L'!AR:AR,'Combined P&L'!$C:$C,'P&L Forecast'!$B42) -> 27.97568
B43: Software & Apps - G&A | C43: =SUMIFS($P43:$AT43,$P$5:$AT$5,">"&C$199,$P$5:$AT$5,"<"&C$200) -> 60.91594 | D43: =SUMIFS($P43:$AT43,$P$5:$AT$5,">"&D$199,$P$5:$AT$5,"<"&D$200) -> 117.05866 | F43: =SUMIFS($P43:$AT43,$P$5:$AT$5,">"&F$199,$P$5:$AT$5,"<"&F$200) -> 56.8115 | G43: =SUMIFS($P43:$AT43,$P$5:$AT$5,">"&G$199,$P$5:$AT$5,"<"&G$200) -> 97.04798 | I43: =SUMIFS($P43:$AT43,$P$5:$AT$5,">"&I$199,$P$5:$AT$5,"<"&I$200) -> 86.51489 | J43: =SUMIFS($P43:$AT43,$P$5:$AT$5,">"&J$199,$P$5:$AT$5,"<"&J$200) -> 157.29514 | K43: =+C142 -> 155.82264 | M43: =K43-J43 -> -1.4725 | N43: =IFERROR(K43/J43-1,0) -> -0.0093613827 | P43: =SUMIFS('Combined P&L'!N:N,'Combined P&L'!$C:$C,'P&L Forecast'!$B43) -> 3.45285 | Q43: =SUMIFS('Combined P&L'!O:O,'Combined P&L'!$C:$C,'P&L Forecast'!$B43) -> 3.61753 | R43: =SUMIFS('Combined P&L'!P:P,'Combined P&L'!$C:$C,'P&L Forecast'!$B43) -> 3.97407 | S43: =SUMIFS('Combined P&L'!Q:Q,'Combined P&L'!$C:$C,'P&L Forecast'!$B43) -> 4.22365 | T43: =SUMIFS('Combined P&L'!R:R,'Combined P&L'!$C:$C,'P&L Forecast'!$B43) -> 5.09725 | U43: =SUMIFS('Combined P&L'!S:S,'Combined P&L'!$C:$C,'P&L Forecast'!$B43) -> 5.33351 | V43: =SUMIFS('Combined P&L'!T:T,'Combined P&L'!$C:$C,'P&L Forecast'!$B43) -> 5.51369 | W43: =SUMIFS('Combined P&L'!U:U,'Combined P&L'!$C:$C,'P&L Forecast'!$B43) -> 5.23169 | X43: =SUMIFS('Combined P&L'!V:V,'Combined P&L'!$C:$C,'P&L Forecast'!$B43) -> 5.51622 | Y43: =SUMIFS('Combined P&L'!W:W,'Combined P&L'!$C:$C,'P&L Forecast'!$B43) -> 6.12797 | Z43: =SUMIFS('Combined P&L'!X:X,'Combined P&L'!$C:$C,'P&L Forecast'!$B43) -> 6.15097 | AA43: =SUMIFS('Combined P&L'!Y:Y,'Combined P&L'!$C:$C,'P&L Forecast'!$B43) -> 6.67654 | AB43: =SUMIFS('Combined P&L'!Z:Z,'Combined P&L'!$C:$C,'P&L Forecast'!$B43) -> 7.74646 | AC43: =SUMIFS('Combined P&L'!AA:AA,'Combined P&L'!$C:$C,'P&L Forecast'!$B43) -> 7.89181 | AD43: =SUMIFS('Combined P&L'!AB:AB,'Combined P&L'!$C:$C,'P&L Forecast'!$B43) -> 7.89085 | AE43: =SUMIFS('Combined P&L'!AC:AC,'Combined P&L'!$C:$C,'P&L Forecast'!$B43) -> 7.83463 | AF43: =SUMIFS('Combined P&L'!AD:AD,'Combined P&L'!$C:$C,'P&L Forecast'!$B43) -> 8.11723 | AG43: =SUMIFS('Combined P&L'!AE:AE,'Combined P&L'!$C:$C,'P&L Forecast'!$B43) -> 8.34584 | AH43: =SUMIFS('Combined P&L'!AF:AF,'Combined P&L'!$C:$C,'P&L Forecast'!$B43) -> 8.98468 | AI43: =SUMIFS('Combined P&L'!AG:AG,'Combined P&L'!$C:$C,'P&L Forecast'!$B43) -> 9.8566 | AJ43: =SUMIFS('Combined P&L'!AH:AH,'Combined P&L'!$C:$C,'P&L Forecast'!$B43) -> 10.73391 | AK43: =SUMIFS('Combined P&L'!AI:AI,'Combined P&L'!$C:$C,'P&L Forecast'!$B43) -> 12.08939 | AL43: =SUMIFS('Combined P&L'!AJ:AJ,'Combined P&L'!$C:$C,'P&L Forecast'!$B43) -> 13.14583 | AM43: =SUMIFS('Combined P&L'!AK:AK,'Combined P&L'!$C:$C,'P&L Forecast'!$B43) -> 14.42143 | AN43: =SUMIFS('Combined P&L'!AL:AL,'Combined P&L'!$C:$C,'P&L Forecast'!$B43) -> 13.26316 | AO43: =SUMIFS('Combined P&L'!AM:AM,'Combined P&L'!$C:$C,'P&L Forecast'!$B43) -> 14.7201 | AP43: =SUMIFS('Combined P&L'!AN:AN,'Combined P&L'!$C:$C,'P&L Forecast'!$B43) -> 14.99072 | AQ43: =SUMIFS('Combined P&L'!AO:AO,'Combined P&L'!$C:$C,'P&L Forecast'!$B43) -> 14.74459 | AR43: =SUMIFS('Combined P&L'!AP:AP,'Combined P&L'!$C:$C,'P&L Forecast'!$B43) -> 13.2292 | AS43: =SUMIFS('Combined P&L'!AQ:AQ,'Combined P&L'!$C:$C,'P&L Forecast'!$B43) -> 13.11499 | AT43: =SUMIFS('Combined P&L'!AR:AR,'Combined P&L'!$C:$C,'P&L Forecast'!$B43) -> 12.98522
B44: Software & Apps - Topkey | C44: =SUMIFS($P44:$AT44,$P$5:$AT$5,">"&C$199,$P$5:$AT$5,"<"&C$200) -> 0 | D44: =SUMIFS($P44:$AT44,$P$5:$AT$5,">"&D$199,$P$5:$AT$5,"<"&D$200) -> 7.14125 | F44: =SUMIFS($P44:$AT44,$P$5:$AT$5,">"&F$199,$P$5:$AT$5,"<"&F$200) -> 0 | G44: =SUMIFS($P44:$AT44,$P$5:$AT$5,">"&G$199,$P$5:$AT$5,"<"&G$200) -> 28.82775 | I44: =SUMIFS($P44:$AT44,$P$5:$AT$5,">"&I$199,$P$5:$AT$5,"<"&I$200) -> 0 | J44: =SUMIFS($P44:$AT44,$P$5:$AT$5,">"&J$199,$P$5:$AT$5,"<"&J$200) -> 35.969 | K44: =+C143 -> 60.84 | M44: =K44-J44 -> 24.871 | N44: =IFERROR(K44/J44-1,0) -> 0.69145653 | P44: =SUMIFS('Combined P&L'!N:N,'Combined P&L'!$C:$C,'P&L Forecast'!$B44) -> 0 | Q44: =SUMIFS('Combined P&L'!O:O,'Combined P&L'!$C:$C,'P&L Forecast'!$B44) -> 0 | R44: =SUMIFS('Combined P&L'!P:P,'Combined P&L'!$C:$C,'P&L Forecast'!$B44) -> 0 | S44: =SUMIFS('Combined P&L'!Q:Q,'Combined P&L'!$C:$C,'P&L Forecast'!$B44) -> 0 | T44: =SUMIFS('Combined P&L'!R:R,'Combined P&L'!$C:$C,'P&L Forecast'!$B44) -> 0 | U44: =SUMIFS('Combined P&L'!S:S,'Combined P&L'!$C:$C,'P&L Forecast'!$B44) -> 0 | V44: =SUMIFS('Combined P&L'!T:T,'Combined P&L'!$C:$C,'P&L Forecast'!$B44) -> 0 | W44: =SUMIFS('Combined P&L'!U:U,'Combined P&L'!$C:$C,'P&L Forecast'!$B44) -> 0 | X44: =SUMIFS('Combined P&L'!V:V,'Combined P&L'!$C:$C,'P&L Forecast'!$B44) -> 0 | Y44: =SUMIFS('Combined P&L'!W:W,'Combined P&L'!$C:$C,'P&L Forecast'!$B44) -> 0 | Z44: =SUMIFS('Combined P&L'!X:X,'Combined P&L'!$C:$C,'P&L Forecast'!$B44) -> 0 | AA44: =SUMIFS('Combined P&L'!Y:Y,'Combined P&L'!$C:$C,'P&L Forecast'!$B44) -> 0 | AB44: =SUMIFS('Combined P&L'!Z:Z,'Combined P&L'!$C:$C,'P&L Forecast'!$B44) -> 0 | AC44: =SUMIFS('Combined P&L'!AA:AA,'Combined P&L'!$C:$C,'P&L Forecast'!$B44) -> 0 | AD44: =SUMIFS('Combined P&L'!AB:AB,'Combined P&L'!$C:$C,'P&L Forecast'!$B44) -> 0 | AE44: =SUMIFS('Combined P&L'!AC:AC,'Combined P&L'!$C:$C,'P&L Forecast'!$B44) -> 0 | AF44: =SUMIFS('Combined P&L'!AD:AD,'Combined P&L'!$C:$C,'P&L Forecast'!$B44) -> 0 | AG44: =SUMIFS('Combined P&L'!AE:AE,'Combined P&L'!$C:$C,'P&L Forecast'!$B44) -> 0 | AH44: =SUMIFS('Combined P&L'!AF:AF,'Combined P&L'!$C:$C,'P&L Forecast'!$B44) -> 0 | AI44: =SUMIFS('Combined P&L'!AG:AG,'Combined P&L'!$C:$C,'P&L Forecast'!$B44) -> 0 | AJ44: =SUMIFS('Combined P&L'!AH:AH,'Combined P&L'!$C:$C,'P&L Forecast'!$B44) -> 0.93725 | AK44: =SUMIFS('Combined P&L'!AI:AI,'Combined P&L'!$C:$C,'P&L Forecast'!$B44) -> 1.39225 | AL44: =SUMIFS('Combined P&L'!AJ:AJ,'Combined P&L'!$C:$C,'P&L Forecast'!$B44) -> 2.36125 | AM44: =SUMIFS('Combined P&L'!AK:AK,'Combined P&L'!$C:$C,'P&L Forecast'!$B44) -> 2.4505 | AN44: =SUMIFS('Combined P&L'!AL:AL,'Combined P&L'!$C:$C,'P&L Forecast'!$B44) -> 2.94975 | AO44: =SUMIFS('Combined P&L'!AM:AM,'Combined P&L'!$C:$C,'P&L Forecast'!$B44) -> 3.42 | AP44: =SUMIFS('Combined P&L'!AN:AN,'Combined P&L'!$C:$C,'P&L Forecast'!$B44) -> 3.678 | AQ44: =SUMIFS('Combined P&L'!AO:AO,'Combined P&L'!$C:$C,'P&L Forecast'!$B44) -> 4.218 | AR44: =SUMIFS('Combined P&L'!AP:AP,'Combined P&L'!$C:$C,'P&L Forecast'!$B44) -> 4.284 | AS44: =SUMIFS('Combined P&L'!AQ:AQ,'Combined P&L'!$C:$C,'P&L Forecast'!$B44) -> 5.208 | AT44: =SUMIFS('Combined P&L'!AR:AR,'Combined P&L'!$C:$C,'P&L Forecast'!$B44) -> 5.07
B45: Software & Apps - AI tools | C45: =SUMIFS($P45:$AT45,$P$5:$AT$5,">"&C$199,$P$5:$AT$5,"<"&C$200) -> 0 | D45: =SUMIFS($P45:$AT45,$P$5:$AT$5,">"&D$199,$P$5:$AT$5,"<"&D$200) -> 0 | F45: =SUMIFS($P45:$AT45,$P$5:$AT$5,">"&F$199,$P$5:$AT$5,"<"&F$200) -> 0 | G45: =SUMIFS($P45:$AT45,$P$5:$AT$5,">"&G$199,$P$5:$AT$5,"<"&G$200) -> 6.52752 | I45: =SUMIFS($P45:$AT45,$P$5:$AT$5,">"&I$199,$P$5:$AT$5,"<"&I$200) -> 0 | J45: =SUMIFS($P45:$AT45,$P$5:$AT$5,">"&J$199,$P$5:$AT$5,"<"&J$200) -> 6.52752 | K45: =+C144 -> 15.74376 | M45: =K45-J45 -> 9.21624 | N45: =IFERROR(K45/J45-1,0) -> 1.4119053 | P45: =SUMIFS('Combined P&L'!N:N,'Combined P&L'!$C:$C,'P&L Forecast'!$B45) -> 0 | Q45: =SUMIFS('Combined P&L'!O:O,'Combined P&L'!$C:$C,'P&L Forecast'!$B45) -> 0 | R45: =SUMIFS('Combined P&L'!P:P,'Combined P&L'!$C:$C,'P&L Forecast'!$B45) -> 0 | S45: =SUMIFS('Combined P&L'!Q:Q,'Combined P&L'!$C:$C,'P&L Forecast'!$B45) -> 0 | T45: =SUMIFS('Combined P&L'!R:R,'Combined P&L'!$C:$C,'P&L Forecast'!$B45) -> 0 | U45: =SUMIFS('Combined P&L'!S:S,'Combined P&L'!$C:$C,'P&L Forecast'!$B45) -> 0 | V45: =SUMIFS('Combined P&L'!T:T,'Combined P&L'!$C:$C,'P&L Forecast'!$B45) -> 0 | W45: =SUMIFS('Combined P&L'!U:U,'Combined P&L'!$C:$C,'P&L Forecast'!$B45) -> 0 | X45: =SUMIFS('Combined P&L'!V:V,'Combined P&L'!$C:$C,'P&L Forecast'!$B45) -> 0 | Y45: =SUMIFS('Combined P&L'!W:W,'Combined P&L'!$C:$C,'P&L Forecast'!$B45) -> 0 | Z45: =SUMIFS('Combined P&L'!X:X,'Combined P&L'!$C:$C,'P&L Forecast'!$B45) -> 0 | AA45: =SUMIFS('Combined P&L'!Y:Y,'Combined P&L'!$C:$C,'P&L Forecast'!$B45) -> 0 | AB45: =SUMIFS('Combined P&L'!Z:Z,'Combined P&L'!$C:$C,'P&L Forecast'!$B45) -> 0 | AC45: =SUMIFS('Combined P&L'!AA:AA,'Combined P&L'!$C:$C,'P&L Forecast'!$B45) -> 0 | AD45: =SUMIFS('Combined P&L'!AB:AB,'Combined P&L'!$C:$C,'P&L Forecast'!$B45) -> 0 | AE45: =SUMIFS('Combined P&L'!AC:AC,'Combined P&L'!$C:$C,'P&L Forecast'!$B45) -> 0 | AF45: =SUMIFS('Combined P&L'!AD:AD,'Combined P&L'!$C:$C,'P&L Forecast'!$B45) -> 0 | AG45: =SUMIFS('Combined P&L'!AE:AE,'Combined P&L'!$C:$C,'P&L Forecast'!$B45) -> 0 | AH45: =SUMIFS('Combined P&L'!AF:AF,'Combined P&L'!$C:$C,'P&L Forecast'!$B45) -> 0 | AI45: =SUMIFS('Combined P&L'!AG:AG,'Combined P&L'!$C:$C,'P&L Forecast'!$B45) -> 0 | AJ45: =SUMIFS('Combined P&L'!AH:AH,'Combined P&L'!$C:$C,'P&L Forecast'!$B45) -> 0 | AK45: =SUMIFS('Combined P&L'!AI:AI,'Combined P&L'!$C:$C,'P&L Forecast'!$B45) -> 0 | AL45: =SUMIFS('Combined P&L'!AJ:AJ,'Combined P&L'!$C:$C,'P&L Forecast'!$B45) -> 0 | AM45: =SUMIFS('Combined P&L'!AK:AK,'Combined P&L'!$C:$C,'P&L Forecast'!$B45) -> 0 | AN45: =SUMIFS('Combined P&L'!AL:AL,'Combined P&L'!$C:$C,'P&L Forecast'!$B45) -> 0.12 | AO45: =SUMIFS('Combined P&L'!AM:AM,'Combined P&L'!$C:$C,'P&L Forecast'!$B45) -> 0.12 | AP45: =SUMIFS('Combined P&L'!AN:AN,'Combined P&L'!$C:$C,'P&L Forecast'!$B45) -> 0.70166 | AQ45: =SUMIFS('Combined P&L'!AO:AO,'Combined P&L'!$C:$C,'P&L Forecast'!$B45) -> 2.20736 | AR45: =SUMIFS('Combined P&L'!AP:AP,'Combined P&L'!$C:$C,'P&L Forecast'!$B45) -> 0.91487 | AS45: =SUMIFS('Combined P&L'!AQ:AQ,'Combined P&L'!$C:$C,'P&L Forecast'!$B45) -> 1.15165 | AT45: =SUMIFS('Combined P&L'!AR:AR,'Combined P&L'!$C:$C,'P&L Forecast'!$B45) -> 1.31198
B46: Total Software Expenses | C46: =SUM(C42:C45) -> 175.33863 | D46: =SUM(D42:D45) -> 281.69462 | F46: =SUM(F42:F45) -> 141.78009 | G46: =SUM(G42:G45) -> 284.68482 | I46: =SUM(I42:I45) -> 228.79834 | J46: =SUM(J42:J45) -> 424.59935 | K46: =SUM(K42:K45) -> 568.11456 | M46: =SUM(M42:M45) -> 143.51521 | N46: =IFERROR(K46/J46-1,0) -> 0.33800148 | P46: =SUM(P42:P45) -> 10.52585 | Q46: =SUM(Q42:Q45) -> 10.63571 | R46: =SUM(R42:R45) -> 11.75195 | S46: =SUM(S42:S45) -> 11.98489 | T46: =SUM(T42:T45) -> 12.81546 | U46: =SUM(U42:U45) -> 14.24615 | V46: =SUM(V42:V45) -> 16.36037 | W46: =SUM(W42:W45) -> 16.36683 | ... AT46: =SUM(AT42:AT45) -> 47.34288
B48: Other Professional Fees | C48: =SUMIFS($P48:$AT48,$P$5:$AT$5,">"&C$199,$P$5:$AT$5,"<"&C$200) -> 18.23425 | D48: =SUMIFS($P48:$AT48,$P$5:$AT$5,">"&D$199,$P$5:$AT$5,"<"&D$200) -> 27.04095 | F48: =SUMIFS($P48:$AT48,$P$5:$AT$5,">"&F$199,$P$5:$AT$5,"<"&F$200) -> 12.014 | G48: =SUMIFS($P48:$AT48,$P$5:$AT$5,">"&G$199,$P$5:$AT$5,"<"&G$200) -> 57.55 | I48: =SUMIFS($P48:$AT48,$P$5:$AT$5,">"&I$199,$P$5:$AT$5,"<"&I$200) -> 21.74858 | J48: =SUMIFS($P48:$AT48,$P$5:$AT$5,">"&J$199,$P$5:$AT$5,"<"&J$200) -> 72.57695 | K48: =+C148 -> 72.57695 | M48: =K48-J48 -> 0 | N48: =IFERROR(K48/J48-1,0) -> 0 | P48: =SUMIFS('Combined P&L'!N:N,'Combined P&L'!$C:$C,'P&L Forecast'!$B48) -> 0 | Q48: =SUMIFS('Combined P&L'!O:O,'Combined P&L'!$C:$C,'P&L Forecast'!$B48) -> 1.1665 | R48: =SUMIFS('Combined P&L'!P:P,'Combined P&L'!$C:$C,'P&L Forecast'!$B48) -> 1.1665 | S48: =SUMIFS('Combined P&L'!Q:Q,'Combined P&L'!$C:$C,'P&L Forecast'!$B48) -> 1.16667 | T48: =SUMIFS('Combined P&L'!R:R,'Combined P&L'!$C:$C,'P&L Forecast'!$B48) -> 1.16667 | U48: =SUMIFS('Combined P&L'!S:S,'Combined P&L'!$C:$C,'P&L Forecast'!$B48) -> 2.66666 | V48: =SUMIFS('Combined P&L'!T:T,'Combined P&L'!$C:$C,'P&L Forecast'!$B48) -> 1.16667 | W48: =SUMIFS('Combined P&L'!U:U,'Combined P&L'!$C:$C,'P&L Forecast'!$B48) -> 1.16667 | X48: =SUMIFS('Combined P&L'!V:V,'Combined P&L'!$C:$C,'P&L Forecast'!$B48) -> 3.06791 | Y48: =SUMIFS('Combined P&L'!W:W,'Combined P&L'!$C:$C,'P&L Forecast'!$B48) -> 1.16667 | Z48: =SUMIFS('Combined P&L'!X:X,'Combined P&L'!$C:$C,'P&L Forecast'!$B48) -> 2.16667 | AA48: =SUMIFS('Combined P&L'!Y:Y,'Combined P&L'!$C:$C,'P&L Forecast'!$B48) -> 2.16666 | AB48: =SUMIFS('Combined P&L'!Z:Z,'Combined P&L'!$C:$C,'P&L Forecast'!$B48) -> 2.16667 | AC48: =SUMIFS('Combined P&L'!AA:AA,'Combined P&L'!$C:$C,'P&L Forecast'!$B48) -> 2.16667 | AD48: =SUMIFS('Combined P&L'!AB:AB,'Combined P&L'!$C:$C,'P&L Forecast'!$B48) -> 2.16666 | AE48: =SUMIFS('Combined P&L'!AC:AC,'Combined P&L'!$C:$C,'P&L Forecast'!$B48) -> 2.76067 | AF48: =SUMIFS('Combined P&L'!AD:AD,'Combined P&L'!$C:$C,'P&L Forecast'!$B48) -> 1.58667 | AG48: =SUMIFS('Combined P&L'!AE:AE,'Combined P&L'!$C:$C,'P&L Forecast'!$B48) -> 1.16666 | AH48: =SUMIFS('Combined P&L'!AF:AF,'Combined P&L'!$C:$C,'P&L Forecast'!$B48) -> 0 | AI48: =SUMIFS('Combined P&L'!AG:AG,'Combined P&L'!$C:$C,'P&L Forecast'!$B48) -> 0.2 | AJ48: =SUMIFS('Combined P&L'!AH:AH,'Combined P&L'!$C:$C,'P&L Forecast'!$B48) -> 1.32695 | AK48: =SUMIFS('Combined P&L'!AI:AI,'Combined P&L'!$C:$C,'P&L Forecast'!$B48) -> 0 | AL48: =SUMIFS('Combined P&L'!AJ:AJ,'Combined P&L'!$C:$C,'P&L Forecast'!$B48) -> 6 | AM48: =SUMIFS('Combined P&L'!AK:AK,'Combined P&L'!$C:$C,'P&L Forecast'!$B48) -> 7.5 | AN48: =SUMIFS('Combined P&L'!AL:AL,'Combined P&L'!$C:$C,'P&L Forecast'!$B48) -> 0 | AO48: =SUMIFS('Combined P&L'!AM:AM,'Combined P&L'!$C:$C,'P&L Forecast'!$B48) -> 0 | AP48: =SUMIFS('Combined P&L'!AN:AN,'Combined P&L'!$C:$C,'P&L Forecast'!$B48) -> 6.6 | AQ48: =SUMIFS('Combined P&L'!AO:AO,'Combined P&L'!$C:$C,'P&L Forecast'!$B48) -> 14 | AR48: =SUMIFS('Combined P&L'!AP:AP,'Combined P&L'!$C:$C,'P&L Forecast'!$B48) -> 18 | AS48: =SUMIFS('Combined P&L'!AQ:AQ,'Combined P&L'!$C:$C,'P&L Forecast'!$B48) -> 0 | AT48: =SUMIFS('Combined P&L'!AR:AR,'Combined P&L'!$C:$C,'P&L Forecast'!$B48) -> 18.95
B49: Referral Fees | C49: =SUMIFS($P49:$AT49,$P$5:$AT$5,">"&C$199,$P$5:$AT$5,"<"&C$200) -> 24.82 | D49: =SUMIFS($P49:$AT49,$P$5:$AT$5,">"&D$199,$P$5:$AT$5,"<"&D$200) -> 27.15374 | F49: =SUMIFS($P49:$AT49,$P$5:$AT$5,">"&F$199,$P$5:$AT$5,"<"&F$200) -> 17.0895 | G49: =SUMIFS($P49:$AT49,$P$5:$AT$5,">"&G$199,$P$5:$AT$5,"<"&G$200) -> 20.62969 | I49: =SUMIFS($P49:$AT49,$P$5:$AT$5,">"&I$199,$P$5:$AT$5,"<"&I$200) -> 26.2095 | J49: =SUMIFS($P49:$AT49,$P$5:$AT$5,">"&J$199,$P$5:$AT$5,"<"&J$200) -> 30.69393 | K49: =+C149 -> 30.69393 | M49: =K49-J49 -> 0 | N49: =IFERROR(K49/J49-1,0) -> 0 | P49: =SUMIFS('Combined P&L'!N:N,'Combined P&L'!$C:$C,'P&L Forecast'!$B49) -> 2.21 | Q49: =SUMIFS('Combined P&L'!O:O,'Combined P&L'!$C:$C,'P&L Forecast'!$B49) -> 2.735 | R49: =SUMIFS('Combined P&L'!P:P,'Combined P&L'!$C:$C,'P&L Forecast'!$B49) -> 2.715 | S49: =SUMIFS('Combined P&L'!Q:Q,'Combined P&L'!$C:$C,'P&L Forecast'!$B49) -> 2.735 | T49: =SUMIFS('Combined P&L'!R:R,'Combined P&L'!$C:$C,'P&L Forecast'!$B49) -> 0.78 | U49: =SUMIFS('Combined P&L'!S:S,'Combined P&L'!$C:$C,'P&L Forecast'!$B49) -> 3.245 | V49: =SUMIFS('Combined P&L'!T:T,'Combined P&L'!$C:$C,'P&L Forecast'!$B49) -> 1.28 | W49: =SUMIFS('Combined P&L'!U:U,'Combined P&L'!$C:$C,'P&L Forecast'!$B49) -> 1.3 | X49: =SUMIFS('Combined P&L'!V:V,'Combined P&L'!$C:$C,'P&L Forecast'!$B49) -> 1.81 | Y49: =SUMIFS('Combined P&L'!W:W,'Combined P&L'!$C:$C,'P&L Forecast'!$B49) -> 1.82 | Z49: =SUMIFS('Combined P&L'!X:X,'Combined P&L'!$C:$C,'P&L Forecast'!$B49) -> 1.835 | AA49: =SUMIFS('Combined P&L'!Y:Y,'Combined P&L'!$C:$C,'P&L Forecast'!$B49) -> 2.355 | AB49: =SUMIFS('Combined P&L'!Z:Z,'Combined P&L'!$C:$C,'P&L Forecast'!$B49) -> 1.47025 | AC49: =SUMIFS('Combined P&L'!AA:AA,'Combined P&L'!$C:$C,'P&L Forecast'!$B49) -> 1.665 | AD49: =SUMIFS('Combined P&L'!AB:AB,'Combined P&L'!$C:$C,'P&L Forecast'!$B49) -> 2.62775 | AE49: =SUMIFS('Combined P&L'!AC:AC,'Combined P&L'!$C:$C,'P&L Forecast'!$B49) -> 1.24875 | AF49: =SUMIFS('Combined P&L'!AD:AD,'Combined P&L'!$C:$C,'P&L Forecast'!$B49) -> 2.154 | AG49: =SUMIFS('Combined P&L'!AE:AE,'Combined P&L'!$C:$C,'P&L Forecast'!$B49) -> 4.154 | AH49: =SUMIFS('Combined P&L'!AF:AF,'Combined P&L'!$C:$C,'P&L Forecast'!$B49) -> 3.76975 | AI49: =SUMIFS('Combined P&L'!AG:AG,'Combined P&L'!$C:$C,'P&L Forecast'!$B49) -> 1.696 | AJ49: =SUMIFS('Combined P&L'!AH:AH,'Combined P&L'!$C:$C,'P&L Forecast'!$B49) -> 2.2275 | AK49: =SUMIFS('Combined P&L'!AI:AI,'Combined P&L'!$C:$C,'P&L Forecast'!$B49) -> 1.6645 | AL49: =SUMIFS('Combined P&L'!AJ:AJ,'Combined P&L'!$C:$C,'P&L Forecast'!$B49) -> 1.71879 | AM49: =SUMIFS('Combined P&L'!AK:AK,'Combined P&L'!$C:$C,'P&L Forecast'!$B49) -> 2.75745 | AN49: =SUMIFS('Combined P&L'!AL:AL,'Combined P&L'!$C:$C,'P&L Forecast'!$B49) -> 1.8688 | AO49: =SUMIFS('Combined P&L'!AM:AM,'Combined P&L'!$C:$C,'P&L Forecast'!$B49) -> 4.43991 | AP49: =SUMIFS('Combined P&L'!AN:AN,'Combined P&L'!$C:$C,'P&L Forecast'!$B49) -> 2.39361 | AQ49: =SUMIFS('Combined P&L'!AO:AO,'Combined P&L'!$C:$C,'P&L Forecast'!$B49) -> 3.65786 | AR49: =SUMIFS('Combined P&L'!AP:AP,'Combined P&L'!$C:$C,'P&L Forecast'!$B49) -> 2.93379 | AS49: =SUMIFS('Combined P&L'!AQ:AQ,'Combined P&L'!$C:$C,'P&L Forecast'!$B49) -> 1.5662 | AT49: =SUMIFS('Combined P&L'!AR:AR,'Combined P&L'!$C:$C,'P&L Forecast'!$B49) -> 3.76952
