Workbook

Sheet Cover
B24: Keystone Bookkeepers
B25: Pre-LOI Business Analysis
B26: ="As of "&TEXT(TODAY(),"mm/dd/yy") -> As of 09/24/26

Sheet Offer Overview
B2: =Cover!$B$24 -> Keystone Bookkeepers
B3: Offer & Equity Upside Scenarios ($000s) | G3: Print | H3: 1
B5: Offer Breakdown | C5: Today
B6: Run-Rate Revenue (PF Jul'26) | C6: ='P&L Overview'!$K$16 -> 2998.541
B7: (x) Revenue Multiple — Implied | C7: =IFERROR($C$8/$C$6,0) -> 1.0004866
B8: Total Valuation — Offer Price | C8: 3000
B9: (-) Cash at Close | C9: 650
B10: Topkey Equity Consideration | C10: =C8-C9 -> 2350
B12: Topkey Pre-Deal Valuation | C12: ='Offer Comparison'!$C$9 -> 60000
B13: (+) Keystone Value Acquired | C13: =$C$8 -> 3000
B14: (-) Cash Paid at Close | C14: =$C$9 -> 650
B15: Topkey Post-Money Valuation | C15: =C12+C13-C14 -> 62350
B16: Ben's Implied Topkey Ownership % | C16: =IFERROR($C$10/$C$15,0) -> 0.037690457
B17: Keystone Enterprise Value Today | C17: =$C$8 -> 3000
B18: Existing Shareholders' Value Post-Close | C18: =(1-$C$16)*$C$15 -> 60000
B20: Topkey Pre-Deal Valuation | C20: =$C$12 -> 60000
B21: (-) Cash Paid at Close | C21: =$C$14 -> 650
B22: Topkey ex-Keystone Growth Base | C22: =C20-C21 -> 59350
B24: Scenario 1 — Ben Retains 100% of Keystone | C24: Today | D24: 2.0x Valuation | E24: 3.0x Valuation
B25: Keystone Growth Multiple | C25: 1 | D25: 2 | E25: 3
B26: Keystone Enterprise Value | C26: =$C$17*C$25 -> 3000 | D26: =$C$17*D$25 -> 6000 | E26: =$C$17*E$25 -> 9000
B27: Ben's Ownership % — Keystone | C27: 1 | D27: =$C$27 -> 1 | E27: =$C$27 -> 1
B28: Ben's Keystone Equity Value | C28: =C26*$C$27 -> 3000 | D28: =D26*$C$27 -> 6000 | E28: =E26*$C$27 -> 9000
B29: (-) Value at Offer Today | C29: =$C$28 -> 3000 | D29: =$C$28 -> 3000 | E29: =$C$28 -> 3000
B30: Ben's Net Gain vs. Today | C30: =C28-C29 -> 0 | D30: =D28-D29 -> 3000 | E30: =E28-E29 -> 6000
B32: Combined Topkey + Keystone TEV | C32: Growth (ex-Keystone) | D32: =D$24 -> 2.0x Valuation | E32: =E$24 -> 3.0x Valuation
B33: Topkey Grows Half as Fast as Keystone | C33: 0.5 | D33: =$C$22*(1+(D$25-1)*$C33)+$C$17*D$25 -> 95025 | E33: =$C$22*(1+(E$25-1)*$C33)+$C$17*E$25 -> 127700
B34: Topkey Keeps Pace with Keystone | C34: 1 | D34: =$C$22*(1+(D$25-1)*$C34)+$C$17*D$25 -> 124700 | E34: =$C$22*(1+(E$25-1)*$C34)+$C$17*E$25 -> 187050
B35: Topkey Outgrows Keystone | C35: 1.5 | D35: =$C$22*(1+(D$25-1)*$C35)+$C$17*D$25 -> 154375 | E35: =$C$22*(1+(E$25-1)*$C35)+$C$17*E$25 -> 246400
B37: Ben's Total Value — Cash + Topkey Equity | D37: =+D$32 -> 2.0x Valuation | E37: =+E$32 -> 3.0x Valuation
B38: =$B33 -> Topkey Grows Half as Fast as Keystone | D38: =$C$9+$C$16*D33 -> 4231.5357 | E38: =$C$9+$C$16*E33 -> 5463.0714
B39: =$B34 -> Topkey Keeps Pace with Keystone | D39: =$C$9+$C$16*D34 -> 5350 | E39: =$C$9+$C$16*E34 -> 7700
B40: =$B35 -> Topkey Outgrows Keystone | D40: =$C$9+$C$16*D35 -> 6468.4643 | E40: =$C$9+$C$16*E35 -> 9936.9286
B42: Delta vs. Scenario 1 | D42: =+D$32 -> 2.0x Valuation | E42: =+E$32 -> 3.0x Valuation
B43: =$B33 -> Topkey Grows Half as Fast as Keystone | D43: =D38-D$28 -> -1768.4643 | E43: =E38-E$28 -> -3536.9286
B44: =$B34 -> Topkey Keeps Pace with Keystone | D44: =D39-D$28 -> -650 | E44: =E39-E$28 -> -1300
B45: =$B35 -> Topkey Outgrows Keystone | D45: =D40-D$28 -> 468.46431 | E45: =E40-E$28 -> 936.92863
B47: Topkey Growth Required for Parity | D47: =+D$32 -> 2.0x Valuation | E47: =+E$32 -> 3.0x Valuation
B48: Ben's Value — Scenario 1 (Retain 100%) | D48: =D$28 -> 6000 | E48: =E$28 -> 9000
B49: (-) Ben's Cash at Close | D49: =$C$9 -> 650 | E49: =$C$9 -> 650
B50: Required Topkey Equity Value | D50: =D48-D49 -> 5350 | E50: =E48-E49 -> 8350
B51: Required Combined Enterprise Value | D51: =IFERROR(D50/$C$16,0) -> 141945.74 | E51: =IFERROR(E50/$C$16,0) -> 221541.49
B52: (-) Keystone Value at Growth | D52: =$C$17*D$25 -> 6000 | E52: =$C$17*E$25 -> 9000
B53: Required Topkey ex-Keystone Value | D53: =D51-D52 -> 135945.74 | E53: =E51-E52 -> 212541.49
B54: Required Growth Share for Ben to Break Even | D54: =IFERROR((D53/$C$22-1)/(D$25-1),0) -> 1.290577 | E54: =IFERROR((E53/$C$22-1)/(E$25-1),0) -> 1.290577
B56: Offer & Scenario Assumptions
B57: Assumption | C57: Value | D57: Rationale
B58: Run-Rate Revenue (PF Jul'26) ($000s) | C58: =$C$6 -> 2998.541 | D58: Unrounded PF Jul'26 run-rate revenue (P&L Overview K16); same basis as the Buyout and Partnership tabs
B59: Revenue Multiple | C59: =$C$7 -> 1.0004866 | D59: Implied by rounded offer ÷ PF Jul'26 run-rate revenue
B60: Total Valuation — Offer Price ($000s) | C60: =$C$8 -> 3000 | D60: Rounded $3.0M offer price; Keystone value today
B61: Cash at Close ($000s) | C61: =$C$9 -> 650 | D61: Per Topkey offer; balance paid in Topkey equity
B62: Topkey Pre-Deal Valuation ($000s) | C62: =$C$12 -> 60000 | D62: Topkey stated valuation before Keystone; pending confirmation
B63: Ben's Keystone Ownership % | C63: =$C$27 -> 1 | D63: Sole owner; retains full upside in Scenario 1
B64: Topkey ex-Keystone Growth Share — Half Pace | C64: =$C$33 -> 0.5 | D64: Topkey ex-Keystone grows at half Keystone's rate
B65: Topkey ex-Keystone Growth Share — Keeps Pace | C65: =$C$34 -> 1 | D65: Topkey ex-Keystone grows at Keystone's rate
B66: Topkey ex-Keystone Growth Share — Outgrows | C66: =$C$35 -> 1.5 | D66: Default 1.5x Keystone's growth rate
B67: Valuation Growth Multiples | C67: =D$25&"x / "&E$25&"x" -> 2x / 3x | D67: Business doubles / triples in value
B68: Topkey ex-Keystone Growth Base ($000s) | C68: =$C$22 -> 59350 | D68: Pre-deal Topkey less the $650K cash paid to Ben at close
B69: Topkey Post-Money Valuation ($000s) | C69: =$C$15 -> 62350 | D69: Pre-deal + Keystone acquired − cash paid at close

Sheet Offer Comparison
B2: =Cover!$B$24 -> Keystone Bookkeepers
B3: Offer Comparison — Partnership vs. 100% Buyout ($000s) | H3: Print | I3: 0
B5: Offer Comparison | C5: Partnership | D5: 100% Buyout | E5: Variance | G5: Notes
B6: Deal Assumptions
B7: Horizon (Years) | C7: 5 | D7: =C7 -> 5 | E7: =C7-D7 -> 0 | G7: Input — drives Partnership and Buyout tabs (D = C)
B8: Est. Topkey Dilution — Ben's Stake (Year 5) | C8: 0.05 | D8: =C8 -> 0.05 | E8: =C8-D8 -> 0 | G8: Input — drives Partnership and Buyout tabs (D = C)
B9: Topkey Valuation Today — Pre-Deal | C9: 60000 | D9: =C9 -> 60000 | E9: =C9-D9 -> 0 | G9: Input — single Topkey valuation; drives Offer Overview, Partnership and Buyout tabs
B10: Topkey 5-Year Valuation Growth (ex-Keystone) | C10: ='Partnership Analysis'!$C$19 -> 2.021904 | D10: ='100% Buyout Analysis'!$C$18 -> 2.0084034 | E10: =C10-D10 -> 0.013500598 | G10: Differs because the ex-Keystone base is net of each offer's cash at close
B11: Keystone 5-Yr Revenue Increase — Standalone (% of Start) | C11: =IFERROR('Partnership Analysis'!$C$28/'Partnership Analysis'!$C$47,0) -> 0.99837392 | D11: =IFERROR('100% Buyout Analysis'!$C$27/'100% Buyout Analysis'!$C$46,0) -> 0.99837392 | E11: =C11-D11 -> 0 | G11: Total additional revenue ÷ Keystone revenue at close ($2,999)
B12: Keystone 5-Yr Revenue Increase — Partnership (% of Start) | C12: =IFERROR('Partnership Analysis'!$C$42/'Partnership Analysis'!$C$47,0) -> 1.3311652 | D12: =IFERROR('100% Buyout Analysis'!$C$41/'100% Buyout Analysis'!$C$46,0) -> 1.3311652 | E12: =C12-D12 -> 0 | G12: Total additional revenue ÷ Keystone revenue at close ($2,999)
B13: Keystone Initial Revenue Multiple | C13: 1 | D13: =C13 -> 1 | E13: =C13-D13 -> 0 | G13: Input — drives Partnership and Buyout tabs (D = C)
B14: Keystone Scaled Revenue Multiple | C14: 1.25 | D14: =C14 -> 1.25 | E14: =C14-D14 -> 0 | G14: Input — drives Partnership and Buyout tabs (D = C)
B15: Keystone Software-Integration Revenue Multiple | C15: 2 | D15: =C15 -> 2 | E15: =C15-D15 -> 0 | G15: Input — drives Partnership and Buyout tabs (D = C)
B17: Offer Structure
B18: Keystone Value Today (100%) | C18: ='Partnership Analysis'!$C$185 -> 3000 | D18: ='100% Buyout Analysis'!$C$173 -> 3000 | E18: =C18-D18 -> 0
B19: Ben's Rollover % — Keystone | C19: ='Partnership Analysis'!$C$186 -> 0.3 | D19: =1-'100% Buyout Analysis'!$C$96 -> 0 | E19: =C19-D19 -> 0.3 | G19: Buyout: 1 − Topkey stake acquired
B20: Keystone Stake Acquired by Topkey | C20: ='Partnership Analysis'!$C$187 -> 0.7 | D20: ='100% Buyout Analysis'!$C$96 -> 1 | E20: =C20-D20 -> -0.3
B21: Price for Topkey's Stake | C21: ='Partnership Analysis'!$C$188 -> 2100 | D21: ='100% Buyout Analysis'!$C$173 -> 3000 | E21: =C21-D21 -> -900
B22: (-) Cash at Close | C22: ='Partnership Analysis'!$C$189 -> 650 | D22: ='100% Buyout Analysis'!$C$174 -> 500 | E22: =C22-D22 -> 150
B23: Topkey Equity Issued to Ben | C23: ='Partnership Analysis'!$C$190 -> 1450 | D23: ='100% Buyout Analysis'!$C$175 -> 2500 | E23: =C23-D23 -> -1050
B24: (+) Target Cash Earnout (at 100% Achievement) — Year 3 | C24: ='Partnership Analysis'!$C$58 -> 0 | D24: ='100% Buyout Analysis'!$C$57 -> 500 | E24: =C24-D24 -> -500 | G24: Buyout: target $500K; capped at $750K. Partnership: no earnout
B25: (+) Cash at Close | C25: =C22 -> 650 | D25: =D22 -> 500 | E25: =C25-D25 -> 150 | G25: Note the $650K covers Ben's tax situation
B26: Total Consideration Paid by Topkey | C26: ='Partnership Analysis'!$C$106 -> 2100 | D26: ='100% Buyout Analysis'!$C$95 -> 3500 | E26: =C26-D26 -> -1400 | G26: Cash at close + equity issued + target earnout (at 100% achievement)
B27: % of Consideration in Cash (incl. Earnout) | C27: =IFERROR((C22+C24)/C26,0) -> 0.30952381 | D27: =IFERROR((D22+D24)/D26,0) -> 0.28571429 | E27: =C27-D27 -> 0.023809524
B29: Where Ben's Year 5 Value Comes From
B31: Retained Keystone Stake (Direct) | C31: =IFERROR(C94/C$99,0) -> 0.46170498 | D31: =IFERROR(D94/D$99,0) -> 0 | E31: =C31-D31 -> 0.46170498
B32: Keystone via Topkey | C32: =IFERROR(C95/C$99,0) -> 0.024149662 | D32: =IFERROR(D95/D$99,0) -> 0.063750321 | E32: =C32-D32 -> -0.039600659
B33: Topkey ex-Keystone | C33: =IFERROR(C96/C$99,0) -> 0.44258976 | D33: =IFERROR(D96/D$99,0) -> 0.81624844 | E33: =C33-D33 -> -0.37365868
B34: Cash at Close | C34: =IFERROR(C97/C$99,0) -> 0.071555598 | D34: =IFERROR(D97/D$99,0) -> 0.06000062 | E34: =C34-D34 -> 0.011554978
B35: Cash Earnout — Year 3 | C35: =IFERROR(C98/C$99,0) -> 0 | D35: =IFERROR(D98/D$99,0) -> 0.06000062 | E35: =C35-D35 -> -0.06000062
B37: Return Profile — Jon (Topkey) | K37: Helper: Year | L37: 0 | M37: 1 | N37: 2 | O37: 3 | P37: 4 | Q37: 5
B38: Cash at Close (Year 0) | C38: =C22 -> 650 | D38: =D22 -> 500 | E38: =C38-D38 -> 150 | K38: Helper: Partnership CF | L38: =-(L$37=0)*($C$22+$C$23)-(L$37=$L$40)*$C$24+(L$37=$C$7)*$C$42 -> -2100 | M38: =-(M$37=0)*($C$22+$C$23)-(M$37=$L$40)*$C$24+(M$37=$C$7)*$C$42 -> 0 | N38: =-(N$37=0)*($C$22+$C$23)-(N$37=$L$40)*$C$24+(N$37=$C$7)*$C$42 -> 0 | O38: =-(O$37=0)*($C$22+$C$23)-(O$37=$L$40)*$C$24+(O$37=$C$7)*$C$42 -> 0 | P38: =-(P$37=0)*($C$22+$C$23)-(P$37=$L$40)*$C$24+(P$37=$C$7)*$C$42 -> 0 | Q38: =-(Q$37=0)*($C$22+$C$23)-(Q$37=$L$40)*$C$24+(Q$37=$C$7)*$C$42 -> 9786.1324
B39: (+) Equity Issued to Ben (Year 0) | C39: =C23 -> 1450 | D39: =D23 -> 2500 | E39: =C39-D39 -> -1050 | K39: Helper: Buyout CF | L39: =-(L$37=0)*($D$22+$D$23)-(L$37=$L$40)*$D$24+(L$37=$D$7)*$D$42 -> -3000 | M39: =-(M$37=0)*($D$22+$D$23)-(M$37=$L$40)*$D$24+(M$37=$D$7)*$D$42 -> 0 | N39: =-(N$37=0)*($D$22+$D$23)-(N$37=$L$40)*$D$24+(N$37=$D$7)*$D$42 -> 0 | O39: =-(O$37=0)*($D$22+$D$23)-(O$37=$L$40)*$D$24+(O$37=$D$7)*$D$42 -> -500 | P39: =-(P$37=0)*($D$22+$D$23)-(P$37=$L$40)*$D$24+(P$37=$D$7)*$D$42 -> 0 | Q39: =-(Q$37=0)*($D$22+$D$23)-(Q$37=$L$40)*$D$24+(Q$37=$D$7)*$D$42 -> 13980.189
B40: (+) Target Cash Earnout (at 100% Achievement) (Year 3) | C40: =C24 -> 0 | D40: =D24 -> 500 | E40: =C40-D40 -> -500 | K40: Helper: Earnout Year | L40: ='100% Buyout Analysis'!$C$45 -> 3 | M40: Year the target earnout is paid — linked to 100% Buyout Analysis (Earnout Measurement Year)
B41: Total Invested by Jon (Topkey) | C41: =SUM(C38:C40) -> 2100 | D41: =SUM(D38:D40) -> 3500 | E41: =C41-D41 -> -1400 | G41: Ties to Total Consideration (row 26)
B42: Topkey's Keystone Stake — Year 5 Value | C42: ='Partnership Analysis'!$D$82 -> 9786.1324 | D42: ='100% Buyout Analysis'!$D$76 -> 13980.189 | E42: =C42-D42 -> -4194.0567 | G42: 70% (Partnership) or 100% (Buyout) of Keystone's Year 5 value
B43: Deal MOIC | C43: =IFERROR(C42/C41,0) -> 4.660063 | D43: =IFERROR(D42/D41,0) -> 3.9943397 | E43: =C43-D43 -> 0.66572329 | G43: Standard acquirer view: stake value ÷ consideration at issue price
B44: Deal IRR | C44: =IFERROR(IRR($L38:$Q38),0) -> 0.36043676 | D44: =IFERROR(IRR($L39:$Q39),0) -> 0.34242961 | E44: =C44-D44 -> 0.018007148 | G44: Cash-flow IRR; see helper cash flows in L38:Q39
B45: (-) Hurdle MOIC — Break-Even | C45: =IFERROR(C119/(C38+C39),0) -> 2.3809524 | D45: =IFERROR(D119/(D38+D39),0) -> 2.6666667 | E45: =C45-D45 -> -0.28571429 | G45: Break-even stake value (row 119) ÷ cash + stock; no earnout paid at break-even
B46: (-) Hurdle IRR — Break-Even | C46: =IFERROR(C45^(1/C$7)-1,0) -> 0.18946082 | D46: =IFERROR(D45^(1/D$7)-1,0) -> 0.21672868 | E46: =C46-D46 -> -0.027267862 | G46: Blended cost of Jon's currency: cash at 1.0x, stock at Topkey's 5-year growth
B47: Excess MOIC over Hurdle | C47: =C43-C45 -> 2.2791106 | D47: =D43-D45 -> 1.3276731 | E47: =C47-D47 -> 0.95143758 | G47: Deal return after backing out the cost of paying in Topkey stock
B48: Excess IRR over Hurdle (% pts) | C48: =C44-C46 -> 0.17097594 | D48: =D44-D46 -> 0.12570093 | E48: =C48-D48 -> 0.04527501 | G48: Deal IRR less hurdle IRR
B49: Jon's Year 5 Value — With Deal | C49: =C$138*('Partnership Analysis'!$D$81+'Partnership Analysis'!$D$82) -> 175439.54 | D49: =D$138*('100% Buyout Analysis'!$D$75+'100% Buyout Analysis'!$D$76) -> 175997.93 | E49: =C49-D49 -> -558.39551 | G49: Jon's diluted % × (Topkey ex-Keystone + Keystone stake)
B50: (-) Jon's Year 5 Value — Without Deal | C50: =(1-C$8)*('Partnership Analysis'!$D$81+C22+C24) -> 171000 | D50: =(1-D$8)*('100% Buyout Analysis'!$D$75+D22+D24) -> 171000 | E50: =C50-D50 -> 0 | G50: Topkey keeps its cash and pays no earnout; Jon diluted by the same est. %
B51: Net Value Created for Jon | C51: =C49-C50 -> 4439.5369 | D51: =D49-D50 -> 4997.9324 | E51: =C51-D51 -> -558.39551 | G51: Includes the cost of stock sharing Topkey's growth with Ben
B52: All-In MOIC | C52: =IFERROR((C41+C51)/C41,0) -> 3.1140652 | D52: =IFERROR((D41+D51)/D41,0) -> 2.4279807 | E52: =C52-D52 -> 0.68608451 | G52: (Invested + net value created) ÷ invested
B53: All-In IRR | C53: =IFERROR(C52^(1/C$7)-1,0) -> 0.25506304 | D53: =IFERROR(D52^(1/D$7)-1,0) -> 0.19412295 | E53: =C53-D53 -> 0.060940088 | G53: MOIC^(1 / horizon) − 1
B55: Partnership Upside Analysis
C56: First 70% (Partnership) | D56: 100% (Buyout) | E56: Extra 30% | G56: Column E = incremental cost and return of buying the last 30% (Buyout less Partnership)
B57: Keystone Stake Acquired by Topkey | C57: =C20 -> 0.7 | D57: =D20 -> 1 | E57: =D57-C57 -> 0.3
B58: Total Invested by Jon (Topkey) | C58: =C41 -> 2100 | D58: =D41 -> 3500 | E58: =D58-C58 -> 1400 | G58: Incremental cost of the last 30%
B59: Cost per 1% of Keystone | C59: =IFERROR(C58/(C57*100),0) -> 30 | D59: =IFERROR(D58/(D57*100),0) -> 35 | E59: =IFERROR(E58/(E57*100),0) -> 46.666667 | G59: Price per point rises on the extra 30% (earnout added)
B60: Paid in Topkey Stock (% of Invested) | C60: =IFERROR(C39/C58,0) -> 0.69047619 | D60: =IFERROR(D39/D58,0) -> 0.71428571 | E60: =IFERROR((D39-C39)/E58,0) -> 0.75 | G60: Stock is Jon's most expensive currency (shares Topkey's growth)
B61: Keystone Stake Value — Year 5 | C61: =C42 -> 9786.1324 | D61: =D42 -> 13980.189 | E61: =D61-C61 -> 4194.0567
B62: Deal MOIC | C62: =IFERROR(C61/C58,0) -> 4.660063 | D62: =IFERROR(D61/D58,0) -> 3.9943397 | E62: =IFERROR(E61/E58,0) -> 2.9957548 | G62: Stake value ÷ consideration at issue price
B63: Hurdle MOIC — Break-Even | C63: =C45 -> 2.3809524 | D63: =D45 -> 2.6666667 | E63: n/m | G63: From Jon's return profile (row 45); n/m for the extra 30% (break-even excludes earnout, so hurdles aren't additive)
B64: Net Value Created for Jon | C64: =C51 -> 4439.5369 | D64: =D51 -> 4997.9324 | E64: =D64-C64 -> 558.39551 | G64: Incremental value to Jon from the last 30%
B65: All-In MOIC | C65: =IFERROR((C58+C64)/C58,0) -> 3.1140652 | D65: =IFERROR((D58+D64)/D58,0) -> 2.4279807 | E65: =IFERROR((E58+E64)/E58,0) -> 1.3988539 | G65: (Invested + net value created) ÷ invested
B66: All-In IRR | C66: =IFERROR(C65^(1/C$7)-1,0) -> 0.25506304 | D66: =IFERROR(D65^(1/D$7)-1,0) -> 0.19412295 | E66: =IFERROR(E65^(1/D$7)-1,0) -> 0.069435198 | G66: MOIC^(1 / horizon) − 1
B68: Return Profile — Ben | K68: Helper: Year | L68: 0 | M68: 1 | N68: 2 | O68: 3 | P68: 4 | Q68: 5
B69: Keystone Value Contributed by Ben (Year 0) | C69: =C18 -> 3000 | D69: =D18 -> 3000 | E69: =C69-D69 -> 0 | G69: Ben gives up 100% of Keystone at today's value in both offers | K69: Helper: Partnership CF | L69: =-(L$68=0)*($C$69-$C$70)+(L$68=$L$40)*$C$71+(L$68=$C$7)*($C$72+$C$73) -> -2350 | M69: =-(M$68=0)*($C$69-$C$70)+(M$68=$L$40)*$C$71+(M$68=$C$7)*($C$72+$C$73) -> 0 | N69: =-(N$68=0)*($C$69-$C$70)+(N$68=$L$40)*$C$71+(N$68=$C$7)*($C$72+$C$73) -> 0 | O69: =-(O$68=0)*($C$69-$C$70)+(O$68=$L$40)*$C$71+(O$68=$C$7)*($C$72+$C$73) -> 0 | P69: =-(P$68=0)*($C$69-$C$70)+(P$68=$L$40)*$C$71+(P$68=$C$7)*($C$72+$C$73) -> 0 | Q69: =-(Q$68=0)*($C$69-$C$70)+(Q$68=$L$40)*$C$71+(Q$68=$C$7)*($C$72+$C$73) -> 8433.8455
B70: Cash at Close (Year 0) | C70: =C97 -> 650 | D70: =D97 -> 500 | E70: =C70-D70 -> 150 | K70: Helper: Buyout CF | L70: =-(L$68=0)*($D$69-$D$70)+(L$68=$L$40)*$D$71+(L$68=$D$7)*($D$72+$D$73) -> -2500 | M70: =-(M$68=0)*($D$69-$D$70)+(M$68=$L$40)*$D$71+(M$68=$D$7)*($D$72+$D$73) -> 0 | N70: =-(N$68=0)*($D$69-$D$70)+(N$68=$L$40)*$D$71+(N$68=$D$7)*($D$72+$D$73) -> 0 | O70: =-(O$68=0)*($D$69-$D$70)+(O$68=$L$40)*$D$71+(O$68=$D$7)*($D$72+$D$73) -> 500 | P70: =-(P$68=0)*($D$69-$D$70)+(P$68=$L$40)*$D$71+(P$68=$D$7)*($D$72+$D$73) -> 0 | Q70: =-(Q$68=0)*($D$69-$D$70)+(Q$68=$L$40)*$D$71+(Q$68=$D$7)*($D$72+$D$73) -> 7333.2472
B71: (+) Target Cash Earnout (at 100% Achievement) (Year 3) | C71: =C98 -> 0 | D71: =D98 -> 500 | E71: =C71-D71 -> -500
B72: (+) Retained Keystone Stake — Year 5 | C72: =C94 -> 4194.0567 | D72: =D94 -> 0 | E72: =C72-D72 -> 4194.0567 | G72: Partnership: Ben's 30%; Buyout: none
B73: (+) Topkey Equity — Year 5 | C73: =C95+C96 -> 4239.7888 | D73: =D95+D96 -> 7333.2472 | E73: =C73-D73 -> -3093.4584 | G73: Diluted Topkey stake, incl. Ben's indirect share of Keystone
B74: Total Value Received by Ben | C74: =SUM(C70:C73) -> 9083.8455 | D74: =SUM(D70:D73) -> 8333.2472 | E74: =C74-D74 -> 750.59835 | G74: Ties to Ben's Value — Offer (row 81); tie-out in row 91
B75: Total MOIC | C75: =IFERROR(C74/C69,0) -> 3.0279485 | D75: =IFERROR(D74/D69,0) -> 2.7777491 | E75: =C75-D75 -> 0.25019945 | G75: Total value received ÷ Keystone value contributed
B76: Total IRR | C76: =IFERROR(IRR($L69:$Q69),0) -> 0.29119417 | D76: =IFERROR(IRR($L70:$Q70),0) -> 0.266139 | E76: =C76-D76 -> 0.025055167 | G76: Cash-flow IRR; see helper cash flows in L69:Q70
B77: (-) Ben's Year 5 Value — Standalone | C77: =C82 -> 7490.2577 | D77: =D82 -> 7490.2577 | E77: =C77-D77 -> 0 | G77: Ben keeps 100% of Keystone
B78: Net Value Created for Ben | C78: =C74-C77 -> 1593.5878 | D78: =D74-D77 -> 842.98949 | E78: =C78-D78 -> 750.59835 | G78: Offer vs. keeping 100% of Keystone
B80: Ben — Offer vs. Standalone (Year 5)
B81: Ben's Value — Offer | C81: ='Partnership Analysis'!$D$92 -> 9083.8455 | D81: ='100% Buyout Analysis'!$D$81 -> 8333.2472 | E81: =C81-D81 -> 750.59835
B82: (-) Ben's Value — Standalone | C82: ='Partnership Analysis'!$D$74 -> 7490.2577 | D82: ='100% Buyout Analysis'!$D$72 -> 7490.2577 | E82: =C82-D82 -> 0
B83: Offer Less Standalone ($) | C83: =C81-C82 -> 1593.5878 | D83: =D81-D82 -> 842.98949 | E83: =C83-D83 -> 750.59835
B84: Offer Less Standalone (%) | C84: =IFERROR(C81/C82-1,0) -> 0.21275474 | D84: =IFERROR(D81/D82-1,0) -> 0.11254479
B85: MOIC — Offer | C85: ='Partnership Analysis'!$D$97 -> 3.0279485 | D85: ='100% Buyout Analysis'!$D$86 -> 2.7777491 | E85: =C85-D85 -> 0.25019945
B86: (-) MOIC — Standalone | C86: =IFERROR('Partnership Analysis'!$D$74/'Partnership Analysis'!$C$74,0) -> 2.4967526 | D86: =IFERROR('100% Buyout Analysis'!$D$72/'100% Buyout Analysis'!$C$72,0) -> 2.4967526 | E86: =C86-D86 -> 0 | G86: Keystone Year 5 value ÷ value today
B87: MOIC Delta — Offer vs. Standalone | C87: =C85-C86 -> 0.53119594 | D87: =D85-D86 -> 0.2809965 | E87: =C87-D87 -> 0.25019945
B88: IRR — Offer | C88: ='Partnership Analysis'!$D$98 -> 0.29119417 | D88: ='100% Buyout Analysis'!$D$87 -> 0.266139 | E88: =C88-D88 -> 0.025055167 | G88: From each tab's cash-flow IRR (includes cash timing)
B89: (-) IRR — Standalone | C89: =IFERROR(C86^(1/C$7)-1,0) -> 0.20081223 | D89: =IFERROR(D86^(1/D$7)-1,0) -> 0.20081223 | E89: =C89-D89 -> 0
B90: IRR Delta — Offer vs. Standalone | C90: =C88-C89 -> 0.090381943 | D90: =D88-D89 -> 0.065326775 | E90: =C90-D90 -> 0.025055167
B91: Tie Out — Ben's Value by Source vs. Offer | C91: =C74-C81 -> 0 | D91: =D74-D81 -> 0 | G91: Must equal zero
B93: Where Ben's Year 5 Value Comes From
B94: Retained Keystone Stake (Direct) | C94: ='Partnership Analysis'!$D$87 -> 4194.0567 | D94: 0 | E94: =C94-D94 -> 4194.0567 | G94: Buyout: no retained stake
B95: (+) Keystone via Topkey | C95: ='Partnership Analysis'!$D$88 -> 219.3718 | D95: ='100% Buyout Analysis'!$C$118 -> 531.24718 | E95: =C95-D95 -> -311.87538
B96: (+) Topkey ex-Keystone | C96: ='Partnership Analysis'!$D$89 -> 4020.417 | D96: ='100% Buyout Analysis'!$C$117 -> 6802 | E96: =C96-D96 -> -2781.583
B97: (+) Cash at Close | C97: ='Partnership Analysis'!$D$90 -> 650 | D97: ='100% Buyout Analysis'!$C$119 -> 500 | E97: =C97-D97 -> 150
B98: (+) Cash Earnout — Year 3 | C98: ='Partnership Analysis'!$D$91 -> 0 | D98: ='100% Buyout Analysis'!$C$120 -> 500 | E98: =C98-D98 -> -500
B99: Ben's Value — Offer (Year 5) | C99: =SUM(C94:C98) -> 9083.8455 | D99: =SUM(D94:D98) -> 8333.2472 | E99: =C99-D99 -> 750.59835
B100: Tie Out — Value by Source vs. Offer | C100: =C99-C81 -> 0 | D100: =D99-D81 -> 0 | G100: Must equal zero
B102: Ben's Break-Even — Downside Threshold
B103: Partnership Revenue Multiple | C103: ='Partnership Analysis'!$C$136 -> 1.2778459 | D103: n/m | E103: =IF(ISNUMBER(D103),C103-D103,"n/m") -> n/m | G103: n/m: Ben keeps no direct Keystone stake in the buyout
B104: Required Topkey ex-Keystone Value — Year 5 | C104: ='Partnership Analysis'!$C$137 -> 108260.36 | D104: ='100% Buyout Analysis'!$C$133 -> 156816.07 | E104: =C104-D104 -> -48555.701
B105: Topkey Future Revenue Multiple | C105: ='Partnership Analysis'!$C$138 -> 11.591141 | D105: ='100% Buyout Analysis'!$C$134 -> 16.79609 | E105: =C105-D105 -> -5.204949
B106: Topkey Annual Net Client Wins | C106: ='Partnership Analysis'!$C$139 -> 52.986229 | D106: ='100% Buyout Analysis'!$C$135 -> 105.9674 | E106: =C106-D106 -> -52.981176
B107: Total Dilution of Ben's Topkey Stake | C107: ='Partnership Analysis'!$C$141 -> 0.40707166 | D107: ='100% Buyout Analysis'!$C$136 -> 0.15920674 | E107: =C107-D107 -> 0.24786492
B108: Topkey Revenue CAGR | C108: ='Partnership Analysis'!$C$140 -> 0.12774199 | D108: ='100% Buyout Analysis'!$C$137 -> 0.21465019 | E108: =C108-D108 -> -0.086908196
B110: Ben's Break-Even Cushion — Base Case vs. Break-Even
B111: Partnership Revenue Multiple — Cushion (x) | C111: ='Partnership Analysis'!$D$136-C103 -> 0.72215414 | D111: n/m | E111: =IF(ISNUMBER(D111),C111-D111,"n/m") -> n/m | G111: Base integration multiple (row 15) less break-even; n/m for Buyout (no retained stake)
B112: Topkey ex-Keystone Value (Year 5) — Cushion ($) | C112: ='Partnership Analysis'!$D$137-C104 -> 71089.635 | D112: ='100% Buyout Analysis'!$D$133-D104 -> 22183.934 | E112: =C112-D112 -> 48905.701 | G112: Base-case value less break-even value
...

Sheet Partnership Sensitivity Tables
B2: =Cover!$B$24 -> Keystone Bookkeepers
B3: Partnership Sensitivity Tables ($000s) | N3: Print | O3: 0
B5: Ben's Return Profile Based on Partnerning
B6: Ben's Net Returns Based on Topkey Growth & Rollover %
D8: Topkey ex-Keystone Value Growth (%) | S8: Helper: IRR Year Index | Z8: Helper: Unrounded Net Return
D9: =E9-$G$274 -> 1 | E9: =F9-$G$274 -> 1.25 | F9: =G9-$G$274 -> 1.5 | G9: =H9-$G$274 -> 1.75 | H9: =$G$273 -> 2 | I9: =H9+$G$274 -> 2.25 | J9: =I9+$G$274 -> 2.5 | K9: =J9+$G$274 -> 2.75 | L9: =K9+$G$274 -> 3 | N9: Helper: Rollover % | O9: Helper: Cash at Close | P9: Helper: Topkey Equity Issued | Q9: Helper: Topkey ex-Keystone Today | R9: Helper: Ben's Yr 5 Topkey % | S9: 0 | T9: =S9+1 -> 1 | U9: =T9+1 -> 2 | V9: =U9+1 -> 3 | W9: =V9+1 -> 4 | X9: =W9+1 -> 5 | Z9: =D$9 -> 1 | AA9: =E$9 -> 1.25 | AB9: =F$9 -> 1.5 | AC9: =G$9 -> 1.75 | AD9: =H$9 -> 2 | AE9: =I$9 -> 2.25 | AF9: =J$9 -> 2.5 | AG9: =K$9 -> 2.75 | AH9: =L$9 -> 3 | AT9: Helper: Gradient Band (0 = below $1M hurdle)
B10: Ben's Rollover % | C10: =C11-$G$272 -> 0.15 | D10: =ROUND(Z10,$G$285) -> 3400 | E10: =ROUND(AA10,$G$285) -> 3800 | F10: =ROUND(AB10,$G$285) -> 4200 | G10: =ROUND(AC10,$G$285) -> 4600 | H10: =ROUND(AD10,$G$285) -> 5000 | I10: =ROUND(AE10,$G$285) -> 5400 | J10: =ROUND(AF10,$G$285) -> 5800 | K10: =ROUND(AG10,$G$285) -> 6200 | L10: =ROUND(AH10,$G$285) -> 6600 | N10: =$C10 -> 0.15 | O10: =$G$263*(1-N10)*$G$266 -> 789.28571 | P10: =$G$263*(1-N10)-O10 -> 1760.7143 | Q10: =$G$265-O10 -> 59210.714 | R10: =IFERROR(P10/(Q10+$G$263*(1-N10)),0)*(1-$G$267) -> 0.027083213 | Z10: =$O10+$G$268+$N10*$G$264+$R10*($Q10*(1+D$9)+$G$264*(1-$N10))-$G$263 -> 3415.381 | AA10: =$O10+$G$268+$N10*$G$264+$R10*($Q10*(1+E$9)+$G$264*(1-$N10))-$G$263 -> 3816.2851 | AB10: =$O10+$G$268+$N10*$G$264+$R10*($Q10*(1+F$9)+$G$264*(1-$N10))-$G$263 -> 4217.1892 | AC10: =$O10+$G$268+$N10*$G$264+$R10*($Q10*(1+G$9)+$G$264*(1-$N10))-$G$263 -> 4618.0933 | AD10: =$O10+$G$268+$N10*$G$264+$R10*($Q10*(1+H$9)+$G$264*(1-$N10))-$G$263 -> 5018.9974 | AE10: =$O10+$G$268+$N10*$G$264+$R10*($Q10*(1+I$9)+$G$264*(1-$N10))-$G$263 -> 5419.9015 | AF10: =$O10+$G$268+$N10*$G$264+$R10*($Q10*(1+J$9)+$G$264*(1-$N10))-$G$263 -> 5820.8056 | AG10: =$O10+$G$268+$N10*$G$264+$R10*($Q10*(1+K$9)+$G$264*(1-$N10))-$G$263 -> 6221.7097 | AH10: =$O10+$G$268+$N10*$G$264+$R10*($Q10*(1+L$9)+$G$264*(1-$N10))-$G$263 -> 6622.6138 | AT10: =IF(Z50<$G$282,0,MIN($G$279,1+IFERROR(INT((Z50-$G$282)/$G$284),0))) -> 0 | AU10: =IF(AA50<$G$282,0,MIN($G$279,1+IFERROR(INT((AA50-$G$282)/$G$284),0))) -> 0 | AV10: =IF(AB50<$G$282,0,MIN($G$279,1+IFERROR(INT((AB50-$G$282)/$G$284),0))) -> 0 | AW10: =IF(AC50<$G$282,0,MIN($G$279,1+IFERROR(INT((AC50-$G$282)/$G$284),0))) -> 0 | AX10: =IF(AD50<$G$282,0,MIN($G$279,1+IFERROR(INT((AD50-$G$282)/$G$284),0))) -> 0 | AY10: =IF(AE50<$G$282,0,MIN($G$279,1+IFERROR(INT((AE50-$G$282)/$G$284),0))) -> 0 | AZ10: =IF(AF50<$G$282,0,MIN($G$279,1+IFERROR(INT((AF50-$G$282)/$G$284),0))) -> 2 | BA10: =IF(AG50<$G$282,0,MIN($G$279,1+IFERROR(INT((AG50-$G$282)/$G$284),0))) -> 3 | BB10: =IF(AH50<$G$282,0,MIN($G$279,1+IFERROR(INT((AH50-$G$282)/$G$284),0))) -> 5
C11: =C12-$G$272 -> 0.2 | D11: =ROUND(Z11,$G$285) -> 3900 | E11: =ROUND(AA11,$G$285) -> 4200 | F11: =ROUND(AB11,$G$285) -> 4600 | G11: =ROUND(AC11,$G$285) -> 5000 | H11: =ROUND(AD11,$G$285) -> 5400 | I11: =ROUND(AE11,$G$285) -> 5700 | J11: =ROUND(AF11,$G$285) -> 6100 | K11: =ROUND(AG11,$G$285) -> 6500 | L11: =ROUND(AH11,$G$285) -> 6900 | N11: =$C11 -> 0.2 | O11: =$G$263*(1-N11)*$G$266 -> 742.85714 | P11: =$G$263*(1-N11)-O11 -> 1657.1429 | Q11: =$G$265-O11 -> 59257.143 | R11: =IFERROR(P11/(Q11+$G$263*(1-N11)),0)*(1-$G$267) -> 0.025532901 | Z11: =$O11+$G$268+$N11*$G$264+$R11*($Q11*(1+D$9)+$G$264*(1-$N11))-$G$263 -> 3850.4723 | AA11: =$O11+$G$268+$N11*$G$264+$R11*($Q11*(1+E$9)+$G$264*(1-$N11))-$G$263 -> 4228.724 | AB11: =$O11+$G$268+$N11*$G$264+$R11*($Q11*(1+F$9)+$G$264*(1-$N11))-$G$263 -> 4606.9757 | AC11: =$O11+$G$268+$N11*$G$264+$R11*($Q11*(1+G$9)+$G$264*(1-$N11))-$G$263 -> 4985.2274 | AD11: =$O11+$G$268+$N11*$G$264+$R11*($Q11*(1+H$9)+$G$264*(1-$N11))-$G$263 -> 5363.479 | AE11: =$O11+$G$268+$N11*$G$264+$R11*($Q11*(1+I$9)+$G$264*(1-$N11))-$G$263 -> 5741.7307 | AF11: =$O11+$G$268+$N11*$G$264+$R11*($Q11*(1+J$9)+$G$264*(1-$N11))-$G$263 -> 6119.9824 | AG11: =$O11+$G$268+$N11*$G$264+$R11*($Q11*(1+K$9)+$G$264*(1-$N11))-$G$263 -> 6498.2341 | AH11: =$O11+$G$268+$N11*$G$264+$R11*($Q11*(1+L$9)+$G$264*(1-$N11))-$G$263 -> 6876.4858 | AT11: =IF(Z51<$G$282,0,MIN($G$279,1+IFERROR(INT((Z51-$G$282)/$G$284),0))) -> 0 | AU11: =IF(AA51<$G$282,0,MIN($G$279,1+IFERROR(INT((AA51-$G$282)/$G$284),0))) -> 0 | AV11: =IF(AB51<$G$282,0,MIN($G$279,1+IFERROR(INT((AB51-$G$282)/$G$284),0))) -> 0 | AW11: =IF(AC51<$G$282,0,MIN($G$279,1+IFERROR(INT((AC51-$G$282)/$G$284),0))) -> 0 | AX11: =IF(AD51<$G$282,0,MIN($G$279,1+IFERROR(INT((AD51-$G$282)/$G$284),0))) -> 0 | AY11: =IF(AE51<$G$282,0,MIN($G$279,1+IFERROR(INT((AE51-$G$282)/$G$284),0))) -> 1 | AZ11: =IF(AF51<$G$282,0,MIN($G$279,1+IFERROR(INT((AF51-$G$282)/$G$284),0))) -> 3 | BA11: =IF(AG51<$G$282,0,MIN($G$279,1+IFERROR(INT((AG51-$G$282)/$G$284),0))) -> 4 | BB11: =IF(AH51<$G$282,0,MIN($G$279,1+IFERROR(INT((AH51-$G$282)/$G$284),0))) -> 6
C12: =C13-$G$272 -> 0.25 | D12: =ROUND(Z12,$G$285) -> 4300 | E12: =ROUND(AA12,$G$285) -> 4600 | F12: =ROUND(AB12,$G$285) -> 5000 | G12: =ROUND(AC12,$G$285) -> 5400 | H12: =ROUND(AD12,$G$285) -> 5700 | I12: =ROUND(AE12,$G$285) -> 6100 | J12: =ROUND(AF12,$G$285) -> 6400 | K12: =ROUND(AG12,$G$285) -> 6800 | L12: =ROUND(AH12,$G$285) -> 7100 | N12: =$C12 -> 0.25 | O12: =$G$263*(1-N12)*$G$266 -> 696.42857 | P12: =$G$263*(1-N12)-O12 -> 1553.5714 | Q12: =$G$265-O12 -> 59303.571 | R12: =IFERROR(P12/(Q12+$G$263*(1-N12)),0)*(1-$G$267) -> 0.023977372 | Z12: =$O12+$G$268+$N12*$G$264+$R12*($Q12*(1+D$9)+$G$264*(1-$N12))-$G$263 -> 4286.7695 | AA12: =$O12+$G$268+$N12*$G$264+$R12*($Q12*(1+E$9)+$G$264*(1-$N12))-$G$263 -> 4642.2555 | AB12: =$O12+$G$268+$N12*$G$264+$R12*($Q12*(1+F$9)+$G$264*(1-$N12))-$G$263 -> 4997.7414 | AC12: =$O12+$G$268+$N12*$G$264+$R12*($Q12*(1+G$9)+$G$264*(1-$N12))-$G$263 -> 5353.2274 | AD12: =$O12+$G$268+$N12*$G$264+$R12*($Q12*(1+H$9)+$G$264*(1-$N12))-$G$263 -> 5708.7133 | AE12: =$O12+$G$268+$N12*$G$264+$R12*($Q12*(1+I$9)+$G$264*(1-$N12))-$G$263 -> 6064.1992 | AF12: =$O12+$G$268+$N12*$G$264+$R12*($Q12*(1+J$9)+$G$264*(1-$N12))-$G$263 -> 6419.6852 | AG12: =$O12+$G$268+$N12*$G$264+$R12*($Q12*(1+K$9)+$G$264*(1-$N12))-$G$263 -> 6775.1711 | AH12: =$O12+$G$268+$N12*$G$264+$R12*($Q12*(1+L$9)+$G$264*(1-$N12))-$G$263 -> 7130.6571 | AT12: =IF(Z52<$G$282,0,MIN($G$279,1+IFERROR(INT((Z52-$G$282)/$G$284),0))) -> 0 | AU12: =IF(AA52<$G$282,0,MIN($G$279,1+IFERROR(INT((AA52-$G$282)/$G$284),0))) -> 0 | AV12: =IF(AB52<$G$282,0,MIN($G$279,1+IFERROR(INT((AB52-$G$282)/$G$284),0))) -> 0 | AW12: =IF(AC52<$G$282,0,MIN($G$279,1+IFERROR(INT((AC52-$G$282)/$G$284),0))) -> 0 | AX12: =IF(AD52<$G$282,0,MIN($G$279,1+IFERROR(INT((AD52-$G$282)/$G$284),0))) -> 1 | AY12: =IF(AE52<$G$282,0,MIN($G$279,1+IFERROR(INT((AE52-$G$282)/$G$284),0))) -> 3 | AZ12: =IF(AF52<$G$282,0,MIN($G$279,1+IFERROR(INT((AF52-$G$282)/$G$284),0))) -> 4 | BA12: =IF(AG52<$G$282,0,MIN($G$279,1+IFERROR(INT((AG52-$G$282)/$G$284),0))) -> 5 | BB12: =IF(AH52<$G$282,0,MIN($G$279,1+IFERROR(INT((AH52-$G$282)/$G$284),0))) -> 7
C13: =$G$271 -> 0.3 | D13: =ROUND(Z13,$G$285) -> 4700 | E13: =ROUND(AA13,$G$285) -> 5100 | F13: =ROUND(AB13,$G$285) -> 5400 | G13: =ROUND(AC13,$G$285) -> 5700 | H13: =ROUND(AD13,$G$285) -> 6100 | I13: =ROUND(AE13,$G$285) -> 6400 | J13: =ROUND(AF13,$G$285) -> 6700 | K13: =ROUND(AG13,$G$285) -> 7100 | L13: =ROUND(AH13,$G$285) -> 7400 | N13: =$C13 -> 0.3 | O13: =$G$263*(1-N13)*$G$266 -> 650 | P13: =$G$263*(1-N13)-O13 -> 1450 | Q13: =$G$265-O13 -> 59350 | R13: =IFERROR(P13/(Q13+$G$263*(1-N13)),0)*(1-$G$267) -> 0.022416599 | Z13: =$O13+$G$268+$N13*$G$264+$R13*($Q13*(1+D$9)+$G$264*(1-$N13))-$G$263 -> 4724.2788 | AA13: =$O13+$G$268+$N13*$G$264+$R13*($Q13*(1+E$9)+$G$264*(1-$N13))-$G$263 -> 5056.8851 | AB13: =$O13+$G$268+$N13*$G$264+$R13*($Q13*(1+F$9)+$G$264*(1-$N13))-$G$263 -> 5389.4914 | AC13: =$O13+$G$268+$N13*$G$264+$R13*($Q13*(1+G$9)+$G$264*(1-$N13))-$G$263 -> 5722.0977 | AD13: =$O13+$G$268+$N13*$G$264+$R13*($Q13*(1+H$9)+$G$264*(1-$N13))-$G$263 -> 6054.704 | AE13: =$O13+$G$268+$N13*$G$264+$R13*($Q13*(1+I$9)+$G$264*(1-$N13))-$G$263 -> 6387.3102 | AF13: =$O13+$G$268+$N13*$G$264+$R13*($Q13*(1+J$9)+$G$264*(1-$N13))-$G$263 -> 6719.9165 | AG13: =$O13+$G$268+$N13*$G$264+$R13*($Q13*(1+K$9)+$G$264*(1-$N13))-$G$263 -> 7052.5228 | AH13: =$O13+$G$268+$N13*$G$264+$R13*($Q13*(1+L$9)+$G$264*(1-$N13))-$G$263 -> 7385.1291 | AT13: =IF(Z53<$G$282,0,MIN($G$279,1+IFERROR(INT((Z53-$G$282)/$G$284),0))) -> 0 | AU13: =IF(AA53<$G$282,0,MIN($G$279,1+IFERROR(INT((AA53-$G$282)/$G$284),0))) -> 0 | AV13: =IF(AB53<$G$282,0,MIN($G$279,1+IFERROR(INT((AB53-$G$282)/$G$284),0))) -> 0 | AW13: =IF(AC53<$G$282,0,MIN($G$279,1+IFERROR(INT((AC53-$G$282)/$G$284),0))) -> 1 | AX13: =IF(AD53<$G$282,0,MIN($G$279,1+IFERROR(INT((AD53-$G$282)/$G$284),0))) -> 3 | AY13: =IF(AE53<$G$282,0,MIN($G$279,1+IFERROR(INT((AE53-$G$282)/$G$284),0))) -> 4 | AZ13: =IF(AF53<$G$282,0,MIN($G$279,1+IFERROR(INT((AF53-$G$282)/$G$284),0))) -> 5 | BA13: =IF(AG53<$G$282,0,MIN($G$279,1+IFERROR(INT((AG53-$G$282)/$G$284),0))) -> 6 | BB13: =IF(AH53<$G$282,0,MIN($G$279,1+IFERROR(INT((AH53-$G$282)/$G$284),0))) -> 8
C14: =C13+$G$272 -> 0.35 | D14: =ROUND(Z14,$G$285) -> 5200 | E14: =ROUND(AA14,$G$285) -> 5500 | F14: =ROUND(AB14,$G$285) -> 5800 | G14: =ROUND(AC14,$G$285) -> 6100 | H14: =ROUND(AD14,$G$285) -> 6400 | I14: =ROUND(AE14,$G$285) -> 6700 | J14: =ROUND(AF14,$G$285) -> 7000 | K14: =ROUND(AG14,$G$285) -> 7300 | L14: =ROUND(AH14,$G$285) -> 7600 | N14: =$C14 -> 0.35 | O14: =$G$263*(1-N14)*$G$266 -> 603.57143 | P14: =$G$263*(1-N14)-O14 -> 1346.4286 | Q14: =$G$265-O14 -> 59396.429 | R14: =IFERROR(P14/(Q14+$G$263*(1-N14)),0)*(1-$G$267) -> 0.020850556 | Z14: =$O14+$G$268+$N14*$G$264+$R14*($Q14*(1+D$9)+$G$264*(1-$N14))-$G$263 -> 5163.0063 | AA14: =$O14+$G$268+$N14*$G$264+$R14*($Q14*(1+E$9)+$G$264*(1-$N14))-$G$263 -> 5472.6184 | AB14: =$O14+$G$268+$N14*$G$264+$R14*($Q14*(1+F$9)+$G$264*(1-$N14))-$G$263 -> 5782.2306 | AC14: =$O14+$G$268+$N14*$G$264+$R14*($Q14*(1+G$9)+$G$264*(1-$N14))-$G$263 -> 6091.8427 | AD14: =$O14+$G$268+$N14*$G$264+$R14*($Q14*(1+H$9)+$G$264*(1-$N14))-$G$263 -> 6401.4548 | AE14: =$O14+$G$268+$N14*$G$264+$R14*($Q14*(1+I$9)+$G$264*(1-$N14))-$G$263 -> 6711.067 | AF14: =$O14+$G$268+$N14*$G$264+$R14*($Q14*(1+J$9)+$G$264*(1-$N14))-$G$263 -> 7020.6791 | AG14: =$O14+$G$268+$N14*$G$264+$R14*($Q14*(1+K$9)+$G$264*(1-$N14))-$G$263 -> 7330.2913 | AH14: =$O14+$G$268+$N14*$G$264+$R14*($Q14*(1+L$9)+$G$264*(1-$N14))-$G$263 -> 7639.9034 | AT14: =IF(Z54<$G$282,0,MIN($G$279,1+IFERROR(INT((Z54-$G$282)/$G$284),0))) -> 0 | AU14: =IF(AA54<$G$282,0,MIN($G$279,1+IFERROR(INT((AA54-$G$282)/$G$284),0))) -> 0 | AV14: =IF(AB54<$G$282,0,MIN($G$279,1+IFERROR(INT((AB54-$G$282)/$G$284),0))) -> 2 | AW14: =IF(AC54<$G$282,0,MIN($G$279,1+IFERROR(INT((AC54-$G$282)/$G$284),0))) -> 3 | AX14: =IF(AD54<$G$282,0,MIN($G$279,1+IFERROR(INT((AD54-$G$282)/$G$284),0))) -> 4 | AY14: =IF(AE54<$G$282,0,MIN($G$279,1+IFERROR(INT((AE54-$G$282)/$G$284),0))) -> 5 | AZ14: =IF(AF54<$G$282,0,MIN($G$279,1+IFERROR(INT((AF54-$G$282)/$G$284),0))) -> 6 | BA14: =IF(AG54<$G$282,0,MIN($G$279,1+IFERROR(INT((AG54-$G$282)/$G$284),0))) -> 7 | BB14: =IF(AH54<$G$282,0,MIN($G$279,1+IFERROR(INT((AH54-$G$282)/$G$284),0))) -> 9
C15: =C14+$G$272 -> 0.4 | D15: =ROUND(Z15,$G$285) -> 5600 | E15: =ROUND(AA15,$G$285) -> 5900 | F15: =ROUND(AB15,$G$285) -> 6200 | G15: =ROUND(AC15,$G$285) -> 6500 | H15: =ROUND(AD15,$G$285) -> 6700 | I15: =ROUND(AE15,$G$285) -> 7000 | J15: =ROUND(AF15,$G$285) -> 7300 | K15: =ROUND(AG15,$G$285) -> 7600 | L15: =ROUND(AH15,$G$285) -> 7900 | N15: =$C15 -> 0.4 | O15: =$G$263*(1-N15)*$G$266 -> 557.14286 | P15: =$G$263*(1-N15)-O15 -> 1242.8571 | Q15: =$G$265-O15 -> 59442.857 | R15: =IFERROR(P15/(Q15+$G$263*(1-N15)),0)*(1-$G$267) -> 0.019279216 | Z15: =$O15+$G$268+$N15*$G$264+$R15*($Q15*(1+D$9)+$G$264*(1-$N15))-$G$263 -> 5602.9581 | AA15: =$O15+$G$268+$N15*$G$264+$R15*($Q15*(1+E$9)+$G$264*(1-$N15))-$G$263 -> 5889.4611 | AB15: =$O15+$G$268+$N15*$G$264+$R15*($Q15*(1+F$9)+$G$264*(1-$N15))-$G$263 -> 6175.964 | AC15: =$O15+$G$268+$N15*$G$264+$R15*($Q15*(1+G$9)+$G$264*(1-$N15))-$G$263 -> 6462.4669 | AD15: =$O15+$G$268+$N15*$G$264+$R15*($Q15*(1+H$9)+$G$264*(1-$N15))-$G$263 -> 6748.9698 | AE15: =$O15+$G$268+$N15*$G$264+$R15*($Q15*(1+I$9)+$G$264*(1-$N15))-$G$263 -> 7035.4728 | AF15: =$O15+$G$268+$N15*$G$264+$R15*($Q15*(1+J$9)+$G$264*(1-$N15))-$G$263 -> 7321.9757 | AG15: =$O15+$G$268+$N15*$G$264+$R15*($Q15*(1+K$9)+$G$264*(1-$N15))-$G$263 -> 7608.4786 | AH15: =$O15+$G$268+$N15*$G$264+$R15*($Q15*(1+L$9)+$G$264*(1-$N15))-$G$263 -> 7894.9815 | AT15: =IF(Z55<$G$282,0,MIN($G$279,1+IFERROR(INT((Z55-$G$282)/$G$284),0))) -> 1 | AU15: =IF(AA55<$G$282,0,MIN($G$279,1+IFERROR(INT((AA55-$G$282)/$G$284),0))) -> 2 | AV15: =IF(AB55<$G$282,0,MIN($G$279,1+IFERROR(INT((AB55-$G$282)/$G$284),0))) -> 3 | AW15: =IF(AC55<$G$282,0,MIN($G$279,1+IFERROR(INT((AC55-$G$282)/$G$284),0))) -> 4 | AX15: =IF(AD55<$G$282,0,MIN($G$279,1+IFERROR(INT((AD55-$G$282)/$G$284),0))) -> 5 | AY15: =IF(AE55<$G$282,0,MIN($G$279,1+IFERROR(INT((AE55-$G$282)/$G$284),0))) -> 6 | AZ15: =IF(AF55<$G$282,0,MIN($G$279,1+IFERROR(INT((AF55-$G$282)/$G$284),0))) -> 7 | BA15: =IF(AG55<$G$282,0,MIN($G$279,1+IFERROR(INT((AG55-$G$282)/$G$284),0))) -> 8 | BB15: =IF(AH55<$G$282,0,MIN($G$279,1+IFERROR(INT((AH55-$G$282)/$G$284),0))) -> 10
C16: =C15+$G$272 -> 0.45 | D16: =ROUND(Z16,$G$285) -> 6000 | E16: =ROUND(AA16,$G$285) -> 6300 | F16: =ROUND(AB16,$G$285) -> 6600 | G16: =ROUND(AC16,$G$285) -> 6800 | H16: =ROUND(AD16,$G$285) -> 7100 | I16: =ROUND(AE16,$G$285) -> 7400 | J16: =ROUND(AF16,$G$285) -> 7600 | K16: =ROUND(AG16,$G$285) -> 7900 | L16: =ROUND(AH16,$G$285) -> 8200 | N16: =$C16 -> 0.45 | O16: =$G$263*(1-N16)*$G$266 -> 510.71429 | P16: =$G$263*(1-N16)-O16 -> 1139.2857 | Q16: =$G$265-O16 -> 59489.286 | R16: =IFERROR(P16/(Q16+$G$263*(1-N16)),0)*(1-$G$267) -> 0.017702553 | Z16: =$O16+$G$268+$N16*$G$264+$R16*($Q16*(1+D$9)+$G$264*(1-$N16))-$G$263 -> 6044.1406 | AA16: =$O16+$G$268+$N16*$G$264+$R16*($Q16*(1+E$9)+$G$264*(1-$N16))-$G$263 -> 6307.4186 | AB16: =$O16+$G$268+$N16*$G$264+$R16*($Q16*(1+F$9)+$G$264*(1-$N16))-$G$263 -> 6570.6967 | AC16: =$O16+$G$268+$N16*$G$264+$R16*($Q16*(1+G$9)+$G$264*(1-$N16))-$G$263 -> 6833.9747 | AD16: =$O16+$G$268+$N16*$G$264+$R16*($Q16*(1+H$9)+$G$264*(1-$N16))-$G$263 -> 7097.2528 | AE16: =$O16+$G$268+$N16*$G$264+$R16*($Q16*(1+I$9)+$G$264*(1-$N16))-$G$263 -> 7360.5308 | AF16: =$O16+$G$268+$N16*$G$264+$R16*($Q16*(1+J$9)+$G$264*(1-$N16))-$G$263 -> 7623.8089 | AG16: =$O16+$G$268+$N16*$G$264+$R16*($Q16*(1+K$9)+$G$264*(1-$N16))-$G$263 -> 7887.087 | AH16: =$O16+$G$268+$N16*$G$264+$R16*($Q16*(1+L$9)+$G$264*(1-$N16))-$G$263 -> 8150.365 | AT16: =IF(Z56<$G$282,0,MIN($G$279,1+IFERROR(INT((Z56-$G$282)/$G$284),0))) -> 3 | AU16: =IF(AA56<$G$282,0,MIN($G$279,1+IFERROR(INT((AA56-$G$282)/$G$284),0))) -> 4 | AV16: =IF(AB56<$G$282,0,MIN($G$279,1+IFERROR(INT((AB56-$G$282)/$G$284),0))) -> 5 | AW16: =IF(AC56<$G$282,0,MIN($G$279,1+IFERROR(INT((AC56-$G$282)/$G$284),0))) -> 6 | AX16: =IF(AD56<$G$282,0,MIN($G$279,1+IFERROR(INT((AD56-$G$282)/$G$284),0))) -> 7 | AY16: =IF(AE56<$G$282,0,MIN($G$279,1+IFERROR(INT((AE56-$G$282)/$G$284),0))) -> 8 | AZ16: =IF(AF56<$G$282,0,MIN($G$279,1+IFERROR(INT((AF56-$G$282)/$G$284),0))) -> 9 | BA16: =IF(AG56<$G$282,0,MIN($G$279,1+IFERROR(INT((AG56-$G$282)/$G$284),0))) -> 10 | BB16: =IF(AH56<$G$282,0,MIN($G$279,1+IFERROR(INT((AH56-$G$282)/$G$284),0))) -> 10
B17: Ben's Year 5 value (cash at close + earnout + retained Keystone stake + Topkey stock, after dilution) less Keystone value today (G263)
N18: =$G$269 -> 0.3 | O18: =$G$263*(1-N18)*$G$266 -> 650 | P18: =$G$263*(1-N18)-O18 -> 1450 | Q18: =$G$265-O18 -> 59350 | R18: =IFERROR(P18/(Q18+$G$263*(1-N18)),0)*(1-$G$267) -> 0.022416599
B19: Ben's % Return on Keystone Value Based on Topkey Growth & Rollover %
D21: Topkey ex-Keystone Value Growth (%)
D22: =E22-$G$274 -> 1 | E22: =F22-$G$274 -> 1.25 | F22: =G22-$G$274 -> 1.5 | G22: =H22-$G$274 -> 1.75 | H22: =$G$273 -> 2 | I22: =H22+$G$274 -> 2.25 | J22: =I22+$G$274 -> 2.5 | K22: =J22+$G$274 -> 2.75 | L22: =K22+$G$274 -> 3 | AT22: Helper: Gradient Band (0 = below $1M hurdle)
B23: Ben's Rollover % | C23: =C24-$G$272 -> 0.15 | D23: =IFERROR(Z10/$G$263,0) -> 1.1384603 | E23: =IFERROR(AA10/$G$263,0) -> 1.272095 | F23: =IFERROR(AB10/$G$263,0) -> 1.4057297 | G23: =IFERROR(AC10/$G$263,0) -> 1.5393644 | H23: =IFERROR(AD10/$G$263,0) -> 1.6729991 | I23: =IFERROR(AE10/$G$263,0) -> 1.8066338 | J23: =IFERROR(AF10/$G$263,0) -> 1.9402685 | K23: =IFERROR(AG10/$G$263,0) -> 2.0739032 | L23: =IFERROR(AH10/$G$263,0) -> 2.2075379 | AT23: =IF(Z50<$G$282,0,MIN($G$279,1+IFERROR(INT((Z50-$G$282)/$G$284),0))) -> 0 | AU23: =IF(AA50<$G$282,0,MIN($G$279,1+IFERROR(INT((AA50-$G$282)/$G$284),0))) -> 0 | AV23: =IF(AB50<$G$282,0,MIN($G$279,1+IFERROR(INT((AB50-$G$282)/$G$284),0))) -> 0 | AW23: =IF(AC50<$G$282,0,MIN($G$279,1+IFERROR(INT((AC50-$G$282)/$G$284),0))) -> 0 | AX23: =IF(AD50<$G$282,0,MIN($G$279,1+IFERROR(INT((AD50-$G$282)/$G$284),0))) -> 0 | AY23: =IF(AE50<$G$282,0,MIN($G$279,1+IFERROR(INT((AE50-$G$282)/$G$284),0))) -> 0 | AZ23: =IF(AF50<$G$282,0,MIN($G$279,1+IFERROR(INT((AF50-$G$282)/$G$284),0))) -> 2 | BA23: =IF(AG50<$G$282,0,MIN($G$279,1+IFERROR(INT((AG50-$G$282)/$G$284),0))) -> 3 | BB23: =IF(AH50<$G$282,0,MIN($G$279,1+IFERROR(INT((AH50-$G$282)/$G$284),0))) -> 5
C24: =C25-$G$272 -> 0.2 | D24: =IFERROR(Z11/$G$263,0) -> 1.2834908 | E24: =IFERROR(AA11/$G$263,0) -> 1.4095747 | F24: =IFERROR(AB11/$G$263,0) -> 1.5356586 | G24: =IFERROR(AC11/$G$263,0) -> 1.6617425 | H24: =IFERROR(AD11/$G$263,0) -> 1.7878263 | I24: =IFERROR(AE11/$G$263,0) -> 1.9139102 | J24: =IFERROR(AF11/$G$263,0) -> 2.0399941 | K24: =IFERROR(AG11/$G$263,0) -> 2.166078 | L24: =IFERROR(AH11/$G$263,0) -> 2.2921619 | AT24: =IF(Z51<$G$282,0,MIN($G$279,1+IFERROR(INT((Z51-$G$282)/$G$284),0))) -> 0 | AU24: =IF(AA51<$G$282,0,MIN($G$279,1+IFERROR(INT((AA51-$G$282)/$G$284),0))) -> 0 | AV24: =IF(AB51<$G$282,0,MIN($G$279,1+IFERROR(INT((AB51-$G$282)/$G$284),0))) -> 0 | AW24: =IF(AC51<$G$282,0,MIN($G$279,1+IFERROR(INT((AC51-$G$282)/$G$284),0))) -> 0 | AX24: =IF(AD51<$G$282,0,MIN($G$279,1+IFERROR(INT((AD51-$G$282)/$G$284),0))) -> 0 | AY24: =IF(AE51<$G$282,0,MIN($G$279,1+IFERROR(INT((AE51-$G$282)/$G$284),0))) -> 1 | AZ24: =IF(AF51<$G$282,0,MIN($G$279,1+IFERROR(INT((AF51-$G$282)/$G$284),0))) -> 3 | BA24: =IF(AG51<$G$282,0,MIN($G$279,1+IFERROR(INT((AG51-$G$282)/$G$284),0))) -> 4 | BB24: =IF(AH51<$G$282,0,MIN($G$279,1+IFERROR(INT((AH51-$G$282)/$G$284),0))) -> 6
C25: =C26-$G$272 -> 0.25 | D25: =IFERROR(Z12/$G$263,0) -> 1.4289232 | E25: =IFERROR(AA12/$G$263,0) -> 1.5474185 | F25: =IFERROR(AB12/$G$263,0) -> 1.6659138 | G25: =IFERROR(AC12/$G$263,0) -> 1.7844091 | H25: =IFERROR(AD12/$G$263,0) -> 1.9029044 | I25: =IFERROR(AE12/$G$263,0) -> 2.0213997 | J25: =IFERROR(AF12/$G$263,0) -> 2.1398951 | K25: =IFERROR(AG12/$G$263,0) -> 2.2583904 | L25: =IFERROR(AH12/$G$263,0) -> 2.3768857 | AT25: =IF(Z52<$G$282,0,MIN($G$279,1+IFERROR(INT((Z52-$G$282)/$G$284),0))) -> 0 | AU25: =IF(AA52<$G$282,0,MIN($G$279,1+IFERROR(INT((AA52-$G$282)/$G$284),0))) -> 0 | AV25: =IF(AB52<$G$282,0,MIN($G$279,1+IFERROR(INT((AB52-$G$282)/$G$284),0))) -> 0 | AW25: =IF(AC52<$G$282,0,MIN($G$279,1+IFERROR(INT((AC52-$G$282)/$G$284),0))) -> 0 | AX25: =IF(AD52<$G$282,0,MIN($G$279,1+IFERROR(INT((AD52-$G$282)/$G$284),0))) -> 1 | AY25: =IF(AE52<$G$282,0,MIN($G$279,1+IFERROR(INT((AE52-$G$282)/$G$284),0))) -> 3 | AZ25: =IF(AF52<$G$282,0,MIN($G$279,1+IFERROR(INT((AF52-$G$282)/$G$284),0))) -> 4 | BA25: =IF(AG52<$G$282,0,MIN($G$279,1+IFERROR(INT((AG52-$G$282)/$G$284),0))) -> 5 | BB25: =IF(AH52<$G$282,0,MIN($G$279,1+IFERROR(INT((AH52-$G$282)/$G$284),0))) -> 7
C26: =$G$271 -> 0.3 | D26: =IFERROR(Z13/$G$263,0) -> 1.5747596 | E26: =IFERROR(AA13/$G$263,0) -> 1.6856284 | F26: =IFERROR(AB13/$G$263,0) -> 1.7964971 | G26: =IFERROR(AC13/$G$263,0) -> 1.9073659 | H26: =IFERROR(AD13/$G$263,0) -> 2.0182347 | I26: =IFERROR(AE13/$G$263,0) -> 2.1291034 | J26: =IFERROR(AF13/$G$263,0) -> 2.2399722 | K26: =IFERROR(AG13/$G$263,0) -> 2.3508409 | L26: =IFERROR(AH13/$G$263,0) -> 2.4617097 | AT26: =IF(Z53<$G$282,0,MIN($G$279,1+IFERROR(INT((Z53-$G$282)/$G$284),0))) -> 0 | AU26: =IF(AA53<$G$282,0,MIN($G$279,1+IFERROR(INT((AA53-$G$282)/$G$284),0))) -> 0 | AV26: =IF(AB53<$G$282,0,MIN($G$279,1+IFERROR(INT((AB53-$G$282)/$G$284),0))) -> 0 | AW26: =IF(AC53<$G$282,0,MIN($G$279,1+IFERROR(INT((AC53-$G$282)/$G$284),0))) -> 1 | AX26: =IF(AD53<$G$282,0,MIN($G$279,1+IFERROR(INT((AD53-$G$282)/$G$284),0))) -> 3 | AY26: =IF(AE53<$G$282,0,MIN($G$279,1+IFERROR(INT((AE53-$G$282)/$G$284),0))) -> 4 | AZ26: =IF(AF53<$G$282,0,MIN($G$279,1+IFERROR(INT((AF53-$G$282)/$G$284),0))) -> 5 | BA26: =IF(AG53<$G$282,0,MIN($G$279,1+IFERROR(INT((AG53-$G$282)/$G$284),0))) -> 6 | BB26: =IF(AH53<$G$282,0,MIN($G$279,1+IFERROR(INT((AH53-$G$282)/$G$284),0))) -> 8
C27: =C26+$G$272 -> 0.35 | D27: =IFERROR(Z14/$G$263,0) -> 1.7210021 | E27: =IFERROR(AA14/$G$263,0) -> 1.8242061 | F27: =IFERROR(AB14/$G$263,0) -> 1.9274102 | G27: =IFERROR(AC14/$G$263,0) -> 2.0306142 | H27: =IFERROR(AD14/$G$263,0) -> 2.1338183 | I27: =IFERROR(AE14/$G$263,0) -> 2.2370223 | J27: =IFERROR(AF14/$G$263,0) -> 2.3402264 | K27: =IFERROR(AG14/$G$263,0) -> 2.4434304 | L27: =IFERROR(AH14/$G$263,0) -> 2.5466345 | AT27: =IF(Z54<$G$282,0,MIN($G$279,1+IFERROR(INT((Z54-$G$282)/$G$284),0))) -> 0 | AU27: =IF(AA54<$G$282,0,MIN($G$279,1+IFERROR(INT((AA54-$G$282)/$G$284),0))) -> 0 | AV27: =IF(AB54<$G$282,0,MIN($G$279,1+IFERROR(INT((AB54-$G$282)/$G$284),0))) -> 2 | AW27: =IF(AC54<$G$282,0,MIN($G$279,1+IFERROR(INT((AC54-$G$282)/$G$284),0))) -> 3 | AX27: =IF(AD54<$G$282,0,MIN($G$279,1+IFERROR(INT((AD54-$G$282)/$G$284),0))) -> 4 | AY27: =IF(AE54<$G$282,0,MIN($G$279,1+IFERROR(INT((AE54-$G$282)/$G$284),0))) -> 5 | AZ27: =IF(AF54<$G$282,0,MIN($G$279,1+IFERROR(INT((AF54-$G$282)/$G$284),0))) -> 6 | BA27: =IF(AG54<$G$282,0,MIN($G$279,1+IFERROR(INT((AG54-$G$282)/$G$284),0))) -> 7 | BB27: =IF(AH54<$G$282,0,MIN($G$279,1+IFERROR(INT((AH54-$G$282)/$G$284),0))) -> 9
C28: =C27+$G$272 -> 0.4 | D28: =IFERROR(Z15/$G$263,0) -> 1.8676527 | E28: =IFERROR(AA15/$G$263,0) -> 1.9631537 | F28: =IFERROR(AB15/$G$263,0) -> 2.0586547 | G28: =IFERROR(AC15/$G$263,0) -> 2.1541556 | H28: =IFERROR(AD15/$G$263,0) -> 2.2496566 | I28: =IFERROR(AE15/$G$263,0) -> 2.3451576 | J28: =IFERROR(AF15/$G$263,0) -> 2.4406586 | K28: =IFERROR(AG15/$G$263,0) -> 2.5361595 | L28: =IFERROR(AH15/$G$263,0) -> 2.6316605 | AT28: =IF(Z55<$G$282,0,MIN($G$279,1+IFERROR(INT((Z55-$G$282)/$G$284),0))) -> 1 | AU28: =IF(AA55<$G$282,0,MIN($G$279,1+IFERROR(INT((AA55-$G$282)/$G$284),0))) -> 2 | AV28: =IF(AB55<$G$282,0,MIN($G$279,1+IFERROR(INT((AB55-$G$282)/$G$284),0))) -> 3 | AW28: =IF(AC55<$G$282,0,MIN($G$279,1+IFERROR(INT((AC55-$G$282)/$G$284),0))) -> 4 | AX28: =IF(AD55<$G$282,0,MIN($G$279,1+IFERROR(INT((AD55-$G$282)/$G$284),0))) -> 5 | AY28: =IF(AE55<$G$282,0,MIN($G$279,1+IFERROR(INT((AE55-$G$282)/$G$284),0))) -> 6 | AZ28: =IF(AF55<$G$282,0,MIN($G$279,1+IFERROR(INT((AF55-$G$282)/$G$284),0))) -> 7 | BA28: =IF(AG55<$G$282,0,MIN($G$279,1+IFERROR(INT((AG55-$G$282)/$G$284),0))) -> 8 | BB28: =IF(AH55<$G$282,0,MIN($G$279,1+IFERROR(INT((AH55-$G$282)/$G$284),0))) -> 10
C29: =C28+$G$272 -> 0.45 | D29: =IFERROR(Z16/$G$263,0) -> 2.0147135 | E29: =IFERROR(AA16/$G$263,0) -> 2.1024729 | F29: =IFERROR(AB16/$G$263,0) -> 2.1902322 | G29: =IFERROR(AC16/$G$263,0) -> 2.2779916 | H29: =IFERROR(AD16/$G$263,0) -> 2.3657509 | I29: =IFERROR(AE16/$G$263,0) -> 2.4535103 | J29: =IFERROR(AF16/$G$263,0) -> 2.5412696 | K29: =IFERROR(AG16/$G$263,0) -> 2.629029 | L29: =IFERROR(AH16/$G$263,0) -> 2.7167883 | AT29: =IF(Z56<$G$282,0,MIN($G$279,1+IFERROR(INT((Z56-$G$282)/$G$284),0))) -> 3 | AU29: =IF(AA56<$G$282,0,MIN($G$279,1+IFERROR(INT((AA56-$G$282)/$G$284),0))) -> 4 | AV29: =IF(AB56<$G$282,0,MIN($G$279,1+IFERROR(INT((AB56-$G$282)/$G$284),0))) -> 5 | AW29: =IF(AC56<$G$282,0,MIN($G$279,1+IFERROR(INT((AC56-$G$282)/$G$284),0))) -> 6 | AX29: =IF(AD56<$G$282,0,MIN($G$279,1+IFERROR(INT((AD56-$G$282)/$G$284),0))) -> 7 | AY29: =IF(AE56<$G$282,0,MIN($G$279,1+IFERROR(INT((AE56-$G$282)/$G$284),0))) -> 8 | AZ29: =IF(AF56<$G$282,0,MIN($G$279,1+IFERROR(INT((AF56-$G$282)/$G$284),0))) -> 9 | BA29: =IF(AG56<$G$282,0,MIN($G$279,1+IFERROR(INT((AG56-$G$282)/$G$284),0))) -> 10 | BB29: =IF(AH56<$G$282,0,MIN($G$279,1+IFERROR(INT((AH56-$G$282)/$G$284),0))) -> 10
B30: Ben's Year 5 total value ÷ Keystone value today (G263), less 1
B32: Ben's IRR Based on Topkey Growth & Rollover %
D34: Topkey ex-Keystone Value Growth (%)
D35: =E35-$G$274 -> 1 | E35: =F35-$G$274 -> 1.25 | F35: =G35-$G$274 -> 1.5 | G35: =H35-$G$274 -> 1.75 | H35: =$G$273 -> 2 | I35: =H35+$G$274 -> 2.25 | J35: =I35+$G$274 -> 2.5 | K35: =J35+$G$274 -> 2.75 | L35: =K35+$G$274 -> 3 | AT35: Helper: Gradient Band (0 = below $1M hurdle)
B36: Ben's Rollover % | C36: =C37-$G$272 -> 0.15 | D36: {=IFERROR(IRR(IF($S$9:$X$9=0,$O10-$G$263,0)+IF($S$9:$X$9=$G$277,$G$268,0)+IF($S$9:$X$9=$G$278,Z10+$G$263-$O10-$G$268,0)),0)} -> 0.20541029 | E36: {=IFERROR(IRR(IF($S$9:$X$9=0,$O10-$G$263,0)+IF($S$9:$X$9=$G$277,$G$268,0)+IF($S$9:$X$9=$G$278,AA10+$G$263-$O10-$G$268,0)),0)} -> 0.22211959 | F36: {=IFERROR(IRR(IF($S$9:$X$9=0,$O10-$G$263,0)+IF($S$9:$X$9=$G$277,$G$268,0)+IF($S$9:$X$9=$G$278,AB10+$G$263-$O10-$G$268,0)),0)} -> 0.23796209 | G36: {=IFERROR(IRR(IF($S$9:$X$9=0,$O10-$G$263,0)+IF($S$9:$X$9=$G$277,$G$268,0)+IF($S$9:$X$9=$G$278,AC10+$G$263-$O10-$G$268,0)),0)} -> 0.25303283 | H36: {=IFERROR(IRR(IF($S$9:$X$9=0,$O10-$G$263,0)+IF($S$9:$X$9=$G$277,$G$268,0)+IF($S$9:$X$9=$G$278,AD10+$G$263-$O10-$G$268,0)),0)} -> 0.26741158 | I36: {=IFERROR(IRR(IF($S$9:$X$9=0,$O10-$G$263,0)+IF($S$9:$X$9=$G$277,$G$268,0)+IF($S$9:$X$9=$G$278,AE10+$G$263-$O10-$G$268,0)),0)} -> 0.28116597 | J36: {=IFERROR(IRR(IF($S$9:$X$9=0,$O10-$G$263,0)+IF($S$9:$X$9=$G$277,$G$268,0)+IF($S$9:$X$9=$G$278,AF10+$G$263-$O10-$G$268,0)),0)} -> 0.29435386 | K36: {=IFERROR(IRR(IF($S$9:$X$9=0,$O10-$G$263,0)+IF($S$9:$X$9=$G$277,$G$268,0)+IF($S$9:$X$9=$G$278,AG10+$G$263-$O10-$G$268,0)),0)} -> 0.30702521 | L36: {=IFERROR(IRR(IF($S$9:$X$9=0,$O10-$G$263,0)+IF($S$9:$X$9=$G$277,$G$268,0)+IF($S$9:$X$9=$G$278,AH10+$G$263-$O10-$G$268,0)),0)} -> 0.31922341 | AT36: =IF(Z50<$G$282,0,MIN($G$279,1+IFERROR(INT((Z50-$G$282)/$G$284),0))) -> 0 | AU36: =IF(AA50<$G$282,0,MIN($G$279,1+IFERROR(INT((AA50-$G$282)/$G$284),0))) -> 0 | AV36: =IF(AB50<$G$282,0,MIN($G$279,1+IFERROR(INT((AB50-$G$282)/$G$284),0))) -> 0 | AW36: =IF(AC50<$G$282,0,MIN($G$279,1+IFERROR(INT((AC50-$G$282)/$G$284),0))) -> 0 | AX36: =IF(AD50<$G$282,0,MIN($G$279,1+IFERROR(INT((AD50-$G$282)/$G$284),0))) -> 0 | AY36: =IF(AE50<$G$282,0,MIN($G$279,1+IFERROR(INT((AE50-$G$282)/$G$284),0))) -> 0 | AZ36: =IF(AF50<$G$282,0,MIN($G$279,1+IFERROR(INT((AF50-$G$282)/$G$284),0))) -> 2 | BA36: =IF(AG50<$G$282,0,MIN($G$279,1+IFERROR(INT((AG50-$G$282)/$G$284),0))) -> 3 | BB36: =IF(AH50<$G$282,0,MIN($G$279,1+IFERROR(INT((AH50-$G$282)/$G$284),0))) -> 5
C37: =C38-$G$272 -> 0.2 | D37: {=IFERROR(IRR(IF($S$9:$X$9=0,$O11-$G$263,0)+IF($S$9:$X$9=$G$277,$G$268,0)+IF($S$9:$X$9=$G$278,Z11+$G$263-$O11-$G$268,0)),0)} -> 0.22028851 | E37: {=IFERROR(IRR(IF($S$9:$X$9=0,$O11-$G$263,0)+IF($S$9:$X$9=$G$277,$G$268,0)+IF($S$9:$X$9=$G$278,AA11+$G$263-$O11-$G$268,0)),0)} -> 0.2350422 | F37: {=IFERROR(IRR(IF($S$9:$X$9=0,$O11-$G$263,0)+IF($S$9:$X$9=$G$277,$G$268,0)+IF($S$9:$X$9=$G$278,AB11+$G$263-$O11-$G$268,0)),0)} -> 0.24912283 | G37: {=IFERROR(IRR(IF($S$9:$X$9=0,$O11-$G$263,0)+IF($S$9:$X$9=$G$277,$G$268,0)+IF($S$9:$X$9=$G$278,AC11+$G$263-$O11-$G$268,0)),0)} -> 0.26259578 | H37: {=IFERROR(IRR(IF($S$9:$X$9=0,$O11-$G$263,0)+IF($S$9:$X$9=$G$277,$G$268,0)+IF($S$9:$X$9=$G$278,AD11+$G$263-$O11-$G$268,0)),0)} -> 0.27551707 | I37: {=IFERROR(IRR(IF($S$9:$X$9=0,$O11-$G$263,0)+IF($S$9:$X$9=$G$277,$G$268,0)+IF($S$9:$X$9=$G$278,AE11+$G$263-$O11-$G$268,0)),0)} -> 0.28793504 | J37: {=IFERROR(IRR(IF($S$9:$X$9=0,$O11-$G$263,0)+IF($S$9:$X$9=$G$277,$G$268,0)+IF($S$9:$X$9=$G$278,AF11+$G$263-$O11-$G$268,0)),0)} -> 0.29989177 | K37: {=IFERROR(IRR(IF($S$9:$X$9=0,$O11-$G$263,0)+IF($S$9:$X$9=$G$277,$G$268,0)+IF($S$9:$X$9=$G$278,AG11+$G$263-$O11-$G$268,0)),0)} -> 0.3114241 | L37: {=IFERROR(IRR(IF($S$9:$X$9=0,$O11-$G$263,0)+IF($S$9:$X$9=$G$277,$G$268,0)+IF($S$9:$X$9=$G$278,AH11+$G$263-$O11-$G$268,0)),0)} -> 0.3225645 | AT37: =IF(Z51<$G$282,0,MIN($G$279,1+IFERROR(INT((Z51-$G$282)/$G$284),0))) -> 0 | AU37: =IF(AA51<$G$282,0,MIN($G$279,1+IFERROR(INT((AA51-$G$282)/$G$284),0))) -> 0 | AV37: =IF(AB51<$G$282,0,MIN($G$279,1+IFERROR(INT((AB51-$G$282)/$G$284),0))) -> 0 | AW37: =IF(AC51<$G$282,0,MIN($G$279,1+IFERROR(INT((AC51-$G$282)/$G$284),0))) -> 0 | AX37: =IF(AD51<$G$282,0,MIN($G$279,1+IFERROR(INT((AD51-$G$282)/$G$284),0))) -> 0 | AY37: =IF(AE51<$G$282,0,MIN($G$279,1+IFERROR(INT((AE51-$G$282)/$G$284),0))) -> 1 | AZ37: =IF(AF51<$G$282,0,MIN($G$279,1+IFERROR(INT((AF51-$G$282)/$G$284),0))) -> 3 | BA37: =IF(AG51<$G$282,0,MIN($G$279,1+IFERROR(INT((AG51-$G$282)/$G$284),0))) -> 4 | BB37: =IF(AH51<$G$282,0,MIN($G$279,1+IFERROR(INT((AH51-$G$282)/$G$284),0))) -> 6
C38: =C39-$G$272 -> 0.25 | D38: {=IFERROR(IRR(IF($S$9:$X$9=0,$O12-$G$263,0)+IF($S$9:$X$9=$G$277,$G$268,0)+IF($S$9:$X$9=$G$278,Z12+$G$263-$O12-$G$268,0)),0)} -> 0.23396045 | E38: {=IFERROR(IRR(IF($S$9:$X$9=0,$O12-$G$263,0)+IF($S$9:$X$9=$G$277,$G$268,0)+IF($S$9:$X$9=$G$278,AA12+$G$263-$O12-$G$268,0)),0)} -> 0.24699426 | F38: {=IFERROR(IRR(IF($S$9:$X$9=0,$O12-$G$263,0)+IF($S$9:$X$9=$G$277,$G$268,0)+IF($S$9:$X$9=$G$278,AB12+$G$263-$O12-$G$268,0)),0)} -> 0.25950488 | G38: {=IFERROR(IRR(IF($S$9:$X$9=0,$O12-$G$263,0)+IF($S$9:$X$9=$G$277,$G$268,0)+IF($S$9:$X$9=$G$278,AC12+$G$263-$O12-$G$268,0)),0)} -> 0.27153732 | H38: {=IFERROR(IRR(IF($S$9:$X$9=0,$O12-$G$263,0)+IF($S$9:$X$9=$G$277,$G$268,0)+IF($S$9:$X$9=$G$278,AD12+$G$263-$O12-$G$268,0)),0)} -> 0.28313082 | I38: {=IFERROR(IRR(IF($S$9:$X$9=0,$O12-$G$263,0)+IF($S$9:$X$9=$G$277,$G$268,0)+IF($S$9:$X$9=$G$278,AE12+$G$263-$O12-$G$268,0)),0)} -> 0.29431987 | J38: {=IFERROR(IRR(IF($S$9:$X$9=0,$O12-$G$263,0)+IF($S$9:$X$9=$G$277,$G$268,0)+IF($S$9:$X$9=$G$278,AF12+$G$263-$O12-$G$268,0)),0)} -> 0.30513487 | K38: {=IFERROR(IRR(IF($S$9:$X$9=0,$O12-$G$263,0)+IF($S$9:$X$9=$G$277,$G$268,0)+IF($S$9:$X$9=$G$278,AG12+$G$263-$O12-$G$268,0)),0)} -> 0.31560284 | L38: {=IFERROR(IRR(IF($S$9:$X$9=0,$O12-$G$263,0)+IF($S$9:$X$9=$G$277,$G$268,0)+IF($S$9:$X$9=$G$278,AH12+$G$263-$O12-$G$268,0)),0)} -> 0.32574788 | AT38: =IF(Z52<$G$282,0,MIN($G$279,1+IFERROR(INT((Z52-$G$282)/$G$284),0))) -> 0 | AU38: =IF(AA52<$G$282,0,MIN($G$279,1+IFERROR(INT((AA52-$G$282)/$G$284),0))) -> 0 | AV38: =IF(AB52<$G$282,0,MIN($G$279,1+IFERROR(INT((AB52-$G$282)/$G$284),0))) -> 0 | AW38: =IF(AC52<$G$282,0,MIN($G$279,1+IFERROR(INT((AC52-$G$282)/$G$284),0))) -> 0 | AX38: =IF(AD52<$G$282,0,MIN($G$279,1+IFERROR(INT((AD52-$G$282)/$G$284),0))) -> 1 | AY38: =IF(AE52<$G$282,0,MIN($G$279,1+IFERROR(INT((AE52-$G$282)/$G$284),0))) -> 3 | AZ38: =IF(AF52<$G$282,0,MIN($G$279,1+IFERROR(INT((AF52-$G$282)/$G$284),0))) -> 4 | BA38: =IF(AG52<$G$282,0,MIN($G$279,1+IFERROR(INT((AG52-$G$282)/$G$284),0))) -> 5 | BB38: =IF(AH52<$G$282,0,MIN($G$279,1+IFERROR(INT((AH52-$G$282)/$G$284),0))) -> 7
C39: =$G$271 -> 0.3 | D39: {=IFERROR(IRR(IF($S$9:$X$9=0,$O13-$G$263,0)+IF($S$9:$X$9=$G$277,$G$268,0)+IF($S$9:$X$9=$G$278,Z13+$G$263-$O13-$G$268,0)),0)} -> 0.24658777 | E39: {=IFERROR(IRR(IF($S$9:$X$9=0,$O13-$G$263,0)+IF($S$9:$X$9=$G$277,$G$268,0)+IF($S$9:$X$9=$G$278,AA13+$G$263-$O13-$G$268,0)),0)} -> 0.25809533 | F39: {=IFERROR(IRR(IF($S$9:$X$9=0,$O13-$G$263,0)+IF($S$9:$X$9=$G$277,$G$268,0)+IF($S$9:$X$9=$G$278,AB13+$G$263-$O13-$G$268,0)),0)} -> 0.26919663 | G39: {=IFERROR(IRR(IF($S$9:$X$9=0,$O13-$G$263,0)+IF($S$9:$X$9=$G$277,$G$268,0)+IF($S$9:$X$9=$G$278,AC13+$G$263-$O13-$G$268,0)),0)} -> 0.2799226 | H39: {=IFERROR(IRR(IF($S$9:$X$9=0,$O13-$G$263,0)+IF($S$9:$X$9=$G$277,$G$268,0)+IF($S$9:$X$9=$G$278,AD13+$G$263-$O13-$G$268,0)),0)} -> 0.29030064 | I39: {=IFERROR(IRR(IF($S$9:$X$9=0,$O13-$G$263,0)+IF($S$9:$X$9=$G$277,$G$268,0)+IF($S$9:$X$9=$G$278,AE13+$G$263-$O13-$G$268,0)),0)} -> 0.30035514 | J39: {=IFERROR(IRR(IF($S$9:$X$9=0,$O13-$G$263,0)+IF($S$9:$X$9=$G$277,$G$268,0)+IF($S$9:$X$9=$G$278,AF13+$G$263-$O13-$G$268,0)),0)} -> 0.31010796 | K39: {=IFERROR(IRR(IF($S$9:$X$9=0,$O13-$G$263,0)+IF($S$9:$X$9=$G$277,$G$268,0)+IF($S$9:$X$9=$G$278,AG13+$G$263-$O13-$G$268,0)),0)} -> 0.31957873 | L39: {=IFERROR(IRR(IF($S$9:$X$9=0,$O13-$G$263,0)+IF($S$9:$X$9=$G$277,$G$268,0)+IF($S$9:$X$9=$G$278,AH13+$G$263-$O13-$G$268,0)),0)} -> 0.32878516 | AT39: =IF(Z53<$G$282,0,MIN($G$279,1+IFERROR(INT((Z53-$G$282)/$G$284),0))) -> 0 | AU39: =IF(AA53<$G$282,0,MIN($G$279,1+IFERROR(INT((AA53-$G$282)/$G$284),0))) -> 0 | AV39: =IF(AB53<$G$282,0,MIN($G$279,1+IFERROR(INT((AB53-$G$282)/$G$284),0))) -> 0 | AW39: =IF(AC53<$G$282,0,MIN($G$279,1+IFERROR(INT((AC53-$G$282)/$G$284),0))) -> 1 | AX39: =IF(AD53<$G$282,0,MIN($G$279,1+IFERROR(INT((AD53-$G$282)/$G$284),0))) -> 3 | AY39: =IF(AE53<$G$282,0,MIN($G$279,1+IFERROR(INT((AE53-$G$282)/$G$284),0))) -> 4 | AZ39: =IF(AF53<$G$282,0,MIN($G$279,1+IFERROR(INT((AF53-$G$282)/$G$284),0))) -> 5 | BA39: =IF(AG53<$G$282,0,MIN($G$279,1+IFERROR(INT((AG53-$G$282)/$G$284),0))) -> 6 | BB39: =IF(AH53<$G$282,0,MIN($G$279,1+IFERROR(INT((AH53-$G$282)/$G$284),0))) -> 8
C40: =C39+$G$272 -> 0.35 | D40: {=IFERROR(IRR(IF($S$9:$X$9=0,$O14-$G$263,0)+IF($S$9:$X$9=$G$277,$G$268,0)+IF($S$9:$X$9=$G$278,Z14+$G$263-$O14-$G$268,0)),0)} -> 0.25830224 | E40: {=IFERROR(IRR(IF($S$9:$X$9=0,$O14-$G$263,0)+IF($S$9:$X$9=$G$277,$G$268,0)+IF($S$9:$X$9=$G$278,AA14+$G$263-$O14-$G$268,0)),0)} -> 0.26844468 | F40: {=IFERROR(IRR(IF($S$9:$X$9=0,$O14-$G$263,0)+IF($S$9:$X$9=$G$277,$G$268,0)+IF($S$9:$X$9=$G$278,AB14+$G$263-$O14-$G$268,0)),0)} -> 0.27827273 | G40: {=IFERROR(IRR(IF($S$9:$X$9=0,$O14-$G$263,0)+IF($S$9:$X$9=$G$277,$G$268,0)+IF($S$9:$X$9=$G$278,AC14+$G$263-$O14-$G$268,0)),0)} -> 0.28780751 | H40: {=IFERROR(IRR(IF($S$9:$X$9=0,$O14-$G$263,0)+IF($S$9:$X$9=$G$277,$G$268,0)+IF($S$9:$X$9=$G$278,AD14+$G$263-$O14-$G$268,0)),0)} -> 0.29706799 | I40: {=IFERROR(IRR(IF($S$9:$X$9=0,$O14-$G$263,0)+IF($S$9:$X$9=$G$277,$G$268,0)+IF($S$9:$X$9=$G$278,AE14+$G$263-$O14-$G$268,0)),0)} -> 0.30607133 | J40: {=IFERROR(IRR(IF($S$9:$X$9=0,$O14-$G$263,0)+IF($S$9:$X$9=$G$277,$G$268,0)+IF($S$9:$X$9=$G$278,AF14+$G$263-$O14-$G$268,0)),0)} -> 0.31483304 | K40: {=IFERROR(IRR(IF($S$9:$X$9=0,$O14-$G$263,0)+IF($S$9:$X$9=$G$277,$G$268,0)+IF($S$9:$X$9=$G$278,AG14+$G$263-$O14-$G$268,0)),0)} -> 0.32336725 | L40: {=IFERROR(IRR(IF($S$9:$X$9=0,$O14-$G$263,0)+IF($S$9:$X$9=$G$277,$G$268,0)+IF($S$9:$X$9=$G$278,AH14+$G$263-$O14-$G$268,0)),0)} -> 0.33168683 | AT40: =IF(Z54<$G$282,0,MIN($G$279,1+IFERROR(INT((Z54-$G$282)/$G$284),0))) -> 0 | AU40: =IF(AA54<$G$282,0,MIN($G$279,1+IFERROR(INT((AA54-$G$282)/$G$284),0))) -> 0 | AV40: =IF(AB54<$G$282,0,MIN($G$279,1+IFERROR(INT((AB54-$G$282)/$G$284),0))) -> 2 | AW40: =IF(AC54<$G$282,0,MIN($G$279,1+IFERROR(INT((AC54-$G$282)/$G$284),0))) -> 3 | AX40: =IF(AD54<$G$282,0,MIN($G$279,1+IFERROR(INT((AD54-$G$282)/$G$284),0))) -> 4 | AY40: =IF(AE54<$G$282,0,MIN($G$279,1+IFERROR(INT((AE54-$G$282)/$G$284),0))) -> 5 | AZ40: =IF(AF54<$G$282,0,MIN($G$279,1+IFERROR(INT((AF54-$G$282)/$G$284),0))) -> 6 | BA40: =IF(AG54<$G$282,0,MIN($G$279,1+IFERROR(INT((AG54-$G$282)/$G$284),0))) -> 7 | BB40: =IF(AH54<$G$282,0,MIN($G$279,1+IFERROR(INT((AH54-$G$282)/$G$284),0))) -> 9
C41: =C40+$G$272 -> 0.4 | D41: {=IFERROR(IRR(IF($S$9:$X$9=0,$O15-$G$263,0)+IF($S$9:$X$9=$G$277,$G$268,0)+IF($S$9:$X$9=$G$278,Z15+$G$263-$O15-$G$268,0)),0)} -> 0.26921267 | E41: {=IFERROR(IRR(IF($S$9:$X$9=0,$O15-$G$263,0)+IF($S$9:$X$9=$G$277,$G$268,0)+IF($S$9:$X$9=$G$278,AA15+$G$263-$O15-$G$268,0)),0)} -> 0.27812566 | F41: {=IFERROR(IRR(IF($S$9:$X$9=0,$O15-$G$263,0)+IF($S$9:$X$9=$G$277,$G$268,0)+IF($S$9:$X$9=$G$278,AB15+$G$263-$O15-$G$268,0)),0)} -> 0.28679676 | G41: {=IFERROR(IRR(IF($S$9:$X$9=0,$O15-$G$263,0)+IF($S$9:$X$9=$G$277,$G$268,0)+IF($S$9:$X$9=$G$278,AC15+$G$263-$O15-$G$268,0)),0)} -> 0.29524025 | H41: {=IFERROR(IRR(IF($S$9:$X$9=0,$O15-$G$263,0)+IF($S$9:$X$9=$G$277,$G$268,0)+IF($S$9:$X$9=$G$278,AD15+$G$263-$O15-$G$268,0)),0)} -> 0.30346914 | I41: {=IFERROR(IRR(IF($S$9:$X$9=0,$O15-$G$263,0)+IF($S$9:$X$9=$G$277,$G$268,0)+IF($S$9:$X$9=$G$278,AE15+$G$263-$O15-$G$268,0)),0)} -> 0.31149533 | J41: {=IFERROR(IRR(IF($S$9:$X$9=0,$O15-$G$263,0)+IF($S$9:$X$9=$G$277,$G$268,0)+IF($S$9:$X$9=$G$278,AF15+$G$263-$O15-$G$268,0)),0)} -> 0.31932973 | K41: {=IFERROR(IRR(IF($S$9:$X$9=0,$O15-$G$263,0)+IF($S$9:$X$9=$G$277,$G$268,0)+IF($S$9:$X$9=$G$278,AG15+$G$263-$O15-$G$268,0)),0)} -> 0.32698234 | L41: {=IFERROR(IRR(IF($S$9:$X$9=0,$O15-$G$263,0)+IF($S$9:$X$9=$G$277,$G$268,0)+IF($S$9:$X$9=$G$278,AH15+$G$263-$O15-$G$268,0)),0)} -> 0.33446238 | AT41: =IF(Z55<$G$282,0,MIN($G$279,1+IFERROR(INT((Z55-$G$282)/$G$284),0))) -> 1 | AU41: =IF(AA55<$G$282,0,MIN($G$279,1+IFERROR(INT((AA55-$G$282)/$G$284),0))) -> 2 | AV41: =IF(AB55<$G$282,0,MIN($G$279,1+IFERROR(INT((AB55-$G$282)/$G$284),0))) -> 3 | AW41: =IF(AC55<$G$282,0,MIN($G$279,1+IFERROR(INT((AC55-$G$282)/$G$284),0))) -> 4 | AX41: =IF(AD55<$G$282,0,MIN($G$279,1+IFERROR(INT((AD55-$G$282)/$G$284),0))) -> 5 | AY41: =IF(AE55<$G$282,0,MIN($G$279,1+IFERROR(INT((AE55-$G$282)/$G$284),0))) -> 6 | AZ41: =IF(AF55<$G$282,0,MIN($G$279,1+IFERROR(INT((AF55-$G$282)/$G$284),0))) -> 7 | BA41: =IF(AG55<$G$282,0,MIN($G$279,1+IFERROR(INT((AG55-$G$282)/$G$284),0))) -> 8 | BB41: =IF(AH55<$G$282,0,MIN($G$279,1+IFERROR(INT((AH55-$G$282)/$G$284),0))) -> 10
C42: =C41+$G$272 -> 0.45 | D42: {=IFERROR(IRR(IF($S$9:$X$9=0,$O16-$G$263,0)+IF($S$9:$X$9=$G$277,$G$268,0)+IF($S$9:$X$9=$G$278,Z16+$G$263-$O16-$G$268,0)),0)} -> 0.27940999 | E42: {=IFERROR(IRR(IF($S$9:$X$9=0,$O16-$G$263,0)+IF($S$9:$X$9=$G$277,$G$268,0)+IF($S$9:$X$9=$G$278,AA16+$G$263-$O16-$G$268,0)),0)} -> 0.28720895 | F42: {=IFERROR(IRR(IF($S$9:$X$9=0,$O16-$G$263,0)+IF($S$9:$X$9=$G$277,$G$268,0)+IF($S$9:$X$9=$G$278,AB16+$G$263-$O16-$G$268,0)),0)} -> 0.29482335 | G42: {=IFERROR(IRR(IF($S$9:$X$9=0,$O16-$G$263,0)+IF($S$9:$X$9=$G$277,$G$268,0)+IF($S$9:$X$9=$G$278,AC16+$G$263-$O16-$G$268,0)),0)} -> 0.30226274 | H42: {=IFERROR(IRR(IF($S$9:$X$9=0,$O16-$G$263,0)+IF($S$9:$X$9=$G$277,$G$268,0)+IF($S$9:$X$9=$G$278,AD16+$G$263-$O16-$G$268,0)),0)} -> 0.30953592 | I42: {=IFERROR(IRR(IF($S$9:$X$9=0,$O16-$G$263,0)+IF($S$9:$X$9=$G$277,$G$268,0)+IF($S$9:$X$9=$G$278,AE16+$G$263-$O16-$G$268,0)),0)} -> 0.31665102 | J42: {=IFERROR(IRR(IF($S$9:$X$9=0,$O16-$G$263,0)+IF($S$9:$X$9=$G$277,$G$268,0)+IF($S$9:$X$9=$G$278,AF16+$G$263-$O16-$G$268,0)),0)} -> 0.32361556 | K42: {=IFERROR(IRR(IF($S$9:$X$9=0,$O16-$G$263,0)+IF($S$9:$X$9=$G$277,$G$268,0)+IF($S$9:$X$9=$G$278,AG16+$G$263-$O16-$G$268,0)),0)} -> 0.33043654 | L42: {=IFERROR(IRR(IF($S$9:$X$9=0,$O16-$G$263,0)+IF($S$9:$X$9=$G$277,$G$268,0)+IF($S$9:$X$9=$G$278,AH16+$G$263-$O16-$G$268,0)),0)} -> 0.33712043 | AT42: =IF(Z56<$G$282,0,MIN($G$279,1+IFERROR(INT((Z56-$G$282)/$G$284),0))) -> 3 | AU42: =IF(AA56<$G$282,0,MIN($G$279,1+IFERROR(INT((AA56-$G$282)/$G$284),0))) -> 4 | AV42: =IF(AB56<$G$282,0,MIN($G$279,1+IFERROR(INT((AB56-$G$282)/$G$284),0))) -> 5 | AW42: =IF(AC56<$G$282,0,MIN($G$279,1+IFERROR(INT((AC56-$G$282)/$G$284),0))) -> 6 | AX42: =IF(AD56<$G$282,0,MIN($G$279,1+IFERROR(INT((AD56-$G$282)/$G$284),0))) -> 7 | AY42: =IF(AE56<$G$282,0,MIN($G$279,1+IFERROR(INT((AE56-$G$282)/$G$284),0))) -> 8 | AZ42: =IF(AF56<$G$282,0,MIN($G$279,1+IFERROR(INT((AF56-$G$282)/$G$284),0))) -> 9 | BA42: =IF(AG56<$G$282,0,MIN($G$279,1+IFERROR(INT((AG56-$G$282)/$G$284),0))) -> 10 | BB42: =IF(AH56<$G$282,0,MIN($G$279,1+IFERROR(INT((AH56-$G$282)/$G$284),0))) -> 10
B43: IRR on Ben's cash flows: Yr 0 = cash at close less Keystone value today; earnout in Yr 3; Yr 5 = stake value
B45: Ben's Return Profile Based on Partnerning - Less Standalone
B46: Ben's Net Returns vs. Standalone Based on Topkey Growth & Rollover %
D48: Topkey ex-Keystone Value Growth (%) | Z48: Helper: Unrounded Net Return vs. Standalone
D49: =E49-$G$274 -> 1 | E49: =F49-$G$274 -> 1.25 | F49: =G49-$G$274 -> 1.5 | G49: =H49-$G$274 -> 1.75 | H49: =$G$273 -> 2 | I49: =H49+$G$274 -> 2.25 | J49: =I49+$G$274 -> 2.5 | K49: =J49+$G$274 -> 2.75 | L49: =K49+$G$274 -> 3 | Z49: =D$9 -> 1 | AA49: =E$9 -> 1.25 | AB49: =F$9 -> 1.5 | AC49: =G$9 -> 1.75 | AD49: =H$9 -> 2 | AE49: =I$9 -> 2.25 | AF49: =J$9 -> 2.5 | AG49: =K$9 -> 2.75 | AH49: =L$9 -> 3 | AT49: Helper: Gradient Band (0 = below $1M hurdle)
B50: Ben's Rollover % | C50: =C51-$G$272 -> 0.15 | D50: =ROUND(Z50,$G$285) -> -1100 | E50: =ROUND(AA50,$G$285) -> -700 | F50: =ROUND(AB50,$G$285) -> -300 | G50: =ROUND(AC50,$G$285) -> 100 | H50: =ROUND(AD50,$G$285) -> 500 | I50: =ROUND(AE50,$G$285) -> 900 | J50: =ROUND(AF50,$G$285) -> 1300 | K50: =ROUND(AG50,$G$285) -> 1700 | L50: =ROUND(AH50,$G$285) -> 2100 | Z50: =Z10+$G$263-$G$280 -> -1074.8767 | AA50: =AA10+$G$263-$G$280 -> -673.9726 | AB50: =AB10+$G$263-$G$280 -> -273.06851 | AC50: =AC10+$G$263-$G$280 -> 127.83559 | AD50: =AD10+$G$263-$G$280 -> 528.73968 | AE50: =AE10+$G$263-$G$280 -> 929.64378 | AF50: =AF10+$G$263-$G$280 -> 1330.5479 | AG50: =AG10+$G$263-$G$280 -> 1731.452 | AH50: =AH10+$G$263-$G$280 -> 2132.3561 | AT50: =IF(Z50<$G$282,0,MIN($G$279,1+IFERROR(INT((Z50-$G$282)/$G$284),0))) -> 0 | AU50: =IF(AA50<$G$282,0,MIN($G$279,1+IFERROR(INT((AA50-$G$282)/$G$284),0))) -> 0 | AV50: =IF(AB50<$G$282,0,MIN($G$279,1+IFERROR(INT((AB50-$G$282)/$G$284),0))) -> 0 | AW50: =IF(AC50<$G$282,0,MIN($G$279,1+IFERROR(INT((AC50-$G$282)/$G$284),0))) -> 0 | AX50: =IF(AD50<$G$282,0,MIN($G$279,1+IFERROR(INT((AD50-$G$282)/$G$284),0))) -> 0 | AY50: =IF(AE50<$G$282,0,MIN($G$279,1+IFERROR(INT((AE50-$G$282)/$G$284),0))) -> 0 | AZ50: =IF(AF50<$G$282,0,MIN($G$279,1+IFERROR(INT((AF50-$G$282)/$G$284),0))) -> 2 | BA50: =IF(AG50<$G$282,0,MIN($G$279,1+IFERROR(INT((AG50-$G$282)/$G$284),0))) -> 3 | BB50: =IF(AH50<$G$282,0,MIN($G$279,1+IFERROR(INT((AH50-$G$282)/$G$284),0))) -> 5
C51: =C52-$G$272 -> 0.2 | D51: =ROUND(Z51,$G$285) -> -600 | E51: =ROUND(AA51,$G$285) -> -300 | F51: =ROUND(AB51,$G$285) -> 100 | G51: =ROUND(AC51,$G$285) -> 500 | H51: =ROUND(AD51,$G$285) -> 900 | I51: =ROUND(AE51,$G$285) -> 1300 | J51: =ROUND(AF51,$G$285) -> 1600 | K51: =ROUND(AG51,$G$285) -> 2000 | L51: =ROUND(AH51,$G$285) -> 2400 | Z51: =Z11+$G$263-$G$280 -> -639.78541 | AA51: =AA11+$G$263-$G$280 -> -261.53372 | AB51: =AB11+$G$263-$G$280 -> 116.71797 | AC51: =AC11+$G$263-$G$280 -> 494.96965 | AD51: =AD11+$G$263-$G$280 -> 873.22134 | AE51: =AE11+$G$263-$G$280 -> 1251.473 | AF51: =AF11+$G$263-$G$280 -> 1629.7247 | AG51: =AG11+$G$263-$G$280 -> 2007.9764 | AH51: =AH11+$G$263-$G$280 -> 2386.2281 | AT51: =IF(Z51<$G$282,0,MIN($G$279,1+IFERROR(INT((Z51-$G$282)/$G$284),0))) -> 0 | AU51: =IF(AA51<$G$282,0,MIN($G$279,1+IFERROR(INT((AA51-$G$282)/$G$284),0))) -> 0 | AV51: =IF(AB51<$G$282,0,MIN($G$279,1+IFERROR(INT((AB51-$G$282)/$G$284),0))) -> 0 | AW51: =IF(AC51<$G$282,0,MIN($G$279,1+IFERROR(INT((AC51-$G$282)/$G$284),0))) -> 0 | AX51: =IF(AD51<$G$282,0,MIN($G$279,1+IFERROR(INT((AD51-$G$282)/$G$284),0))) -> 0 | AY51: =IF(AE51<$G$282,0,MIN($G$279,1+IFERROR(INT((AE51-$G$282)/$G$284),0))) -> 1 | AZ51: =IF(AF51<$G$282,0,MIN($G$279,1+IFERROR(INT((AF51-$G$282)/$G$284),0))) -> 3 | BA51: =IF(AG51<$G$282,0,MIN($G$279,1+IFERROR(INT((AG51-$G$282)/$G$284),0))) -> 4 | BB51: =IF(AH51<$G$282,0,MIN($G$279,1+IFERROR(INT((AH51-$G$282)/$G$284),0))) -> 6
C52: =C53-$G$272 -> 0.25 | D52: =ROUND(Z52,$G$285) -> -200 | E52: =ROUND(AA52,$G$285) -> 200 | F52: =ROUND(AB52,$G$285) -> 500 | G52: =ROUND(AC52,$G$285) -> 900 | H52: =ROUND(AD52,$G$285) -> 1200 | I52: =ROUND(AE52,$G$285) -> 1600 | J52: =ROUND(AF52,$G$285) -> 1900 | K52: =ROUND(AG52,$G$285) -> 2300 | L52: =ROUND(AH52,$G$285) -> 2600 | Z52: =Z12+$G$263-$G$280 -> -203.48817 | AA52: =AA12+$G$263-$G$280 -> 151.99777 | AB52: =AB12+$G$263-$G$280 -> 507.48371 | AC52: =AC12+$G$263-$G$280 -> 862.96965 | AD52: =AD12+$G$263-$G$280 -> 1218.4556 | AE52: =AE12+$G$263-$G$280 -> 1573.9415 | AF52: =AF12+$G$263-$G$280 -> 1929.4275 | AG52: =AG12+$G$263-$G$280 -> 2284.9134 | AH52: =AH12+$G$263-$G$280 -> 2640.3994 | AT52: =IF(Z52<$G$282,0,MIN($G$279,1+IFERROR(INT((Z52-$G$282)/$G$284),0))) -> 0 | AU52: =IF(AA52<$G$282,0,MIN($G$279,1+IFERROR(INT((AA52-$G$282)/$G$284),0))) -> 0 | AV52: =IF(AB52<$G$282,0,MIN($G$279,1+IFERROR(INT((AB52-$G$282)/$G$284),0))) -> 0 | AW52: =IF(AC52<$G$282,0,MIN($G$279,1+IFERROR(INT((AC52-$G$282)/$G$284),0))) -> 0 | AX52: =IF(AD52<$G$282,0,MIN($G$279,1+IFERROR(INT((AD52-$G$282)/$G$284),0))) -> 1 | AY52: =IF(AE52<$G$282,0,MIN($G$279,1+IFERROR(INT((AE52-$G$282)/$G$284),0))) -> 3 | AZ52: =IF(AF52<$G$282,0,MIN($G$279,1+IFERROR(INT((AF52-$G$282)/$G$284),0))) -> 4 | BA52: =IF(AG52<$G$282,0,MIN($G$279,1+IFERROR(INT((AG52-$G$282)/$G$284),0))) -> 5 | BB52: =IF(AH52<$G$282,0,MIN($G$279,1+IFERROR(INT((AH52-$G$282)/$G$284),0))) -> 7
C53: =$G$271 -> 0.3 | D53: =ROUND(Z53,$G$285) -> 200 | E53: =ROUND(AA53,$G$285) -> 600 | F53: =ROUND(AB53,$G$285) -> 900 | G53: =ROUND(AC53,$G$285) -> 1200 | H53: =ROUND(AD53,$G$285) -> 1600 | I53: =ROUND(AE53,$G$285) -> 1900 | J53: =ROUND(AF53,$G$285) -> 2200 | K53: =ROUND(AG53,$G$285) -> 2600 | L53: =ROUND(AH53,$G$285) -> 2900 | Z53: =Z13+$G$263-$G$280 -> 234.02111 | AA53: =AA13+$G$263-$G$280 -> 566.6274 | AB53: =AB13+$G$263-$G$280 -> 899.23368 | AC53: =AC13+$G$263-$G$280 -> 1231.84 | AD53: =AD13+$G$263-$G$280 -> 1564.4463 | AE53: =AE13+$G$263-$G$280 -> 1897.0525 | AF53: =AF13+$G$263-$G$280 -> 2229.6588 | AG53: =AG13+$G$263-$G$280 -> 2562.2651 | AH53: =AH13+$G$263-$G$280 -> 2894.8714 | AT53: =IF(Z53<$G$282,0,MIN($G$279,1+IFERROR(INT((Z53-$G$282)/$G$284),0))) -> 0 | AU53: =IF(AA53<$G$282,0,MIN($G$279,1+IFERROR(INT((AA53-$G$282)/$G$284),0))) -> 0 | AV53: =IF(AB53<$G$282,0,MIN($G$279,1+IFERROR(INT((AB53-$G$282)/$G$284),0))) -> 0 | AW53: =IF(AC53<$G$282,0,MIN($G$279,1+IFERROR(INT((AC53-$G$282)/$G$284),0))) -> 1 | AX53: =IF(AD53<$G$282,0,MIN($G$279,1+IFERROR(INT((AD53-$G$282)/$G$284),0))) -> 3 | AY53: =IF(AE53<$G$282,0,MIN($G$279,1+IFERROR(INT((AE53-$G$282)/$G$284),0))) -> 4 | AZ53: =IF(AF53<$G$282,0,MIN($G$279,1+IFERROR(INT((AF53-$G$282)/$G$284),0))) -> 5 | BA53: =IF(AG53<$G$282,0,MIN($G$279,1+IFERROR(INT((AG53-$G$282)/$G$284),0))) -> 6 | BB53: =IF(AH53<$G$282,0,MIN($G$279,1+IFERROR(INT((AH53-$G$282)/$G$284),0))) -> 8
C54: =C53+$G$272 -> 0.35 | D54: =ROUND(Z54,$G$285) -> 700 | E54: =ROUND(AA54,$G$285) -> 1000 | F54: =ROUND(AB54,$G$285) -> 1300 | G54: =ROUND(AC54,$G$285) -> 1600 | H54: =ROUND(AD54,$G$285) -> 1900 | I54: =ROUND(AE54,$G$285) -> 2200 | J54: =ROUND(AF54,$G$285) -> 2500 | K54: =ROUND(AG54,$G$285) -> 2800 | L54: =ROUND(AH54,$G$285) -> 3100 | Z54: =Z14+$G$263-$G$280 -> 672.74859 | AA54: =AA14+$G$263-$G$280 -> 982.36073 | AB54: =AB14+$G$263-$G$280 -> 1291.9729 | AC54: =AC14+$G$263-$G$280 -> 1601.585 | AD54: =AD14+$G$263-$G$280 -> 1911.1971 | AE54: =AE14+$G$263-$G$280 -> 2220.8093 | AF54: =AF14+$G$263-$G$280 -> 2530.4214 | AG54: =AG14+$G$263-$G$280 -> 2840.0336 | AH54: =AH14+$G$263-$G$280 -> 3149.6457 | AT54: =IF(Z54<$G$282,0,MIN($G$279,1+IFERROR(INT((Z54-$G$282)/$G$284),0))) -> 0 | AU54: =IF(AA54<$G$282,0,MIN($G$279,1+IFERROR(INT((AA54-$G$282)/$G$284),0))) -> 0 | AV54: =IF(AB54<$G$282,0,MIN($G$279,1+IFERROR(INT((AB54-$G$282)/$G$284),0))) -> 2 | AW54: =IF(AC54<$G$282,0,MIN($G$279,1+IFERROR(INT((AC54-$G$282)/$G$284),0))) -> 3 | AX54: =IF(AD54<$G$282,0,MIN($G$279,1+IFERROR(INT((AD54-$G$282)/$G$284),0))) -> 4 | AY54: =IF(AE54<$G$282,0,MIN($G$279,1+IFERROR(INT((AE54-$G$282)/$G$284),0))) -> 5 | AZ54: =IF(AF54<$G$282,0,MIN($G$279,1+IFERROR(INT((AF54-$G$282)/$G$284),0))) -> 6 | BA54: =IF(AG54<$G$282,0,MIN($G$279,1+IFERROR(INT((AG54-$G$282)/$G$284),0))) -> 7 | BB54: =IF(AH54<$G$282,0,MIN($G$279,1+IFERROR(INT((AH54-$G$282)/$G$284),0))) -> 9
C55: =C54+$G$272 -> 0.4 | D55: =ROUND(Z55,$G$285) -> 1100 | E55: =ROUND(AA55,$G$285) -> 1400 | F55: =ROUND(AB55,$G$285) -> 1700 | G55: =ROUND(AC55,$G$285) -> 2000 | H55: =ROUND(AD55,$G$285) -> 2300 | I55: =ROUND(AE55,$G$285) -> 2500 | J55: =ROUND(AF55,$G$285) -> 2800 | K55: =ROUND(AG55,$G$285) -> 3100 | L55: =ROUND(AH55,$G$285) -> 3400 | Z55: =Z15+$G$263-$G$280 -> 1112.7004 | AA55: =AA15+$G$263-$G$280 -> 1399.2034 | AB55: =AB15+$G$263-$G$280 -> 1685.7063 | AC55: =AC15+$G$263-$G$280 -> 1972.2092 | AD55: =AD15+$G$263-$G$280 -> 2258.7121 | AE55: =AE15+$G$263-$G$280 -> 2545.2151 | AF55: =AF15+$G$263-$G$280 -> 2831.718 | AG55: =AG15+$G$263-$G$280 -> 3118.2209 | AH55: =AH15+$G$263-$G$280 -> 3404.7238 | AT55: =IF(Z55<$G$282,0,MIN($G$279,1+IFERROR(INT((Z55-$G$282)/$G$284),0))) -> 1 | AU55: =IF(AA55<$G$282,0,MIN($G$279,1+IFERROR(INT((AA55-$G$282)/$G$284),0))) -> 2 | AV55: =IF(AB55<$G$282,0,MIN($G$279,1+IFERROR(INT((AB55-$G$282)/$G$284),0))) -> 3 | AW55: =IF(AC55<$G$282,0,MIN($G$279,1+IFERROR(INT((AC55-$G$282)/$G$284),0))) -> 4 | AX55: =IF(AD55<$G$282,0,MIN($G$279,1+IFERROR(INT((AD55-$G$282)/$G$284),0))) -> 5 | AY55: =IF(AE55<$G$282,0,MIN($G$279,1+IFERROR(INT((AE55-$G$282)/$G$284),0))) -> 6 | AZ55: =IF(AF55<$G$282,0,MIN($G$279,1+IFERROR(INT((AF55-$G$282)/$G$284),0))) -> 7 | BA55: =IF(AG55<$G$282,0,MIN($G$279,1+IFERROR(INT((AG55-$G$282)/$G$284),0))) -> 8 | BB55: =IF(AH55<$G$282,0,MIN($G$279,1+IFERROR(INT((AH55-$G$282)/$G$284),0))) -> 10
C56: =C55+$G$272 -> 0.45 | D56: =ROUND(Z56,$G$285) -> 1600 | E56: =ROUND(AA56,$G$285) -> 1800 | F56: =ROUND(AB56,$G$285) -> 2100 | G56: =ROUND(AC56,$G$285) -> 2300 | H56: =ROUND(AD56,$G$285) -> 2600 | I56: =ROUND(AE56,$G$285) -> 2900 | J56: =ROUND(AF56,$G$285) -> 3100 | K56: =ROUND(AG56,$G$285) -> 3400 | L56: =ROUND(AH56,$G$285) -> 3700 | Z56: =Z16+$G$263-$G$280 -> 1553.8829 | AA56: =AA16+$G$263-$G$280 -> 1817.1609 | AB56: =AB16+$G$263-$G$280 -> 2080.439 | AC56: =AC16+$G$263-$G$280 -> 2343.717 | AD56: =AD16+$G$263-$G$280 -> 2606.9951 | AE56: =AE16+$G$263-$G$280 -> 2870.2731 | AF56: =AF16+$G$263-$G$280 -> 3133.5512 | AG56: =AG16+$G$263-$G$280 -> 3396.8293 | AH56: =AH16+$G$263-$G$280 -> 3660.1073 | AT56: =IF(Z56<$G$282,0,MIN($G$279,1+IFERROR(INT((Z56-$G$282)/$G$284),0))) -> 3 | AU56: =IF(AA56<$G$282,0,MIN($G$279,1+IFERROR(INT((AA56-$G$282)/$G$284),0))) -> 4 | AV56: =IF(AB56<$G$282,0,MIN($G$279,1+IFERROR(INT((AB56-$G$282)/$G$284),0))) -> 5 | AW56: =IF(AC56<$G$282,0,MIN($G$279,1+IFERROR(INT((AC56-$G$282)/$G$284),0))) -> 6 | AX56: =IF(AD56<$G$282,0,MIN($G$279,1+IFERROR(INT((AD56-$G$282)/$G$284),0))) -> 7 | AY56: =IF(AE56<$G$282,0,MIN($G$279,1+IFERROR(INT((AE56-$G$282)/$G$284),0))) -> 8 | AZ56: =IF(AF56<$G$282,0,MIN($G$279,1+IFERROR(INT((AF56-$G$282)/$G$284),0))) -> 9 | BA56: =IF(AG56<$G$282,0,MIN($G$279,1+IFERROR(INT((AG56-$G$282)/$G$284),0))) -> 10 | BB56: =IF(AH56<$G$282,0,MIN($G$279,1+IFERROR(INT((AH56-$G$282)/$G$284),0))) -> 10
B57: Ben's Year 5 partnership value less standalone Year 5 value (G280)
B59: Ben's % Return vs. Standalone Based on Topkey Growth & Rollover %
D61: Topkey ex-Keystone Value Growth (%)
D62: =E62-$G$274 -> 1 | E62: =F62-$G$274 -> 1.25 | F62: =G62-$G$274 -> 1.5 | G62: =H62-$G$274 -> 1.75 | H62: =$G$273 -> 2 | I62: =H62+$G$274 -> 2.25 | J62: =I62+$G$274 -> 2.5 | K62: =J62+$G$274 -> 2.75 | L62: =K62+$G$274 -> 3 | AT62: Helper: Gradient Band (0 = below $1M hurdle)
B63: Ben's Rollover % | C63: =C64-$G$272 -> 0.15 | D63: =IFERROR(Z50/$G$280,0) -> -0.1435033 | E63: =IFERROR(AA50/$G$280,0) -> -0.089979895 | F63: =IFERROR(AB50/$G$280,0) -> -0.03645649 | G63: =IFERROR(AC50/$G$280,0) -> 0.017066915 | H63: =IFERROR(AD50/$G$280,0) -> 0.07059032 | I63: =IFERROR(AE50/$G$280,0) -> 0.12411372 | J63: =IFERROR(AF50/$G$280,0) -> 0.17763713 | K63: =IFERROR(AG50/$G$280,0) -> 0.23116053 | L63: =IFERROR(AH50/$G$280,0) -> 0.28468394 | AT63: =IF(Z50<$G$282,0,MIN($G$279,1+IFERROR(INT((Z50-$G$282)/$G$284),0))) -> 0 | AU63: =IF(AA50<$G$282,0,MIN($G$279,1+IFERROR(INT((AA50-$G$282)/$G$284),0))) -> 0 | AV63: =IF(AB50<$G$282,0,MIN($G$279,1+IFERROR(INT((AB50-$G$282)/$G$284),0))) -> 0 | AW63: =IF(AC50<$G$282,0,MIN($G$279,1+IFERROR(INT((AC50-$G$282)/$G$284),0))) -> 0 | AX63: =IF(AD50<$G$282,0,MIN($G$279,1+IFERROR(INT((AD50-$G$282)/$G$284),0))) -> 0 | AY63: =IF(AE50<$G$282,0,MIN($G$279,1+IFERROR(INT((AE50-$G$282)/$G$284),0))) -> 0 | AZ63: =IF(AF50<$G$282,0,MIN($G$279,1+IFERROR(INT((AF50-$G$282)/$G$284),0))) -> 2 | BA63: =IF(AG50<$G$282,0,MIN($G$279,1+IFERROR(INT((AG50-$G$282)/$G$284),0))) -> 3 | BB63: =IF(AH50<$G$282,0,MIN($G$279,1+IFERROR(INT((AH50-$G$282)/$G$284),0))) -> 5
C64: =C65-$G$272 -> 0.2 | D64: =IFERROR(Z51/$G$280,0) -> -0.085415674 | E64: =IFERROR(AA51/$G$280,0) -> -0.034916519 | F64: =IFERROR(AB51/$G$280,0) -> 0.015582637 | G64: =IFERROR(AC51/$G$280,0) -> 0.066081792 | H64: =IFERROR(AD51/$G$280,0) -> 0.11658095 | I64: =IFERROR(AE51/$G$280,0) -> 0.1670801 | J64: =IFERROR(AF51/$G$280,0) -> 0.21757926 | K64: =IFERROR(AG51/$G$280,0) -> 0.26807841 | L64: =IFERROR(AH51/$G$280,0) -> 0.31857757 | AT64: =IF(Z51<$G$282,0,MIN($G$279,1+IFERROR(INT((Z51-$G$282)/$G$284),0))) -> 0 | AU64: =IF(AA51<$G$282,0,MIN($G$279,1+IFERROR(INT((AA51-$G$282)/$G$284),0))) -> 0 | AV64: =IF(AB51<$G$282,0,MIN($G$279,1+IFERROR(INT((AB51-$G$282)/$G$284),0))) -> 0 | AW64: =IF(AC51<$G$282,0,MIN($G$279,1+IFERROR(INT((AC51-$G$282)/$G$284),0))) -> 0 | AX64: =IF(AD51<$G$282,0,MIN($G$279,1+IFERROR(INT((AD51-$G$282)/$G$284),0))) -> 0 | AY64: =IF(AE51<$G$282,0,MIN($G$279,1+IFERROR(INT((AE51-$G$282)/$G$284),0))) -> 1 | AZ64: =IF(AF51<$G$282,0,MIN($G$279,1+IFERROR(INT((AF51-$G$282)/$G$284),0))) -> 3 | BA64: =IF(AG51<$G$282,0,MIN($G$279,1+IFERROR(INT((AG51-$G$282)/$G$284),0))) -> 4 | BB64: =IF(AH51<$G$282,0,MIN($G$279,1+IFERROR(INT((AH51-$G$282)/$G$284),0))) -> 6
C65: =C66-$G$272 -> 0.25 | D65: =IFERROR(Z52/$G$280,0) -> -0.027167046 | E65: =IFERROR(AA52/$G$280,0) -> 0.020292729 | F65: =IFERROR(AB52/$G$280,0) -> 0.067752504 | G65: =IFERROR(AC52/$G$280,0) -> 0.11521228 | H65: =IFERROR(AD52/$G$280,0) -> 0.16267205 | I65: =IFERROR(AE52/$G$280,0) -> 0.21013183 | J65: =IFERROR(AF52/$G$280,0) -> 0.2575916 | K65: =IFERROR(AG52/$G$280,0) -> 0.30505138 | L65: =IFERROR(AH52/$G$280,0) -> 0.35251115 | AT65: =IF(Z52<$G$282,0,MIN($G$279,1+IFERROR(INT((Z52-$G$282)/$G$284),0))) -> 0 | AU65: =IF(AA52<$G$282,0,MIN($G$279,1+IFERROR(INT((AA52-$G$282)/$G$284),0))) -> 0 | AV65: =IF(AB52<$G$282,0,MIN($G$279,1+IFERROR(INT((AB52-$G$282)/$G$284),0))) -> 0 | AW65: =IF(AC52<$G$282,0,MIN($G$279,1+IFERROR(INT((AC52-$G$282)/$G$284),0))) -> 0 | AX65: =IF(AD52<$G$282,0,MIN($G$279,1+IFERROR(INT((AD52-$G$282)/$G$284),0))) -> 1 | AY65: =IF(AE52<$G$282,0,MIN($G$279,1+IFERROR(INT((AE52-$G$282)/$G$284),0))) -> 3 | AZ65: =IF(AF52<$G$282,0,MIN($G$279,1+IFERROR(INT((AF52-$G$282)/$G$284),0))) -> 4 | BA65: =IF(AG52<$G$282,0,MIN($G$279,1+IFERROR(INT((AG52-$G$282)/$G$284),0))) -> 5 | BB65: =IF(AH52<$G$282,0,MIN($G$279,1+IFERROR(INT((AH52-$G$282)/$G$284),0))) -> 7
C66: =$G$271 -> 0.3 | D66: =IFERROR(Z53/$G$280,0) -> 0.031243399 | E66: =IFERROR(AA53/$G$280,0) -> 0.075648585 | F66: =IFERROR(AB53/$G$280,0) -> 0.12005377 | G66: =IFERROR(AC53/$G$280,0) -> 0.16445896 | H66: =IFERROR(AD53/$G$280,0) -> 0.20886414 | I66: =IFERROR(AE53/$G$280,0) -> 0.25326933 | J66: =IFERROR(AF53/$G$280,0) -> 0.29767451 | K66: =IFERROR(AG53/$G$280,0) -> 0.3420797 | L66: =IFERROR(AH53/$G$280,0) -> 0.38648489 | AT66: =IF(Z53<$G$282,0,MIN($G$279,1+IFERROR(INT((Z53-$G$282)/$G$284),0))) -> 0 | AU66: =IF(AA53<$G$282,0,MIN($G$279,1+IFERROR(INT((AA53-$G$282)/$G$284),0))) -> 0 | AV66: =IF(AB53<$G$282,0,MIN($G$279,1+IFERROR(INT((AB53-$G$282)/$G$284),0))) -> 0 | AW66: =IF(AC53<$G$282,0,MIN($G$279,1+IFERROR(INT((AC53-$G$282)/$G$284),0))) -> 1 | AX66: =IF(AD53<$G$282,0,MIN($G$279,1+IFERROR(INT((AD53-$G$282)/$G$284),0))) -> 3 | AY66: =IF(AE53<$G$282,0,MIN($G$279,1+IFERROR(INT((AE53-$G$282)/$G$284),0))) -> 4 | AZ66: =IF(AF53<$G$282,0,MIN($G$279,1+IFERROR(INT((AF53-$G$282)/$G$284),0))) -> 5 | BA66: =IF(AG53<$G$282,0,MIN($G$279,1+IFERROR(INT((AG53-$G$282)/$G$284),0))) -> 6 | BB66: =IF(AH53<$G$282,0,MIN($G$279,1+IFERROR(INT((AH53-$G$282)/$G$284),0))) -> 8
C67: =C66+$G$272 -> 0.35 | D67: =IFERROR(Z54/$G$280,0) -> 0.089816481 | E67: =IFERROR(AA54/$G$280,0) -> 0.13115179 | F67: =IFERROR(AB54/$G$280,0) -> 0.17248711 | G67: =IFERROR(AC54/$G$280,0) -> 0.21382242 | H67: =IFERROR(AD54/$G$280,0) -> 0.25515773 | I67: =IFERROR(AE54/$G$280,0) -> 0.29649304 | J67: =IFERROR(AF54/$G$280,0) -> 0.33782835 | K67: =IFERROR(AG54/$G$280,0) -> 0.37916367 | L67: =IFERROR(AH54/$G$280,0) -> 0.42049898 | AT67: =IF(Z54<$G$282,0,MIN($G$279,1+IFERROR(INT((Z54-$G$282)/$G$284),0))) -> 0 | AU67: =IF(AA54<$G$282,0,MIN($G$279,1+IFERROR(INT((AA54-$G$282)/$G$284),0))) -> 0 | AV67: =IF(AB54<$G$282,0,MIN($G$279,1+IFERROR(INT((AB54-$G$282)/$G$284),0))) -> 2 | AW67: =IF(AC54<$G$282,0,MIN($G$279,1+IFERROR(INT((AC54-$G$282)/$G$284),0))) -> 3 | AX67: =IF(AD54<$G$282,0,MIN($G$279,1+IFERROR(INT((AD54-$G$282)/$G$284),0))) -> 4 | AY67: =IF(AE54<$G$282,0,MIN($G$279,1+IFERROR(INT((AE54-$G$282)/$G$284),0))) -> 5 | AZ67: =IF(AF54<$G$282,0,MIN($G$279,1+IFERROR(INT((AF54-$G$282)/$G$284),0))) -> 6 | BA67: =IF(AG54<$G$282,0,MIN($G$279,1+IFERROR(INT((AG54-$G$282)/$G$284),0))) -> 7 | BB67: =IF(AH54<$G$282,0,MIN($G$279,1+IFERROR(INT((AH54-$G$282)/$G$284),0))) -> 9
C68: =C67+$G$272 -> 0.4 | D68: =IFERROR(Z55/$G$280,0) -> 0.14855302 | E68: =IFERROR(AA55/$G$280,0) -> 0.1868031 | F68: =IFERROR(AB55/$G$280,0) -> 0.22505318 | G68: =IFERROR(AC55/$G$280,0) -> 0.26330325 | H68: =IFERROR(AD55/$G$280,0) -> 0.30155333 | I68: =IFERROR(AE55/$G$280,0) -> 0.3398034 | J68: =IFERROR(AF55/$G$280,0) -> 0.37805348 | K68: =IFERROR(AG55/$G$280,0) -> 0.41630355 | L68: =IFERROR(AH55/$G$280,0) -> 0.45455363 | AT68: =IF(Z55<$G$282,0,MIN($G$279,1+IFERROR(INT((Z55-$G$282)/$G$284),0))) -> 1 | AU68: =IF(AA55<$G$282,0,MIN($G$279,1+IFERROR(INT((AA55-$G$282)/$G$284),0))) -> 2 | AV68: =IF(AB55<$G$282,0,MIN($G$279,1+IFERROR(INT((AB55-$G$282)/$G$284),0))) -> 3 | AW68: =IF(AC55<$G$282,0,MIN($G$279,1+IFERROR(INT((AC55-$G$282)/$G$284),0))) -> 4 | AX68: =IF(AD55<$G$282,0,MIN($G$279,1+IFERROR(INT((AD55-$G$282)/$G$284),0))) -> 5 | AY68: =IF(AE55<$G$282,0,MIN($G$279,1+IFERROR(INT((AE55-$G$282)/$G$284),0))) -> 6 | AZ68: =IF(AF55<$G$282,0,MIN($G$279,1+IFERROR(INT((AF55-$G$282)/$G$284),0))) -> 7 | BA68: =IF(AG55<$G$282,0,MIN($G$279,1+IFERROR(INT((AG55-$G$282)/$G$284),0))) -> 8 | BB68: =IF(AH55<$G$282,0,MIN($G$279,1+IFERROR(INT((AH55-$G$282)/$G$284),0))) -> 10
C69: =C68+$G$272 -> 0.45 | D69: =IFERROR(Z56/$G$280,0) -> 0.20745386 | E69: =IFERROR(AA56/$G$280,0) -> 0.24260326 | F69: =IFERROR(AB56/$G$280,0) -> 0.27775266 | G69: =IFERROR(AC56/$G$280,0) -> 0.31290206 | H69: =IFERROR(AD56/$G$280,0) -> 0.34805145 | I69: =IFERROR(AE56/$G$280,0) -> 0.38320085 | J69: =IFERROR(AF56/$G$280,0) -> 0.41835025 | K69: =IFERROR(AG56/$G$280,0) -> 0.45349965 | L69: =IFERROR(AH56/$G$280,0) -> 0.48864905 | AT69: =IF(Z56<$G$282,0,MIN($G$279,1+IFERROR(INT((Z56-$G$282)/$G$284),0))) -> 3 | AU69: =IF(AA56<$G$282,0,MIN($G$279,1+IFERROR(INT((AA56-$G$282)/$G$284),0))) -> 4 | AV69: =IF(AB56<$G$282,0,MIN($G$279,1+IFERROR(INT((AB56-$G$282)/$G$284),0))) -> 5 | AW69: =IF(AC56<$G$282,0,MIN($G$279,1+IFERROR(INT((AC56-$G$282)/$G$284),0))) -> 6 | AX69: =IF(AD56<$G$282,0,MIN($G$279,1+IFERROR(INT((AD56-$G$282)/$G$284),0))) -> 7 | AY69: =IF(AE56<$G$282,0,MIN($G$279,1+IFERROR(INT((AE56-$G$282)/$G$284),0))) -> 8 | AZ69: =IF(AF56<$G$282,0,MIN($G$279,1+IFERROR(INT((AF56-$G$282)/$G$284),0))) -> 9 | BA69: =IF(AG56<$G$282,0,MIN($G$279,1+IFERROR(INT((AG56-$G$282)/$G$284),0))) -> 10 | BB69: =IF(AH56<$G$282,0,MIN($G$279,1+IFERROR(INT((AH56-$G$282)/$G$284),0))) -> 10
B70: Ben's Year 5 partnership value ÷ standalone Year 5 value (G280), less 1
B72: Ben's IRR Premium vs. Standalone Based on Topkey Growth & Rollover %
D74: Topkey ex-Keystone Value Growth (%)
D75: =E75-$G$274 -> 1 | E75: =F75-$G$274 -> 1.25 | F75: =G75-$G$274 -> 1.5 | G75: =H75-$G$274 -> 1.75 | H75: =$G$273 -> 2 | I75: =H75+$G$274 -> 2.25 | J75: =I75+$G$274 -> 2.5 | K75: =J75+$G$274 -> 2.75 | L75: =K75+$G$274 -> 3 | AT75: Helper: Gradient Band (0 = below $1M hurdle)
B76: Ben's Rollover % | C76: =C77-$G$272 -> 0.15 | D76: =D36-$G$281 -> 0.0045980604 | E76: =E36-$G$281 -> 0.021307365 | F76: =F36-$G$281 -> 0.037149865 | G76: =G36-$G$281 -> 0.052220609 | H76: =H36-$G$281 -> 0.066599357 | I76: =I36-$G$281 -> 0.080353741 | J76: =J36-$G$281 -> 0.093541636 | K76: =K36-$G$281 -> 0.10621298 | L76: =L36-$G$281 -> 0.11841118 | AT76: =IF(Z50<$G$282,0,MIN($G$279,1+IFERROR(INT((Z50-$G$282)/$G$284),0))) -> 0 | AU76: =IF(AA50<$G$282,0,MIN($G$279,1+IFERROR(INT((AA50-$G$282)/$G$284),0))) -> 0 | AV76: =IF(AB50<$G$282,0,MIN($G$279,1+IFERROR(INT((AB50-$G$282)/$G$284),0))) -> 0 | AW76: =IF(AC50<$G$282,0,MIN($G$279,1+IFERROR(INT((AC50-$G$282)/$G$284),0))) -> 0 | AX76: =IF(AD50<$G$282,0,MIN($G$279,1+IFERROR(INT((AD50-$G$282)/$G$284),0))) -> 0 | AY76: =IF(AE50<$G$282,0,MIN($G$279,1+IFERROR(INT((AE50-$G$282)/$G$284),0))) -> 0 | AZ76: =IF(AF50<$G$282,0,MIN($G$279,1+IFERROR(INT((AF50-$G$282)/$G$284),0))) -> 2 | BA76: =IF(AG50<$G$282,0,MIN($G$279,1+IFERROR(INT((AG50-$G$282)/$G$284),0))) -> 3 | BB76: =IF(AH50<$G$282,0,MIN($G$279,1+IFERROR(INT((AH50-$G$282)/$G$284),0))) -> 5
C77: =C78-$G$272 -> 0.2 | D77: =D37-$G$281 -> 0.019476287 | E77: =E37-$G$281 -> 0.034229971 | F77: =F37-$G$281 -> 0.048310602 | G77: =G37-$G$281 -> 0.061783558 | H77: =H37-$G$281 -> 0.074704839 | I77: =I37-$G$281 -> 0.087122809 | J77: =J37-$G$281 -> 0.09907954 | K77: =K37-$G$281 -> 0.11061187 | L77: =L37-$G$281 -> 0.12175227 | AT77: =IF(Z51<$G$282,0,MIN($G$279,1+IFERROR(INT((Z51-$G$282)/$G$284),0))) -> 0 | AU77: =IF(AA51<$G$282,0,MIN($G$279,1+IFERROR(INT((AA51-$G$282)/$G$284),0))) -> 0 | AV77: =IF(AB51<$G$282,0,MIN($G$279,1+IFERROR(INT((AB51-$G$282)/$G$284),0))) -> 0 | AW77: =IF(AC51<$G$282,0,MIN($G$279,1+IFERROR(INT((AC51-$G$282)/$G$284),0))) -> 0 | AX77: =IF(AD51<$G$282,0,MIN($G$279,1+IFERROR(INT((AD51-$G$282)/$G$284),0))) -> 0 | AY77: =IF(AE51<$G$282,0,MIN($G$279,1+IFERROR(INT((AE51-$G$282)/$G$284),0))) -> 1 | AZ77: =IF(AF51<$G$282,0,MIN($G$279,1+IFERROR(INT((AF51-$G$282)/$G$284),0))) -> 3 | BA77: =IF(AG51<$G$282,0,MIN($G$279,1+IFERROR(INT((AG51-$G$282)/$G$284),0))) -> 4 | BB77: =IF(AH51<$G$282,0,MIN($G$279,1+IFERROR(INT((AH51-$G$282)/$G$284),0))) -> 6
C78: =C79-$G$272 -> 0.25 | D78: =D38-$G$281 -> 0.033148224 | E78: =E38-$G$281 -> 0.046182034 | F78: =F38-$G$281 -> 0.058692655 | G78: =G38-$G$281 -> 0.07072509 | H78: =H38-$G$281 -> 0.082318599 | I78: =I38-$G$281 -> 0.09350764 | J78: =J38-$G$281 -> 0.10432264 | K78: =K38-$G$281 -> 0.11479062 | L78: =L38-$G$281 -> 0.12493565 | AT78: =IF(Z52<$G$282,0,MIN($G$279,1+IFERROR(INT((Z52-$G$282)/$G$284),0))) -> 0 | AU78: =IF(AA52<$G$282,0,MIN($G$279,1+IFERROR(INT((AA52-$G$282)/$G$284),0))) -> 0 | AV78: =IF(AB52<$G$282,0,MIN($G$279,1+IFERROR(INT((AB52-$G$282)/$G$284),0))) -> 0 | AW78: =IF(AC52<$G$282,0,MIN($G$279,1+IFERROR(INT((AC52-$G$282)/$G$284),0))) -> 0 | AX78: =IF(AD52<$G$282,0,MIN($G$279,1+IFERROR(INT((AD52-$G$282)/$G$284),0))) -> 1 | AY78: =IF(AE52<$G$282,0,MIN($G$279,1+IFERROR(INT((AE52-$G$282)/$G$284),0))) -> 3 | AZ78: =IF(AF52<$G$282,0,MIN($G$279,1+IFERROR(INT((AF52-$G$282)/$G$284),0))) -> 4 | BA78: =IF(AG52<$G$282,0,MIN($G$279,1+IFERROR(INT((AG52-$G$282)/$G$284),0))) -> 5 | BB78: =IF(AH52<$G$282,0,MIN($G$279,1+IFERROR(INT((AH52-$G$282)/$G$284),0))) -> 7
C79: =$G$271 -> 0.3 | D79: =D39-$G$281 -> 0.045775545 | E79: =E39-$G$281 -> 0.0572831 | F79: =F39-$G$281 -> 0.068384408 | G79: =G39-$G$281 -> 0.079110379 | H79: =H39-$G$281 -> 0.089488411 | I79: =I39-$G$281 -> 0.099542915 | J79: =J39-$G$281 -> 0.10929573 | K79: =K39-$G$281 -> 0.1187665 | L79: =L39-$G$281 -> 0.12797294 | AT79: =IF(Z53<$G$282,0,MIN($G$279,1+IFERROR(INT((Z53-$G$282)/$G$284),0))) -> 0 | AU79: =IF(AA53<$G$282,0,MIN($G$279,1+IFERROR(INT((AA53-$G$282)/$G$284),0))) -> 0 | AV79: =IF(AB53<$G$282,0,MIN($G$279,1+IFERROR(INT((AB53-$G$282)/$G$284),0))) -> 0 | AW79: =IF(AC53<$G$282,0,MIN($G$279,1+IFERROR(INT((AC53-$G$282)/$G$284),0))) -> 1 | AX79: =IF(AD53<$G$282,0,MIN($G$279,1+IFERROR(INT((AD53-$G$282)/$G$284),0))) -> 3 | AY79: =IF(AE53<$G$282,0,MIN($G$279,1+IFERROR(INT((AE53-$G$282)/$G$284),0))) -> 4 | AZ79: =IF(AF53<$G$282,0,MIN($G$279,1+IFERROR(INT((AF53-$G$282)/$G$284),0))) -> 5 | BA79: =IF(AG53<$G$282,0,MIN($G$279,1+IFERROR(INT((AG53-$G$282)/$G$284),0))) -> 6 | BB79: =IF(AH53<$G$282,0,MIN($G$279,1+IFERROR(INT((AH53-$G$282)/$G$284),0))) -> 8
C80: =C79+$G$272 -> 0.35 | D80: =D40-$G$281 -> 0.057490009 | E80: =E40-$G$281 -> 0.06763245 | F80: =F40-$G$281 -> 0.077460504 | G80: =G40-$G$281 -> 0.086995281 | H80: =H40-$G$281 -> 0.096255768 | I80: =I40-$G$281 -> 0.1052591 | J80: =J40-$G$281 -> 0.11402082 | K80: =K40-$G$281 -> 0.12255503 | L80: =L40-$G$281 -> 0.13087461 | AT80: =IF(Z54<$G$282,0,MIN($G$279,1+IFERROR(INT((Z54-$G$282)/$G$284),0))) -> 0 | AU80: =IF(AA54<$G$282,0,MIN($G$279,1+IFERROR(INT((AA54-$G$282)/$G$284),0))) -> 0 | AV80: =IF(AB54<$G$282,0,MIN($G$279,1+IFERROR(INT((AB54-$G$282)/$G$284),0))) -> 2 | AW80: =IF(AC54<$G$282,0,MIN($G$279,1+IFERROR(INT((AC54-$G$282)/$G$284),0))) -> 3 | AX80: =IF(AD54<$G$282,0,MIN($G$279,1+IFERROR(INT((AD54-$G$282)/$G$284),0))) -> 4 | AY80: =IF(AE54<$G$282,0,MIN($G$279,1+IFERROR(INT((AE54-$G$282)/$G$284),0))) -> 5 | AZ80: =IF(AF54<$G$282,0,MIN($G$279,1+IFERROR(INT((AF54-$G$282)/$G$284),0))) -> 6 | BA80: =IF(AG54<$G$282,0,MIN($G$279,1+IFERROR(INT((AG54-$G$282)/$G$284),0))) -> 7 | BB80: =IF(AH54<$G$282,0,MIN($G$279,1+IFERROR(INT((AH54-$G$282)/$G$284),0))) -> 9
C81: =C80+$G$272 -> 0.4 | D81: =D41-$G$281 -> 0.06840044 | E81: =E41-$G$281 -> 0.077313438 | F81: =F41-$G$281 -> 0.085984536 | G81: =G41-$G$281 -> 0.094428023 | H81: =H41-$G$281 -> 0.10265692 | I81: =I41-$G$281 -> 0.11068311 | J81: =J41-$G$281 -> 0.1185175 | K81: =K41-$G$281 -> 0.12617011 | L81: =L41-$G$281 -> 0.13365016 | AT81: =IF(Z55<$G$282,0,MIN($G$279,1+IFERROR(INT((Z55-$G$282)/$G$284),0))) -> 1 | AU81: =IF(AA55<$G$282,0,MIN($G$279,1+IFERROR(INT((AA55-$G$282)/$G$284),0))) -> 2 | AV81: =IF(AB55<$G$282,0,MIN($G$279,1+IFERROR(INT((AB55-$G$282)/$G$284),0))) -> 3 | AW81: =IF(AC55<$G$282,0,MIN($G$279,1+IFERROR(INT((AC55-$G$282)/$G$284),0))) -> 4 | AX81: =IF(AD55<$G$282,0,MIN($G$279,1+IFERROR(INT((AD55-$G$282)/$G$284),0))) -> 5 | AY81: =IF(AE55<$G$282,0,MIN($G$279,1+IFERROR(INT((AE55-$G$282)/$G$284),0))) -> 6 | AZ81: =IF(AF55<$G$282,0,MIN($G$279,1+IFERROR(INT((AF55-$G$282)/$G$284),0))) -> 7 | BA81: =IF(AG55<$G$282,0,MIN($G$279,1+IFERROR(INT((AG55-$G$282)/$G$284),0))) -> 8 | BB81: =IF(AH55<$G$282,0,MIN($G$279,1+IFERROR(INT((AH55-$G$282)/$G$284),0))) -> 10
C82: =C81+$G$272 -> 0.45 | D82: =D42-$G$281 -> 0.078597768 | E82: =E42-$G$281 -> 0.086396721 | F82: =F42-$G$281 -> 0.094011121 | G82: =G42-$G$281 -> 0.10145051 | H82: =H42-$G$281 -> 0.10872369 | I82: =I42-$G$281 -> 0.11583879 | J82: =J42-$G$281 -> 0.12280334 | K82: =K42-$G$281 -> 0.12962431 | L82: =L42-$G$281 -> 0.13630821 | AT82: =IF(Z56<$G$282,0,MIN($G$279,1+IFERROR(INT((Z56-$G$282)/$G$284),0))) -> 3 | AU82: =IF(AA56<$G$282,0,MIN($G$279,1+IFERROR(INT((AA56-$G$282)/$G$284),0))) -> 4 | AV82: =IF(AB56<$G$282,0,MIN($G$279,1+IFERROR(INT((AB56-$G$282)/$G$284),0))) -> 5 | AW82: =IF(AC56<$G$282,0,MIN($G$279,1+IFERROR(INT((AC56-$G$282)/$G$284),0))) -> 6 | AX82: =IF(AD56<$G$282,0,MIN($G$279,1+IFERROR(INT((AD56-$G$282)/$G$284),0))) -> 7 | AY82: =IF(AE56<$G$282,0,MIN($G$279,1+IFERROR(INT((AE56-$G$282)/$G$284),0))) -> 8 | AZ82: =IF(AF56<$G$282,0,MIN($G$279,1+IFERROR(INT((AF56-$G$282)/$G$284),0))) -> 9 | BA82: =IF(AG56<$G$282,0,MIN($G$279,1+IFERROR(INT((AG56-$G$282)/$G$284),0))) -> 10 | BB82: =IF(AH56<$G$282,0,MIN($G$279,1+IFERROR(INT((AH56-$G$282)/$G$284),0))) -> 10
B83: Partnership IRR (table above) less standalone IRR (G281), in percentage points
B85: Ben's Return Profile Based on Partnering — Net Client Wins
B86: Ben's Net Returns Based on Net Client Wins & Rollover %
D88: Keystone Total Annual Net Client Wins — Partnership (#) | Z88: Helper: Unrounded Net Return — Net Client Wins | AJ88: Helper: Keystone EV Yr 5 by Net Client Wins
D89: =E89+$G$291 -> 64 | E89: =F89+$G$291 -> 60 | F89: =G89+$G$291 -> 56 | G89: =H89+$G$291 -> 52 | H89: =$G$290 -> 48 | I89: =H89-$G$291 -> 44 | J89: =I89-$G$291 -> 40 | K89: =J89-$G$291 -> 36 | L89: =K89-$G$291 -> 32 | N89: Helper: Rollover % | O89: Helper: Cash at Close | P89: Helper: Topkey Equity Issued | Q89: Helper: Topkey ex-Keystone Today | R89: Helper: Ben's Yr 5 Topkey % | Z89: =D$89 -> 64 | AA89: =E$89 -> 60 | AB89: =F$89 -> 56 | AC89: =G$89 -> 52 | AD89: =H$89 -> 48 | AE89: =I$89 -> 44 | AF89: =J$89 -> 40 | AG89: =K$89 -> 36 | AH89: =L$89 -> 32 | AJ89: =D$89 -> 64 | AK89: =E$89 -> 60 | AL89: =F$89 -> 56 | AM89: =G$89 -> 52 | AN89: =H$89 -> 48 | AO89: =I$89 -> 44 | AP89: =J$89 -> 40 | AQ89: =K$89 -> 36 | AR89: =L$89 -> 32 | AT89: Helper: Gradient Band (0 = below $1M hurdle)
B90: Ben's Rollover % | C90: =C91-$G$272 -> 0.15 | D90: =ROUND(Z90,$G$285) -> 5500 | E90: =ROUND(AA90,$G$285) -> 5400 | F90: =ROUND(AB90,$G$285) -> 5300 | G90: =ROUND(AC90,$G$285) -> 5200 | H90: =ROUND(AD90,$G$285) -> 5100 | I90: =ROUND(AE90,$G$285) -> 4900 | J90: =ROUND(AF90,$G$285) -> 4800 | K90: =ROUND(AG90,$G$285) -> 4700 | L90: =ROUND(AH90,$G$285) -> 4600 | N90: =$C90 -> 0.15 | O90: =$G$263*(1-N90)*$G$266 -> 789.28571 | P90: =$G$263*(1-N90)-O90 -> 1760.7143 | Q90: =$G$265-O90 -> 59210.714 | R90: =IFERROR(P90/(Q90+$G$263*(1-N90)),0)*(1-$G$267) -> 0.027083213 | Z90: =$O90+$G$268+$N90*AJ$90+$R90*($Q90*(1+$G$270)+AJ$90*(1-$N90))-$G$263 -> 5514.5373 | AA90: =$O90+$G$268+$N90*AK$90+$R90*($Q90*(1+$G$270)+AK$90*(1-$N90))-$G$263 -> 5399.4337 | AB90: =$O90+$G$268+$N90*AL$90+$R90*($Q90*(1+$G$270)+AL$90*(1-$N90))-$G$263 -> 5284.3301 | AC90: =$O90+$G$268+$N90*AM$90+$R90*($Q90*(1+$G$270)+AM$90*(1-$N90))-$G$263 -> 5169.2265 | AD90: =$O90+$G$268+$N90*AN$90+$R90*($Q90*(1+$G$270)+AN$90*(1-$N90))-$G$263 -> 5054.1229 | AE90: =$O90+$G$268+$N90*AO$90+$R90*($Q90*(1+$G$270)+AO$90*(1-$N90))-$G$263 -> 4939.0193 | AF90: =$O90+$G$268+$N90*AP$90+$R90*($Q90*(1+$G$270)+AP$90*(1-$N90))-$G$263 -> 4823.9158 | AG90: =$O90+$G$268+$N90*AQ$90+$R90*($Q90*(1+$G$270)+AQ$90*(1-$N90))-$G$263 -> 4708.8122 | AH90: =$O90+$G$268+$N90*AR$90+$R90*($Q90*(1+$G$270)+AR$90*(1-$N90))-$G$263 -> 4593.7086 | AJ90: =($G$286+AJ$89*$G$278*$G$287)*$G$288 -> 16641.225 | AK90: =($G$286+AK$89*$G$278*$G$287)*$G$288 -> 15975.966 | AL90: =($G$286+AL$89*$G$278*$G$287)*$G$288 -> 15310.707 | AM90: =($G$286+AM$89*$G$278*$G$287)*$G$288 -> 14645.448 | AN90: =($G$286+AN$89*$G$278*$G$287)*$G$288 -> 13980.189 | AO90: =($G$286+AO$89*$G$278*$G$287)*$G$288 -> 13314.93 | AP90: =($G$286+AP$89*$G$278*$G$287)*$G$288 -> 12649.671 | AQ90: =($G$286+AQ$89*$G$278*$G$287)*$G$288 -> 11984.412 | AR90: =($G$286+AR$89*$G$278*$G$287)*$G$288 -> 11319.153 | AT90: =IF(Z130<$G$282,0,MIN($G$279,1+IFERROR(INT((Z130-$G$282)/$G$296),0))) -> 0 | AU90: =IF(AA130<$G$282,0,MIN($G$279,1+IFERROR(INT((AA130-$G$282)/$G$296),0))) -> 0 | AV90: =IF(AB130<$G$282,0,MIN($G$279,1+IFERROR(INT((AB130-$G$282)/$G$296),0))) -> 0 | AW90: =IF(AC130<$G$282,0,MIN($G$279,1+IFERROR(INT((AC130-$G$282)/$G$296),0))) -> 0 | AX90: =IF(AD130<$G$282,0,MIN($G$279,1+IFERROR(INT((AD130-$G$282)/$G$296),0))) -> 0 | AY90: =IF(AE130<$G$282,0,MIN($G$279,1+IFERROR(INT((AE130-$G$282)/$G$296),0))) -> 0 | AZ90: =IF(AF130<$G$282,0,MIN($G$279,1+IFERROR(INT((AF130-$G$282)/$G$296),0))) -> 1 | BA90: =IF(AG130<$G$282,0,MIN($G$279,1+IFERROR(INT((AG130-$G$282)/$G$296),0))) -> 3 | BB90: =IF(AH130<$G$282,0,MIN($G$279,1+IFERROR(INT((AH130-$G$282)/$G$296),0))) -> 4
C91: =C92-$G$272 -> 0.2 | D91: =ROUND(Z91,$G$285) -> 6000 | E91: =ROUND(AA91,$G$285) -> 5800 | F91: =ROUND(AB91,$G$285) -> 5700 | G91: =ROUND(AC91,$G$285) -> 5500 | H91: =ROUND(AD91,$G$285) -> 5400 | I91: =ROUND(AE91,$G$285) -> 5200 | J91: =ROUND(AF91,$G$285) -> 5100 | K91: =ROUND(AG91,$G$285) -> 5000 | L91: =ROUND(AH91,$G$285) -> 4800 | N91: =$C91 -> 0.2 | O91: =$G$263*(1-N91)*$G$266 -> 742.85714 | P91: =$G$263*(1-N91)-O91 -> 1657.1429 | Q91: =$G$265-O91 -> 59257.143 | R91: =IFERROR(P91/(Q91+$G$263*(1-N91)),0)*(1-$G$267) -> 0.025532901 | Z91: =$O91+$G$268+$N91*AJ$90+$R91*($Q91*(1+$G$270)+AJ$90*(1-$N91))-$G$263 -> 5983.1822 | AA91: =$O91+$G$268+$N91*AK$90+$R91*($Q91*(1+$G$270)+AK$90*(1-$N91))-$G$263 -> 5836.5416 | AB91: =$O91+$G$268+$N91*AL$90+$R91*($Q91*(1+$G$270)+AL$90*(1-$N91))-$G$263 -> 5689.901 | AC91: =$O91+$G$268+$N91*AM$90+$R91*($Q91*(1+$G$270)+AM$90*(1-$N91))-$G$263 -> 5543.2605 | AD91: =$O91+$G$268+$N91*AN$90+$R91*($Q91*(1+$G$270)+AN$90*(1-$N91))-$G$263 -> 5396.6199 | AE91: =$O91+$G$268+$N91*AO$90+$R91*($Q91*(1+$G$270)+AO$90*(1-$N91))-$G$263 -> 5249.9793 | AF91: =$O91+$G$268+$N91*AP$90+$R91*($Q91*(1+$G$270)+AP$90*(1-$N91))-$G$263 -> 5103.3387 | AG91: =$O91+$G$268+$N91*AQ$90+$R91*($Q91*(1+$G$270)+AQ$90*(1-$N91))-$G$263 -> 4956.6982 | AH91: =$O91+$G$268+$N91*AR$90+$R91*($Q91*(1+$G$270)+AR$90*(1-$N91))-$G$263 -> 4810.0576 | AT91: =IF(Z131<$G$282,0,MIN($G$279,1+IFERROR(INT((Z131-$G$282)/$G$296),0))) -> 0 | AU91: =IF(AA131<$G$282,0,MIN($G$279,1+IFERROR(INT((AA131-$G$282)/$G$296),0))) -> 0 | AV91: =IF(AB131<$G$282,0,MIN($G$279,1+IFERROR(INT((AB131-$G$282)/$G$296),0))) -> 0 | AW91: =IF(AC131<$G$282,0,MIN($G$279,1+IFERROR(INT((AC131-$G$282)/$G$296),0))) -> 0 | AX91: =IF(AD131<$G$282,0,MIN($G$279,1+IFERROR(INT((AD131-$G$282)/$G$296),0))) -> 0 | AY91: =IF(AE131<$G$282,0,MIN($G$279,1+IFERROR(INT((AE131-$G$282)/$G$296),0))) -> 1 | AZ91: =IF(AF131<$G$282,0,MIN($G$279,1+IFERROR(INT((AF131-$G$282)/$G$296),0))) -> 3 | BA91: =IF(AG131<$G$282,0,MIN($G$279,1+IFERROR(INT((AG131-$G$282)/$G$296),0))) -> 4 | BB91: =IF(AH131<$G$282,0,MIN($G$279,1+IFERROR(INT((AH131-$G$282)/$G$296),0))) -> 5
C92: =C93-$G$272 -> 0.25 | D92: =ROUND(Z92,$G$285) -> 6500 | E92: =ROUND(AA92,$G$285) -> 6300 | F92: =ROUND(AB92,$G$285) -> 6100 | G92: =ROUND(AC92,$G$285) -> 5900 | H92: =ROUND(AD92,$G$285) -> 5700 | I92: =ROUND(AE92,$G$285) -> 5600 | J92: =ROUND(AF92,$G$285) -> 5400 | K92: =ROUND(AG92,$G$285) -> 5200 | L92: =ROUND(AH92,$G$285) -> 5000 | N92: =$C92 -> 0.25 | O92: =$G$263*(1-N92)*$G$266 -> 696.42857 | P92: =$G$263*(1-N92)-O92 -> 1553.5714 | Q92: =$G$265-O92 -> 59303.571 | R92: =IFERROR(P92/(Q92+$G$263*(1-N92)),0)*(1-$G$267) -> 0.023977372 | Z92: =$O92+$G$268+$N92*AJ$90+$R92*($Q92*(1+$G$270)+AJ$90*(1-$N92))-$G$263 -> 6452.9719 | AA92: =$O92+$G$268+$N92*AK$90+$R92*($Q92*(1+$G$270)+AK$90*(1-$N92))-$G$263 -> 6274.6938 | AB92: =$O92+$G$268+$N92*AL$90+$R92*($Q92*(1+$G$270)+AL$90*(1-$N92))-$G$263 -> 6096.4157 | AC92: =$O92+$G$268+$N92*AM$90+$R92*($Q92*(1+$G$270)+AM$90*(1-$N92))-$G$263 -> 5918.1376 | AD92: =$O92+$G$268+$N92*AN$90+$R92*($Q92*(1+$G$270)+AN$90*(1-$N92))-$G$263 -> 5739.8595 | AE92: =$O92+$G$268+$N92*AO$90+$R92*($Q92*(1+$G$270)+AO$90*(1-$N92))-$G$263 -> 5561.5814 | AF92: =$O92+$G$268+$N92*AP$90+$R92*($Q92*(1+$G$270)+AP$90*(1-$N92))-$G$263 -> 5383.3033 | AG92: =$O92+$G$268+$N92*AQ$90+$R92*($Q92*(1+$G$270)+AQ$90*(1-$N92))-$G$263 -> 5205.0252 | AH92: =$O92+$G$268+$N92*AR$90+$R92*($Q92*(1+$G$270)+AR$90*(1-$N92))-$G$263 -> 5026.7471 | AJ92: Helper: Standalone Yr 5 Value by Net Client Wins | AT92: =IF(Z132<$G$282,0,MIN($G$279,1+IFERROR(INT((Z132-$G$282)/$G$296),0))) -> 0 | AU92: =IF(AA132<$G$282,0,MIN($G$279,1+IFERROR(INT((AA132-$G$282)/$G$296),0))) -> 0 | AV92: =IF(AB132<$G$282,0,MIN($G$279,1+IFERROR(INT((AB132-$G$282)/$G$296),0))) -> 0 | AW92: =IF(AC132<$G$282,0,MIN($G$279,1+IFERROR(INT((AC132-$G$282)/$G$296),0))) -> 1 | AX92: =IF(AD132<$G$282,0,MIN($G$279,1+IFERROR(INT((AD132-$G$282)/$G$296),0))) -> 2 | AY92: =IF(AE132<$G$282,0,MIN($G$279,1+IFERROR(INT((AE132-$G$282)/$G$296),0))) -> 3 | AZ92: =IF(AF132<$G$282,0,MIN($G$279,1+IFERROR(INT((AF132-$G$282)/$G$296),0))) -> 4 | BA92: =IF(AG132<$G$282,0,MIN($G$279,1+IFERROR(INT((AG132-$G$282)/$G$296),0))) -> 5 | BB92: =IF(AH132<$G$282,0,MIN($G$279,1+IFERROR(INT((AH132-$G$282)/$G$296),0))) -> 6
C93: =$G$271 -> 0.3 | D93: =ROUND(Z93,$G$285) -> 6900 | E93: =ROUND(AA93,$G$285) -> 6700 | F93: =ROUND(AB93,$G$285) -> 6500 | G93: =ROUND(AC93,$G$285) -> 6300 | H93: =ROUND(AD93,$G$285) -> 6100 | I93: =ROUND(AE93,$G$285) -> 5900 | J93: =ROUND(AF93,$G$285) -> 5700 | K93: =ROUND(AG93,$G$285) -> 5500 | L93: =ROUND(AH93,$G$285) -> 5200 | N93: =$C93 -> 0.3 | O93: =$G$263*(1-N93)*$G$266 -> 650 | P93: =$G$263*(1-N93)-O93 -> 1450 | Q93: =$G$265-O93 -> 59350 | R93: =IFERROR(P93/(Q93+$G$263*(1-N93)),0)*(1-$G$267) -> 0.022416599 | Z93: =$O93+$G$268+$N93*AJ$90+$R93*($Q93*(1+$G$270)+AJ$90*(1-$N93))-$G$263 -> 6923.9122 | AA93: =$O93+$G$268+$N93*AK$90+$R93*($Q93*(1+$G$270)+AK$90*(1-$N93))-$G$263 -> 6713.8955 | AB93: =$O93+$G$268+$N93*AL$90+$R93*($Q93*(1+$G$270)+AL$90*(1-$N93))-$G$263 -> 6503.8789 | AC93: =$O93+$G$268+$N93*AM$90+$R93*($Q93*(1+$G$270)+AM$90*(1-$N93))-$G$263 -> 6293.8622 | AD93: =$O93+$G$268+$N93*AN$90+$R93*($Q93*(1+$G$270)+AN$90*(1-$N93))-$G$263 -> 6083.8455 | AE93: =$O93+$G$268+$N93*AO$90+$R93*($Q93*(1+$G$270)+AO$90*(1-$N93))-$G$263 -> 5873.8289 | AF93: =$O93+$G$268+$N93*AP$90+$R93*($Q93*(1+$G$270)+AP$90*(1-$N93))-$G$263 -> 5663.8122 | AG93: =$O93+$G$268+$N93*AQ$90+$R93*($Q93*(1+$G$270)+AQ$90*(1-$N93))-$G$263 -> 5453.7955 | AH93: =$O93+$G$268+$N93*AR$90+$R93*($Q93*(1+$G$270)+AR$90*(1-$N93))-$G$263 -> 5243.7789 | AJ93: =($G$286+(AJ$89-$G$292)*$G$278*$G$293)*$G$294*$G$295 -> 9153.405 | AK93: =($G$286+(AK$89-$G$292)*$G$278*$G$293)*$G$294*$G$295 -> 8737.6182 | AL93: =($G$286+(AL$89-$G$292)*$G$278*$G$293)*$G$294*$G$295 -> 8321.8313 | AM93: =($G$286+(AM$89-$G$292)*$G$278*$G$293)*$G$294*$G$295 -> 7906.0445 | AN93: =($G$286+(AN$89-$G$292)*$G$278*$G$293)*$G$294*$G$295 -> 7490.2577 | AO93: =($G$286+(AO$89-$G$292)*$G$278*$G$293)*$G$294*$G$295 -> 7074.4709 | AP93: =($G$286+(AP$89-$G$292)*$G$278*$G$293)*$G$294*$G$295 -> 6658.684 | AQ93: =($G$286+(AQ$89-$G$292)*$G$278*$G$293)*$G$294*$G$295 -> 6242.8972 | AR93: =($G$286+(AR$89-$G$292)*$G$278*$G$293)*$G$294*$G$295 -> 5827.1104 | AT93: =IF(Z133<$G$282,0,MIN($G$279,1+IFERROR(INT((Z133-$G$282)/$G$296),0))) -> 0 | AU93: =IF(AA133<$G$282,0,MIN($G$279,1+IFERROR(INT((AA133-$G$282)/$G$296),0))) -> 0 | AV93: =IF(AB133<$G$282,0,MIN($G$279,1+IFERROR(INT((AB133-$G$282)/$G$296),0))) -> 1 | AW93: =IF(AC133<$G$282,0,MIN($G$279,1+IFERROR(INT((AC133-$G$282)/$G$296),0))) -> 2 | AX93: =IF(AD133<$G$282,0,MIN($G$279,1+IFERROR(INT((AD133-$G$282)/$G$296),0))) -> 3 | AY93: =IF(AE133<$G$282,0,MIN($G$279,1+IFERROR(INT((AE133-$G$282)/$G$296),0))) -> 4 | AZ93: =IF(AF133<$G$282,0,MIN($G$279,1+IFERROR(INT((AF133-$G$282)/$G$296),0))) -> 5 | BA93: =IF(AG133<$G$282,0,MIN($G$279,1+IFERROR(INT((AG133-$G$282)/$G$296),0))) -> 6 | BB93: =IF(AH133<$G$282,0,MIN($G$279,1+IFERROR(INT((AH133-$G$282)/$G$296),0))) -> 7
C94: =C93+$G$272 -> 0.35 | D94: =ROUND(Z94,$G$285) -> 7400 | E94: =ROUND(AA94,$G$285) -> 7200 | F94: =ROUND(AB94,$G$285) -> 6900 | G94: =ROUND(AC94,$G$285) -> 6700 | H94: =ROUND(AD94,$G$285) -> 6400 | I94: =ROUND(AE94,$G$285) -> 6200 | J94: =ROUND(AF94,$G$285) -> 5900 | K94: =ROUND(AG94,$G$285) -> 5700 | L94: =ROUND(AH94,$G$285) -> 5500 | N94: =$C94 -> 0.35 | O94: =$G$263*(1-N94)*$G$266 -> 603.57143 | P94: =$G$263*(1-N94)-O94 -> 1346.4286 | Q94: =$G$265-O94 -> 59396.429 | R94: =IFERROR(P94/(Q94+$G$263*(1-N94)),0)*(1-$G$267) -> 0.020850556 | Z94: =$O94+$G$268+$N94*AJ$90+$R94*($Q94*(1+$G$270)+AJ$90*(1-$N94))-$G$263 -> 7396.0089 | AA94: =$O94+$G$268+$N94*AK$90+$R94*($Q94*(1+$G$270)+AK$90*(1-$N94))-$G$263 -> 7154.1521 | AB94: =$O94+$G$268+$N94*AL$90+$R94*($Q94*(1+$G$270)+AL$90*(1-$N94))-$G$263 -> 6912.2953 | AC94: =$O94+$G$268+$N94*AM$90+$R94*($Q94*(1+$G$270)+AM$90*(1-$N94))-$G$263 -> 6670.4386 | AD94: =$O94+$G$268+$N94*AN$90+$R94*($Q94*(1+$G$270)+AN$90*(1-$N94))-$G$263 -> 6428.5818 | AE94: =$O94+$G$268+$N94*AO$90+$R94*($Q94*(1+$G$270)+AO$90*(1-$N94))-$G$263 -> 6186.725 | AF94: =$O94+$G$268+$N94*AP$90+$R94*($Q94*(1+$G$270)+AP$90*(1-$N94))-$G$263 -> 5944.8682 | AG94: =$O94+$G$268+$N94*AQ$90+$R94*($Q94*(1+$G$270)+AQ$90*(1-$N94))-$G$263 -> 5703.0114 | AH94: =$O94+$G$268+$N94*AR$90+$R94*($Q94*(1+$G$270)+AR$90*(1-$N94))-$G$263 -> 5461.1546 | AJ94: Helper: Standalone IRR by Net Client Wins | AT94: =IF(Z134<$G$282,0,MIN($G$279,1+IFERROR(INT((Z134-$G$282)/$G$296),0))) -> 2 | AU94: =IF(AA134<$G$282,0,MIN($G$279,1+IFERROR(INT((AA134-$G$282)/$G$296),0))) -> 3 | AV94: =IF(AB134<$G$282,0,MIN($G$279,1+IFERROR(INT((AB134-$G$282)/$G$296),0))) -> 3 | AW94: =IF(AC134<$G$282,0,MIN($G$279,1+IFERROR(INT((AC134-$G$282)/$G$296),0))) -> 4 | AX94: =IF(AD134<$G$282,0,MIN($G$279,1+IFERROR(INT((AD134-$G$282)/$G$296),0))) -> 5 | AY94: =IF(AE134<$G$282,0,MIN($G$279,1+IFERROR(INT((AE134-$G$282)/$G$296),0))) -> 6 | AZ94: =IF(AF134<$G$282,0,MIN($G$279,1+IFERROR(INT((AF134-$G$282)/$G$296),0))) -> 7 | BA94: =IF(AG134<$G$282,0,MIN($G$279,1+IFERROR(INT((AG134-$G$282)/$G$296),0))) -> 8 | BB94: =IF(AH134<$G$282,0,MIN($G$279,1+IFERROR(INT((AH134-$G$282)/$G$296),0))) -> 8
C95: =C94+$G$272 -> 0.4 | D95: =ROUND(Z95,$G$285) -> 7900 | E95: =ROUND(AA95,$G$285) -> 7600 | F95: =ROUND(AB95,$G$285) -> 7300 | G95: =ROUND(AC95,$G$285) -> 7000 | H95: =ROUND(AD95,$G$285) -> 6800 | I95: =ROUND(AE95,$G$285) -> 6500 | J95: =ROUND(AF95,$G$285) -> 6200 | K95: =ROUND(AG95,$G$285) -> 6000 | L95: =ROUND(AH95,$G$285) -> 5700 | N95: =$C95 -> 0.4 | O95: =$G$263*(1-N95)*$G$266 -> 557.14286 | P95: =$G$263*(1-N95)-O95 -> 1242.8571 | Q95: =$G$265-O95 -> 59442.857 | R95: =IFERROR(P95/(Q95+$G$263*(1-N95)),0)*(1-$G$267) -> 0.019279216 | Z95: =$O95+$G$268+$N95*AJ$90+$R95*($Q95*(1+$G$270)+AJ$90*(1-$N95))-$G$263 -> 7869.2679 | AA95: =$O95+$G$268+$N95*AK$90+$R95*($Q95*(1+$G$270)+AK$90*(1-$N95))-$G$263 -> 7595.4689 | AB95: =$O95+$G$268+$N95*AL$90+$R95*($Q95*(1+$G$270)+AL$90*(1-$N95))-$G$263 -> 7321.67 | AC95: =$O95+$G$268+$N95*AM$90+$R95*($Q95*(1+$G$270)+AM$90*(1-$N95))-$G$263 -> 7047.871 | AD95: =$O95+$G$268+$N95*AN$90+$R95*($Q95*(1+$G$270)+AN$90*(1-$N95))-$G$263 -> 6774.072 | AE95: =$O95+$G$268+$N95*AO$90+$R95*($Q95*(1+$G$270)+AO$90*(1-$N95))-$G$263 -> 6500.2731 | AF95: =$O95+$G$268+$N95*AP$90+$R95*($Q95*(1+$G$270)+AP$90*(1-$N95))-$G$263 -> 6226.4741 | AG95: =$O95+$G$268+$N95*AQ$90+$R95*($Q95*(1+$G$270)+AQ$90*(1-$N95))-$G$263 -> 5952.6751 | AH95: =$O95+$G$268+$N95*AR$90+$R95*($Q95*(1+$G$270)+AR$90*(1-$N95))-$G$263 -> 5678.8761 | AJ95: =IFERROR((AJ$93/$G$263)^(1/$G$278)-1,0) -> 0.24994897 | AK95: =IFERROR((AK$93/$G$263)^(1/$G$278)-1,0) -> 0.23838123 | AL95: =IFERROR((AL$93/$G$263)^(1/$G$278)-1,0) -> 0.22636439 | AM95: =IFERROR((AM$93/$G$263)^(1/$G$278)-1,0) -> 0.2138572 | AN95: =IFERROR((AN$93/$G$263)^(1/$G$278)-1,0) -> 0.20081223 | AO95: =IFERROR((AO$93/$G$263)^(1/$G$278)-1,0) -> 0.18717445 | AP95: =IFERROR((AP$93/$G$263)^(1/$G$278)-1,0) -> 0.17287959 | AQ95: =IFERROR((AQ$93/$G$263)^(1/$G$278)-1,0) -> 0.15785183 | AR95: =IFERROR((AR$93/$G$263)^(1/$G$278)-1,0) -> 0.14200077 | AT95: =IF(Z135<$G$282,0,MIN($G$279,1+IFERROR(INT((Z135-$G$282)/$G$296),0))) -> 4 | AU95: =IF(AA135<$G$282,0,MIN($G$279,1+IFERROR(INT((AA135-$G$282)/$G$296),0))) -> 5 | AV95: =IF(AB135<$G$282,0,MIN($G$279,1+IFERROR(INT((AB135-$G$282)/$G$296),0))) -> 5 | AW95: =IF(AC135<$G$282,0,MIN($G$279,1+IFERROR(INT((AC135-$G$282)/$G$296),0))) -> 6 | AX95: =IF(AD135<$G$282,0,MIN($G$279,1+IFERROR(INT((AD135-$G$282)/$G$296),0))) -> 7 | AY95: =IF(AE135<$G$282,0,MIN($G$279,1+IFERROR(INT((AE135-$G$282)/$G$296),0))) -> 7 | AZ95: =IF(AF135<$G$282,0,MIN($G$279,1+IFERROR(INT((AF135-$G$282)/$G$296),0))) -> 8 | BA95: =IF(AG135<$G$282,0,MIN($G$279,1+IFERROR(INT((AG135-$G$282)/$G$296),0))) -> 9 | BB95: =IF(AH135<$G$282,0,MIN($G$279,1+IFERROR(INT((AH135-$G$282)/$G$296),0))) -> 9
C96: =C95+$G$272 -> 0.45 | D96: =ROUND(Z96,$G$285) -> 8300 | E96: =ROUND(AA96,$G$285) -> 8000 | F96: =ROUND(AB96,$G$285) -> 7700 | G96: =ROUND(AC96,$G$285) -> 7400 | H96: =ROUND(AD96,$G$285) -> 7100 | I96: =ROUND(AE96,$G$285) -> 6800 | J96: =ROUND(AF96,$G$285) -> 6500 | K96: =ROUND(AG96,$G$285) -> 6200 | L96: =ROUND(AH96,$G$285) -> 5900 | N96: =$C96 -> 0.45 | O96: =$G$263*(1-N96)*$G$266 -> 510.71429 | P96: =$G$263*(1-N96)-O96 -> 1139.2857 | Q96: =$G$265-O96 -> 59489.286 | R96: =IFERROR(P96/(Q96+$G$263*(1-N96)),0)*(1-$G$267) -> 0.017702553 | Z96: =$O96+$G$268+$N96*AJ$90+$R96*($Q96*(1+$G$270)+AJ$90*(1-$N96))-$G$263 -> 8343.6951 | AA96: =$O96+$G$268+$N96*AK$90+$R96*($Q96*(1+$G$270)+AK$90*(1-$N96))-$G$263 -> 8037.8513 | AB96: =$O96+$G$268+$N96*AL$90+$R96*($Q96*(1+$G$270)+AL$90*(1-$N96))-$G$263 -> 7732.0076 | AC96: =$O96+$G$268+$N96*AM$90+$R96*($Q96*(1+$G$270)+AM$90*(1-$N96))-$G$263 -> 7426.1639 | AD96: =$O96+$G$268+$N96*AN$90+$R96*($Q96*(1+$G$270)+AN$90*(1-$N96))-$G$263 -> 7120.3201 | AE96: =$O96+$G$268+$N96*AO$90+$R96*($Q96*(1+$G$270)+AO$90*(1-$N96))-$G$263 -> 6814.4764 | AF96: =$O96+$G$268+$N96*AP$90+$R96*($Q96*(1+$G$270)+AP$90*(1-$N96))-$G$263 -> 6508.6326 | AG96: =$O96+$G$268+$N96*AQ$90+$R96*($Q96*(1+$G$270)+AQ$90*(1-$N96))-$G$263 -> 6202.7889 | AH96: =$O96+$G$268+$N96*AR$90+$R96*($Q96*(1+$G$270)+AR$90*(1-$N96))-$G$263 -> 5896.9451 | AT96: =IF(Z136<$G$282,0,MIN($G$279,1+IFERROR(INT((Z136-$G$282)/$G$296),0))) -> 6 | AU96: =IF(AA136<$G$282,0,MIN($G$279,1+IFERROR(INT((AA136-$G$282)/$G$296),0))) -> 7 | AV96: =IF(AB136<$G$282,0,MIN($G$279,1+IFERROR(INT((AB136-$G$282)/$G$296),0))) -> 7 | AW96: =IF(AC136<$G$282,0,MIN($G$279,1+IFERROR(INT((AC136-$G$282)/$G$296),0))) -> 8 | AX96: =IF(AD136<$G$282,0,MIN($G$279,1+IFERROR(INT((AD136-$G$282)/$G$296),0))) -> 8 | AY96: =IF(AE136<$G$282,0,MIN($G$279,1+IFERROR(INT((AE136-$G$282)/$G$296),0))) -> 9 | AZ96: =IF(AF136<$G$282,0,MIN($G$279,1+IFERROR(INT((AF136-$G$282)/$G$296),0))) -> 9 | BA96: =IF(AG136<$G$282,0,MIN($G$279,1+IFERROR(INT((AG136-$G$282)/$G$296),0))) -> 10 | BB96: =IF(AH136<$G$282,0,MIN($G$279,1+IFERROR(INT((AH136-$G$282)/$G$296),0))) -> 10
B97: Ben's Year 5 value (cash at close + earnout + retained Keystone stake + Topkey stock, after dilution) less Keystone value today (G263); Topkey growth held at model (G270)
B99: Ben's % Return on Keystone Value Based on Net Client Wins & Rollover %
D101: Keystone Total Annual Net Client Wins — Partnership (#)
D102: =E102+$G$291 -> 64 | E102: =F102+$G$291 -> 60 | F102: =G102+$G$291 -> 56 | G102: =H102+$G$291 -> 52 | H102: =$G$290 -> 48 | I102: =H102-$G$291 -> 44 | J102: =I102-$G$291 -> 40 | K102: =J102-$G$291 -> 36 | L102: =K102-$G$291 -> 32 | AT102: Helper: Gradient Band (0 = below $1M hurdle)
B103: Ben's Rollover % | C103: =C104-$G$272 -> 0.15 | D103: =IFERROR(Z90/$G$263,0) -> 1.8381791 | E103: =IFERROR(AA90/$G$263,0) -> 1.7998112 | F103: =IFERROR(AB90/$G$263,0) -> 1.7614434 | G103: =IFERROR(AC90/$G$263,0) -> 1.7230755 | H103: =IFERROR(AD90/$G$263,0) -> 1.6847076 | I103: =IFERROR(AE90/$G$263,0) -> 1.6463398 | J103: =IFERROR(AF90/$G$263,0) -> 1.6079719 | K103: =IFERROR(AG90/$G$263,0) -> 1.5696041 | L103: =IFERROR(AH90/$G$263,0) -> 1.5312362 | AT103: =IF(Z130<$G$282,0,MIN($G$279,1+IFERROR(INT((Z130-$G$282)/$G$296),0))) -> 0 | AU103: =IF(AA130<$G$282,0,MIN($G$279,1+IFERROR(INT((AA130-$G$282)/$G$296),0))) -> 0 | AV103: =IF(AB130<$G$282,0,MIN($G$279,1+IFERROR(INT((AB130-$G$282)/$G$296),0))) -> 0 | AW103: =IF(AC130<$G$282,0,MIN($G$279,1+IFERROR(INT((AC130-$G$282)/$G$296),0))) -> 0 | AX103: =IF(AD130<$G$282,0,MIN($G$279,1+IFERROR(INT((AD130-$G$282)/$G$296),0))) -> 0 | AY103: =IF(AE130<$G$282,0,MIN($G$279,1+IFERROR(INT((AE130-$G$282)/$G$296),0))) -> 0 | AZ103: =IF(AF130<$G$282,0,MIN($G$279,1+IFERROR(INT((AF130-$G$282)/$G$296),0))) -> 1 | BA103: =IF(AG130<$G$282,0,MIN($G$279,1+IFERROR(INT((AG130-$G$282)/$G$296),0))) -> 3 | BB103: =IF(AH130<$G$282,0,MIN($G$279,1+IFERROR(INT((AH130-$G$282)/$G$296),0))) -> 4
C104: =C105-$G$272 -> 0.2 | D104: =IFERROR(Z91/$G$263,0) -> 1.9943941 | E104: =IFERROR(AA91/$G$263,0) -> 1.9455139 | F104: =IFERROR(AB91/$G$263,0) -> 1.8966337 | G104: =IFERROR(AC91/$G$263,0) -> 1.8477535 | H104: =IFERROR(AD91/$G$263,0) -> 1.7988733 | I104: =IFERROR(AE91/$G$263,0) -> 1.7499931 | J104: =IFERROR(AF91/$G$263,0) -> 1.7011129 | K104: =IFERROR(AG91/$G$263,0) -> 1.6522327 | L104: =IFERROR(AH91/$G$263,0) -> 1.6033525 | AT104: =IF(Z131<$G$282,0,MIN($G$279,1+IFERROR(INT((Z131-$G$282)/$G$296),0))) -> 0 | AU104: =IF(AA131<$G$282,0,MIN($G$279,1+IFERROR(INT((AA131-$G$282)/$G$296),0))) -> 0 | AV104: =IF(AB131<$G$282,0,MIN($G$279,1+IFERROR(INT((AB131-$G$282)/$G$296),0))) -> 0 | AW104: =IF(AC131<$G$282,0,MIN($G$279,1+IFERROR(INT((AC131-$G$282)/$G$296),0))) -> 0 | AX104: =IF(AD131<$G$282,0,MIN($G$279,1+IFERROR(INT((AD131-$G$282)/$G$296),0))) -> 0 | AY104: =IF(AE131<$G$282,0,MIN($G$279,1+IFERROR(INT((AE131-$G$282)/$G$296),0))) -> 1 | AZ104: =IF(AF131<$G$282,0,MIN($G$279,1+IFERROR(INT((AF131-$G$282)/$G$296),0))) -> 3 | BA104: =IF(AG131<$G$282,0,MIN($G$279,1+IFERROR(INT((AG131-$G$282)/$G$296),0))) -> 4 | BB104: =IF(AH131<$G$282,0,MIN($G$279,1+IFERROR(INT((AH131-$G$282)/$G$296),0))) -> 5
C105: =C106-$G$272 -> 0.25 | D105: =IFERROR(Z92/$G$263,0) -> 2.1509906 | E105: =IFERROR(AA92/$G$263,0) -> 2.0915646 | F105: =IFERROR(AB92/$G$263,0) -> 2.0321386 | G105: =IFERROR(AC92/$G$263,0) -> 1.9727125 | H105: =IFERROR(AD92/$G$263,0) -> 1.9132865 | I105: =IFERROR(AE92/$G$263,0) -> 1.8538605 | J105: =IFERROR(AF92/$G$263,0) -> 1.7944344 | K105: =IFERROR(AG92/$G$263,0) -> 1.7350084 | L105: =IFERROR(AH92/$G$263,0) -> 1.6755824 | AT105: =IF(Z132<$G$282,0,MIN($G$279,1+IFERROR(INT((Z132-$G$282)/$G$296),0))) -> 0 | AU105: =IF(AA132<$G$282,0,MIN($G$279,1+IFERROR(INT((AA132-$G$282)/$G$296),0))) -> 0 | AV105: =IF(AB132<$G$282,0,MIN($G$279,1+IFERROR(INT((AB132-$G$282)/$G$296),0))) -> 0 | AW105: =IF(AC132<$G$282,0,MIN($G$279,1+IFERROR(INT((AC132-$G$282)/$G$296),0))) -> 1 | AX105: =IF(AD132<$G$282,0,MIN($G$279,1+IFERROR(INT((AD132-$G$282)/$G$296),0))) -> 2 | AY105: =IF(AE132<$G$282,0,MIN($G$279,1+IFERROR(INT((AE132-$G$282)/$G$296),0))) -> 3 | AZ105: =IF(AF132<$G$282,0,MIN($G$279,1+IFERROR(INT((AF132-$G$282)/$G$296),0))) -> 4 | BA105: =IF(AG132<$G$282,0,MIN($G$279,1+IFERROR(INT((AG132-$G$282)/$G$296),0))) -> 5 | BB105: =IF(AH132<$G$282,0,MIN($G$279,1+IFERROR(INT((AH132-$G$282)/$G$296),0))) -> 6
C106: =$G$271 -> 0.3 | D106: =IFERROR(Z93/$G$263,0) -> 2.3079707 | E106: =IFERROR(AA93/$G$263,0) -> 2.2379652 | F106: =IFERROR(AB93/$G$263,0) -> 2.1679596 | G106: =IFERROR(AC93/$G$263,0) -> 2.0979541 | H106: =IFERROR(AD93/$G$263,0) -> 2.0279485 | I106: =IFERROR(AE93/$G$263,0) -> 1.957943 | J106: =IFERROR(AF93/$G$263,0) -> 1.8879374 | K106: =IFERROR(AG93/$G$263,0) -> 1.8179318 | L106: =IFERROR(AH93/$G$263,0) -> 1.7479263 | AT106: =IF(Z133<$G$282,0,MIN($G$279,1+IFERROR(INT((Z133-$G$282)/$G$296),0))) -> 0 | AU106: =IF(AA133<$G$282,0,MIN($G$279,1+IFERROR(INT((AA133-$G$282)/$G$296),0))) -> 0 | AV106: =IF(AB133<$G$282,0,MIN($G$279,1+IFERROR(INT((AB133-$G$282)/$G$296),0))) -> 1 | AW106: =IF(AC133<$G$282,0,MIN($G$279,1+IFERROR(INT((AC133-$G$282)/$G$296),0))) -> 2 | AX106: =IF(AD133<$G$282,0,MIN($G$279,1+IFERROR(INT((AD133-$G$282)/$G$296),0))) -> 3 | AY106: =IF(AE133<$G$282,0,MIN($G$279,1+IFERROR(INT((AE133-$G$282)/$G$296),0))) -> 4 | AZ106: =IF(AF133<$G$282,0,MIN($G$279,1+IFERROR(INT((AF133-$G$282)/$G$296),0))) -> 5 | BA106: =IF(AG133<$G$282,0,MIN($G$279,1+IFERROR(INT((AG133-$G$282)/$G$296),0))) -> 6 | BB106: =IF(AH133<$G$282,0,MIN($G$279,1+IFERROR(INT((AH133-$G$282)/$G$296),0))) -> 7
C107: =C106+$G$272 -> 0.35 | D107: =IFERROR(Z94/$G$263,0) -> 2.4653363 | E107: =IFERROR(AA94/$G$263,0) -> 2.3847174 | F107: =IFERROR(AB94/$G$263,0) -> 2.3040984 | G107: =IFERROR(AC94/$G$263,0) -> 2.2234795 | H107: =IFERROR(AD94/$G$263,0) -> 2.1428606 | I107: =IFERROR(AE94/$G$263,0) -> 2.0622417 | J107: =IFERROR(AF94/$G$263,0) -> 1.9816227 | K107: =IFERROR(AG94/$G$263,0) -> 1.9010038 | L107: =IFERROR(AH94/$G$263,0) -> 1.8203849 | AT107: =IF(Z134<$G$282,0,MIN($G$279,1+IFERROR(INT((Z134-$G$282)/$G$296),0))) -> 2 | AU107: =IF(AA134<$G$282,0,MIN($G$279,1+IFERROR(INT((AA134-$G$282)/$G$296),0))) -> 3 | AV107: =IF(AB134<$G$282,0,MIN($G$279,1+IFERROR(INT((AB134-$G$282)/$G$296),0))) -> 3 | AW107: =IF(AC134<$G$282,0,MIN($G$279,1+IFERROR(INT((AC134-$G$282)/$G$296),0))) -> 4 | AX107: =IF(AD134<$G$282,0,MIN($G$279,1+IFERROR(INT((AD134-$G$282)/$G$296),0))) -> 5 | AY107: =IF(AE134<$G$282,0,MIN($G$279,1+IFERROR(INT((AE134-$G$282)/$G$296),0))) -> 6 | AZ107: =IF(AF134<$G$282,0,MIN($G$279,1+IFERROR(INT((AF134-$G$282)/$G$296),0))) -> 7 | BA107: =IF(AG134<$G$282,0,MIN($G$279,1+IFERROR(INT((AG134-$G$282)/$G$296),0))) -> 8 | BB107: =IF(AH134<$G$282,0,MIN($G$279,1+IFERROR(INT((AH134-$G$282)/$G$296),0))) -> 8
C108: =C107+$G$272 -> 0.4 | D108: =IFERROR(Z95/$G$263,0) -> 2.6230893 | E108: =IFERROR(AA95/$G$263,0) -> 2.531823 | F108: =IFERROR(AB95/$G$263,0) -> 2.4405567 | G108: =IFERROR(AC95/$G$263,0) -> 2.3492903 | H108: =IFERROR(AD95/$G$263,0) -> 2.258024 | I108: =IFERROR(AE95/$G$263,0) -> 2.1667577 | J108: =IFERROR(AF95/$G$263,0) -> 2.0754914 | K108: =IFERROR(AG95/$G$263,0) -> 1.984225 | L108: =IFERROR(AH95/$G$263,0) -> 1.8929587 | AT108: =IF(Z135<$G$282,0,MIN($G$279,1+IFERROR(INT((Z135-$G$282)/$G$296),0))) -> 4 | AU108: =IF(AA135<$G$282,0,MIN($G$279,1+IFERROR(INT((AA135-$G$282)/$G$296),0))) -> 5 | AV108: =IF(AB135<$G$282,0,MIN($G$279,1+IFERROR(INT((AB135-$G$282)/$G$296),0))) -> 5 | AW108: =IF(AC135<$G$282,0,MIN($G$279,1+IFERROR(INT((AC135-$G$282)/$G$296),0))) -> 6 | AX108: =IF(AD135<$G$282,0,MIN($G$279,1+IFERROR(INT((AD135-$G$282)/$G$296),0))) -> 7 | AY108: =IF(AE135<$G$282,0,MIN($G$279,1+IFERROR(INT((AE135-$G$282)/$G$296),0))) -> 7 | AZ108: =IF(AF135<$G$282,0,MIN($G$279,1+IFERROR(INT((AF135-$G$282)/$G$296),0))) -> 8 | BA108: =IF(AG135<$G$282,0,MIN($G$279,1+IFERROR(INT((AG135-$G$282)/$G$296),0))) -> 9 | BB108: =IF(AH135<$G$282,0,MIN($G$279,1+IFERROR(INT((AH135-$G$282)/$G$296),0))) -> 9
C109: =C108+$G$272 -> 0.45 | D109: =IFERROR(Z96/$G$263,0) -> 2.7812317 | E109: =IFERROR(AA96/$G$263,0) -> 2.6792838 | F109: =IFERROR(AB96/$G$263,0) -> 2.5773359 | G109: =IFERROR(AC96/$G$263,0) -> 2.475388 | H109: =IFERROR(AD96/$G$263,0) -> 2.37344 | I109: =IFERROR(AE96/$G$263,0) -> 2.2714921 | J109: =IFERROR(AF96/$G$263,0) -> 2.1695442 | K109: =IFERROR(AG96/$G$263,0) -> 2.0675963 | L109: =IFERROR(AH96/$G$263,0) -> 1.9656484 | AT109: =IF(Z136<$G$282,0,MIN($G$279,1+IFERROR(INT((Z136-$G$282)/$G$296),0))) -> 6 | AU109: =IF(AA136<$G$282,0,MIN($G$279,1+IFERROR(INT((AA136-$G$282)/$G$296),0))) -> 7 | AV109: =IF(AB136<$G$282,0,MIN($G$279,1+IFERROR(INT((AB136-$G$282)/$G$296),0))) -> 7 | AW109: =IF(AC136<$G$282,0,MIN($G$279,1+IFERROR(INT((AC136-$G$282)/$G$296),0))) -> 8 | AX109: =IF(AD136<$G$282,0,MIN($G$279,1+IFERROR(INT((AD136-$G$282)/$G$296),0))) -> 8 | AY109: =IF(AE136<$G$282,0,MIN($G$279,1+IFERROR(INT((AE136-$G$282)/$G$296),0))) -> 9 | AZ109: =IF(AF136<$G$282,0,MIN($G$279,1+IFERROR(INT((AF136-$G$282)/$G$296),0))) -> 9 | BA109: =IF(AG136<$G$282,0,MIN($G$279,1+IFERROR(INT((AG136-$G$282)/$G$296),0))) -> 10 | BB109: =IF(AH136<$G$282,0,MIN($G$279,1+IFERROR(INT((AH136-$G$282)/$G$296),0))) -> 10
B110: Ben's Year 5 total value ÷ Keystone value today (G263), less 1
B112: Ben's IRR Based on Net Client Wins & Rollover %
D114: Keystone Total Annual Net Client Wins — Partnership (#)
D115: =E115+$G$291 -> 64 | E115: =F115+$G$291 -> 60 | F115: =G115+$G$291 -> 56 | G115: =H115+$G$291 -> 52 | H115: =$G$290 -> 48 | I115: =H115-$G$291 -> 44 | J115: =I115-$G$291 -> 40 | K115: =J115-$G$291 -> 36 | L115: =K115-$G$291 -> 32 | AT115: Helper: Gradient Band (0 = below $1M hurdle)
B116: Ben's Rollover % | C116: =C117-$G$272 -> 0.15 | D116: {=IFERROR(IRR(IF($S$9:$X$9=0,$O90-$G$263,0)+IF($S$9:$X$9=$G$277,$G$268,0)+IF($S$9:$X$9=$G$278,Z90+$G$263-$O90-$G$268,0)),0)} -> 0.28432815 | E116: {=IFERROR(IRR(IF($S$9:$X$9=0,$O90-$G$263,0)+IF($S$9:$X$9=$G$277,$G$268,0)+IF($S$9:$X$9=$G$278,AA90+$G$263-$O90-$G$268,0)),0)} -> 0.28047793 | F116: {=IFERROR(IRR(IF($S$9:$X$9=0,$O90-$G$263,0)+IF($S$9:$X$9=$G$277,$G$268,0)+IF($S$9:$X$9=$G$278,AB90+$G$263-$O90-$G$268,0)),0)} -> 0.27658083 | G116: {=IFERROR(IRR(IF($S$9:$X$9=0,$O90-$G$263,0)+IF($S$9:$X$9=$G$277,$G$268,0)+IF($S$9:$X$9=$G$278,AC90+$G$263-$O90-$G$268,0)),0)} -> 0.27263555 | H116: {=IFERROR(IRR(IF($S$9:$X$9=0,$O90-$G$263,0)+IF($S$9:$X$9=$G$277,$G$268,0)+IF($S$9:$X$9=$G$278,AD90+$G$263-$O90-$G$268,0)),0)} -> 0.26864074 | I116: {=IFERROR(IRR(IF($S$9:$X$9=0,$O90-$G$263,0)+IF($S$9:$X$9=$G$277,$G$268,0)+IF($S$9:$X$9=$G$278,AE90+$G$263-$O90-$G$268,0)),0)} -> 0.26459497 | J116: {=IFERROR(IRR(IF($S$9:$X$9=0,$O90-$G$263,0)+IF($S$9:$X$9=$G$277,$G$268,0)+IF($S$9:$X$9=$G$278,AF90+$G$263-$O90-$G$268,0)),0)} -> 0.26049675 | K116: {=IFERROR(IRR(IF($S$9:$X$9=0,$O90-$G$263,0)+IF($S$9:$X$9=$G$277,$G$268,0)+IF($S$9:$X$9=$G$278,AG90+$G$263-$O90-$G$268,0)),0)} -> 0.25634452 | L116: {=IFERROR(IRR(IF($S$9:$X$9=0,$O90-$G$263,0)+IF($S$9:$X$9=$G$277,$G$268,0)+IF($S$9:$X$9=$G$278,AH90+$G$263-$O90-$G$268,0)),0)} -> 0.25213667 | AT116: =IF(Z130<$G$282,0,MIN($G$279,1+IFERROR(INT((Z130-$G$282)/$G$296),0))) -> 0 | AU116: =IF(AA130<$G$282,0,MIN($G$279,1+IFERROR(INT((AA130-$G$282)/$G$296),0))) -> 0 | AV116: =IF(AB130<$G$282,0,MIN($G$279,1+IFERROR(INT((AB130-$G$282)/$G$296),0))) -> 0 | AW116: =IF(AC130<$G$282,0,MIN($G$279,1+IFERROR(INT((AC130-$G$282)/$G$296),0))) -> 0 | AX116: =IF(AD130<$G$282,0,MIN($G$279,1+IFERROR(INT((AD130-$G$282)/$G$296),0))) -> 0 | AY116: =IF(AE130<$G$282,0,MIN($G$279,1+IFERROR(INT((AE130-$G$282)/$G$296),0))) -> 0 | AZ116: =IF(AF130<$G$282,0,MIN($G$279,1+IFERROR(INT((AF130-$G$282)/$G$296),0))) -> 1 | BA116: =IF(AG130<$G$282,0,MIN($G$279,1+IFERROR(INT((AG130-$G$282)/$G$296),0))) -> 3 | BB116: =IF(AH130<$G$282,0,MIN($G$279,1+IFERROR(INT((AH130-$G$282)/$G$296),0))) -> 4
C117: =C118-$G$272 -> 0.2 | D117: {=IFERROR(IRR(IF($S$9:$X$9=0,$O91-$G$263,0)+IF($S$9:$X$9=$G$277,$G$268,0)+IF($S$9:$X$9=$G$278,Z91+$G$263-$O91-$G$268,0)),0)} -> 0.29561826 | E117: {=IFERROR(IRR(IF($S$9:$X$9=0,$O91-$G$263,0)+IF($S$9:$X$9=$G$277,$G$268,0)+IF($S$9:$X$9=$G$278,AA91+$G$263-$O91-$G$268,0)),0)} -> 0.29097385 | F117: {=IFERROR(IRR(IF($S$9:$X$9=0,$O91-$G$263,0)+IF($S$9:$X$9=$G$277,$G$268,0)+IF($S$9:$X$9=$G$278,AB91+$G$263-$O91-$G$268,0)),0)} -> 0.28626163 | G117: {=IFERROR(IRR(IF($S$9:$X$9=0,$O91-$G$263,0)+IF($S$9:$X$9=$G$277,$G$268,0)+IF($S$9:$X$9=$G$278,AC91+$G$263-$O91-$G$268,0)),0)} -> 0.28147932 | H117: {=IFERROR(IRR(IF($S$9:$X$9=0,$O91-$G$263,0)+IF($S$9:$X$9=$G$277,$G$268,0)+IF($S$9:$X$9=$G$278,AD91+$G$263-$O91-$G$268,0)),0)} -> 0.27662454 | I117: {=IFERROR(IRR(IF($S$9:$X$9=0,$O91-$G$263,0)+IF($S$9:$X$9=$G$277,$G$268,0)+IF($S$9:$X$9=$G$278,AE91+$G$263-$O91-$G$268,0)),0)} -> 0.27169478 | J117: {=IFERROR(IRR(IF($S$9:$X$9=0,$O91-$G$263,0)+IF($S$9:$X$9=$G$277,$G$268,0)+IF($S$9:$X$9=$G$278,AF91+$G$263-$O91-$G$268,0)),0)} -> 0.26668736 | K117: {=IFERROR(IRR(IF($S$9:$X$9=0,$O91-$G$263,0)+IF($S$9:$X$9=$G$277,$G$268,0)+IF($S$9:$X$9=$G$278,AG91+$G$263-$O91-$G$268,0)),0)} -> 0.26159949 | L117: {=IFERROR(IRR(IF($S$9:$X$9=0,$O91-$G$263,0)+IF($S$9:$X$9=$G$277,$G$268,0)+IF($S$9:$X$9=$G$278,AH91+$G$263-$O91-$G$268,0)),0)} -> 0.25642819 | AT117: =IF(Z131<$G$282,0,MIN($G$279,1+IFERROR(INT((Z131-$G$282)/$G$296),0))) -> 0 | AU117: =IF(AA131<$G$282,0,MIN($G$279,1+IFERROR(INT((AA131-$G$282)/$G$296),0))) -> 0 | AV117: =IF(AB131<$G$282,0,MIN($G$279,1+IFERROR(INT((AB131-$G$282)/$G$296),0))) -> 0 | AW117: =IF(AC131<$G$282,0,MIN($G$279,1+IFERROR(INT((AC131-$G$282)/$G$296),0))) -> 0 | AX117: =IF(AD131<$G$282,0,MIN($G$279,1+IFERROR(INT((AD131-$G$282)/$G$296),0))) -> 0 | AY117: =IF(AE131<$G$282,0,MIN($G$279,1+IFERROR(INT((AE131-$G$282)/$G$296),0))) -> 1 | AZ117: =IF(AF131<$G$282,0,MIN($G$279,1+IFERROR(INT((AF131-$G$282)/$G$296),0))) -> 3 | BA117: =IF(AG131<$G$282,0,MIN($G$279,1+IFERROR(INT((AG131-$G$282)/$G$296),0))) -> 4 | BB117: =IF(AH131<$G$282,0,MIN($G$279,1+IFERROR(INT((AH131-$G$282)/$G$296),0))) -> 5
C118: =C119-$G$272 -> 0.25 | D118: {=IFERROR(IRR(IF($S$9:$X$9=0,$O92-$G$263,0)+IF($S$9:$X$9=$G$277,$G$268,0)+IF($S$9:$X$9=$G$278,Z92+$G$263-$O92-$G$268,0)),0)} -> 0.30612939 | E118: {=IFERROR(IRR(IF($S$9:$X$9=0,$O92-$G$263,0)+IF($S$9:$X$9=$G$277,$G$268,0)+IF($S$9:$X$9=$G$278,AA92+$G$263-$O92-$G$268,0)),0)} -> 0.30076714 | F118: {=IFERROR(IRR(IF($S$9:$X$9=0,$O92-$G$263,0)+IF($S$9:$X$9=$G$277,$G$268,0)+IF($S$9:$X$9=$G$278,AB92+$G$263-$O92-$G$268,0)),0)} -> 0.29531498 | G118: {=IFERROR(IRR(IF($S$9:$X$9=0,$O92-$G$263,0)+IF($S$9:$X$9=$G$277,$G$268,0)+IF($S$9:$X$9=$G$278,AC92+$G$263-$O92-$G$268,0)),0)} -> 0.28976944 | H118: {=IFERROR(IRR(IF($S$9:$X$9=0,$O92-$G$263,0)+IF($S$9:$X$9=$G$277,$G$268,0)+IF($S$9:$X$9=$G$278,AD92+$G$263-$O92-$G$268,0)),0)} -> 0.28412686 | I118: {=IFERROR(IRR(IF($S$9:$X$9=0,$O92-$G$263,0)+IF($S$9:$X$9=$G$277,$G$268,0)+IF($S$9:$X$9=$G$278,AE92+$G$263-$O92-$G$268,0)),0)} -> 0.27838332 | J118: {=IFERROR(IRR(IF($S$9:$X$9=0,$O92-$G$263,0)+IF($S$9:$X$9=$G$277,$G$268,0)+IF($S$9:$X$9=$G$278,AF92+$G$263-$O92-$G$268,0)),0)} -> 0.27253467 | K118: {=IFERROR(IRR(IF($S$9:$X$9=0,$O92-$G$263,0)+IF($S$9:$X$9=$G$277,$G$268,0)+IF($S$9:$X$9=$G$278,AG92+$G$263-$O92-$G$268,0)),0)} -> 0.26657648 | L118: {=IFERROR(IRR(IF($S$9:$X$9=0,$O92-$G$263,0)+IF($S$9:$X$9=$G$277,$G$268,0)+IF($S$9:$X$9=$G$278,AH92+$G$263-$O92-$G$268,0)),0)} -> 0.26050401 | AT118: =IF(Z132<$G$282,0,MIN($G$279,1+IFERROR(INT((Z132-$G$282)/$G$296),0))) -> 0 | AU118: =IF(AA132<$G$282,0,MIN($G$279,1+IFERROR(INT((AA132-$G$282)/$G$296),0))) -> 0 | AV118: =IF(AB132<$G$282,0,MIN($G$279,1+IFERROR(INT((AB132-$G$282)/$G$296),0))) -> 0 | AW118: =IF(AC132<$G$282,0,MIN($G$279,1+IFERROR(INT((AC132-$G$282)/$G$296),0))) -> 1 | AX118: =IF(AD132<$G$282,0,MIN($G$279,1+IFERROR(INT((AD132-$G$282)/$G$296),0))) -> 2 | AY118: =IF(AE132<$G$282,0,MIN($G$279,1+IFERROR(INT((AE132-$G$282)/$G$296),0))) -> 3 | AZ118: =IF(AF132<$G$282,0,MIN($G$279,1+IFERROR(INT((AF132-$G$282)/$G$296),0))) -> 4 | BA118: =IF(AG132<$G$282,0,MIN($G$279,1+IFERROR(INT((AG132-$G$282)/$G$296),0))) -> 5 | BB118: =IF(AH132<$G$282,0,MIN($G$279,1+IFERROR(INT((AH132-$G$282)/$G$296),0))) -> 6
...

Sheet 100% Buyout Analysis
B2: =Cover!$B$24 -> Keystone Bookkeepers
B3: Valuation Growth Scenarios ($000s) | G3: Print | H3: 1
B5: Revenue Growth Assumptions | C5: Value | F5: Rationale / Notes
B6: General Assumptions
B7: Horizon (Years) | C7: ='Offer Comparison'!$D$7 -> 5 | F7: Projection horizon for Year 5 columns
B8: Est. Topkey Dilution — Ben's Stake (Year 5) | C8: ='Offer Comparison'!$D$8 -> 0.05 | F8: AMB estimate: future Topkey equity issuance (capital raise, option pool, acquisitions) reduces Ben's Topkey % by this share by Year 5
B9: Topkey - Current Monthly Revenue | C9: 261 | F9: Topkey-provided monthly revenue ($000s). Red: source pending confirmation
B10: Topkey - Current Run-Rate Revenue | C10: =C9*12 -> 3132
B11: Topkey - Current Revenue Multiple | C11: =IFERROR(C176/C10,0) -> 19.157088 | F11: Implied multiple: Topkey pre-deal valuation (C163) ÷ run-rate revenue (C9)
B12: Topkey - Future Revenue Multiple | C12: =C11 -> 19.157088 | F12: Assumed flat at current multiple
B13: Topkey - Current Client Count | C13: 325 | F13: Topkey-provided client count. Red: source pending confirmation
B14: Topkey - Avg. Revenue Per Client | C14: =C10/C13 -> 9.6369231
B15: Topkey - Annual Net Client Wins | C15: 130 | F15: AMB placeholder. Red: source pending confirmation
B16: Total Net Client Wins | C16: =C15*$C$7 -> 650
B17: Total Additional Revenue | C17: =C16*C14 -> 6264
B18: ="Check - "&$C$7&" Year Topkey Valuation Growth" -> Check - 5 Year Topkey Valuation Growth | C18: =IFERROR(D75/C75-1,0) -> 2.0084034 | F18: % growth in Topkey ex-Keystone Value (row 73), Today → Year N
B20: Keystone Standalone Assumptions
B21: Revenue Multiple | C21: ='Offer Comparison'!$D$13 -> 1 | F21: Keystone standalone valued at 1.0x revenue (offer implies ~1.00x)
B22: Scaled Revenue Multiple | C22: ='Offer Comparison'!$D$14 -> 1.25 | F22: Future revenue multiple for Keystone
B23: Avg. Revenue Per Client | C23: =+'Steady-State Staffing'!AB8 -> 16.631473 | F23: Sep'26 annualized fee per non-tax client (Steady-State Staffing AB8)
B24: Target Monthly Net Client Wins | C24: 3 | F24: Target pace per AMB; LTM actual is 26/yr (~2.2/month), see build at rows 170-175
B25: Annual Net Client Wins | C25: =C24*12 -> 36 | F25: Target monthly pace × 12
B26: Total Net Client Wins | C26: =C25*$C$7 -> 180
B27: Total Additional Revenue | C27: =C26*C23 -> 2993.6651
B29: Keystone Partnership Assumptions
B30: Software-Integration Revenue Multiple | C30: ='Offer Comparison'!$D$15 -> 2 | F30: Assumed revenue multiple for software-integrated partnership
B31: VR Platform Run-Rate Tech Cost | C31: 240 | F31: Run-rate tech cost provided by the target; memo only — VR savings assumed captured in the 20% partnership margin (C109) and revenue multiple
B33: =+B23 -> Avg. Revenue Per Client | C33: =+C23 -> 16.631473
B34: (+) Software-Enabled Price Increase / Client | C34: 0 | F34: Only if Topkey software supports higher client fees; VR platform cost no longer added to revenue per client
B35: Total Avg. Revenue Per Client | C35: =+C33+C34 -> 16.631473
B37: =+B25 -> Annual Net Client Wins | C37: =+C25 -> 36
B38: (+) Additional Annual Net Client Wins From Topkey | C38: 12 | F38: Topkey-provided. Red: source pending confirmation
B39: Total Annual Net Client Wins | C39: =SUM(C37:C38) -> 48
B40: Total Net Client Wins | C40: =C39*$C$7 -> 240
B41: Total Additional Revenue | C41: =C40*C35 -> 3991.5535
B42: Increase in Keystone Revenue vs. Standalone | C42: =C41-C27 -> 997.88838
B44: Cash Earnout — Year 3 Keystone Revenue (Sliding Scale)
B45: Earnout Measurement Year | C45: 3 | F45: Earnout measured on Year 3 run-rate: average of months 34–36 × 12 (see C54)
B46: Keystone Revenue at Close | C46: =C172 -> 2998.541 | F46: PF Jul'26 run-rate revenue at close (C159); unchanged
B47: Year 3 Run-Rate Revenue Target | C47: =C46+C41*(C45-(C56-1)/2/12)/C7 -> 5326.9472 | F47: Run-rate at close + partnership added revenue ramped to the midpoint of the averaging window (month 35 ÷ 60); same basis as the earnout measurement
B48: (x) Achievement vs. Target | C48: 1 | F48: Base case assumes the model's Year 3 revenue is achieved; flex to test payout
B49: Year 3 Run-Rate Revenue — Achieved | C49: =C47*C48 -> 5326.9472
B50: Threshold — % of Target | C50: 0.8 | F50: No earnout below this share of target; payout starts at the threshold % below
B51: Target Earnout — at 100% of Target | C51: 500 | F51: Opening ask: $500K at target (AMB internal range $750K–$1M)
B52: Payout at Threshold — % of Target Earnout | C52: 0.5 | F52: Share of target earnout paid at the 80% threshold
B53: Cap — % of Target Earnout | C53: 1.5 | F53: Payout capped at 120% of target, symmetric with the 80% threshold (50% at 80%, 150% at 120%)
B54: Payout % Earned | C54: =IF(C48<C50,0,MIN(C53,C52+(1-C52)*(C48-C50)/(1-C50))) -> 1 | F54: Straight line from threshold payout at 80% to 100% at target, continuing above target until the cap
B55: Maximum Earnout (Cap) | C55: =C51*C53 -> 750 | F55: Topkey's maximum earnout exposure
B56: Run-Rate Window — Months Averaged | C56: 3 | F56: Earnout measured on average monthly recurring revenue for the last 3 months of Year 3 (months 34–36) × 12; averaging prevents one strong month from triggering the payout
B57: Cash Earnout Payable — Year 3 | C57: =C51*C54 -> 500 | F57: Paid in cash by Topkey; flows into Scenario 2 (row 78), Ben's MOIC/IRR (rows 84-85) and Topkey's return (row 92)
B58: Probability of Achievement | C58: 0.7 | F58: AMB estimate for the memo line below
B59: Discount Rate | C59: 0.15 | F59: AMB estimate for the memo line below
B60: Risk-Weighted Earnout — PV at Close (Memo) | C60: =C57*C58/(1+C59)^C45 -> 230.13068 | F60: Memo only; not used in Scenario 2
B62: Offer Structure | C62: =C$171 -> Today | D62: % of Total
B63: Cash at Close | C63: =$C$174 -> 500 | D63: =IFERROR(C63/C$65,0) -> 0.16666667 | F63: Cash paid at close (C174)
B64: (+) Topkey Equity Issued to Ben | C64: =$C$175 -> 2500 | D64: =IFERROR(C64/C$65,0) -> 0.83333333 | F64: Topkey stock issued at the $60M pre-deal valuation (C175)
B65: Total Offer Value — at Close | C65: =SUM(C63:C64) -> 3000 | D65: =IFERROR(C65/C$65,0) -> 1 | F65: Ties to Keystone Value Today (C173)
B66: (+) Cash Earnout — Year 3 (Contingent) | C66: =$C$57 -> 500 | D66: =IFERROR(C66/C$65,0) -> 0.16666667 | F66: Paid only if Year 3 revenue target is met (C57); % shown vs. offer value at close
B67: Total Consideration incl. Earnout | C67: =C65+C66 -> 3500 | D67: =IFERROR(C67/C$65,0) -> 1.1666667 | F67: Ties to Topkey's Total Consideration Paid
B69: Scenario 1 — Ben Retains 100% of Keystone | C69: =C$171 -> Today | D69: ="Year "&$C$7 -> Year 5
B70: Keystone Enterprise Value | C70: =ROUND(C172*C21,-1) -> 3000 | D70: =(C172+C27)*$C$22 -> 7490.2577 | F70: Today at offer value; Year 5 = (PF run-rate revenue + standalone added revenue) x standalone multiple
B71: Ben's Ownership % — Keystone | C71: ='Offer Overview'!$C$27 -> 1 | D71: =$C$71 -> 1
B72: Ben's Value — Scenario 1 | C72: =C70*C71 -> 3000 | D72: =D70*D71 -> 7490.2577
B74: Scenario 2 — Ben Accepts the Topkey Offer | C74: =C$171 -> Today | D74: =D$69 -> Year 5
B75: Topkey ex-Keystone Value | C75: =C179 -> 59500 | D75: =(C10+C17)*C12-C174-$C$57 -> 179000
B76: (+) Keystone Value — Post-Acquisition | C76: =C70 -> 3000 | D76: =(C41+C172)*C30 -> 13980.189 | F76: Today at offer value (same as Scenario 1)
B77: Combined Enterprise Value | C77: =C75+C76 -> 62500 | D77: =D75+D76 -> 192980.19
B78: Ben's Topkey Equity Value | C78: =C77*$C$178 -> 2500 | D78: =D77*$D$178 -> 7333.2472
B79: (+) Cash at Close | C79: =$C$174 -> 500 | D79: =$C$174 -> 500
B80: (+) Cash Earnout — Year 3 | D80: =$C$57 -> 500
B81: Ben's Value — Scenario 2 | C81: =C78+C79+C80 -> 3000 | D81: =D78+D79+D80 -> 8333.2472
B83: Scenario 2 vs. Scenario 1 | C83: =C$171 -> Today | D83: =D$69 -> Year 5
B84: Increase in Proceeds | C84: =C81-C72 -> 0 | D84: =D81-D72 -> 842.98949
B85: Delta (%) | C85: =IFERROR(C81/C72-1,0) -> 0 | D85: =IFERROR(D81/D72-1,0) -> 0.11254479
B86: Buyout MOIC — Keystone (Ben) | D86: =IFERROR(D81/C173,0) -> 2.7777491 | F86: Ben's Year 5 value (D79: cash + earnout + Topkey stock) ÷ Keystone value given up at close (C160)
B87: Buyout IRR — Keystone (Ben) | D87: =IFERROR(IRR(D199:D204),0) -> 0.266139 | F87: IRR on Ben's Scenario 2 cash flows (supporting table at rows 185-191); Year 5 = stake value, not a cash exit
B88: Break-Even Topkey CAGR | D88: =IFERROR((((D72-$C$174-$C$57)/$D$178-D76+$C$57)/$C$179)^(1/C$7)-1,0) -> 0.21465019
B89: Estimated Topkey CAGR | D89: =IFERROR(((D75+$C$57)/$C$179)^(1/$C$7)-1,0) -> 0.2471236
B91: Topkey's Return on the Keystone Acquisition | C91: Value
B92: Cash Paid at Close | C92: =C174 -> 500 | F92: Cash portion of offer (C161)
B93: (+) Topkey Equity Issued to Ben | C93: =C175 -> 2500 | F93: Topkey stock issued, at issue value (C162)
B94: (+) Cash Earnout — Year 3 | C94: =C57 -> 500 | F94: Cash earnout at base-case achievement (C55)
B95: Total Consideration Paid by Topkey | C95: =SUM(C92:C94) -> 3500 | F95: Everything Topkey gives up for Keystone
B96: (x) Topkey's Keystone Stake % | C96: 1 | F96: 100% buyout
B97: Keystone Enterprise Value — Year 5 | C97: =D76 -> 13980.189 | F97: Year 5 partnership value of Keystone (D74)
B98: Value of Topkey's Keystone Stake — Year 5 | C98: =C96*C97 -> 13980.189 | F98: Topkey's Year 5 value of Keystone
B99: MOIC — Topkey | C99: =IFERROR(C98/C95,0) -> 3.9943397 | F99: Year 5 stake value ÷ total consideration
B100: IRR — Topkey | C100: =IFERROR(IRR(D191:D196),0) -> 0.34242961 | F100: IRR on Topkey's cash flows (supporting table at rows 177-183); excludes software fee income and Keystone profits, so understated
B102: Internal - Implied Keystone Standalone Multiple | C102: =D$69 -> Year 5
B103: Year 5 Keystone Standalone Revenue | C103: =+C27+C172 -> 5992.2062
B104: (x) Steady-State Margins | C104: 0.15 | F104: Assumed steady-state EBITDA margin
B105: Year 5 EBITDA | C105: =C104*C103 -> 898.83092
B106: Year 5 Keystone Valuation | C106: =+D72 -> 7490.2577
B107: Implied EBITDA Multiple | C107: =C106/C105 -> 8.3333333
B109: Internal - Implied Keystone Partnership Multiple | C109: =D$69 -> Year 5
B110: Year 5 Keystone Partnership Revenue | C110: =+C41+C172 -> 6990.0945
B111: (x) Steady-State Margins | C111: 0.2 | F111: Assumed steady-state EBITDA margin with software integration
B112: Year 5 EBITDA | C112: =C111*C110 -> 1398.0189
B113: Year 5 Keystone Valuation | C113: =D76 -> 13980.189
B114: Implied EBITDA Multiple | C114: =C113/C112 -> 10
...

Sheet Partnership Analysis
B2: =Cover!$B$24 -> Keystone Bookkeepers
B3: Partnership Rollover Scenarios ($000s) | G3: Print | H3: 1
B5: Revenue Growth Assumptions | C5: Value | F5: Rationale / Notes
B6: General Assumptions
B7: Ben's Rollover % — Keystone | C7: 0.3 | F7: Share of Keystone Ben keeps; Topkey buys the rest for cash + Topkey equity (per AMB)
B8: Est. Topkey Dilution — Ben's Stake (Year 5) | C8: ='Offer Comparison'!$C$8 -> 0.05 | F8: AMB estimate: future Topkey equity issuance (capital raise, option pool, acquisitions) reduces Ben's Topkey % by this share by Year 5
B9: Horizon (Years) | C9: ='Offer Comparison'!$C$7 -> 5 | F9: Projection horizon for Year 5 columns
B10: Topkey - Current Monthly Revenue | C10: 261 | F10: Topkey-provided monthly revenue ($000s). Red: source pending confirmation
B11: Topkey - Current Run-Rate Revenue | C11: =C10*12 -> 3132
B12: Topkey - Current Revenue Multiple | C12: =IFERROR(C191/C11,0) -> 19.157088 | F12: Implied multiple: Topkey pre-deal valuation (C175) ÷ run-rate revenue (C10)
B13: Topkey - Future Revenue Multiple | C13: =C12 -> 19.157088 | F13: Assumed flat at current multiple
B14: Topkey - Current Client Count | C14: 325 | F14: Topkey-provided client count. Red: source pending confirmation
B15: Topkey - Avg. Revenue Per Client | C15: =C11/C14 -> 9.6369231
B16: Topkey - Annual Net Client Wins | C16: 130 | F16: AMB placeholder. Red: source pending confirmation
B17: Total Net Client Wins | C17: =C16*$C$9 -> 650
B18: Total Additional Revenue | C18: =C17*C15 -> 6264
B19: ="Check - "&$C$9&" Year Topkey Valuation Growth" -> Check - 5 Year Topkey Valuation Growth | C19: =IFERROR(D81/C81-1,0) -> 2.021904 | F19: % growth in Topkey ex-Keystone Value (row 80), Today → Year N
B21: Keystone Standalone Assumptions
B22: Revenue Multiple | C22: ='Offer Comparison'!$C$13 -> 1 | F22: Keystone standalone valued at 1.0x revenue (offer implies ~1.00x)
B23: Scaled Revenue Multiple | C23: ='Offer Comparison'!$C$14 -> 1.25 | F23: Future revenue multiple for Keystone
B24: Avg. Revenue Per Client | C24: =+'Steady-State Staffing'!AB8 -> 16.631473 | F24: Sep'26 annualized fee per non-tax client (Steady-State Staffing AB8)
B25: Target Monthly Net Client Wins | C25: 3 | F25: Target pace per AMB; LTM actual is 26/yr (~2.2/month), see build at rows 183-188
B26: Annual Net Client Wins | C26: =C25*12 -> 36 | F26: Target monthly pace × 12
B27: Total Net Client Wins | C27: =C26*$C$9 -> 180
B28: Total Additional Revenue | C28: =C27*C24 -> 2993.6651
B30: Keystone Partnership Assumptions
B31: Software-Integration Revenue Multiple | C31: ='Offer Comparison'!$C$15 -> 2 | F31: Assumed revenue multiple for software-integrated partnership
B32: VR Platform Run-Rate Tech Cost | C32: 240 | F32: Run-rate tech cost provided by the target
B34: =+B24 -> Avg. Revenue Per Client | C34: =+C24 -> 16.631473
B35: (+) Software-Enabled Price Increase / Client | C35: 0 | F35: Only if Topkey software supports higher client fees; VR cost treated as a cost (memo block at rows 190-200)
B36: Total Avg. Revenue Per Client | C36: =+C34+C35 -> 16.631473
B38: =+B26 -> Annual Net Client Wins | C38: =+C26 -> 36
B39: (+) Additional Annual Net Client Wins From Topkey | C39: 12 | F39: Topkey-provided. Red: source pending confirmation
B40: Total Annual Net Client Wins | C40: =SUM(C38:C39) -> 48
B41: Total Net Client Wins | C41: =C40*$C$9 -> 240
B42: Total Additional Revenue | C42: =C41*C36 -> 3991.5535
B43: Increase in Keystone Revenue vs. Standalone | C43: =C42-C28 -> 997.88838
B45: Cash Earnout — Year 3 Keystone Revenue (Sliding Scale)
B46: Earnout Measurement Year | C46: 3 | F46: Earnout measured on Year 3 run-rate: average of months 34–36 × 12 (see C55)
B47: Keystone Revenue at Close | C47: =C184 -> 2998.541 | F47: PF Jul'26 run-rate revenue at close (C168); unchanged
B48: Year 3 Run-Rate Revenue Target | C48: =C47+C42*(C46-(C57-1)/2/12)/C9 -> 5326.9472 | F48: Run-rate at close + partnership added revenue ramped to the midpoint of the averaging window (month 35 ÷ 60); same basis as the earnout measurement
B49: (x) Achievement vs. Target | C49: 1 | F49: Base case assumes the model's Year 3 revenue is achieved; flex to test payout
B50: Year 3 Run-Rate Revenue — Achieved | C50: =C48*C49 -> 5326.9472
B51: Threshold — % of Target | C51: 0.8 | F51: No earnout below this share of target; payout starts at the threshold % below
B52: Target Earnout — at 100% of Target | C52: 0 | F52: Initial position does not include earnout
B53: Payout at Threshold — % of Target Earnout | C53: 0.5 | F53: Share of target earnout paid at the 80% threshold
B54: Cap — % of Target Earnout | C54: 1.5 | F54: Payout capped at 120% of target, symmetric with the 80% threshold (50% at 80%, 150% at 120%)
B55: Payout % Earned | C55: =IF(C49<C51,0,MIN(C54,C53+(1-C53)*(C49-C51)/(1-C51))) -> 1 | F55: Straight line from threshold payout at 80% to 100% at target, continuing above target until the cap
B56: Maximum Earnout (Cap) | C56: =C52*C54 -> 0 | F56: Topkey's maximum earnout exposure
B57: Run-Rate Window — Months Averaged | C57: 3 | F57: Earnout measured on average monthly recurring revenue for the last 3 months of Year 3 (months 34–36) × 12; averaging prevents one strong month from triggering the payout
B58: Cash Earnout Payable — Year 3 | C58: =C52*C55 -> 0 | F58: Paid in cash by Topkey; flows into Scenario 2 (row 89), Ben's MOIC/IRR and Topkey's return (row 103)
B59: Probability of Achievement | C59: 0.7 | F59: AMB estimate for the memo line below
B60: Discount Rate | C60: 0.15 | F60: AMB estimate for the memo line below
B61: Risk-Weighted Earnout — PV at Close (Memo) | C61: =C58*C59/(1+C60)^C46 -> 0 | F61: Memo only; not used in Scenario 2
B63: Offer Structure | C63: =C$183 -> Today | D63: % of Total
B64: Cash at Close | C64: =$C$189 -> 650 | D64: =IFERROR(C64/C$67,0) -> 0.21666667 | F64: Cash paid at close for Topkey's stake (C189)
B65: (+) Topkey Equity Issued to Ben | C65: =$C$190 -> 1450 | D65: =IFERROR(C65/C$67,0) -> 0.48333333 | F65: Topkey stock issued at the $60M pre-deal valuation (C190)
B66: (+) Ben's Rolled Keystone Equity | C66: =$C$185*$C$186 -> 900 | D66: =IFERROR(C66/C$67,0) -> 0.3 | F66: Keystone value today × Ben's rollover % (C185 × C186)
B67: Total Offer Value — at Close | C67: =SUM(C64:C66) -> 3000 | D67: =IFERROR(C67/C$67,0) -> 1 | F67: Ties to Keystone Value Today (C185)
B68: (+) Cash Earnout — Year 3 (Contingent) | C68: =$C$58 -> 0 | D68: =IFERROR(C68/C$67,0) -> 0 | F68: Paid only if Year 3 revenue target is met (C58); % shown vs. offer value at close
B69: Total Consideration incl. Earnout | C69: =C67+C68 -> 3000 | D69: =IFERROR(C69/C$67,0) -> 1
B71: Scenario 1 — Ben Retains 100% of Keystone | C71: =C$183 -> Today | D71: ="Year "&$C$9 -> Year 5
B72: Keystone Enterprise Value | C72: =ROUND(C184*C22,-1) -> 3000 | D72: =(C184+C28)*$C$23 -> 7490.2577 | F72: Today at offer value; Year 5 = (PF run-rate revenue + standalone added revenue) x standalone multiple
B73: Ben's Ownership % — Keystone | C73: ='Offer Overview'!$C$27 -> 1 | D73: =$C$73 -> 1
B74: Ben's Value — Scenario 1 | C74: =C72*C73 -> 3000 | D74: =D72*D73 -> 7490.2577
B76: ="Scenario 2 — Ben Rolls "&TEXT($C$186,"0%")&" of Keystone Equity" -> Scenario 2 — Ben Rolls 30% of Keystone Equity | C76: =C$183 -> Today | D76: =D$71 -> Year 5
B77: Keystone Enterprise Value — Partnership | C77: =C185 -> 3000 | D77: =(C42+C184)*C31 -> 13980.189 | F77: Today at offer value; Year 5 = partnership revenue × partnership multiple (C29)
B78: (x) Ben's Retained Keystone % | C78: =$C$186 -> 0.3 | D78: =$C$186 -> 0.3
B79: Ben's Keystone Equity Value | C79: =C77*C78 -> 900 | D79: =D77*D78 -> 4194.0567 | F79: Ben's retained Keystone stake (C7 × Keystone value)
B81: Topkey ex-Keystone Value | C81: =C194 -> 59350 | D81: =(C11+C18)*C13-$C$189-$C$58 -> 179350
B82: (+) Topkey's Share of Keystone Value | C82: =C77*$C$187 -> 2100 | D82: =D77*$C$187 -> 9786.1324 | F82: Topkey's stake in Keystone is part of Topkey's value
B83: Topkey Combined Enterprise Value | C83: =C81+C82 -> 61450 | D83: =D81+D82 -> 189136.13
B84: (x) Ben's Topkey Ownership % | C84: =$C$193 -> 0.02359642 | D84: =$D$193 -> 0.022416599
B85: Ben's Topkey Equity Value | C85: =C83*C84 -> 1450 | D85: =D83*D84 -> 4239.7888 | F85: Ties to Topkey equity issued (tie-out row 180)
B86: Ben's Value by Source
B87: Keystone — Ben's Direct Retained Stake | C87: =C79 -> 900 | D87: =D79 -> 4194.0567 | F87: Keystone value Ben owns directly
B88: (+) Keystone — Ben's Indirect Share via Topkey | C88: =C82*C84 -> 49.552482 | D88: =D82*D84 -> 219.3718 | F88: Ben's Topkey % × Topkey's Keystone stake
B89: (+) Topkey ex-Keystone — Ben's Share | C89: =C81*C84 -> 1400.4475 | D89: =D81*D84 -> 4020.417 | F89: Ben's Topkey % × Topkey's own business
B90: (+) Cash at Close | C90: =$C$189 -> 650 | D90: =$C$189 -> 650
B91: (+) Cash Earnout — Year 3 | D91: =$C$58 -> 0
B92: Ben's Value — Scenario 2 | C92: =SUM(C87:C91) -> 3000 | D92: =SUM(D87:D91) -> 9083.8455 | F92: Direct Keystone + indirect Keystone + Topkey + cash
B94: Scenario 2 vs. Scenario 1 | C94: =C$183 -> Today | D94: =D$71 -> Year 5
B95: Increase in Proceeds | C95: =C92-C74 -> 0 | D95: =D92-D74 -> 1593.5878
B96: Delta (%) | C96: 0 | D96: =IFERROR(D92/D74-1,0) -> 0.21275474
B97: Partnership MOIC — Keystone (Ben) | D97: =IFERROR(D92/C185,0) -> 3.0279485 | F97: Ben's Year 5 value (D90: cash + earnout + retained stake + Topkey stock) ÷ Keystone value given up at close (C169)
B98: Partnership IRR — Keystone (Ben) | D98: =IFERROR(IRR(D227:D232),0) -> 0.29119417 | F98: IRR on Ben's Scenario 2 cash flows (supporting table at rows 210-216); Year 5 = stake values, not a cash exit
B99: Break-Even Topkey CAGR | C99: 0 | D99: =MAX(0,IFERROR(((C137+$C$58)/$C$194)^(1/$C$9)-1,0)) -> 0.12774199 | F99: Topkey revenue CAGR needed for Scenario 2 to equal Scenario 1 (from required value in C135, before earnout paid); floored at zero
B100: Estimated Topkey CAGR | C100: 0 | D100: =IFERROR(((D81+$C$58)/$C$194)^(1/$C$9)-1,0) -> 0.24754475
B102: Topkey's Return on the Keystone Stake | C102: Value
B103: Cash Paid at Close | C103: =C189 -> 650 | F103: Cash portion of stake price (C173)
B104: (+) Topkey Equity Issued to Ben | C104: =C190 -> 1450 | F104: Topkey stock issued, at issue value (C174)
B105: (+) Cash Earnout — Year 3 | C105: =C58 -> 0 | F105: Cash earnout at base-case achievement (C56)
B106: Total Consideration Paid by Topkey | C106: =SUM(C103:C105) -> 2100 | F106: Everything Topkey gives up for its Keystone stake
B107: (x) Topkey's Keystone Stake % | C107: =C187 -> 0.7 | F107: Topkey's share of Keystone (C171)
B108: Keystone Enterprise Value — Year 5 | C108: =D77 -> 13980.189 | F108: Year 5 partnership value of 100% of Keystone (D75)
B109: Value of Topkey's Keystone Stake — Year 5 | C109: =C107*C108 -> 9786.1324 | F109: Ties to Topkey's share of Keystone in Scenario 2 (D80)
B110: MOIC — Topkey | C110: =IFERROR(C109/C106,0) -> 4.660063 | F110: Year 5 stake value ÷ total consideration
B111: IRR — Topkey | C111: =IFERROR(IRR(D219:D224),0) -> 0.36043676 | F111: IRR on Topkey's cash flows (supporting table at rows 202-208); excludes software fee income and Keystone distributions, so understated
B113: Internal - Implied Keystone Standalone Multiple | C113: =D$71 -> Year 5
B114: Year 5 Keystone Standalone Revenue | C114: =+C28+C184 -> 5992.2062
...

Sheet P&L Overview
B2: =+Cover!B24 -> Keystone Bookkeepers
B3: Summary P&L Overview ($000s) | P3: Print | Q3: 1
C5: Full Year | F5: YTD | I5: LTM | K5: PF | M5: PF Delta
B6: P&L Summary | C6: 2024 | D6: 2025 | F6: July'25 | G6: July'26 | I6: July'25 | J6: July'26 | K6: July'26 | M6: ($) | N6: (%)
B7: Revenue
B8: =+'P&L Forecast'!B7 -> STR Subscription | C8: =+'P&L Forecast'!C7 -> 793.47225 | D8: =+'P&L Forecast'!D7 -> 1450.4923 | F8: =+'P&L Forecast'!F7 -> 751.5286 | G8: =+'P&L Forecast'!G7 -> 1261.4769 | I8: =+'P&L Forecast'!I7 -> 1152.3203 | J8: =+'P&L Forecast'!J7 -> 1960.4406 | K8: =+'P&L Forecast'!K7 -> 2410.05 | M8: =K8-J8 -> 449.6094 | N8: =IFERROR(K8/J8-1,0) -> 0.229341
B9: =+'P&L Forecast'!B8 -> Occupancy Taxes | C9: =+'P&L Forecast'!C8 -> 0.56 | D9: =+'P&L Forecast'!D8 -> 55.0805 | F9: =+'P&L Forecast'!F8 -> 23.2255 | G9: =+'P&L Forecast'!G8 -> 91.65114 | I9: =+'P&L Forecast'!I8 -> 23.7855 | J9: =+'P&L Forecast'!J8 -> 123.50614 | K9: =+'P&L Forecast'!K8 -> 192.8298 | M9: =K9-J9 -> 69.32366 | N9: =IFERROR(K9/J9-1,0) -> 0.56129728
B10: =+'P&L Forecast'!B9 -> SMB Subscription | C10: =+'P&L Forecast'!C9 -> 224.791 | D10: =+'P&L Forecast'!D9 -> 149.77 | F10: =+'P&L Forecast'!F9 -> 90.4525 | G10: =+'P&L Forecast'!G9 -> 73.4185 | I10: =+'P&L Forecast'!I9 -> 169.5465 | J10: =+'P&L Forecast'!J9 -> 132.736 | K10: =+'P&L Forecast'!K9 -> 16.2 | M10: =K10-J10 -> -116.536 | N10: =IFERROR(K10/J10-1,0) -> -0.87795323
B11: =+'P&L Forecast'!B10 -> Onboarding | C11: =+'P&L Forecast'!C10 -> 44.0585 | D11: =+'P&L Forecast'!D10 -> 74.5193 | F11: =+'P&L Forecast'!F10 -> 42.25405 | G11: =+'P&L Forecast'!G10 -> 59.055 | I11: =+'P&L Forecast'!I10 -> 57.49255 | J11: =+'P&L Forecast'!J10 -> 91.32025 | K11: =+'P&L Forecast'!K10 -> 103.5675 | M11: =K11-J11 -> 12.24725 | N11: =IFERROR(K11/J11-1,0) -> 0.13411319
B12: =+'P&L Forecast'!B11 -> Topkey Subscription | C12: =+'P&L Forecast'!C11 -> 0 | D12: =+'P&L Forecast'!D11 -> 9.947 | F12: =+'P&L Forecast'!F11 -> 0 | G12: =+'P&L Forecast'!G11 -> 45.086 | I12: =+'P&L Forecast'!I11 -> 0 | J12: =+'P&L Forecast'!J11 -> 55.033 | K12: =+'P&L Forecast'!K11 -> 94.836 | M12: =K12-J12 -> 39.803 | N12: =IFERROR(K12/J12-1,0) -> 0.72325695
B13: =+'P&L Forecast'!B12 -> STR Bill Pay | C13: =+'P&L Forecast'!C12 -> 0.06 | D13: =+'P&L Forecast'!D12 -> 36.6065 | F13: =+'P&L Forecast'!F12 -> 15.4915 | G13: =+'P&L Forecast'!G12 -> 45.13 | I13: =+'P&L Forecast'!I12 -> 15.5515 | J13: =+'P&L Forecast'!J12 -> 66.245 | K13: =+'P&L Forecast'!K12 -> 83.46 | M13: =K13-J13 -> 17.215 | N13: =IFERROR(K13/J13-1,0) -> 0.25986867
B14: =+'P&L Forecast'!B13 -> Controller Services | C14: =+'P&L Forecast'!C13 -> 13.75 | D14: =+'P&L Forecast'!D13 -> 46.4 | F14: =+'P&L Forecast'!F13 -> 31.5 | G14: =+'P&L Forecast'!G13 -> 24.25 | I14: =+'P&L Forecast'!I13 -> 44 | J14: =+'P&L Forecast'!J13 -> 39.15 | K14: =+'P&L Forecast'!K13 -> 42 | M14: =K14-J14 -> 2.85 | N14: =IFERROR(K14/J14-1,0) -> 0.072796935
B15: Other Revenue | C15: =+C16-SUM(C8:C14) -> 58.2741 | D15: =+D16-SUM(D8:D14) -> 56.56748 | F15: =+F16-SUM(F8:F14) -> 43.42095 | G15: =+G16-SUM(G8:G14) -> 70.95371 | I15: =+I16-SUM(I8:I14) -> 61.71435 | J15: =+J16-SUM(J8:J14) -> 84.10024 | K15: =+K16-SUM(K8:K14) -> 55.59772 | M15: =K15-J15 -> -28.50252 | N15: =IFERROR(K15/J15-1,0) -> -0.33891128
B16: Total Run-Rate Revenue | C16: =+'P&L Forecast'!C24 -> 1134.9659 | D16: =+'P&L Forecast'!D24 -> 1879.3831 | F16: =+'P&L Forecast'!F24 -> 997.8731 | G16: =+'P&L Forecast'!G24 -> 1671.0212 | I16: =+'P&L Forecast'!I24 -> 1524.4107 | J16: =+'P&L Forecast'!J24 -> 2552.5312 | K16: =+'P&L Forecast'!K24 -> 2998.541 | M16: =SUM(M8:M15) -> 446.00979 | N16: =IFERROR(K16/J16-1,0) -> 0.17473235
B17: Unclassified Active Client Revenue | C17: =+'P&L Forecast'!C26 -> 0 | D17: =+'P&L Forecast'!D26 -> 0 | F17: =+'P&L Forecast'!F26 -> 0 | G17: =+'P&L Forecast'!G26 -> 0 | I17: =+'P&L Forecast'!I26 -> 0 | J17: =+'P&L Forecast'!J26 -> 0 | K17: =+'P&L Forecast'!K26 -> 93.9827 | M17: =K17-J17 -> 93.9827 | N17: =IFERROR(K17/J17-1,0) -> 0
B18: Total Adj. Revenue | C18: =+'P&L Forecast'!C28 -> 1134.9659 | D18: =+'P&L Forecast'!D28 -> 1879.3831 | F18: =+'P&L Forecast'!F28 -> 997.8731 | G18: =+'P&L Forecast'!G28 -> 1671.0212 | I18: =+'P&L Forecast'!I28 -> 1524.4107 | J18: =+'P&L Forecast'!J28 -> 2552.5312 | K18: =+'P&L Forecast'!K28 -> 3092.5237 | M18: =SUM(M16:M17) -> 539.99249 | N18: =IFERROR(K18/J18-1,0) -> 0.21155177
B20: Expenses
B21: =+'P&L Forecast'!B31 -> Indirect Labor | C21: =+'P&L Forecast'!C31 -> 101.3752 | D21: =+'P&L Forecast'!D31 -> 281.24054 | F21: =+'P&L Forecast'!F31 -> 136.29648 | G21: =+'P&L Forecast'!G31 -> 357.27472 | I21: =+'P&L Forecast'!I31 -> 202.41598 | J21: =+'P&L Forecast'!J31 -> 502.21878 | K21: =+'P&L Forecast'!K31 -> 681.3 | M21: =K21-J21 -> 179.08122 | N21: =IFERROR(K21/J21-1,0) -> 0.35658009 | P21: =K21/$K$30 -> 0.32533849
B22: =+'P&L Forecast'!B32 -> Bookkeeper Wages | C22: =+'P&L Forecast'!C32 -> 183.36903 | D22: =+'P&L Forecast'!D32 -> 316.18462 | F22: =+'P&L Forecast'!F32 -> 147.26813 | G22: =+'P&L Forecast'!G32 -> 267.7574 | I22: =+'P&L Forecast'!I32 -> 240.18098 | J22: =+'P&L Forecast'!J32 -> 436.67389 | K22: =+'P&L Forecast'!K32 -> 492.6 | M22: =K22-J22 -> 55.92611 | N22: =IFERROR(K22/J22-1,0) -> 0.12807294 | P22: =K22/$K$30 -> 0.23522933
B23: =+'P&L Forecast'!B33 -> Client Lead Wages | C23: =+'P&L Forecast'!C33 -> 286.16129 | D23: =+'P&L Forecast'!D33 -> 352.95844 | F23: =+'P&L Forecast'!F33 -> 201.27983 | G23: =+'P&L Forecast'!G33 -> 202.05309 | I23: =+'P&L Forecast'!I33 -> 353.12843 | J23: =+'P&L Forecast'!J33 -> 353.7317 | K23: =+'P&L Forecast'!K33 -> 392.92452 | M23: =K23-J23 -> 39.19282 | N23: =IFERROR(K23/J23-1,0) -> 0.11079816 | P23: =K23/$K$30 -> 0.18763169
B24: =+'P&L Forecast'!B34 -> Onboarding Team Wages | C24: =+'P&L Forecast'!C34 -> 122.81255 | D24: =+'P&L Forecast'!D34 -> 152.16972 | F24: =+'P&L Forecast'!F34 -> 73.94962 | G24: =+'P&L Forecast'!G34 -> 111.27999 | I24: =+'P&L Forecast'!I34 -> 121.30735 | J24: =+'P&L Forecast'!J34 -> 189.50009 | K24: =+'P&L Forecast'!K34 -> 197.14944 | M24: =K24-J24 -> 7.64935 | N24: =IFERROR(K24/J24-1,0) -> 0.040365944 | P24: =K24/$K$30 -> 0.094143992
B25: =+'P&L Forecast'!B35 -> Owner Wages | C25: =+'P&L Forecast'!C35 -> 0 | D25: =+'P&L Forecast'!D35 -> 90.66704 | F25: =+'P&L Forecast'!F35 -> 45.46612 | G25: =+'P&L Forecast'!G35 -> 63.14302 | I25: =+'P&L Forecast'!I35 -> 45.46612 | J25: =+'P&L Forecast'!J35 -> 108.34394 | K25: =+'P&L Forecast'!K35 -> 108.34394 | M25: =K25-J25 -> 0 | N25: =IFERROR(K25/J25-1,0) -> 0 | P25: =K25/$K$30 -> 0.051737053
B26: =+'P&L Forecast'!B36 -> S&M Wages | C26: =+'P&L Forecast'!C36 -> 0 | D26: =+'P&L Forecast'!D36 -> 19.14963 | F26: =+'P&L Forecast'!F36 -> 3.09945 | G26: =+'P&L Forecast'!G36 -> 51.94131 | I26: =+'P&L Forecast'!I36 -> 3.09945 | J26: =+'P&L Forecast'!J36 -> 67.99149 | K26: =+'P&L Forecast'!K36 -> 98.34912 | M26: =K26-J26 -> 30.35763 | N26: =IFERROR(K26/J26-1,0) -> 0.44649161 | P26: =K26/$K$30 -> 0.046964266
B27: =+'P&L Forecast'!B37 -> Occupancy Tax Specialist | C27: =+'P&L Forecast'!C37 -> 1.11335 | D27: =+'P&L Forecast'!D37 -> 29.56415 | F27: =+'P&L Forecast'!F37 -> 14.27585 | G27: =+'P&L Forecast'!G37 -> 42.08505 | I27: =+'P&L Forecast'!I37 -> 15.3892 | J27: =+'P&L Forecast'!J37 -> 57.37335 | K27: =+'P&L Forecast'!K37 -> 58.2 | M27: =K27-J27 -> 0.82665 | N27: =IFERROR(K27/J27-1,0) -> 0.014408257 | P27: =K27/$K$30 -> 0.027792016
B28: =+'P&L Forecast'!B38 -> Sr. Client Lead Wages | C28: =+'P&L Forecast'!C38 -> 0 | D28: =+'P&L Forecast'!D38 -> 0 | F28: =+'P&L Forecast'!F38 -> 0 | G28: =+'P&L Forecast'!G38 -> 7.995 | I28: =+'P&L Forecast'!I38 -> 0 | J28: =+'P&L Forecast'!J38 -> 7.995 | K28: =+'P&L Forecast'!K38 -> 33.08124 | M28: =K28-J28 -> 25.08624 | N28: =IFERROR(K28/J28-1,0) -> 3.1377411 | P28: =K28/$K$30 -> 0.015797154
B29: =+'P&L Forecast'!B39 -> Employee Benefits | C29: =+'P&L Forecast'!C39 -> 5.37405 | D29: =+'P&L Forecast'!D39 -> 19.23245 | F29: =+'P&L Forecast'!F39 -> 9.02166 | G29: =+'P&L Forecast'!G39 -> 17.36251 | I29: =+'P&L Forecast'!I39 -> 12.16686 | J29: =+'P&L Forecast'!J39 -> 27.5733 | K29: =+'P&L Forecast'!K39 -> 32.17836 | M29: =K29-J29 -> 4.60506 | N29: =IFERROR(K29/J29-1,0) -> 0.16701157 | P29: =K29/$K$30 -> 0.015366005
B30: =+'P&L Forecast'!B40 -> Total Payroll Expenses | C30: =SUM(C21:C29) -> 700.20547 | D30: =SUM(D21:D29) -> 1261.1666 | F30: =SUM(F21:F29) -> 630.65714 | G30: =SUM(G21:G29) -> 1120.8921 | I30: =SUM(I21:I29) -> 993.15437 | J30: =SUM(J21:J29) -> 1751.4015 | K30: =SUM(K21:K29) -> 2094.1266 | M30: =SUM(M21:M29) -> 342.72508 | N30: =K30/J30-1 -> 0.19568618
B32: =+'P&L Forecast'!B42 -> Software & Apps - COGS | C32: =+'P&L Forecast'!C42 -> 114.42269 | D32: =+'P&L Forecast'!D42 -> 157.49471 | F32: =+'P&L Forecast'!F42 -> 84.96859 | G32: =+'P&L Forecast'!G42 -> 152.28157 | I32: =+'P&L Forecast'!I42 -> 142.28345 | J32: =+'P&L Forecast'!J42 -> 224.80769 | K32: =+'P&L Forecast'!K42 -> 335.70816 | M32: =K32-J32 -> 110.90047 | N32: =IFERROR(K32/J32-1,0) -> 0.49331262
B33: =+'P&L Forecast'!B43 -> Software & Apps - G&A | C33: =+'P&L Forecast'!C43 -> 60.91594 | D33: =+'P&L Forecast'!D43 -> 117.05866 | F33: =+'P&L Forecast'!F43 -> 56.8115 | G33: =+'P&L Forecast'!G43 -> 97.04798 | I33: =+'P&L Forecast'!I43 -> 86.51489 | J33: =+'P&L Forecast'!J43 -> 157.29514 | K33: =+'P&L Forecast'!K43 -> 155.82264 | M33: =K33-J33 -> -1.4725 | N33: =IFERROR(K33/J33-1,0) -> -0.0093613827
B34: =+'P&L Forecast'!B44 -> Software & Apps - Topkey | C34: =+'P&L Forecast'!C44 -> 0 | D34: =+'P&L Forecast'!D44 -> 7.14125 | F34: =+'P&L Forecast'!F44 -> 0 | G34: =+'P&L Forecast'!G44 -> 28.82775 | I34: =+'P&L Forecast'!I44 -> 0 | J34: =+'P&L Forecast'!J44 -> 35.969 | K34: =+'P&L Forecast'!K44 -> 60.84 | M34: =K34-J34 -> 24.871 | N34: =IFERROR(K34/J34-1,0) -> 0.69145653
B35: =+'P&L Forecast'!B45 -> Software & Apps - AI tools | C35: =+'P&L Forecast'!C45 -> 0 | D35: =+'P&L Forecast'!D45 -> 0 | F35: =+'P&L Forecast'!F45 -> 0 | G35: =+'P&L Forecast'!G45 -> 6.52752 | I35: =+'P&L Forecast'!I45 -> 0 | J35: =+'P&L Forecast'!J45 -> 6.52752 | K35: =+'P&L Forecast'!K45 -> 15.74376 | M35: =K35-J35 -> 9.21624 | N35: =IFERROR(K35/J35-1,0) -> 1.4119053
B36: =+'P&L Forecast'!B46 -> Total Software Expenses | C36: =SUM(C32:C35) -> 175.33863 | D36: =SUM(D32:D35) -> 281.69462 | F36: =SUM(F32:F35) -> 141.78009 | G36: =SUM(G32:G35) -> 284.68482 | I36: =SUM(I32:I35) -> 228.79834 | J36: =SUM(J32:J35) -> 424.59935 | K36: =SUM(K32:K35) -> 568.11456 | M36: =SUM(M32:M35) -> 143.51521 | N36: =K36/J36-1 -> 0.33800148
B38: =+'P&L Forecast'!B48 -> Other Professional Fees | C38: =+'P&L Forecast'!C48 -> 18.23425 | D38: =+'P&L Forecast'!D48 -> 27.04095 | F38: =+'P&L Forecast'!F48 -> 12.014 | G38: =+'P&L Forecast'!G48 -> 57.55 | I38: =+'P&L Forecast'!I48 -> 21.74858 | J38: =+'P&L Forecast'!J48 -> 72.57695 | K38: =+'P&L Forecast'!K48 -> 72.57695 | M38: =K38-J38 -> 0 | N38: =IFERROR(K38/J38-1,0) -> 0
B39: =+'P&L Forecast'!B49 -> Referral Fees | C39: =+'P&L Forecast'!C49 -> 24.82 | D39: =+'P&L Forecast'!D49 -> 27.15374 | F39: =+'P&L Forecast'!F49 -> 17.0895 | G39: =+'P&L Forecast'!G49 -> 20.62969 | I39: =+'P&L Forecast'!I49 -> 26.2095 | J39: =+'P&L Forecast'!J49 -> 30.69393 | K39: =+'P&L Forecast'!K49 -> 30.69393 | M39: =K39-J39 -> 0 | N39: =IFERROR(K39/J39-1,0) -> 0
B40: =+'P&L Forecast'!B50 -> Travel, Meals & Entertainment | C40: =+'P&L Forecast'!C50 -> 0 | D40: =+'P&L Forecast'!D50 -> 29.76122 | F40: =+'P&L Forecast'!F50 -> 22.29558 | G40: =+'P&L Forecast'!G50 -> 20.68542 | I40: =+'P&L Forecast'!I50 -> 22.29558 | J40: =+'P&L Forecast'!J50 -> 28.15106 | K40: =+'P&L Forecast'!K50 -> 28.15106 | M40: =K40-J40 -> 0 | N40: =IFERROR(K40/J40-1,0) -> 0
B41: =+'P&L Forecast'!B51 -> Payment Collection Fees | C41: =+'P&L Forecast'!C51 -> 8.67099 | D41: =+'P&L Forecast'!D51 -> 13.35153 | F41: =+'P&L Forecast'!F51 -> 6.80445 | G41: =+'P&L Forecast'!G51 -> 9.02684 | I41: =+'P&L Forecast'!I51 -> 10.54373 | J41: =+'P&L Forecast'!J51 -> 15.57392 | K41: =+'P&L Forecast'!K51 -> 15.57392 | M41: =K41-J41 -> 0 | N41: =IFERROR(K41/J41-1,0) -> 0
B42: =+'P&L Forecast'!B52 -> Professional Organizations | C42: =+'P&L Forecast'!C52 -> 5.44332 | D42: =+'P&L Forecast'!D52 -> 11.22296 | F42: =+'P&L Forecast'!F52 -> 6.191 | G42: =+'P&L Forecast'!G52 -> 6.57881 | I42: =+'P&L Forecast'!I52 -> 9.53268 | J42: =+'P&L Forecast'!J52 -> 11.61077 | K42: =+'P&L Forecast'!K52 -> 11.61077 | M42: =K42-J42 -> 0 | N42: =IFERROR(K42/J42-1,0) -> 0
B43: =+'P&L Forecast'!B53 -> S&M Events | C43: =+'P&L Forecast'!C53 -> 0 | D43: =+'P&L Forecast'!D53 -> 11.4983 | F43: =+'P&L Forecast'!F53 -> 0 | G43: =+'P&L Forecast'!G53 -> 11.84548 | I43: =+'P&L Forecast'!I53 -> 0 | J43: =+'P&L Forecast'!J53 -> 23.34378 | K43: =+'P&L Forecast'!K53 -> 23.34378 | M43: =K43-J43 -> 0 | N43: =IFERROR(K43/J43-1,0) -> 0
B44: =+'P&L Forecast'!B54 -> Contract Labor - Tax | C44: =+'P&L Forecast'!C54 -> 0 | D44: =+'P&L Forecast'!D54 -> 1.5875 | F44: =+'P&L Forecast'!F54 -> 0 | G44: =+'P&L Forecast'!G54 -> 30.5155 | I44: =+'P&L Forecast'!I54 -> 0 | J44: =+'P&L Forecast'!J54 -> 32.103 | K44: =+'P&L Forecast'!K54 -> 38.7615 | M44: =K44-J44 -> 6.6585 | N44: =IFERROR(K44/J44-1,0) -> 0.20741052
B45: =+'P&L Forecast'!B55 -> Recruiting Fees | C45: =+'P&L Forecast'!C55 -> 14.90205 | D45: =+'P&L Forecast'!D55 -> 31.6041 | F45: =+'P&L Forecast'!F55 -> 28.29994 | G45: =+'P&L Forecast'!G55 -> 5.5646 | I45: =+'P&L Forecast'!I55 -> 35.34606 | J45: =+'P&L Forecast'!J55 -> 8.86876 | K45: =+'P&L Forecast'!K55 -> 8.86876 | M45: =K45-J45 -> 0 | N45: =IFERROR(K45/J45-1,0) -> 0
B46: Other Expenses | C46: =+C47-SUM(C38:C45) -> 41.87929 | D46: =+D47-SUM(D38:D45) -> 52.32132 | F46: =+F47-SUM(F38:F45) -> 28.90542 | G46: =+G47-SUM(G38:G45) -> 26.90445 | I46: =+I47-SUM(I38:I45) -> 41.76881 | J46: =+J47-SUM(J38:J45) -> 50.32035 | K46: =+K47-SUM(K38:K45) -> 56.05462 | M46: =K46-J46 -> 5.73427 | N46: =IFERROR(K46/J46-1,0) -> 0.11395529
B47: Total Overhead | C47: =+'P&L Forecast'!C66 -> 113.9499 | D47: =+'P&L Forecast'!D66 -> 205.54162 | F47: =+'P&L Forecast'!F66 -> 121.59989 | G47: =+'P&L Forecast'!G66 -> 189.30079 | I47: =+'P&L Forecast'!I66 -> 167.44494 | J47: =+'P&L Forecast'!J66 -> 273.24252 | K47: =+'P&L Forecast'!K66 -> 285.63529 | M47: =SUM(M38:M46) -> 12.39277 | N47: =K47/J47-1 -> 0.045354471
B49: Net Income | C49: =+C16-C30-C36-C47 -> 145.47185 | D49: =+D16-D30-D36-D47 -> 130.9803 | F49: =+F16-F30-F36-F47 -> 103.83598 | G49: =+G16-G30-G36-G47 -> 76.1435 | I49: =+I16-I30-I36-I47 -> 135.013 | J49: =+J16-J30-J36-J47 -> 103.28782 | K49: =+K16-K30-K36-K47 -> 50.66455 | M49: =+M16-M30-M36-M47 -> -52.62327 | N49: =IFERROR(K49/J49-1,0) -> -0.50948185
B50: % Margin | C50: =C49/C$16 -> 0.12817289 | D50: =D49/D$16 -> 0.06969324 | F50: =F49/F$16 -> 0.1040573 | G50: =G49/G$16 -> 0.045567046 | I50: =I49/I$16 -> 0.088567342 | J50: =J49/J$16 -> 0.04046486 | K50: =K49/K$16 -> 0.016896401 | M50: =M49/M$16 -> -0.1179868 | N50: 0
B52: P&L Adjustments
B53: Karbon, Uncat, & Xenett Savings | C53: =+'P&L Forecast'!C91 -> 0 | D53: =+'P&L Forecast'!D91 -> 0 | F53: =+'P&L Forecast'!F91 -> 0 | G53: =+'P&L Forecast'!G91 -> 0 | I53: =+'P&L Forecast'!I91 -> 0 | J53: =+'P&L Forecast'!J91 -> 0 | K53: =+'P&L Forecast'!K91 -> 96.8 | M53: =K53-J53 -> 96.8 | N53: =IFERROR(K53/J53-1,0) -> 0
B54: Other Professional Fees | C54: =+'P&L Forecast'!C90 -> 18.23425 | D54: =+'P&L Forecast'!D90 -> 27.04095 | F54: =+'P&L Forecast'!F90 -> 12.014 | G54: =+'P&L Forecast'!G90 -> 57.55 | I54: =+'P&L Forecast'!I90 -> 21.74858 | J54: =+'P&L Forecast'!J90 -> 72.57695 | K54: =+'P&L Forecast'!K90 -> 72.57695 | M54: =K54-J54 -> 0 | N54: =IFERROR(K54/J54-1,0) -> 0
B55: Unclassified Active Client Contribution | C55: =+'P&L Forecast'!C92 -> 0 | D55: =+'P&L Forecast'!D92 -> 0 | F55: =+'P&L Forecast'!F92 -> 0 | G55: =+'P&L Forecast'!G92 -> 0 | I55: =+'P&L Forecast'!I92 -> 0 | J55: =+'P&L Forecast'!J92 -> 0 | K55: =+'P&L Forecast'!K92 -> 50.703313 | M55: =K55-J55 -> 50.703313 | N55: =IFERROR(K55/J55-1,0) -> 0
B56: Definitional EBITDA Adj. | C56: =SUM('P&L Forecast'!C75:C77) -> 14.24964 | D56: =SUM('P&L Forecast'!D75:D77) -> 18.07948 | F56: =SUM('P&L Forecast'!F75:F77) -> 6.97104 | G56: =SUM('P&L Forecast'!G75:G77) -> 1.98303 | I56: =SUM('P&L Forecast'!I75:I77) -> 12.50268 | J56: =SUM('P&L Forecast'!J75:J77) -> 13.09147 | K56: =SUM('P&L Forecast'!K75:K77) -> 13.09147 | M56: =K56-J56 -> 0 | N56: =IFERROR(K56/J56-1,0) -> 0
B57: Personal Expenses | C57: =+'P&L Forecast'!C82+'P&L Forecast'!C83 -> 1.05983 | D57: =+'P&L Forecast'!D82+'P&L Forecast'!D83 -> 5.99533 | F57: =+'P&L Forecast'!F82+'P&L Forecast'!F83 -> 2.02633 | G57: =+'P&L Forecast'!G82+'P&L Forecast'!G83 -> 1.943 | I57: =+'P&L Forecast'!I82+'P&L Forecast'!I83 -> 2.45133 | J57: =+'P&L Forecast'!J82+'P&L Forecast'!J83 -> 5.912 | K57: =+'P&L Forecast'!K82+'P&L Forecast'!K83 -> 5.912 | M57: =K57-J57 -> 0 | N57: =IFERROR(K57/J57-1,0) -> 0
B58: Onboarding Manager | C58: =+'P&L Forecast'!C89 -> 0 | D58: =+'P&L Forecast'!D89 -> 0 | F58: =+'P&L Forecast'!F89 -> 0 | G58: =+'P&L Forecast'!G89 -> 0 | I58: =+'P&L Forecast'!I89 -> 0 | J58: =+'P&L Forecast'!J89 -> 0 | K58: =+'P&L Forecast'!K89 -> -116.25 | M58: =K58-J58 -> -116.25 | N58: =IFERROR(K58/J58-1,0) -> 0
B59: Go-Forward Owner Comp | C59: =+'P&L Forecast'!C88 -> -228.245 | D59: =+'P&L Forecast'!D88 -> -137.57796 | F59: =+'P&L Forecast'!F88 -> -182.77888 | G59: =+'P&L Forecast'!G88 -> -165.10198 | I59: =+'P&L Forecast'!I88 -> -182.77888 | J59: =+'P&L Forecast'!J88 -> -119.90106 | K59: =+'P&L Forecast'!K88 -> -119.90106 | M59: =K59-J59 -> 0 | N59: =IFERROR(K59/J59-1,0) -> 0
B60: Total Near-Term Adjustments | C60: =SUM(C53:C59) -> -194.70128 | D60: =SUM(D53:D59) -> -86.4622 | F60: =SUM(F53:F59) -> -161.76751 | G60: =SUM(G53:G59) -> -103.62595 | I60: =SUM(I53:I59) -> -146.07629 | J60: =SUM(J53:J59) -> -28.32064 | K60: =SUM(K53:K59) -> 2.9326728 | M60: =SUM(M53:M59) -> 31.253313 | N60: =K60/J60-1 -> -1.1035525
B62: =+'P&L Forecast'!B95 -> Near-Term Adj. EBITDA | C62: =+C49+C60 -> -49.22943 | D62: =+D49+D60 -> 44.5181 | F62: =+F49+F60 -> -57.93153 | G62: =+G49+G60 -> -27.48245 | I62: =+I49+I60 -> -11.06329 | J62: =+J49+J60 -> 74.96718 | K62: =+K49+K60 -> 53.597223 | M62: =+M49+M60 -> -21.369957 | N62: =IFERROR(K62/J62-1,0) -> -0.2850575
B63: % Margin | C63: =C62/C$18 -> -0.043375252 | D63: =D62/D$18 -> 0.023687613 | F63: =F62/F$18 -> -0.058055007 | G63: =G62/G$18 -> -0.0164465 | I63: =I62/I$18 -> -0.0072574211 | J63: =J62/J$18 -> 0.029369741 | K63: =K62/K$18 -> 0.017331224 | M63: =M62/M$16 -> -0.047913651 | N63: 0
B65: Normalized Bookkeeper Staffing | C65: =+'P&L Forecast'!C101 -> 0 | D65: =+'P&L Forecast'!D101 -> 0 | F65: =+'P&L Forecast'!F101 -> 0 | G65: =+'P&L Forecast'!G101 -> 0 | I65: =+'P&L Forecast'!I101 -> 0 | J65: =+'P&L Forecast'!J101 -> 0 | K65: =+'P&L Forecast'!K101 -> 220.13063 | M65: =K65-J65 -> 220.13063 | N65: =IFERROR(K65/J65-1,0) -> 0
B66: VR Platform Cost Savings | C66: =+'P&L Forecast'!C102 -> 0 | D66: =+'P&L Forecast'!D102 -> 0 | F66: =+'P&L Forecast'!F102 -> 0 | G66: =+'P&L Forecast'!G102 -> 0 | I66: =+'P&L Forecast'!I102 -> 0 | J66: =+'P&L Forecast'!J102 -> 0 | K66: =+'P&L Forecast'!K102 -> 143.23972 | M66: =K66-J66 -> 143.23972 | N66: =IFERROR(K66/J66-1,0) -> 0
B67: Onboarding Team Wages | C67: =+'P&L Forecast'!C100 -> 0 | D67: =+'P&L Forecast'!D100 -> 0 | F67: =+'P&L Forecast'!F100 -> 0 | G67: =+'P&L Forecast'!G100 -> 0 | I67: =+'P&L Forecast'!I100 -> 0 | J67: =+'P&L Forecast'!J100 -> 0 | K67: =+'P&L Forecast'!K100 -> 49.28736 | M67: =K67-J67 -> 49.28736 | N67: =IFERROR(K67/J67-1,0) -> 0
B68: S&M Wages | C68: =+'P&L Forecast'!C103 -> 0 | D68: =+'P&L Forecast'!D103 -> 0 | F68: =+'P&L Forecast'!F103 -> 0 | G68: =+'P&L Forecast'!G103 -> 0 | I68: =+'P&L Forecast'!I103 -> 0 | J68: =+'P&L Forecast'!J103 -> 0 | K68: =+'P&L Forecast'!K103 -> 28.2 | M68: =K68-J68 -> 28.2 | N68: =IFERROR(K68/J68-1,0) -> 0
B69: Onboarding Revenue | C69: =+'P&L Forecast'!C99 -> 0 | D69: =+'P&L Forecast'!D99 -> 0 | F69: =+'P&L Forecast'!F99 -> 0 | G69: =+'P&L Forecast'!G99 -> 0 | I69: =+'P&L Forecast'!I99 -> 0 | J69: =+'P&L Forecast'!J99 -> 0 | K69: =+'P&L Forecast'!K99 -> -25.891875 | M69: =K69-J69 -> -25.891875 | N69: =IFERROR(K69/J69-1,0) -> 0
B70: Total Steady-State Adj. | C70: =SUM(C65:C69) -> 0 | D70: =SUM(D65:D69) -> 0 | F70: =SUM(F65:F69) -> 0 | G70: =SUM(G65:G69) -> 0 | I70: =SUM(I65:I69) -> 0 | J70: =SUM(J65:J69) -> 0 | K70: =SUM(K65:K69) -> 414.96583 | M70: =SUM(M65:M69) -> 414.96583 | N70: =IFERROR(K70/J70-1,0) -> 0
B72: =+'P&L Forecast'!B106 -> Steady-State Adj. EBITDA | C72: =+C70+C62 -> -49.22943 | D72: =+D70+D62 -> 44.5181 | F72: =+F70+F62 -> -57.93153 | G72: =+G70+G62 -> -27.48245 | I72: =+I70+I62 -> -11.06329 | J72: =+J70+J62 -> 74.96718 | K72: =+K70+K62 -> 468.56306 | M72: =+M70+M62 -> 393.59588 | N72: =IFERROR(K72/J72-1,0) -> 5.2502425
B73: % Margin | C73: =C72/C$18 -> -0.043375252 | D73: =D72/D$18 -> 0.023687613 | F73: =F72/F$18 -> -0.058055007 | G73: =G72/G$18 -> -0.0164465 | I73: =I72/I$18 -> -0.0072574211 | J73: =J72/J$18 -> 0.029369741 | K73: =K72/K$18 -> 0.15151478 | M73: =M72/M$16 -> 0.8824826 | N73: 0

Sheet Software Overview
B2: =+Cover!B24 -> Keystone Bookkeepers
B3: Software Utilization Overview ($)
B5: Software Utilization | C5: Current Clients | G5: Former Clients | K5: Total
B6: Bill Pay | C6: Clients | D6: Properties | E6: Avg. Monthly Fee | G6: Clients | H6: Properties | I6: Avg. Monthly Fee | K6: Clients | L6: Properties | M6: % of Clients
B7: Yes | C7: =COUNTIFS('Customer List w Software'!$B$4:$B$310,"<>Former client",'Customer List w Software'!$V$4:$V$310,$B7) -> 41 | D7: =SUMIFS('Customer List w Software'!$K$4:$K$310,'Customer List w Software'!$B$4:$B$310,"<>Former client",'Customer List w Software'!$V$4:$V$310,$B7) -> 1285 | E7: =IFERROR(AVERAGEIFS('Customer List w Software'!$J$4:$J$310,'Customer List w Software'!$B$4:$B$310,"<>Former client",'Customer List w Software'!$V$4:$V$310,$B7),0) -> 2011.8227 | G7: =COUNTIFS('Customer List w Software'!$B$4:$B$310,"Former client",'Customer List w Software'!$V$4:$V$310,$B7) -> 4 | H7: =SUMIFS('Customer List w Software'!$K$4:$K$310,'Customer List w Software'!$B$4:$B$310,"Former client",'Customer List w Software'!$V$4:$V$310,$B7) -> 72 | I7: =IFERROR(AVERAGEIFS('Customer List w Software'!$J$4:$J$310,'Customer List w Software'!$B$4:$B$310,"Former client",'Customer List w Software'!$V$4:$V$310,$B7),0) -> 1602.6667 | K7: =C7+G7 -> 45 | L7: =D7+H7 -> 1357 | M7: =K7/K$10 -> 0.1465798
B8: No | C8: =COUNTIFS('Customer List w Software'!$B$4:$B$310,"<>Former client",'Customer List w Software'!$V$4:$V$310,$B8) -> 133 | D8: =SUMIFS('Customer List w Software'!$K$4:$K$310,'Customer List w Software'!$B$4:$B$310,"<>Former client",'Customer List w Software'!$V$4:$V$310,$B8) -> 2472 | E8: =IFERROR(AVERAGEIFS('Customer List w Software'!$J$4:$J$310,'Customer List w Software'!$B$4:$B$310,"<>Former client",'Customer List w Software'!$V$4:$V$310,$B8),0) -> 1186.0576 | G8: =COUNTIFS('Customer List w Software'!$B$4:$B$310,"Former client",'Customer List w Software'!$V$4:$V$310,$B8) -> 52 | H8: =SUMIFS('Customer List w Software'!$K$4:$K$310,'Customer List w Software'!$B$4:$B$310,"Former client",'Customer List w Software'!$V$4:$V$310,$B8) -> 352 | I8: =IFERROR(AVERAGEIFS('Customer List w Software'!$J$4:$J$310,'Customer List w Software'!$B$4:$B$310,"Former client",'Customer List w Software'!$V$4:$V$310,$B8),0) -> 631.64103 | K8: =C8+G8 -> 185 | L8: =D8+H8 -> 2824 | M8: =K8/K$10 -> 0.60260586
B9: Not Designated | C9: =COUNTIFS('Customer List w Software'!$B$4:$B$310,"<>Former client",'Customer List w Software'!$V$4:$V$310,"") -> 0 | D9: =SUMIFS('Customer List w Software'!$K$4:$K$310,'Customer List w Software'!$B$4:$B$310,"<>Former client",'Customer List w Software'!$V$4:$V$310,"") -> 0 | E9: =IFERROR(AVERAGEIFS('Customer List w Software'!$J$4:$J$310,'Customer List w Software'!$B$4:$B$310,"<>Former client",'Customer List w Software'!$V$4:$V$310,""),0) -> 0 | G9: =COUNTIFS('Customer List w Software'!$B$4:$B$310,"Former client",'Customer List w Software'!$V$4:$V$310,"") -> 77 | H9: =SUMIFS('Customer List w Software'!$K$4:$K$310,'Customer List w Software'!$B$4:$B$310,"Former client",'Customer List w Software'!$V$4:$V$310,"") -> 30 | I9: =IFERROR(AVERAGEIFS('Customer List w Software'!$J$4:$J$310,'Customer List w Software'!$B$4:$B$310,"Former client",'Customer List w Software'!$V$4:$V$310,""),0) -> 592.10266 | K9: =C9+G9 -> 77 | L9: =D9+H9 -> 30 | M9: =K9/K$10 -> 0.25081433
B10: Total Clients | C10: =COUNTIFS('Customer List w Software'!$B$4:$B$310,"<>Former client") -> 174 | D10: =SUMIFS('Customer List w Software'!$K$4:$K$310,'Customer List w Software'!$B$4:$B$310,"<>Former client") -> 3757 | E10: =AVERAGEIFS('Customer List w Software'!$J$4:$J$310,'Customer List w Software'!$B$4:$B$310,"<>Former client") -> 1380.6344 | G10: =COUNTIFS('Customer List w Software'!$B$4:$B$310,"Former client") -> 133 | H10: =SUMIFS('Customer List w Software'!$K$4:$K$310,'Customer List w Software'!$B$4:$B$310,"Former client") -> 454 | I10: =AVERAGEIFS('Customer List w Software'!$J$4:$J$310,'Customer List w Software'!$B$4:$B$310,"Former client") -> 637.95417 | K10: =C10+G10 -> 307 | L10: =D10+H10 -> 4211 | M10: =K10/K$10 -> 1
B12: Trust / Accounting Software
B13: VRT | C13: =COUNTIFS('Customer List w Software'!$B$4:$B$310,"<>Former client",'Customer List w Software'!$W$4:$W$310,$B13) -> 117 | D13: =SUMIFS('Customer List w Software'!$K$4:$K$310,'Customer List w Software'!$B$4:$B$310,"<>Former client",'Customer List w Software'!$W$4:$W$310,$B13) -> 2999 | E13: =IFERROR(AVERAGEIFS('Customer List w Software'!$J$4:$J$310,'Customer List w Software'!$B$4:$B$310,"<>Former client",'Customer List w Software'!$W$4:$W$310,$B13),0) -> 1521.7699 | G13: =COUNTIFS('Customer List w Software'!$B$4:$B$310,"Former client",'Customer List w Software'!$W$4:$W$310,$B13) -> 6 | H13: =SUMIFS('Customer List w Software'!$K$4:$K$310,'Customer List w Software'!$B$4:$B$310,"Former client",'Customer List w Software'!$W$4:$W$310,$B13) -> 84 | I13: =IFERROR(AVERAGEIFS('Customer List w Software'!$J$4:$J$310,'Customer List w Software'!$B$4:$B$310,"Former client",'Customer List w Software'!$W$4:$W$310,$B13),0) -> 1230.2222 | K13: =C13+G13 -> 123 | L13: =D13+H13 -> 3083 | M13: =K13/K$18 -> 0.40065147
B14: VRP | C14: =COUNTIFS('Customer List w Software'!$B$4:$B$310,"<>Former client",'Customer List w Software'!$W$4:$W$310,$B14) -> 36 | D14: =SUMIFS('Customer List w Software'!$K$4:$K$310,'Customer List w Software'!$B$4:$B$310,"<>Former client",'Customer List w Software'!$W$4:$W$310,$B14) -> 659 | E14: =IFERROR(AVERAGEIFS('Customer List w Software'!$J$4:$J$310,'Customer List w Software'!$B$4:$B$310,"<>Former client",'Customer List w Software'!$W$4:$W$310,$B14),0) -> 1378.1986 | G14: =COUNTIFS('Customer List w Software'!$B$4:$B$310,"Former client",'Customer List w Software'!$W$4:$W$310,$B14) -> 8 | H14: =SUMIFS('Customer List w Software'!$K$4:$K$310,'Customer List w Software'!$B$4:$B$310,"Former client",'Customer List w Software'!$W$4:$W$310,$B14) -> 123 | I14: =IFERROR(AVERAGEIFS('Customer List w Software'!$J$4:$J$310,'Customer List w Software'!$B$4:$B$310,"Former client",'Customer List w Software'!$W$4:$W$310,$B14),0) -> 1073.6042 | K14: =C14+G14 -> 44 | L14: =D14+H14 -> 782 | M14: =K14/K$18 -> 0.14332248
B15: Guesty | C15: =COUNTIFS('Customer List w Software'!$B$4:$B$310,"<>Former client",'Customer List w Software'!$W$4:$W$310,$B15) -> 2 | D15: =SUMIFS('Customer List w Software'!$K$4:$K$310,'Customer List w Software'!$B$4:$B$310,"<>Former client",'Customer List w Software'!$W$4:$W$310,$B15) -> 47 | E15: =IFERROR(AVERAGEIFS('Customer List w Software'!$J$4:$J$310,'Customer List w Software'!$B$4:$B$310,"<>Former client",'Customer List w Software'!$W$4:$W$310,$B15),0) -> 1226.1667 | G15: =COUNTIFS('Customer List w Software'!$B$4:$B$310,"Former client",'Customer List w Software'!$W$4:$W$310,$B15) -> 2 | H15: =SUMIFS('Customer List w Software'!$K$4:$K$310,'Customer List w Software'!$B$4:$B$310,"Former client",'Customer List w Software'!$W$4:$W$310,$B15) -> 17 | I15: =IFERROR(AVERAGEIFS('Customer List w Software'!$J$4:$J$310,'Customer List w Software'!$B$4:$B$310,"Former client",'Customer List w Software'!$W$4:$W$310,$B15),0) -> 841.83333 | K15: =C15+G15 -> 4 | L15: =D15+H15 -> 64 | M15: =K15/K$18 -> 0.013029316
B16: Clearing | C16: =COUNTIFS('Customer List w Software'!$B$4:$B$310,"<>Former client",'Customer List w Software'!$W$4:$W$310,$B16) -> 1 | D16: =SUMIFS('Customer List w Software'!$K$4:$K$310,'Customer List w Software'!$B$4:$B$310,"<>Former client",'Customer List w Software'!$W$4:$W$310,$B16) -> 15 | E16: =IFERROR(AVERAGEIFS('Customer List w Software'!$J$4:$J$310,'Customer List w Software'!$B$4:$B$310,"<>Former client",'Customer List w Software'!$W$4:$W$310,$B16),0) -> 1662.5 | G16: =COUNTIFS('Customer List w Software'!$B$4:$B$310,"Former client",'Customer List w Software'!$W$4:$W$310,$B16) -> 3 | H16: =SUMIFS('Customer List w Software'!$K$4:$K$310,'Customer List w Software'!$B$4:$B$310,"Former client",'Customer List w Software'!$W$4:$W$310,$B16) -> 34 | I16: =IFERROR(AVERAGEIFS('Customer List w Software'!$J$4:$J$310,'Customer List w Software'!$B$4:$B$310,"Former client",'Customer List w Software'!$W$4:$W$310,$B16),0) -> 723.22222 | K16: =C16+G16 -> 4 | L16: =D16+H16 -> 49 | M16: =K16/K$18 -> 0.013029316
B17: None | C17: =COUNTIFS('Customer List w Software'!$B$4:$B$310,"<>Former client",'Customer List w Software'!$W$4:$W$310,"") -> 18 | D17: =SUMIFS('Customer List w Software'!$K$4:$K$310,'Customer List w Software'!$B$4:$B$310,"<>Former client",'Customer List w Software'!$W$4:$W$310,"") -> 37 | E17: =IFERROR(AVERAGEIFS('Customer List w Software'!$J$4:$J$310,'Customer List w Software'!$B$4:$B$310,"<>Former client",'Customer List w Software'!$W$4:$W$310,""),0) -> 469.62963 | G17: =COUNTIFS('Customer List w Software'!$B$4:$B$310,"Former client",'Customer List w Software'!$W$4:$W$310,"") -> 114 | H17: =SUMIFS('Customer List w Software'!$K$4:$K$310,'Customer List w Software'!$B$4:$B$310,"Former client",'Customer List w Software'!$W$4:$W$310,"") -> 196 | I17: =IFERROR(AVERAGEIFS('Customer List w Software'!$J$4:$J$310,'Customer List w Software'!$B$4:$B$310,"Former client",'Customer List w Software'!$W$4:$W$310,""),0) -> 570.38952 | K17: =C17+G17 -> 132 | L17: =D17+H17 -> 233 | M17: =K17/K$18 -> 0.42996743
B18: Total Clients | C18: =COUNTIFS('Customer List w Software'!$B$4:$B$310,"<>Former client") -> 174 | D18: =SUMIFS('Customer List w Software'!$K$4:$K$310,'Customer List w Software'!$B$4:$B$310,"<>Former client") -> 3757 | E18: =AVERAGEIFS('Customer List w Software'!$J$4:$J$310,'Customer List w Software'!$B$4:$B$310,"<>Former client") -> 1380.6344 | G18: =COUNTIFS('Customer List w Software'!$B$4:$B$310,"Former client") -> 133 | H18: =SUMIFS('Customer List w Software'!$K$4:$K$310,'Customer List w Software'!$B$4:$B$310,"Former client") -> 454 | I18: =AVERAGEIFS('Customer List w Software'!$J$4:$J$310,'Customer List w Software'!$B$4:$B$310,"Former client") -> 637.95417 | K18: =C18+G18 -> 307 | L18: =D18+H18 -> 4211 | M18: =K18/K$18 -> 1
B20: Property Management System (PMS)
B21: Guesty | C21: =COUNTIFS('Customer List w Software'!$B$4:$B$310,"<>Former client",'Customer List w Software'!$X$4:$X$310,$B21) -> 51 | D21: =SUMIFS('Customer List w Software'!$K$4:$K$310,'Customer List w Software'!$B$4:$B$310,"<>Former client",'Customer List w Software'!$X$4:$X$310,$B21) -> 1338 | E21: =IFERROR(AVERAGEIFS('Customer List w Software'!$J$4:$J$310,'Customer List w Software'!$B$4:$B$310,"<>Former client",'Customer List w Software'!$X$4:$X$310,$B21),0) -> 1661.0776 | G21: =COUNTIFS('Customer List w Software'!$B$4:$B$310,"Former client",'Customer List w Software'!$X$4:$X$310,$B21) -> 6 | H21: =SUMIFS('Customer List w Software'!$K$4:$K$310,'Customer List w Software'!$B$4:$B$310,"Former client",'Customer List w Software'!$X$4:$X$310,$B21) -> 70 | I21: =IFERROR(AVERAGEIFS('Customer List w Software'!$J$4:$J$310,'Customer List w Software'!$B$4:$B$310,"Former client",'Customer List w Software'!$X$4:$X$310,$B21),0) -> 976.33333 | K21: =C21+G21 -> 57 | L21: =D21+H21 -> 1408 | M21: =K21/K$29 -> 0.18566775
B22: Hospitable | C22: =COUNTIFS('Customer List w Software'!$B$4:$B$310,"<>Former client",'Customer List w Software'!$X$4:$X$310,$B22) -> 48 | D22: =SUMIFS('Customer List w Software'!$K$4:$K$310,'Customer List w Software'!$B$4:$B$310,"<>Former client",'Customer List w Software'!$X$4:$X$310,$B22) -> 829 | E22: =IFERROR(AVERAGEIFS('Customer List w Software'!$J$4:$J$310,'Customer List w Software'!$B$4:$B$310,"<>Former client",'Customer List w Software'!$X$4:$X$310,$B22),0) -> 1090.3717 | G22: =COUNTIFS('Customer List w Software'!$B$4:$B$310,"Former client",'Customer List w Software'!$X$4:$X$310,$B22) -> 2 | H22: =SUMIFS('Customer List w Software'!$K$4:$K$310,'Customer List w Software'!$B$4:$B$310,"Former client",'Customer List w Software'!$X$4:$X$310,$B22) -> 0 | I22: =IFERROR(AVERAGEIFS('Customer List w Software'!$J$4:$J$310,'Customer List w Software'!$B$4:$B$310,"Former client",'Customer List w Software'!$X$4:$X$310,$B22),0) -> 459 | K22: =C22+G22 -> 50 | L22: =D22+H22 -> 829 | M22: =K22/K$29 -> 0.16286645
B23: OwnerRez | C23: =COUNTIFS('Customer List w Software'!$B$4:$B$310,"<>Former client",'Customer List w Software'!$X$4:$X$310,$B23) -> 24 | D23: =SUMIFS('Customer List w Software'!$K$4:$K$310,'Customer List w Software'!$B$4:$B$310,"<>Former client",'Customer List w Software'!$X$4:$X$310,$B23) -> 438 | E23: =IFERROR(AVERAGEIFS('Customer List w Software'!$J$4:$J$310,'Customer List w Software'!$B$4:$B$310,"<>Former client",'Customer List w Software'!$X$4:$X$310,$B23),0) -> 1275.3854 | G23: =COUNTIFS('Customer List w Software'!$B$4:$B$310,"Former client",'Customer List w Software'!$X$4:$X$310,$B23) -> 5 | H23: =SUMIFS('Customer List w Software'!$K$4:$K$310,'Customer List w Software'!$B$4:$B$310,"Former client",'Customer List w Software'!$X$4:$X$310,$B23) -> 48 | I23: =IFERROR(AVERAGEIFS('Customer List w Software'!$J$4:$J$310,'Customer List w Software'!$B$4:$B$310,"Former client",'Customer List w Software'!$X$4:$X$310,$B23),0) -> 833.16667 | K23: =C23+G23 -> 29 | L23: =D23+H23 -> 486 | M23: =K23/K$29 -> 0.094462541
B24: Hostaway | C24: =COUNTIFS('Customer List w Software'!$B$4:$B$310,"<>Former client",'Customer List w Software'!$X$4:$X$310,$B24) -> 20 | D24: =SUMIFS('Customer List w Software'!$K$4:$K$310,'Customer List w Software'!$B$4:$B$310,"<>Former client",'Customer List w Software'!$X$4:$X$310,$B24) -> 544 | E24: =IFERROR(AVERAGEIFS('Customer List w Software'!$J$4:$J$310,'Customer List w Software'!$B$4:$B$310,"<>Former client",'Customer List w Software'!$X$4:$X$310,$B24),0) -> 1667.55 | G24: =COUNTIFS('Customer List w Software'!$B$4:$B$310,"Former client",'Customer List w Software'!$X$4:$X$310,$B24) -> 2 | H24: =SUMIFS('Customer List w Software'!$K$4:$K$310,'Customer List w Software'!$B$4:$B$310,"Former client",'Customer List w Software'!$X$4:$X$310,$B24) -> 29 | I24: =IFERROR(AVERAGEIFS('Customer List w Software'!$J$4:$J$310,'Customer List w Software'!$B$4:$B$310,"Former client",'Customer List w Software'!$X$4:$X$310,$B24),0) -> 375 | K24: =C24+G24 -> 22 | L24: =D24+H24 -> 573 | M24: =K24/K$29 -> 0.071661238
B25: Hostfully | C25: =COUNTIFS('Customer List w Software'!$B$4:$B$310,"<>Former client",'Customer List w Software'!$X$4:$X$310,$B25) -> 8 | D25: =SUMIFS('Customer List w Software'!$K$4:$K$310,'Customer List w Software'!$B$4:$B$310,"<>Former client",'Customer List w Software'!$X$4:$X$310,$B25) -> 152 | E25: =IFERROR(AVERAGEIFS('Customer List w Software'!$J$4:$J$310,'Customer List w Software'!$B$4:$B$310,"<>Former client",'Customer List w Software'!$X$4:$X$310,$B25),0) -> 1303.4375 | G25: =COUNTIFS('Customer List w Software'!$B$4:$B$310,"Former client",'Customer List w Software'!$X$4:$X$310,$B25) -> 0 | H25: =SUMIFS('Customer List w Software'!$K$4:$K$310,'Customer List w Software'!$B$4:$B$310,"Former client",'Customer List w Software'!$X$4:$X$310,$B25) -> 0 | I25: =IFERROR(AVERAGEIFS('Customer List w Software'!$J$4:$J$310,'Customer List w Software'!$B$4:$B$310,"Former client",'Customer List w Software'!$X$4:$X$310,$B25),0) -> 0 | K25: =C25+G25 -> 8 | L25: =D25+H25 -> 152 | M25: =K25/K$29 -> 0.026058632
B26: Lodgify | C26: =COUNTIFS('Customer List w Software'!$B$4:$B$310,"<>Former client",'Customer List w Software'!$X$4:$X$310,$B26) -> 1 | D26: =SUMIFS('Customer List w Software'!$K$4:$K$310,'Customer List w Software'!$B$4:$B$310,"<>Former client",'Customer List w Software'!$X$4:$X$310,$B26) -> 29 | E26: =IFERROR(AVERAGEIFS('Customer List w Software'!$J$4:$J$310,'Customer List w Software'!$B$4:$B$310,"<>Former client",'Customer List w Software'!$X$4:$X$310,$B26),0) -> 2639 | G26: =COUNTIFS('Customer List w Software'!$B$4:$B$310,"Former client",'Customer List w Software'!$X$4:$X$310,$B26) -> 0 | H26: =SUMIFS('Customer List w Software'!$K$4:$K$310,'Customer List w Software'!$B$4:$B$310,"Former client",'Customer List w Software'!$X$4:$X$310,$B26) -> 0 | I26: =IFERROR(AVERAGEIFS('Customer List w Software'!$J$4:$J$310,'Customer List w Software'!$B$4:$B$310,"Former client",'Customer List w Software'!$X$4:$X$310,$B26),0) -> 0 | K26: =C26+G26 -> 1 | L26: =D26+H26 -> 29 | M26: =K26/K$29 -> 0.003257329
B27: Multiple Platforms | C27: =COUNTIFS('Customer List w Software'!$B$4:$B$310,"<>Former client",'Customer List w Software'!$X$4:$X$310,"*,*") -> 4 | D27: =SUMIFS('Customer List w Software'!$K$4:$K$310,'Customer List w Software'!$B$4:$B$310,"<>Former client",'Customer List w Software'!$X$4:$X$310,"*,*") -> 98 | E27: =IFERROR(AVERAGEIFS('Customer List w Software'!$J$4:$J$310,'Customer List w Software'!$B$4:$B$310,"<>Former client",'Customer List w Software'!$X$4:$X$310,"*,*"),0) -> 1695.7042 | G27: =COUNTIFS('Customer List w Software'!$B$4:$B$310,"Former client",'Customer List w Software'!$X$4:$X$310,"*,*") -> 0 | H27: =SUMIFS('Customer List w Software'!$K$4:$K$310,'Customer List w Software'!$B$4:$B$310,"Former client",'Customer List w Software'!$X$4:$X$310,"*,*") -> 0 | I27: =IFERROR(AVERAGEIFS('Customer List w Software'!$J$4:$J$310,'Customer List w Software'!$B$4:$B$310,"Former client",'Customer List w Software'!$X$4:$X$310,"*,*"),0) -> 0 | K27: =C27+G27 -> 4 | L27: =D27+H27 -> 98 | M27: =K27/K$29 -> 0.013029316
B28: None | C28: =COUNTIFS('Customer List w Software'!$B$4:$B$310,"<>Former client",'Customer List w Software'!$X$4:$X$310,"") -> 18 | D28: =SUMIFS('Customer List w Software'!$K$4:$K$310,'Customer List w Software'!$B$4:$B$310,"<>Former client",'Customer List w Software'!$X$4:$X$310,"") -> 329 | E28: =IFERROR(AVERAGEIFS('Customer List w Software'!$J$4:$J$310,'Customer List w Software'!$B$4:$B$310,"<>Former client",'Customer List w Software'!$X$4:$X$310,""),0) -> 1076.0017 | G28: =COUNTIFS('Customer List w Software'!$B$4:$B$310,"Former client",'Customer List w Software'!$X$4:$X$310,"") -> 118 | H28: =SUMIFS('Customer List w Software'!$K$4:$K$310,'Customer List w Software'!$B$4:$B$310,"Former client",'Customer List w Software'!$X$4:$X$310,"") -> 307 | I28: =IFERROR(AVERAGEIFS('Customer List w Software'!$J$4:$J$310,'Customer List w Software'!$B$4:$B$310,"Former client",'Customer List w Software'!$X$4:$X$310,""),0) -> 619.96671 | K28: =C28+G28 -> 136 | L28: =D28+H28 -> 636 | M28: =K28/K$29 -> 0.44299674
B29: Total Clients | C29: =COUNTIFS('Customer List w Software'!$B$4:$B$310,"<>Former client") -> 174 | D29: =SUMIFS('Customer List w Software'!$K$4:$K$310,'Customer List w Software'!$B$4:$B$310,"<>Former client") -> 3757 | E29: =AVERAGEIFS('Customer List w Software'!$J$4:$J$310,'Customer List w Software'!$B$4:$B$310,"<>Former client") -> 1380.6344 | G29: =COUNTIFS('Customer List w Software'!$B$4:$B$310,"Former client") -> 133 | H29: =SUMIFS('Customer List w Software'!$K$4:$K$310,'Customer List w Software'!$B$4:$B$310,"Former client") -> 454 | I29: =AVERAGEIFS('Customer List w Software'!$J$4:$J$310,'Customer List w Software'!$B$4:$B$310,"Former client") -> 637.95417 | K29: =C29+G29 -> 307 | L29: =D29+H29 -> 4211 | M29: =K29/K$29 -> 1
B31: Expense Tool
B32: Topkey | C32: =COUNTIFS('Customer List w Software'!$B$4:$B$310,"<>Former client",'Customer List w Software'!$Y$4:$Y$310,$B32) -> 48 | D32: =SUMIFS('Customer List w Software'!$K$4:$K$310,'Customer List w Software'!$B$4:$B$310,"<>Former client",'Customer List w Software'!$Y$4:$Y$310,$B32) -> 1841 | E32: =IFERROR(AVERAGEIFS('Customer List w Software'!$J$4:$J$310,'Customer List w Software'!$B$4:$B$310,"<>Former client",'Customer List w Software'!$Y$4:$Y$310,$B32),0) -> 2389.2051 | G32: =COUNTIFS('Customer List w Software'!$B$4:$B$310,"Former client",'Customer List w Software'!$Y$4:$Y$310,$B32) -> 4 | H32: =SUMIFS('Customer List w Software'!$K$4:$K$310,'Customer List w Software'!$B$4:$B$310,"Former client",'Customer List w Software'!$Y$4:$Y$310,$B32) -> 120 | I32: =IFERROR(AVERAGEIFS('Customer List w Software'!$J$4:$J$310,'Customer List w Software'!$B$4:$B$310,"Former client",'Customer List w Software'!$Y$4:$Y$310,$B32),0) -> 2159.8333 | K32: =C32+G32 -> 52 | L32: =D32+H32 -> 1961 | M32: =K32/K$36 -> 0.16938111
B33: Bill.com | C33: =COUNTIFS('Customer List w Software'!$B$4:$B$310,"<>Former client",'Customer List w Software'!$Y$4:$Y$310,$B33) -> 12 | D33: =SUMIFS('Customer List w Software'!$K$4:$K$310,'Customer List w Software'!$B$4:$B$310,"<>Former client",'Customer List w Software'!$Y$4:$Y$310,$B33) -> 231 | E33: =IFERROR(AVERAGEIFS('Customer List w Software'!$J$4:$J$310,'Customer List w Software'!$B$4:$B$310,"<>Former client",'Customer List w Software'!$Y$4:$Y$310,$B33),0) -> 1409.9444 | G33: =COUNTIFS('Customer List w Software'!$B$4:$B$310,"Former client",'Customer List w Software'!$Y$4:$Y$310,$B33) -> 1 | H33: =SUMIFS('Customer List w Software'!$K$4:$K$310,'Customer List w Software'!$B$4:$B$310,"Former client",'Customer List w Software'!$Y$4:$Y$310,$B33) -> 0 | I33: =IFERROR(AVERAGEIFS('Customer List w Software'!$J$4:$J$310,'Customer List w Software'!$B$4:$B$310,"Former client",'Customer List w Software'!$Y$4:$Y$310,$B33),0) -> 540 | K33: =C33+G33 -> 13 | L33: =D33+H33 -> 231 | M33: =K33/K$36 -> 0.042345277
B34: Ramp | C34: =COUNTIFS('Customer List w Software'!$B$4:$B$310,"<>Former client",'Customer List w Software'!$Y$4:$Y$310,$B34) -> 0 | D34: =SUMIFS('Customer List w Software'!$K$4:$K$310,'Customer List w Software'!$B$4:$B$310,"<>Former client",'Customer List w Software'!$Y$4:$Y$310,$B34) -> 0 | E34: =IFERROR(AVERAGEIFS('Customer List w Software'!$J$4:$J$310,'Customer List w Software'!$B$4:$B$310,"<>Former client",'Customer List w Software'!$Y$4:$Y$310,$B34),0) -> 0 | G34: =COUNTIFS('Customer List w Software'!$B$4:$B$310,"Former client",'Customer List w Software'!$Y$4:$Y$310,$B34) -> 1 | H34: =SUMIFS('Customer List w Software'!$K$4:$K$310,'Customer List w Software'!$B$4:$B$310,"Former client",'Customer List w Software'!$Y$4:$Y$310,$B34) -> 0 | I34: =IFERROR(AVERAGEIFS('Customer List w Software'!$J$4:$J$310,'Customer List w Software'!$B$4:$B$310,"Former client",'Customer List w Software'!$Y$4:$Y$310,$B34),0) -> 486.33333 | K34: =C34+G34 -> 1 | L34: =D34+H34 -> 0 | M34: =K34/K$36 -> 0.003257329
B35: None | C35: =COUNTIFS('Customer List w Software'!$B$4:$B$310,"<>Former client",'Customer List w Software'!$Y$4:$Y$310,"") -> 114 | D35: =SUMIFS('Customer List w Software'!$K$4:$K$310,'Customer List w Software'!$B$4:$B$310,"<>Former client",'Customer List w Software'!$Y$4:$Y$310,"") -> 1685 | E35: =IFERROR(AVERAGEIFS('Customer List w Software'!$J$4:$J$310,'Customer List w Software'!$B$4:$B$310,"<>Former client",'Customer List w Software'!$Y$4:$Y$310,""),0) -> 952.88787 | G35: =COUNTIFS('Customer List w Software'!$B$4:$B$310,"Former client",'Customer List w Software'!$Y$4:$Y$310,"") -> 127 | H35: =SUMIFS('Customer List w Software'!$K$4:$K$310,'Customer List w Software'!$B$4:$B$310,"Former client",'Customer List w Software'!$Y$4:$Y$310,"") -> 334 | I35: =IFERROR(AVERAGEIFS('Customer List w Software'!$J$4:$J$310,'Customer List w Software'!$B$4:$B$310,"Former client",'Customer List w Software'!$Y$4:$Y$310,""),0) -> 591.98613 | K35: =C35+G35 -> 241 | L35: =D35+H35 -> 2019 | M35: =K35/K$36 -> 0.78501629
B36: Total Clients | C36: =COUNTIFS('Customer List w Software'!$B$4:$B$310,"<>Former client") -> 174 | D36: =SUMIFS('Customer List w Software'!$K$4:$K$310,'Customer List w Software'!$B$4:$B$310,"<>Former client") -> 3757 | E36: =AVERAGEIFS('Customer List w Software'!$J$4:$J$310,'Customer List w Software'!$B$4:$B$310,"<>Former client") -> 1380.6344 | G36: =COUNTIFS('Customer List w Software'!$B$4:$B$310,"Former client") -> 133 | H36: =SUMIFS('Customer List w Software'!$K$4:$K$310,'Customer List w Software'!$B$4:$B$310,"Former client") -> 454 | I36: =AVERAGEIFS('Customer List w Software'!$J$4:$J$310,'Customer List w Software'!$B$4:$B$310,"Former client") -> 637.95417 | K36: =C36+G36 -> 307 | L36: =D36+H36 -> 4211 | M36: =K36/K$36 -> 1
B38: Reference
B39: Current clients = status "Active" or "Onboarding"; Former clients = status "Former client"
B40: Active clients | C40: =COUNTIFS('Customer List w Software'!$B$4:$B$310,"Active") -> 163
B41: Onboarding clients | C41: =COUNTIFS('Customer List w Software'!$B$4:$B$310,"Onboarding") -> 11
B42: Note: "Multiple Platforms" captures clients listing two PMS platforms; property counts are blank for clients with no listing data, so Properties will understate for those rows.
B44: Tie-Out: Avg. Fee per Current Client | C44: Monthly | D44: Annual
B45: Software Overview — current clients (row 10) | C45: =+E10 -> 1380.6344 | D45: =C45*12 -> 16567.613
B46: Client Retention $ — avg. annual fee per client (Sep-26) | C46: =D46/12 -> 1355.1213 | D46: =+'Client Retention $'!AD16*1000 -> 16261.456
B47: Variance | C47: =C45-C46 -> 25.513115 | D47: =D45-D46 -> 306.15738
B48: Variance % | D48: =D47/D46 -> 0.018827181
B50: Reconciliation Drivers
B51: Client count — Customer List w Software (current) | C51: =+C10 -> 174
B52: Client count — Client Retention (Sep-26 avg. clients) | C52: =+'Client Retention'!AD15 -> 188
B53: Total monthly fees — Customer List w Software (current) | C53: =SUMIFS('Customer List w Software'!$J$4:$J$310,'Customer List w Software'!$B$4:$B$310,"<>Former client") -> 240230.39
B54: Total monthly fees — Client Retention $ (Sep-26 avg.) | C54: =+'Client Retention $'!AD15*1000 -> 254762.81
B55: Note: Client Retention $ is built on the Full Customer List "Active" flag (190 clients, ties to its ending monthly fees); this tab uses the status column on Customer List w Software (163 Active + 11 Onboarding). The 16-client / $17k monthly gap is the difference between those two universes.

Sheet Earnings Sensitivity Table
B2: =+Cover!B24 -> Keystone Bookkeepers
B3: Earnings & Valuation Sensitivity ($000s)
B5: Base Case Inputs
B6: Steady-State Adj. EBITDA (PF July'26) | C6: ='P&L Forecast'!$K$106 -> 468.56306
B7: Normalized Bookkeeper Staffing Cost | C7: ='P&L Forecast'!$C$185 -> 272.46938
B8: Current Bookkeeping Clients | C8: ='P&L Forecast'!$C$181 -> 177
B9: Target Load (Clients per Bookkeeper) | C9: ='P&L Forecast'!$C$182 -> 8
B10: Avg. Bookkeeper Compensation | C10: ='P&L Forecast'!$C$184 -> 12.315
B11: EV / EBITDA Multiple (base) | C11: 7
B13: Implied Valuation — Steady-State Adj. EBITDA × Multiple
C14: Steady-State Bookkeeper Load (Clients per Bookkeeper)
B15: EV / EBITDA Multiple | C15: =$C$9-3 -> 5 | D15: =$C$9-2 -> 6 | E15: =$C$9-1 -> 7 | F15: =$C$9+0 -> 8 | G15: =$C$9+1 -> 9 | H15: =$C$9+2 -> 10 | I15: =$C$9+3 -> 11
B16: =$C$11-2 -> 5 | C16: =($C$6+$C$7-($C$8/C$15)*$C$10)*$B16 -> 1525.4072 | D16: =($C$6+$C$7-($C$8/D$15)*$C$10)*$B16 -> 1888.6997 | E16: =($C$6+$C$7-($C$8/E$15)*$C$10)*$B16 -> 2148.1943 | F16: =($C$6+$C$7-($C$8/F$15)*$C$10)*$B16 -> 2342.8153 | G16: =($C$6+$C$7-($C$8/G$15)*$C$10)*$B16 -> 2494.1872 | H16: =($C$6+$C$7-($C$8/H$15)*$C$10)*$B16 -> 2615.2847 | I16: =($C$6+$C$7-($C$8/I$15)*$C$10)*$B16 -> 2714.3644
B17: =$C$11-1 -> 6 | C17: =($C$6+$C$7-($C$8/C$15)*$C$10)*$B17 -> 1830.4886 | D17: =($C$6+$C$7-($C$8/D$15)*$C$10)*$B17 -> 2266.4396 | E17: =($C$6+$C$7-($C$8/E$15)*$C$10)*$B17 -> 2577.8332 | F17: =($C$6+$C$7-($C$8/F$15)*$C$10)*$B17 -> 2811.3783 | G17: =($C$6+$C$7-($C$8/G$15)*$C$10)*$B17 -> 2993.0246 | H17: =($C$6+$C$7-($C$8/H$15)*$C$10)*$B17 -> 3138.3416 | I17: =($C$6+$C$7-($C$8/I$15)*$C$10)*$B17 -> 3257.2373
B18: =$C$11+0 -> 7 | C18: =($C$6+$C$7-($C$8/C$15)*$C$10)*$B18 -> 2135.57 | D18: =($C$6+$C$7-($C$8/D$15)*$C$10)*$B18 -> 2644.1795 | E18: =($C$6+$C$7-($C$8/E$15)*$C$10)*$B18 -> 3007.472 | F18: =($C$6+$C$7-($C$8/F$15)*$C$10)*$B18 -> 3279.9414 | G18: =($C$6+$C$7-($C$8/G$15)*$C$10)*$B18 -> 3491.862 | H18: =($C$6+$C$7-($C$8/H$15)*$C$10)*$B18 -> 3661.3985 | I18: =($C$6+$C$7-($C$8/I$15)*$C$10)*$B18 -> 3800.1102
B19: =$C$11+1 -> 8 | C19: =($C$6+$C$7-($C$8/C$15)*$C$10)*$B19 -> 2440.6515 | D19: =($C$6+$C$7-($C$8/D$15)*$C$10)*$B19 -> 3021.9195 | E19: =($C$6+$C$7-($C$8/E$15)*$C$10)*$B19 -> 3437.1109 | F19: =($C$6+$C$7-($C$8/F$15)*$C$10)*$B19 -> 3748.5045 | G19: =($C$6+$C$7-($C$8/G$15)*$C$10)*$B19 -> 3990.6995 | H19: =($C$6+$C$7-($C$8/H$15)*$C$10)*$B19 -> 4184.4555 | I19: =($C$6+$C$7-($C$8/I$15)*$C$10)*$B19 -> 4342.9831
B20: =$C$11+2 -> 9 | C20: =($C$6+$C$7-($C$8/C$15)*$C$10)*$B20 -> 2745.7329 | D20: =($C$6+$C$7-($C$8/D$15)*$C$10)*$B20 -> 3399.6594 | E20: =($C$6+$C$7-($C$8/E$15)*$C$10)*$B20 -> 3866.7497 | F20: =($C$6+$C$7-($C$8/F$15)*$C$10)*$B20 -> 4217.0675 | G20: =($C$6+$C$7-($C$8/G$15)*$C$10)*$B20 -> 4489.5369 | H20: =($C$6+$C$7-($C$8/H$15)*$C$10)*$B20 -> 4707.5124 | I20: =($C$6+$C$7-($C$8/I$15)*$C$10)*$B20 -> 4885.856
B22: Estimated Steady-State Adj. EBITDA
C23: Steady-State Bookkeeper Load (Clients per Bookkeeper)
B24: Avg. Bookkeeper Compensation | C24: =C$15 -> 5 | D24: =D$15 -> 6 | E24: =E$15 -> 7 | F24: =F$15 -> 8 | G24: =G$15 -> 9 | H24: =H$15 -> 10 | I24: =I$15 -> 11
B25: =$C$10-2 -> 10.315 | C25: =$C$6+$C$7-($C$8/C$24)*$B25 -> 375.88143 | D25: =$C$6+$C$7-($C$8/D$24)*$B25 -> 436.73993 | E25: =$C$6+$C$7-($C$8/E$24)*$B25 -> 480.21029 | F25: =$C$6+$C$7-($C$8/F$24)*$B25 -> 512.81306 | G25: =$C$6+$C$7-($C$8/G$24)*$B25 -> 538.17077 | H25: =$C$6+$C$7-($C$8/H$24)*$B25 -> 558.45693 | I25: =$C$6+$C$7-($C$8/I$24)*$B25 -> 575.0547
B26: =$C$10-1 -> 11.315 | C26: =$C$6+$C$7-($C$8/C$24)*$B26 -> 340.48143 | D26: =$C$6+$C$7-($C$8/D$24)*$B26 -> 407.23993 | E26: =$C$6+$C$7-($C$8/E$24)*$B26 -> 454.92458 | F26: =$C$6+$C$7-($C$8/F$24)*$B26 -> 490.68806 | G26: =$C$6+$C$7-($C$8/G$24)*$B26 -> 518.5041 | H26: =$C$6+$C$7-($C$8/H$24)*$B26 -> 540.75693 | I26: =$C$6+$C$7-($C$8/I$24)*$B26 -> 558.9638
B27: =$C$10+0 -> 12.315 | C27: =$C$6+$C$7-($C$8/C$24)*$B27 -> 305.08143 | D27: =$C$6+$C$7-($C$8/D$24)*$B27 -> 377.73993 | E27: =$C$6+$C$7-($C$8/E$24)*$B27 -> 429.63886 | F27: =$C$6+$C$7-($C$8/F$24)*$B27 -> 468.56306 | G27: =$C$6+$C$7-($C$8/G$24)*$B27 -> 498.83743 | H27: =$C$6+$C$7-($C$8/H$24)*$B27 -> 523.05693 | I27: =$C$6+$C$7-($C$8/I$24)*$B27 -> 542.87289
B28: =$C$10+1 -> 13.315 | C28: =$C$6+$C$7-($C$8/C$24)*$B28 -> 269.68143 | D28: =$C$6+$C$7-($C$8/D$24)*$B28 -> 348.23993 | E28: =$C$6+$C$7-($C$8/E$24)*$B28 -> 404.35315 | F28: =$C$6+$C$7-($C$8/F$24)*$B28 -> 446.43806 | G28: =$C$6+$C$7-($C$8/G$24)*$B28 -> 479.17077 | H28: =$C$6+$C$7-($C$8/H$24)*$B28 -> 505.35693 | I28: =$C$6+$C$7-($C$8/I$24)*$B28 -> 526.78198
B29: =$C$10+2 -> 14.315 | C29: =$C$6+$C$7-($C$8/C$24)*$B29 -> 234.28143 | D29: =$C$6+$C$7-($C$8/D$24)*$B29 -> 318.73993 | E29: =$C$6+$C$7-($C$8/E$24)*$B29 -> 379.06743 | F29: =$C$6+$C$7-($C$8/F$24)*$B29 -> 424.31306 | G29: =$C$6+$C$7-($C$8/G$24)*$B29 -> 459.5041 | H29: =$C$6+$C$7-($C$8/H$24)*$B29 -> 487.65693 | I29: =$C$6+$C$7-($C$8/I$24)*$B29 -> 510.69107
B31: Reference — Observed Bookkeeper Load (Steady-State Staffing tab)
B32: FY2025 | C32: ='Steady-State Staffing'!C21 -> 7.3863636
B33: YTD2026 | C33: ='Steady-State Staffing'!D21 -> 5.056338
B34: LTM Sep'26 | C34: ='Steady-State Staffing'!F21 -> 5.3134328
B35: Jan-25 (peak) | C35: ='Steady-State Staffing'!H21 -> 11.230769
B36: Sep-26 (latest) | C36: ='Steady-State Staffing'!AB21 -> 4.4810127
B37: Note: load axis is the P&L Forecast target load (row 182) ±3 clients, bracketing the observed range above. Only the normalized bookkeeper staffing cost flexes; all other PF adj. EBITDA items are held constant.

Sheet P&L Overview (Target Version)
B2: =+Cover!B24 -> Keystone Bookkeepers
B3: Summary P&L Overview ($000s) | P3: Print | Q3: 1
C5: Full Year | F5: YTD | I5: LTM | K5: PF | M5: PF Delta
B6: P&L Summary | C6: 2024 | D6: 2025 | F6: July'25 | G6: July'26 | I6: July'25 | J6: July'26 | K6: July'26 | M6: ($) | N6: (%)
B7: Revenue
B8: =+'P&L Forecast'!B7 -> STR Subscription | C8: =+'P&L Forecast'!C7 -> 793.47225 | D8: =+'P&L Forecast'!D7 -> 1450.4923 | F8: =+'P&L Forecast'!F7 -> 751.5286 | G8: =+'P&L Forecast'!G7 -> 1261.4769 | I8: =+'P&L Forecast'!I7 -> 1152.3203 | J8: =+'P&L Forecast'!J7 -> 1960.4406 | K8: =+'P&L Forecast'!K7 -> 2410.05 | M8: =K8-J8 -> 449.6094 | N8: =IFERROR(K8/J8-1,0) -> 0.229341
B9: =+'P&L Forecast'!B8 -> Occupancy Taxes | C9: =+'P&L Forecast'!C8 -> 0.56 | D9: =+'P&L Forecast'!D8 -> 55.0805 | F9: =+'P&L Forecast'!F8 -> 23.2255 | G9: =+'P&L Forecast'!G8 -> 91.65114 | I9: =+'P&L Forecast'!I8 -> 23.7855 | J9: =+'P&L Forecast'!J8 -> 123.50614 | K9: =+'P&L Forecast'!K8 -> 192.8298 | M9: =K9-J9 -> 69.32366 | N9: =IFERROR(K9/J9-1,0) -> 0.56129728
