Workbook

Sheet Cover
B24: Keystone Bookkeepers
B25: Initial Financial Review
B26: ="As of "&TEXT(TODAY(),"mm/dd/yy") -> As of 09/10/26

Sheet P&L Overview
B2: =+Cover!B24 -> Keystone Bookkeepers
B3: Summary P&L Overview ($000s) | P3: Print | Q3: 1
C5: Full Year | F5: YTD | I5: LTM | K5: PF | M5: PF Delta
B6: P&L Summary | C6: 2024 | D6: 2025 | F6: July'25 | G6: July'26 | I6: July'25 | J6: July'26 | K6: July'26 | M6: ($) | N6: (%)
B7: Revenue
B8: =+'P&L Forecast'!B7 -> STR Subscription | C8: =+'P&L Forecast'!C7 -> 793.47225 | D8: =+'P&L Forecast'!D7 -> 1450.4923 | F8: =+'P&L Forecast'!F7 -> 751.5286 | G8: =+'P&L Forecast'!G7 -> 1261.4769 | I8: =+'P&L Forecast'!I7 -> 1152.3203 | J8: =+'P&L Forecast'!J7 -> 1960.4406 | K8: =+'P&L Forecast'!K7 -> 2410.05 | M8: =K8-J8 -> 449.6094 | N8: =IFERROR(K8/J8-1,0) -> 0.229341
B9: =+'P&L Forecast'!B8 -> Occupancy Taxes | C9: =+'P&L Forecast'!C8 -> 0.56 | D9: =+'P&L Forecast'!D8 -> 55.0805 | F9: =+'P&L Forecast'!F8 -> 23.2255 | G9: =+'P&L Forecast'!G8 -> 91.65114 | I9: =+'P&L Forecast'!I8 -> 23.7855 | J9: =+'P&L Forecast'!J8 -> 123.50614 | K9: =+'P&L Forecast'!K8 -> 192.8298 | M9: =K9-J9 -> 69.32366 | N9: =IFERROR(K9/J9-1,0) -> 0.56129728
B10: =+'P&L Forecast'!B9 -> SMB Subscription | C10: =+'P&L Forecast'!C9 -> 224.791 | D10: =+'P&L Forecast'!D9 -> 149.77 | F10: =+'P&L Forecast'!F9 -> 90.4525 | G10: =+'P&L Forecast'!G9 -> 73.4185 | I10: =+'P&L Forecast'!I9 -> 169.5465 | J10: =+'P&L Forecast'!J9 -> 132.736 | K10: =+'P&L Forecast'!K9 -> 0 | M10: =K10-J10 -> -132.736 | N10: =IFERROR(K10/J10-1,0) -> -1
B11: =+'P&L Forecast'!B10 -> Onboarding | C11: =+'P&L Forecast'!C10 -> 44.0585 | D11: =+'P&L Forecast'!D10 -> 74.5193 | F11: =+'P&L Forecast'!F10 -> 42.25405 | G11: =+'P&L Forecast'!G10 -> 59.055 | I11: =+'P&L Forecast'!I10 -> 57.49255 | J11: =+'P&L Forecast'!J10 -> 91.32025 | K11: =+'P&L Forecast'!K10 -> 103.5675 | M11: =K11-J11 -> 12.24725 | N11: =IFERROR(K11/J11-1,0) -> 0.13411319
B12: =+'P&L Forecast'!B11 -> Topkey Subscription | C12: =+'P&L Forecast'!C11 -> 0 | D12: =+'P&L Forecast'!D11 -> 9.947 | F12: =+'P&L Forecast'!F11 -> 0 | G12: =+'P&L Forecast'!G11 -> 45.086 | I12: =+'P&L Forecast'!I11 -> 0 | J12: =+'P&L Forecast'!J11 -> 55.033 | K12: =+'P&L Forecast'!K11 -> 94.836 | M12: =K12-J12 -> 39.803 | N12: =IFERROR(K12/J12-1,0) -> 0.72325695
B13: =+'P&L Forecast'!B12 -> STR Bill Pay | C13: =+'P&L Forecast'!C12 -> 0.06 | D13: =+'P&L Forecast'!D12 -> 36.6065 | F13: =+'P&L Forecast'!F12 -> 15.4915 | G13: =+'P&L Forecast'!G12 -> 45.13 | I13: =+'P&L Forecast'!I12 -> 15.5515 | J13: =+'P&L Forecast'!J12 -> 66.245 | K13: =+'P&L Forecast'!K12 -> 83.46 | M13: =K13-J13 -> 17.215 | N13: =IFERROR(K13/J13-1,0) -> 0.25986867
B14: =+'P&L Forecast'!B13 -> Controller Services | C14: =+'P&L Forecast'!C13 -> 13.75 | D14: =+'P&L Forecast'!D13 -> 46.4 | F14: =+'P&L Forecast'!F13 -> 31.5 | G14: =+'P&L Forecast'!G13 -> 24.25 | I14: =+'P&L Forecast'!I13 -> 44 | J14: =+'P&L Forecast'!J13 -> 39.15 | K14: =+'P&L Forecast'!K13 -> 42 | M14: =K14-J14 -> 2.85 | N14: =IFERROR(K14/J14-1,0) -> 0.072796935
B15: Other Revenue | C15: =+C16-SUM(C8:C14) -> 58.2741 | D15: =+D16-SUM(D8:D14) -> 56.56748 | F15: =+F16-SUM(F8:F14) -> 43.42095 | G15: =+G16-SUM(G8:G14) -> 70.95371 | I15: =+I16-SUM(I8:I14) -> 61.71435 | J15: =+J16-SUM(J8:J14) -> 84.10024 | K15: =+K16-SUM(K8:K14) -> 55.59772 | M15: =K15-J15 -> -28.50252 | N15: =IFERROR(K15/J15-1,0) -> -0.33891128
B16: Total Revenue | C16: =+'P&L Forecast'!C24 -> 1134.9659 | D16: =+'P&L Forecast'!D24 -> 1879.3831 | F16: =+'P&L Forecast'!F24 -> 997.8731 | G16: =+'P&L Forecast'!G24 -> 1671.0212 | I16: =+'P&L Forecast'!I24 -> 1524.4107 | J16: =+'P&L Forecast'!J24 -> 2552.5312 | K16: =+'P&L Forecast'!K24 -> 2982.341 | M16: =SUM(M8:M15) -> 429.80979 | N16: =IFERROR(K16/J16-1,0) -> 0.16838571
B18: Expenses
B19: =+'P&L Forecast'!B27 -> Indirect Labor | C19: =+'P&L Forecast'!C27 -> 101.3752 | D19: =+'P&L Forecast'!D27 -> 281.24054 | F19: =+'P&L Forecast'!F27 -> 136.29648 | G19: =+'P&L Forecast'!G27 -> 357.27472 | I19: =+'P&L Forecast'!I27 -> 202.41598 | J19: =+'P&L Forecast'!J27 -> 502.21878 | K19: =+'P&L Forecast'!K27 -> 694.74456 | M19: =K19-J19 -> 192.52578 | N19: =IFERROR(K19/J19-1,0) -> 0.38335042 | P19: =K19/$K$28 -> 0.32182939
B20: =+'P&L Forecast'!B28 -> Bookkeeper Wages | C20: =+'P&L Forecast'!C28 -> 183.36903 | D20: =+'P&L Forecast'!D28 -> 316.18462 | F20: =+'P&L Forecast'!F28 -> 147.26813 | G20: =+'P&L Forecast'!G28 -> 267.7574 | I20: =+'P&L Forecast'!I28 -> 240.18098 | J20: =+'P&L Forecast'!J28 -> 436.67389 | K20: =+'P&L Forecast'!K28 -> 533.8512 | M20: =K20-J20 -> 97.17731 | N20: =IFERROR(K20/J20-1,0) -> 0.22253978 | P20: =K20/$K$28 -> 0.2472981
B21: =+'P&L Forecast'!B29 -> Client Lead Wages | C21: =+'P&L Forecast'!C29 -> 286.16129 | D21: =+'P&L Forecast'!D29 -> 352.95844 | F21: =+'P&L Forecast'!F29 -> 201.27983 | G21: =+'P&L Forecast'!G29 -> 202.05309 | I21: =+'P&L Forecast'!I29 -> 353.12843 | J21: =+'P&L Forecast'!J29 -> 353.7317 | K21: =+'P&L Forecast'!K29 -> 392.92452 | M21: =K21-J21 -> 39.19282 | N21: =IFERROR(K21/J21-1,0) -> 0.11079816 | P21: =K21/$K$28 -> 0.18201605
B22: =+'P&L Forecast'!B30 -> Onboarding Team Wages | C22: =+'P&L Forecast'!C30 -> 122.81255 | D22: =+'P&L Forecast'!D30 -> 152.16972 | F22: =+'P&L Forecast'!F30 -> 73.94962 | G22: =+'P&L Forecast'!G30 -> 111.27999 | I22: =+'P&L Forecast'!I30 -> 121.30735 | J22: =+'P&L Forecast'!J30 -> 189.50009 | K22: =+'P&L Forecast'!K30 -> 197.14944 | M22: =K22-J22 -> 7.64935 | N22: =IFERROR(K22/J22-1,0) -> 0.040365944 | P22: =K22/$K$28 -> 0.091326349
B23: =+'P&L Forecast'!B31 -> Owner Wages | C23: =+'P&L Forecast'!C31 -> 0 | D23: =+'P&L Forecast'!D31 -> 90.66704 | F23: =+'P&L Forecast'!F31 -> 45.46612 | G23: =+'P&L Forecast'!G31 -> 63.14302 | I23: =+'P&L Forecast'!I31 -> 45.46612 | J23: =+'P&L Forecast'!J31 -> 108.34394 | K23: =+'P&L Forecast'!K31 -> 108.34394 | M23: =K23-J23 -> 0 | N23: =IFERROR(K23/J23-1,0) -> 0 | P23: =K23/$K$28 -> 0.050188611
B24: =+'P&L Forecast'!B32 -> S&M Wages | C24: =+'P&L Forecast'!C32 -> 0 | D24: =+'P&L Forecast'!D32 -> 19.14963 | F24: =+'P&L Forecast'!F32 -> 3.09945 | G24: =+'P&L Forecast'!G32 -> 51.94131 | I24: =+'P&L Forecast'!I32 -> 3.09945 | J24: =+'P&L Forecast'!J32 -> 67.99149 | K24: =+'P&L Forecast'!K32 -> 98.34912 | M24: =K24-J24 -> 30.35763 | N24: =IFERROR(K24/J24-1,0) -> 0.44649161 | P24: =K24/$K$28 -> 0.045558669
B25: =+'P&L Forecast'!B33 -> Occupancy Tax Specialist | C25: =+'P&L Forecast'!C33 -> 1.11335 | D25: =+'P&L Forecast'!D33 -> 29.56415 | F25: =+'P&L Forecast'!F33 -> 14.27585 | G25: =+'P&L Forecast'!G33 -> 42.08505 | I25: =+'P&L Forecast'!I33 -> 15.3892 | J25: =+'P&L Forecast'!J33 -> 57.37335 | K25: =+'P&L Forecast'!K33 -> 68.1132 | M25: =K25-J25 -> 10.73985 | N25: =IFERROR(K25/J25-1,0) -> 0.18719231 | P25: =K25/$K$28 -> 0.031552359
B26: =+'P&L Forecast'!B34 -> Sr. Client Lead Wages | C26: =+'P&L Forecast'!C34 -> 0 | D26: =+'P&L Forecast'!D34 -> 0 | F26: =+'P&L Forecast'!F34 -> 0 | G26: =+'P&L Forecast'!G34 -> 7.995 | I26: =+'P&L Forecast'!I34 -> 0 | J26: =+'P&L Forecast'!J34 -> 7.995 | K26: =+'P&L Forecast'!K34 -> 33.08124 | M26: =K26-J26 -> 25.08624 | N26: =IFERROR(K26/J26-1,0) -> 3.1377411 | P26: =K26/$K$28 -> 0.015324359
B27: =+'P&L Forecast'!B35 -> Employee Benefits | C27: =+'P&L Forecast'!C35 -> 5.37405 | D27: =+'P&L Forecast'!D35 -> 19.23245 | F27: =+'P&L Forecast'!F35 -> 9.02166 | G27: =+'P&L Forecast'!G35 -> 17.36251 | I27: =+'P&L Forecast'!I35 -> 12.16686 | J27: =+'P&L Forecast'!J35 -> 27.5733 | K27: =+'P&L Forecast'!K35 -> 32.17836 | M27: =K27-J27 -> 4.60506 | N27: =IFERROR(K27/J27-1,0) -> 0.16701157 | P27: =K27/$K$28 -> 0.014906115
B28: =+'P&L Forecast'!B36 -> Total Payroll Expenses | C28: =SUM(C19:C27) -> 700.20547 | D28: =SUM(D19:D27) -> 1261.1666 | F28: =SUM(F19:F27) -> 630.65714 | G28: =SUM(G19:G27) -> 1120.8921 | I28: =SUM(I19:I27) -> 993.15437 | J28: =SUM(J19:J27) -> 1751.4015 | K28: =SUM(K19:K27) -> 2158.7356 | M28: =SUM(M19:M27) -> 407.33404 | N28: =K28/J28-1 -> 0.23257604
B30: =+'P&L Forecast'!B38 -> Software & Apps - COGS | C30: =+'P&L Forecast'!C38 -> 114.42269 | D30: =+'P&L Forecast'!D38 -> 157.49471 | F30: =+'P&L Forecast'!F38 -> 84.96859 | G30: =+'P&L Forecast'!G38 -> 152.28157 | I30: =+'P&L Forecast'!I38 -> 142.28345 | J30: =+'P&L Forecast'!J38 -> 224.80769 | K30: =+'P&L Forecast'!K38 -> 335.70816 | M30: =K30-J30 -> 110.90047 | N30: =IFERROR(K30/J30-1,0) -> 0.49331262
B31: =+'P&L Forecast'!B39 -> Software & Apps - G&A | C31: =+'P&L Forecast'!C39 -> 60.91594 | D31: =+'P&L Forecast'!D39 -> 117.05866 | F31: =+'P&L Forecast'!F39 -> 56.8115 | G31: =+'P&L Forecast'!G39 -> 97.04798 | I31: =+'P&L Forecast'!I39 -> 86.51489 | J31: =+'P&L Forecast'!J39 -> 157.29514 | K31: =+'P&L Forecast'!K39 -> 155.82264 | M31: =K31-J31 -> -1.4725 | N31: =IFERROR(K31/J31-1,0) -> -0.0093613827
B32: =+'P&L Forecast'!B40 -> Software & Apps - Topkey | C32: =+'P&L Forecast'!C40 -> 0 | D32: =+'P&L Forecast'!D40 -> 7.14125 | F32: =+'P&L Forecast'!F40 -> 0 | G32: =+'P&L Forecast'!G40 -> 28.82775 | I32: =+'P&L Forecast'!I40 -> 0 | J32: =+'P&L Forecast'!J40 -> 35.969 | K32: =+'P&L Forecast'!K40 -> 60.84 | M32: =K32-J32 -> 24.871 | N32: =IFERROR(K32/J32-1,0) -> 0.69145653
B33: =+'P&L Forecast'!B41 -> Software & Apps - AI tools | C33: =+'P&L Forecast'!C41 -> 0 | D33: =+'P&L Forecast'!D41 -> 0 | F33: =+'P&L Forecast'!F41 -> 0 | G33: =+'P&L Forecast'!G41 -> 6.52752 | I33: =+'P&L Forecast'!I41 -> 0 | J33: =+'P&L Forecast'!J41 -> 6.52752 | K33: =+'P&L Forecast'!K41 -> 15.74376 | M33: =K33-J33 -> 9.21624 | N33: =IFERROR(K33/J33-1,0) -> 1.4119053
B34: =+'P&L Forecast'!B42 -> Total Software Expenses | C34: =SUM(C30:C33) -> 175.33863 | D34: =SUM(D30:D33) -> 281.69462 | F34: =SUM(F30:F33) -> 141.78009 | G34: =SUM(G30:G33) -> 284.68482 | I34: =SUM(I30:I33) -> 228.79834 | J34: =SUM(J30:J33) -> 424.59935 | K34: =SUM(K30:K33) -> 568.11456 | M34: =SUM(M30:M33) -> 143.51521 | N34: =K34/J34-1 -> 0.33800148
B36: =+'P&L Forecast'!B44 -> Other Professional Fees | C36: =+'P&L Forecast'!C44 -> 18.23425 | D36: =+'P&L Forecast'!D44 -> 27.04095 | F36: =+'P&L Forecast'!F44 -> 12.014 | G36: =+'P&L Forecast'!G44 -> 57.55 | I36: =+'P&L Forecast'!I44 -> 21.74858 | J36: =+'P&L Forecast'!J44 -> 72.57695 | K36: =+'P&L Forecast'!K44 -> 72.57695 | M36: =K36-J36 -> 0 | N36: =IFERROR(K36/J36-1,0) -> 0
B37: =+'P&L Forecast'!B45 -> Referral Fees | C37: =+'P&L Forecast'!C45 -> 24.82 | D37: =+'P&L Forecast'!D45 -> 27.15374 | F37: =+'P&L Forecast'!F45 -> 17.0895 | G37: =+'P&L Forecast'!G45 -> 20.62969 | I37: =+'P&L Forecast'!I45 -> 26.2095 | J37: =+'P&L Forecast'!J45 -> 30.69393 | K37: =+'P&L Forecast'!K45 -> 30.69393 | M37: =K37-J37 -> 0 | N37: =IFERROR(K37/J37-1,0) -> 0
B38: =+'P&L Forecast'!B46 -> Travel, Meals & Entertainment | C38: =+'P&L Forecast'!C46 -> 0 | D38: =+'P&L Forecast'!D46 -> 29.76122 | F38: =+'P&L Forecast'!F46 -> 22.29558 | G38: =+'P&L Forecast'!G46 -> 20.68542 | I38: =+'P&L Forecast'!I46 -> 22.29558 | J38: =+'P&L Forecast'!J46 -> 28.15106 | K38: =+'P&L Forecast'!K46 -> 28.15106 | M38: =K38-J38 -> 0 | N38: =IFERROR(K38/J38-1,0) -> 0
B39: =+'P&L Forecast'!B47 -> Payment Collection Fees | C39: =+'P&L Forecast'!C47 -> 8.67099 | D39: =+'P&L Forecast'!D47 -> 13.35153 | F39: =+'P&L Forecast'!F47 -> 6.80445 | G39: =+'P&L Forecast'!G47 -> 9.02684 | I39: =+'P&L Forecast'!I47 -> 10.54373 | J39: =+'P&L Forecast'!J47 -> 15.57392 | K39: =+'P&L Forecast'!K47 -> 15.57392 | M39: =K39-J39 -> 0 | N39: =IFERROR(K39/J39-1,0) -> 0
B40: =+'P&L Forecast'!B48 -> Professional Organizations | C40: =+'P&L Forecast'!C48 -> 5.44332 | D40: =+'P&L Forecast'!D48 -> 11.22296 | F40: =+'P&L Forecast'!F48 -> 6.191 | G40: =+'P&L Forecast'!G48 -> 6.57881 | I40: =+'P&L Forecast'!I48 -> 9.53268 | J40: =+'P&L Forecast'!J48 -> 11.61077 | K40: =+'P&L Forecast'!K48 -> 11.61077 | M40: =K40-J40 -> 0 | N40: =IFERROR(K40/J40-1,0) -> 0
B41: =+'P&L Forecast'!B49 -> S&M Events | C41: =+'P&L Forecast'!C49 -> 0 | D41: =+'P&L Forecast'!D49 -> 11.4983 | F41: =+'P&L Forecast'!F49 -> 0 | G41: =+'P&L Forecast'!G49 -> 11.84548 | I41: =+'P&L Forecast'!I49 -> 0 | J41: =+'P&L Forecast'!J49 -> 23.34378 | K41: =+'P&L Forecast'!K49 -> 23.34378 | M41: =K41-J41 -> 0 | N41: =IFERROR(K41/J41-1,0) -> 0
B42: =+'P&L Forecast'!B50 -> Contract Labor - Tax | C42: =+'P&L Forecast'!C50 -> 0 | D42: =+'P&L Forecast'!D50 -> 1.5875 | F42: =+'P&L Forecast'!F50 -> 0 | G42: =+'P&L Forecast'!G50 -> 30.5155 | I42: =+'P&L Forecast'!I50 -> 0 | J42: =+'P&L Forecast'!J50 -> 32.103 | K42: =+'P&L Forecast'!K50 -> 38.7615 | M42: =K42-J42 -> 6.6585 | N42: =IFERROR(K42/J42-1,0) -> 0.20741052
B43: =+'P&L Forecast'!B51 -> Recruiting Fees | C43: =+'P&L Forecast'!C51 -> 14.90205 | D43: =+'P&L Forecast'!D51 -> 31.6041 | F43: =+'P&L Forecast'!F51 -> 28.29994 | G43: =+'P&L Forecast'!G51 -> 5.5646 | I43: =+'P&L Forecast'!I51 -> 35.34606 | J43: =+'P&L Forecast'!J51 -> 8.86876 | K43: =+'P&L Forecast'!K51 -> 8.86876 | M43: =K43-J43 -> 0 | N43: =IFERROR(K43/J43-1,0) -> 0
B44: Other Expenses | C44: =+C45-SUM(C36:C43) -> 41.87929 | D44: =+D45-SUM(D36:D43) -> 52.32132 | F44: =+F45-SUM(F36:F43) -> 28.90542 | G44: =+G45-SUM(G36:G43) -> 26.90445 | I44: =+I45-SUM(I36:I43) -> 41.76881 | J44: =+J45-SUM(J36:J43) -> 50.32035 | K44: =+K45-SUM(K36:K43) -> 51.0799 | M44: =K44-J44 -> 0.75955 | N44: =IFERROR(K44/J44-1,0) -> 0.015094291
B45: Total Overhead | C45: =+'P&L Forecast'!C62 -> 113.9499 | D45: =+'P&L Forecast'!D62 -> 205.54162 | F45: =+'P&L Forecast'!F62 -> 121.59989 | G45: =+'P&L Forecast'!G62 -> 189.30079 | I45: =+'P&L Forecast'!I62 -> 167.44494 | J45: =+'P&L Forecast'!J62 -> 273.24252 | K45: =+'P&L Forecast'!K62 -> 280.66057 | M45: =SUM(M36:M44) -> 7.41805 | N45: =K45/J45-1 -> 0.027148227
B47: Net Income | C47: =+C16-C28-C34-C45 -> 145.47185 | D47: =+D16-D28-D34-D45 -> 130.9803 | F47: =+F16-F28-F34-F45 -> 103.83598 | G47: =+G16-G28-G34-G45 -> 76.1435 | I47: =+I16-I28-I34-I45 -> 135.013 | J47: =+J16-J28-J34-J45 -> 103.28782 | K47: =+K16-K28-K34-K45 -> -25.16969 | M47: =+M16-M28-M34-M45 -> -128.45751 | N47: =IFERROR(K47/J47-1,0) -> -1.243685
B48: % Margin | C48: =C47/C$16 -> 0.12817289 | D48: =D47/D$16 -> 0.06969324 | F48: =F47/F$16 -> 0.1040573 | G48: =G47/G$16 -> 0.045567046 | I48: =I47/I$16 -> 0.088567342 | J48: =J47/J$16 -> 0.04046486 | K48: =K47/K$16 -> -0.0084395748 | M48: =M47/M$16 -> -0.2988706 | N48: 0
B50: P&L Adjustments
B51: Other Professional Fees | C51: =+'P&L Forecast'!C85 -> 18.23425 | D51: =+'P&L Forecast'!D85 -> 27.04095 | F51: =+'P&L Forecast'!F85 -> 12.014 | G51: =+'P&L Forecast'!G85 -> 57.55 | I51: =+'P&L Forecast'!I85 -> 21.74858 | J51: =+'P&L Forecast'!J85 -> 72.57695 | K51: =+'P&L Forecast'!K85 -> 72.57695 | M51: =K51-J51 -> 0 | N51: =IFERROR(K51/J51-1,0) -> 0
B52: Definitional EBITDA Adj. | C52: =SUM('P&L Forecast'!C71:C73) -> 14.24964 | D52: =SUM('P&L Forecast'!D71:D73) -> 18.07948 | F52: =SUM('P&L Forecast'!F71:F73) -> 6.97104 | G52: =SUM('P&L Forecast'!G71:G73) -> 1.98303 | I52: =SUM('P&L Forecast'!I71:I73) -> 12.50268 | J52: =SUM('P&L Forecast'!J71:J73) -> 13.09147 | K52: =SUM('P&L Forecast'!K71:K73) -> 13.09147 | M52: =K52-J52 -> 0 | N52: =IFERROR(K52/J52-1,0) -> 0
B53: Personal Expenses | C53: =+'P&L Forecast'!C78+'P&L Forecast'!C79 -> 1.05983 | D53: =+'P&L Forecast'!D78+'P&L Forecast'!D79 -> 5.99533 | F53: =+'P&L Forecast'!F78+'P&L Forecast'!F79 -> 2.02633 | G53: =+'P&L Forecast'!G78+'P&L Forecast'!G79 -> 1.943 | I53: =+'P&L Forecast'!I78+'P&L Forecast'!I79 -> 2.45133 | J53: =+'P&L Forecast'!J78+'P&L Forecast'!J79 -> 5.912 | K53: =+'P&L Forecast'!K78+'P&L Forecast'!K79 -> 5.912 | M53: =K53-J53 -> 0 | N53: =IFERROR(K53/J53-1,0) -> 0
B54: Go-Forward Owner Comp | C54: =+'P&L Forecast'!C84 -> -200 | D54: =+'P&L Forecast'!D84 -> -109.33296 | F54: =+'P&L Forecast'!F84 -> -71.200547 | G54: =+'P&L Forecast'!G84 -> -53.523647 | I54: =+'P&L Forecast'!I84 -> -154.53388 | J54: =+'P&L Forecast'!J84 -> -91.65606 | K54: =+'P&L Forecast'!K84 -> -91.65606 | M54: =K54-J54 -> 0 | N54: =IFERROR(K54/J54-1,0) -> 0
B55: Total Near-Term Adjustments | C55: =SUM(C51:C54) -> -166.45628 | D55: =SUM(D51:D54) -> -58.2172 | F55: =SUM(F51:F54) -> -50.189177 | G55: =SUM(G51:G54) -> 7.9523833 | I55: =SUM(I51:I54) -> -117.83129 | J55: =SUM(J51:J54) -> -0.07564 | K55: =SUM(K51:K54) -> -0.07564 | M55: =SUM(M51:M54) -> 0 | N55: =K55/J55-1 -> 0
B57: =+'P&L Forecast'!B91 -> Near-Term Adj. EBITDA | C57: =+C47+C55 -> -20.98443 | D57: =+D47+D55 -> 72.7631 | F57: =+F47+F55 -> 53.646803 | G57: =+G47+G55 -> 84.095883 | I57: =+I47+I55 -> 17.18171 | J57: =+J47+J55 -> 103.21218 | K57: =+K47+K55 -> -25.24533 | M57: =+M47+M55 -> -128.45751 | N57: =IFERROR(K57/J57-1,0) -> -1.2445964
B58: % Margin | C58: =C57/C$16 -> -0.018489041 | D58: =D57/D$16 -> 0.03871648 | F58: =F57/F$16 -> 0.053761148 | G58: =G57/G$16 -> 0.050326042 | I58: =I57/I$16 -> 0.011271051 | J58: =J57/J$16 -> 0.040435227 | K58: =K57/K$16 -> -0.0084649374 | M58: =M57/M$16 -> -0.2988706 | N58: 0
B60: Onboarding Revenue | C60: =+'P&L Forecast'!C95 -> -44.0585 | D60: =+'P&L Forecast'!D95 -> -74.5193 | F60: =+'P&L Forecast'!F95 -> -42.25405 | G60: =+'P&L Forecast'!G95 -> -59.055 | I60: =+'P&L Forecast'!I95 -> -57.49255 | J60: =+'P&L Forecast'!J95 -> -91.32025 | K60: =+'P&L Forecast'!K95 -> -103.5675 | M60: =K60-J60 -> -12.24725 | N60: =IFERROR(K60/J60-1,0) -> 0.13411319 | P60: Reconsider
B61: Onboarding Team Wages | C61: =+'P&L Forecast'!C96 -> 122.81255 | D61: =+'P&L Forecast'!D96 -> 152.16972 | F61: =+'P&L Forecast'!F96 -> 73.94962 | G61: =+'P&L Forecast'!G96 -> 111.27999 | I61: =+'P&L Forecast'!I96 -> 121.30735 | J61: =+'P&L Forecast'!J96 -> 189.50009 | K61: =+'P&L Forecast'!K96 -> 197.14944 | M61: =K61-J61 -> 7.64935 | N61: =IFERROR(K61/J61-1,0) -> 0.040365944 | P61: Reconsider
B62: S&M Wages | C62: =+'P&L Forecast'!C97 -> 0 | D62: =+'P&L Forecast'!D97 -> 19.14963 | F62: =+'P&L Forecast'!F97 -> 3.09945 | G62: =+'P&L Forecast'!G97 -> 51.94131 | I62: =+'P&L Forecast'!I97 -> 3.09945 | J62: =+'P&L Forecast'!J97 -> 67.99149 | K62: =+'P&L Forecast'!K97 -> 98.34912 | M62: =K62-J62 -> 30.35763 | N62: =IFERROR(K62/J62-1,0) -> 0.44649161 | P62: Keep sales person and think about seperating marketing person
B63: Referral Fees | C63: =+'P&L Forecast'!C98 -> 24.82 | D63: =+'P&L Forecast'!D98 -> 27.15374 | F63: =+'P&L Forecast'!F98 -> 17.0895 | G63: =+'P&L Forecast'!G98 -> 20.62969 | I63: =+'P&L Forecast'!I98 -> 26.2095 | J63: =+'P&L Forecast'!J98 -> 30.69393 | K63: =+'P&L Forecast'!K98 -> 30.69393 | M63: =K63-J63 -> 0 | N63: =IFERROR(K63/J63-1,0) -> 0 | P63: Don't back out - has some level of sales
B64: Total Steady-State Adj. | C64: =SUM(C60:C63) -> 103.57405 | D64: =SUM(D60:D63) -> 123.95379 | F64: =SUM(F60:F63) -> 51.88452 | G64: =SUM(G60:G63) -> 124.79599 | I64: =SUM(I60:I63) -> 93.12375 | J64: =SUM(J60:J63) -> 196.86526 | K64: =SUM(K60:K63) -> 222.62499 | M64: =SUM(M60:M63) -> 25.75973 | N64: =K64/J64-1 -> 0.13084955
B66: =+'P&L Forecast'!B101 -> Steady-State Adj. EBITDA | C66: =+C64+C57 -> 82.58962 | D66: =+D64+D57 -> 196.71689 | F66: =+F64+F57 -> 105.53132 | G66: =+G64+G57 -> 208.89187 | I66: =+I64+I57 -> 110.30546 | J66: =+J64+J57 -> 300.07744 | K66: =+K64+K57 -> 197.37966 | M66: =+M64+M57 -> -102.69778 | N66: =IFERROR(K66/J66-1,0) -> -0.34223759
B67: % Margin | C67: =C66/C$16 -> 0.072768374 | D67: =D66/D$16 -> 0.10467099 | F67: =F66/F$16 -> 0.10575626 | G67: =G66/G$16 -> 0.12500851 | I67: =I66/I$16 -> 0.072359413 | J67: =J66/J$16 -> 0.11756073 | K67: =K66/K$16 -> 0.066182794 | M67: =M66/M$16 -> -0.23893774 | N67: 0

Sheet P&L Overview (Target Version)
B2: =+Cover!B24 -> Keystone Bookkeepers
B3: Summary P&L Overview ($000s) | P3: Print | Q3: 1
C5: Full Year | F5: YTD | I5: LTM | K5: PF | M5: PF Delta
B6: P&L Summary | C6: 2024 | D6: 2025 | F6: July'25 | G6: July'26 | I6: July'25 | J6: July'26 | K6: July'26 | M6: ($) | N6: (%)
B7: Revenue
B8: =+'P&L Forecast'!B7 -> STR Subscription | C8: =+'P&L Forecast'!C7 -> 793.47225 | D8: =+'P&L Forecast'!D7 -> 1450.4923 | F8: =+'P&L Forecast'!F7 -> 751.5286 | G8: =+'P&L Forecast'!G7 -> 1261.4769 | I8: =+'P&L Forecast'!I7 -> 1152.3203 | J8: =+'P&L Forecast'!J7 -> 1960.4406 | K8: =+'P&L Forecast'!K7 -> 2410.05 | M8: =K8-J8 -> 449.6094 | N8: =IFERROR(K8/J8-1,0) -> 0.229341
B9: =+'P&L Forecast'!B8 -> Occupancy Taxes | C9: =+'P&L Forecast'!C8 -> 0.56 | D9: =+'P&L Forecast'!D8 -> 55.0805 | F9: =+'P&L Forecast'!F8 -> 23.2255 | G9: =+'P&L Forecast'!G8 -> 91.65114 | I9: =+'P&L Forecast'!I8 -> 23.7855 | J9: =+'P&L Forecast'!J8 -> 123.50614 | K9: =+'P&L Forecast'!K8 -> 192.8298 | M9: =K9-J9 -> 69.32366 | N9: =IFERROR(K9/J9-1,0) -> 0.56129728
B10: =+'P&L Forecast'!B9 -> SMB Subscription | C10: =+'P&L Forecast'!C9 -> 224.791 | D10: =+'P&L Forecast'!D9 -> 149.77 | F10: =+'P&L Forecast'!F9 -> 90.4525 | G10: =+'P&L Forecast'!G9 -> 73.4185 | I10: =+'P&L Forecast'!I9 -> 169.5465 | J10: =+'P&L Forecast'!J9 -> 132.736 | K10: =+'P&L Forecast'!K9 -> 0 | M10: =K10-J10 -> -132.736 | N10: =IFERROR(K10/J10-1,0) -> -1
B11: =+'P&L Forecast'!B10 -> Onboarding | C11: =+'P&L Forecast'!C10 -> 44.0585 | D11: =+'P&L Forecast'!D10 -> 74.5193 | F11: =+'P&L Forecast'!F10 -> 42.25405 | G11: =+'P&L Forecast'!G10 -> 59.055 | I11: =+'P&L Forecast'!I10 -> 57.49255 | J11: =+'P&L Forecast'!J10 -> 91.32025 | K11: =+'P&L Forecast'!K10 -> 103.5675 | M11: =K11-J11 -> 12.24725 | N11: =IFERROR(K11/J11-1,0) -> 0.13411319
B12: =+'P&L Forecast'!B11 -> Topkey Subscription | C12: =+'P&L Forecast'!C11 -> 0 | D12: =+'P&L Forecast'!D11 -> 9.947 | F12: =+'P&L Forecast'!F11 -> 0 | G12: =+'P&L Forecast'!G11 -> 45.086 | I12: =+'P&L Forecast'!I11 -> 0 | J12: =+'P&L Forecast'!J11 -> 55.033 | K12: =+'P&L Forecast'!K11 -> 94.836 | M12: =K12-J12 -> 39.803 | N12: =IFERROR(K12/J12-1,0) -> 0.72325695
B13: =+'P&L Forecast'!B12 -> STR Bill Pay | C13: =+'P&L Forecast'!C12 -> 0.06 | D13: =+'P&L Forecast'!D12 -> 36.6065 | F13: =+'P&L Forecast'!F12 -> 15.4915 | G13: =+'P&L Forecast'!G12 -> 45.13 | I13: =+'P&L Forecast'!I12 -> 15.5515 | J13: =+'P&L Forecast'!J12 -> 66.245 | K13: =+'P&L Forecast'!K12 -> 83.46 | M13: =K13-J13 -> 17.215 | N13: =IFERROR(K13/J13-1,0) -> 0.25986867
B14: =+'P&L Forecast'!B13 -> Controller Services | C14: =+'P&L Forecast'!C13 -> 13.75 | D14: =+'P&L Forecast'!D13 -> 46.4 | F14: =+'P&L Forecast'!F13 -> 31.5 | G14: =+'P&L Forecast'!G13 -> 24.25 | I14: =+'P&L Forecast'!I13 -> 44 | J14: =+'P&L Forecast'!J13 -> 39.15 | K14: =+'P&L Forecast'!K13 -> 42 | M14: =K14-J14 -> 2.85 | N14: =IFERROR(K14/J14-1,0) -> 0.072796935
B15: Other Revenue | C15: =+C16-SUM(C8:C14) -> 58.2741 | D15: =+D16-SUM(D8:D14) -> 56.56748 | F15: =+F16-SUM(F8:F14) -> 43.42095 | G15: =+G16-SUM(G8:G14) -> 70.95371 | I15: =+I16-SUM(I8:I14) -> 61.71435 | J15: =+J16-SUM(J8:J14) -> 84.10024 | K15: =+K16-SUM(K8:K14) -> 55.59772 | M15: =K15-J15 -> -28.50252 | N15: =IFERROR(K15/J15-1,0) -> -0.33891128
B16: Total Revenue | C16: =+'P&L Forecast'!C24 -> 1134.9659 | D16: =+'P&L Forecast'!D24 -> 1879.3831 | F16: =+'P&L Forecast'!F24 -> 997.8731 | G16: =+'P&L Forecast'!G24 -> 1671.0212 | I16: =+'P&L Forecast'!I24 -> 1524.4107 | J16: =+'P&L Forecast'!J24 -> 2552.5312 | K16: =+'P&L Forecast'!K24 -> 2982.341 | M16: =SUM(M8:M15) -> 429.80979 | N16: =IFERROR(K16/J16-1,0) -> 0.16838571
B18: Expenses
B19: =+'P&L Forecast'!B27 -> Indirect Labor | C19: =+'P&L Forecast'!C27 -> 101.3752 | D19: =+'P&L Forecast'!D27 -> 281.24054 | F19: =+'P&L Forecast'!F27 -> 136.29648 | G19: =+'P&L Forecast'!G27 -> 357.27472 | I19: =+'P&L Forecast'!I27 -> 202.41598 | J19: =+'P&L Forecast'!J27 -> 502.21878 | K19: =+'P&L Forecast'!K27 -> 694.74456 | M19: =K19-J19 -> 192.52578 | N19: =IFERROR(K19/J19-1,0) -> 0.38335042
B20: =+'P&L Forecast'!B28 -> Bookkeeper Wages | C20: =+'P&L Forecast'!C28 -> 183.36903 | D20: =+'P&L Forecast'!D28 -> 316.18462 | F20: =+'P&L Forecast'!F28 -> 147.26813 | G20: =+'P&L Forecast'!G28 -> 267.7574 | I20: =+'P&L Forecast'!I28 -> 240.18098 | J20: =+'P&L Forecast'!J28 -> 436.67389 | K20: =+'P&L Forecast'!K28 -> 533.8512 | M20: =K20-J20 -> 97.17731 | N20: =IFERROR(K20/J20-1,0) -> 0.22253978
B21: =+'P&L Forecast'!B29 -> Client Lead Wages | C21: =+'P&L Forecast'!C29 -> 286.16129 | D21: =+'P&L Forecast'!D29 -> 352.95844 | F21: =+'P&L Forecast'!F29 -> 201.27983 | G21: =+'P&L Forecast'!G29 -> 202.05309 | I21: =+'P&L Forecast'!I29 -> 353.12843 | J21: =+'P&L Forecast'!J29 -> 353.7317 | K21: =+'P&L Forecast'!K29 -> 392.92452 | M21: =K21-J21 -> 39.19282 | N21: =IFERROR(K21/J21-1,0) -> 0.11079816
B22: =+'P&L Forecast'!B30 -> Onboarding Team Wages | C22: =+'P&L Forecast'!C30 -> 122.81255 | D22: =+'P&L Forecast'!D30 -> 152.16972 | F22: =+'P&L Forecast'!F30 -> 73.94962 | G22: =+'P&L Forecast'!G30 -> 111.27999 | I22: =+'P&L Forecast'!I30 -> 121.30735 | J22: =+'P&L Forecast'!J30 -> 189.50009 | K22: =+'P&L Forecast'!K30 -> 197.14944 | M22: =K22-J22 -> 7.64935 | N22: =IFERROR(K22/J22-1,0) -> 0.040365944
B23: =+'P&L Forecast'!B31 -> Owner Wages | C23: =+'P&L Forecast'!C31 -> 0 | D23: =+'P&L Forecast'!D31 -> 90.66704 | F23: =+'P&L Forecast'!F31 -> 45.46612 | G23: =+'P&L Forecast'!G31 -> 63.14302 | I23: =+'P&L Forecast'!I31 -> 45.46612 | J23: =+'P&L Forecast'!J31 -> 108.34394 | K23: =+'P&L Forecast'!K31 -> 108.34394 | M23: =K23-J23 -> 0 | N23: =IFERROR(K23/J23-1,0) -> 0
B24: =+'P&L Forecast'!B32 -> S&M Wages | C24: =+'P&L Forecast'!C32 -> 0 | D24: =+'P&L Forecast'!D32 -> 19.14963 | F24: =+'P&L Forecast'!F32 -> 3.09945 | G24: =+'P&L Forecast'!G32 -> 51.94131 | I24: =+'P&L Forecast'!I32 -> 3.09945 | J24: =+'P&L Forecast'!J32 -> 67.99149 | K24: =+'P&L Forecast'!K32 -> 98.34912 | M24: =K24-J24 -> 30.35763 | N24: =IFERROR(K24/J24-1,0) -> 0.44649161
B25: =+'P&L Forecast'!B33 -> Occupancy Tax Specialist | C25: =+'P&L Forecast'!C33 -> 1.11335 | D25: =+'P&L Forecast'!D33 -> 29.56415 | F25: =+'P&L Forecast'!F33 -> 14.27585 | G25: =+'P&L Forecast'!G33 -> 42.08505 | I25: =+'P&L Forecast'!I33 -> 15.3892 | J25: =+'P&L Forecast'!J33 -> 57.37335 | K25: =+'P&L Forecast'!K33 -> 68.1132 | M25: =K25-J25 -> 10.73985 | N25: =IFERROR(K25/J25-1,0) -> 0.18719231
B26: =+'P&L Forecast'!B34 -> Sr. Client Lead Wages | C26: =+'P&L Forecast'!C34 -> 0 | D26: =+'P&L Forecast'!D34 -> 0 | F26: =+'P&L Forecast'!F34 -> 0 | G26: =+'P&L Forecast'!G34 -> 7.995 | I26: =+'P&L Forecast'!I34 -> 0 | J26: =+'P&L Forecast'!J34 -> 7.995 | K26: =+'P&L Forecast'!K34 -> 33.08124 | M26: =K26-J26 -> 25.08624 | N26: =IFERROR(K26/J26-1,0) -> 3.1377411
B27: =+'P&L Forecast'!B35 -> Employee Benefits | C27: =+'P&L Forecast'!C35 -> 5.37405 | D27: =+'P&L Forecast'!D35 -> 19.23245 | F27: =+'P&L Forecast'!F35 -> 9.02166 | G27: =+'P&L Forecast'!G35 -> 17.36251 | I27: =+'P&L Forecast'!I35 -> 12.16686 | J27: =+'P&L Forecast'!J35 -> 27.5733 | K27: =+'P&L Forecast'!K35 -> 32.17836 | M27: =K27-J27 -> 4.60506 | N27: =IFERROR(K27/J27-1,0) -> 0.16701157
B28: =+'P&L Forecast'!B36 -> Total Payroll Expenses | C28: =SUM(C19:C27) -> 700.20547 | D28: =SUM(D19:D27) -> 1261.1666 | F28: =SUM(F19:F27) -> 630.65714 | G28: =SUM(G19:G27) -> 1120.8921 | I28: =SUM(I19:I27) -> 993.15437 | J28: =SUM(J19:J27) -> 1751.4015 | K28: =SUM(K19:K27) -> 2158.7356 | M28: =SUM(M19:M27) -> 407.33404 | N28: =K28/J28-1 -> 0.23257604
B30: =+'P&L Forecast'!B38 -> Software & Apps - COGS | C30: =+'P&L Forecast'!C38 -> 114.42269 | D30: =+'P&L Forecast'!D38 -> 157.49471 | F30: =+'P&L Forecast'!F38 -> 84.96859 | G30: =+'P&L Forecast'!G38 -> 152.28157 | I30: =+'P&L Forecast'!I38 -> 142.28345 | J30: =+'P&L Forecast'!J38 -> 224.80769 | K30: =+'P&L Forecast'!K38 -> 335.70816 | M30: =K30-J30 -> 110.90047 | N30: =IFERROR(K30/J30-1,0) -> 0.49331262
B31: =+'P&L Forecast'!B39 -> Software & Apps - G&A | C31: =+'P&L Forecast'!C39 -> 60.91594 | D31: =+'P&L Forecast'!D39 -> 117.05866 | F31: =+'P&L Forecast'!F39 -> 56.8115 | G31: =+'P&L Forecast'!G39 -> 97.04798 | I31: =+'P&L Forecast'!I39 -> 86.51489 | J31: =+'P&L Forecast'!J39 -> 157.29514 | K31: =+'P&L Forecast'!K39 -> 155.82264 | M31: =K31-J31 -> -1.4725 | N31: =IFERROR(K31/J31-1,0) -> -0.0093613827
B32: =+'P&L Forecast'!B40 -> Software & Apps - Topkey | C32: =+'P&L Forecast'!C40 -> 0 | D32: =+'P&L Forecast'!D40 -> 7.14125 | F32: =+'P&L Forecast'!F40 -> 0 | G32: =+'P&L Forecast'!G40 -> 28.82775 | I32: =+'P&L Forecast'!I40 -> 0 | J32: =+'P&L Forecast'!J40 -> 35.969 | K32: =+'P&L Forecast'!K40 -> 60.84 | M32: =K32-J32 -> 24.871 | N32: =IFERROR(K32/J32-1,0) -> 0.69145653
B33: =+'P&L Forecast'!B41 -> Software & Apps - AI tools | C33: =+'P&L Forecast'!C41 -> 0 | D33: =+'P&L Forecast'!D41 -> 0 | F33: =+'P&L Forecast'!F41 -> 0 | G33: =+'P&L Forecast'!G41 -> 6.52752 | I33: =+'P&L Forecast'!I41 -> 0 | J33: =+'P&L Forecast'!J41 -> 6.52752 | K33: =+'P&L Forecast'!K41 -> 15.74376 | M33: =K33-J33 -> 9.21624 | N33: =IFERROR(K33/J33-1,0) -> 1.4119053
B34: =+'P&L Forecast'!B42 -> Total Software Expenses | C34: =SUM(C30:C33) -> 175.33863 | D34: =SUM(D30:D33) -> 281.69462 | F34: =SUM(F30:F33) -> 141.78009 | G34: =SUM(G30:G33) -> 284.68482 | I34: =SUM(I30:I33) -> 228.79834 | J34: =SUM(J30:J33) -> 424.59935 | K34: =SUM(K30:K33) -> 568.11456 | M34: =SUM(M30:M33) -> 143.51521 | N34: =K34/J34-1 -> 0.33800148
B36: =+'P&L Forecast'!B44 -> Other Professional Fees | C36: =+'P&L Forecast'!C44 -> 18.23425 | D36: =+'P&L Forecast'!D44 -> 27.04095 | F36: =+'P&L Forecast'!F44 -> 12.014 | G36: =+'P&L Forecast'!G44 -> 57.55 | I36: =+'P&L Forecast'!I44 -> 21.74858 | J36: =+'P&L Forecast'!J44 -> 72.57695 | K36: =+'P&L Forecast'!K44 -> 72.57695 | M36: =K36-J36 -> 0 | N36: =IFERROR(K36/J36-1,0) -> 0
B37: =+'P&L Forecast'!B45 -> Referral Fees | C37: =+'P&L Forecast'!C45 -> 24.82 | D37: =+'P&L Forecast'!D45 -> 27.15374 | F37: =+'P&L Forecast'!F45 -> 17.0895 | G37: =+'P&L Forecast'!G45 -> 20.62969 | I37: =+'P&L Forecast'!I45 -> 26.2095 | J37: =+'P&L Forecast'!J45 -> 30.69393 | K37: =+'P&L Forecast'!K45 -> 30.69393 | M37: =K37-J37 -> 0 | N37: =IFERROR(K37/J37-1,0) -> 0
B38: =+'P&L Forecast'!B46 -> Travel, Meals & Entertainment | C38: =+'P&L Forecast'!C46 -> 0 | D38: =+'P&L Forecast'!D46 -> 29.76122 | F38: =+'P&L Forecast'!F46 -> 22.29558 | G38: =+'P&L Forecast'!G46 -> 20.68542 | I38: =+'P&L Forecast'!I46 -> 22.29558 | J38: =+'P&L Forecast'!J46 -> 28.15106 | K38: =+'P&L Forecast'!K46 -> 28.15106 | M38: =K38-J38 -> 0 | N38: =IFERROR(K38/J38-1,0) -> 0
B39: =+'P&L Forecast'!B47 -> Payment Collection Fees | C39: =+'P&L Forecast'!C47 -> 8.67099 | D39: =+'P&L Forecast'!D47 -> 13.35153 | F39: =+'P&L Forecast'!F47 -> 6.80445 | G39: =+'P&L Forecast'!G47 -> 9.02684 | I39: =+'P&L Forecast'!I47 -> 10.54373 | J39: =+'P&L Forecast'!J47 -> 15.57392 | K39: =+'P&L Forecast'!K47 -> 15.57392 | M39: =K39-J39 -> 0 | N39: =IFERROR(K39/J39-1,0) -> 0
B40: =+'P&L Forecast'!B48 -> Professional Organizations | C40: =+'P&L Forecast'!C48 -> 5.44332 | D40: =+'P&L Forecast'!D48 -> 11.22296 | F40: =+'P&L Forecast'!F48 -> 6.191 | G40: =+'P&L Forecast'!G48 -> 6.57881 | I40: =+'P&L Forecast'!I48 -> 9.53268 | J40: =+'P&L Forecast'!J48 -> 11.61077 | K40: =+'P&L Forecast'!K48 -> 11.61077 | M40: =K40-J40 -> 0 | N40: =IFERROR(K40/J40-1,0) -> 0
B41: =+'P&L Forecast'!B49 -> S&M Events | C41: =+'P&L Forecast'!C49 -> 0 | D41: =+'P&L Forecast'!D49 -> 11.4983 | F41: =+'P&L Forecast'!F49 -> 0 | G41: =+'P&L Forecast'!G49 -> 11.84548 | I41: =+'P&L Forecast'!I49 -> 0 | J41: =+'P&L Forecast'!J49 -> 23.34378 | K41: =+'P&L Forecast'!K49 -> 23.34378 | M41: =K41-J41 -> 0 | N41: =IFERROR(K41/J41-1,0) -> 0
B42: =+'P&L Forecast'!B50 -> Contract Labor - Tax | C42: =+'P&L Forecast'!C50 -> 0 | D42: =+'P&L Forecast'!D50 -> 1.5875 | F42: =+'P&L Forecast'!F50 -> 0 | G42: =+'P&L Forecast'!G50 -> 30.5155 | I42: =+'P&L Forecast'!I50 -> 0 | J42: =+'P&L Forecast'!J50 -> 32.103 | K42: =+'P&L Forecast'!K50 -> 38.7615 | M42: =K42-J42 -> 6.6585 | N42: =IFERROR(K42/J42-1,0) -> 0.20741052
B43: =+'P&L Forecast'!B51 -> Recruiting Fees | C43: =+'P&L Forecast'!C51 -> 14.90205 | D43: =+'P&L Forecast'!D51 -> 31.6041 | F43: =+'P&L Forecast'!F51 -> 28.29994 | G43: =+'P&L Forecast'!G51 -> 5.5646 | I43: =+'P&L Forecast'!I51 -> 35.34606 | J43: =+'P&L Forecast'!J51 -> 8.86876 | K43: =+'P&L Forecast'!K51 -> 8.86876 | M43: =K43-J43 -> 0 | N43: =IFERROR(K43/J43-1,0) -> 0
B44: Other Expenses | C44: =+C45-SUM(C36:C43) -> 41.87929 | D44: =+D45-SUM(D36:D43) -> 52.32132 | F44: =+F45-SUM(F36:F43) -> 28.90542 | G44: =+G45-SUM(G36:G43) -> 26.90445 | I44: =+I45-SUM(I36:I43) -> 41.76881 | J44: =+J45-SUM(J36:J43) -> 50.32035 | K44: =+K45-SUM(K36:K43) -> 51.0799 | M44: =K44-J44 -> 0.75955 | N44: =IFERROR(K44/J44-1,0) -> 0.015094291
B45: Total Overhead | C45: =+'P&L Forecast'!C62 -> 113.9499 | D45: =+'P&L Forecast'!D62 -> 205.54162 | F45: =+'P&L Forecast'!F62 -> 121.59989 | G45: =+'P&L Forecast'!G62 -> 189.30079 | I45: =+'P&L Forecast'!I62 -> 167.44494 | J45: =+'P&L Forecast'!J62 -> 273.24252 | K45: =+'P&L Forecast'!K62 -> 280.66057 | M45: =SUM(M36:M44) -> 7.41805 | N45: =K45/J45-1 -> 0.027148227
B47: Net Income | C47: =+C16-C28-C34-C45 -> 145.47185 | D47: =+D16-D28-D34-D45 -> 130.9803 | F47: =+F16-F28-F34-F45 -> 103.83598 | G47: =+G16-G28-G34-G45 -> 76.1435 | I47: =+I16-I28-I34-I45 -> 135.013 | J47: =+J16-J28-J34-J45 -> 103.28782 | K47: =+K16-K28-K34-K45 -> -25.16969 | M47: =+M16-M28-M34-M45 -> -128.45751 | N47: =IFERROR(K47/J47-1,0) -> -1.243685
B48: % Margin | C48: =C47/C$16 -> 0.12817289 | D48: =D47/D$16 -> 0.06969324 | F48: =F47/F$16 -> 0.1040573 | G48: =G47/G$16 -> 0.045567046 | I48: =I47/I$16 -> 0.088567342 | J48: =J47/J$16 -> 0.04046486 | K48: =K47/K$16 -> -0.0084395748 | M48: =M47/M$16 -> -0.2988706 | N48: 0

Sheet P&L Forecast
B2: =+Cover!B24 -> Keystone Bookkeepers
B3: Pre-LOI P&L Forecast ($000s)
B5: P&L Summary ($000s) | C5: FY2024 | D5: FY2025 | F5: July'25 YTD | G5: July'26 YTD | I5: Jul'25 LTM | J5: Jul'26 LTM | K5: Jul'26 PF | M5: Delta ($) | N5: Delta (%) | P5: 45292 | Q5: =EOMONTH(P5,0)+1 -> 45323 | R5: =EOMONTH(Q5,0)+1 -> 45352 | S5: =EOMONTH(R5,0)+1 -> 45383 | T5: =EOMONTH(S5,0)+1 -> 45413 | U5: =EOMONTH(T5,0)+1 -> 45444 | V5: =EOMONTH(U5,0)+1 -> 45474 | W5: =EOMONTH(V5,0)+1 -> 45505 | X5: =EOMONTH(W5,0)+1 -> 45536 | ... AT5: =EOMONTH(AS5,0)+1 -> 46204
A6: x | B6: Revenue
B7: STR Subscription | C7: =SUMIFS($P7:$AT7,$P$5:$AT$5,">"&C$168,$P$5:$AT$5,"<"&C$169) -> 793.47225 | D7: =SUMIFS($P7:$AT7,$P$5:$AT$5,">"&D$168,$P$5:$AT$5,"<"&D$169) -> 1450.4923 | F7: =SUMIFS($P7:$AT7,$P$5:$AT$5,">"&F$168,$P$5:$AT$5,"<"&F$169) -> 751.5286 | G7: =SUMIFS($P7:$AT7,$P$5:$AT$5,">"&G$168,$P$5:$AT$5,"<"&G$169) -> 1261.4769 | I7: =SUMIFS($P7:$AT7,$P$5:$AT$5,">"&I$168,$P$5:$AT$5,"<"&I$169) -> 1152.3203 | J7: =SUMIFS($P7:$AT7,$P$5:$AT$5,">"&J$168,$P$5:$AT$5,"<"&J$169) -> 1960.4406 | K7: =+C106 -> 2410.05 | M7: =K7-J7 -> 449.6094 | N7: =IFERROR(K7/J7-1,0) -> 0.229341 | P7: =SUMIFS('Combined P&L'!N:N,'Combined P&L'!$C:$C,'P&L Forecast'!$B7) -> 44.6835 | Q7: =SUMIFS('Combined P&L'!O:O,'Combined P&L'!$C:$C,'P&L Forecast'!$B7) -> 47.046 | R7: =SUMIFS('Combined P&L'!P:P,'Combined P&L'!$C:$C,'P&L Forecast'!$B7) -> 52.47 | S7: =SUMIFS('Combined P&L'!Q:Q,'Combined P&L'!$C:$C,'P&L Forecast'!$B7) -> 57.1697 | T7: =SUMIFS('Combined P&L'!R:R,'Combined P&L'!$C:$C,'P&L Forecast'!$B7) -> 57.51415 | U7: =SUMIFS('Combined P&L'!S:S,'Combined P&L'!$C:$C,'P&L Forecast'!$B7) -> 65.516 | V7: =SUMIFS('Combined P&L'!T:T,'Combined P&L'!$C:$C,'P&L Forecast'!$B7) -> 68.28125 | W7: =SUMIFS('Combined P&L'!U:U,'Combined P&L'!$C:$C,'P&L Forecast'!$B7) -> 73.25135 | X7: =SUMIFS('Combined P&L'!V:V,'Combined P&L'!$C:$C,'P&L Forecast'!$B7) -> 75.5517 | Y7: =SUMIFS('Combined P&L'!W:W,'Combined P&L'!$C:$C,'P&L Forecast'!$B7) -> 79.11325 | Z7: =SUMIFS('Combined P&L'!X:X,'Combined P&L'!$C:$C,'P&L Forecast'!$B7) -> 83.2908 | AA7: =SUMIFS('Combined P&L'!Y:Y,'Combined P&L'!$C:$C,'P&L Forecast'!$B7) -> 89.58455 | AB7: =SUMIFS('Combined P&L'!Z:Z,'Combined P&L'!$C:$C,'P&L Forecast'!$B7) -> 92.4189 | AC7: =SUMIFS('Combined P&L'!AA:AA,'Combined P&L'!$C:$C,'P&L Forecast'!$B7) -> 94.00215 | AD7: =SUMIFS('Combined P&L'!AB:AB,'Combined P&L'!$C:$C,'P&L Forecast'!$B7) -> 101.50605 | AE7: =SUMIFS('Combined P&L'!AC:AC,'Combined P&L'!$C:$C,'P&L Forecast'!$B7) -> 106.1375 | AF7: =SUMIFS('Combined P&L'!AD:AD,'Combined P&L'!$C:$C,'P&L Forecast'!$B7) -> 115.93875 | AG7: =SUMIFS('Combined P&L'!AE:AE,'Combined P&L'!$C:$C,'P&L Forecast'!$B7) -> 119.43125 | AH7: =SUMIFS('Combined P&L'!AF:AF,'Combined P&L'!$C:$C,'P&L Forecast'!$B7) -> 122.094 | AI7: =SUMIFS('Combined P&L'!AG:AG,'Combined P&L'!$C:$C,'P&L Forecast'!$B7) -> 130.08525 | AJ7: =SUMIFS('Combined P&L'!AH:AH,'Combined P&L'!$C:$C,'P&L Forecast'!$B7) -> 133.5905 | AK7: =SUMIFS('Combined P&L'!AI:AI,'Combined P&L'!$C:$C,'P&L Forecast'!$B7) -> 139.609 | AL7: =SUMIFS('Combined P&L'!AJ:AJ,'Combined P&L'!$C:$C,'P&L Forecast'!$B7) -> 145.28075 | AM7: =SUMIFS('Combined P&L'!AK:AK,'Combined P&L'!$C:$C,'P&L Forecast'!$B7) -> 150.39825 | AN7: =SUMIFS('Combined P&L'!AL:AL,'Combined P&L'!$C:$C,'P&L Forecast'!$B7) -> 156.5388 | AO7: =SUMIFS('Combined P&L'!AM:AM,'Combined P&L'!$C:$C,'P&L Forecast'!$B7) -> 164.9034 | AP7: =SUMIFS('Combined P&L'!AN:AN,'Combined P&L'!$C:$C,'P&L Forecast'!$B7) -> 170.34425 | AQ7: =SUMIFS('Combined P&L'!AO:AO,'Combined P&L'!$C:$C,'P&L Forecast'!$B7) -> 183.662 | AR7: =SUMIFS('Combined P&L'!AP:AP,'Combined P&L'!$C:$C,'P&L Forecast'!$B7) -> 190.7844 | AS7: =SUMIFS('Combined P&L'!AQ:AQ,'Combined P&L'!$C:$C,'P&L Forecast'!$B7) -> 194.4065 | AT7: =SUMIFS('Combined P&L'!AR:AR,'Combined P&L'!$C:$C,'P&L Forecast'!$B7) -> 200.8375
B8: Occupancy Taxes | C8: =SUMIFS($P8:$AT8,$P$5:$AT$5,">"&C$168,$P$5:$AT$5,"<"&C$169) -> 0.56 | D8: =SUMIFS($P8:$AT8,$P$5:$AT$5,">"&D$168,$P$5:$AT$5,"<"&D$169) -> 55.0805 | F8: =SUMIFS($P8:$AT8,$P$5:$AT$5,">"&F$168,$P$5:$AT$5,"<"&F$169) -> 23.2255 | G8: =SUMIFS($P8:$AT8,$P$5:$AT$5,">"&G$168,$P$5:$AT$5,"<"&G$169) -> 91.65114 | I8: =SUMIFS($P8:$AT8,$P$5:$AT$5,">"&I$168,$P$5:$AT$5,"<"&I$169) -> 23.7855 | J8: =SUMIFS($P8:$AT8,$P$5:$AT$5,">"&J$168,$P$5:$AT$5,"<"&J$169) -> 123.50614 | K8: =+C108 -> 192.8298 | M8: =K8-J8 -> 69.32366 | N8: =IFERROR(K8/J8-1,0) -> 0.56129728 | P8: =SUMIFS('Combined P&L'!N:N,'Combined P&L'!$C:$C,'P&L Forecast'!$B8) -> 0 | Q8: =SUMIFS('Combined P&L'!O:O,'Combined P&L'!$C:$C,'P&L Forecast'!$B8) -> 0 | R8: =SUMIFS('Combined P&L'!P:P,'Combined P&L'!$C:$C,'P&L Forecast'!$B8) -> 0 | S8: =SUMIFS('Combined P&L'!Q:Q,'Combined P&L'!$C:$C,'P&L Forecast'!$B8) -> 0 | T8: =SUMIFS('Combined P&L'!R:R,'Combined P&L'!$C:$C,'P&L Forecast'!$B8) -> 0 | U8: =SUMIFS('Combined P&L'!S:S,'Combined P&L'!$C:$C,'P&L Forecast'!$B8) -> 0 | V8: =SUMIFS('Combined P&L'!T:T,'Combined P&L'!$C:$C,'P&L Forecast'!$B8) -> 0 | W8: =SUMIFS('Combined P&L'!U:U,'Combined P&L'!$C:$C,'P&L Forecast'!$B8) -> 0 | X8: =SUMIFS('Combined P&L'!V:V,'Combined P&L'!$C:$C,'P&L Forecast'!$B8) -> 0 | Y8: =SUMIFS('Combined P&L'!W:W,'Combined P&L'!$C:$C,'P&L Forecast'!$B8) -> 0 | Z8: =SUMIFS('Combined P&L'!X:X,'Combined P&L'!$C:$C,'P&L Forecast'!$B8) -> 0.08 | AA8: =SUMIFS('Combined P&L'!Y:Y,'Combined P&L'!$C:$C,'P&L Forecast'!$B8) -> 0.48 | AB8: =SUMIFS('Combined P&L'!Z:Z,'Combined P&L'!$C:$C,'P&L Forecast'!$B8) -> 1.13 | AC8: =SUMIFS('Combined P&L'!AA:AA,'Combined P&L'!$C:$C,'P&L Forecast'!$B8) -> 2.14 | AD8: =SUMIFS('Combined P&L'!AB:AB,'Combined P&L'!$C:$C,'P&L Forecast'!$B8) -> 2.66 | AE8: =SUMIFS('Combined P&L'!AC:AC,'Combined P&L'!$C:$C,'P&L Forecast'!$B8) -> 3.65 | AF8: =SUMIFS('Combined P&L'!AD:AD,'Combined P&L'!$C:$C,'P&L Forecast'!$B8) -> 3.623 | AG8: =SUMIFS('Combined P&L'!AE:AE,'Combined P&L'!$C:$C,'P&L Forecast'!$B8) -> 4.964 | AH8: =SUMIFS('Combined P&L'!AF:AF,'Combined P&L'!$C:$C,'P&L Forecast'!$B8) -> 5.0585 | AI8: =SUMIFS('Combined P&L'!AG:AG,'Combined P&L'!$C:$C,'P&L Forecast'!$B8) -> 4.73 | AJ8: =SUMIFS('Combined P&L'!AH:AH,'Combined P&L'!$C:$C,'P&L Forecast'!$B8) -> 4.82 | AK8: =SUMIFS('Combined P&L'!AI:AI,'Combined P&L'!$C:$C,'P&L Forecast'!$B8) -> 5.37 | AL8: =SUMIFS('Combined P&L'!AJ:AJ,'Combined P&L'!$C:$C,'P&L Forecast'!$B8) -> 8.05 | AM8: =SUMIFS('Combined P&L'!AK:AK,'Combined P&L'!$C:$C,'P&L Forecast'!$B8) -> 8.885 | AN8: =SUMIFS('Combined P&L'!AL:AL,'Combined P&L'!$C:$C,'P&L Forecast'!$B8) -> 10.90952 | AO8: =SUMIFS('Combined P&L'!AM:AM,'Combined P&L'!$C:$C,'P&L Forecast'!$B8) -> 10.33497 | AP8: =SUMIFS('Combined P&L'!AN:AN,'Combined P&L'!$C:$C,'P&L Forecast'!$B8) -> 11.175 | AQ8: =SUMIFS('Combined P&L'!AO:AO,'Combined P&L'!$C:$C,'P&L Forecast'!$B8) -> 11.95311 | AR8: =SUMIFS('Combined P&L'!AP:AP,'Combined P&L'!$C:$C,'P&L Forecast'!$B8) -> 15.04071 | AS8: =SUMIFS('Combined P&L'!AQ:AQ,'Combined P&L'!$C:$C,'P&L Forecast'!$B8) -> 16.16868 | AT8: =SUMIFS('Combined P&L'!AR:AR,'Combined P&L'!$C:$C,'P&L Forecast'!$B8) -> 16.06915
B9: SMB Subscription | C9: =SUMIFS($P9:$AT9,$P$5:$AT$5,">"&C$168,$P$5:$AT$5,"<"&C$169) -> 224.791 | D9: =SUMIFS($P9:$AT9,$P$5:$AT$5,">"&D$168,$P$5:$AT$5,"<"&D$169) -> 149.77 | F9: =SUMIFS($P9:$AT9,$P$5:$AT$5,">"&F$168,$P$5:$AT$5,"<"&F$169) -> 90.4525 | G9: =SUMIFS($P9:$AT9,$P$5:$AT$5,">"&G$168,$P$5:$AT$5,"<"&G$169) -> 73.4185 | I9: =SUMIFS($P9:$AT9,$P$5:$AT$5,">"&I$168,$P$5:$AT$5,"<"&I$169) -> 169.5465 | J9: =SUMIFS($P9:$AT9,$P$5:$AT$5,">"&J$168,$P$5:$AT$5,"<"&J$169) -> 132.736 | K9: =+C107 -> 0 | M9: =K9-J9 -> -132.736 | N9: =IFERROR(K9/J9-1,0) -> -1 | P9: =SUMIFS('Combined P&L'!N:N,'Combined P&L'!$C:$C,'P&L Forecast'!$B9) -> 22.001 | Q9: =SUMIFS('Combined P&L'!O:O,'Combined P&L'!$C:$C,'P&L Forecast'!$B9) -> 22.036 | R9: =SUMIFS('Combined P&L'!P:P,'Combined P&L'!$C:$C,'P&L Forecast'!$B9) -> 22.111 | S9: =SUMIFS('Combined P&L'!Q:Q,'Combined P&L'!$C:$C,'P&L Forecast'!$B9) -> 22.146 | T9: =SUMIFS('Combined P&L'!R:R,'Combined P&L'!$C:$C,'P&L Forecast'!$B9) -> 21.966 | U9: =SUMIFS('Combined P&L'!S:S,'Combined P&L'!$C:$C,'P&L Forecast'!$B9) -> 17.816 | V9: =SUMIFS('Combined P&L'!T:T,'Combined P&L'!$C:$C,'P&L Forecast'!$B9) -> 17.621 | W9: =SUMIFS('Combined P&L'!U:U,'Combined P&L'!$C:$C,'P&L Forecast'!$B9) -> 17.536 | X9: =SUMIFS('Combined P&L'!V:V,'Combined P&L'!$C:$C,'P&L Forecast'!$B9) -> 16.426 | Y9: =SUMIFS('Combined P&L'!W:W,'Combined P&L'!$C:$C,'P&L Forecast'!$B9) -> 15.381 | Z9: =SUMIFS('Combined P&L'!X:X,'Combined P&L'!$C:$C,'P&L Forecast'!$B9) -> 14.6755 | AA9: =SUMIFS('Combined P&L'!Y:Y,'Combined P&L'!$C:$C,'P&L Forecast'!$B9) -> 15.0755 | AB9: =SUMIFS('Combined P&L'!Z:Z,'Combined P&L'!$C:$C,'P&L Forecast'!$B9) -> 14.5625 | AC9: =SUMIFS('Combined P&L'!AA:AA,'Combined P&L'!$C:$C,'P&L Forecast'!$B9) -> 12.8025 | AD9: =SUMIFS('Combined P&L'!AB:AB,'Combined P&L'!$C:$C,'P&L Forecast'!$B9) -> 12.4025 | AE9: =SUMIFS('Combined P&L'!AC:AC,'Combined P&L'!$C:$C,'P&L Forecast'!$B9) -> 12.6025 | AF9: =SUMIFS('Combined P&L'!AD:AD,'Combined P&L'!$C:$C,'P&L Forecast'!$B9) -> 12.7525 | AG9: =SUMIFS('Combined P&L'!AE:AE,'Combined P&L'!$C:$C,'P&L Forecast'!$B9) -> 12.7925 | AH9: =SUMIFS('Combined P&L'!AF:AF,'Combined P&L'!$C:$C,'P&L Forecast'!$B9) -> 12.5375 | AI9: =SUMIFS('Combined P&L'!AG:AG,'Combined P&L'!$C:$C,'P&L Forecast'!$B9) -> 11.8575 | AJ9: =SUMIFS('Combined P&L'!AH:AH,'Combined P&L'!$C:$C,'P&L Forecast'!$B9) -> 12.3025 | AK9: =SUMIFS('Combined P&L'!AI:AI,'Combined P&L'!$C:$C,'P&L Forecast'!$B9) -> 11.6925 | AL9: =SUMIFS('Combined P&L'!AJ:AJ,'Combined P&L'!$C:$C,'P&L Forecast'!$B9) -> 11.7175 | AM9: =SUMIFS('Combined P&L'!AK:AK,'Combined P&L'!$C:$C,'P&L Forecast'!$B9) -> 11.7475 | AN9: =SUMIFS('Combined P&L'!AL:AL,'Combined P&L'!$C:$C,'P&L Forecast'!$B9) -> 11.2805 | AO9: =SUMIFS('Combined P&L'!AM:AM,'Combined P&L'!$C:$C,'P&L Forecast'!$B9) -> 10.9305 | AP9: =SUMIFS('Combined P&L'!AN:AN,'Combined P&L'!$C:$C,'P&L Forecast'!$B9) -> 10.6255 | AQ9: =SUMIFS('Combined P&L'!AO:AO,'Combined P&L'!$C:$C,'P&L Forecast'!$B9) -> 10.3155 | AR9: =SUMIFS('Combined P&L'!AP:AP,'Combined P&L'!$C:$C,'P&L Forecast'!$B9) -> 10.3155 | AS9: =SUMIFS('Combined P&L'!AQ:AQ,'Combined P&L'!$C:$C,'P&L Forecast'!$B9) -> 9.9755 | AT9: =SUMIFS('Combined P&L'!AR:AR,'Combined P&L'!$C:$C,'P&L Forecast'!$B9) -> 9.9755
B10: Onboarding | C10: =SUMIFS($P10:$AT10,$P$5:$AT$5,">"&C$168,$P$5:$AT$5,"<"&C$169) -> 44.0585 | D10: =SUMIFS($P10:$AT10,$P$5:$AT$5,">"&D$168,$P$5:$AT$5,"<"&D$169) -> 74.5193 | F10: =SUMIFS($P10:$AT10,$P$5:$AT$5,">"&F$168,$P$5:$AT$5,"<"&F$169) -> 42.25405 | G10: =SUMIFS($P10:$AT10,$P$5:$AT$5,">"&G$168,$P$5:$AT$5,"<"&G$169) -> 59.055 | I10: =SUMIFS($P10:$AT10,$P$5:$AT$5,">"&I$168,$P$5:$AT$5,"<"&I$169) -> 57.49255 | J10: =SUMIFS($P10:$AT10,$P$5:$AT$5,">"&J$168,$P$5:$AT$5,"<"&J$169) -> 91.32025 | K10: =+C109 -> 103.5675 | M10: =K10-J10 -> 12.24725 | N10: =IFERROR(K10/J10-1,0) -> 0.13411319 | P10: =SUMIFS('Combined P&L'!N:N,'Combined P&L'!$C:$C,'P&L Forecast'!$B10) -> 5.465 | Q10: =SUMIFS('Combined P&L'!O:O,'Combined P&L'!$C:$C,'P&L Forecast'!$B10) -> 3.9 | R10: =SUMIFS('Combined P&L'!P:P,'Combined P&L'!$C:$C,'P&L Forecast'!$B10) -> 2.755 | S10: =SUMIFS('Combined P&L'!Q:Q,'Combined P&L'!$C:$C,'P&L Forecast'!$B10) -> 3.502 | T10: =SUMIFS('Combined P&L'!R:R,'Combined P&L'!$C:$C,'P&L Forecast'!$B10) -> 4.659 | U10: =SUMIFS('Combined P&L'!S:S,'Combined P&L'!$C:$C,'P&L Forecast'!$B10) -> 3.937 | V10: =SUMIFS('Combined P&L'!T:T,'Combined P&L'!$C:$C,'P&L Forecast'!$B10) -> 4.602 | W10: =SUMIFS('Combined P&L'!U:U,'Combined P&L'!$C:$C,'P&L Forecast'!$B10) -> 4.738 | X10: =SUMIFS('Combined P&L'!V:V,'Combined P&L'!$C:$C,'P&L Forecast'!$B10) -> 2.119 | Y10: =SUMIFS('Combined P&L'!W:W,'Combined P&L'!$C:$C,'P&L Forecast'!$B10) -> 2.064 | Z10: =SUMIFS('Combined P&L'!X:X,'Combined P&L'!$C:$C,'P&L Forecast'!$B10) -> 3.0125 | AA10: =SUMIFS('Combined P&L'!Y:Y,'Combined P&L'!$C:$C,'P&L Forecast'!$B10) -> 3.305 | AB10: =SUMIFS('Combined P&L'!Z:Z,'Combined P&L'!$C:$C,'P&L Forecast'!$B10) -> 3.079 | AC10: =SUMIFS('Combined P&L'!AA:AA,'Combined P&L'!$C:$C,'P&L Forecast'!$B10) -> 0.7 | AD10: =SUMIFS('Combined P&L'!AB:AB,'Combined P&L'!$C:$C,'P&L Forecast'!$B10) -> 10.43855 | AE10: =SUMIFS('Combined P&L'!AC:AC,'Combined P&L'!$C:$C,'P&L Forecast'!$B10) -> 4.3 | AF10: =SUMIFS('Combined P&L'!AD:AD,'Combined P&L'!$C:$C,'P&L Forecast'!$B10) -> 11.14 | AG10: =SUMIFS('Combined P&L'!AE:AE,'Combined P&L'!$C:$C,'P&L Forecast'!$B10) -> 6.1625 | AH10: =SUMIFS('Combined P&L'!AF:AF,'Combined P&L'!$C:$C,'P&L Forecast'!$B10) -> 6.434 | AI10: =SUMIFS('Combined P&L'!AG:AG,'Combined P&L'!$C:$C,'P&L Forecast'!$B10) -> 3.965 | AJ10: =SUMIFS('Combined P&L'!AH:AH,'Combined P&L'!$C:$C,'P&L Forecast'!$B10) -> 3.92 | AK10: =SUMIFS('Combined P&L'!AI:AI,'Combined P&L'!$C:$C,'P&L Forecast'!$B10) -> 9.1365 | AL10: =SUMIFS('Combined P&L'!AJ:AJ,'Combined P&L'!$C:$C,'P&L Forecast'!$B10) -> 5.25375 | AM10: =SUMIFS('Combined P&L'!AK:AK,'Combined P&L'!$C:$C,'P&L Forecast'!$B10) -> 9.99 | AN10: =SUMIFS('Combined P&L'!AL:AL,'Combined P&L'!$C:$C,'P&L Forecast'!$B10) -> 10.2105 | AO10: =SUMIFS('Combined P&L'!AM:AM,'Combined P&L'!$C:$C,'P&L Forecast'!$B10) -> 6.675 | AP10: =SUMIFS('Combined P&L'!AN:AN,'Combined P&L'!$C:$C,'P&L Forecast'!$B10) -> 9.099 | AQ10: =SUMIFS('Combined P&L'!AO:AO,'Combined P&L'!$C:$C,'P&L Forecast'!$B10) -> 8.9545 | AR10: =SUMIFS('Combined P&L'!AP:AP,'Combined P&L'!$C:$C,'P&L Forecast'!$B10) -> 12.606 | AS10: =SUMIFS('Combined P&L'!AQ:AQ,'Combined P&L'!$C:$C,'P&L Forecast'!$B10) -> 5.4115 | AT10: =SUMIFS('Combined P&L'!AR:AR,'Combined P&L'!$C:$C,'P&L Forecast'!$B10) -> 6.0985
B11: Topkey Subscription | C11: =SUMIFS($P11:$AT11,$P$5:$AT$5,">"&C$168,$P$5:$AT$5,"<"&C$169) -> 0 | D11: =SUMIFS($P11:$AT11,$P$5:$AT$5,">"&D$168,$P$5:$AT$5,"<"&D$169) -> 9.947 | F11: =SUMIFS($P11:$AT11,$P$5:$AT$5,">"&F$168,$P$5:$AT$5,"<"&F$169) -> 0 | G11: =SUMIFS($P11:$AT11,$P$5:$AT$5,">"&G$168,$P$5:$AT$5,"<"&G$169) -> 45.086 | I11: =SUMIFS($P11:$AT11,$P$5:$AT$5,">"&I$168,$P$5:$AT$5,"<"&I$169) -> 0 | J11: =SUMIFS($P11:$AT11,$P$5:$AT$5,">"&J$168,$P$5:$AT$5,"<"&J$169) -> 55.033 | K11: =+C111 -> 94.836 | M11: =K11-J11 -> 39.803 | N11: =IFERROR(K11/J11-1,0) -> 0.72325695 | P11: =SUMIFS('Combined P&L'!N:N,'Combined P&L'!$C:$C,'P&L Forecast'!$B11) -> 0 | Q11: =SUMIFS('Combined P&L'!O:O,'Combined P&L'!$C:$C,'P&L Forecast'!$B11) -> 0 | R11: =SUMIFS('Combined P&L'!P:P,'Combined P&L'!$C:$C,'P&L Forecast'!$B11) -> 0 | S11: =SUMIFS('Combined P&L'!Q:Q,'Combined P&L'!$C:$C,'P&L Forecast'!$B11) -> 0 | T11: =SUMIFS('Combined P&L'!R:R,'Combined P&L'!$C:$C,'P&L Forecast'!$B11) -> 0 | U11: =SUMIFS('Combined P&L'!S:S,'Combined P&L'!$C:$C,'P&L Forecast'!$B11) -> 0 | V11: =SUMIFS('Combined P&L'!T:T,'Combined P&L'!$C:$C,'P&L Forecast'!$B11) -> 0 | W11: =SUMIFS('Combined P&L'!U:U,'Combined P&L'!$C:$C,'P&L Forecast'!$B11) -> 0 | X11: =SUMIFS('Combined P&L'!V:V,'Combined P&L'!$C:$C,'P&L Forecast'!$B11) -> 0 | Y11: =SUMIFS('Combined P&L'!W:W,'Combined P&L'!$C:$C,'P&L Forecast'!$B11) -> 0 | Z11: =SUMIFS('Combined P&L'!X:X,'Combined P&L'!$C:$C,'P&L Forecast'!$B11) -> 0 | AA11: =SUMIFS('Combined P&L'!Y:Y,'Combined P&L'!$C:$C,'P&L Forecast'!$B11) -> 0 | AB11: =SUMIFS('Combined P&L'!Z:Z,'Combined P&L'!$C:$C,'P&L Forecast'!$B11) -> 0 | AC11: =SUMIFS('Combined P&L'!AA:AA,'Combined P&L'!$C:$C,'P&L Forecast'!$B11) -> 0 | AD11: =SUMIFS('Combined P&L'!AB:AB,'Combined P&L'!$C:$C,'P&L Forecast'!$B11) -> 0 | AE11: =SUMIFS('Combined P&L'!AC:AC,'Combined P&L'!$C:$C,'P&L Forecast'!$B11) -> 0 | AF11: =SUMIFS('Combined P&L'!AD:AD,'Combined P&L'!$C:$C,'P&L Forecast'!$B11) -> 0 | AG11: =SUMIFS('Combined P&L'!AE:AE,'Combined P&L'!$C:$C,'P&L Forecast'!$B11) -> 0 | AH11: =SUMIFS('Combined P&L'!AF:AF,'Combined P&L'!$C:$C,'P&L Forecast'!$B11) -> 0 | AI11: =SUMIFS('Combined P&L'!AG:AG,'Combined P&L'!$C:$C,'P&L Forecast'!$B11) -> 0 | AJ11: =SUMIFS('Combined P&L'!AH:AH,'Combined P&L'!$C:$C,'P&L Forecast'!$B11) -> 0.52 | AK11: =SUMIFS('Combined P&L'!AI:AI,'Combined P&L'!$C:$C,'P&L Forecast'!$B11) -> 2.357 | AL11: =SUMIFS('Combined P&L'!AJ:AJ,'Combined P&L'!$C:$C,'P&L Forecast'!$B11) -> 2.811 | AM11: =SUMIFS('Combined P&L'!AK:AK,'Combined P&L'!$C:$C,'P&L Forecast'!$B11) -> 4.259 | AN11: =SUMIFS('Combined P&L'!AL:AL,'Combined P&L'!$C:$C,'P&L Forecast'!$B11) -> 5.254 | AO11: =SUMIFS('Combined P&L'!AM:AM,'Combined P&L'!$C:$C,'P&L Forecast'!$B11) -> 5.652 | AP11: =SUMIFS('Combined P&L'!AN:AN,'Combined P&L'!$C:$C,'P&L Forecast'!$B11) -> 5.324 | AQ11: =SUMIFS('Combined P&L'!AO:AO,'Combined P&L'!$C:$C,'P&L Forecast'!$B11) -> 6.321 | AR11: =SUMIFS('Combined P&L'!AP:AP,'Combined P&L'!$C:$C,'P&L Forecast'!$B11) -> 6.959 | AS11: =SUMIFS('Combined P&L'!AQ:AQ,'Combined P&L'!$C:$C,'P&L Forecast'!$B11) -> 7.673 | AT11: =SUMIFS('Combined P&L'!AR:AR,'Combined P&L'!$C:$C,'P&L Forecast'!$B11) -> 7.903
B12: STR Bill Pay | C12: =SUMIFS($P12:$AT12,$P$5:$AT$5,">"&C$168,$P$5:$AT$5,"<"&C$169) -> 0.06 | D12: =SUMIFS($P12:$AT12,$P$5:$AT$5,">"&D$168,$P$5:$AT$5,"<"&D$169) -> 36.6065 | F12: =SUMIFS($P12:$AT12,$P$5:$AT$5,">"&F$168,$P$5:$AT$5,"<"&F$169) -> 15.4915 | G12: =SUMIFS($P12:$AT12,$P$5:$AT$5,">"&G$168,$P$5:$AT$5,"<"&G$169) -> 45.13 | I12: =SUMIFS($P12:$AT12,$P$5:$AT$5,">"&I$168,$P$5:$AT$5,"<"&I$169) -> 15.5515 | J12: =SUMIFS($P12:$AT12,$P$5:$AT$5,">"&J$168,$P$5:$AT$5,"<"&J$169) -> 66.245 | K12: =+C110 -> 83.46 | M12: =K12-J12 -> 17.215 | N12: =IFERROR(K12/J12-1,0) -> 0.25986867 | P12: =SUMIFS('Combined P&L'!N:N,'Combined P&L'!$C:$C,'P&L Forecast'!$B12) -> 0 | Q12: =SUMIFS('Combined P&L'!O:O,'Combined P&L'!$C:$C,'P&L Forecast'!$B12) -> 0 | R12: =SUMIFS('Combined P&L'!P:P,'Combined P&L'!$C:$C,'P&L Forecast'!$B12) -> 0 | S12: =SUMIFS('Combined P&L'!Q:Q,'Combined P&L'!$C:$C,'P&L Forecast'!$B12) -> 0 | T12: =SUMIFS('Combined P&L'!R:R,'Combined P&L'!$C:$C,'P&L Forecast'!$B12) -> 0 | U12: =SUMIFS('Combined P&L'!S:S,'Combined P&L'!$C:$C,'P&L Forecast'!$B12) -> 0 | V12: =SUMIFS('Combined P&L'!T:T,'Combined P&L'!$C:$C,'P&L Forecast'!$B12) -> 0 | W12: =SUMIFS('Combined P&L'!U:U,'Combined P&L'!$C:$C,'P&L Forecast'!$B12) -> 0 | X12: =SUMIFS('Combined P&L'!V:V,'Combined P&L'!$C:$C,'P&L Forecast'!$B12) -> 0 | Y12: =SUMIFS('Combined P&L'!W:W,'Combined P&L'!$C:$C,'P&L Forecast'!$B12) -> 0 | Z12: =SUMIFS('Combined P&L'!X:X,'Combined P&L'!$C:$C,'P&L Forecast'!$B12) -> 0 | AA12: =SUMIFS('Combined P&L'!Y:Y,'Combined P&L'!$C:$C,'P&L Forecast'!$B12) -> 0.06 | AB12: =SUMIFS('Combined P&L'!Z:Z,'Combined P&L'!$C:$C,'P&L Forecast'!$B12) -> 0.97 | AC12: =SUMIFS('Combined P&L'!AA:AA,'Combined P&L'!$C:$C,'P&L Forecast'!$B12) -> 1.1 | AD12: =SUMIFS('Combined P&L'!AB:AB,'Combined P&L'!$C:$C,'P&L Forecast'!$B12) -> 1.735 | AE12: =SUMIFS('Combined P&L'!AC:AC,'Combined P&L'!$C:$C,'P&L Forecast'!$B12) -> 2.14 | AF12: =SUMIFS('Combined P&L'!AD:AD,'Combined P&L'!$C:$C,'P&L Forecast'!$B12) -> 2.363 | AG12: =SUMIFS('Combined P&L'!AE:AE,'Combined P&L'!$C:$C,'P&L Forecast'!$B12) -> 3.2635 | AH12: =SUMIFS('Combined P&L'!AF:AF,'Combined P&L'!$C:$C,'P&L Forecast'!$B12) -> 3.92 | AI12: =SUMIFS('Combined P&L'!AG:AG,'Combined P&L'!$C:$C,'P&L Forecast'!$B12) -> 3.905 | AJ12: =SUMIFS('Combined P&L'!AH:AH,'Combined P&L'!$C:$C,'P&L Forecast'!$B12) -> 3.78 | AK12: =SUMIFS('Combined P&L'!AI:AI,'Combined P&L'!$C:$C,'P&L Forecast'!$B12) -> 3.795 | AL12: =SUMIFS('Combined P&L'!AJ:AJ,'Combined P&L'!$C:$C,'P&L Forecast'!$B12) -> 4.33 | AM12: =SUMIFS('Combined P&L'!AK:AK,'Combined P&L'!$C:$C,'P&L Forecast'!$B12) -> 5.305 | AN12: =SUMIFS('Combined P&L'!AL:AL,'Combined P&L'!$C:$C,'P&L Forecast'!$B12) -> 6.3 | AO12: =SUMIFS('Combined P&L'!AM:AM,'Combined P&L'!$C:$C,'P&L Forecast'!$B12) -> 6.39 | AP12: =SUMIFS('Combined P&L'!AN:AN,'Combined P&L'!$C:$C,'P&L Forecast'!$B12) -> 6.425 | AQ12: =SUMIFS('Combined P&L'!AO:AO,'Combined P&L'!$C:$C,'P&L Forecast'!$B12) -> 6.08 | AR12: =SUMIFS('Combined P&L'!AP:AP,'Combined P&L'!$C:$C,'P&L Forecast'!$B12) -> 6.325 | AS12: =SUMIFS('Combined P&L'!AQ:AQ,'Combined P&L'!$C:$C,'P&L Forecast'!$B12) -> 6.655 | AT12: =SUMIFS('Combined P&L'!AR:AR,'Combined P&L'!$C:$C,'P&L Forecast'!$B12) -> 6.955
B13: Controller Services | C13: =SUMIFS($P13:$AT13,$P$5:$AT$5,">"&C$168,$P$5:$AT$5,"<"&C$169) -> 13.75 | D13: =SUMIFS($P13:$AT13,$P$5:$AT$5,">"&D$168,$P$5:$AT$5,"<"&D$169) -> 46.4 | F13: =SUMIFS($P13:$AT13,$P$5:$AT$5,">"&F$168,$P$5:$AT$5,"<"&F$169) -> 31.5 | G13: =SUMIFS($P13:$AT13,$P$5:$AT$5,">"&G$168,$P$5:$AT$5,"<"&G$169) -> 24.25 | I13: =SUMIFS($P13:$AT13,$P$5:$AT$5,">"&I$168,$P$5:$AT$5,"<"&I$169) -> 44 | J13: =SUMIFS($P13:$AT13,$P$5:$AT$5,">"&J$168,$P$5:$AT$5,"<"&J$169) -> 39.15 | K13: =+C112 -> 42 | M13: =K13-J13 -> 2.85 | N13: =IFERROR(K13/J13-1,0) -> 0.072796935 | P13: =SUMIFS('Combined P&L'!N:N,'Combined P&L'!$C:$C,'P&L Forecast'!$B13) -> 0 | Q13: =SUMIFS('Combined P&L'!O:O,'Combined P&L'!$C:$C,'P&L Forecast'!$B13) -> 0 | R13: =SUMIFS('Combined P&L'!P:P,'Combined P&L'!$C:$C,'P&L Forecast'!$B13) -> 0 | S13: =SUMIFS('Combined P&L'!Q:Q,'Combined P&L'!$C:$C,'P&L Forecast'!$B13) -> 0 | T13: =SUMIFS('Combined P&L'!R:R,'Combined P&L'!$C:$C,'P&L Forecast'!$B13) -> 0 | U13: =SUMIFS('Combined P&L'!S:S,'Combined P&L'!$C:$C,'P&L Forecast'!$B13) -> 0 | V13: =SUMIFS('Combined P&L'!T:T,'Combined P&L'!$C:$C,'P&L Forecast'!$B13) -> 1.25 | W13: =SUMIFS('Combined P&L'!U:U,'Combined P&L'!$C:$C,'P&L Forecast'!$B13) -> 1.25 | X13: =SUMIFS('Combined P&L'!V:V,'Combined P&L'!$C:$C,'P&L Forecast'!$B13) -> 1.25 | Y13: =SUMIFS('Combined P&L'!W:W,'Combined P&L'!$C:$C,'P&L Forecast'!$B13) -> 1.25 | Z13: =SUMIFS('Combined P&L'!X:X,'Combined P&L'!$C:$C,'P&L Forecast'!$B13) -> 5.75 | AA13: =SUMIFS('Combined P&L'!Y:Y,'Combined P&L'!$C:$C,'P&L Forecast'!$B13) -> 3 | AB13: =SUMIFS('Combined P&L'!Z:Z,'Combined P&L'!$C:$C,'P&L Forecast'!$B13) -> 4.45 | AC13: =SUMIFS('Combined P&L'!AA:AA,'Combined P&L'!$C:$C,'P&L Forecast'!$B13) -> 3.45 | AD13: =SUMIFS('Combined P&L'!AB:AB,'Combined P&L'!$C:$C,'P&L Forecast'!$B13) -> 3.45 | AE13: =SUMIFS('Combined P&L'!AC:AC,'Combined P&L'!$C:$C,'P&L Forecast'!$B13) -> 5.95 | AF13: =SUMIFS('Combined P&L'!AD:AD,'Combined P&L'!$C:$C,'P&L Forecast'!$B13) -> 5.2 | AG13: =SUMIFS('Combined P&L'!AE:AE,'Combined P&L'!$C:$C,'P&L Forecast'!$B13) -> 5 | AH13: =SUMIFS('Combined P&L'!AF:AF,'Combined P&L'!$C:$C,'P&L Forecast'!$B13) -> 4 | AI13: =SUMIFS('Combined P&L'!AG:AG,'Combined P&L'!$C:$C,'P&L Forecast'!$B13) -> 2.95 | AJ13: =SUMIFS('Combined P&L'!AH:AH,'Combined P&L'!$C:$C,'P&L Forecast'!$B13) -> 3.025 | AK13: =SUMIFS('Combined P&L'!AI:AI,'Combined P&L'!$C:$C,'P&L Forecast'!$B13) -> 3.025 | AL13: =SUMIFS('Combined P&L'!AJ:AJ,'Combined P&L'!$C:$C,'P&L Forecast'!$B13) -> 2.95 | AM13: =SUMIFS('Combined P&L'!AK:AK,'Combined P&L'!$C:$C,'P&L Forecast'!$B13) -> 2.95 | AN13: =SUMIFS('Combined P&L'!AL:AL,'Combined P&L'!$C:$C,'P&L Forecast'!$B13) -> 2.75 | AO13: =SUMIFS('Combined P&L'!AM:AM,'Combined P&L'!$C:$C,'P&L Forecast'!$B13) -> 3.5 | AP13: =SUMIFS('Combined P&L'!AN:AN,'Combined P&L'!$C:$C,'P&L Forecast'!$B13) -> 2.75 | AQ13: =SUMIFS('Combined P&L'!AO:AO,'Combined P&L'!$C:$C,'P&L Forecast'!$B13) -> 4.75 | AR13: =SUMIFS('Combined P&L'!AP:AP,'Combined P&L'!$C:$C,'P&L Forecast'!$B13) -> 3.5 | AS13: =SUMIFS('Combined P&L'!AQ:AQ,'Combined P&L'!$C:$C,'P&L Forecast'!$B13) -> 3.5 | AT13: =SUMIFS('Combined P&L'!AR:AR,'Combined P&L'!$C:$C,'P&L Forecast'!$B13) -> 3.5
B14: Historical Cleanup | C14: =SUMIFS($P14:$AT14,$P$5:$AT$5,">"&C$168,$P$5:$AT$5,"<"&C$169) -> 17.624 | D14: =SUMIFS($P14:$AT14,$P$5:$AT$5,">"&D$168,$P$5:$AT$5,"<"&D$169) -> 5.03375 | F14: =SUMIFS($P14:$AT14,$P$5:$AT$5,">"&F$168,$P$5:$AT$5,"<"&F$169) -> 4.43875 | G14: =SUMIFS($P14:$AT14,$P$5:$AT$5,">"&G$168,$P$5:$AT$5,"<"&G$169) -> 0 | I14: =SUMIFS($P14:$AT14,$P$5:$AT$5,">"&I$168,$P$5:$AT$5,"<"&I$169) -> 12.84275 | J14: =SUMIFS($P14:$AT14,$P$5:$AT$5,">"&J$168,$P$5:$AT$5,"<"&J$169) -> 0.595 | K14: =+C113 -> 0 | M14: =K14-J14 -> -0.595 | N14: =IFERROR(K14/J14-1,0) -> -1 | P14: =SUMIFS('Combined P&L'!N:N,'Combined P&L'!$C:$C,'P&L Forecast'!$B14) -> 1.2 | Q14: =SUMIFS('Combined P&L'!O:O,'Combined P&L'!$C:$C,'P&L Forecast'!$B14) -> 1.7625 | R14: =SUMIFS('Combined P&L'!P:P,'Combined P&L'!$C:$C,'P&L Forecast'!$B14) -> 0.66 | S14: =SUMIFS('Combined P&L'!Q:Q,'Combined P&L'!$C:$C,'P&L Forecast'!$B14) -> 0.395 | T14: =SUMIFS('Combined P&L'!R:R,'Combined P&L'!$C:$C,'P&L Forecast'!$B14) -> 2.465 | U14: =SUMIFS('Combined P&L'!S:S,'Combined P&L'!$C:$C,'P&L Forecast'!$B14) -> 1.275 | V14: =SUMIFS('Combined P&L'!T:T,'Combined P&L'!$C:$C,'P&L Forecast'!$B14) -> 1.4625 | W14: =SUMIFS('Combined P&L'!U:U,'Combined P&L'!$C:$C,'P&L Forecast'!$B14) -> 0 | X14: =SUMIFS('Combined P&L'!V:V,'Combined P&L'!$C:$C,'P&L Forecast'!$B14) -> 1.14525 | Y14: =SUMIFS('Combined P&L'!W:W,'Combined P&L'!$C:$C,'P&L Forecast'!$B14) -> 1.35525 | Z14: =SUMIFS('Combined P&L'!X:X,'Combined P&L'!$C:$C,'P&L Forecast'!$B14) -> 1.9035 | AA14: =SUMIFS('Combined P&L'!Y:Y,'Combined P&L'!$C:$C,'P&L Forecast'!$B14) -> 4 | AB14: =SUMIFS('Combined P&L'!Z:Z,'Combined P&L'!$C:$C,'P&L Forecast'!$B14) -> 1.08375 | AC14: =SUMIFS('Combined P&L'!AA:AA,'Combined P&L'!$C:$C,'P&L Forecast'!$B14) -> 2 | AD14: =SUMIFS('Combined P&L'!AB:AB,'Combined P&L'!$C:$C,'P&L Forecast'!$B14) -> 1.355 | AE14: =SUMIFS('Combined P&L'!AC:AC,'Combined P&L'!$C:$C,'P&L Forecast'!$B14) -> 0 | AF14: =SUMIFS('Combined P&L'!AD:AD,'Combined P&L'!$C:$C,'P&L Forecast'!$B14) -> 0 | AG14: =SUMIFS('Combined P&L'!AE:AE,'Combined P&L'!$C:$C,'P&L Forecast'!$B14) -> 0 | AH14: =SUMIFS('Combined P&L'!AF:AF,'Combined P&L'!$C:$C,'P&L Forecast'!$B14) -> 0 | AI14: =SUMIFS('Combined P&L'!AG:AG,'Combined P&L'!$C:$C,'P&L Forecast'!$B14) -> 0 | AJ14: =SUMIFS('Combined P&L'!AH:AH,'Combined P&L'!$C:$C,'P&L Forecast'!$B14) -> 0 | AK14: =SUMIFS('Combined P&L'!AI:AI,'Combined P&L'!$C:$C,'P&L Forecast'!$B14) -> 0.595 | AL14: =SUMIFS('Combined P&L'!AJ:AJ,'Combined P&L'!$C:$C,'P&L Forecast'!$B14) -> 0 | AM14: =SUMIFS('Combined P&L'!AK:AK,'Combined P&L'!$C:$C,'P&L Forecast'!$B14) -> 0 | AN14: =SUMIFS('Combined P&L'!AL:AL,'Combined P&L'!$C:$C,'P&L Forecast'!$B14) -> 0 | AO14: =SUMIFS('Combined P&L'!AM:AM,'Combined P&L'!$C:$C,'P&L Forecast'!$B14) -> 0 | AP14: =SUMIFS('Combined P&L'!AN:AN,'Combined P&L'!$C:$C,'P&L Forecast'!$B14) -> 0 | AQ14: =SUMIFS('Combined P&L'!AO:AO,'Combined P&L'!$C:$C,'P&L Forecast'!$B14) -> 0 | AR14: =SUMIFS('Combined P&L'!AP:AP,'Combined P&L'!$C:$C,'P&L Forecast'!$B14) -> 0 | AS14: =SUMIFS('Combined P&L'!AQ:AQ,'Combined P&L'!$C:$C,'P&L Forecast'!$B14) -> 0 | AT14: =SUMIFS('Combined P&L'!AR:AR,'Combined P&L'!$C:$C,'P&L Forecast'!$B14) -> 0
B15: Total Recurring Revenue | C15: =SUM(C7:C14) -> 1094.3157 | D15: =SUM(D7:D14) -> 1827.8494 | F15: =SUM(F7:F14) -> 958.8909 | G15: =SUM(G7:G14) -> 1600.0675 | I15: =SUM(I7:I14) -> 1475.5391 | J15: =SUM(J7:J14) -> 2469.026 | K15: =SUM(K7:K14) -> 2926.7433 | M15: =SUM(M7:M14) -> 457.71731 | N15: =IFERROR(K15/J15-1,0) -> 0.18538376 | P15: =SUM(P7:P14) -> 73.3495 | Q15: =SUM(Q7:Q14) -> 74.7445 | R15: =SUM(R7:R14) -> 77.996 | S15: =SUM(S7:S14) -> 83.2127 | T15: =SUM(T7:T14) -> 86.60415 | U15: =SUM(U7:U14) -> 88.544 | V15: =SUM(V7:V14) -> 93.21675 | W15: =SUM(W7:W14) -> 96.77535 | ... AT15: =SUM(AT7:AT14) -> 251.33865
B17: Profit Share | C17: =SUMIFS($P17:$AT17,$P$5:$AT$5,">"&C$168,$P$5:$AT$5,"<"&C$169) -> 6.2004 | D17: =SUMIFS($P17:$AT17,$P$5:$AT$5,">"&D$168,$P$5:$AT$5,"<"&D$169) -> 23.26179 | F17: =SUMIFS($P17:$AT17,$P$5:$AT$5,">"&F$168,$P$5:$AT$5,"<"&F$169) -> 14.50495 | G17: =SUMIFS($P17:$AT17,$P$5:$AT$5,">"&G$168,$P$5:$AT$5,"<"&G$169) -> 8.07938 | I17: =SUMIFS($P17:$AT17,$P$5:$AT$5,">"&I$168,$P$5:$AT$5,"<"&I$169) -> 18.32935 | J17: =SUMIFS($P17:$AT17,$P$5:$AT$5,">"&J$168,$P$5:$AT$5,"<"&J$169) -> 16.83622 | K17: =+C118 -> 16.83622 | M17: =K17-J17 -> 0 | N17: =IFERROR(K17/J17-1,0) -> 0 | P17: =SUMIFS('Combined P&L'!N:N,'Combined P&L'!$C:$C,'P&L Forecast'!$B17) -> 0.0686 | Q17: =SUMIFS('Combined P&L'!O:O,'Combined P&L'!$C:$C,'P&L Forecast'!$B17) -> 0.1312 | R17: =SUMIFS('Combined P&L'!P:P,'Combined P&L'!$C:$C,'P&L Forecast'!$B17) -> 0.0712 | S17: =SUMIFS('Combined P&L'!Q:Q,'Combined P&L'!$C:$C,'P&L Forecast'!$B17) -> 0.0556 | T17: =SUMIFS('Combined P&L'!R:R,'Combined P&L'!$C:$C,'P&L Forecast'!$B17) -> 0.577 | U17: =SUMIFS('Combined P&L'!S:S,'Combined P&L'!$C:$C,'P&L Forecast'!$B17) -> 0.8068 | V17: =SUMIFS('Combined P&L'!T:T,'Combined P&L'!$C:$C,'P&L Forecast'!$B17) -> 0.6656 | W17: =SUMIFS('Combined P&L'!U:U,'Combined P&L'!$C:$C,'P&L Forecast'!$B17) -> 0.8264 | X17: =SUMIFS('Combined P&L'!V:V,'Combined P&L'!$C:$C,'P&L Forecast'!$B17) -> 1.3808 | Y17: =SUMIFS('Combined P&L'!W:W,'Combined P&L'!$C:$C,'P&L Forecast'!$B17) -> 0.8604 | Z17: =SUMIFS('Combined P&L'!X:X,'Combined P&L'!$C:$C,'P&L Forecast'!$B17) -> 0.51 | AA17: =SUMIFS('Combined P&L'!Y:Y,'Combined P&L'!$C:$C,'P&L Forecast'!$B17) -> 0.2468 | AB17: =SUMIFS('Combined P&L'!Z:Z,'Combined P&L'!$C:$C,'P&L Forecast'!$B17) -> 7.3584 | AC17: =SUMIFS('Combined P&L'!AA:AA,'Combined P&L'!$C:$C,'P&L Forecast'!$B17) -> 1.29335 | AD17: =SUMIFS('Combined P&L'!AB:AB,'Combined P&L'!$C:$C,'P&L Forecast'!$B17) -> 0.96833 | AE17: =SUMIFS('Combined P&L'!AC:AC,'Combined P&L'!$C:$C,'P&L Forecast'!$B17) -> 1.1656 | AF17: =SUMIFS('Combined P&L'!AD:AD,'Combined P&L'!$C:$C,'P&L Forecast'!$B17) -> 0.96093 | AG17: =SUMIFS('Combined P&L'!AE:AE,'Combined P&L'!$C:$C,'P&L Forecast'!$B17) -> 1.71127 | AH17: =SUMIFS('Combined P&L'!AF:AF,'Combined P&L'!$C:$C,'P&L Forecast'!$B17) -> 1.04707 | AI17: =SUMIFS('Combined P&L'!AG:AG,'Combined P&L'!$C:$C,'P&L Forecast'!$B17) -> 2.04088 | AJ17: =SUMIFS('Combined P&L'!AH:AH,'Combined P&L'!$C:$C,'P&L Forecast'!$B17) -> 1.13621 | AK17: =SUMIFS('Combined P&L'!AI:AI,'Combined P&L'!$C:$C,'P&L Forecast'!$B17) -> 2.01424 | AL17: =SUMIFS('Combined P&L'!AJ:AJ,'Combined P&L'!$C:$C,'P&L Forecast'!$B17) -> 1.29758 | AM17: =SUMIFS('Combined P&L'!AK:AK,'Combined P&L'!$C:$C,'P&L Forecast'!$B17) -> 2.26793 | AN17: =SUMIFS('Combined P&L'!AL:AL,'Combined P&L'!$C:$C,'P&L Forecast'!$B17) -> 2.67784 | AO17: =SUMIFS('Combined P&L'!AM:AM,'Combined P&L'!$C:$C,'P&L Forecast'!$B17) -> 2.35401 | AP17: =SUMIFS('Combined P&L'!AN:AN,'Combined P&L'!$C:$C,'P&L Forecast'!$B17) -> 0.2276 | AQ17: =SUMIFS('Combined P&L'!AO:AO,'Combined P&L'!$C:$C,'P&L Forecast'!$B17) -> 1.47836 | AR17: =SUMIFS('Combined P&L'!AP:AP,'Combined P&L'!$C:$C,'P&L Forecast'!$B17) -> 0.66824 | AS17: =SUMIFS('Combined P&L'!AQ:AQ,'Combined P&L'!$C:$C,'P&L Forecast'!$B17) -> 0.58613 | AT17: =SUMIFS('Combined P&L'!AR:AR,'Combined P&L'!$C:$C,'P&L Forecast'!$B17) -> 0.0872
B18: 1099 Filing | C18: =SUMIFS($P18:$AT18,$P$5:$AT$5,">"&C$168,$P$5:$AT$5,"<"&C$169) -> 10.475 | D18: =SUMIFS($P18:$AT18,$P$5:$AT$5,">"&D$168,$P$5:$AT$5,"<"&D$169) -> 23.55 | F18: =SUMIFS($P18:$AT18,$P$5:$AT$5,">"&F$168,$P$5:$AT$5,"<"&F$169) -> 23.49 | G18: =SUMIFS($P18:$AT18,$P$5:$AT$5,">"&G$168,$P$5:$AT$5,"<"&G$169) -> 38.7015 | I18: =SUMIFS($P18:$AT18,$P$5:$AT$5,">"&I$168,$P$5:$AT$5,"<"&I$169) -> 23.52 | J18: =SUMIFS($P18:$AT18,$P$5:$AT$5,">"&J$168,$P$5:$AT$5,"<"&J$169) -> 38.7615 | K18: =+C116 -> 38.7615 | M18: =K18-J18 -> 0 | N18: =IFERROR(K18/J18-1,0) -> 0 | P18: =SUMIFS('Combined P&L'!N:N,'Combined P&L'!$C:$C,'P&L Forecast'!$B18) -> 6.945 | Q18: =SUMIFS('Combined P&L'!O:O,'Combined P&L'!$C:$C,'P&L Forecast'!$B18) -> 3.38 | R18: =SUMIFS('Combined P&L'!P:P,'Combined P&L'!$C:$C,'P&L Forecast'!$B18) -> 0.045 | S18: =SUMIFS('Combined P&L'!Q:Q,'Combined P&L'!$C:$C,'P&L Forecast'!$B18) -> 0.06 | T18: =SUMIFS('Combined P&L'!R:R,'Combined P&L'!$C:$C,'P&L Forecast'!$B18) -> 0.015 | U18: =SUMIFS('Combined P&L'!S:S,'Combined P&L'!$C:$C,'P&L Forecast'!$B18) -> 0 | V18: =SUMIFS('Combined P&L'!T:T,'Combined P&L'!$C:$C,'P&L Forecast'!$B18) -> 0 | W18: =SUMIFS('Combined P&L'!U:U,'Combined P&L'!$C:$C,'P&L Forecast'!$B18) -> 0.015 | X18: =SUMIFS('Combined P&L'!V:V,'Combined P&L'!$C:$C,'P&L Forecast'!$B18) -> 0 | Y18: =SUMIFS('Combined P&L'!W:W,'Combined P&L'!$C:$C,'P&L Forecast'!$B18) -> 0 | Z18: =SUMIFS('Combined P&L'!X:X,'Combined P&L'!$C:$C,'P&L Forecast'!$B18) -> 0.015 | AA18: =SUMIFS('Combined P&L'!Y:Y,'Combined P&L'!$C:$C,'P&L Forecast'!$B18) -> 0 | AB18: =SUMIFS('Combined P&L'!Z:Z,'Combined P&L'!$C:$C,'P&L Forecast'!$B18) -> 13.485 | AC18: =SUMIFS('Combined P&L'!AA:AA,'Combined P&L'!$C:$C,'P&L Forecast'!$B18) -> 9.915 | AD18: =SUMIFS('Combined P&L'!AB:AB,'Combined P&L'!$C:$C,'P&L Forecast'!$B18) -> 0.06 | AE18: =SUMIFS('Combined P&L'!AC:AC,'Combined P&L'!$C:$C,'P&L Forecast'!$B18) -> 0.03 | AF18: =SUMIFS('Combined P&L'!AD:AD,'Combined P&L'!$C:$C,'P&L Forecast'!$B18) -> 0 | AG18: =SUMIFS('Combined P&L'!AE:AE,'Combined P&L'!$C:$C,'P&L Forecast'!$B18) -> 0 | AH18: =SUMIFS('Combined P&L'!AF:AF,'Combined P&L'!$C:$C,'P&L Forecast'!$B18) -> 0 | AI18: =SUMIFS('Combined P&L'!AG:AG,'Combined P&L'!$C:$C,'P&L Forecast'!$B18) -> 0.03 | AJ18: =SUMIFS('Combined P&L'!AH:AH,'Combined P&L'!$C:$C,'P&L Forecast'!$B18) -> 0.03 | AK18: =SUMIFS('Combined P&L'!AI:AI,'Combined P&L'!$C:$C,'P&L Forecast'!$B18) -> 0 | AL18: =SUMIFS('Combined P&L'!AJ:AJ,'Combined P&L'!$C:$C,'P&L Forecast'!$B18) -> 0 | AM18: =SUMIFS('Combined P&L'!AK:AK,'Combined P&L'!$C:$C,'P&L Forecast'!$B18) -> 0 | AN18: =SUMIFS('Combined P&L'!AL:AL,'Combined P&L'!$C:$C,'P&L Forecast'!$B18) -> 6.105 | AO18: =SUMIFS('Combined P&L'!AM:AM,'Combined P&L'!$C:$C,'P&L Forecast'!$B18) -> 31.1565 | AP18: =SUMIFS('Combined P&L'!AN:AN,'Combined P&L'!$C:$C,'P&L Forecast'!$B18) -> 1.26 | AQ18: =SUMIFS('Combined P&L'!AO:AO,'Combined P&L'!$C:$C,'P&L Forecast'!$B18) -> 0.18 | AR18: =SUMIFS('Combined P&L'!AP:AP,'Combined P&L'!$C:$C,'P&L Forecast'!$B18) -> 0 | AS18: =SUMIFS('Combined P&L'!AQ:AQ,'Combined P&L'!$C:$C,'P&L Forecast'!$B18) -> 0 | AT18: =SUMIFS('Combined P&L'!AR:AR,'Combined P&L'!$C:$C,'P&L Forecast'!$B18) -> 0
B19: Income Tax | C19: =SUMIFS($P19:$AT19,$P$5:$AT$5,">"&C$168,$P$5:$AT$5,"<"&C$169) -> 0 | D19: =SUMIFS($P19:$AT19,$P$5:$AT$5,">"&D$168,$P$5:$AT$5,"<"&D$169) -> 3.4 | F19: =SUMIFS($P19:$AT19,$P$5:$AT$5,">"&F$168,$P$5:$AT$5,"<"&F$169) -> 0 | G19: =SUMIFS($P19:$AT19,$P$5:$AT$5,">"&G$168,$P$5:$AT$5,"<"&G$169) -> 23.915 | I19: =SUMIFS($P19:$AT19,$P$5:$AT$5,">"&I$168,$P$5:$AT$5,"<"&I$169) -> 0 | J19: =SUMIFS($P19:$AT19,$P$5:$AT$5,">"&J$168,$P$5:$AT$5,"<"&J$169) -> 27.315 | K19: =+C117 -> 0 | M19: =K19-J19 -> -27.315 | N19: =IFERROR(K19/J19-1,0) -> -1 | P19: =SUMIFS('Combined P&L'!N:N,'Combined P&L'!$C:$C,'P&L Forecast'!$B19) -> 0 | Q19: =SUMIFS('Combined P&L'!O:O,'Combined P&L'!$C:$C,'P&L Forecast'!$B19) -> 0 | R19: =SUMIFS('Combined P&L'!P:P,'Combined P&L'!$C:$C,'P&L Forecast'!$B19) -> 0 | S19: =SUMIFS('Combined P&L'!Q:Q,'Combined P&L'!$C:$C,'P&L Forecast'!$B19) -> 0 | T19: =SUMIFS('Combined P&L'!R:R,'Combined P&L'!$C:$C,'P&L Forecast'!$B19) -> 0 | U19: =SUMIFS('Combined P&L'!S:S,'Combined P&L'!$C:$C,'P&L Forecast'!$B19) -> 0 | V19: =SUMIFS('Combined P&L'!T:T,'Combined P&L'!$C:$C,'P&L Forecast'!$B19) -> 0 | W19: =SUMIFS('Combined P&L'!U:U,'Combined P&L'!$C:$C,'P&L Forecast'!$B19) -> 0 | X19: =SUMIFS('Combined P&L'!V:V,'Combined P&L'!$C:$C,'P&L Forecast'!$B19) -> 0 | Y19: =SUMIFS('Combined P&L'!W:W,'Combined P&L'!$C:$C,'P&L Forecast'!$B19) -> 0 | Z19: =SUMIFS('Combined P&L'!X:X,'Combined P&L'!$C:$C,'P&L Forecast'!$B19) -> 0 | AA19: =SUMIFS('Combined P&L'!Y:Y,'Combined P&L'!$C:$C,'P&L Forecast'!$B19) -> 0 | AB19: =SUMIFS('Combined P&L'!Z:Z,'Combined P&L'!$C:$C,'P&L Forecast'!$B19) -> 0 | AC19: =SUMIFS('Combined P&L'!AA:AA,'Combined P&L'!$C:$C,'P&L Forecast'!$B19) -> 0 | AD19: =SUMIFS('Combined P&L'!AB:AB,'Combined P&L'!$C:$C,'P&L Forecast'!$B19) -> 0 | AE19: =SUMIFS('Combined P&L'!AC:AC,'Combined P&L'!$C:$C,'P&L Forecast'!$B19) -> 0 | AF19: =SUMIFS('Combined P&L'!AD:AD,'Combined P&L'!$C:$C,'P&L Forecast'!$B19) -> 0 | AG19: =SUMIFS('Combined P&L'!AE:AE,'Combined P&L'!$C:$C,'P&L Forecast'!$B19) -> 0 | AH19: =SUMIFS('Combined P&L'!AF:AF,'Combined P&L'!$C:$C,'P&L Forecast'!$B19) -> 0 | AI19: =SUMIFS('Combined P&L'!AG:AG,'Combined P&L'!$C:$C,'P&L Forecast'!$B19) -> 0 | AJ19: =SUMIFS('Combined P&L'!AH:AH,'Combined P&L'!$C:$C,'P&L Forecast'!$B19) -> 0.875 | AK19: =SUMIFS('Combined P&L'!AI:AI,'Combined P&L'!$C:$C,'P&L Forecast'!$B19) -> 1.65 | AL19: =SUMIFS('Combined P&L'!AJ:AJ,'Combined P&L'!$C:$C,'P&L Forecast'!$B19) -> 0 | AM19: =SUMIFS('Combined P&L'!AK:AK,'Combined P&L'!$C:$C,'P&L Forecast'!$B19) -> 0.875 | AN19: =SUMIFS('Combined P&L'!AL:AL,'Combined P&L'!$C:$C,'P&L Forecast'!$B19) -> 0 | AO19: =SUMIFS('Combined P&L'!AM:AM,'Combined P&L'!$C:$C,'P&L Forecast'!$B19) -> 0 | AP19: =SUMIFS('Combined P&L'!AN:AN,'Combined P&L'!$C:$C,'P&L Forecast'!$B19) -> 14.19 | AQ19: =SUMIFS('Combined P&L'!AO:AO,'Combined P&L'!$C:$C,'P&L Forecast'!$B19) -> 6.625 | AR19: =SUMIFS('Combined P&L'!AP:AP,'Combined P&L'!$C:$C,'P&L Forecast'!$B19) -> 0 | AS19: =SUMIFS('Combined P&L'!AQ:AQ,'Combined P&L'!$C:$C,'P&L Forecast'!$B19) -> 3.1 | AT19: =SUMIFS('Combined P&L'!AR:AR,'Combined P&L'!$C:$C,'P&L Forecast'!$B19) -> 0
B20: Billable Expense Income | C20: =SUMIFS($P20:$AT20,$P$5:$AT$5,">"&C$168,$P$5:$AT$5,"<"&C$169) -> 0.3747 | D20: =SUMIFS($P20:$AT20,$P$5:$AT$5,">"&D$168,$P$5:$AT$5,"<"&D$169) -> 1.12194 | F20: =SUMIFS($P20:$AT20,$P$5:$AT$5,">"&F$168,$P$5:$AT$5,"<"&F$169) -> 0.78725 | G20: =SUMIFS($P20:$AT20,$P$5:$AT$5,">"&G$168,$P$5:$AT$5,"<"&G$169) -> 0.25783 | I20: =SUMIFS($P20:$AT20,$P$5:$AT$5,">"&I$168,$P$5:$AT$5,"<"&I$169) -> 0.78725 | J20: =SUMIFS($P20:$AT20,$P$5:$AT$5,">"&J$168,$P$5:$AT$5,"<"&J$169) -> 0.59252 | K20: =+C119 -> 0 | M20: =K20-J20 -> -0.59252 | N20: =IFERROR(K20/J20-1,0) -> -1 | P20: =SUMIFS('Combined P&L'!N:N,'Combined P&L'!$C:$C,'P&L Forecast'!$B20) -> 0.05 | Q20: =SUMIFS('Combined P&L'!O:O,'Combined P&L'!$C:$C,'P&L Forecast'!$B20) -> 0 | R20: =SUMIFS('Combined P&L'!P:P,'Combined P&L'!$C:$C,'P&L Forecast'!$B20) -> 0 | S20: =SUMIFS('Combined P&L'!Q:Q,'Combined P&L'!$C:$C,'P&L Forecast'!$B20) -> 0.025 | T20: =SUMIFS('Combined P&L'!R:R,'Combined P&L'!$C:$C,'P&L Forecast'!$B20) -> 0 | U20: =SUMIFS('Combined P&L'!S:S,'Combined P&L'!$C:$C,'P&L Forecast'!$B20) -> 0 | V20: =SUMIFS('Combined P&L'!T:T,'Combined P&L'!$C:$C,'P&L Forecast'!$B20) -> 0.2997 | W20: =SUMIFS('Combined P&L'!U:U,'Combined P&L'!$C:$C,'P&L Forecast'!$B20) -> 0 | X20: =SUMIFS('Combined P&L'!V:V,'Combined P&L'!$C:$C,'P&L Forecast'!$B20) -> 0 | Y20: =SUMIFS('Combined P&L'!W:W,'Combined P&L'!$C:$C,'P&L Forecast'!$B20) -> 0 | Z20: =SUMIFS('Combined P&L'!X:X,'Combined P&L'!$C:$C,'P&L Forecast'!$B20) -> 0 | AA20: =SUMIFS('Combined P&L'!Y:Y,'Combined P&L'!$C:$C,'P&L Forecast'!$B20) -> 0 | AB20: =SUMIFS('Combined P&L'!Z:Z,'Combined P&L'!$C:$C,'P&L Forecast'!$B20) -> 0.025 | AC20: =SUMIFS('Combined P&L'!AA:AA,'Combined P&L'!$C:$C,'P&L Forecast'!$B20) -> 0.3996 | AD20: =SUMIFS('Combined P&L'!AB:AB,'Combined P&L'!$C:$C,'P&L Forecast'!$B20) -> 0 | AE20: =SUMIFS('Combined P&L'!AC:AC,'Combined P&L'!$C:$C,'P&L Forecast'!$B20) -> 0 | AF20: =SUMIFS('Combined P&L'!AD:AD,'Combined P&L'!$C:$C,'P&L Forecast'!$B20) -> 0.07294 | AG20: =SUMIFS('Combined P&L'!AE:AE,'Combined P&L'!$C:$C,'P&L Forecast'!$B20) -> 0 | AH20: =SUMIFS('Combined P&L'!AF:AF,'Combined P&L'!$C:$C,'P&L Forecast'!$B20) -> 0.28971 | AI20: =SUMIFS('Combined P&L'!AG:AG,'Combined P&L'!$C:$C,'P&L Forecast'!$B20) -> 0.30969 | AJ20: =SUMIFS('Combined P&L'!AH:AH,'Combined P&L'!$C:$C,'P&L Forecast'!$B20) -> 0 | AK20: =SUMIFS('Combined P&L'!AI:AI,'Combined P&L'!$C:$C,'P&L Forecast'!$B20) -> 0 | AL20: =SUMIFS('Combined P&L'!AJ:AJ,'Combined P&L'!$C:$C,'P&L Forecast'!$B20) -> 0 | AM20: =SUMIFS('Combined P&L'!AK:AK,'Combined P&L'!$C:$C,'P&L Forecast'!$B20) -> 0.025 | AN20: =SUMIFS('Combined P&L'!AL:AL,'Combined P&L'!$C:$C,'P&L Forecast'!$B20) -> 0.15984 | AO20: =SUMIFS('Combined P&L'!AM:AM,'Combined P&L'!$C:$C,'P&L Forecast'!$B20) -> 0 | AP20: =SUMIFS('Combined P&L'!AN:AN,'Combined P&L'!$C:$C,'P&L Forecast'!$B20) -> 0.075 | AQ20: =SUMIFS('Combined P&L'!AO:AO,'Combined P&L'!$C:$C,'P&L Forecast'!$B20) -> 0 | AR20: =SUMIFS('Combined P&L'!AP:AP,'Combined P&L'!$C:$C,'P&L Forecast'!$B20) -> 0 | AS20: =SUMIFS('Combined P&L'!AQ:AQ,'Combined P&L'!$C:$C,'P&L Forecast'!$B20) -> 0.02299 | AT20: =SUMIFS('Combined P&L'!AR:AR,'Combined P&L'!$C:$C,'P&L Forecast'!$B20) -> 0
B21: Offshore Recruiting | C21: =SUMIFS($P21:$AT21,$P$5:$AT$5,">"&C$168,$P$5:$AT$5,"<"&C$169) -> 23.6 | D21: =SUMIFS($P21:$AT21,$P$5:$AT$5,">"&D$168,$P$5:$AT$5,"<"&D$169) -> 0.2 | F21: =SUMIFS($P21:$AT21,$P$5:$AT$5,">"&F$168,$P$5:$AT$5,"<"&F$169) -> 0.2 | G21: =SUMIFS($P21:$AT21,$P$5:$AT$5,">"&G$168,$P$5:$AT$5,"<"&G$169) -> 0 | I21: =SUMIFS($P21:$AT21,$P$5:$AT$5,">"&I$168,$P$5:$AT$5,"<"&I$169) -> 6.235 | J21: =SUMIFS($P21:$AT21,$P$5:$AT$5,">"&J$168,$P$5:$AT$5,"<"&J$169) -> 0 | K21: =+C120 -> 0 | M21: =K21-J21 -> 0 | N21: =IFERROR(K21/J21-1,0) -> 0 | P21: =SUMIFS('Combined P&L'!N:N,'Combined P&L'!$C:$C,'P&L Forecast'!$B21) -> 0.5 | Q21: =SUMIFS('Combined P&L'!O:O,'Combined P&L'!$C:$C,'P&L Forecast'!$B21) -> 3 | R21: =SUMIFS('Combined P&L'!P:P,'Combined P&L'!$C:$C,'P&L Forecast'!$B21) -> 0 | S21: =SUMIFS('Combined P&L'!Q:Q,'Combined P&L'!$C:$C,'P&L Forecast'!$B21) -> 0 | T21: =SUMIFS('Combined P&L'!R:R,'Combined P&L'!$C:$C,'P&L Forecast'!$B21) -> 3 | U21: =SUMIFS('Combined P&L'!S:S,'Combined P&L'!$C:$C,'P&L Forecast'!$B21) -> 0.565 | V21: =SUMIFS('Combined P&L'!T:T,'Combined P&L'!$C:$C,'P&L Forecast'!$B21) -> 10.5 | W21: =SUMIFS('Combined P&L'!U:U,'Combined P&L'!$C:$C,'P&L Forecast'!$B21) -> 6.5 | X21: =SUMIFS('Combined P&L'!V:V,'Combined P&L'!$C:$C,'P&L Forecast'!$B21) -> 0.5 | Y21: =SUMIFS('Combined P&L'!W:W,'Combined P&L'!$C:$C,'P&L Forecast'!$B21) -> -0.965 | Z21: =SUMIFS('Combined P&L'!X:X,'Combined P&L'!$C:$C,'P&L Forecast'!$B21) -> 0 | AA21: =SUMIFS('Combined P&L'!Y:Y,'Combined P&L'!$C:$C,'P&L Forecast'!$B21) -> 0 | AB21: =SUMIFS('Combined P&L'!Z:Z,'Combined P&L'!$C:$C,'P&L Forecast'!$B21) -> 0.1 | AC21: =SUMIFS('Combined P&L'!AA:AA,'Combined P&L'!$C:$C,'P&L Forecast'!$B21) -> 0 | AD21: =SUMIFS('Combined P&L'!AB:AB,'Combined P&L'!$C:$C,'P&L Forecast'!$B21) -> 0.1 | AE21: =SUMIFS('Combined P&L'!AC:AC,'Combined P&L'!$C:$C,'P&L Forecast'!$B21) -> 0 | AF21: =SUMIFS('Combined P&L'!AD:AD,'Combined P&L'!$C:$C,'P&L Forecast'!$B21) -> 0 | AG21: =SUMIFS('Combined P&L'!AE:AE,'Combined P&L'!$C:$C,'P&L Forecast'!$B21) -> 0 | AH21: =SUMIFS('Combined P&L'!AF:AF,'Combined P&L'!$C:$C,'P&L Forecast'!$B21) -> 0 | AI21: =SUMIFS('Combined P&L'!AG:AG,'Combined P&L'!$C:$C,'P&L Forecast'!$B21) -> 0 | AJ21: =SUMIFS('Combined P&L'!AH:AH,'Combined P&L'!$C:$C,'P&L Forecast'!$B21) -> 0 | AK21: =SUMIFS('Combined P&L'!AI:AI,'Combined P&L'!$C:$C,'P&L Forecast'!$B21) -> 0 | AL21: =SUMIFS('Combined P&L'!AJ:AJ,'Combined P&L'!$C:$C,'P&L Forecast'!$B21) -> 0 | AM21: =SUMIFS('Combined P&L'!AK:AK,'Combined P&L'!$C:$C,'P&L Forecast'!$B21) -> 0 | AN21: =SUMIFS('Combined P&L'!AL:AL,'Combined P&L'!$C:$C,'P&L Forecast'!$B21) -> 0 | AO21: =SUMIFS('Combined P&L'!AM:AM,'Combined P&L'!$C:$C,'P&L Forecast'!$B21) -> 0 | AP21: =SUMIFS('Combined P&L'!AN:AN,'Combined P&L'!$C:$C,'P&L Forecast'!$B21) -> 0 | AQ21: =SUMIFS('Combined P&L'!AO:AO,'Combined P&L'!$C:$C,'P&L Forecast'!$B21) -> 0 | AR21: =SUMIFS('Combined P&L'!AP:AP,'Combined P&L'!$C:$C,'P&L Forecast'!$B21) -> 0 | AS21: =SUMIFS('Combined P&L'!AQ:AQ,'Combined P&L'!$C:$C,'P&L Forecast'!$B21) -> 0 | AT21: =SUMIFS('Combined P&L'!AR:AR,'Combined P&L'!$C:$C,'P&L Forecast'!$B21) -> 0
B22: Total Nonrecurring Revenue | C22: =SUM(C17:C21) -> 40.6501 | D22: =SUM(D17:D21) -> 51.53373 | F22: =SUM(F17:F21) -> 38.9822 | G22: =SUM(G17:G21) -> 70.95371 | I22: =SUM(I17:I21) -> 48.8716 | J22: =SUM(J17:J21) -> 83.50524 | K22: =SUM(K17:K21) -> 55.59772 | M22: =SUM(M17:M21) -> -27.90752 | N22: =IFERROR(K22/J22-1,0) -> -0.33420082 | P22: =SUM(P17:P21) -> 7.5636 | Q22: =SUM(Q17:Q21) -> 6.5112 | R22: =SUM(R17:R21) -> 0.1162 | S22: =SUM(S17:S21) -> 0.1406 | T22: =SUM(T17:T21) -> 3.592 | U22: =SUM(U17:U21) -> 1.3718 | V22: =SUM(V17:V21) -> 11.4653 | W22: =SUM(W17:W21) -> 7.3414 | ... AT22: =SUM(AT17:AT21) -> 0.0872
B24: Total Revenue | C24: =+C22+C15 -> 1134.9659 | D24: =+D22+D15 -> 1879.3831 | F24: =+F22+F15 -> 997.8731 | G24: =+G22+G15 -> 1671.0212 | I24: =+I22+I15 -> 1524.4107 | J24: =+J22+J15 -> 2552.5312 | K24: =+K22+K15 -> 2982.341 | M24: =+M22+M15 -> 429.80979 | N24: =IFERROR(K24/J24-1,0) -> 0.16838571 | P24: =+P22+P15 -> 80.9131 | Q24: =+Q22+Q15 -> 81.2557 | R24: =+R22+R15 -> 78.1122 | S24: =+S22+S15 -> 83.3533 | T24: =+T22+T15 -> 90.19615 | U24: =+U22+U15 -> 89.9158 | V24: =+V22+V15 -> 104.68205 | W24: =+W22+W15 -> 104.11675 | ... AT24: =+AT22+AT15 -> 251.42585
B26: Expenses
B27: Indirect Labor | C27: =SUMIFS($P27:$AT27,$P$5:$AT$5,">"&C$168,$P$5:$AT$5,"<"&C$169) -> 101.3752 | D27: =SUMIFS($P27:$AT27,$P$5:$AT$5,">"&D$168,$P$5:$AT$5,"<"&D$169) -> 281.24054 | F27: =SUMIFS($P27:$AT27,$P$5:$AT$5,">"&F$168,$P$5:$AT$5,"<"&F$169) -> 136.29648 | G27: =SUMIFS($P27:$AT27,$P$5:$AT$5,">"&G$168,$P$5:$AT$5,"<"&G$169) -> 357.27472 | I27: =SUMIFS($P27:$AT27,$P$5:$AT$5,">"&I$168,$P$5:$AT$5,"<"&I$169) -> 202.41598 | J27: =SUMIFS($P27:$AT27,$P$5:$AT$5,">"&J$168,$P$5:$AT$5,"<"&J$169) -> 502.21878 | K27: =+C124 -> 694.74456 | M27: =K27-J27 -> 192.52578 | N27: =IFERROR(K27/J27-1,0) -> 0.38335042 | P27: =SUMIFS('Combined P&L'!N:N,'Combined P&L'!$C:$C,'P&L Forecast'!$B27) -> 3.09346 | Q27: =SUMIFS('Combined P&L'!O:O,'Combined P&L'!$C:$C,'P&L Forecast'!$B27) -> 4.63017 | R27: =SUMIFS('Combined P&L'!P:P,'Combined P&L'!$C:$C,'P&L Forecast'!$B27) -> 4.39507 | S27: =SUMIFS('Combined P&L'!Q:Q,'Combined P&L'!$C:$C,'P&L Forecast'!$B27) -> 5.86387 | T27: =SUMIFS('Combined P&L'!R:R,'Combined P&L'!$C:$C,'P&L Forecast'!$B27) -> 7.37233 | U27: =SUMIFS('Combined P&L'!S:S,'Combined P&L'!$C:$C,'P&L Forecast'!$B27) -> 4.9504 | V27: =SUMIFS('Combined P&L'!T:T,'Combined P&L'!$C:$C,'P&L Forecast'!$B27) -> 4.9504 | W27: =SUMIFS('Combined P&L'!U:U,'Combined P&L'!$C:$C,'P&L Forecast'!$B27) -> 4.70035 | X27: =SUMIFS('Combined P&L'!V:V,'Combined P&L'!$C:$C,'P&L Forecast'!$B27) -> 4.9504 | Y27: =SUMIFS('Combined P&L'!W:W,'Combined P&L'!$C:$C,'P&L Forecast'!$B27) -> 5.99987 | Z27: =SUMIFS('Combined P&L'!X:X,'Combined P&L'!$C:$C,'P&L Forecast'!$B27) -> 26.02876 | AA27: =SUMIFS('Combined P&L'!Y:Y,'Combined P&L'!$C:$C,'P&L Forecast'!$B27) -> 24.44012 | AB27: =SUMIFS('Combined P&L'!Z:Z,'Combined P&L'!$C:$C,'P&L Forecast'!$B27) -> 21.05234 | AC27: =SUMIFS('Combined P&L'!AA:AA,'Combined P&L'!$C:$C,'P&L Forecast'!$B27) -> 19.91603 | AD27: =SUMIFS('Combined P&L'!AB:AB,'Combined P&L'!$C:$C,'P&L Forecast'!$B27) -> 11.74387 | AE27: =SUMIFS('Combined P&L'!AC:AC,'Combined P&L'!$C:$C,'P&L Forecast'!$B27) -> 19.61792 | AF27: =SUMIFS('Combined P&L'!AD:AD,'Combined P&L'!$C:$C,'P&L Forecast'!$B27) -> 20.66978 | AG27: =SUMIFS('Combined P&L'!AE:AE,'Combined P&L'!$C:$C,'P&L Forecast'!$B27) -> 20.6939 | AH27: =SUMIFS('Combined P&L'!AF:AF,'Combined P&L'!$C:$C,'P&L Forecast'!$B27) -> 22.60264 | AI27: =SUMIFS('Combined P&L'!AG:AG,'Combined P&L'!$C:$C,'P&L Forecast'!$B27) -> 19.96128 | AJ27: =SUMIFS('Combined P&L'!AH:AH,'Combined P&L'!$C:$C,'P&L Forecast'!$B27) -> 27.60563 | AK27: =SUMIFS('Combined P&L'!AI:AI,'Combined P&L'!$C:$C,'P&L Forecast'!$B27) -> 34.18589 | AL27: =SUMIFS('Combined P&L'!AJ:AJ,'Combined P&L'!$C:$C,'P&L Forecast'!$B27) -> 29.73157 | AM27: =SUMIFS('Combined P&L'!AK:AK,'Combined P&L'!$C:$C,'P&L Forecast'!$B27) -> 33.45969 | AN27: =SUMIFS('Combined P&L'!AL:AL,'Combined P&L'!$C:$C,'P&L Forecast'!$B27) -> 36.2536 | AO27: =SUMIFS('Combined P&L'!AM:AM,'Combined P&L'!$C:$C,'P&L Forecast'!$B27) -> 33.60751 | AP27: =SUMIFS('Combined P&L'!AN:AN,'Combined P&L'!$C:$C,'P&L Forecast'!$B27) -> 57.19924 | AQ27: =SUMIFS('Combined P&L'!AO:AO,'Combined P&L'!$C:$C,'P&L Forecast'!$B27) -> 58.24595 | AR27: =SUMIFS('Combined P&L'!AP:AP,'Combined P&L'!$C:$C,'P&L Forecast'!$B27) -> 54.06923 | AS27: =SUMIFS('Combined P&L'!AQ:AQ,'Combined P&L'!$C:$C,'P&L Forecast'!$B27) -> 60.00381 | AT27: =SUMIFS('Combined P&L'!AR:AR,'Combined P&L'!$C:$C,'P&L Forecast'!$B27) -> 57.89538
B28: Bookkeeper Wages | C28: =SUMIFS($P28:$AT28,$P$5:$AT$5,">"&C$168,$P$5:$AT$5,"<"&C$169) -> 183.36903 | D28: =SUMIFS($P28:$AT28,$P$5:$AT$5,">"&D$168,$P$5:$AT$5,"<"&D$169) -> 316.18462 | F28: =SUMIFS($P28:$AT28,$P$5:$AT$5,">"&F$168,$P$5:$AT$5,"<"&F$169) -> 147.26813 | G28: =SUMIFS($P28:$AT28,$P$5:$AT$5,">"&G$168,$P$5:$AT$5,"<"&G$169) -> 267.7574 | I28: =SUMIFS($P28:$AT28,$P$5:$AT$5,">"&I$168,$P$5:$AT$5,"<"&I$169) -> 240.18098 | J28: =SUMIFS($P28:$AT28,$P$5:$AT$5,">"&J$168,$P$5:$AT$5,"<"&J$169) -> 436.67389 | K28: =+C125 -> 533.8512 | M28: =K28-J28 -> 97.17731 | N28: =IFERROR(K28/J28-1,0) -> 0.22253978 | P28: =SUMIFS('Combined P&L'!N:N,'Combined P&L'!$C:$C,'P&L Forecast'!$B28) -> 9.555 | Q28: =SUMIFS('Combined P&L'!O:O,'Combined P&L'!$C:$C,'P&L Forecast'!$B28) -> 9.555 | R28: =SUMIFS('Combined P&L'!P:P,'Combined P&L'!$C:$C,'P&L Forecast'!$B28) -> 10.3972 | S28: =SUMIFS('Combined P&L'!Q:Q,'Combined P&L'!$C:$C,'P&L Forecast'!$B28) -> 14.99967 | T28: =SUMIFS('Combined P&L'!R:R,'Combined P&L'!$C:$C,'P&L Forecast'!$B28) -> 18.0098 | U28: =SUMIFS('Combined P&L'!S:S,'Combined P&L'!$C:$C,'P&L Forecast'!$B28) -> 13.89127 | V28: =SUMIFS('Combined P&L'!T:T,'Combined P&L'!$C:$C,'P&L Forecast'!$B28) -> 14.04824 | W28: =SUMIFS('Combined P&L'!U:U,'Combined P&L'!$C:$C,'P&L Forecast'!$B28) -> 13.39091 | X28: =SUMIFS('Combined P&L'!V:V,'Combined P&L'!$C:$C,'P&L Forecast'!$B28) -> 14.66931 | Y28: =SUMIFS('Combined P&L'!W:W,'Combined P&L'!$C:$C,'P&L Forecast'!$B28) -> 15.88253 | Z28: =SUMIFS('Combined P&L'!X:X,'Combined P&L'!$C:$C,'P&L Forecast'!$B28) -> 27.18867 | AA28: =SUMIFS('Combined P&L'!Y:Y,'Combined P&L'!$C:$C,'P&L Forecast'!$B28) -> 21.78143 | AB28: =SUMIFS('Combined P&L'!Z:Z,'Combined P&L'!$C:$C,'P&L Forecast'!$B28) -> 19.40233 | AC28: =SUMIFS('Combined P&L'!AA:AA,'Combined P&L'!$C:$C,'P&L Forecast'!$B28) -> 16.40053 | AD28: =SUMIFS('Combined P&L'!AB:AB,'Combined P&L'!$C:$C,'P&L Forecast'!$B28) -> 19.56983 | AE28: =SUMIFS('Combined P&L'!AC:AC,'Combined P&L'!$C:$C,'P&L Forecast'!$B28) -> 22.1542 | AF28: =SUMIFS('Combined P&L'!AD:AD,'Combined P&L'!$C:$C,'P&L Forecast'!$B28) -> 20.79154 | AG28: =SUMIFS('Combined P&L'!AE:AE,'Combined P&L'!$C:$C,'P&L Forecast'!$B28) -> 21.04079 | AH28: =SUMIFS('Combined P&L'!AF:AF,'Combined P&L'!$C:$C,'P&L Forecast'!$B28) -> 27.90891 | AI28: =SUMIFS('Combined P&L'!AG:AG,'Combined P&L'!$C:$C,'P&L Forecast'!$B28) -> 29.547 | AJ28: =SUMIFS('Combined P&L'!AH:AH,'Combined P&L'!$C:$C,'P&L Forecast'!$B28) -> 33.44727 | AK28: =SUMIFS('Combined P&L'!AI:AI,'Combined P&L'!$C:$C,'P&L Forecast'!$B28) -> 37.79432 | AL28: =SUMIFS('Combined P&L'!AJ:AJ,'Combined P&L'!$C:$C,'P&L Forecast'!$B28) -> 34.06332 | AM28: =SUMIFS('Combined P&L'!AK:AK,'Combined P&L'!$C:$C,'P&L Forecast'!$B28) -> 34.06458 | AN28: =SUMIFS('Combined P&L'!AL:AL,'Combined P&L'!$C:$C,'P&L Forecast'!$B28) -> 38.37888 | AO28: =SUMIFS('Combined P&L'!AM:AM,'Combined P&L'!$C:$C,'P&L Forecast'!$B28) -> 29.70152 | AP28: =SUMIFS('Combined P&L'!AN:AN,'Combined P&L'!$C:$C,'P&L Forecast'!$B28) -> 37.4225 | AQ28: =SUMIFS('Combined P&L'!AO:AO,'Combined P&L'!$C:$C,'P&L Forecast'!$B28) -> 38.7723 | AR28: =SUMIFS('Combined P&L'!AP:AP,'Combined P&L'!$C:$C,'P&L Forecast'!$B28) -> 38.29477 | AS28: =SUMIFS('Combined P&L'!AQ:AQ,'Combined P&L'!$C:$C,'P&L Forecast'!$B28) -> 40.69983 | AT28: =SUMIFS('Combined P&L'!AR:AR,'Combined P&L'!$C:$C,'P&L Forecast'!$B28) -> 44.4876
B29: Client Lead Wages | C29: =SUMIFS($P29:$AT29,$P$5:$AT$5,">"&C$168,$P$5:$AT$5,"<"&C$169) -> 286.16129 | D29: =SUMIFS($P29:$AT29,$P$5:$AT$5,">"&D$168,$P$5:$AT$5,"<"&D$169) -> 352.95844 | F29: =SUMIFS($P29:$AT29,$P$5:$AT$5,">"&F$168,$P$5:$AT$5,"<"&F$169) -> 201.27983 | G29: =SUMIFS($P29:$AT29,$P$5:$AT$5,">"&G$168,$P$5:$AT$5,"<"&G$169) -> 202.05309 | I29: =SUMIFS($P29:$AT29,$P$5:$AT$5,">"&I$168,$P$5:$AT$5,"<"&I$169) -> 353.12843 | J29: =SUMIFS($P29:$AT29,$P$5:$AT$5,">"&J$168,$P$5:$AT$5,"<"&J$169) -> 353.7317 | K29: =+C127 -> 392.92452 | M29: =K29-J29 -> 39.19282 | N29: =IFERROR(K29/J29-1,0) -> 0.11079816 | P29: =SUMIFS('Combined P&L'!N:N,'Combined P&L'!$C:$C,'P&L Forecast'!$B29) -> 9.96108 | Q29: =SUMIFS('Combined P&L'!O:O,'Combined P&L'!$C:$C,'P&L Forecast'!$B29) -> 13.85026 | R29: =SUMIFS('Combined P&L'!P:P,'Combined P&L'!$C:$C,'P&L Forecast'!$B29) -> 12.79054 | S29: =SUMIFS('Combined P&L'!Q:Q,'Combined P&L'!$C:$C,'P&L Forecast'!$B29) -> 14.57145 | T29: =SUMIFS('Combined P&L'!R:R,'Combined P&L'!$C:$C,'P&L Forecast'!$B29) -> 28.28563 | U29: =SUMIFS('Combined P&L'!S:S,'Combined P&L'!$C:$C,'P&L Forecast'!$B29) -> 26.54254 | V29: =SUMIFS('Combined P&L'!T:T,'Combined P&L'!$C:$C,'P&L Forecast'!$B29) -> 28.31119 | W29: =SUMIFS('Combined P&L'!U:U,'Combined P&L'!$C:$C,'P&L Forecast'!$B29) -> 28.18746 | X29: =SUMIFS('Combined P&L'!V:V,'Combined P&L'!$C:$C,'P&L Forecast'!$B29) -> 30.86801 | Y29: =SUMIFS('Combined P&L'!W:W,'Combined P&L'!$C:$C,'P&L Forecast'!$B29) -> 31.62128 | Z29: =SUMIFS('Combined P&L'!X:X,'Combined P&L'!$C:$C,'P&L Forecast'!$B29) -> 28.44974 | AA29: =SUMIFS('Combined P&L'!Y:Y,'Combined P&L'!$C:$C,'P&L Forecast'!$B29) -> 32.72211 | AB29: =SUMIFS('Combined P&L'!Z:Z,'Combined P&L'!$C:$C,'P&L Forecast'!$B29) -> 32.78076 | AC29: =SUMIFS('Combined P&L'!AA:AA,'Combined P&L'!$C:$C,'P&L Forecast'!$B29) -> 23.36184 | AD29: =SUMIFS('Combined P&L'!AB:AB,'Combined P&L'!$C:$C,'P&L Forecast'!$B29) -> 26.91427 | AE29: =SUMIFS('Combined P&L'!AC:AC,'Combined P&L'!$C:$C,'P&L Forecast'!$B29) -> 28.81298 | AF29: =SUMIFS('Combined P&L'!AD:AD,'Combined P&L'!$C:$C,'P&L Forecast'!$B29) -> 30.65875 | AG29: =SUMIFS('Combined P&L'!AE:AE,'Combined P&L'!$C:$C,'P&L Forecast'!$B29) -> 29.2716 | AH29: =SUMIFS('Combined P&L'!AF:AF,'Combined P&L'!$C:$C,'P&L Forecast'!$B29) -> 29.47963 | AI29: =SUMIFS('Combined P&L'!AG:AG,'Combined P&L'!$C:$C,'P&L Forecast'!$B29) -> 26.83064 | AJ29: =SUMIFS('Combined P&L'!AH:AH,'Combined P&L'!$C:$C,'P&L Forecast'!$B29) -> 29.78555 | AK29: =SUMIFS('Combined P&L'!AI:AI,'Combined P&L'!$C:$C,'P&L Forecast'!$B29) -> 32.89937 | AL29: =SUMIFS('Combined P&L'!AJ:AJ,'Combined P&L'!$C:$C,'P&L Forecast'!$B29) -> 29.49334 | AM29: =SUMIFS('Combined P&L'!AK:AK,'Combined P&L'!$C:$C,'P&L Forecast'!$B29) -> 32.66971 | AN29: =SUMIFS('Combined P&L'!AL:AL,'Combined P&L'!$C:$C,'P&L Forecast'!$B29) -> 26.1149 | AO29: =SUMIFS('Combined P&L'!AM:AM,'Combined P&L'!$C:$C,'P&L Forecast'!$B29) -> 21.9055 | AP29: =SUMIFS('Combined P&L'!AN:AN,'Combined P&L'!$C:$C,'P&L Forecast'!$B29) -> 30.75844 | AQ29: =SUMIFS('Combined P&L'!AO:AO,'Combined P&L'!$C:$C,'P&L Forecast'!$B29) -> 31.59038 | AR29: =SUMIFS('Combined P&L'!AP:AP,'Combined P&L'!$C:$C,'P&L Forecast'!$B29) -> 27.69992 | AS29: =SUMIFS('Combined P&L'!AQ:AQ,'Combined P&L'!$C:$C,'P&L Forecast'!$B29) -> 31.24024 | AT29: =SUMIFS('Combined P&L'!AR:AR,'Combined P&L'!$C:$C,'P&L Forecast'!$B29) -> 32.74371
B30: Onboarding Team Wages | C30: =SUMIFS($P30:$AT30,$P$5:$AT$5,">"&C$168,$P$5:$AT$5,"<"&C$169) -> 122.81255 | D30: =SUMIFS($P30:$AT30,$P$5:$AT$5,">"&D$168,$P$5:$AT$5,"<"&D$169) -> 152.16972 | F30: =SUMIFS($P30:$AT30,$P$5:$AT$5,">"&F$168,$P$5:$AT$5,"<"&F$169) -> 73.94962 | G30: =SUMIFS($P30:$AT30,$P$5:$AT$5,">"&G$168,$P$5:$AT$5,"<"&G$169) -> 111.27999 | I30: =SUMIFS($P30:$AT30,$P$5:$AT$5,">"&I$168,$P$5:$AT$5,"<"&I$169) -> 121.30735 | J30: =SUMIFS($P30:$AT30,$P$5:$AT$5,">"&J$168,$P$5:$AT$5,"<"&J$169) -> 189.50009 | K30: =+C131 -> 197.14944 | M30: =K30-J30 -> 7.64935 | N30: =IFERROR(K30/J30-1,0) -> 0.040365944 | P30: =SUMIFS('Combined P&L'!N:N,'Combined P&L'!$C:$C,'P&L Forecast'!$B30) -> 9.13728 | Q30: =SUMIFS('Combined P&L'!O:O,'Combined P&L'!$C:$C,'P&L Forecast'!$B30) -> 8.96296 | R30: =SUMIFS('Combined P&L'!P:P,'Combined P&L'!$C:$C,'P&L Forecast'!$B30) -> 10.19584 | S30: =SUMIFS('Combined P&L'!Q:Q,'Combined P&L'!$C:$C,'P&L Forecast'!$B30) -> 15.04429 | T30: =SUMIFS('Combined P&L'!R:R,'Combined P&L'!$C:$C,'P&L Forecast'!$B30) -> 16.63744 | U30: =SUMIFS('Combined P&L'!S:S,'Combined P&L'!$C:$C,'P&L Forecast'!$B30) -> 7.49499 | V30: =SUMIFS('Combined P&L'!T:T,'Combined P&L'!$C:$C,'P&L Forecast'!$B30) -> 7.98202 | W30: =SUMIFS('Combined P&L'!U:U,'Combined P&L'!$C:$C,'P&L Forecast'!$B30) -> 5.90274 | X30: =SUMIFS('Combined P&L'!V:V,'Combined P&L'!$C:$C,'P&L Forecast'!$B30) -> 7.76763 | Y30: =SUMIFS('Combined P&L'!W:W,'Combined P&L'!$C:$C,'P&L Forecast'!$B30) -> 8.21417 | Z30: =SUMIFS('Combined P&L'!X:X,'Combined P&L'!$C:$C,'P&L Forecast'!$B30) -> 12.62272 | AA30: =SUMIFS('Combined P&L'!Y:Y,'Combined P&L'!$C:$C,'P&L Forecast'!$B30) -> 12.85047 | AB30: =SUMIFS('Combined P&L'!Z:Z,'Combined P&L'!$C:$C,'P&L Forecast'!$B30) -> 10.34556 | AC30: =SUMIFS('Combined P&L'!AA:AA,'Combined P&L'!$C:$C,'P&L Forecast'!$B30) -> 8.08798 | AD30: =SUMIFS('Combined P&L'!AB:AB,'Combined P&L'!$C:$C,'P&L Forecast'!$B30) -> 9.75287 | AE30: =SUMIFS('Combined P&L'!AC:AC,'Combined P&L'!$C:$C,'P&L Forecast'!$B30) -> 10.28 | AF30: =SUMIFS('Combined P&L'!AD:AD,'Combined P&L'!$C:$C,'P&L Forecast'!$B30) -> 11.13632 | AG30: =SUMIFS('Combined P&L'!AE:AE,'Combined P&L'!$C:$C,'P&L Forecast'!$B30) -> 10.87432 | AH30: =SUMIFS('Combined P&L'!AF:AF,'Combined P&L'!$C:$C,'P&L Forecast'!$B30) -> 13.47257 | AI30: =SUMIFS('Combined P&L'!AG:AG,'Combined P&L'!$C:$C,'P&L Forecast'!$B30) -> 12.70407 | AJ30: =SUMIFS('Combined P&L'!AH:AH,'Combined P&L'!$C:$C,'P&L Forecast'!$B30) -> 14.69884 | AK30: =SUMIFS('Combined P&L'!AI:AI,'Combined P&L'!$C:$C,'P&L Forecast'!$B30) -> 15.54306 | AL30: =SUMIFS('Combined P&L'!AJ:AJ,'Combined P&L'!$C:$C,'P&L Forecast'!$B30) -> 14.34361 | AM30: =SUMIFS('Combined P&L'!AK:AK,'Combined P&L'!$C:$C,'P&L Forecast'!$B30) -> 20.93052 | AN30: =SUMIFS('Combined P&L'!AL:AL,'Combined P&L'!$C:$C,'P&L Forecast'!$B30) -> 16.55394 | AO30: =SUMIFS('Combined P&L'!AM:AM,'Combined P&L'!$C:$C,'P&L Forecast'!$B30) -> 11.52661 | AP30: =SUMIFS('Combined P&L'!AN:AN,'Combined P&L'!$C:$C,'P&L Forecast'!$B30) -> 14.93883 | AQ30: =SUMIFS('Combined P&L'!AO:AO,'Combined P&L'!$C:$C,'P&L Forecast'!$B30) -> 15.58352 | AR30: =SUMIFS('Combined P&L'!AP:AP,'Combined P&L'!$C:$C,'P&L Forecast'!$B30) -> 19.6034 | AS30: =SUMIFS('Combined P&L'!AQ:AQ,'Combined P&L'!$C:$C,'P&L Forecast'!$B30) -> 16.64457 | AT30: =SUMIFS('Combined P&L'!AR:AR,'Combined P&L'!$C:$C,'P&L Forecast'!$B30) -> 16.42912
B31: Owner Wages | C31: =SUMIFS($P31:$AT31,$P$5:$AT$5,">"&C$168,$P$5:$AT$5,"<"&C$169) -> 0 | D31: =SUMIFS($P31:$AT31,$P$5:$AT$5,">"&D$168,$P$5:$AT$5,"<"&D$169) -> 90.66704 | F31: =SUMIFS($P31:$AT31,$P$5:$AT$5,">"&F$168,$P$5:$AT$5,"<"&F$169) -> 45.46612 | G31: =SUMIFS($P31:$AT31,$P$5:$AT$5,">"&G$168,$P$5:$AT$5,"<"&G$169) -> 63.14302 | I31: =SUMIFS($P31:$AT31,$P$5:$AT$5,">"&I$168,$P$5:$AT$5,"<"&I$169) -> 45.46612 | J31: =SUMIFS($P31:$AT31,$P$5:$AT$5,">"&J$168,$P$5:$AT$5,"<"&J$169) -> 108.34394 | K31: =+C126 -> 108.34394 | M31: =K31-J31 -> 0 | N31: =IFERROR(K31/J31-1,0) -> 0 | P31: =SUMIFS('Combined P&L'!N:N,'Combined P&L'!$C:$C,'P&L Forecast'!$B31) -> 0 | Q31: =SUMIFS('Combined P&L'!O:O,'Combined P&L'!$C:$C,'P&L Forecast'!$B31) -> 0 | R31: =SUMIFS('Combined P&L'!P:P,'Combined P&L'!$C:$C,'P&L Forecast'!$B31) -> 0 | S31: =SUMIFS('Combined P&L'!Q:Q,'Combined P&L'!$C:$C,'P&L Forecast'!$B31) -> 0 | T31: =SUMIFS('Combined P&L'!R:R,'Combined P&L'!$C:$C,'P&L Forecast'!$B31) -> 0 | U31: =SUMIFS('Combined P&L'!S:S,'Combined P&L'!$C:$C,'P&L Forecast'!$B31) -> 0 | V31: =SUMIFS('Combined P&L'!T:T,'Combined P&L'!$C:$C,'P&L Forecast'!$B31) -> 0 | W31: =SUMIFS('Combined P&L'!U:U,'Combined P&L'!$C:$C,'P&L Forecast'!$B31) -> 0 | X31: =SUMIFS('Combined P&L'!V:V,'Combined P&L'!$C:$C,'P&L Forecast'!$B31) -> 0 | Y31: =SUMIFS('Combined P&L'!W:W,'Combined P&L'!$C:$C,'P&L Forecast'!$B31) -> 0 | Z31: =SUMIFS('Combined P&L'!X:X,'Combined P&L'!$C:$C,'P&L Forecast'!$B31) -> 0 | AA31: =SUMIFS('Combined P&L'!Y:Y,'Combined P&L'!$C:$C,'P&L Forecast'!$B31) -> 0 | AB31: =SUMIFS('Combined P&L'!Z:Z,'Combined P&L'!$C:$C,'P&L Forecast'!$B31) -> 0 | AC31: =SUMIFS('Combined P&L'!AA:AA,'Combined P&L'!$C:$C,'P&L Forecast'!$B31) -> 0 | AD31: =SUMIFS('Combined P&L'!AB:AB,'Combined P&L'!$C:$C,'P&L Forecast'!$B31) -> 8.90639 | AE31: =SUMIFS('Combined P&L'!AC:AC,'Combined P&L'!$C:$C,'P&L Forecast'!$B31) -> 9.23323 | AF31: =SUMIFS('Combined P&L'!AD:AD,'Combined P&L'!$C:$C,'P&L Forecast'!$B31) -> 9.10884 | AG31: =SUMIFS('Combined P&L'!AE:AE,'Combined P&L'!$C:$C,'P&L Forecast'!$B31) -> 8.69479 | AH31: =SUMIFS('Combined P&L'!AF:AF,'Combined P&L'!$C:$C,'P&L Forecast'!$B31) -> 9.52287 | AI31: =SUMIFS('Combined P&L'!AG:AG,'Combined P&L'!$C:$C,'P&L Forecast'!$B31) -> 8.69481 | AJ31: =SUMIFS('Combined P&L'!AH:AH,'Combined P&L'!$C:$C,'P&L Forecast'!$B31) -> 9.10884 | AK31: =SUMIFS('Combined P&L'!AI:AI,'Combined P&L'!$C:$C,'P&L Forecast'!$B31) -> 9.52287 | AL31: =SUMIFS('Combined P&L'!AJ:AJ,'Combined P&L'!$C:$C,'P&L Forecast'!$B31) -> 8.28076 | AM31: =SUMIFS('Combined P&L'!AK:AK,'Combined P&L'!$C:$C,'P&L Forecast'!$B31) -> 9.59364 | AN31: =SUMIFS('Combined P&L'!AL:AL,'Combined P&L'!$C:$C,'P&L Forecast'!$B31) -> 9.27621 | AO31: =SUMIFS('Combined P&L'!AM:AM,'Combined P&L'!$C:$C,'P&L Forecast'!$B31) -> 8.32263 | AP31: =SUMIFS('Combined P&L'!AN:AN,'Combined P&L'!$C:$C,'P&L Forecast'!$B31) -> 9.10883 | AQ31: =SUMIFS('Combined P&L'!AO:AO,'Combined P&L'!$C:$C,'P&L Forecast'!$B31) -> 9.10883 | AR31: =SUMIFS('Combined P&L'!AP:AP,'Combined P&L'!$C:$C,'P&L Forecast'!$B31) -> 8.69481 | AS31: =SUMIFS('Combined P&L'!AQ:AQ,'Combined P&L'!$C:$C,'P&L Forecast'!$B31) -> 9.10884 | AT31: =SUMIFS('Combined P&L'!AR:AR,'Combined P&L'!$C:$C,'P&L Forecast'!$B31) -> 9.52287
B32: S&M Wages | C32: =SUMIFS($P32:$AT32,$P$5:$AT$5,">"&C$168,$P$5:$AT$5,"<"&C$169) -> 0 | D32: =SUMIFS($P32:$AT32,$P$5:$AT$5,">"&D$168,$P$5:$AT$5,"<"&D$169) -> 19.14963 | F32: =SUMIFS($P32:$AT32,$P$5:$AT$5,">"&F$168,$P$5:$AT$5,"<"&F$169) -> 3.09945 | G32: =SUMIFS($P32:$AT32,$P$5:$AT$5,">"&G$168,$P$5:$AT$5,"<"&G$169) -> 51.94131 | I32: =SUMIFS($P32:$AT32,$P$5:$AT$5,">"&I$168,$P$5:$AT$5,"<"&I$169) -> 3.09945 | J32: =SUMIFS($P32:$AT32,$P$5:$AT$5,">"&J$168,$P$5:$AT$5,"<"&J$169) -> 67.99149 | K32: =+C128 -> 98.34912 | M32: =K32-J32 -> 30.35763 | N32: =IFERROR(K32/J32-1,0) -> 0.44649161 | P32: =SUMIFS('Combined P&L'!N:N,'Combined P&L'!$C:$C,'P&L Forecast'!$B32) -> 0 | Q32: =SUMIFS('Combined P&L'!O:O,'Combined P&L'!$C:$C,'P&L Forecast'!$B32) -> 0 | R32: =SUMIFS('Combined P&L'!P:P,'Combined P&L'!$C:$C,'P&L Forecast'!$B32) -> 0 | S32: =SUMIFS('Combined P&L'!Q:Q,'Combined P&L'!$C:$C,'P&L Forecast'!$B32) -> 0 | T32: =SUMIFS('Combined P&L'!R:R,'Combined P&L'!$C:$C,'P&L Forecast'!$B32) -> 0 | U32: =SUMIFS('Combined P&L'!S:S,'Combined P&L'!$C:$C,'P&L Forecast'!$B32) -> 0 | V32: =SUMIFS('Combined P&L'!T:T,'Combined P&L'!$C:$C,'P&L Forecast'!$B32) -> 0 | W32: =SUMIFS('Combined P&L'!U:U,'Combined P&L'!$C:$C,'P&L Forecast'!$B32) -> 0 | X32: =SUMIFS('Combined P&L'!V:V,'Combined P&L'!$C:$C,'P&L Forecast'!$B32) -> 0 | Y32: =SUMIFS('Combined P&L'!W:W,'Combined P&L'!$C:$C,'P&L Forecast'!$B32) -> 0 | Z32: =SUMIFS('Combined P&L'!X:X,'Combined P&L'!$C:$C,'P&L Forecast'!$B32) -> 0 | AA32: =SUMIFS('Combined P&L'!Y:Y,'Combined P&L'!$C:$C,'P&L Forecast'!$B32) -> 0 | AB32: =SUMIFS('Combined P&L'!Z:Z,'Combined P&L'!$C:$C,'P&L Forecast'!$B32) -> 0 | AC32: =SUMIFS('Combined P&L'!AA:AA,'Combined P&L'!$C:$C,'P&L Forecast'!$B32) -> 0 | AD32: =SUMIFS('Combined P&L'!AB:AB,'Combined P&L'!$C:$C,'P&L Forecast'!$B32) -> 0 | AE32: =SUMIFS('Combined P&L'!AC:AC,'Combined P&L'!$C:$C,'P&L Forecast'!$B32) -> 0 | AF32: =SUMIFS('Combined P&L'!AD:AD,'Combined P&L'!$C:$C,'P&L Forecast'!$B32) -> 0 | AG32: =SUMIFS('Combined P&L'!AE:AE,'Combined P&L'!$C:$C,'P&L Forecast'!$B32) -> 1.4668 | AH32: =SUMIFS('Combined P&L'!AF:AF,'Combined P&L'!$C:$C,'P&L Forecast'!$B32) -> 1.63265 | AI32: =SUMIFS('Combined P&L'!AG:AG,'Combined P&L'!$C:$C,'P&L Forecast'!$B32) -> 1.71805 | AJ32: =SUMIFS('Combined P&L'!AH:AH,'Combined P&L'!$C:$C,'P&L Forecast'!$B32) -> 1.9146 | AK32: =SUMIFS('Combined P&L'!AI:AI,'Combined P&L'!$C:$C,'P&L Forecast'!$B32) -> 2.3529 | AL32: =SUMIFS('Combined P&L'!AJ:AJ,'Combined P&L'!$C:$C,'P&L Forecast'!$B32) -> 2.24524 | AM32: =SUMIFS('Combined P&L'!AK:AK,'Combined P&L'!$C:$C,'P&L Forecast'!$B32) -> 7.81939 | AN32: =SUMIFS('Combined P&L'!AL:AL,'Combined P&L'!$C:$C,'P&L Forecast'!$B32) -> 5.6534 | AO32: =SUMIFS('Combined P&L'!AM:AM,'Combined P&L'!$C:$C,'P&L Forecast'!$B32) -> 5.95689 | AP32: =SUMIFS('Combined P&L'!AN:AN,'Combined P&L'!$C:$C,'P&L Forecast'!$B32) -> 7.7828 | AQ32: =SUMIFS('Combined P&L'!AO:AO,'Combined P&L'!$C:$C,'P&L Forecast'!$B32) -> 8.13701 | AR32: =SUMIFS('Combined P&L'!AP:AP,'Combined P&L'!$C:$C,'P&L Forecast'!$B32) -> 7.80825 | AS32: =SUMIFS('Combined P&L'!AQ:AQ,'Combined P&L'!$C:$C,'P&L Forecast'!$B32) -> 8.4072 | AT32: =SUMIFS('Combined P&L'!AR:AR,'Combined P&L'!$C:$C,'P&L Forecast'!$B32) -> 8.19576
B33: Occupancy Tax Specialist | C33: =SUMIFS($P33:$AT33,$P$5:$AT$5,">"&C$168,$P$5:$AT$5,"<"&C$169) -> 1.11335 | D33: =SUMIFS($P33:$AT33,$P$5:$AT$5,">"&D$168,$P$5:$AT$5,"<"&D$169) -> 29.56415 | F33: =SUMIFS($P33:$AT33,$P$5:$AT$5,">"&F$168,$P$5:$AT$5,"<"&F$169) -> 14.27585 | G33: =SUMIFS($P33:$AT33,$P$5:$AT$5,">"&G$168,$P$5:$AT$5,"<"&G$169) -> 42.08505 | I33: =SUMIFS($P33:$AT33,$P$5:$AT$5,">"&I$168,$P$5:$AT$5,"<"&I$169) -> 15.3892 | J33: =SUMIFS($P33:$AT33,$P$5:$AT$5,">"&J$168,$P$5:$AT$5,"<"&J$169) -> 57.37335 | K33: =+C129 -> 68.1132 | M33: =K33-J33 -> 10.73985 | N33: =IFERROR(K33/J33-1,0) -> 0.18719231 | P33: =SUMIFS('Combined P&L'!N:N,'Combined P&L'!$C:$C,'P&L Forecast'!$B33) -> 0 | Q33: =SUMIFS('Combined P&L'!O:O,'Combined P&L'!$C:$C,'P&L Forecast'!$B33) -> 0 | R33: =SUMIFS('Combined P&L'!P:P,'Combined P&L'!$C:$C,'P&L Forecast'!$B33) -> 0 | S33: =SUMIFS('Combined P&L'!Q:Q,'Combined P&L'!$C:$C,'P&L Forecast'!$B33) -> 0 | T33: =SUMIFS('Combined P&L'!R:R,'Combined P&L'!$C:$C,'P&L Forecast'!$B33) -> 0 | U33: =SUMIFS('Combined P&L'!S:S,'Combined P&L'!$C:$C,'P&L Forecast'!$B33) -> 0 | V33: =SUMIFS('Combined P&L'!T:T,'Combined P&L'!$C:$C,'P&L Forecast'!$B33) -> 0 | W33: =SUMIFS('Combined P&L'!U:U,'Combined P&L'!$C:$C,'P&L Forecast'!$B33) -> 0 | X33: =SUMIFS('Combined P&L'!V:V,'Combined P&L'!$C:$C,'P&L Forecast'!$B33) -> 0 | Y33: =SUMIFS('Combined P&L'!W:W,'Combined P&L'!$C:$C,'P&L Forecast'!$B33) -> 0 | Z33: =SUMIFS('Combined P&L'!X:X,'Combined P&L'!$C:$C,'P&L Forecast'!$B33) -> 0 | AA33: =SUMIFS('Combined P&L'!Y:Y,'Combined P&L'!$C:$C,'P&L Forecast'!$B33) -> 1.11335 | AB33: =SUMIFS('Combined P&L'!Z:Z,'Combined P&L'!$C:$C,'P&L Forecast'!$B33) -> 2.17917 | AC33: =SUMIFS('Combined P&L'!AA:AA,'Combined P&L'!$C:$C,'P&L Forecast'!$B33) -> 1.82504 | AD33: =SUMIFS('Combined P&L'!AB:AB,'Combined P&L'!$C:$C,'P&L Forecast'!$B33) -> 1.97853 | AE33: =SUMIFS('Combined P&L'!AC:AC,'Combined P&L'!$C:$C,'P&L Forecast'!$B33) -> 2.06213 | AF33: =SUMIFS('Combined P&L'!AD:AD,'Combined P&L'!$C:$C,'P&L Forecast'!$B33) -> 2.06213 | AG33: =SUMIFS('Combined P&L'!AE:AE,'Combined P&L'!$C:$C,'P&L Forecast'!$B33) -> 1.98968 | AH33: =SUMIFS('Combined P&L'!AF:AF,'Combined P&L'!$C:$C,'P&L Forecast'!$B33) -> 2.17917 | AI33: =SUMIFS('Combined P&L'!AG:AG,'Combined P&L'!$C:$C,'P&L Forecast'!$B33) -> 2.12293 | AJ33: =SUMIFS('Combined P&L'!AH:AH,'Combined P&L'!$C:$C,'P&L Forecast'!$B33) -> 3.1042 | AK33: =SUMIFS('Combined P&L'!AI:AI,'Combined P&L'!$C:$C,'P&L Forecast'!$B33) -> 3.27137 | AL33: =SUMIFS('Combined P&L'!AJ:AJ,'Combined P&L'!$C:$C,'P&L Forecast'!$B33) -> 3.63947 | AM33: =SUMIFS('Combined P&L'!AK:AK,'Combined P&L'!$C:$C,'P&L Forecast'!$B33) -> 3.15033 | AN33: =SUMIFS('Combined P&L'!AL:AL,'Combined P&L'!$C:$C,'P&L Forecast'!$B33) -> 1.69116 | AO33: =SUMIFS('Combined P&L'!AM:AM,'Combined P&L'!$C:$C,'P&L Forecast'!$B33) -> 5.54919 | AP33: =SUMIFS('Combined P&L'!AN:AN,'Combined P&L'!$C:$C,'P&L Forecast'!$B33) -> 7.1999 | AQ33: =SUMIFS('Combined P&L'!AO:AO,'Combined P&L'!$C:$C,'P&L Forecast'!$B33) -> 8.1927 | AR33: =SUMIFS('Combined P&L'!AP:AP,'Combined P&L'!$C:$C,'P&L Forecast'!$B33) -> 8.28335 | AS33: =SUMIFS('Combined P&L'!AQ:AQ,'Combined P&L'!$C:$C,'P&L Forecast'!$B33) -> 5.49265 | AT33: =SUMIFS('Combined P&L'!AR:AR,'Combined P&L'!$C:$C,'P&L Forecast'!$B33) -> 5.6761
B34: Sr. Client Lead Wages | C34: =SUMIFS($P34:$AT34,$P$5:$AT$5,">"&C$168,$P$5:$AT$5,"<"&C$169) -> 0 | D34: =SUMIFS($P34:$AT34,$P$5:$AT$5,">"&D$168,$P$5:$AT$5,"<"&D$169) -> 0 | F34: =SUMIFS($P34:$AT34,$P$5:$AT$5,">"&F$168,$P$5:$AT$5,"<"&F$169) -> 0 | G34: =SUMIFS($P34:$AT34,$P$5:$AT$5,">"&G$168,$P$5:$AT$5,"<"&G$169) -> 7.995 | I34: =SUMIFS($P34:$AT34,$P$5:$AT$5,">"&I$168,$P$5:$AT$5,"<"&I$169) -> 0 | J34: =SUMIFS($P34:$AT34,$P$5:$AT$5,">"&J$168,$P$5:$AT$5,"<"&J$169) -> 7.995 | K34: =+C130 -> 33.08124 | M34: =K34-J34 -> 25.08624 | N34: =IFERROR(K34/J34-1,0) -> 3.1377411 | P34: =SUMIFS('Combined P&L'!N:N,'Combined P&L'!$C:$C,'P&L Forecast'!$B34) -> 0 | Q34: =SUMIFS('Combined P&L'!O:O,'Combined P&L'!$C:$C,'P&L Forecast'!$B34) -> 0 | R34: =SUMIFS('Combined P&L'!P:P,'Combined P&L'!$C:$C,'P&L Forecast'!$B34) -> 0 | S34: =SUMIFS('Combined P&L'!Q:Q,'Combined P&L'!$C:$C,'P&L Forecast'!$B34) -> 0 | T34: =SUMIFS('Combined P&L'!R:R,'Combined P&L'!$C:$C,'P&L Forecast'!$B34) -> 0 | U34: =SUMIFS('Combined P&L'!S:S,'Combined P&L'!$C:$C,'P&L Forecast'!$B34) -> 0 | V34: =SUMIFS('Combined P&L'!T:T,'Combined P&L'!$C:$C,'P&L Forecast'!$B34) -> 0 | W34: =SUMIFS('Combined P&L'!U:U,'Combined P&L'!$C:$C,'P&L Forecast'!$B34) -> 0 | X34: =SUMIFS('Combined P&L'!V:V,'Combined P&L'!$C:$C,'P&L Forecast'!$B34) -> 0 | Y34: =SUMIFS('Combined P&L'!W:W,'Combined P&L'!$C:$C,'P&L Forecast'!$B34) -> 0 | Z34: =SUMIFS('Combined P&L'!X:X,'Combined P&L'!$C:$C,'P&L Forecast'!$B34) -> 0 | AA34: =SUMIFS('Combined P&L'!Y:Y,'Combined P&L'!$C:$C,'P&L Forecast'!$B34) -> 0 | AB34: =SUMIFS('Combined P&L'!Z:Z,'Combined P&L'!$C:$C,'P&L Forecast'!$B34) -> 0 | AC34: =SUMIFS('Combined P&L'!AA:AA,'Combined P&L'!$C:$C,'P&L Forecast'!$B34) -> 0 | AD34: =SUMIFS('Combined P&L'!AB:AB,'Combined P&L'!$C:$C,'P&L Forecast'!$B34) -> 0 | AE34: =SUMIFS('Combined P&L'!AC:AC,'Combined P&L'!$C:$C,'P&L Forecast'!$B34) -> 0 | AF34: =SUMIFS('Combined P&L'!AD:AD,'Combined P&L'!$C:$C,'P&L Forecast'!$B34) -> 0 | AG34: =SUMIFS('Combined P&L'!AE:AE,'Combined P&L'!$C:$C,'P&L Forecast'!$B34) -> 0 | AH34: =SUMIFS('Combined P&L'!AF:AF,'Combined P&L'!$C:$C,'P&L Forecast'!$B34) -> 0 | AI34: =SUMIFS('Combined P&L'!AG:AG,'Combined P&L'!$C:$C,'P&L Forecast'!$B34) -> 0 | AJ34: =SUMIFS('Combined P&L'!AH:AH,'Combined P&L'!$C:$C,'P&L Forecast'!$B34) -> 0 | AK34: =SUMIFS('Combined P&L'!AI:AI,'Combined P&L'!$C:$C,'P&L Forecast'!$B34) -> 0 | AL34: =SUMIFS('Combined P&L'!AJ:AJ,'Combined P&L'!$C:$C,'P&L Forecast'!$B34) -> 0 | AM34: =SUMIFS('Combined P&L'!AK:AK,'Combined P&L'!$C:$C,'P&L Forecast'!$B34) -> 0 | AN34: =SUMIFS('Combined P&L'!AL:AL,'Combined P&L'!$C:$C,'P&L Forecast'!$B34) -> 0 | AO34: =SUMIFS('Combined P&L'!AM:AM,'Combined P&L'!$C:$C,'P&L Forecast'!$B34) -> 0 | AP34: =SUMIFS('Combined P&L'!AN:AN,'Combined P&L'!$C:$C,'P&L Forecast'!$B34) -> 0 | AQ34: =SUMIFS('Combined P&L'!AO:AO,'Combined P&L'!$C:$C,'P&L Forecast'!$B34) -> 0 | AR34: =SUMIFS('Combined P&L'!AP:AP,'Combined P&L'!$C:$C,'P&L Forecast'!$B34) -> 2.51706 | AS34: =SUMIFS('Combined P&L'!AQ:AQ,'Combined P&L'!$C:$C,'P&L Forecast'!$B34) -> 2.72117 | AT34: =SUMIFS('Combined P&L'!AR:AR,'Combined P&L'!$C:$C,'P&L Forecast'!$B34) -> 2.75677
B35: Employee Benefits | C35: =SUMIFS($P35:$AT35,$P$5:$AT$5,">"&C$168,$P$5:$AT$5,"<"&C$169) -> 5.37405 | D35: =SUMIFS($P35:$AT35,$P$5:$AT$5,">"&D$168,$P$5:$AT$5,"<"&D$169) -> 19.23245 | F35: =SUMIFS($P35:$AT35,$P$5:$AT$5,">"&F$168,$P$5:$AT$5,"<"&F$169) -> 9.02166 | G35: =SUMIFS($P35:$AT35,$P$5:$AT$5,">"&G$168,$P$5:$AT$5,"<"&G$169) -> 17.36251 | I35: =SUMIFS($P35:$AT35,$P$5:$AT$5,">"&I$168,$P$5:$AT$5,"<"&I$169) -> 12.16686 | J35: =SUMIFS($P35:$AT35,$P$5:$AT$5,">"&J$168,$P$5:$AT$5,"<"&J$169) -> 27.5733 | K35: =+C132 -> 32.17836 | M35: =K35-J35 -> 4.60506 | N35: =IFERROR(K35/J35-1,0) -> 0.16701157 | P35: =SUMIFS('Combined P&L'!N:N,'Combined P&L'!$C:$C,'P&L Forecast'!$B35) -> 0 | Q35: =SUMIFS('Combined P&L'!O:O,'Combined P&L'!$C:$C,'P&L Forecast'!$B35) -> 0.6277 | R35: =SUMIFS('Combined P&L'!P:P,'Combined P&L'!$C:$C,'P&L Forecast'!$B35) -> 0 | S35: =SUMIFS('Combined P&L'!Q:Q,'Combined P&L'!$C:$C,'P&L Forecast'!$B35) -> 0.3389 | T35: =SUMIFS('Combined P&L'!R:R,'Combined P&L'!$C:$C,'P&L Forecast'!$B35) -> 0.3389 | U35: =SUMIFS('Combined P&L'!S:S,'Combined P&L'!$C:$C,'P&L Forecast'!$B35) -> 0.06145 | V35: =SUMIFS('Combined P&L'!T:T,'Combined P&L'!$C:$C,'P&L Forecast'!$B35) -> 0.8619 | W35: =SUMIFS('Combined P&L'!U:U,'Combined P&L'!$C:$C,'P&L Forecast'!$B35) -> 0.35956 | X35: =SUMIFS('Combined P&L'!V:V,'Combined P&L'!$C:$C,'P&L Forecast'!$B35) -> 0.38745 | Y35: =SUMIFS('Combined P&L'!W:W,'Combined P&L'!$C:$C,'P&L Forecast'!$B35) -> 0.6989 | Z35: =SUMIFS('Combined P&L'!X:X,'Combined P&L'!$C:$C,'P&L Forecast'!$B35) -> 0.917 | AA35: =SUMIFS('Combined P&L'!Y:Y,'Combined P&L'!$C:$C,'P&L Forecast'!$B35) -> 0.78229 | AB35: =SUMIFS('Combined P&L'!Z:Z,'Combined P&L'!$C:$C,'P&L Forecast'!$B35) -> 0.93724 | AC35: =SUMIFS('Combined P&L'!AA:AA,'Combined P&L'!$C:$C,'P&L Forecast'!$B35) -> 1.03107 | AD35: =SUMIFS('Combined P&L'!AB:AB,'Combined P&L'!$C:$C,'P&L Forecast'!$B35) -> 0.66153 | AE35: =SUMIFS('Combined P&L'!AC:AC,'Combined P&L'!$C:$C,'P&L Forecast'!$B35) -> 0.71453 | AF35: =SUMIFS('Combined P&L'!AD:AD,'Combined P&L'!$C:$C,'P&L Forecast'!$B35) -> 2.25493 | AG35: =SUMIFS('Combined P&L'!AE:AE,'Combined P&L'!$C:$C,'P&L Forecast'!$B35) -> 1.86153 | AH35: =SUMIFS('Combined P&L'!AF:AF,'Combined P&L'!$C:$C,'P&L Forecast'!$B35) -> 1.56083 | AI35: =SUMIFS('Combined P&L'!AG:AG,'Combined P&L'!$C:$C,'P&L Forecast'!$B35) -> 1.74767 | AJ35: =SUMIFS('Combined P&L'!AH:AH,'Combined P&L'!$C:$C,'P&L Forecast'!$B35) -> 0.90753 | AK35: =SUMIFS('Combined P&L'!AI:AI,'Combined P&L'!$C:$C,'P&L Forecast'!$B35) -> 2.51353 | AL35: =SUMIFS('Combined P&L'!AJ:AJ,'Combined P&L'!$C:$C,'P&L Forecast'!$B35) -> 1.03753 | AM35: =SUMIFS('Combined P&L'!AK:AK,'Combined P&L'!$C:$C,'P&L Forecast'!$B35) -> 4.00453 | AN35: =SUMIFS('Combined P&L'!AL:AL,'Combined P&L'!$C:$C,'P&L Forecast'!$B35) -> 1.57873 | AO35: =SUMIFS('Combined P&L'!AM:AM,'Combined P&L'!$C:$C,'P&L Forecast'!$B35) -> 1.14553 | AP35: =SUMIFS('Combined P&L'!AN:AN,'Combined P&L'!$C:$C,'P&L Forecast'!$B35) -> 5.13853 | AQ35: =SUMIFS('Combined P&L'!AO:AO,'Combined P&L'!$C:$C,'P&L Forecast'!$B35) -> 1.92353 | AR35: =SUMIFS('Combined P&L'!AP:AP,'Combined P&L'!$C:$C,'P&L Forecast'!$B35) -> 1.46353 | AS35: =SUMIFS('Combined P&L'!AQ:AQ,'Combined P&L'!$C:$C,'P&L Forecast'!$B35) -> 3.43113 | AT35: =SUMIFS('Combined P&L'!AR:AR,'Combined P&L'!$C:$C,'P&L Forecast'!$B35) -> 2.68153
B36: Total Payroll Expenses | C36: =SUM(C27:C35) -> 700.20547 | D36: =SUM(D27:D35) -> 1261.1666 | F36: =SUM(F27:F35) -> 630.65714 | G36: =SUM(G27:G35) -> 1120.8921 | I36: =SUM(I27:I35) -> 993.15437 | J36: =SUM(J27:J35) -> 1751.4015 | K36: =SUM(K27:K35) -> 2158.7356 | M36: =SUM(M27:M35) -> 407.33404 | N36: =IFERROR(K36/J36-1,0) -> 0.23257604 | P36: =SUM(P27:P35) -> 31.74682 | Q36: =SUM(Q27:Q35) -> 37.62609 | R36: =SUM(R27:R35) -> 37.77865 | S36: =SUM(S27:S35) -> 50.81818 | T36: =SUM(T27:T35) -> 70.6441 | U36: =SUM(U27:U35) -> 52.94065 | V36: =SUM(V27:V35) -> 56.15375 | W36: =SUM(W27:W35) -> 52.54102 | ... AT36: =SUM(AT27:AT35) -> 180.38884
B38: Software & Apps - COGS | C38: =SUMIFS($P38:$AT38,$P$5:$AT$5,">"&C$168,$P$5:$AT$5,"<"&C$169) -> 114.42269 | D38: =SUMIFS($P38:$AT38,$P$5:$AT$5,">"&D$168,$P$5:$AT$5,"<"&D$169) -> 157.49471 | F38: =SUMIFS($P38:$AT38,$P$5:$AT$5,">"&F$168,$P$5:$AT$5,"<"&F$169) -> 84.96859 | G38: =SUMIFS($P38:$AT38,$P$5:$AT$5,">"&G$168,$P$5:$AT$5,"<"&G$169) -> 152.28157 | I38: =SUMIFS($P38:$AT38,$P$5:$AT$5,">"&I$168,$P$5:$AT$5,"<"&I$169) -> 142.28345 | J38: =SUMIFS($P38:$AT38,$P$5:$AT$5,">"&J$168,$P$5:$AT$5,"<"&J$169) -> 224.80769 | K38: =+C136 -> 335.70816 | M38: =K38-J38 -> 110.90047 | N38: =IFERROR(K38/J38-1,0) -> 0.49331262 | P38: =SUMIFS('Combined P&L'!N:N,'Combined P&L'!$C:$C,'P&L Forecast'!$B38) -> 7.073 | Q38: =SUMIFS('Combined P&L'!O:O,'Combined P&L'!$C:$C,'P&L Forecast'!$B38) -> 7.01818 | R38: =SUMIFS('Combined P&L'!P:P,'Combined P&L'!$C:$C,'P&L Forecast'!$B38) -> 7.77788 | S38: =SUMIFS('Combined P&L'!Q:Q,'Combined P&L'!$C:$C,'P&L Forecast'!$B38) -> 7.76124 | T38: =SUMIFS('Combined P&L'!R:R,'Combined P&L'!$C:$C,'P&L Forecast'!$B38) -> 7.71821 | U38: =SUMIFS('Combined P&L'!S:S,'Combined P&L'!$C:$C,'P&L Forecast'!$B38) -> 8.91264 | V38: =SUMIFS('Combined P&L'!T:T,'Combined P&L'!$C:$C,'P&L Forecast'!$B38) -> 10.84668 | W38: =SUMIFS('Combined P&L'!U:U,'Combined P&L'!$C:$C,'P&L Forecast'!$B38) -> 11.13514 | X38: =SUMIFS('Combined P&L'!V:V,'Combined P&L'!$C:$C,'P&L Forecast'!$B38) -> 11.0345 | Y38: =SUMIFS('Combined P&L'!W:W,'Combined P&L'!$C:$C,'P&L Forecast'!$B38) -> 11.72873 | Z38: =SUMIFS('Combined P&L'!X:X,'Combined P&L'!$C:$C,'P&L Forecast'!$B38) -> 11.44691 | AA38: =SUMIFS('Combined P&L'!Y:Y,'Combined P&L'!$C:$C,'P&L Forecast'!$B38) -> 11.96958 | AB38: =SUMIFS('Combined P&L'!Z:Z,'Combined P&L'!$C:$C,'P&L Forecast'!$B38) -> 10.84853 | AC38: =SUMIFS('Combined P&L'!AA:AA,'Combined P&L'!$C:$C,'P&L Forecast'!$B38) -> 12.21311 | AD38: =SUMIFS('Combined P&L'!AB:AB,'Combined P&L'!$C:$C,'P&L Forecast'!$B38) -> 11.57167 | AE38: =SUMIFS('Combined P&L'!AC:AC,'Combined P&L'!$C:$C,'P&L Forecast'!$B38) -> 11.81087 | AF38: =SUMIFS('Combined P&L'!AD:AD,'Combined P&L'!$C:$C,'P&L Forecast'!$B38) -> 12.52563 | AG38: =SUMIFS('Combined P&L'!AE:AE,'Combined P&L'!$C:$C,'P&L Forecast'!$B38) -> 12.86333 | AH38: =SUMIFS('Combined P&L'!AF:AF,'Combined P&L'!$C:$C,'P&L Forecast'!$B38) -> 13.13545 | AI38: =SUMIFS('Combined P&L'!AG:AG,'Combined P&L'!$C:$C,'P&L Forecast'!$B38) -> 14.25715 | AJ38: =SUMIFS('Combined P&L'!AH:AH,'Combined P&L'!$C:$C,'P&L Forecast'!$B38) -> 13.59512 | AK38: =SUMIFS('Combined P&L'!AI:AI,'Combined P&L'!$C:$C,'P&L Forecast'!$B38) -> 12.34762 | AL38: =SUMIFS('Combined P&L'!AJ:AJ,'Combined P&L'!$C:$C,'P&L Forecast'!$B38) -> 15.21781 | AM38: =SUMIFS('Combined P&L'!AK:AK,'Combined P&L'!$C:$C,'P&L Forecast'!$B38) -> 17.10842 | AN38: =SUMIFS('Combined P&L'!AL:AL,'Combined P&L'!$C:$C,'P&L Forecast'!$B38) -> 18.4683 | AO38: =SUMIFS('Combined P&L'!AM:AM,'Combined P&L'!$C:$C,'P&L Forecast'!$B38) -> 17.92027 | AP38: =SUMIFS('Combined P&L'!AN:AN,'Combined P&L'!$C:$C,'P&L Forecast'!$B38) -> 18.40906 | AQ38: =SUMIFS('Combined P&L'!AO:AO,'Combined P&L'!$C:$C,'P&L Forecast'!$B38) -> 21.38775 | AR38: =SUMIFS('Combined P&L'!AP:AP,'Combined P&L'!$C:$C,'P&L Forecast'!$B38) -> 23.44584 | AS38: =SUMIFS('Combined P&L'!AQ:AQ,'Combined P&L'!$C:$C,'P&L Forecast'!$B38) -> 24.67467 | AT38: =SUMIFS('Combined P&L'!AR:AR,'Combined P&L'!$C:$C,'P&L Forecast'!$B38) -> 27.97568
B39: Software & Apps - G&A | C39: =SUMIFS($P39:$AT39,$P$5:$AT$5,">"&C$168,$P$5:$AT$5,"<"&C$169) -> 60.91594 | D39: =SUMIFS($P39:$AT39,$P$5:$AT$5,">"&D$168,$P$5:$AT$5,"<"&D$169) -> 117.05866 | F39: =SUMIFS($P39:$AT39,$P$5:$AT$5,">"&F$168,$P$5:$AT$5,"<"&F$169) -> 56.8115 | G39: =SUMIFS($P39:$AT39,$P$5:$AT$5,">"&G$168,$P$5:$AT$5,"<"&G$169) -> 97.04798 | I39: =SUMIFS($P39:$AT39,$P$5:$AT$5,">"&I$168,$P$5:$AT$5,"<"&I$169) -> 86.51489 | J39: =SUMIFS($P39:$AT39,$P$5:$AT$5,">"&J$168,$P$5:$AT$5,"<"&J$169) -> 157.29514 | K39: =+C137 -> 155.82264 | M39: =K39-J39 -> -1.4725 | N39: =IFERROR(K39/J39-1,0) -> -0.0093613827 | P39: =SUMIFS('Combined P&L'!N:N,'Combined P&L'!$C:$C,'P&L Forecast'!$B39) -> 3.45285 | Q39: =SUMIFS('Combined P&L'!O:O,'Combined P&L'!$C:$C,'P&L Forecast'!$B39) -> 3.61753 | R39: =SUMIFS('Combined P&L'!P:P,'Combined P&L'!$C:$C,'P&L Forecast'!$B39) -> 3.97407 | S39: =SUMIFS('Combined P&L'!Q:Q,'Combined P&L'!$C:$C,'P&L Forecast'!$B39) -> 4.22365 | T39: =SUMIFS('Combined P&L'!R:R,'Combined P&L'!$C:$C,'P&L Forecast'!$B39) -> 5.09725 | U39: =SUMIFS('Combined P&L'!S:S,'Combined P&L'!$C:$C,'P&L Forecast'!$B39) -> 5.33351 | V39: =SUMIFS('Combined P&L'!T:T,'Combined P&L'!$C:$C,'P&L Forecast'!$B39) -> 5.51369 | W39: =SUMIFS('Combined P&L'!U:U,'Combined P&L'!$C:$C,'P&L Forecast'!$B39) -> 5.23169 | X39: =SUMIFS('Combined P&L'!V:V,'Combined P&L'!$C:$C,'P&L Forecast'!$B39) -> 5.51622 | Y39: =SUMIFS('Combined P&L'!W:W,'Combined P&L'!$C:$C,'P&L Forecast'!$B39) -> 6.12797 | Z39: =SUMIFS('Combined P&L'!X:X,'Combined P&L'!$C:$C,'P&L Forecast'!$B39) -> 6.15097 | AA39: =SUMIFS('Combined P&L'!Y:Y,'Combined P&L'!$C:$C,'P&L Forecast'!$B39) -> 6.67654 | AB39: =SUMIFS('Combined P&L'!Z:Z,'Combined P&L'!$C:$C,'P&L Forecast'!$B39) -> 7.74646 | AC39: =SUMIFS('Combined P&L'!AA:AA,'Combined P&L'!$C:$C,'P&L Forecast'!$B39) -> 7.89181 | AD39: =SUMIFS('Combined P&L'!AB:AB,'Combined P&L'!$C:$C,'P&L Forecast'!$B39) -> 7.89085 | AE39: =SUMIFS('Combined P&L'!AC:AC,'Combined P&L'!$C:$C,'P&L Forecast'!$B39) -> 7.83463 | AF39: =SUMIFS('Combined P&L'!AD:AD,'Combined P&L'!$C:$C,'P&L Forecast'!$B39) -> 8.11723 | AG39: =SUMIFS('Combined P&L'!AE:AE,'Combined P&L'!$C:$C,'P&L Forecast'!$B39) -> 8.34584 | AH39: =SUMIFS('Combined P&L'!AF:AF,'Combined P&L'!$C:$C,'P&L Forecast'!$B39) -> 8.98468 | AI39: =SUMIFS('Combined P&L'!AG:AG,'Combined P&L'!$C:$C,'P&L Forecast'!$B39) -> 9.8566 | AJ39: =SUMIFS('Combined P&L'!AH:AH,'Combined P&L'!$C:$C,'P&L Forecast'!$B39) -> 10.73391 | AK39: =SUMIFS('Combined P&L'!AI:AI,'Combined P&L'!$C:$C,'P&L Forecast'!$B39) -> 12.08939 | AL39: =SUMIFS('Combined P&L'!AJ:AJ,'Combined P&L'!$C:$C,'P&L Forecast'!$B39) -> 13.14583 | AM39: =SUMIFS('Combined P&L'!AK:AK,'Combined P&L'!$C:$C,'P&L Forecast'!$B39) -> 14.42143 | AN39: =SUMIFS('Combined P&L'!AL:AL,'Combined P&L'!$C:$C,'P&L Forecast'!$B39) -> 13.26316 | AO39: =SUMIFS('Combined P&L'!AM:AM,'Combined P&L'!$C:$C,'P&L Forecast'!$B39) -> 14.7201 | AP39: =SUMIFS('Combined P&L'!AN:AN,'Combined P&L'!$C:$C,'P&L Forecast'!$B39) -> 14.99072 | AQ39: =SUMIFS('Combined P&L'!AO:AO,'Combined P&L'!$C:$C,'P&L Forecast'!$B39) -> 14.74459 | AR39: =SUMIFS('Combined P&L'!AP:AP,'Combined P&L'!$C:$C,'P&L Forecast'!$B39) -> 13.2292 | AS39: =SUMIFS('Combined P&L'!AQ:AQ,'Combined P&L'!$C:$C,'P&L Forecast'!$B39) -> 13.11499 | AT39: =SUMIFS('Combined P&L'!AR:AR,'Combined P&L'!$C:$C,'P&L Forecast'!$B39) -> 12.98522
B40: Software & Apps - Topkey | C40: =SUMIFS($P40:$AT40,$P$5:$AT$5,">"&C$168,$P$5:$AT$5,"<"&C$169) -> 0 | D40: =SUMIFS($P40:$AT40,$P$5:$AT$5,">"&D$168,$P$5:$AT$5,"<"&D$169) -> 7.14125 | F40: =SUMIFS($P40:$AT40,$P$5:$AT$5,">"&F$168,$P$5:$AT$5,"<"&F$169) -> 0 | G40: =SUMIFS($P40:$AT40,$P$5:$AT$5,">"&G$168,$P$5:$AT$5,"<"&G$169) -> 28.82775 | I40: =SUMIFS($P40:$AT40,$P$5:$AT$5,">"&I$168,$P$5:$AT$5,"<"&I$169) -> 0 | J40: =SUMIFS($P40:$AT40,$P$5:$AT$5,">"&J$168,$P$5:$AT$5,"<"&J$169) -> 35.969 | K40: =+C138 -> 60.84 | M40: =K40-J40 -> 24.871 | N40: =IFERROR(K40/J40-1,0) -> 0.69145653 | P40: =SUMIFS('Combined P&L'!N:N,'Combined P&L'!$C:$C,'P&L Forecast'!$B40) -> 0 | Q40: =SUMIFS('Combined P&L'!O:O,'Combined P&L'!$C:$C,'P&L Forecast'!$B40) -> 0 | R40: =SUMIFS('Combined P&L'!P:P,'Combined P&L'!$C:$C,'P&L Forecast'!$B40) -> 0 | S40: =SUMIFS('Combined P&L'!Q:Q,'Combined P&L'!$C:$C,'P&L Forecast'!$B40) -> 0 | T40: =SUMIFS('Combined P&L'!R:R,'Combined P&L'!$C:$C,'P&L Forecast'!$B40) -> 0 | U40: =SUMIFS('Combined P&L'!S:S,'Combined P&L'!$C:$C,'P&L Forecast'!$B40) -> 0 | V40: =SUMIFS('Combined P&L'!T:T,'Combined P&L'!$C:$C,'P&L Forecast'!$B40) -> 0 | W40: =SUMIFS('Combined P&L'!U:U,'Combined P&L'!$C:$C,'P&L Forecast'!$B40) -> 0 | X40: =SUMIFS('Combined P&L'!V:V,'Combined P&L'!$C:$C,'P&L Forecast'!$B40) -> 0 | Y40: =SUMIFS('Combined P&L'!W:W,'Combined P&L'!$C:$C,'P&L Forecast'!$B40) -> 0 | Z40: =SUMIFS('Combined P&L'!X:X,'Combined P&L'!$C:$C,'P&L Forecast'!$B40) -> 0 | AA40: =SUMIFS('Combined P&L'!Y:Y,'Combined P&L'!$C:$C,'P&L Forecast'!$B40) -> 0 | AB40: =SUMIFS('Combined P&L'!Z:Z,'Combined P&L'!$C:$C,'P&L Forecast'!$B40) -> 0 | AC40: =SUMIFS('Combined P&L'!AA:AA,'Combined P&L'!$C:$C,'P&L Forecast'!$B40) -> 0 | AD40: =SUMIFS('Combined P&L'!AB:AB,'Combined P&L'!$C:$C,'P&L Forecast'!$B40) -> 0 | AE40: =SUMIFS('Combined P&L'!AC:AC,'Combined P&L'!$C:$C,'P&L Forecast'!$B40) -> 0 | AF40: =SUMIFS('Combined P&L'!AD:AD,'Combined P&L'!$C:$C,'P&L Forecast'!$B40) -> 0 | AG40: =SUMIFS('Combined P&L'!AE:AE,'Combined P&L'!$C:$C,'P&L Forecast'!$B40) -> 0 | AH40: =SUMIFS('Combined P&L'!AF:AF,'Combined P&L'!$C:$C,'P&L Forecast'!$B40) -> 0 | AI40: =SUMIFS('Combined P&L'!AG:AG,'Combined P&L'!$C:$C,'P&L Forecast'!$B40) -> 0 | AJ40: =SUMIFS('Combined P&L'!AH:AH,'Combined P&L'!$C:$C,'P&L Forecast'!$B40) -> 0.93725 | AK40: =SUMIFS('Combined P&L'!AI:AI,'Combined P&L'!$C:$C,'P&L Forecast'!$B40) -> 1.39225 | AL40: =SUMIFS('Combined P&L'!AJ:AJ,'Combined P&L'!$C:$C,'P&L Forecast'!$B40) -> 2.36125 | AM40: =SUMIFS('Combined P&L'!AK:AK,'Combined P&L'!$C:$C,'P&L Forecast'!$B40) -> 2.4505 | AN40: =SUMIFS('Combined P&L'!AL:AL,'Combined P&L'!$C:$C,'P&L Forecast'!$B40) -> 2.94975 | AO40: =SUMIFS('Combined P&L'!AM:AM,'Combined P&L'!$C:$C,'P&L Forecast'!$B40) -> 3.42 | AP40: =SUMIFS('Combined P&L'!AN:AN,'Combined P&L'!$C:$C,'P&L Forecast'!$B40) -> 3.678 | AQ40: =SUMIFS('Combined P&L'!AO:AO,'Combined P&L'!$C:$C,'P&L Forecast'!$B40) -> 4.218 | AR40: =SUMIFS('Combined P&L'!AP:AP,'Combined P&L'!$C:$C,'P&L Forecast'!$B40) -> 4.284 | AS40: =SUMIFS('Combined P&L'!AQ:AQ,'Combined P&L'!$C:$C,'P&L Forecast'!$B40) -> 5.208 | AT40: =SUMIFS('Combined P&L'!AR:AR,'Combined P&L'!$C:$C,'P&L Forecast'!$B40) -> 5.07
B41: Software & Apps - AI tools | C41: =SUMIFS($P41:$AT41,$P$5:$AT$5,">"&C$168,$P$5:$AT$5,"<"&C$169) -> 0 | D41: =SUMIFS($P41:$AT41,$P$5:$AT$5,">"&D$168,$P$5:$AT$5,"<"&D$169) -> 0 | F41: =SUMIFS($P41:$AT41,$P$5:$AT$5,">"&F$168,$P$5:$AT$5,"<"&F$169) -> 0 | G41: =SUMIFS($P41:$AT41,$P$5:$AT$5,">"&G$168,$P$5:$AT$5,"<"&G$169) -> 6.52752 | I41: =SUMIFS($P41:$AT41,$P$5:$AT$5,">"&I$168,$P$5:$AT$5,"<"&I$169) -> 0 | J41: =SUMIFS($P41:$AT41,$P$5:$AT$5,">"&J$168,$P$5:$AT$5,"<"&J$169) -> 6.52752 | K41: =+C139 -> 15.74376 | M41: =K41-J41 -> 9.21624 | N41: =IFERROR(K41/J41-1,0) -> 1.4119053 | P41: =SUMIFS('Combined P&L'!N:N,'Combined P&L'!$C:$C,'P&L Forecast'!$B41) -> 0 | Q41: =SUMIFS('Combined P&L'!O:O,'Combined P&L'!$C:$C,'P&L Forecast'!$B41) -> 0 | R41: =SUMIFS('Combined P&L'!P:P,'Combined P&L'!$C:$C,'P&L Forecast'!$B41) -> 0 | S41: =SUMIFS('Combined P&L'!Q:Q,'Combined P&L'!$C:$C,'P&L Forecast'!$B41) -> 0 | T41: =SUMIFS('Combined P&L'!R:R,'Combined P&L'!$C:$C,'P&L Forecast'!$B41) -> 0 | U41: =SUMIFS('Combined P&L'!S:S,'Combined P&L'!$C:$C,'P&L Forecast'!$B41) -> 0 | V41: =SUMIFS('Combined P&L'!T:T,'Combined P&L'!$C:$C,'P&L Forecast'!$B41) -> 0 | W41: =SUMIFS('Combined P&L'!U:U,'Combined P&L'!$C:$C,'P&L Forecast'!$B41) -> 0 | X41: =SUMIFS('Combined P&L'!V:V,'Combined P&L'!$C:$C,'P&L Forecast'!$B41) -> 0 | Y41: =SUMIFS('Combined P&L'!W:W,'Combined P&L'!$C:$C,'P&L Forecast'!$B41) -> 0 | Z41: =SUMIFS('Combined P&L'!X:X,'Combined P&L'!$C:$C,'P&L Forecast'!$B41) -> 0 | AA41: =SUMIFS('Combined P&L'!Y:Y,'Combined P&L'!$C:$C,'P&L Forecast'!$B41) -> 0 | AB41: =SUMIFS('Combined P&L'!Z:Z,'Combined P&L'!$C:$C,'P&L Forecast'!$B41) -> 0 | AC41: =SUMIFS('Combined P&L'!AA:AA,'Combined P&L'!$C:$C,'P&L Forecast'!$B41) -> 0 | AD41: =SUMIFS('Combined P&L'!AB:AB,'Combined P&L'!$C:$C,'P&L Forecast'!$B41) -> 0 | AE41: =SUMIFS('Combined P&L'!AC:AC,'Combined P&L'!$C:$C,'P&L Forecast'!$B41) -> 0 | AF41: =SUMIFS('Combined P&L'!AD:AD,'Combined P&L'!$C:$C,'P&L Forecast'!$B41) -> 0 | AG41: =SUMIFS('Combined P&L'!AE:AE,'Combined P&L'!$C:$C,'P&L Forecast'!$B41) -> 0 | AH41: =SUMIFS('Combined P&L'!AF:AF,'Combined P&L'!$C:$C,'P&L Forecast'!$B41) -> 0 | AI41: =SUMIFS('Combined P&L'!AG:AG,'Combined P&L'!$C:$C,'P&L Forecast'!$B41) -> 0 | AJ41: =SUMIFS('Combined P&L'!AH:AH,'Combined P&L'!$C:$C,'P&L Forecast'!$B41) -> 0 | AK41: =SUMIFS('Combined P&L'!AI:AI,'Combined P&L'!$C:$C,'P&L Forecast'!$B41) -> 0 | AL41: =SUMIFS('Combined P&L'!AJ:AJ,'Combined P&L'!$C:$C,'P&L Forecast'!$B41) -> 0 | AM41: =SUMIFS('Combined P&L'!AK:AK,'Combined P&L'!$C:$C,'P&L Forecast'!$B41) -> 0 | AN41: =SUMIFS('Combined P&L'!AL:AL,'Combined P&L'!$C:$C,'P&L Forecast'!$B41) -> 0.12 | AO41: =SUMIFS('Combined P&L'!AM:AM,'Combined P&L'!$C:$C,'P&L Forecast'!$B41) -> 0.12 | AP41: =SUMIFS('Combined P&L'!AN:AN,'Combined P&L'!$C:$C,'P&L Forecast'!$B41) -> 0.70166 | AQ41: =SUMIFS('Combined P&L'!AO:AO,'Combined P&L'!$C:$C,'P&L Forecast'!$B41) -> 2.20736 | AR41: =SUMIFS('Combined P&L'!AP:AP,'Combined P&L'!$C:$C,'P&L Forecast'!$B41) -> 0.91487 | AS41: =SUMIFS('Combined P&L'!AQ:AQ,'Combined P&L'!$C:$C,'P&L Forecast'!$B41) -> 1.15165 | AT41: =SUMIFS('Combined P&L'!AR:AR,'Combined P&L'!$C:$C,'P&L Forecast'!$B41) -> 1.31198
B42: Total Software Expenses | C42: =SUM(C38:C41) -> 175.33863 | D42: =SUM(D38:D41) -> 281.69462 | F42: =SUM(F38:F41) -> 141.78009 | G42: =SUM(G38:G41) -> 284.68482 | I42: =SUM(I38:I41) -> 228.79834 | J42: =SUM(J38:J41) -> 424.59935 | K42: =SUM(K38:K41) -> 568.11456 | M42: =SUM(M38:M41) -> 143.51521 | N42: =IFERROR(K42/J42-1,0) -> 0.33800148 | P42: =SUM(P38:P41) -> 10.52585 | Q42: =SUM(Q38:Q41) -> 10.63571 | R42: =SUM(R38:R41) -> 11.75195 | S42: =SUM(S38:S41) -> 11.98489 | T42: =SUM(T38:T41) -> 12.81546 | U42: =SUM(U38:U41) -> 14.24615 | V42: =SUM(V38:V41) -> 16.36037 | W42: =SUM(W38:W41) -> 16.36683 | ... AT42: =SUM(AT38:AT41) -> 47.34288
B44: Other Professional Fees | C44: =SUMIFS($P44:$AT44,$P$5:$AT$5,">"&C$168,$P$5:$AT$5,"<"&C$169) -> 18.23425 | D44: =SUMIFS($P44:$AT44,$P$5:$AT$5,">"&D$168,$P$5:$AT$5,"<"&D$169) -> 27.04095 | F44: =SUMIFS($P44:$AT44,$P$5:$AT$5,">"&F$168,$P$5:$AT$5,"<"&F$169) -> 12.014 | G44: =SUMIFS($P44:$AT44,$P$5:$AT$5,">"&G$168,$P$5:$AT$5,"<"&G$169) -> 57.55 | I44: =SUMIFS($P44:$AT44,$P$5:$AT$5,">"&I$168,$P$5:$AT$5,"<"&I$169) -> 21.74858 | J44: =SUMIFS($P44:$AT44,$P$5:$AT$5,">"&J$168,$P$5:$AT$5,"<"&J$169) -> 72.57695 | K44: =+C143 -> 72.57695 | M44: =K44-J44 -> 0 | N44: =IFERROR(K44/J44-1,0) -> 0 | P44: =SUMIFS('Combined P&L'!N:N,'Combined P&L'!$C:$C,'P&L Forecast'!$B44) -> 0 | Q44: =SUMIFS('Combined P&L'!O:O,'Combined P&L'!$C:$C,'P&L Forecast'!$B44) -> 1.1665 | R44: =SUMIFS('Combined P&L'!P:P,'Combined P&L'!$C:$C,'P&L Forecast'!$B44) -> 1.1665 | S44: =SUMIFS('Combined P&L'!Q:Q,'Combined P&L'!$C:$C,'P&L Forecast'!$B44) -> 1.16667 | T44: =SUMIFS('Combined P&L'!R:R,'Combined P&L'!$C:$C,'P&L Forecast'!$B44) -> 1.16667 | U44: =SUMIFS('Combined P&L'!S:S,'Combined P&L'!$C:$C,'P&L Forecast'!$B44) -> 2.66666 | V44: =SUMIFS('Combined P&L'!T:T,'Combined P&L'!$C:$C,'P&L Forecast'!$B44) -> 1.16667 | W44: =SUMIFS('Combined P&L'!U:U,'Combined P&L'!$C:$C,'P&L Forecast'!$B44) -> 1.16667 | X44: =SUMIFS('Combined P&L'!V:V,'Combined P&L'!$C:$C,'P&L Forecast'!$B44) -> 3.06791 | Y44: =SUMIFS('Combined P&L'!W:W,'Combined P&L'!$C:$C,'P&L Forecast'!$B44) -> 1.16667 | Z44: =SUMIFS('Combined P&L'!X:X,'Combined P&L'!$C:$C,'P&L Forecast'!$B44) -> 2.16667 | AA44: =SUMIFS('Combined P&L'!Y:Y,'Combined P&L'!$C:$C,'P&L Forecast'!$B44) -> 2.16666 | AB44: =SUMIFS('Combined P&L'!Z:Z,'Combined P&L'!$C:$C,'P&L Forecast'!$B44) -> 2.16667 | AC44: =SUMIFS('Combined P&L'!AA:AA,'Combined P&L'!$C:$C,'P&L Forecast'!$B44) -> 2.16667 | AD44: =SUMIFS('Combined P&L'!AB:AB,'Combined P&L'!$C:$C,'P&L Forecast'!$B44) -> 2.16666 | AE44: =SUMIFS('Combined P&L'!AC:AC,'Combined P&L'!$C:$C,'P&L Forecast'!$B44) -> 2.76067 | AF44: =SUMIFS('Combined P&L'!AD:AD,'Combined P&L'!$C:$C,'P&L Forecast'!$B44) -> 1.58667 | AG44: =SUMIFS('Combined P&L'!AE:AE,'Combined P&L'!$C:$C,'P&L Forecast'!$B44) -> 1.16666 | AH44: =SUMIFS('Combined P&L'!AF:AF,'Combined P&L'!$C:$C,'P&L Forecast'!$B44) -> 0 | AI44: =SUMIFS('Combined P&L'!AG:AG,'Combined P&L'!$C:$C,'P&L Forecast'!$B44) -> 0.2 | AJ44: =SUMIFS('Combined P&L'!AH:AH,'Combined P&L'!$C:$C,'P&L Forecast'!$B44) -> 1.32695 | AK44: =SUMIFS('Combined P&L'!AI:AI,'Combined P&L'!$C:$C,'P&L Forecast'!$B44) -> 0 | AL44: =SUMIFS('Combined P&L'!AJ:AJ,'Combined P&L'!$C:$C,'P&L Forecast'!$B44) -> 6 | AM44: =SUMIFS('Combined P&L'!AK:AK,'Combined P&L'!$C:$C,'P&L Forecast'!$B44) -> 7.5 | AN44: =SUMIFS('Combined P&L'!AL:AL,'Combined P&L'!$C:$C,'P&L Forecast'!$B44) -> 0 | AO44: =SUMIFS('Combined P&L'!AM:AM,'Combined P&L'!$C:$C,'P&L Forecast'!$B44) -> 0 | AP44: =SUMIFS('Combined P&L'!AN:AN,'Combined P&L'!$C:$C,'P&L Forecast'!$B44) -> 6.6 | AQ44: =SUMIFS('Combined P&L'!AO:AO,'Combined P&L'!$C:$C,'P&L Forecast'!$B44) -> 14 | AR44: =SUMIFS('Combined P&L'!AP:AP,'Combined P&L'!$C:$C,'P&L Forecast'!$B44) -> 18 | AS44: =SUMIFS('Combined P&L'!AQ:AQ,'Combined P&L'!$C:$C,'P&L Forecast'!$B44) -> 0 | AT44: =SUMIFS('Combined P&L'!AR:AR,'Combined P&L'!$C:$C,'P&L Forecast'!$B44) -> 18.95
B45: Referral Fees | C45: =SUMIFS($P45:$AT45,$P$5:$AT$5,">"&C$168,$P$5:$AT$5,"<"&C$169) -> 24.82 | D45: =SUMIFS($P45:$AT45,$P$5:$AT$5,">"&D$168,$P$5:$AT$5,"<"&D$169) -> 27.15374 | F45: =SUMIFS($P45:$AT45,$P$5:$AT$5,">"&F$168,$P$5:$AT$5,"<"&F$169) -> 17.0895 | G45: =SUMIFS($P45:$AT45,$P$5:$AT$5,">"&G$168,$P$5:$AT$5,"<"&G$169) -> 20.62969 | I45: =SUMIFS($P45:$AT45,$P$5:$AT$5,">"&I$168,$P$5:$AT$5,"<"&I$169) -> 26.2095 | J45: =SUMIFS($P45:$AT45,$P$5:$AT$5,">"&J$168,$P$5:$AT$5,"<"&J$169) -> 30.69393 | K45: =+C144 -> 30.69393 | M45: =K45-J45 -> 0 | N45: =IFERROR(K45/J45-1,0) -> 0 | P45: =SUMIFS('Combined P&L'!N:N,'Combined P&L'!$C:$C,'P&L Forecast'!$B45) -> 2.21 | Q45: =SUMIFS('Combined P&L'!O:O,'Combined P&L'!$C:$C,'P&L Forecast'!$B45) -> 2.735 | R45: =SUMIFS('Combined P&L'!P:P,'Combined P&L'!$C:$C,'P&L Forecast'!$B45) -> 2.715 | S45: =SUMIFS('Combined P&L'!Q:Q,'Combined P&L'!$C:$C,'P&L Forecast'!$B45) -> 2.735 | T45: =SUMIFS('Combined P&L'!R:R,'Combined P&L'!$C:$C,'P&L Forecast'!$B45) -> 0.78 | U45: =SUMIFS('Combined P&L'!S:S,'Combined P&L'!$C:$C,'P&L Forecast'!$B45) -> 3.245 | V45: =SUMIFS('Combined P&L'!T:T,'Combined P&L'!$C:$C,'P&L Forecast'!$B45) -> 1.28 | W45: =SUMIFS('Combined P&L'!U:U,'Combined P&L'!$C:$C,'P&L Forecast'!$B45) -> 1.3 | X45: =SUMIFS('Combined P&L'!V:V,'Combined P&L'!$C:$C,'P&L Forecast'!$B45) -> 1.81 | Y45: =SUMIFS('Combined P&L'!W:W,'Combined P&L'!$C:$C,'P&L Forecast'!$B45) -> 1.82 | Z45: =SUMIFS('Combined P&L'!X:X,'Combined P&L'!$C:$C,'P&L Forecast'!$B45) -> 1.835 | AA45: =SUMIFS('Combined P&L'!Y:Y,'Combined P&L'!$C:$C,'P&L Forecast'!$B45) -> 2.355 | AB45: =SUMIFS('Combined P&L'!Z:Z,'Combined P&L'!$C:$C,'P&L Forecast'!$B45) -> 1.47025 | AC45: =SUMIFS('Combined P&L'!AA:AA,'Combined P&L'!$C:$C,'P&L Forecast'!$B45) -> 1.665 | AD45: =SUMIFS('Combined P&L'!AB:AB,'Combined P&L'!$C:$C,'P&L Forecast'!$B45) -> 2.62775 | AE45: =SUMIFS('Combined P&L'!AC:AC,'Combined P&L'!$C:$C,'P&L Forecast'!$B45) -> 1.24875 | AF45: =SUMIFS('Combined P&L'!AD:AD,'Combined P&L'!$C:$C,'P&L Forecast'!$B45) -> 2.154 | AG45: =SUMIFS('Combined P&L'!AE:AE,'Combined P&L'!$C:$C,'P&L Forecast'!$B45) -> 4.154 | AH45: =SUMIFS('Combined P&L'!AF:AF,'Combined P&L'!$C:$C,'P&L Forecast'!$B45) -> 3.76975 | AI45: =SUMIFS('Combined P&L'!AG:AG,'Combined P&L'!$C:$C,'P&L Forecast'!$B45) -> 1.696 | AJ45: =SUMIFS('Combined P&L'!AH:AH,'Combined P&L'!$C:$C,'P&L Forecast'!$B45) -> 2.2275 | AK45: =SUMIFS('Combined P&L'!AI:AI,'Combined P&L'!$C:$C,'P&L Forecast'!$B45) -> 1.6645 | AL45: =SUMIFS('Combined P&L'!AJ:AJ,'Combined P&L'!$C:$C,'P&L Forecast'!$B45) -> 1.71879 | AM45: =SUMIFS('Combined P&L'!AK:AK,'Combined P&L'!$C:$C,'P&L Forecast'!$B45) -> 2.75745 | AN45: =SUMIFS('Combined P&L'!AL:AL,'Combined P&L'!$C:$C,'P&L Forecast'!$B45) -> 1.8688 | AO45: =SUMIFS('Combined P&L'!AM:AM,'Combined P&L'!$C:$C,'P&L Forecast'!$B45) -> 4.43991 | AP45: =SUMIFS('Combined P&L'!AN:AN,'Combined P&L'!$C:$C,'P&L Forecast'!$B45) -> 2.39361 | AQ45: =SUMIFS('Combined P&L'!AO:AO,'Combined P&L'!$C:$C,'P&L Forecast'!$B45) -> 3.65786 | AR45: =SUMIFS('Combined P&L'!AP:AP,'Combined P&L'!$C:$C,'P&L Forecast'!$B45) -> 2.93379 | AS45: =SUMIFS('Combined P&L'!AQ:AQ,'Combined P&L'!$C:$C,'P&L Forecast'!$B45) -> 1.5662 | AT45: =SUMIFS('Combined P&L'!AR:AR,'Combined P&L'!$C:$C,'P&L Forecast'!$B45) -> 3.76952
B46: Travel, Meals & Entertainment | C46: =SUMIFS($P46:$AT46,$P$5:$AT$5,">"&C$168,$P$5:$AT$5,"<"&C$169) -> 0 | D46: =SUMIFS($P46:$AT46,$P$5:$AT$5,">"&D$168,$P$5:$AT$5,"<"&D$169) -> 29.76122 | F46: =SUMIFS($P46:$AT46,$P$5:$AT$5,">"&F$168,$P$5:$AT$5,"<"&F$169) -> 22.29558 | G46: =SUMIFS($P46:$AT46,$P$5:$AT$5,">"&G$168,$P$5:$AT$5,"<"&G$169) -> 20.68542 | I46: =SUMIFS($P46:$AT46,$P$5:$AT$5,">"&I$168,$P$5:$AT$5,"<"&I$169) -> 22.29558 | J46: =SUMIFS($P46:$AT46,$P$5:$AT$5,">"&J$168,$P$5:$AT$5,"<"&J$169) -> 28.15106 | K46: =+C145 -> 28.15106 | M46: =K46-J46 -> 0 | N46: =IFERROR(K46/J46-1,0) -> 0 | P46: =SUMIFS('Combined P&L'!N:N,'Combined P&L'!$C:$C,'P&L Forecast'!$B46) -> 0 | Q46: =SUMIFS('Combined P&L'!O:O,'Combined P&L'!$C:$C,'P&L Forecast'!$B46) -> 0 | R46: =SUMIFS('Combined P&L'!P:P,'Combined P&L'!$C:$C,'P&L Forecast'!$B46) -> 0 | S46: =SUMIFS('Combined P&L'!Q:Q,'Combined P&L'!$C:$C,'P&L Forecast'!$B46) -> 0 | T46: =SUMIFS('Combined P&L'!R:R,'Combined P&L'!$C:$C,'P&L Forecast'!$B46) -> 0 | U46: =SUMIFS('Combined P&L'!S:S,'Combined P&L'!$C:$C,'P&L Forecast'!$B46) -> 0 | V46: =SUMIFS('Combined P&L'!T:T,'Combined P&L'!$C:$C,'P&L Forecast'!$B46) -> 0 | W46: =SUMIFS('Combined P&L'!U:U,'Combined P&L'!$C:$C,'P&L Forecast'!$B46) -> 0 | X46: =SUMIFS('Combined P&L'!V:V,'Combined P&L'!$C:$C,'P&L Forecast'!$B46) -> 0 | Y46: =SUMIFS('Combined P&L'!W:W,'Combined P&L'!$C:$C,'P&L Forecast'!$B46) -> 0 | Z46: =SUMIFS('Combined P&L'!X:X,'Combined P&L'!$C:$C,'P&L Forecast'!$B46) -> 0 | AA46: =SUMIFS('Combined P&L'!Y:Y,'Combined P&L'!$C:$C,'P&L Forecast'!$B46) -> 0 | AB46: =SUMIFS('Combined P&L'!Z:Z,'Combined P&L'!$C:$C,'P&L Forecast'!$B46) -> 0.00691 | AC46: =SUMIFS('Combined P&L'!AA:AA,'Combined P&L'!$C:$C,'P&L Forecast'!$B46) -> 0 | AD46: =SUMIFS('Combined P&L'!AB:AB,'Combined P&L'!$C:$C,'P&L Forecast'!$B46) -> 0 | AE46: =SUMIFS('Combined P&L'!AC:AC,'Combined P&L'!$C:$C,'P&L Forecast'!$B46) -> 11.40629 | AF46: =SUMIFS('Combined P&L'!AD:AD,'Combined P&L'!$C:$C,'P&L Forecast'!$B46) -> 10.78472 | AG46: =SUMIFS('Combined P&L'!AE:AE,'Combined P&L'!$C:$C,'P&L Forecast'!$B46) -> 0 | AH46: =SUMIFS('Combined P&L'!AF:AF,'Combined P&L'!$C:$C,'P&L Forecast'!$B46) -> 0.09766 | AI46: =SUMIFS('Combined P&L'!AG:AG,'Combined P&L'!$C:$C,'P&L Forecast'!$B46) -> 0.92152 | AJ46: =SUMIFS('Combined P&L'!AH:AH,'Combined P&L'!$C:$C,'P&L Forecast'!$B46) -> 2.96423 | AK46: =SUMIFS('Combined P&L'!AI:AI,'Combined P&L'!$C:$C,'P&L Forecast'!$B46) -> 1.03679 | AL46: =SUMIFS('Combined P&L'!AJ:AJ,'Combined P&L'!$C:$C,'P&L Forecast'!$B46) -> 2.11036 | AM46: =SUMIFS('Combined P&L'!AK:AK,'Combined P&L'!$C:$C,'P&L Forecast'!$B46) -> 0.43274 | AN46: =SUMIFS('Combined P&L'!AL:AL,'Combined P&L'!$C:$C,'P&L Forecast'!$B46) -> 0 | AO46: =SUMIFS('Combined P&L'!AM:AM,'Combined P&L'!$C:$C,'P&L Forecast'!$B46) -> 0 | AP46: =SUMIFS('Combined P&L'!AN:AN,'Combined P&L'!$C:$C,'P&L Forecast'!$B46) -> 0 | AQ46: =SUMIFS('Combined P&L'!AO:AO,'Combined P&L'!$C:$C,'P&L Forecast'!$B46) -> 9.7651 | AR46: =SUMIFS('Combined P&L'!AP:AP,'Combined P&L'!$C:$C,'P&L Forecast'!$B46) -> 10.25443 | AS46: =SUMIFS('Combined P&L'!AQ:AQ,'Combined P&L'!$C:$C,'P&L Forecast'!$B46) -> 0.6559 | AT46: =SUMIFS('Combined P&L'!AR:AR,'Combined P&L'!$C:$C,'P&L Forecast'!$B46) -> 0.00999
B47: Payment Collection Fees | C47: =SUMIFS($P47:$AT47,$P$5:$AT$5,">"&C$168,$P$5:$AT$5,"<"&C$169) -> 8.67099 | D47: =SUMIFS($P47:$AT47,$P$5:$AT$5,">"&D$168,$P$5:$AT$5,"<"&D$169) -> 13.35153 | F47: =SUMIFS($P47:$AT47,$P$5:$AT$5,">"&F$168,$P$5:$AT$5,"<"&F$169) -> 6.80445 | G47: =SUMIFS($P47:$AT47,$P$5:$AT$5,">"&G$168,$P$5:$AT$5,"<"&G$169) -> 9.02684 | I47: =SUMIFS($P47:$AT47,$P$5:$AT$5,">"&I$168,$P$5:$AT$5,"<"&I$169) -> 10.54373 | J47: =SUMIFS($P47:$AT47,$P$5:$AT$5,">"&J$168,$P$5:$AT$5,"<"&J$169) -> 15.57392 | K47: =+C146 -> 15.57392 | M47: =K47-J47 -> 0 | N47: =IFERROR(K47/J47-1,0) -> 0 | P47: =SUMIFS('Combined P&L'!N:N,'Combined P&L'!$C:$C,'P&L Forecast'!$B47) -> 0.6179 | Q47: =SUMIFS('Combined P&L'!O:O,'Combined P&L'!$C:$C,'P&L Forecast'!$B47) -> 0.8374 | R47: =SUMIFS('Combined P&L'!P:P,'Combined P&L'!$C:$C,'P&L Forecast'!$B47) -> 0.62936 | S47: =SUMIFS('Combined P&L'!Q:Q,'Combined P&L'!$C:$C,'P&L Forecast'!$B47) -> 0.68245 | T47: =SUMIFS('Combined P&L'!R:R,'Combined P&L'!$C:$C,'P&L Forecast'!$B47) -> 0.72151 | U47: =SUMIFS('Combined P&L'!S:S,'Combined P&L'!$C:$C,'P&L Forecast'!$B47) -> 0.78747 | V47: =SUMIFS('Combined P&L'!T:T,'Combined P&L'!$C:$C,'P&L Forecast'!$B47) -> 0.65562 | W47: =SUMIFS('Combined P&L'!U:U,'Combined P&L'!$C:$C,'P&L Forecast'!$B47) -> 0.79491 | X47: =SUMIFS('Combined P&L'!V:V,'Combined P&L'!$C:$C,'P&L Forecast'!$B47) -> 0.69063 | Y47: =SUMIFS('Combined P&L'!W:W,'Combined P&L'!$C:$C,'P&L Forecast'!$B47) -> 0.71761 | Z47: =SUMIFS('Combined P&L'!X:X,'Combined P&L'!$C:$C,'P&L Forecast'!$B47) -> 0.73795 | AA47: =SUMIFS('Combined P&L'!Y:Y,'Combined P&L'!$C:$C,'P&L Forecast'!$B47) -> 0.79818 | AB47: =SUMIFS('Combined P&L'!Z:Z,'Combined P&L'!$C:$C,'P&L Forecast'!$B47) -> 0.83546 | AC47: =SUMIFS('Combined P&L'!AA:AA,'Combined P&L'!$C:$C,'P&L Forecast'!$B47) -> 1.05394 | AD47: =SUMIFS('Combined P&L'!AB:AB,'Combined P&L'!$C:$C,'P&L Forecast'!$B47) -> 0.87069 | AE47: =SUMIFS('Combined P&L'!AC:AC,'Combined P&L'!$C:$C,'P&L Forecast'!$B47) -> 0.90555 | AF47: =SUMIFS('Combined P&L'!AD:AD,'Combined P&L'!$C:$C,'P&L Forecast'!$B47) -> 0.91157 | AG47: =SUMIFS('Combined P&L'!AE:AE,'Combined P&L'!$C:$C,'P&L Forecast'!$B47) -> 1.00249 | AH47: =SUMIFS('Combined P&L'!AF:AF,'Combined P&L'!$C:$C,'P&L Forecast'!$B47) -> 1.22475 | AI47: =SUMIFS('Combined P&L'!AG:AG,'Combined P&L'!$C:$C,'P&L Forecast'!$B47) -> 1.10438 | AJ47: =SUMIFS('Combined P&L'!AH:AH,'Combined P&L'!$C:$C,'P&L Forecast'!$B47) -> 1.29723 | AK47: =SUMIFS('Combined P&L'!AI:AI,'Combined P&L'!$C:$C,'P&L Forecast'!$B47) -> 1.21739 | AL47: =SUMIFS('Combined P&L'!AJ:AJ,'Combined P&L'!$C:$C,'P&L Forecast'!$B47) -> 1.62294 | AM47: =SUMIFS('Combined P&L'!AK:AK,'Combined P&L'!$C:$C,'P&L Forecast'!$B47) -> 1.30514 | AN47: =SUMIFS('Combined P&L'!AL:AL,'Combined P&L'!$C:$C,'P&L Forecast'!$B47) -> 1.22974 | AO47: =SUMIFS('Combined P&L'!AM:AM,'Combined P&L'!$C:$C,'P&L Forecast'!$B47) -> 1.73847 | AP47: =SUMIFS('Combined P&L'!AN:AN,'Combined P&L'!$C:$C,'P&L Forecast'!$B47) -> 1.35348 | AQ47: =SUMIFS('Combined P&L'!AO:AO,'Combined P&L'!$C:$C,'P&L Forecast'!$B47) -> 1.23399 | AR47: =SUMIFS('Combined P&L'!AP:AP,'Combined P&L'!$C:$C,'P&L Forecast'!$B47) -> 1.17137 | AS47: =SUMIFS('Combined P&L'!AQ:AQ,'Combined P&L'!$C:$C,'P&L Forecast'!$B47) -> 1.15392 | AT47: =SUMIFS('Combined P&L'!AR:AR,'Combined P&L'!$C:$C,'P&L Forecast'!$B47) -> 1.14587
B48: Professional Organizations | C48: =SUMIFS($P48:$AT48,$P$5:$AT$5,">"&C$168,$P$5:$AT$5,"<"&C$169) -> 5.44332 | D48: =SUMIFS($P48:$AT48,$P$5:$AT$5,">"&D$168,$P$5:$AT$5,"<"&D$169) -> 11.22296 | F48: =SUMIFS($P48:$AT48,$P$5:$AT$5,">"&F$168,$P$5:$AT$5,"<"&F$169) -> 6.191 | G48: =SUMIFS($P48:$AT48,$P$5:$AT$5,">"&G$168,$P$5:$AT$5,"<"&G$169) -> 6.57881 | I48: =SUMIFS($P48:$AT48,$P$5:$AT$5,">"&I$168,$P$5:$AT$5,"<"&I$169) -> 9.53268 | J48: =SUMIFS($P48:$AT48,$P$5:$AT$5,">"&J$168,$P$5:$AT$5,"<"&J$169) -> 11.61077 | K48: =+C147 -> 11.61077 | M48: =K48-J48 -> 0 | N48: =IFERROR(K48/J48-1,0) -> 0 | P48: =SUMIFS('Combined P&L'!N:N,'Combined P&L'!$C:$C,'P&L Forecast'!$B48) -> 0.33417 | Q48: =SUMIFS('Combined P&L'!O:O,'Combined P&L'!$C:$C,'P&L Forecast'!$B48) -> 0.33417 | R48: =SUMIFS('Combined P&L'!P:P,'Combined P&L'!$C:$C,'P&L Forecast'!$B48) -> 0.33417 | S48: =SUMIFS('Combined P&L'!Q:Q,'Combined P&L'!$C:$C,'P&L Forecast'!$B48) -> 0.33417 | T48: =SUMIFS('Combined P&L'!R:R,'Combined P&L'!$C:$C,'P&L Forecast'!$B48) -> 0.255 | U48: =SUMIFS('Combined P&L'!S:S,'Combined P&L'!$C:$C,'P&L Forecast'!$B48) -> 0.255 | V48: =SUMIFS('Combined P&L'!T:T,'Combined P&L'!$C:$C,'P&L Forecast'!$B48) -> 0.25496 | W48: =SUMIFS('Combined P&L'!U:U,'Combined P&L'!$C:$C,'P&L Forecast'!$B48) -> 0.205 | X48: =SUMIFS('Combined P&L'!V:V,'Combined P&L'!$C:$C,'P&L Forecast'!$B48) -> 0.78417 | Y48: =SUMIFS('Combined P&L'!W:W,'Combined P&L'!$C:$C,'P&L Forecast'!$B48) -> 0.78417 | Z48: =SUMIFS('Combined P&L'!X:X,'Combined P&L'!$C:$C,'P&L Forecast'!$B48) -> 0.78417 | AA48: =SUMIFS('Combined P&L'!Y:Y,'Combined P&L'!$C:$C,'P&L Forecast'!$B48) -> 0.78417 | AB48: =SUMIFS('Combined P&L'!Z:Z,'Combined P&L'!$C:$C,'P&L Forecast'!$B48) -> 0.78417 | AC48: =SUMIFS('Combined P&L'!AA:AA,'Combined P&L'!$C:$C,'P&L Forecast'!$B48) -> 0.78417 | AD48: =SUMIFS('Combined P&L'!AB:AB,'Combined P&L'!$C:$C,'P&L Forecast'!$B48) -> 0.78417 | AE48: =SUMIFS('Combined P&L'!AC:AC,'Combined P&L'!$C:$C,'P&L Forecast'!$B48) -> 0.78417 | AF48: =SUMIFS('Combined P&L'!AD:AD,'Combined P&L'!$C:$C,'P&L Forecast'!$B48) -> 0.78417 | AG48: =SUMIFS('Combined P&L'!AE:AE,'Combined P&L'!$C:$C,'P&L Forecast'!$B48) -> 0.78417 | AH48: =SUMIFS('Combined P&L'!AF:AF,'Combined P&L'!$C:$C,'P&L Forecast'!$B48) -> 1.48598 | AI48: =SUMIFS('Combined P&L'!AG:AG,'Combined P&L'!$C:$C,'P&L Forecast'!$B48) -> 0.9633 | AJ48: =SUMIFS('Combined P&L'!AH:AH,'Combined P&L'!$C:$C,'P&L Forecast'!$B48) -> 0.98042 | AK48: =SUMIFS('Combined P&L'!AI:AI,'Combined P&L'!$C:$C,'P&L Forecast'!$B48) -> 1.02942 | AL48: =SUMIFS('Combined P&L'!AJ:AJ,'Combined P&L'!$C:$C,'P&L Forecast'!$B48) -> 1.02942 | AM48: =SUMIFS('Combined P&L'!AK:AK,'Combined P&L'!$C:$C,'P&L Forecast'!$B48) -> 1.0294 | AN48: =SUMIFS('Combined P&L'!AL:AL,'Combined P&L'!$C:$C,'P&L Forecast'!$B48) -> 0.93983 | AO48: =SUMIFS('Combined P&L'!AM:AM,'Combined P&L'!$C:$C,'P&L Forecast'!$B48) -> 0.93983 | AP48: =SUMIFS('Combined P&L'!AN:AN,'Combined P&L'!$C:$C,'P&L Forecast'!$B48) -> 0.93983 | AQ48: =SUMIFS('Combined P&L'!AO:AO,'Combined P&L'!$C:$C,'P&L Forecast'!$B48) -> 0.93983 | AR48: =SUMIFS('Combined P&L'!AP:AP,'Combined P&L'!$C:$C,'P&L Forecast'!$B48) -> 0.93983 | AS48: =SUMIFS('Combined P&L'!AQ:AQ,'Combined P&L'!$C:$C,'P&L Forecast'!$B48) -> 0.93983 | AT48: =SUMIFS('Combined P&L'!AR:AR,'Combined P&L'!$C:$C,'P&L Forecast'!$B48) -> 0.93983
B49: S&M Events | C49: =SUMIFS($P49:$AT49,$P$5:$AT$5,">"&C$168,$P$5:$AT$5,"<"&C$169) -> 0 | D49: =SUMIFS($P49:$AT49,$P$5:$AT$5,">"&D$168,$P$5:$AT$5,"<"&D$169) -> 11.4983 | F49: =SUMIFS($P49:$AT49,$P$5:$AT$5,">"&F$168,$P$5:$AT$5,"<"&F$169) -> 0 | G49: =SUMIFS($P49:$AT49,$P$5:$AT$5,">"&G$168,$P$5:$AT$5,"<"&G$169) -> 11.84548 | I49: =SUMIFS($P49:$AT49,$P$5:$AT$5,">"&I$168,$P$5:$AT$5,"<"&I$169) -> 0 | J49: =SUMIFS($P49:$AT49,$P$5:$AT$5,">"&J$168,$P$5:$AT$5,"<"&J$169) -> 23.34378 | K49: =+C148 -> 23.34378 | M49: =K49-J49 -> 0 | N49: =IFERROR(K49/J49-1,0) -> 0 | P49: =SUMIFS('Combined P&L'!N:N,'Combined P&L'!$C:$C,'P&L Forecast'!$B49) -> 0 | Q49: =SUMIFS('Combined P&L'!O:O,'Combined P&L'!$C:$C,'P&L Forecast'!$B49) -> 0 | R49: =SUMIFS('Combined P&L'!P:P,'Combined P&L'!$C:$C,'P&L Forecast'!$B49) -> 0 | S49: =SUMIFS('Combined P&L'!Q:Q,'Combined P&L'!$C:$C,'P&L Forecast'!$B49) -> 0 | T49: =SUMIFS('Combined P&L'!R:R,'Combined P&L'!$C:$C,'P&L Forecast'!$B49) -> 0 | U49: =SUMIFS('Combined P&L'!S:S,'Combined P&L'!$C:$C,'P&L Forecast'!$B49) -> 0 | V49: =SUMIFS('Combined P&L'!T:T,'Combined P&L'!$C:$C,'P&L Forecast'!$B49) -> 0 | W49: =SUMIFS('Combined P&L'!U:U,'Combined P&L'!$C:$C,'P&L Forecast'!$B49) -> 0 | X49: =SUMIFS('Combined P&L'!V:V,'Combined P&L'!$C:$C,'P&L Forecast'!$B49) -> 0 | Y49: =SUMIFS('Combined P&L'!W:W,'Combined P&L'!$C:$C,'P&L Forecast'!$B49) -> 0 | Z49: =SUMIFS('Combined P&L'!X:X,'Combined P&L'!$C:$C,'P&L Forecast'!$B49) -> 0 | AA49: =SUMIFS('Combined P&L'!Y:Y,'Combined P&L'!$C:$C,'P&L Forecast'!$B49) -> 0 | AB49: =SUMIFS('Combined P&L'!Z:Z,'Combined P&L'!$C:$C,'P&L Forecast'!$B49) -> 0 | AC49: =SUMIFS('Combined P&L'!AA:AA,'Combined P&L'!$C:$C,'P&L Forecast'!$B49) -> 0 | AD49: =SUMIFS('Combined P&L'!AB:AB,'Combined P&L'!$C:$C,'P&L Forecast'!$B49) -> 0 | AE49: =SUMIFS('Combined P&L'!AC:AC,'Combined P&L'!$C:$C,'P&L Forecast'!$B49) -> 0 | AF49: =SUMIFS('Combined P&L'!AD:AD,'Combined P&L'!$C:$C,'P&L Forecast'!$B49) -> 0 | AG49: =SUMIFS('Combined P&L'!AE:AE,'Combined P&L'!$C:$C,'P&L Forecast'!$B49) -> 0 | AH49: =SUMIFS('Combined P&L'!AF:AF,'Combined P&L'!$C:$C,'P&L Forecast'!$B49) -> 0 | AI49: =SUMIFS('Combined P&L'!AG:AG,'Combined P&L'!$C:$C,'P&L Forecast'!$B49) -> 7.17 | AJ49: =SUMIFS('Combined P&L'!AH:AH,'Combined P&L'!$C:$C,'P&L Forecast'!$B49) -> 1.6495 | AK49: =SUMIFS('Combined P&L'!AI:AI,'Combined P&L'!$C:$C,'P&L Forecast'!$B49) -> 2.6788 | AL49: =SUMIFS('Combined P&L'!AJ:AJ,'Combined P&L'!$C:$C,'P&L Forecast'!$B49) -> 0 | AM49: =SUMIFS('Combined P&L'!AK:AK,'Combined P&L'!$C:$C,'P&L Forecast'!$B49) -> 0 | AN49: =SUMIFS('Combined P&L'!AL:AL,'Combined P&L'!$C:$C,'P&L Forecast'!$B49) -> 0.05 | AO49: =SUMIFS('Combined P&L'!AM:AM,'Combined P&L'!$C:$C,'P&L Forecast'!$B49) -> 0 | AP49: =SUMIFS('Combined P&L'!AN:AN,'Combined P&L'!$C:$C,'P&L Forecast'!$B49) -> 0 | AQ49: =SUMIFS('Combined P&L'!AO:AO,'Combined P&L'!$C:$C,'P&L Forecast'!$B49) -> 0 | AR49: =SUMIFS('Combined P&L'!AP:AP,'Combined P&L'!$C:$C,'P&L Forecast'!$B49) -> 0.09805 | AS49: =SUMIFS('Combined P&L'!AQ:AQ,'Combined P&L'!$C:$C,'P&L Forecast'!$B49) -> 0.00243 | AT49: =SUMIFS('Combined P&L'!AR:AR,'Combined P&L'!$C:$C,'P&L Forecast'!$B49) -> 11.695
B50: Contract Labor - Tax | C50: =SUMIFS($P50:$AT50,$P$5:$AT$5,">"&C$168,$P$5:$AT$5,"<"&C$169) -> 0 | D50: =SUMIFS($P50:$AT50,$P$5:$AT$5,">"&D$168,$P$5:$AT$5,"<"&D$169) -> 1.5875 | F50: =SUMIFS($P50:$AT50,$P$5:$AT$5,">"&F$168,$P$5:$AT$5,"<"&F$169) -> 0 | G50: =SUMIFS($P50:$AT50,$P$5:$AT$5,">"&G$168,$P$5:$AT$5,"<"&G$169) -> 30.5155 | I50: =SUMIFS($P50:$AT50,$P$5:$AT$5,">"&I$168,$P$5:$AT$5,"<"&I$169) -> 0 | J50: =SUMIFS($P50:$AT50,$P$5:$AT$5,">"&J$168,$P$5:$AT$5,"<"&J$169) -> 32.103 | K50: =+C149 -> 38.7615 | M50: =K50-J50 -> 6.6585 | N50: =IFERROR(K50/J50-1,0) -> 0.20741052 | P50: =SUMIFS('Combined P&L'!N:N,'Combined P&L'!$C:$C,'P&L Forecast'!$B50) -> 0 | Q50: =SUMIFS('Combined P&L'!O:O,'Combined P&L'!$C:$C,'P&L Forecast'!$B50) -> 0 | R50: =SUMIFS('Combined P&L'!P:P,'Combined P&L'!$C:$C,'P&L Forecast'!$B50) -> 0 | S50: =SUMIFS('Combined P&L'!Q:Q,'Combined P&L'!$C:$C,'P&L Forecast'!$B50) -> 0 | T50: =SUMIFS('Combined P&L'!R:R,'Combined P&L'!$C:$C,'P&L Forecast'!$B50) -> 0 | U50: =SUMIFS('Combined P&L'!S:S,'Combined P&L'!$C:$C,'P&L Forecast'!$B50) -> 0 | V50: =SUMIFS('Combined P&L'!T:T,'Combined P&L'!$C:$C,'P&L Forecast'!$B50) -> 0 | W50: =SUMIFS('Combined P&L'!U:U,'Combined P&L'!$C:$C,'P&L Forecast'!$B50) -> 0 | X50: =SUMIFS('Combined P&L'!V:V,'Combined P&L'!$C:$C,'P&L Forecast'!$B50) -> 0 | Y50: =SUMIFS('Combined P&L'!W:W,'Combined P&L'!$C:$C,'P&L Forecast'!$B50) -> 0 | Z50: =SUMIFS('Combined P&L'!X:X,'Combined P&L'!$C:$C,'P&L Forecast'!$B50) -> 0 | AA50: =SUMIFS('Combined P&L'!Y:Y,'Combined P&L'!$C:$C,'P&L Forecast'!$B50) -> 0 | AB50: =SUMIFS('Combined P&L'!Z:Z,'Combined P&L'!$C:$C,'P&L Forecast'!$B50) -> 0 | AC50: =SUMIFS('Combined P&L'!AA:AA,'Combined P&L'!$C:$C,'P&L Forecast'!$B50) -> 0 | AD50: =SUMIFS('Combined P&L'!AB:AB,'Combined P&L'!$C:$C,'P&L Forecast'!$B50) -> 0 | AE50: =SUMIFS('Combined P&L'!AC:AC,'Combined P&L'!$C:$C,'P&L Forecast'!$B50) -> 0 | AF50: =SUMIFS('Combined P&L'!AD:AD,'Combined P&L'!$C:$C,'P&L Forecast'!$B50) -> 0 | AG50: =SUMIFS('Combined P&L'!AE:AE,'Combined P&L'!$C:$C,'P&L Forecast'!$B50) -> 0 | AH50: =SUMIFS('Combined P&L'!AF:AF,'Combined P&L'!$C:$C,'P&L Forecast'!$B50) -> 0 | AI50: =SUMIFS('Combined P&L'!AG:AG,'Combined P&L'!$C:$C,'P&L Forecast'!$B50) -> 0 | AJ50: =SUMIFS('Combined P&L'!AH:AH,'Combined P&L'!$C:$C,'P&L Forecast'!$B50) -> 0 | AK50: =SUMIFS('Combined P&L'!AI:AI,'Combined P&L'!$C:$C,'P&L Forecast'!$B50) -> 1.15 | AL50: =SUMIFS('Combined P&L'!AJ:AJ,'Combined P&L'!$C:$C,'P&L Forecast'!$B50) -> 0.4375 | AM50: =SUMIFS('Combined P&L'!AK:AK,'Combined P&L'!$C:$C,'P&L Forecast'!$B50) -> 0 | AN50: =SUMIFS('Combined P&L'!AL:AL,'Combined P&L'!$C:$C,'P&L Forecast'!$B50) -> 0 | AO50: =SUMIFS('Combined P&L'!AM:AM,'Combined P&L'!$C:$C,'P&L Forecast'!$B50) -> 3 | AP50: =SUMIFS('Combined P&L'!AN:AN,'Combined P&L'!$C:$C,'P&L Forecast'!$B50) -> 16.2655 | AQ50: =SUMIFS('Combined P&L'!AO:AO,'Combined P&L'!$C:$C,'P&L Forecast'!$B50) -> 2.8 | AR50: =SUMIFS('Combined P&L'!AP:AP,'Combined P&L'!$C:$C,'P&L Forecast'!$B50) -> 0 | AS50: =SUMIFS('Combined P&L'!AQ:AQ,'Combined P&L'!$C:$C,'P&L Forecast'!$B50) -> 8.45 | AT50: =SUMIFS('Combined P&L'!AR:AR,'Combined P&L'!$C:$C,'P&L Forecast'!$B50) -> 0
B51: Recruiting Fees | C51: =SUMIFS($P51:$AT51,$P$5:$AT$5,">"&C$168,$P$5:$AT$5,"<"&C$169) -> 14.90205 | D51: =SUMIFS($P51:$AT51,$P$5:$AT$5,">"&D$168,$P$5:$AT$5,"<"&D$169) -> 31.6041 | F51: =SUMIFS($P51:$AT51,$P$5:$AT$5,">"&F$168,$P$5:$AT$5,"<"&F$169) -> 28.29994 | G51: =SUMIFS($P51:$AT51,$P$5:$AT$5,">"&G$168,$P$5:$AT$5,"<"&G$169) -> 5.5646 | I51: =SUMIFS($P51:$AT51,$P$5:$AT$5,">"&I$168,$P$5:$AT$5,"<"&I$169) -> 35.34606 | J51: =SUMIFS($P51:$AT51,$P$5:$AT$5,">"&J$168,$P$5:$AT$5,"<"&J$169) -> 8.86876 | K51: =+C150 -> 8.86876 | M51: =K51-J51 -> 0 | N51: =IFERROR(K51/J51-1,0) -> 0 | P51: =SUMIFS('Combined P&L'!N:N,'Combined P&L'!$C:$C,'P&L Forecast'!$B51) -> 0.02492 | Q51: =SUMIFS('Combined P&L'!O:O,'Combined P&L'!$C:$C,'P&L Forecast'!$B51) -> 1.02492 | R51: =SUMIFS('Combined P&L'!P:P,'Combined P&L'!$C:$C,'P&L Forecast'!$B51) -> 1.02492 | S51: =SUMIFS('Combined P&L'!Q:Q,'Combined P&L'!$C:$C,'P&L Forecast'!$B51) -> 1.22492 | T51: =SUMIFS('Combined P&L'!R:R,'Combined P&L'!$C:$C,'P&L Forecast'!$B51) -> 1.02492 | U51: =SUMIFS('Combined P&L'!S:S,'Combined P&L'!$C:$C,'P&L Forecast'!$B51) -> 1.51802 | V51: =SUMIFS('Combined P&L'!T:T,'Combined P&L'!$C:$C,'P&L Forecast'!$B51) -> 2.01331 | W51: =SUMIFS('Combined P&L'!U:U,'Combined P&L'!$C:$C,'P&L Forecast'!$B51) -> 1.6009 | X51: =SUMIFS('Combined P&L'!V:V,'Combined P&L'!$C:$C,'P&L Forecast'!$B51) -> 1.58969 | Y51: =SUMIFS('Combined P&L'!W:W,'Combined P&L'!$C:$C,'P&L Forecast'!$B51) -> 1.12582 | Z51: =SUMIFS('Combined P&L'!X:X,'Combined P&L'!$C:$C,'P&L Forecast'!$B51) -> 1.44199 | AA51: =SUMIFS('Combined P&L'!Y:Y,'Combined P&L'!$C:$C,'P&L Forecast'!$B51) -> 1.28772 | AB51: =SUMIFS('Combined P&L'!Z:Z,'Combined P&L'!$C:$C,'P&L Forecast'!$B51) -> 2.41295 | AC51: =SUMIFS('Combined P&L'!AA:AA,'Combined P&L'!$C:$C,'P&L Forecast'!$B51) -> 22.3793 | AD51: =SUMIFS('Combined P&L'!AB:AB,'Combined P&L'!$C:$C,'P&L Forecast'!$B51) -> 0.72983 | AE51: =SUMIFS('Combined P&L'!AC:AC,'Combined P&L'!$C:$C,'P&L Forecast'!$B51) -> 0.59597 | AF51: =SUMIFS('Combined P&L'!AD:AD,'Combined P&L'!$C:$C,'P&L Forecast'!$B51) -> 0.87534 | AG51: =SUMIFS('Combined P&L'!AE:AE,'Combined P&L'!$C:$C,'P&L Forecast'!$B51) -> 0.52967 | AH51: =SUMIFS('Combined P&L'!AF:AF,'Combined P&L'!$C:$C,'P&L Forecast'!$B51) -> 0.77688 | AI51: =SUMIFS('Combined P&L'!AG:AG,'Combined P&L'!$C:$C,'P&L Forecast'!$B51) -> 0.21671 | AJ51: =SUMIFS('Combined P&L'!AH:AH,'Combined P&L'!$C:$C,'P&L Forecast'!$B51) -> 0.74952 | AK51: =SUMIFS('Combined P&L'!AI:AI,'Combined P&L'!$C:$C,'P&L Forecast'!$B51) -> 0.92573 | AL51: =SUMIFS('Combined P&L'!AJ:AJ,'Combined P&L'!$C:$C,'P&L Forecast'!$B51) -> 0.66044 | AM51: =SUMIFS('Combined P&L'!AK:AK,'Combined P&L'!$C:$C,'P&L Forecast'!$B51) -> 0.75176 | AN51: =SUMIFS('Combined P&L'!AL:AL,'Combined P&L'!$C:$C,'P&L Forecast'!$B51) -> 0.8203 | AO51: =SUMIFS('Combined P&L'!AM:AM,'Combined P&L'!$C:$C,'P&L Forecast'!$B51) -> 0.68046 | AP51: =SUMIFS('Combined P&L'!AN:AN,'Combined P&L'!$C:$C,'P&L Forecast'!$B51) -> 0.77239 | AQ51: =SUMIFS('Combined P&L'!AO:AO,'Combined P&L'!$C:$C,'P&L Forecast'!$B51) -> 0.71608 | AR51: =SUMIFS('Combined P&L'!AP:AP,'Combined P&L'!$C:$C,'P&L Forecast'!$B51) -> 0.6402 | AS51: =SUMIFS('Combined P&L'!AQ:AQ,'Combined P&L'!$C:$C,'P&L Forecast'!$B51) -> 1.13538 | AT51: =SUMIFS('Combined P&L'!AR:AR,'Combined P&L'!$C:$C,'P&L Forecast'!$B51) -> 0.79979
B52: Amortization | C52: =SUMIFS($P52:$AT52,$P$5:$AT$5,">"&C$168,$P$5:$AT$5,"<"&C$169) -> 6.673 | D52: =SUMIFS($P52:$AT52,$P$5:$AT$5,">"&D$168,$P$5:$AT$5,"<"&D$169) -> 6.673 | F52: =SUMIFS($P52:$AT52,$P$5:$AT$5,">"&F$168,$P$5:$AT$5,"<"&F$169) -> 0 | G52: =SUMIFS($P52:$AT52,$P$5:$AT$5,">"&G$168,$P$5:$AT$5,"<"&G$169) -> 0 | I52: =SUMIFS($P52:$AT52,$P$5:$AT$5,">"&I$168,$P$5:$AT$5,"<"&I$169) -> 6.673 | J52: =SUMIFS($P52:$AT52,$P$5:$AT$5,">"&J$168,$P$5:$AT$5,"<"&J$169) -> 6.673 | K52: =+C151 -> 6.673 | M52: =K52-J52 -> 0 | N52: =IFERROR(K52/J52-1,0) -> 0 | P52: =SUMIFS('Combined P&L'!N:N,'Combined P&L'!$C:$C,'P&L Forecast'!$B52) -> 0 | Q52: =SUMIFS('Combined P&L'!O:O,'Combined P&L'!$C:$C,'P&L Forecast'!$B52) -> 0 | R52: =SUMIFS('Combined P&L'!P:P,'Combined P&L'!$C:$C,'P&L Forecast'!$B52) -> 0 | S52: =SUMIFS('Combined P&L'!Q:Q,'Combined P&L'!$C:$C,'P&L Forecast'!$B52) -> 0 | T52: =SUMIFS('Combined P&L'!R:R,'Combined P&L'!$C:$C,'P&L Forecast'!$B52) -> 0 | U52: =SUMIFS('Combined P&L'!S:S,'Combined P&L'!$C:$C,'P&L Forecast'!$B52) -> 0 | V52: =SUMIFS('Combined P&L'!T:T,'Combined P&L'!$C:$C,'P&L Forecast'!$B52) -> 0 | W52: =SUMIFS('Combined P&L'!U:U,'Combined P&L'!$C:$C,'P&L Forecast'!$B52) -> 0 | X52: =SUMIFS('Combined P&L'!V:V,'Combined P&L'!$C:$C,'P&L Forecast'!$B52) -> 0 | Y52: =SUMIFS('Combined P&L'!W:W,'Combined P&L'!$C:$C,'P&L Forecast'!$B52) -> 0 | Z52: =SUMIFS('Combined P&L'!X:X,'Combined P&L'!$C:$C,'P&L Forecast'!$B52) -> 0 | AA52: =SUMIFS('Combined P&L'!Y:Y,'Combined P&L'!$C:$C,'P&L Forecast'!$B52) -> 6.673 | AB52: =SUMIFS('Combined P&L'!Z:Z,'Combined P&L'!$C:$C,'P&L Forecast'!$B52) -> 0 | AC52: =SUMIFS('Combined P&L'!AA:AA,'Combined P&L'!$C:$C,'P&L Forecast'!$B52) -> 0 | AD52: =SUMIFS('Combined P&L'!AB:AB,'Combined P&L'!$C:$C,'P&L Forecast'!$B52) -> 0 | AE52: =SUMIFS('Combined P&L'!AC:AC,'Combined P&L'!$C:$C,'P&L Forecast'!$B52) -> 0 | AF52: =SUMIFS('Combined P&L'!AD:AD,'Combined P&L'!$C:$C,'P&L Forecast'!$B52) -> 0 | AG52: =SUMIFS('Combined P&L'!AE:AE,'Combined P&L'!$C:$C,'P&L Forecast'!$B52) -> 0 | AH52: =SUMIFS('Combined P&L'!AF:AF,'Combined P&L'!$C:$C,'P&L Forecast'!$B52) -> 0 | AI52: =SUMIFS('Combined P&L'!AG:AG,'Combined P&L'!$C:$C,'P&L Forecast'!$B52) -> 0 | AJ52: =SUMIFS('Combined P&L'!AH:AH,'Combined P&L'!$C:$C,'P&L Forecast'!$B52) -> 0 | AK52: =SUMIFS('Combined P&L'!AI:AI,'Combined P&L'!$C:$C,'P&L Forecast'!$B52) -> 0 | AL52: =SUMIFS('Combined P&L'!AJ:AJ,'Combined P&L'!$C:$C,'P&L Forecast'!$B52) -> 0 | AM52: =SUMIFS('Combined P&L'!AK:AK,'Combined P&L'!$C:$C,'P&L Forecast'!$B52) -> 6.673 | AN52: =SUMIFS('Combined P&L'!AL:AL,'Combined P&L'!$C:$C,'P&L Forecast'!$B52) -> 0 | AO52: =SUMIFS('Combined P&L'!AM:AM,'Combined P&L'!$C:$C,'P&L Forecast'!$B52) -> 0 | AP52: =SUMIFS('Combined P&L'!AN:AN,'Combined P&L'!$C:$C,'P&L Forecast'!$B52) -> 0 | AQ52: =SUMIFS('Combined P&L'!AO:AO,'Combined P&L'!$C:$C,'P&L Forecast'!$B52) -> 0 | AR52: =SUMIFS('Combined P&L'!AP:AP,'Combined P&L'!$C:$C,'P&L Forecast'!$B52) -> 0 | AS52: =SUMIFS('Combined P&L'!AQ:AQ,'Combined P&L'!$C:$C,'P&L Forecast'!$B52) -> 0 | AT52: =SUMIFS('Combined P&L'!AR:AR,'Combined P&L'!$C:$C,'P&L Forecast'!$B52) -> 0
B53: Website | C53: =SUMIFS($P53:$AT53,$P$5:$AT$5,">"&C$168,$P$5:$AT$5,"<"&C$169) -> 7.26173 | D53: =SUMIFS($P53:$AT53,$P$5:$AT$5,">"&D$168,$P$5:$AT$5,"<"&D$169) -> 4.91967 | F53: =SUMIFS($P53:$AT53,$P$5:$AT$5,">"&F$168,$P$5:$AT$5,"<"&F$169) -> 2.92467 | G53: =SUMIFS($P53:$AT53,$P$5:$AT$5,">"&G$168,$P$5:$AT$5,"<"&G$169) -> 2.90857 | I53: =SUMIFS($P53:$AT53,$P$5:$AT$5,">"&I$168,$P$5:$AT$5,"<"&I$169) -> 5.74187 | J53: =SUMIFS($P53:$AT53,$P$5:$AT$5,">"&J$168,$P$5:$AT$5,"<"&J$169) -> 4.90357 | K53: =+C152 -> 4.90357 | M53: =K53-J53 -> 0 | N53: =IFERROR(K53/J53-1,0) -> 0 | P53: =SUMIFS('Combined P&L'!N:N,'Combined P&L'!$C:$C,'P&L Forecast'!$B53) -> 0.43326 | Q53: =SUMIFS('Combined P&L'!O:O,'Combined P&L'!$C:$C,'P&L Forecast'!$B53) -> 1.63176 | R53: =SUMIFS('Combined P&L'!P:P,'Combined P&L'!$C:$C,'P&L Forecast'!$B53) -> 0.43368 | S53: =SUMIFS('Combined P&L'!Q:Q,'Combined P&L'!$C:$C,'P&L Forecast'!$B53) -> 0.48413 | T53: =SUMIFS('Combined P&L'!R:R,'Combined P&L'!$C:$C,'P&L Forecast'!$B53) -> 0.48413 | U53: =SUMIFS('Combined P&L'!S:S,'Combined P&L'!$C:$C,'P&L Forecast'!$B53) -> 0.48413 | V53: =SUMIFS('Combined P&L'!T:T,'Combined P&L'!$C:$C,'P&L Forecast'!$B53) -> 0.49344 | W53: =SUMIFS('Combined P&L'!U:U,'Combined P&L'!$C:$C,'P&L Forecast'!$B53) -> 0.84344 | X53: =SUMIFS('Combined P&L'!V:V,'Combined P&L'!$C:$C,'P&L Forecast'!$B53) -> 0.49344 | Y53: =SUMIFS('Combined P&L'!W:W,'Combined P&L'!$C:$C,'P&L Forecast'!$B53) -> 0.49344 | Z53: =SUMIFS('Combined P&L'!X:X,'Combined P&L'!$C:$C,'P&L Forecast'!$B53) -> 0.49344 | AA53: =SUMIFS('Combined P&L'!Y:Y,'Combined P&L'!$C:$C,'P&L Forecast'!$B53) -> 0.49344 | AB53: =SUMIFS('Combined P&L'!Z:Z,'Combined P&L'!$C:$C,'P&L Forecast'!$B53) -> 0.53067 | AC53: =SUMIFS('Combined P&L'!AA:AA,'Combined P&L'!$C:$C,'P&L Forecast'!$B53) -> 0.399 | AD53: =SUMIFS('Combined P&L'!AB:AB,'Combined P&L'!$C:$C,'P&L Forecast'!$B53) -> 0.399 | AE53: =SUMIFS('Combined P&L'!AC:AC,'Combined P&L'!$C:$C,'P&L Forecast'!$B53) -> 0.399 | AF53: =SUMIFS('Combined P&L'!AD:AD,'Combined P&L'!$C:$C,'P&L Forecast'!$B53) -> 0.399 | AG53: =SUMIFS('Combined P&L'!AE:AE,'Combined P&L'!$C:$C,'P&L Forecast'!$B53) -> 0.399 | AH53: =SUMIFS('Combined P&L'!AF:AF,'Combined P&L'!$C:$C,'P&L Forecast'!$B53) -> 0.399 | AI53: =SUMIFS('Combined P&L'!AG:AG,'Combined P&L'!$C:$C,'P&L Forecast'!$B53) -> 0.399 | AJ53: =SUMIFS('Combined P&L'!AH:AH,'Combined P&L'!$C:$C,'P&L Forecast'!$B53) -> 0.399 | AK53: =SUMIFS('Combined P&L'!AI:AI,'Combined P&L'!$C:$C,'P&L Forecast'!$B53) -> 0.399 | AL53: =SUMIFS('Combined P&L'!AJ:AJ,'Combined P&L'!$C:$C,'P&L Forecast'!$B53) -> 0.399 | AM53: =SUMIFS('Combined P&L'!AK:AK,'Combined P&L'!$C:$C,'P&L Forecast'!$B53) -> 0.399 | AN53: =SUMIFS('Combined P&L'!AL:AL,'Combined P&L'!$C:$C,'P&L Forecast'!$B53) -> 0.43619 | AO53: =SUMIFS('Combined P&L'!AM:AM,'Combined P&L'!$C:$C,'P&L Forecast'!$B53) -> 0.399 | AP53: =SUMIFS('Combined P&L'!AN:AN,'Combined P&L'!$C:$C,'P&L Forecast'!$B53) -> 0.47738 | AQ53: =SUMIFS('Combined P&L'!AO:AO,'Combined P&L'!$C:$C,'P&L Forecast'!$B53) -> 0.399 | AR53: =SUMIFS('Combined P&L'!AP:AP,'Combined P&L'!$C:$C,'P&L Forecast'!$B53) -> 0.399 | AS53: =SUMIFS('Combined P&L'!AQ:AQ,'Combined P&L'!$C:$C,'P&L Forecast'!$B53) -> 0.399 | AT53: =SUMIFS('Combined P&L'!AR:AR,'Combined P&L'!$C:$C,'P&L Forecast'!$B53) -> 0.399
B54: State Taxes | C54: =SUMIFS($P54:$AT54,$P$5:$AT$5,">"&C$168,$P$5:$AT$5,"<"&C$169) -> 7.497 | D54: =SUMIFS($P54:$AT54,$P$5:$AT$5,">"&D$168,$P$5:$AT$5,"<"&D$169) -> 9.984 | F54: =SUMIFS($P54:$AT54,$P$5:$AT$5,">"&F$168,$P$5:$AT$5,"<"&F$169) -> 5.894 | G54: =SUMIFS($P54:$AT54,$P$5:$AT$5,">"&G$168,$P$5:$AT$5,"<"&G$169) -> 1.172 | I54: =SUMIFS($P54:$AT54,$P$5:$AT$5,">"&I$168,$P$5:$AT$5,"<"&I$169) -> 4.673 | J54: =SUMIFS($P54:$AT54,$P$5:$AT$5,">"&J$168,$P$5:$AT$5,"<"&J$169) -> 5.262 | K54: =+C153 -> 5.262 | M54: =K54-J54 -> 0 | N54: =IFERROR(K54/J54-1,0) -> 0 | P54: =SUMIFS('Combined P&L'!N:N,'Combined P&L'!$C:$C,'P&L Forecast'!$B54) -> 0 | Q54: =SUMIFS('Combined P&L'!O:O,'Combined P&L'!$C:$C,'P&L Forecast'!$B54) -> 0 | R54: =SUMIFS('Combined P&L'!P:P,'Combined P&L'!$C:$C,'P&L Forecast'!$B54) -> 0 | S54: =SUMIFS('Combined P&L'!Q:Q,'Combined P&L'!$C:$C,'P&L Forecast'!$B54) -> 6.246 | T54: =SUMIFS('Combined P&L'!R:R,'Combined P&L'!$C:$C,'P&L Forecast'!$B54) -> 0 | U54: =SUMIFS('Combined P&L'!S:S,'Combined P&L'!$C:$C,'P&L Forecast'!$B54) -> 2.472 | V54: =SUMIFS('Combined P&L'!T:T,'Combined P&L'!$C:$C,'P&L Forecast'!$B54) -> 0 | W54: =SUMIFS('Combined P&L'!U:U,'Combined P&L'!$C:$C,'P&L Forecast'!$B54) -> 0 | X54: =SUMIFS('Combined P&L'!V:V,'Combined P&L'!$C:$C,'P&L Forecast'!$B54) -> 2.472 | Y54: =SUMIFS('Combined P&L'!W:W,'Combined P&L'!$C:$C,'P&L Forecast'!$B54) -> 0 | Z54: =SUMIFS('Combined P&L'!X:X,'Combined P&L'!$C:$C,'P&L Forecast'!$B54) -> 0 | AA54: =SUMIFS('Combined P&L'!Y:Y,'Combined P&L'!$C:$C,'P&L Forecast'!$B54) -> -3.693 | AB54: =SUMIFS('Combined P&L'!Z:Z,'Combined P&L'!$C:$C,'P&L Forecast'!$B54) -> 2.472 | AC54: =SUMIFS('Combined P&L'!AA:AA,'Combined P&L'!$C:$C,'P&L Forecast'!$B54) -> 0 | AD54: =SUMIFS('Combined P&L'!AB:AB,'Combined P&L'!$C:$C,'P&L Forecast'!$B54) -> 0 | AE54: =SUMIFS('Combined P&L'!AC:AC,'Combined P&L'!$C:$C,'P&L Forecast'!$B54) -> 3.649 | AF54: =SUMIFS('Combined P&L'!AD:AD,'Combined P&L'!$C:$C,'P&L Forecast'!$B54) -> -2.272 | AG54: =SUMIFS('Combined P&L'!AE:AE,'Combined P&L'!$C:$C,'P&L Forecast'!$B54) -> 2.045 | AH54: =SUMIFS('Combined P&L'!AF:AF,'Combined P&L'!$C:$C,'P&L Forecast'!$B54) -> 0 | AI54: =SUMIFS('Combined P&L'!AG:AG,'Combined P&L'!$C:$C,'P&L Forecast'!$B54) -> 0 | AJ54: =SUMIFS('Combined P&L'!AH:AH,'Combined P&L'!$C:$C,'P&L Forecast'!$B54) -> 2.045 | AK54: =SUMIFS('Combined P&L'!AI:AI,'Combined P&L'!$C:$C,'P&L Forecast'!$B54) -> 0 | AL54: =SUMIFS('Combined P&L'!AJ:AJ,'Combined P&L'!$C:$C,'P&L Forecast'!$B54) -> 0 | AM54: =SUMIFS('Combined P&L'!AK:AK,'Combined P&L'!$C:$C,'P&L Forecast'!$B54) -> 2.045 | AN54: =SUMIFS('Combined P&L'!AL:AL,'Combined P&L'!$C:$C,'P&L Forecast'!$B54) -> 0 | AO54: =SUMIFS('Combined P&L'!AM:AM,'Combined P&L'!$C:$C,'P&L Forecast'!$B54) -> 0 | AP54: =SUMIFS('Combined P&L'!AN:AN,'Combined P&L'!$C:$C,'P&L Forecast'!$B54) -> 5.036 | AQ54: =SUMIFS('Combined P&L'!AO:AO,'Combined P&L'!$C:$C,'P&L Forecast'!$B54) -> -4.864 | AR54: =SUMIFS('Combined P&L'!AP:AP,'Combined P&L'!$C:$C,'P&L Forecast'!$B54) -> 0 | AS54: =SUMIFS('Combined P&L'!AQ:AQ,'Combined P&L'!$C:$C,'P&L Forecast'!$B54) -> 1 | AT54: =SUMIFS('Combined P&L'!AR:AR,'Combined P&L'!$C:$C,'P&L Forecast'!$B54) -> 0
B55: Insurance | C55: =SUMIFS($P55:$AT55,$P$5:$AT$5,">"&C$168,$P$5:$AT$5,"<"&C$169) -> 2.08994 | D55: =SUMIFS($P55:$AT55,$P$5:$AT$5,">"&D$168,$P$5:$AT$5,"<"&D$169) -> 2.61982 | F55: =SUMIFS($P55:$AT55,$P$5:$AT$5,">"&F$168,$P$5:$AT$5,"<"&F$169) -> 1.44049 | G55: =SUMIFS($P55:$AT55,$P$5:$AT$5,">"&G$168,$P$5:$AT$5,"<"&G$169) -> 3.70971 | I55: =SUMIFS($P55:$AT55,$P$5:$AT$5,">"&I$168,$P$5:$AT$5,"<"&I$169) -> 2.33371 | J55: =SUMIFS($P55:$AT55,$P$5:$AT$5,">"&J$168,$P$5:$AT$5,"<"&J$169) -> 4.88904 | K55: =+C154 -> 4.88904 | M55: =K55-J55 -> 0 | N55: =IFERROR(K55/J55-1,0) -> 0 | P55: =SUMIFS('Combined P&L'!N:N,'Combined P&L'!$C:$C,'P&L Forecast'!$B55) -> 0.14747 | Q55: =SUMIFS('Combined P&L'!O:O,'Combined P&L'!$C:$C,'P&L Forecast'!$B55) -> 0.14747 | R55: =SUMIFS('Combined P&L'!P:P,'Combined P&L'!$C:$C,'P&L Forecast'!$B55) -> 0.17755 | S55: =SUMIFS('Combined P&L'!Q:Q,'Combined P&L'!$C:$C,'P&L Forecast'!$B55) -> 0.19167 | T55: =SUMIFS('Combined P&L'!R:R,'Combined P&L'!$C:$C,'P&L Forecast'!$B55) -> 0.18014 | U55: =SUMIFS('Combined P&L'!S:S,'Combined P&L'!$C:$C,'P&L Forecast'!$B55) -> 0.17622 | V55: =SUMIFS('Combined P&L'!T:T,'Combined P&L'!$C:$C,'P&L Forecast'!$B55) -> 0.1762 | W55: =SUMIFS('Combined P&L'!U:U,'Combined P&L'!$C:$C,'P&L Forecast'!$B55) -> 0.17622 | X55: =SUMIFS('Combined P&L'!V:V,'Combined P&L'!$C:$C,'P&L Forecast'!$B55) -> 0.18712 | Y55: =SUMIFS('Combined P&L'!W:W,'Combined P&L'!$C:$C,'P&L Forecast'!$B55) -> 0.17744 | Z55: =SUMIFS('Combined P&L'!X:X,'Combined P&L'!$C:$C,'P&L Forecast'!$B55) -> 0.17622 | AA55: =SUMIFS('Combined P&L'!Y:Y,'Combined P&L'!$C:$C,'P&L Forecast'!$B55) -> 0.17622 | AB55: =SUMIFS('Combined P&L'!Z:Z,'Combined P&L'!$C:$C,'P&L Forecast'!$B55) -> 0.17678 | AC55: =SUMIFS('Combined P&L'!AA:AA,'Combined P&L'!$C:$C,'P&L Forecast'!$B55) -> 0.20899 | AD55: =SUMIFS('Combined P&L'!AB:AB,'Combined P&L'!$C:$C,'P&L Forecast'!$B55) -> 0.1896 | AE55: =SUMIFS('Combined P&L'!AC:AC,'Combined P&L'!$C:$C,'P&L Forecast'!$B55) -> 0.1759 | AF55: =SUMIFS('Combined P&L'!AD:AD,'Combined P&L'!$C:$C,'P&L Forecast'!$B55) -> 0.2357 | AG55: =SUMIFS('Combined P&L'!AE:AE,'Combined P&L'!$C:$C,'P&L Forecast'!$B55) -> 0.22676 | AH55: =SUMIFS('Combined P&L'!AF:AF,'Combined P&L'!$C:$C,'P&L Forecast'!$B55) -> 0.22676 | AI55: =SUMIFS('Combined P&L'!AG:AG,'Combined P&L'!$C:$C,'P&L Forecast'!$B55) -> 0.22676 | AJ55: =SUMIFS('Combined P&L'!AH:AH,'Combined P&L'!$C:$C,'P&L Forecast'!$B55) -> 0.24325 | AK55: =SUMIFS('Combined P&L'!AI:AI,'Combined P&L'!$C:$C,'P&L Forecast'!$B55) -> 0.24228 | AL55: =SUMIFS('Combined P&L'!AJ:AJ,'Combined P&L'!$C:$C,'P&L Forecast'!$B55) -> 0.23352 | AM55: =SUMIFS('Combined P&L'!AK:AK,'Combined P&L'!$C:$C,'P&L Forecast'!$B55) -> 0.23352 | AN55: =SUMIFS('Combined P&L'!AL:AL,'Combined P&L'!$C:$C,'P&L Forecast'!$B55) -> 0.22943 | AO55: =SUMIFS('Combined P&L'!AM:AM,'Combined P&L'!$C:$C,'P&L Forecast'!$B55) -> 2.22858 | AP55: =SUMIFS('Combined P&L'!AN:AN,'Combined P&L'!$C:$C,'P&L Forecast'!$B55) -> 0.25448 | AQ55: =SUMIFS('Combined P&L'!AO:AO,'Combined P&L'!$C:$C,'P&L Forecast'!$B55) -> 0.25564 | AR55: =SUMIFS('Combined P&L'!AP:AP,'Combined P&L'!$C:$C,'P&L Forecast'!$B55) -> 0.26164 | AS55: =SUMIFS('Combined P&L'!AQ:AQ,'Combined P&L'!$C:$C,'P&L Forecast'!$B55) -> 0.26183 | AT55: =SUMIFS('Combined P&L'!AR:AR,'Combined P&L'!$C:$C,'P&L Forecast'!$B55) -> 0.21811
... B57: Utilities | C57: =SUMIFS($P57:$AT57,$P$5:$AT$5,">"&C$168,$P$5:$AT$5,"<"&C$169) -> 1.05983 | D57: =SUMIFS($P57:$AT57,$P$5:$AT$5,">"&D$168,$P$5:$AT$5,"<"&D$169) -> 3.29133 | F57: =SUMIFS($P57:$AT57,$P$5:$AT$5,">"&F$168,$P$5:$AT$5,"<"&F$169) -> 2.02633 | G57: =SUMIFS($P57:$AT57,$P$5:$AT$5,">"&G$168,$P$5:$AT$5,"<"&G$169) -> 1.943 | I57: =SUMIFS($P57:$AT57,$P$5:$AT$5,">"&I$168,$P$5:$AT$5,"<"&I$169) -> 2.45133 | J57: =SUMIFS($P57:$AT57,$P$5:$AT$5,">"&J$168,$P$5:$AT$5,"<"&J$169) -> 3.208 | K57: =+C156 -> 3.208 | M57: =K57-J57 -> 0 | N57: =IFERROR(K57/J57-1,0) -> 0 | P57: =SUMIFS('Combined P&L'!N:N,'Combined P&L'!$C:$C,'P&L Forecast'!$B57) -> 0.085 | Q57: =SUMIFS('Combined P&L'!O:O,'Combined P&L'!$C:$C,'P&L Forecast'!$B57) -> 0.085 | R57: =SUMIFS('Combined P&L'!P:P,'Combined P&L'!$C:$C,'P&L Forecast'!$B57) -> 0.097 | S57: =SUMIFS('Combined P&L'!Q:Q,'Combined P&L'!$C:$C,'P&L Forecast'!$B57) -> 0.11283 | T57: =SUMIFS('Combined P&L'!R:R,'Combined P&L'!$C:$C,'P&L Forecast'!$B57) -> 0.085 | U57: =SUMIFS('Combined P&L'!S:S,'Combined P&L'!$C:$C,'P&L Forecast'!$B57) -> 0.085 | V57: =SUMIFS('Combined P&L'!T:T,'Combined P&L'!$C:$C,'P&L Forecast'!$B57) -> 0.085 | W57: =SUMIFS('Combined P&L'!U:U,'Combined P&L'!$C:$C,'P&L Forecast'!$B57) -> 0.085 | X57: =SUMIFS('Combined P&L'!V:V,'Combined P&L'!$C:$C,'P&L Forecast'!$B57) -> 0.085 | Y57: =SUMIFS('Combined P&L'!W:W,'Combined P&L'!$C:$C,'P&L Forecast'!$B57) -> 0.085 | Z57: =SUMIFS('Combined P&L'!X:X,'Combined P&L'!$C:$C,'P&L Forecast'!$B57) -> 0.085 | AA57: =SUMIFS('Combined P&L'!Y:Y,'Combined P&L'!$C:$C,'P&L Forecast'!$B57) -> 0.085 | AB57: =SUMIFS('Combined P&L'!Z:Z,'Combined P&L'!$C:$C,'P&L Forecast'!$B57) -> 0.085 | AC57: =SUMIFS('Combined P&L'!AA:AA,'Combined P&L'!$C:$C,'P&L Forecast'!$B57) -> 0.09449 | AD57: =SUMIFS('Combined P&L'!AB:AB,'Combined P&L'!$C:$C,'P&L Forecast'!$B57) -> 0.82489 | AE57: =SUMIFS('Combined P&L'!AC:AC,'Combined P&L'!$C:$C,'P&L Forecast'!$B57) -> 0.253 | AF57: =SUMIFS('Combined P&L'!AD:AD,'Combined P&L'!$C:$C,'P&L Forecast'!$B57) -> 0.26295 | AG57: =SUMIFS('Combined P&L'!AE:AE,'Combined P&L'!$C:$C,'P&L Forecast'!$B57) -> 0.253 | AH57: =SUMIFS('Combined P&L'!AF:AF,'Combined P&L'!$C:$C,'P&L Forecast'!$B57) -> 0.253 | AI57: =SUMIFS('Combined P&L'!AG:AG,'Combined P&L'!$C:$C,'P&L Forecast'!$B57) -> 0.253 | AJ57: =SUMIFS('Combined P&L'!AH:AH,'Combined P&L'!$C:$C,'P&L Forecast'!$B57) -> 0.253 | AK57: =SUMIFS('Combined P&L'!AI:AI,'Combined P&L'!$C:$C,'P&L Forecast'!$B57) -> 0.253 | AL57: =SUMIFS('Combined P&L'!AJ:AJ,'Combined P&L'!$C:$C,'P&L Forecast'!$B57) -> 0.253 | AM57: =SUMIFS('Combined P&L'!AK:AK,'Combined P&L'!$C:$C,'P&L Forecast'!$B57) -> 0.253 | AN57: =SUMIFS('Combined P&L'!AL:AL,'Combined P&L'!$C:$C,'P&L Forecast'!$B57) -> 0.253 | AO57: =SUMIFS('Combined P&L'!AM:AM,'Combined P&L'!$C:$C,'P&L Forecast'!$B57) -> 0.255 | AP57: =SUMIFS('Combined P&L'!AN:AN,'Combined P&L'!$C:$C,'P&L Forecast'!$B57) -> 0.283 | AQ57: =SUMIFS('Combined P&L'!AO:AO,'Combined P&L'!$C:$C,'P&L Forecast'!$B57) -> 0.283 | AR57: =SUMIFS('Combined P&L'!AP:AP,'Combined P&L'!$C:$C,'P&L Forecast'!$B57) -> 0.283 | AS57: =SUMIFS('Combined P&L'!AQ:AQ,'Combined P&L'!$C:$C,'P&L Forecast'!$B57) -> 0.293 | AT57: =SUMIFS('Combined P&L'!AR:AR,'Combined P&L'!$C:$C,'P&L Forecast'!$B57) -> 0.293
B58: Interest | C58: =SUMIFS($P58:$AT58,$P$5:$AT$5,">"&C$168,$P$5:$AT$5,"<"&C$169) -> 0.07964 | D58: =SUMIFS($P58:$AT58,$P$5:$AT$5,">"&D$168,$P$5:$AT$5,"<"&D$169) -> 1.42248 | F58: =SUMIFS($P58:$AT58,$P$5:$AT$5,">"&F$168,$P$5:$AT$5,"<"&F$169) -> 1.07704 | G58: =SUMIFS($P58:$AT58,$P$5:$AT$5,">"&G$168,$P$5:$AT$5,"<"&G$169) -> 0.81103 | I58: =SUMIFS($P58:$AT58,$P$5:$AT$5,">"&I$168,$P$5:$AT$5,"<"&I$169) -> 1.15668 | J58: =SUMIFS($P58:$AT58,$P$5:$AT$5,">"&J$168,$P$5:$AT$5,"<"&J$169) -> 1.15647 | K58: =+C158 -> 1.15647 | M58: =K58-J58 -> 0 | N58: =IFERROR(K58/J58-1,0) -> 0 | P58: =SUMIFS('Combined P&L'!N:N,'Combined P&L'!$C:$C,'P&L Forecast'!$B58) -> 0 | Q58: =SUMIFS('Combined P&L'!O:O,'Combined P&L'!$C:$C,'P&L Forecast'!$B58) -> 0 | R58: =SUMIFS('Combined P&L'!P:P,'Combined P&L'!$C:$C,'P&L Forecast'!$B58) -> 0 | S58: =SUMIFS('Combined P&L'!Q:Q,'Combined P&L'!$C:$C,'P&L Forecast'!$B58) -> 0 | T58: =SUMIFS('Combined P&L'!R:R,'Combined P&L'!$C:$C,'P&L Forecast'!$B58) -> 0 | U58: =SUMIFS('Combined P&L'!S:S,'Combined P&L'!$C:$C,'P&L Forecast'!$B58) -> 0 | V58: =SUMIFS('Combined P&L'!T:T,'Combined P&L'!$C:$C,'P&L Forecast'!$B58) -> 0 | W58: =SUMIFS('Combined P&L'!U:U,'Combined P&L'!$C:$C,'P&L Forecast'!$B58) -> 0 | X58: =SUMIFS('Combined P&L'!V:V,'Combined P&L'!$C:$C,'P&L Forecast'!$B58) -> 0 | Y58: =SUMIFS('Combined P&L'!W:W,'Combined P&L'!$C:$C,'P&L Forecast'!$B58) -> 0 | Z58: =SUMIFS('Combined P&L'!X:X,'Combined P&L'!$C:$C,'P&L Forecast'!$B58) -> 0.0715 | AA58: =SUMIFS('Combined P&L'!Y:Y,'Combined P&L'!$C:$C,'P&L Forecast'!$B58) -> 0.00814 | AB58: =SUMIFS('Combined P&L'!Z:Z,'Combined P&L'!$C:$C,'P&L Forecast'!$B58) -> 0.11752 | AC58: =SUMIFS('Combined P&L'!AA:AA,'Combined P&L'!$C:$C,'P&L Forecast'!$B58) -> 0.20646 | AD58: =SUMIFS('Combined P&L'!AB:AB,'Combined P&L'!$C:$C,'P&L Forecast'!$B58) -> 0.01174 | AE58: =SUMIFS('Combined P&L'!AC:AC,'Combined P&L'!$C:$C,'P&L Forecast'!$B58) -> 0.0366 | AF58: =SUMIFS('Combined P&L'!AD:AD,'Combined P&L'!$C:$C,'P&L Forecast'!$B58) -> 0.11484 | AG58: =SUMIFS('Combined P&L'!AE:AE,'Combined P&L'!$C:$C,'P&L Forecast'!$B58) -> 0.24788 | AH58: =SUMIFS('Combined P&L'!AF:AF,'Combined P&L'!$C:$C,'P&L Forecast'!$B58) -> 0.342 | AI58: =SUMIFS('Combined P&L'!AG:AG,'Combined P&L'!$C:$C,'P&L Forecast'!$B58) -> 0.25109 | AJ58: =SUMIFS('Combined P&L'!AH:AH,'Combined P&L'!$C:$C,'P&L Forecast'!$B58) -> 0.06529 | AK58: =SUMIFS('Combined P&L'!AI:AI,'Combined P&L'!$C:$C,'P&L Forecast'!$B58) -> 0.01916 | AL58: =SUMIFS('Combined P&L'!AJ:AJ,'Combined P&L'!$C:$C,'P&L Forecast'!$B58) -> 0.0099 | AM58: =SUMIFS('Combined P&L'!AK:AK,'Combined P&L'!$C:$C,'P&L Forecast'!$B58) -> 0 | AN58: =SUMIFS('Combined P&L'!AL:AL,'Combined P&L'!$C:$C,'P&L Forecast'!$B58) -> 0.2887 | AO58: =SUMIFS('Combined P&L'!AM:AM,'Combined P&L'!$C:$C,'P&L Forecast'!$B58) -> 0.14453 | AP58: =SUMIFS('Combined P&L'!AN:AN,'Combined P&L'!$C:$C,'P&L Forecast'!$B58) -> 0 | AQ58: =SUMIFS('Combined P&L'!AO:AO,'Combined P&L'!$C:$C,'P&L Forecast'!$B58) -> 0.15 | AR58: =SUMIFS('Combined P&L'!AP:AP,'Combined P&L'!$C:$C,'P&L Forecast'!$B58) -> 0.11769 | AS58: =SUMIFS('Combined P&L'!AQ:AQ,'Combined P&L'!$C:$C,'P&L Forecast'!$B58) -> 0.11011 | AT58: =SUMIFS('Combined P&L'!AR:AR,'Combined P&L'!$C:$C,'P&L Forecast'!$B58) -> 0
B59: 1099 Filing Fees | C59: =SUMIFS($P59:$AT59,$P$5:$AT$5,">"&C$168,$P$5:$AT$5,"<"&C$169) -> 1.34593 | D59: =SUMIFS($P59:$AT59,$P$5:$AT$5,">"&D$168,$P$5:$AT$5,"<"&D$169) -> 2.49433 | F59: =SUMIFS($P59:$AT59,$P$5:$AT$5,">"&F$168,$P$5:$AT$5,"<"&F$169) -> 2.38088 | G59: =SUMIFS($P59:$AT59,$P$5:$AT$5,">"&G$168,$P$5:$AT$5,"<"&G$169) -> 3.20461 | I59: =SUMIFS($P59:$AT59,$P$5:$AT$5,">"&I$168,$P$5:$AT$5,"<"&I$169) -> 2.38282 | J59: =SUMIFS($P59:$AT59,$P$5:$AT$5,">"&J$168,$P$5:$AT$5,"<"&J$169) -> 3.31806 | K59: =+C157 -> 3.31806 | M59: =K59-J59 -> 0 | N59: =IFERROR(K59/J59-1,0) -> 0 | P59: =SUMIFS('Combined P&L'!N:N,'Combined P&L'!$C:$C,'P&L Forecast'!$B59) -> 1.29934 | Q59: =SUMIFS('Combined P&L'!O:O,'Combined P&L'!$C:$C,'P&L Forecast'!$B59) -> 0.03012 | R59: =SUMIFS('Combined P&L'!P:P,'Combined P&L'!$C:$C,'P&L Forecast'!$B59) -> 0.01063 | S59: =SUMIFS('Combined P&L'!Q:Q,'Combined P&L'!$C:$C,'P&L Forecast'!$B59) -> 0.00325 | T59: =SUMIFS('Combined P&L'!R:R,'Combined P&L'!$C:$C,'P&L Forecast'!$B59) -> 0.00065 | U59: =SUMIFS('Combined P&L'!S:S,'Combined P&L'!$C:$C,'P&L Forecast'!$B59) -> 0 | V59: =SUMIFS('Combined P&L'!T:T,'Combined P&L'!$C:$C,'P&L Forecast'!$B59) -> 0 | W59: =SUMIFS('Combined P&L'!U:U,'Combined P&L'!$C:$C,'P&L Forecast'!$B59) -> 0.00194 | X59: =SUMIFS('Combined P&L'!V:V,'Combined P&L'!$C:$C,'P&L Forecast'!$B59) -> 0 | Y59: =SUMIFS('Combined P&L'!W:W,'Combined P&L'!$C:$C,'P&L Forecast'!$B59) -> 0 | Z59: =SUMIFS('Combined P&L'!X:X,'Combined P&L'!$C:$C,'P&L Forecast'!$B59) -> 0 | AA59: =SUMIFS('Combined P&L'!Y:Y,'Combined P&L'!$C:$C,'P&L Forecast'!$B59) -> 0 | AB59: =SUMIFS('Combined P&L'!Z:Z,'Combined P&L'!$C:$C,'P&L Forecast'!$B59) -> 1.22655 | AC59: =SUMIFS('Combined P&L'!AA:AA,'Combined P&L'!$C:$C,'P&L Forecast'!$B59) -> 0 | AD59: =SUMIFS('Combined P&L'!AB:AB,'Combined P&L'!$C:$C,'P&L Forecast'!$B59) -> 1.15433 | AE59: =SUMIFS('Combined P&L'!AC:AC,'Combined P&L'!$C:$C,'P&L Forecast'!$B59) -> 0 | AF59: =SUMIFS('Combined P&L'!AD:AD,'Combined P&L'!$C:$C,'P&L Forecast'!$B59) -> 0 | AG59: =SUMIFS('Combined P&L'!AE:AE,'Combined P&L'!$C:$C,'P&L Forecast'!$B59) -> 0 | AH59: =SUMIFS('Combined P&L'!AF:AF,'Combined P&L'!$C:$C,'P&L Forecast'!$B59) -> 0 | AI59: =SUMIFS('Combined P&L'!AG:AG,'Combined P&L'!$C:$C,'P&L Forecast'!$B59) -> 0 | AJ59: =SUMIFS('Combined P&L'!AH:AH,'Combined P&L'!$C:$C,'P&L Forecast'!$B59) -> 0 | AK59: =SUMIFS('Combined P&L'!AI:AI,'Combined P&L'!$C:$C,'P&L Forecast'!$B59) -> 0.11345 | AL59: =SUMIFS('Combined P&L'!AJ:AJ,'Combined P&L'!$C:$C,'P&L Forecast'!$B59) -> 0 | AM59: =SUMIFS('Combined P&L'!AK:AK,'Combined P&L'!$C:$C,'P&L Forecast'!$B59) -> 0 | AN59: =SUMIFS('Combined P&L'!AL:AL,'Combined P&L'!$C:$C,'P&L Forecast'!$B59) -> 2.4948 | AO59: =SUMIFS('Combined P&L'!AM:AM,'Combined P&L'!$C:$C,'P&L Forecast'!$B59) -> 0 | AP59: =SUMIFS('Combined P&L'!AN:AN,'Combined P&L'!$C:$C,'P&L Forecast'!$B59) -> 0 | AQ59: =SUMIFS('Combined P&L'!AO:AO,'Combined P&L'!$C:$C,'P&L Forecast'!$B59) -> 0.70981 | AR59: =SUMIFS('Combined P&L'!AP:AP,'Combined P&L'!$C:$C,'P&L Forecast'!$B59) -> 0 | AS59: =SUMIFS('Combined P&L'!AQ:AQ,'Combined P&L'!$C:$C,'P&L Forecast'!$B59) -> 0 | AT59: =SUMIFS('Combined P&L'!AR:AR,'Combined P&L'!$C:$C,'P&L Forecast'!$B59) -> 0
B60: Other Income | C60: =SUMIFS($P60:$AT60,$P$5:$AT$5,">"&C$168,$P$5:$AT$5,"<"&C$169) -> -0.02736 | D60: =SUMIFS($P60:$AT60,$P$5:$AT$5,">"&D$168,$P$5:$AT$5,"<"&D$169) -> -0.21722 | F60: =SUMIFS($P60:$AT60,$P$5:$AT$5,">"&F$168,$P$5:$AT$5,"<"&F$169) -> -0.11733 | G60: =SUMIFS($P60:$AT60,$P$5:$AT$5,">"&G$168,$P$5:$AT$5,"<"&G$169) -> -0.15587 | I60: =SUMIFS($P60:$AT60,$P$5:$AT$5,">"&I$168,$P$5:$AT$5,"<"&I$169) -> -0.14469 | J60: =SUMIFS($P60:$AT60,$P$5:$AT$5,">"&J$168,$P$5:$AT$5,"<"&J$169) -> -0.25576 | K60: =+C159 -> -0.25576 | M60: =K60-J60 -> 0 | N60: =IFERROR(K60/J60-1,0) -> 0 | P60: =-SUMIFS('Combined P&L'!N:N,'Combined P&L'!$C:$C,'P&L Forecast'!$B60) -> 0 | Q60: =-SUMIFS('Combined P&L'!O:O,'Combined P&L'!$C:$C,'P&L Forecast'!$B60) -> 0 | R60: =-SUMIFS('Combined P&L'!P:P,'Combined P&L'!$C:$C,'P&L Forecast'!$B60) -> 0 | S60: =-SUMIFS('Combined P&L'!Q:Q,'Combined P&L'!$C:$C,'P&L Forecast'!$B60) -> 0 | T60: =-SUMIFS('Combined P&L'!R:R,'Combined P&L'!$C:$C,'P&L Forecast'!$B60) -> 0 | U60: =-SUMIFS('Combined P&L'!S:S,'Combined P&L'!$C:$C,'P&L Forecast'!$B60) -> 0 | V60: =-SUMIFS('Combined P&L'!T:T,'Combined P&L'!$C:$C,'P&L Forecast'!$B60) -> 0 | W60: =-SUMIFS('Combined P&L'!U:U,'Combined P&L'!$C:$C,'P&L Forecast'!$B60) -> 0 | X60: =-SUMIFS('Combined P&L'!V:V,'Combined P&L'!$C:$C,'P&L Forecast'!$B60) -> 0 | Y60: =-SUMIFS('Combined P&L'!W:W,'Combined P&L'!$C:$C,'P&L Forecast'!$B60) -> 0 | Z60: =-SUMIFS('Combined P&L'!X:X,'Combined P&L'!$C:$C,'P&L Forecast'!$B60) -> 0 | AA60: =-SUMIFS('Combined P&L'!Y:Y,'Combined P&L'!$C:$C,'P&L Forecast'!$B60) -> -0.02736 | AB60: =-SUMIFS('Combined P&L'!Z:Z,'Combined P&L'!$C:$C,'P&L Forecast'!$B60) -> 0 | AC60: =-SUMIFS('Combined P&L'!AA:AA,'Combined P&L'!$C:$C,'P&L Forecast'!$B60) -> -0.01993 | AD60: =-SUMIFS('Combined P&L'!AB:AB,'Combined P&L'!$C:$C,'P&L Forecast'!$B60) -> -0.01293 | AE60: =-SUMIFS('Combined P&L'!AC:AC,'Combined P&L'!$C:$C,'P&L Forecast'!$B60) -> -0.01963 | AF60: =-SUMIFS('Combined P&L'!AD:AD,'Combined P&L'!$C:$C,'P&L Forecast'!$B60) -> -0.02315 | AG60: =-SUMIFS('Combined P&L'!AE:AE,'Combined P&L'!$C:$C,'P&L Forecast'!$B60) -> -0.00962 | AH60: =-SUMIFS('Combined P&L'!AF:AF,'Combined P&L'!$C:$C,'P&L Forecast'!$B60) -> -0.03207 | AI60: =-SUMIFS('Combined P&L'!AG:AG,'Combined P&L'!$C:$C,'P&L Forecast'!$B60) -> -0.01634 | AJ60: =-SUMIFS('Combined P&L'!AH:AH,'Combined P&L'!$C:$C,'P&L Forecast'!$B60) -> -0.01584 | AK60: =-SUMIFS('Combined P&L'!AI:AI,'Combined P&L'!$C:$C,'P&L Forecast'!$B60) -> -0.02396 | AL60: =-SUMIFS('Combined P&L'!AJ:AJ,'Combined P&L'!$C:$C,'P&L Forecast'!$B60) -> -0.02513 | AM60: =-SUMIFS('Combined P&L'!AK:AK,'Combined P&L'!$C:$C,'P&L Forecast'!$B60) -> -0.01862 | AN60: =-SUMIFS('Combined P&L'!AL:AL,'Combined P&L'!$C:$C,'P&L Forecast'!$B60) -> -0.0103 | AO60: =-SUMIFS('Combined P&L'!AM:AM,'Combined P&L'!$C:$C,'P&L Forecast'!$B60) -> -0.0138 | AP60: =-SUMIFS('Combined P&L'!AN:AN,'Combined P&L'!$C:$C,'P&L Forecast'!$B60) -> -0.00925 | AQ60: =-SUMIFS('Combined P&L'!AO:AO,'Combined P&L'!$C:$C,'P&L Forecast'!$B60) -> -0.06181 | AR60: =-SUMIFS('Combined P&L'!AP:AP,'Combined P&L'!$C:$C,'P&L Forecast'!$B60) -> -0.03316 | AS60: =-SUMIFS('Combined P&L'!AQ:AQ,'Combined P&L'!$C:$C,'P&L Forecast'!$B60) -> -0.01614 | AT60: =-SUMIFS('Combined P&L'!AR:AR,'Combined P&L'!$C:$C,'P&L Forecast'!$B60) -> -0.01141
B61: Other Expenses | C61: =SUMIFS($P61:$AT61,$P$5:$AT$5,">"&C$168,$P$5:$AT$5,"<"&C$169) -> 15.89958 | D61: =SUMIFS($P61:$AT61,$P$5:$AT$5,">"&D$168,$P$5:$AT$5,"<"&D$169) -> 19.378 | F61: =SUMIFS($P61:$AT61,$P$5:$AT$5,">"&F$168,$P$5:$AT$5,"<"&F$169) -> 12.74039 | G61: =SUMIFS($P61:$AT61,$P$5:$AT$5,">"&G$168,$P$5:$AT$5,"<"&G$169) -> 11.77191 | I61: =SUMIFS($P61:$AT61,$P$5:$AT$5,">"&I$168,$P$5:$AT$5,"<"&I$169) -> 15.96214 | J61: =SUMIFS($P61:$AT61,$P$5:$AT$5,">"&J$168,$P$5:$AT$5,"<"&J$169) -> 18.40952 | K61: =+C160 -> 18.40952 | M61: =K61-J61 -> 0 | N61: =IFERROR(K61/J61-1,0) -> 0 | P61: =SUMIFS('Combined P&L'!N:N,'Combined P&L'!$C:$C,'P&L Forecast'!$B61) -> 1.19783 | Q61: =SUMIFS('Combined P&L'!O:O,'Combined P&L'!$C:$C,'P&L Forecast'!$B61) -> 1.34599 | R61: =SUMIFS('Combined P&L'!P:P,'Combined P&L'!$C:$C,'P&L Forecast'!$B61) -> 3.98375 | S61: =SUMIFS('Combined P&L'!Q:Q,'Combined P&L'!$C:$C,'P&L Forecast'!$B61) -> 4.06544 | T61: =SUMIFS('Combined P&L'!R:R,'Combined P&L'!$C:$C,'P&L Forecast'!$B61) -> 1.06699 | U61: =SUMIFS('Combined P&L'!S:S,'Combined P&L'!$C:$C,'P&L Forecast'!$B61) -> 1.0122 | V61: =SUMIFS('Combined P&L'!T:T,'Combined P&L'!$C:$C,'P&L Forecast'!$B61) -> 0.00563 | W61: =SUMIFS('Combined P&L'!U:U,'Combined P&L'!$C:$C,'P&L Forecast'!$B61) -> 0.171 | X61: =SUMIFS('Combined P&L'!V:V,'Combined P&L'!$C:$C,'P&L Forecast'!$B61) -> 1.1635 | Y61: =SUMIFS('Combined P&L'!W:W,'Combined P&L'!$C:$C,'P&L Forecast'!$B61) -> 0.52825 | Z61: =SUMIFS('Combined P&L'!X:X,'Combined P&L'!$C:$C,'P&L Forecast'!$B61) -> 0.20442 | AA61: =SUMIFS('Combined P&L'!Y:Y,'Combined P&L'!$C:$C,'P&L Forecast'!$B61) -> 1.15458 | AB61: =SUMIFS('Combined P&L'!Z:Z,'Combined P&L'!$C:$C,'P&L Forecast'!$B61) -> 0.61331 | AC61: =SUMIFS('Combined P&L'!AA:AA,'Combined P&L'!$C:$C,'P&L Forecast'!$B61) -> 0.63213 | AD61: =SUMIFS('Combined P&L'!AB:AB,'Combined P&L'!$C:$C,'P&L Forecast'!$B61) -> 5.38202 | AE61: =SUMIFS('Combined P&L'!AC:AC,'Combined P&L'!$C:$C,'P&L Forecast'!$B61) -> 4.32782 | AF61: =SUMIFS('Combined P&L'!AD:AD,'Combined P&L'!$C:$C,'P&L Forecast'!$B61) -> 0.93786 | AG61: =SUMIFS('Combined P&L'!AE:AE,'Combined P&L'!$C:$C,'P&L Forecast'!$B61) -> 0.33005 | AH61: =SUMIFS('Combined P&L'!AF:AF,'Combined P&L'!$C:$C,'P&L Forecast'!$B61) -> 0.5172 | AI61: =SUMIFS('Combined P&L'!AG:AG,'Combined P&L'!$C:$C,'P&L Forecast'!$B61) -> 0.67979 | AJ61: =SUMIFS('Combined P&L'!AH:AH,'Combined P&L'!$C:$C,'P&L Forecast'!$B61) -> 0.73355 | AK61: =SUMIFS('Combined P&L'!AI:AI,'Combined P&L'!$C:$C,'P&L Forecast'!$B61) -> 1.51913 | AL61: =SUMIFS('Combined P&L'!AJ:AJ,'Combined P&L'!$C:$C,'P&L Forecast'!$B61) -> 0.34955 | AM61: =SUMIFS('Combined P&L'!AK:AK,'Combined P&L'!$C:$C,'P&L Forecast'!$B61) -> 3.35559 | AN61: =SUMIFS('Combined P&L'!AL:AL,'Combined P&L'!$C:$C,'P&L Forecast'!$B61) -> 1.40831 | AO61: =SUMIFS('Combined P&L'!AM:AM,'Combined P&L'!$C:$C,'P&L Forecast'!$B61) -> 3.7293 | AP61: =SUMIFS('Combined P&L'!AN:AN,'Combined P&L'!$C:$C,'P&L Forecast'!$B61) -> 3.4082 | AQ61: =SUMIFS('Combined P&L'!AO:AO,'Combined P&L'!$C:$C,'P&L Forecast'!$B61) -> 0.67764 | AR61: =SUMIFS('Combined P&L'!AP:AP,'Combined P&L'!$C:$C,'P&L Forecast'!$B61) -> 0.9296 | AS61: =SUMIFS('Combined P&L'!AQ:AQ,'Combined P&L'!$C:$C,'P&L Forecast'!$B61) -> 0.64815 | AT61: =SUMIFS('Combined P&L'!AR:AR,'Combined P&L'!$C:$C,'P&L Forecast'!$B61) -> 0.97071
B62: Total Overhead | C62: =SUM(C44:C61) -> 113.9499 | D62: =SUM(D44:D61) -> 205.54162 | F62: =SUM(F44:F61) -> 121.59989 | G62: =SUM(G44:G61) -> 189.30079 | I62: =SUM(I44:I61) -> 167.44494 | J62: =SUM(J44:J61) -> 273.24252 | K62: =SUM(K44:K61) -> 280.66057 | M62: =SUM(M44:M61) -> 7.41805 | N62: =IFERROR(K62/J62-1,0) -> 0.027148227 | P62: =SUM(P44:P61) -> 6.34989 | Q62: =SUM(Q44:Q61) -> 9.33833 | R62: =SUM(R44:R61) -> 10.57256 | S62: =SUM(S44:S61) -> 17.24653 | T62: =SUM(T44:T61) -> 5.76501 | U62: =SUM(U44:U61) -> 12.7017 | V62: =SUM(V44:V61) -> 6.13083 | W62: =SUM(W44:W61) -> 6.34508 | ... AT62: =SUM(AT44:AT61) -> 39.88697
B64: Net Income | C64: =+C24-C36-C42-C62 -> 145.47185 | D64: =+D24-D36-D42-D62 -> 130.9803 | F64: =+F24-F36-F42-F62 -> 103.83598 | G64: =+G24-G36-G42-G62 -> 76.1435 | I64: =+I24-I36-I42-I62 -> 135.013 | J64: =+J24-J36-J42-J62 -> 103.28782 | K64: =+K24-K36-K42-K62 -> -25.16969 | M64: =M24-M36-M42-M62 -> -128.45751 | N64: =IFERROR(K64/J64-1,0) -> -1.243685 | P64: =+P24-P36-P42-P62 -> 32.29054 | Q64: =+Q24-Q36-Q42-Q62 -> 23.65557 | R64: =+R24-R36-R42-R62 -> 18.00904 | S64: =+S24-S36-S42-S62 -> 3.3037 | T64: =+T24-T36-T42-T62 -> 0.97158 | U64: =+U24-U36-U42-U62 -> 10.0273 | V64: =+V24-V36-V42-V62 -> 26.0371 | W64: =+W24-W36-W42-W62 -> 28.86382 | ... AT64: =+AT24-AT36-AT42-AT62 -> -16.19284
B65: % Margin | C65: =C64/C$24 -> 0.12817289 | D65: =D64/D$24 -> 0.06969324 | F65: =F64/F$24 -> 0.1040573 | G65: =G64/G$24 -> 0.045567046 | I65: =I64/I$24 -> 0.088567342 | J65: =J64/J$24 -> 0.04046486 | K65: =K64/K$24 -> -0.0084395748 | M65: 0 | N65: 0 | P65: =P64/P$24 -> 0.39907679 | Q65: =Q64/Q$24 -> 0.29112505 | R65: =R64/R$24 -> 0.23055349 | S65: =S64/S$24 -> 0.039634903 | T65: =T64/T$24 -> 0.010771857 | U65: =U64/U$24 -> 0.11151878 | V65: =V64/V$24 -> 0.24872555 | W65: =W64/W$24 -> 0.27722552 | ... AT65: =AT64/AT$24 -> -0.064404038
A67: x | B67: Tie Out | C67: =C64-'Combined P&L'!E114 -> 0 | D67: =D64-'Combined P&L'!F114 -> 0 | F67: =F64-'Combined P&L'!H114 -> -2.2737368e-13 | G67: =G64-'Combined P&L'!I114 -> 3.2684966e-13 | I67: =I64-'Combined P&L'!K114 -> 0 | J67: =J64-'Combined P&L'!L114 -> 0 | P67: =P64-'Combined P&L'!N114 -> 0 | Q67: =Q64-'Combined P&L'!O114 -> 0 | R67: =R64-'Combined P&L'!P114 -> 0 | S67: =S64-'Combined P&L'!Q114 -> -8.8817842e-15 | T67: =T64-'Combined P&L'!R114 -> 1.5987212e-14 | U67: =U64-'Combined P&L'!S114 -> 0 | V67: =V64-'Combined P&L'!T114 -> 0 | W67: =W64-'Combined P&L'!U114 -> 0 | ... AT67: =AT64-'Combined P&L'!AR114 -> 0
B69: EBITDA Bridge
B70: =+B64 -> Net Income | C70: =+C64 -> 145.47185 | D70: =+D64 -> 130.9803 | F70: =+F64 -> 103.83598 | G70: =+G64 -> 76.1435 | I70: =+I64 -> 135.013 | J70: =+J64 -> 103.28782 | K70: =+K64 -> -25.16969 | M70: =+M64 -> -128.45751 | N70: =IFERROR(K70/J70-1,0) -> -1.243685 | P70: =+P64 -> 32.29054 | Q70: =+Q64 -> 23.65557 | R70: =+R64 -> 18.00904 | S70: =+S64 -> 3.3037 | T70: =+T64 -> 0.97158 | U70: =+U64 -> 10.0273 | V70: =+V64 -> 26.0371 | W70: =+W64 -> 28.86382 | ... AT70: =+AT64 -> -16.19284
B71: (+) Amortization | C71: =+C52 -> 6.673 | D71: =+D52 -> 6.673 | F71: =+F52 -> 0 | G71: =+G52 -> 0 | I71: =+I52 -> 6.673 | J71: =+J52 -> 6.673 | K71: =+K52 -> 6.673 | M71: =K71-J71 -> 0 | N71: =IFERROR(K71/J71-1,0) -> 0 | P71: =+P52 -> 0 | Q71: =+Q52 -> 0 | R71: =+R52 -> 0 | S71: =+S52 -> 0 | T71: =+T52 -> 0 | U71: =+U52 -> 0 | V71: =+V52 -> 0 | W71: =+W52 -> 0 | ... AT71: =+AT52 -> 0
B72: (+) Taxes | C72: =+C54 -> 7.497 | D72: =+D54 -> 9.984 | F72: =+F54 -> 5.894 | G72: =+G54 -> 1.172 | I72: =+I54 -> 4.673 | J72: =+J54 -> 5.262 | K72: =+K54 -> 5.262 | M72: =K72-J72 -> 0 | N72: =IFERROR(K72/J72-1,0) -> 0 | P72: =+P54 -> 0 | Q72: =+Q54 -> 0 | R72: =+R54 -> 0 | S72: =+S54 -> 6.246 | T72: =+T54 -> 0 | U72: =+U54 -> 2.472 | V72: =+V54 -> 0 | W72: =+W54 -> 0 | ... AT72: =+AT54 -> 0
B73: (+) Interest | C73: =+C58 -> 0.07964 | D73: =+D58 -> 1.42248 | F73: =+F58 -> 1.07704 | G73: =+G58 -> 0.81103 | I73: =+I58 -> 1.15668 | J73: =+J58 -> 1.15647 | K73: =+K58 -> 1.15647 | M73: =K73-J73 -> 0 | N73: =IFERROR(K73/J73-1,0) -> 0 | P73: =+P58 -> 0 | Q73: =+Q58 -> 0 | R73: =+R58 -> 0 | S73: =+S58 -> 0 | T73: =+T58 -> 0 | U73: =+U58 -> 0 | V73: =+V58 -> 0 | W73: =+W58 -> 0 | ... AT73: =+AT58 -> 0
B74: Reported EBITDA | C74: =SUM(C70:C73) -> 159.72149 | D74: =SUM(D70:D73) -> 149.05978 | F74: =SUM(F70:F73) -> 110.80702 | G74: =SUM(G70:G73) -> 78.12653 | I74: =SUM(I70:I73) -> 147.51568 | J74: =SUM(J70:J73) -> 116.37929 | K74: =SUM(K70:K73) -> -12.07822 | M74: =SUM(M70:M73) -> -128.45751 | N74: =IFERROR(K74/J74-1,0) -> -1.1037832 | P74: =SUM(P70:P73) -> 32.29054 | Q74: =SUM(Q70:Q73) -> 23.65557 | R74: =SUM(R70:R73) -> 18.00904 | S74: =SUM(S70:S73) -> 9.5497 | T74: =SUM(T70:T73) -> 0.97158 | U74: =SUM(U70:U73) -> 12.4993 | V74: =SUM(V70:V73) -> 26.0371 | W74: =SUM(W70:W73) -> 28.86382 | ... AT74: =SUM(AT70:AT73) -> -16.19284
B75: % Margin | C75: =C74/C$24 -> 0.14072801 | D75: =D74/D$24 -> 0.079313141 | F75: =F74/F$24 -> 0.1110432 | G75: =G74/G$24 -> 0.046753764 | I75: =I74/I$24 -> 0.096768991 | J75: =J74/J$24 -> 0.045593679 | K75: =K74/K$24 -> -0.0040499124 | M75: 0 | N75: 0 | P75: =P74/P$24 -> 0.39907679 | Q75: =Q74/Q$24 -> 0.29112505 | R75: =R74/R$24 -> 0.23055349 | S75: =S74/S$24 -> 0.11456895 | T75: =T74/T$24 -> 0.010771857 | U75: =U74/U$24 -> 0.13901116 | V75: =V74/V$24 -> 0.24872555 | W75: =W74/W$24 -> 0.27722552 | ... AT75: =AT74/AT$24 -> -0.064404038
B77: Personal Expenses
B78: (+) Home Office Expense | C78: =SUMIFS($P78:$AT78,$P$5:$AT$5,">"&C$168,$P$5:$AT$5,"<"&C$169) -> 0 | D78: =SUMIFS($P78:$AT78,$P$5:$AT$5,">"&D$168,$P$5:$AT$5,"<"&D$169) -> 2.704 | F78: =SUMIFS($P78:$AT78,$P$5:$AT$5,">"&F$168,$P$5:$AT$5,"<"&F$169) -> 0 | G78: =SUMIFS($P78:$AT78,$P$5:$AT$5,">"&G$168,$P$5:$AT$5,"<"&G$169) -> 0 | I78: =SUMIFS($P78:$AT78,$P$5:$AT$5,">"&I$168,$P$5:$AT$5,"<"&I$169) -> 0 | J78: =SUMIFS($P78:$AT78,$P$5:$AT$5,">"&J$168,$P$5:$AT$5,"<"&J$169) -> 2.704 | K78: =J78 -> 2.704 | M78: =K78-J78 -> 0 | N78: =IFERROR(K78/J78-1,0) -> 0 | P78: =SUMIFS('Combined P&L'!N:N,'Combined P&L'!$D:$D,'P&L Forecast'!$B78) -> 0 | Q78: =SUMIFS('Combined P&L'!O:O,'Combined P&L'!$D:$D,'P&L Forecast'!$B78) -> 0 | R78: =SUMIFS('Combined P&L'!P:P,'Combined P&L'!$D:$D,'P&L Forecast'!$B78) -> 0 | S78: =SUMIFS('Combined P&L'!Q:Q,'Combined P&L'!$D:$D,'P&L Forecast'!$B78) -> 0 | T78: =SUMIFS('Combined P&L'!R:R,'Combined P&L'!$D:$D,'P&L Forecast'!$B78) -> 0 | U78: =SUMIFS('Combined P&L'!S:S,'Combined P&L'!$D:$D,'P&L Forecast'!$B78) -> 0 | V78: =SUMIFS('Combined P&L'!T:T,'Combined P&L'!$D:$D,'P&L Forecast'!$B78) -> 0 | W78: =SUMIFS('Combined P&L'!U:U,'Combined P&L'!$D:$D,'P&L Forecast'!$B78) -> 0 | X78: =SUMIFS('Combined P&L'!V:V,'Combined P&L'!$D:$D,'P&L Forecast'!$B78) -> 0 | Y78: =SUMIFS('Combined P&L'!W:W,'Combined P&L'!$D:$D,'P&L Forecast'!$B78) -> 0 | Z78: =SUMIFS('Combined P&L'!X:X,'Combined P&L'!$D:$D,'P&L Forecast'!$B78) -> 0 | AA78: =SUMIFS('Combined P&L'!Y:Y,'Combined P&L'!$D:$D,'P&L Forecast'!$B78) -> 0 | AB78: =SUMIFS('Combined P&L'!Z:Z,'Combined P&L'!$D:$D,'P&L Forecast'!$B78) -> 0 | AC78: =SUMIFS('Combined P&L'!AA:AA,'Combined P&L'!$D:$D,'P&L Forecast'!$B78) -> 0 | AD78: =SUMIFS('Combined P&L'!AB:AB,'Combined P&L'!$D:$D,'P&L Forecast'!$B78) -> 0 | AE78: =SUMIFS('Combined P&L'!AC:AC,'Combined P&L'!$D:$D,'P&L Forecast'!$B78) -> 0 | AF78: =SUMIFS('Combined P&L'!AD:AD,'Combined P&L'!$D:$D,'P&L Forecast'!$B78) -> 0 | AG78: =SUMIFS('Combined P&L'!AE:AE,'Combined P&L'!$D:$D,'P&L Forecast'!$B78) -> 0 | AH78: =SUMIFS('Combined P&L'!AF:AF,'Combined P&L'!$D:$D,'P&L Forecast'!$B78) -> 0 | AI78: =SUMIFS('Combined P&L'!AG:AG,'Combined P&L'!$D:$D,'P&L Forecast'!$B78) -> 0 | AJ78: =SUMIFS('Combined P&L'!AH:AH,'Combined P&L'!$D:$D,'P&L Forecast'!$B78) -> 0 | AK78: =SUMIFS('Combined P&L'!AI:AI,'Combined P&L'!$D:$D,'P&L Forecast'!$B78) -> 0 | AL78: =SUMIFS('Combined P&L'!AJ:AJ,'Combined P&L'!$D:$D,'P&L Forecast'!$B78) -> 0 | AM78: =SUMIFS('Combined P&L'!AK:AK,'Combined P&L'!$D:$D,'P&L Forecast'!$B78) -> 2.704 | AN78: =SUMIFS('Combined P&L'!AL:AL,'Combined P&L'!$D:$D,'P&L Forecast'!$B78) -> 0 | AO78: =SUMIFS('Combined P&L'!AM:AM,'Combined P&L'!$D:$D,'P&L Forecast'!$B78) -> 0 | AP78: =SUMIFS('Combined P&L'!AN:AN,'Combined P&L'!$D:$D,'P&L Forecast'!$B78) -> 0 | AQ78: =SUMIFS('Combined P&L'!AO:AO,'Combined P&L'!$D:$D,'P&L Forecast'!$B78) -> 0 | AR78: =SUMIFS('Combined P&L'!AP:AP,'Combined P&L'!$D:$D,'P&L Forecast'!$B78) -> 0 | AS78: =SUMIFS('Combined P&L'!AQ:AQ,'Combined P&L'!$D:$D,'P&L Forecast'!$B78) -> 0 | AT78: =SUMIFS('Combined P&L'!AR:AR,'Combined P&L'!$D:$D,'P&L Forecast'!$B78) -> 0
B79: (+) Utilities | C79: =+C57 -> 1.05983 | D79: =+D57 -> 3.29133 | F79: =+F57 -> 2.02633 | G79: =+G57 -> 1.943 | I79: =+I57 -> 2.45133 | J79: =+J57 -> 3.208 | K79: =J79 -> 3.208 | M79: =K79-J79 -> 0 | N79: =IFERROR(K79/J79-1,0) -> 0 | P79: =+P57 -> 0.085 | Q79: =+Q57 -> 0.085 | R79: =+R57 -> 0.097 | S79: =+S57 -> 0.11283 | T79: =+T57 -> 0.085 | U79: =+U57 -> 0.085 | V79: =+V57 -> 0.085 | W79: =+W57 -> 0.085 | ... AT79: =+AT57 -> 0.293
B80: Adj. EBITDA | C80: =+C74+C78+C79 -> 160.78132 | D80: =+D74+D78+D79 -> 155.05511 | F80: =+F74+F78+F79 -> 112.83335 | G80: =+G74+G78+G79 -> 80.06953 | I80: =+I74+I78+I79 -> 149.96701 | J80: =+J74+J78+J79 -> 122.29129 | K80: =+K74+K78+K79 -> -6.16622 | M80: =+M74+M78+M79 -> -128.45751 | N80: =IFERROR(K80/J80-1,0) -> -1.0504224 | P80: =+P74+P78+P79 -> 32.37554 | Q80: =+Q74+Q78+Q79 -> 23.74057 | R80: =+R74+R78+R79 -> 18.10604 | S80: =+S74+S78+S79 -> 9.66253 | T80: =+T74+T78+T79 -> 1.05658 | U80: =+U74+U78+U79 -> 12.5843 | V80: =+V74+V78+V79 -> 26.1221 | W80: =+W74+W78+W79 -> 28.94882 | ... AT80: =+AT74+AT78+AT79 -> -15.89984
B81: % Margin | C81: =C80/C$24 -> 0.14166181 | D81: =D80/D$24 -> 0.082503193 | F81: =F80/F$24 -> 0.11307385 | G81: =G80/G$24 -> 0.047916526 | I81: =I80/I$24 -> 0.098377042 | J81: =J80/J$24 -> 0.047909811 | K81: =K80/K$24 -> -0.0020675771 | M81: 0 | N81: 0 | P81: =P80/P$24 -> 0.4001273 | Q81: =Q80/Q$24 -> 0.29217113 | R81: =R80/R$24 -> 0.23179529 | S81: =S80/S$24 -> 0.11592258 | T81: =T80/T$24 -> 0.011714247 | U81: =U80/U$24 -> 0.13995649 | V81: =V80/V$24 -> 0.24953753 | W81: =W80/W$24 -> 0.27804191 | ... AT81: =AT80/AT$24 -> -0.063238684
B83: Near-Term Adjustments
B84: (-) Go-Forward Owner Compensation | C84: =-$C$163+C$31 -> -200 | D84: =-$C$163+D$31 -> -109.33296 | F84: =-$C$163/12*7+F$31 -> -71.200547 | G84: =-$C$163/12*7+G$31 -> -53.523647 | I84: =-$C$163+I$31 -> -154.53388 | J84: =-$C$163+J$31 -> -91.65606 | K84: =-$C$163+K$31 -> -91.65606 | M84: =K84-J84 -> 0 | N84: =IFERROR(K84/J84-1,0) -> 0 | P84: =-$C$163/12+P$31 -> -16.666667 | Q84: =-$C$163/12+Q$31 -> -16.666667 | R84: =-$C$163/12+R$31 -> -16.666667 | S84: =-$C$163/12+S$31 -> -16.666667 | T84: =-$C$163/12+T$31 -> -16.666667 | U84: =-$C$163/12+U$31 -> -16.666667 | V84: =-$C$163/12+V$31 -> -16.666667 | W84: =-$C$163/12+W$31 -> -16.666667 | ... AT84: =-$C$163/12+AT$31 -> -7.1437967
B85: (+) Other Professional Fees | C85: =+C44 -> 18.23425 | D85: =+D44 -> 27.04095 | F85: =+F44 -> 12.014 | G85: =+G44 -> 57.55 | I85: =+I44 -> 21.74858 | J85: =+J44 -> 72.57695 | K85: =+C164 -> 72.57695 | M85: =K85-J85 -> 0 | P85: =+P44-$C$164/12 -> -6.0480792 | Q85: =+Q44-$C$164/12 -> -4.8815792 | R85: =+R44-$C$164/12 -> -4.8815792 | S85: =+S44-$C$164/12 -> -4.8814092 | T85: =+T44-$C$164/12 -> -4.8814092 | U85: =+U44-$C$164/12 -> -3.3814192 | V85: =+V44-$C$164/12 -> -4.8814092 | W85: =+W44-$C$164/12 -> -4.8814092 | ... AT85: =+AT44-$C$164/12 -> 12.901921
B86: (+) Software Savings | C86: 0 | D86: 0 | F86: 0 | G86: 0 | I86: 0 | J86: 0 | K86: 0 | M86: =K86-J86 -> 0 | N86: =IFERROR(K86/J86-1,0) -> 0 | P86: 0 | Q86: 0 | R86: 0 | S86: 0 | T86: 0 | U86: 0 | V86: 0 | W86: 0 | X86: 0 | Y86: 0 | Z86: 0 | AA86: 0 | AB86: 0 | AC86: 0 | AD86: 0 | AE86: 0 | AF86: 0 | AG86: 0 | AH86: 0 | AI86: 0 | AJ86: 0 | AK86: 0 | AL86: 0 | AM86: 0 | AN86: 0 | AO86: 0 | AP86: 0 | AQ86: 0 | AR86: 0 | AS86: 0 | AT86: 0
B87: (+) Other Personnel Savings/Expenses | C87: 0 | D87: 0 | F87: 0 | G87: 0 | I87: 0 | J87: 0 | K87: 0 | M87: =K87-J87 -> 0 | N87: =IFERROR(K87/J87-1,0) -> 0 | P87: 0 | Q87: 0 | R87: 0 | S87: 0 | T87: 0 | U87: 0 | V87: 0 | W87: 0 | X87: 0 | Y87: 0 | Z87: 0 | AA87: 0 | AB87: 0 | AC87: 0 | AD87: 0 | AE87: 0 | AF87: 0 | AG87: 0 | AH87: 0 | AI87: 0 | AJ87: 0 | AK87: 0 | AL87: 0 | AM87: 0 | AN87: 0 | AO87: 0 | AP87: 0 | AQ87: 0 | AR87: 0 | AS87: 0 | AT87: 0
B88: (+) [ ] | C88: 0 | D88: 0 | F88: 0 | G88: 0 | I88: 0 | J88: 0 | K88: 0 | M88: =K88-J88 -> 0 | N88: =IFERROR(K88/J88-1,0) -> 0 | P88: 0 | Q88: 0 | R88: 0 | S88: 0 | T88: 0 | U88: 0 | V88: 0 | W88: 0 | X88: 0 | Y88: 0 | Z88: 0 | AA88: 0 | AB88: 0 | AC88: 0 | AD88: 0 | AE88: 0 | AF88: 0 | AG88: 0 | AH88: 0 | AI88: 0 | AJ88: 0 | AK88: 0 | AL88: 0 | AM88: 0 | AN88: 0 | AO88: 0 | AP88: 0 | AQ88: 0 | AR88: 0 | AS88: 0 | AT88: 0
B89: Total Near-Term Adjustments | C89: =SUM(C84:C88) -> -181.76575 | D89: =SUM(D84:D88) -> -82.29201 | F89: =SUM(F84:F88) -> -59.186547 | G89: =SUM(G84:G88) -> 4.0263533 | I89: =SUM(I84:I88) -> -132.7853 | J89: =SUM(J84:J88) -> -19.07911 | K89: =SUM(K84:K88) -> -19.07911 | M89: =SUM(M84:M88) -> 0 | N89: =IFERROR(K89/J89-1,0) -> 0 | P89: =SUM(P84:P88) -> -22.714746 | Q89: =SUM(Q84:Q88) -> -21.548246 | R89: =SUM(R84:R88) -> -21.548246 | S89: =SUM(S84:S88) -> -21.548076 | T89: =SUM(T84:T88) -> -21.548076 | U89: =SUM(U84:U88) -> -20.048086 | V89: =SUM(V84:V88) -> -21.548076 | W89: =SUM(W84:W88) -> -21.548076 | ... AT89: =SUM(AT84:AT88) -> 5.7581242
B91: Near-Term Adj. EBITDA | C91: =+C89+C80 -> -20.98443 | D91: =+D89+D80 -> 72.7631 | F91: =+F89+F80 -> 53.646803 | G91: =+G89+G80 -> 84.095883 | I91: =+I89+I80 -> 17.18171 | J91: =+J89+J80 -> 103.21218 | K91: =+K89+K80 -> -25.24533 | M91: =+M89+M80 -> -128.45751 | N91: =IFERROR(K91/J91-1,0) -> -1.2445964 | P91: =+P89+P80 -> 9.6607942 | Q91: =+Q89+Q80 -> 2.1923242 | R91: =+R89+R80 -> -3.4422058 | S91: =+S89+S80 -> -11.885546 | T91: =+T89+T80 -> -20.491496 | U91: =+U89+U80 -> -7.4637858 | V91: =+V89+V80 -> 4.5740242 | W91: =+W89+W80 -> 7.4007442 | ... AT91: =+AT89+AT80 -> -10.141716
B92: % Margin | C92: =C91/C$24 -> -0.018489041 | D92: =D91/D$24 -> 0.03871648 | F92: =F91/F$24 -> 0.053761148 | G92: =G91/G$24 -> 0.050326042 | I92: =I91/I$24 -> 0.011271051 | J92: =J91/J$24 -> 0.040435227 | K92: =K91/K$24 -> -0.0084649374 | M92: 0 | N92: 0 | P92: =P91/P$24 -> 0.11939716 | Q92: =Q91/Q$24 -> 0.026980558 | R92: =R91/R$24 -> -0.044067455 | S92: =S91/S$24 -> -0.14259238 | T92: =T91/T$24 -> -0.22718814 | U92: =U91/U$24 -> -0.083008613 | V92: =V91/V$24 -> 0.043694446 | W92: =W91/W$24 -> 0.071081206 | ... AT92: =AT91/AT$24 -> -0.040336806
B94: Steady-State Adjustments
B95: (-) Onboarding Revenue | C95: =-C10 -> -44.0585 | D95: =-D10 -> -74.5193 | F95: =-F10 -> -42.25405 | G95: =-G10 -> -59.055 | I95: =-I10 -> -57.49255 | J95: =-J10 -> -91.32025 | K95: =-K10 -> -103.5675 | M95: =K95-J95 -> -12.24725 | N95: =IFERROR(K95/J95-1,0) -> 0.13411319 | P95: =-P10 -> -5.465 | Q95: =-Q10 -> -3.9 | R95: =-R10 -> -2.755 | S95: =-S10 -> -3.502 | T95: =-T10 -> -4.659 | U95: =-U10 -> -3.937 | V95: =-V10 -> -4.602 | W95: =-W10 -> -4.738 | ... AT95: =-AT10 -> -6.0985
B96: (+) Onboarding Team Wages | C96: =+C30 -> 122.81255 | D96: =+D30 -> 152.16972 | F96: =+F30 -> 73.94962 | G96: =+G30 -> 111.27999 | I96: =+I30 -> 121.30735 | J96: =+J30 -> 189.50009 | K96: =+K30 -> 197.14944 | M96: =K96-J96 -> 7.64935 | N96: =IFERROR(K96/J96-1,0) -> 0.040365944 | P96: =+P30 -> 9.13728 | Q96: =+Q30 -> 8.96296 | R96: =+R30 -> 10.19584 | S96: =+S30 -> 15.04429 | T96: =+T30 -> 16.63744 | U96: =+U30 -> 7.49499 | V96: =+V30 -> 7.98202 | W96: =+W30 -> 5.90274 | ... AT96: =+AT30 -> 16.42912
B97: (+) S&M Wages | C97: =+C32 -> 0 | D97: =+D32 -> 19.14963 | F97: =+F32 -> 3.09945 | G97: =+G32 -> 51.94131 | I97: =+I32 -> 3.09945 | J97: =+J32 -> 67.99149 | K97: =+K32 -> 98.34912 | M97: =K97-J97 -> 30.35763 | N97: =IFERROR(K97/J97-1,0) -> 0.44649161 | P97: =+P32 -> 0 | Q97: =+Q32 -> 0 | R97: =+R32 -> 0 | S97: =+S32 -> 0 | T97: =+T32 -> 0 | U97: =+U32 -> 0 | V97: =+V32 -> 0 | W97: =+W32 -> 0 | ... AT97: =+AT32 -> 8.19576
B98: (+) Referral Fees | C98: =+C45 -> 24.82 | D98: =+D45 -> 27.15374 | F98: =+F45 -> 17.0895 | G98: =+G45 -> 20.62969 | I98: =+I45 -> 26.2095 | J98: =+J45 -> 30.69393 | K98: =+K45 -> 30.69393 | M98: =K98-J98 -> 0 | N98: =IFERROR(K98/J98-1,0) -> 0 | P98: =+P45 -> 2.21 | Q98: =+Q45 -> 2.735 | R98: =+R45 -> 2.715 | S98: =+S45 -> 2.735 | T98: =+T45 -> 0.78 | U98: =+U45 -> 3.245 | V98: =+V45 -> 1.28 | W98: =+W45 -> 1.3 | ... AT98: =+AT45 -> 3.76952
B99: Total Steady-State Adj. | C99: =SUM(C95:C98) -> 103.57405 | D99: =SUM(D95:D98) -> 123.95379 | F99: =SUM(F95:F98) -> 51.88452 | G99: =SUM(G95:G98) -> 124.79599 | I99: =SUM(I95:I98) -> 93.12375 | J99: =SUM(J95:J98) -> 196.86526 | K99: =SUM(K95:K98) -> 222.62499 | M99: =SUM(M95:M98) -> 25.75973 | N99: =IFERROR(K99/J99-1,0) -> 0.13084955 | P99: =SUM(P95:P98) -> 5.88228 | Q99: =SUM(Q95:Q98) -> 7.79796 | R99: =SUM(R95:R98) -> 10.15584 | S99: =SUM(S95:S98) -> 14.27729 | T99: =SUM(T95:T98) -> 12.75844 | U99: =SUM(U95:U98) -> 6.80299 | V99: =SUM(V95:V98) -> 4.66002 | W99: =SUM(W95:W98) -> 2.46474 | ... AT99: =SUM(AT95:AT98) -> 22.2959
B101: Steady-State Adj. EBITDA | C101: =+C91+C99 -> 82.58962 | D101: =+D91+D99 -> 196.71689 | F101: =+F91+F99 -> 105.53132 | G101: =+G91+G99 -> 208.89187 | I101: =+I91+I99 -> 110.30546 | J101: =+J91+J99 -> 300.07744 | K101: =+K91+K99 -> 197.37966 | M101: =+M91+M99 -> -102.69778 | N101: =IFERROR(K101/J101-1,0) -> -0.34223759 | P101: =+P91+P99 -> 15.543074 | Q101: =+Q91+Q99 -> 9.9902842 | R101: =+R91+R99 -> 6.7136342 | S101: =+S91+S99 -> 2.3917442 | T101: =+T91+T99 -> -7.7330558 | U101: =+U91+U99 -> -0.66079583 | V101: =+V91+V99 -> 9.2340442 | W101: =+W91+W99 -> 9.8654842 | ... AT101: =+AT91+AT99 -> 12.154184
B102: % Margin | C102: =C101/C$24 -> 0.072768374 | D102: =D101/D$24 -> 0.10467099 | F102: =F101/F$24 -> 0.10575626 | G102: =G101/G$24 -> 0.12500851 | I102: =I101/I$24 -> 0.072359413 | J102: =J101/J$24 -> 0.11756073 | K102: =K101/K$24 -> 0.066182794 | M102: 0 | N102: 0 | P102: =P101/P$24 -> 0.19209589 | Q102: =Q101/Q$24 -> 0.12294872 | R102: =R101/R$24 -> 0.085948599 | S102: =S101/S$24 -> 0.028694055 | T102: =T101/T$24 -> -0.085735986 | U102: =U101/U$24 -> -0.0073490514 | V102: =V101/V$24 -> 0.088210387 | W102: =W101/W$24 -> 0.094754054 | ... AT102: =AT101/AT$24 -> 0.048341028
A104: x | B104: PF Annualization Assumptions | D104: Rationale
B105: Revenue Assumptions
B106: =+B7 -> STR Subscription | C106: =+AT7*12 -> 2410.05 | D106: Annualized most recent month
B107: =+B9 -> SMB Subscription | C107: 0 | D107: Sold to former employee in August 2026
B108: =+B8 -> Occupancy Taxes | C108: =+AT8*12 -> 192.8298 | D108: Annualized most recent month
B109: =+B10 -> Onboarding | C109: =AVERAGE(AM10:AT10)*12 -> 103.5675 | D109: Annualilized the Dec'25 - July'26 average (period with increased onboarding staffing)
B110: =+B12 -> STR Bill Pay | C110: =+AT12*12 -> 83.46 | D110: Annualized most recent month
B111: =+B11 -> Topkey Subscription | C111: =+AT11*12 -> 94.836 | D111: Annualized most recent month
B112: =+B13 -> Controller Services | C112: =+AT13*12 -> 42 | D112: Annualized most recent month
B113: =+B14 -> Historical Cleanup | C113: =+AT14*12 -> 0 | D113: Account appears to have been reclassified
B114: =+B15 -> Total Recurring Revenue | C114: =SUM(C106:C113) -> 2926.7433
B116: =+B18 -> 1099 Filing | C116: =+J18 -> 38.7615 | D116: Consistent with client count at the time of 1Q26 service
B117: =+B19 -> Income Tax | C117: 0 | D117: Conservative approach for nonrecurring items
B118: =+B17 -> Profit Share | C118: =AVERAGE(AI17:AT17)*12 -> 16.83622 | D118: Annualized LTM average
...

Sheet Employee Overview
B2: =+'Revenue Analysis'!B2 -> Keystone Bookkeepers
B3: Staffing Overview ($000s) | I3: Print | J3: 1
B5: Active Employees - Summary | C5: Count | D5: Average Comp | E5: Annual Comp | F5: LTM July'26 | G5: Delta | H5: Implied Team Growth | I5: Active
B6: Bookkeeping Team
B7: Bookkeeper | C7: =COUNTIFS('Headcount & Compensation'!$C:$C,'Employee Overview'!$I$5,'Headcount & Compensation'!$E:$E,$B7) -> 41 | D7: =E7/C7 -> 12.343902 | E7: =SUMIFS('Headcount & Compensation'!$L:$L,'Headcount & Compensation'!$C:$C,'Employee Overview'!$I$5,'Headcount & Compensation'!$E:$E,'Employee Overview'!$B7)/1000 -> 506.1 | F7: =+'P&L Forecast'!J28 -> 436.67389 | G7: =E7-F7 -> 69.42611 | H7: =G7/D7 -> 5.6243243
B8: Client Lead | C8: =COUNTIFS('Headcount & Compensation'!$C:$C,'Employee Overview'!$I$5,'Headcount & Compensation'!$E:$E,$B8) -> 16 | D8: =E8/C8 -> 23.775 | E8: =SUMIFS('Headcount & Compensation'!$L:$L,'Headcount & Compensation'!$C:$C,'Employee Overview'!$I$5,'Headcount & Compensation'!$E:$E,'Employee Overview'!$B8)/1000 -> 380.4 | F8: =+'P&L Forecast'!J29+'P&L Forecast'!J34 -> 361.7267 | G8: =E8-F8 -> 18.6733 | H8: =G8/D8 -> 0.78541746
B9: Accounting Manager | C9: =COUNTIFS('Headcount & Compensation'!$C:$C,'Employee Overview'!$I$5,'Headcount & Compensation'!$E:$E,$B9) -> 4 | D9: =E9/C9 -> 116.25 | E9: =SUMIFS('Headcount & Compensation'!$L:$L,'Headcount & Compensation'!$C:$C,'Employee Overview'!$I$5,'Headcount & Compensation'!$E:$E,'Employee Overview'!$B9)/1000 -> 465
B10: Bookkeeping Total | C10: =SUM(C7:C9) -> 61 | D10: =E10/C10 -> 22.155738 | E10: =SUM(E7:E9) -> 1351.5 | F10: =SUM(F7:F9) -> 798.40059 | G10: =SUM(G7:G9) -> 88.09941 | H10: =SUM(H7:H9) -> 6.4097417
B12: Onboarding Team
B13: Onboarding Support | C13: =COUNTIFS('Headcount & Compensation'!$C:$C,'Employee Overview'!$I$5,'Headcount & Compensation'!$E:$E,$B13) -> 4 | D13: =E13/C13 -> 11.325 | E13: =SUMIFS('Headcount & Compensation'!$L:$L,'Headcount & Compensation'!$C:$C,'Employee Overview'!$I$5,'Headcount & Compensation'!$E:$E,'Employee Overview'!$B13)/1000 -> 45.3
B14: Onboarding Specialist | C14: =COUNTIFS('Headcount & Compensation'!$C:$C,'Employee Overview'!$I$5,'Headcount & Compensation'!$E:$E,$B14) -> 4 | D14: =E14/C14 -> 22.2 | E14: =SUMIFS('Headcount & Compensation'!$L:$L,'Headcount & Compensation'!$C:$C,'Employee Overview'!$I$5,'Headcount & Compensation'!$E:$E,'Employee Overview'!$B14)/1000 -> 88.8
B15: Onboarding Total | C15: =SUM(C13:C14) -> 8 | D15: =E15/C15 -> 16.7625 | E15: =SUM(E13:E14) -> 134.1 | F15: =SUM(F13:F14) -> 0 | G15: =SUM(G13:G14) -> 0 | H15: =SUM(H13:H14) -> 0
B17: Remaining Team
B18: Admin | C18: =COUNTIFS('Headcount & Compensation'!$C:$C,'Employee Overview'!$I$5,'Headcount & Compensation'!$E:$E,$B18) -> 8 | D18: =E18/C18 -> 13.8 | E18: =SUMIFS('Headcount & Compensation'!$L:$L,'Headcount & Compensation'!$C:$C,'Employee Overview'!$I$5,'Headcount & Compensation'!$E:$E,'Employee Overview'!$B18)/1000 -> 110.4
