Workbook

Sheet Cover
B24: Keystone Bookkeepers
B25: Pre-LOI Business Analysis
B26: ="As of "&TEXT(TODAY(),"mm/dd/yy") -> As of 09/15/26

Sheet P&L Overview
B2: =+Cover!B24 -> Keystone Bookkeepers
B3: Summary P&L Overview ($000s) | P3: Print | Q3: 1
C5: Full Year | F5: YTD | I5: LTM | K5: PF | M5: PF Delta
B6: P&L Summary | C6: 2024 | D6: 2025 | F6: July'25 | G6: July'26 | I6: July'25 | J6: July'26 | K6: July'26 | M6: ($) | N6: (%)
B7: Revenue
B8: =+'P&L Forecast'!B7 -> STR Subscription | C8: =+'P&L Forecast'!C7 -> 793.47225 | D8: =+'P&L Forecast'!D7 -> 1450.4923 | F8: =+'P&L Forecast'!F7 -> 751.5286 | G8: =+'P&L Forecast'!G7 -> 1261.4769 | I8: =+'P&L Forecast'!I7 -> 1152.3203 | J8: =+'P&L Forecast'!J7 -> 1960.4406 | K8: =+'P&L Forecast'!K7 -> 2410.05 | M8: =K8-J8 -> 449.6094 | N8: =IFERROR(K8/J8-1,0) -> 0.229341
B9: =+'P&L Forecast'!B8 -> Occupancy Taxes | C9: =+'P&L Forecast'!C8 -> 0.56 | D9: =+'P&L Forecast'!D8 -> 55.0805 | F9: =+'P&L Forecast'!F8 -> 23.2255 | G9: =+'P&L Forecast'!G8 -> 91.65114 | I9: =+'P&L Forecast'!I8 -> 23.7855 | J9: =+'P&L Forecast'!J8 -> 123.50614 | K9: =+'P&L Forecast'!K8 -> 192.8298 | M9: =K9-J9 -> 69.32366 | N9: =IFERROR(K9/J9-1,0) -> 0.56129728
B10: =+'P&L Forecast'!B9 -> SMB Subscription | C10: =+'P&L Forecast'!C9 -> 224.791 | D10: =+'P&L Forecast'!D9 -> 149.77 | F10: =+'P&L Forecast'!F9 -> 90.4525 | G10: =+'P&L Forecast'!G9 -> 73.4185 | I10: =+'P&L Forecast'!I9 -> 169.5465 | J10: =+'P&L Forecast'!J9 -> 132.736 | K10: =+'P&L Forecast'!K9 -> 16.2 | M10: =K10-J10 -> -116.536 | N10: =IFERROR(K10/J10-1,0) -> -0.87795323
B11: =+'P&L Forecast'!B10 -> Onboarding | C11: =+'P&L Forecast'!C10 -> 44.0585 | D11: =+'P&L Forecast'!D10 -> 74.5193 | F11: =+'P&L Forecast'!F10 -> 42.25405 | G11: =+'P&L Forecast'!G10 -> 59.055 | I11: =+'P&L Forecast'!I10 -> 57.49255 | J11: =+'P&L Forecast'!J10 -> 91.32025 | K11: =+'P&L Forecast'!K10 -> 103.5675 | M11: =K11-J11 -> 12.24725 | N11: =IFERROR(K11/J11-1,0) -> 0.13411319
B12: =+'P&L Forecast'!B11 -> Topkey Subscription | C12: =+'P&L Forecast'!C11 -> 0 | D12: =+'P&L Forecast'!D11 -> 9.947 | F12: =+'P&L Forecast'!F11 -> 0 | G12: =+'P&L Forecast'!G11 -> 45.086 | I12: =+'P&L Forecast'!I11 -> 0 | J12: =+'P&L Forecast'!J11 -> 55.033 | K12: =+'P&L Forecast'!K11 -> 94.836 | M12: =K12-J12 -> 39.803 | N12: =IFERROR(K12/J12-1,0) -> 0.72325695
B13: =+'P&L Forecast'!B12 -> STR Bill Pay | C13: =+'P&L Forecast'!C12 -> 0.06 | D13: =+'P&L Forecast'!D12 -> 36.6065 | F13: =+'P&L Forecast'!F12 -> 15.4915 | G13: =+'P&L Forecast'!G12 -> 45.13 | I13: =+'P&L Forecast'!I12 -> 15.5515 | J13: =+'P&L Forecast'!J12 -> 66.245 | K13: =+'P&L Forecast'!K12 -> 83.46 | M13: =K13-J13 -> 17.215 | N13: =IFERROR(K13/J13-1,0) -> 0.25986867
B14: =+'P&L Forecast'!B13 -> Controller Services | C14: =+'P&L Forecast'!C13 -> 13.75 | D14: =+'P&L Forecast'!D13 -> 46.4 | F14: =+'P&L Forecast'!F13 -> 31.5 | G14: =+'P&L Forecast'!G13 -> 24.25 | I14: =+'P&L Forecast'!I13 -> 44 | J14: =+'P&L Forecast'!J13 -> 39.15 | K14: =+'P&L Forecast'!K13 -> 42 | M14: =K14-J14 -> 2.85 | N14: =IFERROR(K14/J14-1,0) -> 0.072796935
B15: Other Revenue | C15: =+C16-SUM(C8:C14) -> 58.2741 | D15: =+D16-SUM(D8:D14) -> 56.56748 | F15: =+F16-SUM(F8:F14) -> 43.42095 | G15: =+G16-SUM(G8:G14) -> 70.95371 | I15: =+I16-SUM(I8:I14) -> 61.71435 | J15: =+J16-SUM(J8:J14) -> 84.10024 | K15: =+K16-SUM(K8:K14) -> 55.59772 | M15: =K15-J15 -> -28.50252 | N15: =IFERROR(K15/J15-1,0) -> -0.33891128
B16: Total Run-Rate Revenue | C16: =+'P&L Forecast'!C24 -> 1134.9659 | D16: =+'P&L Forecast'!D24 -> 1879.3831 | F16: =+'P&L Forecast'!F24 -> 997.8731 | G16: =+'P&L Forecast'!G24 -> 1671.0212 | I16: =+'P&L Forecast'!I24 -> 1524.4107 | J16: =+'P&L Forecast'!J24 -> 2552.5312 | K16: =+'P&L Forecast'!K24 -> 2998.541 | M16: =SUM(M8:M15) -> 446.00979 | N16: =IFERROR(K16/J16-1,0) -> 0.17473235
B17: Unclassified Active Client Revenue | C17: =+'P&L Forecast'!C26 -> 0 | D17: =+'P&L Forecast'!D26 -> 0 | F17: =+'P&L Forecast'!F26 -> 0 | G17: =+'P&L Forecast'!G26 -> 0 | I17: =+'P&L Forecast'!I26 -> 0 | J17: =+'P&L Forecast'!J26 -> 0 | K17: =+'P&L Forecast'!K26 -> 93.9827 | M17: =K17-J17 -> 93.9827 | N17: =IFERROR(K17/J17-1,0) -> 0
B18: Total Adj. Revenue | C18: =+'P&L Forecast'!C28 -> 1134.9659 | D18: =+'P&L Forecast'!D28 -> 1879.3831 | F18: =+'P&L Forecast'!F28 -> 997.8731 | G18: =+'P&L Forecast'!G28 -> 1671.0212 | I18: =+'P&L Forecast'!I28 -> 1524.4107 | J18: =+'P&L Forecast'!J28 -> 2552.5312 | K18: =+'P&L Forecast'!K28 -> 3092.5237 | M18: =SUM(M16:M17) -> 539.99249 | N18: =IFERROR(K18/J18-1,0) -> 0.21155177
B20: Expenses
B21: =+'P&L Forecast'!B31 -> Indirect Labor | C21: =+'P&L Forecast'!C31 -> 101.3752 | D21: =+'P&L Forecast'!D31 -> 281.24054 | F21: =+'P&L Forecast'!F31 -> 136.29648 | G21: =+'P&L Forecast'!G31 -> 357.27472 | I21: =+'P&L Forecast'!I31 -> 202.41598 | J21: =+'P&L Forecast'!J31 -> 502.21878 | K21: =+'P&L Forecast'!K31 -> 681.3 | M21: =K21-J21 -> 179.08122 | N21: =IFERROR(K21/J21-1,0) -> 0.35658009 | P21: =K21/$K$30 -> 0.32533849
B22: =+'P&L Forecast'!B32 -> Bookkeeper Wages | C22: =+'P&L Forecast'!C32 -> 183.36903 | D22: =+'P&L Forecast'!D32 -> 316.18462 | F22: =+'P&L Forecast'!F32 -> 147.26813 | G22: =+'P&L Forecast'!G32 -> 267.7574 | I22: =+'P&L Forecast'!I32 -> 240.18098 | J22: =+'P&L Forecast'!J32 -> 436.67389 | K22: =+'P&L Forecast'!K32 -> 492.6 | M22: =K22-J22 -> 55.92611 | N22: =IFERROR(K22/J22-1,0) -> 0.12807294 | P22: =K22/$K$30 -> 0.23522933
B23: =+'P&L Forecast'!B33 -> Client Lead Wages | C23: =+'P&L Forecast'!C33 -> 286.16129 | D23: =+'P&L Forecast'!D33 -> 352.95844 | F23: =+'P&L Forecast'!F33 -> 201.27983 | G23: =+'P&L Forecast'!G33 -> 202.05309 | I23: =+'P&L Forecast'!I33 -> 353.12843 | J23: =+'P&L Forecast'!J33 -> 353.7317 | K23: =+'P&L Forecast'!K33 -> 392.92452 | M23: =K23-J23 -> 39.19282 | N23: =IFERROR(K23/J23-1,0) -> 0.11079816 | P23: =K23/$K$30 -> 0.18763169
B24: =+'P&L Forecast'!B34 -> Onboarding Team Wages | C24: =+'P&L Forecast'!C34 -> 122.81255 | D24: =+'P&L Forecast'!D34 -> 152.16972 | F24: =+'P&L Forecast'!F34 -> 73.94962 | G24: =+'P&L Forecast'!G34 -> 111.27999 | I24: =+'P&L Forecast'!I34 -> 121.30735 | J24: =+'P&L Forecast'!J34 -> 189.50009 | K24: =+'P&L Forecast'!K34 -> 197.14944 | M24: =K24-J24 -> 7.64935 | N24: =IFERROR(K24/J24-1,0) -> 0.040365944 | P24: =K24/$K$30 -> 0.094143992
B25: =+'P&L Forecast'!B35 -> Owner Wages | C25: =+'P&L Forecast'!C35 -> 0 | D25: =+'P&L Forecast'!D35 -> 90.66704 | F25: =+'P&L Forecast'!F35 -> 45.46612 | G25: =+'P&L Forecast'!G35 -> 63.14302 | I25: =+'P&L Forecast'!I35 -> 45.46612 | J25: =+'P&L Forecast'!J35 -> 108.34394 | K25: =+'P&L Forecast'!K35 -> 108.34394 | M25: =K25-J25 -> 0 | N25: =IFERROR(K25/J25-1,0) -> 0 | P25: =K25/$K$30 -> 0.051737053
B26: =+'P&L Forecast'!B36 -> S&M Wages | C26: =+'P&L Forecast'!C36 -> 0 | D26: =+'P&L Forecast'!D36 -> 19.14963 | F26: =+'P&L Forecast'!F36 -> 3.09945 | G26: =+'P&L Forecast'!G36 -> 51.94131 | I26: =+'P&L Forecast'!I36 -> 3.09945 | J26: =+'P&L Forecast'!J36 -> 67.99149 | K26: =+'P&L Forecast'!K36 -> 98.34912 | M26: =K26-J26 -> 30.35763 | N26: =IFERROR(K26/J26-1,0) -> 0.44649161 | P26: =K26/$K$30 -> 0.046964266
B27: =+'P&L Forecast'!B37 -> Occupancy Tax Specialist | C27: =+'P&L Forecast'!C37 -> 1.11335 | D27: =+'P&L Forecast'!D37 -> 29.56415 | F27: =+'P&L Forecast'!F37 -> 14.27585 | G27: =+'P&L Forecast'!G37 -> 42.08505 | I27: =+'P&L Forecast'!I37 -> 15.3892 | J27: =+'P&L Forecast'!J37 -> 57.37335 | K27: =+'P&L Forecast'!K37 -> 58.2 | M27: =K27-J27 -> 0.82665 | N27: =IFERROR(K27/J27-1,0) -> 0.014408257 | P27: =K27/$K$30 -> 0.027792016
B28: =+'P&L Forecast'!B38 -> Sr. Client Lead Wages | C28: =+'P&L Forecast'!C38 -> 0 | D28: =+'P&L Forecast'!D38 -> 0 | F28: =+'P&L Forecast'!F38 -> 0 | G28: =+'P&L Forecast'!G38 -> 7.995 | I28: =+'P&L Forecast'!I38 -> 0 | J28: =+'P&L Forecast'!J38 -> 7.995 | K28: =+'P&L Forecast'!K38 -> 33.08124 | M28: =K28-J28 -> 25.08624 | N28: =IFERROR(K28/J28-1,0) -> 3.1377411 | P28: =K28/$K$30 -> 0.015797154
B29: =+'P&L Forecast'!B39 -> Employee Benefits | C29: =+'P&L Forecast'!C39 -> 5.37405 | D29: =+'P&L Forecast'!D39 -> 19.23245 | F29: =+'P&L Forecast'!F39 -> 9.02166 | G29: =+'P&L Forecast'!G39 -> 17.36251 | I29: =+'P&L Forecast'!I39 -> 12.16686 | J29: =+'P&L Forecast'!J39 -> 27.5733 | K29: =+'P&L Forecast'!K39 -> 32.17836 | M29: =K29-J29 -> 4.60506 | N29: =IFERROR(K29/J29-1,0) -> 0.16701157 | P29: =K29/$K$30 -> 0.015366005
B30: =+'P&L Forecast'!B40 -> Total Payroll Expenses | C30: =SUM(C21:C29) -> 700.20547 | D30: =SUM(D21:D29) -> 1261.1666 | F30: =SUM(F21:F29) -> 630.65714 | G30: =SUM(G21:G29) -> 1120.8921 | I30: =SUM(I21:I29) -> 993.15437 | J30: =SUM(J21:J29) -> 1751.4015 | K30: =SUM(K21:K29) -> 2094.1266 | M30: =SUM(M21:M29) -> 342.72508 | N30: =K30/J30-1 -> 0.19568618
B32: =+'P&L Forecast'!B42 -> Software & Apps - COGS | C32: =+'P&L Forecast'!C42 -> 114.42269 | D32: =+'P&L Forecast'!D42 -> 157.49471 | F32: =+'P&L Forecast'!F42 -> 84.96859 | G32: =+'P&L Forecast'!G42 -> 152.28157 | I32: =+'P&L Forecast'!I42 -> 142.28345 | J32: =+'P&L Forecast'!J42 -> 224.80769 | K32: =+'P&L Forecast'!K42 -> 335.70816 | M32: =K32-J32 -> 110.90047 | N32: =IFERROR(K32/J32-1,0) -> 0.49331262
B33: =+'P&L Forecast'!B43 -> Software & Apps - G&A | C33: =+'P&L Forecast'!C43 -> 60.91594 | D33: =+'P&L Forecast'!D43 -> 117.05866 | F33: =+'P&L Forecast'!F43 -> 56.8115 | G33: =+'P&L Forecast'!G43 -> 97.04798 | I33: =+'P&L Forecast'!I43 -> 86.51489 | J33: =+'P&L Forecast'!J43 -> 157.29514 | K33: =+'P&L Forecast'!K43 -> 155.82264 | M33: =K33-J33 -> -1.4725 | N33: =IFERROR(K33/J33-1,0) -> -0.0093613827
B34: =+'P&L Forecast'!B44 -> Software & Apps - Topkey | C34: =+'P&L Forecast'!C44 -> 0 | D34: =+'P&L Forecast'!D44 -> 7.14125 | F34: =+'P&L Forecast'!F44 -> 0 | G34: =+'P&L Forecast'!G44 -> 28.82775 | I34: =+'P&L Forecast'!I44 -> 0 | J34: =+'P&L Forecast'!J44 -> 35.969 | K34: =+'P&L Forecast'!K44 -> 60.84 | M34: =K34-J34 -> 24.871 | N34: =IFERROR(K34/J34-1,0) -> 0.69145653
B35: =+'P&L Forecast'!B45 -> Software & Apps - AI tools | C35: =+'P&L Forecast'!C45 -> 0 | D35: =+'P&L Forecast'!D45 -> 0 | F35: =+'P&L Forecast'!F45 -> 0 | G35: =+'P&L Forecast'!G45 -> 6.52752 | I35: =+'P&L Forecast'!I45 -> 0 | J35: =+'P&L Forecast'!J45 -> 6.52752 | K35: =+'P&L Forecast'!K45 -> 15.74376 | M35: =K35-J35 -> 9.21624 | N35: =IFERROR(K35/J35-1,0) -> 1.4119053
B36: =+'P&L Forecast'!B46 -> Total Software Expenses | C36: =SUM(C32:C35) -> 175.33863 | D36: =SUM(D32:D35) -> 281.69462 | F36: =SUM(F32:F35) -> 141.78009 | G36: =SUM(G32:G35) -> 284.68482 | I36: =SUM(I32:I35) -> 228.79834 | J36: =SUM(J32:J35) -> 424.59935 | K36: =SUM(K32:K35) -> 568.11456 | M36: =SUM(M32:M35) -> 143.51521 | N36: =K36/J36-1 -> 0.33800148
B38: =+'P&L Forecast'!B48 -> Other Professional Fees | C38: =+'P&L Forecast'!C48 -> 18.23425 | D38: =+'P&L Forecast'!D48 -> 27.04095 | F38: =+'P&L Forecast'!F48 -> 12.014 | G38: =+'P&L Forecast'!G48 -> 57.55 | I38: =+'P&L Forecast'!I48 -> 21.74858 | J38: =+'P&L Forecast'!J48 -> 72.57695 | K38: =+'P&L Forecast'!K48 -> 72.57695 | M38: =K38-J38 -> 0 | N38: =IFERROR(K38/J38-1,0) -> 0
B39: =+'P&L Forecast'!B49 -> Referral Fees | C39: =+'P&L Forecast'!C49 -> 24.82 | D39: =+'P&L Forecast'!D49 -> 27.15374 | F39: =+'P&L Forecast'!F49 -> 17.0895 | G39: =+'P&L Forecast'!G49 -> 20.62969 | I39: =+'P&L Forecast'!I49 -> 26.2095 | J39: =+'P&L Forecast'!J49 -> 30.69393 | K39: =+'P&L Forecast'!K49 -> 30.69393 | M39: =K39-J39 -> 0 | N39: =IFERROR(K39/J39-1,0) -> 0
B40: =+'P&L Forecast'!B50 -> Travel, Meals & Entertainment | C40: =+'P&L Forecast'!C50 -> 0 | D40: =+'P&L Forecast'!D50 -> 29.76122 | F40: =+'P&L Forecast'!F50 -> 22.29558 | G40: =+'P&L Forecast'!G50 -> 20.68542 | I40: =+'P&L Forecast'!I50 -> 22.29558 | J40: =+'P&L Forecast'!J50 -> 28.15106 | K40: =+'P&L Forecast'!K50 -> 28.15106 | M40: =K40-J40 -> 0 | N40: =IFERROR(K40/J40-1,0) -> 0
B41: =+'P&L Forecast'!B51 -> Payment Collection Fees | C41: =+'P&L Forecast'!C51 -> 8.67099 | D41: =+'P&L Forecast'!D51 -> 13.35153 | F41: =+'P&L Forecast'!F51 -> 6.80445 | G41: =+'P&L Forecast'!G51 -> 9.02684 | I41: =+'P&L Forecast'!I51 -> 10.54373 | J41: =+'P&L Forecast'!J51 -> 15.57392 | K41: =+'P&L Forecast'!K51 -> 15.57392 | M41: =K41-J41 -> 0 | N41: =IFERROR(K41/J41-1,0) -> 0
B42: =+'P&L Forecast'!B52 -> Professional Organizations | C42: =+'P&L Forecast'!C52 -> 5.44332 | D42: =+'P&L Forecast'!D52 -> 11.22296 | F42: =+'P&L Forecast'!F52 -> 6.191 | G42: =+'P&L Forecast'!G52 -> 6.57881 | I42: =+'P&L Forecast'!I52 -> 9.53268 | J42: =+'P&L Forecast'!J52 -> 11.61077 | K42: =+'P&L Forecast'!K52 -> 11.61077 | M42: =K42-J42 -> 0 | N42: =IFERROR(K42/J42-1,0) -> 0
B43: =+'P&L Forecast'!B53 -> S&M Events | C43: =+'P&L Forecast'!C53 -> 0 | D43: =+'P&L Forecast'!D53 -> 11.4983 | F43: =+'P&L Forecast'!F53 -> 0 | G43: =+'P&L Forecast'!G53 -> 11.84548 | I43: =+'P&L Forecast'!I53 -> 0 | J43: =+'P&L Forecast'!J53 -> 23.34378 | K43: =+'P&L Forecast'!K53 -> 23.34378 | M43: =K43-J43 -> 0 | N43: =IFERROR(K43/J43-1,0) -> 0
B44: =+'P&L Forecast'!B54 -> Contract Labor - Tax | C44: =+'P&L Forecast'!C54 -> 0 | D44: =+'P&L Forecast'!D54 -> 1.5875 | F44: =+'P&L Forecast'!F54 -> 0 | G44: =+'P&L Forecast'!G54 -> 30.5155 | I44: =+'P&L Forecast'!I54 -> 0 | J44: =+'P&L Forecast'!J54 -> 32.103 | K44: =+'P&L Forecast'!K54 -> 38.7615 | M44: =K44-J44 -> 6.6585 | N44: =IFERROR(K44/J44-1,0) -> 0.20741052
B45: =+'P&L Forecast'!B55 -> Recruiting Fees | C45: =+'P&L Forecast'!C55 -> 14.90205 | D45: =+'P&L Forecast'!D55 -> 31.6041 | F45: =+'P&L Forecast'!F55 -> 28.29994 | G45: =+'P&L Forecast'!G55 -> 5.5646 | I45: =+'P&L Forecast'!I55 -> 35.34606 | J45: =+'P&L Forecast'!J55 -> 8.86876 | K45: =+'P&L Forecast'!K55 -> 8.86876 | M45: =K45-J45 -> 0 | N45: =IFERROR(K45/J45-1,0) -> 0
B46: Other Expenses | C46: =+C47-SUM(C38:C45) -> 41.87929 | D46: =+D47-SUM(D38:D45) -> 52.32132 | F46: =+F47-SUM(F38:F45) -> 28.90542 | G46: =+G47-SUM(G38:G45) -> 26.90445 | I46: =+I47-SUM(I38:I45) -> 41.76881 | J46: =+J47-SUM(J38:J45) -> 50.32035 | K46: =+K47-SUM(K38:K45) -> 56.05462 | M46: =K46-J46 -> 5.73427 | N46: =IFERROR(K46/J46-1,0) -> 0.11395529
B47: Total Overhead | C47: =+'P&L Forecast'!C66 -> 113.9499 | D47: =+'P&L Forecast'!D66 -> 205.54162 | F47: =+'P&L Forecast'!F66 -> 121.59989 | G47: =+'P&L Forecast'!G66 -> 189.30079 | I47: =+'P&L Forecast'!I66 -> 167.44494 | J47: =+'P&L Forecast'!J66 -> 273.24252 | K47: =+'P&L Forecast'!K66 -> 285.63529 | M47: =SUM(M38:M46) -> 12.39277 | N47: =K47/J47-1 -> 0.045354471
B49: Net Income | C49: =+C16-C30-C36-C47 -> 145.47185 | D49: =+D16-D30-D36-D47 -> 130.9803 | F49: =+F16-F30-F36-F47 -> 103.83598 | G49: =+G16-G30-G36-G47 -> 76.1435 | I49: =+I16-I30-I36-I47 -> 135.013 | J49: =+J16-J30-J36-J47 -> 103.28782 | K49: =+K16-K30-K36-K47 -> 50.66455 | M49: =+M16-M30-M36-M47 -> -52.62327 | N49: =IFERROR(K49/J49-1,0) -> -0.50948185
B50: % Margin | C50: =C49/C$16 -> 0.12817289 | D50: =D49/D$16 -> 0.06969324 | F50: =F49/F$16 -> 0.1040573 | G50: =G49/G$16 -> 0.045567046 | I50: =I49/I$16 -> 0.088567342 | J50: =J49/J$16 -> 0.04046486 | K50: =K49/K$16 -> 0.016896401 | M50: =M49/M$16 -> -0.1179868 | N50: 0
B52: P&L Adjustments
B53: Karbon, Uncat, & Xenett Savings | C53: =+'P&L Forecast'!C91 -> 0 | D53: =+'P&L Forecast'!D91 -> 0 | F53: =+'P&L Forecast'!F91 -> 0 | G53: =+'P&L Forecast'!G91 -> 0 | I53: =+'P&L Forecast'!I91 -> 0 | J53: =+'P&L Forecast'!J91 -> 96.8 | K53: =+'P&L Forecast'!K91 -> 96.8 | M53: =K53-J53 -> 0 | N53: =IFERROR(K53/J53-1,0) -> 0
B54: Other Professional Fees | C54: =+'P&L Forecast'!C90 -> 18.23425 | D54: =+'P&L Forecast'!D90 -> 27.04095 | F54: =+'P&L Forecast'!F90 -> 12.014 | G54: =+'P&L Forecast'!G90 -> 57.55 | I54: =+'P&L Forecast'!I90 -> 21.74858 | J54: =+'P&L Forecast'!J90 -> 72.57695 | K54: =+'P&L Forecast'!K90 -> 72.57695 | M54: =K54-J54 -> 0 | N54: =IFERROR(K54/J54-1,0) -> 0
B55: Unclassified Active Client Contribution | C55: =+'P&L Forecast'!C92 -> 0 | D55: =+'P&L Forecast'!D92 -> 0 | F55: =+'P&L Forecast'!F92 -> 0 | G55: =+'P&L Forecast'!G92 -> 0 | I55: =+'P&L Forecast'!I92 -> 0 | J55: =+'P&L Forecast'!J92 -> 0 | K55: =+'P&L Forecast'!K92 -> 50.703313 | M55: =K55-J55 -> 50.703313 | N55: =IFERROR(K55/J55-1,0) -> 0
B56: Definitional EBITDA Adj. | C56: =SUM('P&L Forecast'!C75:C77) -> 14.24964 | D56: =SUM('P&L Forecast'!D75:D77) -> 18.07948 | F56: =SUM('P&L Forecast'!F75:F77) -> 6.97104 | G56: =SUM('P&L Forecast'!G75:G77) -> 1.98303 | I56: =SUM('P&L Forecast'!I75:I77) -> 12.50268 | J56: =SUM('P&L Forecast'!J75:J77) -> 13.09147 | K56: =SUM('P&L Forecast'!K75:K77) -> 13.09147 | M56: =K56-J56 -> 0 | N56: =IFERROR(K56/J56-1,0) -> 0
B57: Personal Expenses | C57: =+'P&L Forecast'!C82+'P&L Forecast'!C83 -> 1.05983 | D57: =+'P&L Forecast'!D82+'P&L Forecast'!D83 -> 5.99533 | F57: =+'P&L Forecast'!F82+'P&L Forecast'!F83 -> 2.02633 | G57: =+'P&L Forecast'!G82+'P&L Forecast'!G83 -> 1.943 | I57: =+'P&L Forecast'!I82+'P&L Forecast'!I83 -> 2.45133 | J57: =+'P&L Forecast'!J82+'P&L Forecast'!J83 -> 5.912 | K57: =+'P&L Forecast'!K82+'P&L Forecast'!K83 -> 5.912 | M57: =K57-J57 -> 0 | N57: =IFERROR(K57/J57-1,0) -> 0
B58: Onboarding Manager | C58: =+'P&L Forecast'!C89 -> 0 | D58: =+'P&L Forecast'!D89 -> 0 | F58: =+'P&L Forecast'!F89 -> 0 | G58: =+'P&L Forecast'!G89 -> 0 | I58: =+'P&L Forecast'!I89 -> 0 | J58: =+'P&L Forecast'!J89 -> -116.25 | K58: =+'P&L Forecast'!K89 -> -116.25 | M58: =K58-J58 -> 0 | N58: =IFERROR(K58/J58-1,0) -> 0
B59: Go-Forward Owner Comp | C59: =+'P&L Forecast'!C88 -> -228.245 | D59: =+'P&L Forecast'!D88 -> -137.57796 | F59: =+'P&L Forecast'!F88 -> -182.77888 | G59: =+'P&L Forecast'!G88 -> -165.10198 | I59: =+'P&L Forecast'!I88 -> -182.77888 | J59: =+'P&L Forecast'!J88 -> -119.90106 | K59: =+'P&L Forecast'!K88 -> -119.90106 | M59: =K59-J59 -> 0 | N59: =IFERROR(K59/J59-1,0) -> 0
B60: Total Near-Term Adjustments | C60: =SUM(C53:C59) -> -194.70128 | D60: =SUM(D53:D59) -> -86.4622 | F60: =SUM(F53:F59) -> -161.76751 | G60: =SUM(G53:G59) -> -103.62595 | I60: =SUM(I53:I59) -> -146.07629 | J60: =SUM(J53:J59) -> -47.77064 | K60: =SUM(K53:K59) -> 2.9326728 | M60: =SUM(M53:M59) -> 50.703313 | N60: =K60/J60-1 -> -1.0613907
B62: =+'P&L Forecast'!B95 -> Near-Term Adj. EBITDA | C62: =+C49+C60 -> -49.22943 | D62: =+D49+D60 -> 44.5181 | F62: =+F49+F60 -> -57.93153 | G62: =+G49+G60 -> -27.48245 | I62: =+I49+I60 -> -11.06329 | J62: =+J49+J60 -> 55.51718 | K62: =+K49+K60 -> 53.597223 | M62: =+M49+M60 -> -1.9199572 | N62: =IFERROR(K62/J62-1,0) -> -0.034583118
B63: % Margin | C63: =C62/C$18 -> -0.043375252 | D63: =D62/D$18 -> 0.023687613 | F63: =F62/F$18 -> -0.058055007 | G63: =G62/G$18 -> -0.0164465 | I63: =I62/I$18 -> -0.0072574211 | J63: =J62/J$18 -> 0.021749853 | K63: =K62/K$18 -> 0.017331224 | M63: =M62/M$16 -> -0.0043047423 | N63: 0
B65: Normalized Bookkeeper Staffing | C65: =+'P&L Forecast'!C101 -> 0 | D65: =+'P&L Forecast'!D101 -> 0 | F65: =+'P&L Forecast'!F101 -> 0 | G65: =+'P&L Forecast'!G101 -> 0 | I65: =+'P&L Forecast'!I101 -> 0 | J65: =+'P&L Forecast'!J101 -> 0 | K65: =+'P&L Forecast'!K101 -> 220.13063 | M65: =K65-J65 -> 220.13063 | N65: =IFERROR(K65/J65-1,0) -> 0
B66: VR Platform Cost Savings | C66: =+'P&L Forecast'!C102 -> 0 | D66: =+'P&L Forecast'!D102 -> 0 | F66: =+'P&L Forecast'!F102 -> 0 | G66: =+'P&L Forecast'!G102 -> 0 | I66: =+'P&L Forecast'!I102 -> 0 | J66: =+'P&L Forecast'!J102 -> 179.04966 | K66: =+'P&L Forecast'!K102 -> 179.04966 | M66: =K66-J66 -> 0 | N66: =IFERROR(K66/J66-1,0) -> 0
B67: Onboarding Team Wages | C67: =+'P&L Forecast'!C100 -> 122.81255 | D67: =+'P&L Forecast'!D100 -> 152.16972 | F67: =+'P&L Forecast'!F100 -> 73.94962 | G67: =+'P&L Forecast'!G100 -> 111.27999 | I67: =+'P&L Forecast'!I100 -> 121.30735 | J67: =+'P&L Forecast'!J100 -> 189.50009 | K67: =+'P&L Forecast'!K100 -> 147.86208 | M67: =K67-J67 -> -41.63801 | N67: =IFERROR(K67/J67-1,0) -> -0.21972554
B68: S&M Wages | C68: =+'P&L Forecast'!C103 -> 0 | D68: =+'P&L Forecast'!D103 -> 0 | F68: =+'P&L Forecast'!F103 -> 0 | G68: =+'P&L Forecast'!G103 -> 0 | I68: =+'P&L Forecast'!I103 -> 0 | J68: =+'P&L Forecast'!J103 -> 28.2 | K68: =+'P&L Forecast'!K103 -> 28.2 | M68: =K68-J68 -> 0 | N68: =IFERROR(K68/J68-1,0) -> 0
B69: Onboarding Revenue | C69: =+'P&L Forecast'!C99 -> -44.0585 | D69: =+'P&L Forecast'!D99 -> -74.5193 | F69: =+'P&L Forecast'!F99 -> -42.25405 | G69: =+'P&L Forecast'!G99 -> -59.055 | I69: =+'P&L Forecast'!I99 -> -57.49255 | J69: =+'P&L Forecast'!J99 -> -91.32025 | K69: =+'P&L Forecast'!K99 -> -77.675625 | M69: =K69-J69 -> 13.644625 | N69: =IFERROR(K69/J69-1,0) -> -0.14941511
B70: Total Steady-State Adj. | C70: =SUM(C65:C69) -> 78.75405 | D70: =SUM(D65:D69) -> 77.65042 | F70: =SUM(F65:F69) -> 31.69557 | G70: =SUM(G65:G69) -> 52.22499 | I70: =SUM(I65:I69) -> 63.8148 | J70: =SUM(J65:J69) -> 305.4295 | K70: =SUM(K65:K69) -> 497.56674 | M70: =SUM(M65:M69) -> 192.13724 | N70: =K70/J70-1 -> 0.62907232
B72: =+'P&L Forecast'!B106 -> Steady-State Adj. EBITDA | C72: =+C70+C62 -> 29.52462 | D72: =+D70+D62 -> 122.16852 | F72: =+F70+F62 -> -26.23596 | G72: =+G70+G62 -> 24.74254 | I72: =+I70+I62 -> 52.75151 | J72: =+J70+J62 -> 360.94668 | K72: =+K70+K62 -> 551.16396 | M72: =+M70+M62 -> 190.21728 | N72: =IFERROR(K72/J72-1,0) -> 0.52699553
B73: % Margin | C73: =C72/C$18 -> 0.026013664 | D73: =D72/D$18 -> 0.065004585 | F73: =F72/F$18 -> -0.02629188 | G73: =G72/G$18 -> 0.014806838 | I73: =I72/I$18 -> 0.034604527 | J73: =J72/J$18 -> 0.14140735 | K73: =K72/K$18 -> 0.17822465 | M73: =M72/M$16 -> 0.42648679 | N73: 0

Sheet Software Overview
B2: =+Cover!B24 -> Keystone Bookkeepers
B3: Software Utilization Overview ($)
B5: Software Utilization | C5: Current Clients | G5: Former Clients | K5: Total
B6: Bill Pay | C6: Clients | D6: Properties | E6: Avg. Monthly Fee | G6: Clients | H6: Properties | I6: Avg. Monthly Fee | K6: Clients | L6: Properties | M6: % of Clients
B7: Yes | C7: =COUNTIFS('Customer List w Software'!$B$4:$B$310,"<>Former client",'Customer List w Software'!$V$4:$V$310,$B7) -> 41 | D7: =SUMIFS('Customer List w Software'!$K$4:$K$310,'Customer List w Software'!$B$4:$B$310,"<>Former client",'Customer List w Software'!$V$4:$V$310,$B7) -> 1285 | E7: =IFERROR(AVERAGEIFS('Customer List w Software'!$J$4:$J$310,'Customer List w Software'!$B$4:$B$310,"<>Former client",'Customer List w Software'!$V$4:$V$310,$B7),0) -> 2011.8227 | G7: =COUNTIFS('Customer List w Software'!$B$4:$B$310,"Former client",'Customer List w Software'!$V$4:$V$310,$B7) -> 4 | H7: =SUMIFS('Customer List w Software'!$K$4:$K$310,'Customer List w Software'!$B$4:$B$310,"Former client",'Customer List w Software'!$V$4:$V$310,$B7) -> 72 | I7: =IFERROR(AVERAGEIFS('Customer List w Software'!$J$4:$J$310,'Customer List w Software'!$B$4:$B$310,"Former client",'Customer List w Software'!$V$4:$V$310,$B7),0) -> 1602.6667 | K7: =C7+G7 -> 45 | L7: =D7+H7 -> 1357 | M7: =K7/K$10 -> 0.1465798
B8: No | C8: =COUNTIFS('Customer List w Software'!$B$4:$B$310,"<>Former client",'Customer List w Software'!$V$4:$V$310,$B8) -> 133 | D8: =SUMIFS('Customer List w Software'!$K$4:$K$310,'Customer List w Software'!$B$4:$B$310,"<>Former client",'Customer List w Software'!$V$4:$V$310,$B8) -> 2472 | E8: =IFERROR(AVERAGEIFS('Customer List w Software'!$J$4:$J$310,'Customer List w Software'!$B$4:$B$310,"<>Former client",'Customer List w Software'!$V$4:$V$310,$B8),0) -> 1186.0576 | G8: =COUNTIFS('Customer List w Software'!$B$4:$B$310,"Former client",'Customer List w Software'!$V$4:$V$310,$B8) -> 52 | H8: =SUMIFS('Customer List w Software'!$K$4:$K$310,'Customer List w Software'!$B$4:$B$310,"Former client",'Customer List w Software'!$V$4:$V$310,$B8) -> 352 | I8: =IFERROR(AVERAGEIFS('Customer List w Software'!$J$4:$J$310,'Customer List w Software'!$B$4:$B$310,"Former client",'Customer List w Software'!$V$4:$V$310,$B8),0) -> 631.64103 | K8: =C8+G8 -> 185 | L8: =D8+H8 -> 2824 | M8: =K8/K$10 -> 0.60260586
B9: Not Designated | C9: =COUNTIFS('Customer List w Software'!$B$4:$B$310,"<>Former client",'Customer List w Software'!$V$4:$V$310,"") -> 0 | D9: =SUMIFS('Customer List w Software'!$K$4:$K$310,'Customer List w Software'!$B$4:$B$310,"<>Former client",'Customer List w Software'!$V$4:$V$310,"") -> 0 | E9: =IFERROR(AVERAGEIFS('Customer List w Software'!$J$4:$J$310,'Customer List w Software'!$B$4:$B$310,"<>Former client",'Customer List w Software'!$V$4:$V$310,""),0) -> 0 | G9: =COUNTIFS('Customer List w Software'!$B$4:$B$310,"Former client",'Customer List w Software'!$V$4:$V$310,"") -> 77 | H9: =SUMIFS('Customer List w Software'!$K$4:$K$310,'Customer List w Software'!$B$4:$B$310,"Former client",'Customer List w Software'!$V$4:$V$310,"") -> 30 | I9: =IFERROR(AVERAGEIFS('Customer List w Software'!$J$4:$J$310,'Customer List w Software'!$B$4:$B$310,"Former client",'Customer List w Software'!$V$4:$V$310,""),0) -> 592.10266 | K9: =C9+G9 -> 77 | L9: =D9+H9 -> 30 | M9: =K9/K$10 -> 0.25081433
B10: Total Clients | C10: =COUNTIFS('Customer List w Software'!$B$4:$B$310,"<>Former client") -> 174 | D10: =SUMIFS('Customer List w Software'!$K$4:$K$310,'Customer List w Software'!$B$4:$B$310,"<>Former client") -> 3757 | E10: =AVERAGEIFS('Customer List w Software'!$J$4:$J$310,'Customer List w Software'!$B$4:$B$310,"<>Former client") -> 1380.6344 | G10: =COUNTIFS('Customer List w Software'!$B$4:$B$310,"Former client") -> 133 | H10: =SUMIFS('Customer List w Software'!$K$4:$K$310,'Customer List w Software'!$B$4:$B$310,"Former client") -> 454 | I10: =AVERAGEIFS('Customer List w Software'!$J$4:$J$310,'Customer List w Software'!$B$4:$B$310,"Former client") -> 637.95417 | K10: =C10+G10 -> 307 | L10: =D10+H10 -> 4211 | M10: =K10/K$10 -> 1
B12: Trust / Accounting Software
B13: VRT | C13: =COUNTIFS('Customer List w Software'!$B$4:$B$310,"<>Former client",'Customer List w Software'!$W$4:$W$310,$B13) -> 117 | D13: =SUMIFS('Customer List w Software'!$K$4:$K$310,'Customer List w Software'!$B$4:$B$310,"<>Former client",'Customer List w Software'!$W$4:$W$310,$B13) -> 2999 | E13: =IFERROR(AVERAGEIFS('Customer List w Software'!$J$4:$J$310,'Customer List w Software'!$B$4:$B$310,"<>Former client",'Customer List w Software'!$W$4:$W$310,$B13),0) -> 1521.7699 | G13: =COUNTIFS('Customer List w Software'!$B$4:$B$310,"Former client",'Customer List w Software'!$W$4:$W$310,$B13) -> 6 | H13: =SUMIFS('Customer List w Software'!$K$4:$K$310,'Customer List w Software'!$B$4:$B$310,"Former client",'Customer List w Software'!$W$4:$W$310,$B13) -> 84 | I13: =IFERROR(AVERAGEIFS('Customer List w Software'!$J$4:$J$310,'Customer List w Software'!$B$4:$B$310,"Former client",'Customer List w Software'!$W$4:$W$310,$B13),0) -> 1230.2222 | K13: =C13+G13 -> 123 | L13: =D13+H13 -> 3083 | M13: =K13/K$18 -> 0.40065147
B14: VRP | C14: =COUNTIFS('Customer List w Software'!$B$4:$B$310,"<>Former client",'Customer List w Software'!$W$4:$W$310,$B14) -> 36 | D14: =SUMIFS('Customer List w Software'!$K$4:$K$310,'Customer List w Software'!$B$4:$B$310,"<>Former client",'Customer List w Software'!$W$4:$W$310,$B14) -> 659 | E14: =IFERROR(AVERAGEIFS('Customer List w Software'!$J$4:$J$310,'Customer List w Software'!$B$4:$B$310,"<>Former client",'Customer List w Software'!$W$4:$W$310,$B14),0) -> 1378.1986 | G14: =COUNTIFS('Customer List w Software'!$B$4:$B$310,"Former client",'Customer List w Software'!$W$4:$W$310,$B14) -> 8 | H14: =SUMIFS('Customer List w Software'!$K$4:$K$310,'Customer List w Software'!$B$4:$B$310,"Former client",'Customer List w Software'!$W$4:$W$310,$B14) -> 123 | I14: =IFERROR(AVERAGEIFS('Customer List w Software'!$J$4:$J$310,'Customer List w Software'!$B$4:$B$310,"Former client",'Customer List w Software'!$W$4:$W$310,$B14),0) -> 1073.6042 | K14: =C14+G14 -> 44 | L14: =D14+H14 -> 782 | M14: =K14/K$18 -> 0.14332248
B15: Guesty | C15: =COUNTIFS('Customer List w Software'!$B$4:$B$310,"<>Former client",'Customer List w Software'!$W$4:$W$310,$B15) -> 2 | D15: =SUMIFS('Customer List w Software'!$K$4:$K$310,'Customer List w Software'!$B$4:$B$310,"<>Former client",'Customer List w Software'!$W$4:$W$310,$B15) -> 47 | E15: =IFERROR(AVERAGEIFS('Customer List w Software'!$J$4:$J$310,'Customer List w Software'!$B$4:$B$310,"<>Former client",'Customer List w Software'!$W$4:$W$310,$B15),0) -> 1226.1667 | G15: =COUNTIFS('Customer List w Software'!$B$4:$B$310,"Former client",'Customer List w Software'!$W$4:$W$310,$B15) -> 2 | H15: =SUMIFS('Customer List w Software'!$K$4:$K$310,'Customer List w Software'!$B$4:$B$310,"Former client",'Customer List w Software'!$W$4:$W$310,$B15) -> 17 | I15: =IFERROR(AVERAGEIFS('Customer List w Software'!$J$4:$J$310,'Customer List w Software'!$B$4:$B$310,"Former client",'Customer List w Software'!$W$4:$W$310,$B15),0) -> 841.83333 | K15: =C15+G15 -> 4 | L15: =D15+H15 -> 64 | M15: =K15/K$18 -> 0.013029316
B16: Clearing | C16: =COUNTIFS('Customer List w Software'!$B$4:$B$310,"<>Former client",'Customer List w Software'!$W$4:$W$310,$B16) -> 1 | D16: =SUMIFS('Customer List w Software'!$K$4:$K$310,'Customer List w Software'!$B$4:$B$310,"<>Former client",'Customer List w Software'!$W$4:$W$310,$B16) -> 15 | E16: =IFERROR(AVERAGEIFS('Customer List w Software'!$J$4:$J$310,'Customer List w Software'!$B$4:$B$310,"<>Former client",'Customer List w Software'!$W$4:$W$310,$B16),0) -> 1662.5 | G16: =COUNTIFS('Customer List w Software'!$B$4:$B$310,"Former client",'Customer List w Software'!$W$4:$W$310,$B16) -> 3 | H16: =SUMIFS('Customer List w Software'!$K$4:$K$310,'Customer List w Software'!$B$4:$B$310,"Former client",'Customer List w Software'!$W$4:$W$310,$B16) -> 34 | I16: =IFERROR(AVERAGEIFS('Customer List w Software'!$J$4:$J$310,'Customer List w Software'!$B$4:$B$310,"Former client",'Customer List w Software'!$W$4:$W$310,$B16),0) -> 723.22222 | K16: =C16+G16 -> 4 | L16: =D16+H16 -> 49 | M16: =K16/K$18 -> 0.013029316
B17: None | C17: =COUNTIFS('Customer List w Software'!$B$4:$B$310,"<>Former client",'Customer List w Software'!$W$4:$W$310,"") -> 18 | D17: =SUMIFS('Customer List w Software'!$K$4:$K$310,'Customer List w Software'!$B$4:$B$310,"<>Former client",'Customer List w Software'!$W$4:$W$310,"") -> 37 | E17: =IFERROR(AVERAGEIFS('Customer List w Software'!$J$4:$J$310,'Customer List w Software'!$B$4:$B$310,"<>Former client",'Customer List w Software'!$W$4:$W$310,""),0) -> 469.62963 | G17: =COUNTIFS('Customer List w Software'!$B$4:$B$310,"Former client",'Customer List w Software'!$W$4:$W$310,"") -> 114 | H17: =SUMIFS('Customer List w Software'!$K$4:$K$310,'Customer List w Software'!$B$4:$B$310,"Former client",'Customer List w Software'!$W$4:$W$310,"") -> 196 | I17: =IFERROR(AVERAGEIFS('Customer List w Software'!$J$4:$J$310,'Customer List w Software'!$B$4:$B$310,"Former client",'Customer List w Software'!$W$4:$W$310,""),0) -> 570.38952 | K17: =C17+G17 -> 132 | L17: =D17+H17 -> 233 | M17: =K17/K$18 -> 0.42996743
B18: Total Clients | C18: =COUNTIFS('Customer List w Software'!$B$4:$B$310,"<>Former client") -> 174 | D18: =SUMIFS('Customer List w Software'!$K$4:$K$310,'Customer List w Software'!$B$4:$B$310,"<>Former client") -> 3757 | E18: =AVERAGEIFS('Customer List w Software'!$J$4:$J$310,'Customer List w Software'!$B$4:$B$310,"<>Former client") -> 1380.6344 | G18: =COUNTIFS('Customer List w Software'!$B$4:$B$310,"Former client") -> 133 | H18: =SUMIFS('Customer List w Software'!$K$4:$K$310,'Customer List w Software'!$B$4:$B$310,"Former client") -> 454 | I18: =AVERAGEIFS('Customer List w Software'!$J$4:$J$310,'Customer List w Software'!$B$4:$B$310,"Former client") -> 637.95417 | K18: =C18+G18 -> 307 | L18: =D18+H18 -> 4211 | M18: =K18/K$18 -> 1
B20: Property Management System (PMS)
B21: Guesty | C21: =COUNTIFS('Customer List w Software'!$B$4:$B$310,"<>Former client",'Customer List w Software'!$X$4:$X$310,$B21) -> 51 | D21: =SUMIFS('Customer List w Software'!$K$4:$K$310,'Customer List w Software'!$B$4:$B$310,"<>Former client",'Customer List w Software'!$X$4:$X$310,$B21) -> 1338 | E21: =IFERROR(AVERAGEIFS('Customer List w Software'!$J$4:$J$310,'Customer List w Software'!$B$4:$B$310,"<>Former client",'Customer List w Software'!$X$4:$X$310,$B21),0) -> 1661.0776 | G21: =COUNTIFS('Customer List w Software'!$B$4:$B$310,"Former client",'Customer List w Software'!$X$4:$X$310,$B21) -> 6 | H21: =SUMIFS('Customer List w Software'!$K$4:$K$310,'Customer List w Software'!$B$4:$B$310,"Former client",'Customer List w Software'!$X$4:$X$310,$B21) -> 70 | I21: =IFERROR(AVERAGEIFS('Customer List w Software'!$J$4:$J$310,'Customer List w Software'!$B$4:$B$310,"Former client",'Customer List w Software'!$X$4:$X$310,$B21),0) -> 976.33333 | K21: =C21+G21 -> 57 | L21: =D21+H21 -> 1408 | M21: =K21/K$29 -> 0.18566775
B22: Hospitable | C22: =COUNTIFS('Customer List w Software'!$B$4:$B$310,"<>Former client",'Customer List w Software'!$X$4:$X$310,$B22) -> 48 | D22: =SUMIFS('Customer List w Software'!$K$4:$K$310,'Customer List w Software'!$B$4:$B$310,"<>Former client",'Customer List w Software'!$X$4:$X$310,$B22) -> 829 | E22: =IFERROR(AVERAGEIFS('Customer List w Software'!$J$4:$J$310,'Customer List w Software'!$B$4:$B$310,"<>Former client",'Customer List w Software'!$X$4:$X$310,$B22),0) -> 1090.3717 | G22: =COUNTIFS('Customer List w Software'!$B$4:$B$310,"Former client",'Customer List w Software'!$X$4:$X$310,$B22) -> 2 | H22: =SUMIFS('Customer List w Software'!$K$4:$K$310,'Customer List w Software'!$B$4:$B$310,"Former client",'Customer List w Software'!$X$4:$X$310,$B22) -> 0 | I22: =IFERROR(AVERAGEIFS('Customer List w Software'!$J$4:$J$310,'Customer List w Software'!$B$4:$B$310,"Former client",'Customer List w Software'!$X$4:$X$310,$B22),0) -> 459 | K22: =C22+G22 -> 50 | L22: =D22+H22 -> 829 | M22: =K22/K$29 -> 0.16286645
B23: OwnerRez | C23: =COUNTIFS('Customer List w Software'!$B$4:$B$310,"<>Former client",'Customer List w Software'!$X$4:$X$310,$B23) -> 24 | D23: =SUMIFS('Customer List w Software'!$K$4:$K$310,'Customer List w Software'!$B$4:$B$310,"<>Former client",'Customer List w Software'!$X$4:$X$310,$B23) -> 438 | E23: =IFERROR(AVERAGEIFS('Customer List w Software'!$J$4:$J$310,'Customer List w Software'!$B$4:$B$310,"<>Former client",'Customer List w Software'!$X$4:$X$310,$B23),0) -> 1275.3854 | G23: =COUNTIFS('Customer List w Software'!$B$4:$B$310,"Former client",'Customer List w Software'!$X$4:$X$310,$B23) -> 5 | H23: =SUMIFS('Customer List w Software'!$K$4:$K$310,'Customer List w Software'!$B$4:$B$310,"Former client",'Customer List w Software'!$X$4:$X$310,$B23) -> 48 | I23: =IFERROR(AVERAGEIFS('Customer List w Software'!$J$4:$J$310,'Customer List w Software'!$B$4:$B$310,"Former client",'Customer List w Software'!$X$4:$X$310,$B23),0) -> 833.16667 | K23: =C23+G23 -> 29 | L23: =D23+H23 -> 486 | M23: =K23/K$29 -> 0.094462541
B24: Hostaway | C24: =COUNTIFS('Customer List w Software'!$B$4:$B$310,"<>Former client",'Customer List w Software'!$X$4:$X$310,$B24) -> 20 | D24: =SUMIFS('Customer List w Software'!$K$4:$K$310,'Customer List w Software'!$B$4:$B$310,"<>Former client",'Customer List w Software'!$X$4:$X$310,$B24) -> 544 | E24: =IFERROR(AVERAGEIFS('Customer List w Software'!$J$4:$J$310,'Customer List w Software'!$B$4:$B$310,"<>Former client",'Customer List w Software'!$X$4:$X$310,$B24),0) -> 1667.55 | G24: =COUNTIFS('Customer List w Software'!$B$4:$B$310,"Former client",'Customer List w Software'!$X$4:$X$310,$B24) -> 2 | H24: =SUMIFS('Customer List w Software'!$K$4:$K$310,'Customer List w Software'!$B$4:$B$310,"Former client",'Customer List w Software'!$X$4:$X$310,$B24) -> 29 | I24: =IFERROR(AVERAGEIFS('Customer List w Software'!$J$4:$J$310,'Customer List w Software'!$B$4:$B$310,"Former client",'Customer List w Software'!$X$4:$X$310,$B24),0) -> 375 | K24: =C24+G24 -> 22 | L24: =D24+H24 -> 573 | M24: =K24/K$29 -> 0.071661238
B25: Hostfully | C25: =COUNTIFS('Customer List w Software'!$B$4:$B$310,"<>Former client",'Customer List w Software'!$X$4:$X$310,$B25) -> 8 | D25: =SUMIFS('Customer List w Software'!$K$4:$K$310,'Customer List w Software'!$B$4:$B$310,"<>Former client",'Customer List w Software'!$X$4:$X$310,$B25) -> 152 | E25: =IFERROR(AVERAGEIFS('Customer List w Software'!$J$4:$J$310,'Customer List w Software'!$B$4:$B$310,"<>Former client",'Customer List w Software'!$X$4:$X$310,$B25),0) -> 1303.4375 | G25: =COUNTIFS('Customer List w Software'!$B$4:$B$310,"Former client",'Customer List w Software'!$X$4:$X$310,$B25) -> 0 | H25: =SUMIFS('Customer List w Software'!$K$4:$K$310,'Customer List w Software'!$B$4:$B$310,"Former client",'Customer List w Software'!$X$4:$X$310,$B25) -> 0 | I25: =IFERROR(AVERAGEIFS('Customer List w Software'!$J$4:$J$310,'Customer List w Software'!$B$4:$B$310,"Former client",'Customer List w Software'!$X$4:$X$310,$B25),0) -> 0 | K25: =C25+G25 -> 8 | L25: =D25+H25 -> 152 | M25: =K25/K$29 -> 0.026058632
B26: Lodgify | C26: =COUNTIFS('Customer List w Software'!$B$4:$B$310,"<>Former client",'Customer List w Software'!$X$4:$X$310,$B26) -> 1 | D26: =SUMIFS('Customer List w Software'!$K$4:$K$310,'Customer List w Software'!$B$4:$B$310,"<>Former client",'Customer List w Software'!$X$4:$X$310,$B26) -> 29 | E26: =IFERROR(AVERAGEIFS('Customer List w Software'!$J$4:$J$310,'Customer List w Software'!$B$4:$B$310,"<>Former client",'Customer List w Software'!$X$4:$X$310,$B26),0) -> 2639 | G26: =COUNTIFS('Customer List w Software'!$B$4:$B$310,"Former client",'Customer List w Software'!$X$4:$X$310,$B26) -> 0 | H26: =SUMIFS('Customer List w Software'!$K$4:$K$310,'Customer List w Software'!$B$4:$B$310,"Former client",'Customer List w Software'!$X$4:$X$310,$B26) -> 0 | I26: =IFERROR(AVERAGEIFS('Customer List w Software'!$J$4:$J$310,'Customer List w Software'!$B$4:$B$310,"Former client",'Customer List w Software'!$X$4:$X$310,$B26),0) -> 0 | K26: =C26+G26 -> 1 | L26: =D26+H26 -> 29 | M26: =K26/K$29 -> 0.003257329
B27: Multiple Platforms | C27: =COUNTIFS('Customer List w Software'!$B$4:$B$310,"<>Former client",'Customer List w Software'!$X$4:$X$310,"*,*") -> 4 | D27: =SUMIFS('Customer List w Software'!$K$4:$K$310,'Customer List w Software'!$B$4:$B$310,"<>Former client",'Customer List w Software'!$X$4:$X$310,"*,*") -> 98 | E27: =IFERROR(AVERAGEIFS('Customer List w Software'!$J$4:$J$310,'Customer List w Software'!$B$4:$B$310,"<>Former client",'Customer List w Software'!$X$4:$X$310,"*,*"),0) -> 1695.7042 | G27: =COUNTIFS('Customer List w Software'!$B$4:$B$310,"Former client",'Customer List w Software'!$X$4:$X$310,"*,*") -> 0 | H27: =SUMIFS('Customer List w Software'!$K$4:$K$310,'Customer List w Software'!$B$4:$B$310,"Former client",'Customer List w Software'!$X$4:$X$310,"*,*") -> 0 | I27: =IFERROR(AVERAGEIFS('Customer List w Software'!$J$4:$J$310,'Customer List w Software'!$B$4:$B$310,"Former client",'Customer List w Software'!$X$4:$X$310,"*,*"),0) -> 0 | K27: =C27+G27 -> 4 | L27: =D27+H27 -> 98 | M27: =K27/K$29 -> 0.013029316
B28: None | C28: =COUNTIFS('Customer List w Software'!$B$4:$B$310,"<>Former client",'Customer List w Software'!$X$4:$X$310,"") -> 18 | D28: =SUMIFS('Customer List w Software'!$K$4:$K$310,'Customer List w Software'!$B$4:$B$310,"<>Former client",'Customer List w Software'!$X$4:$X$310,"") -> 329 | E28: =IFERROR(AVERAGEIFS('Customer List w Software'!$J$4:$J$310,'Customer List w Software'!$B$4:$B$310,"<>Former client",'Customer List w Software'!$X$4:$X$310,""),0) -> 1076.0017 | G28: =COUNTIFS('Customer List w Software'!$B$4:$B$310,"Former client",'Customer List w Software'!$X$4:$X$310,"") -> 118 | H28: =SUMIFS('Customer List w Software'!$K$4:$K$310,'Customer List w Software'!$B$4:$B$310,"Former client",'Customer List w Software'!$X$4:$X$310,"") -> 307 | I28: =IFERROR(AVERAGEIFS('Customer List w Software'!$J$4:$J$310,'Customer List w Software'!$B$4:$B$310,"Former client",'Customer List w Software'!$X$4:$X$310,""),0) -> 619.96671 | K28: =C28+G28 -> 136 | L28: =D28+H28 -> 636 | M28: =K28/K$29 -> 0.44299674
B29: Total Clients | C29: =COUNTIFS('Customer List w Software'!$B$4:$B$310,"<>Former client") -> 174 | D29: =SUMIFS('Customer List w Software'!$K$4:$K$310,'Customer List w Software'!$B$4:$B$310,"<>Former client") -> 3757 | E29: =AVERAGEIFS('Customer List w Software'!$J$4:$J$310,'Customer List w Software'!$B$4:$B$310,"<>Former client") -> 1380.6344 | G29: =COUNTIFS('Customer List w Software'!$B$4:$B$310,"Former client") -> 133 | H29: =SUMIFS('Customer List w Software'!$K$4:$K$310,'Customer List w Software'!$B$4:$B$310,"Former client") -> 454 | I29: =AVERAGEIFS('Customer List w Software'!$J$4:$J$310,'Customer List w Software'!$B$4:$B$310,"Former client") -> 637.95417 | K29: =C29+G29 -> 307 | L29: =D29+H29 -> 4211 | M29: =K29/K$29 -> 1
B31: Expense Tool
B32: Topkey | C32: =COUNTIFS('Customer List w Software'!$B$4:$B$310,"<>Former client",'Customer List w Software'!$Y$4:$Y$310,$B32) -> 48 | D32: =SUMIFS('Customer List w Software'!$K$4:$K$310,'Customer List w Software'!$B$4:$B$310,"<>Former client",'Customer List w Software'!$Y$4:$Y$310,$B32) -> 1841 | E32: =IFERROR(AVERAGEIFS('Customer List w Software'!$J$4:$J$310,'Customer List w Software'!$B$4:$B$310,"<>Former client",'Customer List w Software'!$Y$4:$Y$310,$B32),0) -> 2389.2051 | G32: =COUNTIFS('Customer List w Software'!$B$4:$B$310,"Former client",'Customer List w Software'!$Y$4:$Y$310,$B32) -> 4 | H32: =SUMIFS('Customer List w Software'!$K$4:$K$310,'Customer List w Software'!$B$4:$B$310,"Former client",'Customer List w Software'!$Y$4:$Y$310,$B32) -> 120 | I32: =IFERROR(AVERAGEIFS('Customer List w Software'!$J$4:$J$310,'Customer List w Software'!$B$4:$B$310,"Former client",'Customer List w Software'!$Y$4:$Y$310,$B32),0) -> 2159.8333 | K32: =C32+G32 -> 52 | L32: =D32+H32 -> 1961 | M32: =K32/K$36 -> 0.16938111
B33: Bill.com | C33: =COUNTIFS('Customer List w Software'!$B$4:$B$310,"<>Former client",'Customer List w Software'!$Y$4:$Y$310,$B33) -> 12 | D33: =SUMIFS('Customer List w Software'!$K$4:$K$310,'Customer List w Software'!$B$4:$B$310,"<>Former client",'Customer List w Software'!$Y$4:$Y$310,$B33) -> 231 | E33: =IFERROR(AVERAGEIFS('Customer List w Software'!$J$4:$J$310,'Customer List w Software'!$B$4:$B$310,"<>Former client",'Customer List w Software'!$Y$4:$Y$310,$B33),0) -> 1409.9444 | G33: =COUNTIFS('Customer List w Software'!$B$4:$B$310,"Former client",'Customer List w Software'!$Y$4:$Y$310,$B33) -> 1 | H33: =SUMIFS('Customer List w Software'!$K$4:$K$310,'Customer List w Software'!$B$4:$B$310,"Former client",'Customer List w Software'!$Y$4:$Y$310,$B33) -> 0 | I33: =IFERROR(AVERAGEIFS('Customer List w Software'!$J$4:$J$310,'Customer List w Software'!$B$4:$B$310,"Former client",'Customer List w Software'!$Y$4:$Y$310,$B33),0) -> 540 | K33: =C33+G33 -> 13 | L33: =D33+H33 -> 231 | M33: =K33/K$36 -> 0.042345277
B34: Ramp | C34: =COUNTIFS('Customer List w Software'!$B$4:$B$310,"<>Former client",'Customer List w Software'!$Y$4:$Y$310,$B34) -> 0 | D34: =SUMIFS('Customer List w Software'!$K$4:$K$310,'Customer List w Software'!$B$4:$B$310,"<>Former client",'Customer List w Software'!$Y$4:$Y$310,$B34) -> 0 | E34: =IFERROR(AVERAGEIFS('Customer List w Software'!$J$4:$J$310,'Customer List w Software'!$B$4:$B$310,"<>Former client",'Customer List w Software'!$Y$4:$Y$310,$B34),0) -> 0 | G34: =COUNTIFS('Customer List w Software'!$B$4:$B$310,"Former client",'Customer List w Software'!$Y$4:$Y$310,$B34) -> 1 | H34: =SUMIFS('Customer List w Software'!$K$4:$K$310,'Customer List w Software'!$B$4:$B$310,"Former client",'Customer List w Software'!$Y$4:$Y$310,$B34) -> 0 | I34: =IFERROR(AVERAGEIFS('Customer List w Software'!$J$4:$J$310,'Customer List w Software'!$B$4:$B$310,"Former client",'Customer List w Software'!$Y$4:$Y$310,$B34),0) -> 486.33333 | K34: =C34+G34 -> 1 | L34: =D34+H34 -> 0 | M34: =K34/K$36 -> 0.003257329
B35: None | C35: =COUNTIFS('Customer List w Software'!$B$4:$B$310,"<>Former client",'Customer List w Software'!$Y$4:$Y$310,"") -> 114 | D35: =SUMIFS('Customer List w Software'!$K$4:$K$310,'Customer List w Software'!$B$4:$B$310,"<>Former client",'Customer List w Software'!$Y$4:$Y$310,"") -> 1685 | E35: =IFERROR(AVERAGEIFS('Customer List w Software'!$J$4:$J$310,'Customer List w Software'!$B$4:$B$310,"<>Former client",'Customer List w Software'!$Y$4:$Y$310,""),0) -> 952.88787 | G35: =COUNTIFS('Customer List w Software'!$B$4:$B$310,"Former client",'Customer List w Software'!$Y$4:$Y$310,"") -> 127 | H35: =SUMIFS('Customer List w Software'!$K$4:$K$310,'Customer List w Software'!$B$4:$B$310,"Former client",'Customer List w Software'!$Y$4:$Y$310,"") -> 334 | I35: =IFERROR(AVERAGEIFS('Customer List w Software'!$J$4:$J$310,'Customer List w Software'!$B$4:$B$310,"Former client",'Customer List w Software'!$Y$4:$Y$310,""),0) -> 591.98613 | K35: =C35+G35 -> 241 | L35: =D35+H35 -> 2019 | M35: =K35/K$36 -> 0.78501629
B36: Total Clients | C36: =COUNTIFS('Customer List w Software'!$B$4:$B$310,"<>Former client") -> 174 | D36: =SUMIFS('Customer List w Software'!$K$4:$K$310,'Customer List w Software'!$B$4:$B$310,"<>Former client") -> 3757 | E36: =AVERAGEIFS('Customer List w Software'!$J$4:$J$310,'Customer List w Software'!$B$4:$B$310,"<>Former client") -> 1380.6344 | G36: =COUNTIFS('Customer List w Software'!$B$4:$B$310,"Former client") -> 133 | H36: =SUMIFS('Customer List w Software'!$K$4:$K$310,'Customer List w Software'!$B$4:$B$310,"Former client") -> 454 | I36: =AVERAGEIFS('Customer List w Software'!$J$4:$J$310,'Customer List w Software'!$B$4:$B$310,"Former client") -> 637.95417 | K36: =C36+G36 -> 307 | L36: =D36+H36 -> 4211 | M36: =K36/K$36 -> 1
B38: Reference
B39: Current clients = status "Active" or "Onboarding"; Former clients = status "Former client"
B40: Active clients | C40: =COUNTIFS('Customer List w Software'!$B$4:$B$310,"Active") -> 163
B41: Onboarding clients | C41: =COUNTIFS('Customer List w Software'!$B$4:$B$310,"Onboarding") -> 11
B42: Note: "Multiple Platforms" captures clients listing two PMS platforms; property counts are blank for clients with no listing data, so Properties will understate for those rows.
B44: Tie-Out: Avg. Fee per Current Client | C44: Monthly | D44: Annual
B45: Software Overview — current clients (row 10) | C45: =+E10 -> 1380.6344 | D45: =C45*12 -> 16567.613
B46: Client Retention $ — avg. annual fee per client (Sep-26) | C46: =D46/12 -> 1355.1213 | D46: =+'Client Retention $'!AD16*1000 -> 16261.456
B47: Variance | C47: =C45-C46 -> 25.513115 | D47: =D45-D46 -> 306.15738
B48: Variance % | D48: =D47/D46 -> 0.018827181
B50: Reconciliation Drivers
B51: Client count — Customer List w Software (current) | C51: =+C10 -> 174
B52: Client count — Client Retention (Sep-26 avg. clients) | C52: =+'Client Retention'!AD15 -> 188
B53: Total monthly fees — Customer List w Software (current) | C53: =SUMIFS('Customer List w Software'!$J$4:$J$310,'Customer List w Software'!$B$4:$B$310,"<>Former client") -> 240230.39
B54: Total monthly fees — Client Retention $ (Sep-26 avg.) | C54: =+'Client Retention $'!AD15*1000 -> 254762.81
B55: Note: Client Retention $ is built on the Full Customer List "Active" flag (190 clients, ties to its ending monthly fees); this tab uses the status column on Customer List w Software (163 Active + 11 Onboarding). The 16-client / $17k monthly gap is the difference between those two universes.

Sheet Earnings Sensitivity Table
B2: =+Cover!B24 -> Keystone Bookkeepers
B3: Earnings & Valuation Sensitivity ($000s)
B5: Base Case Inputs
B6: Steady-State Adj. EBITDA (PF July'26) | C6: ='P&L Forecast'!$K$106 -> 551.16396
B7: Normalized Bookkeeper Staffing Cost | C7: ='P&L Forecast'!$C$185 -> 272.46938
B8: Current Bookkeeping Clients | C8: ='P&L Forecast'!$C$181 -> 177
B9: Target Load (Clients per Bookkeeper) | C9: ='P&L Forecast'!$C$182 -> 8
B10: Avg. Bookkeeper Compensation | C10: ='P&L Forecast'!$C$184 -> 12.315
B11: EV / EBITDA Multiple (base) | C11: 7
B13: Implied Valuation — Steady-State Adj. EBITDA × Multiple
C14: Steady-State Bookkeeper Load (Clients per Bookkeeper)
B15: EV / EBITDA Multiple | C15: =$C$9-3 -> 5 | D15: =$C$9-2 -> 6 | E15: =$C$9-1 -> 7 | F15: =$C$9+0 -> 8 | G15: =$C$9+1 -> 9 | H15: =$C$9+2 -> 10 | I15: =$C$9+3 -> 11
B16: =$C$11-2 -> 5 | C16: =($C$6+$C$7-($C$8/C$15)*$C$10)*$B16 -> 1938.4117 | D16: =($C$6+$C$7-($C$8/D$15)*$C$10)*$B16 -> 2301.7042 | E16: =($C$6+$C$7-($C$8/E$15)*$C$10)*$B16 -> 2561.1988 | F16: =($C$6+$C$7-($C$8/F$15)*$C$10)*$B16 -> 2755.8198 | G16: =($C$6+$C$7-($C$8/G$15)*$C$10)*$B16 -> 2907.1917 | H16: =($C$6+$C$7-($C$8/H$15)*$C$10)*$B16 -> 3028.2892 | I16: =($C$6+$C$7-($C$8/I$15)*$C$10)*$B16 -> 3127.3689
B17: =$C$11-1 -> 6 | C17: =($C$6+$C$7-($C$8/C$15)*$C$10)*$B17 -> 2326.094 | D17: =($C$6+$C$7-($C$8/D$15)*$C$10)*$B17 -> 2762.045 | E17: =($C$6+$C$7-($C$8/E$15)*$C$10)*$B17 -> 3073.4386 | F17: =($C$6+$C$7-($C$8/F$15)*$C$10)*$B17 -> 3306.9838 | G17: =($C$6+$C$7-($C$8/G$15)*$C$10)*$B17 -> 3488.63 | H17: =($C$6+$C$7-($C$8/H$15)*$C$10)*$B17 -> 3633.947 | I17: =($C$6+$C$7-($C$8/I$15)*$C$10)*$B17 -> 3752.8427
B18: =$C$11+0 -> 7 | C18: =($C$6+$C$7-($C$8/C$15)*$C$10)*$B18 -> 2713.7763 | D18: =($C$6+$C$7-($C$8/D$15)*$C$10)*$B18 -> 3222.3858 | E18: =($C$6+$C$7-($C$8/E$15)*$C$10)*$B18 -> 3585.6783 | F18: =($C$6+$C$7-($C$8/F$15)*$C$10)*$B18 -> 3858.1477 | G18: =($C$6+$C$7-($C$8/G$15)*$C$10)*$B18 -> 4070.0683 | H18: =($C$6+$C$7-($C$8/H$15)*$C$10)*$B18 -> 4239.6048 | I18: =($C$6+$C$7-($C$8/I$15)*$C$10)*$B18 -> 4378.3165
B19: =$C$11+1 -> 8 | C19: =($C$6+$C$7-($C$8/C$15)*$C$10)*$B19 -> 3101.4587 | D19: =($C$6+$C$7-($C$8/D$15)*$C$10)*$B19 -> 3682.7267 | E19: =($C$6+$C$7-($C$8/E$15)*$C$10)*$B19 -> 4097.9181 | F19: =($C$6+$C$7-($C$8/F$15)*$C$10)*$B19 -> 4409.3117 | G19: =($C$6+$C$7-($C$8/G$15)*$C$10)*$B19 -> 4651.5067 | H19: =($C$6+$C$7-($C$8/H$15)*$C$10)*$B19 -> 4845.2627 | I19: =($C$6+$C$7-($C$8/I$15)*$C$10)*$B19 -> 5003.7903
B20: =$C$11+2 -> 9 | C20: =($C$6+$C$7-($C$8/C$15)*$C$10)*$B20 -> 3489.141 | D20: =($C$6+$C$7-($C$8/D$15)*$C$10)*$B20 -> 4143.0675 | E20: =($C$6+$C$7-($C$8/E$15)*$C$10)*$B20 -> 4610.1579 | F20: =($C$6+$C$7-($C$8/F$15)*$C$10)*$B20 -> 4960.4756 | G20: =($C$6+$C$7-($C$8/G$15)*$C$10)*$B20 -> 5232.945 | H20: =($C$6+$C$7-($C$8/H$15)*$C$10)*$B20 -> 5450.9205 | I20: =($C$6+$C$7-($C$8/I$15)*$C$10)*$B20 -> 5629.2641
B22: Estimated Steady-State Adj. EBITDA
C23: Steady-State Bookkeeper Load (Clients per Bookkeeper)
B24: Avg. Bookkeeper Compensation | C24: =C$15 -> 5 | D24: =D$15 -> 6 | E24: =E$15 -> 7 | F24: =F$15 -> 8 | G24: =G$15 -> 9 | H24: =H$15 -> 10 | I24: =I$15 -> 11
B25: =$C$10-2 -> 10.315 | C25: =$C$6+$C$7-($C$8/C$24)*$B25 -> 458.48233 | D25: =$C$6+$C$7-($C$8/D$24)*$B25 -> 519.34083 | E25: =$C$6+$C$7-($C$8/E$24)*$B25 -> 562.81119 | F25: =$C$6+$C$7-($C$8/F$24)*$B25 -> 595.41396 | G25: =$C$6+$C$7-($C$8/G$24)*$B25 -> 620.77167 | H25: =$C$6+$C$7-($C$8/H$24)*$B25 -> 641.05783 | I25: =$C$6+$C$7-($C$8/I$24)*$B25 -> 657.65561
B26: =$C$10-1 -> 11.315 | C26: =$C$6+$C$7-($C$8/C$24)*$B26 -> 423.08233 | D26: =$C$6+$C$7-($C$8/D$24)*$B26 -> 489.84083 | E26: =$C$6+$C$7-($C$8/E$24)*$B26 -> 537.52548 | F26: =$C$6+$C$7-($C$8/F$24)*$B26 -> 573.28896 | G26: =$C$6+$C$7-($C$8/G$24)*$B26 -> 601.105 | H26: =$C$6+$C$7-($C$8/H$24)*$B26 -> 623.35783 | I26: =$C$6+$C$7-($C$8/I$24)*$B26 -> 641.5647
B27: =$C$10+0 -> 12.315 | C27: =$C$6+$C$7-($C$8/C$24)*$B27 -> 387.68233 | D27: =$C$6+$C$7-($C$8/D$24)*$B27 -> 460.34083 | E27: =$C$6+$C$7-($C$8/E$24)*$B27 -> 512.23976 | F27: =$C$6+$C$7-($C$8/F$24)*$B27 -> 551.16396 | G27: =$C$6+$C$7-($C$8/G$24)*$B27 -> 581.43833 | H27: =$C$6+$C$7-($C$8/H$24)*$B27 -> 605.65783 | I27: =$C$6+$C$7-($C$8/I$24)*$B27 -> 625.47379
B28: =$C$10+1 -> 13.315 | C28: =$C$6+$C$7-($C$8/C$24)*$B28 -> 352.28233 | D28: =$C$6+$C$7-($C$8/D$24)*$B28 -> 430.84083 | E28: =$C$6+$C$7-($C$8/E$24)*$B28 -> 486.95405 | F28: =$C$6+$C$7-($C$8/F$24)*$B28 -> 529.03896 | G28: =$C$6+$C$7-($C$8/G$24)*$B28 -> 561.77167 | H28: =$C$6+$C$7-($C$8/H$24)*$B28 -> 587.95783 | I28: =$C$6+$C$7-($C$8/I$24)*$B28 -> 609.38288
B29: =$C$10+2 -> 14.315 | C29: =$C$6+$C$7-($C$8/C$24)*$B29 -> 316.88233 | D29: =$C$6+$C$7-($C$8/D$24)*$B29 -> 401.34083 | E29: =$C$6+$C$7-($C$8/E$24)*$B29 -> 461.66833 | F29: =$C$6+$C$7-($C$8/F$24)*$B29 -> 506.91396 | G29: =$C$6+$C$7-($C$8/G$24)*$B29 -> 542.105 | H29: =$C$6+$C$7-($C$8/H$24)*$B29 -> 570.25783 | I29: =$C$6+$C$7-($C$8/I$24)*$B29 -> 593.29197
B31: Reference — Observed Bookkeeper Load (Steady-State Staffing tab)
B32: FY2025 | C32: ='Steady-State Staffing'!C21 -> 7.3863636
B33: YTD2026 | C33: ='Steady-State Staffing'!D21 -> 5.056338
B34: LTM Sep'26 | C34: ='Steady-State Staffing'!F21 -> 5.3134328
B35: Jan-25 (peak) | C35: ='Steady-State Staffing'!H21 -> 11.230769
B36: Sep-26 (latest) | C36: ='Steady-State Staffing'!AB21 -> 4.4810127
B37: Note: load axis is the P&L Forecast target load (row 182) ±3 clients, bracketing the observed range above. Only the normalized bookkeeper staffing cost flexes; all other PF adj. EBITDA items are held constant.

Sheet P&L Overview (Target Version)
B2: =+Cover!B24 -> Keystone Bookkeepers
B3: Summary P&L Overview ($000s) | P3: Print | Q3: 1
C5: Full Year | F5: YTD | I5: LTM | K5: PF | M5: PF Delta
B6: P&L Summary | C6: 2024 | D6: 2025 | F6: July'25 | G6: July'26 | I6: July'25 | J6: July'26 | K6: July'26 | M6: ($) | N6: (%)
B7: Revenue
B8: =+'P&L Forecast'!B7 -> STR Subscription | C8: =+'P&L Forecast'!C7 -> 793.47225 | D8: =+'P&L Forecast'!D7 -> 1450.4923 | F8: =+'P&L Forecast'!F7 -> 751.5286 | G8: =+'P&L Forecast'!G7 -> 1261.4769 | I8: =+'P&L Forecast'!I7 -> 1152.3203 | J8: =+'P&L Forecast'!J7 -> 1960.4406 | K8: =+'P&L Forecast'!K7 -> 2410.05 | M8: =K8-J8 -> 449.6094 | N8: =IFERROR(K8/J8-1,0) -> 0.229341
B9: =+'P&L Forecast'!B8 -> Occupancy Taxes | C9: =+'P&L Forecast'!C8 -> 0.56 | D9: =+'P&L Forecast'!D8 -> 55.0805 | F9: =+'P&L Forecast'!F8 -> 23.2255 | G9: =+'P&L Forecast'!G8 -> 91.65114 | I9: =+'P&L Forecast'!I8 -> 23.7855 | J9: =+'P&L Forecast'!J8 -> 123.50614 | K9: =+'P&L Forecast'!K8 -> 192.8298 | M9: =K9-J9 -> 69.32366 | N9: =IFERROR(K9/J9-1,0) -> 0.56129728
B10: =+'P&L Forecast'!B9 -> SMB Subscription | C10: =+'P&L Forecast'!C9 -> 224.791 | D10: =+'P&L Forecast'!D9 -> 149.77 | F10: =+'P&L Forecast'!F9 -> 90.4525 | G10: =+'P&L Forecast'!G9 -> 73.4185 | I10: =+'P&L Forecast'!I9 -> 169.5465 | J10: =+'P&L Forecast'!J9 -> 132.736 | K10: =+'P&L Forecast'!K9 -> 16.2 | M10: =K10-J10 -> -116.536 | N10: =IFERROR(K10/J10-1,0) -> -0.87795323
B11: =+'P&L Forecast'!B10 -> Onboarding | C11: =+'P&L Forecast'!C10 -> 44.0585 | D11: =+'P&L Forecast'!D10 -> 74.5193 | F11: =+'P&L Forecast'!F10 -> 42.25405 | G11: =+'P&L Forecast'!G10 -> 59.055 | I11: =+'P&L Forecast'!I10 -> 57.49255 | J11: =+'P&L Forecast'!J10 -> 91.32025 | K11: =+'P&L Forecast'!K10 -> 103.5675 | M11: =K11-J11 -> 12.24725 | N11: =IFERROR(K11/J11-1,0) -> 0.13411319
B12: =+'P&L Forecast'!B11 -> Topkey Subscription | C12: =+'P&L Forecast'!C11 -> 0 | D12: =+'P&L Forecast'!D11 -> 9.947 | F12: =+'P&L Forecast'!F11 -> 0 | G12: =+'P&L Forecast'!G11 -> 45.086 | I12: =+'P&L Forecast'!I11 -> 0 | J12: =+'P&L Forecast'!J11 -> 55.033 | K12: =+'P&L Forecast'!K11 -> 94.836 | M12: =K12-J12 -> 39.803 | N12: =IFERROR(K12/J12-1,0) -> 0.72325695
B13: =+'P&L Forecast'!B12 -> STR Bill Pay | C13: =+'P&L Forecast'!C12 -> 0.06 | D13: =+'P&L Forecast'!D12 -> 36.6065 | F13: =+'P&L Forecast'!F12 -> 15.4915 | G13: =+'P&L Forecast'!G12 -> 45.13 | I13: =+'P&L Forecast'!I12 -> 15.5515 | J13: =+'P&L Forecast'!J12 -> 66.245 | K13: =+'P&L Forecast'!K12 -> 83.46 | M13: =K13-J13 -> 17.215 | N13: =IFERROR(K13/J13-1,0) -> 0.25986867
B14: =+'P&L Forecast'!B13 -> Controller Services | C14: =+'P&L Forecast'!C13 -> 13.75 | D14: =+'P&L Forecast'!D13 -> 46.4 | F14: =+'P&L Forecast'!F13 -> 31.5 | G14: =+'P&L Forecast'!G13 -> 24.25 | I14: =+'P&L Forecast'!I13 -> 44 | J14: =+'P&L Forecast'!J13 -> 39.15 | K14: =+'P&L Forecast'!K13 -> 42 | M14: =K14-J14 -> 2.85 | N14: =IFERROR(K14/J14-1,0) -> 0.072796935
B15: Other Revenue | C15: =+C16-SUM(C8:C14) -> 58.2741 | D15: =+D16-SUM(D8:D14) -> 56.56748 | F15: =+F16-SUM(F8:F14) -> 43.42095 | G15: =+G16-SUM(G8:G14) -> 70.95371 | I15: =+I16-SUM(I8:I14) -> 61.71435 | J15: =+J16-SUM(J8:J14) -> 84.10024 | K15: =+K16-SUM(K8:K14) -> 55.59772 | M15: =K15-J15 -> -28.50252 | N15: =IFERROR(K15/J15-1,0) -> -0.33891128
B16: Total Revenue | C16: =+'P&L Forecast'!C24 -> 1134.9659 | D16: =+'P&L Forecast'!D24 -> 1879.3831 | F16: =+'P&L Forecast'!F24 -> 997.8731 | G16: =+'P&L Forecast'!G24 -> 1671.0212 | I16: =+'P&L Forecast'!I24 -> 1524.4107 | J16: =+'P&L Forecast'!J24 -> 2552.5312 | K16: =+'P&L Forecast'!K24 -> 2998.541 | M16: =SUM(M8:M15) -> 446.00979 | N16: =IFERROR(K16/J16-1,0) -> 0.17473235
B18: Expenses
B19: =+'P&L Forecast'!B31 -> Indirect Labor | C19: =+'P&L Forecast'!C31 -> 101.3752 | D19: =+'P&L Forecast'!D31 -> 281.24054 | F19: =+'P&L Forecast'!F31 -> 136.29648 | G19: =+'P&L Forecast'!G31 -> 357.27472 | I19: =+'P&L Forecast'!I31 -> 202.41598 | J19: =+'P&L Forecast'!J31 -> 502.21878 | K19: =+'P&L Forecast'!K31 -> 681.3 | M19: =K19-J19 -> 179.08122 | N19: =IFERROR(K19/J19-1,0) -> 0.35658009
B20: =+'P&L Forecast'!B32 -> Bookkeeper Wages | C20: =+'P&L Forecast'!C32 -> 183.36903 | D20: =+'P&L Forecast'!D32 -> 316.18462 | F20: =+'P&L Forecast'!F32 -> 147.26813 | G20: =+'P&L Forecast'!G32 -> 267.7574 | I20: =+'P&L Forecast'!I32 -> 240.18098 | J20: =+'P&L Forecast'!J32 -> 436.67389 | K20: =+'P&L Forecast'!K32 -> 492.6 | M20: =K20-J20 -> 55.92611 | N20: =IFERROR(K20/J20-1,0) -> 0.12807294
B21: =+'P&L Forecast'!B33 -> Client Lead Wages | C21: =+'P&L Forecast'!C33 -> 286.16129 | D21: =+'P&L Forecast'!D33 -> 352.95844 | F21: =+'P&L Forecast'!F33 -> 201.27983 | G21: =+'P&L Forecast'!G33 -> 202.05309 | I21: =+'P&L Forecast'!I33 -> 353.12843 | J21: =+'P&L Forecast'!J33 -> 353.7317 | K21: =+'P&L Forecast'!K33 -> 392.92452 | M21: =K21-J21 -> 39.19282 | N21: =IFERROR(K21/J21-1,0) -> 0.11079816
B22: =+'P&L Forecast'!B34 -> Onboarding Team Wages | C22: =+'P&L Forecast'!C34 -> 122.81255 | D22: =+'P&L Forecast'!D34 -> 152.16972 | F22: =+'P&L Forecast'!F34 -> 73.94962 | G22: =+'P&L Forecast'!G34 -> 111.27999 | I22: =+'P&L Forecast'!I34 -> 121.30735 | J22: =+'P&L Forecast'!J34 -> 189.50009 | K22: =+'P&L Forecast'!K34 -> 197.14944 | M22: =K22-J22 -> 7.64935 | N22: =IFERROR(K22/J22-1,0) -> 0.040365944
B23: =+'P&L Forecast'!B35 -> Owner Wages | C23: =+'P&L Forecast'!C35 -> 0 | D23: =+'P&L Forecast'!D35 -> 90.66704 | F23: =+'P&L Forecast'!F35 -> 45.46612 | G23: =+'P&L Forecast'!G35 -> 63.14302 | I23: =+'P&L Forecast'!I35 -> 45.46612 | J23: =+'P&L Forecast'!J35 -> 108.34394 | K23: =+'P&L Forecast'!K35 -> 108.34394 | M23: =K23-J23 -> 0 | N23: =IFERROR(K23/J23-1,0) -> 0
B24: =+'P&L Forecast'!B36 -> S&M Wages | C24: =+'P&L Forecast'!C36 -> 0 | D24: =+'P&L Forecast'!D36 -> 19.14963 | F24: =+'P&L Forecast'!F36 -> 3.09945 | G24: =+'P&L Forecast'!G36 -> 51.94131 | I24: =+'P&L Forecast'!I36 -> 3.09945 | J24: =+'P&L Forecast'!J36 -> 67.99149 | K24: =+'P&L Forecast'!K36 -> 98.34912 | M24: =K24-J24 -> 30.35763 | N24: =IFERROR(K24/J24-1,0) -> 0.44649161
B25: =+'P&L Forecast'!B37 -> Occupancy Tax Specialist | C25: =+'P&L Forecast'!C37 -> 1.11335 | D25: =+'P&L Forecast'!D37 -> 29.56415 | F25: =+'P&L Forecast'!F37 -> 14.27585 | G25: =+'P&L Forecast'!G37 -> 42.08505 | I25: =+'P&L Forecast'!I37 -> 15.3892 | J25: =+'P&L Forecast'!J37 -> 57.37335 | K25: =+'P&L Forecast'!K37 -> 58.2 | M25: =K25-J25 -> 0.82665 | N25: =IFERROR(K25/J25-1,0) -> 0.014408257
B26: =+'P&L Forecast'!B38 -> Sr. Client Lead Wages | C26: =+'P&L Forecast'!C38 -> 0 | D26: =+'P&L Forecast'!D38 -> 0 | F26: =+'P&L Forecast'!F38 -> 0 | G26: =+'P&L Forecast'!G38 -> 7.995 | I26: =+'P&L Forecast'!I38 -> 0 | J26: =+'P&L Forecast'!J38 -> 7.995 | K26: =+'P&L Forecast'!K38 -> 33.08124 | M26: =K26-J26 -> 25.08624 | N26: =IFERROR(K26/J26-1,0) -> 3.1377411
B27: =+'P&L Forecast'!B39 -> Employee Benefits | C27: =+'P&L Forecast'!C39 -> 5.37405 | D27: =+'P&L Forecast'!D39 -> 19.23245 | F27: =+'P&L Forecast'!F39 -> 9.02166 | G27: =+'P&L Forecast'!G39 -> 17.36251 | I27: =+'P&L Forecast'!I39 -> 12.16686 | J27: =+'P&L Forecast'!J39 -> 27.5733 | K27: =+'P&L Forecast'!K39 -> 32.17836 | M27: =K27-J27 -> 4.60506 | N27: =IFERROR(K27/J27-1,0) -> 0.16701157
B28: =+'P&L Forecast'!B40 -> Total Payroll Expenses | C28: =SUM(C19:C27) -> 700.20547 | D28: =SUM(D19:D27) -> 1261.1666 | F28: =SUM(F19:F27) -> 630.65714 | G28: =SUM(G19:G27) -> 1120.8921 | I28: =SUM(I19:I27) -> 993.15437 | J28: =SUM(J19:J27) -> 1751.4015 | K28: =SUM(K19:K27) -> 2094.1266 | M28: =SUM(M19:M27) -> 342.72508 | N28: =K28/J28-1 -> 0.19568618
B30: =+'P&L Forecast'!B42 -> Software & Apps - COGS | C30: =+'P&L Forecast'!C42 -> 114.42269 | D30: =+'P&L Forecast'!D42 -> 157.49471 | F30: =+'P&L Forecast'!F42 -> 84.96859 | G30: =+'P&L Forecast'!G42 -> 152.28157 | I30: =+'P&L Forecast'!I42 -> 142.28345 | J30: =+'P&L Forecast'!J42 -> 224.80769 | K30: =+'P&L Forecast'!K42 -> 335.70816 | M30: =K30-J30 -> 110.90047 | N30: =IFERROR(K30/J30-1,0) -> 0.49331262
B31: =+'P&L Forecast'!B43 -> Software & Apps - G&A | C31: =+'P&L Forecast'!C43 -> 60.91594 | D31: =+'P&L Forecast'!D43 -> 117.05866 | F31: =+'P&L Forecast'!F43 -> 56.8115 | G31: =+'P&L Forecast'!G43 -> 97.04798 | I31: =+'P&L Forecast'!I43 -> 86.51489 | J31: =+'P&L Forecast'!J43 -> 157.29514 | K31: =+'P&L Forecast'!K43 -> 155.82264 | M31: =K31-J31 -> -1.4725 | N31: =IFERROR(K31/J31-1,0) -> -0.0093613827
B32: =+'P&L Forecast'!B44 -> Software & Apps - Topkey | C32: =+'P&L Forecast'!C44 -> 0 | D32: =+'P&L Forecast'!D44 -> 7.14125 | F32: =+'P&L Forecast'!F44 -> 0 | G32: =+'P&L Forecast'!G44 -> 28.82775 | I32: =+'P&L Forecast'!I44 -> 0 | J32: =+'P&L Forecast'!J44 -> 35.969 | K32: =+'P&L Forecast'!K44 -> 60.84 | M32: =K32-J32 -> 24.871 | N32: =IFERROR(K32/J32-1,0) -> 0.69145653
B33: =+'P&L Forecast'!B45 -> Software & Apps - AI tools | C33: =+'P&L Forecast'!C45 -> 0 | D33: =+'P&L Forecast'!D45 -> 0 | F33: =+'P&L Forecast'!F45 -> 0 | G33: =+'P&L Forecast'!G45 -> 6.52752 | I33: =+'P&L Forecast'!I45 -> 0 | J33: =+'P&L Forecast'!J45 -> 6.52752 | K33: =+'P&L Forecast'!K45 -> 15.74376 | M33: =K33-J33 -> 9.21624 | N33: =IFERROR(K33/J33-1,0) -> 1.4119053
B34: =+'P&L Forecast'!B46 -> Total Software Expenses | C34: =SUM(C30:C33) -> 175.33863 | D34: =SUM(D30:D33) -> 281.69462 | F34: =SUM(F30:F33) -> 141.78009 | G34: =SUM(G30:G33) -> 284.68482 | I34: =SUM(I30:I33) -> 228.79834 | J34: =SUM(J30:J33) -> 424.59935 | K34: =SUM(K30:K33) -> 568.11456 | M34: =SUM(M30:M33) -> 143.51521 | N34: =K34/J34-1 -> 0.33800148
B36: =+'P&L Forecast'!B48 -> Other Professional Fees | C36: =+'P&L Forecast'!C48 -> 18.23425 | D36: =+'P&L Forecast'!D48 -> 27.04095 | F36: =+'P&L Forecast'!F48 -> 12.014 | G36: =+'P&L Forecast'!G48 -> 57.55 | I36: =+'P&L Forecast'!I48 -> 21.74858 | J36: =+'P&L Forecast'!J48 -> 72.57695 | K36: =+'P&L Forecast'!K48 -> 72.57695 | M36: =K36-J36 -> 0 | N36: =IFERROR(K36/J36-1,0) -> 0
B37: =+'P&L Forecast'!B49 -> Referral Fees | C37: =+'P&L Forecast'!C49 -> 24.82 | D37: =+'P&L Forecast'!D49 -> 27.15374 | F37: =+'P&L Forecast'!F49 -> 17.0895 | G37: =+'P&L Forecast'!G49 -> 20.62969 | I37: =+'P&L Forecast'!I49 -> 26.2095 | J37: =+'P&L Forecast'!J49 -> 30.69393 | K37: =+'P&L Forecast'!K49 -> 30.69393 | M37: =K37-J37 -> 0 | N37: =IFERROR(K37/J37-1,0) -> 0
B38: =+'P&L Forecast'!B50 -> Travel, Meals & Entertainment | C38: =+'P&L Forecast'!C50 -> 0 | D38: =+'P&L Forecast'!D50 -> 29.76122 | F38: =+'P&L Forecast'!F50 -> 22.29558 | G38: =+'P&L Forecast'!G50 -> 20.68542 | I38: =+'P&L Forecast'!I50 -> 22.29558 | J38: =+'P&L Forecast'!J50 -> 28.15106 | K38: =+'P&L Forecast'!K50 -> 28.15106 | M38: =K38-J38 -> 0 | N38: =IFERROR(K38/J38-1,0) -> 0
B39: =+'P&L Forecast'!B51 -> Payment Collection Fees | C39: =+'P&L Forecast'!C51 -> 8.67099 | D39: =+'P&L Forecast'!D51 -> 13.35153 | F39: =+'P&L Forecast'!F51 -> 6.80445 | G39: =+'P&L Forecast'!G51 -> 9.02684 | I39: =+'P&L Forecast'!I51 -> 10.54373 | J39: =+'P&L Forecast'!J51 -> 15.57392 | K39: =+'P&L Forecast'!K51 -> 15.57392 | M39: =K39-J39 -> 0 | N39: =IFERROR(K39/J39-1,0) -> 0
B40: =+'P&L Forecast'!B52 -> Professional Organizations | C40: =+'P&L Forecast'!C52 -> 5.44332 | D40: =+'P&L Forecast'!D52 -> 11.22296 | F40: =+'P&L Forecast'!F52 -> 6.191 | G40: =+'P&L Forecast'!G52 -> 6.57881 | I40: =+'P&L Forecast'!I52 -> 9.53268 | J40: =+'P&L Forecast'!J52 -> 11.61077 | K40: =+'P&L Forecast'!K52 -> 11.61077 | M40: =K40-J40 -> 0 | N40: =IFERROR(K40/J40-1,0) -> 0
B41: =+'P&L Forecast'!B53 -> S&M Events | C41: =+'P&L Forecast'!C53 -> 0 | D41: =+'P&L Forecast'!D53 -> 11.4983 | F41: =+'P&L Forecast'!F53 -> 0 | G41: =+'P&L Forecast'!G53 -> 11.84548 | I41: =+'P&L Forecast'!I53 -> 0 | J41: =+'P&L Forecast'!J53 -> 23.34378 | K41: =+'P&L Forecast'!K53 -> 23.34378 | M41: =K41-J41 -> 0 | N41: =IFERROR(K41/J41-1,0) -> 0
B42: =+'P&L Forecast'!B54 -> Contract Labor - Tax | C42: =+'P&L Forecast'!C54 -> 0 | D42: =+'P&L Forecast'!D54 -> 1.5875 | F42: =+'P&L Forecast'!F54 -> 0 | G42: =+'P&L Forecast'!G54 -> 30.5155 | I42: =+'P&L Forecast'!I54 -> 0 | J42: =+'P&L Forecast'!J54 -> 32.103 | K42: =+'P&L Forecast'!K54 -> 38.7615 | M42: =K42-J42 -> 6.6585 | N42: =IFERROR(K42/J42-1,0) -> 0.20741052
B43: =+'P&L Forecast'!B55 -> Recruiting Fees | C43: =+'P&L Forecast'!C55 -> 14.90205 | D43: =+'P&L Forecast'!D55 -> 31.6041 | F43: =+'P&L Forecast'!F55 -> 28.29994 | G43: =+'P&L Forecast'!G55 -> 5.5646 | I43: =+'P&L Forecast'!I55 -> 35.34606 | J43: =+'P&L Forecast'!J55 -> 8.86876 | K43: =+'P&L Forecast'!K55 -> 8.86876 | M43: =K43-J43 -> 0 | N43: =IFERROR(K43/J43-1,0) -> 0
B44: Other Expenses | C44: =+C45-SUM(C36:C43) -> 41.87929 | D44: =+D45-SUM(D36:D43) -> 52.32132 | F44: =+F45-SUM(F36:F43) -> 28.90542 | G44: =+G45-SUM(G36:G43) -> 26.90445 | I44: =+I45-SUM(I36:I43) -> 41.76881 | J44: =+J45-SUM(J36:J43) -> 50.32035 | K44: =+K45-SUM(K36:K43) -> 56.05462 | M44: =K44-J44 -> 5.73427 | N44: =IFERROR(K44/J44-1,0) -> 0.11395529
B45: Total Overhead | C45: =+'P&L Forecast'!C66 -> 113.9499 | D45: =+'P&L Forecast'!D66 -> 205.54162 | F45: =+'P&L Forecast'!F66 -> 121.59989 | G45: =+'P&L Forecast'!G66 -> 189.30079 | I45: =+'P&L Forecast'!I66 -> 167.44494 | J45: =+'P&L Forecast'!J66 -> 273.24252 | K45: =+'P&L Forecast'!K66 -> 285.63529 | M45: =SUM(M36:M44) -> 12.39277 | N45: =K45/J45-1 -> 0.045354471
B47: Net Income | C47: =+C16-C28-C34-C45 -> 145.47185 | D47: =+D16-D28-D34-D45 -> 130.9803 | F47: =+F16-F28-F34-F45 -> 103.83598 | G47: =+G16-G28-G34-G45 -> 76.1435 | I47: =+I16-I28-I34-I45 -> 135.013 | J47: =+J16-J28-J34-J45 -> 103.28782 | K47: =+K16-K28-K34-K45 -> 50.66455 | M47: =+M16-M28-M34-M45 -> -52.62327 | N47: =IFERROR(K47/J47-1,0) -> -0.50948185
B48: % Margin | C48: =C47/C$16 -> 0.12817289 | D48: =D47/D$16 -> 0.06969324 | F48: =F47/F$16 -> 0.1040573 | G48: =G47/G$16 -> 0.045567046 | I48: =I47/I$16 -> 0.088567342 | J48: =J47/J$16 -> 0.04046486 | K48: =K47/K$16 -> 0.016896401 | M48: =M47/M$16 -> -0.1179868 | N48: 0

Sheet P&L Forecast
B2: =+Cover!B24 -> Keystone Bookkeepers
B3: Pre-LOI P&L Forecast ($000s)
B5: P&L Summary ($000s) | C5: FY2024 | D5: FY2025 | F5: July'25 YTD | G5: July'26 YTD | I5: Jul'25 LTM | J5: Jul'26 LTM | K5: Jul'26 PF | M5: Delta ($) | N5: Delta (%) | P5: 45292 | Q5: =EOMONTH(P5,0)+1 -> 45323 | R5: =EOMONTH(Q5,0)+1 -> 45352 | S5: =EOMONTH(R5,0)+1 -> 45383 | T5: =EOMONTH(S5,0)+1 -> 45413 | U5: =EOMONTH(T5,0)+1 -> 45444 | V5: =EOMONTH(U5,0)+1 -> 45474 | W5: =EOMONTH(V5,0)+1 -> 45505 | X5: =EOMONTH(W5,0)+1 -> 45536 | ... AT5: =EOMONTH(AS5,0)+1 -> 46204
A6: x | B6: Revenue
B7: STR Subscription | C7: =SUMIFS($P7:$AT7,$P$5:$AT$5,">"&C$199,$P$5:$AT$5,"<"&C$200) -> 793.47225 | D7: =SUMIFS($P7:$AT7,$P$5:$AT$5,">"&D$199,$P$5:$AT$5,"<"&D$200) -> 1450.4923 | F7: =SUMIFS($P7:$AT7,$P$5:$AT$5,">"&F$199,$P$5:$AT$5,"<"&F$200) -> 751.5286 | G7: =SUMIFS($P7:$AT7,$P$5:$AT$5,">"&G$199,$P$5:$AT$5,"<"&G$200) -> 1261.4769 | I7: =SUMIFS($P7:$AT7,$P$5:$AT$5,">"&I$199,$P$5:$AT$5,"<"&I$200) -> 1152.3203 | J7: =SUMIFS($P7:$AT7,$P$5:$AT$5,">"&J$199,$P$5:$AT$5,"<"&J$200) -> 1960.4406 | K7: =+C111 -> 2410.05 | M7: =K7-J7 -> 449.6094 | N7: =IFERROR(K7/J7-1,0) -> 0.229341 | P7: =SUMIFS('Combined P&L'!N:N,'Combined P&L'!$C:$C,'P&L Forecast'!$B7) -> 44.6835 | Q7: =SUMIFS('Combined P&L'!O:O,'Combined P&L'!$C:$C,'P&L Forecast'!$B7) -> 47.046 | R7: =SUMIFS('Combined P&L'!P:P,'Combined P&L'!$C:$C,'P&L Forecast'!$B7) -> 52.47 | S7: =SUMIFS('Combined P&L'!Q:Q,'Combined P&L'!$C:$C,'P&L Forecast'!$B7) -> 57.1697 | T7: =SUMIFS('Combined P&L'!R:R,'Combined P&L'!$C:$C,'P&L Forecast'!$B7) -> 57.51415 | U7: =SUMIFS('Combined P&L'!S:S,'Combined P&L'!$C:$C,'P&L Forecast'!$B7) -> 65.516 | V7: =SUMIFS('Combined P&L'!T:T,'Combined P&L'!$C:$C,'P&L Forecast'!$B7) -> 68.28125 | W7: =SUMIFS('Combined P&L'!U:U,'Combined P&L'!$C:$C,'P&L Forecast'!$B7) -> 73.25135 | X7: =SUMIFS('Combined P&L'!V:V,'Combined P&L'!$C:$C,'P&L Forecast'!$B7) -> 75.5517 | Y7: =SUMIFS('Combined P&L'!W:W,'Combined P&L'!$C:$C,'P&L Forecast'!$B7) -> 79.11325 | Z7: =SUMIFS('Combined P&L'!X:X,'Combined P&L'!$C:$C,'P&L Forecast'!$B7) -> 83.2908 | AA7: =SUMIFS('Combined P&L'!Y:Y,'Combined P&L'!$C:$C,'P&L Forecast'!$B7) -> 89.58455 | AB7: =SUMIFS('Combined P&L'!Z:Z,'Combined P&L'!$C:$C,'P&L Forecast'!$B7) -> 92.4189 | AC7: =SUMIFS('Combined P&L'!AA:AA,'Combined P&L'!$C:$C,'P&L Forecast'!$B7) -> 94.00215 | AD7: =SUMIFS('Combined P&L'!AB:AB,'Combined P&L'!$C:$C,'P&L Forecast'!$B7) -> 101.50605 | AE7: =SUMIFS('Combined P&L'!AC:AC,'Combined P&L'!$C:$C,'P&L Forecast'!$B7) -> 106.1375 | AF7: =SUMIFS('Combined P&L'!AD:AD,'Combined P&L'!$C:$C,'P&L Forecast'!$B7) -> 115.93875 | AG7: =SUMIFS('Combined P&L'!AE:AE,'Combined P&L'!$C:$C,'P&L Forecast'!$B7) -> 119.43125 | AH7: =SUMIFS('Combined P&L'!AF:AF,'Combined P&L'!$C:$C,'P&L Forecast'!$B7) -> 122.094 | AI7: =SUMIFS('Combined P&L'!AG:AG,'Combined P&L'!$C:$C,'P&L Forecast'!$B7) -> 130.08525 | AJ7: =SUMIFS('Combined P&L'!AH:AH,'Combined P&L'!$C:$C,'P&L Forecast'!$B7) -> 133.5905 | AK7: =SUMIFS('Combined P&L'!AI:AI,'Combined P&L'!$C:$C,'P&L Forecast'!$B7) -> 139.609 | AL7: =SUMIFS('Combined P&L'!AJ:AJ,'Combined P&L'!$C:$C,'P&L Forecast'!$B7) -> 145.28075 | AM7: =SUMIFS('Combined P&L'!AK:AK,'Combined P&L'!$C:$C,'P&L Forecast'!$B7) -> 150.39825 | AN7: =SUMIFS('Combined P&L'!AL:AL,'Combined P&L'!$C:$C,'P&L Forecast'!$B7) -> 156.5388 | AO7: =SUMIFS('Combined P&L'!AM:AM,'Combined P&L'!$C:$C,'P&L Forecast'!$B7) -> 164.9034 | AP7: =SUMIFS('Combined P&L'!AN:AN,'Combined P&L'!$C:$C,'P&L Forecast'!$B7) -> 170.34425 | AQ7: =SUMIFS('Combined P&L'!AO:AO,'Combined P&L'!$C:$C,'P&L Forecast'!$B7) -> 183.662 | AR7: =SUMIFS('Combined P&L'!AP:AP,'Combined P&L'!$C:$C,'P&L Forecast'!$B7) -> 190.7844 | AS7: =SUMIFS('Combined P&L'!AQ:AQ,'Combined P&L'!$C:$C,'P&L Forecast'!$B7) -> 194.4065 | AT7: =SUMIFS('Combined P&L'!AR:AR,'Combined P&L'!$C:$C,'P&L Forecast'!$B7) -> 200.8375
B8: Occupancy Taxes | C8: =SUMIFS($P8:$AT8,$P$5:$AT$5,">"&C$199,$P$5:$AT$5,"<"&C$200) -> 0.56 | D8: =SUMIFS($P8:$AT8,$P$5:$AT$5,">"&D$199,$P$5:$AT$5,"<"&D$200) -> 55.0805 | F8: =SUMIFS($P8:$AT8,$P$5:$AT$5,">"&F$199,$P$5:$AT$5,"<"&F$200) -> 23.2255 | G8: =SUMIFS($P8:$AT8,$P$5:$AT$5,">"&G$199,$P$5:$AT$5,"<"&G$200) -> 91.65114 | I8: =SUMIFS($P8:$AT8,$P$5:$AT$5,">"&I$199,$P$5:$AT$5,"<"&I$200) -> 23.7855 | J8: =SUMIFS($P8:$AT8,$P$5:$AT$5,">"&J$199,$P$5:$AT$5,"<"&J$200) -> 123.50614 | K8: =+C113 -> 192.8298 | M8: =K8-J8 -> 69.32366 | N8: =IFERROR(K8/J8-1,0) -> 0.56129728 | P8: =SUMIFS('Combined P&L'!N:N,'Combined P&L'!$C:$C,'P&L Forecast'!$B8) -> 0 | Q8: =SUMIFS('Combined P&L'!O:O,'Combined P&L'!$C:$C,'P&L Forecast'!$B8) -> 0 | R8: =SUMIFS('Combined P&L'!P:P,'Combined P&L'!$C:$C,'P&L Forecast'!$B8) -> 0 | S8: =SUMIFS('Combined P&L'!Q:Q,'Combined P&L'!$C:$C,'P&L Forecast'!$B8) -> 0 | T8: =SUMIFS('Combined P&L'!R:R,'Combined P&L'!$C:$C,'P&L Forecast'!$B8) -> 0 | U8: =SUMIFS('Combined P&L'!S:S,'Combined P&L'!$C:$C,'P&L Forecast'!$B8) -> 0 | V8: =SUMIFS('Combined P&L'!T:T,'Combined P&L'!$C:$C,'P&L Forecast'!$B8) -> 0 | W8: =SUMIFS('Combined P&L'!U:U,'Combined P&L'!$C:$C,'P&L Forecast'!$B8) -> 0 | X8: =SUMIFS('Combined P&L'!V:V,'Combined P&L'!$C:$C,'P&L Forecast'!$B8) -> 0 | Y8: =SUMIFS('Combined P&L'!W:W,'Combined P&L'!$C:$C,'P&L Forecast'!$B8) -> 0 | Z8: =SUMIFS('Combined P&L'!X:X,'Combined P&L'!$C:$C,'P&L Forecast'!$B8) -> 0.08 | AA8: =SUMIFS('Combined P&L'!Y:Y,'Combined P&L'!$C:$C,'P&L Forecast'!$B8) -> 0.48 | AB8: =SUMIFS('Combined P&L'!Z:Z,'Combined P&L'!$C:$C,'P&L Forecast'!$B8) -> 1.13 | AC8: =SUMIFS('Combined P&L'!AA:AA,'Combined P&L'!$C:$C,'P&L Forecast'!$B8) -> 2.14 | AD8: =SUMIFS('Combined P&L'!AB:AB,'Combined P&L'!$C:$C,'P&L Forecast'!$B8) -> 2.66 | AE8: =SUMIFS('Combined P&L'!AC:AC,'Combined P&L'!$C:$C,'P&L Forecast'!$B8) -> 3.65 | AF8: =SUMIFS('Combined P&L'!AD:AD,'Combined P&L'!$C:$C,'P&L Forecast'!$B8) -> 3.623 | AG8: =SUMIFS('Combined P&L'!AE:AE,'Combined P&L'!$C:$C,'P&L Forecast'!$B8) -> 4.964 | AH8: =SUMIFS('Combined P&L'!AF:AF,'Combined P&L'!$C:$C,'P&L Forecast'!$B8) -> 5.0585 | AI8: =SUMIFS('Combined P&L'!AG:AG,'Combined P&L'!$C:$C,'P&L Forecast'!$B8) -> 4.73 | AJ8: =SUMIFS('Combined P&L'!AH:AH,'Combined P&L'!$C:$C,'P&L Forecast'!$B8) -> 4.82 | AK8: =SUMIFS('Combined P&L'!AI:AI,'Combined P&L'!$C:$C,'P&L Forecast'!$B8) -> 5.37 | AL8: =SUMIFS('Combined P&L'!AJ:AJ,'Combined P&L'!$C:$C,'P&L Forecast'!$B8) -> 8.05 | AM8: =SUMIFS('Combined P&L'!AK:AK,'Combined P&L'!$C:$C,'P&L Forecast'!$B8) -> 8.885 | AN8: =SUMIFS('Combined P&L'!AL:AL,'Combined P&L'!$C:$C,'P&L Forecast'!$B8) -> 10.90952 | AO8: =SUMIFS('Combined P&L'!AM:AM,'Combined P&L'!$C:$C,'P&L Forecast'!$B8) -> 10.33497 | AP8: =SUMIFS('Combined P&L'!AN:AN,'Combined P&L'!$C:$C,'P&L Forecast'!$B8) -> 11.175 | AQ8: =SUMIFS('Combined P&L'!AO:AO,'Combined P&L'!$C:$C,'P&L Forecast'!$B8) -> 11.95311 | AR8: =SUMIFS('Combined P&L'!AP:AP,'Combined P&L'!$C:$C,'P&L Forecast'!$B8) -> 15.04071 | AS8: =SUMIFS('Combined P&L'!AQ:AQ,'Combined P&L'!$C:$C,'P&L Forecast'!$B8) -> 16.16868 | AT8: =SUMIFS('Combined P&L'!AR:AR,'Combined P&L'!$C:$C,'P&L Forecast'!$B8) -> 16.06915
B9: SMB Subscription | C9: =SUMIFS($P9:$AT9,$P$5:$AT$5,">"&C$199,$P$5:$AT$5,"<"&C$200) -> 224.791 | D9: =SUMIFS($P9:$AT9,$P$5:$AT$5,">"&D$199,$P$5:$AT$5,"<"&D$200) -> 149.77 | F9: =SUMIFS($P9:$AT9,$P$5:$AT$5,">"&F$199,$P$5:$AT$5,"<"&F$200) -> 90.4525 | G9: =SUMIFS($P9:$AT9,$P$5:$AT$5,">"&G$199,$P$5:$AT$5,"<"&G$200) -> 73.4185 | I9: =SUMIFS($P9:$AT9,$P$5:$AT$5,">"&I$199,$P$5:$AT$5,"<"&I$200) -> 169.5465 | J9: =SUMIFS($P9:$AT9,$P$5:$AT$5,">"&J$199,$P$5:$AT$5,"<"&J$200) -> 132.736 | K9: =+C112 -> 16.2 | M9: =K9-J9 -> -116.536 | N9: =IFERROR(K9/J9-1,0) -> -0.87795323 | P9: =SUMIFS('Combined P&L'!N:N,'Combined P&L'!$C:$C,'P&L Forecast'!$B9) -> 22.001 | Q9: =SUMIFS('Combined P&L'!O:O,'Combined P&L'!$C:$C,'P&L Forecast'!$B9) -> 22.036 | R9: =SUMIFS('Combined P&L'!P:P,'Combined P&L'!$C:$C,'P&L Forecast'!$B9) -> 22.111 | S9: =SUMIFS('Combined P&L'!Q:Q,'Combined P&L'!$C:$C,'P&L Forecast'!$B9) -> 22.146 | T9: =SUMIFS('Combined P&L'!R:R,'Combined P&L'!$C:$C,'P&L Forecast'!$B9) -> 21.966 | U9: =SUMIFS('Combined P&L'!S:S,'Combined P&L'!$C:$C,'P&L Forecast'!$B9) -> 17.816 | V9: =SUMIFS('Combined P&L'!T:T,'Combined P&L'!$C:$C,'P&L Forecast'!$B9) -> 17.621 | W9: =SUMIFS('Combined P&L'!U:U,'Combined P&L'!$C:$C,'P&L Forecast'!$B9) -> 17.536 | X9: =SUMIFS('Combined P&L'!V:V,'Combined P&L'!$C:$C,'P&L Forecast'!$B9) -> 16.426 | Y9: =SUMIFS('Combined P&L'!W:W,'Combined P&L'!$C:$C,'P&L Forecast'!$B9) -> 15.381 | Z9: =SUMIFS('Combined P&L'!X:X,'Combined P&L'!$C:$C,'P&L Forecast'!$B9) -> 14.6755 | AA9: =SUMIFS('Combined P&L'!Y:Y,'Combined P&L'!$C:$C,'P&L Forecast'!$B9) -> 15.0755 | AB9: =SUMIFS('Combined P&L'!Z:Z,'Combined P&L'!$C:$C,'P&L Forecast'!$B9) -> 14.5625 | AC9: =SUMIFS('Combined P&L'!AA:AA,'Combined P&L'!$C:$C,'P&L Forecast'!$B9) -> 12.8025 | AD9: =SUMIFS('Combined P&L'!AB:AB,'Combined P&L'!$C:$C,'P&L Forecast'!$B9) -> 12.4025 | AE9: =SUMIFS('Combined P&L'!AC:AC,'Combined P&L'!$C:$C,'P&L Forecast'!$B9) -> 12.6025 | AF9: =SUMIFS('Combined P&L'!AD:AD,'Combined P&L'!$C:$C,'P&L Forecast'!$B9) -> 12.7525 | AG9: =SUMIFS('Combined P&L'!AE:AE,'Combined P&L'!$C:$C,'P&L Forecast'!$B9) -> 12.7925 | AH9: =SUMIFS('Combined P&L'!AF:AF,'Combined P&L'!$C:$C,'P&L Forecast'!$B9) -> 12.5375 | AI9: =SUMIFS('Combined P&L'!AG:AG,'Combined P&L'!$C:$C,'P&L Forecast'!$B9) -> 11.8575 | AJ9: =SUMIFS('Combined P&L'!AH:AH,'Combined P&L'!$C:$C,'P&L Forecast'!$B9) -> 12.3025 | AK9: =SUMIFS('Combined P&L'!AI:AI,'Combined P&L'!$C:$C,'P&L Forecast'!$B9) -> 11.6925 | AL9: =SUMIFS('Combined P&L'!AJ:AJ,'Combined P&L'!$C:$C,'P&L Forecast'!$B9) -> 11.7175 | AM9: =SUMIFS('Combined P&L'!AK:AK,'Combined P&L'!$C:$C,'P&L Forecast'!$B9) -> 11.7475 | AN9: =SUMIFS('Combined P&L'!AL:AL,'Combined P&L'!$C:$C,'P&L Forecast'!$B9) -> 11.2805 | AO9: =SUMIFS('Combined P&L'!AM:AM,'Combined P&L'!$C:$C,'P&L Forecast'!$B9) -> 10.9305 | AP9: =SUMIFS('Combined P&L'!AN:AN,'Combined P&L'!$C:$C,'P&L Forecast'!$B9) -> 10.6255 | AQ9: =SUMIFS('Combined P&L'!AO:AO,'Combined P&L'!$C:$C,'P&L Forecast'!$B9) -> 10.3155 | AR9: =SUMIFS('Combined P&L'!AP:AP,'Combined P&L'!$C:$C,'P&L Forecast'!$B9) -> 10.3155 | AS9: =SUMIFS('Combined P&L'!AQ:AQ,'Combined P&L'!$C:$C,'P&L Forecast'!$B9) -> 9.9755 | AT9: =SUMIFS('Combined P&L'!AR:AR,'Combined P&L'!$C:$C,'P&L Forecast'!$B9) -> 9.9755
B10: Onboarding | C10: =SUMIFS($P10:$AT10,$P$5:$AT$5,">"&C$199,$P$5:$AT$5,"<"&C$200) -> 44.0585 | D10: =SUMIFS($P10:$AT10,$P$5:$AT$5,">"&D$199,$P$5:$AT$5,"<"&D$200) -> 74.5193 | F10: =SUMIFS($P10:$AT10,$P$5:$AT$5,">"&F$199,$P$5:$AT$5,"<"&F$200) -> 42.25405 | G10: =SUMIFS($P10:$AT10,$P$5:$AT$5,">"&G$199,$P$5:$AT$5,"<"&G$200) -> 59.055 | I10: =SUMIFS($P10:$AT10,$P$5:$AT$5,">"&I$199,$P$5:$AT$5,"<"&I$200) -> 57.49255 | J10: =SUMIFS($P10:$AT10,$P$5:$AT$5,">"&J$199,$P$5:$AT$5,"<"&J$200) -> 91.32025 | K10: =+C114 -> 103.5675 | M10: =K10-J10 -> 12.24725 | N10: =IFERROR(K10/J10-1,0) -> 0.13411319 | P10: =SUMIFS('Combined P&L'!N:N,'Combined P&L'!$C:$C,'P&L Forecast'!$B10) -> 5.465 | Q10: =SUMIFS('Combined P&L'!O:O,'Combined P&L'!$C:$C,'P&L Forecast'!$B10) -> 3.9 | R10: =SUMIFS('Combined P&L'!P:P,'Combined P&L'!$C:$C,'P&L Forecast'!$B10) -> 2.755 | S10: =SUMIFS('Combined P&L'!Q:Q,'Combined P&L'!$C:$C,'P&L Forecast'!$B10) -> 3.502 | T10: =SUMIFS('Combined P&L'!R:R,'Combined P&L'!$C:$C,'P&L Forecast'!$B10) -> 4.659 | U10: =SUMIFS('Combined P&L'!S:S,'Combined P&L'!$C:$C,'P&L Forecast'!$B10) -> 3.937 | V10: =SUMIFS('Combined P&L'!T:T,'Combined P&L'!$C:$C,'P&L Forecast'!$B10) -> 4.602 | W10: =SUMIFS('Combined P&L'!U:U,'Combined P&L'!$C:$C,'P&L Forecast'!$B10) -> 4.738 | X10: =SUMIFS('Combined P&L'!V:V,'Combined P&L'!$C:$C,'P&L Forecast'!$B10) -> 2.119 | Y10: =SUMIFS('Combined P&L'!W:W,'Combined P&L'!$C:$C,'P&L Forecast'!$B10) -> 2.064 | Z10: =SUMIFS('Combined P&L'!X:X,'Combined P&L'!$C:$C,'P&L Forecast'!$B10) -> 3.0125 | AA10: =SUMIFS('Combined P&L'!Y:Y,'Combined P&L'!$C:$C,'P&L Forecast'!$B10) -> 3.305 | AB10: =SUMIFS('Combined P&L'!Z:Z,'Combined P&L'!$C:$C,'P&L Forecast'!$B10) -> 3.079 | AC10: =SUMIFS('Combined P&L'!AA:AA,'Combined P&L'!$C:$C,'P&L Forecast'!$B10) -> 0.7 | AD10: =SUMIFS('Combined P&L'!AB:AB,'Combined P&L'!$C:$C,'P&L Forecast'!$B10) -> 10.43855 | AE10: =SUMIFS('Combined P&L'!AC:AC,'Combined P&L'!$C:$C,'P&L Forecast'!$B10) -> 4.3 | AF10: =SUMIFS('Combined P&L'!AD:AD,'Combined P&L'!$C:$C,'P&L Forecast'!$B10) -> 11.14 | AG10: =SUMIFS('Combined P&L'!AE:AE,'Combined P&L'!$C:$C,'P&L Forecast'!$B10) -> 6.1625 | AH10: =SUMIFS('Combined P&L'!AF:AF,'Combined P&L'!$C:$C,'P&L Forecast'!$B10) -> 6.434 | AI10: =SUMIFS('Combined P&L'!AG:AG,'Combined P&L'!$C:$C,'P&L Forecast'!$B10) -> 3.965 | AJ10: =SUMIFS('Combined P&L'!AH:AH,'Combined P&L'!$C:$C,'P&L Forecast'!$B10) -> 3.92 | AK10: =SUMIFS('Combined P&L'!AI:AI,'Combined P&L'!$C:$C,'P&L Forecast'!$B10) -> 9.1365 | AL10: =SUMIFS('Combined P&L'!AJ:AJ,'Combined P&L'!$C:$C,'P&L Forecast'!$B10) -> 5.25375 | AM10: =SUMIFS('Combined P&L'!AK:AK,'Combined P&L'!$C:$C,'P&L Forecast'!$B10) -> 9.99 | AN10: =SUMIFS('Combined P&L'!AL:AL,'Combined P&L'!$C:$C,'P&L Forecast'!$B10) -> 10.2105 | AO10: =SUMIFS('Combined P&L'!AM:AM,'Combined P&L'!$C:$C,'P&L Forecast'!$B10) -> 6.675 | AP10: =SUMIFS('Combined P&L'!AN:AN,'Combined P&L'!$C:$C,'P&L Forecast'!$B10) -> 9.099 | AQ10: =SUMIFS('Combined P&L'!AO:AO,'Combined P&L'!$C:$C,'P&L Forecast'!$B10) -> 8.9545 | AR10: =SUMIFS('Combined P&L'!AP:AP,'Combined P&L'!$C:$C,'P&L Forecast'!$B10) -> 12.606 | AS10: =SUMIFS('Combined P&L'!AQ:AQ,'Combined P&L'!$C:$C,'P&L Forecast'!$B10) -> 5.4115 | AT10: =SUMIFS('Combined P&L'!AR:AR,'Combined P&L'!$C:$C,'P&L Forecast'!$B10) -> 6.0985
B11: Topkey Subscription | C11: =SUMIFS($P11:$AT11,$P$5:$AT$5,">"&C$199,$P$5:$AT$5,"<"&C$200) -> 0 | D11: =SUMIFS($P11:$AT11,$P$5:$AT$5,">"&D$199,$P$5:$AT$5,"<"&D$200) -> 9.947 | F11: =SUMIFS($P11:$AT11,$P$5:$AT$5,">"&F$199,$P$5:$AT$5,"<"&F$200) -> 0 | G11: =SUMIFS($P11:$AT11,$P$5:$AT$5,">"&G$199,$P$5:$AT$5,"<"&G$200) -> 45.086 | I11: =SUMIFS($P11:$AT11,$P$5:$AT$5,">"&I$199,$P$5:$AT$5,"<"&I$200) -> 0 | J11: =SUMIFS($P11:$AT11,$P$5:$AT$5,">"&J$199,$P$5:$AT$5,"<"&J$200) -> 55.033 | K11: =+C116 -> 94.836 | M11: =K11-J11 -> 39.803 | N11: =IFERROR(K11/J11-1,0) -> 0.72325695 | P11: =SUMIFS('Combined P&L'!N:N,'Combined P&L'!$C:$C,'P&L Forecast'!$B11) -> 0 | Q11: =SUMIFS('Combined P&L'!O:O,'Combined P&L'!$C:$C,'P&L Forecast'!$B11) -> 0 | R11: =SUMIFS('Combined P&L'!P:P,'Combined P&L'!$C:$C,'P&L Forecast'!$B11) -> 0 | S11: =SUMIFS('Combined P&L'!Q:Q,'Combined P&L'!$C:$C,'P&L Forecast'!$B11) -> 0 | T11: =SUMIFS('Combined P&L'!R:R,'Combined P&L'!$C:$C,'P&L Forecast'!$B11) -> 0 | U11: =SUMIFS('Combined P&L'!S:S,'Combined P&L'!$C:$C,'P&L Forecast'!$B11) -> 0 | V11: =SUMIFS('Combined P&L'!T:T,'Combined P&L'!$C:$C,'P&L Forecast'!$B11) -> 0 | W11: =SUMIFS('Combined P&L'!U:U,'Combined P&L'!$C:$C,'P&L Forecast'!$B11) -> 0 | X11: =SUMIFS('Combined P&L'!V:V,'Combined P&L'!$C:$C,'P&L Forecast'!$B11) -> 0 | Y11: =SUMIFS('Combined P&L'!W:W,'Combined P&L'!$C:$C,'P&L Forecast'!$B11) -> 0 | Z11: =SUMIFS('Combined P&L'!X:X,'Combined P&L'!$C:$C,'P&L Forecast'!$B11) -> 0 | AA11: =SUMIFS('Combined P&L'!Y:Y,'Combined P&L'!$C:$C,'P&L Forecast'!$B11) -> 0 | AB11: =SUMIFS('Combined P&L'!Z:Z,'Combined P&L'!$C:$C,'P&L Forecast'!$B11) -> 0 | AC11: =SUMIFS('Combined P&L'!AA:AA,'Combined P&L'!$C:$C,'P&L Forecast'!$B11) -> 0 | AD11: =SUMIFS('Combined P&L'!AB:AB,'Combined P&L'!$C:$C,'P&L Forecast'!$B11) -> 0 | AE11: =SUMIFS('Combined P&L'!AC:AC,'Combined P&L'!$C:$C,'P&L Forecast'!$B11) -> 0 | AF11: =SUMIFS('Combined P&L'!AD:AD,'Combined P&L'!$C:$C,'P&L Forecast'!$B11) -> 0 | AG11: =SUMIFS('Combined P&L'!AE:AE,'Combined P&L'!$C:$C,'P&L Forecast'!$B11) -> 0 | AH11: =SUMIFS('Combined P&L'!AF:AF,'Combined P&L'!$C:$C,'P&L Forecast'!$B11) -> 0 | AI11: =SUMIFS('Combined P&L'!AG:AG,'Combined P&L'!$C:$C,'P&L Forecast'!$B11) -> 0 | AJ11: =SUMIFS('Combined P&L'!AH:AH,'Combined P&L'!$C:$C,'P&L Forecast'!$B11) -> 0.52 | AK11: =SUMIFS('Combined P&L'!AI:AI,'Combined P&L'!$C:$C,'P&L Forecast'!$B11) -> 2.357 | AL11: =SUMIFS('Combined P&L'!AJ:AJ,'Combined P&L'!$C:$C,'P&L Forecast'!$B11) -> 2.811 | AM11: =SUMIFS('Combined P&L'!AK:AK,'Combined P&L'!$C:$C,'P&L Forecast'!$B11) -> 4.259 | AN11: =SUMIFS('Combined P&L'!AL:AL,'Combined P&L'!$C:$C,'P&L Forecast'!$B11) -> 5.254 | AO11: =SUMIFS('Combined P&L'!AM:AM,'Combined P&L'!$C:$C,'P&L Forecast'!$B11) -> 5.652 | AP11: =SUMIFS('Combined P&L'!AN:AN,'Combined P&L'!$C:$C,'P&L Forecast'!$B11) -> 5.324 | AQ11: =SUMIFS('Combined P&L'!AO:AO,'Combined P&L'!$C:$C,'P&L Forecast'!$B11) -> 6.321 | AR11: =SUMIFS('Combined P&L'!AP:AP,'Combined P&L'!$C:$C,'P&L Forecast'!$B11) -> 6.959 | AS11: =SUMIFS('Combined P&L'!AQ:AQ,'Combined P&L'!$C:$C,'P&L Forecast'!$B11) -> 7.673 | AT11: =SUMIFS('Combined P&L'!AR:AR,'Combined P&L'!$C:$C,'P&L Forecast'!$B11) -> 7.903
B12: STR Bill Pay | C12: =SUMIFS($P12:$AT12,$P$5:$AT$5,">"&C$199,$P$5:$AT$5,"<"&C$200) -> 0.06 | D12: =SUMIFS($P12:$AT12,$P$5:$AT$5,">"&D$199,$P$5:$AT$5,"<"&D$200) -> 36.6065 | F12: =SUMIFS($P12:$AT12,$P$5:$AT$5,">"&F$199,$P$5:$AT$5,"<"&F$200) -> 15.4915 | G12: =SUMIFS($P12:$AT12,$P$5:$AT$5,">"&G$199,$P$5:$AT$5,"<"&G$200) -> 45.13 | I12: =SUMIFS($P12:$AT12,$P$5:$AT$5,">"&I$199,$P$5:$AT$5,"<"&I$200) -> 15.5515 | J12: =SUMIFS($P12:$AT12,$P$5:$AT$5,">"&J$199,$P$5:$AT$5,"<"&J$200) -> 66.245 | K12: =+C115 -> 83.46 | M12: =K12-J12 -> 17.215 | N12: =IFERROR(K12/J12-1,0) -> 0.25986867 | P12: =SUMIFS('Combined P&L'!N:N,'Combined P&L'!$C:$C,'P&L Forecast'!$B12) -> 0 | Q12: =SUMIFS('Combined P&L'!O:O,'Combined P&L'!$C:$C,'P&L Forecast'!$B12) -> 0 | R12: =SUMIFS('Combined P&L'!P:P,'Combined P&L'!$C:$C,'P&L Forecast'!$B12) -> 0 | S12: =SUMIFS('Combined P&L'!Q:Q,'Combined P&L'!$C:$C,'P&L Forecast'!$B12) -> 0 | T12: =SUMIFS('Combined P&L'!R:R,'Combined P&L'!$C:$C,'P&L Forecast'!$B12) -> 0 | U12: =SUMIFS('Combined P&L'!S:S,'Combined P&L'!$C:$C,'P&L Forecast'!$B12) -> 0 | V12: =SUMIFS('Combined P&L'!T:T,'Combined P&L'!$C:$C,'P&L Forecast'!$B12) -> 0 | W12: =SUMIFS('Combined P&L'!U:U,'Combined P&L'!$C:$C,'P&L Forecast'!$B12) -> 0 | X12: =SUMIFS('Combined P&L'!V:V,'Combined P&L'!$C:$C,'P&L Forecast'!$B12) -> 0 | Y12: =SUMIFS('Combined P&L'!W:W,'Combined P&L'!$C:$C,'P&L Forecast'!$B12) -> 0 | Z12: =SUMIFS('Combined P&L'!X:X,'Combined P&L'!$C:$C,'P&L Forecast'!$B12) -> 0 | AA12: =SUMIFS('Combined P&L'!Y:Y,'Combined P&L'!$C:$C,'P&L Forecast'!$B12) -> 0.06 | AB12: =SUMIFS('Combined P&L'!Z:Z,'Combined P&L'!$C:$C,'P&L Forecast'!$B12) -> 0.97 | AC12: =SUMIFS('Combined P&L'!AA:AA,'Combined P&L'!$C:$C,'P&L Forecast'!$B12) -> 1.1 | AD12: =SUMIFS('Combined P&L'!AB:AB,'Combined P&L'!$C:$C,'P&L Forecast'!$B12) -> 1.735 | AE12: =SUMIFS('Combined P&L'!AC:AC,'Combined P&L'!$C:$C,'P&L Forecast'!$B12) -> 2.14 | AF12: =SUMIFS('Combined P&L'!AD:AD,'Combined P&L'!$C:$C,'P&L Forecast'!$B12) -> 2.363 | AG12: =SUMIFS('Combined P&L'!AE:AE,'Combined P&L'!$C:$C,'P&L Forecast'!$B12) -> 3.2635 | AH12: =SUMIFS('Combined P&L'!AF:AF,'Combined P&L'!$C:$C,'P&L Forecast'!$B12) -> 3.92 | AI12: =SUMIFS('Combined P&L'!AG:AG,'Combined P&L'!$C:$C,'P&L Forecast'!$B12) -> 3.905 | AJ12: =SUMIFS('Combined P&L'!AH:AH,'Combined P&L'!$C:$C,'P&L Forecast'!$B12) -> 3.78 | AK12: =SUMIFS('Combined P&L'!AI:AI,'Combined P&L'!$C:$C,'P&L Forecast'!$B12) -> 3.795 | AL12: =SUMIFS('Combined P&L'!AJ:AJ,'Combined P&L'!$C:$C,'P&L Forecast'!$B12) -> 4.33 | AM12: =SUMIFS('Combined P&L'!AK:AK,'Combined P&L'!$C:$C,'P&L Forecast'!$B12) -> 5.305 | AN12: =SUMIFS('Combined P&L'!AL:AL,'Combined P&L'!$C:$C,'P&L Forecast'!$B12) -> 6.3 | AO12: =SUMIFS('Combined P&L'!AM:AM,'Combined P&L'!$C:$C,'P&L Forecast'!$B12) -> 6.39 | AP12: =SUMIFS('Combined P&L'!AN:AN,'Combined P&L'!$C:$C,'P&L Forecast'!$B12) -> 6.425 | AQ12: =SUMIFS('Combined P&L'!AO:AO,'Combined P&L'!$C:$C,'P&L Forecast'!$B12) -> 6.08 | AR12: =SUMIFS('Combined P&L'!AP:AP,'Combined P&L'!$C:$C,'P&L Forecast'!$B12) -> 6.325 | AS12: =SUMIFS('Combined P&L'!AQ:AQ,'Combined P&L'!$C:$C,'P&L Forecast'!$B12) -> 6.655 | AT12: =SUMIFS('Combined P&L'!AR:AR,'Combined P&L'!$C:$C,'P&L Forecast'!$B12) -> 6.955
B13: Controller Services | C13: =SUMIFS($P13:$AT13,$P$5:$AT$5,">"&C$199,$P$5:$AT$5,"<"&C$200) -> 13.75 | D13: =SUMIFS($P13:$AT13,$P$5:$AT$5,">"&D$199,$P$5:$AT$5,"<"&D$200) -> 46.4 | F13: =SUMIFS($P13:$AT13,$P$5:$AT$5,">"&F$199,$P$5:$AT$5,"<"&F$200) -> 31.5 | G13: =SUMIFS($P13:$AT13,$P$5:$AT$5,">"&G$199,$P$5:$AT$5,"<"&G$200) -> 24.25 | I13: =SUMIFS($P13:$AT13,$P$5:$AT$5,">"&I$199,$P$5:$AT$5,"<"&I$200) -> 44 | J13: =SUMIFS($P13:$AT13,$P$5:$AT$5,">"&J$199,$P$5:$AT$5,"<"&J$200) -> 39.15 | K13: =+C117 -> 42 | M13: =K13-J13 -> 2.85 | N13: =IFERROR(K13/J13-1,0) -> 0.072796935 | P13: =SUMIFS('Combined P&L'!N:N,'Combined P&L'!$C:$C,'P&L Forecast'!$B13) -> 0 | Q13: =SUMIFS('Combined P&L'!O:O,'Combined P&L'!$C:$C,'P&L Forecast'!$B13) -> 0 | R13: =SUMIFS('Combined P&L'!P:P,'Combined P&L'!$C:$C,'P&L Forecast'!$B13) -> 0 | S13: =SUMIFS('Combined P&L'!Q:Q,'Combined P&L'!$C:$C,'P&L Forecast'!$B13) -> 0 | T13: =SUMIFS('Combined P&L'!R:R,'Combined P&L'!$C:$C,'P&L Forecast'!$B13) -> 0 | U13: =SUMIFS('Combined P&L'!S:S,'Combined P&L'!$C:$C,'P&L Forecast'!$B13) -> 0 | V13: =SUMIFS('Combined P&L'!T:T,'Combined P&L'!$C:$C,'P&L Forecast'!$B13) -> 1.25 | W13: =SUMIFS('Combined P&L'!U:U,'Combined P&L'!$C:$C,'P&L Forecast'!$B13) -> 1.25 | X13: =SUMIFS('Combined P&L'!V:V,'Combined P&L'!$C:$C,'P&L Forecast'!$B13) -> 1.25 | Y13: =SUMIFS('Combined P&L'!W:W,'Combined P&L'!$C:$C,'P&L Forecast'!$B13) -> 1.25 | Z13: =SUMIFS('Combined P&L'!X:X,'Combined P&L'!$C:$C,'P&L Forecast'!$B13) -> 5.75 | AA13: =SUMIFS('Combined P&L'!Y:Y,'Combined P&L'!$C:$C,'P&L Forecast'!$B13) -> 3 | AB13: =SUMIFS('Combined P&L'!Z:Z,'Combined P&L'!$C:$C,'P&L Forecast'!$B13) -> 4.45 | AC13: =SUMIFS('Combined P&L'!AA:AA,'Combined P&L'!$C:$C,'P&L Forecast'!$B13) -> 3.45 | AD13: =SUMIFS('Combined P&L'!AB:AB,'Combined P&L'!$C:$C,'P&L Forecast'!$B13) -> 3.45 | AE13: =SUMIFS('Combined P&L'!AC:AC,'Combined P&L'!$C:$C,'P&L Forecast'!$B13) -> 5.95 | AF13: =SUMIFS('Combined P&L'!AD:AD,'Combined P&L'!$C:$C,'P&L Forecast'!$B13) -> 5.2 | AG13: =SUMIFS('Combined P&L'!AE:AE,'Combined P&L'!$C:$C,'P&L Forecast'!$B13) -> 5 | AH13: =SUMIFS('Combined P&L'!AF:AF,'Combined P&L'!$C:$C,'P&L Forecast'!$B13) -> 4 | AI13: =SUMIFS('Combined P&L'!AG:AG,'Combined P&L'!$C:$C,'P&L Forecast'!$B13) -> 2.95 | AJ13: =SUMIFS('Combined P&L'!AH:AH,'Combined P&L'!$C:$C,'P&L Forecast'!$B13) -> 3.025 | AK13: =SUMIFS('Combined P&L'!AI:AI,'Combined P&L'!$C:$C,'P&L Forecast'!$B13) -> 3.025 | AL13: =SUMIFS('Combined P&L'!AJ:AJ,'Combined P&L'!$C:$C,'P&L Forecast'!$B13) -> 2.95 | AM13: =SUMIFS('Combined P&L'!AK:AK,'Combined P&L'!$C:$C,'P&L Forecast'!$B13) -> 2.95 | AN13: =SUMIFS('Combined P&L'!AL:AL,'Combined P&L'!$C:$C,'P&L Forecast'!$B13) -> 2.75 | AO13: =SUMIFS('Combined P&L'!AM:AM,'Combined P&L'!$C:$C,'P&L Forecast'!$B13) -> 3.5 | AP13: =SUMIFS('Combined P&L'!AN:AN,'Combined P&L'!$C:$C,'P&L Forecast'!$B13) -> 2.75 | AQ13: =SUMIFS('Combined P&L'!AO:AO,'Combined P&L'!$C:$C,'P&L Forecast'!$B13) -> 4.75 | AR13: =SUMIFS('Combined P&L'!AP:AP,'Combined P&L'!$C:$C,'P&L Forecast'!$B13) -> 3.5 | AS13: =SUMIFS('Combined P&L'!AQ:AQ,'Combined P&L'!$C:$C,'P&L Forecast'!$B13) -> 3.5 | AT13: =SUMIFS('Combined P&L'!AR:AR,'Combined P&L'!$C:$C,'P&L Forecast'!$B13) -> 3.5
B14: Historical Cleanup | C14: =SUMIFS($P14:$AT14,$P$5:$AT$5,">"&C$199,$P$5:$AT$5,"<"&C$200) -> 17.624 | D14: =SUMIFS($P14:$AT14,$P$5:$AT$5,">"&D$199,$P$5:$AT$5,"<"&D$200) -> 5.03375 | F14: =SUMIFS($P14:$AT14,$P$5:$AT$5,">"&F$199,$P$5:$AT$5,"<"&F$200) -> 4.43875 | G14: =SUMIFS($P14:$AT14,$P$5:$AT$5,">"&G$199,$P$5:$AT$5,"<"&G$200) -> 0 | I14: =SUMIFS($P14:$AT14,$P$5:$AT$5,">"&I$199,$P$5:$AT$5,"<"&I$200) -> 12.84275 | J14: =SUMIFS($P14:$AT14,$P$5:$AT$5,">"&J$199,$P$5:$AT$5,"<"&J$200) -> 0.595 | K14: =+C118 -> 0 | M14: =K14-J14 -> -0.595 | N14: =IFERROR(K14/J14-1,0) -> -1 | P14: =SUMIFS('Combined P&L'!N:N,'Combined P&L'!$C:$C,'P&L Forecast'!$B14) -> 1.2 | Q14: =SUMIFS('Combined P&L'!O:O,'Combined P&L'!$C:$C,'P&L Forecast'!$B14) -> 1.7625 | R14: =SUMIFS('Combined P&L'!P:P,'Combined P&L'!$C:$C,'P&L Forecast'!$B14) -> 0.66 | S14: =SUMIFS('Combined P&L'!Q:Q,'Combined P&L'!$C:$C,'P&L Forecast'!$B14) -> 0.395 | T14: =SUMIFS('Combined P&L'!R:R,'Combined P&L'!$C:$C,'P&L Forecast'!$B14) -> 2.465 | U14: =SUMIFS('Combined P&L'!S:S,'Combined P&L'!$C:$C,'P&L Forecast'!$B14) -> 1.275 | V14: =SUMIFS('Combined P&L'!T:T,'Combined P&L'!$C:$C,'P&L Forecast'!$B14) -> 1.4625 | W14: =SUMIFS('Combined P&L'!U:U,'Combined P&L'!$C:$C,'P&L Forecast'!$B14) -> 0 | X14: =SUMIFS('Combined P&L'!V:V,'Combined P&L'!$C:$C,'P&L Forecast'!$B14) -> 1.14525 | Y14: =SUMIFS('Combined P&L'!W:W,'Combined P&L'!$C:$C,'P&L Forecast'!$B14) -> 1.35525 | Z14: =SUMIFS('Combined P&L'!X:X,'Combined P&L'!$C:$C,'P&L Forecast'!$B14) -> 1.9035 | AA14: =SUMIFS('Combined P&L'!Y:Y,'Combined P&L'!$C:$C,'P&L Forecast'!$B14) -> 4 | AB14: =SUMIFS('Combined P&L'!Z:Z,'Combined P&L'!$C:$C,'P&L Forecast'!$B14) -> 1.08375 | AC14: =SUMIFS('Combined P&L'!AA:AA,'Combined P&L'!$C:$C,'P&L Forecast'!$B14) -> 2 | AD14: =SUMIFS('Combined P&L'!AB:AB,'Combined P&L'!$C:$C,'P&L Forecast'!$B14) -> 1.355 | AE14: =SUMIFS('Combined P&L'!AC:AC,'Combined P&L'!$C:$C,'P&L Forecast'!$B14) -> 0 | AF14: =SUMIFS('Combined P&L'!AD:AD,'Combined P&L'!$C:$C,'P&L Forecast'!$B14) -> 0 | AG14: =SUMIFS('Combined P&L'!AE:AE,'Combined P&L'!$C:$C,'P&L Forecast'!$B14) -> 0 | AH14: =SUMIFS('Combined P&L'!AF:AF,'Combined P&L'!$C:$C,'P&L Forecast'!$B14) -> 0 | AI14: =SUMIFS('Combined P&L'!AG:AG,'Combined P&L'!$C:$C,'P&L Forecast'!$B14) -> 0 | AJ14: =SUMIFS('Combined P&L'!AH:AH,'Combined P&L'!$C:$C,'P&L Forecast'!$B14) -> 0 | AK14: =SUMIFS('Combined P&L'!AI:AI,'Combined P&L'!$C:$C,'P&L Forecast'!$B14) -> 0.595 | AL14: =SUMIFS('Combined P&L'!AJ:AJ,'Combined P&L'!$C:$C,'P&L Forecast'!$B14) -> 0 | AM14: =SUMIFS('Combined P&L'!AK:AK,'Combined P&L'!$C:$C,'P&L Forecast'!$B14) -> 0 | AN14: =SUMIFS('Combined P&L'!AL:AL,'Combined P&L'!$C:$C,'P&L Forecast'!$B14) -> 0 | AO14: =SUMIFS('Combined P&L'!AM:AM,'Combined P&L'!$C:$C,'P&L Forecast'!$B14) -> 0 | AP14: =SUMIFS('Combined P&L'!AN:AN,'Combined P&L'!$C:$C,'P&L Forecast'!$B14) -> 0 | AQ14: =SUMIFS('Combined P&L'!AO:AO,'Combined P&L'!$C:$C,'P&L Forecast'!$B14) -> 0 | AR14: =SUMIFS('Combined P&L'!AP:AP,'Combined P&L'!$C:$C,'P&L Forecast'!$B14) -> 0 | AS14: =SUMIFS('Combined P&L'!AQ:AQ,'Combined P&L'!$C:$C,'P&L Forecast'!$B14) -> 0 | AT14: =SUMIFS('Combined P&L'!AR:AR,'Combined P&L'!$C:$C,'P&L Forecast'!$B14) -> 0
B15: Total Recurring Revenue | C15: =SUM(C7:C14) -> 1094.3157 | D15: =SUM(D7:D14) -> 1827.8494 | F15: =SUM(F7:F14) -> 958.8909 | G15: =SUM(G7:G14) -> 1600.0675 | I15: =SUM(I7:I14) -> 1475.5391 | J15: =SUM(J7:J14) -> 2469.026 | K15: =SUM(K7:K14) -> 2942.9433 | M15: =SUM(M7:M14) -> 473.91731 | N15: =IFERROR(K15/J15-1,0) -> 0.19194505 | P15: =SUM(P7:P14) -> 73.3495 | Q15: =SUM(Q7:Q14) -> 74.7445 | R15: =SUM(R7:R14) -> 77.996 | S15: =SUM(S7:S14) -> 83.2127 | T15: =SUM(T7:T14) -> 86.60415 | U15: =SUM(U7:U14) -> 88.544 | V15: =SUM(V7:V14) -> 93.21675 | W15: =SUM(W7:W14) -> 96.77535 | ... AT15: =SUM(AT7:AT14) -> 251.33865
B17: Profit Share | C17: =SUMIFS($P17:$AT17,$P$5:$AT$5,">"&C$199,$P$5:$AT$5,"<"&C$200) -> 6.2004 | D17: =SUMIFS($P17:$AT17,$P$5:$AT$5,">"&D$199,$P$5:$AT$5,"<"&D$200) -> 23.26179 | F17: =SUMIFS($P17:$AT17,$P$5:$AT$5,">"&F$199,$P$5:$AT$5,"<"&F$200) -> 14.50495 | G17: =SUMIFS($P17:$AT17,$P$5:$AT$5,">"&G$199,$P$5:$AT$5,"<"&G$200) -> 8.07938 | I17: =SUMIFS($P17:$AT17,$P$5:$AT$5,">"&I$199,$P$5:$AT$5,"<"&I$200) -> 18.32935 | J17: =SUMIFS($P17:$AT17,$P$5:$AT$5,">"&J$199,$P$5:$AT$5,"<"&J$200) -> 16.83622 | K17: =+C123 -> 16.83622 | M17: =K17-J17 -> 0 | N17: =IFERROR(K17/J17-1,0) -> 0 | P17: =SUMIFS('Combined P&L'!N:N,'Combined P&L'!$C:$C,'P&L Forecast'!$B17) -> 0.0686 | Q17: =SUMIFS('Combined P&L'!O:O,'Combined P&L'!$C:$C,'P&L Forecast'!$B17) -> 0.1312 | R17: =SUMIFS('Combined P&L'!P:P,'Combined P&L'!$C:$C,'P&L Forecast'!$B17) -> 0.0712 | S17: =SUMIFS('Combined P&L'!Q:Q,'Combined P&L'!$C:$C,'P&L Forecast'!$B17) -> 0.0556 | T17: =SUMIFS('Combined P&L'!R:R,'Combined P&L'!$C:$C,'P&L Forecast'!$B17) -> 0.577 | U17: =SUMIFS('Combined P&L'!S:S,'Combined P&L'!$C:$C,'P&L Forecast'!$B17) -> 0.8068 | V17: =SUMIFS('Combined P&L'!T:T,'Combined P&L'!$C:$C,'P&L Forecast'!$B17) -> 0.6656 | W17: =SUMIFS('Combined P&L'!U:U,'Combined P&L'!$C:$C,'P&L Forecast'!$B17) -> 0.8264 | X17: =SUMIFS('Combined P&L'!V:V,'Combined P&L'!$C:$C,'P&L Forecast'!$B17) -> 1.3808 | Y17: =SUMIFS('Combined P&L'!W:W,'Combined P&L'!$C:$C,'P&L Forecast'!$B17) -> 0.8604 | Z17: =SUMIFS('Combined P&L'!X:X,'Combined P&L'!$C:$C,'P&L Forecast'!$B17) -> 0.51 | AA17: =SUMIFS('Combined P&L'!Y:Y,'Combined P&L'!$C:$C,'P&L Forecast'!$B17) -> 0.2468 | AB17: =SUMIFS('Combined P&L'!Z:Z,'Combined P&L'!$C:$C,'P&L Forecast'!$B17) -> 7.3584 | AC17: =SUMIFS('Combined P&L'!AA:AA,'Combined P&L'!$C:$C,'P&L Forecast'!$B17) -> 1.29335 | AD17: =SUMIFS('Combined P&L'!AB:AB,'Combined P&L'!$C:$C,'P&L Forecast'!$B17) -> 0.96833 | AE17: =SUMIFS('Combined P&L'!AC:AC,'Combined P&L'!$C:$C,'P&L Forecast'!$B17) -> 1.1656 | AF17: =SUMIFS('Combined P&L'!AD:AD,'Combined P&L'!$C:$C,'P&L Forecast'!$B17) -> 0.96093 | AG17: =SUMIFS('Combined P&L'!AE:AE,'Combined P&L'!$C:$C,'P&L Forecast'!$B17) -> 1.71127 | AH17: =SUMIFS('Combined P&L'!AF:AF,'Combined P&L'!$C:$C,'P&L Forecast'!$B17) -> 1.04707 | AI17: =SUMIFS('Combined P&L'!AG:AG,'Combined P&L'!$C:$C,'P&L Forecast'!$B17) -> 2.04088 | AJ17: =SUMIFS('Combined P&L'!AH:AH,'Combined P&L'!$C:$C,'P&L Forecast'!$B17) -> 1.13621 | AK17: =SUMIFS('Combined P&L'!AI:AI,'Combined P&L'!$C:$C,'P&L Forecast'!$B17) -> 2.01424 | AL17: =SUMIFS('Combined P&L'!AJ:AJ,'Combined P&L'!$C:$C,'P&L Forecast'!$B17) -> 1.29758 | AM17: =SUMIFS('Combined P&L'!AK:AK,'Combined P&L'!$C:$C,'P&L Forecast'!$B17) -> 2.26793 | AN17: =SUMIFS('Combined P&L'!AL:AL,'Combined P&L'!$C:$C,'P&L Forecast'!$B17) -> 2.67784 | AO17: =SUMIFS('Combined P&L'!AM:AM,'Combined P&L'!$C:$C,'P&L Forecast'!$B17) -> 2.35401 | AP17: =SUMIFS('Combined P&L'!AN:AN,'Combined P&L'!$C:$C,'P&L Forecast'!$B17) -> 0.2276 | AQ17: =SUMIFS('Combined P&L'!AO:AO,'Combined P&L'!$C:$C,'P&L Forecast'!$B17) -> 1.47836 | AR17: =SUMIFS('Combined P&L'!AP:AP,'Combined P&L'!$C:$C,'P&L Forecast'!$B17) -> 0.66824 | AS17: =SUMIFS('Combined P&L'!AQ:AQ,'Combined P&L'!$C:$C,'P&L Forecast'!$B17) -> 0.58613 | AT17: =SUMIFS('Combined P&L'!AR:AR,'Combined P&L'!$C:$C,'P&L Forecast'!$B17) -> 0.0872
B18: 1099 Filing | C18: =SUMIFS($P18:$AT18,$P$5:$AT$5,">"&C$199,$P$5:$AT$5,"<"&C$200) -> 10.475 | D18: =SUMIFS($P18:$AT18,$P$5:$AT$5,">"&D$199,$P$5:$AT$5,"<"&D$200) -> 23.55 | F18: =SUMIFS($P18:$AT18,$P$5:$AT$5,">"&F$199,$P$5:$AT$5,"<"&F$200) -> 23.49 | G18: =SUMIFS($P18:$AT18,$P$5:$AT$5,">"&G$199,$P$5:$AT$5,"<"&G$200) -> 38.7015 | I18: =SUMIFS($P18:$AT18,$P$5:$AT$5,">"&I$199,$P$5:$AT$5,"<"&I$200) -> 23.52 | J18: =SUMIFS($P18:$AT18,$P$5:$AT$5,">"&J$199,$P$5:$AT$5,"<"&J$200) -> 38.7615 | K18: =+C121 -> 38.7615 | M18: =K18-J18 -> 0 | N18: =IFERROR(K18/J18-1,0) -> 0 | P18: =SUMIFS('Combined P&L'!N:N,'Combined P&L'!$C:$C,'P&L Forecast'!$B18) -> 6.945 | Q18: =SUMIFS('Combined P&L'!O:O,'Combined P&L'!$C:$C,'P&L Forecast'!$B18) -> 3.38 | R18: =SUMIFS('Combined P&L'!P:P,'Combined P&L'!$C:$C,'P&L Forecast'!$B18) -> 0.045 | S18: =SUMIFS('Combined P&L'!Q:Q,'Combined P&L'!$C:$C,'P&L Forecast'!$B18) -> 0.06 | T18: =SUMIFS('Combined P&L'!R:R,'Combined P&L'!$C:$C,'P&L Forecast'!$B18) -> 0.015 | U18: =SUMIFS('Combined P&L'!S:S,'Combined P&L'!$C:$C,'P&L Forecast'!$B18) -> 0 | V18: =SUMIFS('Combined P&L'!T:T,'Combined P&L'!$C:$C,'P&L Forecast'!$B18) -> 0 | W18: =SUMIFS('Combined P&L'!U:U,'Combined P&L'!$C:$C,'P&L Forecast'!$B18) -> 0.015 | X18: =SUMIFS('Combined P&L'!V:V,'Combined P&L'!$C:$C,'P&L Forecast'!$B18) -> 0 | Y18: =SUMIFS('Combined P&L'!W:W,'Combined P&L'!$C:$C,'P&L Forecast'!$B18) -> 0 | Z18: =SUMIFS('Combined P&L'!X:X,'Combined P&L'!$C:$C,'P&L Forecast'!$B18) -> 0.015 | AA18: =SUMIFS('Combined P&L'!Y:Y,'Combined P&L'!$C:$C,'P&L Forecast'!$B18) -> 0 | AB18: =SUMIFS('Combined P&L'!Z:Z,'Combined P&L'!$C:$C,'P&L Forecast'!$B18) -> 13.485 | AC18: =SUMIFS('Combined P&L'!AA:AA,'Combined P&L'!$C:$C,'P&L Forecast'!$B18) -> 9.915 | AD18: =SUMIFS('Combined P&L'!AB:AB,'Combined P&L'!$C:$C,'P&L Forecast'!$B18) -> 0.06 | AE18: =SUMIFS('Combined P&L'!AC:AC,'Combined P&L'!$C:$C,'P&L Forecast'!$B18) -> 0.03 | AF18: =SUMIFS('Combined P&L'!AD:AD,'Combined P&L'!$C:$C,'P&L Forecast'!$B18) -> 0 | AG18: =SUMIFS('Combined P&L'!AE:AE,'Combined P&L'!$C:$C,'P&L Forecast'!$B18) -> 0 | AH18: =SUMIFS('Combined P&L'!AF:AF,'Combined P&L'!$C:$C,'P&L Forecast'!$B18) -> 0 | AI18: =SUMIFS('Combined P&L'!AG:AG,'Combined P&L'!$C:$C,'P&L Forecast'!$B18) -> 0.03 | AJ18: =SUMIFS('Combined P&L'!AH:AH,'Combined P&L'!$C:$C,'P&L Forecast'!$B18) -> 0.03 | AK18: =SUMIFS('Combined P&L'!AI:AI,'Combined P&L'!$C:$C,'P&L Forecast'!$B18) -> 0 | AL18: =SUMIFS('Combined P&L'!AJ:AJ,'Combined P&L'!$C:$C,'P&L Forecast'!$B18) -> 0 | AM18: =SUMIFS('Combined P&L'!AK:AK,'Combined P&L'!$C:$C,'P&L Forecast'!$B18) -> 0 | AN18: =SUMIFS('Combined P&L'!AL:AL,'Combined P&L'!$C:$C,'P&L Forecast'!$B18) -> 6.105 | AO18: =SUMIFS('Combined P&L'!AM:AM,'Combined P&L'!$C:$C,'P&L Forecast'!$B18) -> 31.1565 | AP18: =SUMIFS('Combined P&L'!AN:AN,'Combined P&L'!$C:$C,'P&L Forecast'!$B18) -> 1.26 | AQ18: =SUMIFS('Combined P&L'!AO:AO,'Combined P&L'!$C:$C,'P&L Forecast'!$B18) -> 0.18 | AR18: =SUMIFS('Combined P&L'!AP:AP,'Combined P&L'!$C:$C,'P&L Forecast'!$B18) -> 0 | AS18: =SUMIFS('Combined P&L'!AQ:AQ,'Combined P&L'!$C:$C,'P&L Forecast'!$B18) -> 0 | AT18: =SUMIFS('Combined P&L'!AR:AR,'Combined P&L'!$C:$C,'P&L Forecast'!$B18) -> 0
B19: Income Tax | C19: =SUMIFS($P19:$AT19,$P$5:$AT$5,">"&C$199,$P$5:$AT$5,"<"&C$200) -> 0 | D19: =SUMIFS($P19:$AT19,$P$5:$AT$5,">"&D$199,$P$5:$AT$5,"<"&D$200) -> 3.4 | F19: =SUMIFS($P19:$AT19,$P$5:$AT$5,">"&F$199,$P$5:$AT$5,"<"&F$200) -> 0 | G19: =SUMIFS($P19:$AT19,$P$5:$AT$5,">"&G$199,$P$5:$AT$5,"<"&G$200) -> 23.915 | I19: =SUMIFS($P19:$AT19,$P$5:$AT$5,">"&I$199,$P$5:$AT$5,"<"&I$200) -> 0 | J19: =SUMIFS($P19:$AT19,$P$5:$AT$5,">"&J$199,$P$5:$AT$5,"<"&J$200) -> 27.315 | K19: =+C122 -> 0 | M19: =K19-J19 -> -27.315 | N19: =IFERROR(K19/J19-1,0) -> -1 | P19: =SUMIFS('Combined P&L'!N:N,'Combined P&L'!$C:$C,'P&L Forecast'!$B19) -> 0 | Q19: =SUMIFS('Combined P&L'!O:O,'Combined P&L'!$C:$C,'P&L Forecast'!$B19) -> 0 | R19: =SUMIFS('Combined P&L'!P:P,'Combined P&L'!$C:$C,'P&L Forecast'!$B19) -> 0 | S19: =SUMIFS('Combined P&L'!Q:Q,'Combined P&L'!$C:$C,'P&L Forecast'!$B19) -> 0 | T19: =SUMIFS('Combined P&L'!R:R,'Combined P&L'!$C:$C,'P&L Forecast'!$B19) -> 0 | U19: =SUMIFS('Combined P&L'!S:S,'Combined P&L'!$C:$C,'P&L Forecast'!$B19) -> 0 | V19: =SUMIFS('Combined P&L'!T:T,'Combined P&L'!$C:$C,'P&L Forecast'!$B19) -> 0 | W19: =SUMIFS('Combined P&L'!U:U,'Combined P&L'!$C:$C,'P&L Forecast'!$B19) -> 0 | X19: =SUMIFS('Combined P&L'!V:V,'Combined P&L'!$C:$C,'P&L Forecast'!$B19) -> 0 | Y19: =SUMIFS('Combined P&L'!W:W,'Combined P&L'!$C:$C,'P&L Forecast'!$B19) -> 0 | Z19: =SUMIFS('Combined P&L'!X:X,'Combined P&L'!$C:$C,'P&L Forecast'!$B19) -> 0 | AA19: =SUMIFS('Combined P&L'!Y:Y,'Combined P&L'!$C:$C,'P&L Forecast'!$B19) -> 0 | AB19: =SUMIFS('Combined P&L'!Z:Z,'Combined P&L'!$C:$C,'P&L Forecast'!$B19) -> 0 | AC19: =SUMIFS('Combined P&L'!AA:AA,'Combined P&L'!$C:$C,'P&L Forecast'!$B19) -> 0 | AD19: =SUMIFS('Combined P&L'!AB:AB,'Combined P&L'!$C:$C,'P&L Forecast'!$B19) -> 0 | AE19: =SUMIFS('Combined P&L'!AC:AC,'Combined P&L'!$C:$C,'P&L Forecast'!$B19) -> 0 | AF19: =SUMIFS('Combined P&L'!AD:AD,'Combined P&L'!$C:$C,'P&L Forecast'!$B19) -> 0 | AG19: =SUMIFS('Combined P&L'!AE:AE,'Combined P&L'!$C:$C,'P&L Forecast'!$B19) -> 0 | AH19: =SUMIFS('Combined P&L'!AF:AF,'Combined P&L'!$C:$C,'P&L Forecast'!$B19) -> 0 | AI19: =SUMIFS('Combined P&L'!AG:AG,'Combined P&L'!$C:$C,'P&L Forecast'!$B19) -> 0 | AJ19: =SUMIFS('Combined P&L'!AH:AH,'Combined P&L'!$C:$C,'P&L Forecast'!$B19) -> 0.875 | AK19: =SUMIFS('Combined P&L'!AI:AI,'Combined P&L'!$C:$C,'P&L Forecast'!$B19) -> 1.65 | AL19: =SUMIFS('Combined P&L'!AJ:AJ,'Combined P&L'!$C:$C,'P&L Forecast'!$B19) -> 0 | AM19: =SUMIFS('Combined P&L'!AK:AK,'Combined P&L'!$C:$C,'P&L Forecast'!$B19) -> 0.875 | AN19: =SUMIFS('Combined P&L'!AL:AL,'Combined P&L'!$C:$C,'P&L Forecast'!$B19) -> 0 | AO19: =SUMIFS('Combined P&L'!AM:AM,'Combined P&L'!$C:$C,'P&L Forecast'!$B19) -> 0 | AP19: =SUMIFS('Combined P&L'!AN:AN,'Combined P&L'!$C:$C,'P&L Forecast'!$B19) -> 14.19 | AQ19: =SUMIFS('Combined P&L'!AO:AO,'Combined P&L'!$C:$C,'P&L Forecast'!$B19) -> 6.625 | AR19: =SUMIFS('Combined P&L'!AP:AP,'Combined P&L'!$C:$C,'P&L Forecast'!$B19) -> 0 | AS19: =SUMIFS('Combined P&L'!AQ:AQ,'Combined P&L'!$C:$C,'P&L Forecast'!$B19) -> 3.1 | AT19: =SUMIFS('Combined P&L'!AR:AR,'Combined P&L'!$C:$C,'P&L Forecast'!$B19) -> 0
B20: Billable Expense Income | C20: =SUMIFS($P20:$AT20,$P$5:$AT$5,">"&C$199,$P$5:$AT$5,"<"&C$200) -> 0.3747 | D20: =SUMIFS($P20:$AT20,$P$5:$AT$5,">"&D$199,$P$5:$AT$5,"<"&D$200) -> 1.12194 | F20: =SUMIFS($P20:$AT20,$P$5:$AT$5,">"&F$199,$P$5:$AT$5,"<"&F$200) -> 0.78725 | G20: =SUMIFS($P20:$AT20,$P$5:$AT$5,">"&G$199,$P$5:$AT$5,"<"&G$200) -> 0.25783 | I20: =SUMIFS($P20:$AT20,$P$5:$AT$5,">"&I$199,$P$5:$AT$5,"<"&I$200) -> 0.78725 | J20: =SUMIFS($P20:$AT20,$P$5:$AT$5,">"&J$199,$P$5:$AT$5,"<"&J$200) -> 0.59252 | K20: =+C124 -> 0 | M20: =K20-J20 -> -0.59252 | N20: =IFERROR(K20/J20-1,0) -> -1 | P20: =SUMIFS('Combined P&L'!N:N,'Combined P&L'!$C:$C,'P&L Forecast'!$B20) -> 0.05 | Q20: =SUMIFS('Combined P&L'!O:O,'Combined P&L'!$C:$C,'P&L Forecast'!$B20) -> 0 | R20: =SUMIFS('Combined P&L'!P:P,'Combined P&L'!$C:$C,'P&L Forecast'!$B20) -> 0 | S20: =SUMIFS('Combined P&L'!Q:Q,'Combined P&L'!$C:$C,'P&L Forecast'!$B20) -> 0.025 | T20: =SUMIFS('Combined P&L'!R:R,'Combined P&L'!$C:$C,'P&L Forecast'!$B20) -> 0 | U20: =SUMIFS('Combined P&L'!S:S,'Combined P&L'!$C:$C,'P&L Forecast'!$B20) -> 0 | V20: =SUMIFS('Combined P&L'!T:T,'Combined P&L'!$C:$C,'P&L Forecast'!$B20) -> 0.2997 | W20: =SUMIFS('Combined P&L'!U:U,'Combined P&L'!$C:$C,'P&L Forecast'!$B20) -> 0 | X20: =SUMIFS('Combined P&L'!V:V,'Combined P&L'!$C:$C,'P&L Forecast'!$B20) -> 0 | Y20: =SUMIFS('Combined P&L'!W:W,'Combined P&L'!$C:$C,'P&L Forecast'!$B20) -> 0 | Z20: =SUMIFS('Combined P&L'!X:X,'Combined P&L'!$C:$C,'P&L Forecast'!$B20) -> 0 | AA20: =SUMIFS('Combined P&L'!Y:Y,'Combined P&L'!$C:$C,'P&L Forecast'!$B20) -> 0 | AB20: =SUMIFS('Combined P&L'!Z:Z,'Combined P&L'!$C:$C,'P&L Forecast'!$B20) -> 0.025 | AC20: =SUMIFS('Combined P&L'!AA:AA,'Combined P&L'!$C:$C,'P&L Forecast'!$B20) -> 0.3996 | AD20: =SUMIFS('Combined P&L'!AB:AB,'Combined P&L'!$C:$C,'P&L Forecast'!$B20) -> 0 | AE20: =SUMIFS('Combined P&L'!AC:AC,'Combined P&L'!$C:$C,'P&L Forecast'!$B20) -> 0 | AF20: =SUMIFS('Combined P&L'!AD:AD,'Combined P&L'!$C:$C,'P&L Forecast'!$B20) -> 0.07294 | AG20: =SUMIFS('Combined P&L'!AE:AE,'Combined P&L'!$C:$C,'P&L Forecast'!$B20) -> 0 | AH20: =SUMIFS('Combined P&L'!AF:AF,'Combined P&L'!$C:$C,'P&L Forecast'!$B20) -> 0.28971 | AI20: =SUMIFS('Combined P&L'!AG:AG,'Combined P&L'!$C:$C,'P&L Forecast'!$B20) -> 0.30969 | AJ20: =SUMIFS('Combined P&L'!AH:AH,'Combined P&L'!$C:$C,'P&L Forecast'!$B20) -> 0 | AK20: =SUMIFS('Combined P&L'!AI:AI,'Combined P&L'!$C:$C,'P&L Forecast'!$B20) -> 0 | AL20: =SUMIFS('Combined P&L'!AJ:AJ,'Combined P&L'!$C:$C,'P&L Forecast'!$B20) -> 0 | AM20: =SUMIFS('Combined P&L'!AK:AK,'Combined P&L'!$C:$C,'P&L Forecast'!$B20) -> 0.025 | AN20: =SUMIFS('Combined P&L'!AL:AL,'Combined P&L'!$C:$C,'P&L Forecast'!$B20) -> 0.15984 | AO20: =SUMIFS('Combined P&L'!AM:AM,'Combined P&L'!$C:$C,'P&L Forecast'!$B20) -> 0 | AP20: =SUMIFS('Combined P&L'!AN:AN,'Combined P&L'!$C:$C,'P&L Forecast'!$B20) -> 0.075 | AQ20: =SUMIFS('Combined P&L'!AO:AO,'Combined P&L'!$C:$C,'P&L Forecast'!$B20) -> 0 | AR20: =SUMIFS('Combined P&L'!AP:AP,'Combined P&L'!$C:$C,'P&L Forecast'!$B20) -> 0 | AS20: =SUMIFS('Combined P&L'!AQ:AQ,'Combined P&L'!$C:$C,'P&L Forecast'!$B20) -> 0.02299 | AT20: =SUMIFS('Combined P&L'!AR:AR,'Combined P&L'!$C:$C,'P&L Forecast'!$B20) -> 0
B21: Offshore Recruiting | C21: =SUMIFS($P21:$AT21,$P$5:$AT$5,">"&C$199,$P$5:$AT$5,"<"&C$200) -> 23.6 | D21: =SUMIFS($P21:$AT21,$P$5:$AT$5,">"&D$199,$P$5:$AT$5,"<"&D$200) -> 0.2 | F21: =SUMIFS($P21:$AT21,$P$5:$AT$5,">"&F$199,$P$5:$AT$5,"<"&F$200) -> 0.2 | G21: =SUMIFS($P21:$AT21,$P$5:$AT$5,">"&G$199,$P$5:$AT$5,"<"&G$200) -> 0 | I21: =SUMIFS($P21:$AT21,$P$5:$AT$5,">"&I$199,$P$5:$AT$5,"<"&I$200) -> 6.235 | J21: =SUMIFS($P21:$AT21,$P$5:$AT$5,">"&J$199,$P$5:$AT$5,"<"&J$200) -> 0 | K21: =+C125 -> 0 | M21: =K21-J21 -> 0 | N21: =IFERROR(K21/J21-1,0) -> 0 | P21: =SUMIFS('Combined P&L'!N:N,'Combined P&L'!$C:$C,'P&L Forecast'!$B21) -> 0.5 | Q21: =SUMIFS('Combined P&L'!O:O,'Combined P&L'!$C:$C,'P&L Forecast'!$B21) -> 3 | R21: =SUMIFS('Combined P&L'!P:P,'Combined P&L'!$C:$C,'P&L Forecast'!$B21) -> 0 | S21: =SUMIFS('Combined P&L'!Q:Q,'Combined P&L'!$C:$C,'P&L Forecast'!$B21) -> 0 | T21: =SUMIFS('Combined P&L'!R:R,'Combined P&L'!$C:$C,'P&L Forecast'!$B21) -> 3 | U21: =SUMIFS('Combined P&L'!S:S,'Combined P&L'!$C:$C,'P&L Forecast'!$B21) -> 0.565 | V21: =SUMIFS('Combined P&L'!T:T,'Combined P&L'!$C:$C,'P&L Forecast'!$B21) -> 10.5 | W21: =SUMIFS('Combined P&L'!U:U,'Combined P&L'!$C:$C,'P&L Forecast'!$B21) -> 6.5 | X21: =SUMIFS('Combined P&L'!V:V,'Combined P&L'!$C:$C,'P&L Forecast'!$B21) -> 0.5 | Y21: =SUMIFS('Combined P&L'!W:W,'Combined P&L'!$C:$C,'P&L Forecast'!$B21) -> -0.965 | Z21: =SUMIFS('Combined P&L'!X:X,'Combined P&L'!$C:$C,'P&L Forecast'!$B21) -> 0 | AA21: =SUMIFS('Combined P&L'!Y:Y,'Combined P&L'!$C:$C,'P&L Forecast'!$B21) -> 0 | AB21: =SUMIFS('Combined P&L'!Z:Z,'Combined P&L'!$C:$C,'P&L Forecast'!$B21) -> 0.1 | AC21: =SUMIFS('Combined P&L'!AA:AA,'Combined P&L'!$C:$C,'P&L Forecast'!$B21) -> 0 | AD21: =SUMIFS('Combined P&L'!AB:AB,'Combined P&L'!$C:$C,'P&L Forecast'!$B21) -> 0.1 | AE21: =SUMIFS('Combined P&L'!AC:AC,'Combined P&L'!$C:$C,'P&L Forecast'!$B21) -> 0 | AF21: =SUMIFS('Combined P&L'!AD:AD,'Combined P&L'!$C:$C,'P&L Forecast'!$B21) -> 0 | AG21: =SUMIFS('Combined P&L'!AE:AE,'Combined P&L'!$C:$C,'P&L Forecast'!$B21) -> 0 | AH21: =SUMIFS('Combined P&L'!AF:AF,'Combined P&L'!$C:$C,'P&L Forecast'!$B21) -> 0 | AI21: =SUMIFS('Combined P&L'!AG:AG,'Combined P&L'!$C:$C,'P&L Forecast'!$B21) -> 0 | AJ21: =SUMIFS('Combined P&L'!AH:AH,'Combined P&L'!$C:$C,'P&L Forecast'!$B21) -> 0 | AK21: =SUMIFS('Combined P&L'!AI:AI,'Combined P&L'!$C:$C,'P&L Forecast'!$B21) -> 0 | AL21: =SUMIFS('Combined P&L'!AJ:AJ,'Combined P&L'!$C:$C,'P&L Forecast'!$B21) -> 0 | AM21: =SUMIFS('Combined P&L'!AK:AK,'Combined P&L'!$C:$C,'P&L Forecast'!$B21) -> 0 | AN21: =SUMIFS('Combined P&L'!AL:AL,'Combined P&L'!$C:$C,'P&L Forecast'!$B21) -> 0 | AO21: =SUMIFS('Combined P&L'!AM:AM,'Combined P&L'!$C:$C,'P&L Forecast'!$B21) -> 0 | AP21: =SUMIFS('Combined P&L'!AN:AN,'Combined P&L'!$C:$C,'P&L Forecast'!$B21) -> 0 | AQ21: =SUMIFS('Combined P&L'!AO:AO,'Combined P&L'!$C:$C,'P&L Forecast'!$B21) -> 0 | AR21: =SUMIFS('Combined P&L'!AP:AP,'Combined P&L'!$C:$C,'P&L Forecast'!$B21) -> 0 | AS21: =SUMIFS('Combined P&L'!AQ:AQ,'Combined P&L'!$C:$C,'P&L Forecast'!$B21) -> 0 | AT21: =SUMIFS('Combined P&L'!AR:AR,'Combined P&L'!$C:$C,'P&L Forecast'!$B21) -> 0
B22: Total Nonrecurring Revenue | C22: =SUM(C17:C21) -> 40.6501 | D22: =SUM(D17:D21) -> 51.53373 | F22: =SUM(F17:F21) -> 38.9822 | G22: =SUM(G17:G21) -> 70.95371 | I22: =SUM(I17:I21) -> 48.8716 | J22: =SUM(J17:J21) -> 83.50524 | K22: =SUM(K17:K21) -> 55.59772 | M22: =SUM(M17:M21) -> -27.90752 | N22: =IFERROR(K22/J22-1,0) -> -0.33420082 | P22: =SUM(P17:P21) -> 7.5636 | Q22: =SUM(Q17:Q21) -> 6.5112 | R22: =SUM(R17:R21) -> 0.1162 | S22: =SUM(S17:S21) -> 0.1406 | T22: =SUM(T17:T21) -> 3.592 | U22: =SUM(U17:U21) -> 1.3718 | V22: =SUM(V17:V21) -> 11.4653 | W22: =SUM(W17:W21) -> 7.3414 | ... AT22: =SUM(AT17:AT21) -> 0.0872
B24: Total Run-Rate Revenue | C24: =+C22+C15 -> 1134.9659 | D24: =+D22+D15 -> 1879.3831 | F24: =+F22+F15 -> 997.8731 | G24: =+G22+G15 -> 1671.0212 | I24: =+I22+I15 -> 1524.4107 | J24: =+J22+J15 -> 2552.5312 | K24: =+K22+K15 -> 2998.541 | M24: =+M22+M15 -> 446.00979 | N24: =IFERROR(K24/J24-1,0) -> 0.17473235 | P24: =+P22+P15 -> 80.9131 | Q24: =+Q22+Q15 -> 81.2557 | R24: =+R22+R15 -> 78.1122 | S24: =+S22+S15 -> 83.3533 | T24: =+T22+T15 -> 90.19615 | U24: =+U22+U15 -> 89.9158 | V24: =+V22+V15 -> 104.68205 | W24: =+W22+W15 -> 104.11675 | ... AT24: =+AT22+AT15 -> 251.42585
B26: Unclassified Active Client Revenue | C26: 0 | D26: 0 | F26: 0 | G26: 0 | I26: 0 | J26: 0 | K26: =+'Client Retention $'!F13-'P&L Forecast'!K24 -> 93.9827 | M26: =K26-J26 -> 93.9827 | N26: =IFERROR(K26/J26-1,0) -> 0 | P26: 0 | Q26: 0 | R26: 0 | S26: 0 | T26: 0 | U26: 0 | V26: 0 | W26: 0 | X26: 0 | Y26: 0 | Z26: 0 | AA26: 0 | AB26: 0 | AC26: 0 | AD26: 0 | AE26: 0 | AF26: 0 | AG26: 0 | AH26: 0 | AI26: 0 | AJ26: 0 | AK26: 0 | AL26: 0 | AM26: 0 | AN26: 0 | AO26: 0 | AP26: 0 | AQ26: 0 | AR26: 0 | AS26: 0 | AT26: 0
B28: Total Adj. Revenue | C28: =+C26+C24 -> 1134.9659 | D28: =+D26+D24 -> 1879.3831 | F28: =+F26+F24 -> 997.8731 | G28: =+G26+G24 -> 1671.0212 | I28: =+I26+I24 -> 1524.4107 | J28: =+J26+J24 -> 2552.5312 | K28: =+K26+K24 -> 3092.5237 | M28: =+M26+M24 -> 539.99249 | N28: =IFERROR(K28/J28-1,0) -> 0.21155177 | P28: =+P26+P19 -> 0 | Q28: =+Q26+Q19 -> 0 | R28: =+R26+R19 -> 0 | S28: =+S26+S19 -> 0 | T28: =+T26+T19 -> 0 | U28: =+U26+U19 -> 0 | V28: =+V26+V19 -> 0 | W28: =+W26+W19 -> 0 | ... AT28: =+AT26+AT19 -> 0
B30: Expenses
B31: Indirect Labor | C31: =SUMIFS($P31:$AT31,$P$5:$AT$5,">"&C$199,$P$5:$AT$5,"<"&C$200) -> 101.3752 | D31: =SUMIFS($P31:$AT31,$P$5:$AT$5,">"&D$199,$P$5:$AT$5,"<"&D$200) -> 281.24054 | F31: =SUMIFS($P31:$AT31,$P$5:$AT$5,">"&F$199,$P$5:$AT$5,"<"&F$200) -> 136.29648 | G31: =SUMIFS($P31:$AT31,$P$5:$AT$5,">"&G$199,$P$5:$AT$5,"<"&G$200) -> 357.27472 | I31: =SUMIFS($P31:$AT31,$P$5:$AT$5,">"&I$199,$P$5:$AT$5,"<"&I$200) -> 202.41598 | J31: =SUMIFS($P31:$AT31,$P$5:$AT$5,">"&J$199,$P$5:$AT$5,"<"&J$200) -> 502.21878 | K31: =+C129 -> 681.3 | M31: =K31-J31 -> 179.08122 | N31: =IFERROR(K31/J31-1,0) -> 0.35658009 | P31: =SUMIFS('Combined P&L'!N:N,'Combined P&L'!$C:$C,'P&L Forecast'!$B31) -> 3.09346 | Q31: =SUMIFS('Combined P&L'!O:O,'Combined P&L'!$C:$C,'P&L Forecast'!$B31) -> 4.63017 | R31: =SUMIFS('Combined P&L'!P:P,'Combined P&L'!$C:$C,'P&L Forecast'!$B31) -> 4.39507 | S31: =SUMIFS('Combined P&L'!Q:Q,'Combined P&L'!$C:$C,'P&L Forecast'!$B31) -> 5.86387 | T31: =SUMIFS('Combined P&L'!R:R,'Combined P&L'!$C:$C,'P&L Forecast'!$B31) -> 7.37233 | U31: =SUMIFS('Combined P&L'!S:S,'Combined P&L'!$C:$C,'P&L Forecast'!$B31) -> 4.9504 | V31: =SUMIFS('Combined P&L'!T:T,'Combined P&L'!$C:$C,'P&L Forecast'!$B31) -> 4.9504 | W31: =SUMIFS('Combined P&L'!U:U,'Combined P&L'!$C:$C,'P&L Forecast'!$B31) -> 4.70035 | X31: =SUMIFS('Combined P&L'!V:V,'Combined P&L'!$C:$C,'P&L Forecast'!$B31) -> 4.9504 | Y31: =SUMIFS('Combined P&L'!W:W,'Combined P&L'!$C:$C,'P&L Forecast'!$B31) -> 5.99987 | Z31: =SUMIFS('Combined P&L'!X:X,'Combined P&L'!$C:$C,'P&L Forecast'!$B31) -> 26.02876 | AA31: =SUMIFS('Combined P&L'!Y:Y,'Combined P&L'!$C:$C,'P&L Forecast'!$B31) -> 24.44012 | AB31: =SUMIFS('Combined P&L'!Z:Z,'Combined P&L'!$C:$C,'P&L Forecast'!$B31) -> 21.05234 | AC31: =SUMIFS('Combined P&L'!AA:AA,'Combined P&L'!$C:$C,'P&L Forecast'!$B31) -> 19.91603 | AD31: =SUMIFS('Combined P&L'!AB:AB,'Combined P&L'!$C:$C,'P&L Forecast'!$B31) -> 11.74387 | AE31: =SUMIFS('Combined P&L'!AC:AC,'Combined P&L'!$C:$C,'P&L Forecast'!$B31) -> 19.61792 | AF31: =SUMIFS('Combined P&L'!AD:AD,'Combined P&L'!$C:$C,'P&L Forecast'!$B31) -> 20.66978 | AG31: =SUMIFS('Combined P&L'!AE:AE,'Combined P&L'!$C:$C,'P&L Forecast'!$B31) -> 20.6939 | AH31: =SUMIFS('Combined P&L'!AF:AF,'Combined P&L'!$C:$C,'P&L Forecast'!$B31) -> 22.60264 | AI31: =SUMIFS('Combined P&L'!AG:AG,'Combined P&L'!$C:$C,'P&L Forecast'!$B31) -> 19.96128 | AJ31: =SUMIFS('Combined P&L'!AH:AH,'Combined P&L'!$C:$C,'P&L Forecast'!$B31) -> 27.60563 | AK31: =SUMIFS('Combined P&L'!AI:AI,'Combined P&L'!$C:$C,'P&L Forecast'!$B31) -> 34.18589 | AL31: =SUMIFS('Combined P&L'!AJ:AJ,'Combined P&L'!$C:$C,'P&L Forecast'!$B31) -> 29.73157 | AM31: =SUMIFS('Combined P&L'!AK:AK,'Combined P&L'!$C:$C,'P&L Forecast'!$B31) -> 33.45969 | AN31: =SUMIFS('Combined P&L'!AL:AL,'Combined P&L'!$C:$C,'P&L Forecast'!$B31) -> 36.2536 | AO31: =SUMIFS('Combined P&L'!AM:AM,'Combined P&L'!$C:$C,'P&L Forecast'!$B31) -> 33.60751 | AP31: =SUMIFS('Combined P&L'!AN:AN,'Combined P&L'!$C:$C,'P&L Forecast'!$B31) -> 57.19924 | AQ31: =SUMIFS('Combined P&L'!AO:AO,'Combined P&L'!$C:$C,'P&L Forecast'!$B31) -> 58.24595 | AR31: =SUMIFS('Combined P&L'!AP:AP,'Combined P&L'!$C:$C,'P&L Forecast'!$B31) -> 54.06923 | AS31: =SUMIFS('Combined P&L'!AQ:AQ,'Combined P&L'!$C:$C,'P&L Forecast'!$B31) -> 60.00381 | AT31: =SUMIFS('Combined P&L'!AR:AR,'Combined P&L'!$C:$C,'P&L Forecast'!$B31) -> 57.89538
B32: Bookkeeper Wages | C32: =SUMIFS($P32:$AT32,$P$5:$AT$5,">"&C$199,$P$5:$AT$5,"<"&C$200) -> 183.36903 | D32: =SUMIFS($P32:$AT32,$P$5:$AT$5,">"&D$199,$P$5:$AT$5,"<"&D$200) -> 316.18462 | F32: =SUMIFS($P32:$AT32,$P$5:$AT$5,">"&F$199,$P$5:$AT$5,"<"&F$200) -> 147.26813 | G32: =SUMIFS($P32:$AT32,$P$5:$AT$5,">"&G$199,$P$5:$AT$5,"<"&G$200) -> 267.7574 | I32: =SUMIFS($P32:$AT32,$P$5:$AT$5,">"&I$199,$P$5:$AT$5,"<"&I$200) -> 240.18098 | J32: =SUMIFS($P32:$AT32,$P$5:$AT$5,">"&J$199,$P$5:$AT$5,"<"&J$200) -> 436.67389 | K32: =+C130 -> 492.6 | M32: =K32-J32 -> 55.92611 | N32: =IFERROR(K32/J32-1,0) -> 0.12807294 | P32: =SUMIFS('Combined P&L'!N:N,'Combined P&L'!$C:$C,'P&L Forecast'!$B32) -> 9.555 | Q32: =SUMIFS('Combined P&L'!O:O,'Combined P&L'!$C:$C,'P&L Forecast'!$B32) -> 9.555 | R32: =SUMIFS('Combined P&L'!P:P,'Combined P&L'!$C:$C,'P&L Forecast'!$B32) -> 10.3972 | S32: =SUMIFS('Combined P&L'!Q:Q,'Combined P&L'!$C:$C,'P&L Forecast'!$B32) -> 14.99967 | T32: =SUMIFS('Combined P&L'!R:R,'Combined P&L'!$C:$C,'P&L Forecast'!$B32) -> 18.0098 | U32: =SUMIFS('Combined P&L'!S:S,'Combined P&L'!$C:$C,'P&L Forecast'!$B32) -> 13.89127 | V32: =SUMIFS('Combined P&L'!T:T,'Combined P&L'!$C:$C,'P&L Forecast'!$B32) -> 14.04824 | W32: =SUMIFS('Combined P&L'!U:U,'Combined P&L'!$C:$C,'P&L Forecast'!$B32) -> 13.39091 | X32: =SUMIFS('Combined P&L'!V:V,'Combined P&L'!$C:$C,'P&L Forecast'!$B32) -> 14.66931 | Y32: =SUMIFS('Combined P&L'!W:W,'Combined P&L'!$C:$C,'P&L Forecast'!$B32) -> 15.88253 | Z32: =SUMIFS('Combined P&L'!X:X,'Combined P&L'!$C:$C,'P&L Forecast'!$B32) -> 27.18867 | AA32: =SUMIFS('Combined P&L'!Y:Y,'Combined P&L'!$C:$C,'P&L Forecast'!$B32) -> 21.78143 | AB32: =SUMIFS('Combined P&L'!Z:Z,'Combined P&L'!$C:$C,'P&L Forecast'!$B32) -> 19.40233 | AC32: =SUMIFS('Combined P&L'!AA:AA,'Combined P&L'!$C:$C,'P&L Forecast'!$B32) -> 16.40053 | AD32: =SUMIFS('Combined P&L'!AB:AB,'Combined P&L'!$C:$C,'P&L Forecast'!$B32) -> 19.56983 | AE32: =SUMIFS('Combined P&L'!AC:AC,'Combined P&L'!$C:$C,'P&L Forecast'!$B32) -> 22.1542 | AF32: =SUMIFS('Combined P&L'!AD:AD,'Combined P&L'!$C:$C,'P&L Forecast'!$B32) -> 20.79154 | AG32: =SUMIFS('Combined P&L'!AE:AE,'Combined P&L'!$C:$C,'P&L Forecast'!$B32) -> 21.04079 | AH32: =SUMIFS('Combined P&L'!AF:AF,'Combined P&L'!$C:$C,'P&L Forecast'!$B32) -> 27.90891 | AI32: =SUMIFS('Combined P&L'!AG:AG,'Combined P&L'!$C:$C,'P&L Forecast'!$B32) -> 29.547 | AJ32: =SUMIFS('Combined P&L'!AH:AH,'Combined P&L'!$C:$C,'P&L Forecast'!$B32) -> 33.44727 | AK32: =SUMIFS('Combined P&L'!AI:AI,'Combined P&L'!$C:$C,'P&L Forecast'!$B32) -> 37.79432 | AL32: =SUMIFS('Combined P&L'!AJ:AJ,'Combined P&L'!$C:$C,'P&L Forecast'!$B32) -> 34.06332 | AM32: =SUMIFS('Combined P&L'!AK:AK,'Combined P&L'!$C:$C,'P&L Forecast'!$B32) -> 34.06458 | AN32: =SUMIFS('Combined P&L'!AL:AL,'Combined P&L'!$C:$C,'P&L Forecast'!$B32) -> 38.37888 | AO32: =SUMIFS('Combined P&L'!AM:AM,'Combined P&L'!$C:$C,'P&L Forecast'!$B32) -> 29.70152 | AP32: =SUMIFS('Combined P&L'!AN:AN,'Combined P&L'!$C:$C,'P&L Forecast'!$B32) -> 37.4225 | AQ32: =SUMIFS('Combined P&L'!AO:AO,'Combined P&L'!$C:$C,'P&L Forecast'!$B32) -> 38.7723 | AR32: =SUMIFS('Combined P&L'!AP:AP,'Combined P&L'!$C:$C,'P&L Forecast'!$B32) -> 38.29477 | AS32: =SUMIFS('Combined P&L'!AQ:AQ,'Combined P&L'!$C:$C,'P&L Forecast'!$B32) -> 40.69983 | AT32: =SUMIFS('Combined P&L'!AR:AR,'Combined P&L'!$C:$C,'P&L Forecast'!$B32) -> 44.4876
B33: Client Lead Wages | C33: =SUMIFS($P33:$AT33,$P$5:$AT$5,">"&C$199,$P$5:$AT$5,"<"&C$200) -> 286.16129 | D33: =SUMIFS($P33:$AT33,$P$5:$AT$5,">"&D$199,$P$5:$AT$5,"<"&D$200) -> 352.95844 | F33: =SUMIFS($P33:$AT33,$P$5:$AT$5,">"&F$199,$P$5:$AT$5,"<"&F$200) -> 201.27983 | G33: =SUMIFS($P33:$AT33,$P$5:$AT$5,">"&G$199,$P$5:$AT$5,"<"&G$200) -> 202.05309 | I33: =SUMIFS($P33:$AT33,$P$5:$AT$5,">"&I$199,$P$5:$AT$5,"<"&I$200) -> 353.12843 | J33: =SUMIFS($P33:$AT33,$P$5:$AT$5,">"&J$199,$P$5:$AT$5,"<"&J$200) -> 353.7317 | K33: =+C132 -> 392.92452 | M33: =K33-J33 -> 39.19282 | N33: =IFERROR(K33/J33-1,0) -> 0.11079816 | P33: =SUMIFS('Combined P&L'!N:N,'Combined P&L'!$C:$C,'P&L Forecast'!$B33) -> 9.96108 | Q33: =SUMIFS('Combined P&L'!O:O,'Combined P&L'!$C:$C,'P&L Forecast'!$B33) -> 13.85026 | R33: =SUMIFS('Combined P&L'!P:P,'Combined P&L'!$C:$C,'P&L Forecast'!$B33) -> 12.79054 | S33: =SUMIFS('Combined P&L'!Q:Q,'Combined P&L'!$C:$C,'P&L Forecast'!$B33) -> 14.57145 | T33: =SUMIFS('Combined P&L'!R:R,'Combined P&L'!$C:$C,'P&L Forecast'!$B33) -> 28.28563 | U33: =SUMIFS('Combined P&L'!S:S,'Combined P&L'!$C:$C,'P&L Forecast'!$B33) -> 26.54254 | V33: =SUMIFS('Combined P&L'!T:T,'Combined P&L'!$C:$C,'P&L Forecast'!$B33) -> 28.31119 | W33: =SUMIFS('Combined P&L'!U:U,'Combined P&L'!$C:$C,'P&L Forecast'!$B33) -> 28.18746 | X33: =SUMIFS('Combined P&L'!V:V,'Combined P&L'!$C:$C,'P&L Forecast'!$B33) -> 30.86801 | Y33: =SUMIFS('Combined P&L'!W:W,'Combined P&L'!$C:$C,'P&L Forecast'!$B33) -> 31.62128 | Z33: =SUMIFS('Combined P&L'!X:X,'Combined P&L'!$C:$C,'P&L Forecast'!$B33) -> 28.44974 | AA33: =SUMIFS('Combined P&L'!Y:Y,'Combined P&L'!$C:$C,'P&L Forecast'!$B33) -> 32.72211 | AB33: =SUMIFS('Combined P&L'!Z:Z,'Combined P&L'!$C:$C,'P&L Forecast'!$B33) -> 32.78076 | AC33: =SUMIFS('Combined P&L'!AA:AA,'Combined P&L'!$C:$C,'P&L Forecast'!$B33) -> 23.36184 | AD33: =SUMIFS('Combined P&L'!AB:AB,'Combined P&L'!$C:$C,'P&L Forecast'!$B33) -> 26.91427 | AE33: =SUMIFS('Combined P&L'!AC:AC,'Combined P&L'!$C:$C,'P&L Forecast'!$B33) -> 28.81298 | AF33: =SUMIFS('Combined P&L'!AD:AD,'Combined P&L'!$C:$C,'P&L Forecast'!$B33) -> 30.65875 | AG33: =SUMIFS('Combined P&L'!AE:AE,'Combined P&L'!$C:$C,'P&L Forecast'!$B33) -> 29.2716 | AH33: =SUMIFS('Combined P&L'!AF:AF,'Combined P&L'!$C:$C,'P&L Forecast'!$B33) -> 29.47963 | AI33: =SUMIFS('Combined P&L'!AG:AG,'Combined P&L'!$C:$C,'P&L Forecast'!$B33) -> 26.83064 | AJ33: =SUMIFS('Combined P&L'!AH:AH,'Combined P&L'!$C:$C,'P&L Forecast'!$B33) -> 29.78555 | AK33: =SUMIFS('Combined P&L'!AI:AI,'Combined P&L'!$C:$C,'P&L Forecast'!$B33) -> 32.89937 | AL33: =SUMIFS('Combined P&L'!AJ:AJ,'Combined P&L'!$C:$C,'P&L Forecast'!$B33) -> 29.49334 | AM33: =SUMIFS('Combined P&L'!AK:AK,'Combined P&L'!$C:$C,'P&L Forecast'!$B33) -> 32.66971 | AN33: =SUMIFS('Combined P&L'!AL:AL,'Combined P&L'!$C:$C,'P&L Forecast'!$B33) -> 26.1149 | AO33: =SUMIFS('Combined P&L'!AM:AM,'Combined P&L'!$C:$C,'P&L Forecast'!$B33) -> 21.9055 | AP33: =SUMIFS('Combined P&L'!AN:AN,'Combined P&L'!$C:$C,'P&L Forecast'!$B33) -> 30.75844 | AQ33: =SUMIFS('Combined P&L'!AO:AO,'Combined P&L'!$C:$C,'P&L Forecast'!$B33) -> 31.59038 | AR33: =SUMIFS('Combined P&L'!AP:AP,'Combined P&L'!$C:$C,'P&L Forecast'!$B33) -> 27.69992 | AS33: =SUMIFS('Combined P&L'!AQ:AQ,'Combined P&L'!$C:$C,'P&L Forecast'!$B33) -> 31.24024 | AT33: =SUMIFS('Combined P&L'!AR:AR,'Combined P&L'!$C:$C,'P&L Forecast'!$B33) -> 32.74371
B34: Onboarding Team Wages | C34: =SUMIFS($P34:$AT34,$P$5:$AT$5,">"&C$199,$P$5:$AT$5,"<"&C$200) -> 122.81255 | D34: =SUMIFS($P34:$AT34,$P$5:$AT$5,">"&D$199,$P$5:$AT$5,"<"&D$200) -> 152.16972 | F34: =SUMIFS($P34:$AT34,$P$5:$AT$5,">"&F$199,$P$5:$AT$5,"<"&F$200) -> 73.94962 | G34: =SUMIFS($P34:$AT34,$P$5:$AT$5,">"&G$199,$P$5:$AT$5,"<"&G$200) -> 111.27999 | I34: =SUMIFS($P34:$AT34,$P$5:$AT$5,">"&I$199,$P$5:$AT$5,"<"&I$200) -> 121.30735 | J34: =SUMIFS($P34:$AT34,$P$5:$AT$5,">"&J$199,$P$5:$AT$5,"<"&J$200) -> 189.50009 | K34: =+C136 -> 197.14944 | M34: =K34-J34 -> 7.64935 | N34: =IFERROR(K34/J34-1,0) -> 0.040365944 | P34: =SUMIFS('Combined P&L'!N:N,'Combined P&L'!$C:$C,'P&L Forecast'!$B34) -> 9.13728 | Q34: =SUMIFS('Combined P&L'!O:O,'Combined P&L'!$C:$C,'P&L Forecast'!$B34) -> 8.96296 | R34: =SUMIFS('Combined P&L'!P:P,'Combined P&L'!$C:$C,'P&L Forecast'!$B34) -> 10.19584 | S34: =SUMIFS('Combined P&L'!Q:Q,'Combined P&L'!$C:$C,'P&L Forecast'!$B34) -> 15.04429 | T34: =SUMIFS('Combined P&L'!R:R,'Combined P&L'!$C:$C,'P&L Forecast'!$B34) -> 16.63744 | U34: =SUMIFS('Combined P&L'!S:S,'Combined P&L'!$C:$C,'P&L Forecast'!$B34) -> 7.49499 | V34: =SUMIFS('Combined P&L'!T:T,'Combined P&L'!$C:$C,'P&L Forecast'!$B34) -> 7.98202 | W34: =SUMIFS('Combined P&L'!U:U,'Combined P&L'!$C:$C,'P&L Forecast'!$B34) -> 5.90274 | X34: =SUMIFS('Combined P&L'!V:V,'Combined P&L'!$C:$C,'P&L Forecast'!$B34) -> 7.76763 | Y34: =SUMIFS('Combined P&L'!W:W,'Combined P&L'!$C:$C,'P&L Forecast'!$B34) -> 8.21417 | Z34: =SUMIFS('Combined P&L'!X:X,'Combined P&L'!$C:$C,'P&L Forecast'!$B34) -> 12.62272 | AA34: =SUMIFS('Combined P&L'!Y:Y,'Combined P&L'!$C:$C,'P&L Forecast'!$B34) -> 12.85047 | AB34: =SUMIFS('Combined P&L'!Z:Z,'Combined P&L'!$C:$C,'P&L Forecast'!$B34) -> 10.34556 | AC34: =SUMIFS('Combined P&L'!AA:AA,'Combined P&L'!$C:$C,'P&L Forecast'!$B34) -> 8.08798 | AD34: =SUMIFS('Combined P&L'!AB:AB,'Combined P&L'!$C:$C,'P&L Forecast'!$B34) -> 9.75287 | AE34: =SUMIFS('Combined P&L'!AC:AC,'Combined P&L'!$C:$C,'P&L Forecast'!$B34) -> 10.28 | AF34: =SUMIFS('Combined P&L'!AD:AD,'Combined P&L'!$C:$C,'P&L Forecast'!$B34) -> 11.13632 | AG34: =SUMIFS('Combined P&L'!AE:AE,'Combined P&L'!$C:$C,'P&L Forecast'!$B34) -> 10.87432 | AH34: =SUMIFS('Combined P&L'!AF:AF,'Combined P&L'!$C:$C,'P&L Forecast'!$B34) -> 13.47257 | AI34: =SUMIFS('Combined P&L'!AG:AG,'Combined P&L'!$C:$C,'P&L Forecast'!$B34) -> 12.70407 | AJ34: =SUMIFS('Combined P&L'!AH:AH,'Combined P&L'!$C:$C,'P&L Forecast'!$B34) -> 14.69884 | AK34: =SUMIFS('Combined P&L'!AI:AI,'Combined P&L'!$C:$C,'P&L Forecast'!$B34) -> 15.54306 | AL34: =SUMIFS('Combined P&L'!AJ:AJ,'Combined P&L'!$C:$C,'P&L Forecast'!$B34) -> 14.34361 | AM34: =SUMIFS('Combined P&L'!AK:AK,'Combined P&L'!$C:$C,'P&L Forecast'!$B34) -> 20.93052 | AN34: =SUMIFS('Combined P&L'!AL:AL,'Combined P&L'!$C:$C,'P&L Forecast'!$B34) -> 16.55394 | AO34: =SUMIFS('Combined P&L'!AM:AM,'Combined P&L'!$C:$C,'P&L Forecast'!$B34) -> 11.52661 | AP34: =SUMIFS('Combined P&L'!AN:AN,'Combined P&L'!$C:$C,'P&L Forecast'!$B34) -> 14.93883 | AQ34: =SUMIFS('Combined P&L'!AO:AO,'Combined P&L'!$C:$C,'P&L Forecast'!$B34) -> 15.58352 | AR34: =SUMIFS('Combined P&L'!AP:AP,'Combined P&L'!$C:$C,'P&L Forecast'!$B34) -> 19.6034 | AS34: =SUMIFS('Combined P&L'!AQ:AQ,'Combined P&L'!$C:$C,'P&L Forecast'!$B34) -> 16.64457 | AT34: =SUMIFS('Combined P&L'!AR:AR,'Combined P&L'!$C:$C,'P&L Forecast'!$B34) -> 16.42912
B35: Owner Wages | C35: =SUMIFS($P35:$AT35,$P$5:$AT$5,">"&C$199,$P$5:$AT$5,"<"&C$200) -> 0 | D35: =SUMIFS($P35:$AT35,$P$5:$AT$5,">"&D$199,$P$5:$AT$5,"<"&D$200) -> 90.66704 | F35: =SUMIFS($P35:$AT35,$P$5:$AT$5,">"&F$199,$P$5:$AT$5,"<"&F$200) -> 45.46612 | G35: =SUMIFS($P35:$AT35,$P$5:$AT$5,">"&G$199,$P$5:$AT$5,"<"&G$200) -> 63.14302 | I35: =SUMIFS($P35:$AT35,$P$5:$AT$5,">"&I$199,$P$5:$AT$5,"<"&I$200) -> 45.46612 | J35: =SUMIFS($P35:$AT35,$P$5:$AT$5,">"&J$199,$P$5:$AT$5,"<"&J$200) -> 108.34394 | K35: =+C131 -> 108.34394 | M35: =K35-J35 -> 0 | N35: =IFERROR(K35/J35-1,0) -> 0 | P35: =SUMIFS('Combined P&L'!N:N,'Combined P&L'!$C:$C,'P&L Forecast'!$B35) -> 0 | Q35: =SUMIFS('Combined P&L'!O:O,'Combined P&L'!$C:$C,'P&L Forecast'!$B35) -> 0 | R35: =SUMIFS('Combined P&L'!P:P,'Combined P&L'!$C:$C,'P&L Forecast'!$B35) -> 0 | S35: =SUMIFS('Combined P&L'!Q:Q,'Combined P&L'!$C:$C,'P&L Forecast'!$B35) -> 0 | T35: =SUMIFS('Combined P&L'!R:R,'Combined P&L'!$C:$C,'P&L Forecast'!$B35) -> 0 | U35: =SUMIFS('Combined P&L'!S:S,'Combined P&L'!$C:$C,'P&L Forecast'!$B35) -> 0 | V35: =SUMIFS('Combined P&L'!T:T,'Combined P&L'!$C:$C,'P&L Forecast'!$B35) -> 0 | W35: =SUMIFS('Combined P&L'!U:U,'Combined P&L'!$C:$C,'P&L Forecast'!$B35) -> 0 | X35: =SUMIFS('Combined P&L'!V:V,'Combined P&L'!$C:$C,'P&L Forecast'!$B35) -> 0 | Y35: =SUMIFS('Combined P&L'!W:W,'Combined P&L'!$C:$C,'P&L Forecast'!$B35) -> 0 | Z35: =SUMIFS('Combined P&L'!X:X,'Combined P&L'!$C:$C,'P&L Forecast'!$B35) -> 0 | AA35: =SUMIFS('Combined P&L'!Y:Y,'Combined P&L'!$C:$C,'P&L Forecast'!$B35) -> 0 | AB35: =SUMIFS('Combined P&L'!Z:Z,'Combined P&L'!$C:$C,'P&L Forecast'!$B35) -> 0 | AC35: =SUMIFS('Combined P&L'!AA:AA,'Combined P&L'!$C:$C,'P&L Forecast'!$B35) -> 0 | AD35: =SUMIFS('Combined P&L'!AB:AB,'Combined P&L'!$C:$C,'P&L Forecast'!$B35) -> 8.90639 | AE35: =SUMIFS('Combined P&L'!AC:AC,'Combined P&L'!$C:$C,'P&L Forecast'!$B35) -> 9.23323 | AF35: =SUMIFS('Combined P&L'!AD:AD,'Combined P&L'!$C:$C,'P&L Forecast'!$B35) -> 9.10884 | AG35: =SUMIFS('Combined P&L'!AE:AE,'Combined P&L'!$C:$C,'P&L Forecast'!$B35) -> 8.69479 | AH35: =SUMIFS('Combined P&L'!AF:AF,'Combined P&L'!$C:$C,'P&L Forecast'!$B35) -> 9.52287 | AI35: =SUMIFS('Combined P&L'!AG:AG,'Combined P&L'!$C:$C,'P&L Forecast'!$B35) -> 8.69481 | AJ35: =SUMIFS('Combined P&L'!AH:AH,'Combined P&L'!$C:$C,'P&L Forecast'!$B35) -> 9.10884 | AK35: =SUMIFS('Combined P&L'!AI:AI,'Combined P&L'!$C:$C,'P&L Forecast'!$B35) -> 9.52287 | AL35: =SUMIFS('Combined P&L'!AJ:AJ,'Combined P&L'!$C:$C,'P&L Forecast'!$B35) -> 8.28076 | AM35: =SUMIFS('Combined P&L'!AK:AK,'Combined P&L'!$C:$C,'P&L Forecast'!$B35) -> 9.59364 | AN35: =SUMIFS('Combined P&L'!AL:AL,'Combined P&L'!$C:$C,'P&L Forecast'!$B35) -> 9.27621 | AO35: =SUMIFS('Combined P&L'!AM:AM,'Combined P&L'!$C:$C,'P&L Forecast'!$B35) -> 8.32263 | AP35: =SUMIFS('Combined P&L'!AN:AN,'Combined P&L'!$C:$C,'P&L Forecast'!$B35) -> 9.10883 | AQ35: =SUMIFS('Combined P&L'!AO:AO,'Combined P&L'!$C:$C,'P&L Forecast'!$B35) -> 9.10883 | AR35: =SUMIFS('Combined P&L'!AP:AP,'Combined P&L'!$C:$C,'P&L Forecast'!$B35) -> 8.69481 | AS35: =SUMIFS('Combined P&L'!AQ:AQ,'Combined P&L'!$C:$C,'P&L Forecast'!$B35) -> 9.10884 | AT35: =SUMIFS('Combined P&L'!AR:AR,'Combined P&L'!$C:$C,'P&L Forecast'!$B35) -> 9.52287
B36: S&M Wages | C36: =SUMIFS($P36:$AT36,$P$5:$AT$5,">"&C$199,$P$5:$AT$5,"<"&C$200) -> 0 | D36: =SUMIFS($P36:$AT36,$P$5:$AT$5,">"&D$199,$P$5:$AT$5,"<"&D$200) -> 19.14963 | F36: =SUMIFS($P36:$AT36,$P$5:$AT$5,">"&F$199,$P$5:$AT$5,"<"&F$200) -> 3.09945 | G36: =SUMIFS($P36:$AT36,$P$5:$AT$5,">"&G$199,$P$5:$AT$5,"<"&G$200) -> 51.94131 | I36: =SUMIFS($P36:$AT36,$P$5:$AT$5,">"&I$199,$P$5:$AT$5,"<"&I$200) -> 3.09945 | J36: =SUMIFS($P36:$AT36,$P$5:$AT$5,">"&J$199,$P$5:$AT$5,"<"&J$200) -> 67.99149 | K36: =+C133 -> 98.34912 | M36: =K36-J36 -> 30.35763 | N36: =IFERROR(K36/J36-1,0) -> 0.44649161 | P36: =SUMIFS('Combined P&L'!N:N,'Combined P&L'!$C:$C,'P&L Forecast'!$B36) -> 0 | Q36: =SUMIFS('Combined P&L'!O:O,'Combined P&L'!$C:$C,'P&L Forecast'!$B36) -> 0 | R36: =SUMIFS('Combined P&L'!P:P,'Combined P&L'!$C:$C,'P&L Forecast'!$B36) -> 0 | S36: =SUMIFS('Combined P&L'!Q:Q,'Combined P&L'!$C:$C,'P&L Forecast'!$B36) -> 0 | T36: =SUMIFS('Combined P&L'!R:R,'Combined P&L'!$C:$C,'P&L Forecast'!$B36) -> 0 | U36: =SUMIFS('Combined P&L'!S:S,'Combined P&L'!$C:$C,'P&L Forecast'!$B36) -> 0 | V36: =SUMIFS('Combined P&L'!T:T,'Combined P&L'!$C:$C,'P&L Forecast'!$B36) -> 0 | W36: =SUMIFS('Combined P&L'!U:U,'Combined P&L'!$C:$C,'P&L Forecast'!$B36) -> 0 | X36: =SUMIFS('Combined P&L'!V:V,'Combined P&L'!$C:$C,'P&L Forecast'!$B36) -> 0 | Y36: =SUMIFS('Combined P&L'!W:W,'Combined P&L'!$C:$C,'P&L Forecast'!$B36) -> 0 | Z36: =SUMIFS('Combined P&L'!X:X,'Combined P&L'!$C:$C,'P&L Forecast'!$B36) -> 0 | AA36: =SUMIFS('Combined P&L'!Y:Y,'Combined P&L'!$C:$C,'P&L Forecast'!$B36) -> 0 | AB36: =SUMIFS('Combined P&L'!Z:Z,'Combined P&L'!$C:$C,'P&L Forecast'!$B36) -> 0 | AC36: =SUMIFS('Combined P&L'!AA:AA,'Combined P&L'!$C:$C,'P&L Forecast'!$B36) -> 0 | AD36: =SUMIFS('Combined P&L'!AB:AB,'Combined P&L'!$C:$C,'P&L Forecast'!$B36) -> 0 | AE36: =SUMIFS('Combined P&L'!AC:AC,'Combined P&L'!$C:$C,'P&L Forecast'!$B36) -> 0 | AF36: =SUMIFS('Combined P&L'!AD:AD,'Combined P&L'!$C:$C,'P&L Forecast'!$B36) -> 0 | AG36: =SUMIFS('Combined P&L'!AE:AE,'Combined P&L'!$C:$C,'P&L Forecast'!$B36) -> 1.4668 | AH36: =SUMIFS('Combined P&L'!AF:AF,'Combined P&L'!$C:$C,'P&L Forecast'!$B36) -> 1.63265 | AI36: =SUMIFS('Combined P&L'!AG:AG,'Combined P&L'!$C:$C,'P&L Forecast'!$B36) -> 1.71805 | AJ36: =SUMIFS('Combined P&L'!AH:AH,'Combined P&L'!$C:$C,'P&L Forecast'!$B36) -> 1.9146 | AK36: =SUMIFS('Combined P&L'!AI:AI,'Combined P&L'!$C:$C,'P&L Forecast'!$B36) -> 2.3529 | AL36: =SUMIFS('Combined P&L'!AJ:AJ,'Combined P&L'!$C:$C,'P&L Forecast'!$B36) -> 2.24524 | AM36: =SUMIFS('Combined P&L'!AK:AK,'Combined P&L'!$C:$C,'P&L Forecast'!$B36) -> 7.81939 | AN36: =SUMIFS('Combined P&L'!AL:AL,'Combined P&L'!$C:$C,'P&L Forecast'!$B36) -> 5.6534 | AO36: =SUMIFS('Combined P&L'!AM:AM,'Combined P&L'!$C:$C,'P&L Forecast'!$B36) -> 5.95689 | AP36: =SUMIFS('Combined P&L'!AN:AN,'Combined P&L'!$C:$C,'P&L Forecast'!$B36) -> 7.7828 | AQ36: =SUMIFS('Combined P&L'!AO:AO,'Combined P&L'!$C:$C,'P&L Forecast'!$B36) -> 8.13701 | AR36: =SUMIFS('Combined P&L'!AP:AP,'Combined P&L'!$C:$C,'P&L Forecast'!$B36) -> 7.80825 | AS36: =SUMIFS('Combined P&L'!AQ:AQ,'Combined P&L'!$C:$C,'P&L Forecast'!$B36) -> 8.4072 | AT36: =SUMIFS('Combined P&L'!AR:AR,'Combined P&L'!$C:$C,'P&L Forecast'!$B36) -> 8.19576
B37: Occupancy Tax Specialist | C37: =SUMIFS($P37:$AT37,$P$5:$AT$5,">"&C$199,$P$5:$AT$5,"<"&C$200) -> 1.11335 | D37: =SUMIFS($P37:$AT37,$P$5:$AT$5,">"&D$199,$P$5:$AT$5,"<"&D$200) -> 29.56415 | F37: =SUMIFS($P37:$AT37,$P$5:$AT$5,">"&F$199,$P$5:$AT$5,"<"&F$200) -> 14.27585 | G37: =SUMIFS($P37:$AT37,$P$5:$AT$5,">"&G$199,$P$5:$AT$5,"<"&G$200) -> 42.08505 | I37: =SUMIFS($P37:$AT37,$P$5:$AT$5,">"&I$199,$P$5:$AT$5,"<"&I$200) -> 15.3892 | J37: =SUMIFS($P37:$AT37,$P$5:$AT$5,">"&J$199,$P$5:$AT$5,"<"&J$200) -> 57.37335 | K37: =+C134 -> 58.2 | M37: =K37-J37 -> 0.82665 | N37: =IFERROR(K37/J37-1,0) -> 0.014408257 | P37: =SUMIFS('Combined P&L'!N:N,'Combined P&L'!$C:$C,'P&L Forecast'!$B37) -> 0 | Q37: =SUMIFS('Combined P&L'!O:O,'Combined P&L'!$C:$C,'P&L Forecast'!$B37) -> 0 | R37: =SUMIFS('Combined P&L'!P:P,'Combined P&L'!$C:$C,'P&L Forecast'!$B37) -> 0 | S37: =SUMIFS('Combined P&L'!Q:Q,'Combined P&L'!$C:$C,'P&L Forecast'!$B37) -> 0 | T37: =SUMIFS('Combined P&L'!R:R,'Combined P&L'!$C:$C,'P&L Forecast'!$B37) -> 0 | U37: =SUMIFS('Combined P&L'!S:S,'Combined P&L'!$C:$C,'P&L Forecast'!$B37) -> 0 | V37: =SUMIFS('Combined P&L'!T:T,'Combined P&L'!$C:$C,'P&L Forecast'!$B37) -> 0 | W37: =SUMIFS('Combined P&L'!U:U,'Combined P&L'!$C:$C,'P&L Forecast'!$B37) -> 0 | X37: =SUMIFS('Combined P&L'!V:V,'Combined P&L'!$C:$C,'P&L Forecast'!$B37) -> 0 | Y37: =SUMIFS('Combined P&L'!W:W,'Combined P&L'!$C:$C,'P&L Forecast'!$B37) -> 0 | Z37: =SUMIFS('Combined P&L'!X:X,'Combined P&L'!$C:$C,'P&L Forecast'!$B37) -> 0 | AA37: =SUMIFS('Combined P&L'!Y:Y,'Combined P&L'!$C:$C,'P&L Forecast'!$B37) -> 1.11335 | AB37: =SUMIFS('Combined P&L'!Z:Z,'Combined P&L'!$C:$C,'P&L Forecast'!$B37) -> 2.17917 | AC37: =SUMIFS('Combined P&L'!AA:AA,'Combined P&L'!$C:$C,'P&L Forecast'!$B37) -> 1.82504 | AD37: =SUMIFS('Combined P&L'!AB:AB,'Combined P&L'!$C:$C,'P&L Forecast'!$B37) -> 1.97853 | AE37: =SUMIFS('Combined P&L'!AC:AC,'Combined P&L'!$C:$C,'P&L Forecast'!$B37) -> 2.06213 | AF37: =SUMIFS('Combined P&L'!AD:AD,'Combined P&L'!$C:$C,'P&L Forecast'!$B37) -> 2.06213 | AG37: =SUMIFS('Combined P&L'!AE:AE,'Combined P&L'!$C:$C,'P&L Forecast'!$B37) -> 1.98968 | AH37: =SUMIFS('Combined P&L'!AF:AF,'Combined P&L'!$C:$C,'P&L Forecast'!$B37) -> 2.17917 | AI37: =SUMIFS('Combined P&L'!AG:AG,'Combined P&L'!$C:$C,'P&L Forecast'!$B37) -> 2.12293 | AJ37: =SUMIFS('Combined P&L'!AH:AH,'Combined P&L'!$C:$C,'P&L Forecast'!$B37) -> 3.1042 | AK37: =SUMIFS('Combined P&L'!AI:AI,'Combined P&L'!$C:$C,'P&L Forecast'!$B37) -> 3.27137 | AL37: =SUMIFS('Combined P&L'!AJ:AJ,'Combined P&L'!$C:$C,'P&L Forecast'!$B37) -> 3.63947 | AM37: =SUMIFS('Combined P&L'!AK:AK,'Combined P&L'!$C:$C,'P&L Forecast'!$B37) -> 3.15033 | AN37: =SUMIFS('Combined P&L'!AL:AL,'Combined P&L'!$C:$C,'P&L Forecast'!$B37) -> 1.69116 | AO37: =SUMIFS('Combined P&L'!AM:AM,'Combined P&L'!$C:$C,'P&L Forecast'!$B37) -> 5.54919 | AP37: =SUMIFS('Combined P&L'!AN:AN,'Combined P&L'!$C:$C,'P&L Forecast'!$B37) -> 7.1999 | AQ37: =SUMIFS('Combined P&L'!AO:AO,'Combined P&L'!$C:$C,'P&L Forecast'!$B37) -> 8.1927 | AR37: =SUMIFS('Combined P&L'!AP:AP,'Combined P&L'!$C:$C,'P&L Forecast'!$B37) -> 8.28335 | AS37: =SUMIFS('Combined P&L'!AQ:AQ,'Combined P&L'!$C:$C,'P&L Forecast'!$B37) -> 5.49265 | AT37: =SUMIFS('Combined P&L'!AR:AR,'Combined P&L'!$C:$C,'P&L Forecast'!$B37) -> 5.6761
B38: Sr. Client Lead Wages | C38: =SUMIFS($P38:$AT38,$P$5:$AT$5,">"&C$199,$P$5:$AT$5,"<"&C$200) -> 0 | D38: =SUMIFS($P38:$AT38,$P$5:$AT$5,">"&D$199,$P$5:$AT$5,"<"&D$200) -> 0 | F38: =SUMIFS($P38:$AT38,$P$5:$AT$5,">"&F$199,$P$5:$AT$5,"<"&F$200) -> 0 | G38: =SUMIFS($P38:$AT38,$P$5:$AT$5,">"&G$199,$P$5:$AT$5,"<"&G$200) -> 7.995 | I38: =SUMIFS($P38:$AT38,$P$5:$AT$5,">"&I$199,$P$5:$AT$5,"<"&I$200) -> 0 | J38: =SUMIFS($P38:$AT38,$P$5:$AT$5,">"&J$199,$P$5:$AT$5,"<"&J$200) -> 7.995 | K38: =+C135 -> 33.08124 | M38: =K38-J38 -> 25.08624 | N38: =IFERROR(K38/J38-1,0) -> 3.1377411 | P38: =SUMIFS('Combined P&L'!N:N,'Combined P&L'!$C:$C,'P&L Forecast'!$B38) -> 0 | Q38: =SUMIFS('Combined P&L'!O:O,'Combined P&L'!$C:$C,'P&L Forecast'!$B38) -> 0 | R38: =SUMIFS('Combined P&L'!P:P,'Combined P&L'!$C:$C,'P&L Forecast'!$B38) -> 0 | S38: =SUMIFS('Combined P&L'!Q:Q,'Combined P&L'!$C:$C,'P&L Forecast'!$B38) -> 0 | T38: =SUMIFS('Combined P&L'!R:R,'Combined P&L'!$C:$C,'P&L Forecast'!$B38) -> 0 | U38: =SUMIFS('Combined P&L'!S:S,'Combined P&L'!$C:$C,'P&L Forecast'!$B38) -> 0 | V38: =SUMIFS('Combined P&L'!T:T,'Combined P&L'!$C:$C,'P&L Forecast'!$B38) -> 0 | W38: =SUMIFS('Combined P&L'!U:U,'Combined P&L'!$C:$C,'P&L Forecast'!$B38) -> 0 | X38: =SUMIFS('Combined P&L'!V:V,'Combined P&L'!$C:$C,'P&L Forecast'!$B38) -> 0 | Y38: =SUMIFS('Combined P&L'!W:W,'Combined P&L'!$C:$C,'P&L Forecast'!$B38) -> 0 | Z38: =SUMIFS('Combined P&L'!X:X,'Combined P&L'!$C:$C,'P&L Forecast'!$B38) -> 0 | AA38: =SUMIFS('Combined P&L'!Y:Y,'Combined P&L'!$C:$C,'P&L Forecast'!$B38) -> 0 | AB38: =SUMIFS('Combined P&L'!Z:Z,'Combined P&L'!$C:$C,'P&L Forecast'!$B38) -> 0 | AC38: =SUMIFS('Combined P&L'!AA:AA,'Combined P&L'!$C:$C,'P&L Forecast'!$B38) -> 0 | AD38: =SUMIFS('Combined P&L'!AB:AB,'Combined P&L'!$C:$C,'P&L Forecast'!$B38) -> 0 | AE38: =SUMIFS('Combined P&L'!AC:AC,'Combined P&L'!$C:$C,'P&L Forecast'!$B38) -> 0 | AF38: =SUMIFS('Combined P&L'!AD:AD,'Combined P&L'!$C:$C,'P&L Forecast'!$B38) -> 0 | AG38: =SUMIFS('Combined P&L'!AE:AE,'Combined P&L'!$C:$C,'P&L Forecast'!$B38) -> 0 | AH38: =SUMIFS('Combined P&L'!AF:AF,'Combined P&L'!$C:$C,'P&L Forecast'!$B38) -> 0 | AI38: =SUMIFS('Combined P&L'!AG:AG,'Combined P&L'!$C:$C,'P&L Forecast'!$B38) -> 0 | AJ38: =SUMIFS('Combined P&L'!AH:AH,'Combined P&L'!$C:$C,'P&L Forecast'!$B38) -> 0 | AK38: =SUMIFS('Combined P&L'!AI:AI,'Combined P&L'!$C:$C,'P&L Forecast'!$B38) -> 0 | AL38: =SUMIFS('Combined P&L'!AJ:AJ,'Combined P&L'!$C:$C,'P&L Forecast'!$B38) -> 0 | AM38: =SUMIFS('Combined P&L'!AK:AK,'Combined P&L'!$C:$C,'P&L Forecast'!$B38) -> 0 | AN38: =SUMIFS('Combined P&L'!AL:AL,'Combined P&L'!$C:$C,'P&L Forecast'!$B38) -> 0 | AO38: =SUMIFS('Combined P&L'!AM:AM,'Combined P&L'!$C:$C,'P&L Forecast'!$B38) -> 0 | AP38: =SUMIFS('Combined P&L'!AN:AN,'Combined P&L'!$C:$C,'P&L Forecast'!$B38) -> 0 | AQ38: =SUMIFS('Combined P&L'!AO:AO,'Combined P&L'!$C:$C,'P&L Forecast'!$B38) -> 0 | AR38: =SUMIFS('Combined P&L'!AP:AP,'Combined P&L'!$C:$C,'P&L Forecast'!$B38) -> 2.51706 | AS38: =SUMIFS('Combined P&L'!AQ:AQ,'Combined P&L'!$C:$C,'P&L Forecast'!$B38) -> 2.72117 | AT38: =SUMIFS('Combined P&L'!AR:AR,'Combined P&L'!$C:$C,'P&L Forecast'!$B38) -> 2.75677
B39: Employee Benefits | C39: =SUMIFS($P39:$AT39,$P$5:$AT$5,">"&C$199,$P$5:$AT$5,"<"&C$200) -> 5.37405 | D39: =SUMIFS($P39:$AT39,$P$5:$AT$5,">"&D$199,$P$5:$AT$5,"<"&D$200) -> 19.23245 | F39: =SUMIFS($P39:$AT39,$P$5:$AT$5,">"&F$199,$P$5:$AT$5,"<"&F$200) -> 9.02166 | G39: =SUMIFS($P39:$AT39,$P$5:$AT$5,">"&G$199,$P$5:$AT$5,"<"&G$200) -> 17.36251 | I39: =SUMIFS($P39:$AT39,$P$5:$AT$5,">"&I$199,$P$5:$AT$5,"<"&I$200) -> 12.16686 | J39: =SUMIFS($P39:$AT39,$P$5:$AT$5,">"&J$199,$P$5:$AT$5,"<"&J$200) -> 27.5733 | K39: =+C137 -> 32.17836 | M39: =K39-J39 -> 4.60506 | N39: =IFERROR(K39/J39-1,0) -> 0.16701157 | P39: =SUMIFS('Combined P&L'!N:N,'Combined P&L'!$C:$C,'P&L Forecast'!$B39) -> 0 | Q39: =SUMIFS('Combined P&L'!O:O,'Combined P&L'!$C:$C,'P&L Forecast'!$B39) -> 0.6277 | R39: =SUMIFS('Combined P&L'!P:P,'Combined P&L'!$C:$C,'P&L Forecast'!$B39) -> 0 | S39: =SUMIFS('Combined P&L'!Q:Q,'Combined P&L'!$C:$C,'P&L Forecast'!$B39) -> 0.3389 | T39: =SUMIFS('Combined P&L'!R:R,'Combined P&L'!$C:$C,'P&L Forecast'!$B39) -> 0.3389 | U39: =SUMIFS('Combined P&L'!S:S,'Combined P&L'!$C:$C,'P&L Forecast'!$B39) -> 0.06145 | V39: =SUMIFS('Combined P&L'!T:T,'Combined P&L'!$C:$C,'P&L Forecast'!$B39) -> 0.8619 | W39: =SUMIFS('Combined P&L'!U:U,'Combined P&L'!$C:$C,'P&L Forecast'!$B39) -> 0.35956 | X39: =SUMIFS('Combined P&L'!V:V,'Combined P&L'!$C:$C,'P&L Forecast'!$B39) -> 0.38745 | Y39: =SUMIFS('Combined P&L'!W:W,'Combined P&L'!$C:$C,'P&L Forecast'!$B39) -> 0.6989 | Z39: =SUMIFS('Combined P&L'!X:X,'Combined P&L'!$C:$C,'P&L Forecast'!$B39) -> 0.917 | AA39: =SUMIFS('Combined P&L'!Y:Y,'Combined P&L'!$C:$C,'P&L Forecast'!$B39) -> 0.78229 | AB39: =SUMIFS('Combined P&L'!Z:Z,'Combined P&L'!$C:$C,'P&L Forecast'!$B39) -> 0.93724 | AC39: =SUMIFS('Combined P&L'!AA:AA,'Combined P&L'!$C:$C,'P&L Forecast'!$B39) -> 1.03107 | AD39: =SUMIFS('Combined P&L'!AB:AB,'Combined P&L'!$C:$C,'P&L Forecast'!$B39) -> 0.66153 | AE39: =SUMIFS('Combined P&L'!AC:AC,'Combined P&L'!$C:$C,'P&L Forecast'!$B39) -> 0.71453 | AF39: =SUMIFS('Combined P&L'!AD:AD,'Combined P&L'!$C:$C,'P&L Forecast'!$B39) -> 2.25493 | AG39: =SUMIFS('Combined P&L'!AE:AE,'Combined P&L'!$C:$C,'P&L Forecast'!$B39) -> 1.86153 | AH39: =SUMIFS('Combined P&L'!AF:AF,'Combined P&L'!$C:$C,'P&L Forecast'!$B39) -> 1.56083 | AI39: =SUMIFS('Combined P&L'!AG:AG,'Combined P&L'!$C:$C,'P&L Forecast'!$B39) -> 1.74767 | AJ39: =SUMIFS('Combined P&L'!AH:AH,'Combined P&L'!$C:$C,'P&L Forecast'!$B39) -> 0.90753 | AK39: =SUMIFS('Combined P&L'!AI:AI,'Combined P&L'!$C:$C,'P&L Forecast'!$B39) -> 2.51353 | AL39: =SUMIFS('Combined P&L'!AJ:AJ,'Combined P&L'!$C:$C,'P&L Forecast'!$B39) -> 1.03753 | AM39: =SUMIFS('Combined P&L'!AK:AK,'Combined P&L'!$C:$C,'P&L Forecast'!$B39) -> 4.00453 | AN39: =SUMIFS('Combined P&L'!AL:AL,'Combined P&L'!$C:$C,'P&L Forecast'!$B39) -> 1.57873 | AO39: =SUMIFS('Combined P&L'!AM:AM,'Combined P&L'!$C:$C,'P&L Forecast'!$B39) -> 1.14553 | AP39: =SUMIFS('Combined P&L'!AN:AN,'Combined P&L'!$C:$C,'P&L Forecast'!$B39) -> 5.13853 | AQ39: =SUMIFS('Combined P&L'!AO:AO,'Combined P&L'!$C:$C,'P&L Forecast'!$B39) -> 1.92353 | AR39: =SUMIFS('Combined P&L'!AP:AP,'Combined P&L'!$C:$C,'P&L Forecast'!$B39) -> 1.46353 | AS39: =SUMIFS('Combined P&L'!AQ:AQ,'Combined P&L'!$C:$C,'P&L Forecast'!$B39) -> 3.43113 | AT39: =SUMIFS('Combined P&L'!AR:AR,'Combined P&L'!$C:$C,'P&L Forecast'!$B39) -> 2.68153
B40: Total Payroll Expenses | C40: =SUM(C31:C39) -> 700.20547 | D40: =SUM(D31:D39) -> 1261.1666 | F40: =SUM(F31:F39) -> 630.65714 | G40: =SUM(G31:G39) -> 1120.8921 | I40: =SUM(I31:I39) -> 993.15437 | J40: =SUM(J31:J39) -> 1751.4015 | K40: =SUM(K31:K39) -> 2094.1266 | M40: =SUM(M31:M39) -> 342.72508 | N40: =IFERROR(K40/J40-1,0) -> 0.19568618 | P40: =SUM(P31:P39) -> 31.74682 | Q40: =SUM(Q31:Q39) -> 37.62609 | R40: =SUM(R31:R39) -> 37.77865 | S40: =SUM(S31:S39) -> 50.81818 | T40: =SUM(T31:T39) -> 70.6441 | U40: =SUM(U31:U39) -> 52.94065 | V40: =SUM(V31:V39) -> 56.15375 | W40: =SUM(W31:W39) -> 52.54102 | ... AT40: =SUM(AT31:AT39) -> 180.38884
B42: Software & Apps - COGS | C42: =SUMIFS($P42:$AT42,$P$5:$AT$5,">"&C$199,$P$5:$AT$5,"<"&C$200) -> 114.42269 | D42: =SUMIFS($P42:$AT42,$P$5:$AT$5,">"&D$199,$P$5:$AT$5,"<"&D$200) -> 157.49471 | F42: =SUMIFS($P42:$AT42,$P$5:$AT$5,">"&F$199,$P$5:$AT$5,"<"&F$200) -> 84.96859 | G42: =SUMIFS($P42:$AT42,$P$5:$AT$5,">"&G$199,$P$5:$AT$5,"<"&G$200) -> 152.28157 | I42: =SUMIFS($P42:$AT42,$P$5:$AT$5,">"&I$199,$P$5:$AT$5,"<"&I$200) -> 142.28345 | J42: =SUMIFS($P42:$AT42,$P$5:$AT$5,">"&J$199,$P$5:$AT$5,"<"&J$200) -> 224.80769 | K42: =+C141 -> 335.70816 | M42: =K42-J42 -> 110.90047 | N42: =IFERROR(K42/J42-1,0) -> 0.49331262 | P42: =SUMIFS('Combined P&L'!N:N,'Combined P&L'!$C:$C,'P&L Forecast'!$B42) -> 7.073 | Q42: =SUMIFS('Combined P&L'!O:O,'Combined P&L'!$C:$C,'P&L Forecast'!$B42) -> 7.01818 | R42: =SUMIFS('Combined P&L'!P:P,'Combined P&L'!$C:$C,'P&L Forecast'!$B42) -> 7.77788 | S42: =SUMIFS('Combined P&L'!Q:Q,'Combined P&L'!$C:$C,'P&L Forecast'!$B42) -> 7.76124 | T42: =SUMIFS('Combined P&L'!R:R,'Combined P&L'!$C:$C,'P&L Forecast'!$B42) -> 7.71821 | U42: =SUMIFS('Combined P&L'!S:S,'Combined P&L'!$C:$C,'P&L Forecast'!$B42) -> 8.91264 | V42: =SUMIFS('Combined P&L'!T:T,'Combined P&L'!$C:$C,'P&L Forecast'!$B42) -> 10.84668 | W42: =SUMIFS('Combined P&L'!U:U,'Combined P&L'!$C:$C,'P&L Forecast'!$B42) -> 11.13514 | X42: =SUMIFS('Combined P&L'!V:V,'Combined P&L'!$C:$C,'P&L Forecast'!$B42) -> 11.0345 | Y42: =SUMIFS('Combined P&L'!W:W,'Combined P&L'!$C:$C,'P&L Forecast'!$B42) -> 11.72873 | Z42: =SUMIFS('Combined P&L'!X:X,'Combined P&L'!$C:$C,'P&L Forecast'!$B42) -> 11.44691 | AA42: =SUMIFS('Combined P&L'!Y:Y,'Combined P&L'!$C:$C,'P&L Forecast'!$B42) -> 11.96958 | AB42: =SUMIFS('Combined P&L'!Z:Z,'Combined P&L'!$C:$C,'P&L Forecast'!$B42) -> 10.84853 | AC42: =SUMIFS('Combined P&L'!AA:AA,'Combined P&L'!$C:$C,'P&L Forecast'!$B42) -> 12.21311 | AD42: =SUMIFS('Combined P&L'!AB:AB,'Combined P&L'!$C:$C,'P&L Forecast'!$B42) -> 11.57167 | AE42: =SUMIFS('Combined P&L'!AC:AC,'Combined P&L'!$C:$C,'P&L Forecast'!$B42) -> 11.81087 | AF42: =SUMIFS('Combined P&L'!AD:AD,'Combined P&L'!$C:$C,'P&L Forecast'!$B42) -> 12.52563 | AG42: =SUMIFS('Combined P&L'!AE:AE,'Combined P&L'!$C:$C,'P&L Forecast'!$B42) -> 12.86333 | AH42: =SUMIFS('Combined P&L'!AF:AF,'Combined P&L'!$C:$C,'P&L Forecast'!$B42) -> 13.13545 | AI42: =SUMIFS('Combined P&L'!AG:AG,'Combined P&L'!$C:$C,'P&L Forecast'!$B42) -> 14.25715 | AJ42: =SUMIFS('Combined P&L'!AH:AH,'Combined P&L'!$C:$C,'P&L Forecast'!$B42) -> 13.59512 | AK42: =SUMIFS('Combined P&L'!AI:AI,'Combined P&L'!$C:$C,'P&L Forecast'!$B42) -> 12.34762 | AL42: =SUMIFS('Combined P&L'!AJ:AJ,'Combined P&L'!$C:$C,'P&L Forecast'!$B42) -> 15.21781 | AM42: =SUMIFS('Combined P&L'!AK:AK,'Combined P&L'!$C:$C,'P&L Forecast'!$B42) -> 17.10842 | AN42: =SUMIFS('Combined P&L'!AL:AL,'Combined P&L'!$C:$C,'P&L Forecast'!$B42) -> 18.4683 | AO42: =SUMIFS('Combined P&L'!AM:AM,'Combined P&L'!$C:$C,'P&L Forecast'!$B42) -> 17.92027 | AP42: =SUMIFS('Combined P&L'!AN:AN,'Combined P&L'!$C:$C,'P&L Forecast'!$B42) -> 18.40906 | AQ42: =SUMIFS('Combined P&L'!AO:AO,'Combined P&L'!$C:$C,'P&L Forecast'!$B42) -> 21.38775 | AR42: =SUMIFS('Combined P&L'!AP:AP,'Combined P&L'!$C:$C,'P&L Forecast'!$B42) -> 23.44584 | AS42: =SUMIFS('Combined P&L'!AQ:AQ,'Combined P&L'!$C:$C,'P&L Forecast'!$B42) -> 24.67467 | AT42: =SUMIFS('Combined P&L'!AR:AR,'Combined P&L'!$C:$C,'P&L Forecast'!$B42) -> 27.97568
B43: Software & Apps - G&A | C43: =SUMIFS($P43:$AT43,$P$5:$AT$5,">"&C$199,$P$5:$AT$5,"<"&C$200) -> 60.91594 | D43: =SUMIFS($P43:$AT43,$P$5:$AT$5,">"&D$199,$P$5:$AT$5,"<"&D$200) -> 117.05866 | F43: =SUMIFS($P43:$AT43,$P$5:$AT$5,">"&F$199,$P$5:$AT$5,"<"&F$200) -> 56.8115 | G43: =SUMIFS($P43:$AT43,$P$5:$AT$5,">"&G$199,$P$5:$AT$5,"<"&G$200) -> 97.04798 | I43: =SUMIFS($P43:$AT43,$P$5:$AT$5,">"&I$199,$P$5:$AT$5,"<"&I$200) -> 86.51489 | J43: =SUMIFS($P43:$AT43,$P$5:$AT$5,">"&J$199,$P$5:$AT$5,"<"&J$200) -> 157.29514 | K43: =+C142 -> 155.82264 | M43: =K43-J43 -> -1.4725 | N43: =IFERROR(K43/J43-1,0) -> -0.0093613827 | P43: =SUMIFS('Combined P&L'!N:N,'Combined P&L'!$C:$C,'P&L Forecast'!$B43) -> 3.45285 | Q43: =SUMIFS('Combined P&L'!O:O,'Combined P&L'!$C:$C,'P&L Forecast'!$B43) -> 3.61753 | R43: =SUMIFS('Combined P&L'!P:P,'Combined P&L'!$C:$C,'P&L Forecast'!$B43) -> 3.97407 | S43: =SUMIFS('Combined P&L'!Q:Q,'Combined P&L'!$C:$C,'P&L Forecast'!$B43) -> 4.22365 | T43: =SUMIFS('Combined P&L'!R:R,'Combined P&L'!$C:$C,'P&L Forecast'!$B43) -> 5.09725 | U43: =SUMIFS('Combined P&L'!S:S,'Combined P&L'!$C:$C,'P&L Forecast'!$B43) -> 5.33351 | V43: =SUMIFS('Combined P&L'!T:T,'Combined P&L'!$C:$C,'P&L Forecast'!$B43) -> 5.51369 | W43: =SUMIFS('Combined P&L'!U:U,'Combined P&L'!$C:$C,'P&L Forecast'!$B43) -> 5.23169 | X43: =SUMIFS('Combined P&L'!V:V,'Combined P&L'!$C:$C,'P&L Forecast'!$B43) -> 5.51622 | Y43: =SUMIFS('Combined P&L'!W:W,'Combined P&L'!$C:$C,'P&L Forecast'!$B43) -> 6.12797 | Z43: =SUMIFS('Combined P&L'!X:X,'Combined P&L'!$C:$C,'P&L Forecast'!$B43) -> 6.15097 | AA43: =SUMIFS('Combined P&L'!Y:Y,'Combined P&L'!$C:$C,'P&L Forecast'!$B43) -> 6.67654 | AB43: =SUMIFS('Combined P&L'!Z:Z,'Combined P&L'!$C:$C,'P&L Forecast'!$B43) -> 7.74646 | AC43: =SUMIFS('Combined P&L'!AA:AA,'Combined P&L'!$C:$C,'P&L Forecast'!$B43) -> 7.89181 | AD43: =SUMIFS('Combined P&L'!AB:AB,'Combined P&L'!$C:$C,'P&L Forecast'!$B43) -> 7.89085 | AE43: =SUMIFS('Combined P&L'!AC:AC,'Combined P&L'!$C:$C,'P&L Forecast'!$B43) -> 7.83463 | AF43: =SUMIFS('Combined P&L'!AD:AD,'Combined P&L'!$C:$C,'P&L Forecast'!$B43) -> 8.11723 | AG43: =SUMIFS('Combined P&L'!AE:AE,'Combined P&L'!$C:$C,'P&L Forecast'!$B43) -> 8.34584 | AH43: =SUMIFS('Combined P&L'!AF:AF,'Combined P&L'!$C:$C,'P&L Forecast'!$B43) -> 8.98468 | AI43: =SUMIFS('Combined P&L'!AG:AG,'Combined P&L'!$C:$C,'P&L Forecast'!$B43) -> 9.8566 | AJ43: =SUMIFS('Combined P&L'!AH:AH,'Combined P&L'!$C:$C,'P&L Forecast'!$B43) -> 10.73391 | AK43: =SUMIFS('Combined P&L'!AI:AI,'Combined P&L'!$C:$C,'P&L Forecast'!$B43) -> 12.08939 | AL43: =SUMIFS('Combined P&L'!AJ:AJ,'Combined P&L'!$C:$C,'P&L Forecast'!$B43) -> 13.14583 | AM43: =SUMIFS('Combined P&L'!AK:AK,'Combined P&L'!$C:$C,'P&L Forecast'!$B43) -> 14.42143 | AN43: =SUMIFS('Combined P&L'!AL:AL,'Combined P&L'!$C:$C,'P&L Forecast'!$B43) -> 13.26316 | AO43: =SUMIFS('Combined P&L'!AM:AM,'Combined P&L'!$C:$C,'P&L Forecast'!$B43) -> 14.7201 | AP43: =SUMIFS('Combined P&L'!AN:AN,'Combined P&L'!$C:$C,'P&L Forecast'!$B43) -> 14.99072 | AQ43: =SUMIFS('Combined P&L'!AO:AO,'Combined P&L'!$C:$C,'P&L Forecast'!$B43) -> 14.74459 | AR43: =SUMIFS('Combined P&L'!AP:AP,'Combined P&L'!$C:$C,'P&L Forecast'!$B43) -> 13.2292 | AS43: =SUMIFS('Combined P&L'!AQ:AQ,'Combined P&L'!$C:$C,'P&L Forecast'!$B43) -> 13.11499 | AT43: =SUMIFS('Combined P&L'!AR:AR,'Combined P&L'!$C:$C,'P&L Forecast'!$B43) -> 12.98522
B44: Software & Apps - Topkey | C44: =SUMIFS($P44:$AT44,$P$5:$AT$5,">"&C$199,$P$5:$AT$5,"<"&C$200) -> 0 | D44: =SUMIFS($P44:$AT44,$P$5:$AT$5,">"&D$199,$P$5:$AT$5,"<"&D$200) -> 7.14125 | F44: =SUMIFS($P44:$AT44,$P$5:$AT$5,">"&F$199,$P$5:$AT$5,"<"&F$200) -> 0 | G44: =SUMIFS($P44:$AT44,$P$5:$AT$5,">"&G$199,$P$5:$AT$5,"<"&G$200) -> 28.82775 | I44: =SUMIFS($P44:$AT44,$P$5:$AT$5,">"&I$199,$P$5:$AT$5,"<"&I$200) -> 0 | J44: =SUMIFS($P44:$AT44,$P$5:$AT$5,">"&J$199,$P$5:$AT$5,"<"&J$200) -> 35.969 | K44: =+C143 -> 60.84 | M44: =K44-J44 -> 24.871 | N44: =IFERROR(K44/J44-1,0) -> 0.69145653 | P44: =SUMIFS('Combined P&L'!N:N,'Combined P&L'!$C:$C,'P&L Forecast'!$B44) -> 0 | Q44: =SUMIFS('Combined P&L'!O:O,'Combined P&L'!$C:$C,'P&L Forecast'!$B44) -> 0 | R44: =SUMIFS('Combined P&L'!P:P,'Combined P&L'!$C:$C,'P&L Forecast'!$B44) -> 0 | S44: =SUMIFS('Combined P&L'!Q:Q,'Combined P&L'!$C:$C,'P&L Forecast'!$B44) -> 0 | T44: =SUMIFS('Combined P&L'!R:R,'Combined P&L'!$C:$C,'P&L Forecast'!$B44) -> 0 | U44: =SUMIFS('Combined P&L'!S:S,'Combined P&L'!$C:$C,'P&L Forecast'!$B44) -> 0 | V44: =SUMIFS('Combined P&L'!T:T,'Combined P&L'!$C:$C,'P&L Forecast'!$B44) -> 0 | W44: =SUMIFS('Combined P&L'!U:U,'Combined P&L'!$C:$C,'P&L Forecast'!$B44) -> 0 | X44: =SUMIFS('Combined P&L'!V:V,'Combined P&L'!$C:$C,'P&L Forecast'!$B44) -> 0 | Y44: =SUMIFS('Combined P&L'!W:W,'Combined P&L'!$C:$C,'P&L Forecast'!$B44) -> 0 | Z44: =SUMIFS('Combined P&L'!X:X,'Combined P&L'!$C:$C,'P&L Forecast'!$B44) -> 0 | AA44: =SUMIFS('Combined P&L'!Y:Y,'Combined P&L'!$C:$C,'P&L Forecast'!$B44) -> 0 | AB44: =SUMIFS('Combined P&L'!Z:Z,'Combined P&L'!$C:$C,'P&L Forecast'!$B44) -> 0 | AC44: =SUMIFS('Combined P&L'!AA:AA,'Combined P&L'!$C:$C,'P&L Forecast'!$B44) -> 0 | AD44: =SUMIFS('Combined P&L'!AB:AB,'Combined P&L'!$C:$C,'P&L Forecast'!$B44) -> 0 | AE44: =SUMIFS('Combined P&L'!AC:AC,'Combined P&L'!$C:$C,'P&L Forecast'!$B44) -> 0 | AF44: =SUMIFS('Combined P&L'!AD:AD,'Combined P&L'!$C:$C,'P&L Forecast'!$B44) -> 0 | AG44: =SUMIFS('Combined P&L'!AE:AE,'Combined P&L'!$C:$C,'P&L Forecast'!$B44) -> 0 | AH44: =SUMIFS('Combined P&L'!AF:AF,'Combined P&L'!$C:$C,'P&L Forecast'!$B44) -> 0 | AI44: =SUMIFS('Combined P&L'!AG:AG,'Combined P&L'!$C:$C,'P&L Forecast'!$B44) -> 0 | AJ44: =SUMIFS('Combined P&L'!AH:AH,'Combined P&L'!$C:$C,'P&L Forecast'!$B44) -> 0.93725 | AK44: =SUMIFS('Combined P&L'!AI:AI,'Combined P&L'!$C:$C,'P&L Forecast'!$B44) -> 1.39225 | AL44: =SUMIFS('Combined P&L'!AJ:AJ,'Combined P&L'!$C:$C,'P&L Forecast'!$B44) -> 2.36125 | AM44: =SUMIFS('Combined P&L'!AK:AK,'Combined P&L'!$C:$C,'P&L Forecast'!$B44) -> 2.4505 | AN44: =SUMIFS('Combined P&L'!AL:AL,'Combined P&L'!$C:$C,'P&L Forecast'!$B44) -> 2.94975 | AO44: =SUMIFS('Combined P&L'!AM:AM,'Combined P&L'!$C:$C,'P&L Forecast'!$B44) -> 3.42 | AP44: =SUMIFS('Combined P&L'!AN:AN,'Combined P&L'!$C:$C,'P&L Forecast'!$B44) -> 3.678 | AQ44: =SUMIFS('Combined P&L'!AO:AO,'Combined P&L'!$C:$C,'P&L Forecast'!$B44) -> 4.218 | AR44: =SUMIFS('Combined P&L'!AP:AP,'Combined P&L'!$C:$C,'P&L Forecast'!$B44) -> 4.284 | AS44: =SUMIFS('Combined P&L'!AQ:AQ,'Combined P&L'!$C:$C,'P&L Forecast'!$B44) -> 5.208 | AT44: =SUMIFS('Combined P&L'!AR:AR,'Combined P&L'!$C:$C,'P&L Forecast'!$B44) -> 5.07
B45: Software & Apps - AI tools | C45: =SUMIFS($P45:$AT45,$P$5:$AT$5,">"&C$199,$P$5:$AT$5,"<"&C$200) -> 0 | D45: =SUMIFS($P45:$AT45,$P$5:$AT$5,">"&D$199,$P$5:$AT$5,"<"&D$200) -> 0 | F45: =SUMIFS($P45:$AT45,$P$5:$AT$5,">"&F$199,$P$5:$AT$5,"<"&F$200) -> 0 | G45: =SUMIFS($P45:$AT45,$P$5:$AT$5,">"&G$199,$P$5:$AT$5,"<"&G$200) -> 6.52752 | I45: =SUMIFS($P45:$AT45,$P$5:$AT$5,">"&I$199,$P$5:$AT$5,"<"&I$200) -> 0 | J45: =SUMIFS($P45:$AT45,$P$5:$AT$5,">"&J$199,$P$5:$AT$5,"<"&J$200) -> 6.52752 | K45: =+C144 -> 15.74376 | M45: =K45-J45 -> 9.21624 | N45: =IFERROR(K45/J45-1,0) -> 1.4119053 | P45: =SUMIFS('Combined P&L'!N:N,'Combined P&L'!$C:$C,'P&L Forecast'!$B45) -> 0 | Q45: =SUMIFS('Combined P&L'!O:O,'Combined P&L'!$C:$C,'P&L Forecast'!$B45) -> 0 | R45: =SUMIFS('Combined P&L'!P:P,'Combined P&L'!$C:$C,'P&L Forecast'!$B45) -> 0 | S45: =SUMIFS('Combined P&L'!Q:Q,'Combined P&L'!$C:$C,'P&L Forecast'!$B45) -> 0 | T45: =SUMIFS('Combined P&L'!R:R,'Combined P&L'!$C:$C,'P&L Forecast'!$B45) -> 0 | U45: =SUMIFS('Combined P&L'!S:S,'Combined P&L'!$C:$C,'P&L Forecast'!$B45) -> 0 | V45: =SUMIFS('Combined P&L'!T:T,'Combined P&L'!$C:$C,'P&L Forecast'!$B45) -> 0 | W45: =SUMIFS('Combined P&L'!U:U,'Combined P&L'!$C:$C,'P&L Forecast'!$B45) -> 0 | X45: =SUMIFS('Combined P&L'!V:V,'Combined P&L'!$C:$C,'P&L Forecast'!$B45) -> 0 | Y45: =SUMIFS('Combined P&L'!W:W,'Combined P&L'!$C:$C,'P&L Forecast'!$B45) -> 0 | Z45: =SUMIFS('Combined P&L'!X:X,'Combined P&L'!$C:$C,'P&L Forecast'!$B45) -> 0 | AA45: =SUMIFS('Combined P&L'!Y:Y,'Combined P&L'!$C:$C,'P&L Forecast'!$B45) -> 0 | AB45: =SUMIFS('Combined P&L'!Z:Z,'Combined P&L'!$C:$C,'P&L Forecast'!$B45) -> 0 | AC45: =SUMIFS('Combined P&L'!AA:AA,'Combined P&L'!$C:$C,'P&L Forecast'!$B45) -> 0 | AD45: =SUMIFS('Combined P&L'!AB:AB,'Combined P&L'!$C:$C,'P&L Forecast'!$B45) -> 0 | AE45: =SUMIFS('Combined P&L'!AC:AC,'Combined P&L'!$C:$C,'P&L Forecast'!$B45) -> 0 | AF45: =SUMIFS('Combined P&L'!AD:AD,'Combined P&L'!$C:$C,'P&L Forecast'!$B45) -> 0 | AG45: =SUMIFS('Combined P&L'!AE:AE,'Combined P&L'!$C:$C,'P&L Forecast'!$B45) -> 0 | AH45: =SUMIFS('Combined P&L'!AF:AF,'Combined P&L'!$C:$C,'P&L Forecast'!$B45) -> 0 | AI45: =SUMIFS('Combined P&L'!AG:AG,'Combined P&L'!$C:$C,'P&L Forecast'!$B45) -> 0 | AJ45: =SUMIFS('Combined P&L'!AH:AH,'Combined P&L'!$C:$C,'P&L Forecast'!$B45) -> 0 | AK45: =SUMIFS('Combined P&L'!AI:AI,'Combined P&L'!$C:$C,'P&L Forecast'!$B45) -> 0 | AL45: =SUMIFS('Combined P&L'!AJ:AJ,'Combined P&L'!$C:$C,'P&L Forecast'!$B45) -> 0 | AM45: =SUMIFS('Combined P&L'!AK:AK,'Combined P&L'!$C:$C,'P&L Forecast'!$B45) -> 0 | AN45: =SUMIFS('Combined P&L'!AL:AL,'Combined P&L'!$C:$C,'P&L Forecast'!$B45) -> 0.12 | AO45: =SUMIFS('Combined P&L'!AM:AM,'Combined P&L'!$C:$C,'P&L Forecast'!$B45) -> 0.12 | AP45: =SUMIFS('Combined P&L'!AN:AN,'Combined P&L'!$C:$C,'P&L Forecast'!$B45) -> 0.70166 | AQ45: =SUMIFS('Combined P&L'!AO:AO,'Combined P&L'!$C:$C,'P&L Forecast'!$B45) -> 2.20736 | AR45: =SUMIFS('Combined P&L'!AP:AP,'Combined P&L'!$C:$C,'P&L Forecast'!$B45) -> 0.91487 | AS45: =SUMIFS('Combined P&L'!AQ:AQ,'Combined P&L'!$C:$C,'P&L Forecast'!$B45) -> 1.15165 | AT45: =SUMIFS('Combined P&L'!AR:AR,'Combined P&L'!$C:$C,'P&L Forecast'!$B45) -> 1.31198
B46: Total Software Expenses | C46: =SUM(C42:C45) -> 175.33863 | D46: =SUM(D42:D45) -> 281.69462 | F46: =SUM(F42:F45) -> 141.78009 | G46: =SUM(G42:G45) -> 284.68482 | I46: =SUM(I42:I45) -> 228.79834 | J46: =SUM(J42:J45) -> 424.59935 | K46: =SUM(K42:K45) -> 568.11456 | M46: =SUM(M42:M45) -> 143.51521 | N46: =IFERROR(K46/J46-1,0) -> 0.33800148 | P46: =SUM(P42:P45) -> 10.52585 | Q46: =SUM(Q42:Q45) -> 10.63571 | R46: =SUM(R42:R45) -> 11.75195 | S46: =SUM(S42:S45) -> 11.98489 | T46: =SUM(T42:T45) -> 12.81546 | U46: =SUM(U42:U45) -> 14.24615 | V46: =SUM(V42:V45) -> 16.36037 | W46: =SUM(W42:W45) -> 16.36683 | ... AT46: =SUM(AT42:AT45) -> 47.34288
B48: Other Professional Fees | C48: =SUMIFS($P48:$AT48,$P$5:$AT$5,">"&C$199,$P$5:$AT$5,"<"&C$200) -> 18.23425 | D48: =SUMIFS($P48:$AT48,$P$5:$AT$5,">"&D$199,$P$5:$AT$5,"<"&D$200) -> 27.04095 | F48: =SUMIFS($P48:$AT48,$P$5:$AT$5,">"&F$199,$P$5:$AT$5,"<"&F$200) -> 12.014 | G48: =SUMIFS($P48:$AT48,$P$5:$AT$5,">"&G$199,$P$5:$AT$5,"<"&G$200) -> 57.55 | I48: =SUMIFS($P48:$AT48,$P$5:$AT$5,">"&I$199,$P$5:$AT$5,"<"&I$200) -> 21.74858 | J48: =SUMIFS($P48:$AT48,$P$5:$AT$5,">"&J$199,$P$5:$AT$5,"<"&J$200) -> 72.57695 | K48: =+C148 -> 72.57695 | M48: =K48-J48 -> 0 | N48: =IFERROR(K48/J48-1,0) -> 0 | P48: =SUMIFS('Combined P&L'!N:N,'Combined P&L'!$C:$C,'P&L Forecast'!$B48) -> 0 | Q48: =SUMIFS('Combined P&L'!O:O,'Combined P&L'!$C:$C,'P&L Forecast'!$B48) -> 1.1665 | R48: =SUMIFS('Combined P&L'!P:P,'Combined P&L'!$C:$C,'P&L Forecast'!$B48) -> 1.1665 | S48: =SUMIFS('Combined P&L'!Q:Q,'Combined P&L'!$C:$C,'P&L Forecast'!$B48) -> 1.16667 | T48: =SUMIFS('Combined P&L'!R:R,'Combined P&L'!$C:$C,'P&L Forecast'!$B48) -> 1.16667 | U48: =SUMIFS('Combined P&L'!S:S,'Combined P&L'!$C:$C,'P&L Forecast'!$B48) -> 2.66666 | V48: =SUMIFS('Combined P&L'!T:T,'Combined P&L'!$C:$C,'P&L Forecast'!$B48) -> 1.16667 | W48: =SUMIFS('Combined P&L'!U:U,'Combined P&L'!$C:$C,'P&L Forecast'!$B48) -> 1.16667 | X48: =SUMIFS('Combined P&L'!V:V,'Combined P&L'!$C:$C,'P&L Forecast'!$B48) -> 3.06791 | Y48: =SUMIFS('Combined P&L'!W:W,'Combined P&L'!$C:$C,'P&L Forecast'!$B48) -> 1.16667 | Z48: =SUMIFS('Combined P&L'!X:X,'Combined P&L'!$C:$C,'P&L Forecast'!$B48) -> 2.16667 | AA48: =SUMIFS('Combined P&L'!Y:Y,'Combined P&L'!$C:$C,'P&L Forecast'!$B48) -> 2.16666 | AB48: =SUMIFS('Combined P&L'!Z:Z,'Combined P&L'!$C:$C,'P&L Forecast'!$B48) -> 2.16667 | AC48: =SUMIFS('Combined P&L'!AA:AA,'Combined P&L'!$C:$C,'P&L Forecast'!$B48) -> 2.16667 | AD48: =SUMIFS('Combined P&L'!AB:AB,'Combined P&L'!$C:$C,'P&L Forecast'!$B48) -> 2.16666 | AE48: =SUMIFS('Combined P&L'!AC:AC,'Combined P&L'!$C:$C,'P&L Forecast'!$B48) -> 2.76067 | AF48: =SUMIFS('Combined P&L'!AD:AD,'Combined P&L'!$C:$C,'P&L Forecast'!$B48) -> 1.58667 | AG48: =SUMIFS('Combined P&L'!AE:AE,'Combined P&L'!$C:$C,'P&L Forecast'!$B48) -> 1.16666 | AH48: =SUMIFS('Combined P&L'!AF:AF,'Combined P&L'!$C:$C,'P&L Forecast'!$B48) -> 0 | AI48: =SUMIFS('Combined P&L'!AG:AG,'Combined P&L'!$C:$C,'P&L Forecast'!$B48) -> 0.2 | AJ48: =SUMIFS('Combined P&L'!AH:AH,'Combined P&L'!$C:$C,'P&L Forecast'!$B48) -> 1.32695 | AK48: =SUMIFS('Combined P&L'!AI:AI,'Combined P&L'!$C:$C,'P&L Forecast'!$B48) -> 0 | AL48: =SUMIFS('Combined P&L'!AJ:AJ,'Combined P&L'!$C:$C,'P&L Forecast'!$B48) -> 6 | AM48: =SUMIFS('Combined P&L'!AK:AK,'Combined P&L'!$C:$C,'P&L Forecast'!$B48) -> 7.5 | AN48: =SUMIFS('Combined P&L'!AL:AL,'Combined P&L'!$C:$C,'P&L Forecast'!$B48) -> 0 | AO48: =SUMIFS('Combined P&L'!AM:AM,'Combined P&L'!$C:$C,'P&L Forecast'!$B48) -> 0 | AP48: =SUMIFS('Combined P&L'!AN:AN,'Combined P&L'!$C:$C,'P&L Forecast'!$B48) -> 6.6 | AQ48: =SUMIFS('Combined P&L'!AO:AO,'Combined P&L'!$C:$C,'P&L Forecast'!$B48) -> 14 | AR48: =SUMIFS('Combined P&L'!AP:AP,'Combined P&L'!$C:$C,'P&L Forecast'!$B48) -> 18 | AS48: =SUMIFS('Combined P&L'!AQ:AQ,'Combined P&L'!$C:$C,'P&L Forecast'!$B48) -> 0 | AT48: =SUMIFS('Combined P&L'!AR:AR,'Combined P&L'!$C:$C,'P&L Forecast'!$B48) -> 18.95
B49: Referral Fees | C49: =SUMIFS($P49:$AT49,$P$5:$AT$5,">"&C$199,$P$5:$AT$5,"<"&C$200) -> 24.82 | D49: =SUMIFS($P49:$AT49,$P$5:$AT$5,">"&D$199,$P$5:$AT$5,"<"&D$200) -> 27.15374 | F49: =SUMIFS($P49:$AT49,$P$5:$AT$5,">"&F$199,$P$5:$AT$5,"<"&F$200) -> 17.0895 | G49: =SUMIFS($P49:$AT49,$P$5:$AT$5,">"&G$199,$P$5:$AT$5,"<"&G$200) -> 20.62969 | I49: =SUMIFS($P49:$AT49,$P$5:$AT$5,">"&I$199,$P$5:$AT$5,"<"&I$200) -> 26.2095 | J49: =SUMIFS($P49:$AT49,$P$5:$AT$5,">"&J$199,$P$5:$AT$5,"<"&J$200) -> 30.69393 | K49: =+C149 -> 30.69393 | M49: =K49-J49 -> 0 | N49: =IFERROR(K49/J49-1,0) -> 0 | P49: =SUMIFS('Combined P&L'!N:N,'Combined P&L'!$C:$C,'P&L Forecast'!$B49) -> 2.21 | Q49: =SUMIFS('Combined P&L'!O:O,'Combined P&L'!$C:$C,'P&L Forecast'!$B49) -> 2.735 | R49: =SUMIFS('Combined P&L'!P:P,'Combined P&L'!$C:$C,'P&L Forecast'!$B49) -> 2.715 | S49: =SUMIFS('Combined P&L'!Q:Q,'Combined P&L'!$C:$C,'P&L Forecast'!$B49) -> 2.735 | T49: =SUMIFS('Combined P&L'!R:R,'Combined P&L'!$C:$C,'P&L Forecast'!$B49) -> 0.78 | U49: =SUMIFS('Combined P&L'!S:S,'Combined P&L'!$C:$C,'P&L Forecast'!$B49) -> 3.245 | V49: =SUMIFS('Combined P&L'!T:T,'Combined P&L'!$C:$C,'P&L Forecast'!$B49) -> 1.28 | W49: =SUMIFS('Combined P&L'!U:U,'Combined P&L'!$C:$C,'P&L Forecast'!$B49) -> 1.3 | X49: =SUMIFS('Combined P&L'!V:V,'Combined P&L'!$C:$C,'P&L Forecast'!$B49) -> 1.81 | Y49: =SUMIFS('Combined P&L'!W:W,'Combined P&L'!$C:$C,'P&L Forecast'!$B49) -> 1.82 | Z49: =SUMIFS('Combined P&L'!X:X,'Combined P&L'!$C:$C,'P&L Forecast'!$B49) -> 1.835 | AA49: =SUMIFS('Combined P&L'!Y:Y,'Combined P&L'!$C:$C,'P&L Forecast'!$B49) -> 2.355 | AB49: =SUMIFS('Combined P&L'!Z:Z,'Combined P&L'!$C:$C,'P&L Forecast'!$B49) -> 1.47025 | AC49: =SUMIFS('Combined P&L'!AA:AA,'Combined P&L'!$C:$C,'P&L Forecast'!$B49) -> 1.665 | AD49: =SUMIFS('Combined P&L'!AB:AB,'Combined P&L'!$C:$C,'P&L Forecast'!$B49) -> 2.62775 | AE49: =SUMIFS('Combined P&L'!AC:AC,'Combined P&L'!$C:$C,'P&L Forecast'!$B49) -> 1.24875 | AF49: =SUMIFS('Combined P&L'!AD:AD,'Combined P&L'!$C:$C,'P&L Forecast'!$B49) -> 2.154 | AG49: =SUMIFS('Combined P&L'!AE:AE,'Combined P&L'!$C:$C,'P&L Forecast'!$B49) -> 4.154 | AH49: =SUMIFS('Combined P&L'!AF:AF,'Combined P&L'!$C:$C,'P&L Forecast'!$B49) -> 3.76975 | AI49: =SUMIFS('Combined P&L'!AG:AG,'Combined P&L'!$C:$C,'P&L Forecast'!$B49) -> 1.696 | AJ49: =SUMIFS('Combined P&L'!AH:AH,'Combined P&L'!$C:$C,'P&L Forecast'!$B49) -> 2.2275 | AK49: =SUMIFS('Combined P&L'!AI:AI,'Combined P&L'!$C:$C,'P&L Forecast'!$B49) -> 1.6645 | AL49: =SUMIFS('Combined P&L'!AJ:AJ,'Combined P&L'!$C:$C,'P&L Forecast'!$B49) -> 1.71879 | AM49: =SUMIFS('Combined P&L'!AK:AK,'Combined P&L'!$C:$C,'P&L Forecast'!$B49) -> 2.75745 | AN49: =SUMIFS('Combined P&L'!AL:AL,'Combined P&L'!$C:$C,'P&L Forecast'!$B49) -> 1.8688 | AO49: =SUMIFS('Combined P&L'!AM:AM,'Combined P&L'!$C:$C,'P&L Forecast'!$B49) -> 4.43991 | AP49: =SUMIFS('Combined P&L'!AN:AN,'Combined P&L'!$C:$C,'P&L Forecast'!$B49) -> 2.39361 | AQ49: =SUMIFS('Combined P&L'!AO:AO,'Combined P&L'!$C:$C,'P&L Forecast'!$B49) -> 3.65786 | AR49: =SUMIFS('Combined P&L'!AP:AP,'Combined P&L'!$C:$C,'P&L Forecast'!$B49) -> 2.93379 | AS49: =SUMIFS('Combined P&L'!AQ:AQ,'Combined P&L'!$C:$C,'P&L Forecast'!$B49) -> 1.5662 | AT49: =SUMIFS('Combined P&L'!AR:AR,'Combined P&L'!$C:$C,'P&L Forecast'!$B49) -> 3.76952
B50: Travel, Meals & Entertainment | C50: =SUMIFS($P50:$AT50,$P$5:$AT$5,">"&C$199,$P$5:$AT$5,"<"&C$200) -> 0 | D50: =SUMIFS($P50:$AT50,$P$5:$AT$5,">"&D$199,$P$5:$AT$5,"<"&D$200) -> 29.76122 | F50: =SUMIFS($P50:$AT50,$P$5:$AT$5,">"&F$199,$P$5:$AT$5,"<"&F$200) -> 22.29558 | G50: =SUMIFS($P50:$AT50,$P$5:$AT$5,">"&G$199,$P$5:$AT$5,"<"&G$200) -> 20.68542 | I50: =SUMIFS($P50:$AT50,$P$5:$AT$5,">"&I$199,$P$5:$AT$5,"<"&I$200) -> 22.29558 | J50: =SUMIFS($P50:$AT50,$P$5:$AT$5,">"&J$199,$P$5:$AT$5,"<"&J$200) -> 28.15106 | K50: =+C150 -> 28.15106 | M50: =K50-J50 -> 0 | N50: =IFERROR(K50/J50-1,0) -> 0 | P50: =SUMIFS('Combined P&L'!N:N,'Combined P&L'!$C:$C,'P&L Forecast'!$B50) -> 0 | Q50: =SUMIFS('Combined P&L'!O:O,'Combined P&L'!$C:$C,'P&L Forecast'!$B50) -> 0 | R50: =SUMIFS('Combined P&L'!P:P,'Combined P&L'!$C:$C,'P&L Forecast'!$B50) -> 0 | S50: =SUMIFS('Combined P&L'!Q:Q,'Combined P&L'!$C:$C,'P&L Forecast'!$B50) -> 0 | T50: =SUMIFS('Combined P&L'!R:R,'Combined P&L'!$C:$C,'P&L Forecast'!$B50) -> 0 | U50: =SUMIFS('Combined P&L'!S:S,'Combined P&L'!$C:$C,'P&L Forecast'!$B50) -> 0 | V50: =SUMIFS('Combined P&L'!T:T,'Combined P&L'!$C:$C,'P&L Forecast'!$B50) -> 0 | W50: =SUMIFS('Combined P&L'!U:U,'Combined P&L'!$C:$C,'P&L Forecast'!$B50) -> 0 | X50: =SUMIFS('Combined P&L'!V:V,'Combined P&L'!$C:$C,'P&L Forecast'!$B50) -> 0 | Y50: =SUMIFS('Combined P&L'!W:W,'Combined P&L'!$C:$C,'P&L Forecast'!$B50) -> 0 | Z50: =SUMIFS('Combined P&L'!X:X,'Combined P&L'!$C:$C,'P&L Forecast'!$B50) -> 0 | AA50: =SUMIFS('Combined P&L'!Y:Y,'Combined P&L'!$C:$C,'P&L Forecast'!$B50) -> 0 | AB50: =SUMIFS('Combined P&L'!Z:Z,'Combined P&L'!$C:$C,'P&L Forecast'!$B50) -> 0.00691 | AC50: =SUMIFS('Combined P&L'!AA:AA,'Combined P&L'!$C:$C,'P&L Forecast'!$B50) -> 0 | AD50: =SUMIFS('Combined P&L'!AB:AB,'Combined P&L'!$C:$C,'P&L Forecast'!$B50) -> 0 | AE50: =SUMIFS('Combined P&L'!AC:AC,'Combined P&L'!$C:$C,'P&L Forecast'!$B50) -> 11.40629 | AF50: =SUMIFS('Combined P&L'!AD:AD,'Combined P&L'!$C:$C,'P&L Forecast'!$B50) -> 10.78472 | AG50: =SUMIFS('Combined P&L'!AE:AE,'Combined P&L'!$C:$C,'P&L Forecast'!$B50) -> 0 | AH50: =SUMIFS('Combined P&L'!AF:AF,'Combined P&L'!$C:$C,'P&L Forecast'!$B50) -> 0.09766 | AI50: =SUMIFS('Combined P&L'!AG:AG,'Combined P&L'!$C:$C,'P&L Forecast'!$B50) -> 0.92152 | AJ50: =SUMIFS('Combined P&L'!AH:AH,'Combined P&L'!$C:$C,'P&L Forecast'!$B50) -> 2.96423 | AK50: =SUMIFS('Combined P&L'!AI:AI,'Combined P&L'!$C:$C,'P&L Forecast'!$B50) -> 1.03679 | AL50: =SUMIFS('Combined P&L'!AJ:AJ,'Combined P&L'!$C:$C,'P&L Forecast'!$B50) -> 2.11036 | AM50: =SUMIFS('Combined P&L'!AK:AK,'Combined P&L'!$C:$C,'P&L Forecast'!$B50) -> 0.43274 | AN50: =SUMIFS('Combined P&L'!AL:AL,'Combined P&L'!$C:$C,'P&L Forecast'!$B50) -> 0 | AO50: =SUMIFS('Combined P&L'!AM:AM,'Combined P&L'!$C:$C,'P&L Forecast'!$B50) -> 0 | AP50: =SUMIFS('Combined P&L'!AN:AN,'Combined P&L'!$C:$C,'P&L Forecast'!$B50) -> 0 | AQ50: =SUMIFS('Combined P&L'!AO:AO,'Combined P&L'!$C:$C,'P&L Forecast'!$B50) -> 9.7651 | AR50: =SUMIFS('Combined P&L'!AP:AP,'Combined P&L'!$C:$C,'P&L Forecast'!$B50) -> 10.25443 | AS50: =SUMIFS('Combined P&L'!AQ:AQ,'Combined P&L'!$C:$C,'P&L Forecast'!$B50) -> 0.6559 | AT50: =SUMIFS('Combined P&L'!AR:AR,'Combined P&L'!$C:$C,'P&L Forecast'!$B50) -> 0.00999
B51: Payment Collection Fees | C51: =SUMIFS($P51:$AT51,$P$5:$AT$5,">"&C$199,$P$5:$AT$5,"<"&C$200) -> 8.67099 | D51: =SUMIFS($P51:$AT51,$P$5:$AT$5,">"&D$199,$P$5:$AT$5,"<"&D$200) -> 13.35153 | F51: =SUMIFS($P51:$AT51,$P$5:$AT$5,">"&F$199,$P$5:$AT$5,"<"&F$200) -> 6.80445 | G51: =SUMIFS($P51:$AT51,$P$5:$AT$5,">"&G$199,$P$5:$AT$5,"<"&G$200) -> 9.02684 | I51: =SUMIFS($P51:$AT51,$P$5:$AT$5,">"&I$199,$P$5:$AT$5,"<"&I$200) -> 10.54373 | J51: =SUMIFS($P51:$AT51,$P$5:$AT$5,">"&J$199,$P$5:$AT$5,"<"&J$200) -> 15.57392 | K51: =+C151 -> 15.57392 | M51: =K51-J51 -> 0 | N51: =IFERROR(K51/J51-1,0) -> 0 | P51: =SUMIFS('Combined P&L'!N:N,'Combined P&L'!$C:$C,'P&L Forecast'!$B51) -> 0.6179 | Q51: =SUMIFS('Combined P&L'!O:O,'Combined P&L'!$C:$C,'P&L Forecast'!$B51) -> 0.8374 | R51: =SUMIFS('Combined P&L'!P:P,'Combined P&L'!$C:$C,'P&L Forecast'!$B51) -> 0.62936 | S51: =SUMIFS('Combined P&L'!Q:Q,'Combined P&L'!$C:$C,'P&L Forecast'!$B51) -> 0.68245 | T51: =SUMIFS('Combined P&L'!R:R,'Combined P&L'!$C:$C,'P&L Forecast'!$B51) -> 0.72151 | U51: =SUMIFS('Combined P&L'!S:S,'Combined P&L'!$C:$C,'P&L Forecast'!$B51) -> 0.78747 | V51: =SUMIFS('Combined P&L'!T:T,'Combined P&L'!$C:$C,'P&L Forecast'!$B51) -> 0.65562 | W51: =SUMIFS('Combined P&L'!U:U,'Combined P&L'!$C:$C,'P&L Forecast'!$B51) -> 0.79491 | X51: =SUMIFS('Combined P&L'!V:V,'Combined P&L'!$C:$C,'P&L Forecast'!$B51) -> 0.69063 | Y51: =SUMIFS('Combined P&L'!W:W,'Combined P&L'!$C:$C,'P&L Forecast'!$B51) -> 0.71761 | Z51: =SUMIFS('Combined P&L'!X:X,'Combined P&L'!$C:$C,'P&L Forecast'!$B51) -> 0.73795 | AA51: =SUMIFS('Combined P&L'!Y:Y,'Combined P&L'!$C:$C,'P&L Forecast'!$B51) -> 0.79818 | AB51: =SUMIFS('Combined P&L'!Z:Z,'Combined P&L'!$C:$C,'P&L Forecast'!$B51) -> 0.83546 | AC51: =SUMIFS('Combined P&L'!AA:AA,'Combined P&L'!$C:$C,'P&L Forecast'!$B51) -> 1.05394 | AD51: =SUMIFS('Combined P&L'!AB:AB,'Combined P&L'!$C:$C,'P&L Forecast'!$B51) -> 0.87069 | AE51: =SUMIFS('Combined P&L'!AC:AC,'Combined P&L'!$C:$C,'P&L Forecast'!$B51) -> 0.90555 | AF51: =SUMIFS('Combined P&L'!AD:AD,'Combined P&L'!$C:$C,'P&L Forecast'!$B51) -> 0.91157 | AG51: =SUMIFS('Combined P&L'!AE:AE,'Combined P&L'!$C:$C,'P&L Forecast'!$B51) -> 1.00249 | AH51: =SUMIFS('Combined P&L'!AF:AF,'Combined P&L'!$C:$C,'P&L Forecast'!$B51) -> 1.22475 | AI51: =SUMIFS('Combined P&L'!AG:AG,'Combined P&L'!$C:$C,'P&L Forecast'!$B51) -> 1.10438 | AJ51: =SUMIFS('Combined P&L'!AH:AH,'Combined P&L'!$C:$C,'P&L Forecast'!$B51) -> 1.29723 | AK51: =SUMIFS('Combined P&L'!AI:AI,'Combined P&L'!$C:$C,'P&L Forecast'!$B51) -> 1.21739 | AL51: =SUMIFS('Combined P&L'!AJ:AJ,'Combined P&L'!$C:$C,'P&L Forecast'!$B51) -> 1.62294 | AM51: =SUMIFS('Combined P&L'!AK:AK,'Combined P&L'!$C:$C,'P&L Forecast'!$B51) -> 1.30514 | AN51: =SUMIFS('Combined P&L'!AL:AL,'Combined P&L'!$C:$C,'P&L Forecast'!$B51) -> 1.22974 | AO51: =SUMIFS('Combined P&L'!AM:AM,'Combined P&L'!$C:$C,'P&L Forecast'!$B51) -> 1.73847 | AP51: =SUMIFS('Combined P&L'!AN:AN,'Combined P&L'!$C:$C,'P&L Forecast'!$B51) -> 1.35348 | AQ51: =SUMIFS('Combined P&L'!AO:AO,'Combined P&L'!$C:$C,'P&L Forecast'!$B51) -> 1.23399 | AR51: =SUMIFS('Combined P&L'!AP:AP,'Combined P&L'!$C:$C,'P&L Forecast'!$B51) -> 1.17137 | AS51: =SUMIFS('Combined P&L'!AQ:AQ,'Combined P&L'!$C:$C,'P&L Forecast'!$B51) -> 1.15392 | AT51: =SUMIFS('Combined P&L'!AR:AR,'Combined P&L'!$C:$C,'P&L Forecast'!$B51) -> 1.14587
B52: Professional Organizations | C52: =SUMIFS($P52:$AT52,$P$5:$AT$5,">"&C$199,$P$5:$AT$5,"<"&C$200) -> 5.44332 | D52: =SUMIFS($P52:$AT52,$P$5:$AT$5,">"&D$199,$P$5:$AT$5,"<"&D$200) -> 11.22296 | F52: =SUMIFS($P52:$AT52,$P$5:$AT$5,">"&F$199,$P$5:$AT$5,"<"&F$200) -> 6.191 | G52: =SUMIFS($P52:$AT52,$P$5:$AT$5,">"&G$199,$P$5:$AT$5,"<"&G$200) -> 6.57881 | I52: =SUMIFS($P52:$AT52,$P$5:$AT$5,">"&I$199,$P$5:$AT$5,"<"&I$200) -> 9.53268 | J52: =SUMIFS($P52:$AT52,$P$5:$AT$5,">"&J$199,$P$5:$AT$5,"<"&J$200) -> 11.61077 | K52: =+C152 -> 11.61077 | M52: =K52-J52 -> 0 | N52: =IFERROR(K52/J52-1,0) -> 0 | P52: =SUMIFS('Combined P&L'!N:N,'Combined P&L'!$C:$C,'P&L Forecast'!$B52) -> 0.33417 | Q52: =SUMIFS('Combined P&L'!O:O,'Combined P&L'!$C:$C,'P&L Forecast'!$B52) -> 0.33417 | R52: =SUMIFS('Combined P&L'!P:P,'Combined P&L'!$C:$C,'P&L Forecast'!$B52) -> 0.33417 | S52: =SUMIFS('Combined P&L'!Q:Q,'Combined P&L'!$C:$C,'P&L Forecast'!$B52) -> 0.33417 | T52: =SUMIFS('Combined P&L'!R:R,'Combined P&L'!$C:$C,'P&L Forecast'!$B52) -> 0.255 | U52: =SUMIFS('Combined P&L'!S:S,'Combined P&L'!$C:$C,'P&L Forecast'!$B52) -> 0.255 | V52: =SUMIFS('Combined P&L'!T:T,'Combined P&L'!$C:$C,'P&L Forecast'!$B52) -> 0.25496 | W52: =SUMIFS('Combined P&L'!U:U,'Combined P&L'!$C:$C,'P&L Forecast'!$B52) -> 0.205 | X52: =SUMIFS('Combined P&L'!V:V,'Combined P&L'!$C:$C,'P&L Forecast'!$B52) -> 0.78417 | Y52: =SUMIFS('Combined P&L'!W:W,'Combined P&L'!$C:$C,'P&L Forecast'!$B52) -> 0.78417 | Z52: =SUMIFS('Combined P&L'!X:X,'Combined P&L'!$C:$C,'P&L Forecast'!$B52) -> 0.78417 | AA52: =SUMIFS('Combined P&L'!Y:Y,'Combined P&L'!$C:$C,'P&L Forecast'!$B52) -> 0.78417 | AB52: =SUMIFS('Combined P&L'!Z:Z,'Combined P&L'!$C:$C,'P&L Forecast'!$B52) -> 0.78417 | AC52: =SUMIFS('Combined P&L'!AA:AA,'Combined P&L'!$C:$C,'P&L Forecast'!$B52) -> 0.78417 | AD52: =SUMIFS('Combined P&L'!AB:AB,'Combined P&L'!$C:$C,'P&L Forecast'!$B52) -> 0.78417 | AE52: =SUMIFS('Combined P&L'!AC:AC,'Combined P&L'!$C:$C,'P&L Forecast'!$B52) -> 0.78417 | AF52: =SUMIFS('Combined P&L'!AD:AD,'Combined P&L'!$C:$C,'P&L Forecast'!$B52) -> 0.78417 | AG52: =SUMIFS('Combined P&L'!AE:AE,'Combined P&L'!$C:$C,'P&L Forecast'!$B52) -> 0.78417 | AH52: =SUMIFS('Combined P&L'!AF:AF,'Combined P&L'!$C:$C,'P&L Forecast'!$B52) -> 1.48598 | AI52: =SUMIFS('Combined P&L'!AG:AG,'Combined P&L'!$C:$C,'P&L Forecast'!$B52) -> 0.9633 | AJ52: =SUMIFS('Combined P&L'!AH:AH,'Combined P&L'!$C:$C,'P&L Forecast'!$B52) -> 0.98042 | AK52: =SUMIFS('Combined P&L'!AI:AI,'Combined P&L'!$C:$C,'P&L Forecast'!$B52) -> 1.02942 | AL52: =SUMIFS('Combined P&L'!AJ:AJ,'Combined P&L'!$C:$C,'P&L Forecast'!$B52) -> 1.02942 | AM52: =SUMIFS('Combined P&L'!AK:AK,'Combined P&L'!$C:$C,'P&L Forecast'!$B52) -> 1.0294 | AN52: =SUMIFS('Combined P&L'!AL:AL,'Combined P&L'!$C:$C,'P&L Forecast'!$B52) -> 0.93983 | AO52: =SUMIFS('Combined P&L'!AM:AM,'Combined P&L'!$C:$C,'P&L Forecast'!$B52) -> 0.93983 | AP52: =SUMIFS('Combined P&L'!AN:AN,'Combined P&L'!$C:$C,'P&L Forecast'!$B52) -> 0.93983 | AQ52: =SUMIFS('Combined P&L'!AO:AO,'Combined P&L'!$C:$C,'P&L Forecast'!$B52) -> 0.93983 | AR52: =SUMIFS('Combined P&L'!AP:AP,'Combined P&L'!$C:$C,'P&L Forecast'!$B52) -> 0.93983 | AS52: =SUMIFS('Combined P&L'!AQ:AQ,'Combined P&L'!$C:$C,'P&L Forecast'!$B52) -> 0.93983 | AT52: =SUMIFS('Combined P&L'!AR:AR,'Combined P&L'!$C:$C,'P&L Forecast'!$B52) -> 0.93983
B53: S&M Events | C53: =SUMIFS($P53:$AT53,$P$5:$AT$5,">"&C$199,$P$5:$AT$5,"<"&C$200) -> 0 | D53: =SUMIFS($P53:$AT53,$P$5:$AT$5,">"&D$199,$P$5:$AT$5,"<"&D$200) -> 11.4983 | F53: =SUMIFS($P53:$AT53,$P$5:$AT$5,">"&F$199,$P$5:$AT$5,"<"&F$200) -> 0 | G53: =SUMIFS($P53:$AT53,$P$5:$AT$5,">"&G$199,$P$5:$AT$5,"<"&G$200) -> 11.84548 | I53: =SUMIFS($P53:$AT53,$P$5:$AT$5,">"&I$199,$P$5:$AT$5,"<"&I$200) -> 0 | J53: =SUMIFS($P53:$AT53,$P$5:$AT$5,">"&J$199,$P$5:$AT$5,"<"&J$200) -> 23.34378 | K53: =+C153 -> 23.34378 | M53: =K53-J53 -> 0 | N53: =IFERROR(K53/J53-1,0) -> 0 | P53: =SUMIFS('Combined P&L'!N:N,'Combined P&L'!$C:$C,'P&L Forecast'!$B53) -> 0 | Q53: =SUMIFS('Combined P&L'!O:O,'Combined P&L'!$C:$C,'P&L Forecast'!$B53) -> 0 | R53: =SUMIFS('Combined P&L'!P:P,'Combined P&L'!$C:$C,'P&L Forecast'!$B53) -> 0 | S53: =SUMIFS('Combined P&L'!Q:Q,'Combined P&L'!$C:$C,'P&L Forecast'!$B53) -> 0 | T53: =SUMIFS('Combined P&L'!R:R,'Combined P&L'!$C:$C,'P&L Forecast'!$B53) -> 0 | U53: =SUMIFS('Combined P&L'!S:S,'Combined P&L'!$C:$C,'P&L Forecast'!$B53) -> 0 | V53: =SUMIFS('Combined P&L'!T:T,'Combined P&L'!$C:$C,'P&L Forecast'!$B53) -> 0 | W53: =SUMIFS('Combined P&L'!U:U,'Combined P&L'!$C:$C,'P&L Forecast'!$B53) -> 0 | X53: =SUMIFS('Combined P&L'!V:V,'Combined P&L'!$C:$C,'P&L Forecast'!$B53) -> 0 | Y53: =SUMIFS('Combined P&L'!W:W,'Combined P&L'!$C:$C,'P&L Forecast'!$B53) -> 0 | Z53: =SUMIFS('Combined P&L'!X:X,'Combined P&L'!$C:$C,'P&L Forecast'!$B53) -> 0 | AA53: =SUMIFS('Combined P&L'!Y:Y,'Combined P&L'!$C:$C,'P&L Forecast'!$B53) -> 0 | AB53: =SUMIFS('Combined P&L'!Z:Z,'Combined P&L'!$C:$C,'P&L Forecast'!$B53) -> 0 | AC53: =SUMIFS('Combined P&L'!AA:AA,'Combined P&L'!$C:$C,'P&L Forecast'!$B53) -> 0 | AD53: =SUMIFS('Combined P&L'!AB:AB,'Combined P&L'!$C:$C,'P&L Forecast'!$B53) -> 0 | AE53: =SUMIFS('Combined P&L'!AC:AC,'Combined P&L'!$C:$C,'P&L Forecast'!$B53) -> 0 | AF53: =SUMIFS('Combined P&L'!AD:AD,'Combined P&L'!$C:$C,'P&L Forecast'!$B53) -> 0 | AG53: =SUMIFS('Combined P&L'!AE:AE,'Combined P&L'!$C:$C,'P&L Forecast'!$B53) -> 0 | AH53: =SUMIFS('Combined P&L'!AF:AF,'Combined P&L'!$C:$C,'P&L Forecast'!$B53) -> 0 | AI53: =SUMIFS('Combined P&L'!AG:AG,'Combined P&L'!$C:$C,'P&L Forecast'!$B53) -> 7.17 | AJ53: =SUMIFS('Combined P&L'!AH:AH,'Combined P&L'!$C:$C,'P&L Forecast'!$B53) -> 1.6495 | AK53: =SUMIFS('Combined P&L'!AI:AI,'Combined P&L'!$C:$C,'P&L Forecast'!$B53) -> 2.6788 | AL53: =SUMIFS('Combined P&L'!AJ:AJ,'Combined P&L'!$C:$C,'P&L Forecast'!$B53) -> 0 | AM53: =SUMIFS('Combined P&L'!AK:AK,'Combined P&L'!$C:$C,'P&L Forecast'!$B53) -> 0 | AN53: =SUMIFS('Combined P&L'!AL:AL,'Combined P&L'!$C:$C,'P&L Forecast'!$B53) -> 0.05 | AO53: =SUMIFS('Combined P&L'!AM:AM,'Combined P&L'!$C:$C,'P&L Forecast'!$B53) -> 0 | AP53: =SUMIFS('Combined P&L'!AN:AN,'Combined P&L'!$C:$C,'P&L Forecast'!$B53) -> 0 | AQ53: =SUMIFS('Combined P&L'!AO:AO,'Combined P&L'!$C:$C,'P&L Forecast'!$B53) -> 0 | AR53: =SUMIFS('Combined P&L'!AP:AP,'Combined P&L'!$C:$C,'P&L Forecast'!$B53) -> 0.09805 | AS53: =SUMIFS('Combined P&L'!AQ:AQ,'Combined P&L'!$C:$C,'P&L Forecast'!$B53) -> 0.00243 | AT53: =SUMIFS('Combined P&L'!AR:AR,'Combined P&L'!$C:$C,'P&L Forecast'!$B53) -> 11.695
B54: Contract Labor - Tax | C54: =SUMIFS($P54:$AT54,$P$5:$AT$5,">"&C$199,$P$5:$AT$5,"<"&C$200) -> 0 | D54: =SUMIFS($P54:$AT54,$P$5:$AT$5,">"&D$199,$P$5:$AT$5,"<"&D$200) -> 1.5875 | F54: =SUMIFS($P54:$AT54,$P$5:$AT$5,">"&F$199,$P$5:$AT$5,"<"&F$200) -> 0 | G54: =SUMIFS($P54:$AT54,$P$5:$AT$5,">"&G$199,$P$5:$AT$5,"<"&G$200) -> 30.5155 | I54: =SUMIFS($P54:$AT54,$P$5:$AT$5,">"&I$199,$P$5:$AT$5,"<"&I$200) -> 0 | J54: =SUMIFS($P54:$AT54,$P$5:$AT$5,">"&J$199,$P$5:$AT$5,"<"&J$200) -> 32.103 | K54: =+C154 -> 38.7615 | M54: =K54-J54 -> 6.6585 | N54: =IFERROR(K54/J54-1,0) -> 0.20741052 | P54: =SUMIFS('Combined P&L'!N:N,'Combined P&L'!$C:$C,'P&L Forecast'!$B54) -> 0 | Q54: =SUMIFS('Combined P&L'!O:O,'Combined P&L'!$C:$C,'P&L Forecast'!$B54) -> 0 | R54: =SUMIFS('Combined P&L'!P:P,'Combined P&L'!$C:$C,'P&L Forecast'!$B54) -> 0 | S54: =SUMIFS('Combined P&L'!Q:Q,'Combined P&L'!$C:$C,'P&L Forecast'!$B54) -> 0 | T54: =SUMIFS('Combined P&L'!R:R,'Combined P&L'!$C:$C,'P&L Forecast'!$B54) -> 0 | U54: =SUMIFS('Combined P&L'!S:S,'Combined P&L'!$C:$C,'P&L Forecast'!$B54) -> 0 | V54: =SUMIFS('Combined P&L'!T:T,'Combined P&L'!$C:$C,'P&L Forecast'!$B54) -> 0 | W54: =SUMIFS('Combined P&L'!U:U,'Combined P&L'!$C:$C,'P&L Forecast'!$B54) -> 0 | X54: =SUMIFS('Combined P&L'!V:V,'Combined P&L'!$C:$C,'P&L Forecast'!$B54) -> 0 | Y54: =SUMIFS('Combined P&L'!W:W,'Combined P&L'!$C:$C,'P&L Forecast'!$B54) -> 0 | Z54: =SUMIFS('Combined P&L'!X:X,'Combined P&L'!$C:$C,'P&L Forecast'!$B54) -> 0 | AA54: =SUMIFS('Combined P&L'!Y:Y,'Combined P&L'!$C:$C,'P&L Forecast'!$B54) -> 0 | AB54: =SUMIFS('Combined P&L'!Z:Z,'Combined P&L'!$C:$C,'P&L Forecast'!$B54) -> 0 | AC54: =SUMIFS('Combined P&L'!AA:AA,'Combined P&L'!$C:$C,'P&L Forecast'!$B54) -> 0 | AD54: =SUMIFS('Combined P&L'!AB:AB,'Combined P&L'!$C:$C,'P&L Forecast'!$B54) -> 0 | AE54: =SUMIFS('Combined P&L'!AC:AC,'Combined P&L'!$C:$C,'P&L Forecast'!$B54) -> 0 | AF54: =SUMIFS('Combined P&L'!AD:AD,'Combined P&L'!$C:$C,'P&L Forecast'!$B54) -> 0 | AG54: =SUMIFS('Combined P&L'!AE:AE,'Combined P&L'!$C:$C,'P&L Forecast'!$B54) -> 0 | AH54: =SUMIFS('Combined P&L'!AF:AF,'Combined P&L'!$C:$C,'P&L Forecast'!$B54) -> 0 | AI54: =SUMIFS('Combined P&L'!AG:AG,'Combined P&L'!$C:$C,'P&L Forecast'!$B54) -> 0 | AJ54: =SUMIFS('Combined P&L'!AH:AH,'Combined P&L'!$C:$C,'P&L Forecast'!$B54) -> 0 | AK54: =SUMIFS('Combined P&L'!AI:AI,'Combined P&L'!$C:$C,'P&L Forecast'!$B54) -> 1.15 | AL54: =SUMIFS('Combined P&L'!AJ:AJ,'Combined P&L'!$C:$C,'P&L Forecast'!$B54) -> 0.4375 | AM54: =SUMIFS('Combined P&L'!AK:AK,'Combined P&L'!$C:$C,'P&L Forecast'!$B54) -> 0 | AN54: =SUMIFS('Combined P&L'!AL:AL,'Combined P&L'!$C:$C,'P&L Forecast'!$B54) -> 0 | AO54: =SUMIFS('Combined P&L'!AM:AM,'Combined P&L'!$C:$C,'P&L Forecast'!$B54) -> 3 | AP54: =SUMIFS('Combined P&L'!AN:AN,'Combined P&L'!$C:$C,'P&L Forecast'!$B54) -> 16.2655 | AQ54: =SUMIFS('Combined P&L'!AO:AO,'Combined P&L'!$C:$C,'P&L Forecast'!$B54) -> 2.8 | AR54: =SUMIFS('Combined P&L'!AP:AP,'Combined P&L'!$C:$C,'P&L Forecast'!$B54) -> 0 | AS54: =SUMIFS('Combined P&L'!AQ:AQ,'Combined P&L'!$C:$C,'P&L Forecast'!$B54) -> 8.45 | AT54: =SUMIFS('Combined P&L'!AR:AR,'Combined P&L'!$C:$C,'P&L Forecast'!$B54) -> 0
B55: Recruiting Fees | C55: =SUMIFS($P55:$AT55,$P$5:$AT$5,">"&C$199,$P$5:$AT$5,"<"&C$200) -> 14.90205 | D55: =SUMIFS($P55:$AT55,$P$5:$AT$5,">"&D$199,$P$5:$AT$5,"<"&D$200) -> 31.6041 | F55: =SUMIFS($P55:$AT55,$P$5:$AT$5,">"&F$199,$P$5:$AT$5,"<"&F$200) -> 28.29994 | G55: =SUMIFS($P55:$AT55,$P$5:$AT$5,">"&G$199,$P$5:$AT$5,"<"&G$200) -> 5.5646 | I55: =SUMIFS($P55:$AT55,$P$5:$AT$5,">"&I$199,$P$5:$AT$5,"<"&I$200) -> 35.34606 | J55: =SUMIFS($P55:$AT55,$P$5:$AT$5,">"&J$199,$P$5:$AT$5,"<"&J$200) -> 8.86876 | K55: =+C155 -> 8.86876 | M55: =K55-J55 -> 0 | N55: =IFERROR(K55/J55-1,0) -> 0 | P55: =SUMIFS('Combined P&L'!N:N,'Combined P&L'!$C:$C,'P&L Forecast'!$B55) -> 0.02492 | Q55: =SUMIFS('Combined P&L'!O:O,'Combined P&L'!$C:$C,'P&L Forecast'!$B55) -> 1.02492 | R55: =SUMIFS('Combined P&L'!P:P,'Combined P&L'!$C:$C,'P&L Forecast'!$B55) -> 1.02492 | S55: =SUMIFS('Combined P&L'!Q:Q,'Combined P&L'!$C:$C,'P&L Forecast'!$B55) -> 1.22492 | T55: =SUMIFS('Combined P&L'!R:R,'Combined P&L'!$C:$C,'P&L Forecast'!$B55) -> 1.02492 | U55: =SUMIFS('Combined P&L'!S:S,'Combined P&L'!$C:$C,'P&L Forecast'!$B55) -> 1.51802 | V55: =SUMIFS('Combined P&L'!T:T,'Combined P&L'!$C:$C,'P&L Forecast'!$B55) -> 2.01331 | W55: =SUMIFS('Combined P&L'!U:U,'Combined P&L'!$C:$C,'P&L Forecast'!$B55) -> 1.6009 | X55: =SUMIFS('Combined P&L'!V:V,'Combined P&L'!$C:$C,'P&L Forecast'!$B55) -> 1.58969 | Y55: =SUMIFS('Combined P&L'!W:W,'Combined P&L'!$C:$C,'P&L Forecast'!$B55) -> 1.12582 | Z55: =SUMIFS('Combined P&L'!X:X,'Combined P&L'!$C:$C,'P&L Forecast'!$B55) -> 1.44199 | AA55: =SUMIFS('Combined P&L'!Y:Y,'Combined P&L'!$C:$C,'P&L Forecast'!$B55) -> 1.28772 | AB55: =SUMIFS('Combined P&L'!Z:Z,'Combined P&L'!$C:$C,'P&L Forecast'!$B55) -> 2.41295 | AC55: =SUMIFS('Combined P&L'!AA:AA,'Combined P&L'!$C:$C,'P&L Forecast'!$B55) -> 22.3793 | AD55: =SUMIFS('Combined P&L'!AB:AB,'Combined P&L'!$C:$C,'P&L Forecast'!$B55) -> 0.72983 | AE55: =SUMIFS('Combined P&L'!AC:AC,'Combined P&L'!$C:$C,'P&L Forecast'!$B55) -> 0.59597 | AF55: =SUMIFS('Combined P&L'!AD:AD,'Combined P&L'!$C:$C,'P&L Forecast'!$B55) -> 0.87534 | AG55: =SUMIFS('Combined P&L'!AE:AE,'Combined P&L'!$C:$C,'P&L Forecast'!$B55) -> 0.52967 | AH55: =SUMIFS('Combined P&L'!AF:AF,'Combined P&L'!$C:$C,'P&L Forecast'!$B55) -> 0.77688 | AI55: =SUMIFS('Combined P&L'!AG:AG,'Combined P&L'!$C:$C,'P&L Forecast'!$B55) -> 0.21671 | AJ55: =SUMIFS('Combined P&L'!AH:AH,'Combined P&L'!$C:$C,'P&L Forecast'!$B55) -> 0.74952 | AK55: =SUMIFS('Combined P&L'!AI:AI,'Combined P&L'!$C:$C,'P&L Forecast'!$B55) -> 0.92573 | AL55: =SUMIFS('Combined P&L'!AJ:AJ,'Combined P&L'!$C:$C,'P&L Forecast'!$B55) -> 0.66044 | AM55: =SUMIFS('Combined P&L'!AK:AK,'Combined P&L'!$C:$C,'P&L Forecast'!$B55) -> 0.75176 | AN55: =SUMIFS('Combined P&L'!AL:AL,'Combined P&L'!$C:$C,'P&L Forecast'!$B55) -> 0.8203 | AO55: =SUMIFS('Combined P&L'!AM:AM,'Combined P&L'!$C:$C,'P&L Forecast'!$B55) -> 0.68046 | AP55: =SUMIFS('Combined P&L'!AN:AN,'Combined P&L'!$C:$C,'P&L Forecast'!$B55) -> 0.77239 | AQ55: =SUMIFS('Combined P&L'!AO:AO,'Combined P&L'!$C:$C,'P&L Forecast'!$B55) -> 0.71608 | AR55: =SUMIFS('Combined P&L'!AP:AP,'Combined P&L'!$C:$C,'P&L Forecast'!$B55) -> 0.6402 | AS55: =SUMIFS('Combined P&L'!AQ:AQ,'Combined P&L'!$C:$C,'P&L Forecast'!$B55) -> 1.13538 | AT55: =SUMIFS('Combined P&L'!AR:AR,'Combined P&L'!$C:$C,'P&L Forecast'!$B55) -> 0.79979
B56: Amortization | C56: =SUMIFS($P56:$AT56,$P$5:$AT$5,">"&C$199,$P$5:$AT$5,"<"&C$200) -> 6.673 | D56: =SUMIFS($P56:$AT56,$P$5:$AT$5,">"&D$199,$P$5:$AT$5,"<"&D$200) -> 6.673 | F56: =SUMIFS($P56:$AT56,$P$5:$AT$5,">"&F$199,$P$5:$AT$5,"<"&F$200) -> 0 | G56: =SUMIFS($P56:$AT56,$P$5:$AT$5,">"&G$199,$P$5:$AT$5,"<"&G$200) -> 0 | I56: =SUMIFS($P56:$AT56,$P$5:$AT$5,">"&I$199,$P$5:$AT$5,"<"&I$200) -> 6.673 | J56: =SUMIFS($P56:$AT56,$P$5:$AT$5,">"&J$199,$P$5:$AT$5,"<"&J$200) -> 6.673 | K56: =+C156 -> 6.673 | M56: =K56-J56 -> 0 | N56: =IFERROR(K56/J56-1,0) -> 0 | P56: =SUMIFS('Combined P&L'!N:N,'Combined P&L'!$C:$C,'P&L Forecast'!$B56) -> 0 | Q56: =SUMIFS('Combined P&L'!O:O,'Combined P&L'!$C:$C,'P&L Forecast'!$B56) -> 0 | R56: =SUMIFS('Combined P&L'!P:P,'Combined P&L'!$C:$C,'P&L Forecast'!$B56) -> 0 | S56: =SUMIFS('Combined P&L'!Q:Q,'Combined P&L'!$C:$C,'P&L Forecast'!$B56) -> 0 | T56: =SUMIFS('Combined P&L'!R:R,'Combined P&L'!$C:$C,'P&L Forecast'!$B56) -> 0 | U56: =SUMIFS('Combined P&L'!S:S,'Combined P&L'!$C:$C,'P&L Forecast'!$B56) -> 0 | V56: =SUMIFS('Combined P&L'!T:T,'Combined P&L'!$C:$C,'P&L Forecast'!$B56) -> 0 | W56: =SUMIFS('Combined P&L'!U:U,'Combined P&L'!$C:$C,'P&L Forecast'!$B56) -> 0 | X56: =SUMIFS('Combined P&L'!V:V,'Combined P&L'!$C:$C,'P&L Forecast'!$B56) -> 0 | Y56: =SUMIFS('Combined P&L'!W:W,'Combined P&L'!$C:$C,'P&L Forecast'!$B56) -> 0 | Z56: =SUMIFS('Combined P&L'!X:X,'Combined P&L'!$C:$C,'P&L Forecast'!$B56) -> 0 | AA56: =SUMIFS('Combined P&L'!Y:Y,'Combined P&L'!$C:$C,'P&L Forecast'!$B56) -> 6.673 | AB56: =SUMIFS('Combined P&L'!Z:Z,'Combined P&L'!$C:$C,'P&L Forecast'!$B56) -> 0 | AC56: =SUMIFS('Combined P&L'!AA:AA,'Combined P&L'!$C:$C,'P&L Forecast'!$B56) -> 0 | AD56: =SUMIFS('Combined P&L'!AB:AB,'Combined P&L'!$C:$C,'P&L Forecast'!$B56) -> 0 | AE56: =SUMIFS('Combined P&L'!AC:AC,'Combined P&L'!$C:$C,'P&L Forecast'!$B56) -> 0 | AF56: =SUMIFS('Combined P&L'!AD:AD,'Combined P&L'!$C:$C,'P&L Forecast'!$B56) -> 0 | AG56: =SUMIFS('Combined P&L'!AE:AE,'Combined P&L'!$C:$C,'P&L Forecast'!$B56) -> 0 | AH56: =SUMIFS('Combined P&L'!AF:AF,'Combined P&L'!$C:$C,'P&L Forecast'!$B56) -> 0 | AI56: =SUMIFS('Combined P&L'!AG:AG,'Combined P&L'!$C:$C,'P&L Forecast'!$B56) -> 0 | AJ56: =SUMIFS('Combined P&L'!AH:AH,'Combined P&L'!$C:$C,'P&L Forecast'!$B56) -> 0 | AK56: =SUMIFS('Combined P&L'!AI:AI,'Combined P&L'!$C:$C,'P&L Forecast'!$B56) -> 0 | AL56: =SUMIFS('Combined P&L'!AJ:AJ,'Combined P&L'!$C:$C,'P&L Forecast'!$B56) -> 0 | AM56: =SUMIFS('Combined P&L'!AK:AK,'Combined P&L'!$C:$C,'P&L Forecast'!$B56) -> 6.673 | AN56: =SUMIFS('Combined P&L'!AL:AL,'Combined P&L'!$C:$C,'P&L Forecast'!$B56) -> 0 | AO56: =SUMIFS('Combined P&L'!AM:AM,'Combined P&L'!$C:$C,'P&L Forecast'!$B56) -> 0 | AP56: =SUMIFS('Combined P&L'!AN:AN,'Combined P&L'!$C:$C,'P&L Forecast'!$B56) -> 0 | AQ56: =SUMIFS('Combined P&L'!AO:AO,'Combined P&L'!$C:$C,'P&L Forecast'!$B56) -> 0 | AR56: =SUMIFS('Combined P&L'!AP:AP,'Combined P&L'!$C:$C,'P&L Forecast'!$B56) -> 0 | AS56: =SUMIFS('Combined P&L'!AQ:AQ,'Combined P&L'!$C:$C,'P&L Forecast'!$B56) -> 0 | AT56: =SUMIFS('Combined P&L'!AR:AR,'Combined P&L'!$C:$C,'P&L Forecast'!$B56) -> 0
B57: Website | C57: =SUMIFS($P57:$AT57,$P$5:$AT$5,">"&C$199,$P$5:$AT$5,"<"&C$200) -> 7.26173 | D57: =SUMIFS($P57:$AT57,$P$5:$AT$5,">"&D$199,$P$5:$AT$5,"<"&D$200) -> 4.91967 | F57: =SUMIFS($P57:$AT57,$P$5:$AT$5,">"&F$199,$P$5:$AT$5,"<"&F$200) -> 2.92467 | G57: =SUMIFS($P57:$AT57,$P$5:$AT$5,">"&G$199,$P$5:$AT$5,"<"&G$200) -> 2.90857 | I57: =SUMIFS($P57:$AT57,$P$5:$AT$5,">"&I$199,$P$5:$AT$5,"<"&I$200) -> 5.74187 | J57: =SUMIFS($P57:$AT57,$P$5:$AT$5,">"&J$199,$P$5:$AT$5,"<"&J$200) -> 4.90357 | K57: =+C157 -> 4.90357 | M57: =K57-J57 -> 0 | N57: =IFERROR(K57/J57-1,0) -> 0 | P57: =SUMIFS('Combined P&L'!N:N,'Combined P&L'!$C:$C,'P&L Forecast'!$B57) -> 0.43326 | Q57: =SUMIFS('Combined P&L'!O:O,'Combined P&L'!$C:$C,'P&L Forecast'!$B57) -> 1.63176 | R57: =SUMIFS('Combined P&L'!P:P,'Combined P&L'!$C:$C,'P&L Forecast'!$B57) -> 0.43368 | S57: =SUMIFS('Combined P&L'!Q:Q,'Combined P&L'!$C:$C,'P&L Forecast'!$B57) -> 0.48413 | T57: =SUMIFS('Combined P&L'!R:R,'Combined P&L'!$C:$C,'P&L Forecast'!$B57) -> 0.48413 | U57: =SUMIFS('Combined P&L'!S:S,'Combined P&L'!$C:$C,'P&L Forecast'!$B57) -> 0.48413 | V57: =SUMIFS('Combined P&L'!T:T,'Combined P&L'!$C:$C,'P&L Forecast'!$B57) -> 0.49344 | W57: =SUMIFS('Combined P&L'!U:U,'Combined P&L'!$C:$C,'P&L Forecast'!$B57) -> 0.84344 | X57: =SUMIFS('Combined P&L'!V:V,'Combined P&L'!$C:$C,'P&L Forecast'!$B57) -> 0.49344 | Y57: =SUMIFS('Combined P&L'!W:W,'Combined P&L'!$C:$C,'P&L Forecast'!$B57) -> 0.49344 | Z57: =SUMIFS('Combined P&L'!X:X,'Combined P&L'!$C:$C,'P&L Forecast'!$B57) -> 0.49344 | AA57: =SUMIFS('Combined P&L'!Y:Y,'Combined P&L'!$C:$C,'P&L Forecast'!$B57) -> 0.49344 | AB57: =SUMIFS('Combined P&L'!Z:Z,'Combined P&L'!$C:$C,'P&L Forecast'!$B57) -> 0.53067 | AC57: =SUMIFS('Combined P&L'!AA:AA,'Combined P&L'!$C:$C,'P&L Forecast'!$B57) -> 0.399 | AD57: =SUMIFS('Combined P&L'!AB:AB,'Combined P&L'!$C:$C,'P&L Forecast'!$B57) -> 0.399 | AE57: =SUMIFS('Combined P&L'!AC:AC,'Combined P&L'!$C:$C,'P&L Forecast'!$B57) -> 0.399 | AF57: =SUMIFS('Combined P&L'!AD:AD,'Combined P&L'!$C:$C,'P&L Forecast'!$B57) -> 0.399 | AG57: =SUMIFS('Combined P&L'!AE:AE,'Combined P&L'!$C:$C,'P&L Forecast'!$B57) -> 0.399 | AH57: =SUMIFS('Combined P&L'!AF:AF,'Combined P&L'!$C:$C,'P&L Forecast'!$B57) -> 0.399 | AI57: =SUMIFS('Combined P&L'!AG:AG,'Combined P&L'!$C:$C,'P&L Forecast'!$B57) -> 0.399 | AJ57: =SUMIFS('Combined P&L'!AH:AH,'Combined P&L'!$C:$C,'P&L Forecast'!$B57) -> 0.399 | AK57: =SUMIFS('Combined P&L'!AI:AI,'Combined P&L'!$C:$C,'P&L Forecast'!$B57) -> 0.399 | AL57: =SUMIFS('Combined P&L'!AJ:AJ,'Combined P&L'!$C:$C,'P&L Forecast'!$B57) -> 0.399 | AM57: =SUMIFS('Combined P&L'!AK:AK,'Combined P&L'!$C:$C,'P&L Forecast'!$B57) -> 0.399 | AN57: =SUMIFS('Combined P&L'!AL:AL,'Combined P&L'!$C:$C,'P&L Forecast'!$B57) -> 0.43619 | AO57: =SUMIFS('Combined P&L'!AM:AM,'Combined P&L'!$C:$C,'P&L Forecast'!$B57) -> 0.399 | AP57: =SUMIFS('Combined P&L'!AN:AN,'Combined P&L'!$C:$C,'P&L Forecast'!$B57) -> 0.47738 | AQ57: =SUMIFS('Combined P&L'!AO:AO,'Combined P&L'!$C:$C,'P&L Forecast'!$B57) -> 0.399 | AR57: =SUMIFS('Combined P&L'!AP:AP,'Combined P&L'!$C:$C,'P&L Forecast'!$B57) -> 0.399 | AS57: =SUMIFS('Combined P&L'!AQ:AQ,'Combined P&L'!$C:$C,'P&L Forecast'!$B57) -> 0.399 | AT57: =SUMIFS('Combined P&L'!AR:AR,'Combined P&L'!$C:$C,'P&L Forecast'!$B57) -> 0.399
B58: State Taxes | C58: =SUMIFS($P58:$AT58,$P$5:$AT$5,">"&C$199,$P$5:$AT$5,"<"&C$200) -> 7.497 | D58: =SUMIFS($P58:$AT58,$P$5:$AT$5,">"&D$199,$P$5:$AT$5,"<"&D$200) -> 9.984 | F58: =SUMIFS($P58:$AT58,$P$5:$AT$5,">"&F$199,$P$5:$AT$5,"<"&F$200) -> 5.894 | G58: =SUMIFS($P58:$AT58,$P$5:$AT$5,">"&G$199,$P$5:$AT$5,"<"&G$200) -> 1.172 | I58: =SUMIFS($P58:$AT58,$P$5:$AT$5,">"&I$199,$P$5:$AT$5,"<"&I$200) -> 4.673 | J58: =SUMIFS($P58:$AT58,$P$5:$AT$5,">"&J$199,$P$5:$AT$5,"<"&J$200) -> 5.262 | K58: =+C158 -> 5.262 | M58: =K58-J58 -> 0 | N58: =IFERROR(K58/J58-1,0) -> 0 | P58: =SUMIFS('Combined P&L'!N:N,'Combined P&L'!$C:$C,'P&L Forecast'!$B58) -> 0 | Q58: =SUMIFS('Combined P&L'!O:O,'Combined P&L'!$C:$C,'P&L Forecast'!$B58) -> 0 | R58: =SUMIFS('Combined P&L'!P:P,'Combined P&L'!$C:$C,'P&L Forecast'!$B58) -> 0 | S58: =SUMIFS('Combined P&L'!Q:Q,'Combined P&L'!$C:$C,'P&L Forecast'!$B58) -> 6.246 | T58: =SUMIFS('Combined P&L'!R:R,'Combined P&L'!$C:$C,'P&L Forecast'!$B58) -> 0 | U58: =SUMIFS('Combined P&L'!S:S,'Combined P&L'!$C:$C,'P&L Forecast'!$B58) -> 2.472 | V58: =SUMIFS('Combined P&L'!T:T,'Combined P&L'!$C:$C,'P&L Forecast'!$B58) -> 0 | W58: =SUMIFS('Combined P&L'!U:U,'Combined P&L'!$C:$C,'P&L Forecast'!$B58) -> 0 | X58: =SUMIFS('Combined P&L'!V:V,'Combined P&L'!$C:$C,'P&L Forecast'!$B58) -> 2.472 | Y58: =SUMIFS('Combined P&L'!W:W,'Combined P&L'!$C:$C,'P&L Forecast'!$B58) -> 0 | Z58: =SUMIFS('Combined P&L'!X:X,'Combined P&L'!$C:$C,'P&L Forecast'!$B58) -> 0 | AA58: =SUMIFS('Combined P&L'!Y:Y,'Combined P&L'!$C:$C,'P&L Forecast'!$B58) -> -3.693 | AB58: =SUMIFS('Combined P&L'!Z:Z,'Combined P&L'!$C:$C,'P&L Forecast'!$B58) -> 2.472 | AC58: =SUMIFS('Combined P&L'!AA:AA,'Combined P&L'!$C:$C,'P&L Forecast'!$B58) -> 0 | AD58: =SUMIFS('Combined P&L'!AB:AB,'Combined P&L'!$C:$C,'P&L Forecast'!$B58) -> 0 | AE58: =SUMIFS('Combined P&L'!AC:AC,'Combined P&L'!$C:$C,'P&L Forecast'!$B58) -> 3.649 | AF58: =SUMIFS('Combined P&L'!AD:AD,'Combined P&L'!$C:$C,'P&L Forecast'!$B58) -> -2.272 | AG58: =SUMIFS('Combined P&L'!AE:AE,'Combined P&L'!$C:$C,'P&L Forecast'!$B58) -> 2.045 | AH58: =SUMIFS('Combined P&L'!AF:AF,'Combined P&L'!$C:$C,'P&L Forecast'!$B58) -> 0 | AI58: =SUMIFS('Combined P&L'!AG:AG,'Combined P&L'!$C:$C,'P&L Forecast'!$B58) -> 0 | AJ58: =SUMIFS('Combined P&L'!AH:AH,'Combined P&L'!$C:$C,'P&L Forecast'!$B58) -> 2.045 | AK58: =SUMIFS('Combined P&L'!AI:AI,'Combined P&L'!$C:$C,'P&L Forecast'!$B58) -> 0 | AL58: =SUMIFS('Combined P&L'!AJ:AJ,'Combined P&L'!$C:$C,'P&L Forecast'!$B58) -> 0 | AM58: =SUMIFS('Combined P&L'!AK:AK,'Combined P&L'!$C:$C,'P&L Forecast'!$B58) -> 2.045 | AN58: =SUMIFS('Combined P&L'!AL:AL,'Combined P&L'!$C:$C,'P&L Forecast'!$B58) -> 0 | AO58: =SUMIFS('Combined P&L'!AM:AM,'Combined P&L'!$C:$C,'P&L Forecast'!$B58) -> 0 | AP58: =SUMIFS('Combined P&L'!AN:AN,'Combined P&L'!$C:$C,'P&L Forecast'!$B58) -> 5.036 | AQ58: =SUMIFS('Combined P&L'!AO:AO,'Combined P&L'!$C:$C,'P&L Forecast'!$B58) -> -4.864 | AR58: =SUMIFS('Combined P&L'!AP:AP,'Combined P&L'!$C:$C,'P&L Forecast'!$B58) -> 0 | AS58: =SUMIFS('Combined P&L'!AQ:AQ,'Combined P&L'!$C:$C,'P&L Forecast'!$B58) -> 1 | AT58: =SUMIFS('Combined P&L'!AR:AR,'Combined P&L'!$C:$C,'P&L Forecast'!$B58) -> 0
B59: Insurance | C59: =SUMIFS($P59:$AT59,$P$5:$AT$5,">"&C$199,$P$5:$AT$5,"<"&C$200) -> 2.08994 | D59: =SUMIFS($P59:$AT59,$P$5:$AT$5,">"&D$199,$P$5:$AT$5,"<"&D$200) -> 2.61982 | F59: =SUMIFS($P59:$AT59,$P$5:$AT$5,">"&F$199,$P$5:$AT$5,"<"&F$200) -> 1.44049 | G59: =SUMIFS($P59:$AT59,$P$5:$AT$5,">"&G$199,$P$5:$AT$5,"<"&G$200) -> 3.70971 | I59: =SUMIFS($P59:$AT59,$P$5:$AT$5,">"&I$199,$P$5:$AT$5,"<"&I$200) -> 2.33371 | J59: =SUMIFS($P59:$AT59,$P$5:$AT$5,">"&J$199,$P$5:$AT$5,"<"&J$200) -> 4.88904 | K59: =+C159 -> 4.88904 | M59: =K59-J59 -> 0 | N59: =IFERROR(K59/J59-1,0) -> 0 | P59: =SUMIFS('Combined P&L'!N:N,'Combined P&L'!$C:$C,'P&L Forecast'!$B59) -> 0.14747 | Q59: =SUMIFS('Combined P&L'!O:O,'Combined P&L'!$C:$C,'P&L Forecast'!$B59) -> 0.14747 | R59: =SUMIFS('Combined P&L'!P:P,'Combined P&L'!$C:$C,'P&L Forecast'!$B59) -> 0.17755 | S59: =SUMIFS('Combined P&L'!Q:Q,'Combined P&L'!$C:$C,'P&L Forecast'!$B59) -> 0.19167 | T59: =SUMIFS('Combined P&L'!R:R,'Combined P&L'!$C:$C,'P&L Forecast'!$B59) -> 0.18014 | U59: =SUMIFS('Combined P&L'!S:S,'Combined P&L'!$C:$C,'P&L Forecast'!$B59) -> 0.17622 | V59: =SUMIFS('Combined P&L'!T:T,'Combined P&L'!$C:$C,'P&L Forecast'!$B59) -> 0.1762 | W59: =SUMIFS('Combined P&L'!U:U,'Combined P&L'!$C:$C,'P&L Forecast'!$B59) -> 0.17622 | X59: =SUMIFS('Combined P&L'!V:V,'Combined P&L'!$C:$C,'P&L Forecast'!$B59) -> 0.18712 | Y59: =SUMIFS('Combined P&L'!W:W,'Combined P&L'!$C:$C,'P&L Forecast'!$B59) -> 0.17744 | Z59: =SUMIFS('Combined P&L'!X:X,'Combined P&L'!$C:$C,'P&L Forecast'!$B59) -> 0.17622 | AA59: =SUMIFS('Combined P&L'!Y:Y,'Combined P&L'!$C:$C,'P&L Forecast'!$B59) -> 0.17622 | AB59: =SUMIFS('Combined P&L'!Z:Z,'Combined P&L'!$C:$C,'P&L Forecast'!$B59) -> 0.17678 | AC59: =SUMIFS('Combined P&L'!AA:AA,'Combined P&L'!$C:$C,'P&L Forecast'!$B59) -> 0.20899 | AD59: =SUMIFS('Combined P&L'!AB:AB,'Combined P&L'!$C:$C,'P&L Forecast'!$B59) -> 0.1896 | AE59: =SUMIFS('Combined P&L'!AC:AC,'Combined P&L'!$C:$C,'P&L Forecast'!$B59) -> 0.1759 | AF59: =SUMIFS('Combined P&L'!AD:AD,'Combined P&L'!$C:$C,'P&L Forecast'!$B59) -> 0.2357 | AG59: =SUMIFS('Combined P&L'!AE:AE,'Combined P&L'!$C:$C,'P&L Forecast'!$B59) -> 0.22676 | AH59: =SUMIFS('Combined P&L'!AF:AF,'Combined P&L'!$C:$C,'P&L Forecast'!$B59) -> 0.22676 | AI59: =SUMIFS('Combined P&L'!AG:AG,'Combined P&L'!$C:$C,'P&L Forecast'!$B59) -> 0.22676 | AJ59: =SUMIFS('Combined P&L'!AH:AH,'Combined P&L'!$C:$C,'P&L Forecast'!$B59) -> 0.24325 | AK59: =SUMIFS('Combined P&L'!AI:AI,'Combined P&L'!$C:$C,'P&L Forecast'!$B59) -> 0.24228 | AL59: =SUMIFS('Combined P&L'!AJ:AJ,'Combined P&L'!$C:$C,'P&L Forecast'!$B59) -> 0.23352 | AM59: =SUMIFS('Combined P&L'!AK:AK,'Combined P&L'!$C:$C,'P&L Forecast'!$B59) -> 0.23352 | AN59: =SUMIFS('Combined P&L'!AL:AL,'Combined P&L'!$C:$C,'P&L Forecast'!$B59) -> 0.22943 | AO59: =SUMIFS('Combined P&L'!AM:AM,'Combined P&L'!$C:$C,'P&L Forecast'!$B59) -> 2.22858 | AP59: =SUMIFS('Combined P&L'!AN:AN,'Combined P&L'!$C:$C,'P&L Forecast'!$B59) -> 0.25448 | AQ59: =SUMIFS('Combined P&L'!AO:AO,'Combined P&L'!$C:$C,'P&L Forecast'!$B59) -> 0.25564 | AR59: =SUMIFS('Combined P&L'!AP:AP,'Combined P&L'!$C:$C,'P&L Forecast'!$B59) -> 0.26164 | AS59: =SUMIFS('Combined P&L'!AQ:AQ,'Combined P&L'!$C:$C,'P&L Forecast'!$B59) -> 0.26183 | AT59: =SUMIFS('Combined P&L'!AR:AR,'Combined P&L'!$C:$C,'P&L Forecast'!$B59) -> 0.21811
... B61: Utilities | C61: =SUMIFS($P61:$AT61,$P$5:$AT$5,">"&C$199,$P$5:$AT$5,"<"&C$200) -> 1.05983 | D61: =SUMIFS($P61:$AT61,$P$5:$AT$5,">"&D$199,$P$5:$AT$5,"<"&D$200) -> 3.29133 | F61: =SUMIFS($P61:$AT61,$P$5:$AT$5,">"&F$199,$P$5:$AT$5,"<"&F$200) -> 2.02633 | G61: =SUMIFS($P61:$AT61,$P$5:$AT$5,">"&G$199,$P$5:$AT$5,"<"&G$200) -> 1.943 | I61: =SUMIFS($P61:$AT61,$P$5:$AT$5,">"&I$199,$P$5:$AT$5,"<"&I$200) -> 2.45133 | J61: =SUMIFS($P61:$AT61,$P$5:$AT$5,">"&J$199,$P$5:$AT$5,"<"&J$200) -> 3.208 | K61: =+C161 -> 3.208 | M61: =K61-J61 -> 0 | N61: =IFERROR(K61/J61-1,0) -> 0 | P61: =SUMIFS('Combined P&L'!N:N,'Combined P&L'!$C:$C,'P&L Forecast'!$B61) -> 0.085 | Q61: =SUMIFS('Combined P&L'!O:O,'Combined P&L'!$C:$C,'P&L Forecast'!$B61) -> 0.085 | R61: =SUMIFS('Combined P&L'!P:P,'Combined P&L'!$C:$C,'P&L Forecast'!$B61) -> 0.097 | S61: =SUMIFS('Combined P&L'!Q:Q,'Combined P&L'!$C:$C,'P&L Forecast'!$B61) -> 0.11283 | T61: =SUMIFS('Combined P&L'!R:R,'Combined P&L'!$C:$C,'P&L Forecast'!$B61) -> 0.085 | U61: =SUMIFS('Combined P&L'!S:S,'Combined P&L'!$C:$C,'P&L Forecast'!$B61) -> 0.085 | V61: =SUMIFS('Combined P&L'!T:T,'Combined P&L'!$C:$C,'P&L Forecast'!$B61) -> 0.085 | W61: =SUMIFS('Combined P&L'!U:U,'Combined P&L'!$C:$C,'P&L Forecast'!$B61) -> 0.085 | X61: =SUMIFS('Combined P&L'!V:V,'Combined P&L'!$C:$C,'P&L Forecast'!$B61) -> 0.085 | Y61: =SUMIFS('Combined P&L'!W:W,'Combined P&L'!$C:$C,'P&L Forecast'!$B61) -> 0.085 | Z61: =SUMIFS('Combined P&L'!X:X,'Combined P&L'!$C:$C,'P&L Forecast'!$B61) -> 0.085 | AA61: =SUMIFS('Combined P&L'!Y:Y,'Combined P&L'!$C:$C,'P&L Forecast'!$B61) -> 0.085 | AB61: =SUMIFS('Combined P&L'!Z:Z,'Combined P&L'!$C:$C,'P&L Forecast'!$B61) -> 0.085 | AC61: =SUMIFS('Combined P&L'!AA:AA,'Combined P&L'!$C:$C,'P&L Forecast'!$B61) -> 0.09449 | AD61: =SUMIFS('Combined P&L'!AB:AB,'Combined P&L'!$C:$C,'P&L Forecast'!$B61) -> 0.82489 | AE61: =SUMIFS('Combined P&L'!AC:AC,'Combined P&L'!$C:$C,'P&L Forecast'!$B61) -> 0.253 | AF61: =SUMIFS('Combined P&L'!AD:AD,'Combined P&L'!$C:$C,'P&L Forecast'!$B61) -> 0.26295 | AG61: =SUMIFS('Combined P&L'!AE:AE,'Combined P&L'!$C:$C,'P&L Forecast'!$B61) -> 0.253 | AH61: =SUMIFS('Combined P&L'!AF:AF,'Combined P&L'!$C:$C,'P&L Forecast'!$B61) -> 0.253 | AI61: =SUMIFS('Combined P&L'!AG:AG,'Combined P&L'!$C:$C,'P&L Forecast'!$B61) -> 0.253 | AJ61: =SUMIFS('Combined P&L'!AH:AH,'Combined P&L'!$C:$C,'P&L Forecast'!$B61) -> 0.253 | AK61: =SUMIFS('Combined P&L'!AI:AI,'Combined P&L'!$C:$C,'P&L Forecast'!$B61) -> 0.253 | AL61: =SUMIFS('Combined P&L'!AJ:AJ,'Combined P&L'!$C:$C,'P&L Forecast'!$B61) -> 0.253 | AM61: =SUMIFS('Combined P&L'!AK:AK,'Combined P&L'!$C:$C,'P&L Forecast'!$B61) -> 0.253 | AN61: =SUMIFS('Combined P&L'!AL:AL,'Combined P&L'!$C:$C,'P&L Forecast'!$B61) -> 0.253 | AO61: =SUMIFS('Combined P&L'!AM:AM,'Combined P&L'!$C:$C,'P&L Forecast'!$B61) -> 0.255 | AP61: =SUMIFS('Combined P&L'!AN:AN,'Combined P&L'!$C:$C,'P&L Forecast'!$B61) -> 0.283 | AQ61: =SUMIFS('Combined P&L'!AO:AO,'Combined P&L'!$C:$C,'P&L Forecast'!$B61) -> 0.283 | AR61: =SUMIFS('Combined P&L'!AP:AP,'Combined P&L'!$C:$C,'P&L Forecast'!$B61) -> 0.283 | AS61: =SUMIFS('Combined P&L'!AQ:AQ,'Combined P&L'!$C:$C,'P&L Forecast'!$B61) -> 0.293 | AT61: =SUMIFS('Combined P&L'!AR:AR,'Combined P&L'!$C:$C,'P&L Forecast'!$B61) -> 0.293
