Workbook

Sheet Cover
B24: Keystone Bookkeepers
B25: Diligence Workbook
B26: ="As of "&TEXT(TODAY(),"mm/dd/yy") -> As of 09/02/26

Sheet P&L Overview
B2: =+Cover!B24 -> Keystone Bookkeepers
B3: Summary P&L Overview ($000s)
B5: P&L Summary ($000s) | C5: FY2024 | D5: FY2025 | F5: July'25 YTD | G5: July'26 YTD | I5: Jul'25 LTM | J5: Jul'26 LTM | L5: 45292 | M5: =EOMONTH(L5,0)+1 -> 45323 | N5: =EOMONTH(M5,0)+1 -> 45352 | O5: =EOMONTH(N5,0)+1 -> 45383 | P5: =EOMONTH(O5,0)+1 -> 45413 | Q5: =EOMONTH(P5,0)+1 -> 45444 | R5: =EOMONTH(Q5,0)+1 -> 45474 | S5: =EOMONTH(R5,0)+1 -> 45505 | T5: =EOMONTH(S5,0)+1 -> 45536 | ... AP5: =EOMONTH(AO5,0)+1 -> 46204
B6: Revenue
B7: STR Subscription | C7: =SUMIFS($L7:$AP7,$L$5:$AP$5,">"&C$42,$L$5:$AP$5,"<"&C$43) -> 793.47225 | D7: =SUMIFS($L7:$AP7,$L$5:$AP$5,">"&D$42,$L$5:$AP$5,"<"&D$43) -> 1450.4923 | F7: =SUMIFS($L7:$AP7,$L$5:$AP$5,">"&F$42,$L$5:$AP$5,"<"&F$43) -> 751.5286 | G7: =SUMIFS($L7:$AP7,$L$5:$AP$5,">"&G$42,$L$5:$AP$5,"<"&G$43) -> 1261.4769 | I7: =SUMIFS($L7:$AP7,$L$5:$AP$5,">"&I$42,$L$5:$AP$5,"<"&I$43) -> 1098.5075 | J7: =SUMIFS($L7:$AP7,$L$5:$AP$5,">"&J$42,$L$5:$AP$5,"<"&J$43) -> 1881.6971 | L7: =SUMIFS('Combined P&L'!N:N,'Combined P&L'!$C:$C,'P&L Overview'!$B7) -> 44.6835 | M7: =SUMIFS('Combined P&L'!O:O,'Combined P&L'!$C:$C,'P&L Overview'!$B7) -> 47.046 | N7: =SUMIFS('Combined P&L'!P:P,'Combined P&L'!$C:$C,'P&L Overview'!$B7) -> 52.47 | O7: =SUMIFS('Combined P&L'!Q:Q,'Combined P&L'!$C:$C,'P&L Overview'!$B7) -> 57.1697 | P7: =SUMIFS('Combined P&L'!R:R,'Combined P&L'!$C:$C,'P&L Overview'!$B7) -> 57.51415 | Q7: =SUMIFS('Combined P&L'!S:S,'Combined P&L'!$C:$C,'P&L Overview'!$B7) -> 65.516 | R7: =SUMIFS('Combined P&L'!T:T,'Combined P&L'!$C:$C,'P&L Overview'!$B7) -> 68.28125 | S7: =SUMIFS('Combined P&L'!U:U,'Combined P&L'!$C:$C,'P&L Overview'!$B7) -> 73.25135 | T7: =SUMIFS('Combined P&L'!V:V,'Combined P&L'!$C:$C,'P&L Overview'!$B7) -> 75.5517 | U7: =SUMIFS('Combined P&L'!W:W,'Combined P&L'!$C:$C,'P&L Overview'!$B7) -> 79.11325 | V7: =SUMIFS('Combined P&L'!X:X,'Combined P&L'!$C:$C,'P&L Overview'!$B7) -> 83.2908 | W7: =SUMIFS('Combined P&L'!Y:Y,'Combined P&L'!$C:$C,'P&L Overview'!$B7) -> 89.58455 | X7: =SUMIFS('Combined P&L'!Z:Z,'Combined P&L'!$C:$C,'P&L Overview'!$B7) -> 92.4189 | Y7: =SUMIFS('Combined P&L'!AA:AA,'Combined P&L'!$C:$C,'P&L Overview'!$B7) -> 94.00215 | Z7: =SUMIFS('Combined P&L'!AB:AB,'Combined P&L'!$C:$C,'P&L Overview'!$B7) -> 101.50605 | AA7: =SUMIFS('Combined P&L'!AC:AC,'Combined P&L'!$C:$C,'P&L Overview'!$B7) -> 106.1375 | AB7: =SUMIFS('Combined P&L'!AD:AD,'Combined P&L'!$C:$C,'P&L Overview'!$B7) -> 115.93875 | AC7: =SUMIFS('Combined P&L'!AE:AE,'Combined P&L'!$C:$C,'P&L Overview'!$B7) -> 119.43125 | AD7: =SUMIFS('Combined P&L'!AF:AF,'Combined P&L'!$C:$C,'P&L Overview'!$B7) -> 122.094 | AE7: =SUMIFS('Combined P&L'!AG:AG,'Combined P&L'!$C:$C,'P&L Overview'!$B7) -> 130.08525 | AF7: =SUMIFS('Combined P&L'!AH:AH,'Combined P&L'!$C:$C,'P&L Overview'!$B7) -> 133.5905 | AG7: =SUMIFS('Combined P&L'!AI:AI,'Combined P&L'!$C:$C,'P&L Overview'!$B7) -> 139.609 | AH7: =SUMIFS('Combined P&L'!AJ:AJ,'Combined P&L'!$C:$C,'P&L Overview'!$B7) -> 145.28075 | AI7: =SUMIFS('Combined P&L'!AK:AK,'Combined P&L'!$C:$C,'P&L Overview'!$B7) -> 150.39825 | AJ7: =SUMIFS('Combined P&L'!AL:AL,'Combined P&L'!$C:$C,'P&L Overview'!$B7) -> 156.5388 | AK7: =SUMIFS('Combined P&L'!AM:AM,'Combined P&L'!$C:$C,'P&L Overview'!$B7) -> 164.9034 | AL7: =SUMIFS('Combined P&L'!AN:AN,'Combined P&L'!$C:$C,'P&L Overview'!$B7) -> 170.34425 | AM7: =SUMIFS('Combined P&L'!AO:AO,'Combined P&L'!$C:$C,'P&L Overview'!$B7) -> 183.662 | AN7: =SUMIFS('Combined P&L'!AP:AP,'Combined P&L'!$C:$C,'P&L Overview'!$B7) -> 190.7844 | AO7: =SUMIFS('Combined P&L'!AQ:AQ,'Combined P&L'!$C:$C,'P&L Overview'!$B7) -> 194.4065 | AP7: =SUMIFS('Combined P&L'!AR:AR,'Combined P&L'!$C:$C,'P&L Overview'!$B7) -> 200.8375
B8: SMB Subscription | C8: =SUMIFS($L8:$AP8,$L$5:$AP$5,">"&C$42,$L$5:$AP$5,"<"&C$43) -> 224.791 | D8: =SUMIFS($L8:$AP8,$L$5:$AP$5,">"&D$42,$L$5:$AP$5,"<"&D$43) -> 149.77 | F8: =SUMIFS($L8:$AP8,$L$5:$AP$5,">"&F$42,$L$5:$AP$5,"<"&F$43) -> 90.4525 | G8: =SUMIFS($L8:$AP8,$L$5:$AP$5,">"&G$42,$L$5:$AP$5,"<"&G$43) -> 73.4185 | I8: =SUMIFS($L8:$AP8,$L$5:$AP$5,">"&I$42,$L$5:$AP$5,"<"&I$43) -> 174.63 | J8: =SUMIFS($L8:$AP8,$L$5:$AP$5,">"&J$42,$L$5:$AP$5,"<"&J$43) -> 135.298 | L8: =SUMIFS('Combined P&L'!N:N,'Combined P&L'!$C:$C,'P&L Overview'!$B8) -> 22.001 | M8: =SUMIFS('Combined P&L'!O:O,'Combined P&L'!$C:$C,'P&L Overview'!$B8) -> 22.036 | N8: =SUMIFS('Combined P&L'!P:P,'Combined P&L'!$C:$C,'P&L Overview'!$B8) -> 22.111 | O8: =SUMIFS('Combined P&L'!Q:Q,'Combined P&L'!$C:$C,'P&L Overview'!$B8) -> 22.146 | P8: =SUMIFS('Combined P&L'!R:R,'Combined P&L'!$C:$C,'P&L Overview'!$B8) -> 21.966 | Q8: =SUMIFS('Combined P&L'!S:S,'Combined P&L'!$C:$C,'P&L Overview'!$B8) -> 17.816 | R8: =SUMIFS('Combined P&L'!T:T,'Combined P&L'!$C:$C,'P&L Overview'!$B8) -> 17.621 | S8: =SUMIFS('Combined P&L'!U:U,'Combined P&L'!$C:$C,'P&L Overview'!$B8) -> 17.536 | T8: =SUMIFS('Combined P&L'!V:V,'Combined P&L'!$C:$C,'P&L Overview'!$B8) -> 16.426 | U8: =SUMIFS('Combined P&L'!W:W,'Combined P&L'!$C:$C,'P&L Overview'!$B8) -> 15.381 | V8: =SUMIFS('Combined P&L'!X:X,'Combined P&L'!$C:$C,'P&L Overview'!$B8) -> 14.6755 | W8: =SUMIFS('Combined P&L'!Y:Y,'Combined P&L'!$C:$C,'P&L Overview'!$B8) -> 15.0755 | X8: =SUMIFS('Combined P&L'!Z:Z,'Combined P&L'!$C:$C,'P&L Overview'!$B8) -> 14.5625 | Y8: =SUMIFS('Combined P&L'!AA:AA,'Combined P&L'!$C:$C,'P&L Overview'!$B8) -> 12.8025 | Z8: =SUMIFS('Combined P&L'!AB:AB,'Combined P&L'!$C:$C,'P&L Overview'!$B8) -> 12.4025 | AA8: =SUMIFS('Combined P&L'!AC:AC,'Combined P&L'!$C:$C,'P&L Overview'!$B8) -> 12.6025 | AB8: =SUMIFS('Combined P&L'!AD:AD,'Combined P&L'!$C:$C,'P&L Overview'!$B8) -> 12.7525 | AC8: =SUMIFS('Combined P&L'!AE:AE,'Combined P&L'!$C:$C,'P&L Overview'!$B8) -> 12.7925 | AD8: =SUMIFS('Combined P&L'!AF:AF,'Combined P&L'!$C:$C,'P&L Overview'!$B8) -> 12.5375 | AE8: =SUMIFS('Combined P&L'!AG:AG,'Combined P&L'!$C:$C,'P&L Overview'!$B8) -> 11.8575 | AF8: =SUMIFS('Combined P&L'!AH:AH,'Combined P&L'!$C:$C,'P&L Overview'!$B8) -> 12.3025 | AG8: =SUMIFS('Combined P&L'!AI:AI,'Combined P&L'!$C:$C,'P&L Overview'!$B8) -> 11.6925 | AH8: =SUMIFS('Combined P&L'!AJ:AJ,'Combined P&L'!$C:$C,'P&L Overview'!$B8) -> 11.7175 | AI8: =SUMIFS('Combined P&L'!AK:AK,'Combined P&L'!$C:$C,'P&L Overview'!$B8) -> 11.7475 | AJ8: =SUMIFS('Combined P&L'!AL:AL,'Combined P&L'!$C:$C,'P&L Overview'!$B8) -> 11.2805 | AK8: =SUMIFS('Combined P&L'!AM:AM,'Combined P&L'!$C:$C,'P&L Overview'!$B8) -> 10.9305 | AL8: =SUMIFS('Combined P&L'!AN:AN,'Combined P&L'!$C:$C,'P&L Overview'!$B8) -> 10.6255 | AM8: =SUMIFS('Combined P&L'!AO:AO,'Combined P&L'!$C:$C,'P&L Overview'!$B8) -> 10.3155 | AN8: =SUMIFS('Combined P&L'!AP:AP,'Combined P&L'!$C:$C,'P&L Overview'!$B8) -> 10.3155 | AO8: =SUMIFS('Combined P&L'!AQ:AQ,'Combined P&L'!$C:$C,'P&L Overview'!$B8) -> 9.9755 | AP8: =SUMIFS('Combined P&L'!AR:AR,'Combined P&L'!$C:$C,'P&L Overview'!$B8) -> 9.9755
B9: Occupancy Taxes | C9: =SUMIFS($L9:$AP9,$L$5:$AP$5,">"&C$42,$L$5:$AP$5,"<"&C$43) -> 0.56 | D9: =SUMIFS($L9:$AP9,$L$5:$AP$5,">"&D$42,$L$5:$AP$5,"<"&D$43) -> 55.0805 | F9: =SUMIFS($L9:$AP9,$L$5:$AP$5,">"&F$42,$L$5:$AP$5,"<"&F$43) -> 23.2255 | G9: =SUMIFS($L9:$AP9,$L$5:$AP$5,">"&G$42,$L$5:$AP$5,"<"&G$43) -> 91.65114 | I9: =SUMIFS($L9:$AP9,$L$5:$AP$5,">"&I$42,$L$5:$AP$5,"<"&I$43) -> 18.727 | J9: =SUMIFS($L9:$AP9,$L$5:$AP$5,">"&J$42,$L$5:$AP$5,"<"&J$43) -> 112.49549 | L9: =SUMIFS('Combined P&L'!N:N,'Combined P&L'!$C:$C,'P&L Overview'!$B9) -> 0 | M9: =SUMIFS('Combined P&L'!O:O,'Combined P&L'!$C:$C,'P&L Overview'!$B9) -> 0 | N9: =SUMIFS('Combined P&L'!P:P,'Combined P&L'!$C:$C,'P&L Overview'!$B9) -> 0 | O9: =SUMIFS('Combined P&L'!Q:Q,'Combined P&L'!$C:$C,'P&L Overview'!$B9) -> 0 | P9: =SUMIFS('Combined P&L'!R:R,'Combined P&L'!$C:$C,'P&L Overview'!$B9) -> 0 | Q9: =SUMIFS('Combined P&L'!S:S,'Combined P&L'!$C:$C,'P&L Overview'!$B9) -> 0 | R9: =SUMIFS('Combined P&L'!T:T,'Combined P&L'!$C:$C,'P&L Overview'!$B9) -> 0 | S9: =SUMIFS('Combined P&L'!U:U,'Combined P&L'!$C:$C,'P&L Overview'!$B9) -> 0 | T9: =SUMIFS('Combined P&L'!V:V,'Combined P&L'!$C:$C,'P&L Overview'!$B9) -> 0 | U9: =SUMIFS('Combined P&L'!W:W,'Combined P&L'!$C:$C,'P&L Overview'!$B9) -> 0 | V9: =SUMIFS('Combined P&L'!X:X,'Combined P&L'!$C:$C,'P&L Overview'!$B9) -> 0.08 | W9: =SUMIFS('Combined P&L'!Y:Y,'Combined P&L'!$C:$C,'P&L Overview'!$B9) -> 0.48 | X9: =SUMIFS('Combined P&L'!Z:Z,'Combined P&L'!$C:$C,'P&L Overview'!$B9) -> 1.13 | Y9: =SUMIFS('Combined P&L'!AA:AA,'Combined P&L'!$C:$C,'P&L Overview'!$B9) -> 2.14 | Z9: =SUMIFS('Combined P&L'!AB:AB,'Combined P&L'!$C:$C,'P&L Overview'!$B9) -> 2.66 | AA9: =SUMIFS('Combined P&L'!AC:AC,'Combined P&L'!$C:$C,'P&L Overview'!$B9) -> 3.65 | AB9: =SUMIFS('Combined P&L'!AD:AD,'Combined P&L'!$C:$C,'P&L Overview'!$B9) -> 3.623 | AC9: =SUMIFS('Combined P&L'!AE:AE,'Combined P&L'!$C:$C,'P&L Overview'!$B9) -> 4.964 | AD9: =SUMIFS('Combined P&L'!AF:AF,'Combined P&L'!$C:$C,'P&L Overview'!$B9) -> 5.0585 | AE9: =SUMIFS('Combined P&L'!AG:AG,'Combined P&L'!$C:$C,'P&L Overview'!$B9) -> 4.73 | AF9: =SUMIFS('Combined P&L'!AH:AH,'Combined P&L'!$C:$C,'P&L Overview'!$B9) -> 4.82 | AG9: =SUMIFS('Combined P&L'!AI:AI,'Combined P&L'!$C:$C,'P&L Overview'!$B9) -> 5.37 | AH9: =SUMIFS('Combined P&L'!AJ:AJ,'Combined P&L'!$C:$C,'P&L Overview'!$B9) -> 8.05 | AI9: =SUMIFS('Combined P&L'!AK:AK,'Combined P&L'!$C:$C,'P&L Overview'!$B9) -> 8.885 | AJ9: =SUMIFS('Combined P&L'!AL:AL,'Combined P&L'!$C:$C,'P&L Overview'!$B9) -> 10.90952 | AK9: =SUMIFS('Combined P&L'!AM:AM,'Combined P&L'!$C:$C,'P&L Overview'!$B9) -> 10.33497 | AL9: =SUMIFS('Combined P&L'!AN:AN,'Combined P&L'!$C:$C,'P&L Overview'!$B9) -> 11.175 | AM9: =SUMIFS('Combined P&L'!AO:AO,'Combined P&L'!$C:$C,'P&L Overview'!$B9) -> 11.95311 | AN9: =SUMIFS('Combined P&L'!AP:AP,'Combined P&L'!$C:$C,'P&L Overview'!$B9) -> 15.04071 | AO9: =SUMIFS('Combined P&L'!AQ:AQ,'Combined P&L'!$C:$C,'P&L Overview'!$B9) -> 16.16868 | AP9: =SUMIFS('Combined P&L'!AR:AR,'Combined P&L'!$C:$C,'P&L Overview'!$B9) -> 16.06915
B10: Onboarding | C10: =SUMIFS($L10:$AP10,$L$5:$AP$5,">"&C$42,$L$5:$AP$5,"<"&C$43) -> 44.0585 | D10: =SUMIFS($L10:$AP10,$L$5:$AP$5,">"&D$42,$L$5:$AP$5,"<"&D$43) -> 74.5193 | F10: =SUMIFS($L10:$AP10,$L$5:$AP$5,">"&F$42,$L$5:$AP$5,"<"&F$43) -> 42.25405 | G10: =SUMIFS($L10:$AP10,$L$5:$AP$5,">"&G$42,$L$5:$AP$5,"<"&G$43) -> 59.055 | I10: =SUMIFS($L10:$AP10,$L$5:$AP$5,">"&I$42,$L$5:$AP$5,"<"&I$43) -> 55.66055 | J10: =SUMIFS($L10:$AP10,$L$5:$AP$5,">"&J$42,$L$5:$AP$5,"<"&J$43) -> 91.65575 | L10: =SUMIFS('Combined P&L'!N:N,'Combined P&L'!$C:$C,'P&L Overview'!$B10) -> 5.465 | M10: =SUMIFS('Combined P&L'!O:O,'Combined P&L'!$C:$C,'P&L Overview'!$B10) -> 3.9 | N10: =SUMIFS('Combined P&L'!P:P,'Combined P&L'!$C:$C,'P&L Overview'!$B10) -> 2.755 | O10: =SUMIFS('Combined P&L'!Q:Q,'Combined P&L'!$C:$C,'P&L Overview'!$B10) -> 3.502 | P10: =SUMIFS('Combined P&L'!R:R,'Combined P&L'!$C:$C,'P&L Overview'!$B10) -> 4.659 | Q10: =SUMIFS('Combined P&L'!S:S,'Combined P&L'!$C:$C,'P&L Overview'!$B10) -> 3.937 | R10: =SUMIFS('Combined P&L'!T:T,'Combined P&L'!$C:$C,'P&L Overview'!$B10) -> 4.602 | S10: =SUMIFS('Combined P&L'!U:U,'Combined P&L'!$C:$C,'P&L Overview'!$B10) -> 4.738 | T10: =SUMIFS('Combined P&L'!V:V,'Combined P&L'!$C:$C,'P&L Overview'!$B10) -> 2.119 | U10: =SUMIFS('Combined P&L'!W:W,'Combined P&L'!$C:$C,'P&L Overview'!$B10) -> 2.064 | V10: =SUMIFS('Combined P&L'!X:X,'Combined P&L'!$C:$C,'P&L Overview'!$B10) -> 3.0125 | W10: =SUMIFS('Combined P&L'!Y:Y,'Combined P&L'!$C:$C,'P&L Overview'!$B10) -> 3.305 | X10: =SUMIFS('Combined P&L'!Z:Z,'Combined P&L'!$C:$C,'P&L Overview'!$B10) -> 3.079 | Y10: =SUMIFS('Combined P&L'!AA:AA,'Combined P&L'!$C:$C,'P&L Overview'!$B10) -> 0.7 | Z10: =SUMIFS('Combined P&L'!AB:AB,'Combined P&L'!$C:$C,'P&L Overview'!$B10) -> 10.43855 | AA10: =SUMIFS('Combined P&L'!AC:AC,'Combined P&L'!$C:$C,'P&L Overview'!$B10) -> 4.3 | AB10: =SUMIFS('Combined P&L'!AD:AD,'Combined P&L'!$C:$C,'P&L Overview'!$B10) -> 11.14 | AC10: =SUMIFS('Combined P&L'!AE:AE,'Combined P&L'!$C:$C,'P&L Overview'!$B10) -> 6.1625 | AD10: =SUMIFS('Combined P&L'!AF:AF,'Combined P&L'!$C:$C,'P&L Overview'!$B10) -> 6.434 | AE10: =SUMIFS('Combined P&L'!AG:AG,'Combined P&L'!$C:$C,'P&L Overview'!$B10) -> 3.965 | AF10: =SUMIFS('Combined P&L'!AH:AH,'Combined P&L'!$C:$C,'P&L Overview'!$B10) -> 3.92 | AG10: =SUMIFS('Combined P&L'!AI:AI,'Combined P&L'!$C:$C,'P&L Overview'!$B10) -> 9.1365 | AH10: =SUMIFS('Combined P&L'!AJ:AJ,'Combined P&L'!$C:$C,'P&L Overview'!$B10) -> 5.25375 | AI10: =SUMIFS('Combined P&L'!AK:AK,'Combined P&L'!$C:$C,'P&L Overview'!$B10) -> 9.99 | AJ10: =SUMIFS('Combined P&L'!AL:AL,'Combined P&L'!$C:$C,'P&L Overview'!$B10) -> 10.2105 | AK10: =SUMIFS('Combined P&L'!AM:AM,'Combined P&L'!$C:$C,'P&L Overview'!$B10) -> 6.675 | AL10: =SUMIFS('Combined P&L'!AN:AN,'Combined P&L'!$C:$C,'P&L Overview'!$B10) -> 9.099 | AM10: =SUMIFS('Combined P&L'!AO:AO,'Combined P&L'!$C:$C,'P&L Overview'!$B10) -> 8.9545 | AN10: =SUMIFS('Combined P&L'!AP:AP,'Combined P&L'!$C:$C,'P&L Overview'!$B10) -> 12.606 | AO10: =SUMIFS('Combined P&L'!AQ:AQ,'Combined P&L'!$C:$C,'P&L Overview'!$B10) -> 5.4115 | AP10: =SUMIFS('Combined P&L'!AR:AR,'Combined P&L'!$C:$C,'P&L Overview'!$B10) -> 6.0985
B11: STR Bill Pay | C11: =SUMIFS($L11:$AP11,$L$5:$AP$5,">"&C$42,$L$5:$AP$5,"<"&C$43) -> 0.06 | D11: =SUMIFS($L11:$AP11,$L$5:$AP$5,">"&D$42,$L$5:$AP$5,"<"&D$43) -> 36.6065 | F11: =SUMIFS($L11:$AP11,$L$5:$AP$5,">"&F$42,$L$5:$AP$5,"<"&F$43) -> 15.4915 | G11: =SUMIFS($L11:$AP11,$L$5:$AP$5,">"&G$42,$L$5:$AP$5,"<"&G$43) -> 45.13 | I11: =SUMIFS($L11:$AP11,$L$5:$AP$5,">"&I$42,$L$5:$AP$5,"<"&I$43) -> 11.6315 | J11: =SUMIFS($L11:$AP11,$L$5:$AP$5,">"&J$42,$L$5:$AP$5,"<"&J$43) -> 63.21 | L11: =SUMIFS('Combined P&L'!N:N,'Combined P&L'!$C:$C,'P&L Overview'!$B11) -> 0 | M11: =SUMIFS('Combined P&L'!O:O,'Combined P&L'!$C:$C,'P&L Overview'!$B11) -> 0 | N11: =SUMIFS('Combined P&L'!P:P,'Combined P&L'!$C:$C,'P&L Overview'!$B11) -> 0 | O11: =SUMIFS('Combined P&L'!Q:Q,'Combined P&L'!$C:$C,'P&L Overview'!$B11) -> 0 | P11: =SUMIFS('Combined P&L'!R:R,'Combined P&L'!$C:$C,'P&L Overview'!$B11) -> 0 | Q11: =SUMIFS('Combined P&L'!S:S,'Combined P&L'!$C:$C,'P&L Overview'!$B11) -> 0 | R11: =SUMIFS('Combined P&L'!T:T,'Combined P&L'!$C:$C,'P&L Overview'!$B11) -> 0 | S11: =SUMIFS('Combined P&L'!U:U,'Combined P&L'!$C:$C,'P&L Overview'!$B11) -> 0 | T11: =SUMIFS('Combined P&L'!V:V,'Combined P&L'!$C:$C,'P&L Overview'!$B11) -> 0 | U11: =SUMIFS('Combined P&L'!W:W,'Combined P&L'!$C:$C,'P&L Overview'!$B11) -> 0 | V11: =SUMIFS('Combined P&L'!X:X,'Combined P&L'!$C:$C,'P&L Overview'!$B11) -> 0 | W11: =SUMIFS('Combined P&L'!Y:Y,'Combined P&L'!$C:$C,'P&L Overview'!$B11) -> 0.06 | X11: =SUMIFS('Combined P&L'!Z:Z,'Combined P&L'!$C:$C,'P&L Overview'!$B11) -> 0.97 | Y11: =SUMIFS('Combined P&L'!AA:AA,'Combined P&L'!$C:$C,'P&L Overview'!$B11) -> 1.1 | Z11: =SUMIFS('Combined P&L'!AB:AB,'Combined P&L'!$C:$C,'P&L Overview'!$B11) -> 1.735 | AA11: =SUMIFS('Combined P&L'!AC:AC,'Combined P&L'!$C:$C,'P&L Overview'!$B11) -> 2.14 | AB11: =SUMIFS('Combined P&L'!AD:AD,'Combined P&L'!$C:$C,'P&L Overview'!$B11) -> 2.363 | AC11: =SUMIFS('Combined P&L'!AE:AE,'Combined P&L'!$C:$C,'P&L Overview'!$B11) -> 3.2635 | AD11: =SUMIFS('Combined P&L'!AF:AF,'Combined P&L'!$C:$C,'P&L Overview'!$B11) -> 3.92 | AE11: =SUMIFS('Combined P&L'!AG:AG,'Combined P&L'!$C:$C,'P&L Overview'!$B11) -> 3.905 | AF11: =SUMIFS('Combined P&L'!AH:AH,'Combined P&L'!$C:$C,'P&L Overview'!$B11) -> 3.78 | AG11: =SUMIFS('Combined P&L'!AI:AI,'Combined P&L'!$C:$C,'P&L Overview'!$B11) -> 3.795 | AH11: =SUMIFS('Combined P&L'!AJ:AJ,'Combined P&L'!$C:$C,'P&L Overview'!$B11) -> 4.33 | AI11: =SUMIFS('Combined P&L'!AK:AK,'Combined P&L'!$C:$C,'P&L Overview'!$B11) -> 5.305 | AJ11: =SUMIFS('Combined P&L'!AL:AL,'Combined P&L'!$C:$C,'P&L Overview'!$B11) -> 6.3 | AK11: =SUMIFS('Combined P&L'!AM:AM,'Combined P&L'!$C:$C,'P&L Overview'!$B11) -> 6.39 | AL11: =SUMIFS('Combined P&L'!AN:AN,'Combined P&L'!$C:$C,'P&L Overview'!$B11) -> 6.425 | AM11: =SUMIFS('Combined P&L'!AO:AO,'Combined P&L'!$C:$C,'P&L Overview'!$B11) -> 6.08 | AN11: =SUMIFS('Combined P&L'!AP:AP,'Combined P&L'!$C:$C,'P&L Overview'!$B11) -> 6.325 | AO11: =SUMIFS('Combined P&L'!AQ:AQ,'Combined P&L'!$C:$C,'P&L Overview'!$B11) -> 6.655 | AP11: =SUMIFS('Combined P&L'!AR:AR,'Combined P&L'!$C:$C,'P&L Overview'!$B11) -> 6.955
B12: Topkey Subscription | C12: =SUMIFS($L12:$AP12,$L$5:$AP$5,">"&C$42,$L$5:$AP$5,"<"&C$43) -> 0 | D12: =SUMIFS($L12:$AP12,$L$5:$AP$5,">"&D$42,$L$5:$AP$5,"<"&D$43) -> 9.947 | F12: =SUMIFS($L12:$AP12,$L$5:$AP$5,">"&F$42,$L$5:$AP$5,"<"&F$43) -> 0 | G12: =SUMIFS($L12:$AP12,$L$5:$AP$5,">"&G$42,$L$5:$AP$5,"<"&G$43) -> 45.086 | I12: =SUMIFS($L12:$AP12,$L$5:$AP$5,">"&I$42,$L$5:$AP$5,"<"&I$43) -> 0 | J12: =SUMIFS($L12:$AP12,$L$5:$AP$5,">"&J$42,$L$5:$AP$5,"<"&J$43) -> 47.13 | L12: =SUMIFS('Combined P&L'!N:N,'Combined P&L'!$C:$C,'P&L Overview'!$B12) -> 0 | M12: =SUMIFS('Combined P&L'!O:O,'Combined P&L'!$C:$C,'P&L Overview'!$B12) -> 0 | N12: =SUMIFS('Combined P&L'!P:P,'Combined P&L'!$C:$C,'P&L Overview'!$B12) -> 0 | O12: =SUMIFS('Combined P&L'!Q:Q,'Combined P&L'!$C:$C,'P&L Overview'!$B12) -> 0 | P12: =SUMIFS('Combined P&L'!R:R,'Combined P&L'!$C:$C,'P&L Overview'!$B12) -> 0 | Q12: =SUMIFS('Combined P&L'!S:S,'Combined P&L'!$C:$C,'P&L Overview'!$B12) -> 0 | R12: =SUMIFS('Combined P&L'!T:T,'Combined P&L'!$C:$C,'P&L Overview'!$B12) -> 0 | S12: =SUMIFS('Combined P&L'!U:U,'Combined P&L'!$C:$C,'P&L Overview'!$B12) -> 0 | T12: =SUMIFS('Combined P&L'!V:V,'Combined P&L'!$C:$C,'P&L Overview'!$B12) -> 0 | U12: =SUMIFS('Combined P&L'!W:W,'Combined P&L'!$C:$C,'P&L Overview'!$B12) -> 0 | V12: =SUMIFS('Combined P&L'!X:X,'Combined P&L'!$C:$C,'P&L Overview'!$B12) -> 0 | W12: =SUMIFS('Combined P&L'!Y:Y,'Combined P&L'!$C:$C,'P&L Overview'!$B12) -> 0 | X12: =SUMIFS('Combined P&L'!Z:Z,'Combined P&L'!$C:$C,'P&L Overview'!$B12) -> 0 | Y12: =SUMIFS('Combined P&L'!AA:AA,'Combined P&L'!$C:$C,'P&L Overview'!$B12) -> 0 | Z12: =SUMIFS('Combined P&L'!AB:AB,'Combined P&L'!$C:$C,'P&L Overview'!$B12) -> 0 | AA12: =SUMIFS('Combined P&L'!AC:AC,'Combined P&L'!$C:$C,'P&L Overview'!$B12) -> 0 | AB12: =SUMIFS('Combined P&L'!AD:AD,'Combined P&L'!$C:$C,'P&L Overview'!$B12) -> 0 | AC12: =SUMIFS('Combined P&L'!AE:AE,'Combined P&L'!$C:$C,'P&L Overview'!$B12) -> 0 | AD12: =SUMIFS('Combined P&L'!AF:AF,'Combined P&L'!$C:$C,'P&L Overview'!$B12) -> 0 | AE12: =SUMIFS('Combined P&L'!AG:AG,'Combined P&L'!$C:$C,'P&L Overview'!$B12) -> 0 | AF12: =SUMIFS('Combined P&L'!AH:AH,'Combined P&L'!$C:$C,'P&L Overview'!$B12) -> 0.52 | AG12: =SUMIFS('Combined P&L'!AI:AI,'Combined P&L'!$C:$C,'P&L Overview'!$B12) -> 2.357 | AH12: =SUMIFS('Combined P&L'!AJ:AJ,'Combined P&L'!$C:$C,'P&L Overview'!$B12) -> 2.811 | AI12: =SUMIFS('Combined P&L'!AK:AK,'Combined P&L'!$C:$C,'P&L Overview'!$B12) -> 4.259 | AJ12: =SUMIFS('Combined P&L'!AL:AL,'Combined P&L'!$C:$C,'P&L Overview'!$B12) -> 5.254 | AK12: =SUMIFS('Combined P&L'!AM:AM,'Combined P&L'!$C:$C,'P&L Overview'!$B12) -> 5.652 | AL12: =SUMIFS('Combined P&L'!AN:AN,'Combined P&L'!$C:$C,'P&L Overview'!$B12) -> 5.324 | AM12: =SUMIFS('Combined P&L'!AO:AO,'Combined P&L'!$C:$C,'P&L Overview'!$B12) -> 6.321 | AN12: =SUMIFS('Combined P&L'!AP:AP,'Combined P&L'!$C:$C,'P&L Overview'!$B12) -> 6.959 | AO12: =SUMIFS('Combined P&L'!AQ:AQ,'Combined P&L'!$C:$C,'P&L Overview'!$B12) -> 7.673 | AP12: =SUMIFS('Combined P&L'!AR:AR,'Combined P&L'!$C:$C,'P&L Overview'!$B12) -> 7.903
B13: Controller Services | C13: =SUMIFS($L13:$AP13,$L$5:$AP$5,">"&C$42,$L$5:$AP$5,"<"&C$43) -> 13.75 | D13: =SUMIFS($L13:$AP13,$L$5:$AP$5,">"&D$42,$L$5:$AP$5,"<"&D$43) -> 46.4 | F13: =SUMIFS($L13:$AP13,$L$5:$AP$5,">"&F$42,$L$5:$AP$5,"<"&F$43) -> 31.5 | G13: =SUMIFS($L13:$AP13,$L$5:$AP$5,">"&G$42,$L$5:$AP$5,"<"&G$43) -> 24.25 | I13: =SUMIFS($L13:$AP13,$L$5:$AP$5,">"&I$42,$L$5:$AP$5,"<"&I$43) -> 41.25 | J13: =SUMIFS($L13:$AP13,$L$5:$AP$5,">"&J$42,$L$5:$AP$5,"<"&J$43) -> 39.65 | L13: =SUMIFS('Combined P&L'!N:N,'Combined P&L'!$C:$C,'P&L Overview'!$B13) -> 0 | M13: =SUMIFS('Combined P&L'!O:O,'Combined P&L'!$C:$C,'P&L Overview'!$B13) -> 0 | N13: =SUMIFS('Combined P&L'!P:P,'Combined P&L'!$C:$C,'P&L Overview'!$B13) -> 0 | O13: =SUMIFS('Combined P&L'!Q:Q,'Combined P&L'!$C:$C,'P&L Overview'!$B13) -> 0 | P13: =SUMIFS('Combined P&L'!R:R,'Combined P&L'!$C:$C,'P&L Overview'!$B13) -> 0 | Q13: =SUMIFS('Combined P&L'!S:S,'Combined P&L'!$C:$C,'P&L Overview'!$B13) -> 0 | R13: =SUMIFS('Combined P&L'!T:T,'Combined P&L'!$C:$C,'P&L Overview'!$B13) -> 1.25 | S13: =SUMIFS('Combined P&L'!U:U,'Combined P&L'!$C:$C,'P&L Overview'!$B13) -> 1.25 | T13: =SUMIFS('Combined P&L'!V:V,'Combined P&L'!$C:$C,'P&L Overview'!$B13) -> 1.25 | U13: =SUMIFS('Combined P&L'!W:W,'Combined P&L'!$C:$C,'P&L Overview'!$B13) -> 1.25 | V13: =SUMIFS('Combined P&L'!X:X,'Combined P&L'!$C:$C,'P&L Overview'!$B13) -> 5.75 | W13: =SUMIFS('Combined P&L'!Y:Y,'Combined P&L'!$C:$C,'P&L Overview'!$B13) -> 3 | X13: =SUMIFS('Combined P&L'!Z:Z,'Combined P&L'!$C:$C,'P&L Overview'!$B13) -> 4.45 | Y13: =SUMIFS('Combined P&L'!AA:AA,'Combined P&L'!$C:$C,'P&L Overview'!$B13) -> 3.45 | Z13: =SUMIFS('Combined P&L'!AB:AB,'Combined P&L'!$C:$C,'P&L Overview'!$B13) -> 3.45 | AA13: =SUMIFS('Combined P&L'!AC:AC,'Combined P&L'!$C:$C,'P&L Overview'!$B13) -> 5.95 | AB13: =SUMIFS('Combined P&L'!AD:AD,'Combined P&L'!$C:$C,'P&L Overview'!$B13) -> 5.2 | AC13: =SUMIFS('Combined P&L'!AE:AE,'Combined P&L'!$C:$C,'P&L Overview'!$B13) -> 5 | AD13: =SUMIFS('Combined P&L'!AF:AF,'Combined P&L'!$C:$C,'P&L Overview'!$B13) -> 4 | AE13: =SUMIFS('Combined P&L'!AG:AG,'Combined P&L'!$C:$C,'P&L Overview'!$B13) -> 2.95 | AF13: =SUMIFS('Combined P&L'!AH:AH,'Combined P&L'!$C:$C,'P&L Overview'!$B13) -> 3.025 | AG13: =SUMIFS('Combined P&L'!AI:AI,'Combined P&L'!$C:$C,'P&L Overview'!$B13) -> 3.025 | AH13: =SUMIFS('Combined P&L'!AJ:AJ,'Combined P&L'!$C:$C,'P&L Overview'!$B13) -> 2.95 | AI13: =SUMIFS('Combined P&L'!AK:AK,'Combined P&L'!$C:$C,'P&L Overview'!$B13) -> 2.95 | AJ13: =SUMIFS('Combined P&L'!AL:AL,'Combined P&L'!$C:$C,'P&L Overview'!$B13) -> 2.75 | AK13: =SUMIFS('Combined P&L'!AM:AM,'Combined P&L'!$C:$C,'P&L Overview'!$B13) -> 3.5 | AL13: =SUMIFS('Combined P&L'!AN:AN,'Combined P&L'!$C:$C,'P&L Overview'!$B13) -> 2.75 | AM13: =SUMIFS('Combined P&L'!AO:AO,'Combined P&L'!$C:$C,'P&L Overview'!$B13) -> 4.75 | AN13: =SUMIFS('Combined P&L'!AP:AP,'Combined P&L'!$C:$C,'P&L Overview'!$B13) -> 3.5 | AO13: =SUMIFS('Combined P&L'!AQ:AQ,'Combined P&L'!$C:$C,'P&L Overview'!$B13) -> 3.5 | AP13: =SUMIFS('Combined P&L'!AR:AR,'Combined P&L'!$C:$C,'P&L Overview'!$B13) -> 3.5
B14: Historical Cleanup | C14: =SUMIFS($L14:$AP14,$L$5:$AP$5,">"&C$42,$L$5:$AP$5,"<"&C$43) -> 17.624 | D14: =SUMIFS($L14:$AP14,$L$5:$AP$5,">"&D$42,$L$5:$AP$5,"<"&D$43) -> 5.03375 | F14: =SUMIFS($L14:$AP14,$L$5:$AP$5,">"&F$42,$L$5:$AP$5,"<"&F$43) -> 4.43875 | G14: =SUMIFS($L14:$AP14,$L$5:$AP$5,">"&G$42,$L$5:$AP$5,"<"&G$43) -> 0 | I14: =SUMIFS($L14:$AP14,$L$5:$AP$5,">"&I$42,$L$5:$AP$5,"<"&I$43) -> 14.30525 | J14: =SUMIFS($L14:$AP14,$L$5:$AP$5,">"&J$42,$L$5:$AP$5,"<"&J$43) -> 0.595 | L14: =SUMIFS('Combined P&L'!N:N,'Combined P&L'!$C:$C,'P&L Overview'!$B14) -> 1.2 | M14: =SUMIFS('Combined P&L'!O:O,'Combined P&L'!$C:$C,'P&L Overview'!$B14) -> 1.7625 | N14: =SUMIFS('Combined P&L'!P:P,'Combined P&L'!$C:$C,'P&L Overview'!$B14) -> 0.66 | O14: =SUMIFS('Combined P&L'!Q:Q,'Combined P&L'!$C:$C,'P&L Overview'!$B14) -> 0.395 | P14: =SUMIFS('Combined P&L'!R:R,'Combined P&L'!$C:$C,'P&L Overview'!$B14) -> 2.465 | Q14: =SUMIFS('Combined P&L'!S:S,'Combined P&L'!$C:$C,'P&L Overview'!$B14) -> 1.275 | R14: =SUMIFS('Combined P&L'!T:T,'Combined P&L'!$C:$C,'P&L Overview'!$B14) -> 1.4625 | S14: =SUMIFS('Combined P&L'!U:U,'Combined P&L'!$C:$C,'P&L Overview'!$B14) -> 0 | T14: =SUMIFS('Combined P&L'!V:V,'Combined P&L'!$C:$C,'P&L Overview'!$B14) -> 1.14525 | U14: =SUMIFS('Combined P&L'!W:W,'Combined P&L'!$C:$C,'P&L Overview'!$B14) -> 1.35525 | V14: =SUMIFS('Combined P&L'!X:X,'Combined P&L'!$C:$C,'P&L Overview'!$B14) -> 1.9035 | W14: =SUMIFS('Combined P&L'!Y:Y,'Combined P&L'!$C:$C,'P&L Overview'!$B14) -> 4 | X14: =SUMIFS('Combined P&L'!Z:Z,'Combined P&L'!$C:$C,'P&L Overview'!$B14) -> 1.08375 | Y14: =SUMIFS('Combined P&L'!AA:AA,'Combined P&L'!$C:$C,'P&L Overview'!$B14) -> 2 | Z14: =SUMIFS('Combined P&L'!AB:AB,'Combined P&L'!$C:$C,'P&L Overview'!$B14) -> 1.355 | AA14: =SUMIFS('Combined P&L'!AC:AC,'Combined P&L'!$C:$C,'P&L Overview'!$B14) -> 0 | AB14: =SUMIFS('Combined P&L'!AD:AD,'Combined P&L'!$C:$C,'P&L Overview'!$B14) -> 0 | AC14: =SUMIFS('Combined P&L'!AE:AE,'Combined P&L'!$C:$C,'P&L Overview'!$B14) -> 0 | AD14: =SUMIFS('Combined P&L'!AF:AF,'Combined P&L'!$C:$C,'P&L Overview'!$B14) -> 0 | AE14: =SUMIFS('Combined P&L'!AG:AG,'Combined P&L'!$C:$C,'P&L Overview'!$B14) -> 0 | AF14: =SUMIFS('Combined P&L'!AH:AH,'Combined P&L'!$C:$C,'P&L Overview'!$B14) -> 0 | AG14: =SUMIFS('Combined P&L'!AI:AI,'Combined P&L'!$C:$C,'P&L Overview'!$B14) -> 0.595 | AH14: =SUMIFS('Combined P&L'!AJ:AJ,'Combined P&L'!$C:$C,'P&L Overview'!$B14) -> 0 | AI14: =SUMIFS('Combined P&L'!AK:AK,'Combined P&L'!$C:$C,'P&L Overview'!$B14) -> 0 | AJ14: =SUMIFS('Combined P&L'!AL:AL,'Combined P&L'!$C:$C,'P&L Overview'!$B14) -> 0 | AK14: =SUMIFS('Combined P&L'!AM:AM,'Combined P&L'!$C:$C,'P&L Overview'!$B14) -> 0 | AL14: =SUMIFS('Combined P&L'!AN:AN,'Combined P&L'!$C:$C,'P&L Overview'!$B14) -> 0 | AM14: =SUMIFS('Combined P&L'!AO:AO,'Combined P&L'!$C:$C,'P&L Overview'!$B14) -> 0 | AN14: =SUMIFS('Combined P&L'!AP:AP,'Combined P&L'!$C:$C,'P&L Overview'!$B14) -> 0 | AO14: =SUMIFS('Combined P&L'!AQ:AQ,'Combined P&L'!$C:$C,'P&L Overview'!$B14) -> 0 | AP14: =SUMIFS('Combined P&L'!AR:AR,'Combined P&L'!$C:$C,'P&L Overview'!$B14) -> 0
B15: Total Recurring Revenue | C15: =SUM(C7:C14) -> 1094.3157 | D15: =SUM(D7:D14) -> 1827.8494 | F15: =SUM(F7:F14) -> 958.8909 | G15: =SUM(G7:G14) -> 1600.0675 | I15: =SUM(I7:I14) -> 1414.7118 | J15: =SUM(J7:J14) -> 2371.7313 | L15: =SUM(L7:L14) -> 73.3495 | M15: =SUM(M7:M14) -> 74.7445 | N15: =SUM(N7:N14) -> 77.996 | O15: =SUM(O7:O14) -> 83.2127 | P15: =SUM(P7:P14) -> 86.60415 | Q15: =SUM(Q7:Q14) -> 88.544 | R15: =SUM(R7:R14) -> 93.21675 | S15: =SUM(S7:S14) -> 96.77535 | ... AP15: =SUM(AP7:AP14) -> 251.33865
B17: 1099 Filing | C17: =SUMIFS($L17:$AP17,$L$5:$AP$5,">"&C$42,$L$5:$AP$5,"<"&C$43) -> 10.475 | D17: =SUMIFS($L17:$AP17,$L$5:$AP$5,">"&D$42,$L$5:$AP$5,"<"&D$43) -> 23.55 | F17: =SUMIFS($L17:$AP17,$L$5:$AP$5,">"&F$42,$L$5:$AP$5,"<"&F$43) -> 23.49 | G17: =SUMIFS($L17:$AP17,$L$5:$AP$5,">"&G$42,$L$5:$AP$5,"<"&G$43) -> 38.7015 | I17: =SUMIFS($L17:$AP17,$L$5:$AP$5,">"&I$42,$L$5:$AP$5,"<"&I$43) -> 23.52 | J17: =SUMIFS($L17:$AP17,$L$5:$AP$5,">"&J$42,$L$5:$AP$5,"<"&J$43) -> 38.7615 | L17: =SUMIFS('Combined P&L'!N:N,'Combined P&L'!$C:$C,'P&L Overview'!$B17) -> 6.945 | M17: =SUMIFS('Combined P&L'!O:O,'Combined P&L'!$C:$C,'P&L Overview'!$B17) -> 3.38 | N17: =SUMIFS('Combined P&L'!P:P,'Combined P&L'!$C:$C,'P&L Overview'!$B17) -> 0.045 | O17: =SUMIFS('Combined P&L'!Q:Q,'Combined P&L'!$C:$C,'P&L Overview'!$B17) -> 0.06 | P17: =SUMIFS('Combined P&L'!R:R,'Combined P&L'!$C:$C,'P&L Overview'!$B17) -> 0.015 | Q17: =SUMIFS('Combined P&L'!S:S,'Combined P&L'!$C:$C,'P&L Overview'!$B17) -> 0 | R17: =SUMIFS('Combined P&L'!T:T,'Combined P&L'!$C:$C,'P&L Overview'!$B17) -> 0 | S17: =SUMIFS('Combined P&L'!U:U,'Combined P&L'!$C:$C,'P&L Overview'!$B17) -> 0.015 | T17: =SUMIFS('Combined P&L'!V:V,'Combined P&L'!$C:$C,'P&L Overview'!$B17) -> 0 | U17: =SUMIFS('Combined P&L'!W:W,'Combined P&L'!$C:$C,'P&L Overview'!$B17) -> 0 | V17: =SUMIFS('Combined P&L'!X:X,'Combined P&L'!$C:$C,'P&L Overview'!$B17) -> 0.015 | W17: =SUMIFS('Combined P&L'!Y:Y,'Combined P&L'!$C:$C,'P&L Overview'!$B17) -> 0 | X17: =SUMIFS('Combined P&L'!Z:Z,'Combined P&L'!$C:$C,'P&L Overview'!$B17) -> 13.485 | Y17: =SUMIFS('Combined P&L'!AA:AA,'Combined P&L'!$C:$C,'P&L Overview'!$B17) -> 9.915 | Z17: =SUMIFS('Combined P&L'!AB:AB,'Combined P&L'!$C:$C,'P&L Overview'!$B17) -> 0.06 | AA17: =SUMIFS('Combined P&L'!AC:AC,'Combined P&L'!$C:$C,'P&L Overview'!$B17) -> 0.03 | AB17: =SUMIFS('Combined P&L'!AD:AD,'Combined P&L'!$C:$C,'P&L Overview'!$B17) -> 0 | AC17: =SUMIFS('Combined P&L'!AE:AE,'Combined P&L'!$C:$C,'P&L Overview'!$B17) -> 0 | AD17: =SUMIFS('Combined P&L'!AF:AF,'Combined P&L'!$C:$C,'P&L Overview'!$B17) -> 0 | AE17: =SUMIFS('Combined P&L'!AG:AG,'Combined P&L'!$C:$C,'P&L Overview'!$B17) -> 0.03 | AF17: =SUMIFS('Combined P&L'!AH:AH,'Combined P&L'!$C:$C,'P&L Overview'!$B17) -> 0.03 | AG17: =SUMIFS('Combined P&L'!AI:AI,'Combined P&L'!$C:$C,'P&L Overview'!$B17) -> 0 | AH17: =SUMIFS('Combined P&L'!AJ:AJ,'Combined P&L'!$C:$C,'P&L Overview'!$B17) -> 0 | AI17: =SUMIFS('Combined P&L'!AK:AK,'Combined P&L'!$C:$C,'P&L Overview'!$B17) -> 0 | AJ17: =SUMIFS('Combined P&L'!AL:AL,'Combined P&L'!$C:$C,'P&L Overview'!$B17) -> 6.105 | AK17: =SUMIFS('Combined P&L'!AM:AM,'Combined P&L'!$C:$C,'P&L Overview'!$B17) -> 31.1565 | AL17: =SUMIFS('Combined P&L'!AN:AN,'Combined P&L'!$C:$C,'P&L Overview'!$B17) -> 1.26 | AM17: =SUMIFS('Combined P&L'!AO:AO,'Combined P&L'!$C:$C,'P&L Overview'!$B17) -> 0.18 | AN17: =SUMIFS('Combined P&L'!AP:AP,'Combined P&L'!$C:$C,'P&L Overview'!$B17) -> 0 | AO17: =SUMIFS('Combined P&L'!AQ:AQ,'Combined P&L'!$C:$C,'P&L Overview'!$B17) -> 0 | AP17: =SUMIFS('Combined P&L'!AR:AR,'Combined P&L'!$C:$C,'P&L Overview'!$B17) -> 0
B18: Income Tax | C18: =SUMIFS($L18:$AP18,$L$5:$AP$5,">"&C$42,$L$5:$AP$5,"<"&C$43) -> 0 | D18: =SUMIFS($L18:$AP18,$L$5:$AP$5,">"&D$42,$L$5:$AP$5,"<"&D$43) -> 3.4 | F18: =SUMIFS($L18:$AP18,$L$5:$AP$5,">"&F$42,$L$5:$AP$5,"<"&F$43) -> 0 | G18: =SUMIFS($L18:$AP18,$L$5:$AP$5,">"&G$42,$L$5:$AP$5,"<"&G$43) -> 23.915 | I18: =SUMIFS($L18:$AP18,$L$5:$AP$5,">"&I$42,$L$5:$AP$5,"<"&I$43) -> 0 | J18: =SUMIFS($L18:$AP18,$L$5:$AP$5,">"&J$42,$L$5:$AP$5,"<"&J$43) -> 27.315 | L18: =SUMIFS('Combined P&L'!N:N,'Combined P&L'!$C:$C,'P&L Overview'!$B18) -> 0 | M18: =SUMIFS('Combined P&L'!O:O,'Combined P&L'!$C:$C,'P&L Overview'!$B18) -> 0 | N18: =SUMIFS('Combined P&L'!P:P,'Combined P&L'!$C:$C,'P&L Overview'!$B18) -> 0 | O18: =SUMIFS('Combined P&L'!Q:Q,'Combined P&L'!$C:$C,'P&L Overview'!$B18) -> 0 | P18: =SUMIFS('Combined P&L'!R:R,'Combined P&L'!$C:$C,'P&L Overview'!$B18) -> 0 | Q18: =SUMIFS('Combined P&L'!S:S,'Combined P&L'!$C:$C,'P&L Overview'!$B18) -> 0 | R18: =SUMIFS('Combined P&L'!T:T,'Combined P&L'!$C:$C,'P&L Overview'!$B18) -> 0 | S18: =SUMIFS('Combined P&L'!U:U,'Combined P&L'!$C:$C,'P&L Overview'!$B18) -> 0 | T18: =SUMIFS('Combined P&L'!V:V,'Combined P&L'!$C:$C,'P&L Overview'!$B18) -> 0 | U18: =SUMIFS('Combined P&L'!W:W,'Combined P&L'!$C:$C,'P&L Overview'!$B18) -> 0 | V18: =SUMIFS('Combined P&L'!X:X,'Combined P&L'!$C:$C,'P&L Overview'!$B18) -> 0 | W18: =SUMIFS('Combined P&L'!Y:Y,'Combined P&L'!$C:$C,'P&L Overview'!$B18) -> 0 | X18: =SUMIFS('Combined P&L'!Z:Z,'Combined P&L'!$C:$C,'P&L Overview'!$B18) -> 0 | Y18: =SUMIFS('Combined P&L'!AA:AA,'Combined P&L'!$C:$C,'P&L Overview'!$B18) -> 0 | Z18: =SUMIFS('Combined P&L'!AB:AB,'Combined P&L'!$C:$C,'P&L Overview'!$B18) -> 0 | AA18: =SUMIFS('Combined P&L'!AC:AC,'Combined P&L'!$C:$C,'P&L Overview'!$B18) -> 0 | AB18: =SUMIFS('Combined P&L'!AD:AD,'Combined P&L'!$C:$C,'P&L Overview'!$B18) -> 0 | AC18: =SUMIFS('Combined P&L'!AE:AE,'Combined P&L'!$C:$C,'P&L Overview'!$B18) -> 0 | AD18: =SUMIFS('Combined P&L'!AF:AF,'Combined P&L'!$C:$C,'P&L Overview'!$B18) -> 0 | AE18: =SUMIFS('Combined P&L'!AG:AG,'Combined P&L'!$C:$C,'P&L Overview'!$B18) -> 0 | AF18: =SUMIFS('Combined P&L'!AH:AH,'Combined P&L'!$C:$C,'P&L Overview'!$B18) -> 0.875 | AG18: =SUMIFS('Combined P&L'!AI:AI,'Combined P&L'!$C:$C,'P&L Overview'!$B18) -> 1.65 | AH18: =SUMIFS('Combined P&L'!AJ:AJ,'Combined P&L'!$C:$C,'P&L Overview'!$B18) -> 0 | AI18: =SUMIFS('Combined P&L'!AK:AK,'Combined P&L'!$C:$C,'P&L Overview'!$B18) -> 0.875 | AJ18: =SUMIFS('Combined P&L'!AL:AL,'Combined P&L'!$C:$C,'P&L Overview'!$B18) -> 0 | AK18: =SUMIFS('Combined P&L'!AM:AM,'Combined P&L'!$C:$C,'P&L Overview'!$B18) -> 0 | AL18: =SUMIFS('Combined P&L'!AN:AN,'Combined P&L'!$C:$C,'P&L Overview'!$B18) -> 14.19 | AM18: =SUMIFS('Combined P&L'!AO:AO,'Combined P&L'!$C:$C,'P&L Overview'!$B18) -> 6.625 | AN18: =SUMIFS('Combined P&L'!AP:AP,'Combined P&L'!$C:$C,'P&L Overview'!$B18) -> 0 | AO18: =SUMIFS('Combined P&L'!AQ:AQ,'Combined P&L'!$C:$C,'P&L Overview'!$B18) -> 3.1 | AP18: =SUMIFS('Combined P&L'!AR:AR,'Combined P&L'!$C:$C,'P&L Overview'!$B18) -> 0
B19: Profit Share | C19: =SUMIFS($L19:$AP19,$L$5:$AP$5,">"&C$42,$L$5:$AP$5,"<"&C$43) -> 6.2004 | D19: =SUMIFS($L19:$AP19,$L$5:$AP$5,">"&D$42,$L$5:$AP$5,"<"&D$43) -> 23.26179 | F19: =SUMIFS($L19:$AP19,$L$5:$AP$5,">"&F$42,$L$5:$AP$5,"<"&F$43) -> 14.50495 | G19: =SUMIFS($L19:$AP19,$L$5:$AP$5,">"&G$42,$L$5:$AP$5,"<"&G$43) -> 8.07938 | I19: =SUMIFS($L19:$AP19,$L$5:$AP$5,">"&I$42,$L$5:$AP$5,"<"&I$43) -> 17.94788 | J19: =SUMIFS($L19:$AP19,$L$5:$AP$5,">"&J$42,$L$5:$AP$5,"<"&J$43) -> 17.79609 | L19: =SUMIFS('Combined P&L'!N:N,'Combined P&L'!$C:$C,'P&L Overview'!$B19) -> 0.0686 | M19: =SUMIFS('Combined P&L'!O:O,'Combined P&L'!$C:$C,'P&L Overview'!$B19) -> 0.1312 | N19: =SUMIFS('Combined P&L'!P:P,'Combined P&L'!$C:$C,'P&L Overview'!$B19) -> 0.0712 | O19: =SUMIFS('Combined P&L'!Q:Q,'Combined P&L'!$C:$C,'P&L Overview'!$B19) -> 0.0556 | P19: =SUMIFS('Combined P&L'!R:R,'Combined P&L'!$C:$C,'P&L Overview'!$B19) -> 0.577 | Q19: =SUMIFS('Combined P&L'!S:S,'Combined P&L'!$C:$C,'P&L Overview'!$B19) -> 0.8068 | R19: =SUMIFS('Combined P&L'!T:T,'Combined P&L'!$C:$C,'P&L Overview'!$B19) -> 0.6656 | S19: =SUMIFS('Combined P&L'!U:U,'Combined P&L'!$C:$C,'P&L Overview'!$B19) -> 0.8264 | T19: =SUMIFS('Combined P&L'!V:V,'Combined P&L'!$C:$C,'P&L Overview'!$B19) -> 1.3808 | U19: =SUMIFS('Combined P&L'!W:W,'Combined P&L'!$C:$C,'P&L Overview'!$B19) -> 0.8604 | V19: =SUMIFS('Combined P&L'!X:X,'Combined P&L'!$C:$C,'P&L Overview'!$B19) -> 0.51 | W19: =SUMIFS('Combined P&L'!Y:Y,'Combined P&L'!$C:$C,'P&L Overview'!$B19) -> 0.2468 | X19: =SUMIFS('Combined P&L'!Z:Z,'Combined P&L'!$C:$C,'P&L Overview'!$B19) -> 7.3584 | Y19: =SUMIFS('Combined P&L'!AA:AA,'Combined P&L'!$C:$C,'P&L Overview'!$B19) -> 1.29335 | Z19: =SUMIFS('Combined P&L'!AB:AB,'Combined P&L'!$C:$C,'P&L Overview'!$B19) -> 0.96833 | AA19: =SUMIFS('Combined P&L'!AC:AC,'Combined P&L'!$C:$C,'P&L Overview'!$B19) -> 1.1656 | AB19: =SUMIFS('Combined P&L'!AD:AD,'Combined P&L'!$C:$C,'P&L Overview'!$B19) -> 0.96093 | AC19: =SUMIFS('Combined P&L'!AE:AE,'Combined P&L'!$C:$C,'P&L Overview'!$B19) -> 1.71127 | AD19: =SUMIFS('Combined P&L'!AF:AF,'Combined P&L'!$C:$C,'P&L Overview'!$B19) -> 1.04707 | AE19: =SUMIFS('Combined P&L'!AG:AG,'Combined P&L'!$C:$C,'P&L Overview'!$B19) -> 2.04088 | AF19: =SUMIFS('Combined P&L'!AH:AH,'Combined P&L'!$C:$C,'P&L Overview'!$B19) -> 1.13621 | AG19: =SUMIFS('Combined P&L'!AI:AI,'Combined P&L'!$C:$C,'P&L Overview'!$B19) -> 2.01424 | AH19: =SUMIFS('Combined P&L'!AJ:AJ,'Combined P&L'!$C:$C,'P&L Overview'!$B19) -> 1.29758 | AI19: =SUMIFS('Combined P&L'!AK:AK,'Combined P&L'!$C:$C,'P&L Overview'!$B19) -> 2.26793 | AJ19: =SUMIFS('Combined P&L'!AL:AL,'Combined P&L'!$C:$C,'P&L Overview'!$B19) -> 2.67784 | AK19: =SUMIFS('Combined P&L'!AM:AM,'Combined P&L'!$C:$C,'P&L Overview'!$B19) -> 2.35401 | AL19: =SUMIFS('Combined P&L'!AN:AN,'Combined P&L'!$C:$C,'P&L Overview'!$B19) -> 0.2276 | AM19: =SUMIFS('Combined P&L'!AO:AO,'Combined P&L'!$C:$C,'P&L Overview'!$B19) -> 1.47836 | AN19: =SUMIFS('Combined P&L'!AP:AP,'Combined P&L'!$C:$C,'P&L Overview'!$B19) -> 0.66824 | AO19: =SUMIFS('Combined P&L'!AQ:AQ,'Combined P&L'!$C:$C,'P&L Overview'!$B19) -> 0.58613 | AP19: =SUMIFS('Combined P&L'!AR:AR,'Combined P&L'!$C:$C,'P&L Overview'!$B19) -> 0.0872
B20: Billable Expense Income | C20: =SUMIFS($L20:$AP20,$L$5:$AP$5,">"&C$42,$L$5:$AP$5,"<"&C$43) -> 0.3747 | D20: =SUMIFS($L20:$AP20,$L$5:$AP$5,">"&D$42,$L$5:$AP$5,"<"&D$43) -> 1.12194 | F20: =SUMIFS($L20:$AP20,$L$5:$AP$5,">"&F$42,$L$5:$AP$5,"<"&F$43) -> 0.78725 | G20: =SUMIFS($L20:$AP20,$L$5:$AP$5,">"&G$42,$L$5:$AP$5,"<"&G$43) -> 0.25783 | I20: =SUMIFS($L20:$AP20,$L$5:$AP$5,">"&I$42,$L$5:$AP$5,"<"&I$43) -> 0.79724 | J20: =SUMIFS($L20:$AP20,$L$5:$AP$5,">"&J$42,$L$5:$AP$5,"<"&J$43) -> 0.88223 | L20: =SUMIFS('Combined P&L'!N:N,'Combined P&L'!$C:$C,'P&L Overview'!$B20) -> 0.05 | M20: =SUMIFS('Combined P&L'!O:O,'Combined P&L'!$C:$C,'P&L Overview'!$B20) -> 0 | N20: =SUMIFS('Combined P&L'!P:P,'Combined P&L'!$C:$C,'P&L Overview'!$B20) -> 0 | O20: =SUMIFS('Combined P&L'!Q:Q,'Combined P&L'!$C:$C,'P&L Overview'!$B20) -> 0.025 | P20: =SUMIFS('Combined P&L'!R:R,'Combined P&L'!$C:$C,'P&L Overview'!$B20) -> 0 | Q20: =SUMIFS('Combined P&L'!S:S,'Combined P&L'!$C:$C,'P&L Overview'!$B20) -> 0 | R20: =SUMIFS('Combined P&L'!T:T,'Combined P&L'!$C:$C,'P&L Overview'!$B20) -> 0.2997 | S20: =SUMIFS('Combined P&L'!U:U,'Combined P&L'!$C:$C,'P&L Overview'!$B20) -> 0 | T20: =SUMIFS('Combined P&L'!V:V,'Combined P&L'!$C:$C,'P&L Overview'!$B20) -> 0 | U20: =SUMIFS('Combined P&L'!W:W,'Combined P&L'!$C:$C,'P&L Overview'!$B20) -> 0 | V20: =SUMIFS('Combined P&L'!X:X,'Combined P&L'!$C:$C,'P&L Overview'!$B20) -> 0 | W20: =SUMIFS('Combined P&L'!Y:Y,'Combined P&L'!$C:$C,'P&L Overview'!$B20) -> 0 | X20: =SUMIFS('Combined P&L'!Z:Z,'Combined P&L'!$C:$C,'P&L Overview'!$B20) -> 0.025 | Y20: =SUMIFS('Combined P&L'!AA:AA,'Combined P&L'!$C:$C,'P&L Overview'!$B20) -> 0.3996 | Z20: =SUMIFS('Combined P&L'!AB:AB,'Combined P&L'!$C:$C,'P&L Overview'!$B20) -> 0 | AA20: =SUMIFS('Combined P&L'!AC:AC,'Combined P&L'!$C:$C,'P&L Overview'!$B20) -> 0 | AB20: =SUMIFS('Combined P&L'!AD:AD,'Combined P&L'!$C:$C,'P&L Overview'!$B20) -> 0.07294 | AC20: =SUMIFS('Combined P&L'!AE:AE,'Combined P&L'!$C:$C,'P&L Overview'!$B20) -> 0 | AD20: =SUMIFS('Combined P&L'!AF:AF,'Combined P&L'!$C:$C,'P&L Overview'!$B20) -> 0.28971 | AE20: =SUMIFS('Combined P&L'!AG:AG,'Combined P&L'!$C:$C,'P&L Overview'!$B20) -> 0.30969 | AF20: =SUMIFS('Combined P&L'!AH:AH,'Combined P&L'!$C:$C,'P&L Overview'!$B20) -> 0 | AG20: =SUMIFS('Combined P&L'!AI:AI,'Combined P&L'!$C:$C,'P&L Overview'!$B20) -> 0 | AH20: =SUMIFS('Combined P&L'!AJ:AJ,'Combined P&L'!$C:$C,'P&L Overview'!$B20) -> 0 | AI20: =SUMIFS('Combined P&L'!AK:AK,'Combined P&L'!$C:$C,'P&L Overview'!$B20) -> 0.025 | AJ20: =SUMIFS('Combined P&L'!AL:AL,'Combined P&L'!$C:$C,'P&L Overview'!$B20) -> 0.15984 | AK20: =SUMIFS('Combined P&L'!AM:AM,'Combined P&L'!$C:$C,'P&L Overview'!$B20) -> 0 | AL20: =SUMIFS('Combined P&L'!AN:AN,'Combined P&L'!$C:$C,'P&L Overview'!$B20) -> 0.075 | AM20: =SUMIFS('Combined P&L'!AO:AO,'Combined P&L'!$C:$C,'P&L Overview'!$B20) -> 0 | AN20: =SUMIFS('Combined P&L'!AP:AP,'Combined P&L'!$C:$C,'P&L Overview'!$B20) -> 0 | AO20: =SUMIFS('Combined P&L'!AQ:AQ,'Combined P&L'!$C:$C,'P&L Overview'!$B20) -> 0.02299 | AP20: =SUMIFS('Combined P&L'!AR:AR,'Combined P&L'!$C:$C,'P&L Overview'!$B20) -> 0
B21: Offshore Recruiting | C21: =SUMIFS($L21:$AP21,$L$5:$AP$5,">"&C$42,$L$5:$AP$5,"<"&C$43) -> 23.6 | D21: =SUMIFS($L21:$AP21,$L$5:$AP$5,">"&D$42,$L$5:$AP$5,"<"&D$43) -> 0.2 | F21: =SUMIFS($L21:$AP21,$L$5:$AP$5,">"&F$42,$L$5:$AP$5,"<"&F$43) -> 0.2 | G21: =SUMIFS($L21:$AP21,$L$5:$AP$5,">"&G$42,$L$5:$AP$5,"<"&G$43) -> 0 | I21: =SUMIFS($L21:$AP21,$L$5:$AP$5,">"&I$42,$L$5:$AP$5,"<"&I$43) -> 16.735 | J21: =SUMIFS($L21:$AP21,$L$5:$AP$5,">"&J$42,$L$5:$AP$5,"<"&J$43) -> 0 | L21: =SUMIFS('Combined P&L'!N:N,'Combined P&L'!$C:$C,'P&L Overview'!$B21) -> 0.5 | M21: =SUMIFS('Combined P&L'!O:O,'Combined P&L'!$C:$C,'P&L Overview'!$B21) -> 3 | N21: =SUMIFS('Combined P&L'!P:P,'Combined P&L'!$C:$C,'P&L Overview'!$B21) -> 0 | O21: =SUMIFS('Combined P&L'!Q:Q,'Combined P&L'!$C:$C,'P&L Overview'!$B21) -> 0 | P21: =SUMIFS('Combined P&L'!R:R,'Combined P&L'!$C:$C,'P&L Overview'!$B21) -> 3 | Q21: =SUMIFS('Combined P&L'!S:S,'Combined P&L'!$C:$C,'P&L Overview'!$B21) -> 0.565 | R21: =SUMIFS('Combined P&L'!T:T,'Combined P&L'!$C:$C,'P&L Overview'!$B21) -> 10.5 | S21: =SUMIFS('Combined P&L'!U:U,'Combined P&L'!$C:$C,'P&L Overview'!$B21) -> 6.5 | T21: =SUMIFS('Combined P&L'!V:V,'Combined P&L'!$C:$C,'P&L Overview'!$B21) -> 0.5 | U21: =SUMIFS('Combined P&L'!W:W,'Combined P&L'!$C:$C,'P&L Overview'!$B21) -> -0.965 | V21: =SUMIFS('Combined P&L'!X:X,'Combined P&L'!$C:$C,'P&L Overview'!$B21) -> 0 | W21: =SUMIFS('Combined P&L'!Y:Y,'Combined P&L'!$C:$C,'P&L Overview'!$B21) -> 0 | X21: =SUMIFS('Combined P&L'!Z:Z,'Combined P&L'!$C:$C,'P&L Overview'!$B21) -> 0.1 | Y21: =SUMIFS('Combined P&L'!AA:AA,'Combined P&L'!$C:$C,'P&L Overview'!$B21) -> 0 | Z21: =SUMIFS('Combined P&L'!AB:AB,'Combined P&L'!$C:$C,'P&L Overview'!$B21) -> 0.1 | AA21: =SUMIFS('Combined P&L'!AC:AC,'Combined P&L'!$C:$C,'P&L Overview'!$B21) -> 0 | AB21: =SUMIFS('Combined P&L'!AD:AD,'Combined P&L'!$C:$C,'P&L Overview'!$B21) -> 0 | AC21: =SUMIFS('Combined P&L'!AE:AE,'Combined P&L'!$C:$C,'P&L Overview'!$B21) -> 0 | AD21: =SUMIFS('Combined P&L'!AF:AF,'Combined P&L'!$C:$C,'P&L Overview'!$B21) -> 0 | AE21: =SUMIFS('Combined P&L'!AG:AG,'Combined P&L'!$C:$C,'P&L Overview'!$B21) -> 0 | AF21: =SUMIFS('Combined P&L'!AH:AH,'Combined P&L'!$C:$C,'P&L Overview'!$B21) -> 0 | AG21: =SUMIFS('Combined P&L'!AI:AI,'Combined P&L'!$C:$C,'P&L Overview'!$B21) -> 0 | AH21: =SUMIFS('Combined P&L'!AJ:AJ,'Combined P&L'!$C:$C,'P&L Overview'!$B21) -> 0 | AI21: =SUMIFS('Combined P&L'!AK:AK,'Combined P&L'!$C:$C,'P&L Overview'!$B21) -> 0 | AJ21: =SUMIFS('Combined P&L'!AL:AL,'Combined P&L'!$C:$C,'P&L Overview'!$B21) -> 0 | AK21: =SUMIFS('Combined P&L'!AM:AM,'Combined P&L'!$C:$C,'P&L Overview'!$B21) -> 0 | AL21: =SUMIFS('Combined P&L'!AN:AN,'Combined P&L'!$C:$C,'P&L Overview'!$B21) -> 0 | AM21: =SUMIFS('Combined P&L'!AO:AO,'Combined P&L'!$C:$C,'P&L Overview'!$B21) -> 0 | AN21: =SUMIFS('Combined P&L'!AP:AP,'Combined P&L'!$C:$C,'P&L Overview'!$B21) -> 0 | AO21: =SUMIFS('Combined P&L'!AQ:AQ,'Combined P&L'!$C:$C,'P&L Overview'!$B21) -> 0 | AP21: =SUMIFS('Combined P&L'!AR:AR,'Combined P&L'!$C:$C,'P&L Overview'!$B21) -> 0
B22: Total Recurring Revenue | C22: =SUM(C17:C21) -> 40.6501 | D22: =SUM(D17:D21) -> 51.53373 | F22: =SUM(F17:F21) -> 38.9822 | G22: =SUM(G17:G21) -> 70.95371 | I22: =SUM(I17:I21) -> 59.00012 | J22: =SUM(J17:J21) -> 84.75482 | L22: =SUM(L17:L21) -> 7.5636 | M22: =SUM(M17:M21) -> 6.5112 | N22: =SUM(N17:N21) -> 0.1162 | O22: =SUM(O17:O21) -> 0.1406 | P22: =SUM(P17:P21) -> 3.592 | Q22: =SUM(Q17:Q21) -> 1.3718 | R22: =SUM(R17:R21) -> 11.4653 | S22: =SUM(S17:S21) -> 7.3414 | ... AP22: =SUM(AP17:AP21) -> 0.0872
B24: Total Revenue | C24: =+C22+C15 -> 1134.9659 | D24: =+D22+D15 -> 1879.3831 | F24: =+F22+F15 -> 997.8731 | G24: =+G22+G15 -> 1671.0212 | I24: =+I22+I15 -> 1473.7119 | J24: =+J22+J15 -> 2456.4862 | L24: =+L22+L15 -> 80.9131 | M24: =+M22+M15 -> 81.2557 | N24: =+N22+N15 -> 78.1122 | O24: =+O22+O15 -> 83.3533 | P24: =+P22+P15 -> 90.19615 | Q24: =+Q22+Q15 -> 89.9158 | R24: =+R22+R15 -> 104.68205 | S24: =+S22+S15 -> 104.11675 | ... AP24: =+AP22+AP15 -> 251.42585
B26: Expenses
B27: Indirect Labor | C27: =SUMIFS($L27:$AP27,$L$5:$AP$5,">"&C$42,$L$5:$AP$5,"<"&C$43) -> 101.3752 | D27: =SUMIFS($L27:$AP27,$L$5:$AP$5,">"&D$42,$L$5:$AP$5,"<"&D$43) -> 281.24054 | F27: =SUMIFS($L27:$AP27,$L$5:$AP$5,">"&F$42,$L$5:$AP$5,"<"&F$43) -> 136.29648 | G27: =SUMIFS($L27:$AP27,$L$5:$AP$5,">"&G$42,$L$5:$AP$5,"<"&G$43) -> 357.27472 | I27: =SUMIFS($L27:$AP27,$L$5:$AP$5,">"&I$42,$L$5:$AP$5,"<"&I$43) -> 184.76374 | J27: =SUMIFS($L27:$AP27,$L$5:$AP$5,">"&J$42,$L$5:$AP$5,"<"&J$43) -> 466.92604 | L27: =SUMIFS('Combined P&L'!N:N,'Combined P&L'!$C:$C,'P&L Overview'!$B27) -> 3.09346 | M27: =SUMIFS('Combined P&L'!O:O,'Combined P&L'!$C:$C,'P&L Overview'!$B27) -> 4.63017 | N27: =SUMIFS('Combined P&L'!P:P,'Combined P&L'!$C:$C,'P&L Overview'!$B27) -> 4.39507 | O27: =SUMIFS('Combined P&L'!Q:Q,'Combined P&L'!$C:$C,'P&L Overview'!$B27) -> 5.86387 | P27: =SUMIFS('Combined P&L'!R:R,'Combined P&L'!$C:$C,'P&L Overview'!$B27) -> 7.37233 | Q27: =SUMIFS('Combined P&L'!S:S,'Combined P&L'!$C:$C,'P&L Overview'!$B27) -> 4.9504 | R27: =SUMIFS('Combined P&L'!T:T,'Combined P&L'!$C:$C,'P&L Overview'!$B27) -> 4.9504 | S27: =SUMIFS('Combined P&L'!U:U,'Combined P&L'!$C:$C,'P&L Overview'!$B27) -> 4.70035 | T27: =SUMIFS('Combined P&L'!V:V,'Combined P&L'!$C:$C,'P&L Overview'!$B27) -> 4.9504 | U27: =SUMIFS('Combined P&L'!W:W,'Combined P&L'!$C:$C,'P&L Overview'!$B27) -> 5.99987 | V27: =SUMIFS('Combined P&L'!X:X,'Combined P&L'!$C:$C,'P&L Overview'!$B27) -> 26.02876 | W27: =SUMIFS('Combined P&L'!Y:Y,'Combined P&L'!$C:$C,'P&L Overview'!$B27) -> 24.44012 | X27: =SUMIFS('Combined P&L'!Z:Z,'Combined P&L'!$C:$C,'P&L Overview'!$B27) -> 21.05234 | Y27: =SUMIFS('Combined P&L'!AA:AA,'Combined P&L'!$C:$C,'P&L Overview'!$B27) -> 19.91603 | Z27: =SUMIFS('Combined P&L'!AB:AB,'Combined P&L'!$C:$C,'P&L Overview'!$B27) -> 11.74387 | AA27: =SUMIFS('Combined P&L'!AC:AC,'Combined P&L'!$C:$C,'P&L Overview'!$B27) -> 19.61792 | AB27: =SUMIFS('Combined P&L'!AD:AD,'Combined P&L'!$C:$C,'P&L Overview'!$B27) -> 20.66978 | AC27: =SUMIFS('Combined P&L'!AE:AE,'Combined P&L'!$C:$C,'P&L Overview'!$B27) -> 20.6939 | AD27: =SUMIFS('Combined P&L'!AF:AF,'Combined P&L'!$C:$C,'P&L Overview'!$B27) -> 22.60264 | AE27: =SUMIFS('Combined P&L'!AG:AG,'Combined P&L'!$C:$C,'P&L Overview'!$B27) -> 19.96128 | AF27: =SUMIFS('Combined P&L'!AH:AH,'Combined P&L'!$C:$C,'P&L Overview'!$B27) -> 27.60563 | AG27: =SUMIFS('Combined P&L'!AI:AI,'Combined P&L'!$C:$C,'P&L Overview'!$B27) -> 34.18589 | AH27: =SUMIFS('Combined P&L'!AJ:AJ,'Combined P&L'!$C:$C,'P&L Overview'!$B27) -> 29.73157 | AI27: =SUMIFS('Combined P&L'!AK:AK,'Combined P&L'!$C:$C,'P&L Overview'!$B27) -> 33.45969 | AJ27: =SUMIFS('Combined P&L'!AL:AL,'Combined P&L'!$C:$C,'P&L Overview'!$B27) -> 36.2536 | AK27: =SUMIFS('Combined P&L'!AM:AM,'Combined P&L'!$C:$C,'P&L Overview'!$B27) -> 33.60751 | AL27: =SUMIFS('Combined P&L'!AN:AN,'Combined P&L'!$C:$C,'P&L Overview'!$B27) -> 57.19924 | AM27: =SUMIFS('Combined P&L'!AO:AO,'Combined P&L'!$C:$C,'P&L Overview'!$B27) -> 58.24595 | AN27: =SUMIFS('Combined P&L'!AP:AP,'Combined P&L'!$C:$C,'P&L Overview'!$B27) -> 54.06923 | AO27: =SUMIFS('Combined P&L'!AQ:AQ,'Combined P&L'!$C:$C,'P&L Overview'!$B27) -> 60.00381 | AP27: =SUMIFS('Combined P&L'!AR:AR,'Combined P&L'!$C:$C,'P&L Overview'!$B27) -> 57.89538
B28: Bookkeeper Wages | C28: =SUMIFS($L28:$AP28,$L$5:$AP$5,">"&C$42,$L$5:$AP$5,"<"&C$43) -> 183.36903 | D28: =SUMIFS($L28:$AP28,$L$5:$AP$5,">"&D$42,$L$5:$AP$5,"<"&D$43) -> 316.18462 | F28: =SUMIFS($L28:$AP28,$L$5:$AP$5,">"&F$42,$L$5:$AP$5,"<"&F$43) -> 147.26813 | G28: =SUMIFS($L28:$AP28,$L$5:$AP$5,">"&G$42,$L$5:$AP$5,"<"&G$43) -> 267.7574 | I28: =SUMIFS($L28:$AP28,$L$5:$AP$5,">"&I$42,$L$5:$AP$5,"<"&I$43) -> 226.32031 | J28: =SUMIFS($L28:$AP28,$L$5:$AP$5,">"&J$42,$L$5:$AP$5,"<"&J$43) -> 420.0952 | L28: =SUMIFS('Combined P&L'!N:N,'Combined P&L'!$C:$C,'P&L Overview'!$B28) -> 9.555 | M28: =SUMIFS('Combined P&L'!O:O,'Combined P&L'!$C:$C,'P&L Overview'!$B28) -> 9.555 | N28: =SUMIFS('Combined P&L'!P:P,'Combined P&L'!$C:$C,'P&L Overview'!$B28) -> 10.3972 | O28: =SUMIFS('Combined P&L'!Q:Q,'Combined P&L'!$C:$C,'P&L Overview'!$B28) -> 14.99967 | P28: =SUMIFS('Combined P&L'!R:R,'Combined P&L'!$C:$C,'P&L Overview'!$B28) -> 18.0098 | Q28: =SUMIFS('Combined P&L'!S:S,'Combined P&L'!$C:$C,'P&L Overview'!$B28) -> 13.89127 | R28: =SUMIFS('Combined P&L'!T:T,'Combined P&L'!$C:$C,'P&L Overview'!$B28) -> 14.04824 | S28: =SUMIFS('Combined P&L'!U:U,'Combined P&L'!$C:$C,'P&L Overview'!$B28) -> 13.39091 | T28: =SUMIFS('Combined P&L'!V:V,'Combined P&L'!$C:$C,'P&L Overview'!$B28) -> 14.66931 | U28: =SUMIFS('Combined P&L'!W:W,'Combined P&L'!$C:$C,'P&L Overview'!$B28) -> 15.88253 | V28: =SUMIFS('Combined P&L'!X:X,'Combined P&L'!$C:$C,'P&L Overview'!$B28) -> 27.18867 | W28: =SUMIFS('Combined P&L'!Y:Y,'Combined P&L'!$C:$C,'P&L Overview'!$B28) -> 21.78143 | X28: =SUMIFS('Combined P&L'!Z:Z,'Combined P&L'!$C:$C,'P&L Overview'!$B28) -> 19.40233 | Y28: =SUMIFS('Combined P&L'!AA:AA,'Combined P&L'!$C:$C,'P&L Overview'!$B28) -> 16.40053 | Z28: =SUMIFS('Combined P&L'!AB:AB,'Combined P&L'!$C:$C,'P&L Overview'!$B28) -> 19.56983 | AA28: =SUMIFS('Combined P&L'!AC:AC,'Combined P&L'!$C:$C,'P&L Overview'!$B28) -> 22.1542 | AB28: =SUMIFS('Combined P&L'!AD:AD,'Combined P&L'!$C:$C,'P&L Overview'!$B28) -> 20.79154 | AC28: =SUMIFS('Combined P&L'!AE:AE,'Combined P&L'!$C:$C,'P&L Overview'!$B28) -> 21.04079 | AD28: =SUMIFS('Combined P&L'!AF:AF,'Combined P&L'!$C:$C,'P&L Overview'!$B28) -> 27.90891 | AE28: =SUMIFS('Combined P&L'!AG:AG,'Combined P&L'!$C:$C,'P&L Overview'!$B28) -> 29.547 | AF28: =SUMIFS('Combined P&L'!AH:AH,'Combined P&L'!$C:$C,'P&L Overview'!$B28) -> 33.44727 | AG28: =SUMIFS('Combined P&L'!AI:AI,'Combined P&L'!$C:$C,'P&L Overview'!$B28) -> 37.79432 | AH28: =SUMIFS('Combined P&L'!AJ:AJ,'Combined P&L'!$C:$C,'P&L Overview'!$B28) -> 34.06332 | AI28: =SUMIFS('Combined P&L'!AK:AK,'Combined P&L'!$C:$C,'P&L Overview'!$B28) -> 34.06458 | AJ28: =SUMIFS('Combined P&L'!AL:AL,'Combined P&L'!$C:$C,'P&L Overview'!$B28) -> 38.37888 | AK28: =SUMIFS('Combined P&L'!AM:AM,'Combined P&L'!$C:$C,'P&L Overview'!$B28) -> 29.70152 | AL28: =SUMIFS('Combined P&L'!AN:AN,'Combined P&L'!$C:$C,'P&L Overview'!$B28) -> 37.4225 | AM28: =SUMIFS('Combined P&L'!AO:AO,'Combined P&L'!$C:$C,'P&L Overview'!$B28) -> 38.7723 | AN28: =SUMIFS('Combined P&L'!AP:AP,'Combined P&L'!$C:$C,'P&L Overview'!$B28) -> 38.29477 | AO28: =SUMIFS('Combined P&L'!AQ:AQ,'Combined P&L'!$C:$C,'P&L Overview'!$B28) -> 40.69983 | AP28: =SUMIFS('Combined P&L'!AR:AR,'Combined P&L'!$C:$C,'P&L Overview'!$B28) -> 44.4876
B29: Client Lead Wages | C29: =SUMIFS($L29:$AP29,$L$5:$AP$5,">"&C$42,$L$5:$AP$5,"<"&C$43) -> 286.16129 | D29: =SUMIFS($L29:$AP29,$L$5:$AP$5,">"&D$42,$L$5:$AP$5,"<"&D$43) -> 352.95844 | F29: =SUMIFS($L29:$AP29,$L$5:$AP$5,">"&F$42,$L$5:$AP$5,"<"&F$43) -> 201.27983 | G29: =SUMIFS($L29:$AP29,$L$5:$AP$5,">"&G$42,$L$5:$AP$5,"<"&G$43) -> 202.05309 | I29: =SUMIFS($L29:$AP29,$L$5:$AP$5,">"&I$42,$L$5:$AP$5,"<"&I$43) -> 351.95999 | J29: =SUMIFS($L29:$AP29,$L$5:$AP$5,">"&J$42,$L$5:$AP$5,"<"&J$43) -> 350.46762 | L29: =SUMIFS('Combined P&L'!N:N,'Combined P&L'!$C:$C,'P&L Overview'!$B29) -> 9.96108 | M29: =SUMIFS('Combined P&L'!O:O,'Combined P&L'!$C:$C,'P&L Overview'!$B29) -> 13.85026 | N29: =SUMIFS('Combined P&L'!P:P,'Combined P&L'!$C:$C,'P&L Overview'!$B29) -> 12.79054 | O29: =SUMIFS('Combined P&L'!Q:Q,'Combined P&L'!$C:$C,'P&L Overview'!$B29) -> 14.57145 | P29: =SUMIFS('Combined P&L'!R:R,'Combined P&L'!$C:$C,'P&L Overview'!$B29) -> 28.28563 | Q29: =SUMIFS('Combined P&L'!S:S,'Combined P&L'!$C:$C,'P&L Overview'!$B29) -> 26.54254 | R29: =SUMIFS('Combined P&L'!T:T,'Combined P&L'!$C:$C,'P&L Overview'!$B29) -> 28.31119 | S29: =SUMIFS('Combined P&L'!U:U,'Combined P&L'!$C:$C,'P&L Overview'!$B29) -> 28.18746 | T29: =SUMIFS('Combined P&L'!V:V,'Combined P&L'!$C:$C,'P&L Overview'!$B29) -> 30.86801 | U29: =SUMIFS('Combined P&L'!W:W,'Combined P&L'!$C:$C,'P&L Overview'!$B29) -> 31.62128 | V29: =SUMIFS('Combined P&L'!X:X,'Combined P&L'!$C:$C,'P&L Overview'!$B29) -> 28.44974 | W29: =SUMIFS('Combined P&L'!Y:Y,'Combined P&L'!$C:$C,'P&L Overview'!$B29) -> 32.72211 | X29: =SUMIFS('Combined P&L'!Z:Z,'Combined P&L'!$C:$C,'P&L Overview'!$B29) -> 32.78076 | Y29: =SUMIFS('Combined P&L'!AA:AA,'Combined P&L'!$C:$C,'P&L Overview'!$B29) -> 23.36184 | Z29: =SUMIFS('Combined P&L'!AB:AB,'Combined P&L'!$C:$C,'P&L Overview'!$B29) -> 26.91427 | AA29: =SUMIFS('Combined P&L'!AC:AC,'Combined P&L'!$C:$C,'P&L Overview'!$B29) -> 28.81298 | AB29: =SUMIFS('Combined P&L'!AD:AD,'Combined P&L'!$C:$C,'P&L Overview'!$B29) -> 30.65875 | AC29: =SUMIFS('Combined P&L'!AE:AE,'Combined P&L'!$C:$C,'P&L Overview'!$B29) -> 29.2716 | AD29: =SUMIFS('Combined P&L'!AF:AF,'Combined P&L'!$C:$C,'P&L Overview'!$B29) -> 29.47963 | AE29: =SUMIFS('Combined P&L'!AG:AG,'Combined P&L'!$C:$C,'P&L Overview'!$B29) -> 26.83064 | AF29: =SUMIFS('Combined P&L'!AH:AH,'Combined P&L'!$C:$C,'P&L Overview'!$B29) -> 29.78555 | AG29: =SUMIFS('Combined P&L'!AI:AI,'Combined P&L'!$C:$C,'P&L Overview'!$B29) -> 32.89937 | AH29: =SUMIFS('Combined P&L'!AJ:AJ,'Combined P&L'!$C:$C,'P&L Overview'!$B29) -> 29.49334 | AI29: =SUMIFS('Combined P&L'!AK:AK,'Combined P&L'!$C:$C,'P&L Overview'!$B29) -> 32.66971 | AJ29: =SUMIFS('Combined P&L'!AL:AL,'Combined P&L'!$C:$C,'P&L Overview'!$B29) -> 26.1149 | AK29: =SUMIFS('Combined P&L'!AM:AM,'Combined P&L'!$C:$C,'P&L Overview'!$B29) -> 21.9055 | AL29: =SUMIFS('Combined P&L'!AN:AN,'Combined P&L'!$C:$C,'P&L Overview'!$B29) -> 30.75844 | AM29: =SUMIFS('Combined P&L'!AO:AO,'Combined P&L'!$C:$C,'P&L Overview'!$B29) -> 31.59038 | AN29: =SUMIFS('Combined P&L'!AP:AP,'Combined P&L'!$C:$C,'P&L Overview'!$B29) -> 27.69992 | AO29: =SUMIFS('Combined P&L'!AQ:AQ,'Combined P&L'!$C:$C,'P&L Overview'!$B29) -> 31.24024 | AP29: =SUMIFS('Combined P&L'!AR:AR,'Combined P&L'!$C:$C,'P&L Overview'!$B29) -> 32.74371
B30: Onboarding Team Wages | C30: =SUMIFS($L30:$AP30,$L$5:$AP$5,">"&C$42,$L$5:$AP$5,"<"&C$43) -> 122.81255 | D30: =SUMIFS($L30:$AP30,$L$5:$AP$5,">"&D$42,$L$5:$AP$5,"<"&D$43) -> 152.16972 | F30: =SUMIFS($L30:$AP30,$L$5:$AP$5,">"&F$42,$L$5:$AP$5,"<"&F$43) -> 73.94962 | G30: =SUMIFS($L30:$AP30,$L$5:$AP$5,">"&G$42,$L$5:$AP$5,"<"&G$43) -> 111.27999 | I30: =SUMIFS($L30:$AP30,$L$5:$AP$5,">"&I$42,$L$5:$AP$5,"<"&I$43) -> 115.8168 | J30: =SUMIFS($L30:$AP30,$L$5:$AP$5,">"&J$42,$L$5:$AP$5,"<"&J$43) -> 186.54354 | L30: =SUMIFS('Combined P&L'!N:N,'Combined P&L'!$C:$C,'P&L Overview'!$B30) -> 9.13728 | M30: =SUMIFS('Combined P&L'!O:O,'Combined P&L'!$C:$C,'P&L Overview'!$B30) -> 8.96296 | N30: =SUMIFS('Combined P&L'!P:P,'Combined P&L'!$C:$C,'P&L Overview'!$B30) -> 10.19584 | O30: =SUMIFS('Combined P&L'!Q:Q,'Combined P&L'!$C:$C,'P&L Overview'!$B30) -> 15.04429 | P30: =SUMIFS('Combined P&L'!R:R,'Combined P&L'!$C:$C,'P&L Overview'!$B30) -> 16.63744 | Q30: =SUMIFS('Combined P&L'!S:S,'Combined P&L'!$C:$C,'P&L Overview'!$B30) -> 7.49499 | R30: =SUMIFS('Combined P&L'!T:T,'Combined P&L'!$C:$C,'P&L Overview'!$B30) -> 7.98202 | S30: =SUMIFS('Combined P&L'!U:U,'Combined P&L'!$C:$C,'P&L Overview'!$B30) -> 5.90274 | T30: =SUMIFS('Combined P&L'!V:V,'Combined P&L'!$C:$C,'P&L Overview'!$B30) -> 7.76763 | U30: =SUMIFS('Combined P&L'!W:W,'Combined P&L'!$C:$C,'P&L Overview'!$B30) -> 8.21417 | V30: =SUMIFS('Combined P&L'!X:X,'Combined P&L'!$C:$C,'P&L Overview'!$B30) -> 12.62272 | W30: =SUMIFS('Combined P&L'!Y:Y,'Combined P&L'!$C:$C,'P&L Overview'!$B30) -> 12.85047 | X30: =SUMIFS('Combined P&L'!Z:Z,'Combined P&L'!$C:$C,'P&L Overview'!$B30) -> 10.34556 | Y30: =SUMIFS('Combined P&L'!AA:AA,'Combined P&L'!$C:$C,'P&L Overview'!$B30) -> 8.08798 | Z30: =SUMIFS('Combined P&L'!AB:AB,'Combined P&L'!$C:$C,'P&L Overview'!$B30) -> 9.75287 | AA30: =SUMIFS('Combined P&L'!AC:AC,'Combined P&L'!$C:$C,'P&L Overview'!$B30) -> 10.28 | AB30: =SUMIFS('Combined P&L'!AD:AD,'Combined P&L'!$C:$C,'P&L Overview'!$B30) -> 11.13632 | AC30: =SUMIFS('Combined P&L'!AE:AE,'Combined P&L'!$C:$C,'P&L Overview'!$B30) -> 10.87432 | AD30: =SUMIFS('Combined P&L'!AF:AF,'Combined P&L'!$C:$C,'P&L Overview'!$B30) -> 13.47257 | AE30: =SUMIFS('Combined P&L'!AG:AG,'Combined P&L'!$C:$C,'P&L Overview'!$B30) -> 12.70407 | AF30: =SUMIFS('Combined P&L'!AH:AH,'Combined P&L'!$C:$C,'P&L Overview'!$B30) -> 14.69884 | AG30: =SUMIFS('Combined P&L'!AI:AI,'Combined P&L'!$C:$C,'P&L Overview'!$B30) -> 15.54306 | AH30: =SUMIFS('Combined P&L'!AJ:AJ,'Combined P&L'!$C:$C,'P&L Overview'!$B30) -> 14.34361 | AI30: =SUMIFS('Combined P&L'!AK:AK,'Combined P&L'!$C:$C,'P&L Overview'!$B30) -> 20.93052 | AJ30: =SUMIFS('Combined P&L'!AL:AL,'Combined P&L'!$C:$C,'P&L Overview'!$B30) -> 16.55394 | AK30: =SUMIFS('Combined P&L'!AM:AM,'Combined P&L'!$C:$C,'P&L Overview'!$B30) -> 11.52661 | AL30: =SUMIFS('Combined P&L'!AN:AN,'Combined P&L'!$C:$C,'P&L Overview'!$B30) -> 14.93883 | AM30: =SUMIFS('Combined P&L'!AO:AO,'Combined P&L'!$C:$C,'P&L Overview'!$B30) -> 15.58352 | AN30: =SUMIFS('Combined P&L'!AP:AP,'Combined P&L'!$C:$C,'P&L Overview'!$B30) -> 19.6034 | AO30: =SUMIFS('Combined P&L'!AQ:AQ,'Combined P&L'!$C:$C,'P&L Overview'!$B30) -> 16.64457 | AP30: =SUMIFS('Combined P&L'!AR:AR,'Combined P&L'!$C:$C,'P&L Overview'!$B30) -> 16.42912
B31: Owner Wages | C31: =SUMIFS($L31:$AP31,$L$5:$AP$5,">"&C$42,$L$5:$AP$5,"<"&C$43) -> 0 | D31: =SUMIFS($L31:$AP31,$L$5:$AP$5,">"&D$42,$L$5:$AP$5,"<"&D$43) -> 90.66704 | F31: =SUMIFS($L31:$AP31,$L$5:$AP$5,">"&F$42,$L$5:$AP$5,"<"&F$43) -> 45.46612 | G31: =SUMIFS($L31:$AP31,$L$5:$AP$5,">"&G$42,$L$5:$AP$5,"<"&G$43) -> 63.14302 | I31: =SUMIFS($L31:$AP31,$L$5:$AP$5,">"&I$42,$L$5:$AP$5,"<"&I$43) -> 35.94325 | J31: =SUMIFS($L31:$AP31,$L$5:$AP$5,">"&J$42,$L$5:$AP$5,"<"&J$43) -> 108.34394 | L31: =SUMIFS('Combined P&L'!N:N,'Combined P&L'!$C:$C,'P&L Overview'!$B31) -> 0 | M31: =SUMIFS('Combined P&L'!O:O,'Combined P&L'!$C:$C,'P&L Overview'!$B31) -> 0 | N31: =SUMIFS('Combined P&L'!P:P,'Combined P&L'!$C:$C,'P&L Overview'!$B31) -> 0 | O31: =SUMIFS('Combined P&L'!Q:Q,'Combined P&L'!$C:$C,'P&L Overview'!$B31) -> 0 | P31: =SUMIFS('Combined P&L'!R:R,'Combined P&L'!$C:$C,'P&L Overview'!$B31) -> 0 | Q31: =SUMIFS('Combined P&L'!S:S,'Combined P&L'!$C:$C,'P&L Overview'!$B31) -> 0 | R31: =SUMIFS('Combined P&L'!T:T,'Combined P&L'!$C:$C,'P&L Overview'!$B31) -> 0 | S31: =SUMIFS('Combined P&L'!U:U,'Combined P&L'!$C:$C,'P&L Overview'!$B31) -> 0 | T31: =SUMIFS('Combined P&L'!V:V,'Combined P&L'!$C:$C,'P&L Overview'!$B31) -> 0 | U31: =SUMIFS('Combined P&L'!W:W,'Combined P&L'!$C:$C,'P&L Overview'!$B31) -> 0 | V31: =SUMIFS('Combined P&L'!X:X,'Combined P&L'!$C:$C,'P&L Overview'!$B31) -> 0 | W31: =SUMIFS('Combined P&L'!Y:Y,'Combined P&L'!$C:$C,'P&L Overview'!$B31) -> 0 | X31: =SUMIFS('Combined P&L'!Z:Z,'Combined P&L'!$C:$C,'P&L Overview'!$B31) -> 0 | Y31: =SUMIFS('Combined P&L'!AA:AA,'Combined P&L'!$C:$C,'P&L Overview'!$B31) -> 0 | Z31: =SUMIFS('Combined P&L'!AB:AB,'Combined P&L'!$C:$C,'P&L Overview'!$B31) -> 8.90639 | AA31: =SUMIFS('Combined P&L'!AC:AC,'Combined P&L'!$C:$C,'P&L Overview'!$B31) -> 9.23323 | AB31: =SUMIFS('Combined P&L'!AD:AD,'Combined P&L'!$C:$C,'P&L Overview'!$B31) -> 9.10884 | AC31: =SUMIFS('Combined P&L'!AE:AE,'Combined P&L'!$C:$C,'P&L Overview'!$B31) -> 8.69479 | AD31: =SUMIFS('Combined P&L'!AF:AF,'Combined P&L'!$C:$C,'P&L Overview'!$B31) -> 9.52287 | AE31: =SUMIFS('Combined P&L'!AG:AG,'Combined P&L'!$C:$C,'P&L Overview'!$B31) -> 8.69481 | AF31: =SUMIFS('Combined P&L'!AH:AH,'Combined P&L'!$C:$C,'P&L Overview'!$B31) -> 9.10884 | AG31: =SUMIFS('Combined P&L'!AI:AI,'Combined P&L'!$C:$C,'P&L Overview'!$B31) -> 9.52287 | AH31: =SUMIFS('Combined P&L'!AJ:AJ,'Combined P&L'!$C:$C,'P&L Overview'!$B31) -> 8.28076 | AI31: =SUMIFS('Combined P&L'!AK:AK,'Combined P&L'!$C:$C,'P&L Overview'!$B31) -> 9.59364 | AJ31: =SUMIFS('Combined P&L'!AL:AL,'Combined P&L'!$C:$C,'P&L Overview'!$B31) -> 9.27621 | AK31: =SUMIFS('Combined P&L'!AM:AM,'Combined P&L'!$C:$C,'P&L Overview'!$B31) -> 8.32263 | AL31: =SUMIFS('Combined P&L'!AN:AN,'Combined P&L'!$C:$C,'P&L Overview'!$B31) -> 9.10883 | AM31: =SUMIFS('Combined P&L'!AO:AO,'Combined P&L'!$C:$C,'P&L Overview'!$B31) -> 9.10883 | AN31: =SUMIFS('Combined P&L'!AP:AP,'Combined P&L'!$C:$C,'P&L Overview'!$B31) -> 8.69481 | AO31: =SUMIFS('Combined P&L'!AQ:AQ,'Combined P&L'!$C:$C,'P&L Overview'!$B31) -> 9.10884 | AP31: =SUMIFS('Combined P&L'!AR:AR,'Combined P&L'!$C:$C,'P&L Overview'!$B31) -> 9.52287
B32: S&M Wages | C32: =SUMIFS($L32:$AP32,$L$5:$AP$5,">"&C$42,$L$5:$AP$5,"<"&C$43) -> 0 | D32: =SUMIFS($L32:$AP32,$L$5:$AP$5,">"&D$42,$L$5:$AP$5,"<"&D$43) -> 19.14963 | F32: =SUMIFS($L32:$AP32,$L$5:$AP$5,">"&F$42,$L$5:$AP$5,"<"&F$43) -> 3.09945 | G32: =SUMIFS($L32:$AP32,$L$5:$AP$5,">"&G$42,$L$5:$AP$5,"<"&G$43) -> 51.94131 | I32: =SUMIFS($L32:$AP32,$L$5:$AP$5,">"&I$42,$L$5:$AP$5,"<"&I$43) -> 1.4668 | J32: =SUMIFS($L32:$AP32,$L$5:$AP$5,">"&J$42,$L$5:$AP$5,"<"&J$43) -> 61.42838 | L32: =SUMIFS('Combined P&L'!N:N,'Combined P&L'!$C:$C,'P&L Overview'!$B32) -> 0 | M32: =SUMIFS('Combined P&L'!O:O,'Combined P&L'!$C:$C,'P&L Overview'!$B32) -> 0 | N32: =SUMIFS('Combined P&L'!P:P,'Combined P&L'!$C:$C,'P&L Overview'!$B32) -> 0 | O32: =SUMIFS('Combined P&L'!Q:Q,'Combined P&L'!$C:$C,'P&L Overview'!$B32) -> 0 | P32: =SUMIFS('Combined P&L'!R:R,'Combined P&L'!$C:$C,'P&L Overview'!$B32) -> 0 | Q32: =SUMIFS('Combined P&L'!S:S,'Combined P&L'!$C:$C,'P&L Overview'!$B32) -> 0 | R32: =SUMIFS('Combined P&L'!T:T,'Combined P&L'!$C:$C,'P&L Overview'!$B32) -> 0 | S32: =SUMIFS('Combined P&L'!U:U,'Combined P&L'!$C:$C,'P&L Overview'!$B32) -> 0 | T32: =SUMIFS('Combined P&L'!V:V,'Combined P&L'!$C:$C,'P&L Overview'!$B32) -> 0 | U32: =SUMIFS('Combined P&L'!W:W,'Combined P&L'!$C:$C,'P&L Overview'!$B32) -> 0 | V32: =SUMIFS('Combined P&L'!X:X,'Combined P&L'!$C:$C,'P&L Overview'!$B32) -> 0 | W32: =SUMIFS('Combined P&L'!Y:Y,'Combined P&L'!$C:$C,'P&L Overview'!$B32) -> 0 | X32: =SUMIFS('Combined P&L'!Z:Z,'Combined P&L'!$C:$C,'P&L Overview'!$B32) -> 0 | Y32: =SUMIFS('Combined P&L'!AA:AA,'Combined P&L'!$C:$C,'P&L Overview'!$B32) -> 0 | Z32: =SUMIFS('Combined P&L'!AB:AB,'Combined P&L'!$C:$C,'P&L Overview'!$B32) -> 0 | AA32: =SUMIFS('Combined P&L'!AC:AC,'Combined P&L'!$C:$C,'P&L Overview'!$B32) -> 0 | AB32: =SUMIFS('Combined P&L'!AD:AD,'Combined P&L'!$C:$C,'P&L Overview'!$B32) -> 0 | AC32: =SUMIFS('Combined P&L'!AE:AE,'Combined P&L'!$C:$C,'P&L Overview'!$B32) -> 1.4668 | AD32: =SUMIFS('Combined P&L'!AF:AF,'Combined P&L'!$C:$C,'P&L Overview'!$B32) -> 1.63265 | AE32: =SUMIFS('Combined P&L'!AG:AG,'Combined P&L'!$C:$C,'P&L Overview'!$B32) -> 1.71805 | AF32: =SUMIFS('Combined P&L'!AH:AH,'Combined P&L'!$C:$C,'P&L Overview'!$B32) -> 1.9146 | AG32: =SUMIFS('Combined P&L'!AI:AI,'Combined P&L'!$C:$C,'P&L Overview'!$B32) -> 2.3529 | AH32: =SUMIFS('Combined P&L'!AJ:AJ,'Combined P&L'!$C:$C,'P&L Overview'!$B32) -> 2.24524 | AI32: =SUMIFS('Combined P&L'!AK:AK,'Combined P&L'!$C:$C,'P&L Overview'!$B32) -> 7.81939 | AJ32: =SUMIFS('Combined P&L'!AL:AL,'Combined P&L'!$C:$C,'P&L Overview'!$B32) -> 5.6534 | AK32: =SUMIFS('Combined P&L'!AM:AM,'Combined P&L'!$C:$C,'P&L Overview'!$B32) -> 5.95689 | AL32: =SUMIFS('Combined P&L'!AN:AN,'Combined P&L'!$C:$C,'P&L Overview'!$B32) -> 7.7828 | AM32: =SUMIFS('Combined P&L'!AO:AO,'Combined P&L'!$C:$C,'P&L Overview'!$B32) -> 8.13701 | AN32: =SUMIFS('Combined P&L'!AP:AP,'Combined P&L'!$C:$C,'P&L Overview'!$B32) -> 7.80825 | AO32: =SUMIFS('Combined P&L'!AQ:AQ,'Combined P&L'!$C:$C,'P&L Overview'!$B32) -> 8.4072 | AP32: =SUMIFS('Combined P&L'!AR:AR,'Combined P&L'!$C:$C,'P&L Overview'!$B32) -> 8.19576
B33: Occupancy Tax Specialist | C33: =SUMIFS($L33:$AP33,$L$5:$AP$5,">"&C$42,$L$5:$AP$5,"<"&C$43) -> 1.11335 | D33: =SUMIFS($L33:$AP33,$L$5:$AP$5,">"&D$42,$L$5:$AP$5,"<"&D$43) -> 29.56415 | F33: =SUMIFS($L33:$AP33,$L$5:$AP$5,">"&F$42,$L$5:$AP$5,"<"&F$43) -> 14.27585 | G33: =SUMIFS($L33:$AP33,$L$5:$AP$5,">"&G$42,$L$5:$AP$5,"<"&G$43) -> 42.08505 | I33: =SUMIFS($L33:$AP33,$L$5:$AP$5,">"&I$42,$L$5:$AP$5,"<"&I$43) -> 13.21003 | J33: =SUMIFS($L33:$AP33,$L$5:$AP$5,">"&J$42,$L$5:$AP$5,"<"&J$43) -> 53.87642 | L33: =SUMIFS('Combined P&L'!N:N,'Combined P&L'!$C:$C,'P&L Overview'!$B33) -> 0 | M33: =SUMIFS('Combined P&L'!O:O,'Combined P&L'!$C:$C,'P&L Overview'!$B33) -> 0 | N33: =SUMIFS('Combined P&L'!P:P,'Combined P&L'!$C:$C,'P&L Overview'!$B33) -> 0 | O33: =SUMIFS('Combined P&L'!Q:Q,'Combined P&L'!$C:$C,'P&L Overview'!$B33) -> 0 | P33: =SUMIFS('Combined P&L'!R:R,'Combined P&L'!$C:$C,'P&L Overview'!$B33) -> 0 | Q33: =SUMIFS('Combined P&L'!S:S,'Combined P&L'!$C:$C,'P&L Overview'!$B33) -> 0 | R33: =SUMIFS('Combined P&L'!T:T,'Combined P&L'!$C:$C,'P&L Overview'!$B33) -> 0 | S33: =SUMIFS('Combined P&L'!U:U,'Combined P&L'!$C:$C,'P&L Overview'!$B33) -> 0 | T33: =SUMIFS('Combined P&L'!V:V,'Combined P&L'!$C:$C,'P&L Overview'!$B33) -> 0 | U33: =SUMIFS('Combined P&L'!W:W,'Combined P&L'!$C:$C,'P&L Overview'!$B33) -> 0 | V33: =SUMIFS('Combined P&L'!X:X,'Combined P&L'!$C:$C,'P&L Overview'!$B33) -> 0 | W33: =SUMIFS('Combined P&L'!Y:Y,'Combined P&L'!$C:$C,'P&L Overview'!$B33) -> 1.11335 | X33: =SUMIFS('Combined P&L'!Z:Z,'Combined P&L'!$C:$C,'P&L Overview'!$B33) -> 2.17917 | Y33: =SUMIFS('Combined P&L'!AA:AA,'Combined P&L'!$C:$C,'P&L Overview'!$B33) -> 1.82504 | Z33: =SUMIFS('Combined P&L'!AB:AB,'Combined P&L'!$C:$C,'P&L Overview'!$B33) -> 1.97853 | AA33: =SUMIFS('Combined P&L'!AC:AC,'Combined P&L'!$C:$C,'P&L Overview'!$B33) -> 2.06213 | AB33: =SUMIFS('Combined P&L'!AD:AD,'Combined P&L'!$C:$C,'P&L Overview'!$B33) -> 2.06213 | AC33: =SUMIFS('Combined P&L'!AE:AE,'Combined P&L'!$C:$C,'P&L Overview'!$B33) -> 1.98968 | AD33: =SUMIFS('Combined P&L'!AF:AF,'Combined P&L'!$C:$C,'P&L Overview'!$B33) -> 2.17917 | AE33: =SUMIFS('Combined P&L'!AG:AG,'Combined P&L'!$C:$C,'P&L Overview'!$B33) -> 2.12293 | AF33: =SUMIFS('Combined P&L'!AH:AH,'Combined P&L'!$C:$C,'P&L Overview'!$B33) -> 3.1042 | AG33: =SUMIFS('Combined P&L'!AI:AI,'Combined P&L'!$C:$C,'P&L Overview'!$B33) -> 3.27137 | AH33: =SUMIFS('Combined P&L'!AJ:AJ,'Combined P&L'!$C:$C,'P&L Overview'!$B33) -> 3.63947 | AI33: =SUMIFS('Combined P&L'!AK:AK,'Combined P&L'!$C:$C,'P&L Overview'!$B33) -> 3.15033 | AJ33: =SUMIFS('Combined P&L'!AL:AL,'Combined P&L'!$C:$C,'P&L Overview'!$B33) -> 1.69116 | AK33: =SUMIFS('Combined P&L'!AM:AM,'Combined P&L'!$C:$C,'P&L Overview'!$B33) -> 5.54919 | AL33: =SUMIFS('Combined P&L'!AN:AN,'Combined P&L'!$C:$C,'P&L Overview'!$B33) -> 7.1999 | AM33: =SUMIFS('Combined P&L'!AO:AO,'Combined P&L'!$C:$C,'P&L Overview'!$B33) -> 8.1927 | AN33: =SUMIFS('Combined P&L'!AP:AP,'Combined P&L'!$C:$C,'P&L Overview'!$B33) -> 8.28335 | AO33: =SUMIFS('Combined P&L'!AQ:AQ,'Combined P&L'!$C:$C,'P&L Overview'!$B33) -> 5.49265 | AP33: =SUMIFS('Combined P&L'!AR:AR,'Combined P&L'!$C:$C,'P&L Overview'!$B33) -> 5.6761
B34: Sr. Client Lead Wages | C34: =SUMIFS($L34:$AP34,$L$5:$AP$5,">"&C$42,$L$5:$AP$5,"<"&C$43) -> 0 | D34: =SUMIFS($L34:$AP34,$L$5:$AP$5,">"&D$42,$L$5:$AP$5,"<"&D$43) -> 0 | F34: =SUMIFS($L34:$AP34,$L$5:$AP$5,">"&F$42,$L$5:$AP$5,"<"&F$43) -> 0 | G34: =SUMIFS($L34:$AP34,$L$5:$AP$5,">"&G$42,$L$5:$AP$5,"<"&G$43) -> 7.995 | I34: =SUMIFS($L34:$AP34,$L$5:$AP$5,">"&I$42,$L$5:$AP$5,"<"&I$43) -> 0 | J34: =SUMIFS($L34:$AP34,$L$5:$AP$5,">"&J$42,$L$5:$AP$5,"<"&J$43) -> 5.23823 | L34: =SUMIFS('Combined P&L'!N:N,'Combined P&L'!$C:$C,'P&L Overview'!$B34) -> 0 | M34: =SUMIFS('Combined P&L'!O:O,'Combined P&L'!$C:$C,'P&L Overview'!$B34) -> 0 | N34: =SUMIFS('Combined P&L'!P:P,'Combined P&L'!$C:$C,'P&L Overview'!$B34) -> 0 | O34: =SUMIFS('Combined P&L'!Q:Q,'Combined P&L'!$C:$C,'P&L Overview'!$B34) -> 0 | P34: =SUMIFS('Combined P&L'!R:R,'Combined P&L'!$C:$C,'P&L Overview'!$B34) -> 0 | Q34: =SUMIFS('Combined P&L'!S:S,'Combined P&L'!$C:$C,'P&L Overview'!$B34) -> 0 | R34: =SUMIFS('Combined P&L'!T:T,'Combined P&L'!$C:$C,'P&L Overview'!$B34) -> 0 | S34: =SUMIFS('Combined P&L'!U:U,'Combined P&L'!$C:$C,'P&L Overview'!$B34) -> 0 | T34: =SUMIFS('Combined P&L'!V:V,'Combined P&L'!$C:$C,'P&L Overview'!$B34) -> 0 | U34: =SUMIFS('Combined P&L'!W:W,'Combined P&L'!$C:$C,'P&L Overview'!$B34) -> 0 | V34: =SUMIFS('Combined P&L'!X:X,'Combined P&L'!$C:$C,'P&L Overview'!$B34) -> 0 | W34: =SUMIFS('Combined P&L'!Y:Y,'Combined P&L'!$C:$C,'P&L Overview'!$B34) -> 0 | X34: =SUMIFS('Combined P&L'!Z:Z,'Combined P&L'!$C:$C,'P&L Overview'!$B34) -> 0 | Y34: =SUMIFS('Combined P&L'!AA:AA,'Combined P&L'!$C:$C,'P&L Overview'!$B34) -> 0 | Z34: =SUMIFS('Combined P&L'!AB:AB,'Combined P&L'!$C:$C,'P&L Overview'!$B34) -> 0 | AA34: =SUMIFS('Combined P&L'!AC:AC,'Combined P&L'!$C:$C,'P&L Overview'!$B34) -> 0 | AB34: =SUMIFS('Combined P&L'!AD:AD,'Combined P&L'!$C:$C,'P&L Overview'!$B34) -> 0 | AC34: =SUMIFS('Combined P&L'!AE:AE,'Combined P&L'!$C:$C,'P&L Overview'!$B34) -> 0 | AD34: =SUMIFS('Combined P&L'!AF:AF,'Combined P&L'!$C:$C,'P&L Overview'!$B34) -> 0 | AE34: =SUMIFS('Combined P&L'!AG:AG,'Combined P&L'!$C:$C,'P&L Overview'!$B34) -> 0 | AF34: =SUMIFS('Combined P&L'!AH:AH,'Combined P&L'!$C:$C,'P&L Overview'!$B34) -> 0 | AG34: =SUMIFS('Combined P&L'!AI:AI,'Combined P&L'!$C:$C,'P&L Overview'!$B34) -> 0 | AH34: =SUMIFS('Combined P&L'!AJ:AJ,'Combined P&L'!$C:$C,'P&L Overview'!$B34) -> 0 | AI34: =SUMIFS('Combined P&L'!AK:AK,'Combined P&L'!$C:$C,'P&L Overview'!$B34) -> 0 | AJ34: =SUMIFS('Combined P&L'!AL:AL,'Combined P&L'!$C:$C,'P&L Overview'!$B34) -> 0 | AK34: =SUMIFS('Combined P&L'!AM:AM,'Combined P&L'!$C:$C,'P&L Overview'!$B34) -> 0 | AL34: =SUMIFS('Combined P&L'!AN:AN,'Combined P&L'!$C:$C,'P&L Overview'!$B34) -> 0 | AM34: =SUMIFS('Combined P&L'!AO:AO,'Combined P&L'!$C:$C,'P&L Overview'!$B34) -> 0 | AN34: =SUMIFS('Combined P&L'!AP:AP,'Combined P&L'!$C:$C,'P&L Overview'!$B34) -> 2.51706 | AO34: =SUMIFS('Combined P&L'!AQ:AQ,'Combined P&L'!$C:$C,'P&L Overview'!$B34) -> 2.72117 | AP34: =SUMIFS('Combined P&L'!AR:AR,'Combined P&L'!$C:$C,'P&L Overview'!$B34) -> 2.75677
C42: 45291 | D42: =C43 -> 45657 | F42: 45657 | G42: 46022 | I42: 45473 | J42: =I43 -> 45838
C43: =EOMONTH(C42,12) -> 45657 | D43: =EOMONTH(D42,12) -> 46022 | F43: 45869 | G43: =EOMONTH(G42,12) -> 46387 | I43: =EOMONTH(I42,12) -> 45838 | J43: =EOMONTH(J42,12) -> 46203

Sheet P&L Forecast
B2: =+Cover!B24 -> Keystone Bookkeepers
B3: Summary P&L Overview ($000s)
B5: Revenue Assumptions | D5: Rationale
B6: =+B71 -> STR Subscription | C6: =+AT71*12 -> 2410.05 | D6: Annualized most recent month
B7: =+B73 -> SMB Subscription | C7: =+AT73*12 -> 119.706 | D7: Annualized most recent month
B8: =+B72 -> Occupancy Taxes | C8: =+AT72*12 -> 192.8298 | D8: Annualized most recent month
B9: =+B74 -> Onboarding | C9: =AVERAGE(AM74:AT74)*12 -> 103.5675 | D9: Annualilized the Dec'25 - July'26 average (period with increased onboarding staffing)
B10: =+B76 -> STR Bill Pay | C10: =+AT76*12 -> 83.46 | D10: Annualized most recent month
B11: =+B75 -> Topkey Subscription | C11: =+AT75*12 -> 94.836 | D11: Annualized most recent month
B12: =+B77 -> Controller Services | C12: =+AT77*12 -> 42 | D12: Annualized most recent month
B13: =+B78 -> Historical Cleanup | C13: =+AT78*12 -> 0 | D13: Account appears to have been reclassified
B14: =+B79 -> Total Recurring Revenue | C14: =SUM(C6:C13) -> 3046.4493
B16: =+B82 -> 1099 Filing | C16: 0 | D16: Conservative approach for nonrecurring items
B17: =+B83 -> Income Tax | C17: 0 | D17: Conservative approach for nonrecurring items
B18: =+B81 -> Profit Share | C18: =AVERAGE(AI81:AT81)*12 -> 16.83622 | D18: Annualized LTM average
B19: =+B84 -> Billable Expense Income | C19: 0 | D19: Conservative approach for nonrecurring items
B20: =+B85 -> Offshore Recruiting | C20: 0 | D20: Conservative approach for nonrecurring items
B21: =+B86 -> Total Nonrecurring Revenue | C21: =SUM(C16:C20) -> 16.83622
B23: Payroll Assumptions
B24: Indirect Labor | C24: =AT91*12 -> 694.74456 | D24: Annualized most recent month
B25: Bookkeeper Wages | C25: =AT92*12 -> 533.8512 | D25: Annualized most recent month
B26: Owner Wages | C26: 200 | D26: Go-forward seller compensation (salary + benefits + bonus)
B27: Client Lead Wages | C27: =AT93*12 -> 392.92452 | D27: Annualized most recent month
B28: S&M Wages | C28: =AT96*12 -> 98.34912 | D28: Annualized most recent month
B29: Occupancy Tax Specialist | C29: =AT97*12 -> 68.1132 | D29: Annualized most recent month
B30: Sr. Client Lead Wages | C30: =AT98*12 -> 33.08124 | D30: Annualized most recent month
B31: Onboarding Team Wages | C31: =AT95*12 -> 197.14944 | D31: Annualized most recent month
B32: =+B99 -> Employee Benefits | C32: =+AT99*12 -> 32.17836 | D32: Annualized most recent month
B33: =+B100 -> Total Payroll Expenses | C33: =SUM(C24:C32) -> 2250.3916
B35: Software Assumptions
B36: =+B102 -> Software & Apps - COGS | C36: =+AT102*12 -> 335.70816 | D36: Annualized most recent month
B37: =+B103 -> Software & Apps - G&A | C37: =+AT103*12 -> 155.82264 | D37: Annualized most recent month
B38: =+B104 -> Software & Apps - Topkey | C38: =AT104*12 -> 60.84 | D38: Annualized most recent month
B39: =+B105 -> Software & Apps - AI tools | C39: =+AT105*12 -> 15.74376 | D39: Annualized most recent month
B40: =+B106 -> Total Software Expenses | C40: =SUM(C36:C39) -> 568.11456
B42: Opex Assumptions
B43: =+B108 -> Other Professional Fees | C43: =+J108 -> 53.62695 | D43: Assuming no material change | K43: *Re-sort
B44: =+B123 -> Contract Labor - Tax | C44: 0 | D44: Removing associated expenses for nonrecurring items
B45: Referral Fees | C45: =+J109 -> 30.69416 | D45: Assuming no material change
B46: =+B110 -> Travel, Meals & Entertainment | C46: =+J110 -> 28.23873 | D46: Assuming no material change
B47: =+B111 -> Payment Collection Fees | C47: =+J111 -> 15.6528 | D47: Assuming no material change
B48: =+B112 -> Professional Organizations | C48: =+J112 -> 12.15692 | D48: Assuming no material change
B49: =+B113 -> S&M Events | C49: =+J113 -> 11.64878 | D49: Assuming no material change
B50: =+B114 -> Recruiting Fees | C50: =+J114 -> 8.84585 | D50: Assuming no material change
B51: =+B116 -> Website | C51: =+J116 -> 4.90357 | D51: Assuming no material change
B52: =+B117 -> State Taxes | C52: =+J117 -> 5.262 | D52: Assuming no material change
B53: =+B118 -> Insurance | C53: =+J118 -> 4.89769 | D53: Assuming no material change
B54: =+B120 -> Utilities | C54: =+J120 -> 3.168 | D54: Assuming no material change
B55: =+B122 -> 1099 Filing Fees | C55: 0 | D55: Removing associated expenses for nonrecurring items
B56: =+B115 -> Amortization | C56: =+J115 -> 6.673 | D56: Assuming no material change
B57: =+B119 -> Occupancy Tax Filing Fees | C57: =+AT120*12 -> 3.516 | D57: Annualized most recent month
B58: =+B117 -> State Taxes | C58: =+J121 -> 1.49847 | D58: Assuming no material change
B59: =+B114 -> Recruiting Fees
B60: =+B124 -> Other Income | C60: =+J124 -> -0.27642 | D60: Assuming no material change
B61: =+B125 -> Other Expenses | C61: =+J125 -> 17.95601 | D61: Assuming no material change
B63: Steady-State Assumptions
B64: Software Engineer | C64: 100 | D64: $100K addback as stated by seller
A69: x | B69: P&L Summary ($000s) | C69: FY2024 | D69: FY2025 | F69: July'25 YTD | G69: July'26 YTD | I69: Jul'25 LTM | J69: Jul'26 LTM | K69: Jul'26 PF | M69: Delta ($) | N69: Delta (%) | P69: 45292 | Q69: =EOMONTH(P69,0)+1 -> 45323 | R69: =EOMONTH(Q69,0)+1 -> 45352 | S69: =EOMONTH(R69,0)+1 -> 45383 | T69: =EOMONTH(S69,0)+1 -> 45413 | U69: =EOMONTH(T69,0)+1 -> 45444 | V69: =EOMONTH(U69,0)+1 -> 45474 | W69: =EOMONTH(V69,0)+1 -> 45505 | X69: =EOMONTH(W69,0)+1 -> 45536 | ... AT69: =EOMONTH(AS69,0)+1 -> 46204
B70: Revenue
B71: STR Subscription | C71: =SUMIFS($P71:$AT71,$P$69:$AT$69,">"&C$169,$P$69:$AT$69,"<"&C$170) -> 793.47225 | D71: =SUMIFS($P71:$AT71,$P$69:$AT$69,">"&D$169,$P$69:$AT$69,"<"&D$170) -> 1450.4923 | F71: =SUMIFS($P71:$AT71,$P$69:$AT$69,">"&F$169,$P$69:$AT$69,"<"&F$170) -> 751.5286 | G71: =SUMIFS($P71:$AT71,$P$69:$AT$69,">"&G$169,$P$69:$AT$69,"<"&G$170) -> 1261.4769 | I71: =SUMIFS($P71:$AT71,$P$69:$AT$69,">"&I$169,$P$69:$AT$69,"<"&I$170) -> 1098.5075 | J71: =SUMIFS($P71:$AT71,$P$69:$AT$69,">"&J$169,$P$69:$AT$69,"<"&J$170) -> 1881.6971 | K71: =+C6 -> 2410.05 | M71: =K71-J71 -> 528.3529 | N71: =IFERROR(K71/J71-1,0) -> 0.28078531 | P71: =SUMIFS('Combined P&L'!N:N,'Combined P&L'!$C:$C,'P&L Forecast'!$B71) -> 44.6835 | Q71: =SUMIFS('Combined P&L'!O:O,'Combined P&L'!$C:$C,'P&L Forecast'!$B71) -> 47.046 | R71: =SUMIFS('Combined P&L'!P:P,'Combined P&L'!$C:$C,'P&L Forecast'!$B71) -> 52.47 | S71: =SUMIFS('Combined P&L'!Q:Q,'Combined P&L'!$C:$C,'P&L Forecast'!$B71) -> 57.1697 | T71: =SUMIFS('Combined P&L'!R:R,'Combined P&L'!$C:$C,'P&L Forecast'!$B71) -> 57.51415 | U71: =SUMIFS('Combined P&L'!S:S,'Combined P&L'!$C:$C,'P&L Forecast'!$B71) -> 65.516 | V71: =SUMIFS('Combined P&L'!T:T,'Combined P&L'!$C:$C,'P&L Forecast'!$B71) -> 68.28125 | W71: =SUMIFS('Combined P&L'!U:U,'Combined P&L'!$C:$C,'P&L Forecast'!$B71) -> 73.25135 | X71: =SUMIFS('Combined P&L'!V:V,'Combined P&L'!$C:$C,'P&L Forecast'!$B71) -> 75.5517 | Y71: =SUMIFS('Combined P&L'!W:W,'Combined P&L'!$C:$C,'P&L Forecast'!$B71) -> 79.11325 | Z71: =SUMIFS('Combined P&L'!X:X,'Combined P&L'!$C:$C,'P&L Forecast'!$B71) -> 83.2908 | AA71: =SUMIFS('Combined P&L'!Y:Y,'Combined P&L'!$C:$C,'P&L Forecast'!$B71) -> 89.58455 | AB71: =SUMIFS('Combined P&L'!Z:Z,'Combined P&L'!$C:$C,'P&L Forecast'!$B71) -> 92.4189 | AC71: =SUMIFS('Combined P&L'!AA:AA,'Combined P&L'!$C:$C,'P&L Forecast'!$B71) -> 94.00215 | AD71: =SUMIFS('Combined P&L'!AB:AB,'Combined P&L'!$C:$C,'P&L Forecast'!$B71) -> 101.50605 | AE71: =SUMIFS('Combined P&L'!AC:AC,'Combined P&L'!$C:$C,'P&L Forecast'!$B71) -> 106.1375 | AF71: =SUMIFS('Combined P&L'!AD:AD,'Combined P&L'!$C:$C,'P&L Forecast'!$B71) -> 115.93875 | AG71: =SUMIFS('Combined P&L'!AE:AE,'Combined P&L'!$C:$C,'P&L Forecast'!$B71) -> 119.43125 | AH71: =SUMIFS('Combined P&L'!AF:AF,'Combined P&L'!$C:$C,'P&L Forecast'!$B71) -> 122.094 | AI71: =SUMIFS('Combined P&L'!AG:AG,'Combined P&L'!$C:$C,'P&L Forecast'!$B71) -> 130.08525 | AJ71: =SUMIFS('Combined P&L'!AH:AH,'Combined P&L'!$C:$C,'P&L Forecast'!$B71) -> 133.5905 | AK71: =SUMIFS('Combined P&L'!AI:AI,'Combined P&L'!$C:$C,'P&L Forecast'!$B71) -> 139.609 | AL71: =SUMIFS('Combined P&L'!AJ:AJ,'Combined P&L'!$C:$C,'P&L Forecast'!$B71) -> 145.28075 | AM71: =SUMIFS('Combined P&L'!AK:AK,'Combined P&L'!$C:$C,'P&L Forecast'!$B71) -> 150.39825 | AN71: =SUMIFS('Combined P&L'!AL:AL,'Combined P&L'!$C:$C,'P&L Forecast'!$B71) -> 156.5388 | AO71: =SUMIFS('Combined P&L'!AM:AM,'Combined P&L'!$C:$C,'P&L Forecast'!$B71) -> 164.9034 | AP71: =SUMIFS('Combined P&L'!AN:AN,'Combined P&L'!$C:$C,'P&L Forecast'!$B71) -> 170.34425 | AQ71: =SUMIFS('Combined P&L'!AO:AO,'Combined P&L'!$C:$C,'P&L Forecast'!$B71) -> 183.662 | AR71: =SUMIFS('Combined P&L'!AP:AP,'Combined P&L'!$C:$C,'P&L Forecast'!$B71) -> 190.7844 | AS71: =SUMIFS('Combined P&L'!AQ:AQ,'Combined P&L'!$C:$C,'P&L Forecast'!$B71) -> 194.4065 | AT71: =SUMIFS('Combined P&L'!AR:AR,'Combined P&L'!$C:$C,'P&L Forecast'!$B71) -> 200.8375
B72: Occupancy Taxes | C72: =SUMIFS($P72:$AT72,$P$69:$AT$69,">"&C$169,$P$69:$AT$69,"<"&C$170) -> 0.56 | D72: =SUMIFS($P72:$AT72,$P$69:$AT$69,">"&D$169,$P$69:$AT$69,"<"&D$170) -> 55.0805 | F72: =SUMIFS($P72:$AT72,$P$69:$AT$69,">"&F$169,$P$69:$AT$69,"<"&F$170) -> 23.2255 | G72: =SUMIFS($P72:$AT72,$P$69:$AT$69,">"&G$169,$P$69:$AT$69,"<"&G$170) -> 91.65114 | I72: =SUMIFS($P72:$AT72,$P$69:$AT$69,">"&I$169,$P$69:$AT$69,"<"&I$170) -> 18.727 | J72: =SUMIFS($P72:$AT72,$P$69:$AT$69,">"&J$169,$P$69:$AT$69,"<"&J$170) -> 112.49549 | K72: =+C8 -> 192.8298 | M72: =K72-J72 -> 80.33431 | N72: =IFERROR(K72/J72-1,0) -> 0.71411138 | P72: =SUMIFS('Combined P&L'!N:N,'Combined P&L'!$C:$C,'P&L Forecast'!$B72) -> 0 | Q72: =SUMIFS('Combined P&L'!O:O,'Combined P&L'!$C:$C,'P&L Forecast'!$B72) -> 0 | R72: =SUMIFS('Combined P&L'!P:P,'Combined P&L'!$C:$C,'P&L Forecast'!$B72) -> 0 | S72: =SUMIFS('Combined P&L'!Q:Q,'Combined P&L'!$C:$C,'P&L Forecast'!$B72) -> 0 | T72: =SUMIFS('Combined P&L'!R:R,'Combined P&L'!$C:$C,'P&L Forecast'!$B72) -> 0 | U72: =SUMIFS('Combined P&L'!S:S,'Combined P&L'!$C:$C,'P&L Forecast'!$B72) -> 0 | V72: =SUMIFS('Combined P&L'!T:T,'Combined P&L'!$C:$C,'P&L Forecast'!$B72) -> 0 | W72: =SUMIFS('Combined P&L'!U:U,'Combined P&L'!$C:$C,'P&L Forecast'!$B72) -> 0 | X72: =SUMIFS('Combined P&L'!V:V,'Combined P&L'!$C:$C,'P&L Forecast'!$B72) -> 0 | Y72: =SUMIFS('Combined P&L'!W:W,'Combined P&L'!$C:$C,'P&L Forecast'!$B72) -> 0 | Z72: =SUMIFS('Combined P&L'!X:X,'Combined P&L'!$C:$C,'P&L Forecast'!$B72) -> 0.08 | AA72: =SUMIFS('Combined P&L'!Y:Y,'Combined P&L'!$C:$C,'P&L Forecast'!$B72) -> 0.48 | AB72: =SUMIFS('Combined P&L'!Z:Z,'Combined P&L'!$C:$C,'P&L Forecast'!$B72) -> 1.13 | AC72: =SUMIFS('Combined P&L'!AA:AA,'Combined P&L'!$C:$C,'P&L Forecast'!$B72) -> 2.14 | AD72: =SUMIFS('Combined P&L'!AB:AB,'Combined P&L'!$C:$C,'P&L Forecast'!$B72) -> 2.66 | AE72: =SUMIFS('Combined P&L'!AC:AC,'Combined P&L'!$C:$C,'P&L Forecast'!$B72) -> 3.65 | AF72: =SUMIFS('Combined P&L'!AD:AD,'Combined P&L'!$C:$C,'P&L Forecast'!$B72) -> 3.623 | AG72: =SUMIFS('Combined P&L'!AE:AE,'Combined P&L'!$C:$C,'P&L Forecast'!$B72) -> 4.964 | AH72: =SUMIFS('Combined P&L'!AF:AF,'Combined P&L'!$C:$C,'P&L Forecast'!$B72) -> 5.0585 | AI72: =SUMIFS('Combined P&L'!AG:AG,'Combined P&L'!$C:$C,'P&L Forecast'!$B72) -> 4.73 | AJ72: =SUMIFS('Combined P&L'!AH:AH,'Combined P&L'!$C:$C,'P&L Forecast'!$B72) -> 4.82 | AK72: =SUMIFS('Combined P&L'!AI:AI,'Combined P&L'!$C:$C,'P&L Forecast'!$B72) -> 5.37 | AL72: =SUMIFS('Combined P&L'!AJ:AJ,'Combined P&L'!$C:$C,'P&L Forecast'!$B72) -> 8.05 | AM72: =SUMIFS('Combined P&L'!AK:AK,'Combined P&L'!$C:$C,'P&L Forecast'!$B72) -> 8.885 | AN72: =SUMIFS('Combined P&L'!AL:AL,'Combined P&L'!$C:$C,'P&L Forecast'!$B72) -> 10.90952 | AO72: =SUMIFS('Combined P&L'!AM:AM,'Combined P&L'!$C:$C,'P&L Forecast'!$B72) -> 10.33497 | AP72: =SUMIFS('Combined P&L'!AN:AN,'Combined P&L'!$C:$C,'P&L Forecast'!$B72) -> 11.175 | AQ72: =SUMIFS('Combined P&L'!AO:AO,'Combined P&L'!$C:$C,'P&L Forecast'!$B72) -> 11.95311 | AR72: =SUMIFS('Combined P&L'!AP:AP,'Combined P&L'!$C:$C,'P&L Forecast'!$B72) -> 15.04071 | AS72: =SUMIFS('Combined P&L'!AQ:AQ,'Combined P&L'!$C:$C,'P&L Forecast'!$B72) -> 16.16868 | AT72: =SUMIFS('Combined P&L'!AR:AR,'Combined P&L'!$C:$C,'P&L Forecast'!$B72) -> 16.06915
B73: SMB Subscription | C73: =SUMIFS($P73:$AT73,$P$69:$AT$69,">"&C$169,$P$69:$AT$69,"<"&C$170) -> 224.791 | D73: =SUMIFS($P73:$AT73,$P$69:$AT$69,">"&D$169,$P$69:$AT$69,"<"&D$170) -> 149.77 | F73: =SUMIFS($P73:$AT73,$P$69:$AT$69,">"&F$169,$P$69:$AT$69,"<"&F$170) -> 90.4525 | G73: =SUMIFS($P73:$AT73,$P$69:$AT$69,">"&G$169,$P$69:$AT$69,"<"&G$170) -> 73.4185 | I73: =SUMIFS($P73:$AT73,$P$69:$AT$69,">"&I$169,$P$69:$AT$69,"<"&I$170) -> 174.63 | J73: =SUMIFS($P73:$AT73,$P$69:$AT$69,">"&J$169,$P$69:$AT$69,"<"&J$170) -> 135.298 | K73: =+C7 -> 119.706 | M73: =K73-J73 -> -15.592 | N73: =IFERROR(K73/J73-1,0) -> -0.11524191 | P73: =SUMIFS('Combined P&L'!N:N,'Combined P&L'!$C:$C,'P&L Forecast'!$B73) -> 22.001 | Q73: =SUMIFS('Combined P&L'!O:O,'Combined P&L'!$C:$C,'P&L Forecast'!$B73) -> 22.036 | R73: =SUMIFS('Combined P&L'!P:P,'Combined P&L'!$C:$C,'P&L Forecast'!$B73) -> 22.111 | S73: =SUMIFS('Combined P&L'!Q:Q,'Combined P&L'!$C:$C,'P&L Forecast'!$B73) -> 22.146 | T73: =SUMIFS('Combined P&L'!R:R,'Combined P&L'!$C:$C,'P&L Forecast'!$B73) -> 21.966 | U73: =SUMIFS('Combined P&L'!S:S,'Combined P&L'!$C:$C,'P&L Forecast'!$B73) -> 17.816 | V73: =SUMIFS('Combined P&L'!T:T,'Combined P&L'!$C:$C,'P&L Forecast'!$B73) -> 17.621 | W73: =SUMIFS('Combined P&L'!U:U,'Combined P&L'!$C:$C,'P&L Forecast'!$B73) -> 17.536 | X73: =SUMIFS('Combined P&L'!V:V,'Combined P&L'!$C:$C,'P&L Forecast'!$B73) -> 16.426 | Y73: =SUMIFS('Combined P&L'!W:W,'Combined P&L'!$C:$C,'P&L Forecast'!$B73) -> 15.381 | Z73: =SUMIFS('Combined P&L'!X:X,'Combined P&L'!$C:$C,'P&L Forecast'!$B73) -> 14.6755 | AA73: =SUMIFS('Combined P&L'!Y:Y,'Combined P&L'!$C:$C,'P&L Forecast'!$B73) -> 15.0755 | AB73: =SUMIFS('Combined P&L'!Z:Z,'Combined P&L'!$C:$C,'P&L Forecast'!$B73) -> 14.5625 | AC73: =SUMIFS('Combined P&L'!AA:AA,'Combined P&L'!$C:$C,'P&L Forecast'!$B73) -> 12.8025 | AD73: =SUMIFS('Combined P&L'!AB:AB,'Combined P&L'!$C:$C,'P&L Forecast'!$B73) -> 12.4025 | AE73: =SUMIFS('Combined P&L'!AC:AC,'Combined P&L'!$C:$C,'P&L Forecast'!$B73) -> 12.6025 | AF73: =SUMIFS('Combined P&L'!AD:AD,'Combined P&L'!$C:$C,'P&L Forecast'!$B73) -> 12.7525 | AG73: =SUMIFS('Combined P&L'!AE:AE,'Combined P&L'!$C:$C,'P&L Forecast'!$B73) -> 12.7925 | AH73: =SUMIFS('Combined P&L'!AF:AF,'Combined P&L'!$C:$C,'P&L Forecast'!$B73) -> 12.5375 | AI73: =SUMIFS('Combined P&L'!AG:AG,'Combined P&L'!$C:$C,'P&L Forecast'!$B73) -> 11.8575 | AJ73: =SUMIFS('Combined P&L'!AH:AH,'Combined P&L'!$C:$C,'P&L Forecast'!$B73) -> 12.3025 | AK73: =SUMIFS('Combined P&L'!AI:AI,'Combined P&L'!$C:$C,'P&L Forecast'!$B73) -> 11.6925 | AL73: =SUMIFS('Combined P&L'!AJ:AJ,'Combined P&L'!$C:$C,'P&L Forecast'!$B73) -> 11.7175 | AM73: =SUMIFS('Combined P&L'!AK:AK,'Combined P&L'!$C:$C,'P&L Forecast'!$B73) -> 11.7475 | AN73: =SUMIFS('Combined P&L'!AL:AL,'Combined P&L'!$C:$C,'P&L Forecast'!$B73) -> 11.2805 | AO73: =SUMIFS('Combined P&L'!AM:AM,'Combined P&L'!$C:$C,'P&L Forecast'!$B73) -> 10.9305 | AP73: =SUMIFS('Combined P&L'!AN:AN,'Combined P&L'!$C:$C,'P&L Forecast'!$B73) -> 10.6255 | AQ73: =SUMIFS('Combined P&L'!AO:AO,'Combined P&L'!$C:$C,'P&L Forecast'!$B73) -> 10.3155 | AR73: =SUMIFS('Combined P&L'!AP:AP,'Combined P&L'!$C:$C,'P&L Forecast'!$B73) -> 10.3155 | AS73: =SUMIFS('Combined P&L'!AQ:AQ,'Combined P&L'!$C:$C,'P&L Forecast'!$B73) -> 9.9755 | AT73: =SUMIFS('Combined P&L'!AR:AR,'Combined P&L'!$C:$C,'P&L Forecast'!$B73) -> 9.9755
B74: Onboarding | C74: =SUMIFS($P74:$AT74,$P$69:$AT$69,">"&C$169,$P$69:$AT$69,"<"&C$170) -> 44.0585 | D74: =SUMIFS($P74:$AT74,$P$69:$AT$69,">"&D$169,$P$69:$AT$69,"<"&D$170) -> 74.5193 | F74: =SUMIFS($P74:$AT74,$P$69:$AT$69,">"&F$169,$P$69:$AT$69,"<"&F$170) -> 42.25405 | G74: =SUMIFS($P74:$AT74,$P$69:$AT$69,">"&G$169,$P$69:$AT$69,"<"&G$170) -> 59.055 | I74: =SUMIFS($P74:$AT74,$P$69:$AT$69,">"&I$169,$P$69:$AT$69,"<"&I$170) -> 55.66055 | J74: =SUMIFS($P74:$AT74,$P$69:$AT$69,">"&J$169,$P$69:$AT$69,"<"&J$170) -> 91.65575 | K74: =+C9 -> 103.5675 | M74: =K74-J74 -> 11.91175 | N74: =IFERROR(K74/J74-1,0) -> 0.12996184 | P74: =SUMIFS('Combined P&L'!N:N,'Combined P&L'!$C:$C,'P&L Forecast'!$B74) -> 5.465 | Q74: =SUMIFS('Combined P&L'!O:O,'Combined P&L'!$C:$C,'P&L Forecast'!$B74) -> 3.9 | R74: =SUMIFS('Combined P&L'!P:P,'Combined P&L'!$C:$C,'P&L Forecast'!$B74) -> 2.755 | S74: =SUMIFS('Combined P&L'!Q:Q,'Combined P&L'!$C:$C,'P&L Forecast'!$B74) -> 3.502 | T74: =SUMIFS('Combined P&L'!R:R,'Combined P&L'!$C:$C,'P&L Forecast'!$B74) -> 4.659 | U74: =SUMIFS('Combined P&L'!S:S,'Combined P&L'!$C:$C,'P&L Forecast'!$B74) -> 3.937 | V74: =SUMIFS('Combined P&L'!T:T,'Combined P&L'!$C:$C,'P&L Forecast'!$B74) -> 4.602 | W74: =SUMIFS('Combined P&L'!U:U,'Combined P&L'!$C:$C,'P&L Forecast'!$B74) -> 4.738 | X74: =SUMIFS('Combined P&L'!V:V,'Combined P&L'!$C:$C,'P&L Forecast'!$B74) -> 2.119 | Y74: =SUMIFS('Combined P&L'!W:W,'Combined P&L'!$C:$C,'P&L Forecast'!$B74) -> 2.064 | Z74: =SUMIFS('Combined P&L'!X:X,'Combined P&L'!$C:$C,'P&L Forecast'!$B74) -> 3.0125 | AA74: =SUMIFS('Combined P&L'!Y:Y,'Combined P&L'!$C:$C,'P&L Forecast'!$B74) -> 3.305 | AB74: =SUMIFS('Combined P&L'!Z:Z,'Combined P&L'!$C:$C,'P&L Forecast'!$B74) -> 3.079 | AC74: =SUMIFS('Combined P&L'!AA:AA,'Combined P&L'!$C:$C,'P&L Forecast'!$B74) -> 0.7 | AD74: =SUMIFS('Combined P&L'!AB:AB,'Combined P&L'!$C:$C,'P&L Forecast'!$B74) -> 10.43855 | AE74: =SUMIFS('Combined P&L'!AC:AC,'Combined P&L'!$C:$C,'P&L Forecast'!$B74) -> 4.3 | AF74: =SUMIFS('Combined P&L'!AD:AD,'Combined P&L'!$C:$C,'P&L Forecast'!$B74) -> 11.14 | AG74: =SUMIFS('Combined P&L'!AE:AE,'Combined P&L'!$C:$C,'P&L Forecast'!$B74) -> 6.1625 | AH74: =SUMIFS('Combined P&L'!AF:AF,'Combined P&L'!$C:$C,'P&L Forecast'!$B74) -> 6.434 | AI74: =SUMIFS('Combined P&L'!AG:AG,'Combined P&L'!$C:$C,'P&L Forecast'!$B74) -> 3.965 | AJ74: =SUMIFS('Combined P&L'!AH:AH,'Combined P&L'!$C:$C,'P&L Forecast'!$B74) -> 3.92 | AK74: =SUMIFS('Combined P&L'!AI:AI,'Combined P&L'!$C:$C,'P&L Forecast'!$B74) -> 9.1365 | AL74: =SUMIFS('Combined P&L'!AJ:AJ,'Combined P&L'!$C:$C,'P&L Forecast'!$B74) -> 5.25375 | AM74: =SUMIFS('Combined P&L'!AK:AK,'Combined P&L'!$C:$C,'P&L Forecast'!$B74) -> 9.99 | AN74: =SUMIFS('Combined P&L'!AL:AL,'Combined P&L'!$C:$C,'P&L Forecast'!$B74) -> 10.2105 | AO74: =SUMIFS('Combined P&L'!AM:AM,'Combined P&L'!$C:$C,'P&L Forecast'!$B74) -> 6.675 | AP74: =SUMIFS('Combined P&L'!AN:AN,'Combined P&L'!$C:$C,'P&L Forecast'!$B74) -> 9.099 | AQ74: =SUMIFS('Combined P&L'!AO:AO,'Combined P&L'!$C:$C,'P&L Forecast'!$B74) -> 8.9545 | AR74: =SUMIFS('Combined P&L'!AP:AP,'Combined P&L'!$C:$C,'P&L Forecast'!$B74) -> 12.606 | AS74: =SUMIFS('Combined P&L'!AQ:AQ,'Combined P&L'!$C:$C,'P&L Forecast'!$B74) -> 5.4115 | AT74: =SUMIFS('Combined P&L'!AR:AR,'Combined P&L'!$C:$C,'P&L Forecast'!$B74) -> 6.0985
B75: Topkey Subscription | C75: =SUMIFS($P75:$AT75,$P$69:$AT$69,">"&C$169,$P$69:$AT$69,"<"&C$170) -> 0 | D75: =SUMIFS($P75:$AT75,$P$69:$AT$69,">"&D$169,$P$69:$AT$69,"<"&D$170) -> 9.947 | F75: =SUMIFS($P75:$AT75,$P$69:$AT$69,">"&F$169,$P$69:$AT$69,"<"&F$170) -> 0 | G75: =SUMIFS($P75:$AT75,$P$69:$AT$69,">"&G$169,$P$69:$AT$69,"<"&G$170) -> 45.086 | I75: =SUMIFS($P75:$AT75,$P$69:$AT$69,">"&I$169,$P$69:$AT$69,"<"&I$170) -> 0 | J75: =SUMIFS($P75:$AT75,$P$69:$AT$69,">"&J$169,$P$69:$AT$69,"<"&J$170) -> 47.13 | K75: =+C11 -> 94.836 | M75: =K75-J75 -> 47.706 | N75: =IFERROR(K75/J75-1,0) -> 1.0122215 | P75: =SUMIFS('Combined P&L'!N:N,'Combined P&L'!$C:$C,'P&L Forecast'!$B75) -> 0 | Q75: =SUMIFS('Combined P&L'!O:O,'Combined P&L'!$C:$C,'P&L Forecast'!$B75) -> 0 | R75: =SUMIFS('Combined P&L'!P:P,'Combined P&L'!$C:$C,'P&L Forecast'!$B75) -> 0 | S75: =SUMIFS('Combined P&L'!Q:Q,'Combined P&L'!$C:$C,'P&L Forecast'!$B75) -> 0 | T75: =SUMIFS('Combined P&L'!R:R,'Combined P&L'!$C:$C,'P&L Forecast'!$B75) -> 0 | U75: =SUMIFS('Combined P&L'!S:S,'Combined P&L'!$C:$C,'P&L Forecast'!$B75) -> 0 | V75: =SUMIFS('Combined P&L'!T:T,'Combined P&L'!$C:$C,'P&L Forecast'!$B75) -> 0 | W75: =SUMIFS('Combined P&L'!U:U,'Combined P&L'!$C:$C,'P&L Forecast'!$B75) -> 0 | X75: =SUMIFS('Combined P&L'!V:V,'Combined P&L'!$C:$C,'P&L Forecast'!$B75) -> 0 | Y75: =SUMIFS('Combined P&L'!W:W,'Combined P&L'!$C:$C,'P&L Forecast'!$B75) -> 0 | Z75: =SUMIFS('Combined P&L'!X:X,'Combined P&L'!$C:$C,'P&L Forecast'!$B75) -> 0 | AA75: =SUMIFS('Combined P&L'!Y:Y,'Combined P&L'!$C:$C,'P&L Forecast'!$B75) -> 0 | AB75: =SUMIFS('Combined P&L'!Z:Z,'Combined P&L'!$C:$C,'P&L Forecast'!$B75) -> 0 | AC75: =SUMIFS('Combined P&L'!AA:AA,'Combined P&L'!$C:$C,'P&L Forecast'!$B75) -> 0 | AD75: =SUMIFS('Combined P&L'!AB:AB,'Combined P&L'!$C:$C,'P&L Forecast'!$B75) -> 0 | AE75: =SUMIFS('Combined P&L'!AC:AC,'Combined P&L'!$C:$C,'P&L Forecast'!$B75) -> 0 | AF75: =SUMIFS('Combined P&L'!AD:AD,'Combined P&L'!$C:$C,'P&L Forecast'!$B75) -> 0 | AG75: =SUMIFS('Combined P&L'!AE:AE,'Combined P&L'!$C:$C,'P&L Forecast'!$B75) -> 0 | AH75: =SUMIFS('Combined P&L'!AF:AF,'Combined P&L'!$C:$C,'P&L Forecast'!$B75) -> 0 | AI75: =SUMIFS('Combined P&L'!AG:AG,'Combined P&L'!$C:$C,'P&L Forecast'!$B75) -> 0 | AJ75: =SUMIFS('Combined P&L'!AH:AH,'Combined P&L'!$C:$C,'P&L Forecast'!$B75) -> 0.52 | AK75: =SUMIFS('Combined P&L'!AI:AI,'Combined P&L'!$C:$C,'P&L Forecast'!$B75) -> 2.357 | AL75: =SUMIFS('Combined P&L'!AJ:AJ,'Combined P&L'!$C:$C,'P&L Forecast'!$B75) -> 2.811 | AM75: =SUMIFS('Combined P&L'!AK:AK,'Combined P&L'!$C:$C,'P&L Forecast'!$B75) -> 4.259 | AN75: =SUMIFS('Combined P&L'!AL:AL,'Combined P&L'!$C:$C,'P&L Forecast'!$B75) -> 5.254 | AO75: =SUMIFS('Combined P&L'!AM:AM,'Combined P&L'!$C:$C,'P&L Forecast'!$B75) -> 5.652 | AP75: =SUMIFS('Combined P&L'!AN:AN,'Combined P&L'!$C:$C,'P&L Forecast'!$B75) -> 5.324 | AQ75: =SUMIFS('Combined P&L'!AO:AO,'Combined P&L'!$C:$C,'P&L Forecast'!$B75) -> 6.321 | AR75: =SUMIFS('Combined P&L'!AP:AP,'Combined P&L'!$C:$C,'P&L Forecast'!$B75) -> 6.959 | AS75: =SUMIFS('Combined P&L'!AQ:AQ,'Combined P&L'!$C:$C,'P&L Forecast'!$B75) -> 7.673 | AT75: =SUMIFS('Combined P&L'!AR:AR,'Combined P&L'!$C:$C,'P&L Forecast'!$B75) -> 7.903
B76: STR Bill Pay | C76: =SUMIFS($P76:$AT76,$P$69:$AT$69,">"&C$169,$P$69:$AT$69,"<"&C$170) -> 0.06 | D76: =SUMIFS($P76:$AT76,$P$69:$AT$69,">"&D$169,$P$69:$AT$69,"<"&D$170) -> 36.6065 | F76: =SUMIFS($P76:$AT76,$P$69:$AT$69,">"&F$169,$P$69:$AT$69,"<"&F$170) -> 15.4915 | G76: =SUMIFS($P76:$AT76,$P$69:$AT$69,">"&G$169,$P$69:$AT$69,"<"&G$170) -> 45.13 | I76: =SUMIFS($P76:$AT76,$P$69:$AT$69,">"&I$169,$P$69:$AT$69,"<"&I$170) -> 11.6315 | J76: =SUMIFS($P76:$AT76,$P$69:$AT$69,">"&J$169,$P$69:$AT$69,"<"&J$170) -> 63.21 | K76: =+C10 -> 83.46 | M76: =K76-J76 -> 20.25 | N76: =IFERROR(K76/J76-1,0) -> 0.3203607 | P76: =SUMIFS('Combined P&L'!N:N,'Combined P&L'!$C:$C,'P&L Forecast'!$B76) -> 0 | Q76: =SUMIFS('Combined P&L'!O:O,'Combined P&L'!$C:$C,'P&L Forecast'!$B76) -> 0 | R76: =SUMIFS('Combined P&L'!P:P,'Combined P&L'!$C:$C,'P&L Forecast'!$B76) -> 0 | S76: =SUMIFS('Combined P&L'!Q:Q,'Combined P&L'!$C:$C,'P&L Forecast'!$B76) -> 0 | T76: =SUMIFS('Combined P&L'!R:R,'Combined P&L'!$C:$C,'P&L Forecast'!$B76) -> 0 | U76: =SUMIFS('Combined P&L'!S:S,'Combined P&L'!$C:$C,'P&L Forecast'!$B76) -> 0 | V76: =SUMIFS('Combined P&L'!T:T,'Combined P&L'!$C:$C,'P&L Forecast'!$B76) -> 0 | W76: =SUMIFS('Combined P&L'!U:U,'Combined P&L'!$C:$C,'P&L Forecast'!$B76) -> 0 | X76: =SUMIFS('Combined P&L'!V:V,'Combined P&L'!$C:$C,'P&L Forecast'!$B76) -> 0 | Y76: =SUMIFS('Combined P&L'!W:W,'Combined P&L'!$C:$C,'P&L Forecast'!$B76) -> 0 | Z76: =SUMIFS('Combined P&L'!X:X,'Combined P&L'!$C:$C,'P&L Forecast'!$B76) -> 0 | AA76: =SUMIFS('Combined P&L'!Y:Y,'Combined P&L'!$C:$C,'P&L Forecast'!$B76) -> 0.06 | AB76: =SUMIFS('Combined P&L'!Z:Z,'Combined P&L'!$C:$C,'P&L Forecast'!$B76) -> 0.97 | AC76: =SUMIFS('Combined P&L'!AA:AA,'Combined P&L'!$C:$C,'P&L Forecast'!$B76) -> 1.1 | AD76: =SUMIFS('Combined P&L'!AB:AB,'Combined P&L'!$C:$C,'P&L Forecast'!$B76) -> 1.735 | AE76: =SUMIFS('Combined P&L'!AC:AC,'Combined P&L'!$C:$C,'P&L Forecast'!$B76) -> 2.14 | AF76: =SUMIFS('Combined P&L'!AD:AD,'Combined P&L'!$C:$C,'P&L Forecast'!$B76) -> 2.363 | AG76: =SUMIFS('Combined P&L'!AE:AE,'Combined P&L'!$C:$C,'P&L Forecast'!$B76) -> 3.2635 | AH76: =SUMIFS('Combined P&L'!AF:AF,'Combined P&L'!$C:$C,'P&L Forecast'!$B76) -> 3.92 | AI76: =SUMIFS('Combined P&L'!AG:AG,'Combined P&L'!$C:$C,'P&L Forecast'!$B76) -> 3.905 | AJ76: =SUMIFS('Combined P&L'!AH:AH,'Combined P&L'!$C:$C,'P&L Forecast'!$B76) -> 3.78 | AK76: =SUMIFS('Combined P&L'!AI:AI,'Combined P&L'!$C:$C,'P&L Forecast'!$B76) -> 3.795 | AL76: =SUMIFS('Combined P&L'!AJ:AJ,'Combined P&L'!$C:$C,'P&L Forecast'!$B76) -> 4.33 | AM76: =SUMIFS('Combined P&L'!AK:AK,'Combined P&L'!$C:$C,'P&L Forecast'!$B76) -> 5.305 | AN76: =SUMIFS('Combined P&L'!AL:AL,'Combined P&L'!$C:$C,'P&L Forecast'!$B76) -> 6.3 | AO76: =SUMIFS('Combined P&L'!AM:AM,'Combined P&L'!$C:$C,'P&L Forecast'!$B76) -> 6.39 | AP76: =SUMIFS('Combined P&L'!AN:AN,'Combined P&L'!$C:$C,'P&L Forecast'!$B76) -> 6.425 | AQ76: =SUMIFS('Combined P&L'!AO:AO,'Combined P&L'!$C:$C,'P&L Forecast'!$B76) -> 6.08 | AR76: =SUMIFS('Combined P&L'!AP:AP,'Combined P&L'!$C:$C,'P&L Forecast'!$B76) -> 6.325 | AS76: =SUMIFS('Combined P&L'!AQ:AQ,'Combined P&L'!$C:$C,'P&L Forecast'!$B76) -> 6.655 | AT76: =SUMIFS('Combined P&L'!AR:AR,'Combined P&L'!$C:$C,'P&L Forecast'!$B76) -> 6.955
B77: Controller Services | C77: =SUMIFS($P77:$AT77,$P$69:$AT$69,">"&C$169,$P$69:$AT$69,"<"&C$170) -> 13.75 | D77: =SUMIFS($P77:$AT77,$P$69:$AT$69,">"&D$169,$P$69:$AT$69,"<"&D$170) -> 46.4 | F77: =SUMIFS($P77:$AT77,$P$69:$AT$69,">"&F$169,$P$69:$AT$69,"<"&F$170) -> 31.5 | G77: =SUMIFS($P77:$AT77,$P$69:$AT$69,">"&G$169,$P$69:$AT$69,"<"&G$170) -> 24.25 | I77: =SUMIFS($P77:$AT77,$P$69:$AT$69,">"&I$169,$P$69:$AT$69,"<"&I$170) -> 41.25 | J77: =SUMIFS($P77:$AT77,$P$69:$AT$69,">"&J$169,$P$69:$AT$69,"<"&J$170) -> 39.65 | K77: =+C12 -> 42 | M77: =K77-J77 -> 2.35 | N77: =IFERROR(K77/J77-1,0) -> 0.0592686 | P77: =SUMIFS('Combined P&L'!N:N,'Combined P&L'!$C:$C,'P&L Forecast'!$B77) -> 0 | Q77: =SUMIFS('Combined P&L'!O:O,'Combined P&L'!$C:$C,'P&L Forecast'!$B77) -> 0 | R77: =SUMIFS('Combined P&L'!P:P,'Combined P&L'!$C:$C,'P&L Forecast'!$B77) -> 0 | S77: =SUMIFS('Combined P&L'!Q:Q,'Combined P&L'!$C:$C,'P&L Forecast'!$B77) -> 0 | T77: =SUMIFS('Combined P&L'!R:R,'Combined P&L'!$C:$C,'P&L Forecast'!$B77) -> 0 | U77: =SUMIFS('Combined P&L'!S:S,'Combined P&L'!$C:$C,'P&L Forecast'!$B77) -> 0 | V77: =SUMIFS('Combined P&L'!T:T,'Combined P&L'!$C:$C,'P&L Forecast'!$B77) -> 1.25 | W77: =SUMIFS('Combined P&L'!U:U,'Combined P&L'!$C:$C,'P&L Forecast'!$B77) -> 1.25 | X77: =SUMIFS('Combined P&L'!V:V,'Combined P&L'!$C:$C,'P&L Forecast'!$B77) -> 1.25 | Y77: =SUMIFS('Combined P&L'!W:W,'Combined P&L'!$C:$C,'P&L Forecast'!$B77) -> 1.25 | Z77: =SUMIFS('Combined P&L'!X:X,'Combined P&L'!$C:$C,'P&L Forecast'!$B77) -> 5.75 | AA77: =SUMIFS('Combined P&L'!Y:Y,'Combined P&L'!$C:$C,'P&L Forecast'!$B77) -> 3 | AB77: =SUMIFS('Combined P&L'!Z:Z,'Combined P&L'!$C:$C,'P&L Forecast'!$B77) -> 4.45 | AC77: =SUMIFS('Combined P&L'!AA:AA,'Combined P&L'!$C:$C,'P&L Forecast'!$B77) -> 3.45 | AD77: =SUMIFS('Combined P&L'!AB:AB,'Combined P&L'!$C:$C,'P&L Forecast'!$B77) -> 3.45 | AE77: =SUMIFS('Combined P&L'!AC:AC,'Combined P&L'!$C:$C,'P&L Forecast'!$B77) -> 5.95 | AF77: =SUMIFS('Combined P&L'!AD:AD,'Combined P&L'!$C:$C,'P&L Forecast'!$B77) -> 5.2 | AG77: =SUMIFS('Combined P&L'!AE:AE,'Combined P&L'!$C:$C,'P&L Forecast'!$B77) -> 5 | AH77: =SUMIFS('Combined P&L'!AF:AF,'Combined P&L'!$C:$C,'P&L Forecast'!$B77) -> 4 | AI77: =SUMIFS('Combined P&L'!AG:AG,'Combined P&L'!$C:$C,'P&L Forecast'!$B77) -> 2.95 | AJ77: =SUMIFS('Combined P&L'!AH:AH,'Combined P&L'!$C:$C,'P&L Forecast'!$B77) -> 3.025 | AK77: =SUMIFS('Combined P&L'!AI:AI,'Combined P&L'!$C:$C,'P&L Forecast'!$B77) -> 3.025 | AL77: =SUMIFS('Combined P&L'!AJ:AJ,'Combined P&L'!$C:$C,'P&L Forecast'!$B77) -> 2.95 | AM77: =SUMIFS('Combined P&L'!AK:AK,'Combined P&L'!$C:$C,'P&L Forecast'!$B77) -> 2.95 | AN77: =SUMIFS('Combined P&L'!AL:AL,'Combined P&L'!$C:$C,'P&L Forecast'!$B77) -> 2.75 | AO77: =SUMIFS('Combined P&L'!AM:AM,'Combined P&L'!$C:$C,'P&L Forecast'!$B77) -> 3.5 | AP77: =SUMIFS('Combined P&L'!AN:AN,'Combined P&L'!$C:$C,'P&L Forecast'!$B77) -> 2.75 | AQ77: =SUMIFS('Combined P&L'!AO:AO,'Combined P&L'!$C:$C,'P&L Forecast'!$B77) -> 4.75 | AR77: =SUMIFS('Combined P&L'!AP:AP,'Combined P&L'!$C:$C,'P&L Forecast'!$B77) -> 3.5 | AS77: =SUMIFS('Combined P&L'!AQ:AQ,'Combined P&L'!$C:$C,'P&L Forecast'!$B77) -> 3.5 | AT77: =SUMIFS('Combined P&L'!AR:AR,'Combined P&L'!$C:$C,'P&L Forecast'!$B77) -> 3.5
B78: Historical Cleanup | C78: =SUMIFS($P78:$AT78,$P$69:$AT$69,">"&C$169,$P$69:$AT$69,"<"&C$170) -> 17.624 | D78: =SUMIFS($P78:$AT78,$P$69:$AT$69,">"&D$169,$P$69:$AT$69,"<"&D$170) -> 5.03375 | F78: =SUMIFS($P78:$AT78,$P$69:$AT$69,">"&F$169,$P$69:$AT$69,"<"&F$170) -> 4.43875 | G78: =SUMIFS($P78:$AT78,$P$69:$AT$69,">"&G$169,$P$69:$AT$69,"<"&G$170) -> 0 | I78: =SUMIFS($P78:$AT78,$P$69:$AT$69,">"&I$169,$P$69:$AT$69,"<"&I$170) -> 14.30525 | J78: =SUMIFS($P78:$AT78,$P$69:$AT$69,">"&J$169,$P$69:$AT$69,"<"&J$170) -> 0.595 | K78: =+C13 -> 0 | M78: =K78-J78 -> -0.595 | N78: =IFERROR(K78/J78-1,0) -> -1 | P78: =SUMIFS('Combined P&L'!N:N,'Combined P&L'!$C:$C,'P&L Forecast'!$B78) -> 1.2 | Q78: =SUMIFS('Combined P&L'!O:O,'Combined P&L'!$C:$C,'P&L Forecast'!$B78) -> 1.7625 | R78: =SUMIFS('Combined P&L'!P:P,'Combined P&L'!$C:$C,'P&L Forecast'!$B78) -> 0.66 | S78: =SUMIFS('Combined P&L'!Q:Q,'Combined P&L'!$C:$C,'P&L Forecast'!$B78) -> 0.395 | T78: =SUMIFS('Combined P&L'!R:R,'Combined P&L'!$C:$C,'P&L Forecast'!$B78) -> 2.465 | U78: =SUMIFS('Combined P&L'!S:S,'Combined P&L'!$C:$C,'P&L Forecast'!$B78) -> 1.275 | V78: =SUMIFS('Combined P&L'!T:T,'Combined P&L'!$C:$C,'P&L Forecast'!$B78) -> 1.4625 | W78: =SUMIFS('Combined P&L'!U:U,'Combined P&L'!$C:$C,'P&L Forecast'!$B78) -> 0 | X78: =SUMIFS('Combined P&L'!V:V,'Combined P&L'!$C:$C,'P&L Forecast'!$B78) -> 1.14525 | Y78: =SUMIFS('Combined P&L'!W:W,'Combined P&L'!$C:$C,'P&L Forecast'!$B78) -> 1.35525 | Z78: =SUMIFS('Combined P&L'!X:X,'Combined P&L'!$C:$C,'P&L Forecast'!$B78) -> 1.9035 | AA78: =SUMIFS('Combined P&L'!Y:Y,'Combined P&L'!$C:$C,'P&L Forecast'!$B78) -> 4 | AB78: =SUMIFS('Combined P&L'!Z:Z,'Combined P&L'!$C:$C,'P&L Forecast'!$B78) -> 1.08375 | AC78: =SUMIFS('Combined P&L'!AA:AA,'Combined P&L'!$C:$C,'P&L Forecast'!$B78) -> 2 | AD78: =SUMIFS('Combined P&L'!AB:AB,'Combined P&L'!$C:$C,'P&L Forecast'!$B78) -> 1.355 | AE78: =SUMIFS('Combined P&L'!AC:AC,'Combined P&L'!$C:$C,'P&L Forecast'!$B78) -> 0 | AF78: =SUMIFS('Combined P&L'!AD:AD,'Combined P&L'!$C:$C,'P&L Forecast'!$B78) -> 0 | AG78: =SUMIFS('Combined P&L'!AE:AE,'Combined P&L'!$C:$C,'P&L Forecast'!$B78) -> 0 | AH78: =SUMIFS('Combined P&L'!AF:AF,'Combined P&L'!$C:$C,'P&L Forecast'!$B78) -> 0 | AI78: =SUMIFS('Combined P&L'!AG:AG,'Combined P&L'!$C:$C,'P&L Forecast'!$B78) -> 0 | AJ78: =SUMIFS('Combined P&L'!AH:AH,'Combined P&L'!$C:$C,'P&L Forecast'!$B78) -> 0 | AK78: =SUMIFS('Combined P&L'!AI:AI,'Combined P&L'!$C:$C,'P&L Forecast'!$B78) -> 0.595 | AL78: =SUMIFS('Combined P&L'!AJ:AJ,'Combined P&L'!$C:$C,'P&L Forecast'!$B78) -> 0 | AM78: =SUMIFS('Combined P&L'!AK:AK,'Combined P&L'!$C:$C,'P&L Forecast'!$B78) -> 0 | AN78: =SUMIFS('Combined P&L'!AL:AL,'Combined P&L'!$C:$C,'P&L Forecast'!$B78) -> 0 | AO78: =SUMIFS('Combined P&L'!AM:AM,'Combined P&L'!$C:$C,'P&L Forecast'!$B78) -> 0 | AP78: =SUMIFS('Combined P&L'!AN:AN,'Combined P&L'!$C:$C,'P&L Forecast'!$B78) -> 0 | AQ78: =SUMIFS('Combined P&L'!AO:AO,'Combined P&L'!$C:$C,'P&L Forecast'!$B78) -> 0 | AR78: =SUMIFS('Combined P&L'!AP:AP,'Combined P&L'!$C:$C,'P&L Forecast'!$B78) -> 0 | AS78: =SUMIFS('Combined P&L'!AQ:AQ,'Combined P&L'!$C:$C,'P&L Forecast'!$B78) -> 0 | AT78: =SUMIFS('Combined P&L'!AR:AR,'Combined P&L'!$C:$C,'P&L Forecast'!$B78) -> 0
B79: Total Recurring Revenue | C79: =SUM(C71:C78) -> 1094.3157 | D79: =SUM(D71:D78) -> 1827.8494 | F79: =SUM(F71:F78) -> 958.8909 | G79: =SUM(G71:G78) -> 1600.0675 | I79: =SUM(I71:I78) -> 1414.7118 | J79: =SUM(J71:J78) -> 2371.7313 | K79: =SUM(K71:K78) -> 3046.4493 | M79: =SUM(M71:M78) -> 674.71796 | N79: =IFERROR(K79/J79-1,0) -> 0.2844833 | P79: =SUM(P71:P78) -> 73.3495 | Q79: =SUM(Q71:Q78) -> 74.7445 | R79: =SUM(R71:R78) -> 77.996 | S79: =SUM(S71:S78) -> 83.2127 | T79: =SUM(T71:T78) -> 86.60415 | U79: =SUM(U71:U78) -> 88.544 | V79: =SUM(V71:V78) -> 93.21675 | W79: =SUM(W71:W78) -> 96.77535 | ... AT79: =SUM(AT71:AT78) -> 251.33865
B81: Profit Share | C81: =SUMIFS($P81:$AT81,$P$69:$AT$69,">"&C$169,$P$69:$AT$69,"<"&C$170) -> 6.2004 | D81: =SUMIFS($P81:$AT81,$P$69:$AT$69,">"&D$169,$P$69:$AT$69,"<"&D$170) -> 23.26179 | F81: =SUMIFS($P81:$AT81,$P$69:$AT$69,">"&F$169,$P$69:$AT$69,"<"&F$170) -> 14.50495 | G81: =SUMIFS($P81:$AT81,$P$69:$AT$69,">"&G$169,$P$69:$AT$69,"<"&G$170) -> 8.07938 | I81: =SUMIFS($P81:$AT81,$P$69:$AT$69,">"&I$169,$P$69:$AT$69,"<"&I$170) -> 17.94788 | J81: =SUMIFS($P81:$AT81,$P$69:$AT$69,">"&J$169,$P$69:$AT$69,"<"&J$170) -> 17.79609 | K81: =+C18 -> 16.83622 | M81: =K81-J81 -> -0.95987 | N81: =IFERROR(K81/J81-1,0) -> -0.053937129 | P81: =SUMIFS('Combined P&L'!N:N,'Combined P&L'!$C:$C,'P&L Forecast'!$B81) -> 0.0686 | Q81: =SUMIFS('Combined P&L'!O:O,'Combined P&L'!$C:$C,'P&L Forecast'!$B81) -> 0.1312 | R81: =SUMIFS('Combined P&L'!P:P,'Combined P&L'!$C:$C,'P&L Forecast'!$B81) -> 0.0712 | S81: =SUMIFS('Combined P&L'!Q:Q,'Combined P&L'!$C:$C,'P&L Forecast'!$B81) -> 0.0556 | T81: =SUMIFS('Combined P&L'!R:R,'Combined P&L'!$C:$C,'P&L Forecast'!$B81) -> 0.577 | U81: =SUMIFS('Combined P&L'!S:S,'Combined P&L'!$C:$C,'P&L Forecast'!$B81) -> 0.8068 | V81: =SUMIFS('Combined P&L'!T:T,'Combined P&L'!$C:$C,'P&L Forecast'!$B81) -> 0.6656 | W81: =SUMIFS('Combined P&L'!U:U,'Combined P&L'!$C:$C,'P&L Forecast'!$B81) -> 0.8264 | X81: =SUMIFS('Combined P&L'!V:V,'Combined P&L'!$C:$C,'P&L Forecast'!$B81) -> 1.3808 | Y81: =SUMIFS('Combined P&L'!W:W,'Combined P&L'!$C:$C,'P&L Forecast'!$B81) -> 0.8604 | Z81: =SUMIFS('Combined P&L'!X:X,'Combined P&L'!$C:$C,'P&L Forecast'!$B81) -> 0.51 | AA81: =SUMIFS('Combined P&L'!Y:Y,'Combined P&L'!$C:$C,'P&L Forecast'!$B81) -> 0.2468 | AB81: =SUMIFS('Combined P&L'!Z:Z,'Combined P&L'!$C:$C,'P&L Forecast'!$B81) -> 7.3584 | AC81: =SUMIFS('Combined P&L'!AA:AA,'Combined P&L'!$C:$C,'P&L Forecast'!$B81) -> 1.29335 | AD81: =SUMIFS('Combined P&L'!AB:AB,'Combined P&L'!$C:$C,'P&L Forecast'!$B81) -> 0.96833 | AE81: =SUMIFS('Combined P&L'!AC:AC,'Combined P&L'!$C:$C,'P&L Forecast'!$B81) -> 1.1656 | AF81: =SUMIFS('Combined P&L'!AD:AD,'Combined P&L'!$C:$C,'P&L Forecast'!$B81) -> 0.96093 | AG81: =SUMIFS('Combined P&L'!AE:AE,'Combined P&L'!$C:$C,'P&L Forecast'!$B81) -> 1.71127 | AH81: =SUMIFS('Combined P&L'!AF:AF,'Combined P&L'!$C:$C,'P&L Forecast'!$B81) -> 1.04707 | AI81: =SUMIFS('Combined P&L'!AG:AG,'Combined P&L'!$C:$C,'P&L Forecast'!$B81) -> 2.04088 | AJ81: =SUMIFS('Combined P&L'!AH:AH,'Combined P&L'!$C:$C,'P&L Forecast'!$B81) -> 1.13621 | AK81: =SUMIFS('Combined P&L'!AI:AI,'Combined P&L'!$C:$C,'P&L Forecast'!$B81) -> 2.01424 | AL81: =SUMIFS('Combined P&L'!AJ:AJ,'Combined P&L'!$C:$C,'P&L Forecast'!$B81) -> 1.29758 | AM81: =SUMIFS('Combined P&L'!AK:AK,'Combined P&L'!$C:$C,'P&L Forecast'!$B81) -> 2.26793 | AN81: =SUMIFS('Combined P&L'!AL:AL,'Combined P&L'!$C:$C,'P&L Forecast'!$B81) -> 2.67784 | AO81: =SUMIFS('Combined P&L'!AM:AM,'Combined P&L'!$C:$C,'P&L Forecast'!$B81) -> 2.35401 | AP81: =SUMIFS('Combined P&L'!AN:AN,'Combined P&L'!$C:$C,'P&L Forecast'!$B81) -> 0.2276 | AQ81: =SUMIFS('Combined P&L'!AO:AO,'Combined P&L'!$C:$C,'P&L Forecast'!$B81) -> 1.47836 | AR81: =SUMIFS('Combined P&L'!AP:AP,'Combined P&L'!$C:$C,'P&L Forecast'!$B81) -> 0.66824 | AS81: =SUMIFS('Combined P&L'!AQ:AQ,'Combined P&L'!$C:$C,'P&L Forecast'!$B81) -> 0.58613 | AT81: =SUMIFS('Combined P&L'!AR:AR,'Combined P&L'!$C:$C,'P&L Forecast'!$B81) -> 0.0872
B82: 1099 Filing | C82: =SUMIFS($P82:$AT82,$P$69:$AT$69,">"&C$169,$P$69:$AT$69,"<"&C$170) -> 10.475 | D82: =SUMIFS($P82:$AT82,$P$69:$AT$69,">"&D$169,$P$69:$AT$69,"<"&D$170) -> 23.55 | F82: =SUMIFS($P82:$AT82,$P$69:$AT$69,">"&F$169,$P$69:$AT$69,"<"&F$170) -> 23.49 | G82: =SUMIFS($P82:$AT82,$P$69:$AT$69,">"&G$169,$P$69:$AT$69,"<"&G$170) -> 38.7015 | I82: =SUMIFS($P82:$AT82,$P$69:$AT$69,">"&I$169,$P$69:$AT$69,"<"&I$170) -> 23.52 | J82: =SUMIFS($P82:$AT82,$P$69:$AT$69,">"&J$169,$P$69:$AT$69,"<"&J$170) -> 38.7615 | K82: =+C16 -> 0 | M82: =K82-J82 -> -38.7615 | N82: =IFERROR(K82/J82-1,0) -> -1 | P82: =SUMIFS('Combined P&L'!N:N,'Combined P&L'!$C:$C,'P&L Forecast'!$B82) -> 6.945 | Q82: =SUMIFS('Combined P&L'!O:O,'Combined P&L'!$C:$C,'P&L Forecast'!$B82) -> 3.38 | R82: =SUMIFS('Combined P&L'!P:P,'Combined P&L'!$C:$C,'P&L Forecast'!$B82) -> 0.045 | S82: =SUMIFS('Combined P&L'!Q:Q,'Combined P&L'!$C:$C,'P&L Forecast'!$B82) -> 0.06 | T82: =SUMIFS('Combined P&L'!R:R,'Combined P&L'!$C:$C,'P&L Forecast'!$B82) -> 0.015 | U82: =SUMIFS('Combined P&L'!S:S,'Combined P&L'!$C:$C,'P&L Forecast'!$B82) -> 0 | V82: =SUMIFS('Combined P&L'!T:T,'Combined P&L'!$C:$C,'P&L Forecast'!$B82) -> 0 | W82: =SUMIFS('Combined P&L'!U:U,'Combined P&L'!$C:$C,'P&L Forecast'!$B82) -> 0.015 | X82: =SUMIFS('Combined P&L'!V:V,'Combined P&L'!$C:$C,'P&L Forecast'!$B82) -> 0 | Y82: =SUMIFS('Combined P&L'!W:W,'Combined P&L'!$C:$C,'P&L Forecast'!$B82) -> 0 | Z82: =SUMIFS('Combined P&L'!X:X,'Combined P&L'!$C:$C,'P&L Forecast'!$B82) -> 0.015 | AA82: =SUMIFS('Combined P&L'!Y:Y,'Combined P&L'!$C:$C,'P&L Forecast'!$B82) -> 0 | AB82: =SUMIFS('Combined P&L'!Z:Z,'Combined P&L'!$C:$C,'P&L Forecast'!$B82) -> 13.485 | AC82: =SUMIFS('Combined P&L'!AA:AA,'Combined P&L'!$C:$C,'P&L Forecast'!$B82) -> 9.915 | AD82: =SUMIFS('Combined P&L'!AB:AB,'Combined P&L'!$C:$C,'P&L Forecast'!$B82) -> 0.06 | AE82: =SUMIFS('Combined P&L'!AC:AC,'Combined P&L'!$C:$C,'P&L Forecast'!$B82) -> 0.03 | AF82: =SUMIFS('Combined P&L'!AD:AD,'Combined P&L'!$C:$C,'P&L Forecast'!$B82) -> 0 | AG82: =SUMIFS('Combined P&L'!AE:AE,'Combined P&L'!$C:$C,'P&L Forecast'!$B82) -> 0 | AH82: =SUMIFS('Combined P&L'!AF:AF,'Combined P&L'!$C:$C,'P&L Forecast'!$B82) -> 0 | AI82: =SUMIFS('Combined P&L'!AG:AG,'Combined P&L'!$C:$C,'P&L Forecast'!$B82) -> 0.03 | AJ82: =SUMIFS('Combined P&L'!AH:AH,'Combined P&L'!$C:$C,'P&L Forecast'!$B82) -> 0.03 | AK82: =SUMIFS('Combined P&L'!AI:AI,'Combined P&L'!$C:$C,'P&L Forecast'!$B82) -> 0 | AL82: =SUMIFS('Combined P&L'!AJ:AJ,'Combined P&L'!$C:$C,'P&L Forecast'!$B82) -> 0 | AM82: =SUMIFS('Combined P&L'!AK:AK,'Combined P&L'!$C:$C,'P&L Forecast'!$B82) -> 0 | AN82: =SUMIFS('Combined P&L'!AL:AL,'Combined P&L'!$C:$C,'P&L Forecast'!$B82) -> 6.105 | AO82: =SUMIFS('Combined P&L'!AM:AM,'Combined P&L'!$C:$C,'P&L Forecast'!$B82) -> 31.1565 | AP82: =SUMIFS('Combined P&L'!AN:AN,'Combined P&L'!$C:$C,'P&L Forecast'!$B82) -> 1.26 | AQ82: =SUMIFS('Combined P&L'!AO:AO,'Combined P&L'!$C:$C,'P&L Forecast'!$B82) -> 0.18 | AR82: =SUMIFS('Combined P&L'!AP:AP,'Combined P&L'!$C:$C,'P&L Forecast'!$B82) -> 0 | AS82: =SUMIFS('Combined P&L'!AQ:AQ,'Combined P&L'!$C:$C,'P&L Forecast'!$B82) -> 0 | AT82: =SUMIFS('Combined P&L'!AR:AR,'Combined P&L'!$C:$C,'P&L Forecast'!$B82) -> 0
B83: Income Tax | C83: =SUMIFS($P83:$AT83,$P$69:$AT$69,">"&C$169,$P$69:$AT$69,"<"&C$170) -> 0 | D83: =SUMIFS($P83:$AT83,$P$69:$AT$69,">"&D$169,$P$69:$AT$69,"<"&D$170) -> 3.4 | F83: =SUMIFS($P83:$AT83,$P$69:$AT$69,">"&F$169,$P$69:$AT$69,"<"&F$170) -> 0 | G83: =SUMIFS($P83:$AT83,$P$69:$AT$69,">"&G$169,$P$69:$AT$69,"<"&G$170) -> 23.915 | I83: =SUMIFS($P83:$AT83,$P$69:$AT$69,">"&I$169,$P$69:$AT$69,"<"&I$170) -> 0 | J83: =SUMIFS($P83:$AT83,$P$69:$AT$69,">"&J$169,$P$69:$AT$69,"<"&J$170) -> 27.315 | K83: =+C17 -> 0 | M83: =K83-J83 -> -27.315 | N83: =IFERROR(K83/J83-1,0) -> -1 | P83: =SUMIFS('Combined P&L'!N:N,'Combined P&L'!$C:$C,'P&L Forecast'!$B83) -> 0 | Q83: =SUMIFS('Combined P&L'!O:O,'Combined P&L'!$C:$C,'P&L Forecast'!$B83) -> 0 | R83: =SUMIFS('Combined P&L'!P:P,'Combined P&L'!$C:$C,'P&L Forecast'!$B83) -> 0 | S83: =SUMIFS('Combined P&L'!Q:Q,'Combined P&L'!$C:$C,'P&L Forecast'!$B83) -> 0 | T83: =SUMIFS('Combined P&L'!R:R,'Combined P&L'!$C:$C,'P&L Forecast'!$B83) -> 0 | U83: =SUMIFS('Combined P&L'!S:S,'Combined P&L'!$C:$C,'P&L Forecast'!$B83) -> 0 | V83: =SUMIFS('Combined P&L'!T:T,'Combined P&L'!$C:$C,'P&L Forecast'!$B83) -> 0 | W83: =SUMIFS('Combined P&L'!U:U,'Combined P&L'!$C:$C,'P&L Forecast'!$B83) -> 0 | X83: =SUMIFS('Combined P&L'!V:V,'Combined P&L'!$C:$C,'P&L Forecast'!$B83) -> 0 | Y83: =SUMIFS('Combined P&L'!W:W,'Combined P&L'!$C:$C,'P&L Forecast'!$B83) -> 0 | Z83: =SUMIFS('Combined P&L'!X:X,'Combined P&L'!$C:$C,'P&L Forecast'!$B83) -> 0 | AA83: =SUMIFS('Combined P&L'!Y:Y,'Combined P&L'!$C:$C,'P&L Forecast'!$B83) -> 0 | AB83: =SUMIFS('Combined P&L'!Z:Z,'Combined P&L'!$C:$C,'P&L Forecast'!$B83) -> 0 | AC83: =SUMIFS('Combined P&L'!AA:AA,'Combined P&L'!$C:$C,'P&L Forecast'!$B83) -> 0 | AD83: =SUMIFS('Combined P&L'!AB:AB,'Combined P&L'!$C:$C,'P&L Forecast'!$B83) -> 0 | AE83: =SUMIFS('Combined P&L'!AC:AC,'Combined P&L'!$C:$C,'P&L Forecast'!$B83) -> 0 | AF83: =SUMIFS('Combined P&L'!AD:AD,'Combined P&L'!$C:$C,'P&L Forecast'!$B83) -> 0 | AG83: =SUMIFS('Combined P&L'!AE:AE,'Combined P&L'!$C:$C,'P&L Forecast'!$B83) -> 0 | AH83: =SUMIFS('Combined P&L'!AF:AF,'Combined P&L'!$C:$C,'P&L Forecast'!$B83) -> 0 | AI83: =SUMIFS('Combined P&L'!AG:AG,'Combined P&L'!$C:$C,'P&L Forecast'!$B83) -> 0 | AJ83: =SUMIFS('Combined P&L'!AH:AH,'Combined P&L'!$C:$C,'P&L Forecast'!$B83) -> 0.875 | AK83: =SUMIFS('Combined P&L'!AI:AI,'Combined P&L'!$C:$C,'P&L Forecast'!$B83) -> 1.65 | AL83: =SUMIFS('Combined P&L'!AJ:AJ,'Combined P&L'!$C:$C,'P&L Forecast'!$B83) -> 0 | AM83: =SUMIFS('Combined P&L'!AK:AK,'Combined P&L'!$C:$C,'P&L Forecast'!$B83) -> 0.875 | AN83: =SUMIFS('Combined P&L'!AL:AL,'Combined P&L'!$C:$C,'P&L Forecast'!$B83) -> 0 | AO83: =SUMIFS('Combined P&L'!AM:AM,'Combined P&L'!$C:$C,'P&L Forecast'!$B83) -> 0 | AP83: =SUMIFS('Combined P&L'!AN:AN,'Combined P&L'!$C:$C,'P&L Forecast'!$B83) -> 14.19 | AQ83: =SUMIFS('Combined P&L'!AO:AO,'Combined P&L'!$C:$C,'P&L Forecast'!$B83) -> 6.625 | AR83: =SUMIFS('Combined P&L'!AP:AP,'Combined P&L'!$C:$C,'P&L Forecast'!$B83) -> 0 | AS83: =SUMIFS('Combined P&L'!AQ:AQ,'Combined P&L'!$C:$C,'P&L Forecast'!$B83) -> 3.1 | AT83: =SUMIFS('Combined P&L'!AR:AR,'Combined P&L'!$C:$C,'P&L Forecast'!$B83) -> 0
B84: Billable Expense Income | C84: =SUMIFS($P84:$AT84,$P$69:$AT$69,">"&C$169,$P$69:$AT$69,"<"&C$170) -> 0.3747 | D84: =SUMIFS($P84:$AT84,$P$69:$AT$69,">"&D$169,$P$69:$AT$69,"<"&D$170) -> 1.12194 | F84: =SUMIFS($P84:$AT84,$P$69:$AT$69,">"&F$169,$P$69:$AT$69,"<"&F$170) -> 0.78725 | G84: =SUMIFS($P84:$AT84,$P$69:$AT$69,">"&G$169,$P$69:$AT$69,"<"&G$170) -> 0.25783 | I84: =SUMIFS($P84:$AT84,$P$69:$AT$69,">"&I$169,$P$69:$AT$69,"<"&I$170) -> 0.79724 | J84: =SUMIFS($P84:$AT84,$P$69:$AT$69,">"&J$169,$P$69:$AT$69,"<"&J$170) -> 0.88223 | K84: =+C19 -> 0 | M84: =K84-J84 -> -0.88223 | N84: =IFERROR(K84/J84-1,0) -> -1 | P84: =SUMIFS('Combined P&L'!N:N,'Combined P&L'!$C:$C,'P&L Forecast'!$B84) -> 0.05 | Q84: =SUMIFS('Combined P&L'!O:O,'Combined P&L'!$C:$C,'P&L Forecast'!$B84) -> 0 | R84: =SUMIFS('Combined P&L'!P:P,'Combined P&L'!$C:$C,'P&L Forecast'!$B84) -> 0 | S84: =SUMIFS('Combined P&L'!Q:Q,'Combined P&L'!$C:$C,'P&L Forecast'!$B84) -> 0.025 | T84: =SUMIFS('Combined P&L'!R:R,'Combined P&L'!$C:$C,'P&L Forecast'!$B84) -> 0 | U84: =SUMIFS('Combined P&L'!S:S,'Combined P&L'!$C:$C,'P&L Forecast'!$B84) -> 0 | V84: =SUMIFS('Combined P&L'!T:T,'Combined P&L'!$C:$C,'P&L Forecast'!$B84) -> 0.2997 | W84: =SUMIFS('Combined P&L'!U:U,'Combined P&L'!$C:$C,'P&L Forecast'!$B84) -> 0 | X84: =SUMIFS('Combined P&L'!V:V,'Combined P&L'!$C:$C,'P&L Forecast'!$B84) -> 0 | Y84: =SUMIFS('Combined P&L'!W:W,'Combined P&L'!$C:$C,'P&L Forecast'!$B84) -> 0 | Z84: =SUMIFS('Combined P&L'!X:X,'Combined P&L'!$C:$C,'P&L Forecast'!$B84) -> 0 | AA84: =SUMIFS('Combined P&L'!Y:Y,'Combined P&L'!$C:$C,'P&L Forecast'!$B84) -> 0 | AB84: =SUMIFS('Combined P&L'!Z:Z,'Combined P&L'!$C:$C,'P&L Forecast'!$B84) -> 0.025 | AC84: =SUMIFS('Combined P&L'!AA:AA,'Combined P&L'!$C:$C,'P&L Forecast'!$B84) -> 0.3996 | AD84: =SUMIFS('Combined P&L'!AB:AB,'Combined P&L'!$C:$C,'P&L Forecast'!$B84) -> 0 | AE84: =SUMIFS('Combined P&L'!AC:AC,'Combined P&L'!$C:$C,'P&L Forecast'!$B84) -> 0 | AF84: =SUMIFS('Combined P&L'!AD:AD,'Combined P&L'!$C:$C,'P&L Forecast'!$B84) -> 0.07294 | AG84: =SUMIFS('Combined P&L'!AE:AE,'Combined P&L'!$C:$C,'P&L Forecast'!$B84) -> 0 | AH84: =SUMIFS('Combined P&L'!AF:AF,'Combined P&L'!$C:$C,'P&L Forecast'!$B84) -> 0.28971 | AI84: =SUMIFS('Combined P&L'!AG:AG,'Combined P&L'!$C:$C,'P&L Forecast'!$B84) -> 0.30969 | AJ84: =SUMIFS('Combined P&L'!AH:AH,'Combined P&L'!$C:$C,'P&L Forecast'!$B84) -> 0 | AK84: =SUMIFS('Combined P&L'!AI:AI,'Combined P&L'!$C:$C,'P&L Forecast'!$B84) -> 0 | AL84: =SUMIFS('Combined P&L'!AJ:AJ,'Combined P&L'!$C:$C,'P&L Forecast'!$B84) -> 0 | AM84: =SUMIFS('Combined P&L'!AK:AK,'Combined P&L'!$C:$C,'P&L Forecast'!$B84) -> 0.025 | AN84: =SUMIFS('Combined P&L'!AL:AL,'Combined P&L'!$C:$C,'P&L Forecast'!$B84) -> 0.15984 | AO84: =SUMIFS('Combined P&L'!AM:AM,'Combined P&L'!$C:$C,'P&L Forecast'!$B84) -> 0 | AP84: =SUMIFS('Combined P&L'!AN:AN,'Combined P&L'!$C:$C,'P&L Forecast'!$B84) -> 0.075 | AQ84: =SUMIFS('Combined P&L'!AO:AO,'Combined P&L'!$C:$C,'P&L Forecast'!$B84) -> 0 | AR84: =SUMIFS('Combined P&L'!AP:AP,'Combined P&L'!$C:$C,'P&L Forecast'!$B84) -> 0 | AS84: =SUMIFS('Combined P&L'!AQ:AQ,'Combined P&L'!$C:$C,'P&L Forecast'!$B84) -> 0.02299 | AT84: =SUMIFS('Combined P&L'!AR:AR,'Combined P&L'!$C:$C,'P&L Forecast'!$B84) -> 0
B85: Offshore Recruiting | C85: =SUMIFS($P85:$AT85,$P$69:$AT$69,">"&C$169,$P$69:$AT$69,"<"&C$170) -> 23.6 | D85: =SUMIFS($P85:$AT85,$P$69:$AT$69,">"&D$169,$P$69:$AT$69,"<"&D$170) -> 0.2 | F85: =SUMIFS($P85:$AT85,$P$69:$AT$69,">"&F$169,$P$69:$AT$69,"<"&F$170) -> 0.2 | G85: =SUMIFS($P85:$AT85,$P$69:$AT$69,">"&G$169,$P$69:$AT$69,"<"&G$170) -> 0 | I85: =SUMIFS($P85:$AT85,$P$69:$AT$69,">"&I$169,$P$69:$AT$69,"<"&I$170) -> 16.735 | J85: =SUMIFS($P85:$AT85,$P$69:$AT$69,">"&J$169,$P$69:$AT$69,"<"&J$170) -> 0 | K85: =+C20 -> 0 | M85: =K85-J85 -> 0 | N85: =IFERROR(K85/J85-1,0) -> 0 | P85: =SUMIFS('Combined P&L'!N:N,'Combined P&L'!$C:$C,'P&L Forecast'!$B85) -> 0.5 | Q85: =SUMIFS('Combined P&L'!O:O,'Combined P&L'!$C:$C,'P&L Forecast'!$B85) -> 3 | R85: =SUMIFS('Combined P&L'!P:P,'Combined P&L'!$C:$C,'P&L Forecast'!$B85) -> 0 | S85: =SUMIFS('Combined P&L'!Q:Q,'Combined P&L'!$C:$C,'P&L Forecast'!$B85) -> 0 | T85: =SUMIFS('Combined P&L'!R:R,'Combined P&L'!$C:$C,'P&L Forecast'!$B85) -> 3 | U85: =SUMIFS('Combined P&L'!S:S,'Combined P&L'!$C:$C,'P&L Forecast'!$B85) -> 0.565 | V85: =SUMIFS('Combined P&L'!T:T,'Combined P&L'!$C:$C,'P&L Forecast'!$B85) -> 10.5 | W85: =SUMIFS('Combined P&L'!U:U,'Combined P&L'!$C:$C,'P&L Forecast'!$B85) -> 6.5 | X85: =SUMIFS('Combined P&L'!V:V,'Combined P&L'!$C:$C,'P&L Forecast'!$B85) -> 0.5 | Y85: =SUMIFS('Combined P&L'!W:W,'Combined P&L'!$C:$C,'P&L Forecast'!$B85) -> -0.965 | Z85: =SUMIFS('Combined P&L'!X:X,'Combined P&L'!$C:$C,'P&L Forecast'!$B85) -> 0 | AA85: =SUMIFS('Combined P&L'!Y:Y,'Combined P&L'!$C:$C,'P&L Forecast'!$B85) -> 0 | AB85: =SUMIFS('Combined P&L'!Z:Z,'Combined P&L'!$C:$C,'P&L Forecast'!$B85) -> 0.1 | AC85: =SUMIFS('Combined P&L'!AA:AA,'Combined P&L'!$C:$C,'P&L Forecast'!$B85) -> 0 | AD85: =SUMIFS('Combined P&L'!AB:AB,'Combined P&L'!$C:$C,'P&L Forecast'!$B85) -> 0.1 | AE85: =SUMIFS('Combined P&L'!AC:AC,'Combined P&L'!$C:$C,'P&L Forecast'!$B85) -> 0 | AF85: =SUMIFS('Combined P&L'!AD:AD,'Combined P&L'!$C:$C,'P&L Forecast'!$B85) -> 0 | AG85: =SUMIFS('Combined P&L'!AE:AE,'Combined P&L'!$C:$C,'P&L Forecast'!$B85) -> 0 | AH85: =SUMIFS('Combined P&L'!AF:AF,'Combined P&L'!$C:$C,'P&L Forecast'!$B85) -> 0 | AI85: =SUMIFS('Combined P&L'!AG:AG,'Combined P&L'!$C:$C,'P&L Forecast'!$B85) -> 0 | AJ85: =SUMIFS('Combined P&L'!AH:AH,'Combined P&L'!$C:$C,'P&L Forecast'!$B85) -> 0 | AK85: =SUMIFS('Combined P&L'!AI:AI,'Combined P&L'!$C:$C,'P&L Forecast'!$B85) -> 0 | AL85: =SUMIFS('Combined P&L'!AJ:AJ,'Combined P&L'!$C:$C,'P&L Forecast'!$B85) -> 0 | AM85: =SUMIFS('Combined P&L'!AK:AK,'Combined P&L'!$C:$C,'P&L Forecast'!$B85) -> 0 | AN85: =SUMIFS('Combined P&L'!AL:AL,'Combined P&L'!$C:$C,'P&L Forecast'!$B85) -> 0 | AO85: =SUMIFS('Combined P&L'!AM:AM,'Combined P&L'!$C:$C,'P&L Forecast'!$B85) -> 0 | AP85: =SUMIFS('Combined P&L'!AN:AN,'Combined P&L'!$C:$C,'P&L Forecast'!$B85) -> 0 | AQ85: =SUMIFS('Combined P&L'!AO:AO,'Combined P&L'!$C:$C,'P&L Forecast'!$B85) -> 0 | AR85: =SUMIFS('Combined P&L'!AP:AP,'Combined P&L'!$C:$C,'P&L Forecast'!$B85) -> 0 | AS85: =SUMIFS('Combined P&L'!AQ:AQ,'Combined P&L'!$C:$C,'P&L Forecast'!$B85) -> 0 | AT85: =SUMIFS('Combined P&L'!AR:AR,'Combined P&L'!$C:$C,'P&L Forecast'!$B85) -> 0
B86: Total Nonrecurring Revenue | C86: =SUM(C81:C85) -> 40.6501 | D86: =SUM(D81:D85) -> 51.53373 | F86: =SUM(F81:F85) -> 38.9822 | G86: =SUM(G81:G85) -> 70.95371 | I86: =SUM(I81:I85) -> 59.00012 | J86: =SUM(J81:J85) -> 84.75482 | K86: =SUM(K81:K85) -> 16.83622 | M86: =SUM(M81:M85) -> -67.9186 | N86: =IFERROR(K86/J86-1,0) -> -0.80135383 | P86: =SUM(P81:P85) -> 7.5636 | Q86: =SUM(Q81:Q85) -> 6.5112 | R86: =SUM(R81:R85) -> 0.1162 | S86: =SUM(S81:S85) -> 0.1406 | T86: =SUM(T81:T85) -> 3.592 | U86: =SUM(U81:U85) -> 1.3718 | V86: =SUM(V81:V85) -> 11.4653 | W86: =SUM(W81:W85) -> 7.3414 | ... AT86: =SUM(AT81:AT85) -> 0.0872
B88: Total Revenue | C88: =+C86+C79 -> 1134.9659 | D88: =+D86+D79 -> 1879.3831 | F88: =+F86+F79 -> 997.8731 | G88: =+G86+G79 -> 1671.0212 | I88: =+I86+I79 -> 1473.7119 | J88: =+J86+J79 -> 2456.4862 | K88: =+K86+K79 -> 3063.2855 | M88: =+M86+M79 -> 606.79936 | N88: =IFERROR(K88/J88-1,0) -> 0.24701925 | P88: =+P86+P79 -> 80.9131 | Q88: =+Q86+Q79 -> 81.2557 | R88: =+R86+R79 -> 78.1122 | S88: =+S86+S79 -> 83.3533 | T88: =+T86+T79 -> 90.19615 | U88: =+U86+U79 -> 89.9158 | V88: =+V86+V79 -> 104.68205 | W88: =+W86+W79 -> 104.11675 | ... AT88: =+AT86+AT79 -> 251.42585
B90: Expenses
B91: Indirect Labor | C91: =SUMIFS($P91:$AT91,$P$69:$AT$69,">"&C$169,$P$69:$AT$69,"<"&C$170) -> 101.3752 | D91: =SUMIFS($P91:$AT91,$P$69:$AT$69,">"&D$169,$P$69:$AT$69,"<"&D$170) -> 281.24054 | F91: =SUMIFS($P91:$AT91,$P$69:$AT$69,">"&F$169,$P$69:$AT$69,"<"&F$170) -> 136.29648 | G91: =SUMIFS($P91:$AT91,$P$69:$AT$69,">"&G$169,$P$69:$AT$69,"<"&G$170) -> 357.27472 | I91: =SUMIFS($P91:$AT91,$P$69:$AT$69,">"&I$169,$P$69:$AT$69,"<"&I$170) -> 184.76374 | J91: =SUMIFS($P91:$AT91,$P$69:$AT$69,">"&J$169,$P$69:$AT$69,"<"&J$170) -> 466.92604 | K91: =+C24 -> 694.74456 | M91: =+J91-K91 -> -227.81852 | N91: =IFERROR(K91/J91-1,0) -> 0.48791136 | P91: =SUMIFS('Combined P&L'!N:N,'Combined P&L'!$C:$C,'P&L Forecast'!$B91) -> 3.09346 | Q91: =SUMIFS('Combined P&L'!O:O,'Combined P&L'!$C:$C,'P&L Forecast'!$B91) -> 4.63017 | R91: =SUMIFS('Combined P&L'!P:P,'Combined P&L'!$C:$C,'P&L Forecast'!$B91) -> 4.39507 | S91: =SUMIFS('Combined P&L'!Q:Q,'Combined P&L'!$C:$C,'P&L Forecast'!$B91) -> 5.86387 | T91: =SUMIFS('Combined P&L'!R:R,'Combined P&L'!$C:$C,'P&L Forecast'!$B91) -> 7.37233 | U91: =SUMIFS('Combined P&L'!S:S,'Combined P&L'!$C:$C,'P&L Forecast'!$B91) -> 4.9504 | V91: =SUMIFS('Combined P&L'!T:T,'Combined P&L'!$C:$C,'P&L Forecast'!$B91) -> 4.9504 | W91: =SUMIFS('Combined P&L'!U:U,'Combined P&L'!$C:$C,'P&L Forecast'!$B91) -> 4.70035 | X91: =SUMIFS('Combined P&L'!V:V,'Combined P&L'!$C:$C,'P&L Forecast'!$B91) -> 4.9504 | Y91: =SUMIFS('Combined P&L'!W:W,'Combined P&L'!$C:$C,'P&L Forecast'!$B91) -> 5.99987 | Z91: =SUMIFS('Combined P&L'!X:X,'Combined P&L'!$C:$C,'P&L Forecast'!$B91) -> 26.02876 | AA91: =SUMIFS('Combined P&L'!Y:Y,'Combined P&L'!$C:$C,'P&L Forecast'!$B91) -> 24.44012 | AB91: =SUMIFS('Combined P&L'!Z:Z,'Combined P&L'!$C:$C,'P&L Forecast'!$B91) -> 21.05234 | AC91: =SUMIFS('Combined P&L'!AA:AA,'Combined P&L'!$C:$C,'P&L Forecast'!$B91) -> 19.91603 | AD91: =SUMIFS('Combined P&L'!AB:AB,'Combined P&L'!$C:$C,'P&L Forecast'!$B91) -> 11.74387 | AE91: =SUMIFS('Combined P&L'!AC:AC,'Combined P&L'!$C:$C,'P&L Forecast'!$B91) -> 19.61792 | AF91: =SUMIFS('Combined P&L'!AD:AD,'Combined P&L'!$C:$C,'P&L Forecast'!$B91) -> 20.66978 | AG91: =SUMIFS('Combined P&L'!AE:AE,'Combined P&L'!$C:$C,'P&L Forecast'!$B91) -> 20.6939 | AH91: =SUMIFS('Combined P&L'!AF:AF,'Combined P&L'!$C:$C,'P&L Forecast'!$B91) -> 22.60264 | AI91: =SUMIFS('Combined P&L'!AG:AG,'Combined P&L'!$C:$C,'P&L Forecast'!$B91) -> 19.96128 | AJ91: =SUMIFS('Combined P&L'!AH:AH,'Combined P&L'!$C:$C,'P&L Forecast'!$B91) -> 27.60563 | AK91: =SUMIFS('Combined P&L'!AI:AI,'Combined P&L'!$C:$C,'P&L Forecast'!$B91) -> 34.18589 | AL91: =SUMIFS('Combined P&L'!AJ:AJ,'Combined P&L'!$C:$C,'P&L Forecast'!$B91) -> 29.73157 | AM91: =SUMIFS('Combined P&L'!AK:AK,'Combined P&L'!$C:$C,'P&L Forecast'!$B91) -> 33.45969 | AN91: =SUMIFS('Combined P&L'!AL:AL,'Combined P&L'!$C:$C,'P&L Forecast'!$B91) -> 36.2536 | AO91: =SUMIFS('Combined P&L'!AM:AM,'Combined P&L'!$C:$C,'P&L Forecast'!$B91) -> 33.60751 | AP91: =SUMIFS('Combined P&L'!AN:AN,'Combined P&L'!$C:$C,'P&L Forecast'!$B91) -> 57.19924 | AQ91: =SUMIFS('Combined P&L'!AO:AO,'Combined P&L'!$C:$C,'P&L Forecast'!$B91) -> 58.24595 | AR91: =SUMIFS('Combined P&L'!AP:AP,'Combined P&L'!$C:$C,'P&L Forecast'!$B91) -> 54.06923 | AS91: =SUMIFS('Combined P&L'!AQ:AQ,'Combined P&L'!$C:$C,'P&L Forecast'!$B91) -> 60.00381 | AT91: =SUMIFS('Combined P&L'!AR:AR,'Combined P&L'!$C:$C,'P&L Forecast'!$B91) -> 57.89538
B92: Bookkeeper Wages | C92: =SUMIFS($P92:$AT92,$P$69:$AT$69,">"&C$169,$P$69:$AT$69,"<"&C$170) -> 183.36903 | D92: =SUMIFS($P92:$AT92,$P$69:$AT$69,">"&D$169,$P$69:$AT$69,"<"&D$170) -> 316.18462 | F92: =SUMIFS($P92:$AT92,$P$69:$AT$69,">"&F$169,$P$69:$AT$69,"<"&F$170) -> 147.26813 | G92: =SUMIFS($P92:$AT92,$P$69:$AT$69,">"&G$169,$P$69:$AT$69,"<"&G$170) -> 267.7574 | I92: =SUMIFS($P92:$AT92,$P$69:$AT$69,">"&I$169,$P$69:$AT$69,"<"&I$170) -> 226.32031 | J92: =SUMIFS($P92:$AT92,$P$69:$AT$69,">"&J$169,$P$69:$AT$69,"<"&J$170) -> 420.0952 | K92: =+C25 -> 533.8512 | M92: =+J92-K92 -> -113.756 | N92: =IFERROR(K92/J92-1,0) -> 0.27078624 | P92: =SUMIFS('Combined P&L'!N:N,'Combined P&L'!$C:$C,'P&L Forecast'!$B92) -> 9.555 | Q92: =SUMIFS('Combined P&L'!O:O,'Combined P&L'!$C:$C,'P&L Forecast'!$B92) -> 9.555 | R92: =SUMIFS('Combined P&L'!P:P,'Combined P&L'!$C:$C,'P&L Forecast'!$B92) -> 10.3972 | S92: =SUMIFS('Combined P&L'!Q:Q,'Combined P&L'!$C:$C,'P&L Forecast'!$B92) -> 14.99967 | T92: =SUMIFS('Combined P&L'!R:R,'Combined P&L'!$C:$C,'P&L Forecast'!$B92) -> 18.0098 | U92: =SUMIFS('Combined P&L'!S:S,'Combined P&L'!$C:$C,'P&L Forecast'!$B92) -> 13.89127 | V92: =SUMIFS('Combined P&L'!T:T,'Combined P&L'!$C:$C,'P&L Forecast'!$B92) -> 14.04824 | W92: =SUMIFS('Combined P&L'!U:U,'Combined P&L'!$C:$C,'P&L Forecast'!$B92) -> 13.39091 | X92: =SUMIFS('Combined P&L'!V:V,'Combined P&L'!$C:$C,'P&L Forecast'!$B92) -> 14.66931 | Y92: =SUMIFS('Combined P&L'!W:W,'Combined P&L'!$C:$C,'P&L Forecast'!$B92) -> 15.88253 | Z92: =SUMIFS('Combined P&L'!X:X,'Combined P&L'!$C:$C,'P&L Forecast'!$B92) -> 27.18867 | AA92: =SUMIFS('Combined P&L'!Y:Y,'Combined P&L'!$C:$C,'P&L Forecast'!$B92) -> 21.78143 | AB92: =SUMIFS('Combined P&L'!Z:Z,'Combined P&L'!$C:$C,'P&L Forecast'!$B92) -> 19.40233 | AC92: =SUMIFS('Combined P&L'!AA:AA,'Combined P&L'!$C:$C,'P&L Forecast'!$B92) -> 16.40053 | AD92: =SUMIFS('Combined P&L'!AB:AB,'Combined P&L'!$C:$C,'P&L Forecast'!$B92) -> 19.56983 | AE92: =SUMIFS('Combined P&L'!AC:AC,'Combined P&L'!$C:$C,'P&L Forecast'!$B92) -> 22.1542 | AF92: =SUMIFS('Combined P&L'!AD:AD,'Combined P&L'!$C:$C,'P&L Forecast'!$B92) -> 20.79154 | AG92: =SUMIFS('Combined P&L'!AE:AE,'Combined P&L'!$C:$C,'P&L Forecast'!$B92) -> 21.04079 | AH92: =SUMIFS('Combined P&L'!AF:AF,'Combined P&L'!$C:$C,'P&L Forecast'!$B92) -> 27.90891 | AI92: =SUMIFS('Combined P&L'!AG:AG,'Combined P&L'!$C:$C,'P&L Forecast'!$B92) -> 29.547 | AJ92: =SUMIFS('Combined P&L'!AH:AH,'Combined P&L'!$C:$C,'P&L Forecast'!$B92) -> 33.44727 | AK92: =SUMIFS('Combined P&L'!AI:AI,'Combined P&L'!$C:$C,'P&L Forecast'!$B92) -> 37.79432 | AL92: =SUMIFS('Combined P&L'!AJ:AJ,'Combined P&L'!$C:$C,'P&L Forecast'!$B92) -> 34.06332 | AM92: =SUMIFS('Combined P&L'!AK:AK,'Combined P&L'!$C:$C,'P&L Forecast'!$B92) -> 34.06458 | AN92: =SUMIFS('Combined P&L'!AL:AL,'Combined P&L'!$C:$C,'P&L Forecast'!$B92) -> 38.37888 | AO92: =SUMIFS('Combined P&L'!AM:AM,'Combined P&L'!$C:$C,'P&L Forecast'!$B92) -> 29.70152 | AP92: =SUMIFS('Combined P&L'!AN:AN,'Combined P&L'!$C:$C,'P&L Forecast'!$B92) -> 37.4225 | AQ92: =SUMIFS('Combined P&L'!AO:AO,'Combined P&L'!$C:$C,'P&L Forecast'!$B92) -> 38.7723 | AR92: =SUMIFS('Combined P&L'!AP:AP,'Combined P&L'!$C:$C,'P&L Forecast'!$B92) -> 38.29477 | AS92: =SUMIFS('Combined P&L'!AQ:AQ,'Combined P&L'!$C:$C,'P&L Forecast'!$B92) -> 40.69983 | AT92: =SUMIFS('Combined P&L'!AR:AR,'Combined P&L'!$C:$C,'P&L Forecast'!$B92) -> 44.4876
B93: Client Lead Wages | C93: =SUMIFS($P93:$AT93,$P$69:$AT$69,">"&C$169,$P$69:$AT$69,"<"&C$170) -> 286.16129 | D93: =SUMIFS($P93:$AT93,$P$69:$AT$69,">"&D$169,$P$69:$AT$69,"<"&D$170) -> 352.95844 | F93: =SUMIFS($P93:$AT93,$P$69:$AT$69,">"&F$169,$P$69:$AT$69,"<"&F$170) -> 201.27983 | G93: =SUMIFS($P93:$AT93,$P$69:$AT$69,">"&G$169,$P$69:$AT$69,"<"&G$170) -> 202.05309 | I93: =SUMIFS($P93:$AT93,$P$69:$AT$69,">"&I$169,$P$69:$AT$69,"<"&I$170) -> 351.95999 | J93: =SUMIFS($P93:$AT93,$P$69:$AT$69,">"&J$169,$P$69:$AT$69,"<"&J$170) -> 350.46762 | K93: =+C27 -> 392.92452 | M93: =+J93-K93 -> -42.4569 | N93: =IFERROR(K93/J93-1,0) -> 0.12114357 | P93: =SUMIFS('Combined P&L'!N:N,'Combined P&L'!$C:$C,'P&L Forecast'!$B93) -> 9.96108 | Q93: =SUMIFS('Combined P&L'!O:O,'Combined P&L'!$C:$C,'P&L Forecast'!$B93) -> 13.85026 | R93: =SUMIFS('Combined P&L'!P:P,'Combined P&L'!$C:$C,'P&L Forecast'!$B93) -> 12.79054 | S93: =SUMIFS('Combined P&L'!Q:Q,'Combined P&L'!$C:$C,'P&L Forecast'!$B93) -> 14.57145 | T93: =SUMIFS('Combined P&L'!R:R,'Combined P&L'!$C:$C,'P&L Forecast'!$B93) -> 28.28563 | U93: =SUMIFS('Combined P&L'!S:S,'Combined P&L'!$C:$C,'P&L Forecast'!$B93) -> 26.54254 | V93: =SUMIFS('Combined P&L'!T:T,'Combined P&L'!$C:$C,'P&L Forecast'!$B93) -> 28.31119 | W93: =SUMIFS('Combined P&L'!U:U,'Combined P&L'!$C:$C,'P&L Forecast'!$B93) -> 28.18746 | X93: =SUMIFS('Combined P&L'!V:V,'Combined P&L'!$C:$C,'P&L Forecast'!$B93) -> 30.86801 | Y93: =SUMIFS('Combined P&L'!W:W,'Combined P&L'!$C:$C,'P&L Forecast'!$B93) -> 31.62128 | Z93: =SUMIFS('Combined P&L'!X:X,'Combined P&L'!$C:$C,'P&L Forecast'!$B93) -> 28.44974 | AA93: =SUMIFS('Combined P&L'!Y:Y,'Combined P&L'!$C:$C,'P&L Forecast'!$B93) -> 32.72211 | AB93: =SUMIFS('Combined P&L'!Z:Z,'Combined P&L'!$C:$C,'P&L Forecast'!$B93) -> 32.78076 | AC93: =SUMIFS('Combined P&L'!AA:AA,'Combined P&L'!$C:$C,'P&L Forecast'!$B93) -> 23.36184 | AD93: =SUMIFS('Combined P&L'!AB:AB,'Combined P&L'!$C:$C,'P&L Forecast'!$B93) -> 26.91427 | AE93: =SUMIFS('Combined P&L'!AC:AC,'Combined P&L'!$C:$C,'P&L Forecast'!$B93) -> 28.81298 | AF93: =SUMIFS('Combined P&L'!AD:AD,'Combined P&L'!$C:$C,'P&L Forecast'!$B93) -> 30.65875 | AG93: =SUMIFS('Combined P&L'!AE:AE,'Combined P&L'!$C:$C,'P&L Forecast'!$B93) -> 29.2716 | AH93: =SUMIFS('Combined P&L'!AF:AF,'Combined P&L'!$C:$C,'P&L Forecast'!$B93) -> 29.47963 | AI93: =SUMIFS('Combined P&L'!AG:AG,'Combined P&L'!$C:$C,'P&L Forecast'!$B93) -> 26.83064 | AJ93: =SUMIFS('Combined P&L'!AH:AH,'Combined P&L'!$C:$C,'P&L Forecast'!$B93) -> 29.78555 | AK93: =SUMIFS('Combined P&L'!AI:AI,'Combined P&L'!$C:$C,'P&L Forecast'!$B93) -> 32.89937 | AL93: =SUMIFS('Combined P&L'!AJ:AJ,'Combined P&L'!$C:$C,'P&L Forecast'!$B93) -> 29.49334 | AM93: =SUMIFS('Combined P&L'!AK:AK,'Combined P&L'!$C:$C,'P&L Forecast'!$B93) -> 32.66971 | AN93: =SUMIFS('Combined P&L'!AL:AL,'Combined P&L'!$C:$C,'P&L Forecast'!$B93) -> 26.1149 | AO93: =SUMIFS('Combined P&L'!AM:AM,'Combined P&L'!$C:$C,'P&L Forecast'!$B93) -> 21.9055 | AP93: =SUMIFS('Combined P&L'!AN:AN,'Combined P&L'!$C:$C,'P&L Forecast'!$B93) -> 30.75844 | AQ93: =SUMIFS('Combined P&L'!AO:AO,'Combined P&L'!$C:$C,'P&L Forecast'!$B93) -> 31.59038 | AR93: =SUMIFS('Combined P&L'!AP:AP,'Combined P&L'!$C:$C,'P&L Forecast'!$B93) -> 27.69992 | AS93: =SUMIFS('Combined P&L'!AQ:AQ,'Combined P&L'!$C:$C,'P&L Forecast'!$B93) -> 31.24024 | AT93: =SUMIFS('Combined P&L'!AR:AR,'Combined P&L'!$C:$C,'P&L Forecast'!$B93) -> 32.74371
B94: Owner Wages | C94: =SUMIFS($P94:$AT94,$P$69:$AT$69,">"&C$169,$P$69:$AT$69,"<"&C$170) -> 0 | D94: =SUMIFS($P94:$AT94,$P$69:$AT$69,">"&D$169,$P$69:$AT$69,"<"&D$170) -> 90.66704 | F94: =SUMIFS($P94:$AT94,$P$69:$AT$69,">"&F$169,$P$69:$AT$69,"<"&F$170) -> 45.46612 | G94: =SUMIFS($P94:$AT94,$P$69:$AT$69,">"&G$169,$P$69:$AT$69,"<"&G$170) -> 63.14302 | I94: =SUMIFS($P94:$AT94,$P$69:$AT$69,">"&I$169,$P$69:$AT$69,"<"&I$170) -> 35.94325 | J94: =SUMIFS($P94:$AT94,$P$69:$AT$69,">"&J$169,$P$69:$AT$69,"<"&J$170) -> 108.34394 | K94: =+C26 -> 200 | M94: =+J94-K94 -> -91.65606 | N94: =IFERROR(K94/J94-1,0) -> 0.84597311 | P94: =SUMIFS('Combined P&L'!N:N,'Combined P&L'!$C:$C,'P&L Forecast'!$B94) -> 0 | Q94: =SUMIFS('Combined P&L'!O:O,'Combined P&L'!$C:$C,'P&L Forecast'!$B94) -> 0 | R94: =SUMIFS('Combined P&L'!P:P,'Combined P&L'!$C:$C,'P&L Forecast'!$B94) -> 0 | S94: =SUMIFS('Combined P&L'!Q:Q,'Combined P&L'!$C:$C,'P&L Forecast'!$B94) -> 0 | T94: =SUMIFS('Combined P&L'!R:R,'Combined P&L'!$C:$C,'P&L Forecast'!$B94) -> 0 | U94: =SUMIFS('Combined P&L'!S:S,'Combined P&L'!$C:$C,'P&L Forecast'!$B94) -> 0 | V94: =SUMIFS('Combined P&L'!T:T,'Combined P&L'!$C:$C,'P&L Forecast'!$B94) -> 0 | W94: =SUMIFS('Combined P&L'!U:U,'Combined P&L'!$C:$C,'P&L Forecast'!$B94) -> 0 | X94: =SUMIFS('Combined P&L'!V:V,'Combined P&L'!$C:$C,'P&L Forecast'!$B94) -> 0 | Y94: =SUMIFS('Combined P&L'!W:W,'Combined P&L'!$C:$C,'P&L Forecast'!$B94) -> 0 | Z94: =SUMIFS('Combined P&L'!X:X,'Combined P&L'!$C:$C,'P&L Forecast'!$B94) -> 0 | AA94: =SUMIFS('Combined P&L'!Y:Y,'Combined P&L'!$C:$C,'P&L Forecast'!$B94) -> 0 | AB94: =SUMIFS('Combined P&L'!Z:Z,'Combined P&L'!$C:$C,'P&L Forecast'!$B94) -> 0 | AC94: =SUMIFS('Combined P&L'!AA:AA,'Combined P&L'!$C:$C,'P&L Forecast'!$B94) -> 0 | AD94: =SUMIFS('Combined P&L'!AB:AB,'Combined P&L'!$C:$C,'P&L Forecast'!$B94) -> 8.90639 | AE94: =SUMIFS('Combined P&L'!AC:AC,'Combined P&L'!$C:$C,'P&L Forecast'!$B94) -> 9.23323 | AF94: =SUMIFS('Combined P&L'!AD:AD,'Combined P&L'!$C:$C,'P&L Forecast'!$B94) -> 9.10884 | AG94: =SUMIFS('Combined P&L'!AE:AE,'Combined P&L'!$C:$C,'P&L Forecast'!$B94) -> 8.69479 | AH94: =SUMIFS('Combined P&L'!AF:AF,'Combined P&L'!$C:$C,'P&L Forecast'!$B94) -> 9.52287 | AI94: =SUMIFS('Combined P&L'!AG:AG,'Combined P&L'!$C:$C,'P&L Forecast'!$B94) -> 8.69481 | AJ94: =SUMIFS('Combined P&L'!AH:AH,'Combined P&L'!$C:$C,'P&L Forecast'!$B94) -> 9.10884 | AK94: =SUMIFS('Combined P&L'!AI:AI,'Combined P&L'!$C:$C,'P&L Forecast'!$B94) -> 9.52287 | AL94: =SUMIFS('Combined P&L'!AJ:AJ,'Combined P&L'!$C:$C,'P&L Forecast'!$B94) -> 8.28076 | AM94: =SUMIFS('Combined P&L'!AK:AK,'Combined P&L'!$C:$C,'P&L Forecast'!$B94) -> 9.59364 | AN94: =SUMIFS('Combined P&L'!AL:AL,'Combined P&L'!$C:$C,'P&L Forecast'!$B94) -> 9.27621 | AO94: =SUMIFS('Combined P&L'!AM:AM,'Combined P&L'!$C:$C,'P&L Forecast'!$B94) -> 8.32263 | AP94: =SUMIFS('Combined P&L'!AN:AN,'Combined P&L'!$C:$C,'P&L Forecast'!$B94) -> 9.10883 | AQ94: =SUMIFS('Combined P&L'!AO:AO,'Combined P&L'!$C:$C,'P&L Forecast'!$B94) -> 9.10883 | AR94: =SUMIFS('Combined P&L'!AP:AP,'Combined P&L'!$C:$C,'P&L Forecast'!$B94) -> 8.69481 | AS94: =SUMIFS('Combined P&L'!AQ:AQ,'Combined P&L'!$C:$C,'P&L Forecast'!$B94) -> 9.10884 | AT94: =SUMIFS('Combined P&L'!AR:AR,'Combined P&L'!$C:$C,'P&L Forecast'!$B94) -> 9.52287
B95: Onboarding Team Wages | C95: =SUMIFS($P95:$AT95,$P$69:$AT$69,">"&C$169,$P$69:$AT$69,"<"&C$170) -> 122.81255 | D95: =SUMIFS($P95:$AT95,$P$69:$AT$69,">"&D$169,$P$69:$AT$69,"<"&D$170) -> 152.16972 | F95: =SUMIFS($P95:$AT95,$P$69:$AT$69,">"&F$169,$P$69:$AT$69,"<"&F$170) -> 73.94962 | G95: =SUMIFS($P95:$AT95,$P$69:$AT$69,">"&G$169,$P$69:$AT$69,"<"&G$170) -> 111.27999 | I95: =SUMIFS($P95:$AT95,$P$69:$AT$69,">"&I$169,$P$69:$AT$69,"<"&I$170) -> 115.8168 | J95: =SUMIFS($P95:$AT95,$P$69:$AT$69,">"&J$169,$P$69:$AT$69,"<"&J$170) -> 186.54354 | K95: =+C31 -> 197.14944 | M95: =+J95-K95 -> -10.6059 | N95: =IFERROR(K95/J95-1,0) -> 0.056854823 | P95: =SUMIFS('Combined P&L'!N:N,'Combined P&L'!$C:$C,'P&L Forecast'!$B95) -> 9.13728 | Q95: =SUMIFS('Combined P&L'!O:O,'Combined P&L'!$C:$C,'P&L Forecast'!$B95) -> 8.96296 | R95: =SUMIFS('Combined P&L'!P:P,'Combined P&L'!$C:$C,'P&L Forecast'!$B95) -> 10.19584 | S95: =SUMIFS('Combined P&L'!Q:Q,'Combined P&L'!$C:$C,'P&L Forecast'!$B95) -> 15.04429 | T95: =SUMIFS('Combined P&L'!R:R,'Combined P&L'!$C:$C,'P&L Forecast'!$B95) -> 16.63744 | U95: =SUMIFS('Combined P&L'!S:S,'Combined P&L'!$C:$C,'P&L Forecast'!$B95) -> 7.49499 | V95: =SUMIFS('Combined P&L'!T:T,'Combined P&L'!$C:$C,'P&L Forecast'!$B95) -> 7.98202 | W95: =SUMIFS('Combined P&L'!U:U,'Combined P&L'!$C:$C,'P&L Forecast'!$B95) -> 5.90274 | X95: =SUMIFS('Combined P&L'!V:V,'Combined P&L'!$C:$C,'P&L Forecast'!$B95) -> 7.76763 | Y95: =SUMIFS('Combined P&L'!W:W,'Combined P&L'!$C:$C,'P&L Forecast'!$B95) -> 8.21417 | Z95: =SUMIFS('Combined P&L'!X:X,'Combined P&L'!$C:$C,'P&L Forecast'!$B95) -> 12.62272 | AA95: =SUMIFS('Combined P&L'!Y:Y,'Combined P&L'!$C:$C,'P&L Forecast'!$B95) -> 12.85047 | AB95: =SUMIFS('Combined P&L'!Z:Z,'Combined P&L'!$C:$C,'P&L Forecast'!$B95) -> 10.34556 | AC95: =SUMIFS('Combined P&L'!AA:AA,'Combined P&L'!$C:$C,'P&L Forecast'!$B95) -> 8.08798 | AD95: =SUMIFS('Combined P&L'!AB:AB,'Combined P&L'!$C:$C,'P&L Forecast'!$B95) -> 9.75287 | AE95: =SUMIFS('Combined P&L'!AC:AC,'Combined P&L'!$C:$C,'P&L Forecast'!$B95) -> 10.28 | AF95: =SUMIFS('Combined P&L'!AD:AD,'Combined P&L'!$C:$C,'P&L Forecast'!$B95) -> 11.13632 | AG95: =SUMIFS('Combined P&L'!AE:AE,'Combined P&L'!$C:$C,'P&L Forecast'!$B95) -> 10.87432 | AH95: =SUMIFS('Combined P&L'!AF:AF,'Combined P&L'!$C:$C,'P&L Forecast'!$B95) -> 13.47257 | AI95: =SUMIFS('Combined P&L'!AG:AG,'Combined P&L'!$C:$C,'P&L Forecast'!$B95) -> 12.70407 | AJ95: =SUMIFS('Combined P&L'!AH:AH,'Combined P&L'!$C:$C,'P&L Forecast'!$B95) -> 14.69884 | AK95: =SUMIFS('Combined P&L'!AI:AI,'Combined P&L'!$C:$C,'P&L Forecast'!$B95) -> 15.54306 | AL95: =SUMIFS('Combined P&L'!AJ:AJ,'Combined P&L'!$C:$C,'P&L Forecast'!$B95) -> 14.34361 | AM95: =SUMIFS('Combined P&L'!AK:AK,'Combined P&L'!$C:$C,'P&L Forecast'!$B95) -> 20.93052 | AN95: =SUMIFS('Combined P&L'!AL:AL,'Combined P&L'!$C:$C,'P&L Forecast'!$B95) -> 16.55394 | AO95: =SUMIFS('Combined P&L'!AM:AM,'Combined P&L'!$C:$C,'P&L Forecast'!$B95) -> 11.52661 | AP95: =SUMIFS('Combined P&L'!AN:AN,'Combined P&L'!$C:$C,'P&L Forecast'!$B95) -> 14.93883 | AQ95: =SUMIFS('Combined P&L'!AO:AO,'Combined P&L'!$C:$C,'P&L Forecast'!$B95) -> 15.58352 | AR95: =SUMIFS('Combined P&L'!AP:AP,'Combined P&L'!$C:$C,'P&L Forecast'!$B95) -> 19.6034 | AS95: =SUMIFS('Combined P&L'!AQ:AQ,'Combined P&L'!$C:$C,'P&L Forecast'!$B95) -> 16.64457 | AT95: =SUMIFS('Combined P&L'!AR:AR,'Combined P&L'!$C:$C,'P&L Forecast'!$B95) -> 16.42912
B96: S&M Wages | C96: =SUMIFS($P96:$AT96,$P$69:$AT$69,">"&C$169,$P$69:$AT$69,"<"&C$170) -> 0 | D96: =SUMIFS($P96:$AT96,$P$69:$AT$69,">"&D$169,$P$69:$AT$69,"<"&D$170) -> 19.14963 | F96: =SUMIFS($P96:$AT96,$P$69:$AT$69,">"&F$169,$P$69:$AT$69,"<"&F$170) -> 3.09945 | G96: =SUMIFS($P96:$AT96,$P$69:$AT$69,">"&G$169,$P$69:$AT$69,"<"&G$170) -> 51.94131 | I96: =SUMIFS($P96:$AT96,$P$69:$AT$69,">"&I$169,$P$69:$AT$69,"<"&I$170) -> 1.4668 | J96: =SUMIFS($P96:$AT96,$P$69:$AT$69,">"&J$169,$P$69:$AT$69,"<"&J$170) -> 61.42838 | K96: =+C28 -> 98.34912 | M96: =+J96-K96 -> -36.92074 | N96: =IFERROR(K96/J96-1,0) -> 0.60103718 | P96: =SUMIFS('Combined P&L'!N:N,'Combined P&L'!$C:$C,'P&L Forecast'!$B96) -> 0 | Q96: =SUMIFS('Combined P&L'!O:O,'Combined P&L'!$C:$C,'P&L Forecast'!$B96) -> 0 | R96: =SUMIFS('Combined P&L'!P:P,'Combined P&L'!$C:$C,'P&L Forecast'!$B96) -> 0 | S96: =SUMIFS('Combined P&L'!Q:Q,'Combined P&L'!$C:$C,'P&L Forecast'!$B96) -> 0 | T96: =SUMIFS('Combined P&L'!R:R,'Combined P&L'!$C:$C,'P&L Forecast'!$B96) -> 0 | U96: =SUMIFS('Combined P&L'!S:S,'Combined P&L'!$C:$C,'P&L Forecast'!$B96) -> 0 | V96: =SUMIFS('Combined P&L'!T:T,'Combined P&L'!$C:$C,'P&L Forecast'!$B96) -> 0 | W96: =SUMIFS('Combined P&L'!U:U,'Combined P&L'!$C:$C,'P&L Forecast'!$B96) -> 0 | X96: =SUMIFS('Combined P&L'!V:V,'Combined P&L'!$C:$C,'P&L Forecast'!$B96) -> 0 | Y96: =SUMIFS('Combined P&L'!W:W,'Combined P&L'!$C:$C,'P&L Forecast'!$B96) -> 0 | Z96: =SUMIFS('Combined P&L'!X:X,'Combined P&L'!$C:$C,'P&L Forecast'!$B96) -> 0 | AA96: =SUMIFS('Combined P&L'!Y:Y,'Combined P&L'!$C:$C,'P&L Forecast'!$B96) -> 0 | AB96: =SUMIFS('Combined P&L'!Z:Z,'Combined P&L'!$C:$C,'P&L Forecast'!$B96) -> 0 | AC96: =SUMIFS('Combined P&L'!AA:AA,'Combined P&L'!$C:$C,'P&L Forecast'!$B96) -> 0 | AD96: =SUMIFS('Combined P&L'!AB:AB,'Combined P&L'!$C:$C,'P&L Forecast'!$B96) -> 0 | AE96: =SUMIFS('Combined P&L'!AC:AC,'Combined P&L'!$C:$C,'P&L Forecast'!$B96) -> 0 | AF96: =SUMIFS('Combined P&L'!AD:AD,'Combined P&L'!$C:$C,'P&L Forecast'!$B96) -> 0 | AG96: =SUMIFS('Combined P&L'!AE:AE,'Combined P&L'!$C:$C,'P&L Forecast'!$B96) -> 1.4668 | AH96: =SUMIFS('Combined P&L'!AF:AF,'Combined P&L'!$C:$C,'P&L Forecast'!$B96) -> 1.63265 | AI96: =SUMIFS('Combined P&L'!AG:AG,'Combined P&L'!$C:$C,'P&L Forecast'!$B96) -> 1.71805 | AJ96: =SUMIFS('Combined P&L'!AH:AH,'Combined P&L'!$C:$C,'P&L Forecast'!$B96) -> 1.9146 | AK96: =SUMIFS('Combined P&L'!AI:AI,'Combined P&L'!$C:$C,'P&L Forecast'!$B96) -> 2.3529 | AL96: =SUMIFS('Combined P&L'!AJ:AJ,'Combined P&L'!$C:$C,'P&L Forecast'!$B96) -> 2.24524 | AM96: =SUMIFS('Combined P&L'!AK:AK,'Combined P&L'!$C:$C,'P&L Forecast'!$B96) -> 7.81939 | AN96: =SUMIFS('Combined P&L'!AL:AL,'Combined P&L'!$C:$C,'P&L Forecast'!$B96) -> 5.6534 | AO96: =SUMIFS('Combined P&L'!AM:AM,'Combined P&L'!$C:$C,'P&L Forecast'!$B96) -> 5.95689 | AP96: =SUMIFS('Combined P&L'!AN:AN,'Combined P&L'!$C:$C,'P&L Forecast'!$B96) -> 7.7828 | AQ96: =SUMIFS('Combined P&L'!AO:AO,'Combined P&L'!$C:$C,'P&L Forecast'!$B96) -> 8.13701 | AR96: =SUMIFS('Combined P&L'!AP:AP,'Combined P&L'!$C:$C,'P&L Forecast'!$B96) -> 7.80825 | AS96: =SUMIFS('Combined P&L'!AQ:AQ,'Combined P&L'!$C:$C,'P&L Forecast'!$B96) -> 8.4072 | AT96: =SUMIFS('Combined P&L'!AR:AR,'Combined P&L'!$C:$C,'P&L Forecast'!$B96) -> 8.19576
B97: Occupancy Tax Specialist | C97: =SUMIFS($P97:$AT97,$P$69:$AT$69,">"&C$169,$P$69:$AT$69,"<"&C$170) -> 1.11335 | D97: =SUMIFS($P97:$AT97,$P$69:$AT$69,">"&D$169,$P$69:$AT$69,"<"&D$170) -> 29.56415 | F97: =SUMIFS($P97:$AT97,$P$69:$AT$69,">"&F$169,$P$69:$AT$69,"<"&F$170) -> 14.27585 | G97: =SUMIFS($P97:$AT97,$P$69:$AT$69,">"&G$169,$P$69:$AT$69,"<"&G$170) -> 42.08505 | I97: =SUMIFS($P97:$AT97,$P$69:$AT$69,">"&I$169,$P$69:$AT$69,"<"&I$170) -> 13.21003 | J97: =SUMIFS($P97:$AT97,$P$69:$AT$69,">"&J$169,$P$69:$AT$69,"<"&J$170) -> 53.87642 | K97: =+C29 -> 68.1132 | M97: =+J97-K97 -> -14.23678 | N97: =IFERROR(K97/J97-1,0) -> 0.26424881 | P97: =SUMIFS('Combined P&L'!N:N,'Combined P&L'!$C:$C,'P&L Forecast'!$B97) -> 0 | Q97: =SUMIFS('Combined P&L'!O:O,'Combined P&L'!$C:$C,'P&L Forecast'!$B97) -> 0 | R97: =SUMIFS('Combined P&L'!P:P,'Combined P&L'!$C:$C,'P&L Forecast'!$B97) -> 0 | S97: =SUMIFS('Combined P&L'!Q:Q,'Combined P&L'!$C:$C,'P&L Forecast'!$B97) -> 0 | T97: =SUMIFS('Combined P&L'!R:R,'Combined P&L'!$C:$C,'P&L Forecast'!$B97) -> 0 | U97: =SUMIFS('Combined P&L'!S:S,'Combined P&L'!$C:$C,'P&L Forecast'!$B97) -> 0 | V97: =SUMIFS('Combined P&L'!T:T,'Combined P&L'!$C:$C,'P&L Forecast'!$B97) -> 0 | W97: =SUMIFS('Combined P&L'!U:U,'Combined P&L'!$C:$C,'P&L Forecast'!$B97) -> 0 | X97: =SUMIFS('Combined P&L'!V:V,'Combined P&L'!$C:$C,'P&L Forecast'!$B97) -> 0 | Y97: =SUMIFS('Combined P&L'!W:W,'Combined P&L'!$C:$C,'P&L Forecast'!$B97) -> 0 | Z97: =SUMIFS('Combined P&L'!X:X,'Combined P&L'!$C:$C,'P&L Forecast'!$B97) -> 0 | AA97: =SUMIFS('Combined P&L'!Y:Y,'Combined P&L'!$C:$C,'P&L Forecast'!$B97) -> 1.11335 | AB97: =SUMIFS('Combined P&L'!Z:Z,'Combined P&L'!$C:$C,'P&L Forecast'!$B97) -> 2.17917 | AC97: =SUMIFS('Combined P&L'!AA:AA,'Combined P&L'!$C:$C,'P&L Forecast'!$B97) -> 1.82504 | AD97: =SUMIFS('Combined P&L'!AB:AB,'Combined P&L'!$C:$C,'P&L Forecast'!$B97) -> 1.97853 | AE97: =SUMIFS('Combined P&L'!AC:AC,'Combined P&L'!$C:$C,'P&L Forecast'!$B97) -> 2.06213 | AF97: =SUMIFS('Combined P&L'!AD:AD,'Combined P&L'!$C:$C,'P&L Forecast'!$B97) -> 2.06213 | AG97: =SUMIFS('Combined P&L'!AE:AE,'Combined P&L'!$C:$C,'P&L Forecast'!$B97) -> 1.98968 | AH97: =SUMIFS('Combined P&L'!AF:AF,'Combined P&L'!$C:$C,'P&L Forecast'!$B97) -> 2.17917 | AI97: =SUMIFS('Combined P&L'!AG:AG,'Combined P&L'!$C:$C,'P&L Forecast'!$B97) -> 2.12293 | AJ97: =SUMIFS('Combined P&L'!AH:AH,'Combined P&L'!$C:$C,'P&L Forecast'!$B97) -> 3.1042 | AK97: =SUMIFS('Combined P&L'!AI:AI,'Combined P&L'!$C:$C,'P&L Forecast'!$B97) -> 3.27137 | AL97: =SUMIFS('Combined P&L'!AJ:AJ,'Combined P&L'!$C:$C,'P&L Forecast'!$B97) -> 3.63947 | AM97: =SUMIFS('Combined P&L'!AK:AK,'Combined P&L'!$C:$C,'P&L Forecast'!$B97) -> 3.15033 | AN97: =SUMIFS('Combined P&L'!AL:AL,'Combined P&L'!$C:$C,'P&L Forecast'!$B97) -> 1.69116 | AO97: =SUMIFS('Combined P&L'!AM:AM,'Combined P&L'!$C:$C,'P&L Forecast'!$B97) -> 5.54919 | AP97: =SUMIFS('Combined P&L'!AN:AN,'Combined P&L'!$C:$C,'P&L Forecast'!$B97) -> 7.1999 | AQ97: =SUMIFS('Combined P&L'!AO:AO,'Combined P&L'!$C:$C,'P&L Forecast'!$B97) -> 8.1927 | AR97: =SUMIFS('Combined P&L'!AP:AP,'Combined P&L'!$C:$C,'P&L Forecast'!$B97) -> 8.28335 | AS97: =SUMIFS('Combined P&L'!AQ:AQ,'Combined P&L'!$C:$C,'P&L Forecast'!$B97) -> 5.49265 | AT97: =SUMIFS('Combined P&L'!AR:AR,'Combined P&L'!$C:$C,'P&L Forecast'!$B97) -> 5.6761
B98: Sr. Client Lead Wages | C98: =SUMIFS($P98:$AT98,$P$69:$AT$69,">"&C$169,$P$69:$AT$69,"<"&C$170) -> 0 | D98: =SUMIFS($P98:$AT98,$P$69:$AT$69,">"&D$169,$P$69:$AT$69,"<"&D$170) -> 0 | F98: =SUMIFS($P98:$AT98,$P$69:$AT$69,">"&F$169,$P$69:$AT$69,"<"&F$170) -> 0 | G98: =SUMIFS($P98:$AT98,$P$69:$AT$69,">"&G$169,$P$69:$AT$69,"<"&G$170) -> 7.995 | I98: =SUMIFS($P98:$AT98,$P$69:$AT$69,">"&I$169,$P$69:$AT$69,"<"&I$170) -> 0 | J98: =SUMIFS($P98:$AT98,$P$69:$AT$69,">"&J$169,$P$69:$AT$69,"<"&J$170) -> 5.23823 | K98: =+C30 -> 33.08124 | M98: =+J98-K98 -> -27.84301 | N98: =IFERROR(K98/J98-1,0) -> 5.315347 | P98: =SUMIFS('Combined P&L'!N:N,'Combined P&L'!$C:$C,'P&L Forecast'!$B98) -> 0 | Q98: =SUMIFS('Combined P&L'!O:O,'Combined P&L'!$C:$C,'P&L Forecast'!$B98) -> 0 | R98: =SUMIFS('Combined P&L'!P:P,'Combined P&L'!$C:$C,'P&L Forecast'!$B98) -> 0 | S98: =SUMIFS('Combined P&L'!Q:Q,'Combined P&L'!$C:$C,'P&L Forecast'!$B98) -> 0 | T98: =SUMIFS('Combined P&L'!R:R,'Combined P&L'!$C:$C,'P&L Forecast'!$B98) -> 0 | U98: =SUMIFS('Combined P&L'!S:S,'Combined P&L'!$C:$C,'P&L Forecast'!$B98) -> 0 | V98: =SUMIFS('Combined P&L'!T:T,'Combined P&L'!$C:$C,'P&L Forecast'!$B98) -> 0 | W98: =SUMIFS('Combined P&L'!U:U,'Combined P&L'!$C:$C,'P&L Forecast'!$B98) -> 0 | X98: =SUMIFS('Combined P&L'!V:V,'Combined P&L'!$C:$C,'P&L Forecast'!$B98) -> 0 | Y98: =SUMIFS('Combined P&L'!W:W,'Combined P&L'!$C:$C,'P&L Forecast'!$B98) -> 0 | Z98: =SUMIFS('Combined P&L'!X:X,'Combined P&L'!$C:$C,'P&L Forecast'!$B98) -> 0 | AA98: =SUMIFS('Combined P&L'!Y:Y,'Combined P&L'!$C:$C,'P&L Forecast'!$B98) -> 0 | AB98: =SUMIFS('Combined P&L'!Z:Z,'Combined P&L'!$C:$C,'P&L Forecast'!$B98) -> 0 | AC98: =SUMIFS('Combined P&L'!AA:AA,'Combined P&L'!$C:$C,'P&L Forecast'!$B98) -> 0 | AD98: =SUMIFS('Combined P&L'!AB:AB,'Combined P&L'!$C:$C,'P&L Forecast'!$B98) -> 0 | AE98: =SUMIFS('Combined P&L'!AC:AC,'Combined P&L'!$C:$C,'P&L Forecast'!$B98) -> 0 | AF98: =SUMIFS('Combined P&L'!AD:AD,'Combined P&L'!$C:$C,'P&L Forecast'!$B98) -> 0 | AG98: =SUMIFS('Combined P&L'!AE:AE,'Combined P&L'!$C:$C,'P&L Forecast'!$B98) -> 0 | AH98: =SUMIFS('Combined P&L'!AF:AF,'Combined P&L'!$C:$C,'P&L Forecast'!$B98) -> 0 | AI98: =SUMIFS('Combined P&L'!AG:AG,'Combined P&L'!$C:$C,'P&L Forecast'!$B98) -> 0 | AJ98: =SUMIFS('Combined P&L'!AH:AH,'Combined P&L'!$C:$C,'P&L Forecast'!$B98) -> 0 | AK98: =SUMIFS('Combined P&L'!AI:AI,'Combined P&L'!$C:$C,'P&L Forecast'!$B98) -> 0 | AL98: =SUMIFS('Combined P&L'!AJ:AJ,'Combined P&L'!$C:$C,'P&L Forecast'!$B98) -> 0 | AM98: =SUMIFS('Combined P&L'!AK:AK,'Combined P&L'!$C:$C,'P&L Forecast'!$B98) -> 0 | AN98: =SUMIFS('Combined P&L'!AL:AL,'Combined P&L'!$C:$C,'P&L Forecast'!$B98) -> 0 | AO98: =SUMIFS('Combined P&L'!AM:AM,'Combined P&L'!$C:$C,'P&L Forecast'!$B98) -> 0 | AP98: =SUMIFS('Combined P&L'!AN:AN,'Combined P&L'!$C:$C,'P&L Forecast'!$B98) -> 0 | AQ98: =SUMIFS('Combined P&L'!AO:AO,'Combined P&L'!$C:$C,'P&L Forecast'!$B98) -> 0 | AR98: =SUMIFS('Combined P&L'!AP:AP,'Combined P&L'!$C:$C,'P&L Forecast'!$B98) -> 2.51706 | AS98: =SUMIFS('Combined P&L'!AQ:AQ,'Combined P&L'!$C:$C,'P&L Forecast'!$B98) -> 2.72117 | AT98: =SUMIFS('Combined P&L'!AR:AR,'Combined P&L'!$C:$C,'P&L Forecast'!$B98) -> 2.75677
B99: Employee Benefits | C99: =SUMIFS($P99:$AT99,$P$69:$AT$69,">"&C$169,$P$69:$AT$69,"<"&C$170) -> 5.37405 | D99: =SUMIFS($P99:$AT99,$P$69:$AT$69,">"&D$169,$P$69:$AT$69,"<"&D$170) -> 19.23245 | F99: =SUMIFS($P99:$AT99,$P$69:$AT$69,">"&F$169,$P$69:$AT$69,"<"&F$170) -> 9.02166 | G99: =SUMIFS($P99:$AT99,$P$69:$AT$69,">"&G$169,$P$69:$AT$69,"<"&G$170) -> 17.36251 | I99: =SUMIFS($P99:$AT99,$P$69:$AT$69,">"&I$169,$P$69:$AT$69,"<"&I$170) -> 11.46793 | J99: =SUMIFS($P99:$AT99,$P$69:$AT$69,">"&J$169,$P$69:$AT$69,"<"&J$170) -> 26.4526 | K99: =+C32 -> 32.17836 | M99: =+J99-K99 -> -5.72576 | N99: =IFERROR(K99/J99-1,0) -> 0.21645358 | P99: =SUMIFS('Combined P&L'!N:N,'Combined P&L'!$C:$C,'P&L Forecast'!$B99) -> 0 | Q99: =SUMIFS('Combined P&L'!O:O,'Combined P&L'!$C:$C,'P&L Forecast'!$B99) -> 0.6277 | R99: =SUMIFS('Combined P&L'!P:P,'Combined P&L'!$C:$C,'P&L Forecast'!$B99) -> 0 | S99: =SUMIFS('Combined P&L'!Q:Q,'Combined P&L'!$C:$C,'P&L Forecast'!$B99) -> 0.3389 | T99: =SUMIFS('Combined P&L'!R:R,'Combined P&L'!$C:$C,'P&L Forecast'!$B99) -> 0.3389 | U99: =SUMIFS('Combined P&L'!S:S,'Combined P&L'!$C:$C,'P&L Forecast'!$B99) -> 0.06145 | V99: =SUMIFS('Combined P&L'!T:T,'Combined P&L'!$C:$C,'P&L Forecast'!$B99) -> 0.8619 | W99: =SUMIFS('Combined P&L'!U:U,'Combined P&L'!$C:$C,'P&L Forecast'!$B99) -> 0.35956 | X99: =SUMIFS('Combined P&L'!V:V,'Combined P&L'!$C:$C,'P&L Forecast'!$B99) -> 0.38745 | Y99: =SUMIFS('Combined P&L'!W:W,'Combined P&L'!$C:$C,'P&L Forecast'!$B99) -> 0.6989 | Z99: =SUMIFS('Combined P&L'!X:X,'Combined P&L'!$C:$C,'P&L Forecast'!$B99) -> 0.917 | AA99: =SUMIFS('Combined P&L'!Y:Y,'Combined P&L'!$C:$C,'P&L Forecast'!$B99) -> 0.78229 | AB99: =SUMIFS('Combined P&L'!Z:Z,'Combined P&L'!$C:$C,'P&L Forecast'!$B99) -> 0.93724 | AC99: =SUMIFS('Combined P&L'!AA:AA,'Combined P&L'!$C:$C,'P&L Forecast'!$B99) -> 1.03107 | AD99: =SUMIFS('Combined P&L'!AB:AB,'Combined P&L'!$C:$C,'P&L Forecast'!$B99) -> 0.66153 | AE99: =SUMIFS('Combined P&L'!AC:AC,'Combined P&L'!$C:$C,'P&L Forecast'!$B99) -> 0.71453 | AF99: =SUMIFS('Combined P&L'!AD:AD,'Combined P&L'!$C:$C,'P&L Forecast'!$B99) -> 2.25493 | AG99: =SUMIFS('Combined P&L'!AE:AE,'Combined P&L'!$C:$C,'P&L Forecast'!$B99) -> 1.86153 | AH99: =SUMIFS('Combined P&L'!AF:AF,'Combined P&L'!$C:$C,'P&L Forecast'!$B99) -> 1.56083 | AI99: =SUMIFS('Combined P&L'!AG:AG,'Combined P&L'!$C:$C,'P&L Forecast'!$B99) -> 1.74767 | AJ99: =SUMIFS('Combined P&L'!AH:AH,'Combined P&L'!$C:$C,'P&L Forecast'!$B99) -> 0.90753 | AK99: =SUMIFS('Combined P&L'!AI:AI,'Combined P&L'!$C:$C,'P&L Forecast'!$B99) -> 2.51353 | AL99: =SUMIFS('Combined P&L'!AJ:AJ,'Combined P&L'!$C:$C,'P&L Forecast'!$B99) -> 1.03753 | AM99: =SUMIFS('Combined P&L'!AK:AK,'Combined P&L'!$C:$C,'P&L Forecast'!$B99) -> 4.00453 | AN99: =SUMIFS('Combined P&L'!AL:AL,'Combined P&L'!$C:$C,'P&L Forecast'!$B99) -> 1.57873 | AO99: =SUMIFS('Combined P&L'!AM:AM,'Combined P&L'!$C:$C,'P&L Forecast'!$B99) -> 1.14553 | AP99: =SUMIFS('Combined P&L'!AN:AN,'Combined P&L'!$C:$C,'P&L Forecast'!$B99) -> 5.13853 | AQ99: =SUMIFS('Combined P&L'!AO:AO,'Combined P&L'!$C:$C,'P&L Forecast'!$B99) -> 1.92353 | AR99: =SUMIFS('Combined P&L'!AP:AP,'Combined P&L'!$C:$C,'P&L Forecast'!$B99) -> 1.46353 | AS99: =SUMIFS('Combined P&L'!AQ:AQ,'Combined P&L'!$C:$C,'P&L Forecast'!$B99) -> 3.43113 | AT99: =SUMIFS('Combined P&L'!AR:AR,'Combined P&L'!$C:$C,'P&L Forecast'!$B99) -> 2.68153
B100: Total Payroll Expenses | C100: =SUM(C91:C99) -> 700.20547 | D100: =SUM(D91:D99) -> 1261.1666 | F100: =SUM(F91:F99) -> 630.65714 | G100: =SUM(G91:G99) -> 1120.8921 | I100: =SUM(I91:I99) -> 940.94885 | J100: =SUM(J91:J99) -> 1679.372 | K100: =SUM(K91:K99) -> 2250.3916 | M100: =SUM(M91:M99) -> -571.01967 | N100: =IFERROR(K100/J100-1,0) -> 0.34001977 | P100: =SUM(P91:P99) -> 31.74682 | Q100: =SUM(Q91:Q99) -> 37.62609 | R100: =SUM(R91:R99) -> 37.77865 | S100: =SUM(S91:S99) -> 50.81818 | T100: =SUM(T91:T99) -> 70.6441 | U100: =SUM(U91:U99) -> 52.94065 | V100: =SUM(V91:V99) -> 56.15375 | W100: =SUM(W91:W99) -> 52.54102 | ... AT100: =SUM(AT91:AT99) -> 180.38884
B102: Software & Apps - COGS | C102: =SUMIFS($P102:$AT102,$P$69:$AT$69,">"&C$169,$P$69:$AT$69,"<"&C$170) -> 114.42269 | D102: =SUMIFS($P102:$AT102,$P$69:$AT$69,">"&D$169,$P$69:$AT$69,"<"&D$170) -> 157.49471 | F102: =SUMIFS($P102:$AT102,$P$69:$AT$69,">"&F$169,$P$69:$AT$69,"<"&F$170) -> 84.96859 | G102: =SUMIFS($P102:$AT102,$P$69:$AT$69,">"&G$169,$P$69:$AT$69,"<"&G$170) -> 152.28157 | I102: =SUMIFS($P102:$AT102,$P$69:$AT$69,">"&I$169,$P$69:$AT$69,"<"&I$170) -> 139.99468 | J102: =SUMIFS($P102:$AT102,$P$69:$AT$69,">"&J$169,$P$69:$AT$69,"<"&J$170) -> 209.96746 | K102: =+C36 -> 335.70816 | M102: =+J102-K102 -> -125.7407 | N102: =IFERROR(K102/J102-1,0) -> 0.59885803 | P102: =SUMIFS('Combined P&L'!N:N,'Combined P&L'!$C:$C,'P&L Forecast'!$B102) -> 7.073 | Q102: =SUMIFS('Combined P&L'!O:O,'Combined P&L'!$C:$C,'P&L Forecast'!$B102) -> 7.01818 | R102: =SUMIFS('Combined P&L'!P:P,'Combined P&L'!$C:$C,'P&L Forecast'!$B102) -> 7.77788 | S102: =SUMIFS('Combined P&L'!Q:Q,'Combined P&L'!$C:$C,'P&L Forecast'!$B102) -> 7.76124 | T102: =SUMIFS('Combined P&L'!R:R,'Combined P&L'!$C:$C,'P&L Forecast'!$B102) -> 7.71821 | U102: =SUMIFS('Combined P&L'!S:S,'Combined P&L'!$C:$C,'P&L Forecast'!$B102) -> 8.91264 | V102: =SUMIFS('Combined P&L'!T:T,'Combined P&L'!$C:$C,'P&L Forecast'!$B102) -> 10.84668 | W102: =SUMIFS('Combined P&L'!U:U,'Combined P&L'!$C:$C,'P&L Forecast'!$B102) -> 11.13514 | X102: =SUMIFS('Combined P&L'!V:V,'Combined P&L'!$C:$C,'P&L Forecast'!$B102) -> 11.0345 | Y102: =SUMIFS('Combined P&L'!W:W,'Combined P&L'!$C:$C,'P&L Forecast'!$B102) -> 11.72873 | Z102: =SUMIFS('Combined P&L'!X:X,'Combined P&L'!$C:$C,'P&L Forecast'!$B102) -> 11.44691 | AA102: =SUMIFS('Combined P&L'!Y:Y,'Combined P&L'!$C:$C,'P&L Forecast'!$B102) -> 11.96958 | AB102: =SUMIFS('Combined P&L'!Z:Z,'Combined P&L'!$C:$C,'P&L Forecast'!$B102) -> 10.84853 | AC102: =SUMIFS('Combined P&L'!AA:AA,'Combined P&L'!$C:$C,'P&L Forecast'!$B102) -> 12.21311 | AD102: =SUMIFS('Combined P&L'!AB:AB,'Combined P&L'!$C:$C,'P&L Forecast'!$B102) -> 11.57167 | AE102: =SUMIFS('Combined P&L'!AC:AC,'Combined P&L'!$C:$C,'P&L Forecast'!$B102) -> 11.81087 | AF102: =SUMIFS('Combined P&L'!AD:AD,'Combined P&L'!$C:$C,'P&L Forecast'!$B102) -> 12.52563 | AG102: =SUMIFS('Combined P&L'!AE:AE,'Combined P&L'!$C:$C,'P&L Forecast'!$B102) -> 12.86333 | AH102: =SUMIFS('Combined P&L'!AF:AF,'Combined P&L'!$C:$C,'P&L Forecast'!$B102) -> 13.13545 | AI102: =SUMIFS('Combined P&L'!AG:AG,'Combined P&L'!$C:$C,'P&L Forecast'!$B102) -> 14.25715 | AJ102: =SUMIFS('Combined P&L'!AH:AH,'Combined P&L'!$C:$C,'P&L Forecast'!$B102) -> 13.59512 | AK102: =SUMIFS('Combined P&L'!AI:AI,'Combined P&L'!$C:$C,'P&L Forecast'!$B102) -> 12.34762 | AL102: =SUMIFS('Combined P&L'!AJ:AJ,'Combined P&L'!$C:$C,'P&L Forecast'!$B102) -> 15.21781 | AM102: =SUMIFS('Combined P&L'!AK:AK,'Combined P&L'!$C:$C,'P&L Forecast'!$B102) -> 17.10842 | AN102: =SUMIFS('Combined P&L'!AL:AL,'Combined P&L'!$C:$C,'P&L Forecast'!$B102) -> 18.4683 | AO102: =SUMIFS('Combined P&L'!AM:AM,'Combined P&L'!$C:$C,'P&L Forecast'!$B102) -> 17.92027 | AP102: =SUMIFS('Combined P&L'!AN:AN,'Combined P&L'!$C:$C,'P&L Forecast'!$B102) -> 18.40906 | AQ102: =SUMIFS('Combined P&L'!AO:AO,'Combined P&L'!$C:$C,'P&L Forecast'!$B102) -> 21.38775 | AR102: =SUMIFS('Combined P&L'!AP:AP,'Combined P&L'!$C:$C,'P&L Forecast'!$B102) -> 23.44584 | AS102: =SUMIFS('Combined P&L'!AQ:AQ,'Combined P&L'!$C:$C,'P&L Forecast'!$B102) -> 24.67467 | AT102: =SUMIFS('Combined P&L'!AR:AR,'Combined P&L'!$C:$C,'P&L Forecast'!$B102) -> 27.97568
B103: Software & Apps - G&A | C103: =SUMIFS($P103:$AT103,$P$69:$AT$69,">"&C$169,$P$69:$AT$69,"<"&C$170) -> 60.91594 | D103: =SUMIFS($P103:$AT103,$P$69:$AT$69,">"&D$169,$P$69:$AT$69,"<"&D$170) -> 117.05866 | F103: =SUMIFS($P103:$AT103,$P$69:$AT$69,">"&F$169,$P$69:$AT$69,"<"&F$170) -> 56.8115 | G103: =SUMIFS($P103:$AT103,$P$69:$AT$69,">"&G$169,$P$69:$AT$69,"<"&G$170) -> 97.04798 | I103: =SUMIFS($P103:$AT103,$P$69:$AT$69,">"&I$169,$P$69:$AT$69,"<"&I$170) -> 83.0439 | J103: =SUMIFS($P103:$AT103,$P$69:$AT$69,">"&J$169,$P$69:$AT$69,"<"&J$170) -> 153.2946 | K103: =+C37 -> 155.82264 | M103: =+J103-K103 -> -2.52804 | N103: =IFERROR(K103/J103-1,0) -> 0.016491383 | P103: =SUMIFS('Combined P&L'!N:N,'Combined P&L'!$C:$C,'P&L Forecast'!$B103) -> 3.45285 | Q103: =SUMIFS('Combined P&L'!O:O,'Combined P&L'!$C:$C,'P&L Forecast'!$B103) -> 3.61753 | R103: =SUMIFS('Combined P&L'!P:P,'Combined P&L'!$C:$C,'P&L Forecast'!$B103) -> 3.97407 | S103: =SUMIFS('Combined P&L'!Q:Q,'Combined P&L'!$C:$C,'P&L Forecast'!$B103) -> 4.22365 | T103: =SUMIFS('Combined P&L'!R:R,'Combined P&L'!$C:$C,'P&L Forecast'!$B103) -> 5.09725 | U103: =SUMIFS('Combined P&L'!S:S,'Combined P&L'!$C:$C,'P&L Forecast'!$B103) -> 5.33351 | V103: =SUMIFS('Combined P&L'!T:T,'Combined P&L'!$C:$C,'P&L Forecast'!$B103) -> 5.51369 | W103: =SUMIFS('Combined P&L'!U:U,'Combined P&L'!$C:$C,'P&L Forecast'!$B103) -> 5.23169 | X103: =SUMIFS('Combined P&L'!V:V,'Combined P&L'!$C:$C,'P&L Forecast'!$B103) -> 5.51622 | Y103: =SUMIFS('Combined P&L'!W:W,'Combined P&L'!$C:$C,'P&L Forecast'!$B103) -> 6.12797 | Z103: =SUMIFS('Combined P&L'!X:X,'Combined P&L'!$C:$C,'P&L Forecast'!$B103) -> 6.15097 | AA103: =SUMIFS('Combined P&L'!Y:Y,'Combined P&L'!$C:$C,'P&L Forecast'!$B103) -> 6.67654 | AB103: =SUMIFS('Combined P&L'!Z:Z,'Combined P&L'!$C:$C,'P&L Forecast'!$B103) -> 7.74646 | AC103: =SUMIFS('Combined P&L'!AA:AA,'Combined P&L'!$C:$C,'P&L Forecast'!$B103) -> 7.89181 | AD103: =SUMIFS('Combined P&L'!AB:AB,'Combined P&L'!$C:$C,'P&L Forecast'!$B103) -> 7.89085 | AE103: =SUMIFS('Combined P&L'!AC:AC,'Combined P&L'!$C:$C,'P&L Forecast'!$B103) -> 7.83463 | AF103: =SUMIFS('Combined P&L'!AD:AD,'Combined P&L'!$C:$C,'P&L Forecast'!$B103) -> 8.11723 | AG103: =SUMIFS('Combined P&L'!AE:AE,'Combined P&L'!$C:$C,'P&L Forecast'!$B103) -> 8.34584 | AH103: =SUMIFS('Combined P&L'!AF:AF,'Combined P&L'!$C:$C,'P&L Forecast'!$B103) -> 8.98468 | AI103: =SUMIFS('Combined P&L'!AG:AG,'Combined P&L'!$C:$C,'P&L Forecast'!$B103) -> 9.8566 | AJ103: =SUMIFS('Combined P&L'!AH:AH,'Combined P&L'!$C:$C,'P&L Forecast'!$B103) -> 10.73391 | AK103: =SUMIFS('Combined P&L'!AI:AI,'Combined P&L'!$C:$C,'P&L Forecast'!$B103) -> 12.08939 | AL103: =SUMIFS('Combined P&L'!AJ:AJ,'Combined P&L'!$C:$C,'P&L Forecast'!$B103) -> 13.14583 | AM103: =SUMIFS('Combined P&L'!AK:AK,'Combined P&L'!$C:$C,'P&L Forecast'!$B103) -> 14.42143 | AN103: =SUMIFS('Combined P&L'!AL:AL,'Combined P&L'!$C:$C,'P&L Forecast'!$B103) -> 13.26316 | AO103: =SUMIFS('Combined P&L'!AM:AM,'Combined P&L'!$C:$C,'P&L Forecast'!$B103) -> 14.7201 | AP103: =SUMIFS('Combined P&L'!AN:AN,'Combined P&L'!$C:$C,'P&L Forecast'!$B103) -> 14.99072 | AQ103: =SUMIFS('Combined P&L'!AO:AO,'Combined P&L'!$C:$C,'P&L Forecast'!$B103) -> 14.74459 | AR103: =SUMIFS('Combined P&L'!AP:AP,'Combined P&L'!$C:$C,'P&L Forecast'!$B103) -> 13.2292 | AS103: =SUMIFS('Combined P&L'!AQ:AQ,'Combined P&L'!$C:$C,'P&L Forecast'!$B103) -> 13.11499 | AT103: =SUMIFS('Combined P&L'!AR:AR,'Combined P&L'!$C:$C,'P&L Forecast'!$B103) -> 12.98522
B104: Software & Apps - Topkey | C104: =SUMIFS($P104:$AT104,$P$69:$AT$69,">"&C$169,$P$69:$AT$69,"<"&C$170) -> 0 | D104: =SUMIFS($P104:$AT104,$P$69:$AT$69,">"&D$169,$P$69:$AT$69,"<"&D$170) -> 7.14125 | F104: =SUMIFS($P104:$AT104,$P$69:$AT$69,">"&F$169,$P$69:$AT$69,"<"&F$170) -> 0 | G104: =SUMIFS($P104:$AT104,$P$69:$AT$69,">"&G$169,$P$69:$AT$69,"<"&G$170) -> 28.82775 | I104: =SUMIFS($P104:$AT104,$P$69:$AT$69,">"&I$169,$P$69:$AT$69,"<"&I$170) -> 0 | J104: =SUMIFS($P104:$AT104,$P$69:$AT$69,">"&J$169,$P$69:$AT$69,"<"&J$170) -> 30.899 | K104: =+C38 -> 60.84 | M104: =+J104-K104 -> -29.941 | N104: =IFERROR(K104/J104-1,0) -> 0.96899576 | P104: =SUMIFS('Combined P&L'!N:N,'Combined P&L'!$C:$C,'P&L Forecast'!$B104) -> 0 | Q104: =SUMIFS('Combined P&L'!O:O,'Combined P&L'!$C:$C,'P&L Forecast'!$B104) -> 0 | R104: =SUMIFS('Combined P&L'!P:P,'Combined P&L'!$C:$C,'P&L Forecast'!$B104) -> 0 | S104: =SUMIFS('Combined P&L'!Q:Q,'Combined P&L'!$C:$C,'P&L Forecast'!$B104) -> 0 | T104: =SUMIFS('Combined P&L'!R:R,'Combined P&L'!$C:$C,'P&L Forecast'!$B104) -> 0 | U104: =SUMIFS('Combined P&L'!S:S,'Combined P&L'!$C:$C,'P&L Forecast'!$B104) -> 0 | V104: =SUMIFS('Combined P&L'!T:T,'Combined P&L'!$C:$C,'P&L Forecast'!$B104) -> 0 | W104: =SUMIFS('Combined P&L'!U:U,'Combined P&L'!$C:$C,'P&L Forecast'!$B104) -> 0 | X104: =SUMIFS('Combined P&L'!V:V,'Combined P&L'!$C:$C,'P&L Forecast'!$B104) -> 0 | Y104: =SUMIFS('Combined P&L'!W:W,'Combined P&L'!$C:$C,'P&L Forecast'!$B104) -> 0 | Z104: =SUMIFS('Combined P&L'!X:X,'Combined P&L'!$C:$C,'P&L Forecast'!$B104) -> 0 | AA104: =SUMIFS('Combined P&L'!Y:Y,'Combined P&L'!$C:$C,'P&L Forecast'!$B104) -> 0 | AB104: =SUMIFS('Combined P&L'!Z:Z,'Combined P&L'!$C:$C,'P&L Forecast'!$B104) -> 0 | AC104: =SUMIFS('Combined P&L'!AA:AA,'Combined P&L'!$C:$C,'P&L Forecast'!$B104) -> 0 | AD104: =SUMIFS('Combined P&L'!AB:AB,'Combined P&L'!$C:$C,'P&L Forecast'!$B104) -> 0 | AE104: =SUMIFS('Combined P&L'!AC:AC,'Combined P&L'!$C:$C,'P&L Forecast'!$B104) -> 0 | AF104: =SUMIFS('Combined P&L'!AD:AD,'Combined P&L'!$C:$C,'P&L Forecast'!$B104) -> 0 | AG104: =SUMIFS('Combined P&L'!AE:AE,'Combined P&L'!$C:$C,'P&L Forecast'!$B104) -> 0 | AH104: =SUMIFS('Combined P&L'!AF:AF,'Combined P&L'!$C:$C,'P&L Forecast'!$B104) -> 0 | AI104: =SUMIFS('Combined P&L'!AG:AG,'Combined P&L'!$C:$C,'P&L Forecast'!$B104) -> 0 | AJ104: =SUMIFS('Combined P&L'!AH:AH,'Combined P&L'!$C:$C,'P&L Forecast'!$B104) -> 0.93725 | AK104: =SUMIFS('Combined P&L'!AI:AI,'Combined P&L'!$C:$C,'P&L Forecast'!$B104) -> 1.39225 | AL104: =SUMIFS('Combined P&L'!AJ:AJ,'Combined P&L'!$C:$C,'P&L Forecast'!$B104) -> 2.36125 | AM104: =SUMIFS('Combined P&L'!AK:AK,'Combined P&L'!$C:$C,'P&L Forecast'!$B104) -> 2.4505 | AN104: =SUMIFS('Combined P&L'!AL:AL,'Combined P&L'!$C:$C,'P&L Forecast'!$B104) -> 2.94975 | AO104: =SUMIFS('Combined P&L'!AM:AM,'Combined P&L'!$C:$C,'P&L Forecast'!$B104) -> 3.42 | AP104: =SUMIFS('Combined P&L'!AN:AN,'Combined P&L'!$C:$C,'P&L Forecast'!$B104) -> 3.678 | AQ104: =SUMIFS('Combined P&L'!AO:AO,'Combined P&L'!$C:$C,'P&L Forecast'!$B104) -> 4.218 | AR104: =SUMIFS('Combined P&L'!AP:AP,'Combined P&L'!$C:$C,'P&L Forecast'!$B104) -> 4.284 | AS104: =SUMIFS('Combined P&L'!AQ:AQ,'Combined P&L'!$C:$C,'P&L Forecast'!$B104) -> 5.208 | AT104: =SUMIFS('Combined P&L'!AR:AR,'Combined P&L'!$C:$C,'P&L Forecast'!$B104) -> 5.07
B105: Software & Apps - AI tools | C105: =SUMIFS($P105:$AT105,$P$69:$AT$69,">"&C$169,$P$69:$AT$69,"<"&C$170) -> 0 | D105: =SUMIFS($P105:$AT105,$P$69:$AT$69,">"&D$169,$P$69:$AT$69,"<"&D$170) -> 0 | F105: =SUMIFS($P105:$AT105,$P$69:$AT$69,">"&F$169,$P$69:$AT$69,"<"&F$170) -> 0 | G105: =SUMIFS($P105:$AT105,$P$69:$AT$69,">"&G$169,$P$69:$AT$69,"<"&G$170) -> 6.52752 | I105: =SUMIFS($P105:$AT105,$P$69:$AT$69,">"&I$169,$P$69:$AT$69,"<"&I$170) -> 0 | J105: =SUMIFS($P105:$AT105,$P$69:$AT$69,">"&J$169,$P$69:$AT$69,"<"&J$170) -> 5.21554 | K105: =+C39 -> 15.74376 | M105: =+J105-K105 -> -10.52822 | N105: =IFERROR(K105/J105-1,0) -> 2.0186251 | P105: =SUMIFS('Combined P&L'!N:N,'Combined P&L'!$C:$C,'P&L Forecast'!$B105) -> 0 | Q105: =SUMIFS('Combined P&L'!O:O,'Combined P&L'!$C:$C,'P&L Forecast'!$B105) -> 0 | R105: =SUMIFS('Combined P&L'!P:P,'Combined P&L'!$C:$C,'P&L Forecast'!$B105) -> 0 | S105: =SUMIFS('Combined P&L'!Q:Q,'Combined P&L'!$C:$C,'P&L Forecast'!$B105) -> 0 | T105: =SUMIFS('Combined P&L'!R:R,'Combined P&L'!$C:$C,'P&L Forecast'!$B105) -> 0 | U105: =SUMIFS('Combined P&L'!S:S,'Combined P&L'!$C:$C,'P&L Forecast'!$B105) -> 0 | V105: =SUMIFS('Combined P&L'!T:T,'Combined P&L'!$C:$C,'P&L Forecast'!$B105) -> 0 | W105: =SUMIFS('Combined P&L'!U:U,'Combined P&L'!$C:$C,'P&L Forecast'!$B105) -> 0 | X105: =SUMIFS('Combined P&L'!V:V,'Combined P&L'!$C:$C,'P&L Forecast'!$B105) -> 0 | Y105: =SUMIFS('Combined P&L'!W:W,'Combined P&L'!$C:$C,'P&L Forecast'!$B105) -> 0 | Z105: =SUMIFS('Combined P&L'!X:X,'Combined P&L'!$C:$C,'P&L Forecast'!$B105) -> 0 | AA105: =SUMIFS('Combined P&L'!Y:Y,'Combined P&L'!$C:$C,'P&L Forecast'!$B105) -> 0 | AB105: =SUMIFS('Combined P&L'!Z:Z,'Combined P&L'!$C:$C,'P&L Forecast'!$B105) -> 0 | AC105: =SUMIFS('Combined P&L'!AA:AA,'Combined P&L'!$C:$C,'P&L Forecast'!$B105) -> 0 | AD105: =SUMIFS('Combined P&L'!AB:AB,'Combined P&L'!$C:$C,'P&L Forecast'!$B105) -> 0 | AE105: =SUMIFS('Combined P&L'!AC:AC,'Combined P&L'!$C:$C,'P&L Forecast'!$B105) -> 0 | AF105: =SUMIFS('Combined P&L'!AD:AD,'Combined P&L'!$C:$C,'P&L Forecast'!$B105) -> 0 | AG105: =SUMIFS('Combined P&L'!AE:AE,'Combined P&L'!$C:$C,'P&L Forecast'!$B105) -> 0 | AH105: =SUMIFS('Combined P&L'!AF:AF,'Combined P&L'!$C:$C,'P&L Forecast'!$B105) -> 0 | AI105: =SUMIFS('Combined P&L'!AG:AG,'Combined P&L'!$C:$C,'P&L Forecast'!$B105) -> 0 | AJ105: =SUMIFS('Combined P&L'!AH:AH,'Combined P&L'!$C:$C,'P&L Forecast'!$B105) -> 0 | AK105: =SUMIFS('Combined P&L'!AI:AI,'Combined P&L'!$C:$C,'P&L Forecast'!$B105) -> 0 | AL105: =SUMIFS('Combined P&L'!AJ:AJ,'Combined P&L'!$C:$C,'P&L Forecast'!$B105) -> 0 | AM105: =SUMIFS('Combined P&L'!AK:AK,'Combined P&L'!$C:$C,'P&L Forecast'!$B105) -> 0 | AN105: =SUMIFS('Combined P&L'!AL:AL,'Combined P&L'!$C:$C,'P&L Forecast'!$B105) -> 0.12 | AO105: =SUMIFS('Combined P&L'!AM:AM,'Combined P&L'!$C:$C,'P&L Forecast'!$B105) -> 0.12 | AP105: =SUMIFS('Combined P&L'!AN:AN,'Combined P&L'!$C:$C,'P&L Forecast'!$B105) -> 0.70166 | AQ105: =SUMIFS('Combined P&L'!AO:AO,'Combined P&L'!$C:$C,'P&L Forecast'!$B105) -> 2.20736 | AR105: =SUMIFS('Combined P&L'!AP:AP,'Combined P&L'!$C:$C,'P&L Forecast'!$B105) -> 0.91487 | AS105: =SUMIFS('Combined P&L'!AQ:AQ,'Combined P&L'!$C:$C,'P&L Forecast'!$B105) -> 1.15165 | AT105: =SUMIFS('Combined P&L'!AR:AR,'Combined P&L'!$C:$C,'P&L Forecast'!$B105) -> 1.31198
B106: Total Software Expenses | C106: =SUM(C102:C105) -> 175.33863 | D106: =SUM(D102:D105) -> 281.69462 | F106: =SUM(F102:F105) -> 141.78009 | G106: =SUM(G102:G105) -> 284.68482 | I106: =SUM(I102:I105) -> 223.03858 | J106: =SUM(J102:J105) -> 399.3766 | K106: =SUM(K102:K105) -> 568.11456 | M106: =SUM(M102:M105) -> -168.73796 | N106: =IFERROR(K106/J106-1,0) -> 0.42250337 | P106: =SUM(P102:P105) -> 10.52585 | Q106: =SUM(Q102:Q105) -> 10.63571 | R106: =SUM(R102:R105) -> 11.75195 | S106: =SUM(S102:S105) -> 11.98489 | T106: =SUM(T102:T105) -> 12.81546 | U106: =SUM(U102:U105) -> 14.24615 | V106: =SUM(V102:V105) -> 16.36037 | W106: =SUM(W102:W105) -> 16.36683 | ... AT106: =SUM(AT102:AT105) -> 47.34288
B108: Other Professional Fees | C108: =SUMIFS($P108:$AT108,$P$69:$AT$69,">"&C$169,$P$69:$AT$69,"<"&C$170) -> 18.23425 | D108: =SUMIFS($P108:$AT108,$P$69:$AT$69,">"&D$169,$P$69:$AT$69,"<"&D$170) -> 27.04095 | F108: =SUMIFS($P108:$AT108,$P$69:$AT$69,">"&F$169,$P$69:$AT$69,"<"&F$170) -> 12.014 | G108: =SUMIFS($P108:$AT108,$P$69:$AT$69,">"&G$169,$P$69:$AT$69,"<"&G$170) -> 57.55 | I108: =SUMIFS($P108:$AT108,$P$69:$AT$69,">"&I$169,$P$69:$AT$69,"<"&I$170) -> 22.91525 | J108: =SUMIFS($P108:$AT108,$P$69:$AT$69,">"&J$169,$P$69:$AT$69,"<"&J$170) -> 53.62695 | K108: =+C43 -> 53.62695 | M108: =+J108-K108 -> 0 | N108: =IFERROR(K108/J108-1,0) -> 0 | P108: =SUMIFS('Combined P&L'!N:N,'Combined P&L'!$C:$C,'P&L Forecast'!$B108) -> 0 | Q108: =SUMIFS('Combined P&L'!O:O,'Combined P&L'!$C:$C,'P&L Forecast'!$B108) -> 1.1665 | R108: =SUMIFS('Combined P&L'!P:P,'Combined P&L'!$C:$C,'P&L Forecast'!$B108) -> 1.1665 | S108: =SUMIFS('Combined P&L'!Q:Q,'Combined P&L'!$C:$C,'P&L Forecast'!$B108) -> 1.16667 | T108: =SUMIFS('Combined P&L'!R:R,'Combined P&L'!$C:$C,'P&L Forecast'!$B108) -> 1.16667 | U108: =SUMIFS('Combined P&L'!S:S,'Combined P&L'!$C:$C,'P&L Forecast'!$B108) -> 2.66666 | V108: =SUMIFS('Combined P&L'!T:T,'Combined P&L'!$C:$C,'P&L Forecast'!$B108) -> 1.16667 | W108: =SUMIFS('Combined P&L'!U:U,'Combined P&L'!$C:$C,'P&L Forecast'!$B108) -> 1.16667 | X108: =SUMIFS('Combined P&L'!V:V,'Combined P&L'!$C:$C,'P&L Forecast'!$B108) -> 3.06791 | Y108: =SUMIFS('Combined P&L'!W:W,'Combined P&L'!$C:$C,'P&L Forecast'!$B108) -> 1.16667 | Z108: =SUMIFS('Combined P&L'!X:X,'Combined P&L'!$C:$C,'P&L Forecast'!$B108) -> 2.16667 | AA108: =SUMIFS('Combined P&L'!Y:Y,'Combined P&L'!$C:$C,'P&L Forecast'!$B108) -> 2.16666 | AB108: =SUMIFS('Combined P&L'!Z:Z,'Combined P&L'!$C:$C,'P&L Forecast'!$B108) -> 2.16667 | AC108: =SUMIFS('Combined P&L'!AA:AA,'Combined P&L'!$C:$C,'P&L Forecast'!$B108) -> 2.16667 | AD108: =SUMIFS('Combined P&L'!AB:AB,'Combined P&L'!$C:$C,'P&L Forecast'!$B108) -> 2.16666 | AE108: =SUMIFS('Combined P&L'!AC:AC,'Combined P&L'!$C:$C,'P&L Forecast'!$B108) -> 2.76067 | AF108: =SUMIFS('Combined P&L'!AD:AD,'Combined P&L'!$C:$C,'P&L Forecast'!$B108) -> 1.58667 | AG108: =SUMIFS('Combined P&L'!AE:AE,'Combined P&L'!$C:$C,'P&L Forecast'!$B108) -> 1.16666 | AH108: =SUMIFS('Combined P&L'!AF:AF,'Combined P&L'!$C:$C,'P&L Forecast'!$B108) -> 0 | AI108: =SUMIFS('Combined P&L'!AG:AG,'Combined P&L'!$C:$C,'P&L Forecast'!$B108) -> 0.2 | AJ108: =SUMIFS('Combined P&L'!AH:AH,'Combined P&L'!$C:$C,'P&L Forecast'!$B108) -> 1.32695 | AK108: =SUMIFS('Combined P&L'!AI:AI,'Combined P&L'!$C:$C,'P&L Forecast'!$B108) -> 0 | AL108: =SUMIFS('Combined P&L'!AJ:AJ,'Combined P&L'!$C:$C,'P&L Forecast'!$B108) -> 6 | AM108: =SUMIFS('Combined P&L'!AK:AK,'Combined P&L'!$C:$C,'P&L Forecast'!$B108) -> 7.5 | AN108: =SUMIFS('Combined P&L'!AL:AL,'Combined P&L'!$C:$C,'P&L Forecast'!$B108) -> 0 | AO108: =SUMIFS('Combined P&L'!AM:AM,'Combined P&L'!$C:$C,'P&L Forecast'!$B108) -> 0 | AP108: =SUMIFS('Combined P&L'!AN:AN,'Combined P&L'!$C:$C,'P&L Forecast'!$B108) -> 6.6 | AQ108: =SUMIFS('Combined P&L'!AO:AO,'Combined P&L'!$C:$C,'P&L Forecast'!$B108) -> 14 | AR108: =SUMIFS('Combined P&L'!AP:AP,'Combined P&L'!$C:$C,'P&L Forecast'!$B108) -> 18 | AS108: =SUMIFS('Combined P&L'!AQ:AQ,'Combined P&L'!$C:$C,'P&L Forecast'!$B108) -> 0 | AT108: =SUMIFS('Combined P&L'!AR:AR,'Combined P&L'!$C:$C,'P&L Forecast'!$B108) -> 18.95
B109: Referral Fees | C109: =SUMIFS($P109:$AT109,$P$69:$AT$69,">"&C$169,$P$69:$AT$69,"<"&C$170) -> 24.82 | D109: =SUMIFS($P109:$AT109,$P$69:$AT$69,">"&D$169,$P$69:$AT$69,"<"&D$170) -> 27.15374 | F109: =SUMIFS($P109:$AT109,$P$69:$AT$69,">"&F$169,$P$69:$AT$69,"<"&F$170) -> 17.0895 | G109: =SUMIFS($P109:$AT109,$P$69:$AT$69,">"&G$169,$P$69:$AT$69,"<"&G$170) -> 20.62969 | I109: =SUMIFS($P109:$AT109,$P$69:$AT$69,">"&I$169,$P$69:$AT$69,"<"&I$170) -> 23.71975 | J109: =SUMIFS($P109:$AT109,$P$69:$AT$69,">"&J$169,$P$69:$AT$69,"<"&J$170) -> 30.69416 | K109: =+C45 -> 30.69416 | M109: =+J109-K109 -> 0 | N109: =IFERROR(K109/J109-1,0) -> 0 | P109: =SUMIFS('Combined P&L'!N:N,'Combined P&L'!$C:$C,'P&L Forecast'!$B109) -> 2.21 | Q109: =SUMIFS('Combined P&L'!O:O,'Combined P&L'!$C:$C,'P&L Forecast'!$B109) -> 2.735 | R109: =SUMIFS('Combined P&L'!P:P,'Combined P&L'!$C:$C,'P&L Forecast'!$B109) -> 2.715 | S109: =SUMIFS('Combined P&L'!Q:Q,'Combined P&L'!$C:$C,'P&L Forecast'!$B109) -> 2.735 | T109: =SUMIFS('Combined P&L'!R:R,'Combined P&L'!$C:$C,'P&L Forecast'!$B109) -> 0.78 | U109: =SUMIFS('Combined P&L'!S:S,'Combined P&L'!$C:$C,'P&L Forecast'!$B109) -> 3.245 | V109: =SUMIFS('Combined P&L'!T:T,'Combined P&L'!$C:$C,'P&L Forecast'!$B109) -> 1.28 | W109: =SUMIFS('Combined P&L'!U:U,'Combined P&L'!$C:$C,'P&L Forecast'!$B109) -> 1.3 | X109: =SUMIFS('Combined P&L'!V:V,'Combined P&L'!$C:$C,'P&L Forecast'!$B109) -> 1.81 | Y109: =SUMIFS('Combined P&L'!W:W,'Combined P&L'!$C:$C,'P&L Forecast'!$B109) -> 1.82 | Z109: =SUMIFS('Combined P&L'!X:X,'Combined P&L'!$C:$C,'P&L Forecast'!$B109) -> 1.835 | AA109: =SUMIFS('Combined P&L'!Y:Y,'Combined P&L'!$C:$C,'P&L Forecast'!$B109) -> 2.355 | AB109: =SUMIFS('Combined P&L'!Z:Z,'Combined P&L'!$C:$C,'P&L Forecast'!$B109) -> 1.47025 | AC109: =SUMIFS('Combined P&L'!AA:AA,'Combined P&L'!$C:$C,'P&L Forecast'!$B109) -> 1.665 | AD109: =SUMIFS('Combined P&L'!AB:AB,'Combined P&L'!$C:$C,'P&L Forecast'!$B109) -> 2.62775 | AE109: =SUMIFS('Combined P&L'!AC:AC,'Combined P&L'!$C:$C,'P&L Forecast'!$B109) -> 1.24875 | AF109: =SUMIFS('Combined P&L'!AD:AD,'Combined P&L'!$C:$C,'P&L Forecast'!$B109) -> 2.154 | AG109: =SUMIFS('Combined P&L'!AE:AE,'Combined P&L'!$C:$C,'P&L Forecast'!$B109) -> 4.154 | AH109: =SUMIFS('Combined P&L'!AF:AF,'Combined P&L'!$C:$C,'P&L Forecast'!$B109) -> 3.76975 | AI109: =SUMIFS('Combined P&L'!AG:AG,'Combined P&L'!$C:$C,'P&L Forecast'!$B109) -> 1.696 | AJ109: =SUMIFS('Combined P&L'!AH:AH,'Combined P&L'!$C:$C,'P&L Forecast'!$B109) -> 2.2275 | AK109: =SUMIFS('Combined P&L'!AI:AI,'Combined P&L'!$C:$C,'P&L Forecast'!$B109) -> 1.6645 | AL109: =SUMIFS('Combined P&L'!AJ:AJ,'Combined P&L'!$C:$C,'P&L Forecast'!$B109) -> 1.71879 | AM109: =SUMIFS('Combined P&L'!AK:AK,'Combined P&L'!$C:$C,'P&L Forecast'!$B109) -> 2.75745 | AN109: =SUMIFS('Combined P&L'!AL:AL,'Combined P&L'!$C:$C,'P&L Forecast'!$B109) -> 1.8688 | AO109: =SUMIFS('Combined P&L'!AM:AM,'Combined P&L'!$C:$C,'P&L Forecast'!$B109) -> 4.43991 | AP109: =SUMIFS('Combined P&L'!AN:AN,'Combined P&L'!$C:$C,'P&L Forecast'!$B109) -> 2.39361 | AQ109: =SUMIFS('Combined P&L'!AO:AO,'Combined P&L'!$C:$C,'P&L Forecast'!$B109) -> 3.65786 | AR109: =SUMIFS('Combined P&L'!AP:AP,'Combined P&L'!$C:$C,'P&L Forecast'!$B109) -> 2.93379 | AS109: =SUMIFS('Combined P&L'!AQ:AQ,'Combined P&L'!$C:$C,'P&L Forecast'!$B109) -> 1.5662 | AT109: =SUMIFS('Combined P&L'!AR:AR,'Combined P&L'!$C:$C,'P&L Forecast'!$B109) -> 3.76952
B110: Travel, Meals & Entertainment | C110: =SUMIFS($P110:$AT110,$P$69:$AT$69,">"&C$169,$P$69:$AT$69,"<"&C$170) -> 0 | D110: =SUMIFS($P110:$AT110,$P$69:$AT$69,">"&D$169,$P$69:$AT$69,"<"&D$170) -> 29.76122 | F110: =SUMIFS($P110:$AT110,$P$69:$AT$69,">"&F$169,$P$69:$AT$69,"<"&F$170) -> 22.29558 | G110: =SUMIFS($P110:$AT110,$P$69:$AT$69,">"&G$169,$P$69:$AT$69,"<"&G$170) -> 20.68542 | I110: =SUMIFS($P110:$AT110,$P$69:$AT$69,">"&I$169,$P$69:$AT$69,"<"&I$170) -> 22.19792 | J110: =SUMIFS($P110:$AT110,$P$69:$AT$69,">"&J$169,$P$69:$AT$69,"<"&J$170) -> 28.23873 | K110: =+C46 -> 28.23873 | M110: =+J110-K110 -> 0 | N110: =IFERROR(K110/J110-1,0) -> 0 | P110: =SUMIFS('Combined P&L'!N:N,'Combined P&L'!$C:$C,'P&L Forecast'!$B110) -> 0 | Q110: =SUMIFS('Combined P&L'!O:O,'Combined P&L'!$C:$C,'P&L Forecast'!$B110) -> 0 | R110: =SUMIFS('Combined P&L'!P:P,'Combined P&L'!$C:$C,'P&L Forecast'!$B110) -> 0 | S110: =SUMIFS('Combined P&L'!Q:Q,'Combined P&L'!$C:$C,'P&L Forecast'!$B110) -> 0 | T110: =SUMIFS('Combined P&L'!R:R,'Combined P&L'!$C:$C,'P&L Forecast'!$B110) -> 0 | U110: =SUMIFS('Combined P&L'!S:S,'Combined P&L'!$C:$C,'P&L Forecast'!$B110) -> 0 | V110: =SUMIFS('Combined P&L'!T:T,'Combined P&L'!$C:$C,'P&L Forecast'!$B110) -> 0 | W110: =SUMIFS('Combined P&L'!U:U,'Combined P&L'!$C:$C,'P&L Forecast'!$B110) -> 0 | X110: =SUMIFS('Combined P&L'!V:V,'Combined P&L'!$C:$C,'P&L Forecast'!$B110) -> 0 | Y110: =SUMIFS('Combined P&L'!W:W,'Combined P&L'!$C:$C,'P&L Forecast'!$B110) -> 0 | Z110: =SUMIFS('Combined P&L'!X:X,'Combined P&L'!$C:$C,'P&L Forecast'!$B110) -> 0 | AA110: =SUMIFS('Combined P&L'!Y:Y,'Combined P&L'!$C:$C,'P&L Forecast'!$B110) -> 0 | AB110: =SUMIFS('Combined P&L'!Z:Z,'Combined P&L'!$C:$C,'P&L Forecast'!$B110) -> 0.00691 | AC110: =SUMIFS('Combined P&L'!AA:AA,'Combined P&L'!$C:$C,'P&L Forecast'!$B110) -> 0 | AD110: =SUMIFS('Combined P&L'!AB:AB,'Combined P&L'!$C:$C,'P&L Forecast'!$B110) -> 0 | AE110: =SUMIFS('Combined P&L'!AC:AC,'Combined P&L'!$C:$C,'P&L Forecast'!$B110) -> 11.40629 | AF110: =SUMIFS('Combined P&L'!AD:AD,'Combined P&L'!$C:$C,'P&L Forecast'!$B110) -> 10.78472 | AG110: =SUMIFS('Combined P&L'!AE:AE,'Combined P&L'!$C:$C,'P&L Forecast'!$B110) -> 0 | AH110: =SUMIFS('Combined P&L'!AF:AF,'Combined P&L'!$C:$C,'P&L Forecast'!$B110) -> 0.09766 | AI110: =SUMIFS('Combined P&L'!AG:AG,'Combined P&L'!$C:$C,'P&L Forecast'!$B110) -> 0.92152 | AJ110: =SUMIFS('Combined P&L'!AH:AH,'Combined P&L'!$C:$C,'P&L Forecast'!$B110) -> 2.96423 | AK110: =SUMIFS('Combined P&L'!AI:AI,'Combined P&L'!$C:$C,'P&L Forecast'!$B110) -> 1.03679 | AL110: =SUMIFS('Combined P&L'!AJ:AJ,'Combined P&L'!$C:$C,'P&L Forecast'!$B110) -> 2.11036 | AM110: =SUMIFS('Combined P&L'!AK:AK,'Combined P&L'!$C:$C,'P&L Forecast'!$B110) -> 0.43274 | AN110: =SUMIFS('Combined P&L'!AL:AL,'Combined P&L'!$C:$C,'P&L Forecast'!$B110) -> 0 | AO110: =SUMIFS('Combined P&L'!AM:AM,'Combined P&L'!$C:$C,'P&L Forecast'!$B110) -> 0 | AP110: =SUMIFS('Combined P&L'!AN:AN,'Combined P&L'!$C:$C,'P&L Forecast'!$B110) -> 0 | AQ110: =SUMIFS('Combined P&L'!AO:AO,'Combined P&L'!$C:$C,'P&L Forecast'!$B110) -> 9.7651 | AR110: =SUMIFS('Combined P&L'!AP:AP,'Combined P&L'!$C:$C,'P&L Forecast'!$B110) -> 10.25443 | AS110: =SUMIFS('Combined P&L'!AQ:AQ,'Combined P&L'!$C:$C,'P&L Forecast'!$B110) -> 0.6559 | AT110: =SUMIFS('Combined P&L'!AR:AR,'Combined P&L'!$C:$C,'P&L Forecast'!$B110) -> 0.00999
B111: Payment Collection Fees | C111: =SUMIFS($P111:$AT111,$P$69:$AT$69,">"&C$169,$P$69:$AT$69,"<"&C$170) -> 8.67099 | D111: =SUMIFS($P111:$AT111,$P$69:$AT$69,">"&D$169,$P$69:$AT$69,"<"&D$170) -> 13.35153 | F111: =SUMIFS($P111:$AT111,$P$69:$AT$69,">"&F$169,$P$69:$AT$69,"<"&F$170) -> 6.80445 | G111: =SUMIFS($P111:$AT111,$P$69:$AT$69,">"&G$169,$P$69:$AT$69,"<"&G$170) -> 9.02684 | I111: =SUMIFS($P111:$AT111,$P$69:$AT$69,">"&I$169,$P$69:$AT$69,"<"&I$170) -> 9.9746 | J111: =SUMIFS($P111:$AT111,$P$69:$AT$69,">"&J$169,$P$69:$AT$69,"<"&J$170) -> 15.6528 | K111: =+C47 -> 15.6528 | M111: =+J111-K111 -> 0 | N111: =IFERROR(K111/J111-1,0) -> 0 | P111: =SUMIFS('Combined P&L'!N:N,'Combined P&L'!$C:$C,'P&L Forecast'!$B111) -> 0.6179 | Q111: =SUMIFS('Combined P&L'!O:O,'Combined P&L'!$C:$C,'P&L Forecast'!$B111) -> 0.8374 | R111: =SUMIFS('Combined P&L'!P:P,'Combined P&L'!$C:$C,'P&L Forecast'!$B111) -> 0.62936 | S111: =SUMIFS('Combined P&L'!Q:Q,'Combined P&L'!$C:$C,'P&L Forecast'!$B111) -> 0.68245 | T111: =SUMIFS('Combined P&L'!R:R,'Combined P&L'!$C:$C,'P&L Forecast'!$B111) -> 0.72151 | U111: =SUMIFS('Combined P&L'!S:S,'Combined P&L'!$C:$C,'P&L Forecast'!$B111) -> 0.78747 | V111: =SUMIFS('Combined P&L'!T:T,'Combined P&L'!$C:$C,'P&L Forecast'!$B111) -> 0.65562 | W111: =SUMIFS('Combined P&L'!U:U,'Combined P&L'!$C:$C,'P&L Forecast'!$B111) -> 0.79491 | X111: =SUMIFS('Combined P&L'!V:V,'Combined P&L'!$C:$C,'P&L Forecast'!$B111) -> 0.69063 | Y111: =SUMIFS('Combined P&L'!W:W,'Combined P&L'!$C:$C,'P&L Forecast'!$B111) -> 0.71761 | Z111: =SUMIFS('Combined P&L'!X:X,'Combined P&L'!$C:$C,'P&L Forecast'!$B111) -> 0.73795 | AA111: =SUMIFS('Combined P&L'!Y:Y,'Combined P&L'!$C:$C,'P&L Forecast'!$B111) -> 0.79818 | AB111: =SUMIFS('Combined P&L'!Z:Z,'Combined P&L'!$C:$C,'P&L Forecast'!$B111) -> 0.83546 | AC111: =SUMIFS('Combined P&L'!AA:AA,'Combined P&L'!$C:$C,'P&L Forecast'!$B111) -> 1.05394 | AD111: =SUMIFS('Combined P&L'!AB:AB,'Combined P&L'!$C:$C,'P&L Forecast'!$B111) -> 0.87069 | AE111: =SUMIFS('Combined P&L'!AC:AC,'Combined P&L'!$C:$C,'P&L Forecast'!$B111) -> 0.90555 | AF111: =SUMIFS('Combined P&L'!AD:AD,'Combined P&L'!$C:$C,'P&L Forecast'!$B111) -> 0.91157 | AG111: =SUMIFS('Combined P&L'!AE:AE,'Combined P&L'!$C:$C,'P&L Forecast'!$B111) -> 1.00249 | AH111: =SUMIFS('Combined P&L'!AF:AF,'Combined P&L'!$C:$C,'P&L Forecast'!$B111) -> 1.22475 | AI111: =SUMIFS('Combined P&L'!AG:AG,'Combined P&L'!$C:$C,'P&L Forecast'!$B111) -> 1.10438 | AJ111: =SUMIFS('Combined P&L'!AH:AH,'Combined P&L'!$C:$C,'P&L Forecast'!$B111) -> 1.29723 | AK111: =SUMIFS('Combined P&L'!AI:AI,'Combined P&L'!$C:$C,'P&L Forecast'!$B111) -> 1.21739 | AL111: =SUMIFS('Combined P&L'!AJ:AJ,'Combined P&L'!$C:$C,'P&L Forecast'!$B111) -> 1.62294 | AM111: =SUMIFS('Combined P&L'!AK:AK,'Combined P&L'!$C:$C,'P&L Forecast'!$B111) -> 1.30514 | AN111: =SUMIFS('Combined P&L'!AL:AL,'Combined P&L'!$C:$C,'P&L Forecast'!$B111) -> 1.22974 | AO111: =SUMIFS('Combined P&L'!AM:AM,'Combined P&L'!$C:$C,'P&L Forecast'!$B111) -> 1.73847 | AP111: =SUMIFS('Combined P&L'!AN:AN,'Combined P&L'!$C:$C,'P&L Forecast'!$B111) -> 1.35348 | AQ111: =SUMIFS('Combined P&L'!AO:AO,'Combined P&L'!$C:$C,'P&L Forecast'!$B111) -> 1.23399 | AR111: =SUMIFS('Combined P&L'!AP:AP,'Combined P&L'!$C:$C,'P&L Forecast'!$B111) -> 1.17137 | AS111: =SUMIFS('Combined P&L'!AQ:AQ,'Combined P&L'!$C:$C,'P&L Forecast'!$B111) -> 1.15392 | AT111: =SUMIFS('Combined P&L'!AR:AR,'Combined P&L'!$C:$C,'P&L Forecast'!$B111) -> 1.14587
B112: Professional Organizations | C112: =SUMIFS($P112:$AT112,$P$69:$AT$69,">"&C$169,$P$69:$AT$69,"<"&C$170) -> 5.44332 | D112: =SUMIFS($P112:$AT112,$P$69:$AT$69,">"&D$169,$P$69:$AT$69,"<"&D$170) -> 11.22296 | F112: =SUMIFS($P112:$AT112,$P$69:$AT$69,">"&F$169,$P$69:$AT$69,"<"&F$170) -> 6.191 | G112: =SUMIFS($P112:$AT112,$P$69:$AT$69,">"&G$169,$P$69:$AT$69,"<"&G$170) -> 6.57881 | I112: =SUMIFS($P112:$AT112,$P$69:$AT$69,">"&I$169,$P$69:$AT$69,"<"&I$170) -> 8.30166 | J112: =SUMIFS($P112:$AT112,$P$69:$AT$69,">"&J$169,$P$69:$AT$69,"<"&J$170) -> 12.15692 | K112: =+C48 -> 12.15692 | M112: =+J112-K112 -> 0 | N112: =IFERROR(K112/J112-1,0) -> 0 | P112: =SUMIFS('Combined P&L'!N:N,'Combined P&L'!$C:$C,'P&L Forecast'!$B112) -> 0.33417 | Q112: =SUMIFS('Combined P&L'!O:O,'Combined P&L'!$C:$C,'P&L Forecast'!$B112) -> 0.33417 | R112: =SUMIFS('Combined P&L'!P:P,'Combined P&L'!$C:$C,'P&L Forecast'!$B112) -> 0.33417 | S112: =SUMIFS('Combined P&L'!Q:Q,'Combined P&L'!$C:$C,'P&L Forecast'!$B112) -> 0.33417 | T112: =SUMIFS('Combined P&L'!R:R,'Combined P&L'!$C:$C,'P&L Forecast'!$B112) -> 0.255 | U112: =SUMIFS('Combined P&L'!S:S,'Combined P&L'!$C:$C,'P&L Forecast'!$B112) -> 0.255 | V112: =SUMIFS('Combined P&L'!T:T,'Combined P&L'!$C:$C,'P&L Forecast'!$B112) -> 0.25496 | W112: =SUMIFS('Combined P&L'!U:U,'Combined P&L'!$C:$C,'P&L Forecast'!$B112) -> 0.205 | X112: =SUMIFS('Combined P&L'!V:V,'Combined P&L'!$C:$C,'P&L Forecast'!$B112) -> 0.78417 | Y112: =SUMIFS('Combined P&L'!W:W,'Combined P&L'!$C:$C,'P&L Forecast'!$B112) -> 0.78417 | Z112: =SUMIFS('Combined P&L'!X:X,'Combined P&L'!$C:$C,'P&L Forecast'!$B112) -> 0.78417 | AA112: =SUMIFS('Combined P&L'!Y:Y,'Combined P&L'!$C:$C,'P&L Forecast'!$B112) -> 0.78417 | AB112: =SUMIFS('Combined P&L'!Z:Z,'Combined P&L'!$C:$C,'P&L Forecast'!$B112) -> 0.78417 | AC112: =SUMIFS('Combined P&L'!AA:AA,'Combined P&L'!$C:$C,'P&L Forecast'!$B112) -> 0.78417 | AD112: =SUMIFS('Combined P&L'!AB:AB,'Combined P&L'!$C:$C,'P&L Forecast'!$B112) -> 0.78417 | AE112: =SUMIFS('Combined P&L'!AC:AC,'Combined P&L'!$C:$C,'P&L Forecast'!$B112) -> 0.78417 | AF112: =SUMIFS('Combined P&L'!AD:AD,'Combined P&L'!$C:$C,'P&L Forecast'!$B112) -> 0.78417 | AG112: =SUMIFS('Combined P&L'!AE:AE,'Combined P&L'!$C:$C,'P&L Forecast'!$B112) -> 0.78417 | AH112: =SUMIFS('Combined P&L'!AF:AF,'Combined P&L'!$C:$C,'P&L Forecast'!$B112) -> 1.48598 | AI112: =SUMIFS('Combined P&L'!AG:AG,'Combined P&L'!$C:$C,'P&L Forecast'!$B112) -> 0.9633 | AJ112: =SUMIFS('Combined P&L'!AH:AH,'Combined P&L'!$C:$C,'P&L Forecast'!$B112) -> 0.98042 | AK112: =SUMIFS('Combined P&L'!AI:AI,'Combined P&L'!$C:$C,'P&L Forecast'!$B112) -> 1.02942 | AL112: =SUMIFS('Combined P&L'!AJ:AJ,'Combined P&L'!$C:$C,'P&L Forecast'!$B112) -> 1.02942 | AM112: =SUMIFS('Combined P&L'!AK:AK,'Combined P&L'!$C:$C,'P&L Forecast'!$B112) -> 1.0294 | AN112: =SUMIFS('Combined P&L'!AL:AL,'Combined P&L'!$C:$C,'P&L Forecast'!$B112) -> 0.93983 | AO112: =SUMIFS('Combined P&L'!AM:AM,'Combined P&L'!$C:$C,'P&L Forecast'!$B112) -> 0.93983 | AP112: =SUMIFS('Combined P&L'!AN:AN,'Combined P&L'!$C:$C,'P&L Forecast'!$B112) -> 0.93983 | AQ112: =SUMIFS('Combined P&L'!AO:AO,'Combined P&L'!$C:$C,'P&L Forecast'!$B112) -> 0.93983 | AR112: =SUMIFS('Combined P&L'!AP:AP,'Combined P&L'!$C:$C,'P&L Forecast'!$B112) -> 0.93983 | AS112: =SUMIFS('Combined P&L'!AQ:AQ,'Combined P&L'!$C:$C,'P&L Forecast'!$B112) -> 0.93983 | AT112: =SUMIFS('Combined P&L'!AR:AR,'Combined P&L'!$C:$C,'P&L Forecast'!$B112) -> 0.93983
B113: S&M Events | C113: =SUMIFS($P113:$AT113,$P$69:$AT$69,">"&C$169,$P$69:$AT$69,"<"&C$170) -> 0 | D113: =SUMIFS($P113:$AT113,$P$69:$AT$69,">"&D$169,$P$69:$AT$69,"<"&D$170) -> 11.4983 | F113: =SUMIFS($P113:$AT113,$P$69:$AT$69,">"&F$169,$P$69:$AT$69,"<"&F$170) -> 0 | G113: =SUMIFS($P113:$AT113,$P$69:$AT$69,">"&G$169,$P$69:$AT$69,"<"&G$170) -> 11.84548 | I113: =SUMIFS($P113:$AT113,$P$69:$AT$69,">"&I$169,$P$69:$AT$69,"<"&I$170) -> 0 | J113: =SUMIFS($P113:$AT113,$P$69:$AT$69,">"&J$169,$P$69:$AT$69,"<"&J$170) -> 11.64878 | K113: =+C49 -> 11.64878 | M113: =+J113-K113 -> 0 | N113: =IFERROR(K113/J113-1,0) -> 0 | P113: =SUMIFS('Combined P&L'!N:N,'Combined P&L'!$C:$C,'P&L Forecast'!$B113) -> 0 | Q113: =SUMIFS('Combined P&L'!O:O,'Combined P&L'!$C:$C,'P&L Forecast'!$B113) -> 0 | R113: =SUMIFS('Combined P&L'!P:P,'Combined P&L'!$C:$C,'P&L Forecast'!$B113) -> 0 | S113: =SUMIFS('Combined P&L'!Q:Q,'Combined P&L'!$C:$C,'P&L Forecast'!$B113) -> 0 | T113: =SUMIFS('Combined P&L'!R:R,'Combined P&L'!$C:$C,'P&L Forecast'!$B113) -> 0 | U113: =SUMIFS('Combined P&L'!S:S,'Combined P&L'!$C:$C,'P&L Forecast'!$B113) -> 0 | V113: =SUMIFS('Combined P&L'!T:T,'Combined P&L'!$C:$C,'P&L Forecast'!$B113) -> 0 | W113: =SUMIFS('Combined P&L'!U:U,'Combined P&L'!$C:$C,'P&L Forecast'!$B113) -> 0 | X113: =SUMIFS('Combined P&L'!V:V,'Combined P&L'!$C:$C,'P&L Forecast'!$B113) -> 0 | Y113: =SUMIFS('Combined P&L'!W:W,'Combined P&L'!$C:$C,'P&L Forecast'!$B113) -> 0 | Z113: =SUMIFS('Combined P&L'!X:X,'Combined P&L'!$C:$C,'P&L Forecast'!$B113) -> 0 | AA113: =SUMIFS('Combined P&L'!Y:Y,'Combined P&L'!$C:$C,'P&L Forecast'!$B113) -> 0 | AB113: =SUMIFS('Combined P&L'!Z:Z,'Combined P&L'!$C:$C,'P&L Forecast'!$B113) -> 0 | AC113: =SUMIFS('Combined P&L'!AA:AA,'Combined P&L'!$C:$C,'P&L Forecast'!$B113) -> 0 | AD113: =SUMIFS('Combined P&L'!AB:AB,'Combined P&L'!$C:$C,'P&L Forecast'!$B113) -> 0 | AE113: =SUMIFS('Combined P&L'!AC:AC,'Combined P&L'!$C:$C,'P&L Forecast'!$B113) -> 0 | AF113: =SUMIFS('Combined P&L'!AD:AD,'Combined P&L'!$C:$C,'P&L Forecast'!$B113) -> 0 | AG113: =SUMIFS('Combined P&L'!AE:AE,'Combined P&L'!$C:$C,'P&L Forecast'!$B113) -> 0 | AH113: =SUMIFS('Combined P&L'!AF:AF,'Combined P&L'!$C:$C,'P&L Forecast'!$B113) -> 0 | AI113: =SUMIFS('Combined P&L'!AG:AG,'Combined P&L'!$C:$C,'P&L Forecast'!$B113) -> 7.17 | AJ113: =SUMIFS('Combined P&L'!AH:AH,'Combined P&L'!$C:$C,'P&L Forecast'!$B113) -> 1.6495 | AK113: =SUMIFS('Combined P&L'!AI:AI,'Combined P&L'!$C:$C,'P&L Forecast'!$B113) -> 2.6788 | AL113: =SUMIFS('Combined P&L'!AJ:AJ,'Combined P&L'!$C:$C,'P&L Forecast'!$B113) -> 0 | AM113: =SUMIFS('Combined P&L'!AK:AK,'Combined P&L'!$C:$C,'P&L Forecast'!$B113) -> 0 | AN113: =SUMIFS('Combined P&L'!AL:AL,'Combined P&L'!$C:$C,'P&L Forecast'!$B113) -> 0.05 | AO113: =SUMIFS('Combined P&L'!AM:AM,'Combined P&L'!$C:$C,'P&L Forecast'!$B113) -> 0 | AP113: =SUMIFS('Combined P&L'!AN:AN,'Combined P&L'!$C:$C,'P&L Forecast'!$B113) -> 0 | AQ113: =SUMIFS('Combined P&L'!AO:AO,'Combined P&L'!$C:$C,'P&L Forecast'!$B113) -> 0 | AR113: =SUMIFS('Combined P&L'!AP:AP,'Combined P&L'!$C:$C,'P&L Forecast'!$B113) -> 0.09805 | AS113: =SUMIFS('Combined P&L'!AQ:AQ,'Combined P&L'!$C:$C,'P&L Forecast'!$B113) -> 0.00243 | AT113: =SUMIFS('Combined P&L'!AR:AR,'Combined P&L'!$C:$C,'P&L Forecast'!$B113) -> 11.695
B114: Recruiting Fees | C114: =SUMIFS($P114:$AT114,$P$69:$AT$69,">"&C$169,$P$69:$AT$69,"<"&C$170) -> 14.90205 | D114: =SUMIFS($P114:$AT114,$P$69:$AT$69,">"&D$169,$P$69:$AT$69,"<"&D$170) -> 31.6041 | F114: =SUMIFS($P114:$AT114,$P$69:$AT$69,">"&F$169,$P$69:$AT$69,"<"&F$170) -> 28.29994 | G114: =SUMIFS($P114:$AT114,$P$69:$AT$69,">"&G$169,$P$69:$AT$69,"<"&G$170) -> 5.5646 | I114: =SUMIFS($P114:$AT114,$P$69:$AT$69,">"&I$169,$P$69:$AT$69,"<"&I$170) -> 36.58249 | J114: =SUMIFS($P114:$AT114,$P$69:$AT$69,">"&J$169,$P$69:$AT$69,"<"&J$170) -> 8.84585 | K114: =+C50 -> 8.84585 | M114: =+J114-K114 -> 0 | N114: =IFERROR(K114/J114-1,0) -> 0 | P114: =SUMIFS('Combined P&L'!N:N,'Combined P&L'!$C:$C,'P&L Forecast'!$B114) -> 0.02492 | Q114: =SUMIFS('Combined P&L'!O:O,'Combined P&L'!$C:$C,'P&L Forecast'!$B114) -> 1.02492 | R114: =SUMIFS('Combined P&L'!P:P,'Combined P&L'!$C:$C,'P&L Forecast'!$B114) -> 1.02492 | S114: =SUMIFS('Combined P&L'!Q:Q,'Combined P&L'!$C:$C,'P&L Forecast'!$B114) -> 1.22492 | T114: =SUMIFS('Combined P&L'!R:R,'Combined P&L'!$C:$C,'P&L Forecast'!$B114) -> 1.02492 | U114: =SUMIFS('Combined P&L'!S:S,'Combined P&L'!$C:$C,'P&L Forecast'!$B114) -> 1.51802 | V114: =SUMIFS('Combined P&L'!T:T,'Combined P&L'!$C:$C,'P&L Forecast'!$B114) -> 2.01331 | W114: =SUMIFS('Combined P&L'!U:U,'Combined P&L'!$C:$C,'P&L Forecast'!$B114) -> 1.6009 | X114: =SUMIFS('Combined P&L'!V:V,'Combined P&L'!$C:$C,'P&L Forecast'!$B114) -> 1.58969 | Y114: =SUMIFS('Combined P&L'!W:W,'Combined P&L'!$C:$C,'P&L Forecast'!$B114) -> 1.12582 | Z114: =SUMIFS('Combined P&L'!X:X,'Combined P&L'!$C:$C,'P&L Forecast'!$B114) -> 1.44199 | AA114: =SUMIFS('Combined P&L'!Y:Y,'Combined P&L'!$C:$C,'P&L Forecast'!$B114) -> 1.28772 | AB114: =SUMIFS('Combined P&L'!Z:Z,'Combined P&L'!$C:$C,'P&L Forecast'!$B114) -> 2.41295 | AC114: =SUMIFS('Combined P&L'!AA:AA,'Combined P&L'!$C:$C,'P&L Forecast'!$B114) -> 22.3793 | AD114: =SUMIFS('Combined P&L'!AB:AB,'Combined P&L'!$C:$C,'P&L Forecast'!$B114) -> 0.72983 | AE114: =SUMIFS('Combined P&L'!AC:AC,'Combined P&L'!$C:$C,'P&L Forecast'!$B114) -> 0.59597 | AF114: =SUMIFS('Combined P&L'!AD:AD,'Combined P&L'!$C:$C,'P&L Forecast'!$B114) -> 0.87534 | AG114: =SUMIFS('Combined P&L'!AE:AE,'Combined P&L'!$C:$C,'P&L Forecast'!$B114) -> 0.52967 | AH114: =SUMIFS('Combined P&L'!AF:AF,'Combined P&L'!$C:$C,'P&L Forecast'!$B114) -> 0.77688 | AI114: =SUMIFS('Combined P&L'!AG:AG,'Combined P&L'!$C:$C,'P&L Forecast'!$B114) -> 0.21671 | AJ114: =SUMIFS('Combined P&L'!AH:AH,'Combined P&L'!$C:$C,'P&L Forecast'!$B114) -> 0.74952 | AK114: =SUMIFS('Combined P&L'!AI:AI,'Combined P&L'!$C:$C,'P&L Forecast'!$B114) -> 0.92573 | AL114: =SUMIFS('Combined P&L'!AJ:AJ,'Combined P&L'!$C:$C,'P&L Forecast'!$B114) -> 0.66044 | AM114: =SUMIFS('Combined P&L'!AK:AK,'Combined P&L'!$C:$C,'P&L Forecast'!$B114) -> 0.75176 | AN114: =SUMIFS('Combined P&L'!AL:AL,'Combined P&L'!$C:$C,'P&L Forecast'!$B114) -> 0.8203 | AO114: =SUMIFS('Combined P&L'!AM:AM,'Combined P&L'!$C:$C,'P&L Forecast'!$B114) -> 0.68046 | AP114: =SUMIFS('Combined P&L'!AN:AN,'Combined P&L'!$C:$C,'P&L Forecast'!$B114) -> 0.77239 | AQ114: =SUMIFS('Combined P&L'!AO:AO,'Combined P&L'!$C:$C,'P&L Forecast'!$B114) -> 0.71608 | AR114: =SUMIFS('Combined P&L'!AP:AP,'Combined P&L'!$C:$C,'P&L Forecast'!$B114) -> 0.6402 | AS114: =SUMIFS('Combined P&L'!AQ:AQ,'Combined P&L'!$C:$C,'P&L Forecast'!$B114) -> 1.13538 | AT114: =SUMIFS('Combined P&L'!AR:AR,'Combined P&L'!$C:$C,'P&L Forecast'!$B114) -> 0.79979
B115: Amortization | C115: =SUMIFS($P115:$AT115,$P$69:$AT$69,">"&C$169,$P$69:$AT$69,"<"&C$170) -> 6.673 | D115: =SUMIFS($P115:$AT115,$P$69:$AT$69,">"&D$169,$P$69:$AT$69,"<"&D$170) -> 6.673 | F115: =SUMIFS($P115:$AT115,$P$69:$AT$69,">"&F$169,$P$69:$AT$69,"<"&F$170) -> 0 | G115: =SUMIFS($P115:$AT115,$P$69:$AT$69,">"&G$169,$P$69:$AT$69,"<"&G$170) -> 0 | I115: =SUMIFS($P115:$AT115,$P$69:$AT$69,">"&I$169,$P$69:$AT$69,"<"&I$170) -> 6.673 | J115: =SUMIFS($P115:$AT115,$P$69:$AT$69,">"&J$169,$P$69:$AT$69,"<"&J$170) -> 6.673 | K115: =+C56 -> 6.673 | M115: =+J115-K115 -> 0 | N115: =IFERROR(K115/J115-1,0) -> 0 | P115: =SUMIFS('Combined P&L'!N:N,'Combined P&L'!$C:$C,'P&L Forecast'!$B115) -> 0 | Q115: =SUMIFS('Combined P&L'!O:O,'Combined P&L'!$C:$C,'P&L Forecast'!$B115) -> 0 | R115: =SUMIFS('Combined P&L'!P:P,'Combined P&L'!$C:$C,'P&L Forecast'!$B115) -> 0 | S115: =SUMIFS('Combined P&L'!Q:Q,'Combined P&L'!$C:$C,'P&L Forecast'!$B115) -> 0 | T115: =SUMIFS('Combined P&L'!R:R,'Combined P&L'!$C:$C,'P&L Forecast'!$B115) -> 0 | U115: =SUMIFS('Combined P&L'!S:S,'Combined P&L'!$C:$C,'P&L Forecast'!$B115) -> 0 | V115: =SUMIFS('Combined P&L'!T:T,'Combined P&L'!$C:$C,'P&L Forecast'!$B115) -> 0 | W115: =SUMIFS('Combined P&L'!U:U,'Combined P&L'!$C:$C,'P&L Forecast'!$B115) -> 0 | X115: =SUMIFS('Combined P&L'!V:V,'Combined P&L'!$C:$C,'P&L Forecast'!$B115) -> 0 | Y115: =SUMIFS('Combined P&L'!W:W,'Combined P&L'!$C:$C,'P&L Forecast'!$B115) -> 0 | Z115: =SUMIFS('Combined P&L'!X:X,'Combined P&L'!$C:$C,'P&L Forecast'!$B115) -> 0 | AA115: =SUMIFS('Combined P&L'!Y:Y,'Combined P&L'!$C:$C,'P&L Forecast'!$B115) -> 6.673 | AB115: =SUMIFS('Combined P&L'!Z:Z,'Combined P&L'!$C:$C,'P&L Forecast'!$B115) -> 0 | AC115: =SUMIFS('Combined P&L'!AA:AA,'Combined P&L'!$C:$C,'P&L Forecast'!$B115) -> 0 | AD115: =SUMIFS('Combined P&L'!AB:AB,'Combined P&L'!$C:$C,'P&L Forecast'!$B115) -> 0 | AE115: =SUMIFS('Combined P&L'!AC:AC,'Combined P&L'!$C:$C,'P&L Forecast'!$B115) -> 0 | AF115: =SUMIFS('Combined P&L'!AD:AD,'Combined P&L'!$C:$C,'P&L Forecast'!$B115) -> 0 | AG115: =SUMIFS('Combined P&L'!AE:AE,'Combined P&L'!$C:$C,'P&L Forecast'!$B115) -> 0 | AH115: =SUMIFS('Combined P&L'!AF:AF,'Combined P&L'!$C:$C,'P&L Forecast'!$B115) -> 0 | AI115: =SUMIFS('Combined P&L'!AG:AG,'Combined P&L'!$C:$C,'P&L Forecast'!$B115) -> 0 | AJ115: =SUMIFS('Combined P&L'!AH:AH,'Combined P&L'!$C:$C,'P&L Forecast'!$B115) -> 0 | AK115: =SUMIFS('Combined P&L'!AI:AI,'Combined P&L'!$C:$C,'P&L Forecast'!$B115) -> 0 | AL115: =SUMIFS('Combined P&L'!AJ:AJ,'Combined P&L'!$C:$C,'P&L Forecast'!$B115) -> 0 | AM115: =SUMIFS('Combined P&L'!AK:AK,'Combined P&L'!$C:$C,'P&L Forecast'!$B115) -> 6.673 | AN115: =SUMIFS('Combined P&L'!AL:AL,'Combined P&L'!$C:$C,'P&L Forecast'!$B115) -> 0 | AO115: =SUMIFS('Combined P&L'!AM:AM,'Combined P&L'!$C:$C,'P&L Forecast'!$B115) -> 0 | AP115: =SUMIFS('Combined P&L'!AN:AN,'Combined P&L'!$C:$C,'P&L Forecast'!$B115) -> 0 | AQ115: =SUMIFS('Combined P&L'!AO:AO,'Combined P&L'!$C:$C,'P&L Forecast'!$B115) -> 0 | AR115: =SUMIFS('Combined P&L'!AP:AP,'Combined P&L'!$C:$C,'P&L Forecast'!$B115) -> 0 | AS115: =SUMIFS('Combined P&L'!AQ:AQ,'Combined P&L'!$C:$C,'P&L Forecast'!$B115) -> 0 | AT115: =SUMIFS('Combined P&L'!AR:AR,'Combined P&L'!$C:$C,'P&L Forecast'!$B115) -> 0
B116: Website | C116: =SUMIFS($P116:$AT116,$P$69:$AT$69,">"&C$169,$P$69:$AT$69,"<"&C$170) -> 7.26173 | D116: =SUMIFS($P116:$AT116,$P$69:$AT$69,">"&D$169,$P$69:$AT$69,"<"&D$170) -> 4.91967 | F116: =SUMIFS($P116:$AT116,$P$69:$AT$69,">"&F$169,$P$69:$AT$69,"<"&F$170) -> 2.92467 | G116: =SUMIFS($P116:$AT116,$P$69:$AT$69,">"&G$169,$P$69:$AT$69,"<"&G$170) -> 2.90857 | I116: =SUMIFS($P116:$AT116,$P$69:$AT$69,">"&I$169,$P$69:$AT$69,"<"&I$170) -> 5.83631 | J116: =SUMIFS($P116:$AT116,$P$69:$AT$69,">"&J$169,$P$69:$AT$69,"<"&J$170) -> 4.90357 | K116: =+C51 -> 4.90357 | M116: =+J116-K116 -> 0 | N116: =IFERROR(K116/J116-1,0) -> 0 | P116: =SUMIFS('Combined P&L'!N:N,'Combined P&L'!$C:$C,'P&L Forecast'!$B116) -> 0.43326 | Q116: =SUMIFS('Combined P&L'!O:O,'Combined P&L'!$C:$C,'P&L Forecast'!$B116) -> 1.63176 | R116: =SUMIFS('Combined P&L'!P:P,'Combined P&L'!$C:$C,'P&L Forecast'!$B116) -> 0.43368 | S116: =SUMIFS('Combined P&L'!Q:Q,'Combined P&L'!$C:$C,'P&L Forecast'!$B116) -> 0.48413 | T116: =SUMIFS('Combined P&L'!R:R,'Combined P&L'!$C:$C,'P&L Forecast'!$B116) -> 0.48413 | U116: =SUMIFS('Combined P&L'!S:S,'Combined P&L'!$C:$C,'P&L Forecast'!$B116) -> 0.48413 | V116: =SUMIFS('Combined P&L'!T:T,'Combined P&L'!$C:$C,'P&L Forecast'!$B116) -> 0.49344 | W116: =SUMIFS('Combined P&L'!U:U,'Combined P&L'!$C:$C,'P&L Forecast'!$B116) -> 0.84344 | X116: =SUMIFS('Combined P&L'!V:V,'Combined P&L'!$C:$C,'P&L Forecast'!$B116) -> 0.49344 | Y116: =SUMIFS('Combined P&L'!W:W,'Combined P&L'!$C:$C,'P&L Forecast'!$B116) -> 0.49344 | Z116: =SUMIFS('Combined P&L'!X:X,'Combined P&L'!$C:$C,'P&L Forecast'!$B116) -> 0.49344 | AA116: =SUMIFS('Combined P&L'!Y:Y,'Combined P&L'!$C:$C,'P&L Forecast'!$B116) -> 0.49344 | AB116: =SUMIFS('Combined P&L'!Z:Z,'Combined P&L'!$C:$C,'P&L Forecast'!$B116) -> 0.53067 | AC116: =SUMIFS('Combined P&L'!AA:AA,'Combined P&L'!$C:$C,'P&L Forecast'!$B116) -> 0.399 | AD116: =SUMIFS('Combined P&L'!AB:AB,'Combined P&L'!$C:$C,'P&L Forecast'!$B116) -> 0.399 | AE116: =SUMIFS('Combined P&L'!AC:AC,'Combined P&L'!$C:$C,'P&L Forecast'!$B116) -> 0.399 | AF116: =SUMIFS('Combined P&L'!AD:AD,'Combined P&L'!$C:$C,'P&L Forecast'!$B116) -> 0.399 | AG116: =SUMIFS('Combined P&L'!AE:AE,'Combined P&L'!$C:$C,'P&L Forecast'!$B116) -> 0.399 | AH116: =SUMIFS('Combined P&L'!AF:AF,'Combined P&L'!$C:$C,'P&L Forecast'!$B116) -> 0.399 | AI116: =SUMIFS('Combined P&L'!AG:AG,'Combined P&L'!$C:$C,'P&L Forecast'!$B116) -> 0.399 | AJ116: =SUMIFS('Combined P&L'!AH:AH,'Combined P&L'!$C:$C,'P&L Forecast'!$B116) -> 0.399 | AK116: =SUMIFS('Combined P&L'!AI:AI,'Combined P&L'!$C:$C,'P&L Forecast'!$B116) -> 0.399 | AL116: =SUMIFS('Combined P&L'!AJ:AJ,'Combined P&L'!$C:$C,'P&L Forecast'!$B116) -> 0.399 | AM116: =SUMIFS('Combined P&L'!AK:AK,'Combined P&L'!$C:$C,'P&L Forecast'!$B116) -> 0.399 | AN116: =SUMIFS('Combined P&L'!AL:AL,'Combined P&L'!$C:$C,'P&L Forecast'!$B116) -> 0.43619 | AO116: =SUMIFS('Combined P&L'!AM:AM,'Combined P&L'!$C:$C,'P&L Forecast'!$B116) -> 0.399 | AP116: =SUMIFS('Combined P&L'!AN:AN,'Combined P&L'!$C:$C,'P&L Forecast'!$B116) -> 0.47738 | AQ116: =SUMIFS('Combined P&L'!AO:AO,'Combined P&L'!$C:$C,'P&L Forecast'!$B116) -> 0.399 | AR116: =SUMIFS('Combined P&L'!AP:AP,'Combined P&L'!$C:$C,'P&L Forecast'!$B116) -> 0.399 | AS116: =SUMIFS('Combined P&L'!AQ:AQ,'Combined P&L'!$C:$C,'P&L Forecast'!$B116) -> 0.399 | AT116: =SUMIFS('Combined P&L'!AR:AR,'Combined P&L'!$C:$C,'P&L Forecast'!$B116) -> 0.399
...

Sheet Combined P&L
B2: Keystone Bookkeepers
B3: Consolidated Income Statement ($000s)
B5: Line Item | C5: Summary Account | D5: Personal? | E5: FY2024 | F5: FY2025 | H5: July'25 YTD | I5: July'26 YTD | K5: Jul'25 LTM | L5: Jul'26 LTM | N5: 45292 | O5: 45323 | P5: 45352 | Q5: 45383 | R5: 45413 | S5: 45444 | T5: 45474 | U5: 45505 | V5: 45536 | W5: 45566 | X5: 45597 | Y5: 45627 | Z5: 45658 | AA5: 45689 | AB5: 45717 | AC5: 45748 | AD5: 45778 | AE5: 45809 | AF5: 45839 | AG5: 45870 | AH5: 45901 | AI5: 45931 | AJ5: 45962 | AK5: 45992 | AL5: 46023 | AM5: 46054 | AN5: 46082 | AO5: 46113 | AP5: 46143 | AQ5: 46174 | AR5: 46204
B6: Revenue
B7: Income Tax Revenue
B8: Business Income Tax | C8: Income Tax | E8: =SUMIFS($N8:$AR8,$N$5:$AR$5,">"&E$116,$N$5:$AR$5,"<"&E$117) -> 0 | F8: =SUMIFS($N8:$AR8,$N$5:$AR$5,">"&F$116,$N$5:$AR$5,"<"&F$117) -> 1.75 | H8: =SUMIFS($N8:$AR8,$N$5:$AR$5,">"&H$116,$N$5:$AR$5,"<"&H$117) -> 0 | I8: =SUMIFS($N8:$AR8,$N$5:$AR$5,">"&I$116,$N$5:$AR$5,"<"&I$117) -> 21.59 | K8: =SUMIFS($N8:$AR8,$N$5:$AR$5,">"&K$116,$N$5:$AR$5,"<"&K$117) -> 0 | L8: =SUMIFS($N8:$AR8,$N$5:$AR$5,">"&L$116,$N$5:$AR$5,"<"&L$117) -> 23.34 | Z8: ='Raw - 2025 PL'!B8/1000 -> 0 | AA8: ='Raw - 2025 PL'!C8/1000 -> 0 | AB8: ='Raw - 2025 PL'!D8/1000 -> 0 | AC8: ='Raw - 2025 PL'!E8/1000 -> 0 | AD8: ='Raw - 2025 PL'!F8/1000 -> 0 | AE8: ='Raw - 2025 PL'!G8/1000 -> 0 | AF8: ='Raw - 2025 PL'!H8/1000 -> 0 | AG8: ='Raw - 2025 PL'!I8/1000 -> 0 | ... AK8: ='Raw - 2025 PL'!M8/1000 -> 0.875 | AL8: ='Raw - 2026 PL'!B8/1000 -> 0 | AM8: ='Raw - 2026 PL'!C8/1000 -> 0 | AN8: ='Raw - 2026 PL'!D8/1000 -> 14.19 | AO8: ='Raw - 2026 PL'!E8/1000 -> 4.3 | AP8: ='Raw - 2026 PL'!F8/1000 -> 0 | AQ8: ='Raw - 2026 PL'!G8/1000 -> 3.1 | AR8: ='Raw - 2026 PL'!H8/1000 -> 0
B9: Individual Income Tax | C9: Income Tax | E9: =SUMIFS($N9:$AR9,$N$5:$AR$5,">"&E$116,$N$5:$AR$5,"<"&E$117) -> 0 | F9: =SUMIFS($N9:$AR9,$N$5:$AR$5,">"&F$116,$N$5:$AR$5,"<"&F$117) -> 1.65 | H9: =SUMIFS($N9:$AR9,$N$5:$AR$5,">"&H$116,$N$5:$AR$5,"<"&H$117) -> 0 | I9: =SUMIFS($N9:$AR9,$N$5:$AR$5,">"&I$116,$N$5:$AR$5,"<"&I$117) -> 2.325 | K9: =SUMIFS($N9:$AR9,$N$5:$AR$5,">"&K$116,$N$5:$AR$5,"<"&K$117) -> 0 | L9: =SUMIFS($N9:$AR9,$N$5:$AR$5,">"&L$116,$N$5:$AR$5,"<"&L$117) -> 3.975 | Z9: ='Raw - 2025 PL'!B9/1000 -> 0 | AA9: ='Raw - 2025 PL'!C9/1000 -> 0 | AB9: ='Raw - 2025 PL'!D9/1000 -> 0 | AC9: ='Raw - 2025 PL'!E9/1000 -> 0 | AD9: ='Raw - 2025 PL'!F9/1000 -> 0 | AE9: ='Raw - 2025 PL'!G9/1000 -> 0 | AF9: ='Raw - 2025 PL'!H9/1000 -> 0 | AG9: ='Raw - 2025 PL'!I9/1000 -> 0 | ... AK9: ='Raw - 2025 PL'!M9/1000 -> 0 | AL9: ='Raw - 2026 PL'!B9/1000 -> 0 | AM9: ='Raw - 2026 PL'!C9/1000 -> 0 | AN9: ='Raw - 2026 PL'!D9/1000 -> 0 | AO9: ='Raw - 2026 PL'!E9/1000 -> 2.325 | AP9: ='Raw - 2026 PL'!F9/1000 -> 0 | AQ9: ='Raw - 2026 PL'!G9/1000 -> 0 | AR9: ='Raw - 2026 PL'!H9/1000 -> 0
B10: Total Income Tax Revenue | E10: =SUMIFS($N10:$AR10,$N$5:$AR$5,">"&E$116,$N$5:$AR$5,"<"&E$117) -> 0 | F10: =SUMIFS($N10:$AR10,$N$5:$AR$5,">"&F$116,$N$5:$AR$5,"<"&F$117) -> 3.4 | H10: =SUMIFS($N10:$AR10,$N$5:$AR$5,">"&H$116,$N$5:$AR$5,"<"&H$117) -> 0 | I10: =SUMIFS($N10:$AR10,$N$5:$AR$5,">"&I$116,$N$5:$AR$5,"<"&I$117) -> 23.915 | K10: =SUMIFS($N10:$AR10,$N$5:$AR$5,">"&K$116,$N$5:$AR$5,"<"&K$117) -> 0 | L10: =SUMIFS($N10:$AR10,$N$5:$AR$5,">"&L$116,$N$5:$AR$5,"<"&L$117) -> 27.315 | N10: =SUM(N7,N8,N9) -> 0 | O10: =SUM(O7,O8,O9) -> 0 | P10: =SUM(P7,P8,P9) -> 0 | Q10: =SUM(Q7,Q8,Q9) -> 0 | R10: =SUM(R7,R8,R9) -> 0 | S10: =SUM(S7,S8,S9) -> 0 | T10: =SUM(T7,T8,T9) -> 0 | U10: =SUM(U7,U8,U9) -> 0 | ... AR10: =SUM(AR7,AR8,AR9) -> 0
B11: Non-Recurring Revenue
B12: 1099 Filing | C12: 1099 Filing | E12: =SUMIFS($N12:$AR12,$N$5:$AR$5,">"&E$116,$N$5:$AR$5,"<"&E$117) -> 10.475 | F12: =SUMIFS($N12:$AR12,$N$5:$AR$5,">"&F$116,$N$5:$AR$5,"<"&F$117) -> 23.55 | H12: =SUMIFS($N12:$AR12,$N$5:$AR$5,">"&H$116,$N$5:$AR$5,"<"&H$117) -> 23.49 | I12: =SUMIFS($N12:$AR12,$N$5:$AR$5,">"&I$116,$N$5:$AR$5,"<"&I$117) -> 38.7015 | K12: =SUMIFS($N12:$AR12,$N$5:$AR$5,">"&K$116,$N$5:$AR$5,"<"&K$117) -> 23.52 | L12: =SUMIFS($N12:$AR12,$N$5:$AR$5,">"&L$116,$N$5:$AR$5,"<"&L$117) -> 38.7615 | N12: ='Raw - 2024 PL'!B8/1000 -> 6.945 | O12: ='Raw - 2024 PL'!C8/1000 -> 3.38 | P12: ='Raw - 2024 PL'!D8/1000 -> 0.045 | Q12: ='Raw - 2024 PL'!E8/1000 -> 0.06 | R12: ='Raw - 2024 PL'!F8/1000 -> 0.015 | S12: ='Raw - 2024 PL'!G8/1000 -> 0 | T12: ='Raw - 2024 PL'!H8/1000 -> 0 | U12: ='Raw - 2024 PL'!I8/1000 -> 0.015 | ... Y12: ='Raw - 2024 PL'!M8/1000 -> 0 | Z12: ='Raw - 2025 PL'!B12/1000 -> 13.485 | AA12: ='Raw - 2025 PL'!C12/1000 -> 9.915 | AB12: ='Raw - 2025 PL'!D12/1000 -> 0.06 | AC12: ='Raw - 2025 PL'!E12/1000 -> 0.03 | AD12: ='Raw - 2025 PL'!F12/1000 -> 0 | AE12: ='Raw - 2025 PL'!G12/1000 -> 0 | AF12: ='Raw - 2025 PL'!H12/1000 -> 0 | AG12: ='Raw - 2025 PL'!I12/1000 -> 0.03 | ... AK12: ='Raw - 2025 PL'!M12/1000 -> 0 | AL12: ='Raw - 2026 PL'!B12/1000 -> 6.105 | AM12: ='Raw - 2026 PL'!C12/1000 -> 31.1565 | AN12: ='Raw - 2026 PL'!D12/1000 -> 1.26 | AO12: ='Raw - 2026 PL'!E12/1000 -> 0.18 | AP12: ='Raw - 2026 PL'!F12/1000 -> 0 | AQ12: ='Raw - 2026 PL'!G12/1000 -> 0 | AR12: ='Raw - 2026 PL'!H12/1000 -> 0
