Workbook
Name PrintMode: Contents!$I$18
Name MasterCheck: Contents!$I$19
Name AsOfDate: Assumptions!$C$9
Name FYEMonth: Assumptions!$C$14
Name MainStreetMode: Assumptions!$C$18
Name DealForm: Assumptions!$C$20
Name LOIDate: Assumptions!$C$71
Name SigningDate: Assumptions!$C$73
Name EffectiveDate: Assumptions!$C$74
Name Rev_FY: 'P&L Summary'!$C$14:$E$14
Name GP_FY: 'P&L Summary'!$C$18:$E$18
Name RepEBITDA_FY: 'P&L Summary'!$C$32:$E$32
Name Rev_LTM: 'P&L Summary'!$K$14
Name GP_LTM: 'P&L Summary'!$K$18
Name RepEBITDA_LTM: 'P&L Summary'!$K$32
Name Rev_PF: 'P&L Summary'!$L$14
Name SDE_FY: 'Adj. EBITDA'!$C$24:$E$24
Name AdjEBITDA_FY: 'Adj. EBITDA'!$C$28:$E$28
Name SDE_LTM: 'Adj. EBITDA'!$K$24
Name AdjEBITDA_LTM: 'Adj. EBITDA'!$K$28
Name PFAdjEBITDA: 'Adj. EBITDA'!$L$32
Name ChartStart: 'Revenue Charts'!$C$45
Name ChartEnd: 'Revenue Charts'!$AL$45
Name Customers_Latest: 'Customer Overview'!$C$20
Name GDR_LTM: 'Customer Retention'!$E$29
Name NDR_LTM: 'Customer Retention'!$E$30
Name Top10Share_LTM: Concentration!$D$34
Name Headcount_Latest: Headcount!$C$12
Name NWC_Latest: NWC!$H$20
Name NWC_Peg: NWC!$G$20
Name NWC_vsPeg: NWC!$I$20
Name DefRev_Latest: NWC!$H$15
Name Offer_Reference: 'Deal Structure'!$C$5
Name Offer_Count: 'Deal Structure'!$C$28
Name Offer_Headline_1: 'Deal Structure'!$C$22
Name Offer_CashAtClose_1: 'Deal Structure'!$C$23
Name Monthly_Revenue: 'Monthly P&L'!$Q$14:$AZ$14
Name Monthly_GrossProfit: 'Monthly P&L'!$Q$18:$AZ$18
Name Monthly_RepEBITDA: 'Monthly P&L'!$Q$32:$AZ$32
Name Monthly_SDE: 'Monthly P&L'!$Q$51:$AZ$51
Name Monthly_AdjEBITDA: 'Monthly P&L'!$Q$55:$AZ$55

Sheet Cover
B24: Ridgeline Comfort Services LLC
B25: Financial Model
B26: ="As of "&TEXT('Assumptions'!$C$9,"mm/dd/yy") -> As of 12/31/25
B30: Prepared by AMB Advisory Services LLC for Ridgeline Comfort Services LLC | September 29, 2026 | Confidential

Sheet Contents
B2: =Cover!B24
B3: Contents
B5: # | C5: Tab | D5: Purpose | E5: Units | F5: Check | H5: Model information
B6: 1 | C6: =HYPERLINK("#'Cover'!A1","Cover") -> Cover | D6: Cover | F6: – | H6: Business name | I6: Ridgeline Comfort Services LLC
B7: 2 | C7: =HYPERLINK("#'Contents'!A1","Contents") -> Contents | D7: Index, model information, Print switch, master check, log | F7: – | H7: Code name | I7: Project Ridgeline
B8: 3 | C8: =HYPERLINK("#'Summary'!A1","Summary") -> Summary | D8: Key lines, condensed ladder, KPIs and valuation range | E8: $000s | F8: =IF(OR('Checks'!$G24="CHECK"),"CHECK","OK") -> OK | H8: Prepared by | I8: AMB Advisory Services
B9: 4 | C9: =HYPERLINK("#'Assumptions'!A1","Assumptions") -> Assumptions | D9: Every input, blue, with its source | E9: $ | F9: =IF(OR('Checks'!$G39="CHECK",'Checks'!$G24="CHECK"),"CHECK","OK") -> OK | H9: As-of date | I9: ='Assumptions'!$C$9 -> 46022
B10: 5 | C10: =HYPERLINK("#'P&L Summary'!A1","P&L Summary") -> P&L Summary | D10: Historical P&L by period with KPI block | E10: $000s | F10: =IF(OR('Checks'!$G11="CHECK",'Checks'!$G12="CHECK",'Checks'!$G25="CHECK",'Checks'!$G37="CHECK",'Checks'!$G24="CHECK"),"CHECK","OK") -> OK | H10: LTM period | I10: LTM Dec-25 (equals FY2025)
B11: 6 | C11: =HYPERLINK("#'Adj. EBITDA'!A1","Adj. EBITDA") -> Adj. EBITDA | D11: Reported EBITDA to SDE, Adj. and PF Adj. EBITDA, with refs | E11: $000s | F11: =IF(OR('Checks'!$G13="CHECK",'Checks'!$G14="CHECK",'Checks'!$G24="CHECK"),"CHECK","OK") -> OK | H11: Fiscal year-end | I11: December
B12: 7 | C12: =HYPERLINK("#'Adjustments'!A1","Adjustments") -> Adjustments | D12: The schedule: tier, category, basis, evidence, status | E12: $000s | F12: =IF(OR('Checks'!$G14="CHECK",'Checks'!$G24="CHECK"),"CHECK","OK") -> OK | H12: Mode | I12: Main Street: PF Adj. EBITDA before the reserve $453K vs. $1.0M
B13: 8 | C13: =HYPERLINK("#'Revenue Detail'!A1","Revenue Detail") -> Revenue Detail | D13: Revenue by line: $, % of total, % growth; LTM strip | E13: $000s | F13: =IF(OR('Checks'!$G45="CHECK",'Checks'!$G46="CHECK",'Checks'!$G24="CHECK"),"CHECK","OK") -> OK | H13: Deal form | I13: Asset purchase
B14: 9 | C14: =HYPERLINK("#'Revenue Charts'!A1","Revenue Charts") -> Revenue Charts | D14: Monthly revenue and revenue by line (MC-R1, MC-R2) | E14: #, $000s | F14: =IF(OR('Checks'!$G31="CHECK",'Checks'!$G32="CHECK",'Checks'!$G24="CHECK"),"CHECK","OK") -> OK | H14: Source, FY2023 | I14: P&L and balance sheet: QuickBooks export
B15: 10 | C15: =HYPERLINK("#'Expense Detail'!A1","Expense Detail") -> Expense Detail | D15: Cost and expense buckets: $, % of revenue, growth; LTM strip | E15: $000s | F15: =IF(OR('Checks'!$G45="CHECK",'Checks'!$G46="CHECK",'Checks'!$G24="CHECK"),"CHECK","OK") -> OK | H15: Source, FY2024 | I15: P&L and balance sheet: QuickBooks export
B16: 11 | C16: =HYPERLINK("#'Expense Charts'!A1","Expense Charts") -> Expense Charts | D16: Monthly payroll and largest expense, with % of revenue | E16: #, $000s | F16: =IF(OR('Checks'!$G31="CHECK",'Checks'!$G32="CHECK",'Checks'!$G24="CHECK"),"CHECK","OK") -> OK | H16: Source, FY2025 | I16: P&L and balance sheet: QuickBooks export
B17: 12 | C17: =HYPERLINK("#'Customer Overview'!A1","Customer Overview") -> Customer Overview | D17: Mix by type: count, revenue, average revenue | E17: #, $ | F17: =IF(OR('Checks'!$G21="CHECK",'Checks'!$G24="CHECK"),"CHECK","OK") -> OK | H17: Version | I17: v01
B18: 13 | C18: =HYPERLINK("#'Customer Retention'!A1","Customer Retention") -> Customer Retention | D18: Count and dollar roll-forwards, churn, GDR, NDR; monthly strip | E18: #, $ | F18: =IF(OR('Checks'!$G24="CHECK",COUNTIFS('Customer Retention'!$C$31:$E$31,">0.0005")+COUNTIFS('Customer Retention'!$C$31:$E$31,"<-0.0005")>0),"CHECK","OK") -> OK | H18: Print mode (1 = black fonts) | I18: 0
B19: 14 | C19: =HYPERLINK("#'Retention Charts'!A1","Retention Charts") -> Retention Charts | D19: Monthly wins and losses, by churn type and by segment | E19: #, $000s | F19: =IF(OR('Checks'!$G31="CHECK",'Checks'!$G32="CHECK",'Checks'!$G24="CHECK"),"CHECK","OK") -> OK | H19: Master check | I19: =IF(COUNTIF('Checks'!$G:$G,"CHECK")=0,IF(COUNTIF('Checks'!$G:$G,"Pending")=0,"All checks OK","All checks OK (render check pending)"),COUNTIF('Checks'!$G:$G,"CHECK")&IF(COUNTIF('Checks'!$G:$G,"CHECK")=1," check failing"," checks failing")) -> All checks OK
B20: 15 | C20: =HYPERLINK("#'Concentration'!A1","Concentration") -> Concentration | D20: Top 20 customers, coded, cumulative share, tenure | E20: $ | F20: =IF(OR('Checks'!$G24="CHECK"),"CHECK","OK") -> OK
B21: 16 | C21: =HYPERLINK("#'Cohorts'!A1","Cohorts") -> Cohorts | D21: Count and revenue cohort triangles | E21: #, $ | F21: =IF(OR('Checks'!$G24="CHECK",COUNTIFS('Cohorts'!$D$15:$F$15,">0.0005")+COUNTIFS('Cohorts'!$D$15:$F$15,"<-0.0005")>0,COUNTIFS('Cohorts'!$D$34:$F$34,">0.0005")+COUNTIFS('Cohorts'!$D$34:$F$34,"<-0.0005")>0),"CHECK","OK") -> OK
B22: 17 | C22: =HYPERLINK("#'Headcount'!A1","Headcount") -> Headcount | D22: By department; roll-forward; tenure at departure | E22: #, $ | F22: =IF(OR('Checks'!$G22="CHECK",'Checks'!$G24="CHECK"),"CHECK","OK") -> OK
B23: 18 | C23: =HYPERLINK("#'Headcount Charts'!A1","Headcount Charts") -> Headcount Charts | D23: Monthly hires and departures; tenure at departure | E23: #, $000s | F23: =IF(OR('Checks'!$G31="CHECK",'Checks'!$G32="CHECK",'Checks'!$G24="CHECK"),"CHECK","OK") -> OK
B24: 19 | C24: =HYPERLINK("#'Balance Sheet'!A1","Balance Sheet") -> Balance Sheet | D24: Condensed balance sheet at every statement date | E24: $000s | F24: =IF(OR('Checks'!$G15="CHECK",'Checks'!$G24="CHECK"),"CHECK","OK") -> OK
B25: 20 | C25: =HYPERLINK("#'NWC'!A1","NWC") -> NWC | D25: Net working capital by date, peg basis, ratios, transfers | E25: $000s | F25: =IF(OR('Checks'!$G16="CHECK",'Checks'!$G28="CHECK",'Checks'!$G29="CHECK",'Checks'!$G24="CHECK"),"CHECK","OK") -> OK
B26: 21 | C26: =HYPERLINK("#'Debt-Like Items'!A1","Debt-Like Items") -> Debt-Like Items | D26: Debt and debt-like items: treatment and status | E26: $000s | F26: =IF(OR('Checks'!$G28="CHECK",'Checks'!$G24="CHECK"),"CHECK","OK") -> OK
B27: 22 | C27: =HYPERLINK("#'Cash Flow'!A1","Cash Flow") -> Cash Flow | D27: Historical indirect cash flow, capex, free cash flow | E27: $000s | F27: =IF(OR('Checks'!$G17="CHECK",'Checks'!$G24="CHECK"),"CHECK","OK") -> OK
B28: 23 | C28: =HYPERLINK("#'Proof of Cash'!A1","Proof of Cash") -> Proof of Cash | D28: Monthly revenue vs bank deposits | E28: $000s | F28: =IF(OR('Checks'!$G23="CHECK",'Checks'!$G24="CHECK"),"CHECK","OK") -> OK
B29: 24 | C29: =HYPERLINK("#'Projections'!A1","Projections") -> Projections | D29: Five-year driver-based income statement, BS and cash flow | E29: $000s | F29: =IF(OR('Checks'!$G18="CHECK",'Checks'!$G24="CHECK"),"CHECK","OK") -> OK
B30: 25 | C30: =HYPERLINK("#'Opportunities'!A1","Opportunities") -> Opportunities | D30: One sizing grid per growth lever | E30: $000s | F30: =IF(OR('Checks'!$G24="CHECK"),"CHECK","OK") -> OK
B31: 26 | C31: =HYPERLINK("#'Valuation'!A1","Valuation") -> Valuation | D31: Valuation range, multiples, financing, DSCR (internal) | E31: $000s | F31: =IF(OR('Checks'!$G38="CHECK",'Checks'!$G40="CHECK",'Checks'!$G24="CHECK"),"CHECK","OK") -> OK
B32: 27 | C32: =HYPERLINK("#'Deal Structure'!A1","Deal Structure") -> Deal Structure | D32: Terms, sources and uses, seller proceeds, debt service | E32: $000s | F32: =IF(OR('Checks'!$G20="CHECK",'Checks'!$G38="CHECK",'Checks'!$G40="CHECK",'Checks'!$G47="CHECK",'Checks'!$G24="CHECK"),"CHECK","OK") -> OK
B33: 28 | C33: =HYPERLINK("#'Sensitivities'!A1","Sensitivities") -> Sensitivities | D33: Two-way grids centred on the base case | E33: $000s | F33: =IF(OR('Checks'!$G40="CHECK",'Checks'!$G24="CHECK"),"CHECK","OK") -> OK
B34: 29 | C34: =HYPERLINK("#'Checks'!A1","Checks") -> Checks | D34: Every check with difference, tolerance and status | F34: =IF(OR('Checks'!$G24="CHECK",'Checks'!$G26="CHECK",'Checks'!$G27="CHECK"),"CHECK","OK") -> OK
B35: 30 | C35: =HYPERLINK("#'Data -->'!A1","Data -->") -> Data --> | D35: Data tabs follow | F35: –
B36: 31 | C36: =HYPERLINK("#'Monthly P&L'!A1","Monthly P&L") -> Monthly P&L | D36: Category × month grid every period column reads | E36: $000s | F36: =IF(OR('Checks'!$G10="CHECK",'Checks'!$G12="CHECK",'Checks'!$G24="CHECK"),"CHECK","OK") -> OK
B37: 32 | C37: =HYPERLINK("#'Databook'!A1","Databook") -> Databook | D37: Account × period with mapping and the tie to raw exports | E37: $ | F37: =IF(OR('Checks'!$G9="CHECK",'Checks'!$G10="CHECK",'Checks'!$G24="CHECK"),"CHECK","OK") -> OK
B38: 33 | C38: =HYPERLINK("#'Mapping'!A1","Mapping") -> Mapping | D38: Account to AMB category and summary line | F38: =IF(OR('Checks'!$G24="CHECK"),"CHECK","OK") -> OK
B39: 34 | C39: =HYPERLINK("#'Raw - P&L'!A1","Raw - P&L") -> Raw - P&L | D39: P&L as exported | E39: $ | F39: =IF(OR('Checks'!$G9="CHECK"),"CHECK","OK") -> OK
B40: 35 | C40: =HYPERLINK("#'Raw - BS'!A1","Raw - BS") -> Raw - BS | D40: Balance sheet as exported | E40: $ | F40: =IF(OR('Checks'!$G9="CHECK"),"CHECK","OK") -> OK
B41: 36 | C41: =HYPERLINK("#'Raw - Bank'!A1","Raw - Bank") -> Raw - Bank | D41: Bank transactions as exported, classified | E41: $ | F41: =IF(OR('Checks'!$G23="CHECK"),"CHECK","OK") -> OK
B42: 37 | C42: =HYPERLINK("#'Raw - Customers'!A1","Raw - Customers") -> Raw - Customers | D42: Customer list with names (never leaves this tab) | E42: $ | F42: =IF(OR('Checks'!$G21="CHECK"),"CHECK","OK") -> OK
B43: 38 | C43: =HYPERLINK("#'Raw - Payroll'!A1","Raw - Payroll") -> Raw - Payroll | D43: Payroll register with names (never leaves this tab) | E43: $ | F43: =IF(OR('Checks'!$G22="CHECK"),"CHECK","OK") -> OK
B45: Version | C45: Date | D45: Prepared by | E45: Change
B46: v01 | C46: 46294 | D46: AMB Advisory Services | E46: First draft generated by the AMB material bot from the sources listed above

Sheet Summary
B2: =Cover!B24
B3: Summary ($000s) | J3: Print | K3: ='Contents'!$I$18
C5: Full Year | G5: LTM | H5: PF | J5: Notes
B6: Key figures | C6: ='P&L Summary'!C6 -> FY2023 | D6: ='P&L Summary'!D6 -> FY2024 | E6: ='P&L Summary'!E6 -> FY2025 | G6: ='P&L Summary'!K6 -> Dec-25 | H6: ='P&L Summary'!L6 -> Dec-25
B8: Income statement
B9: Total Revenue | C9: ='P&L Summary'!C14 -> 2406.8 | D9: ='P&L Summary'!D14 -> 2718.6 | E9: ='P&L Summary'!E14 -> 3040.8 | G9: ='P&L Summary'!K14 -> 3040.8 | H9: ='P&L Summary'!L14 -> 3040.8
B10: % Growth | C10: ='P&L Summary'!C15 -> n.a. | D10: ='P&L Summary'!D15 -> 0.12954961 | E10: ='P&L Summary'!E15 -> 0.11851688 | G10: ='P&L Summary'!K15 -> 0.11851688 | H10: ='P&L Summary'!L15 -> n.a.
B11: Gross Profit | C11: ='P&L Summary'!C18 -> 1468 | D11: ='P&L Summary'!D18 -> 1670.7 | E11: ='P&L Summary'!E18 -> 1881.9 | G11: ='P&L Summary'!K18 -> 1881.9 | H11: ='P&L Summary'!L18 -> 1881.9
B12: % Margin | C12: ='P&L Summary'!C19 -> 0.60993851 | D12: ='P&L Summary'!D19 -> 0.61454425 | E12: ='P&L Summary'!E19 -> 0.61888319 | G12: ='P&L Summary'!K19 -> 0.61888319 | H12: ='P&L Summary'!L19 -> 0.61888319
B13: Reported EBITDA | C13: ='P&L Summary'!C32 -> 158.2 | D13: ='P&L Summary'!D32 -> 214.64 | E13: ='P&L Summary'!E32 -> 319.515 | G13: ='P&L Summary'!K32 -> 319.515 | H13: ='P&L Summary'!L32 -> 319.515
B14: % Margin | C14: ='P&L Summary'!C33 -> 0.06573043 | D14: ='P&L Summary'!D33 -> 0.078952402 | E14: ='P&L Summary'!E33 -> 0.10507597 | G14: ='P&L Summary'!K33 -> 0.10507597 | H14: ='P&L Summary'!L33 -> 0.10507597
B15: Net Income | C15: ='P&L Summary'!C43 -> 74.6 | D15: ='P&L Summary'!D43 -> 129.24 | E15: ='P&L Summary'!E43 -> 232.815 | G15: ='P&L Summary'!K43 -> 232.815 | H15: ='P&L Summary'!L43 -> 232.815
B17: Adjusted EBITDA ladder (condensed)
B18: Reported EBITDA | C18: ='Adj. EBITDA'!C13 -> 158.2 | D18: ='Adj. EBITDA'!D13 -> 214.64 | E18: ='Adj. EBITDA'!E13 -> 319.515 | G18: ='Adj. EBITDA'!K13 -> 319.515 | H18: ='Adj. EBITDA'!L13 -> 319.515
B19: (+) / (-) Normalization Adjustments | C19: ='Adj. EBITDA'!C21 -> 19.8 | D19: ='Adj. EBITDA'!D21 -> 44.6 | E19: ='Adj. EBITDA'!E21 -> 28.4 | G19: ='Adj. EBITDA'!K21 -> 28.4 | H19: ='Adj. EBITDA'!L21 -> 28.4
B20: ='Adj. EBITDA'!$B$23 -> (+) Owner Compensation [S1] [S4] | C20: ='Adj. EBITDA'!C23 -> 192.584 | D20: ='Adj. EBITDA'!D23 -> 203.25 | E20: ='Adj. EBITDA'!E23 -> 213.86 | G20: ='Adj. EBITDA'!K23 -> 213.86 | H20: ='Adj. EBITDA'!L23 -> 213.86
B21: Seller's Discretionary Earnings (SDE) | C21: ='Adj. EBITDA'!C24 -> 370.584 | D21: ='Adj. EBITDA'!D24 -> 462.49 | E21: ='Adj. EBITDA'!E24 -> 561.775 | G21: ='Adj. EBITDA'!K24 -> 561.775 | H21: ='Adj. EBITDA'!L24 -> 561.775
B22: % Margin | C22: ='Adj. EBITDA'!C25 -> 0.15397374 | D22: ='Adj. EBITDA'!D25 -> 0.17012065 | E22: ='Adj. EBITDA'!E25 -> 0.18474579 | G22: ='Adj. EBITDA'!K25 -> 0.18474579 | H22: ='Adj. EBITDA'!L25 -> 0.18474579
B23: ='Adj. EBITDA'!$B$26 -> (-) Market Replacement Compensation [S2] | C23: ='Adj. EBITDA'!C26 -> -109.25 | D23: ='Adj. EBITDA'!D26 -> -109.25 | E23: ='Adj. EBITDA'!E26 -> -109.25 | G23: ='Adj. EBITDA'!K26 -> -109.25 | H23: ='Adj. EBITDA'!L26 -> -109.25
B24: ='Adj. EBITDA'!$B$27 -> (-) Capital Reserve (Maintenance Capex) [S3] | C24: ='Adj. EBITDA'!C27 -> -66.8 | D24: ='Adj. EBITDA'!D27 -> -66.8 | E24: ='Adj. EBITDA'!E27 -> -66.8 | G24: ='Adj. EBITDA'!K27 -> -66.8 | H24: ='Adj. EBITDA'!L27 -> -66.8
B25: Adj. EBITDA | C25: ='Adj. EBITDA'!C28 -> 194.534 | D25: ='Adj. EBITDA'!D28 -> 286.44 | E25: ='Adj. EBITDA'!E28 -> 385.725 | G25: ='Adj. EBITDA'!K28 -> 385.725 | H25: ='Adj. EBITDA'!L28 -> 385.725
B26: % Margin | C26: ='Adj. EBITDA'!C29 -> 0.080826824 | D26: ='Adj. EBITDA'!D29 -> 0.10536305 | E26: ='Adj. EBITDA'!E29 -> 0.12684984 | G26: ='Adj. EBITDA'!K29 -> 0.12684984 | H26: ='Adj. EBITDA'!L29 -> 0.12684984
B27: (+) / (-) Pro Forma Adjustments | C27: ='Adj. EBITDA'!C31 -> 0 | D27: ='Adj. EBITDA'!D31 -> 0 | E27: ='Adj. EBITDA'!E31 -> 0 | G27: ='Adj. EBITDA'!K31 -> 0 | H27: ='Adj. EBITDA'!L31 -> 0
B28: PF Adj. EBITDA | C28: ='Adj. EBITDA'!C32 -> 194.534 | D28: ='Adj. EBITDA'!D32 -> 286.44 | E28: ='Adj. EBITDA'!E32 -> 385.725 | G28: ='Adj. EBITDA'!K32 -> 385.725 | H28: ='Adj. EBITDA'!L32 -> 385.725
B29: % Margin | C29: ='Adj. EBITDA'!C33 -> 0.080826824 | D29: ='Adj. EBITDA'!D33 -> 0.10536305 | E29: ='Adj. EBITDA'!E33 -> 0.12684984 | G29: ='Adj. EBITDA'!K33 -> 0.12684984 | H29: ='Adj. EBITDA'!L33 -> 0.12684984
B31: Key performance indicators
B32: Customers, active at period end (#) | C32: ='P&L Summary'!C47 -> 44 | D32: ='P&L Summary'!D47 -> 49 | E32: ='P&L Summary'!E47 -> 52 | G32: ='P&L Summary'!K47 -> 52 | H32: ='P&L Summary'!L47 -> 52
B33: Employees, non-owner FTE at period end (#) | C33: ='P&L Summary'!C49 -> 21 | D33: ='P&L Summary'!D49 -> 23 | E33: ='P&L Summary'!E49 -> 23 | G33: ='P&L Summary'!K49 -> 23 | H33: ='P&L Summary'!L49 -> 23
B34: Revenue per employee ($) | C34: ='P&L Summary'!C50 -> 114609.52 | D34: ='P&L Summary'!D50 -> 118200 | E34: ='P&L Summary'!E50 -> 132208.7 | G34: ='P&L Summary'!K50 -> 132208.7 | H34: ='P&L Summary'!L50 -> 132208.7
B35: Labor cost, % of revenue (excludes owner) | C35: ='P&L Summary'!C51 -> 0.29832807 | D35: ='P&L Summary'!D51 -> 0.29605312 | E35: ='P&L Summary'!E51 -> 0.29296238 | G35: ='P&L Summary'!K51 -> 0.29296238 | H35: ='P&L Summary'!L51 -> 0.29296238
B36: Recurring revenue, % of total | C36: ='P&L Summary'!C52 -> 0.089164035 | D36: ='P&L Summary'!D52 -> 0.091333775 | E36: ='P&L Summary'!E52 -> 0.095172323 | G36: ='P&L Summary'!K52 -> 0.095172323 | H36: ='P&L Summary'!L52 -> 0.095172323
B38: At the as-of date (12/31/25)
B39: Top 10 customers, % of revenue | G39: ='Concentration'!$D$34 -> 0.19297553
B40: Adjusted NWC, latest | G40: ='NWC'!H20 -> 173.2 | J40: No peg: year-end balance sheets only
B41: Funded debt, latest | G41: ='Debt-Like Items'!$C$15 -> 279.4 | J41: Seller's; paid from proceeds at close
B42: Mode | G42: =IF('Assumptions'!$C$18=1,"Main Street","Lower middle market") -> Main Street | J42: $453K PF Adj. EBITDA vs. $1.0M threshold
B43: Deal form | G43: ='Assumptions'!$C$20 -> Asset purchase
B45: Operating facts per management (1)
B46: Active maintenance-agreement members (#) | G46: ='Assumptions'!$C$112 -> 1450 | J46: As of 09/21/26. Members with an active agreement: two tune-ups a year, priority scheduling, 15% repair discount
B47: Maintenance-agreement renewal rate | G47: ='Assumptions'!$C$113 -> 0.82 | J47: As of 09/21/26
B48: Service calls on which an agreement is offered | G48: ='Assumptions'!$C$114 -> 0.35 | J48: As of 09/21/26
B49: Google rating | G49: ='Assumptions'!$C$115 -> 4.8 | J49: As of 09/21/26
B50: Google reviews (#) | G50: ='Assumptions'!$C$116 -> 900 | J50: As of 09/21/26. Stated as 900+
B51: Service vans (#) | G51: ='Assumptions'!$C$117 -> 18 | J51: As of 09/21/26
B52: Install trucks (#) | G52: ='Assumptions'!$C$118 -> 2 | J52: As of 09/21/26
B53: Service radius (miles) | G53: ='Assumptions'!$C$119 -> 35 | J53: As of 09/21/26
B54: Shop and office (sq ft) | G54: ='Assumptions'!$C$120 -> 8000 | J54: As of 09/21/26
B55: Owner hours per week (hours) | G55: ='Assumptions'!$C$121 -> 45 | J55: As of 09/21/26
B57: Indicative valuation range (internal; never in the CIM)
B58: SDE × multiple | C58: Low | D58: Mid | E58: High
B59: Total Investment | C59: ='Valuation'!C30 -> 1263.3 | D59: ='Valuation'!D30 -> 1685.33 | E59: ='Valuation'!E30 -> 2163.81
B60: Implied SDE Multiple (x) | C60: ='Valuation'!C31 -> 2.2487651 | D60: ='Valuation'!D31 -> 3.0000089 | E60: ='Valuation'!E31 -> 3.8517378
B61: Implied Adj. EBITDA Multiple (x) | C61: ='Valuation'!C32 -> 3.2751312 | D61: ='Valuation'!D32 -> 4.3692527 | E61: ='Valuation'!E32 -> 5.609722
B62: DSCR, SBA loan only (x) | C62: ='Valuation'!C44 -> 1.7885236 | D62: ='Valuation'!D44 -> 1.5705236 | E62: ='Valuation'!E44 -> 1.4022762 | J62: ='Valuation'!$G$44 -> SBA loan only: High case binds at 1.40x, clearing the 1.25x hurdle
B63: DSCR, Reference structure (x) | C63: n.a. | D63: ='Valuation'!$D$45 -> 0.88926098 | E63: n.a. | J63: =IF(ISNUMBER(D63),IF(D63<'Assumptions'!$C$84,"Below the "&TEXT('Assumptions'!$C$84,"0.00")&"x hurdle: the seller note amortises inside "&TEXT('Assumptions'!$C$57,"0")&" months; lengthen the note or lower the price","Clears the "&TEXT('Assumptions'!$C$84,"0.00")&"x hurdle, seller note included"),"n.a.") -> Below the 1.25x hurdle: the seller note amortises inside 18 months; lengthen the note or lower the price
B65: Note: LTM Dec-25 equals FY2025. Reported EBITDA is net income plus interest, taxes and D&A, so it carries other income; a normalization row removes what is non-operating. (1) Per management; not independently verified.

Sheet Assumptions
B2: =Cover!B24
B3: Assumptions and Inputs ($ unless stated) | I3: Print | J3: ='Contents'!$I$18
C5: Inputs | I5: Source
B6: Assumption | C6: Value | I6: Source
B8: Model information
B9: As-of date (last full month of data) | C9: 46022 | I9: Monthly P&L to 2025-12; fixed by the bot, never TODAY()
B10: First data month | C10: 44927 | I10: First month of the Monthly P&L grid
B11: Source granularity | C11: Monthly | I11: Monthly when the books give 12 or more contiguous months
B12: Books basis | C12: Accrual | I12: Per the source report basis
B13: LTM end month | C13: =EOMONTH($C$9,0) -> 46022 | I13: Derived: EOMONTH(AsOfDate, 0)
B14: Fiscal year-end month (1-12) | C14: 12 | I14: Request list fiscal_year_end
B15: Latest full fiscal year | C15: =YEAR($C$9)+IF(MONTH($C$9)>$C$14,1,0)-IF(MONTH($C$9)=$C$14,0,1) -> 2025 | I15: Derived from the as-of date and fiscal year-end
B16: Units on analysis tabs | C16: $000s | I16: Databook divides raw dollars by 1,000
B17: Customer term | C17: Customer | I17: One term per deal, on every tab and in the CIM
B18: Main Street mode (1 = yes) | C18: 1 | I18: Rule: PF Adj. EBITDA before the capital reserve $452,525 (PF Dec-25) < $1,000,000 (AMB threshold)
B19: Main Street threshold (PF Adj. EBITDA before reserve) | C19: 1000000 | I19: Reference: below $1.0M the bot sets Main Street mode above (SDE in the CIM, capital reserve deducted); change the mode cell to override
B20: Deal form | C20: Asset purchase | I20: Intake notes: the owner prefers an asset sale; the Main Street default agrees
B22: Owner compensation and capital reserve
B23: Owner replacement salary | C23: 95000 | I23: Request list owner_replacement_salary ($95,000); intake notes: $95,000
B24: Payroll taxes and benefits burden | C24: 0.15 | I24: AMB default 15% for payroll taxes and benefits; confirm with the Seller
B25: Market replacement compensation [S2] | C25: =$C$23*(1+$C$24) -> 109250 | I25: Salary × (1 + burden); deducted below SDE
B26: Capital reserve (maintenance capex) [S3] | C26: 66800 | I26: Three-year average of depreciation expense, FY2023–FY2025
B27: Capital reserve basis | C27: D&A proxy | I27: Form 4562 equipment placed in service, else the three-year average of D&A flagged as a proxy
B29: Projection drivers
B30: Driver | C30: FY2026E | D30: FY2027E | E30: FY2028E | F30: FY2029E | G30: FY2030E
B31: Revenue growth | C31: 0.124 | D31: 0.1005 | E31: 0.077 | F31: 0.0535 | G31: 0.03 | I31: FY2023–FY2025 revenue CAGR of 12.4% (capped 0–15%), fading to 3% by year 5. Illustrative; replace with seller guidance.
B32: Cost of goods sold, % of revenue | C32: 0.3811 | D32: 0.3811 | E32: 0.3811 | F32: 0.3811 | G32: 0.3811 | I32: FY2025 % of revenue (latest-year run-rate); see P&L Summary for the trend.
B33: Salaries, wages and benefits, % of revenue | C33: 0.2975 | D33: 0.2975 | E33: 0.2975 | F33: 0.2975 | G33: 0.2975 | I33: FY2025 % of revenue (latest-year run-rate); see P&L Summary for the trend.
B34: Owner / officer compensation ($) | C34: 200000 | D34: 200000 | E34: 200000 | F34: 200000 | G34: 200000 | I34: Held at FY2025 level; the ladder normalises it to the replacement cost.
B35: Rent and occupancy, % of revenue | C35: 0.0251 | D35: 0.0251 | E35: 0.0251 | F35: 0.0251 | G35: 0.0251 | I35: FY2025 % of revenue (latest-year run-rate); see P&L Summary for the trend. Check the lease for scheduled escalations.
B36: Advertising and marketing, % of revenue | C36: 0.0262 | D36: 0.0262 | E36: 0.0262 | F36: 0.0262 | G36: 0.0262 | I36: FY2025 % of revenue (latest-year run-rate); see P&L Summary for the trend.
B37: Other operating expenses, % of revenue | C37: 0.1002 | D37: 0.1002 | E37: 0.1002 | F37: 0.1002 | G37: 0.1002 | I37: FY2025 % of revenue (latest-year run-rate); see P&L Summary for the trend.
B38: Depreciation and amortization, % of revenue | C38: 0.0238 | D38: 0.0238 | E38: 0.0238 | F38: 0.0238 | G38: 0.0238 | I38: FY2025 % of revenue (latest-year run-rate); see P&L Summary for the trend.
B39: Capital expenditures, % of revenue | C39: 0.0238 | D39: 0.0238 | E39: 0.0238 | F39: 0.0238 | G39: 0.0238 | I39: Set equal to D&A (maintenance capex). Raise for growth capex or a fleet refresh.
B40: Receivable days (DSO) | C40: 30 | D40: 30 | E40: 30 | F40: 30 | G40: 30 | I40: FY2025 receivables ÷ revenue × 365, per Balance Sheet.
B41: Inventory days (DIO) | C41: 30 | D41: 30 | E41: 30 | F41: 30 | G41: 30 | I41: FY2025 inventory ÷ COGS × 365, per Balance Sheet.
B42: Payable days (DPO) | C42: 37 | D42: 37 | E42: 37 | F42: 37 | G42: 37 | I42: FY2025 payables ÷ COGS × 365, per Balance Sheet.
... B46: Owner distributions, % of net income | C46: 0 | D46: 0 | E46: 0 | F46: 0 | G46: 0 | I46: Owner distributions as % of net income. 0% lets cash build (deals are cash-free, debt-free).
B48: Valuation multiples
B49: Multiple | C49: Low | D49: Mid | E49: High
B50: SDE multiple (x) | C50: 2.5 | D50: 3 | E50: 3.5 | I50: AMB placeholder range for Main Street services businesses; replace with the licensed comps source before relying on it.
B51: Adj. EBITDA multiple (x) | C51: 4 | D51: 5 | E51: 6 | I51: AMB placeholder range for Main Street services businesses; replace with the licensed comps source before relying on it.
B53: Deal terms (Structure 1)
B54: Structure preset | C54: Traditional | I54: Reference: Traditional is cash plus a seller note; the preset filled the defaults below when the bot ran
B55: Cash at close, % of price | C55: 0.8 | I55: AMB default: 70-80% cash at close, per recent AMB offers
B56: Seller note, % of price | C56: 0.2 | I56: Per recent AMB offers; subordinated to senior debt only
B57: Seller note term (months) | C57: 18 | I57: Per recent AMB offers: 18-month term, quarterly payments
B58: Seller note interest rate | C58: 0.09 | I58: Per recent AMB offers: 9.0%; a recent buy-side model used 6.5% as the low case
B59: Indemnity escrow, % of cash at close | C59: 0.1 | I59: LOI12 §7(h); market 5-10% for 12-18 months (TAX)
B60: Indemnity escrow held (months) | C60: 15 | I60: LOI12 §7(h): 15 months
B61: Buyer equity injection, % of uses | C61: 0.1 | I61: SBA 7(a) minimum 10%; a recent AMB deal used 15%
B62: Senior / SBA loan term (years) | C62: 10 | I62: SBA 7(a) business acquisition: 10 years
B63: Senior / SBA loan interest rate | C63: 0.105 | I63: Placeholder until a lender quotes; replace before relying on DSCR
B64: Buyer transaction fees ($) | C64: 0 | I64: No AMB default; buyer one-time costs on a $3.0M deal run $110-300K (BL)
B65: Reconciliation holdback (months of payroll) | C65: 1 | I65: Per recent AMB offers: one month of payroll on an asset purchase; zero on an equity purchase
B66: Deferred capex / renovation ($) | C66: 0 | I66: Enter known deferred maintenance; adds to Total Investment
B67: True-up settlement | C67: Cash | I67: Cash / Stock / Share-adjusting escrow; Stock when buyer stock is meant to be tax-deferred
B68: Stock consideration intended tax-deferred? (Y/N) | C68: N | I68: Y turns on the boot flag on Deal Structure
B69: Deferred revenue and customer deposits | C69: NWC (operating liability) | I69: AMB default: NWC (operating liability); Debt-like is an override that needs a note
B70: Premises arrangement | C70: Leased from third party | I70: Intake: locations
B71: LOI date | I71: Enter when the LOI is signed (check C36)
B72: Exclusivity (days) | C72: 90 | I72: LOI12 Agreement §1: 90 days plus one automatic 30-day extension
B73: Target signing date | I73: LOI + 9-11 weeks (OUTL)
B74: Target effective date | I74: Signing + 0-15 days; first business day of the next tax year near year-end (RECS #8)
B76: Sensitivity settings
B77: Multiple axis step (x) | C77: 0.25 | I77: Per AMB; axes centre on the base case
B78: Earnings axis step (% of base) | C78: 0.05 | I78: Per AMB
B79: Purchase price axis step (% of base) | C79: 0.05 | I79: Per AMB
B80: Interest rate axis step | C80: 0.005 | I80: Per AMB
B81: Cash at close axis step | C81: 0.05 | I81: Per AMB
B82: Rounding, $ tables (digits at $000s) | C82: 0 | I82: 0 = nearest $1K on the $000s grids
B83: Gradient bands (#) | C83: 5 | I83: Heat-map bands above the hurdle
B84: DSCR hurdle (x) | C84: 1.25 | I84: SBA lenders underwrite to 1.25x
B86: Pro forma scenarios (Main Street mode; base LTM Dec-25)
B87: Driver | C87: Low | D87: Mid | E87: High | F87: Basis
B88: Revenue growth (%) | C88: -0.03 | D88: 0 | E88: 0.03 | F88: Per AMB, by case | I88: Mid is the base case; Low and High must differ from Mid on growth and one operating driver (check C29)
B89: Cost of goods sold method | C89: % of sales, latest year | D89: Latest year | E89: % of sales, latest year | F89: Fixed method list (5.5) | I89: 3-year average, Latest year or % of sales; Latest year reads LTM Dec-25
B90: Salaries, wages and benefits method | C90: Latest year | D90: Latest year | E90: Latest year | F90: Fixed method list (5.5) | I90: 3-year average, Latest year or % of sales; Latest year reads LTM Dec-25
B91: Rent and occupancy method | C91: Latest year | D91: Latest year | E91: Latest year | F91: Fixed method list (5.5) | I91: 3-year average, Latest year or % of sales; Latest year reads LTM Dec-25
B92: Advertising and marketing method | C92: Latest year | D92: Latest year | E92: Latest year | F92: Fixed method list (5.5) | I92: 3-year average, Latest year or % of sales; Latest year reads LTM Dec-25
B93: Other operating expenses method | C93: Latest year | D93: Latest year | E93: Latest year | F93: Fixed method list (5.5) | I93: 3-year average, Latest year or % of sales; Latest year reads LTM Dec-25
B94: Owner replacement salary ($) | C94: =$C$23 -> 95000 | D94: =$C$23 -> 95000 | E94: =$C$23 -> 95000 | F94: Base input above | I94: Base input above; type over a case to vary it
B95: Capital reserve ($) | C95: =$C$26 -> 66800 | D95: =$C$26 -> 66800 | E95: =$C$26 -> 66800 | F95: Base input above | I95: Base input above; type over a case to vary it
B96: Deferred capex / renovation ($) | C96: =$C$66 -> 0 | D96: =$C$66 -> 0 | E96: =$C$66 -> 0 | F96: Base input above | I96: Base input above; type over a case to vary it
B97: Equity injection (%) | C97: =$C$61 -> 0.1 | D97: =$C$61 -> 0.1 | E97: =$C$61 -> 0.1 | F97: Base input above | I97: Base input above; type over a case to vary it
B98: Loan term (years) | C98: =$C$62 -> 10 | D98: =$C$62 -> 10 | E98: =$C$62 -> 10 | F98: Base input above | I98: Base input above; type over a case to vary it
B99: Interest rate (%) | C99: =$C$63 -> 0.105 | D99: =$C$63 -> 0.105 | E99: =$C$63 -> 0.105 | F99: Base input above | I99: Base input above; type over a case to vary it
B100: Valuation multiple (x SDE) | C100: =C50 -> 2.5 | D100: =D50 -> 3 | E100: =E50 -> 3.5 | F100: Valuation multiples above | I100: Valuation multiples above
B102: Employer payroll taxes on the owner's salary ([S4], federal statutory rates)
B103: Social Security rate | C103: 0.062 | I103: Employer share, federal statute
B104: Medicare rate | C104: 0.0145 | I104: Employer share, on all wages
B105: Federal unemployment (FUTA) rate | C105: 0.006 | I105: Net of the state credit
B106: FUTA wage base | C106: 7000 | I106: First $7,000 of wages
B107: Social Security wage base, FY2023 | C107: 160200 | I107: Calendar 2023 wage base
B108: Social Security wage base, FY2024 | C108: 168600 | I108: Calendar 2024 wage base
B109: Social Security wage base, FY2025 | C109: 176100 | I109: Calendar 2025 wage base
B111: Operating facts (per management)
B112: Active maintenance-agreement members (#) | C112: 1450 | I112: Per management, as of 09/21/26. Members with an active agreement: two tune-ups a year, priority scheduling, 15% repair discount
B113: Maintenance-agreement renewal rate | C113: 0.82 | I113: Per management, as of 09/21/26
B114: Service calls on which an agreement is offered | C114: 0.35 | I114: Per management, as of 09/21/26
...

Sheet P&L Summary
B2: =Cover!B24
B3: Historical P&L Summary ($000s) | N3: Print | O3: ='Contents'!$I$18
C5: Full Year | G5: YTD | J5: LTM | L5: PF | N5: PF vs. LTM | Q5: Basis
B6: Income Statement | C6: ="FY"&YEAR(C$59) -> FY2023 | D6: ="FY"&YEAR(D$59) -> FY2024 | E6: ="FY"&YEAR(E$59) -> FY2025 | G6: =TEXT(G$59,"mmm-yy") -> Dec-24 | H6: =TEXT(H$59,"mmm-yy") -> Dec-25 | J6: =TEXT(J$59,"mmm-yy") -> Dec-24 | K6: =TEXT(K$59,"mmm-yy") -> Dec-25 | L6: =TEXT(L$59,"mmm-yy") -> Dec-25 | N6: ($) | O6: (%) | Q6: Basis / notes
B8: Revenue
B9: Residential service and replacement | C9: =SUMIFS('Monthly P&L'!$Q$9:$AZ$9,'Monthly P&L'!$Q$6:$AZ$6,">="&C$58,'Monthly P&L'!$Q$6:$AZ$6,"<="&C$59) -> 1612.4 | D9: =SUMIFS('Monthly P&L'!$Q$9:$AZ$9,'Monthly P&L'!$Q$6:$AZ$6,">="&D$58,'Monthly P&L'!$Q$6:$AZ$6,"<="&D$59) -> 1788.9 | E9: =SUMIFS('Monthly P&L'!$Q$9:$AZ$9,'Monthly P&L'!$Q$6:$AZ$6,">="&E$58,'Monthly P&L'!$Q$6:$AZ$6,"<="&E$59) -> 1964.3 | G9: =SUMIFS('Monthly P&L'!$Q$9:$AZ$9,'Monthly P&L'!$Q$6:$AZ$6,">="&G$58,'Monthly P&L'!$Q$6:$AZ$6,"<="&G$59) -> 1788.9 | H9: =SUMIFS('Monthly P&L'!$Q$9:$AZ$9,'Monthly P&L'!$Q$6:$AZ$6,">="&H$58,'Monthly P&L'!$Q$6:$AZ$6,"<="&H$59) -> 1964.3 | J9: =SUMIFS('Monthly P&L'!$Q$9:$AZ$9,'Monthly P&L'!$Q$6:$AZ$6,">="&J$58,'Monthly P&L'!$Q$6:$AZ$6,"<="&J$59) -> 1788.9 | K9: =SUMIFS('Monthly P&L'!$Q$9:$AZ$9,'Monthly P&L'!$Q$6:$AZ$6,">="&K$58,'Monthly P&L'!$Q$6:$AZ$6,"<="&K$59) -> 1964.3 | L9: =SUMIFS('Monthly P&L'!$Q$9:$AZ$9,'Monthly P&L'!$Q$6:$AZ$6,">="&L$58,'Monthly P&L'!$Q$6:$AZ$6,"<="&L$59) -> 1964.3 | N9: =L9-K9 -> 0 | O9: =IFERROR(L9/K9-1,"n.a.") -> 0 | Q9: Account: Service Revenue - Residential
B10: Commercial service | C10: =SUMIFS('Monthly P&L'!$Q$10:$AZ$10,'Monthly P&L'!$Q$6:$AZ$6,">="&C$58,'Monthly P&L'!$Q$6:$AZ$6,"<="&C$59) -> 598.2 | D10: =SUMIFS('Monthly P&L'!$Q$10:$AZ$10,'Monthly P&L'!$Q$6:$AZ$6,">="&D$58,'Monthly P&L'!$Q$6:$AZ$6,"<="&D$59) -> 702.5 | E10: =SUMIFS('Monthly P&L'!$Q$10:$AZ$10,'Monthly P&L'!$Q$6:$AZ$6,">="&E$58,'Monthly P&L'!$Q$6:$AZ$6,"<="&E$59) -> 811.7 | G10: =SUMIFS('Monthly P&L'!$Q$10:$AZ$10,'Monthly P&L'!$Q$6:$AZ$6,">="&G$58,'Monthly P&L'!$Q$6:$AZ$6,"<="&G$59) -> 702.5 | H10: =SUMIFS('Monthly P&L'!$Q$10:$AZ$10,'Monthly P&L'!$Q$6:$AZ$6,">="&H$58,'Monthly P&L'!$Q$6:$AZ$6,"<="&H$59) -> 811.7 | J10: =SUMIFS('Monthly P&L'!$Q$10:$AZ$10,'Monthly P&L'!$Q$6:$AZ$6,">="&J$58,'Monthly P&L'!$Q$6:$AZ$6,"<="&J$59) -> 702.5 | K10: =SUMIFS('Monthly P&L'!$Q$10:$AZ$10,'Monthly P&L'!$Q$6:$AZ$6,">="&K$58,'Monthly P&L'!$Q$6:$AZ$6,"<="&K$59) -> 811.7 | L10: =SUMIFS('Monthly P&L'!$Q$10:$AZ$10,'Monthly P&L'!$Q$6:$AZ$6,">="&L$58,'Monthly P&L'!$Q$6:$AZ$6,"<="&L$59) -> 811.7 | N10: =L10-K10 -> 0 | O10: =IFERROR(L10/K10-1,"n.a.") -> 0 | Q10: Account: Service Revenue - Commercial
B11: Maintenance agreements | C11: =SUMIFS('Monthly P&L'!$Q$11:$AZ$11,'Monthly P&L'!$Q$6:$AZ$6,">="&C$58,'Monthly P&L'!$Q$6:$AZ$6,"<="&C$59) -> 214.6 | D11: =SUMIFS('Monthly P&L'!$Q$11:$AZ$11,'Monthly P&L'!$Q$6:$AZ$6,">="&D$58,'Monthly P&L'!$Q$6:$AZ$6,"<="&D$59) -> 248.3 | E11: =SUMIFS('Monthly P&L'!$Q$11:$AZ$11,'Monthly P&L'!$Q$6:$AZ$6,">="&E$58,'Monthly P&L'!$Q$6:$AZ$6,"<="&E$59) -> 289.4 | G11: =SUMIFS('Monthly P&L'!$Q$11:$AZ$11,'Monthly P&L'!$Q$6:$AZ$6,">="&G$58,'Monthly P&L'!$Q$6:$AZ$6,"<="&G$59) -> 248.3 | H11: =SUMIFS('Monthly P&L'!$Q$11:$AZ$11,'Monthly P&L'!$Q$6:$AZ$6,">="&H$58,'Monthly P&L'!$Q$6:$AZ$6,"<="&H$59) -> 289.4 | J11: =SUMIFS('Monthly P&L'!$Q$11:$AZ$11,'Monthly P&L'!$Q$6:$AZ$6,">="&J$58,'Monthly P&L'!$Q$6:$AZ$6,"<="&J$59) -> 248.3 | K11: =SUMIFS('Monthly P&L'!$Q$11:$AZ$11,'Monthly P&L'!$Q$6:$AZ$6,">="&K$58,'Monthly P&L'!$Q$6:$AZ$6,"<="&K$59) -> 289.4 | L11: =SUMIFS('Monthly P&L'!$Q$11:$AZ$11,'Monthly P&L'!$Q$6:$AZ$6,">="&L$58,'Monthly P&L'!$Q$6:$AZ$6,"<="&L$59) -> 289.4 | N11: =L11-K11 -> 0 | O11: =IFERROR(L11/K11-1,"n.a.") -> 0 | Q11: Account: Maintenance Agreements
B12: Less: discounts and refunds | C12: =SUMIFS('Monthly P&L'!$Q$12:$AZ$12,'Monthly P&L'!$Q$6:$AZ$6,">="&C$58,'Monthly P&L'!$Q$6:$AZ$6,"<="&C$59) -> -18.4 | D12: =SUMIFS('Monthly P&L'!$Q$12:$AZ$12,'Monthly P&L'!$Q$6:$AZ$6,">="&D$58,'Monthly P&L'!$Q$6:$AZ$6,"<="&D$59) -> -21.1 | E12: =SUMIFS('Monthly P&L'!$Q$12:$AZ$12,'Monthly P&L'!$Q$6:$AZ$6,">="&E$58,'Monthly P&L'!$Q$6:$AZ$6,"<="&E$59) -> -24.6 | G12: =SUMIFS('Monthly P&L'!$Q$12:$AZ$12,'Monthly P&L'!$Q$6:$AZ$6,">="&G$58,'Monthly P&L'!$Q$6:$AZ$6,"<="&G$59) -> -21.1 | H12: =SUMIFS('Monthly P&L'!$Q$12:$AZ$12,'Monthly P&L'!$Q$6:$AZ$6,">="&H$58,'Monthly P&L'!$Q$6:$AZ$6,"<="&H$59) -> -24.6 | J12: =SUMIFS('Monthly P&L'!$Q$12:$AZ$12,'Monthly P&L'!$Q$6:$AZ$6,">="&J$58,'Monthly P&L'!$Q$6:$AZ$6,"<="&J$59) -> -21.1 | K12: =SUMIFS('Monthly P&L'!$Q$12:$AZ$12,'Monthly P&L'!$Q$6:$AZ$6,">="&K$58,'Monthly P&L'!$Q$6:$AZ$6,"<="&K$59) -> -24.6 | L12: =SUMIFS('Monthly P&L'!$Q$12:$AZ$12,'Monthly P&L'!$Q$6:$AZ$6,">="&L$58,'Monthly P&L'!$Q$6:$AZ$6,"<="&L$59) -> -24.6 | N12: =L12-K12 -> 0 | O12: =IFERROR(L12/K12-1,"n.a.") -> 0 | Q12: Account: Discounts Given
B14: Total Revenue | C14: =SUM(C9:C12) -> 2406.8 | D14: =SUM(D9:D12) -> 2718.6 | E14: =SUM(E9:E12) -> 3040.8 | G14: =SUM(G9:G12) -> 2718.6 | H14: =SUM(H9:H12) -> 3040.8 | J14: =SUM(J9:J12) -> 2718.6 | K14: =SUM(K9:K12) -> 3040.8 | L14: =SUM(L9:L12) -> 3040.8 | N14: =L14-K14 -> 0 | O14: =IFERROR(L14/K14-1,"n.a.") -> 0 | Q14: Sum of the revenue lines
B15: % Growth | C15: n.a. | D15: =IFERROR(D14/C14-1,"n.a.") -> 0.12954961 | E15: =IFERROR(E14/D14-1,"n.a.") -> 0.11851688 | G15: =IFERROR(G14/SUMIFS('Monthly P&L'!$Q$14:$AZ$14,'Monthly P&L'!$Q$6:$AZ$6,">="&(EOMONTH(G$58,-13)+1),'Monthly P&L'!$Q$6:$AZ$6,"<="&EOMONTH(G$59,-12))-1,"n.a.") -> 0.12954961 | H15: =IFERROR(H14/G14-1,"n.a.") -> 0.11851688 | J15: =IFERROR(J14/SUMIFS('Monthly P&L'!$Q$14:$AZ$14,'Monthly P&L'!$Q$6:$AZ$6,">="&(EOMONTH(J$58,-13)+1),'Monthly P&L'!$Q$6:$AZ$6,"<="&EOMONTH(J$59,-12))-1,"n.a.") -> 0.12954961 | K15: =IFERROR(K14/J14-1,"n.a.") -> 0.11851688 | L15: n.a. | Q15: Against the same window a year earlier
B16: Cost of Revenue | C16: =SUMIFS('Monthly P&L'!$Q$16:$AZ$16,'Monthly P&L'!$Q$6:$AZ$6,">="&C$58,'Monthly P&L'!$Q$6:$AZ$6,"<="&C$59) -> 938.8 | D16: =SUMIFS('Monthly P&L'!$Q$16:$AZ$16,'Monthly P&L'!$Q$6:$AZ$6,">="&D$58,'Monthly P&L'!$Q$6:$AZ$6,"<="&D$59) -> 1047.9 | E16: =SUMIFS('Monthly P&L'!$Q$16:$AZ$16,'Monthly P&L'!$Q$6:$AZ$6,">="&E$58,'Monthly P&L'!$Q$6:$AZ$6,"<="&E$59) -> 1158.9 | G16: =SUMIFS('Monthly P&L'!$Q$16:$AZ$16,'Monthly P&L'!$Q$6:$AZ$6,">="&G$58,'Monthly P&L'!$Q$6:$AZ$6,"<="&G$59) -> 1047.9 | H16: =SUMIFS('Monthly P&L'!$Q$16:$AZ$16,'Monthly P&L'!$Q$6:$AZ$6,">="&H$58,'Monthly P&L'!$Q$6:$AZ$6,"<="&H$59) -> 1158.9 | J16: =SUMIFS('Monthly P&L'!$Q$16:$AZ$16,'Monthly P&L'!$Q$6:$AZ$6,">="&J$58,'Monthly P&L'!$Q$6:$AZ$6,"<="&J$59) -> 1047.9 | K16: =SUMIFS('Monthly P&L'!$Q$16:$AZ$16,'Monthly P&L'!$Q$6:$AZ$6,">="&K$58,'Monthly P&L'!$Q$6:$AZ$6,"<="&K$59) -> 1158.9 | L16: =SUMIFS('Monthly P&L'!$Q$16:$AZ$16,'Monthly P&L'!$Q$6:$AZ$6,">="&L$58,'Monthly P&L'!$Q$6:$AZ$6,"<="&L$59) -> 1158.9 | N16: =L16-K16 -> 0 | O16: =IFERROR(L16/K16-1,"n.a.") -> 0 | Q16: Accounts: Equipment & Materials and 1 more (Databook)
B18: Gross Profit | C18: =C14-C16 -> 1468 | D18: =D14-D16 -> 1670.7 | E18: =E14-E16 -> 1881.9 | G18: =G14-G16 -> 1670.7 | H18: =H14-H16 -> 1881.9 | J18: =J14-J16 -> 1670.7 | K18: =K14-K16 -> 1881.9 | L18: =L14-L16 -> 1881.9 | N18: =L18-K18 -> 0 | O18: =IFERROR(L18/K18-1,"n.a.") -> 0 | Q18: Total revenue less cost of revenue
B19: % Margin | C19: =IFERROR(C18/C14,"n.m.") -> 0.60993851 | D19: =IFERROR(D18/D14,"n.m.") -> 0.61454425 | E19: =IFERROR(E18/E14,"n.m.") -> 0.61888319 | G19: =IFERROR(G18/G14,"n.m.") -> 0.61454425 | H19: =IFERROR(H18/H14,"n.m.") -> 0.61888319 | J19: =IFERROR(J18/J14,"n.m.") -> 0.61454425 | K19: =IFERROR(K18/K14,"n.m.") -> 0.61888319 | L19: =IFERROR(L18/L14,"n.m.") -> 0.61888319 | Q19: Of total revenue
B21: Operating Expenses
B22: Salaries, Wages and Benefits | C22: =SUMIFS('Monthly P&L'!$Q$22:$AZ$22,'Monthly P&L'!$Q$6:$AZ$6,">="&C$58,'Monthly P&L'!$Q$6:$AZ$6,"<="&C$59) -> 730.6 | D22: =SUMIFS('Monthly P&L'!$Q$22:$AZ$22,'Monthly P&L'!$Q$6:$AZ$6,">="&D$58,'Monthly P&L'!$Q$6:$AZ$6,"<="&D$59) -> 818.1 | E22: =SUMIFS('Monthly P&L'!$Q$22:$AZ$22,'Monthly P&L'!$Q$6:$AZ$6,">="&E$58,'Monthly P&L'!$Q$6:$AZ$6,"<="&E$59) -> 904.7 | G22: =SUMIFS('Monthly P&L'!$Q$22:$AZ$22,'Monthly P&L'!$Q$6:$AZ$6,">="&G$58,'Monthly P&L'!$Q$6:$AZ$6,"<="&G$59) -> 818.1 | H22: =SUMIFS('Monthly P&L'!$Q$22:$AZ$22,'Monthly P&L'!$Q$6:$AZ$6,">="&H$58,'Monthly P&L'!$Q$6:$AZ$6,"<="&H$59) -> 904.7 | J22: =SUMIFS('Monthly P&L'!$Q$22:$AZ$22,'Monthly P&L'!$Q$6:$AZ$6,">="&J$58,'Monthly P&L'!$Q$6:$AZ$6,"<="&J$59) -> 818.1 | K22: =SUMIFS('Monthly P&L'!$Q$22:$AZ$22,'Monthly P&L'!$Q$6:$AZ$6,">="&K$58,'Monthly P&L'!$Q$6:$AZ$6,"<="&K$59) -> 904.7 | L22: =SUMIFS('Monthly P&L'!$Q$22:$AZ$22,'Monthly P&L'!$Q$6:$AZ$6,">="&L$58,'Monthly P&L'!$Q$6:$AZ$6,"<="&L$59) -> 904.7 | N22: =L22-K22 -> 0 | O22: =IFERROR(L22/K22-1,"n.a.") -> 0 | Q22: Accounts: Technician Wages, Office Wages and 2 more (Databook)
B23: Owner / Officer Compensation | C23: =SUMIFS('Monthly P&L'!$Q$23:$AZ$23,'Monthly P&L'!$Q$6:$AZ$6,">="&C$58,'Monthly P&L'!$Q$6:$AZ$6,"<="&C$59) -> 180 | D23: =SUMIFS('Monthly P&L'!$Q$23:$AZ$23,'Monthly P&L'!$Q$6:$AZ$6,">="&D$58,'Monthly P&L'!$Q$6:$AZ$6,"<="&D$59) -> 190 | E23: =SUMIFS('Monthly P&L'!$Q$23:$AZ$23,'Monthly P&L'!$Q$6:$AZ$6,">="&E$58,'Monthly P&L'!$Q$6:$AZ$6,"<="&E$59) -> 200 | G23: =SUMIFS('Monthly P&L'!$Q$23:$AZ$23,'Monthly P&L'!$Q$6:$AZ$6,">="&G$58,'Monthly P&L'!$Q$6:$AZ$6,"<="&G$59) -> 190 | H23: =SUMIFS('Monthly P&L'!$Q$23:$AZ$23,'Monthly P&L'!$Q$6:$AZ$6,">="&H$58,'Monthly P&L'!$Q$6:$AZ$6,"<="&H$59) -> 200 | J23: =SUMIFS('Monthly P&L'!$Q$23:$AZ$23,'Monthly P&L'!$Q$6:$AZ$6,">="&J$58,'Monthly P&L'!$Q$6:$AZ$6,"<="&J$59) -> 190 | K23: =SUMIFS('Monthly P&L'!$Q$23:$AZ$23,'Monthly P&L'!$Q$6:$AZ$6,">="&K$58,'Monthly P&L'!$Q$6:$AZ$6,"<="&K$59) -> 200 | L23: =SUMIFS('Monthly P&L'!$Q$23:$AZ$23,'Monthly P&L'!$Q$6:$AZ$6,">="&L$58,'Monthly P&L'!$Q$6:$AZ$6,"<="&L$59) -> 200 | N23: =L23-K23 -> 0 | O23: =IFERROR(L23/K23-1,"n.a.") -> 0 | Q23: Account: Officer Compensation
B24: Rent and Occupancy | C24: =SUMIFS('Monthly P&L'!$Q$24:$AZ$24,'Monthly P&L'!$Q$6:$AZ$6,">="&C$58,'Monthly P&L'!$Q$6:$AZ$6,"<="&C$59) -> 72 | D24: =SUMIFS('Monthly P&L'!$Q$24:$AZ$24,'Monthly P&L'!$Q$6:$AZ$6,">="&D$58,'Monthly P&L'!$Q$6:$AZ$6,"<="&D$59) -> 74.16 | E24: =SUMIFS('Monthly P&L'!$Q$24:$AZ$24,'Monthly P&L'!$Q$6:$AZ$6,">="&E$58,'Monthly P&L'!$Q$6:$AZ$6,"<="&E$59) -> 76.385 | G24: =SUMIFS('Monthly P&L'!$Q$24:$AZ$24,'Monthly P&L'!$Q$6:$AZ$6,">="&G$58,'Monthly P&L'!$Q$6:$AZ$6,"<="&G$59) -> 74.16 | H24: =SUMIFS('Monthly P&L'!$Q$24:$AZ$24,'Monthly P&L'!$Q$6:$AZ$6,">="&H$58,'Monthly P&L'!$Q$6:$AZ$6,"<="&H$59) -> 76.385 | J24: =SUMIFS('Monthly P&L'!$Q$24:$AZ$24,'Monthly P&L'!$Q$6:$AZ$6,">="&J$58,'Monthly P&L'!$Q$6:$AZ$6,"<="&J$59) -> 74.16 | K24: =SUMIFS('Monthly P&L'!$Q$24:$AZ$24,'Monthly P&L'!$Q$6:$AZ$6,">="&K$58,'Monthly P&L'!$Q$6:$AZ$6,"<="&K$59) -> 76.385 | L24: =SUMIFS('Monthly P&L'!$Q$24:$AZ$24,'Monthly P&L'!$Q$6:$AZ$6,">="&L$58,'Monthly P&L'!$Q$6:$AZ$6,"<="&L$59) -> 76.385 | N24: =L24-K24 -> 0 | O24: =IFERROR(L24/K24-1,"n.a.") -> 0 | Q24: Account: Rent - Shop & Office
B25: Advertising and Marketing | C25: =SUMIFS('Monthly P&L'!$Q$25:$AZ$25,'Monthly P&L'!$Q$6:$AZ$6,">="&C$58,'Monthly P&L'!$Q$6:$AZ$6,"<="&C$59) -> 64.8 | D25: =SUMIFS('Monthly P&L'!$Q$25:$AZ$25,'Monthly P&L'!$Q$6:$AZ$6,">="&D$58,'Monthly P&L'!$Q$6:$AZ$6,"<="&D$59) -> 71.2 | E25: =SUMIFS('Monthly P&L'!$Q$25:$AZ$25,'Monthly P&L'!$Q$6:$AZ$6,">="&E$58,'Monthly P&L'!$Q$6:$AZ$6,"<="&E$59) -> 79.6 | G25: =SUMIFS('Monthly P&L'!$Q$25:$AZ$25,'Monthly P&L'!$Q$6:$AZ$6,">="&G$58,'Monthly P&L'!$Q$6:$AZ$6,"<="&G$59) -> 71.2 | H25: =SUMIFS('Monthly P&L'!$Q$25:$AZ$25,'Monthly P&L'!$Q$6:$AZ$6,">="&H$58,'Monthly P&L'!$Q$6:$AZ$6,"<="&H$59) -> 79.6 | J25: =SUMIFS('Monthly P&L'!$Q$25:$AZ$25,'Monthly P&L'!$Q$6:$AZ$6,">="&J$58,'Monthly P&L'!$Q$6:$AZ$6,"<="&J$59) -> 71.2 | K25: =SUMIFS('Monthly P&L'!$Q$25:$AZ$25,'Monthly P&L'!$Q$6:$AZ$6,">="&K$58,'Monthly P&L'!$Q$6:$AZ$6,"<="&K$59) -> 79.6 | L25: =SUMIFS('Monthly P&L'!$Q$25:$AZ$25,'Monthly P&L'!$Q$6:$AZ$6,">="&L$58,'Monthly P&L'!$Q$6:$AZ$6,"<="&L$59) -> 79.6 | N25: =L25-K25 -> 0 | O25: =IFERROR(L25/K25-1,"n.a.") -> 0 | Q25: Account: Advertising & Marketing
B26: Other Operating Expenses | C26: =SUMIFS('Monthly P&L'!$Q$26:$AZ$26,'Monthly P&L'!$Q$6:$AZ$6,">="&C$58,'Monthly P&L'!$Q$6:$AZ$6,"<="&C$59) -> 263.6 | D26: =SUMIFS('Monthly P&L'!$Q$26:$AZ$26,'Monthly P&L'!$Q$6:$AZ$6,">="&D$58,'Monthly P&L'!$Q$6:$AZ$6,"<="&D$59) -> 305 | E26: =SUMIFS('Monthly P&L'!$Q$26:$AZ$26,'Monthly P&L'!$Q$6:$AZ$6,">="&E$58,'Monthly P&L'!$Q$6:$AZ$6,"<="&E$59) -> 304.8 | G26: =SUMIFS('Monthly P&L'!$Q$26:$AZ$26,'Monthly P&L'!$Q$6:$AZ$6,">="&G$58,'Monthly P&L'!$Q$6:$AZ$6,"<="&G$59) -> 305 | H26: =SUMIFS('Monthly P&L'!$Q$26:$AZ$26,'Monthly P&L'!$Q$6:$AZ$6,">="&H$58,'Monthly P&L'!$Q$6:$AZ$6,"<="&H$59) -> 304.8 | J26: =SUMIFS('Monthly P&L'!$Q$26:$AZ$26,'Monthly P&L'!$Q$6:$AZ$6,">="&J$58,'Monthly P&L'!$Q$6:$AZ$6,"<="&J$59) -> 305 | K26: =SUMIFS('Monthly P&L'!$Q$26:$AZ$26,'Monthly P&L'!$Q$6:$AZ$6,">="&K$58,'Monthly P&L'!$Q$6:$AZ$6,"<="&K$59) -> 304.8 | L26: =SUMIFS('Monthly P&L'!$Q$26:$AZ$26,'Monthly P&L'!$Q$6:$AZ$6,">="&L$58,'Monthly P&L'!$Q$6:$AZ$6,"<="&L$59) -> 304.8 | N26: =L26-K26 -> 0 | O26: =IFERROR(L26/K26-1,"n.a.") -> 0 | Q26: Accounts: Charitable Contributions, Fuel and 8 more (Databook)
B28: Total Operating Expenses | C28: =SUM(C22:C26) -> 1311 | D28: =SUM(D22:D26) -> 1458.46 | E28: =SUM(E22:E26) -> 1565.485 | G28: =SUM(G22:G26) -> 1458.46 | H28: =SUM(H22:H26) -> 1565.485 | J28: =SUM(J22:J26) -> 1458.46 | K28: =SUM(K22:K26) -> 1565.485 | L28: =SUM(L22:L26) -> 1565.485 | N28: =L28-K28 -> 0 | O28: =IFERROR(L28/K28-1,"n.a.") -> 0 | Q28: Sum of the operating expense lines
B29: Other Income | C29: =SUMIFS('Monthly P&L'!$Q$29:$AZ$29,'Monthly P&L'!$Q$6:$AZ$6,">="&C$58,'Monthly P&L'!$Q$6:$AZ$6,"<="&C$59) -> 1.2 | D29: =SUMIFS('Monthly P&L'!$Q$29:$AZ$29,'Monthly P&L'!$Q$6:$AZ$6,">="&D$58,'Monthly P&L'!$Q$6:$AZ$6,"<="&D$59) -> 2.4 | E29: =SUMIFS('Monthly P&L'!$Q$29:$AZ$29,'Monthly P&L'!$Q$6:$AZ$6,">="&E$58,'Monthly P&L'!$Q$6:$AZ$6,"<="&E$59) -> 3.1 | G29: =SUMIFS('Monthly P&L'!$Q$29:$AZ$29,'Monthly P&L'!$Q$6:$AZ$6,">="&G$58,'Monthly P&L'!$Q$6:$AZ$6,"<="&G$59) -> 2.4 | H29: =SUMIFS('Monthly P&L'!$Q$29:$AZ$29,'Monthly P&L'!$Q$6:$AZ$6,">="&H$58,'Monthly P&L'!$Q$6:$AZ$6,"<="&H$59) -> 3.1 | J29: =SUMIFS('Monthly P&L'!$Q$29:$AZ$29,'Monthly P&L'!$Q$6:$AZ$6,">="&J$58,'Monthly P&L'!$Q$6:$AZ$6,"<="&J$59) -> 2.4 | K29: =SUMIFS('Monthly P&L'!$Q$29:$AZ$29,'Monthly P&L'!$Q$6:$AZ$6,">="&K$58,'Monthly P&L'!$Q$6:$AZ$6,"<="&K$59) -> 3.1 | L29: =SUMIFS('Monthly P&L'!$Q$29:$AZ$29,'Monthly P&L'!$Q$6:$AZ$6,">="&L$58,'Monthly P&L'!$Q$6:$AZ$6,"<="&L$59) -> 3.1 | N29: =L29-K29 -> 0 | O29: =IFERROR(L29/K29-1,"n.a.") -> 0 | Q29: Account: Interest Income
B30: Other Expense (non-operating) | C30: =SUMIFS('Monthly P&L'!$Q$30:$AZ$30,'Monthly P&L'!$Q$6:$AZ$6,">="&C$58,'Monthly P&L'!$Q$6:$AZ$6,"<="&C$59) -> 0 | D30: =SUMIFS('Monthly P&L'!$Q$30:$AZ$30,'Monthly P&L'!$Q$6:$AZ$6,">="&D$58,'Monthly P&L'!$Q$6:$AZ$6,"<="&D$59) -> 0 | E30: =SUMIFS('Monthly P&L'!$Q$30:$AZ$30,'Monthly P&L'!$Q$6:$AZ$6,">="&E$58,'Monthly P&L'!$Q$6:$AZ$6,"<="&E$59) -> 0 | G30: =SUMIFS('Monthly P&L'!$Q$30:$AZ$30,'Monthly P&L'!$Q$6:$AZ$6,">="&G$58,'Monthly P&L'!$Q$6:$AZ$6,"<="&G$59) -> 0 | H30: =SUMIFS('Monthly P&L'!$Q$30:$AZ$30,'Monthly P&L'!$Q$6:$AZ$6,">="&H$58,'Monthly P&L'!$Q$6:$AZ$6,"<="&H$59) -> 0 | J30: =SUMIFS('Monthly P&L'!$Q$30:$AZ$30,'Monthly P&L'!$Q$6:$AZ$6,">="&J$58,'Monthly P&L'!$Q$6:$AZ$6,"<="&J$59) -> 0 | K30: =SUMIFS('Monthly P&L'!$Q$30:$AZ$30,'Monthly P&L'!$Q$6:$AZ$6,">="&K$58,'Monthly P&L'!$Q$6:$AZ$6,"<="&K$59) -> 0 | L30: =SUMIFS('Monthly P&L'!$Q$30:$AZ$30,'Monthly P&L'!$Q$6:$AZ$6,">="&L$58,'Monthly P&L'!$Q$6:$AZ$6,"<="&L$59) -> 0 | N30: =L30-K30 -> 0 | O30: =IFERROR(L30/K30-1,"n.a.") -> n.a.
B32: Reported EBITDA | C32: =C18-C28+C29-C30 -> 158.2 | D32: =D18-D28+D29-D30 -> 214.64 | E32: =E18-E28+E29-E30 -> 319.515 | G32: =G18-G28+G29-G30 -> 214.64 | H32: =H18-H28+H29-H30 -> 319.515 | J32: =J18-J28+J29-J30 -> 214.64 | K32: =K18-K28+K29-K30 -> 319.515 | L32: =L18-L28+L29-L30 -> 319.515 | N32: =L32-K32 -> 0 | O32: =IFERROR(L32/K32-1,"n.a.") -> 0 | Q32: Gross profit less opex, plus other income less other expense
B33: % Margin | C33: =IFERROR(C32/C14,"n.m.") -> 0.06573043 | D33: =IFERROR(D32/D14,"n.m.") -> 0.078952402 | E33: =IFERROR(E32/E14,"n.m.") -> 0.10507597 | G33: =IFERROR(G32/G14,"n.m.") -> 0.078952402 | H33: =IFERROR(H32/H14,"n.m.") -> 0.10507597 | J33: =IFERROR(J32/J14,"n.m.") -> 0.078952402 | K33: =IFERROR(K32/K14,"n.m.") -> 0.10507597 | L33: =IFERROR(L32/L14,"n.m.") -> 0.10507597 | Q33: Of total revenue
B35: Depreciation and Amortization | C35: =SUMIFS('Monthly P&L'!$Q$35:$AZ$35,'Monthly P&L'!$Q$6:$AZ$6,">="&C$58,'Monthly P&L'!$Q$6:$AZ$6,"<="&C$59) -> 61.2 | D35: =SUMIFS('Monthly P&L'!$Q$35:$AZ$35,'Monthly P&L'!$Q$6:$AZ$6,">="&D$58,'Monthly P&L'!$Q$6:$AZ$6,"<="&D$59) -> 66.8 | E35: =SUMIFS('Monthly P&L'!$Q$35:$AZ$35,'Monthly P&L'!$Q$6:$AZ$6,">="&E$58,'Monthly P&L'!$Q$6:$AZ$6,"<="&E$59) -> 72.4 | G35: =SUMIFS('Monthly P&L'!$Q$35:$AZ$35,'Monthly P&L'!$Q$6:$AZ$6,">="&G$58,'Monthly P&L'!$Q$6:$AZ$6,"<="&G$59) -> 66.8 | H35: =SUMIFS('Monthly P&L'!$Q$35:$AZ$35,'Monthly P&L'!$Q$6:$AZ$6,">="&H$58,'Monthly P&L'!$Q$6:$AZ$6,"<="&H$59) -> 72.4 | J35: =SUMIFS('Monthly P&L'!$Q$35:$AZ$35,'Monthly P&L'!$Q$6:$AZ$6,">="&J$58,'Monthly P&L'!$Q$6:$AZ$6,"<="&J$59) -> 66.8 | K35: =SUMIFS('Monthly P&L'!$Q$35:$AZ$35,'Monthly P&L'!$Q$6:$AZ$6,">="&K$58,'Monthly P&L'!$Q$6:$AZ$6,"<="&K$59) -> 72.4 | L35: =SUMIFS('Monthly P&L'!$Q$35:$AZ$35,'Monthly P&L'!$Q$6:$AZ$6,">="&L$58,'Monthly P&L'!$Q$6:$AZ$6,"<="&L$59) -> 72.4 | N35: =L35-K35 -> 0 | O35: =IFERROR(L35/K35-1,"n.a.") -> 0 | Q35: Account: Depreciation Expense
B37: EBIT | C37: =C32-C35 -> 97 | D37: =D32-D35 -> 147.84 | E37: =E32-E35 -> 247.115 | G37: =G32-G35 -> 147.84 | H37: =H32-H35 -> 247.115 | J37: =J32-J35 -> 147.84 | K37: =K32-K35 -> 247.115 | L37: =L32-L35 -> 247.115 | N37: =L37-K37 -> 0 | O37: =IFERROR(L37/K37-1,"n.a.") -> 0 | Q37: Reported EBITDA less depreciation and amortization
B38: Interest Expense | C38: =SUMIFS('Monthly P&L'!$Q$38:$AZ$38,'Monthly P&L'!$Q$6:$AZ$6,">="&C$58,'Monthly P&L'!$Q$6:$AZ$6,"<="&C$59) -> 22.4 | D38: =SUMIFS('Monthly P&L'!$Q$38:$AZ$38,'Monthly P&L'!$Q$6:$AZ$6,">="&D$58,'Monthly P&L'!$Q$6:$AZ$6,"<="&D$59) -> 18.6 | E38: =SUMIFS('Monthly P&L'!$Q$38:$AZ$38,'Monthly P&L'!$Q$6:$AZ$6,">="&E$58,'Monthly P&L'!$Q$6:$AZ$6,"<="&E$59) -> 14.3 | G38: =SUMIFS('Monthly P&L'!$Q$38:$AZ$38,'Monthly P&L'!$Q$6:$AZ$6,">="&G$58,'Monthly P&L'!$Q$6:$AZ$6,"<="&G$59) -> 18.6 | H38: =SUMIFS('Monthly P&L'!$Q$38:$AZ$38,'Monthly P&L'!$Q$6:$AZ$6,">="&H$58,'Monthly P&L'!$Q$6:$AZ$6,"<="&H$59) -> 14.3 | J38: =SUMIFS('Monthly P&L'!$Q$38:$AZ$38,'Monthly P&L'!$Q$6:$AZ$6,">="&J$58,'Monthly P&L'!$Q$6:$AZ$6,"<="&J$59) -> 18.6 | K38: =SUMIFS('Monthly P&L'!$Q$38:$AZ$38,'Monthly P&L'!$Q$6:$AZ$6,">="&K$58,'Monthly P&L'!$Q$6:$AZ$6,"<="&K$59) -> 14.3 | L38: =SUMIFS('Monthly P&L'!$Q$38:$AZ$38,'Monthly P&L'!$Q$6:$AZ$6,">="&L$58,'Monthly P&L'!$Q$6:$AZ$6,"<="&L$59) -> 14.3 | N38: =L38-K38 -> 0 | O38: =IFERROR(L38/K38-1,"n.a.") -> 0 | Q38: Account: Interest Expense
B40: Pre-Tax Income | C40: =C37-C38 -> 74.6 | D40: =D37-D38 -> 129.24 | E40: =E37-E38 -> 232.815 | G40: =G37-G38 -> 129.24 | H40: =H37-H38 -> 232.815 | J40: =J37-J38 -> 129.24 | K40: =K37-K38 -> 232.815 | L40: =L37-L38 -> 232.815 | N40: =L40-K40 -> 0 | O40: =IFERROR(L40/K40-1,"n.a.") -> 0 | Q40: EBIT less interest expense
B41: Income Taxes | C41: =SUMIFS('Monthly P&L'!$Q$41:$AZ$41,'Monthly P&L'!$Q$6:$AZ$6,">="&C$58,'Monthly P&L'!$Q$6:$AZ$6,"<="&C$59) -> 0 | D41: =SUMIFS('Monthly P&L'!$Q$41:$AZ$41,'Monthly P&L'!$Q$6:$AZ$6,">="&D$58,'Monthly P&L'!$Q$6:$AZ$6,"<="&D$59) -> 0 | E41: =SUMIFS('Monthly P&L'!$Q$41:$AZ$41,'Monthly P&L'!$Q$6:$AZ$6,">="&E$58,'Monthly P&L'!$Q$6:$AZ$6,"<="&E$59) -> 0 | G41: =SUMIFS('Monthly P&L'!$Q$41:$AZ$41,'Monthly P&L'!$Q$6:$AZ$6,">="&G$58,'Monthly P&L'!$Q$6:$AZ$6,"<="&G$59) -> 0 | H41: =SUMIFS('Monthly P&L'!$Q$41:$AZ$41,'Monthly P&L'!$Q$6:$AZ$6,">="&H$58,'Monthly P&L'!$Q$6:$AZ$6,"<="&H$59) -> 0 | J41: =SUMIFS('Monthly P&L'!$Q$41:$AZ$41,'Monthly P&L'!$Q$6:$AZ$6,">="&J$58,'Monthly P&L'!$Q$6:$AZ$6,"<="&J$59) -> 0 | K41: =SUMIFS('Monthly P&L'!$Q$41:$AZ$41,'Monthly P&L'!$Q$6:$AZ$6,">="&K$58,'Monthly P&L'!$Q$6:$AZ$6,"<="&K$59) -> 0 | L41: =SUMIFS('Monthly P&L'!$Q$41:$AZ$41,'Monthly P&L'!$Q$6:$AZ$6,">="&L$58,'Monthly P&L'!$Q$6:$AZ$6,"<="&L$59) -> 0 | N41: =L41-K41 -> 0 | O41: =IFERROR(L41/K41-1,"n.a.") -> n.a.
B43: Net Income | C43: =C40-C41 -> 74.6 | D43: =D40-D41 -> 129.24 | E43: =E40-E41 -> 232.815 | G43: =G40-G41 -> 129.24 | H43: =H40-H41 -> 232.815 | J43: =J40-J41 -> 129.24 | K43: =K40-K41 -> 232.815 | L43: =L40-L41 -> 232.815 | N43: =L43-K43 -> 0 | O43: =IFERROR(L43/K43-1,"n.a.") -> 0 | Q43: Pre-tax income less income taxes (C04 ties it to the grid)
B44: % Margin | C44: =IFERROR(C43/C14,"n.m.") -> 0.030995513 | D44: =IFERROR(D43/D14,"n.m.") -> 0.047539175 | E44: =IFERROR(E43/E14,"n.m.") -> 0.076563733 | G44: =IFERROR(G43/G14,"n.m.") -> 0.047539175 | H44: =IFERROR(H43/H14,"n.m.") -> 0.076563733 | J44: =IFERROR(J43/J14,"n.m.") -> 0.047539175 | K44: =IFERROR(K43/K14,"n.m.") -> 0.076563733 | L44: =IFERROR(L43/L14,"n.m.") -> 0.076563733 | Q44: Of total revenue
B46: Key Performance Indicators
B47: Customers, active at period end (#) | C47: =COUNTIFS('Raw - Customers'!$E:$E,"<="&C$59,'Raw - Customers'!$F:$F,"")+COUNTIFS('Raw - Customers'!$E:$E,"<="&C$59,'Raw - Customers'!$F:$F,">"&C$59)+COUNTIFS('Raw - Customers'!$E:$E,"",'Raw - Customers'!$I:$I,">0",'Raw - Customers'!$A:$A,"<>Residual") -> 44 | D47: =COUNTIFS('Raw - Customers'!$E:$E,"<="&D$59,'Raw - Customers'!$F:$F,"")+COUNTIFS('Raw - Customers'!$E:$E,"<="&D$59,'Raw - Customers'!$F:$F,">"&D$59)+COUNTIFS('Raw - Customers'!$E:$E,"",'Raw - Customers'!$J:$J,">0",'Raw - Customers'!$A:$A,"<>Residual") -> 49 | E47: =COUNTIFS('Raw - Customers'!$E:$E,"<="&E$59,'Raw - Customers'!$F:$F,"")+COUNTIFS('Raw - Customers'!$E:$E,"<="&E$59,'Raw - Customers'!$F:$F,">"&E$59)+COUNTIFS('Raw - Customers'!$E:$E,"",'Raw - Customers'!$K:$K,">0",'Raw - Customers'!$A:$A,"<>Residual") -> 52 | G47: =COUNTIFS('Raw - Customers'!$E:$E,"<="&G$59,'Raw - Customers'!$F:$F,"")+COUNTIFS('Raw - Customers'!$E:$E,"<="&G$59,'Raw - Customers'!$F:$F,">"&G$59)+COUNTIFS('Raw - Customers'!$E:$E,"",'Raw - Customers'!$J:$J,">0",'Raw - Customers'!$A:$A,"<>Residual") -> 49 | H47: =COUNTIFS('Raw - Customers'!$E:$E,"<="&H$59,'Raw - Customers'!$F:$F,"")+COUNTIFS('Raw - Customers'!$E:$E,"<="&H$59,'Raw - Customers'!$F:$F,">"&H$59)+COUNTIFS('Raw - Customers'!$E:$E,"",'Raw - Customers'!$K:$K,">0",'Raw - Customers'!$A:$A,"<>Residual") -> 52 | J47: =COUNTIFS('Raw - Customers'!$E:$E,"<="&J$59,'Raw - Customers'!$F:$F,"")+COUNTIFS('Raw - Customers'!$E:$E,"<="&J$59,'Raw - Customers'!$F:$F,">"&J$59)+COUNTIFS('Raw - Customers'!$E:$E,"",'Raw - Customers'!$J:$J,">0",'Raw - Customers'!$A:$A,"<>Residual") -> 49 | K47: =COUNTIFS('Raw - Customers'!$E:$E,"<="&K$59,'Raw - Customers'!$F:$F,"")+COUNTIFS('Raw - Customers'!$E:$E,"<="&K$59,'Raw - Customers'!$F:$F,">"&K$59)+COUNTIFS('Raw - Customers'!$E:$E,"",'Raw - Customers'!$K:$K,">0",'Raw - Customers'!$A:$A,"<>Residual") -> 52 | L47: =COUNTIFS('Raw - Customers'!$E:$E,"<="&L$59,'Raw - Customers'!$F:$F,"")+COUNTIFS('Raw - Customers'!$E:$E,"<="&L$59,'Raw - Customers'!$F:$F,">"&L$59)+COUNTIFS('Raw - Customers'!$E:$E,"",'Raw - Customers'!$K:$K,">0",'Raw - Customers'!$A:$A,"<>Residual") -> 52
B48: Revenue per listed customer ($) | C48: =IFERROR((SUMIFS('Raw - Customers'!$I:$I,'Raw - Customers'!$A:$A,"<>Residual")*C61+SUMIFS('Raw - Customers'!$J:$J,'Raw - Customers'!$A:$A,"<>Residual")*C62+SUMIFS('Raw - Customers'!$K:$K,'Raw - Customers'!$A:$A,"<>Residual")*C63)/C47,"n.a.") -> 13595.455 | D48: =IFERROR((SUMIFS('Raw - Customers'!$I:$I,'Raw - Customers'!$A:$A,"<>Residual")*D61+SUMIFS('Raw - Customers'!$J:$J,'Raw - Customers'!$A:$A,"<>Residual")*D62+SUMIFS('Raw - Customers'!$K:$K,'Raw - Customers'!$A:$A,"<>Residual")*D63)/D47,"n.a.") -> 14336.735 | E48: =IFERROR((SUMIFS('Raw - Customers'!$I:$I,'Raw - Customers'!$A:$A,"<>Residual")*E61+SUMIFS('Raw - Customers'!$J:$J,'Raw - Customers'!$A:$A,"<>Residual")*E62+SUMIFS('Raw - Customers'!$K:$K,'Raw - Customers'!$A:$A,"<>Residual")*E63)/E47,"n.a.") -> 15609.615 | G48: =IFERROR((SUMIFS('Raw - Customers'!$I:$I,'Raw - Customers'!$A:$A,"<>Residual")*G61+SUMIFS('Raw - Customers'!$J:$J,'Raw - Customers'!$A:$A,"<>Residual")*G62+SUMIFS('Raw - Customers'!$K:$K,'Raw - Customers'!$A:$A,"<>Residual")*G63)/G47,"n.a.") -> 14336.735 | H48: =IFERROR((SUMIFS('Raw - Customers'!$I:$I,'Raw - Customers'!$A:$A,"<>Residual")*H61+SUMIFS('Raw - Customers'!$J:$J,'Raw - Customers'!$A:$A,"<>Residual")*H62+SUMIFS('Raw - Customers'!$K:$K,'Raw - Customers'!$A:$A,"<>Residual")*H63)/H47,"n.a.") -> 15609.615 | J48: =IFERROR((SUMIFS('Raw - Customers'!$I:$I,'Raw - Customers'!$A:$A,"<>Residual")*J61+SUMIFS('Raw - Customers'!$J:$J,'Raw - Customers'!$A:$A,"<>Residual")*J62+SUMIFS('Raw - Customers'!$K:$K,'Raw - Customers'!$A:$A,"<>Residual")*J63)/J47,"n.a.") -> 14336.735 | K48: =IFERROR((SUMIFS('Raw - Customers'!$I:$I,'Raw - Customers'!$A:$A,"<>Residual")*K61+SUMIFS('Raw - Customers'!$J:$J,'Raw - Customers'!$A:$A,"<>Residual")*K62+SUMIFS('Raw - Customers'!$K:$K,'Raw - Customers'!$A:$A,"<>Residual")*K63)/K47,"n.a.") -> 15609.615 | L48: =IFERROR((SUMIFS('Raw - Customers'!$I:$I,'Raw - Customers'!$A:$A,"<>Residual")*L61+SUMIFS('Raw - Customers'!$J:$J,'Raw - Customers'!$A:$A,"<>Residual")*L62+SUMIFS('Raw - Customers'!$K:$K,'Raw - Customers'!$A:$A,"<>Residual")*L63)/L47,"n.a.") -> 15609.615
B49: Employees, non-owner FTE at period end (#) | C49: =SUMIFS('Raw - Payroll'!$Q:$Q,'Raw - Payroll'!$D:$D,"<="&C$59,'Raw - Payroll'!$O:$O,"No",'Raw - Payroll'!$E:$E,"")+SUMIFS('Raw - Payroll'!$Q:$Q,'Raw - Payroll'!$D:$D,"<="&C$59,'Raw - Payroll'!$O:$O,"No",'Raw - Payroll'!$E:$E,">"&C$59) -> 21 | D49: =SUMIFS('Raw - Payroll'!$Q:$Q,'Raw - Payroll'!$D:$D,"<="&D$59,'Raw - Payroll'!$O:$O,"No",'Raw - Payroll'!$E:$E,"")+SUMIFS('Raw - Payroll'!$Q:$Q,'Raw - Payroll'!$D:$D,"<="&D$59,'Raw - Payroll'!$O:$O,"No",'Raw - Payroll'!$E:$E,">"&D$59) -> 23 | E49: =SUMIFS('Raw - Payroll'!$Q:$Q,'Raw - Payroll'!$D:$D,"<="&E$59,'Raw - Payroll'!$O:$O,"No",'Raw - Payroll'!$E:$E,"")+SUMIFS('Raw - Payroll'!$Q:$Q,'Raw - Payroll'!$D:$D,"<="&E$59,'Raw - Payroll'!$O:$O,"No",'Raw - Payroll'!$E:$E,">"&E$59) -> 23 | G49: =SUMIFS('Raw - Payroll'!$Q:$Q,'Raw - Payroll'!$D:$D,"<="&G$59,'Raw - Payroll'!$O:$O,"No",'Raw - Payroll'!$E:$E,"")+SUMIFS('Raw - Payroll'!$Q:$Q,'Raw - Payroll'!$D:$D,"<="&G$59,'Raw - Payroll'!$O:$O,"No",'Raw - Payroll'!$E:$E,">"&G$59) -> 23 | H49: =SUMIFS('Raw - Payroll'!$Q:$Q,'Raw - Payroll'!$D:$D,"<="&H$59,'Raw - Payroll'!$O:$O,"No",'Raw - Payroll'!$E:$E,"")+SUMIFS('Raw - Payroll'!$Q:$Q,'Raw - Payroll'!$D:$D,"<="&H$59,'Raw - Payroll'!$O:$O,"No",'Raw - Payroll'!$E:$E,">"&H$59) -> 23 | J49: =SUMIFS('Raw - Payroll'!$Q:$Q,'Raw - Payroll'!$D:$D,"<="&J$59,'Raw - Payroll'!$O:$O,"No",'Raw - Payroll'!$E:$E,"")+SUMIFS('Raw - Payroll'!$Q:$Q,'Raw - Payroll'!$D:$D,"<="&J$59,'Raw - Payroll'!$O:$O,"No",'Raw - Payroll'!$E:$E,">"&J$59) -> 23 | K49: =SUMIFS('Raw - Payroll'!$Q:$Q,'Raw - Payroll'!$D:$D,"<="&K$59,'Raw - Payroll'!$O:$O,"No",'Raw - Payroll'!$E:$E,"")+SUMIFS('Raw - Payroll'!$Q:$Q,'Raw - Payroll'!$D:$D,"<="&K$59,'Raw - Payroll'!$O:$O,"No",'Raw - Payroll'!$E:$E,">"&K$59) -> 23 | L49: =SUMIFS('Raw - Payroll'!$Q:$Q,'Raw - Payroll'!$D:$D,"<="&L$59,'Raw - Payroll'!$O:$O,"No",'Raw - Payroll'!$E:$E,"")+SUMIFS('Raw - Payroll'!$Q:$Q,'Raw - Payroll'!$D:$D,"<="&L$59,'Raw - Payroll'!$O:$O,"No",'Raw - Payroll'!$E:$E,">"&L$59) -> 23
B50: Revenue per employee ($) | C50: =IFERROR(C14*1000/C49,"n.a.") -> 114609.52 | D50: =IFERROR(D14*1000/D49,"n.a.") -> 118200 | E50: =IFERROR(E14*1000/E49,"n.a.") -> 132208.7 | G50: =IFERROR(G14*1000/G49,"n.a.") -> 118200 | H50: =IFERROR(H14*1000/H49,"n.a.") -> 132208.7 | J50: =IFERROR(J14*1000/J49,"n.a.") -> 118200 | K50: =IFERROR(K14*1000/K49,"n.a.") -> 132208.7 | L50: =IFERROR(L14*1000/L49,"n.a.") -> 132208.7
B51: Labor cost, % of revenue (excludes owner) | C51: =IFERROR((C22-'Adjustments'!N44)/C14,"n.a.") -> 0.29832807 | D51: =IFERROR((D22-'Adjustments'!O44)/D14,"n.a.") -> 0.29605312 | E51: =IFERROR((E22-'Adjustments'!P44)/E14,"n.a.") -> 0.29296238 | G51: =IFERROR((G22-'Adjustments'!R44)/G14,"n.a.") -> 0.29605312 | H51: =IFERROR((H22-'Adjustments'!S44)/H14,"n.a.") -> 0.29296238 | J51: =IFERROR((J22-'Adjustments'!U44)/J14,"n.a.") -> 0.29605312 | K51: =IFERROR((K22-'Adjustments'!V44)/K14,"n.a.") -> 0.29296238 | L51: =IFERROR((L22-'Adjustments'!W44)/L14,"n.a.") -> 0.29296238
B52: Recurring revenue, % of total | C52: =IFERROR((C11)/C14,"n.a.") -> 0.089164035 | D52: =IFERROR((D11)/D14,"n.a.") -> 0.091333775 | E52: =IFERROR((E11)/E14,"n.a.") -> 0.095172323 | G52: =IFERROR((G11)/G14,"n.a.") -> 0.091333775 | H52: =IFERROR((H11)/H14,"n.a.") -> 0.095172323 | J52: =IFERROR((J11)/J14,"n.a.") -> 0.091333775 | K52: =IFERROR((K11)/K14,"n.a.") -> 0.095172323 | L52: =IFERROR((L11)/L14,"n.a.") -> 0.095172323
B54: Check: Net Income less Monthly P&L | C54: =ROUND(C43-'Monthly P&L'!C43,6) -> 0 | D54: =ROUND(D43-'Monthly P&L'!D43,6) -> 0 | E54: =ROUND(E43-'Monthly P&L'!E43,6) -> 0 | G54: =ROUND(G43-'Monthly P&L'!G43,6) -> 0 | H54: =ROUND(H43-'Monthly P&L'!H43,6) -> 0 | J54: =ROUND(J43-'Monthly P&L'!J43,6) -> 0 | K54: =ROUND(K43-'Monthly P&L'!K43,6) -> 0 | L54: =ROUND(L43-'Monthly P&L'!L43,6) -> 0
B55: Check: every line less its grid months | C55: =ROUND(SUM(C65:C86),6) -> 0 | D55: =ROUND(SUM(D65:D86),6) -> 0 | E55: =ROUND(SUM(E65:E86),6) -> 0 | G55: =ROUND(SUM(G65:G86),6) -> 0 | H55: =ROUND(SUM(H65:H86),6) -> 0 | J55: =ROUND(SUM(J65:J86),6) -> 0 | K55: =ROUND(SUM(K65:K86),6) -> 0 | L55: =ROUND(SUM(L65:L86),6) -> 0
B56: Note: every period column is a SUMIFS over the Monthly P&L grid for the window in the helper rows below. Margins divide by total revenue.
B58: Period start | C58: =EOMONTH(EOMONTH(DATE('Assumptions'!$C$15-2,'Assumptions'!$C$14,1),0),-12)+1 -> 44927 | D58: =EOMONTH(EOMONTH(DATE('Assumptions'!$C$15-1,'Assumptions'!$C$14,1),0),-12)+1 -> 45292 | E58: =EOMONTH(EOMONTH(DATE('Assumptions'!$C$15-0,'Assumptions'!$C$14,1),0),-12)+1 -> 45658 | G58: =EOMONTH(EOMONTH(DATE(YEAR('Assumptions'!$C$9)-IF(MONTH('Assumptions'!$C$9)>'Assumptions'!$C$14,0,1),'Assumptions'!$C$14,1),0)+1,-13)+1 -> 45292 | H58: =EOMONTH(DATE(YEAR('Assumptions'!$C$9)-IF(MONTH('Assumptions'!$C$9)>'Assumptions'!$C$14,0,1),'Assumptions'!$C$14,1),0)+1 -> 45658 | J58: =EOMONTH('Assumptions'!$C$9,-24)+1 -> 45292 | K58: =EOMONTH('Assumptions'!$C$9,-12)+1 -> 45658 | L58: =EOMONTH('Assumptions'!$C$9,-12)+1 -> 45658
B59: Period end | C59: =EOMONTH(DATE('Assumptions'!$C$15-2,'Assumptions'!$C$14,1),0) -> 45291 | D59: =EOMONTH(DATE('Assumptions'!$C$15-1,'Assumptions'!$C$14,1),0) -> 45657 | E59: =EOMONTH(DATE('Assumptions'!$C$15-0,'Assumptions'!$C$14,1),0) -> 46022 | G59: =EOMONTH('Assumptions'!$C$9,-12) -> 45657 | H59: =EOMONTH('Assumptions'!$C$9,0) -> 46022 | J59: =EOMONTH('Assumptions'!$C$9,-12) -> 45657 | K59: =EOMONTH('Assumptions'!$C$9,0) -> 46022 | L59: =EOMONTH('Assumptions'!$C$9,0) -> 46022
B61: Share of FY2023 in the window (listed customers) | C61: =MAX(0,(YEAR(MIN(C$59,EOMONTH(DATE('Assumptions'!$C$15-2,'Assumptions'!$C$14,1),0)))-YEAR(MAX(C$58,EOMONTH(EOMONTH(DATE('Assumptions'!$C$15-2,'Assumptions'!$C$14,1),0),-12)+1)))*12+MONTH(MIN(C$59,EOMONTH(DATE('Assumptions'!$C$15-2,'Assumptions'!$C$14,1),0)))-MONTH(MAX(C$58,EOMONTH(EOMONTH(DATE('Assumptions'!$C$15-2,'Assumptions'!$C$14,1),0),-12)+1))+1)/12 -> 1 | D61: =MAX(0,(YEAR(MIN(D$59,EOMONTH(DATE('Assumptions'!$C$15-2,'Assumptions'!$C$14,1),0)))-YEAR(MAX(D$58,EOMONTH(EOMONTH(DATE('Assumptions'!$C$15-2,'Assumptions'!$C$14,1),0),-12)+1)))*12+MONTH(MIN(D$59,EOMONTH(DATE('Assumptions'!$C$15-2,'Assumptions'!$C$14,1),0)))-MONTH(MAX(D$58,EOMONTH(EOMONTH(DATE('Assumptions'!$C$15-2,'Assumptions'!$C$14,1),0),-12)+1))+1)/12 -> 0 | E61: =MAX(0,(YEAR(MIN(E$59,EOMONTH(DATE('Assumptions'!$C$15-2,'Assumptions'!$C$14,1),0)))-YEAR(MAX(E$58,EOMONTH(EOMONTH(DATE('Assumptions'!$C$15-2,'Assumptions'!$C$14,1),0),-12)+1)))*12+MONTH(MIN(E$59,EOMONTH(DATE('Assumptions'!$C$15-2,'Assumptions'!$C$14,1),0)))-MONTH(MAX(E$58,EOMONTH(EOMONTH(DATE('Assumptions'!$C$15-2,'Assumptions'!$C$14,1),0),-12)+1))+1)/12 -> 0 | G61: =MAX(0,(YEAR(MIN(G$59,EOMONTH(DATE('Assumptions'!$C$15-2,'Assumptions'!$C$14,1),0)))-YEAR(MAX(G$58,EOMONTH(EOMONTH(DATE('Assumptions'!$C$15-2,'Assumptions'!$C$14,1),0),-12)+1)))*12+MONTH(MIN(G$59,EOMONTH(DATE('Assumptions'!$C$15-2,'Assumptions'!$C$14,1),0)))-MONTH(MAX(G$58,EOMONTH(EOMONTH(DATE('Assumptions'!$C$15-2,'Assumptions'!$C$14,1),0),-12)+1))+1)/12 -> 0 | H61: =MAX(0,(YEAR(MIN(H$59,EOMONTH(DATE('Assumptions'!$C$15-2,'Assumptions'!$C$14,1),0)))-YEAR(MAX(H$58,EOMONTH(EOMONTH(DATE('Assumptions'!$C$15-2,'Assumptions'!$C$14,1),0),-12)+1)))*12+MONTH(MIN(H$59,EOMONTH(DATE('Assumptions'!$C$15-2,'Assumptions'!$C$14,1),0)))-MONTH(MAX(H$58,EOMONTH(EOMONTH(DATE('Assumptions'!$C$15-2,'Assumptions'!$C$14,1),0),-12)+1))+1)/12 -> 0 | J61: =MAX(0,(YEAR(MIN(J$59,EOMONTH(DATE('Assumptions'!$C$15-2,'Assumptions'!$C$14,1),0)))-YEAR(MAX(J$58,EOMONTH(EOMONTH(DATE('Assumptions'!$C$15-2,'Assumptions'!$C$14,1),0),-12)+1)))*12+MONTH(MIN(J$59,EOMONTH(DATE('Assumptions'!$C$15-2,'Assumptions'!$C$14,1),0)))-MONTH(MAX(J$58,EOMONTH(EOMONTH(DATE('Assumptions'!$C$15-2,'Assumptions'!$C$14,1),0),-12)+1))+1)/12 -> 0 | K61: =MAX(0,(YEAR(MIN(K$59,EOMONTH(DATE('Assumptions'!$C$15-2,'Assumptions'!$C$14,1),0)))-YEAR(MAX(K$58,EOMONTH(EOMONTH(DATE('Assumptions'!$C$15-2,'Assumptions'!$C$14,1),0),-12)+1)))*12+MONTH(MIN(K$59,EOMONTH(DATE('Assumptions'!$C$15-2,'Assumptions'!$C$14,1),0)))-MONTH(MAX(K$58,EOMONTH(EOMONTH(DATE('Assumptions'!$C$15-2,'Assumptions'!$C$14,1),0),-12)+1))+1)/12 -> 0 | L61: =MAX(0,(YEAR(MIN(L$59,EOMONTH(DATE('Assumptions'!$C$15-2,'Assumptions'!$C$14,1),0)))-YEAR(MAX(L$58,EOMONTH(EOMONTH(DATE('Assumptions'!$C$15-2,'Assumptions'!$C$14,1),0),-12)+1)))*12+MONTH(MIN(L$59,EOMONTH(DATE('Assumptions'!$C$15-2,'Assumptions'!$C$14,1),0)))-MONTH(MAX(L$58,EOMONTH(EOMONTH(DATE('Assumptions'!$C$15-2,'Assumptions'!$C$14,1),0),-12)+1))+1)/12 -> 0
B62: Share of FY2024 in the window (listed customers) | C62: =MAX(0,(YEAR(MIN(C$59,EOMONTH(DATE('Assumptions'!$C$15-1,'Assumptions'!$C$14,1),0)))-YEAR(MAX(C$58,EOMONTH(EOMONTH(DATE('Assumptions'!$C$15-1,'Assumptions'!$C$14,1),0),-12)+1)))*12+MONTH(MIN(C$59,EOMONTH(DATE('Assumptions'!$C$15-1,'Assumptions'!$C$14,1),0)))-MONTH(MAX(C$58,EOMONTH(EOMONTH(DATE('Assumptions'!$C$15-1,'Assumptions'!$C$14,1),0),-12)+1))+1)/12 -> 0 | D62: =MAX(0,(YEAR(MIN(D$59,EOMONTH(DATE('Assumptions'!$C$15-1,'Assumptions'!$C$14,1),0)))-YEAR(MAX(D$58,EOMONTH(EOMONTH(DATE('Assumptions'!$C$15-1,'Assumptions'!$C$14,1),0),-12)+1)))*12+MONTH(MIN(D$59,EOMONTH(DATE('Assumptions'!$C$15-1,'Assumptions'!$C$14,1),0)))-MONTH(MAX(D$58,EOMONTH(EOMONTH(DATE('Assumptions'!$C$15-1,'Assumptions'!$C$14,1),0),-12)+1))+1)/12 -> 1 | E62: =MAX(0,(YEAR(MIN(E$59,EOMONTH(DATE('Assumptions'!$C$15-1,'Assumptions'!$C$14,1),0)))-YEAR(MAX(E$58,EOMONTH(EOMONTH(DATE('Assumptions'!$C$15-1,'Assumptions'!$C$14,1),0),-12)+1)))*12+MONTH(MIN(E$59,EOMONTH(DATE('Assumptions'!$C$15-1,'Assumptions'!$C$14,1),0)))-MONTH(MAX(E$58,EOMONTH(EOMONTH(DATE('Assumptions'!$C$15-1,'Assumptions'!$C$14,1),0),-12)+1))+1)/12 -> 0 | G62: =MAX(0,(YEAR(MIN(G$59,EOMONTH(DATE('Assumptions'!$C$15-1,'Assumptions'!$C$14,1),0)))-YEAR(MAX(G$58,EOMONTH(EOMONTH(DATE('Assumptions'!$C$15-1,'Assumptions'!$C$14,1),0),-12)+1)))*12+MONTH(MIN(G$59,EOMONTH(DATE('Assumptions'!$C$15-1,'Assumptions'!$C$14,1),0)))-MONTH(MAX(G$58,EOMONTH(EOMONTH(DATE('Assumptions'!$C$15-1,'Assumptions'!$C$14,1),0),-12)+1))+1)/12 -> 1 | H62: =MAX(0,(YEAR(MIN(H$59,EOMONTH(DATE('Assumptions'!$C$15-1,'Assumptions'!$C$14,1),0)))-YEAR(MAX(H$58,EOMONTH(EOMONTH(DATE('Assumptions'!$C$15-1,'Assumptions'!$C$14,1),0),-12)+1)))*12+MONTH(MIN(H$59,EOMONTH(DATE('Assumptions'!$C$15-1,'Assumptions'!$C$14,1),0)))-MONTH(MAX(H$58,EOMONTH(EOMONTH(DATE('Assumptions'!$C$15-1,'Assumptions'!$C$14,1),0),-12)+1))+1)/12 -> 0 | J62: =MAX(0,(YEAR(MIN(J$59,EOMONTH(DATE('Assumptions'!$C$15-1,'Assumptions'!$C$14,1),0)))-YEAR(MAX(J$58,EOMONTH(EOMONTH(DATE('Assumptions'!$C$15-1,'Assumptions'!$C$14,1),0),-12)+1)))*12+MONTH(MIN(J$59,EOMONTH(DATE('Assumptions'!$C$15-1,'Assumptions'!$C$14,1),0)))-MONTH(MAX(J$58,EOMONTH(EOMONTH(DATE('Assumptions'!$C$15-1,'Assumptions'!$C$14,1),0),-12)+1))+1)/12 -> 1 | K62: =MAX(0,(YEAR(MIN(K$59,EOMONTH(DATE('Assumptions'!$C$15-1,'Assumptions'!$C$14,1),0)))-YEAR(MAX(K$58,EOMONTH(EOMONTH(DATE('Assumptions'!$C$15-1,'Assumptions'!$C$14,1),0),-12)+1)))*12+MONTH(MIN(K$59,EOMONTH(DATE('Assumptions'!$C$15-1,'Assumptions'!$C$14,1),0)))-MONTH(MAX(K$58,EOMONTH(EOMONTH(DATE('Assumptions'!$C$15-1,'Assumptions'!$C$14,1),0),-12)+1))+1)/12 -> 0 | L62: =MAX(0,(YEAR(MIN(L$59,EOMONTH(DATE('Assumptions'!$C$15-1,'Assumptions'!$C$14,1),0)))-YEAR(MAX(L$58,EOMONTH(EOMONTH(DATE('Assumptions'!$C$15-1,'Assumptions'!$C$14,1),0),-12)+1)))*12+MONTH(MIN(L$59,EOMONTH(DATE('Assumptions'!$C$15-1,'Assumptions'!$C$14,1),0)))-MONTH(MAX(L$58,EOMONTH(EOMONTH(DATE('Assumptions'!$C$15-1,'Assumptions'!$C$14,1),0),-12)+1))+1)/12 -> 0
B63: Share of FY2025 in the window (listed customers) | C63: =MAX(0,(YEAR(MIN(C$59,EOMONTH(DATE('Assumptions'!$C$15-0,'Assumptions'!$C$14,1),0)))-YEAR(MAX(C$58,EOMONTH(EOMONTH(DATE('Assumptions'!$C$15-0,'Assumptions'!$C$14,1),0),-12)+1)))*12+MONTH(MIN(C$59,EOMONTH(DATE('Assumptions'!$C$15-0,'Assumptions'!$C$14,1),0)))-MONTH(MAX(C$58,EOMONTH(EOMONTH(DATE('Assumptions'!$C$15-0,'Assumptions'!$C$14,1),0),-12)+1))+1)/12 -> 0 | D63: =MAX(0,(YEAR(MIN(D$59,EOMONTH(DATE('Assumptions'!$C$15-0,'Assumptions'!$C$14,1),0)))-YEAR(MAX(D$58,EOMONTH(EOMONTH(DATE('Assumptions'!$C$15-0,'Assumptions'!$C$14,1),0),-12)+1)))*12+MONTH(MIN(D$59,EOMONTH(DATE('Assumptions'!$C$15-0,'Assumptions'!$C$14,1),0)))-MONTH(MAX(D$58,EOMONTH(EOMONTH(DATE('Assumptions'!$C$15-0,'Assumptions'!$C$14,1),0),-12)+1))+1)/12 -> 0 | E63: =MAX(0,(YEAR(MIN(E$59,EOMONTH(DATE('Assumptions'!$C$15-0,'Assumptions'!$C$14,1),0)))-YEAR(MAX(E$58,EOMONTH(EOMONTH(DATE('Assumptions'!$C$15-0,'Assumptions'!$C$14,1),0),-12)+1)))*12+MONTH(MIN(E$59,EOMONTH(DATE('Assumptions'!$C$15-0,'Assumptions'!$C$14,1),0)))-MONTH(MAX(E$58,EOMONTH(EOMONTH(DATE('Assumptions'!$C$15-0,'Assumptions'!$C$14,1),0),-12)+1))+1)/12 -> 1 | G63: =MAX(0,(YEAR(MIN(G$59,EOMONTH(DATE('Assumptions'!$C$15-0,'Assumptions'!$C$14,1),0)))-YEAR(MAX(G$58,EOMONTH(EOMONTH(DATE('Assumptions'!$C$15-0,'Assumptions'!$C$14,1),0),-12)+1)))*12+MONTH(MIN(G$59,EOMONTH(DATE('Assumptions'!$C$15-0,'Assumptions'!$C$14,1),0)))-MONTH(MAX(G$58,EOMONTH(EOMONTH(DATE('Assumptions'!$C$15-0,'Assumptions'!$C$14,1),0),-12)+1))+1)/12 -> 0 | H63: =MAX(0,(YEAR(MIN(H$59,EOMONTH(DATE('Assumptions'!$C$15-0,'Assumptions'!$C$14,1),0)))-YEAR(MAX(H$58,EOMONTH(EOMONTH(DATE('Assumptions'!$C$15-0,'Assumptions'!$C$14,1),0),-12)+1)))*12+MONTH(MIN(H$59,EOMONTH(DATE('Assumptions'!$C$15-0,'Assumptions'!$C$14,1),0)))-MONTH(MAX(H$58,EOMONTH(EOMONTH(DATE('Assumptions'!$C$15-0,'Assumptions'!$C$14,1),0),-12)+1))+1)/12 -> 1 | J63: =MAX(0,(YEAR(MIN(J$59,EOMONTH(DATE('Assumptions'!$C$15-0,'Assumptions'!$C$14,1),0)))-YEAR(MAX(J$58,EOMONTH(EOMONTH(DATE('Assumptions'!$C$15-0,'Assumptions'!$C$14,1),0),-12)+1)))*12+MONTH(MIN(J$59,EOMONTH(DATE('Assumptions'!$C$15-0,'Assumptions'!$C$14,1),0)))-MONTH(MAX(J$58,EOMONTH(EOMONTH(DATE('Assumptions'!$C$15-0,'Assumptions'!$C$14,1),0),-12)+1))+1)/12 -> 0 | K63: =MAX(0,(YEAR(MIN(K$59,EOMONTH(DATE('Assumptions'!$C$15-0,'Assumptions'!$C$14,1),0)))-YEAR(MAX(K$58,EOMONTH(EOMONTH(DATE('Assumptions'!$C$15-0,'Assumptions'!$C$14,1),0),-12)+1)))*12+MONTH(MIN(K$59,EOMONTH(DATE('Assumptions'!$C$15-0,'Assumptions'!$C$14,1),0)))-MONTH(MAX(K$58,EOMONTH(EOMONTH(DATE('Assumptions'!$C$15-0,'Assumptions'!$C$14,1),0),-12)+1))+1)/12 -> 1 | L63: =MAX(0,(YEAR(MIN(L$59,EOMONTH(DATE('Assumptions'!$C$15-0,'Assumptions'!$C$14,1),0)))-YEAR(MAX(L$58,EOMONTH(EOMONTH(DATE('Assumptions'!$C$15-0,'Assumptions'!$C$14,1),0),-12)+1)))*12+MONTH(MIN(L$59,EOMONTH(DATE('Assumptions'!$C$15-0,'Assumptions'!$C$14,1),0)))-MONTH(MAX(L$58,EOMONTH(EOMONTH(DATE('Assumptions'!$C$15-0,'Assumptions'!$C$14,1),0),-12)+1))+1)/12 -> 1
B64: C03 helper: each line less the grid's months to its window end, less those before its start
B65: C03: Residential service and replacement | C65: =ABS(C9-(SUMIF('Monthly P&L'!$Q$6:$AZ$6,"<="&C$59,'Monthly P&L'!$Q$9:$AZ$9)-SUMIF('Monthly P&L'!$Q$6:$AZ$6,"<"&C$58,'Monthly P&L'!$Q$9:$AZ$9))) -> 0 | D65: =ABS(D9-(SUMIF('Monthly P&L'!$Q$6:$AZ$6,"<="&D$59,'Monthly P&L'!$Q$9:$AZ$9)-SUMIF('Monthly P&L'!$Q$6:$AZ$6,"<"&D$58,'Monthly P&L'!$Q$9:$AZ$9))) -> 0 | E65: =ABS(E9-(SUMIF('Monthly P&L'!$Q$6:$AZ$6,"<="&E$59,'Monthly P&L'!$Q$9:$AZ$9)-SUMIF('Monthly P&L'!$Q$6:$AZ$6,"<"&E$58,'Monthly P&L'!$Q$9:$AZ$9))) -> 0 | G65: =ABS(G9-(SUMIF('Monthly P&L'!$Q$6:$AZ$6,"<="&G$59,'Monthly P&L'!$Q$9:$AZ$9)-SUMIF('Monthly P&L'!$Q$6:$AZ$6,"<"&G$58,'Monthly P&L'!$Q$9:$AZ$9))) -> 0 | H65: =ABS(H9-(SUMIF('Monthly P&L'!$Q$6:$AZ$6,"<="&H$59,'Monthly P&L'!$Q$9:$AZ$9)-SUMIF('Monthly P&L'!$Q$6:$AZ$6,"<"&H$58,'Monthly P&L'!$Q$9:$AZ$9))) -> 0 | J65: =ABS(J9-(SUMIF('Monthly P&L'!$Q$6:$AZ$6,"<="&J$59,'Monthly P&L'!$Q$9:$AZ$9)-SUMIF('Monthly P&L'!$Q$6:$AZ$6,"<"&J$58,'Monthly P&L'!$Q$9:$AZ$9))) -> 0 | K65: =ABS(K9-(SUMIF('Monthly P&L'!$Q$6:$AZ$6,"<="&K$59,'Monthly P&L'!$Q$9:$AZ$9)-SUMIF('Monthly P&L'!$Q$6:$AZ$6,"<"&K$58,'Monthly P&L'!$Q$9:$AZ$9))) -> 0 | L65: =ABS(L9-(SUMIF('Monthly P&L'!$Q$6:$AZ$6,"<="&L$59,'Monthly P&L'!$Q$9:$AZ$9)-SUMIF('Monthly P&L'!$Q$6:$AZ$6,"<"&L$58,'Monthly P&L'!$Q$9:$AZ$9))) -> 0
B66: C03: Commercial service | C66: =ABS(C10-(SUMIF('Monthly P&L'!$Q$6:$AZ$6,"<="&C$59,'Monthly P&L'!$Q$10:$AZ$10)-SUMIF('Monthly P&L'!$Q$6:$AZ$6,"<"&C$58,'Monthly P&L'!$Q$10:$AZ$10))) -> 0 | D66: =ABS(D10-(SUMIF('Monthly P&L'!$Q$6:$AZ$6,"<="&D$59,'Monthly P&L'!$Q$10:$AZ$10)-SUMIF('Monthly P&L'!$Q$6:$AZ$6,"<"&D$58,'Monthly P&L'!$Q$10:$AZ$10))) -> 0 | E66: =ABS(E10-(SUMIF('Monthly P&L'!$Q$6:$AZ$6,"<="&E$59,'Monthly P&L'!$Q$10:$AZ$10)-SUMIF('Monthly P&L'!$Q$6:$AZ$6,"<"&E$58,'Monthly P&L'!$Q$10:$AZ$10))) -> 0 | G66: =ABS(G10-(SUMIF('Monthly P&L'!$Q$6:$AZ$6,"<="&G$59,'Monthly P&L'!$Q$10:$AZ$10)-SUMIF('Monthly P&L'!$Q$6:$AZ$6,"<"&G$58,'Monthly P&L'!$Q$10:$AZ$10))) -> 0 | H66: =ABS(H10-(SUMIF('Monthly P&L'!$Q$6:$AZ$6,"<="&H$59,'Monthly P&L'!$Q$10:$AZ$10)-SUMIF('Monthly P&L'!$Q$6:$AZ$6,"<"&H$58,'Monthly P&L'!$Q$10:$AZ$10))) -> 0 | J66: =ABS(J10-(SUMIF('Monthly P&L'!$Q$6:$AZ$6,"<="&J$59,'Monthly P&L'!$Q$10:$AZ$10)-SUMIF('Monthly P&L'!$Q$6:$AZ$6,"<"&J$58,'Monthly P&L'!$Q$10:$AZ$10))) -> 0 | K66: =ABS(K10-(SUMIF('Monthly P&L'!$Q$6:$AZ$6,"<="&K$59,'Monthly P&L'!$Q$10:$AZ$10)-SUMIF('Monthly P&L'!$Q$6:$AZ$6,"<"&K$58,'Monthly P&L'!$Q$10:$AZ$10))) -> 0 | L66: =ABS(L10-(SUMIF('Monthly P&L'!$Q$6:$AZ$6,"<="&L$59,'Monthly P&L'!$Q$10:$AZ$10)-SUMIF('Monthly P&L'!$Q$6:$AZ$6,"<"&L$58,'Monthly P&L'!$Q$10:$AZ$10))) -> 0
B67: C03: Maintenance agreements | C67: =ABS(C11-(SUMIF('Monthly P&L'!$Q$6:$AZ$6,"<="&C$59,'Monthly P&L'!$Q$11:$AZ$11)-SUMIF('Monthly P&L'!$Q$6:$AZ$6,"<"&C$58,'Monthly P&L'!$Q$11:$AZ$11))) -> 0 | D67: =ABS(D11-(SUMIF('Monthly P&L'!$Q$6:$AZ$6,"<="&D$59,'Monthly P&L'!$Q$11:$AZ$11)-SUMIF('Monthly P&L'!$Q$6:$AZ$6,"<"&D$58,'Monthly P&L'!$Q$11:$AZ$11))) -> 0 | E67: =ABS(E11-(SUMIF('Monthly P&L'!$Q$6:$AZ$6,"<="&E$59,'Monthly P&L'!$Q$11:$AZ$11)-SUMIF('Monthly P&L'!$Q$6:$AZ$6,"<"&E$58,'Monthly P&L'!$Q$11:$AZ$11))) -> 0 | G67: =ABS(G11-(SUMIF('Monthly P&L'!$Q$6:$AZ$6,"<="&G$59,'Monthly P&L'!$Q$11:$AZ$11)-SUMIF('Monthly P&L'!$Q$6:$AZ$6,"<"&G$58,'Monthly P&L'!$Q$11:$AZ$11))) -> 0 | H67: =ABS(H11-(SUMIF('Monthly P&L'!$Q$6:$AZ$6,"<="&H$59,'Monthly P&L'!$Q$11:$AZ$11)-SUMIF('Monthly P&L'!$Q$6:$AZ$6,"<"&H$58,'Monthly P&L'!$Q$11:$AZ$11))) -> 0 | J67: =ABS(J11-(SUMIF('Monthly P&L'!$Q$6:$AZ$6,"<="&J$59,'Monthly P&L'!$Q$11:$AZ$11)-SUMIF('Monthly P&L'!$Q$6:$AZ$6,"<"&J$58,'Monthly P&L'!$Q$11:$AZ$11))) -> 0 | K67: =ABS(K11-(SUMIF('Monthly P&L'!$Q$6:$AZ$6,"<="&K$59,'Monthly P&L'!$Q$11:$AZ$11)-SUMIF('Monthly P&L'!$Q$6:$AZ$6,"<"&K$58,'Monthly P&L'!$Q$11:$AZ$11))) -> 0 | L67: =ABS(L11-(SUMIF('Monthly P&L'!$Q$6:$AZ$6,"<="&L$59,'Monthly P&L'!$Q$11:$AZ$11)-SUMIF('Monthly P&L'!$Q$6:$AZ$6,"<"&L$58,'Monthly P&L'!$Q$11:$AZ$11))) -> 0
B68: C03: Less: discounts and refunds | C68: =ABS(C12-(SUMIF('Monthly P&L'!$Q$6:$AZ$6,"<="&C$59,'Monthly P&L'!$Q$12:$AZ$12)-SUMIF('Monthly P&L'!$Q$6:$AZ$6,"<"&C$58,'Monthly P&L'!$Q$12:$AZ$12))) -> 0 | D68: =ABS(D12-(SUMIF('Monthly P&L'!$Q$6:$AZ$6,"<="&D$59,'Monthly P&L'!$Q$12:$AZ$12)-SUMIF('Monthly P&L'!$Q$6:$AZ$6,"<"&D$58,'Monthly P&L'!$Q$12:$AZ$12))) -> 0 | E68: =ABS(E12-(SUMIF('Monthly P&L'!$Q$6:$AZ$6,"<="&E$59,'Monthly P&L'!$Q$12:$AZ$12)-SUMIF('Monthly P&L'!$Q$6:$AZ$6,"<"&E$58,'Monthly P&L'!$Q$12:$AZ$12))) -> 0 | G68: =ABS(G12-(SUMIF('Monthly P&L'!$Q$6:$AZ$6,"<="&G$59,'Monthly P&L'!$Q$12:$AZ$12)-SUMIF('Monthly P&L'!$Q$6:$AZ$6,"<"&G$58,'Monthly P&L'!$Q$12:$AZ$12))) -> 0 | H68: =ABS(H12-(SUMIF('Monthly P&L'!$Q$6:$AZ$6,"<="&H$59,'Monthly P&L'!$Q$12:$AZ$12)-SUMIF('Monthly P&L'!$Q$6:$AZ$6,"<"&H$58,'Monthly P&L'!$Q$12:$AZ$12))) -> 0 | J68: =ABS(J12-(SUMIF('Monthly P&L'!$Q$6:$AZ$6,"<="&J$59,'Monthly P&L'!$Q$12:$AZ$12)-SUMIF('Monthly P&L'!$Q$6:$AZ$6,"<"&J$58,'Monthly P&L'!$Q$12:$AZ$12))) -> 0 | K68: =ABS(K12-(SUMIF('Monthly P&L'!$Q$6:$AZ$6,"<="&K$59,'Monthly P&L'!$Q$12:$AZ$12)-SUMIF('Monthly P&L'!$Q$6:$AZ$6,"<"&K$58,'Monthly P&L'!$Q$12:$AZ$12))) -> 0 | L68: =ABS(L12-(SUMIF('Monthly P&L'!$Q$6:$AZ$6,"<="&L$59,'Monthly P&L'!$Q$12:$AZ$12)-SUMIF('Monthly P&L'!$Q$6:$AZ$6,"<"&L$58,'Monthly P&L'!$Q$12:$AZ$12))) -> 0
B69: C03: Total Revenue | C69: =ABS(C14-(SUMIF('Monthly P&L'!$Q$6:$AZ$6,"<="&C$59,'Monthly P&L'!$Q$14:$AZ$14)-SUMIF('Monthly P&L'!$Q$6:$AZ$6,"<"&C$58,'Monthly P&L'!$Q$14:$AZ$14))) -> 0 | D69: =ABS(D14-(SUMIF('Monthly P&L'!$Q$6:$AZ$6,"<="&D$59,'Monthly P&L'!$Q$14:$AZ$14)-SUMIF('Monthly P&L'!$Q$6:$AZ$6,"<"&D$58,'Monthly P&L'!$Q$14:$AZ$14))) -> 0 | E69: =ABS(E14-(SUMIF('Monthly P&L'!$Q$6:$AZ$6,"<="&E$59,'Monthly P&L'!$Q$14:$AZ$14)-SUMIF('Monthly P&L'!$Q$6:$AZ$6,"<"&E$58,'Monthly P&L'!$Q$14:$AZ$14))) -> 0 | G69: =ABS(G14-(SUMIF('Monthly P&L'!$Q$6:$AZ$6,"<="&G$59,'Monthly P&L'!$Q$14:$AZ$14)-SUMIF('Monthly P&L'!$Q$6:$AZ$6,"<"&G$58,'Monthly P&L'!$Q$14:$AZ$14))) -> 0 | H69: =ABS(H14-(SUMIF('Monthly P&L'!$Q$6:$AZ$6,"<="&H$59,'Monthly P&L'!$Q$14:$AZ$14)-SUMIF('Monthly P&L'!$Q$6:$AZ$6,"<"&H$58,'Monthly P&L'!$Q$14:$AZ$14))) -> 0 | J69: =ABS(J14-(SUMIF('Monthly P&L'!$Q$6:$AZ$6,"<="&J$59,'Monthly P&L'!$Q$14:$AZ$14)-SUMIF('Monthly P&L'!$Q$6:$AZ$6,"<"&J$58,'Monthly P&L'!$Q$14:$AZ$14))) -> 0 | K69: =ABS(K14-(SUMIF('Monthly P&L'!$Q$6:$AZ$6,"<="&K$59,'Monthly P&L'!$Q$14:$AZ$14)-SUMIF('Monthly P&L'!$Q$6:$AZ$6,"<"&K$58,'Monthly P&L'!$Q$14:$AZ$14))) -> 0 | L69: =ABS(L14-(SUMIF('Monthly P&L'!$Q$6:$AZ$6,"<="&L$59,'Monthly P&L'!$Q$14:$AZ$14)-SUMIF('Monthly P&L'!$Q$6:$AZ$6,"<"&L$58,'Monthly P&L'!$Q$14:$AZ$14))) -> 0
B70: C03: Cost of Revenue | C70: =ABS(C16-(SUMIF('Monthly P&L'!$Q$6:$AZ$6,"<="&C$59,'Monthly P&L'!$Q$16:$AZ$16)-SUMIF('Monthly P&L'!$Q$6:$AZ$6,"<"&C$58,'Monthly P&L'!$Q$16:$AZ$16))) -> 0 | D70: =ABS(D16-(SUMIF('Monthly P&L'!$Q$6:$AZ$6,"<="&D$59,'Monthly P&L'!$Q$16:$AZ$16)-SUMIF('Monthly P&L'!$Q$6:$AZ$6,"<"&D$58,'Monthly P&L'!$Q$16:$AZ$16))) -> 0 | E70: =ABS(E16-(SUMIF('Monthly P&L'!$Q$6:$AZ$6,"<="&E$59,'Monthly P&L'!$Q$16:$AZ$16)-SUMIF('Monthly P&L'!$Q$6:$AZ$6,"<"&E$58,'Monthly P&L'!$Q$16:$AZ$16))) -> 0 | G70: =ABS(G16-(SUMIF('Monthly P&L'!$Q$6:$AZ$6,"<="&G$59,'Monthly P&L'!$Q$16:$AZ$16)-SUMIF('Monthly P&L'!$Q$6:$AZ$6,"<"&G$58,'Monthly P&L'!$Q$16:$AZ$16))) -> 0 | H70: =ABS(H16-(SUMIF('Monthly P&L'!$Q$6:$AZ$6,"<="&H$59,'Monthly P&L'!$Q$16:$AZ$16)-SUMIF('Monthly P&L'!$Q$6:$AZ$6,"<"&H$58,'Monthly P&L'!$Q$16:$AZ$16))) -> 0 | J70: =ABS(J16-(SUMIF('Monthly P&L'!$Q$6:$AZ$6,"<="&J$59,'Monthly P&L'!$Q$16:$AZ$16)-SUMIF('Monthly P&L'!$Q$6:$AZ$6,"<"&J$58,'Monthly P&L'!$Q$16:$AZ$16))) -> 0 | K70: =ABS(K16-(SUMIF('Monthly P&L'!$Q$6:$AZ$6,"<="&K$59,'Monthly P&L'!$Q$16:$AZ$16)-SUMIF('Monthly P&L'!$Q$6:$AZ$6,"<"&K$58,'Monthly P&L'!$Q$16:$AZ$16))) -> 0 | L70: =ABS(L16-(SUMIF('Monthly P&L'!$Q$6:$AZ$6,"<="&L$59,'Monthly P&L'!$Q$16:$AZ$16)-SUMIF('Monthly P&L'!$Q$6:$AZ$6,"<"&L$58,'Monthly P&L'!$Q$16:$AZ$16))) -> 0
B71: C03: Gross Profit | C71: =ABS(C18-(SUMIF('Monthly P&L'!$Q$6:$AZ$6,"<="&C$59,'Monthly P&L'!$Q$18:$AZ$18)-SUMIF('Monthly P&L'!$Q$6:$AZ$6,"<"&C$58,'Monthly P&L'!$Q$18:$AZ$18))) -> 0 | D71: =ABS(D18-(SUMIF('Monthly P&L'!$Q$6:$AZ$6,"<="&D$59,'Monthly P&L'!$Q$18:$AZ$18)-SUMIF('Monthly P&L'!$Q$6:$AZ$6,"<"&D$58,'Monthly P&L'!$Q$18:$AZ$18))) -> 0 | E71: =ABS(E18-(SUMIF('Monthly P&L'!$Q$6:$AZ$6,"<="&E$59,'Monthly P&L'!$Q$18:$AZ$18)-SUMIF('Monthly P&L'!$Q$6:$AZ$6,"<"&E$58,'Monthly P&L'!$Q$18:$AZ$18))) -> 0 | G71: =ABS(G18-(SUMIF('Monthly P&L'!$Q$6:$AZ$6,"<="&G$59,'Monthly P&L'!$Q$18:$AZ$18)-SUMIF('Monthly P&L'!$Q$6:$AZ$6,"<"&G$58,'Monthly P&L'!$Q$18:$AZ$18))) -> 0 | H71: =ABS(H18-(SUMIF('Monthly P&L'!$Q$6:$AZ$6,"<="&H$59,'Monthly P&L'!$Q$18:$AZ$18)-SUMIF('Monthly P&L'!$Q$6:$AZ$6,"<"&H$58,'Monthly P&L'!$Q$18:$AZ$18))) -> 0 | J71: =ABS(J18-(SUMIF('Monthly P&L'!$Q$6:$AZ$6,"<="&J$59,'Monthly P&L'!$Q$18:$AZ$18)-SUMIF('Monthly P&L'!$Q$6:$AZ$6,"<"&J$58,'Monthly P&L'!$Q$18:$AZ$18))) -> 0 | K71: =ABS(K18-(SUMIF('Monthly P&L'!$Q$6:$AZ$6,"<="&K$59,'Monthly P&L'!$Q$18:$AZ$18)-SUMIF('Monthly P&L'!$Q$6:$AZ$6,"<"&K$58,'Monthly P&L'!$Q$18:$AZ$18))) -> 0 | L71: =ABS(L18-(SUMIF('Monthly P&L'!$Q$6:$AZ$6,"<="&L$59,'Monthly P&L'!$Q$18:$AZ$18)-SUMIF('Monthly P&L'!$Q$6:$AZ$6,"<"&L$58,'Monthly P&L'!$Q$18:$AZ$18))) -> 0
B72: C03: Salaries, Wages and Benefits | C72: =ABS(C22-(SUMIF('Monthly P&L'!$Q$6:$AZ$6,"<="&C$59,'Monthly P&L'!$Q$22:$AZ$22)-SUMIF('Monthly P&L'!$Q$6:$AZ$6,"<"&C$58,'Monthly P&L'!$Q$22:$AZ$22))) -> 0 | D72: =ABS(D22-(SUMIF('Monthly P&L'!$Q$6:$AZ$6,"<="&D$59,'Monthly P&L'!$Q$22:$AZ$22)-SUMIF('Monthly P&L'!$Q$6:$AZ$6,"<"&D$58,'Monthly P&L'!$Q$22:$AZ$22))) -> 0 | E72: =ABS(E22-(SUMIF('Monthly P&L'!$Q$6:$AZ$6,"<="&E$59,'Monthly P&L'!$Q$22:$AZ$22)-SUMIF('Monthly P&L'!$Q$6:$AZ$6,"<"&E$58,'Monthly P&L'!$Q$22:$AZ$22))) -> 0 | G72: =ABS(G22-(SUMIF('Monthly P&L'!$Q$6:$AZ$6,"<="&G$59,'Monthly P&L'!$Q$22:$AZ$22)-SUMIF('Monthly P&L'!$Q$6:$AZ$6,"<"&G$58,'Monthly P&L'!$Q$22:$AZ$22))) -> 0 | H72: =ABS(H22-(SUMIF('Monthly P&L'!$Q$6:$AZ$6,"<="&H$59,'Monthly P&L'!$Q$22:$AZ$22)-SUMIF('Monthly P&L'!$Q$6:$AZ$6,"<"&H$58,'Monthly P&L'!$Q$22:$AZ$22))) -> 0 | J72: =ABS(J22-(SUMIF('Monthly P&L'!$Q$6:$AZ$6,"<="&J$59,'Monthly P&L'!$Q$22:$AZ$22)-SUMIF('Monthly P&L'!$Q$6:$AZ$6,"<"&J$58,'Monthly P&L'!$Q$22:$AZ$22))) -> 0 | K72: =ABS(K22-(SUMIF('Monthly P&L'!$Q$6:$AZ$6,"<="&K$59,'Monthly P&L'!$Q$22:$AZ$22)-SUMIF('Monthly P&L'!$Q$6:$AZ$6,"<"&K$58,'Monthly P&L'!$Q$22:$AZ$22))) -> 0 | L72: =ABS(L22-(SUMIF('Monthly P&L'!$Q$6:$AZ$6,"<="&L$59,'Monthly P&L'!$Q$22:$AZ$22)-SUMIF('Monthly P&L'!$Q$6:$AZ$6,"<"&L$58,'Monthly P&L'!$Q$22:$AZ$22))) -> 0
B73: C03: Owner / Officer Compensation | C73: =ABS(C23-(SUMIF('Monthly P&L'!$Q$6:$AZ$6,"<="&C$59,'Monthly P&L'!$Q$23:$AZ$23)-SUMIF('Monthly P&L'!$Q$6:$AZ$6,"<"&C$58,'Monthly P&L'!$Q$23:$AZ$23))) -> 0 | D73: =ABS(D23-(SUMIF('Monthly P&L'!$Q$6:$AZ$6,"<="&D$59,'Monthly P&L'!$Q$23:$AZ$23)-SUMIF('Monthly P&L'!$Q$6:$AZ$6,"<"&D$58,'Monthly P&L'!$Q$23:$AZ$23))) -> 0 | E73: =ABS(E23-(SUMIF('Monthly P&L'!$Q$6:$AZ$6,"<="&E$59,'Monthly P&L'!$Q$23:$AZ$23)-SUMIF('Monthly P&L'!$Q$6:$AZ$6,"<"&E$58,'Monthly P&L'!$Q$23:$AZ$23))) -> 0 | G73: =ABS(G23-(SUMIF('Monthly P&L'!$Q$6:$AZ$6,"<="&G$59,'Monthly P&L'!$Q$23:$AZ$23)-SUMIF('Monthly P&L'!$Q$6:$AZ$6,"<"&G$58,'Monthly P&L'!$Q$23:$AZ$23))) -> 0 | H73: =ABS(H23-(SUMIF('Monthly P&L'!$Q$6:$AZ$6,"<="&H$59,'Monthly P&L'!$Q$23:$AZ$23)-SUMIF('Monthly P&L'!$Q$6:$AZ$6,"<"&H$58,'Monthly P&L'!$Q$23:$AZ$23))) -> 0 | J73: =ABS(J23-(SUMIF('Monthly P&L'!$Q$6:$AZ$6,"<="&J$59,'Monthly P&L'!$Q$23:$AZ$23)-SUMIF('Monthly P&L'!$Q$6:$AZ$6,"<"&J$58,'Monthly P&L'!$Q$23:$AZ$23))) -> 0 | K73: =ABS(K23-(SUMIF('Monthly P&L'!$Q$6:$AZ$6,"<="&K$59,'Monthly P&L'!$Q$23:$AZ$23)-SUMIF('Monthly P&L'!$Q$6:$AZ$6,"<"&K$58,'Monthly P&L'!$Q$23:$AZ$23))) -> 0 | L73: =ABS(L23-(SUMIF('Monthly P&L'!$Q$6:$AZ$6,"<="&L$59,'Monthly P&L'!$Q$23:$AZ$23)-SUMIF('Monthly P&L'!$Q$6:$AZ$6,"<"&L$58,'Monthly P&L'!$Q$23:$AZ$23))) -> 0
B74: C03: Rent and Occupancy | C74: =ABS(C24-(SUMIF('Monthly P&L'!$Q$6:$AZ$6,"<="&C$59,'Monthly P&L'!$Q$24:$AZ$24)-SUMIF('Monthly P&L'!$Q$6:$AZ$6,"<"&C$58,'Monthly P&L'!$Q$24:$AZ$24))) -> 0 | D74: =ABS(D24-(SUMIF('Monthly P&L'!$Q$6:$AZ$6,"<="&D$59,'Monthly P&L'!$Q$24:$AZ$24)-SUMIF('Monthly P&L'!$Q$6:$AZ$6,"<"&D$58,'Monthly P&L'!$Q$24:$AZ$24))) -> 0 | E74: =ABS(E24-(SUMIF('Monthly P&L'!$Q$6:$AZ$6,"<="&E$59,'Monthly P&L'!$Q$24:$AZ$24)-SUMIF('Monthly P&L'!$Q$6:$AZ$6,"<"&E$58,'Monthly P&L'!$Q$24:$AZ$24))) -> 0 | G74: =ABS(G24-(SUMIF('Monthly P&L'!$Q$6:$AZ$6,"<="&G$59,'Monthly P&L'!$Q$24:$AZ$24)-SUMIF('Monthly P&L'!$Q$6:$AZ$6,"<"&G$58,'Monthly P&L'!$Q$24:$AZ$24))) -> 0 | H74: =ABS(H24-(SUMIF('Monthly P&L'!$Q$6:$AZ$6,"<="&H$59,'Monthly P&L'!$Q$24:$AZ$24)-SUMIF('Monthly P&L'!$Q$6:$AZ$6,"<"&H$58,'Monthly P&L'!$Q$24:$AZ$24))) -> 0 | J74: =ABS(J24-(SUMIF('Monthly P&L'!$Q$6:$AZ$6,"<="&J$59,'Monthly P&L'!$Q$24:$AZ$24)-SUMIF('Monthly P&L'!$Q$6:$AZ$6,"<"&J$58,'Monthly P&L'!$Q$24:$AZ$24))) -> 0 | K74: =ABS(K24-(SUMIF('Monthly P&L'!$Q$6:$AZ$6,"<="&K$59,'Monthly P&L'!$Q$24:$AZ$24)-SUMIF('Monthly P&L'!$Q$6:$AZ$6,"<"&K$58,'Monthly P&L'!$Q$24:$AZ$24))) -> 0 | L74: =ABS(L24-(SUMIF('Monthly P&L'!$Q$6:$AZ$6,"<="&L$59,'Monthly P&L'!$Q$24:$AZ$24)-SUMIF('Monthly P&L'!$Q$6:$AZ$6,"<"&L$58,'Monthly P&L'!$Q$24:$AZ$24))) -> 0
B75: C03: Advertising and Marketing | C75: =ABS(C25-(SUMIF('Monthly P&L'!$Q$6:$AZ$6,"<="&C$59,'Monthly P&L'!$Q$25:$AZ$25)-SUMIF('Monthly P&L'!$Q$6:$AZ$6,"<"&C$58,'Monthly P&L'!$Q$25:$AZ$25))) -> 0 | D75: =ABS(D25-(SUMIF('Monthly P&L'!$Q$6:$AZ$6,"<="&D$59,'Monthly P&L'!$Q$25:$AZ$25)-SUMIF('Monthly P&L'!$Q$6:$AZ$6,"<"&D$58,'Monthly P&L'!$Q$25:$AZ$25))) -> 0 | E75: =ABS(E25-(SUMIF('Monthly P&L'!$Q$6:$AZ$6,"<="&E$59,'Monthly P&L'!$Q$25:$AZ$25)-SUMIF('Monthly P&L'!$Q$6:$AZ$6,"<"&E$58,'Monthly P&L'!$Q$25:$AZ$25))) -> 0 | G75: =ABS(G25-(SUMIF('Monthly P&L'!$Q$6:$AZ$6,"<="&G$59,'Monthly P&L'!$Q$25:$AZ$25)-SUMIF('Monthly P&L'!$Q$6:$AZ$6,"<"&G$58,'Monthly P&L'!$Q$25:$AZ$25))) -> 0 | H75: =ABS(H25-(SUMIF('Monthly P&L'!$Q$6:$AZ$6,"<="&H$59,'Monthly P&L'!$Q$25:$AZ$25)-SUMIF('Monthly P&L'!$Q$6:$AZ$6,"<"&H$58,'Monthly P&L'!$Q$25:$AZ$25))) -> 0 | J75: =ABS(J25-(SUMIF('Monthly P&L'!$Q$6:$AZ$6,"<="&J$59,'Monthly P&L'!$Q$25:$AZ$25)-SUMIF('Monthly P&L'!$Q$6:$AZ$6,"<"&J$58,'Monthly P&L'!$Q$25:$AZ$25))) -> 0 | K75: =ABS(K25-(SUMIF('Monthly P&L'!$Q$6:$AZ$6,"<="&K$59,'Monthly P&L'!$Q$25:$AZ$25)-SUMIF('Monthly P&L'!$Q$6:$AZ$6,"<"&K$58,'Monthly P&L'!$Q$25:$AZ$25))) -> 0 | L75: =ABS(L25-(SUMIF('Monthly P&L'!$Q$6:$AZ$6,"<="&L$59,'Monthly P&L'!$Q$25:$AZ$25)-SUMIF('Monthly P&L'!$Q$6:$AZ$6,"<"&L$58,'Monthly P&L'!$Q$25:$AZ$25))) -> 0
B76: C03: Other Operating Expenses | C76: =ABS(C26-(SUMIF('Monthly P&L'!$Q$6:$AZ$6,"<="&C$59,'Monthly P&L'!$Q$26:$AZ$26)-SUMIF('Monthly P&L'!$Q$6:$AZ$6,"<"&C$58,'Monthly P&L'!$Q$26:$AZ$26))) -> 0 | D76: =ABS(D26-(SUMIF('Monthly P&L'!$Q$6:$AZ$6,"<="&D$59,'Monthly P&L'!$Q$26:$AZ$26)-SUMIF('Monthly P&L'!$Q$6:$AZ$6,"<"&D$58,'Monthly P&L'!$Q$26:$AZ$26))) -> 0 | E76: =ABS(E26-(SUMIF('Monthly P&L'!$Q$6:$AZ$6,"<="&E$59,'Monthly P&L'!$Q$26:$AZ$26)-SUMIF('Monthly P&L'!$Q$6:$AZ$6,"<"&E$58,'Monthly P&L'!$Q$26:$AZ$26))) -> 0 | G76: =ABS(G26-(SUMIF('Monthly P&L'!$Q$6:$AZ$6,"<="&G$59,'Monthly P&L'!$Q$26:$AZ$26)-SUMIF('Monthly P&L'!$Q$6:$AZ$6,"<"&G$58,'Monthly P&L'!$Q$26:$AZ$26))) -> 0 | H76: =ABS(H26-(SUMIF('Monthly P&L'!$Q$6:$AZ$6,"<="&H$59,'Monthly P&L'!$Q$26:$AZ$26)-SUMIF('Monthly P&L'!$Q$6:$AZ$6,"<"&H$58,'Monthly P&L'!$Q$26:$AZ$26))) -> 0 | J76: =ABS(J26-(SUMIF('Monthly P&L'!$Q$6:$AZ$6,"<="&J$59,'Monthly P&L'!$Q$26:$AZ$26)-SUMIF('Monthly P&L'!$Q$6:$AZ$6,"<"&J$58,'Monthly P&L'!$Q$26:$AZ$26))) -> 0 | K76: =ABS(K26-(SUMIF('Monthly P&L'!$Q$6:$AZ$6,"<="&K$59,'Monthly P&L'!$Q$26:$AZ$26)-SUMIF('Monthly P&L'!$Q$6:$AZ$6,"<"&K$58,'Monthly P&L'!$Q$26:$AZ$26))) -> 0 | L76: =ABS(L26-(SUMIF('Monthly P&L'!$Q$6:$AZ$6,"<="&L$59,'Monthly P&L'!$Q$26:$AZ$26)-SUMIF('Monthly P&L'!$Q$6:$AZ$6,"<"&L$58,'Monthly P&L'!$Q$26:$AZ$26))) -> 0
B77: C03: Total Operating Expenses | C77: =ABS(C28-(SUMIF('Monthly P&L'!$Q$6:$AZ$6,"<="&C$59,'Monthly P&L'!$Q$28:$AZ$28)-SUMIF('Monthly P&L'!$Q$6:$AZ$6,"<"&C$58,'Monthly P&L'!$Q$28:$AZ$28))) -> 0 | D77: =ABS(D28-(SUMIF('Monthly P&L'!$Q$6:$AZ$6,"<="&D$59,'Monthly P&L'!$Q$28:$AZ$28)-SUMIF('Monthly P&L'!$Q$6:$AZ$6,"<"&D$58,'Monthly P&L'!$Q$28:$AZ$28))) -> 0 | E77: =ABS(E28-(SUMIF('Monthly P&L'!$Q$6:$AZ$6,"<="&E$59,'Monthly P&L'!$Q$28:$AZ$28)-SUMIF('Monthly P&L'!$Q$6:$AZ$6,"<"&E$58,'Monthly P&L'!$Q$28:$AZ$28))) -> 0 | G77: =ABS(G28-(SUMIF('Monthly P&L'!$Q$6:$AZ$6,"<="&G$59,'Monthly P&L'!$Q$28:$AZ$28)-SUMIF('Monthly P&L'!$Q$6:$AZ$6,"<"&G$58,'Monthly P&L'!$Q$28:$AZ$28))) -> 0 | H77: =ABS(H28-(SUMIF('Monthly P&L'!$Q$6:$AZ$6,"<="&H$59,'Monthly P&L'!$Q$28:$AZ$28)-SUMIF('Monthly P&L'!$Q$6:$AZ$6,"<"&H$58,'Monthly P&L'!$Q$28:$AZ$28))) -> 0 | J77: =ABS(J28-(SUMIF('Monthly P&L'!$Q$6:$AZ$6,"<="&J$59,'Monthly P&L'!$Q$28:$AZ$28)-SUMIF('Monthly P&L'!$Q$6:$AZ$6,"<"&J$58,'Monthly P&L'!$Q$28:$AZ$28))) -> 0 | K77: =ABS(K28-(SUMIF('Monthly P&L'!$Q$6:$AZ$6,"<="&K$59,'Monthly P&L'!$Q$28:$AZ$28)-SUMIF('Monthly P&L'!$Q$6:$AZ$6,"<"&K$58,'Monthly P&L'!$Q$28:$AZ$28))) -> 0 | L77: =ABS(L28-(SUMIF('Monthly P&L'!$Q$6:$AZ$6,"<="&L$59,'Monthly P&L'!$Q$28:$AZ$28)-SUMIF('Monthly P&L'!$Q$6:$AZ$6,"<"&L$58,'Monthly P&L'!$Q$28:$AZ$28))) -> 0
B78: C03: Other Income | C78: =ABS(C29-(SUMIF('Monthly P&L'!$Q$6:$AZ$6,"<="&C$59,'Monthly P&L'!$Q$29:$AZ$29)-SUMIF('Monthly P&L'!$Q$6:$AZ$6,"<"&C$58,'Monthly P&L'!$Q$29:$AZ$29))) -> 0 | D78: =ABS(D29-(SUMIF('Monthly P&L'!$Q$6:$AZ$6,"<="&D$59,'Monthly P&L'!$Q$29:$AZ$29)-SUMIF('Monthly P&L'!$Q$6:$AZ$6,"<"&D$58,'Monthly P&L'!$Q$29:$AZ$29))) -> 0 | E78: =ABS(E29-(SUMIF('Monthly P&L'!$Q$6:$AZ$6,"<="&E$59,'Monthly P&L'!$Q$29:$AZ$29)-SUMIF('Monthly P&L'!$Q$6:$AZ$6,"<"&E$58,'Monthly P&L'!$Q$29:$AZ$29))) -> 0 | G78: =ABS(G29-(SUMIF('Monthly P&L'!$Q$6:$AZ$6,"<="&G$59,'Monthly P&L'!$Q$29:$AZ$29)-SUMIF('Monthly P&L'!$Q$6:$AZ$6,"<"&G$58,'Monthly P&L'!$Q$29:$AZ$29))) -> 0 | H78: =ABS(H29-(SUMIF('Monthly P&L'!$Q$6:$AZ$6,"<="&H$59,'Monthly P&L'!$Q$29:$AZ$29)-SUMIF('Monthly P&L'!$Q$6:$AZ$6,"<"&H$58,'Monthly P&L'!$Q$29:$AZ$29))) -> 0 | J78: =ABS(J29-(SUMIF('Monthly P&L'!$Q$6:$AZ$6,"<="&J$59,'Monthly P&L'!$Q$29:$AZ$29)-SUMIF('Monthly P&L'!$Q$6:$AZ$6,"<"&J$58,'Monthly P&L'!$Q$29:$AZ$29))) -> 0 | K78: =ABS(K29-(SUMIF('Monthly P&L'!$Q$6:$AZ$6,"<="&K$59,'Monthly P&L'!$Q$29:$AZ$29)-SUMIF('Monthly P&L'!$Q$6:$AZ$6,"<"&K$58,'Monthly P&L'!$Q$29:$AZ$29))) -> 0 | L78: =ABS(L29-(SUMIF('Monthly P&L'!$Q$6:$AZ$6,"<="&L$59,'Monthly P&L'!$Q$29:$AZ$29)-SUMIF('Monthly P&L'!$Q$6:$AZ$6,"<"&L$58,'Monthly P&L'!$Q$29:$AZ$29))) -> 0
B79: C03: Other Expense (non-operating) | C79: =ABS(C30-(SUMIF('Monthly P&L'!$Q$6:$AZ$6,"<="&C$59,'Monthly P&L'!$Q$30:$AZ$30)-SUMIF('Monthly P&L'!$Q$6:$AZ$6,"<"&C$58,'Monthly P&L'!$Q$30:$AZ$30))) -> 0 | D79: =ABS(D30-(SUMIF('Monthly P&L'!$Q$6:$AZ$6,"<="&D$59,'Monthly P&L'!$Q$30:$AZ$30)-SUMIF('Monthly P&L'!$Q$6:$AZ$6,"<"&D$58,'Monthly P&L'!$Q$30:$AZ$30))) -> 0 | E79: =ABS(E30-(SUMIF('Monthly P&L'!$Q$6:$AZ$6,"<="&E$59,'Monthly P&L'!$Q$30:$AZ$30)-SUMIF('Monthly P&L'!$Q$6:$AZ$6,"<"&E$58,'Monthly P&L'!$Q$30:$AZ$30))) -> 0 | G79: =ABS(G30-(SUMIF('Monthly P&L'!$Q$6:$AZ$6,"<="&G$59,'Monthly P&L'!$Q$30:$AZ$30)-SUMIF('Monthly P&L'!$Q$6:$AZ$6,"<"&G$58,'Monthly P&L'!$Q$30:$AZ$30))) -> 0 | H79: =ABS(H30-(SUMIF('Monthly P&L'!$Q$6:$AZ$6,"<="&H$59,'Monthly P&L'!$Q$30:$AZ$30)-SUMIF('Monthly P&L'!$Q$6:$AZ$6,"<"&H$58,'Monthly P&L'!$Q$30:$AZ$30))) -> 0 | J79: =ABS(J30-(SUMIF('Monthly P&L'!$Q$6:$AZ$6,"<="&J$59,'Monthly P&L'!$Q$30:$AZ$30)-SUMIF('Monthly P&L'!$Q$6:$AZ$6,"<"&J$58,'Monthly P&L'!$Q$30:$AZ$30))) -> 0 | K79: =ABS(K30-(SUMIF('Monthly P&L'!$Q$6:$AZ$6,"<="&K$59,'Monthly P&L'!$Q$30:$AZ$30)-SUMIF('Monthly P&L'!$Q$6:$AZ$6,"<"&K$58,'Monthly P&L'!$Q$30:$AZ$30))) -> 0 | L79: =ABS(L30-(SUMIF('Monthly P&L'!$Q$6:$AZ$6,"<="&L$59,'Monthly P&L'!$Q$30:$AZ$30)-SUMIF('Monthly P&L'!$Q$6:$AZ$6,"<"&L$58,'Monthly P&L'!$Q$30:$AZ$30))) -> 0
B80: C03: Reported EBITDA | C80: =ABS(C32-(SUMIF('Monthly P&L'!$Q$6:$AZ$6,"<="&C$59,'Monthly P&L'!$Q$32:$AZ$32)-SUMIF('Monthly P&L'!$Q$6:$AZ$6,"<"&C$58,'Monthly P&L'!$Q$32:$AZ$32))) -> 0 | D80: =ABS(D32-(SUMIF('Monthly P&L'!$Q$6:$AZ$6,"<="&D$59,'Monthly P&L'!$Q$32:$AZ$32)-SUMIF('Monthly P&L'!$Q$6:$AZ$6,"<"&D$58,'Monthly P&L'!$Q$32:$AZ$32))) -> 0 | E80: =ABS(E32-(SUMIF('Monthly P&L'!$Q$6:$AZ$6,"<="&E$59,'Monthly P&L'!$Q$32:$AZ$32)-SUMIF('Monthly P&L'!$Q$6:$AZ$6,"<"&E$58,'Monthly P&L'!$Q$32:$AZ$32))) -> 0 | G80: =ABS(G32-(SUMIF('Monthly P&L'!$Q$6:$AZ$6,"<="&G$59,'Monthly P&L'!$Q$32:$AZ$32)-SUMIF('Monthly P&L'!$Q$6:$AZ$6,"<"&G$58,'Monthly P&L'!$Q$32:$AZ$32))) -> 0 | H80: =ABS(H32-(SUMIF('Monthly P&L'!$Q$6:$AZ$6,"<="&H$59,'Monthly P&L'!$Q$32:$AZ$32)-SUMIF('Monthly P&L'!$Q$6:$AZ$6,"<"&H$58,'Monthly P&L'!$Q$32:$AZ$32))) -> 0 | J80: =ABS(J32-(SUMIF('Monthly P&L'!$Q$6:$AZ$6,"<="&J$59,'Monthly P&L'!$Q$32:$AZ$32)-SUMIF('Monthly P&L'!$Q$6:$AZ$6,"<"&J$58,'Monthly P&L'!$Q$32:$AZ$32))) -> 0 | K80: =ABS(K32-(SUMIF('Monthly P&L'!$Q$6:$AZ$6,"<="&K$59,'Monthly P&L'!$Q$32:$AZ$32)-SUMIF('Monthly P&L'!$Q$6:$AZ$6,"<"&K$58,'Monthly P&L'!$Q$32:$AZ$32))) -> 0 | L80: =ABS(L32-(SUMIF('Monthly P&L'!$Q$6:$AZ$6,"<="&L$59,'Monthly P&L'!$Q$32:$AZ$32)-SUMIF('Monthly P&L'!$Q$6:$AZ$6,"<"&L$58,'Monthly P&L'!$Q$32:$AZ$32))) -> 0
B81: C03: Depreciation and Amortization | C81: =ABS(C35-(SUMIF('Monthly P&L'!$Q$6:$AZ$6,"<="&C$59,'Monthly P&L'!$Q$35:$AZ$35)-SUMIF('Monthly P&L'!$Q$6:$AZ$6,"<"&C$58,'Monthly P&L'!$Q$35:$AZ$35))) -> 0 | D81: =ABS(D35-(SUMIF('Monthly P&L'!$Q$6:$AZ$6,"<="&D$59,'Monthly P&L'!$Q$35:$AZ$35)-SUMIF('Monthly P&L'!$Q$6:$AZ$6,"<"&D$58,'Monthly P&L'!$Q$35:$AZ$35))) -> 0 | E81: =ABS(E35-(SUMIF('Monthly P&L'!$Q$6:$AZ$6,"<="&E$59,'Monthly P&L'!$Q$35:$AZ$35)-SUMIF('Monthly P&L'!$Q$6:$AZ$6,"<"&E$58,'Monthly P&L'!$Q$35:$AZ$35))) -> 0 | G81: =ABS(G35-(SUMIF('Monthly P&L'!$Q$6:$AZ$6,"<="&G$59,'Monthly P&L'!$Q$35:$AZ$35)-SUMIF('Monthly P&L'!$Q$6:$AZ$6,"<"&G$58,'Monthly P&L'!$Q$35:$AZ$35))) -> 0 | H81: =ABS(H35-(SUMIF('Monthly P&L'!$Q$6:$AZ$6,"<="&H$59,'Monthly P&L'!$Q$35:$AZ$35)-SUMIF('Monthly P&L'!$Q$6:$AZ$6,"<"&H$58,'Monthly P&L'!$Q$35:$AZ$35))) -> 0 | J81: =ABS(J35-(SUMIF('Monthly P&L'!$Q$6:$AZ$6,"<="&J$59,'Monthly P&L'!$Q$35:$AZ$35)-SUMIF('Monthly P&L'!$Q$6:$AZ$6,"<"&J$58,'Monthly P&L'!$Q$35:$AZ$35))) -> 0 | K81: =ABS(K35-(SUMIF('Monthly P&L'!$Q$6:$AZ$6,"<="&K$59,'Monthly P&L'!$Q$35:$AZ$35)-SUMIF('Monthly P&L'!$Q$6:$AZ$6,"<"&K$58,'Monthly P&L'!$Q$35:$AZ$35))) -> 0 | L81: =ABS(L35-(SUMIF('Monthly P&L'!$Q$6:$AZ$6,"<="&L$59,'Monthly P&L'!$Q$35:$AZ$35)-SUMIF('Monthly P&L'!$Q$6:$AZ$6,"<"&L$58,'Monthly P&L'!$Q$35:$AZ$35))) -> 0
B82: C03: EBIT | C82: =ABS(C37-(SUMIF('Monthly P&L'!$Q$6:$AZ$6,"<="&C$59,'Monthly P&L'!$Q$37:$AZ$37)-SUMIF('Monthly P&L'!$Q$6:$AZ$6,"<"&C$58,'Monthly P&L'!$Q$37:$AZ$37))) -> 0 | D82: =ABS(D37-(SUMIF('Monthly P&L'!$Q$6:$AZ$6,"<="&D$59,'Monthly P&L'!$Q$37:$AZ$37)-SUMIF('Monthly P&L'!$Q$6:$AZ$6,"<"&D$58,'Monthly P&L'!$Q$37:$AZ$37))) -> 0 | E82: =ABS(E37-(SUMIF('Monthly P&L'!$Q$6:$AZ$6,"<="&E$59,'Monthly P&L'!$Q$37:$AZ$37)-SUMIF('Monthly P&L'!$Q$6:$AZ$6,"<"&E$58,'Monthly P&L'!$Q$37:$AZ$37))) -> 0 | G82: =ABS(G37-(SUMIF('Monthly P&L'!$Q$6:$AZ$6,"<="&G$59,'Monthly P&L'!$Q$37:$AZ$37)-SUMIF('Monthly P&L'!$Q$6:$AZ$6,"<"&G$58,'Monthly P&L'!$Q$37:$AZ$37))) -> 0 | H82: =ABS(H37-(SUMIF('Monthly P&L'!$Q$6:$AZ$6,"<="&H$59,'Monthly P&L'!$Q$37:$AZ$37)-SUMIF('Monthly P&L'!$Q$6:$AZ$6,"<"&H$58,'Monthly P&L'!$Q$37:$AZ$37))) -> 0 | J82: =ABS(J37-(SUMIF('Monthly P&L'!$Q$6:$AZ$6,"<="&J$59,'Monthly P&L'!$Q$37:$AZ$37)-SUMIF('Monthly P&L'!$Q$6:$AZ$6,"<"&J$58,'Monthly P&L'!$Q$37:$AZ$37))) -> 0 | K82: =ABS(K37-(SUMIF('Monthly P&L'!$Q$6:$AZ$6,"<="&K$59,'Monthly P&L'!$Q$37:$AZ$37)-SUMIF('Monthly P&L'!$Q$6:$AZ$6,"<"&K$58,'Monthly P&L'!$Q$37:$AZ$37))) -> 0 | L82: =ABS(L37-(SUMIF('Monthly P&L'!$Q$6:$AZ$6,"<="&L$59,'Monthly P&L'!$Q$37:$AZ$37)-SUMIF('Monthly P&L'!$Q$6:$AZ$6,"<"&L$58,'Monthly P&L'!$Q$37:$AZ$37))) -> 0
B83: C03: Interest Expense | C83: =ABS(C38-(SUMIF('Monthly P&L'!$Q$6:$AZ$6,"<="&C$59,'Monthly P&L'!$Q$38:$AZ$38)-SUMIF('Monthly P&L'!$Q$6:$AZ$6,"<"&C$58,'Monthly P&L'!$Q$38:$AZ$38))) -> 0 | D83: =ABS(D38-(SUMIF('Monthly P&L'!$Q$6:$AZ$6,"<="&D$59,'Monthly P&L'!$Q$38:$AZ$38)-SUMIF('Monthly P&L'!$Q$6:$AZ$6,"<"&D$58,'Monthly P&L'!$Q$38:$AZ$38))) -> 0 | E83: =ABS(E38-(SUMIF('Monthly P&L'!$Q$6:$AZ$6,"<="&E$59,'Monthly P&L'!$Q$38:$AZ$38)-SUMIF('Monthly P&L'!$Q$6:$AZ$6,"<"&E$58,'Monthly P&L'!$Q$38:$AZ$38))) -> 0 | G83: =ABS(G38-(SUMIF('Monthly P&L'!$Q$6:$AZ$6,"<="&G$59,'Monthly P&L'!$Q$38:$AZ$38)-SUMIF('Monthly P&L'!$Q$6:$AZ$6,"<"&G$58,'Monthly P&L'!$Q$38:$AZ$38))) -> 0 | H83: =ABS(H38-(SUMIF('Monthly P&L'!$Q$6:$AZ$6,"<="&H$59,'Monthly P&L'!$Q$38:$AZ$38)-SUMIF('Monthly P&L'!$Q$6:$AZ$6,"<"&H$58,'Monthly P&L'!$Q$38:$AZ$38))) -> 0 | J83: =ABS(J38-(SUMIF('Monthly P&L'!$Q$6:$AZ$6,"<="&J$59,'Monthly P&L'!$Q$38:$AZ$38)-SUMIF('Monthly P&L'!$Q$6:$AZ$6,"<"&J$58,'Monthly P&L'!$Q$38:$AZ$38))) -> 0 | K83: =ABS(K38-(SUMIF('Monthly P&L'!$Q$6:$AZ$6,"<="&K$59,'Monthly P&L'!$Q$38:$AZ$38)-SUMIF('Monthly P&L'!$Q$6:$AZ$6,"<"&K$58,'Monthly P&L'!$Q$38:$AZ$38))) -> 0 | L83: =ABS(L38-(SUMIF('Monthly P&L'!$Q$6:$AZ$6,"<="&L$59,'Monthly P&L'!$Q$38:$AZ$38)-SUMIF('Monthly P&L'!$Q$6:$AZ$6,"<"&L$58,'Monthly P&L'!$Q$38:$AZ$38))) -> 0
B84: C03: Pre-Tax Income | C84: =ABS(C40-(SUMIF('Monthly P&L'!$Q$6:$AZ$6,"<="&C$59,'Monthly P&L'!$Q$40:$AZ$40)-SUMIF('Monthly P&L'!$Q$6:$AZ$6,"<"&C$58,'Monthly P&L'!$Q$40:$AZ$40))) -> 0 | D84: =ABS(D40-(SUMIF('Monthly P&L'!$Q$6:$AZ$6,"<="&D$59,'Monthly P&L'!$Q$40:$AZ$40)-SUMIF('Monthly P&L'!$Q$6:$AZ$6,"<"&D$58,'Monthly P&L'!$Q$40:$AZ$40))) -> 0 | E84: =ABS(E40-(SUMIF('Monthly P&L'!$Q$6:$AZ$6,"<="&E$59,'Monthly P&L'!$Q$40:$AZ$40)-SUMIF('Monthly P&L'!$Q$6:$AZ$6,"<"&E$58,'Monthly P&L'!$Q$40:$AZ$40))) -> 0 | G84: =ABS(G40-(SUMIF('Monthly P&L'!$Q$6:$AZ$6,"<="&G$59,'Monthly P&L'!$Q$40:$AZ$40)-SUMIF('Monthly P&L'!$Q$6:$AZ$6,"<"&G$58,'Monthly P&L'!$Q$40:$AZ$40))) -> 0 | H84: =ABS(H40-(SUMIF('Monthly P&L'!$Q$6:$AZ$6,"<="&H$59,'Monthly P&L'!$Q$40:$AZ$40)-SUMIF('Monthly P&L'!$Q$6:$AZ$6,"<"&H$58,'Monthly P&L'!$Q$40:$AZ$40))) -> 0 | J84: =ABS(J40-(SUMIF('Monthly P&L'!$Q$6:$AZ$6,"<="&J$59,'Monthly P&L'!$Q$40:$AZ$40)-SUMIF('Monthly P&L'!$Q$6:$AZ$6,"<"&J$58,'Monthly P&L'!$Q$40:$AZ$40))) -> 0 | K84: =ABS(K40-(SUMIF('Monthly P&L'!$Q$6:$AZ$6,"<="&K$59,'Monthly P&L'!$Q$40:$AZ$40)-SUMIF('Monthly P&L'!$Q$6:$AZ$6,"<"&K$58,'Monthly P&L'!$Q$40:$AZ$40))) -> 0 | L84: =ABS(L40-(SUMIF('Monthly P&L'!$Q$6:$AZ$6,"<="&L$59,'Monthly P&L'!$Q$40:$AZ$40)-SUMIF('Monthly P&L'!$Q$6:$AZ$6,"<"&L$58,'Monthly P&L'!$Q$40:$AZ$40))) -> 0
B85: C03: Income Taxes | C85: =ABS(C41-(SUMIF('Monthly P&L'!$Q$6:$AZ$6,"<="&C$59,'Monthly P&L'!$Q$41:$AZ$41)-SUMIF('Monthly P&L'!$Q$6:$AZ$6,"<"&C$58,'Monthly P&L'!$Q$41:$AZ$41))) -> 0 | D85: =ABS(D41-(SUMIF('Monthly P&L'!$Q$6:$AZ$6,"<="&D$59,'Monthly P&L'!$Q$41:$AZ$41)-SUMIF('Monthly P&L'!$Q$6:$AZ$6,"<"&D$58,'Monthly P&L'!$Q$41:$AZ$41))) -> 0 | E85: =ABS(E41-(SUMIF('Monthly P&L'!$Q$6:$AZ$6,"<="&E$59,'Monthly P&L'!$Q$41:$AZ$41)-SUMIF('Monthly P&L'!$Q$6:$AZ$6,"<"&E$58,'Monthly P&L'!$Q$41:$AZ$41))) -> 0 | G85: =ABS(G41-(SUMIF('Monthly P&L'!$Q$6:$AZ$6,"<="&G$59,'Monthly P&L'!$Q$41:$AZ$41)-SUMIF('Monthly P&L'!$Q$6:$AZ$6,"<"&G$58,'Monthly P&L'!$Q$41:$AZ$41))) -> 0 | H85: =ABS(H41-(SUMIF('Monthly P&L'!$Q$6:$AZ$6,"<="&H$59,'Monthly P&L'!$Q$41:$AZ$41)-SUMIF('Monthly P&L'!$Q$6:$AZ$6,"<"&H$58,'Monthly P&L'!$Q$41:$AZ$41))) -> 0 | J85: =ABS(J41-(SUMIF('Monthly P&L'!$Q$6:$AZ$6,"<="&J$59,'Monthly P&L'!$Q$41:$AZ$41)-SUMIF('Monthly P&L'!$Q$6:$AZ$6,"<"&J$58,'Monthly P&L'!$Q$41:$AZ$41))) -> 0 | K85: =ABS(K41-(SUMIF('Monthly P&L'!$Q$6:$AZ$6,"<="&K$59,'Monthly P&L'!$Q$41:$AZ$41)-SUMIF('Monthly P&L'!$Q$6:$AZ$6,"<"&K$58,'Monthly P&L'!$Q$41:$AZ$41))) -> 0 | L85: =ABS(L41-(SUMIF('Monthly P&L'!$Q$6:$AZ$6,"<="&L$59,'Monthly P&L'!$Q$41:$AZ$41)-SUMIF('Monthly P&L'!$Q$6:$AZ$6,"<"&L$58,'Monthly P&L'!$Q$41:$AZ$41))) -> 0
B86: C03: Net Income | C86: =ABS(C43-(SUMIF('Monthly P&L'!$Q$6:$AZ$6,"<="&C$59,'Monthly P&L'!$Q$43:$AZ$43)-SUMIF('Monthly P&L'!$Q$6:$AZ$6,"<"&C$58,'Monthly P&L'!$Q$43:$AZ$43))) -> 0 | D86: =ABS(D43-(SUMIF('Monthly P&L'!$Q$6:$AZ$6,"<="&D$59,'Monthly P&L'!$Q$43:$AZ$43)-SUMIF('Monthly P&L'!$Q$6:$AZ$6,"<"&D$58,'Monthly P&L'!$Q$43:$AZ$43))) -> 0 | E86: =ABS(E43-(SUMIF('Monthly P&L'!$Q$6:$AZ$6,"<="&E$59,'Monthly P&L'!$Q$43:$AZ$43)-SUMIF('Monthly P&L'!$Q$6:$AZ$6,"<"&E$58,'Monthly P&L'!$Q$43:$AZ$43))) -> 0 | G86: =ABS(G43-(SUMIF('Monthly P&L'!$Q$6:$AZ$6,"<="&G$59,'Monthly P&L'!$Q$43:$AZ$43)-SUMIF('Monthly P&L'!$Q$6:$AZ$6,"<"&G$58,'Monthly P&L'!$Q$43:$AZ$43))) -> 0 | H86: =ABS(H43-(SUMIF('Monthly P&L'!$Q$6:$AZ$6,"<="&H$59,'Monthly P&L'!$Q$43:$AZ$43)-SUMIF('Monthly P&L'!$Q$6:$AZ$6,"<"&H$58,'Monthly P&L'!$Q$43:$AZ$43))) -> 0 | J86: =ABS(J43-(SUMIF('Monthly P&L'!$Q$6:$AZ$6,"<="&J$59,'Monthly P&L'!$Q$43:$AZ$43)-SUMIF('Monthly P&L'!$Q$6:$AZ$6,"<"&J$58,'Monthly P&L'!$Q$43:$AZ$43))) -> 0 | K86: =ABS(K43-(SUMIF('Monthly P&L'!$Q$6:$AZ$6,"<="&K$59,'Monthly P&L'!$Q$43:$AZ$43)-SUMIF('Monthly P&L'!$Q$6:$AZ$6,"<"&K$58,'Monthly P&L'!$Q$43:$AZ$43))) -> 0 | L86: =ABS(L43-(SUMIF('Monthly P&L'!$Q$6:$AZ$6,"<="&L$59,'Monthly P&L'!$Q$43:$AZ$43)-SUMIF('Monthly P&L'!$Q$6:$AZ$6,"<"&L$58,'Monthly P&L'!$Q$43:$AZ$43))) -> 0

Sheet Adj. EBITDA
B2: =Cover!B24
B3: Adjusted EBITDA and SDE ($000s) | N3: Print | O3: ='Contents'!$I$18
C5: Full Year | G5: YTD | J5: LTM | L5: PF | N5: PF vs. LTM
B6: Adj. EBITDA | C6: ="FY"&YEAR(C$59) -> FY2023 | D6: ="FY"&YEAR(D$59) -> FY2024 | E6: ="FY"&YEAR(E$59) -> FY2025 | G6: =TEXT(G$59,"mmm-yy") -> Dec-24 | H6: =TEXT(H$59,"mmm-yy") -> Dec-25 | J6: =TEXT(J$59,"mmm-yy") -> Dec-24 | K6: =TEXT(K$59,"mmm-yy") -> Dec-25 | L6: =TEXT(L$59,"mmm-yy") -> Dec-25 | N6: ($) | O6: (%)
B8: Net Income | C8: ='P&L Summary'!C43 -> 74.6 | D8: ='P&L Summary'!D43 -> 129.24 | E8: ='P&L Summary'!E43 -> 232.815 | G8: ='P&L Summary'!G43 -> 129.24 | H8: ='P&L Summary'!H43 -> 232.815 | J8: ='P&L Summary'!J43 -> 129.24 | K8: ='P&L Summary'!K43 -> 232.815 | L8: ='P&L Summary'!K43 -> 232.815 | N8: =L8-K8 -> 0 | O8: =IFERROR(L8/K8-1,"n.a.") -> 0
B9: Definitional Adjustments
B10: ="(+) Interest Expense"&IF('Adjustments'!$I8="Accepted"," "&'Adjustments'!$B8,"") -> (+) Interest Expense [D1] | C10: =SUMIFS('Adjustments'!$N:$N,'Adjustments'!$D:$D,"Definitional",'Adjustments'!$E:$E,"Interest",'Adjustments'!$I:$I,"Accepted") -> 22.4 | D10: =SUMIFS('Adjustments'!$O:$O,'Adjustments'!$D:$D,"Definitional",'Adjustments'!$E:$E,"Interest",'Adjustments'!$I:$I,"Accepted") -> 18.6 | E10: =SUMIFS('Adjustments'!$P:$P,'Adjustments'!$D:$D,"Definitional",'Adjustments'!$E:$E,"Interest",'Adjustments'!$I:$I,"Accepted") -> 14.3 | G10: =SUMIFS('Adjustments'!$R:$R,'Adjustments'!$D:$D,"Definitional",'Adjustments'!$E:$E,"Interest",'Adjustments'!$I:$I,"Accepted") -> 18.6 | H10: =SUMIFS('Adjustments'!$S:$S,'Adjustments'!$D:$D,"Definitional",'Adjustments'!$E:$E,"Interest",'Adjustments'!$I:$I,"Accepted") -> 14.3 | J10: =SUMIFS('Adjustments'!$U:$U,'Adjustments'!$D:$D,"Definitional",'Adjustments'!$E:$E,"Interest",'Adjustments'!$I:$I,"Accepted") -> 18.6 | K10: =SUMIFS('Adjustments'!$V:$V,'Adjustments'!$D:$D,"Definitional",'Adjustments'!$E:$E,"Interest",'Adjustments'!$I:$I,"Accepted") -> 14.3 | L10: =SUMIFS('Adjustments'!$W:$W,'Adjustments'!$D:$D,"Definitional",'Adjustments'!$E:$E,"Interest",'Adjustments'!$I:$I,"Accepted") -> 14.3 | N10: =L10-K10 -> 0 | O10: =IFERROR(L10/K10-1,"n.a.") -> 0
B11: ="(+) Income Taxes"&IF('Adjustments'!$I9="Accepted"," "&'Adjustments'!$B9,"") -> (+) Income Taxes [D2] | C11: =SUMIFS('Adjustments'!$N:$N,'Adjustments'!$D:$D,"Definitional",'Adjustments'!$E:$E,"Taxes",'Adjustments'!$I:$I,"Accepted") -> 0 | D11: =SUMIFS('Adjustments'!$O:$O,'Adjustments'!$D:$D,"Definitional",'Adjustments'!$E:$E,"Taxes",'Adjustments'!$I:$I,"Accepted") -> 0 | E11: =SUMIFS('Adjustments'!$P:$P,'Adjustments'!$D:$D,"Definitional",'Adjustments'!$E:$E,"Taxes",'Adjustments'!$I:$I,"Accepted") -> 0 | G11: =SUMIFS('Adjustments'!$R:$R,'Adjustments'!$D:$D,"Definitional",'Adjustments'!$E:$E,"Taxes",'Adjustments'!$I:$I,"Accepted") -> 0 | H11: =SUMIFS('Adjustments'!$S:$S,'Adjustments'!$D:$D,"Definitional",'Adjustments'!$E:$E,"Taxes",'Adjustments'!$I:$I,"Accepted") -> 0 | J11: =SUMIFS('Adjustments'!$U:$U,'Adjustments'!$D:$D,"Definitional",'Adjustments'!$E:$E,"Taxes",'Adjustments'!$I:$I,"Accepted") -> 0 | K11: =SUMIFS('Adjustments'!$V:$V,'Adjustments'!$D:$D,"Definitional",'Adjustments'!$E:$E,"Taxes",'Adjustments'!$I:$I,"Accepted") -> 0 | L11: =SUMIFS('Adjustments'!$W:$W,'Adjustments'!$D:$D,"Definitional",'Adjustments'!$E:$E,"Taxes",'Adjustments'!$I:$I,"Accepted") -> 0 | N11: =L11-K11 -> 0 | O11: =IFERROR(L11/K11-1,"n.a.") -> n.a.
B12: ="(+) Depreciation & Amortization"&IF('Adjustments'!$I10="Accepted"," "&'Adjustments'!$B10,"") -> (+) Depreciation & Amortization [D3] | C12: =SUMIFS('Adjustments'!$N:$N,'Adjustments'!$D:$D,"Definitional",'Adjustments'!$E:$E,"D&A",'Adjustments'!$I:$I,"Accepted") -> 61.2 | D12: =SUMIFS('Adjustments'!$O:$O,'Adjustments'!$D:$D,"Definitional",'Adjustments'!$E:$E,"D&A",'Adjustments'!$I:$I,"Accepted") -> 66.8 | E12: =SUMIFS('Adjustments'!$P:$P,'Adjustments'!$D:$D,"Definitional",'Adjustments'!$E:$E,"D&A",'Adjustments'!$I:$I,"Accepted") -> 72.4 | G12: =SUMIFS('Adjustments'!$R:$R,'Adjustments'!$D:$D,"Definitional",'Adjustments'!$E:$E,"D&A",'Adjustments'!$I:$I,"Accepted") -> 66.8 | H12: =SUMIFS('Adjustments'!$S:$S,'Adjustments'!$D:$D,"Definitional",'Adjustments'!$E:$E,"D&A",'Adjustments'!$I:$I,"Accepted") -> 72.4 | J12: =SUMIFS('Adjustments'!$U:$U,'Adjustments'!$D:$D,"Definitional",'Adjustments'!$E:$E,"D&A",'Adjustments'!$I:$I,"Accepted") -> 66.8 | K12: =SUMIFS('Adjustments'!$V:$V,'Adjustments'!$D:$D,"Definitional",'Adjustments'!$E:$E,"D&A",'Adjustments'!$I:$I,"Accepted") -> 72.4 | L12: =SUMIFS('Adjustments'!$W:$W,'Adjustments'!$D:$D,"Definitional",'Adjustments'!$E:$E,"D&A",'Adjustments'!$I:$I,"Accepted") -> 72.4 | N12: =L12-K12 -> 0 | O12: =IFERROR(L12/K12-1,"n.a.") -> 0
B13: Reported EBITDA | C13: =C8+C10+C11+C12 -> 158.2 | D13: =D8+D10+D11+D12 -> 214.64 | E13: =E8+E10+E11+E12 -> 319.515 | G13: =G8+G10+G11+G12 -> 214.64 | H13: =H8+H10+H11+H12 -> 319.515 | J13: =J8+J10+J11+J12 -> 214.64 | K13: =K8+K10+K11+K12 -> 319.515 | L13: =L8+L10+L11+L12 -> 319.515 | N13: =L13-K13 -> 0 | O13: =IFERROR(L13/K13-1,"n.a.") -> 0
B14: % Margin | C14: =IFERROR(C13/'P&L Summary'!C14,"n.m.") -> 0.06573043 | D14: =IFERROR(D13/'P&L Summary'!D14,"n.m.") -> 0.078952402 | E14: =IFERROR(E13/'P&L Summary'!E14,"n.m.") -> 0.10507597 | G14: =IFERROR(G13/'P&L Summary'!G14,"n.m.") -> 0.078952402 | H14: =IFERROR(H13/'P&L Summary'!H14,"n.m.") -> 0.10507597 | J14: =IFERROR(J13/'P&L Summary'!J14,"n.m.") -> 0.078952402 | K14: =IFERROR(K13/'P&L Summary'!K14,"n.m.") -> 0.10507597 | L14: =IFERROR(L13/'P&L Summary'!L14,"n.m.") -> 0.10507597
B15: Normalization Adjustments
B16: =IF(SUM('Adjustments'!$N32:$P32)<0,"(-) ","(+) ")&'Adjustments'!$C11&" "&'Adjustments'!$B11 -> (+) Owner's personal vehicle [N1] | C16: =IF('Adjustments'!$I11="Accepted",N('Adjustments'!N32),0) -> 16 | D16: =IF('Adjustments'!$I11="Accepted",N('Adjustments'!O32),0) -> 17 | E16: =IF('Adjustments'!$I11="Accepted",N('Adjustments'!P32),0) -> 18 | G16: =IF('Adjustments'!$I11="Accepted",N('Adjustments'!R32),0) -> 17 | H16: =IF('Adjustments'!$I11="Accepted",N('Adjustments'!S32),0) -> 18 | J16: =IF('Adjustments'!$I11="Accepted",N('Adjustments'!U32),0) -> 17 | K16: =IF('Adjustments'!$I11="Accepted",N('Adjustments'!V32),0) -> 18 | L16: =IF('Adjustments'!$I11="Accepted",N('Adjustments'!W32),0) -> 18 | N16: =L16-K16 -> 0 | O16: =IFERROR(L16/K16-1,"n.a.") -> 0
B17: =IF(SUM('Adjustments'!$N33:$P33)<0,"(-) ","(+) ")&'Adjustments'!$C12&" "&'Adjustments'!$B12 -> (+) Legal fees: settled customer dispute [N2] | C17: =IF('Adjustments'!$I12="Accepted",N('Adjustments'!N33),0) -> 0 | D17: =IF('Adjustments'!$I12="Accepted",N('Adjustments'!O33),0) -> 24 | E17: =IF('Adjustments'!$I12="Accepted",N('Adjustments'!P33),0) -> 0 | G17: =IF('Adjustments'!$I12="Accepted",N('Adjustments'!R33),0) -> 24 | H17: =IF('Adjustments'!$I12="Accepted",N('Adjustments'!S33),0) -> 0 | J17: =IF('Adjustments'!$I12="Accepted",N('Adjustments'!U33),0) -> 24 | K17: =IF('Adjustments'!$I12="Accepted",N('Adjustments'!V33),0) -> 0 | L17: =IF('Adjustments'!$I12="Accepted",N('Adjustments'!W33),0) -> 0 | N17: =L17-K17 -> 0 | O17: =IFERROR(L17/K17-1,"n.a.") -> n.a.
B18: =IF(SUM('Adjustments'!$N34:$P34)<0,"(-) ","(+) ")&'Adjustments'!$C13&" "&'Adjustments'!$B13 -> (+) Owner family phones and meals [N3] | C18: =IF('Adjustments'!$I13="Accepted",N('Adjustments'!N34),0) -> 0 | D18: =IF('Adjustments'!$I13="Accepted",N('Adjustments'!O34),0) -> 0 | E18: =IF('Adjustments'!$I13="Accepted",N('Adjustments'!P34),0) -> 6 | G18: =IF('Adjustments'!$I13="Accepted",N('Adjustments'!R34),0) -> 0 | H18: =IF('Adjustments'!$I13="Accepted",N('Adjustments'!S34),0) -> 6 | J18: =IF('Adjustments'!$I13="Accepted",N('Adjustments'!U34),0) -> 0 | K18: =IF('Adjustments'!$I13="Accepted",N('Adjustments'!V34),0) -> 6 | L18: =IF('Adjustments'!$I13="Accepted",N('Adjustments'!W34),0) -> 6 | N18: =L18-K18 -> 0 | O18: =IFERROR(L18/K18-1,"n.a.") -> 0
B19: =IF(SUM('Adjustments'!$N35:$P35)<0,"(-) ","(+) ")&'Adjustments'!$C14&" "&'Adjustments'!$B14 -> (+) Charitable contributions [N4] | C19: =IF('Adjustments'!$I14="Accepted",N('Adjustments'!N35),0) -> 5 | D19: =IF('Adjustments'!$I14="Accepted",N('Adjustments'!O35),0) -> 6 | E19: =IF('Adjustments'!$I14="Accepted",N('Adjustments'!P35),0) -> 7.5 | G19: =IF('Adjustments'!$I14="Accepted",N('Adjustments'!R35),0) -> 6 | H19: =IF('Adjustments'!$I14="Accepted",N('Adjustments'!S35),0) -> 7.5 | J19: =IF('Adjustments'!$I14="Accepted",N('Adjustments'!U35),0) -> 6 | K19: =IF('Adjustments'!$I14="Accepted",N('Adjustments'!V35),0) -> 7.5 | L19: =IF('Adjustments'!$I14="Accepted",N('Adjustments'!W35),0) -> 7.5 | N19: =L19-K19 -> 0 | O19: =IFERROR(L19/K19-1,"n.a.") -> 0
B20: =IF(SUM('Adjustments'!$N36:$P36)<0,"(-) ","(+) ")&'Adjustments'!$C15&" "&'Adjustments'!$B15 -> (-) Interest income (non-operating) [N5] | C20: =IF('Adjustments'!$I15="Accepted",N('Adjustments'!N36),0) -> -1.2 | D20: =IF('Adjustments'!$I15="Accepted",N('Adjustments'!O36),0) -> -2.4 | E20: =IF('Adjustments'!$I15="Accepted",N('Adjustments'!P36),0) -> -3.1 | G20: =IF('Adjustments'!$I15="Accepted",N('Adjustments'!R36),0) -> -2.4 | H20: =IF('Adjustments'!$I15="Accepted",N('Adjustments'!S36),0) -> -3.1 | J20: =IF('Adjustments'!$I15="Accepted",N('Adjustments'!U36),0) -> -2.4 | K20: =IF('Adjustments'!$I15="Accepted",N('Adjustments'!V36),0) -> -3.1 | L20: =IF('Adjustments'!$I15="Accepted",N('Adjustments'!W36),0) -> -3.1 | N20: =L20-K20 -> 0 | O20: =IFERROR(L20/K20-1,"n.a.") -> 0
B21: Total Normalization Adjustments | C21: =SUMIFS('Adjustments'!$N:$N,'Adjustments'!$D:$D,"Normalization",'Adjustments'!$I:$I,"Accepted") -> 19.8 | D21: =SUMIFS('Adjustments'!$O:$O,'Adjustments'!$D:$D,"Normalization",'Adjustments'!$I:$I,"Accepted") -> 44.6 | E21: =SUMIFS('Adjustments'!$P:$P,'Adjustments'!$D:$D,"Normalization",'Adjustments'!$I:$I,"Accepted") -> 28.4 | G21: =SUMIFS('Adjustments'!$R:$R,'Adjustments'!$D:$D,"Normalization",'Adjustments'!$I:$I,"Accepted") -> 44.6 | H21: =SUMIFS('Adjustments'!$S:$S,'Adjustments'!$D:$D,"Normalization",'Adjustments'!$I:$I,"Accepted") -> 28.4 | J21: =SUMIFS('Adjustments'!$U:$U,'Adjustments'!$D:$D,"Normalization",'Adjustments'!$I:$I,"Accepted") -> 44.6 | K21: =SUMIFS('Adjustments'!$V:$V,'Adjustments'!$D:$D,"Normalization",'Adjustments'!$I:$I,"Accepted") -> 28.4 | L21: =SUMIFS('Adjustments'!$W:$W,'Adjustments'!$D:$D,"Normalization",'Adjustments'!$I:$I,"Accepted") -> 28.4 | N21: =L21-K21 -> 0 | O21: =IFERROR(L21/K21-1,"n.a.") -> 0
B22: Owner Compensation
B23: ="(+) Owner Compensation"&IF('Adjustments'!$I20="Accepted"," "&'Adjustments'!$B20,"")&IF('Adjustments'!$I23="Accepted"," "&'Adjustments'!$B23,"") -> (+) Owner Compensation [S1] [S4] | C23: =SUMIFS('Adjustments'!$N:$N,'Adjustments'!$D:$D,"Owner compensation",'Adjustments'!$E:$E,"Owner compensation",'Adjustments'!$I:$I,"Accepted") -> 192.584 | D23: =SUMIFS('Adjustments'!$O:$O,'Adjustments'!$D:$D,"Owner compensation",'Adjustments'!$E:$E,"Owner compensation",'Adjustments'!$I:$I,"Accepted") -> 203.25 | E23: =SUMIFS('Adjustments'!$P:$P,'Adjustments'!$D:$D,"Owner compensation",'Adjustments'!$E:$E,"Owner compensation",'Adjustments'!$I:$I,"Accepted") -> 213.86 | G23: =SUMIFS('Adjustments'!$R:$R,'Adjustments'!$D:$D,"Owner compensation",'Adjustments'!$E:$E,"Owner compensation",'Adjustments'!$I:$I,"Accepted") -> 203.25 | H23: =SUMIFS('Adjustments'!$S:$S,'Adjustments'!$D:$D,"Owner compensation",'Adjustments'!$E:$E,"Owner compensation",'Adjustments'!$I:$I,"Accepted") -> 213.86 | J23: =SUMIFS('Adjustments'!$U:$U,'Adjustments'!$D:$D,"Owner compensation",'Adjustments'!$E:$E,"Owner compensation",'Adjustments'!$I:$I,"Accepted") -> 203.25 | K23: =SUMIFS('Adjustments'!$V:$V,'Adjustments'!$D:$D,"Owner compensation",'Adjustments'!$E:$E,"Owner compensation",'Adjustments'!$I:$I,"Accepted") -> 213.86 | L23: =SUMIFS('Adjustments'!$W:$W,'Adjustments'!$D:$D,"Owner compensation",'Adjustments'!$E:$E,"Owner compensation",'Adjustments'!$I:$I,"Accepted") -> 213.86 | N23: =L23-K23 -> 0 | O23: =IFERROR(L23/K23-1,"n.a.") -> 0
B24: Seller's Discretionary Earnings (SDE) | C24: =C13+C21+C23 -> 370.584 | D24: =D13+D21+D23 -> 462.49 | E24: =E13+E21+E23 -> 561.775 | G24: =G13+G21+G23 -> 462.49 | H24: =H13+H21+H23 -> 561.775 | J24: =J13+J21+J23 -> 462.49 | K24: =K13+K21+K23 -> 561.775 | L24: =L13+L21+L23 -> 561.775 | N24: =L24-K24 -> 0 | O24: =IFERROR(L24/K24-1,"n.a.") -> 0
B25: % Margin | C25: =IFERROR(C24/'P&L Summary'!C14,"n.m.") -> 0.15397374 | D25: =IFERROR(D24/'P&L Summary'!D14,"n.m.") -> 0.17012065 | E25: =IFERROR(E24/'P&L Summary'!E14,"n.m.") -> 0.18474579 | G25: =IFERROR(G24/'P&L Summary'!G14,"n.m.") -> 0.17012065 | H25: =IFERROR(H24/'P&L Summary'!H14,"n.m.") -> 0.18474579 | J25: =IFERROR(J24/'P&L Summary'!J14,"n.m.") -> 0.17012065 | K25: =IFERROR(K24/'P&L Summary'!K14,"n.m.") -> 0.18474579 | L25: =IFERROR(L24/'P&L Summary'!L14,"n.m.") -> 0.18474579
B26: ="(-) Market Replacement Compensation"&IF('Adjustments'!$I21="Accepted"," "&'Adjustments'!$B21,"") -> (-) Market Replacement Compensation [S2] | C26: =SUMIFS('Adjustments'!$N:$N,'Adjustments'!$D:$D,"Owner compensation",'Adjustments'!$E:$E,"Replacement cost",'Adjustments'!$I:$I,"Accepted") -> -109.25 | D26: =SUMIFS('Adjustments'!$O:$O,'Adjustments'!$D:$D,"Owner compensation",'Adjustments'!$E:$E,"Replacement cost",'Adjustments'!$I:$I,"Accepted") -> -109.25 | E26: =SUMIFS('Adjustments'!$P:$P,'Adjustments'!$D:$D,"Owner compensation",'Adjustments'!$E:$E,"Replacement cost",'Adjustments'!$I:$I,"Accepted") -> -109.25 | G26: =SUMIFS('Adjustments'!$R:$R,'Adjustments'!$D:$D,"Owner compensation",'Adjustments'!$E:$E,"Replacement cost",'Adjustments'!$I:$I,"Accepted") -> -109.25 | H26: =SUMIFS('Adjustments'!$S:$S,'Adjustments'!$D:$D,"Owner compensation",'Adjustments'!$E:$E,"Replacement cost",'Adjustments'!$I:$I,"Accepted") -> -109.25 | J26: =SUMIFS('Adjustments'!$U:$U,'Adjustments'!$D:$D,"Owner compensation",'Adjustments'!$E:$E,"Replacement cost",'Adjustments'!$I:$I,"Accepted") -> -109.25 | K26: =SUMIFS('Adjustments'!$V:$V,'Adjustments'!$D:$D,"Owner compensation",'Adjustments'!$E:$E,"Replacement cost",'Adjustments'!$I:$I,"Accepted") -> -109.25 | L26: =SUMIFS('Adjustments'!$W:$W,'Adjustments'!$D:$D,"Owner compensation",'Adjustments'!$E:$E,"Replacement cost",'Adjustments'!$I:$I,"Accepted") -> -109.25 | N26: =L26-K26 -> 0 | O26: =IFERROR(L26/K26-1,"n.a.") -> 0
B27: ="(-) Capital Reserve (Maintenance Capex)"&IF('Adjustments'!$I22="Accepted"," "&'Adjustments'!$B22,"") -> (-) Capital Reserve (Maintenance Capex) [S3] | C27: =SUMIFS('Adjustments'!$N:$N,'Adjustments'!$D:$D,"Owner compensation",'Adjustments'!$E:$E,"Capital reserve",'Adjustments'!$I:$I,"Accepted") -> -66.8 | D27: =SUMIFS('Adjustments'!$O:$O,'Adjustments'!$D:$D,"Owner compensation",'Adjustments'!$E:$E,"Capital reserve",'Adjustments'!$I:$I,"Accepted") -> -66.8 | E27: =SUMIFS('Adjustments'!$P:$P,'Adjustments'!$D:$D,"Owner compensation",'Adjustments'!$E:$E,"Capital reserve",'Adjustments'!$I:$I,"Accepted") -> -66.8 | G27: =SUMIFS('Adjustments'!$R:$R,'Adjustments'!$D:$D,"Owner compensation",'Adjustments'!$E:$E,"Capital reserve",'Adjustments'!$I:$I,"Accepted") -> -66.8 | H27: =SUMIFS('Adjustments'!$S:$S,'Adjustments'!$D:$D,"Owner compensation",'Adjustments'!$E:$E,"Capital reserve",'Adjustments'!$I:$I,"Accepted") -> -66.8 | J27: =SUMIFS('Adjustments'!$U:$U,'Adjustments'!$D:$D,"Owner compensation",'Adjustments'!$E:$E,"Capital reserve",'Adjustments'!$I:$I,"Accepted") -> -66.8 | K27: =SUMIFS('Adjustments'!$V:$V,'Adjustments'!$D:$D,"Owner compensation",'Adjustments'!$E:$E,"Capital reserve",'Adjustments'!$I:$I,"Accepted") -> -66.8 | L27: =SUMIFS('Adjustments'!$W:$W,'Adjustments'!$D:$D,"Owner compensation",'Adjustments'!$E:$E,"Capital reserve",'Adjustments'!$I:$I,"Accepted") -> -66.8 | N27: =L27-K27 -> 0 | O27: =IFERROR(L27/K27-1,"n.a.") -> 0
B28: Adj. EBITDA | C28: =C24+C26+C27 -> 194.534 | D28: =D24+D26+D27 -> 286.44 | E28: =E24+E26+E27 -> 385.725 | G28: =G24+G26+G27 -> 286.44 | H28: =H24+H26+H27 -> 385.725 | J28: =J24+J26+J27 -> 286.44 | K28: =K24+K26+K27 -> 385.725 | L28: =L24+L26+L27 -> 385.725 | N28: =L28-K28 -> 0 | O28: =IFERROR(L28/K28-1,"n.a.") -> 0
B29: % Margin | C29: =IFERROR(C28/'P&L Summary'!C14,"n.m.") -> 0.080826824 | D29: =IFERROR(D28/'P&L Summary'!D14,"n.m.") -> 0.10536305 | E29: =IFERROR(E28/'P&L Summary'!E14,"n.m.") -> 0.12684984 | G29: =IFERROR(G28/'P&L Summary'!G14,"n.m.") -> 0.10536305 | H29: =IFERROR(H28/'P&L Summary'!H14,"n.m.") -> 0.12684984 | J29: =IFERROR(J28/'P&L Summary'!J14,"n.m.") -> 0.10536305 | K29: =IFERROR(K28/'P&L Summary'!K14,"n.m.") -> 0.12684984 | L29: =IFERROR(L28/'P&L Summary'!L14,"n.m.") -> 0.12684984
B30: Pro Forma Adjustments
B31: Total Pro Forma Adjustments | C31: =SUMIFS('Adjustments'!$N:$N,'Adjustments'!$D:$D,"Pro forma",'Adjustments'!$I:$I,"Accepted") -> 0 | D31: =SUMIFS('Adjustments'!$O:$O,'Adjustments'!$D:$D,"Pro forma",'Adjustments'!$I:$I,"Accepted") -> 0 | E31: =SUMIFS('Adjustments'!$P:$P,'Adjustments'!$D:$D,"Pro forma",'Adjustments'!$I:$I,"Accepted") -> 0 | G31: =SUMIFS('Adjustments'!$R:$R,'Adjustments'!$D:$D,"Pro forma",'Adjustments'!$I:$I,"Accepted") -> 0 | H31: =SUMIFS('Adjustments'!$S:$S,'Adjustments'!$D:$D,"Pro forma",'Adjustments'!$I:$I,"Accepted") -> 0 | J31: =SUMIFS('Adjustments'!$U:$U,'Adjustments'!$D:$D,"Pro forma",'Adjustments'!$I:$I,"Accepted") -> 0 | K31: =SUMIFS('Adjustments'!$V:$V,'Adjustments'!$D:$D,"Pro forma",'Adjustments'!$I:$I,"Accepted") -> 0 | L31: =SUMIFS('Adjustments'!$W:$W,'Adjustments'!$D:$D,"Pro forma",'Adjustments'!$I:$I,"Accepted") -> 0 | N31: =L31-K31 -> 0 | O31: =IFERROR(L31/K31-1,"n.a.") -> n.a.
B32: PF Adj. EBITDA | C32: =C28+C31 -> 194.534 | D32: =D28+D31 -> 286.44 | E32: =E28+E31 -> 385.725 | G32: =G28+G31 -> 286.44 | H32: =H28+H31 -> 385.725 | J32: =J28+J31 -> 286.44 | K32: =K28+K31 -> 385.725 | L32: =L28+L31 -> 385.725 | N32: =L32-K32 -> 0 | O32: =IFERROR(L32/K32-1,"n.a.") -> 0
B33: % Margin | C33: =IFERROR(C32/'P&L Summary'!C14,"n.m.") -> 0.080826824 | D33: =IFERROR(D32/'P&L Summary'!D14,"n.m.") -> 0.10536305 | E33: =IFERROR(E32/'P&L Summary'!E14,"n.m.") -> 0.12684984 | G33: =IFERROR(G32/'P&L Summary'!G14,"n.m.") -> 0.10536305 | H33: =IFERROR(H32/'P&L Summary'!H14,"n.m.") -> 0.12684984 | J33: =IFERROR(J32/'P&L Summary'!J14,"n.m.") -> 0.10536305 | K33: =IFERROR(K32/'P&L Summary'!K14,"n.m.") -> 0.12684984 | L33: =IFERROR(L32/'P&L Summary'!L14,"n.m.") -> 0.12684984
B34: Memo: Other Considerations (not included above)
B35: ='Adjustments'!$C24&" "&'Adjustments'!$B24 -> After-hours emergency plumbing [M1] | C35: =N('Adjustments'!N45) -> 0 | D35: =N('Adjustments'!O45) -> 0 | E35: =N('Adjustments'!P45) -> 0 | G35: =N('Adjustments'!R45) -> 0 | H35: =N('Adjustments'!S45) -> 0 | J35: =N('Adjustments'!U45) -> 0 | K35: =N('Adjustments'!V45) -> 0 | L35: =N('Adjustments'!W45) -> 0 | N35: =L35-K35 -> 0 | O35: =IFERROR(L35/K35-1,"n.a.") -> n.a.
B37: Check: Reported EBITDA less (Net Income + D1:D3) | C37: =ROUND(C13-'P&L Summary'!C32,6) -> 0 | D37: =ROUND(D13-'P&L Summary'!D32,6) -> 0 | E37: =ROUND(E13-'P&L Summary'!E32,6) -> 0 | G37: =ROUND(G13-'P&L Summary'!G32,6) -> 0 | H37: =ROUND(H13-'P&L Summary'!H32,6) -> 0 | J37: =ROUND(J13-'P&L Summary'!J32,6) -> 0 | K37: =ROUND(K13-'P&L Summary'!K32,6) -> 0 | L37: =ROUND(L13-'P&L Summary'!K32,6) -> 0
B38: Check: Adjustments schedule less ladder, by tier | C38: =ROUND(ABS(SUMIFS('Adjustments'!$N:$N,'Adjustments'!$D:$D,"Definitional",'Adjustments'!$I:$I,"Accepted")-(C10+C11+C12))+ABS(SUMIFS('Adjustments'!$N:$N,'Adjustments'!$D:$D,"Normalization",'Adjustments'!$I:$I,"Accepted")-SUM(C16:C20))+ABS(SUMIFS('Adjustments'!$N:$N,'Adjustments'!$D:$D,"Owner compensation",'Adjustments'!$I:$I,"Accepted")-(C23+C26+C27))+ABS(SUMIFS('Adjustments'!$N:$N,'Adjustments'!$D:$D,"Pro forma",'Adjustments'!$I:$I,"Accepted")-N(0)),6) -> 0 | D38: =ROUND(ABS(SUMIFS('Adjustments'!$O:$O,'Adjustments'!$D:$D,"Definitional",'Adjustments'!$I:$I,"Accepted")-(D10+D11+D12))+ABS(SUMIFS('Adjustments'!$O:$O,'Adjustments'!$D:$D,"Normalization",'Adjustments'!$I:$I,"Accepted")-SUM(D16:D20))+ABS(SUMIFS('Adjustments'!$O:$O,'Adjustments'!$D:$D,"Owner compensation",'Adjustments'!$I:$I,"Accepted")-(D23+D26+D27))+ABS(SUMIFS('Adjustments'!$O:$O,'Adjustments'!$D:$D,"Pro forma",'Adjustments'!$I:$I,"Accepted")-N(0)),6) -> 0 | E38: =ROUND(ABS(SUMIFS('Adjustments'!$P:$P,'Adjustments'!$D:$D,"Definitional",'Adjustments'!$I:$I,"Accepted")-(E10+E11+E12))+ABS(SUMIFS('Adjustments'!$P:$P,'Adjustments'!$D:$D,"Normalization",'Adjustments'!$I:$I,"Accepted")-SUM(E16:E20))+ABS(SUMIFS('Adjustments'!$P:$P,'Adjustments'!$D:$D,"Owner compensation",'Adjustments'!$I:$I,"Accepted")-(E23+E26+E27))+ABS(SUMIFS('Adjustments'!$P:$P,'Adjustments'!$D:$D,"Pro forma",'Adjustments'!$I:$I,"Accepted")-N(0)),6) -> 0 | G38: =ROUND(ABS(SUMIFS('Adjustments'!$R:$R,'Adjustments'!$D:$D,"Definitional",'Adjustments'!$I:$I,"Accepted")-(G10+G11+G12))+ABS(SUMIFS('Adjustments'!$R:$R,'Adjustments'!$D:$D,"Normalization",'Adjustments'!$I:$I,"Accepted")-SUM(G16:G20))+ABS(SUMIFS('Adjustments'!$R:$R,'Adjustments'!$D:$D,"Owner compensation",'Adjustments'!$I:$I,"Accepted")-(G23+G26+G27))+ABS(SUMIFS('Adjustments'!$R:$R,'Adjustments'!$D:$D,"Pro forma",'Adjustments'!$I:$I,"Accepted")-N(0)),6) -> 0 | H38: =ROUND(ABS(SUMIFS('Adjustments'!$S:$S,'Adjustments'!$D:$D,"Definitional",'Adjustments'!$I:$I,"Accepted")-(H10+H11+H12))+ABS(SUMIFS('Adjustments'!$S:$S,'Adjustments'!$D:$D,"Normalization",'Adjustments'!$I:$I,"Accepted")-SUM(H16:H20))+ABS(SUMIFS('Adjustments'!$S:$S,'Adjustments'!$D:$D,"Owner compensation",'Adjustments'!$I:$I,"Accepted")-(H23+H26+H27))+ABS(SUMIFS('Adjustments'!$S:$S,'Adjustments'!$D:$D,"Pro forma",'Adjustments'!$I:$I,"Accepted")-N(0)),6) -> 0 | J38: =ROUND(ABS(SUMIFS('Adjustments'!$U:$U,'Adjustments'!$D:$D,"Definitional",'Adjustments'!$I:$I,"Accepted")-(J10+J11+J12))+ABS(SUMIFS('Adjustments'!$U:$U,'Adjustments'!$D:$D,"Normalization",'Adjustments'!$I:$I,"Accepted")-SUM(J16:J20))+ABS(SUMIFS('Adjustments'!$U:$U,'Adjustments'!$D:$D,"Owner compensation",'Adjustments'!$I:$I,"Accepted")-(J23+J26+J27))+ABS(SUMIFS('Adjustments'!$U:$U,'Adjustments'!$D:$D,"Pro forma",'Adjustments'!$I:$I,"Accepted")-N(0)),6) -> 0 | K38: =ROUND(ABS(SUMIFS('Adjustments'!$V:$V,'Adjustments'!$D:$D,"Definitional",'Adjustments'!$I:$I,"Accepted")-(K10+K11+K12))+ABS(SUMIFS('Adjustments'!$V:$V,'Adjustments'!$D:$D,"Normalization",'Adjustments'!$I:$I,"Accepted")-SUM(K16:K20))+ABS(SUMIFS('Adjustments'!$V:$V,'Adjustments'!$D:$D,"Owner compensation",'Adjustments'!$I:$I,"Accepted")-(K23+K26+K27))+ABS(SUMIFS('Adjustments'!$V:$V,'Adjustments'!$D:$D,"Pro forma",'Adjustments'!$I:$I,"Accepted")-N(0)),6) -> 0 | L38: =ROUND(ABS(SUMIFS('Adjustments'!$W:$W,'Adjustments'!$D:$D,"Definitional",'Adjustments'!$I:$I,"Accepted")-(L10+L11+L12))+ABS(SUMIFS('Adjustments'!$W:$W,'Adjustments'!$D:$D,"Normalization",'Adjustments'!$I:$I,"Accepted")-SUM(L16:L20))+ABS(SUMIFS('Adjustments'!$W:$W,'Adjustments'!$D:$D,"Owner compensation",'Adjustments'!$I:$I,"Accepted")-(L23+L26+L27))+ABS(SUMIFS('Adjustments'!$W:$W,'Adjustments'!$D:$D,"Pro forma",'Adjustments'!$I:$I,"Accepted")-N(0)),6) -> 0
B40: Note: margins divide by total revenue. Main Street mode: SDE is the headline; the capital reserve [S3] is deducted below SDE. The PF column starts from LTM net income and adds the accepted pro forma rows below Adj. EBITDA. Each line links to its schedule row, so a row inserted on the Adjustments tab renumbers the refs here.
B42: Basis of each adjustment (linked from the Adjustments schedule)
B43: ='Adjustments'!$B8&" "&'Adjustments'!$C8 -> [D1] Interest expense | C43: ='Adjustments'!$F8 -> Adds back interest on the Company's debt, $14.3K in FY2025, per the P&L Interest Expense account.
B44: ='Adjustments'!$B9&" "&'Adjustments'!$C9 -> [D2] Income taxes | C44: ='Adjustments'!$F9 -> None: the Company is a pass-through entity, so income tax is paid by the owner and the ladder shows a dash.
B45: ='Adjustments'!$B10&" "&'Adjustments'!$C10 -> [D3] Depreciation and amortization | C45: ='Adjustments'!$F10 -> Adds back depreciation and amortization, $72.4K in FY2025, per the P&L Depreciation Expense account.
B46: ='Adjustments'!$B11&" "&'Adjustments'!$C11 -> [N1] Owner's personal vehicle | C46: ='Adjustments'!$F11 -> Removes the owner's personal vehicle costs coded to Vehicle Expenses, $18.0K in FY2025, per the seller's add-back list.
B47: ='Adjustments'!$B12&" "&'Adjustments'!$C12 -> [N2] Legal fees: settled customer dispute | C47: ='Adjustments'!$F12 -> Removes the one-time cost of settling a customer dispute, $24.0K in FY2024, visible as the spike in Legal & Professional Fees ($38.9K against $16.4K and $17.2K in the adjacent years).
B48: ='Adjustments'!$B13&" "&'Adjustments'!$C13 -> [N3] Owner family phones and meals | C48: ='Adjustments'!$F13 -> Removes family phone lines and personal meals expensed through the Company, $6.0K in FY2025, per the seller's add-back list.
B49: ='Adjustments'!$B14&" "&'Adjustments'!$C14 -> [N4] Charitable contributions | C49: ='Adjustments'!$F14 -> Removes discretionary charitable giving, $7.5K in FY2025, equal to the P&L Charitable Contributions account.
B50: ='Adjustments'!$B15&" "&'Adjustments'!$C15 -> [N5] Interest income (non-operating) | C50: ='Adjustments'!$F15 -> Removes interest income, $3.1K in FY2025, which is non-operating income, per the P&L Interest Income account.
B51: ='Adjustments'!$B20&" "&'Adjustments'!$C20 -> [S1] Owner compensation | C51: ='Adjustments'!$F20 -> Adds back the owner's salary as paid, $200.0K in FY2025, per the P&L Officer Compensation account.
B52: ='Adjustments'!$B21&" "&'Adjustments'!$C21 -> [S2] Market replacement compensation | C52: ='Adjustments'!$F21 -> Deducts a general manager at the $95,000 market salary, plus payroll taxes and benefits at 15% of salary, $109,250 a year.
B53: ='Adjustments'!$B22&" "&'Adjustments'!$C22 -> [S3] Capital reserve (maintenance capex) | C53: ='Adjustments'!$F22 -> Deducts a reserve for equipment replacement of $66,800 a year, equal to the three-year average of depreciation expense, FY2023–FY2025.
B54: ='Adjustments'!$B23&" "&'Adjustments'!$C23 -> [S4] Payroll taxes and benefits on owner compensation | C54: ='Adjustments'!$F23 -> Adds back employer payroll taxes on Mark Delaney's salary at statutory rates, $13.9K in FY2025 (Social Security to the $176,100 wage base, Medicare, federal unemployment); the P&L carries them in payroll. Owner benefits and state unemployment are not included.
B55: ='Adjustments'!$B24&" "&'Adjustments'!$C24 -> [M1] After-hours emergency plumbing | C55: ='Adjustments'!$F24 -> Calls after 7 pm are turned away today; no revenue from an after-hours service is included in any figure above, per management.
B58: Period start | C58: =EOMONTH(EOMONTH(DATE('Assumptions'!$C$15-2,'Assumptions'!$C$14,1),0),-12)+1 -> 44927 | D58: =EOMONTH(EOMONTH(DATE('Assumptions'!$C$15-1,'Assumptions'!$C$14,1),0),-12)+1 -> 45292 | E58: =EOMONTH(EOMONTH(DATE('Assumptions'!$C$15-0,'Assumptions'!$C$14,1),0),-12)+1 -> 45658 | G58: =EOMONTH(EOMONTH(DATE(YEAR('Assumptions'!$C$9)-IF(MONTH('Assumptions'!$C$9)>'Assumptions'!$C$14,0,1),'Assumptions'!$C$14,1),0)+1,-13)+1 -> 45292 | H58: =EOMONTH(DATE(YEAR('Assumptions'!$C$9)-IF(MONTH('Assumptions'!$C$9)>'Assumptions'!$C$14,0,1),'Assumptions'!$C$14,1),0)+1 -> 45658 | J58: =EOMONTH('Assumptions'!$C$9,-24)+1 -> 45292 | K58: =EOMONTH('Assumptions'!$C$9,-12)+1 -> 45658 | L58: =EOMONTH('Assumptions'!$C$9,-12)+1 -> 45658
B59: Period end | C59: =EOMONTH(DATE('Assumptions'!$C$15-2,'Assumptions'!$C$14,1),0) -> 45291 | D59: =EOMONTH(DATE('Assumptions'!$C$15-1,'Assumptions'!$C$14,1),0) -> 45657 | E59: =EOMONTH(DATE('Assumptions'!$C$15-0,'Assumptions'!$C$14,1),0) -> 46022 | G59: =EOMONTH('Assumptions'!$C$9,-12) -> 45657 | H59: =EOMONTH('Assumptions'!$C$9,0) -> 46022 | J59: =EOMONTH('Assumptions'!$C$9,-12) -> 45657 | K59: =EOMONTH('Assumptions'!$C$9,0) -> 46022 | L59: =EOMONTH('Assumptions'!$C$9,0) -> 46022

Sheet Adjustments
B2: =Cover!B24
B3: Recast and Adjustments Schedule ($000s) | V3: Print | W3: ='Contents'!$I$18
B5: Schedule | N5: Full Year | R5: YTD | U5: LTM | W5: PF | Y5: Monthly ($000s)
B6: Ref | C6: Adjustment | D6: Tier | E6: Category | F6: Basis | G6: Source document | H6: Evidence | I6: Status | J6: In CIM | K6: P&L line | L6: PF method | N6: ="FY"&YEAR(N$58) -> FY2023 | O6: ="FY"&YEAR(O$58) -> FY2024 | P6: ="FY"&YEAR(P$58) -> FY2025 | R6: =TEXT(R$58,"mmm-yy") -> Dec-24 | S6: =TEXT(S$58,"mmm-yy") -> Dec-25 | U6: =TEXT(U$58,"mmm-yy") -> Dec-24 | V6: =TEXT(V$58,"mmm-yy") -> Dec-25 | W6: =TEXT(W$58,"mmm-yy") -> Dec-25 | Y6: ='Assumptions'!$C$10 -> 44927 | Z6: =EOMONTH(Y6,0)+1 -> 44958 | AA6: =EOMONTH(Z6,0)+1 -> 44986 | AB6: =EOMONTH(AA6,0)+1 -> 45017 | AC6: =EOMONTH(AB6,0)+1 -> 45047 | AD6: =EOMONTH(AC6,0)+1 -> 45078 | AE6: =EOMONTH(AD6,0)+1 -> 45108 | AF6: =EOMONTH(AE6,0)+1 -> 45139 | AG6: =EOMONTH(AF6,0)+1 -> 45170 | ... BH6: =EOMONTH(BG6,0)+1 -> 45992
B8: ="["&CHOOSE(MATCH(D8,{"Definitional","Normalization","Owner compensation","Pro forma","Memo"},0),"D","N","S","PF","M")&COUNTIF($D$8:D8,D8)&"]" -> [D1] | C8: Interest expense | D8: Definitional | E8: Interest | F8: Adds back interest on the Company's debt, $14.3K in FY2025, per the P&L Interest Expense account. | G8: P&L, account Interest Expense | H8: Documented | I8: Accepted | J8: =IF(I8="Accepted","Yes","No") -> Yes
B9: ="["&CHOOSE(MATCH(D9,{"Definitional","Normalization","Owner compensation","Pro forma","Memo"},0),"D","N","S","PF","M")&COUNTIF($D$8:D9,D9)&"]" -> [D2] | C9: Income taxes | D9: Definitional | E9: Taxes | F9: None: the Company is a pass-through entity, so income tax is paid by the owner and the ladder shows a dash. | G9: P&L (no such account) | H9: Documented | I9: Accepted | J9: =IF(I9="Accepted","Yes","No") -> Yes
B10: ="["&CHOOSE(MATCH(D10,{"Definitional","Normalization","Owner compensation","Pro forma","Memo"},0),"D","N","S","PF","M")&COUNTIF($D$8:D10,D10)&"]" -> [D3] | C10: Depreciation and amortization | D10: Definitional | E10: D&A | F10: Adds back depreciation and amortization, $72.4K in FY2025, per the P&L Depreciation Expense account. | G10: P&L, account Depreciation Expense | H10: Documented | I10: Accepted | J10: =IF(I10="Accepted","Yes","No") -> Yes
B11: ="["&CHOOSE(MATCH(D11,{"Definitional","Normalization","Owner compensation","Pro forma","Memo"},0),"D","N","S","PF","M")&COUNTIF($D$8:D11,D11)&"]" -> [N1] | C11: Owner's personal vehicle | D11: Normalization | E11: Personal / discretionary | F11: Removes the owner's personal vehicle costs coded to Vehicle Expenses, $18.0K in FY2025, per the seller's add-back list. | G11: Seller add-back list; P&L account Vehicle Expenses | H11: Management representation | I11: Accepted | J11: =IF(I11="Accepted","Yes","No") -> Yes
B12: ="["&CHOOSE(MATCH(D12,{"Definitional","Normalization","Owner compensation","Pro forma","Memo"},0),"D","N","S","PF","M")&COUNTIF($D$8:D12,D12)&"]" -> [N2] | C12: Legal fees: settled customer dispute | D12: Normalization | E12: Non-recurring | F12: Removes the one-time cost of settling a customer dispute, $24.0K in FY2024, visible as the spike in Legal & Professional Fees ($38.9K against $16.4K and $17.2K in the adjacent years). | G12: Seller add-back list; settlement agreement; P&L account Legal & Professional Fees | H12: Documented | I12: Accepted | J12: =IF(I12="Accepted","Yes","No") -> Yes
B13: ="["&CHOOSE(MATCH(D13,{"Definitional","Normalization","Owner compensation","Pro forma","Memo"},0),"D","N","S","PF","M")&COUNTIF($D$8:D13,D13)&"]" -> [N3] | C13: Owner family phones and meals | D13: Normalization | E13: Personal / discretionary | F13: Removes family phone lines and personal meals expensed through the Company, $6.0K in FY2025, per the seller's add-back list. | G13: Seller add-back list | H13: Management representation | I13: Accepted | J13: =IF(I13="Accepted","Yes","No") -> Yes
B14: ="["&CHOOSE(MATCH(D14,{"Definitional","Normalization","Owner compensation","Pro forma","Memo"},0),"D","N","S","PF","M")&COUNTIF($D$8:D14,D14)&"]" -> [N4] | C14: Charitable contributions | D14: Normalization | E14: Personal / discretionary | F14: Removes discretionary charitable giving, $7.5K in FY2025, equal to the P&L Charitable Contributions account. | G14: Seller add-back list; P&L account Charitable Contributions | H14: Documented | I14: Accepted | J14: =IF(I14="Accepted","Yes","No") -> Yes
B15: ="["&CHOOSE(MATCH(D15,{"Definitional","Normalization","Owner compensation","Pro forma","Memo"},0),"D","N","S","PF","M")&COUNTIF($D$8:D15,D15)&"]" -> [N5] | C15: Interest income (non-operating) | D15: Normalization | E15: Non-operating | F15: Removes interest income, $3.1K in FY2025, which is non-operating income, per the P&L Interest Income account. | G15: P&L, account Interest Income | H15: Documented | I15: Accepted | J15: =IF(I15="Accepted","Yes","No") -> Yes
B16: ="["&CHOOSE(MATCH(D16,{"Definitional","Normalization","Owner compensation","Pro forma","Memo"},0),"D","N","S","PF","M")&COUNTIF($D$8:D16,D16)&"]" -> [N6] | C16: Vehicle expenses (for review) | D16: Normalization | E16: Personal / discretionary | F16: Flagged for review: Vehicle costs may include the owner's personal use beyond the $51.0K already listed (FY2023, FY2024, FY2025). Account total $101.2K in FY2025. Amount 0 until an advisor enters it. | G16: P&L account Vehicle Expenses | H16: To be requested | I16: Proposed | J16: =IF(I16="Accepted","Yes","No") -> No
B17: ="["&CHOOSE(MATCH(D17,{"Definitional","Normalization","Owner compensation","Pro forma","Memo"},0),"D","N","S","PF","M")&COUNTIF($D$8:D17,D17)&"]" -> [N7] | C17: Fuel (for review) | D17: Normalization | E17: Personal / discretionary | F17: Flagged for review: Vehicle costs may include the owner's personal use. Account total $58.8K in FY2025. Amount 0 until an advisor enters it. | G17: P&L account Fuel | H17: To be requested | I17: Proposed | J17: =IF(I17="Accepted","Yes","No") -> No
B18: ="["&CHOOSE(MATCH(D18,{"Definitional","Normalization","Owner compensation","Pro forma","Memo"},0),"D","N","S","PF","M")&COUNTIF($D$8:D18,D18)&"]" -> [N8] | C18: Legal & professional fees (for review) | D18: Normalization | E18: Personal / discretionary | F18: Flagged for review: Check for one-time legal or consulting work beyond the $24.0K already listed (FY2024). Account total $17.2K in FY2025. Amount 0 until an advisor enters it. | G18: P&L account Legal & Professional Fees | H18: To be requested | I18: Proposed | J18: =IF(I18="Accepted","Yes","No") -> No
B19: ="["&CHOOSE(MATCH(D19,{"Definitional","Normalization","Owner compensation","Pro forma","Memo"},0),"D","N","S","PF","M")&COUNTIF($D$8:D19,D19)&"]" -> [N9] | C19: Meals & entertainment (for review) | D19: Normalization | E19: Personal / discretionary | F19: Flagged for review: Meals & entertainment are often partly personal. Account total $12.6K in FY2025. Amount 0 until an advisor enters it. | G19: P&L account Meals & Entertainment | H19: To be requested | I19: Proposed | J19: =IF(I19="Accepted","Yes","No") -> No
... B24: ="["&CHOOSE(MATCH(D24,{"Definitional","Normalization","Owner compensation","Pro forma","Memo"},0),"D","N","S","PF","M")&COUNTIF($D$8:D24,D24)&"]" -> [M1] | C24: After-hours emergency plumbing | D24: Memo | E24: Other consideration | F24: Calls after 7 pm are turned away today; no revenue from an after-hours service is included in any figure above, per management. | G24: intake-notes.md (intake call; request received 2026-09-21) | H24: Management representation | I24: Proposed | J24: =IF(I24="Accepted","Yes","No") -> No
B26: Note: a positive amount increases EBITDA. Refs number by tier in row order (insert a row and every ref renumbers). Status is an input: the ladder on Adj. EBITDA lists the rows accepted when the bot wrote the workbook (rerun the bot after changing a status to add a rung); a row set to Proposed, Supported or Excluded here drops out of every total at once. Rows with months carry each fiscal year by the named account's monthly shape (a one-time item in the months the account ran above its median, typed as inputs), so YTD and LTM take those months; rows without months are prorated by fiscal-year months in the window.
C28: Figures by period
B29: =B8 -> [D1] | C29: =C8 -> Interest expense | D29: =D8 -> Definitional | E29: =E8 -> Interest | I29: =I8 -> Accepted | N29: =SUMIFS($Y29:$BH29,$Y$6:$BH$6,">="&N$57,$Y$6:$BH$6,"<="&N$58) -> 22.4 | O29: =SUMIFS($Y29:$BH29,$Y$6:$BH$6,">="&O$57,$Y$6:$BH$6,"<="&O$58) -> 18.6 | P29: =SUMIFS($Y29:$BH29,$Y$6:$BH$6,">="&P$57,$Y$6:$BH$6,"<="&P$58) -> 14.3 | R29: =SUMIFS($Y29:$BH29,$Y$6:$BH$6,">="&R$57,$Y$6:$BH$6,"<="&R$58) -> 18.6 | S29: =SUMIFS($Y29:$BH29,$Y$6:$BH$6,">="&S$57,$Y$6:$BH$6,"<="&S$58) -> 14.3 | U29: =SUMIFS($Y29:$BH29,$Y$6:$BH$6,">="&U$57,$Y$6:$BH$6,"<="&U$58) -> 18.6 | V29: =SUMIFS($Y29:$BH29,$Y$6:$BH$6,">="&V$57,$Y$6:$BH$6,"<="&V$58) -> 14.3 | W29: =SUMIFS($Y29:$BH29,$Y$6:$BH$6,">="&W$57,$Y$6:$BH$6,"<="&W$58) -> 14.3 | Y29: ='Monthly P&L'!Q38 -> 2.074 | Z29: ='Monthly P&L'!R38 -> 2.036 | AA29: ='Monthly P&L'!S38 -> 1.999 | AB29: ='Monthly P&L'!T38 -> 1.961 | AC29: ='Monthly P&L'!U38 -> 1.923 | AD29: ='Monthly P&L'!V38 -> 1.886 | AE29: ='Monthly P&L'!W38 -> 1.848 | AF29: ='Monthly P&L'!X38 -> 1.81 | ... BH29: ='Monthly P&L'!AZ38 -> 1.059
B30: =B9 -> [D2] | C30: =C9 -> Income taxes | D30: =D9 -> Definitional | E30: =E9 -> Taxes | I30: =I9 -> Accepted | N30: =SUMIFS($Y30:$BH30,$Y$6:$BH$6,">="&N$57,$Y$6:$BH$6,"<="&N$58) -> 0 | O30: =SUMIFS($Y30:$BH30,$Y$6:$BH$6,">="&O$57,$Y$6:$BH$6,"<="&O$58) -> 0 | P30: =SUMIFS($Y30:$BH30,$Y$6:$BH$6,">="&P$57,$Y$6:$BH$6,"<="&P$58) -> 0 | R30: =SUMIFS($Y30:$BH30,$Y$6:$BH$6,">="&R$57,$Y$6:$BH$6,"<="&R$58) -> 0 | S30: =SUMIFS($Y30:$BH30,$Y$6:$BH$6,">="&S$57,$Y$6:$BH$6,"<="&S$58) -> 0 | U30: =SUMIFS($Y30:$BH30,$Y$6:$BH$6,">="&U$57,$Y$6:$BH$6,"<="&U$58) -> 0 | V30: =SUMIFS($Y30:$BH30,$Y$6:$BH$6,">="&V$57,$Y$6:$BH$6,"<="&V$58) -> 0 | W30: =SUMIFS($Y30:$BH30,$Y$6:$BH$6,">="&W$57,$Y$6:$BH$6,"<="&W$58) -> 0 | Y30: ='Monthly P&L'!Q41 -> 0 | Z30: ='Monthly P&L'!R41 -> 0 | AA30: ='Monthly P&L'!S41 -> 0 | AB30: ='Monthly P&L'!T41 -> 0 | AC30: ='Monthly P&L'!U41 -> 0 | AD30: ='Monthly P&L'!V41 -> 0 | AE30: ='Monthly P&L'!W41 -> 0 | AF30: ='Monthly P&L'!X41 -> 0 | ... BH30: ='Monthly P&L'!AZ41 -> 0
B31: =B10 -> [D3] | C31: =C10 -> Depreciation and amortization | D31: =D10 -> Definitional | E31: =E10 -> D&A | I31: =I10 -> Accepted | N31: =SUMIFS($Y31:$BH31,$Y$6:$BH$6,">="&N$57,$Y$6:$BH$6,"<="&N$58) -> 61.2 | O31: =SUMIFS($Y31:$BH31,$Y$6:$BH$6,">="&O$57,$Y$6:$BH$6,"<="&O$58) -> 66.8 | P31: =SUMIFS($Y31:$BH31,$Y$6:$BH$6,">="&P$57,$Y$6:$BH$6,"<="&P$58) -> 72.4 | R31: =SUMIFS($Y31:$BH31,$Y$6:$BH$6,">="&R$57,$Y$6:$BH$6,"<="&R$58) -> 66.8 | S31: =SUMIFS($Y31:$BH31,$Y$6:$BH$6,">="&S$57,$Y$6:$BH$6,"<="&S$58) -> 72.4 | U31: =SUMIFS($Y31:$BH31,$Y$6:$BH$6,">="&U$57,$Y$6:$BH$6,"<="&U$58) -> 66.8 | V31: =SUMIFS($Y31:$BH31,$Y$6:$BH$6,">="&V$57,$Y$6:$BH$6,"<="&V$58) -> 72.4 | W31: =SUMIFS($Y31:$BH31,$Y$6:$BH$6,">="&W$57,$Y$6:$BH$6,"<="&W$58) -> 72.4 | Y31: ='Monthly P&L'!Q35 -> 5.1 | Z31: ='Monthly P&L'!R35 -> 5.1 | AA31: ='Monthly P&L'!S35 -> 5.1 | AB31: ='Monthly P&L'!T35 -> 5.1 | AC31: ='Monthly P&L'!U35 -> 5.1 | AD31: ='Monthly P&L'!V35 -> 5.1 | AE31: ='Monthly P&L'!W35 -> 5.1 | AF31: ='Monthly P&L'!X35 -> 5.1 | ... BH31: ='Monthly P&L'!AZ35 -> 6.033
B32: =B11 -> [N1] | C32: =C11 -> Owner's personal vehicle | D32: =D11 -> Normalization | E32: =E11 -> Personal / discretionary | I32: =I11 -> Accepted | N32: 16 | O32: 17 | P32: 18 | R32: =SUMIFS($Y32:$BH32,$Y$6:$BH$6,">="&R$57,$Y$6:$BH$6,"<="&R$58) -> 17 | S32: =SUMIFS($Y32:$BH32,$Y$6:$BH$6,">="&S$57,$Y$6:$BH$6,"<="&S$58) -> 18 | U32: =SUMIFS($Y32:$BH32,$Y$6:$BH$6,">="&U$57,$Y$6:$BH$6,"<="&U$58) -> 17 | V32: =SUMIFS($Y32:$BH32,$Y$6:$BH$6,">="&V$57,$Y$6:$BH$6,"<="&V$58) -> 18 | W32: =SUMIFS($Y32:$BH32,$Y$6:$BH$6,">="&W$57,$Y$6:$BH$6,"<="&W$58) -> 18 | Y32: =IFERROR((SUMIFS('Databook'!$Q$8:$Q$33,'Databook'!$B$8:$B$33,"Vehicle Expenses"))*N32/(SUMIFS('Databook'!$I$8:$I$33,'Databook'!$B$8:$B$33,"Vehicle Expenses")),N32/12) -> 1.2266063 | Z32: =IFERROR((SUMIFS('Databook'!$R$8:$R$33,'Databook'!$B$8:$B$33,"Vehicle Expenses"))*N32/(SUMIFS('Databook'!$I$8:$I$33,'Databook'!$B$8:$B$33,"Vehicle Expenses")),N32/12) -> 1.2 | AA32: =IFERROR((SUMIFS('Databook'!$S$8:$S$33,'Databook'!$B$8:$B$33,"Vehicle Expenses"))*N32/(SUMIFS('Databook'!$I$8:$I$33,'Databook'!$B$8:$B$33,"Vehicle Expenses")),N32/12) -> 1.2666063 | AB32: =IFERROR((SUMIFS('Databook'!$T$8:$T$33,'Databook'!$B$8:$B$33,"Vehicle Expenses"))*N32/(SUMIFS('Databook'!$I$8:$I$33,'Databook'!$B$8:$B$33,"Vehicle Expenses")),N32/12) -> 1.3066063 | AC32: =IFERROR((SUMIFS('Databook'!$U$8:$U$33,'Databook'!$B$8:$B$33,"Vehicle Expenses"))*N32/(SUMIFS('Databook'!$I$8:$I$33,'Databook'!$B$8:$B$33,"Vehicle Expenses")),N32/12) -> 1.36 | AD32: =IFERROR((SUMIFS('Databook'!$V$8:$V$33,'Databook'!$B$8:$B$33,"Vehicle Expenses"))*N32/(SUMIFS('Databook'!$I$8:$I$33,'Databook'!$B$8:$B$33,"Vehicle Expenses")),N32/12) -> 1.4667873 | AE32: =IFERROR((SUMIFS('Databook'!$W$8:$W$33,'Databook'!$B$8:$B$33,"Vehicle Expenses"))*N32/(SUMIFS('Databook'!$I$8:$I$33,'Databook'!$B$8:$B$33,"Vehicle Expenses")),N32/12) -> 1.5333937 | AF32: =IFERROR((SUMIFS('Databook'!$X$8:$X$33,'Databook'!$B$8:$B$33,"Vehicle Expenses"))*N32/(SUMIFS('Databook'!$I$8:$I$33,'Databook'!$B$8:$B$33,"Vehicle Expenses")),N32/12) -> 1.4666063 | AG32: =IFERROR((SUMIFS('Databook'!$Y$8:$Y$33,'Databook'!$B$8:$B$33,"Vehicle Expenses"))*N32/(SUMIFS('Databook'!$I$8:$I$33,'Databook'!$B$8:$B$33,"Vehicle Expenses")),N32/12) -> 1.36 | AH32: =IFERROR((SUMIFS('Databook'!$Z$8:$Z$33,'Databook'!$B$8:$B$33,"Vehicle Expenses"))*N32/(SUMIFS('Databook'!$I$8:$I$33,'Databook'!$B$8:$B$33,"Vehicle Expenses")),N32/12) -> 1.28 | AI32: =IFERROR((SUMIFS('Databook'!$AA$8:$AA$33,'Databook'!$B$8:$B$33,"Vehicle Expenses"))*N32/(SUMIFS('Databook'!$I$8:$I$33,'Databook'!$B$8:$B$33,"Vehicle Expenses")),N32/12) -> 1.2533937 | AJ32: =IFERROR((SUMIFS('Databook'!$AB$8:$AB$33,'Databook'!$B$8:$B$33,"Vehicle Expenses"))*N32/(SUMIFS('Databook'!$I$8:$I$33,'Databook'!$B$8:$B$33,"Vehicle Expenses")),N32/12) -> 1.28 | AK32: =IFERROR((SUMIFS('Databook'!$AC$8:$AC$33,'Databook'!$B$8:$B$33,"Vehicle Expenses"))*O32/(SUMIFS('Databook'!$J$8:$J$33,'Databook'!$B$8:$B$33,"Vehicle Expenses")),O32/12) -> 1.3032735 | AL32: =IFERROR((SUMIFS('Databook'!$AD$8:$AD$33,'Databook'!$B$8:$B$33,"Vehicle Expenses"))*O32/(SUMIFS('Databook'!$J$8:$J$33,'Databook'!$B$8:$B$33,"Vehicle Expenses")),O32/12) -> 1.2749102 | AM32: =IFERROR((SUMIFS('Databook'!$AE$8:$AE$33,'Databook'!$B$8:$B$33,"Vehicle Expenses"))*O32/(SUMIFS('Databook'!$J$8:$J$33,'Databook'!$B$8:$B$33,"Vehicle Expenses")),O32/12) -> 1.3458184 | AN32: =IFERROR((SUMIFS('Databook'!$AF$8:$AF$33,'Databook'!$B$8:$B$33,"Vehicle Expenses"))*O32/(SUMIFS('Databook'!$J$8:$J$33,'Databook'!$B$8:$B$33,"Vehicle Expenses")),O32/12) -> 1.3883633 | AO32: =IFERROR((SUMIFS('Databook'!$AG$8:$AG$33,'Databook'!$B$8:$B$33,"Vehicle Expenses"))*O32/(SUMIFS('Databook'!$J$8:$J$33,'Databook'!$B$8:$B$33,"Vehicle Expenses")),O32/12) -> 1.4450898 | AP32: =IFERROR((SUMIFS('Databook'!$AH$8:$AH$33,'Databook'!$B$8:$B$33,"Vehicle Expenses"))*O32/(SUMIFS('Databook'!$J$8:$J$33,'Databook'!$B$8:$B$33,"Vehicle Expenses")),O32/12) -> 1.5583633 | AQ32: =IFERROR((SUMIFS('Databook'!$AI$8:$AI$33,'Databook'!$B$8:$B$33,"Vehicle Expenses"))*O32/(SUMIFS('Databook'!$J$8:$J$33,'Databook'!$B$8:$B$33,"Vehicle Expenses")),O32/12) -> 1.6290919 | AR32: =IFERROR((SUMIFS('Databook'!$AJ$8:$AJ$33,'Databook'!$B$8:$B$33,"Vehicle Expenses"))*O32/(SUMIFS('Databook'!$J$8:$J$33,'Databook'!$B$8:$B$33,"Vehicle Expenses")),O32/12) -> 1.5583633 | AS32: =IFERROR((SUMIFS('Databook'!$AK$8:$AK$33,'Databook'!$B$8:$B$33,"Vehicle Expenses"))*O32/(SUMIFS('Databook'!$J$8:$J$33,'Databook'!$B$8:$B$33,"Vehicle Expenses")),O32/12) -> 1.4450898 | AT32: =IFERROR((SUMIFS('Databook'!$AL$8:$AL$33,'Databook'!$B$8:$B$33,"Vehicle Expenses"))*O32/(SUMIFS('Databook'!$J$8:$J$33,'Databook'!$B$8:$B$33,"Vehicle Expenses")),O32/12) -> 1.36 | AU32: =IFERROR((SUMIFS('Databook'!$AM$8:$AM$33,'Databook'!$B$8:$B$33,"Vehicle Expenses"))*O32/(SUMIFS('Databook'!$J$8:$J$33,'Databook'!$B$8:$B$33,"Vehicle Expenses")),O32/12) -> 1.3316367 | AV32: =IFERROR((SUMIFS('Databook'!$AN$8:$AN$33,'Databook'!$B$8:$B$33,"Vehicle Expenses"))*O32/(SUMIFS('Databook'!$J$8:$J$33,'Databook'!$B$8:$B$33,"Vehicle Expenses")),O32/12) -> 1.36 | AW32: =IFERROR((SUMIFS('Databook'!$AO$8:$AO$33,'Databook'!$B$8:$B$33,"Vehicle Expenses"))*P32/(SUMIFS('Databook'!$K$8:$K$33,'Databook'!$B$8:$B$33,"Vehicle Expenses")),P32/12) -> 1.3800593 | AX32: =IFERROR((SUMIFS('Databook'!$AP$8:$AP$33,'Databook'!$B$8:$B$33,"Vehicle Expenses"))*P32/(SUMIFS('Databook'!$K$8:$K$33,'Databook'!$B$8:$B$33,"Vehicle Expenses")),P32/12) -> 1.35 | AY32: =IFERROR((SUMIFS('Databook'!$AQ$8:$AQ$33,'Databook'!$B$8:$B$33,"Vehicle Expenses"))*P32/(SUMIFS('Databook'!$K$8:$K$33,'Databook'!$B$8:$B$33,"Vehicle Expenses")),P32/12) -> 1.4248814 | AZ32: =IFERROR((SUMIFS('Databook'!$AR$8:$AR$33,'Databook'!$B$8:$B$33,"Vehicle Expenses"))*P32/(SUMIFS('Databook'!$K$8:$K$33,'Databook'!$B$8:$B$33,"Vehicle Expenses")),P32/12) -> 1.4700593 | BA32: =IFERROR((SUMIFS('Databook'!$AS$8:$AS$33,'Databook'!$B$8:$B$33,"Vehicle Expenses"))*P32/(SUMIFS('Databook'!$K$8:$K$33,'Databook'!$B$8:$B$33,"Vehicle Expenses")),P32/12) -> 1.53 | BB32: =IFERROR((SUMIFS('Databook'!$AT$8:$AT$33,'Databook'!$B$8:$B$33,"Vehicle Expenses"))*P32/(SUMIFS('Databook'!$K$8:$K$33,'Databook'!$B$8:$B$33,"Vehicle Expenses")),P32/12) -> 1.6500593 | BC32: =IFERROR((SUMIFS('Databook'!$AU$8:$AU$33,'Databook'!$B$8:$B$33,"Vehicle Expenses"))*P32/(SUMIFS('Databook'!$K$8:$K$33,'Databook'!$B$8:$B$33,"Vehicle Expenses")),P32/12) -> 1.7249407 | BD32: =IFERROR((SUMIFS('Databook'!$AV$8:$AV$33,'Databook'!$B$8:$B$33,"Vehicle Expenses"))*P32/(SUMIFS('Databook'!$K$8:$K$33,'Databook'!$B$8:$B$33,"Vehicle Expenses")),P32/12) -> 1.6500593 | BE32: =IFERROR((SUMIFS('Databook'!$AW$8:$AW$33,'Databook'!$B$8:$B$33,"Vehicle Expenses"))*P32/(SUMIFS('Databook'!$K$8:$K$33,'Databook'!$B$8:$B$33,"Vehicle Expenses")),P32/12) -> 1.53 | BF32: =IFERROR((SUMIFS('Databook'!$AX$8:$AX$33,'Databook'!$B$8:$B$33,"Vehicle Expenses"))*P32/(SUMIFS('Databook'!$K$8:$K$33,'Databook'!$B$8:$B$33,"Vehicle Expenses")),P32/12) -> 1.44 | BG32: =IFERROR((SUMIFS('Databook'!$AY$8:$AY$33,'Databook'!$B$8:$B$33,"Vehicle Expenses"))*P32/(SUMIFS('Databook'!$K$8:$K$33,'Databook'!$B$8:$B$33,"Vehicle Expenses")),P32/12) -> 1.4099407 | BH32: =IFERROR((SUMIFS('Databook'!$AZ$8:$AZ$33,'Databook'!$B$8:$B$33,"Vehicle Expenses"))*P32/(SUMIFS('Databook'!$K$8:$K$33,'Databook'!$B$8:$B$33,"Vehicle Expenses")),P32/12) -> 1.44
B33: =B12 -> [N2] | C33: =C12 -> Legal fees: settled customer dispute | D33: =D12 -> Normalization | E33: =E12 -> Non-recurring | I33: =I12 -> Accepted | N33: =SUMIFS($Y33:$BH33,$Y$6:$BH$6,">="&N$57,$Y$6:$BH$6,"<="&N$58) -> 0 | O33: =SUMIFS($Y33:$BH33,$Y$6:$BH$6,">="&O$57,$Y$6:$BH$6,"<="&O$58) -> 24 | P33: =SUMIFS($Y33:$BH33,$Y$6:$BH$6,">="&P$57,$Y$6:$BH$6,"<="&P$58) -> 0 | R33: =SUMIFS($Y33:$BH33,$Y$6:$BH$6,">="&R$57,$Y$6:$BH$6,"<="&R$58) -> 24 | S33: =SUMIFS($Y33:$BH33,$Y$6:$BH$6,">="&S$57,$Y$6:$BH$6,"<="&S$58) -> 0 | U33: =SUMIFS($Y33:$BH33,$Y$6:$BH$6,">="&U$57,$Y$6:$BH$6,"<="&U$58) -> 24 | V33: =SUMIFS($Y33:$BH33,$Y$6:$BH$6,">="&V$57,$Y$6:$BH$6,"<="&V$58) -> 0 | W33: =SUMIFS($Y33:$BH33,$Y$6:$BH$6,">="&W$57,$Y$6:$BH$6,"<="&W$58) -> 0 | Y33: 0 | Z33: 0 | AA33: 0 | AB33: 0 | AC33: 0 | AD33: 0 | AE33: 0 | AF33: 0 | AG33: 0 | AH33: 0 | AI33: 0 | AJ33: 0 | AK33: 0 | AL33: 0 | AM33: 0 | AN33: 0 | AO33: 0 | AP33: 12 | AQ33: 12 | AR33: 0 | AS33: 0 | AT33: 0 | AU33: 0 | AV33: 0 | AW33: 0 | AX33: 0 | AY33: 0 | AZ33: 0 | BA33: 0 | BB33: 0 | BC33: 0 | BD33: 0 | BE33: 0 | BF33: 0 | BG33: 0 | BH33: 0
B34: =B13 -> [N3] | C34: =C13 -> Owner family phones and meals | D34: =D13 -> Normalization | E34: =E13 -> Personal / discretionary | I34: =I13 -> Accepted | N34: 0 | O34: 0 | P34: 6 | R34: =SUMIFS($Y34:$BH34,$Y$6:$BH$6,">="&R$57,$Y$6:$BH$6,"<="&R$58) -> 0 | S34: =SUMIFS($Y34:$BH34,$Y$6:$BH$6,">="&S$57,$Y$6:$BH$6,"<="&S$58) -> 6 | U34: =SUMIFS($Y34:$BH34,$Y$6:$BH$6,">="&U$57,$Y$6:$BH$6,"<="&U$58) -> 0 | V34: =SUMIFS($Y34:$BH34,$Y$6:$BH$6,">="&V$57,$Y$6:$BH$6,"<="&V$58) -> 6 | W34: =SUMIFS($Y34:$BH34,$Y$6:$BH$6,">="&W$57,$Y$6:$BH$6,"<="&W$58) -> 6 | Y34: =N34/12 -> 0 | Z34: =N34/12 -> 0 | AA34: =N34/12 -> 0 | AB34: =N34/12 -> 0 | AC34: =N34/12 -> 0 | AD34: =N34/12 -> 0 | AE34: =N34/12 -> 0 | AF34: =N34/12 -> 0 | AG34: =N34/12 -> 0 | AH34: =N34/12 -> 0 | AI34: =N34/12 -> 0 | AJ34: =N34/12 -> 0 | AK34: =O34/12 -> 0 | AL34: =O34/12 -> 0 | AM34: =O34/12 -> 0 | AN34: =O34/12 -> 0 | AO34: =O34/12 -> 0 | AP34: =O34/12 -> 0 | AQ34: =O34/12 -> 0 | AR34: =O34/12 -> 0 | AS34: =O34/12 -> 0 | AT34: =O34/12 -> 0 | AU34: =O34/12 -> 0 | AV34: =O34/12 -> 0 | AW34: =P34/12 -> 0.5 | AX34: =P34/12 -> 0.5 | AY34: =P34/12 -> 0.5 | AZ34: =P34/12 -> 0.5 | BA34: =P34/12 -> 0.5 | BB34: =P34/12 -> 0.5 | BC34: =P34/12 -> 0.5 | BD34: =P34/12 -> 0.5 | BE34: =P34/12 -> 0.5 | BF34: =P34/12 -> 0.5 | BG34: =P34/12 -> 0.5 | BH34: =P34/12 -> 0.5
B35: =B14 -> [N4] | C35: =C14 -> Charitable contributions | D35: =D14 -> Normalization | E35: =E14 -> Personal / discretionary | I35: =I14 -> Accepted | N35: 5 | O35: 6 | P35: 7.5 | R35: =SUMIFS($Y35:$BH35,$Y$6:$BH$6,">="&R$57,$Y$6:$BH$6,"<="&R$58) -> 6 | S35: =SUMIFS($Y35:$BH35,$Y$6:$BH$6,">="&S$57,$Y$6:$BH$6,"<="&S$58) -> 7.5 | U35: =SUMIFS($Y35:$BH35,$Y$6:$BH$6,">="&U$57,$Y$6:$BH$6,"<="&U$58) -> 6 | V35: =SUMIFS($Y35:$BH35,$Y$6:$BH$6,">="&V$57,$Y$6:$BH$6,"<="&V$58) -> 7.5 | W35: =SUMIFS($Y35:$BH35,$Y$6:$BH$6,">="&W$57,$Y$6:$BH$6,"<="&W$58) -> 7.5 | Y35: =IFERROR((SUMIFS('Databook'!$Q$8:$Q$33,'Databook'!$B$8:$B$33,"Charitable Contributions"))*N35/(SUMIFS('Databook'!$I$8:$I$33,'Databook'!$B$8:$B$33,"Charitable Contributions")),N35/12) -> 0.209 | Z35: =IFERROR((SUMIFS('Databook'!$R$8:$R$33,'Databook'!$B$8:$B$33,"Charitable Contributions"))*N35/(SUMIFS('Databook'!$I$8:$I$33,'Databook'!$B$8:$B$33,"Charitable Contributions")),N35/12) -> 0.209 | AA35: =IFERROR((SUMIFS('Databook'!$S$8:$S$33,'Databook'!$B$8:$B$33,"Charitable Contributions"))*N35/(SUMIFS('Databook'!$I$8:$I$33,'Databook'!$B$8:$B$33,"Charitable Contributions")),N35/12) -> 0.209 | AB35: =IFERROR((SUMIFS('Databook'!$T$8:$T$33,'Databook'!$B$8:$B$33,"Charitable Contributions"))*N35/(SUMIFS('Databook'!$I$8:$I$33,'Databook'!$B$8:$B$33,"Charitable Contributions")),N35/12) -> 0.208 | AC35: =IFERROR((SUMIFS('Databook'!$U$8:$U$33,'Databook'!$B$8:$B$33,"Charitable Contributions"))*N35/(SUMIFS('Databook'!$I$8:$I$33,'Databook'!$B$8:$B$33,"Charitable Contributions")),N35/12) -> 0.208 | AD35: =IFERROR((SUMIFS('Databook'!$V$8:$V$33,'Databook'!$B$8:$B$33,"Charitable Contributions"))*N35/(SUMIFS('Databook'!$I$8:$I$33,'Databook'!$B$8:$B$33,"Charitable Contributions")),N35/12) -> 0.208 | AE35: =IFERROR((SUMIFS('Databook'!$W$8:$W$33,'Databook'!$B$8:$B$33,"Charitable Contributions"))*N35/(SUMIFS('Databook'!$I$8:$I$33,'Databook'!$B$8:$B$33,"Charitable Contributions")),N35/12) -> 0.208 | AF35: =IFERROR((SUMIFS('Databook'!$X$8:$X$33,'Databook'!$B$8:$B$33,"Charitable Contributions"))*N35/(SUMIFS('Databook'!$I$8:$I$33,'Databook'!$B$8:$B$33,"Charitable Contributions")),N35/12) -> 0.208 | AG35: =IFERROR((SUMIFS('Databook'!$Y$8:$Y$33,'Databook'!$B$8:$B$33,"Charitable Contributions"))*N35/(SUMIFS('Databook'!$I$8:$I$33,'Databook'!$B$8:$B$33,"Charitable Contributions")),N35/12) -> 0.208 | AH35: =IFERROR((SUMIFS('Databook'!$Z$8:$Z$33,'Databook'!$B$8:$B$33,"Charitable Contributions"))*N35/(SUMIFS('Databook'!$I$8:$I$33,'Databook'!$B$8:$B$33,"Charitable Contributions")),N35/12) -> 0.208 | AI35: =IFERROR((SUMIFS('Databook'!$AA$8:$AA$33,'Databook'!$B$8:$B$33,"Charitable Contributions"))*N35/(SUMIFS('Databook'!$I$8:$I$33,'Databook'!$B$8:$B$33,"Charitable Contributions")),N35/12) -> 0.417 | AJ35: =IFERROR((SUMIFS('Databook'!$AB$8:$AB$33,'Databook'!$B$8:$B$33,"Charitable Contributions"))*N35/(SUMIFS('Databook'!$I$8:$I$33,'Databook'!$B$8:$B$33,"Charitable Contributions")),N35/12) -> 2.5 | AK35: =IFERROR((SUMIFS('Databook'!$AC$8:$AC$33,'Databook'!$B$8:$B$33,"Charitable Contributions"))*O35/(SUMIFS('Databook'!$J$8:$J$33,'Databook'!$B$8:$B$33,"Charitable Contributions")),O35/12) -> 0.25 | AL35: =IFERROR((SUMIFS('Databook'!$AD$8:$AD$33,'Databook'!$B$8:$B$33,"Charitable Contributions"))*O35/(SUMIFS('Databook'!$J$8:$J$33,'Databook'!$B$8:$B$33,"Charitable Contributions")),O35/12) -> 0.25 | AM35: =IFERROR((SUMIFS('Databook'!$AE$8:$AE$33,'Databook'!$B$8:$B$33,"Charitable Contributions"))*O35/(SUMIFS('Databook'!$J$8:$J$33,'Databook'!$B$8:$B$33,"Charitable Contributions")),O35/12) -> 0.25 | AN35: =IFERROR((SUMIFS('Databook'!$AF$8:$AF$33,'Databook'!$B$8:$B$33,"Charitable Contributions"))*O35/(SUMIFS('Databook'!$J$8:$J$33,'Databook'!$B$8:$B$33,"Charitable Contributions")),O35/12) -> 0.25 | AO35: =IFERROR((SUMIFS('Databook'!$AG$8:$AG$33,'Databook'!$B$8:$B$33,"Charitable Contributions"))*O35/(SUMIFS('Databook'!$J$8:$J$33,'Databook'!$B$8:$B$33,"Charitable Contributions")),O35/12) -> 0.25 | AP35: =IFERROR((SUMIFS('Databook'!$AH$8:$AH$33,'Databook'!$B$8:$B$33,"Charitable Contributions"))*O35/(SUMIFS('Databook'!$J$8:$J$33,'Databook'!$B$8:$B$33,"Charitable Contributions")),O35/12) -> 0.25 | AQ35: =IFERROR((SUMIFS('Databook'!$AI$8:$AI$33,'Databook'!$B$8:$B$33,"Charitable Contributions"))*O35/(SUMIFS('Databook'!$J$8:$J$33,'Databook'!$B$8:$B$33,"Charitable Contributions")),O35/12) -> 0.25 | AR35: =IFERROR((SUMIFS('Databook'!$AJ$8:$AJ$33,'Databook'!$B$8:$B$33,"Charitable Contributions"))*O35/(SUMIFS('Databook'!$J$8:$J$33,'Databook'!$B$8:$B$33,"Charitable Contributions")),O35/12) -> 0.25 | AS35: =IFERROR((SUMIFS('Databook'!$AK$8:$AK$33,'Databook'!$B$8:$B$33,"Charitable Contributions"))*O35/(SUMIFS('Databook'!$J$8:$J$33,'Databook'!$B$8:$B$33,"Charitable Contributions")),O35/12) -> 0.25 | AT35: =IFERROR((SUMIFS('Databook'!$AL$8:$AL$33,'Databook'!$B$8:$B$33,"Charitable Contributions"))*O35/(SUMIFS('Databook'!$J$8:$J$33,'Databook'!$B$8:$B$33,"Charitable Contributions")),O35/12) -> 0.25 | AU35: =IFERROR((SUMIFS('Databook'!$AM$8:$AM$33,'Databook'!$B$8:$B$33,"Charitable Contributions"))*O35/(SUMIFS('Databook'!$J$8:$J$33,'Databook'!$B$8:$B$33,"Charitable Contributions")),O35/12) -> 0.5 | AV35: =IFERROR((SUMIFS('Databook'!$AN$8:$AN$33,'Databook'!$B$8:$B$33,"Charitable Contributions"))*O35/(SUMIFS('Databook'!$J$8:$J$33,'Databook'!$B$8:$B$33,"Charitable Contributions")),O35/12) -> 3 | AW35: =IFERROR((SUMIFS('Databook'!$AO$8:$AO$33,'Databook'!$B$8:$B$33,"Charitable Contributions"))*P35/(SUMIFS('Databook'!$K$8:$K$33,'Databook'!$B$8:$B$33,"Charitable Contributions")),P35/12) -> 0.313 | AX35: =IFERROR((SUMIFS('Databook'!$AP$8:$AP$33,'Databook'!$B$8:$B$33,"Charitable Contributions"))*P35/(SUMIFS('Databook'!$K$8:$K$33,'Databook'!$B$8:$B$33,"Charitable Contributions")),P35/12) -> 0.313 | AY35: =IFERROR((SUMIFS('Databook'!$AQ$8:$AQ$33,'Databook'!$B$8:$B$33,"Charitable Contributions"))*P35/(SUMIFS('Databook'!$K$8:$K$33,'Databook'!$B$8:$B$33,"Charitable Contributions")),P35/12) -> 0.313 | AZ35: =IFERROR((SUMIFS('Databook'!$AR$8:$AR$33,'Databook'!$B$8:$B$33,"Charitable Contributions"))*P35/(SUMIFS('Databook'!$K$8:$K$33,'Databook'!$B$8:$B$33,"Charitable Contributions")),P35/12) -> 0.313 | BA35: =IFERROR((SUMIFS('Databook'!$AS$8:$AS$33,'Databook'!$B$8:$B$33,"Charitable Contributions"))*P35/(SUMIFS('Databook'!$K$8:$K$33,'Databook'!$B$8:$B$33,"Charitable Contributions")),P35/12) -> 0.313 | BB35: =IFERROR((SUMIFS('Databook'!$AT$8:$AT$33,'Databook'!$B$8:$B$33,"Charitable Contributions"))*P35/(SUMIFS('Databook'!$K$8:$K$33,'Databook'!$B$8:$B$33,"Charitable Contributions")),P35/12) -> 0.312 | BC35: =IFERROR((SUMIFS('Databook'!$AU$8:$AU$33,'Databook'!$B$8:$B$33,"Charitable Contributions"))*P35/(SUMIFS('Databook'!$K$8:$K$33,'Databook'!$B$8:$B$33,"Charitable Contributions")),P35/12) -> 0.312 | BD35: =IFERROR((SUMIFS('Databook'!$AV$8:$AV$33,'Databook'!$B$8:$B$33,"Charitable Contributions"))*P35/(SUMIFS('Databook'!$K$8:$K$33,'Databook'!$B$8:$B$33,"Charitable Contributions")),P35/12) -> 0.312 | BE35: =IFERROR((SUMIFS('Databook'!$AW$8:$AW$33,'Databook'!$B$8:$B$33,"Charitable Contributions"))*P35/(SUMIFS('Databook'!$K$8:$K$33,'Databook'!$B$8:$B$33,"Charitable Contributions")),P35/12) -> 0.312 | BF35: =IFERROR((SUMIFS('Databook'!$AX$8:$AX$33,'Databook'!$B$8:$B$33,"Charitable Contributions"))*P35/(SUMIFS('Databook'!$K$8:$K$33,'Databook'!$B$8:$B$33,"Charitable Contributions")),P35/12) -> 0.312 | BG35: =IFERROR((SUMIFS('Databook'!$AY$8:$AY$33,'Databook'!$B$8:$B$33,"Charitable Contributions"))*P35/(SUMIFS('Databook'!$K$8:$K$33,'Databook'!$B$8:$B$33,"Charitable Contributions")),P35/12) -> 0.625 | BH35: =IFERROR((SUMIFS('Databook'!$AZ$8:$AZ$33,'Databook'!$B$8:$B$33,"Charitable Contributions"))*P35/(SUMIFS('Databook'!$K$8:$K$33,'Databook'!$B$8:$B$33,"Charitable Contributions")),P35/12) -> 3.75
B36: =B15 -> [N5] | C36: =C15 -> Interest income (non-operating) | D36: =D15 -> Normalization | E36: =E15 -> Non-operating | I36: =I15 -> Accepted | N36: =SUMIFS($Y36:$BH36,$Y$6:$BH$6,">="&N$57,$Y$6:$BH$6,"<="&N$58) -> -1.2 | O36: =SUMIFS($Y36:$BH36,$Y$6:$BH$6,">="&O$57,$Y$6:$BH$6,"<="&O$58) -> -2.4 | P36: =SUMIFS($Y36:$BH36,$Y$6:$BH$6,">="&P$57,$Y$6:$BH$6,"<="&P$58) -> -3.1 | R36: =SUMIFS($Y36:$BH36,$Y$6:$BH$6,">="&R$57,$Y$6:$BH$6,"<="&R$58) -> -2.4 | S36: =SUMIFS($Y36:$BH36,$Y$6:$BH$6,">="&S$57,$Y$6:$BH$6,"<="&S$58) -> -3.1 | U36: =SUMIFS($Y36:$BH36,$Y$6:$BH$6,">="&U$57,$Y$6:$BH$6,"<="&U$58) -> -2.4 | V36: =SUMIFS($Y36:$BH36,$Y$6:$BH$6,">="&V$57,$Y$6:$BH$6,"<="&V$58) -> -3.1 | W36: =SUMIFS($Y36:$BH36,$Y$6:$BH$6,">="&W$57,$Y$6:$BH$6,"<="&W$58) -> -3.1 | Y36: =-'Monthly P&L'!Q29 -> -0.1 | Z36: =-'Monthly P&L'!R29 -> -0.1 | AA36: =-'Monthly P&L'!S29 -> -0.1 | AB36: =-'Monthly P&L'!T29 -> -0.1 | AC36: =-'Monthly P&L'!U29 -> -0.1 | AD36: =-'Monthly P&L'!V29 -> -0.1 | AE36: =-'Monthly P&L'!W29 -> -0.1 | AF36: =-'Monthly P&L'!X29 -> -0.1 | ... BH36: =-'Monthly P&L'!AZ29 -> -0.258
B37: =B16 -> [N6] | C37: =C16 -> Vehicle expenses (for review) | D37: =D16 -> Normalization | E37: =E16 -> Personal / discretionary | I37: =I16 -> Proposed | N37: 0 | O37: 0 | P37: 0 | R37: =N37*MAX(0,(YEAR(MIN(R$58,N$58))-YEAR(MAX(R$57,N$57)))*12+MONTH(MIN(R$58,N$58))-MONTH(MAX(R$57,N$57))+1)/12+O37*MAX(0,(YEAR(MIN(R$58,O$58))-YEAR(MAX(R$57,O$57)))*12+MONTH(MIN(R$58,O$58))-MONTH(MAX(R$57,O$57))+1)/12+P37*MAX(0,(YEAR(MIN(R$58,P$58))-YEAR(MAX(R$57,P$57)))*12+MONTH(MIN(R$58,P$58))-MONTH(MAX(R$57,P$57))+1)/12 -> 0 | S37: =N37*MAX(0,(YEAR(MIN(S$58,N$58))-YEAR(MAX(S$57,N$57)))*12+MONTH(MIN(S$58,N$58))-MONTH(MAX(S$57,N$57))+1)/12+O37*MAX(0,(YEAR(MIN(S$58,O$58))-YEAR(MAX(S$57,O$57)))*12+MONTH(MIN(S$58,O$58))-MONTH(MAX(S$57,O$57))+1)/12+P37*MAX(0,(YEAR(MIN(S$58,P$58))-YEAR(MAX(S$57,P$57)))*12+MONTH(MIN(S$58,P$58))-MONTH(MAX(S$57,P$57))+1)/12 -> 0 | U37: =N37*MAX(0,(YEAR(MIN(U$58,N$58))-YEAR(MAX(U$57,N$57)))*12+MONTH(MIN(U$58,N$58))-MONTH(MAX(U$57,N$57))+1)/12+O37*MAX(0,(YEAR(MIN(U$58,O$58))-YEAR(MAX(U$57,O$57)))*12+MONTH(MIN(U$58,O$58))-MONTH(MAX(U$57,O$57))+1)/12+P37*MAX(0,(YEAR(MIN(U$58,P$58))-YEAR(MAX(U$57,P$57)))*12+MONTH(MIN(U$58,P$58))-MONTH(MAX(U$57,P$57))+1)/12 -> 0 | V37: =N37*MAX(0,(YEAR(MIN(V$58,N$58))-YEAR(MAX(V$57,N$57)))*12+MONTH(MIN(V$58,N$58))-MONTH(MAX(V$57,N$57))+1)/12+O37*MAX(0,(YEAR(MIN(V$58,O$58))-YEAR(MAX(V$57,O$57)))*12+MONTH(MIN(V$58,O$58))-MONTH(MAX(V$57,O$57))+1)/12+P37*MAX(0,(YEAR(MIN(V$58,P$58))-YEAR(MAX(V$57,P$57)))*12+MONTH(MIN(V$58,P$58))-MONTH(MAX(V$57,P$57))+1)/12 -> 0 | W37: =N37*MAX(0,(YEAR(MIN(W$58,N$58))-YEAR(MAX(W$57,N$57)))*12+MONTH(MIN(W$58,N$58))-MONTH(MAX(W$57,N$57))+1)/12+O37*MAX(0,(YEAR(MIN(W$58,O$58))-YEAR(MAX(W$57,O$57)))*12+MONTH(MIN(W$58,O$58))-MONTH(MAX(W$57,O$57))+1)/12+P37*MAX(0,(YEAR(MIN(W$58,P$58))-YEAR(MAX(W$57,P$57)))*12+MONTH(MIN(W$58,P$58))-MONTH(MAX(W$57,P$57))+1)/12 -> 0 | Y37: =N37/12 -> 0 | Z37: =N37/12 -> 0 | AA37: =N37/12 -> 0 | AB37: =N37/12 -> 0 | AC37: =N37/12 -> 0 | AD37: =N37/12 -> 0 | AE37: =N37/12 -> 0 | AF37: =N37/12 -> 0 | AG37: =N37/12 -> 0 | AH37: =N37/12 -> 0 | AI37: =N37/12 -> 0 | AJ37: =N37/12 -> 0 | AK37: =O37/12 -> 0 | AL37: =O37/12 -> 0 | AM37: =O37/12 -> 0 | AN37: =O37/12 -> 0 | AO37: =O37/12 -> 0 | AP37: =O37/12 -> 0 | AQ37: =O37/12 -> 0 | AR37: =O37/12 -> 0 | AS37: =O37/12 -> 0 | AT37: =O37/12 -> 0 | AU37: =O37/12 -> 0 | AV37: =O37/12 -> 0 | AW37: =P37/12 -> 0 | AX37: =P37/12 -> 0 | AY37: =P37/12 -> 0 | AZ37: =P37/12 -> 0 | BA37: =P37/12 -> 0 | BB37: =P37/12 -> 0 | BC37: =P37/12 -> 0 | BD37: =P37/12 -> 0 | BE37: =P37/12 -> 0 | BF37: =P37/12 -> 0 | BG37: =P37/12 -> 0 | BH37: =P37/12 -> 0
B38: =B17 -> [N7] | C38: =C17 -> Fuel (for review) | D38: =D17 -> Normalization | E38: =E17 -> Personal / discretionary | I38: =I17 -> Proposed | N38: 0 | O38: 0 | P38: 0 | R38: =N38*MAX(0,(YEAR(MIN(R$58,N$58))-YEAR(MAX(R$57,N$57)))*12+MONTH(MIN(R$58,N$58))-MONTH(MAX(R$57,N$57))+1)/12+O38*MAX(0,(YEAR(MIN(R$58,O$58))-YEAR(MAX(R$57,O$57)))*12+MONTH(MIN(R$58,O$58))-MONTH(MAX(R$57,O$57))+1)/12+P38*MAX(0,(YEAR(MIN(R$58,P$58))-YEAR(MAX(R$57,P$57)))*12+MONTH(MIN(R$58,P$58))-MONTH(MAX(R$57,P$57))+1)/12 -> 0 | S38: =N38*MAX(0,(YEAR(MIN(S$58,N$58))-YEAR(MAX(S$57,N$57)))*12+MONTH(MIN(S$58,N$58))-MONTH(MAX(S$57,N$57))+1)/12+O38*MAX(0,(YEAR(MIN(S$58,O$58))-YEAR(MAX(S$57,O$57)))*12+MONTH(MIN(S$58,O$58))-MONTH(MAX(S$57,O$57))+1)/12+P38*MAX(0,(YEAR(MIN(S$58,P$58))-YEAR(MAX(S$57,P$57)))*12+MONTH(MIN(S$58,P$58))-MONTH(MAX(S$57,P$57))+1)/12 -> 0 | U38: =N38*MAX(0,(YEAR(MIN(U$58,N$58))-YEAR(MAX(U$57,N$57)))*12+MONTH(MIN(U$58,N$58))-MONTH(MAX(U$57,N$57))+1)/12+O38*MAX(0,(YEAR(MIN(U$58,O$58))-YEAR(MAX(U$57,O$57)))*12+MONTH(MIN(U$58,O$58))-MONTH(MAX(U$57,O$57))+1)/12+P38*MAX(0,(YEAR(MIN(U$58,P$58))-YEAR(MAX(U$57,P$57)))*12+MONTH(MIN(U$58,P$58))-MONTH(MAX(U$57,P$57))+1)/12 -> 0 | V38: =N38*MAX(0,(YEAR(MIN(V$58,N$58))-YEAR(MAX(V$57,N$57)))*12+MONTH(MIN(V$58,N$58))-MONTH(MAX(V$57,N$57))+1)/12+O38*MAX(0,(YEAR(MIN(V$58,O$58))-YEAR(MAX(V$57,O$57)))*12+MONTH(MIN(V$58,O$58))-MONTH(MAX(V$57,O$57))+1)/12+P38*MAX(0,(YEAR(MIN(V$58,P$58))-YEAR(MAX(V$57,P$57)))*12+MONTH(MIN(V$58,P$58))-MONTH(MAX(V$57,P$57))+1)/12 -> 0 | W38: =N38*MAX(0,(YEAR(MIN(W$58,N$58))-YEAR(MAX(W$57,N$57)))*12+MONTH(MIN(W$58,N$58))-MONTH(MAX(W$57,N$57))+1)/12+O38*MAX(0,(YEAR(MIN(W$58,O$58))-YEAR(MAX(W$57,O$57)))*12+MONTH(MIN(W$58,O$58))-MONTH(MAX(W$57,O$57))+1)/12+P38*MAX(0,(YEAR(MIN(W$58,P$58))-YEAR(MAX(W$57,P$57)))*12+MONTH(MIN(W$58,P$58))-MONTH(MAX(W$57,P$57))+1)/12 -> 0 | Y38: =N38/12 -> 0 | Z38: =N38/12 -> 0 | AA38: =N38/12 -> 0 | AB38: =N38/12 -> 0 | AC38: =N38/12 -> 0 | AD38: =N38/12 -> 0 | AE38: =N38/12 -> 0 | AF38: =N38/12 -> 0 | AG38: =N38/12 -> 0 | AH38: =N38/12 -> 0 | AI38: =N38/12 -> 0 | AJ38: =N38/12 -> 0 | AK38: =O38/12 -> 0 | AL38: =O38/12 -> 0 | AM38: =O38/12 -> 0 | AN38: =O38/12 -> 0 | AO38: =O38/12 -> 0 | AP38: =O38/12 -> 0 | AQ38: =O38/12 -> 0 | AR38: =O38/12 -> 0 | AS38: =O38/12 -> 0 | AT38: =O38/12 -> 0 | AU38: =O38/12 -> 0 | AV38: =O38/12 -> 0 | AW38: =P38/12 -> 0 | AX38: =P38/12 -> 0 | AY38: =P38/12 -> 0 | AZ38: =P38/12 -> 0 | BA38: =P38/12 -> 0 | BB38: =P38/12 -> 0 | BC38: =P38/12 -> 0 | BD38: =P38/12 -> 0 | BE38: =P38/12 -> 0 | BF38: =P38/12 -> 0 | BG38: =P38/12 -> 0 | BH38: =P38/12 -> 0
B39: =B18 -> [N8] | C39: =C18 -> Legal & professional fees (for review) | D39: =D18 -> Normalization | E39: =E18 -> Personal / discretionary | I39: =I18 -> Proposed | N39: 0 | O39: 0 | P39: 0 | R39: =N39*MAX(0,(YEAR(MIN(R$58,N$58))-YEAR(MAX(R$57,N$57)))*12+MONTH(MIN(R$58,N$58))-MONTH(MAX(R$57,N$57))+1)/12+O39*MAX(0,(YEAR(MIN(R$58,O$58))-YEAR(MAX(R$57,O$57)))*12+MONTH(MIN(R$58,O$58))-MONTH(MAX(R$57,O$57))+1)/12+P39*MAX(0,(YEAR(MIN(R$58,P$58))-YEAR(MAX(R$57,P$57)))*12+MONTH(MIN(R$58,P$58))-MONTH(MAX(R$57,P$57))+1)/12 -> 0 | S39: =N39*MAX(0,(YEAR(MIN(S$58,N$58))-YEAR(MAX(S$57,N$57)))*12+MONTH(MIN(S$58,N$58))-MONTH(MAX(S$57,N$57))+1)/12+O39*MAX(0,(YEAR(MIN(S$58,O$58))-YEAR(MAX(S$57,O$57)))*12+MONTH(MIN(S$58,O$58))-MONTH(MAX(S$57,O$57))+1)/12+P39*MAX(0,(YEAR(MIN(S$58,P$58))-YEAR(MAX(S$57,P$57)))*12+MONTH(MIN(S$58,P$58))-MONTH(MAX(S$57,P$57))+1)/12 -> 0 | U39: =N39*MAX(0,(YEAR(MIN(U$58,N$58))-YEAR(MAX(U$57,N$57)))*12+MONTH(MIN(U$58,N$58))-MONTH(MAX(U$57,N$57))+1)/12+O39*MAX(0,(YEAR(MIN(U$58,O$58))-YEAR(MAX(U$57,O$57)))*12+MONTH(MIN(U$58,O$58))-MONTH(MAX(U$57,O$57))+1)/12+P39*MAX(0,(YEAR(MIN(U$58,P$58))-YEAR(MAX(U$57,P$57)))*12+MONTH(MIN(U$58,P$58))-MONTH(MAX(U$57,P$57))+1)/12 -> 0 | V39: =N39*MAX(0,(YEAR(MIN(V$58,N$58))-YEAR(MAX(V$57,N$57)))*12+MONTH(MIN(V$58,N$58))-MONTH(MAX(V$57,N$57))+1)/12+O39*MAX(0,(YEAR(MIN(V$58,O$58))-YEAR(MAX(V$57,O$57)))*12+MONTH(MIN(V$58,O$58))-MONTH(MAX(V$57,O$57))+1)/12+P39*MAX(0,(YEAR(MIN(V$58,P$58))-YEAR(MAX(V$57,P$57)))*12+MONTH(MIN(V$58,P$58))-MONTH(MAX(V$57,P$57))+1)/12 -> 0 | W39: =N39*MAX(0,(YEAR(MIN(W$58,N$58))-YEAR(MAX(W$57,N$57)))*12+MONTH(MIN(W$58,N$58))-MONTH(MAX(W$57,N$57))+1)/12+O39*MAX(0,(YEAR(MIN(W$58,O$58))-YEAR(MAX(W$57,O$57)))*12+MONTH(MIN(W$58,O$58))-MONTH(MAX(W$57,O$57))+1)/12+P39*MAX(0,(YEAR(MIN(W$58,P$58))-YEAR(MAX(W$57,P$57)))*12+MONTH(MIN(W$58,P$58))-MONTH(MAX(W$57,P$57))+1)/12 -> 0 | Y39: =N39/12 -> 0 | Z39: =N39/12 -> 0 | AA39: =N39/12 -> 0 | AB39: =N39/12 -> 0 | AC39: =N39/12 -> 0 | AD39: =N39/12 -> 0 | AE39: =N39/12 -> 0 | AF39: =N39/12 -> 0 | AG39: =N39/12 -> 0 | AH39: =N39/12 -> 0 | AI39: =N39/12 -> 0 | AJ39: =N39/12 -> 0 | AK39: =O39/12 -> 0 | AL39: =O39/12 -> 0 | AM39: =O39/12 -> 0 | AN39: =O39/12 -> 0 | AO39: =O39/12 -> 0 | AP39: =O39/12 -> 0 | AQ39: =O39/12 -> 0 | AR39: =O39/12 -> 0 | AS39: =O39/12 -> 0 | AT39: =O39/12 -> 0 | AU39: =O39/12 -> 0 | AV39: =O39/12 -> 0 | AW39: =P39/12 -> 0 | AX39: =P39/12 -> 0 | AY39: =P39/12 -> 0 | AZ39: =P39/12 -> 0 | BA39: =P39/12 -> 0 | BB39: =P39/12 -> 0 | BC39: =P39/12 -> 0 | BD39: =P39/12 -> 0 | BE39: =P39/12 -> 0 | BF39: =P39/12 -> 0 | BG39: =P39/12 -> 0 | BH39: =P39/12 -> 0
B40: =B19 -> [N9] | C40: =C19 -> Meals & entertainment (for review) | D40: =D19 -> Normalization | E40: =E19 -> Personal / discretionary | I40: =I19 -> Proposed | N40: 0 | O40: 0 | P40: 0 | R40: =N40*MAX(0,(YEAR(MIN(R$58,N$58))-YEAR(MAX(R$57,N$57)))*12+MONTH(MIN(R$58,N$58))-MONTH(MAX(R$57,N$57))+1)/12+O40*MAX(0,(YEAR(MIN(R$58,O$58))-YEAR(MAX(R$57,O$57)))*12+MONTH(MIN(R$58,O$58))-MONTH(MAX(R$57,O$57))+1)/12+P40*MAX(0,(YEAR(MIN(R$58,P$58))-YEAR(MAX(R$57,P$57)))*12+MONTH(MIN(R$58,P$58))-MONTH(MAX(R$57,P$57))+1)/12 -> 0 | S40: =N40*MAX(0,(YEAR(MIN(S$58,N$58))-YEAR(MAX(S$57,N$57)))*12+MONTH(MIN(S$58,N$58))-MONTH(MAX(S$57,N$57))+1)/12+O40*MAX(0,(YEAR(MIN(S$58,O$58))-YEAR(MAX(S$57,O$57)))*12+MONTH(MIN(S$58,O$58))-MONTH(MAX(S$57,O$57))+1)/12+P40*MAX(0,(YEAR(MIN(S$58,P$58))-YEAR(MAX(S$57,P$57)))*12+MONTH(MIN(S$58,P$58))-MONTH(MAX(S$57,P$57))+1)/12 -> 0 | U40: =N40*MAX(0,(YEAR(MIN(U$58,N$58))-YEAR(MAX(U$57,N$57)))*12+MONTH(MIN(U$58,N$58))-MONTH(MAX(U$57,N$57))+1)/12+O40*MAX(0,(YEAR(MIN(U$58,O$58))-YEAR(MAX(U$57,O$57)))*12+MONTH(MIN(U$58,O$58))-MONTH(MAX(U$57,O$57))+1)/12+P40*MAX(0,(YEAR(MIN(U$58,P$58))-YEAR(MAX(U$57,P$57)))*12+MONTH(MIN(U$58,P$58))-MONTH(MAX(U$57,P$57))+1)/12 -> 0 | V40: =N40*MAX(0,(YEAR(MIN(V$58,N$58))-YEAR(MAX(V$57,N$57)))*12+MONTH(MIN(V$58,N$58))-MONTH(MAX(V$57,N$57))+1)/12+O40*MAX(0,(YEAR(MIN(V$58,O$58))-YEAR(MAX(V$57,O$57)))*12+MONTH(MIN(V$58,O$58))-MONTH(MAX(V$57,O$57))+1)/12+P40*MAX(0,(YEAR(MIN(V$58,P$58))-YEAR(MAX(V$57,P$57)))*12+MONTH(MIN(V$58,P$58))-MONTH(MAX(V$57,P$57))+1)/12 -> 0 | W40: =N40*MAX(0,(YEAR(MIN(W$58,N$58))-YEAR(MAX(W$57,N$57)))*12+MONTH(MIN(W$58,N$58))-MONTH(MAX(W$57,N$57))+1)/12+O40*MAX(0,(YEAR(MIN(W$58,O$58))-YEAR(MAX(W$57,O$57)))*12+MONTH(MIN(W$58,O$58))-MONTH(MAX(W$57,O$57))+1)/12+P40*MAX(0,(YEAR(MIN(W$58,P$58))-YEAR(MAX(W$57,P$57)))*12+MONTH(MIN(W$58,P$58))-MONTH(MAX(W$57,P$57))+1)/12 -> 0 | Y40: =N40/12 -> 0 | Z40: =N40/12 -> 0 | AA40: =N40/12 -> 0 | AB40: =N40/12 -> 0 | AC40: =N40/12 -> 0 | AD40: =N40/12 -> 0 | AE40: =N40/12 -> 0 | AF40: =N40/12 -> 0 | AG40: =N40/12 -> 0 | AH40: =N40/12 -> 0 | AI40: =N40/12 -> 0 | AJ40: =N40/12 -> 0 | AK40: =O40/12 -> 0 | AL40: =O40/12 -> 0 | AM40: =O40/12 -> 0 | AN40: =O40/12 -> 0 | AO40: =O40/12 -> 0 | AP40: =O40/12 -> 0 | AQ40: =O40/12 -> 0 | AR40: =O40/12 -> 0 | AS40: =O40/12 -> 0 | AT40: =O40/12 -> 0 | AU40: =O40/12 -> 0 | AV40: =O40/12 -> 0 | AW40: =P40/12 -> 0 | AX40: =P40/12 -> 0 | AY40: =P40/12 -> 0 | AZ40: =P40/12 -> 0 | BA40: =P40/12 -> 0 | BB40: =P40/12 -> 0 | BC40: =P40/12 -> 0 | BD40: =P40/12 -> 0 | BE40: =P40/12 -> 0 | BF40: =P40/12 -> 0 | BG40: =P40/12 -> 0 | BH40: =P40/12 -> 0
B41: =B20 -> [S1] | C41: =C20 -> Owner compensation | D41: =D20 -> Owner compensation | E41: =E20 -> Owner compensation | I41: =I20 -> Accepted | N41: =SUMIFS($Y41:$BH41,$Y$6:$BH$6,">="&N$57,$Y$6:$BH$6,"<="&N$58) -> 180 | O41: =SUMIFS($Y41:$BH41,$Y$6:$BH$6,">="&O$57,$Y$6:$BH$6,"<="&O$58) -> 190 | P41: =SUMIFS($Y41:$BH41,$Y$6:$BH$6,">="&P$57,$Y$6:$BH$6,"<="&P$58) -> 200 | R41: =SUMIFS($Y41:$BH41,$Y$6:$BH$6,">="&R$57,$Y$6:$BH$6,"<="&R$58) -> 190 | S41: =SUMIFS($Y41:$BH41,$Y$6:$BH$6,">="&S$57,$Y$6:$BH$6,"<="&S$58) -> 200 | U41: =SUMIFS($Y41:$BH41,$Y$6:$BH$6,">="&U$57,$Y$6:$BH$6,"<="&U$58) -> 190 | V41: =SUMIFS($Y41:$BH41,$Y$6:$BH$6,">="&V$57,$Y$6:$BH$6,"<="&V$58) -> 200 | W41: =SUMIFS($Y41:$BH41,$Y$6:$BH$6,">="&W$57,$Y$6:$BH$6,"<="&W$58) -> 200 | Y41: ='Monthly P&L'!Q23 -> 15 | Z41: ='Monthly P&L'!R23 -> 15 | AA41: ='Monthly P&L'!S23 -> 15 | AB41: ='Monthly P&L'!T23 -> 15 | AC41: ='Monthly P&L'!U23 -> 15 | AD41: ='Monthly P&L'!V23 -> 15 | AE41: ='Monthly P&L'!W23 -> 15 | AF41: ='Monthly P&L'!X23 -> 15 | ... BH41: ='Monthly P&L'!AZ23 -> 16.666
B42: =B21 -> [S2] | C42: =C21 -> Market replacement compensation | D42: =D21 -> Owner compensation | E42: =E21 -> Replacement cost | I42: =I21 -> Accepted | N42: =SUMIFS($Y42:$BH42,$Y$6:$BH$6,">="&N$57,$Y$6:$BH$6,"<="&N$58) -> -109.25 | O42: =SUMIFS($Y42:$BH42,$Y$6:$BH$6,">="&O$57,$Y$6:$BH$6,"<="&O$58) -> -109.25 | P42: =SUMIFS($Y42:$BH42,$Y$6:$BH$6,">="&P$57,$Y$6:$BH$6,"<="&P$58) -> -109.25 | R42: =SUMIFS($Y42:$BH42,$Y$6:$BH$6,">="&R$57,$Y$6:$BH$6,"<="&R$58) -> -109.25 | S42: =SUMIFS($Y42:$BH42,$Y$6:$BH$6,">="&S$57,$Y$6:$BH$6,"<="&S$58) -> -109.25 | U42: =SUMIFS($Y42:$BH42,$Y$6:$BH$6,">="&U$57,$Y$6:$BH$6,"<="&U$58) -> -109.25 | V42: =SUMIFS($Y42:$BH42,$Y$6:$BH$6,">="&V$57,$Y$6:$BH$6,"<="&V$58) -> -109.25 | W42: =SUMIFS($Y42:$BH42,$Y$6:$BH$6,">="&W$57,$Y$6:$BH$6,"<="&W$58) -> -109.25 | Y42: =-'Assumptions'!$C$25/12/1000 -> -9.1041667 | Z42: =-'Assumptions'!$C$25/12/1000 -> -9.1041667 | AA42: =-'Assumptions'!$C$25/12/1000 -> -9.1041667 | AB42: =-'Assumptions'!$C$25/12/1000 -> -9.1041667 | AC42: =-'Assumptions'!$C$25/12/1000 -> -9.1041667 | AD42: =-'Assumptions'!$C$25/12/1000 -> -9.1041667 | AE42: =-'Assumptions'!$C$25/12/1000 -> -9.1041667 | AF42: =-'Assumptions'!$C$25/12/1000 -> -9.1041667 | ... BH42: =-'Assumptions'!$C$25/12/1000 -> -9.1041667
B43: =B22 -> [S3] | C43: =C22 -> Capital reserve (maintenance capex) | D43: =D22 -> Owner compensation | E43: =E22 -> Capital reserve | I43: =I22 -> Accepted | N43: =SUMIFS($Y43:$BH43,$Y$6:$BH$6,">="&N$57,$Y$6:$BH$6,"<="&N$58) -> -66.8 | O43: =SUMIFS($Y43:$BH43,$Y$6:$BH$6,">="&O$57,$Y$6:$BH$6,"<="&O$58) -> -66.8 | P43: =SUMIFS($Y43:$BH43,$Y$6:$BH$6,">="&P$57,$Y$6:$BH$6,"<="&P$58) -> -66.8 | R43: =SUMIFS($Y43:$BH43,$Y$6:$BH$6,">="&R$57,$Y$6:$BH$6,"<="&R$58) -> -66.8 | S43: =SUMIFS($Y43:$BH43,$Y$6:$BH$6,">="&S$57,$Y$6:$BH$6,"<="&S$58) -> -66.8 | U43: =SUMIFS($Y43:$BH43,$Y$6:$BH$6,">="&U$57,$Y$6:$BH$6,"<="&U$58) -> -66.8 | V43: =SUMIFS($Y43:$BH43,$Y$6:$BH$6,">="&V$57,$Y$6:$BH$6,"<="&V$58) -> -66.8 | W43: =SUMIFS($Y43:$BH43,$Y$6:$BH$6,">="&W$57,$Y$6:$BH$6,"<="&W$58) -> -66.8 | Y43: =-IF('Assumptions'!$C$18=1,'Assumptions'!$C$26,0)/12/1000 -> -5.5666667 | Z43: =-IF('Assumptions'!$C$18=1,'Assumptions'!$C$26,0)/12/1000 -> -5.5666667 | AA43: =-IF('Assumptions'!$C$18=1,'Assumptions'!$C$26,0)/12/1000 -> -5.5666667 | AB43: =-IF('Assumptions'!$C$18=1,'Assumptions'!$C$26,0)/12/1000 -> -5.5666667 | AC43: =-IF('Assumptions'!$C$18=1,'Assumptions'!$C$26,0)/12/1000 -> -5.5666667 | AD43: =-IF('Assumptions'!$C$18=1,'Assumptions'!$C$26,0)/12/1000 -> -5.5666667 | AE43: =-IF('Assumptions'!$C$18=1,'Assumptions'!$C$26,0)/12/1000 -> -5.5666667 | AF43: =-IF('Assumptions'!$C$18=1,'Assumptions'!$C$26,0)/12/1000 -> -5.5666667 | ... BH43: =-IF('Assumptions'!$C$18=1,'Assumptions'!$C$26,0)/12/1000 -> -5.5666667
B44: =B23 -> [S4] | C44: =C23 -> Payroll taxes and benefits on owner compensation | D44: =D23 -> Owner compensation | E44: =E23 -> Owner compensation | I44: =I23 -> Accepted | N44: =ROUND(MIN(N41*1000,'Assumptions'!$C$107)*'Assumptions'!$C$103+N41*1000*'Assumptions'!$C$104+MIN(N41*1000,'Assumptions'!$C$106)*'Assumptions'!$C$105,0)/1000 -> 12.584 | O44: =ROUND(MIN(O41*1000,'Assumptions'!$C$108)*'Assumptions'!$C$103+O41*1000*'Assumptions'!$C$104+MIN(O41*1000,'Assumptions'!$C$106)*'Assumptions'!$C$105,0)/1000 -> 13.25 | P44: =ROUND(MIN(P41*1000,'Assumptions'!$C$109)*'Assumptions'!$C$103+P41*1000*'Assumptions'!$C$104+MIN(P41*1000,'Assumptions'!$C$106)*'Assumptions'!$C$105,0)/1000 -> 13.86 | R44: =SUMIFS($Y44:$BH44,$Y$6:$BH$6,">="&R$57,$Y$6:$BH$6,"<="&R$58) -> 13.25 | S44: =SUMIFS($Y44:$BH44,$Y$6:$BH$6,">="&S$57,$Y$6:$BH$6,"<="&S$58) -> 13.86 | U44: =SUMIFS($Y44:$BH44,$Y$6:$BH$6,">="&U$57,$Y$6:$BH$6,"<="&U$58) -> 13.25 | V44: =SUMIFS($Y44:$BH44,$Y$6:$BH$6,">="&V$57,$Y$6:$BH$6,"<="&V$58) -> 13.86 | W44: =SUMIFS($Y44:$BH44,$Y$6:$BH$6,">="&W$57,$Y$6:$BH$6,"<="&W$58) -> 13.86 | Y44: =IFERROR((SUMIFS('Databook'!$Q$8:$Q$33,'Databook'!$B$8:$B$33,"Payroll Expenses : Officer Compensation"))*N44/(SUMIFS('Databook'!$I$8:$I$33,'Databook'!$B$8:$B$33,"Payroll Expenses : Officer Compensation")),N44/12) -> 1.0486667 | Z44: =IFERROR((SUMIFS('Databook'!$R$8:$R$33,'Databook'!$B$8:$B$33,"Payroll Expenses : Officer Compensation"))*N44/(SUMIFS('Databook'!$I$8:$I$33,'Databook'!$B$8:$B$33,"Payroll Expenses : Officer Compensation")),N44/12) -> 1.0486667 | AA44: =IFERROR((SUMIFS('Databook'!$S$8:$S$33,'Databook'!$B$8:$B$33,"Payroll Expenses : Officer Compensation"))*N44/(SUMIFS('Databook'!$I$8:$I$33,'Databook'!$B$8:$B$33,"Payroll Expenses : Officer Compensation")),N44/12) -> 1.0486667 | AB44: =IFERROR((SUMIFS('Databook'!$T$8:$T$33,'Databook'!$B$8:$B$33,"Payroll Expenses : Officer Compensation"))*N44/(SUMIFS('Databook'!$I$8:$I$33,'Databook'!$B$8:$B$33,"Payroll Expenses : Officer Compensation")),N44/12) -> 1.0486667 | AC44: =IFERROR((SUMIFS('Databook'!$U$8:$U$33,'Databook'!$B$8:$B$33,"Payroll Expenses : Officer Compensation"))*N44/(SUMIFS('Databook'!$I$8:$I$33,'Databook'!$B$8:$B$33,"Payroll Expenses : Officer Compensation")),N44/12) -> 1.0486667 | AD44: =IFERROR((SUMIFS('Databook'!$V$8:$V$33,'Databook'!$B$8:$B$33,"Payroll Expenses : Officer Compensation"))*N44/(SUMIFS('Databook'!$I$8:$I$33,'Databook'!$B$8:$B$33,"Payroll Expenses : Officer Compensation")),N44/12) -> 1.0486667 | AE44: =IFERROR((SUMIFS('Databook'!$W$8:$W$33,'Databook'!$B$8:$B$33,"Payroll Expenses : Officer Compensation"))*N44/(SUMIFS('Databook'!$I$8:$I$33,'Databook'!$B$8:$B$33,"Payroll Expenses : Officer Compensation")),N44/12) -> 1.0486667 | AF44: =IFERROR((SUMIFS('Databook'!$X$8:$X$33,'Databook'!$B$8:$B$33,"Payroll Expenses : Officer Compensation"))*N44/(SUMIFS('Databook'!$I$8:$I$33,'Databook'!$B$8:$B$33,"Payroll Expenses : Officer Compensation")),N44/12) -> 1.0486667 | AG44: =IFERROR((SUMIFS('Databook'!$Y$8:$Y$33,'Databook'!$B$8:$B$33,"Payroll Expenses : Officer Compensation"))*N44/(SUMIFS('Databook'!$I$8:$I$33,'Databook'!$B$8:$B$33,"Payroll Expenses : Officer Compensation")),N44/12) -> 1.0486667 | AH44: =IFERROR((SUMIFS('Databook'!$Z$8:$Z$33,'Databook'!$B$8:$B$33,"Payroll Expenses : Officer Compensation"))*N44/(SUMIFS('Databook'!$I$8:$I$33,'Databook'!$B$8:$B$33,"Payroll Expenses : Officer Compensation")),N44/12) -> 1.0486667 | AI44: =IFERROR((SUMIFS('Databook'!$AA$8:$AA$33,'Databook'!$B$8:$B$33,"Payroll Expenses : Officer Compensation"))*N44/(SUMIFS('Databook'!$I$8:$I$33,'Databook'!$B$8:$B$33,"Payroll Expenses : Officer Compensation")),N44/12) -> 1.0486667 | AJ44: =IFERROR((SUMIFS('Databook'!$AB$8:$AB$33,'Databook'!$B$8:$B$33,"Payroll Expenses : Officer Compensation"))*N44/(SUMIFS('Databook'!$I$8:$I$33,'Databook'!$B$8:$B$33,"Payroll Expenses : Officer Compensation")),N44/12) -> 1.0486667 | AK44: =IFERROR((SUMIFS('Databook'!$AC$8:$AC$33,'Databook'!$B$8:$B$33,"Payroll Expenses : Officer Compensation"))*O44/(SUMIFS('Databook'!$J$8:$J$33,'Databook'!$B$8:$B$33,"Payroll Expenses : Officer Compensation")),O44/12) -> 1.1042132 | AL44: =IFERROR((SUMIFS('Databook'!$AD$8:$AD$33,'Databook'!$B$8:$B$33,"Payroll Expenses : Officer Compensation"))*O44/(SUMIFS('Databook'!$J$8:$J$33,'Databook'!$B$8:$B$33,"Payroll Expenses : Officer Compensation")),O44/12) -> 1.1042132 | AM44: =IFERROR((SUMIFS('Databook'!$AE$8:$AE$33,'Databook'!$B$8:$B$33,"Payroll Expenses : Officer Compensation"))*O44/(SUMIFS('Databook'!$J$8:$J$33,'Databook'!$B$8:$B$33,"Payroll Expenses : Officer Compensation")),O44/12) -> 1.1042132 | AN44: =IFERROR((SUMIFS('Databook'!$AF$8:$AF$33,'Databook'!$B$8:$B$33,"Payroll Expenses : Officer Compensation"))*O44/(SUMIFS('Databook'!$J$8:$J$33,'Databook'!$B$8:$B$33,"Payroll Expenses : Officer Compensation")),O44/12) -> 1.1042132 | AO44: =IFERROR((SUMIFS('Databook'!$AG$8:$AG$33,'Databook'!$B$8:$B$33,"Payroll Expenses : Officer Compensation"))*O44/(SUMIFS('Databook'!$J$8:$J$33,'Databook'!$B$8:$B$33,"Payroll Expenses : Officer Compensation")),O44/12) -> 1.1041434 | AP44: =IFERROR((SUMIFS('Databook'!$AH$8:$AH$33,'Databook'!$B$8:$B$33,"Payroll Expenses : Officer Compensation"))*O44/(SUMIFS('Databook'!$J$8:$J$33,'Databook'!$B$8:$B$33,"Payroll Expenses : Officer Compensation")),O44/12) -> 1.1041434 | AQ44: =IFERROR((SUMIFS('Databook'!$AI$8:$AI$33,'Databook'!$B$8:$B$33,"Payroll Expenses : Officer Compensation"))*O44/(SUMIFS('Databook'!$J$8:$J$33,'Databook'!$B$8:$B$33,"Payroll Expenses : Officer Compensation")),O44/12) -> 1.1041434 | AR44: =IFERROR((SUMIFS('Databook'!$AJ$8:$AJ$33,'Databook'!$B$8:$B$33,"Payroll Expenses : Officer Compensation"))*O44/(SUMIFS('Databook'!$J$8:$J$33,'Databook'!$B$8:$B$33,"Payroll Expenses : Officer Compensation")),O44/12) -> 1.1041434 | AS44: =IFERROR((SUMIFS('Databook'!$AK$8:$AK$33,'Databook'!$B$8:$B$33,"Payroll Expenses : Officer Compensation"))*O44/(SUMIFS('Databook'!$J$8:$J$33,'Databook'!$B$8:$B$33,"Payroll Expenses : Officer Compensation")),O44/12) -> 1.1041434 | AT44: =IFERROR((SUMIFS('Databook'!$AL$8:$AL$33,'Databook'!$B$8:$B$33,"Payroll Expenses : Officer Compensation"))*O44/(SUMIFS('Databook'!$J$8:$J$33,'Databook'!$B$8:$B$33,"Payroll Expenses : Officer Compensation")),O44/12) -> 1.1041434 | AU44: =IFERROR((SUMIFS('Databook'!$AM$8:$AM$33,'Databook'!$B$8:$B$33,"Payroll Expenses : Officer Compensation"))*O44/(SUMIFS('Databook'!$J$8:$J$33,'Databook'!$B$8:$B$33,"Payroll Expenses : Officer Compensation")),O44/12) -> 1.1041434 | AV44: =IFERROR((SUMIFS('Databook'!$AN$8:$AN$33,'Databook'!$B$8:$B$33,"Payroll Expenses : Officer Compensation"))*O44/(SUMIFS('Databook'!$J$8:$J$33,'Databook'!$B$8:$B$33,"Payroll Expenses : Officer Compensation")),O44/12) -> 1.1041434 | AW44: =IFERROR((SUMIFS('Databook'!$AO$8:$AO$33,'Databook'!$B$8:$B$33,"Payroll Expenses : Officer Compensation"))*P44/(SUMIFS('Databook'!$K$8:$K$33,'Databook'!$B$8:$B$33,"Payroll Expenses : Officer Compensation")),P44/12) -> 1.1550231 | AX44: =IFERROR((SUMIFS('Databook'!$AP$8:$AP$33,'Databook'!$B$8:$B$33,"Payroll Expenses : Officer Compensation"))*P44/(SUMIFS('Databook'!$K$8:$K$33,'Databook'!$B$8:$B$33,"Payroll Expenses : Officer Compensation")),P44/12) -> 1.1550231 | AY44: =IFERROR((SUMIFS('Databook'!$AQ$8:$AQ$33,'Databook'!$B$8:$B$33,"Payroll Expenses : Officer Compensation"))*P44/(SUMIFS('Databook'!$K$8:$K$33,'Databook'!$B$8:$B$33,"Payroll Expenses : Officer Compensation")),P44/12) -> 1.1550231 | AZ44: =IFERROR((SUMIFS('Databook'!$AR$8:$AR$33,'Databook'!$B$8:$B$33,"Payroll Expenses : Officer Compensation"))*P44/(SUMIFS('Databook'!$K$8:$K$33,'Databook'!$B$8:$B$33,"Payroll Expenses : Officer Compensation")),P44/12) -> 1.1550231 | BA44: =IFERROR((SUMIFS('Databook'!$AS$8:$AS$33,'Databook'!$B$8:$B$33,"Payroll Expenses : Officer Compensation"))*P44/(SUMIFS('Databook'!$K$8:$K$33,'Databook'!$B$8:$B$33,"Payroll Expenses : Officer Compensation")),P44/12) -> 1.1550231 | BB44: =IFERROR((SUMIFS('Databook'!$AT$8:$AT$33,'Databook'!$B$8:$B$33,"Payroll Expenses : Officer Compensation"))*P44/(SUMIFS('Databook'!$K$8:$K$33,'Databook'!$B$8:$B$33,"Payroll Expenses : Officer Compensation")),P44/12) -> 1.1550231 | BC44: =IFERROR((SUMIFS('Databook'!$AU$8:$AU$33,'Databook'!$B$8:$B$33,"Payroll Expenses : Officer Compensation"))*P44/(SUMIFS('Databook'!$K$8:$K$33,'Databook'!$B$8:$B$33,"Payroll Expenses : Officer Compensation")),P44/12) -> 1.1550231 | BD44: =IFERROR((SUMIFS('Databook'!$AV$8:$AV$33,'Databook'!$B$8:$B$33,"Payroll Expenses : Officer Compensation"))*P44/(SUMIFS('Databook'!$K$8:$K$33,'Databook'!$B$8:$B$33,"Payroll Expenses : Officer Compensation")),P44/12) -> 1.1550231 | BE44: =IFERROR((SUMIFS('Databook'!$AW$8:$AW$33,'Databook'!$B$8:$B$33,"Payroll Expenses : Officer Compensation"))*P44/(SUMIFS('Databook'!$K$8:$K$33,'Databook'!$B$8:$B$33,"Payroll Expenses : Officer Compensation")),P44/12) -> 1.1549538 | BF44: =IFERROR((SUMIFS('Databook'!$AX$8:$AX$33,'Databook'!$B$8:$B$33,"Payroll Expenses : Officer Compensation"))*P44/(SUMIFS('Databook'!$K$8:$K$33,'Databook'!$B$8:$B$33,"Payroll Expenses : Officer Compensation")),P44/12) -> 1.1549538 | BG44: =IFERROR((SUMIFS('Databook'!$AY$8:$AY$33,'Databook'!$B$8:$B$33,"Payroll Expenses : Officer Compensation"))*P44/(SUMIFS('Databook'!$K$8:$K$33,'Databook'!$B$8:$B$33,"Payroll Expenses : Officer Compensation")),P44/12) -> 1.1549538 | BH44: =IFERROR((SUMIFS('Databook'!$AZ$8:$AZ$33,'Databook'!$B$8:$B$33,"Payroll Expenses : Officer Compensation"))*P44/(SUMIFS('Databook'!$K$8:$K$33,'Databook'!$B$8:$B$33,"Payroll Expenses : Officer Compensation")),P44/12) -> 1.1549538
B45: =B24 -> [M1] | C45: =C24 -> After-hours emergency plumbing | D45: =D24 -> Memo | E45: =E24 -> Other consideration | I45: =I24 -> Proposed | N45: 0 | O45: 0 | P45: 0 | R45: =N45*MAX(0,(YEAR(MIN(R$58,N$58))-YEAR(MAX(R$57,N$57)))*12+MONTH(MIN(R$58,N$58))-MONTH(MAX(R$57,N$57))+1)/12+O45*MAX(0,(YEAR(MIN(R$58,O$58))-YEAR(MAX(R$57,O$57)))*12+MONTH(MIN(R$58,O$58))-MONTH(MAX(R$57,O$57))+1)/12+P45*MAX(0,(YEAR(MIN(R$58,P$58))-YEAR(MAX(R$57,P$57)))*12+MONTH(MIN(R$58,P$58))-MONTH(MAX(R$57,P$57))+1)/12 -> 0 | S45: =N45*MAX(0,(YEAR(MIN(S$58,N$58))-YEAR(MAX(S$57,N$57)))*12+MONTH(MIN(S$58,N$58))-MONTH(MAX(S$57,N$57))+1)/12+O45*MAX(0,(YEAR(MIN(S$58,O$58))-YEAR(MAX(S$57,O$57)))*12+MONTH(MIN(S$58,O$58))-MONTH(MAX(S$57,O$57))+1)/12+P45*MAX(0,(YEAR(MIN(S$58,P$58))-YEAR(MAX(S$57,P$57)))*12+MONTH(MIN(S$58,P$58))-MONTH(MAX(S$57,P$57))+1)/12 -> 0 | U45: =N45*MAX(0,(YEAR(MIN(U$58,N$58))-YEAR(MAX(U$57,N$57)))*12+MONTH(MIN(U$58,N$58))-MONTH(MAX(U$57,N$57))+1)/12+O45*MAX(0,(YEAR(MIN(U$58,O$58))-YEAR(MAX(U$57,O$57)))*12+MONTH(MIN(U$58,O$58))-MONTH(MAX(U$57,O$57))+1)/12+P45*MAX(0,(YEAR(MIN(U$58,P$58))-YEAR(MAX(U$57,P$57)))*12+MONTH(MIN(U$58,P$58))-MONTH(MAX(U$57,P$57))+1)/12 -> 0 | V45: =N45*MAX(0,(YEAR(MIN(V$58,N$58))-YEAR(MAX(V$57,N$57)))*12+MONTH(MIN(V$58,N$58))-MONTH(MAX(V$57,N$57))+1)/12+O45*MAX(0,(YEAR(MIN(V$58,O$58))-YEAR(MAX(V$57,O$57)))*12+MONTH(MIN(V$58,O$58))-MONTH(MAX(V$57,O$57))+1)/12+P45*MAX(0,(YEAR(MIN(V$58,P$58))-YEAR(MAX(V$57,P$57)))*12+MONTH(MIN(V$58,P$58))-MONTH(MAX(V$57,P$57))+1)/12 -> 0 | W45: =N45*MAX(0,(YEAR(MIN(W$58,N$58))-YEAR(MAX(W$57,N$57)))*12+MONTH(MIN(W$58,N$58))-MONTH(MAX(W$57,N$57))+1)/12+O45*MAX(0,(YEAR(MIN(W$58,O$58))-YEAR(MAX(W$57,O$57)))*12+MONTH(MIN(W$58,O$58))-MONTH(MAX(W$57,O$57))+1)/12+P45*MAX(0,(YEAR(MIN(W$58,P$58))-YEAR(MAX(W$57,P$57)))*12+MONTH(MIN(W$58,P$58))-MONTH(MAX(W$57,P$57))+1)/12 -> 0 | Y45: =N45/12 -> 0 | Z45: =N45/12 -> 0 | AA45: =N45/12 -> 0 | AB45: =N45/12 -> 0 | AC45: =N45/12 -> 0 | AD45: =N45/12 -> 0 | AE45: =N45/12 -> 0 | AF45: =N45/12 -> 0 | AG45: =N45/12 -> 0 | AH45: =N45/12 -> 0 | AI45: =N45/12 -> 0 | AJ45: =N45/12 -> 0 | AK45: =O45/12 -> 0 | AL45: =O45/12 -> 0 | AM45: =O45/12 -> 0 | AN45: =O45/12 -> 0 | AO45: =O45/12 -> 0 | AP45: =O45/12 -> 0 | AQ45: =O45/12 -> 0 | AR45: =O45/12 -> 0 | AS45: =O45/12 -> 0 | AT45: =O45/12 -> 0 | AU45: =O45/12 -> 0 | AV45: =O45/12 -> 0 | AW45: =P45/12 -> 0 | AX45: =P45/12 -> 0 | AY45: =P45/12 -> 0 | AZ45: =P45/12 -> 0 | BA45: =P45/12 -> 0 | BB45: =P45/12 -> 0 | BC45: =P45/12 -> 0 | BD45: =P45/12 -> 0 | BE45: =P45/12 -> 0 | BF45: =P45/12 -> 0 | BG45: =P45/12 -> 0 | BH45: =P45/12 -> 0
B47: Ladder totals by tier (accepted rows)
C48: Definitional [D] | N48: =SUMIFS($N$29:$N$46,$D$29:$D$46,"Definitional",$I$29:$I$46,"Accepted") -> 83.6 | O48: =SUMIFS($O$29:$O$46,$D$29:$D$46,"Definitional",$I$29:$I$46,"Accepted") -> 85.4 | P48: =SUMIFS($P$29:$P$46,$D$29:$D$46,"Definitional",$I$29:$I$46,"Accepted") -> 86.7 | R48: =SUMIFS($R$29:$R$46,$D$29:$D$46,"Definitional",$I$29:$I$46,"Accepted") -> 85.4 | S48: =SUMIFS($S$29:$S$46,$D$29:$D$46,"Definitional",$I$29:$I$46,"Accepted") -> 86.7 | U48: =SUMIFS($U$29:$U$46,$D$29:$D$46,"Definitional",$I$29:$I$46,"Accepted") -> 85.4 | V48: =SUMIFS($V$29:$V$46,$D$29:$D$46,"Definitional",$I$29:$I$46,"Accepted") -> 86.7 | W48: =SUMIFS($W$29:$W$46,$D$29:$D$46,"Definitional",$I$29:$I$46,"Accepted") -> 86.7 | Y48: =SUMIFS($Y$29:$Y$46,$D$29:$D$46,"Definitional",$I$29:$I$46,"Accepted") -> 7.174 | Z48: =SUMIFS($Z$29:$Z$46,$D$29:$D$46,"Definitional",$I$29:$I$46,"Accepted") -> 7.136 | AA48: =SUMIFS($AA$29:$AA$46,$D$29:$D$46,"Definitional",$I$29:$I$46,"Accepted") -> 7.099 | AB48: =SUMIFS($AB$29:$AB$46,$D$29:$D$46,"Definitional",$I$29:$I$46,"Accepted") -> 7.061 | AC48: =SUMIFS($AC$29:$AC$46,$D$29:$D$46,"Definitional",$I$29:$I$46,"Accepted") -> 7.023 | AD48: =SUMIFS($AD$29:$AD$46,$D$29:$D$46,"Definitional",$I$29:$I$46,"Accepted") -> 6.986 | AE48: =SUMIFS($AE$29:$AE$46,$D$29:$D$46,"Definitional",$I$29:$I$46,"Accepted") -> 6.948 | AF48: =SUMIFS($AF$29:$AF$46,$D$29:$D$46,"Definitional",$I$29:$I$46,"Accepted") -> 6.91 | AG48: =SUMIFS($AG$29:$AG$46,$D$29:$D$46,"Definitional",$I$29:$I$46,"Accepted") -> 6.872 | AH48: =SUMIFS($AH$29:$AH$46,$D$29:$D$46,"Definitional",$I$29:$I$46,"Accepted") -> 6.835 | AI48: =SUMIFS($AI$29:$AI$46,$D$29:$D$46,"Definitional",$I$29:$I$46,"Accepted") -> 6.797 | AJ48: =SUMIFS($AJ$29:$AJ$46,$D$29:$D$46,"Definitional",$I$29:$I$46,"Accepted") -> 6.759 | AK48: =SUMIFS($AK$29:$AK$46,$D$29:$D$46,"Definitional",$I$29:$I$46,"Accepted") -> 7.289 | AL48: =SUMIFS($AL$29:$AL$46,$D$29:$D$46,"Definitional",$I$29:$I$46,"Accepted") -> 7.258 | AM48: =SUMIFS($AM$29:$AM$46,$D$29:$D$46,"Definitional",$I$29:$I$46,"Accepted") -> 7.227 | AN48: =SUMIFS($AN$29:$AN$46,$D$29:$D$46,"Definitional",$I$29:$I$46,"Accepted") -> 7.195 | AO48: =SUMIFS($AO$29:$AO$46,$D$29:$D$46,"Definitional",$I$29:$I$46,"Accepted") -> 7.164 | AP48: =SUMIFS($AP$29:$AP$46,$D$29:$D$46,"Definitional",$I$29:$I$46,"Accepted") -> 7.133 | AQ48: =SUMIFS($AQ$29:$AQ$46,$D$29:$D$46,"Definitional",$I$29:$I$46,"Accepted") -> 7.101 | AR48: =SUMIFS($AR$29:$AR$46,$D$29:$D$46,"Definitional",$I$29:$I$46,"Accepted") -> 7.07 | AS48: =SUMIFS($AS$29:$AS$46,$D$29:$D$46,"Definitional",$I$29:$I$46,"Accepted") -> 7.038 | AT48: =SUMIFS($AT$29:$AT$46,$D$29:$D$46,"Definitional",$I$29:$I$46,"Accepted") -> 7.006 | AU48: =SUMIFS($AU$29:$AU$46,$D$29:$D$46,"Definitional",$I$29:$I$46,"Accepted") -> 6.975 | AV48: =SUMIFS($AV$29:$AV$46,$D$29:$D$46,"Definitional",$I$29:$I$46,"Accepted") -> 6.944 | AW48: =SUMIFS($AW$29:$AW$46,$D$29:$D$46,"Definitional",$I$29:$I$46,"Accepted") -> 7.358 | AX48: =SUMIFS($AX$29:$AX$46,$D$29:$D$46,"Definitional",$I$29:$I$46,"Accepted") -> 7.334 | AY48: =SUMIFS($AY$29:$AY$46,$D$29:$D$46,"Definitional",$I$29:$I$46,"Accepted") -> 7.31 | AZ48: =SUMIFS($AZ$29:$AZ$46,$D$29:$D$46,"Definitional",$I$29:$I$46,"Accepted") -> 7.286 | BA48: =SUMIFS($BA$29:$BA$46,$D$29:$D$46,"Definitional",$I$29:$I$46,"Accepted") -> 7.261 | BB48: =SUMIFS($BB$29:$BB$46,$D$29:$D$46,"Definitional",$I$29:$I$46,"Accepted") -> 7.237 | BC48: =SUMIFS($BC$29:$BC$46,$D$29:$D$46,"Definitional",$I$29:$I$46,"Accepted") -> 7.213 | BD48: =SUMIFS($BD$29:$BD$46,$D$29:$D$46,"Definitional",$I$29:$I$46,"Accepted") -> 7.189 | BE48: =SUMIFS($BE$29:$BE$46,$D$29:$D$46,"Definitional",$I$29:$I$46,"Accepted") -> 7.164 | BF48: =SUMIFS($BF$29:$BF$46,$D$29:$D$46,"Definitional",$I$29:$I$46,"Accepted") -> 7.14 | BG48: =SUMIFS($BG$29:$BG$46,$D$29:$D$46,"Definitional",$I$29:$I$46,"Accepted") -> 7.116 | BH48: =SUMIFS($BH$29:$BH$46,$D$29:$D$46,"Definitional",$I$29:$I$46,"Accepted") -> 7.092
C49: Normalization [N] | N49: =SUMIFS($N$29:$N$46,$D$29:$D$46,"Normalization",$I$29:$I$46,"Accepted") -> 19.8 | O49: =SUMIFS($O$29:$O$46,$D$29:$D$46,"Normalization",$I$29:$I$46,"Accepted") -> 44.6 | P49: =SUMIFS($P$29:$P$46,$D$29:$D$46,"Normalization",$I$29:$I$46,"Accepted") -> 28.4 | R49: =SUMIFS($R$29:$R$46,$D$29:$D$46,"Normalization",$I$29:$I$46,"Accepted") -> 44.6 | S49: =SUMIFS($S$29:$S$46,$D$29:$D$46,"Normalization",$I$29:$I$46,"Accepted") -> 28.4 | U49: =SUMIFS($U$29:$U$46,$D$29:$D$46,"Normalization",$I$29:$I$46,"Accepted") -> 44.6 | V49: =SUMIFS($V$29:$V$46,$D$29:$D$46,"Normalization",$I$29:$I$46,"Accepted") -> 28.4 | W49: =SUMIFS($W$29:$W$46,$D$29:$D$46,"Normalization",$I$29:$I$46,"Accepted") -> 28.4 | Y49: =SUMIFS($Y$29:$Y$46,$D$29:$D$46,"Normalization",$I$29:$I$46,"Accepted") -> 1.3356063 | Z49: =SUMIFS($Z$29:$Z$46,$D$29:$D$46,"Normalization",$I$29:$I$46,"Accepted") -> 1.309 | AA49: =SUMIFS($AA$29:$AA$46,$D$29:$D$46,"Normalization",$I$29:$I$46,"Accepted") -> 1.3756063 | AB49: =SUMIFS($AB$29:$AB$46,$D$29:$D$46,"Normalization",$I$29:$I$46,"Accepted") -> 1.4146063 | AC49: =SUMIFS($AC$29:$AC$46,$D$29:$D$46,"Normalization",$I$29:$I$46,"Accepted") -> 1.468 | AD49: =SUMIFS($AD$29:$AD$46,$D$29:$D$46,"Normalization",$I$29:$I$46,"Accepted") -> 1.5747873 | AE49: =SUMIFS($AE$29:$AE$46,$D$29:$D$46,"Normalization",$I$29:$I$46,"Accepted") -> 1.6413937 | AF49: =SUMIFS($AF$29:$AF$46,$D$29:$D$46,"Normalization",$I$29:$I$46,"Accepted") -> 1.5746063 | AG49: =SUMIFS($AG$29:$AG$46,$D$29:$D$46,"Normalization",$I$29:$I$46,"Accepted") -> 1.468 | AH49: =SUMIFS($AH$29:$AH$46,$D$29:$D$46,"Normalization",$I$29:$I$46,"Accepted") -> 1.388 | AI49: =SUMIFS($AI$29:$AI$46,$D$29:$D$46,"Normalization",$I$29:$I$46,"Accepted") -> 1.5703937 | AJ49: =SUMIFS($AJ$29:$AJ$46,$D$29:$D$46,"Normalization",$I$29:$I$46,"Accepted") -> 3.68 | AK49: =SUMIFS($AK$29:$AK$46,$D$29:$D$46,"Normalization",$I$29:$I$46,"Accepted") -> 1.3532735 | AL49: =SUMIFS($AL$29:$AL$46,$D$29:$D$46,"Normalization",$I$29:$I$46,"Accepted") -> 1.3249102 | AM49: =SUMIFS($AM$29:$AM$46,$D$29:$D$46,"Normalization",$I$29:$I$46,"Accepted") -> 1.3958184 | AN49: =SUMIFS($AN$29:$AN$46,$D$29:$D$46,"Normalization",$I$29:$I$46,"Accepted") -> 1.4383633 | AO49: =SUMIFS($AO$29:$AO$46,$D$29:$D$46,"Normalization",$I$29:$I$46,"Accepted") -> 1.4950898 | AP49: =SUMIFS($AP$29:$AP$46,$D$29:$D$46,"Normalization",$I$29:$I$46,"Accepted") -> 13.608363 | AQ49: =SUMIFS($AQ$29:$AQ$46,$D$29:$D$46,"Normalization",$I$29:$I$46,"Accepted") -> 13.679092 | AR49: =SUMIFS($AR$29:$AR$46,$D$29:$D$46,"Normalization",$I$29:$I$46,"Accepted") -> 1.6083633 | AS49: =SUMIFS($AS$29:$AS$46,$D$29:$D$46,"Normalization",$I$29:$I$46,"Accepted") -> 1.4950898 | AT49: =SUMIFS($AT$29:$AT$46,$D$29:$D$46,"Normalization",$I$29:$I$46,"Accepted") -> 1.41 | AU49: =SUMIFS($AU$29:$AU$46,$D$29:$D$46,"Normalization",$I$29:$I$46,"Accepted") -> 1.6316367 | AV49: =SUMIFS($AV$29:$AV$46,$D$29:$D$46,"Normalization",$I$29:$I$46,"Accepted") -> 4.16 | AW49: =SUMIFS($AW$29:$AW$46,$D$29:$D$46,"Normalization",$I$29:$I$46,"Accepted") -> 1.9340593 | AX49: =SUMIFS($AX$29:$AX$46,$D$29:$D$46,"Normalization",$I$29:$I$46,"Accepted") -> 1.904 | AY49: =SUMIFS($AY$29:$AY$46,$D$29:$D$46,"Normalization",$I$29:$I$46,"Accepted") -> 1.9788814 | AZ49: =SUMIFS($AZ$29:$AZ$46,$D$29:$D$46,"Normalization",$I$29:$I$46,"Accepted") -> 2.0240593 | BA49: =SUMIFS($BA$29:$BA$46,$D$29:$D$46,"Normalization",$I$29:$I$46,"Accepted") -> 2.085 | BB49: =SUMIFS($BB$29:$BB$46,$D$29:$D$46,"Normalization",$I$29:$I$46,"Accepted") -> 2.2040593 | BC49: =SUMIFS($BC$29:$BC$46,$D$29:$D$46,"Normalization",$I$29:$I$46,"Accepted") -> 2.2789407 | BD49: =SUMIFS($BD$29:$BD$46,$D$29:$D$46,"Normalization",$I$29:$I$46,"Accepted") -> 2.2040593 | BE49: =SUMIFS($BE$29:$BE$46,$D$29:$D$46,"Normalization",$I$29:$I$46,"Accepted") -> 2.084 | BF49: =SUMIFS($BF$29:$BF$46,$D$29:$D$46,"Normalization",$I$29:$I$46,"Accepted") -> 1.994 | BG49: =SUMIFS($BG$29:$BG$46,$D$29:$D$46,"Normalization",$I$29:$I$46,"Accepted") -> 2.2769407 | BH49: =SUMIFS($BH$29:$BH$46,$D$29:$D$46,"Normalization",$I$29:$I$46,"Accepted") -> 5.432
C50: Owner compensation [S1] | N50: =SUMIFS($N$29:$N$46,$D$29:$D$46,"Owner compensation",$E$29:$E$46,"Owner compensation",$I$29:$I$46,"Accepted") -> 192.584 | O50: =SUMIFS($O$29:$O$46,$D$29:$D$46,"Owner compensation",$E$29:$E$46,"Owner compensation",$I$29:$I$46,"Accepted") -> 203.25 | P50: =SUMIFS($P$29:$P$46,$D$29:$D$46,"Owner compensation",$E$29:$E$46,"Owner compensation",$I$29:$I$46,"Accepted") -> 213.86 | R50: =SUMIFS($R$29:$R$46,$D$29:$D$46,"Owner compensation",$E$29:$E$46,"Owner compensation",$I$29:$I$46,"Accepted") -> 203.25 | S50: =SUMIFS($S$29:$S$46,$D$29:$D$46,"Owner compensation",$E$29:$E$46,"Owner compensation",$I$29:$I$46,"Accepted") -> 213.86 | U50: =SUMIFS($U$29:$U$46,$D$29:$D$46,"Owner compensation",$E$29:$E$46,"Owner compensation",$I$29:$I$46,"Accepted") -> 203.25 | V50: =SUMIFS($V$29:$V$46,$D$29:$D$46,"Owner compensation",$E$29:$E$46,"Owner compensation",$I$29:$I$46,"Accepted") -> 213.86 | W50: =SUMIFS($W$29:$W$46,$D$29:$D$46,"Owner compensation",$E$29:$E$46,"Owner compensation",$I$29:$I$46,"Accepted") -> 213.86 | Y50: =SUMIFS($Y$29:$Y$46,$D$29:$D$46,"Owner compensation",$E$29:$E$46,"Owner compensation",$I$29:$I$46,"Accepted") -> 16.048667 | Z50: =SUMIFS($Z$29:$Z$46,$D$29:$D$46,"Owner compensation",$E$29:$E$46,"Owner compensation",$I$29:$I$46,"Accepted") -> 16.048667 | AA50: =SUMIFS($AA$29:$AA$46,$D$29:$D$46,"Owner compensation",$E$29:$E$46,"Owner compensation",$I$29:$I$46,"Accepted") -> 16.048667 | AB50: =SUMIFS($AB$29:$AB$46,$D$29:$D$46,"Owner compensation",$E$29:$E$46,"Owner compensation",$I$29:$I$46,"Accepted") -> 16.048667 | AC50: =SUMIFS($AC$29:$AC$46,$D$29:$D$46,"Owner compensation",$E$29:$E$46,"Owner compensation",$I$29:$I$46,"Accepted") -> 16.048667 | AD50: =SUMIFS($AD$29:$AD$46,$D$29:$D$46,"Owner compensation",$E$29:$E$46,"Owner compensation",$I$29:$I$46,"Accepted") -> 16.048667 | AE50: =SUMIFS($AE$29:$AE$46,$D$29:$D$46,"Owner compensation",$E$29:$E$46,"Owner compensation",$I$29:$I$46,"Accepted") -> 16.048667 | AF50: =SUMIFS($AF$29:$AF$46,$D$29:$D$46,"Owner compensation",$E$29:$E$46,"Owner compensation",$I$29:$I$46,"Accepted") -> 16.048667 | AG50: =SUMIFS($AG$29:$AG$46,$D$29:$D$46,"Owner compensation",$E$29:$E$46,"Owner compensation",$I$29:$I$46,"Accepted") -> 16.048667 | AH50: =SUMIFS($AH$29:$AH$46,$D$29:$D$46,"Owner compensation",$E$29:$E$46,"Owner compensation",$I$29:$I$46,"Accepted") -> 16.048667 | AI50: =SUMIFS($AI$29:$AI$46,$D$29:$D$46,"Owner compensation",$E$29:$E$46,"Owner compensation",$I$29:$I$46,"Accepted") -> 16.048667 | AJ50: =SUMIFS($AJ$29:$AJ$46,$D$29:$D$46,"Owner compensation",$E$29:$E$46,"Owner compensation",$I$29:$I$46,"Accepted") -> 16.048667 | AK50: =SUMIFS($AK$29:$AK$46,$D$29:$D$46,"Owner compensation",$E$29:$E$46,"Owner compensation",$I$29:$I$46,"Accepted") -> 16.938213 | AL50: =SUMIFS($AL$29:$AL$46,$D$29:$D$46,"Owner compensation",$E$29:$E$46,"Owner compensation",$I$29:$I$46,"Accepted") -> 16.938213 | AM50: =SUMIFS($AM$29:$AM$46,$D$29:$D$46,"Owner compensation",$E$29:$E$46,"Owner compensation",$I$29:$I$46,"Accepted") -> 16.938213 | AN50: =SUMIFS($AN$29:$AN$46,$D$29:$D$46,"Owner compensation",$E$29:$E$46,"Owner compensation",$I$29:$I$46,"Accepted") -> 16.938213 | AO50: =SUMIFS($AO$29:$AO$46,$D$29:$D$46,"Owner compensation",$E$29:$E$46,"Owner compensation",$I$29:$I$46,"Accepted") -> 16.937143 | AP50: =SUMIFS($AP$29:$AP$46,$D$29:$D$46,"Owner compensation",$E$29:$E$46,"Owner compensation",$I$29:$I$46,"Accepted") -> 16.937143 | AQ50: =SUMIFS($AQ$29:$AQ$46,$D$29:$D$46,"Owner compensation",$E$29:$E$46,"Owner compensation",$I$29:$I$46,"Accepted") -> 16.937143 | AR50: =SUMIFS($AR$29:$AR$46,$D$29:$D$46,"Owner compensation",$E$29:$E$46,"Owner compensation",$I$29:$I$46,"Accepted") -> 16.937143 | AS50: =SUMIFS($AS$29:$AS$46,$D$29:$D$46,"Owner compensation",$E$29:$E$46,"Owner compensation",$I$29:$I$46,"Accepted") -> 16.937143 | AT50: =SUMIFS($AT$29:$AT$46,$D$29:$D$46,"Owner compensation",$E$29:$E$46,"Owner compensation",$I$29:$I$46,"Accepted") -> 16.937143 | AU50: =SUMIFS($AU$29:$AU$46,$D$29:$D$46,"Owner compensation",$E$29:$E$46,"Owner compensation",$I$29:$I$46,"Accepted") -> 16.937143 | AV50: =SUMIFS($AV$29:$AV$46,$D$29:$D$46,"Owner compensation",$E$29:$E$46,"Owner compensation",$I$29:$I$46,"Accepted") -> 16.937143 | AW50: =SUMIFS($AW$29:$AW$46,$D$29:$D$46,"Owner compensation",$E$29:$E$46,"Owner compensation",$I$29:$I$46,"Accepted") -> 17.822023 | AX50: =SUMIFS($AX$29:$AX$46,$D$29:$D$46,"Owner compensation",$E$29:$E$46,"Owner compensation",$I$29:$I$46,"Accepted") -> 17.822023 | AY50: =SUMIFS($AY$29:$AY$46,$D$29:$D$46,"Owner compensation",$E$29:$E$46,"Owner compensation",$I$29:$I$46,"Accepted") -> 17.822023 | AZ50: =SUMIFS($AZ$29:$AZ$46,$D$29:$D$46,"Owner compensation",$E$29:$E$46,"Owner compensation",$I$29:$I$46,"Accepted") -> 17.822023 | BA50: =SUMIFS($BA$29:$BA$46,$D$29:$D$46,"Owner compensation",$E$29:$E$46,"Owner compensation",$I$29:$I$46,"Accepted") -> 17.822023 | BB50: =SUMIFS($BB$29:$BB$46,$D$29:$D$46,"Owner compensation",$E$29:$E$46,"Owner compensation",$I$29:$I$46,"Accepted") -> 17.822023 | BC50: =SUMIFS($BC$29:$BC$46,$D$29:$D$46,"Owner compensation",$E$29:$E$46,"Owner compensation",$I$29:$I$46,"Accepted") -> 17.822023 | BD50: =SUMIFS($BD$29:$BD$46,$D$29:$D$46,"Owner compensation",$E$29:$E$46,"Owner compensation",$I$29:$I$46,"Accepted") -> 17.822023 | BE50: =SUMIFS($BE$29:$BE$46,$D$29:$D$46,"Owner compensation",$E$29:$E$46,"Owner compensation",$I$29:$I$46,"Accepted") -> 17.820954 | BF50: =SUMIFS($BF$29:$BF$46,$D$29:$D$46,"Owner compensation",$E$29:$E$46,"Owner compensation",$I$29:$I$46,"Accepted") -> 17.820954 | BG50: =SUMIFS($BG$29:$BG$46,$D$29:$D$46,"Owner compensation",$E$29:$E$46,"Owner compensation",$I$29:$I$46,"Accepted") -> 17.820954 | BH50: =SUMIFS($BH$29:$BH$46,$D$29:$D$46,"Owner compensation",$E$29:$E$46,"Owner compensation",$I$29:$I$46,"Accepted") -> 17.820954
